Workbook
Name GOOGL_Drivers_01: 'Revenue Drivers'!$A$6:$EP$136
Name GOOGL_Drivers_02: 'Revenue Drivers'!$A$168:$EP$320
Name GOOGL_IS: IS!$A$6:$EP$182
Name GOOGL_JPMe_vs_Actual: #REF!
Name GOOGL_JPMe_vs_BBRG: #REF!
Name GOOGL_Old_New: #REF!
Name GOOGL_Segments: 'Segment As Reported'!$A$6:$EP$37
Name Linking_1: #REF!
Name Linking_2: 'Segment As Reported'!$A$6:$EP$34
Name Linking_3: #REF!
Name Linking_4: #REF!
Name Threshold: 0.01

Sheet CoverSheet
N2: North America Equities Research
N3: 45960
B7: Company Model
B9: Alphabet Inc. (GOOGL)
B11: Doug Anmuth
B12: (212) 622-6571
B13: douglas.anmuth@jpmorgan.com
B14: J.P. Morgan Securities LLC
B16: Dae Lee
B17: (415) 315-8500
B18: dae.k.lee@jpmorgan.com
B19: J.P. Morgan Securities LLC
B21: Margaret Hoffman
B22: (212) 622-1710
... B30: #$J&098$#*P

Sheet IS
A2: Alphabet Inc.
A3: Income Statement
BO5: with mmi, values only | BY5: Incl. Motorola | FA5: 3 yr CAGR | FB5: 3 yr CAGR | FC5: 3 yr CAGR | FD5: 3 yr CAGR | FE5: 3 yr CAGR | FF5: 3 yr CAGR | FG5: 5 yr CAGR | FH5: 5 yr CAGR | FI5: 5 yr CAGR | FJ5: 5 yr CAGR | FK5: 5 yr CAGR | FL5: 5 yr CAGR
A6: $ in millions, except per share amounts | B6: 3/99A | C6: 6/99A | D6: 9/99A | E6: 12/99A | F6: 1999A | G6: 3/00A | H6: 6/00A | I6: 9/00A | J6: 12/00A | K6: 2000A | L6: 3/01A | M6: 6/01A | N6: 9/01A | O6: 12/01A | P6: 2001A | Q6: 3/02A | R6: 6/02A | S6: 9/02A | T6: 12/02A | U6: 2002A | V6: 3/03A | W6: 6/03A | X6: 9/03A | Y6: 12/03A | Z6: 2003A | AA6: 3/04A | AB6: 6/04A | AC6: 9/04A | AD6: 12/04A | AE6: 2004A | AF6: 3/05A | AG6: 6/05A | AH6: 9/05A | AI6: 12/05A | AJ6: 2005A | AK6: 3/06A | AL6: 6/06A | AM6: 9/06A | AN6: 12/06A | AO6: 2006A | AP6: 3/07A | AQ6: 6/07A | AR6: 9/07A | AS6: 12/07A | AT6: 2007A | AU6: 3/08A | AV6: 6/08A | AW6: 9/08A | AX6: 12/08A | AY6: 2008A | AZ6: 3/09A | BA6: 6/09A | BB6: 9/09A | BC6: 12/09A | BD6: 2009A | BE6: 3/10A | BF6: 6/10A | BG6: 9/10A | BH6: 12/10A | BI6: 2010A | BJ6: 3/11A | BK6: 6/11A | BL6: 9/11A | BM6: 12/11A | BN6: 2011A | BO6: 3/12A | BP6: 6/12A | BQ6: 9/12A | BR6: 12/12A | BS6: 2012A | BT6: 3/12A | BU6: 6/12A | BV6: 9/12A | BW6: 12/12A | BX6: 2012A | BY6: 3/13A | BZ6: 6/13A | CA6: 9/13A | CB6: 12/13A | CC6: 2013A | CD6: 3/13A | CE6: 6/13A | CF6: 9/13A | CG6: 12/13A | CH6: 2013A | CI6: 3/14A | CJ6: 6/14A | CK6: 9/14A | CL6: 12/14A | CM6: 2014A | CN6: 3/15A | CO6: 6/15A | CP6: 9/15A | CQ6: 12/15A | CR6: 2015A | CS6: 3/16A | CT6: 6/16A | CU6: 9/16A | CV6: 12/16A | CW6: 2016A | CX6: 3/17A | CY6: 6/17A | CZ6: 9/17A | DA6: 12/17A | DB6: 2017A | DC6: 3/18A | DD6: 6/18A | DE6: 9/18A | DF6: 12/18A | DG6: 2018A | DH6: 3/19A | DI6: 6/19A | DJ6: 9/19A | DK6: 12/19A | DL6: 2019A | DM6: 3/20A | DN6: 6/20A | DO6: 9/20A | DP6: 12/20A | DQ6: 2020A | DR6: 3/21A | DS6: 6/21A | DT6: 9/21A | DU6: 12/21A | DV6: 2021A | DW6: 3/22A | DX6: 6/22A | DY6: 9/22A | DZ6: 12/22A | EA6: 2022A | EB6: 3/23A | EC6: 6/23A | ED6: 9/23A | EE6: 12/23A | EF6: 2023A | EG6: 3/24A | EH6: 6/24A | EI6: 9/24A | EJ6: 12/24A | EK6: 2024A | EL6: 3/25A | EM6: 6/25A | EN6: 9/25A | EO6: 12/25E | EP6: 2025E | EQ6: 3/26E | ER6: 6/26E | ES6: 9/26E | ET6: 12/26E | EU6: 2026E | EV6: 2027E | EW6: 2028E | EX6: 2029E | EY6: 2030E | FA6: 2019-2022 | FB6: 2020-2023 | FC6: 2021-2024 | FD6: 2022-2025 | FE6: 2023-2026 | FF6: 2024-2027 | FG6: 2019-2024 | FH6: 2020-2025 | FI6: 2021-2026 | FJ6: 2022-2027 | FK6: 2023-2028 | FL6: 2024-2029
A7: Gross Revenues | F7: 0.22 | K7: 19.108 | P7: 86.426 | Q7: 42.285 | R7: 78.525 | S7: 130.787 | T7: 187.911 | U7: =SUM(Q7:T7) -> 439.508 | V7: 248.618 | W7: 311.199 | X7: 393.942 | Y7: 512.175 | Z7: =Z9+Z8 -> 1465.934 | AA7: 651.623 | AB7: 700.212 | AC7: 805.887 | AD7: 1031.501 | AE7: =SUM(AA7:AD7) -> 3189.223 | AF7: 1256.516 | AG7: 1384.495 | AH7: 1578.456 | AI7: 1919.093 | AJ7: =SUM(AF7:AI7) -> 6138.56 | AK7: 2253.755 | AL7: 2455.991 | AM7: 2689.673 | AN7: 3205.498 | AO7: =SUM(AK7:AN7) -> 10604.917 | AP7: 3663.971 | AQ7: 3871.985 | AR7: 4231.351 | AS7: 4826.679 | AT7: =SUM(AP7:AS7) -> 16593.986 | AU7: 5186.043 | AV7: 5367.212 | AW7: 5541.391 | AX7: =5700.904 -> 5700.904 | AY7: =SUM(AU7:AX7) -> 21795.55 | AZ7: 5508.99 | BA7: 5522.897 | BB7: 5944.851 | BC7: =6673.825 -> 6673.825 | BD7: =SUM(AZ7:BC7) -> 23650.563 | BE7: 6775 | BF7: 6820 | BG7: 7286 | BH7: =8440 -> 8440 | BI7: =SUM(BE7:BH7) -> 29321 | BJ7: 8575 | BK7: 9026 | BL7: 9720 | BM7: 10584 | BN7: =SUM(BJ7:BM7) -> 37905 | BO7: 10645 | BP7: 12214 | BQ7: 14101 | BR7: 14419 | BS7: 51379 | BT7: ='Revenue Drivers'!BT69 -> 10645 | BU7: ='Revenue Drivers'!BU69 -> 10964 | BV7: ='Revenue Drivers'!BV69 -> 11526 | BW7: ='Revenue Drivers'!BW69 -> 12905 | BX7: 46039 | BY7: ='Revenue Drivers'!BY69 -> 0 | BZ7: ='Revenue Drivers'!BZ69 -> 0 | CA7: ='Revenue Drivers'!CA69 -> 0 | CB7: ='Revenue Drivers'!CB69 -> 0 | CC7: ='Revenue Drivers'!CC69 -> 0 | CD7: ='Revenue Drivers'!CD69 -> 12951 | CE7: ='Revenue Drivers'!CE69 -> 13107 | CF7: ='Revenue Drivers'!CF69 -> 13754 | ... EY7: ='Revenue Drivers'!EY69 -> 722335.87 | FA7: =(EA7/DL7)^(1/3)-1 -> 0.20448409 | FB7: =(EF7/DQ7)^(1/3)-1 -> 0.18975103 | FC7: =(EK7/DV7)^(1/3)-1 -> 0.1075433 | FD7: =(EP7/EA7)^(1/3)-1 -> 0.123643 | FE7: =(EU7/EF7)^(1/3)-1 -> 0.15065051 | FF7: =(EV7/EK7)^(1/3)-1 -> 0.14884805 | FG7: =(EK7/DL7)^(1/5)-1 -> 0.16678753 | FH7: =(EP7/DQ7)^(1/5)-1 -> 0.17062697 | FI7: =(EU7/DV7)^(1/5)-1 -> 0.126947 | FJ7: =(EV7/EA7)^(1/5)-1 -> 0.13414529 | FK7: =(EW7/EF7)^(1/5)-1 -> 0.14090809 | FL7: =(EX7/EK7)^(1/5)-1 -> 0.13424636
A8: Traffic Acquisition Costs (TAC) | F8: 0 | K8: 0 | P8: 0 | Q8: ='Revenue Drivers'!Q105 -> 0 | R8: ='Revenue Drivers'!R105 -> 14 | S8: ='Revenue Drivers'!S105 -> 29 | T8: ='Revenue Drivers'!T105 -> 51.5 | U8: 94.5 | V8: ='Revenue Drivers'!V105 -> 70.131 | W8: ='Revenue Drivers'!W105 -> 96.559 | X8: ='Revenue Drivers'!X105 -> 143.487 | Y8: ='Revenue Drivers'!Y105 -> 216.356 | Z8: =SUM(V8:Y8) -> 526.533 | AA8: ='Revenue Drivers'!AA105 -> 271.002 | AB8: ='Revenue Drivers'!AB105 -> 277.034 | AC8: ='Revenue Drivers'!AC105 -> 302.9 | AD8: ='Revenue Drivers'!AD105 -> 377.708 | AE8: =SUM(AA8:AD8) -> 1228.644 | AF8: 461.807 | AG8: 494.32 | AH8: 529.874 | AI8: 628.941 | AJ8: =SUM(AF8:AI8) -> 2114.942 | AK8: 722.736 | AL8: 785.159 | AM8: 825.264 | AN8: 975.618 | AO8: =SUM(AK8:AN8) -> 3308.777 | AP8: 1125.032 | AQ8: 1147.913 | AR8: 1221.12 | AS8: =1439.814 -> 1439.814 | AT8: =SUM(AP8:AS8) -> 4933.879 | AU8: =1486.384 -> 1486.384 | AV8: 1473.98 | AW8: 1495.206 | AX8: 1483.382 | AY8: =SUM(AU8:AX8) -> 5938.952 | AZ8: 1435.96 | BA8: 1453.354 | BB8: 1559.216 | BC8: 1720.886 | BD8: =SUM(AZ8:BC8) -> 6169.416 | BE8: 1711 | BF8: 1732 | BG8: 1805 | BH8: =2069 -> 2069 | BI8: =SUM(BE8:BH8) -> 7317 | BJ8: 2038 | BK8: 2110 | BL8: 2210 | BM8: 2450 | BN8: =SUM(BJ8:BM8) -> 8808 | BO8: 2510 | BP8: 2600 | BQ8: 2770 | BR8: 3080 | BS8: 10960 | BT8: =+'Revenue Drivers'!BT105 -> 2510 | BU8: =+'Revenue Drivers'!BU105 -> 2600 | BV8: =+'Revenue Drivers'!BV105 -> 2770 | BW8: =+'Revenue Drivers'!BW105 -> 3080 | BX8: 10956 | BY8: 2962 | BZ8: 3013 | CA8: 2972 | CB8: 3310 | CC8: 12257 | CD8: ='Revenue Drivers'!CD105 -> 2962 | CE8: ='Revenue Drivers'!CE105 -> 3013 | CF8: ='Revenue Drivers'!CF105 -> 2972 | CG8: ='Revenue Drivers'!CG105 -> 3310 | CH8: 12258 | CI8: 3232 | CJ8: ='Revenue Drivers'!CJ105 -> 3293 | CK8: ='Revenue Drivers'!CK105 -> 3348 | CL8: ='Revenue Drivers'!CL105 -> 3620 | CM8: 13497 | CN8: 3345 | CO8: ='Revenue Drivers'!CO105 -> 3377 | CP8: ='Revenue Drivers'!CP105 -> 3566 | CQ8: ='Revenue Drivers'!CQ105 -> 4055 | CR8: ='Revenue Drivers'!CR105 -> 14343 | CS8: ='Revenue Drivers'!CS105 -> 3788 | CT8: ='Revenue Drivers'!CT105 -> 3975 | CU8: ='Revenue Drivers'!CU105 -> 4182 | CV8: ='Revenue Drivers'!CV105 -> 4848 | ... EY8: ='Revenue Drivers'!EY105 -> 85065.792 | FA8: =(EA8/DL8)^(1/3)-1 -> 0.17615105 | FB8: =(EF8/DQ8)^(1/3)-1 -> 0.1579024 | FC8: =(EK8/DV8)^(1/3)-1 -> 0.064087022 | FD8: =(EP8/EA8)^(1/3)-1 -> 0.067707297 | FE8: =(EU8/EF8)^(1/3)-1 -> 0.085399978 | FF8: =(EV8/EK8)^(1/3)-1 -> 0.085380122 | FG8: =(EK8/DL8)^(1/5)-1 -> 0.12780215 | FH8: =(EP8/DQ8)^(1/5)-1 -> 0.12697491 | FI8: =(EU8/DV8)^(1/5)-1 -> 0.073854315 | FJ8: =(EV8/EA8)^(1/5)-1 -> 0.074741888 | FK8: =(EW8/EF8)^(1/5)-1 -> 0.081875981 | FL8: =(EX8/EK8)^(1/5)-1 -> 0.078828557
A9: Net Revenues excluding TAC | F9: =F7-F8 -> 0.22 | K9: =K7-K8 -> 19.108 | P9: =P7-P8 -> 86.426 | Q9: =Q7-Q8 -> 42.285 | R9: =R7-R8 -> 64.525 | S9: =S7-S8 -> 101.787 | T9: =T7-T8 -> 136.411 | U9: =U7-U8 -> 345.008 | V9: =V7-V8 -> 178.487 | W9: =W7-W8 -> 214.64 | ... Y9: =Y7-Y8 -> 295.819 | Z9: =SUM(V9:Y9) -> 939.401 | AA9: =AA7-AA8 -> 380.621 | AB9: =AB7-AB8 -> 423.178 | AC9: =AC7-AC8 -> 502.987 | AD9: =AD7-AD8 -> 653.793 | AE9: =SUM(AA9:AD9) -> 1960.579 | AF9: =AF7-AF8 -> 794.709 | AG9: =AG7-AG8 -> 890.175 | AH9: =AH7-AH8 -> 1048.582 | AI9: =AI7-AI8 -> 1290.152 | AJ9: =SUM(AF9:AI9) -> 4023.618 | AK9: =AK7-AK8 -> 1531.019 | AL9: =AL7-AL8 -> 1670.832 | AM9: =AM7-AM8 -> 1864.409 | AN9: =AN7-AN8 -> 2229.88 | AO9: =SUM(AK9:AN9) -> 7296.14 | AP9: =AP7-AP8 -> 2538.939 | AQ9: =AQ7-AQ8 -> 2724.072 | AR9: =AR7-AR8 -> 3010.231 | AS9: =AS7-AS8 -> 3386.865 | AT9: =SUM(AP9:AS9) -> 11660.107 | AU9: =AU7-AU8 -> 3699.659 | AV9: =AV7-AV8 -> 3893.232 | AW9: =AW7-AW8 -> 4046.185 | AX9: =AX7-AX8 -> 4217.522 | AY9: =SUM(AU9:AX9) -> 15856.598 | AZ9: =AZ7-AZ8 -> 4073.03 | BA9: =BA7-BA8 -> 4069.543 | BB9: =BB7-BB8 -> 4385.635 | BC9: =BC7-BC8 -> 4952.939 | BD9: =SUM(AZ9:BC9) -> 17481.147 | BE9: =BE7-BE8 -> 5064 | BF9: =BF7-BF8 -> 5088 | BG9: =BG7-BG8 -> 5481 | BH9: =BH7-BH8 -> 6371 | BI9: =SUM(BE9:BH9) -> 22004 | BJ9: =BJ7-BJ8 -> 6537 | BK9: =BK7-BK8 -> 6916 | BL9: =BL7-BL8 -> 7510 | BM9: =BM7-BM8 -> 8134 | BN9: =SUM(BJ9:BM9) -> 29097 | BO9: 8135 | BP9: 9614 | BQ9: 11331 | BR9: 11339 | BS9: 40419 | BT9: =BT7-BT8 -> 8135 | BU9: =BU7-BU8 -> 8364 | BV9: =BV7-BV8 -> 8756 | BW9: =BW7-BW8 -> 9825 | BX9: =BX7-BX8 -> 35083 | BY9: 11007 | BZ9: 11092 | CA9: 11921 | CB9: 13548 | CC9: 47568 | CD9: =CD7-CD8 -> 9989 | CE9: =CE7-CE8 -> 10094 | CF9: =CF7-CF8 -> 10782 | CG9: =CG7-CG8 -> 12397 | CH9: =CH7-CH8 -> 43261 | CI9: =CI7-CI8 -> 12188 | CJ9: =CJ7-CJ8 -> 12662 | CK9: =CK7-CK8 -> 13175 | ... EY9: =EY7-EY8 -> 637270.08 | FA9: =(EA9/DL9)^(1/3)-1 -> 0.21077003 | FB9: =(EF9/DQ9)^(1/3)-1 -> 0.19649897 | FC9: =(EK9/DV9)^(1/3)-1 -> 0.11644707 | FD9: =(EP9/EA9)^(1/3)-1 -> 0.1346695 | FE9: =(EU9/EF9)^(1/3)-1 -> 0.16274711 | FF9: =(EV9/EK9)^(1/3)-1 -> 0.15990776 | FG9: =(EK9/DL9)^(1/5)-1 -> 0.17499806 | FH9: =(EP9/DQ9)^(1/5)-1 -> 0.1793639 | FI9: =(EU9/DV9)^(1/5)-1 -> 0.13714301 | FJ9: =(EV9/EA9)^(1/5)-1 -> 0.1451285 | FK9: =(EW9/EF9)^(1/5)-1 -> 0.15127787 | FL9: =(EX9/EK9)^(1/5)-1 -> 0.14344578
A10: Other cost of revenues - non-GAAP | F10: =0.908-F8 -> 0.908 | K10: =6.081-K8 -> 6.081 | P10: =14.228-P8 -> 14.228 | Q10: =5.692-Q8 -> 5.692 | R10: =20.407-R8 -> 6.407 | S10: =39.622-S8 -> 10.622 | T10: =65.789-T8 -> 14.289 | U10: =SUM(Q10:T10) -> 37.01 | V10: =87.195-V8 -> 17.064 | W10: =117.401-W8 -> 20.842 | X10: =170.39-X8 -> 26.903 | Y10: =250.868-Y8 -> 34.512 | Z10: =SUM(V10:Y10) -> 99.321 | AA10: =315.398-AA8 -> 44.396 | AB10: =326.377-AB8 -> 49.343 | AC10: =362.099-AC8 -> 59.199 | AD10: =453.779-AD8 -> 76.071 | AE10: =SUM(AA10:AD10) -> 229.009 | AF10: 83.401 | AG10: =597.095-AG8 -> 102.775 | AH10: =653.826-AH8 -> 123.952 | AI10: 146.44 | AJ10: =SUM(AF10:AI10) -> 456.568 | AK10: =181.383-2.283 -> 179.1 | AL10: =203.873-2.322 -> 201.551 | AM10: =1048.728-2.149-AM8 -> 221.315 | AN10: =1283.148-10.874-AN8 -> 296.656 | AO10: =SUM(AK10:AN10) -> 898.622 | AP10: =345.394-4.389 -> 341.005 | AQ10: =412.342-7.659 -> 404.683 | AR10: =1662.579-AR8-4.031 -> 437.428 | AS10: =516.011-6.255 -> 509.756 | AT10: =SUM(AP10:AS10) -> 1692.872 | AU10: =624.152-9.148 -> 615.004 | AV10: =673.595-9.363 -> 664.232 | AW10: =678.184-10.729 -> 667.455 | AX10: =706.623-12.099 -> 694.524 | AY10: =SUM(AU10:AX10) -> 2641.215 | AZ10: =665.544-12.537 -> 653.007 | BA10: =654.617-13.592 -> 641.025 | BB10: =667.024-14.871 -> 652.153 | BC10: =2408.4-BC8-6.051 -> 681.463 | BD10: =SUM(AZ10:BC10) -> 2627.648 | BE10: =741-6 -> 735 | BF10: =735-8 -> 727 | BG10: =747-8 -> 739 | BH10: =2946-BH8-45 -> 832 | BI10: =SUM(BE10:BH10) -> 3033 | BJ10: =2936-BJ8-49 -> 849 | BK10: =3172-BK8-51 -> 1011 | BL10: =3378-BL8-72 -> 1096 | BM10: =3702-BM8-77 -> 1175 | BN10: =SUM(BJ10:BM10) -> 4131 | BO10: 1205 | BP10: 2318 | BQ10: 3590 | BR10: 2962 | BS10: 10075 | BT10: 1205 | BU10: 1302 | BV10: 1567 | BW10: 1782 | BX10: =+#REF! -> #REF! | BY10: 2982 | BZ10: 2935 | CA10: 3304 | CB10: 3959 | CC10: 13180 | CD10: 2075 | CE10: 2072 | CF10: 2304 | CG10: =6253-127-CG8 -> 2816 | CH10: =21993-CH8-469 -> 9266 | CI10: =2729-95 -> 2634 | CJ10: =6114-100-CJ8 -> 2721 | CK10: =6695-169-CK8 -> 3178 | CL10: =6921-171-CL8 -> 3130 | CM10: =SUM(CI10:CL10) -> 11663 | CN10: =3011-160 -> 2851 | CO10: =6583-163-CO8 -> 3043 | CP10: =7037-231-CP8 -> 3240 | CQ10: =8188-252-CQ8 -> 3881 | CR10: =SUM(CN10:CQ10) -> 13015 | CS10: =7648-241-CS8 -> 3619 | CT10: =8130-255-CT8 -> 3900 | CU10: =8699-325-CU8 -> 4192 | CV10: =10661-336-CV8 -> 5477 | CW10: =SUM(CS10:CV10) -> 17188 | CX10: =CX12-CX11 -> 4800.3315 | CY10: =CY12-CY11 -> 4917.4236 | CZ10: =CZ12-CZ11 -> 5314.7324 | DA10: =DA12-DA11 -> 7480.818 | DB10: =SUM(CX10:DA10) -> 22513.306 | FE10: =(EU10/EF10)^(1/3)-1 -> #DIV/0! | FF10: =(EV10/EK10)^(1/3)-1 -> #DIV/0! | FK10: =(EW10/EF10)^(1/5)-1 -> #DIV/0! | FL10: =(EX10/EK10)^(1/5)-1 -> #DIV/0!
A11: =CONCATENATE("SBC in ",A10) -> SBC in Other cost of revenues - non-GAAP | P11: 0.876 | U11: 1.065 | Z11: 8.557 | AE11: 11.314 | AJ11: 5.579 | AK11: 2.283 | AL11: 2.322 | AM11: 2.149 | AN11: 10.874 | AO11: =SUM(AK11:AN11) -> 17.628 | AP11: 4.389 | AQ11: 7.659 | AR11: 4.031 | AS11: 6.255 | AT11: =SUM(AP11:AS11) -> 22.334 | AU11: 9.148 | AV11: 9.363 | AW11: 10.729 | AX11: 12.099 | AY11: =SUM(AU11:AX11) -> 41.339 | AZ11: 12.537 | BA11: 13.592 | BB11: 14.871 | BC11: 6.051 | BD11: =SUM(AZ11:BC11) -> 47.051 | BE11: 6 | BF11: 8 | BG11: 8 | BH11: 45 | BI11: =SUM(BE11:BH11) -> 67 | BJ11: 49 | BK11: 51 | BL11: 72 | BM11: 77 | BN11: =SUM(BJ11:BM11) -> 249 | BX11: =BX12-BX10 -> #REF! | CD11: =CD12-CD10 -> 99 | CE11: =CE12-CE10 -> 110 | CF11: =CF12-CF10 -> 133 | CG11: 127 | CH11: =CH12-CH10 -> 469 | CI11: 95 | CJ11: 100 | CK11: 169 | CL11: 171 | CM11: =CM12-CM10 -> 531 | CN11: 160 | CO11: 163 | CP11: 231 | CQ11: 252 | CR11: =SUM(CN11:CQ11) -> 806 | CS11: 241 | CT11: 255 | CU11: 325 | CV11: 336 | CW11: =SUM(CS11:CV11) -> 1157 | CX11: =CV11/CV$24*CX$24 -> 365.66847 | CY11: =CX11/CX$24*CY$24 -> 364.57638 | CZ11: =CY11/CY$24*CZ$24 -> 331.26761 | DA11: =CZ11/CZ$24*DA$24 -> 336.18202 | DB11: =SUM(CX11:DA11) -> 1397.6945 | FE11: =(EU11/EF11)^(1/3)-1 -> #DIV/0! | FF11: =(EV11/EK11)^(1/3)-1 -> #DIV/0! | FK11: =(EW11/EF11)^(1/5)-1 -> #DIV/0! | FL11: =(EX11/EK11)^(1/5)-1 -> #DIV/0!
A12: Other cost of revenues | P12: =SUM(P10:P11) -> 15.104 | U12: =SUM(U10:U11) -> 38.075 | Z12: =SUM(Z10:Z11) -> 107.878 | AE12: =SUM(AE10:AE11) -> 240.323 | AJ12: =SUM(AJ10:AJ11) -> 462.147 | AK12: =SUM(AK10:AK11) -> 181.383 | AL12: =SUM(AL10:AL11) -> 203.873 | AM12: =SUM(AM10:AM11) -> 223.464 | AN12: =SUM(AN10:AN11) -> 307.53 | AO12: =SUM(AO10:AO11) -> 916.25 | AP12: =SUM(AP10:AP11) -> 345.394 | AQ12: =SUM(AQ10:AQ11) -> 412.342 | ... BN12: =SUM(BN10:BN11) -> 4380 | BX12: 6220 | BY12: =SUM(BY10,BY11) -> 2982 | BZ12: =SUM(BZ10,BZ11) -> 2935 | CA12: =SUM(CA10,CA11) -> 3304 | CB12: =SUM(CB10,CB11) -> 3959 | CC12: =SUM(BY12:CB12) -> 13180 | CD12: =5136-CD8 -> 2174 | CE12: =5195-CE8 -> 2182 | CF12: =5409-CF8 -> 2437 | CG12: =SUM(CG10,CG11) -> 2943 | CH12: 9735 | CI12: =SUM(CI10,CI11) -> 2729 | CJ12: =SUM(CJ10,CJ11) -> 2821 | CK12: =SUM(CK10,CK11) -> 3347 | CL12: =SUM(CL10,CL11) -> 3301 | CM12: 12194 | CN12: =SUM(CN10,CN11) -> 3011 | CO12: =SUM(CO10,CO11) -> 3206 | CP12: =SUM(CP10,CP11) -> 3471 | CQ12: =SUM(CQ10,CQ11) -> 4133 | CR12: =SUM(CN12:CQ12) -> 13821 | CS12: =SUM(CS10,CS11) -> 3860 | CT12: =SUM(CT10,CT11) -> 4155 | CU12: =SUM(CU10,CU11) -> 4517 | CV12: =SUM(CV10,CV11) -> 5813 | CW12: =SUM(CS12:CV12) -> 18345 | CX12: =9795-CX8 -> 5166 | CY12: =10373-CY8 -> 5282 | CZ12: =11148-CZ8 -> 5646 | DA12: =14267-DA8 -> 7817 | DB12: =SUM(CX12:DA12) -> 23911 | DC12: =13467-DC8 -> 7179 | DD12: =13883-DD8 -> 7463 | DE12: =14281-DE8 -> 7699 | DF12: =17918-DF8 -> 10482 | DG12: =SUM(DC12:DF12) -> 32823 | DH12: =16012-DH8 -> 9152 | DI12: =17296-DI8 -> 10058 | DJ12: =17568-DJ8 -> 10078 | DK12: =21020-DK8 -> 12519 | DL12: =SUM(DH12:DK12) -> 41807 | DM12: =18982-DM8 -> 11530 | DN12: =18553-DN8 -> 11859 | DO12: =21117-DO8 -> 12951 | DP12: =26080-DP8 -> 15614 | DQ12: =SUM(DM12:DP12) -> 51954 | DR12: =24103-DR8 -> 14391 | DS12: =26227-DS8 -> 15298 | DT12: =27621-DT8 -> 16123 | DU12: =32988-DU8 -> 19561 | DV12: =SUM(DR12:DU12) -> 65373 | DW12: =29599-DW8 -> 17609 | DX12: =30104-DX8 -> 17890 | DY12: =31158-DY8 -> 19332 | DZ12: =35342-DZ8 -> 22417 | EA12: =SUM(DW12:DZ12) -> 77248 | EB12: =30612-EB8 -> 18891 | EC12: =31916-EC8 -> 19379 | ED12: =33229-ED8 -> 20587 | EE12: =37575-EE8 -> 23589 | EF12: =SUM(EB12:EE12) -> 82446 | EG12: =33712-EG8 -> 20766 | EH12: =35507-EH8 -> 22120 | EI12: =36474-EI8 -> 22755 | EJ12: =40613-EJ8 -> 25765 | EK12: =SUM(EG12:EJ12) -> 91406 | EL12: =36361-EL8 -> 22613 | EM12: =39039-EM8 -> 24334 | EN12: =41369-EN8 -> 26493 | EO12: =EO9*EO114 -> 30428.208 | EP12: =SUM(EL12:EO12) -> 103868.21 | EQ12: =EQ9*EQ114 -> 27263.919 | ER12: =ER9*ER114 -> 29692.834 | ES12: =ES9*ES114 -> 32870.338 | ET12: =ET9*ET114 -> 37487.696 | EU12: =SUM(EQ12:ET12) -> 127314.79 | EV12: =EV9*EV114 -> 153359.36 | EW12: =EW9*EW114 -> 176392.71 | EX12: =EX9*EX114 -> 197287.56 | EY12: =EY9*EY114 -> 217309.1 | FA12: =(EA12/DL12)^(1/3)-1 -> 0.22709847 | FB12: =(EF12/DQ12)^(1/3)-1 -> 0.16640722 | FC12: =(EK12/DV12)^(1/3)-1 -> 0.1182153 | FD12: =(EP12/EA12)^(1/3)-1 -> 0.10373581 | FE12: =(EU12/EF12)^(1/3)-1 -> 0.15585428 | FF12: =(EV12/EK12)^(1/3)-1 -> 0.18826105 | FG12: =(EK12/DL12)^(1/5)-1 -> 0.16935167 | FH12: =(EP12/DQ12)^(1/5)-1 -> 0.14861036 | FI12: =(EU12/DV12)^(1/5)-1 -> 0.14260491 | FJ12: =(EV12/EA12)^(1/5)-1 -> 0.14700315 | FK12: =(EW12/EF12)^(1/5)-1 -> 0.16429279 | FL12: =(EX12/EK12)^(1/5)-1 -> 0.16633954
A13: Gross profit | F13: =F9-F10 -> -0.688 | K13: =K9-K10 -> 13.027 | P13: =P9-P10 -> 72.198 | Q13: =Q9-Q10 -> 36.593 | R13: =R9-R10 -> 58.118 | S13: =S9-S10 -> 91.165 | T13: =T9-T10 -> 122.122 | U13: =U9-U10 -> 307.998 | V13: =V9-V10 -> 161.423 | W13: =W9-W10 -> 193.798 | ... BN13: =BN9-BN10 -> 24966 | BO13: 6930 | BP13: 7296 | BQ13: 7741 | BR13: 8377 | BS13: 30344 | BT13: =BT9-BT10 -> 6930 | BU13: =BU9-BU10 -> 7062 | BV13: =BV9-BV10 -> 7189 | BW13: =BW9-BW10 -> 8043 | BX13: =BX9-BX12 -> 28863 | BY13: 8025 | BZ13: 8157 | CA13: 8617 | CB13: 9589 | CC13: 34388 | CD13: =CD9-CD12 -> 7815 | CE13: =CE9-CE12 -> 7912 | CF13: =CF9-CF12 -> 8345 | CG13: =CG9-CG12 -> 9454 | CH13: =CH9-CH12 -> 33526 | CI13: =CI9-CI12 -> 9459 | CJ13: =CJ9-CJ12 -> 9841 | CK13: =CK9-CK12 -> 9828 | ... EY13: =EY9-EY12 -> 419960.98 | FA13: =(EA13/DL13)^(1/3)-1 -> 0.20302965 | FB13: =(EF13/DQ13)^(1/3)-1 -> 0.21188787 | FC13: =(EK13/DV13)^(1/3)-1 -> 0.11565729 | FD13: =(EP13/EA13)^(1/3)-1 -> 0.14932313 | FE13: =(EU13/EF13)^(1/3)-1 -> 0.16598363 | FF13: =(EV13/EK13)^(1/3)-1 -> 0.14672274 | FG13: =(EK13/DL13)^(1/5)-1 -> 0.17758555 | FH13: =(EP13/DQ13)^(1/5)-1 -> 0.19447926 | FI13: =(EU13/DV13)^(1/5)-1 -> 0.13467485 | FJ13: =(EV13/EA13)^(1/5)-1 -> 0.14419942 | FK13: =(EW13/EF13)^(1/5)-1 -> 0.14490205 | FL13: =(EX13/EK13)^(1/5)-1 -> 0.13254789
A14: Operating expenses
A15: Research & development - non-GAAP | F15: 2.93 | K15: 10.516 | P15: 16.5 | Q15: 6.183 | R15: 6.457 | S15: 9.053 | T15: 10.055 | U15: =SUM(Q15:T15) -> 31.748 | V15: 12.505 | W15: 17.492 | X15: 32.774 | Y15: 28.457 | Z15: =SUM(V15:Y15) -> 91.228 | AA15: 35.019 | AB15: 45.762 | AC15: 57.409 | AD15: 87.442 | AE15: =SUM(AA15:AD15) -> 225.632 | AF15: 79.412 | AG15: 95.772 | AH15: =151.721 -> 151.721 | AI15: 157.072 | AJ15: =SUM(AF15:AI15) -> 483.977 | AK15: =246.599-73.086 -> 173.513 | AL15: =282.552-70.564 -> 211.988 | AM15: =312.632-61.714 -> 250.918 | AN15: =386.806-82.122 -> 304.684 | AO15: =SUM(AK15:AN15) -> 941.103 | AP15: =408.384-120.787 -> 287.597 | AQ15: =532.106-156.983 -> 375.123 | AR15: =548.712-130.65 -> 418.062 | AS15: =630.783-161.372 -> 469.411 | AT15: =SUM(AP15:AS15) -> 1550.193 | AU15: =673.069-193.8 -> 479.269 | AV15: =682.21-187.281 -> 494.929 | AW15: =704.571-169.263 -> 535.308 | AX15: =733.342-182.075 -> 551.267 | AY15: =SUM(AU15:AX15) -> 2060.773 | AZ15: =641.643-168.561 -> 473.082 | BA15: =707.626-182.209 -> 525.417 | BB15: =757.524-195.624 -> 561.9 | BC15: =736.234-178.948 -> 557.286 | BD15: =SUM(AZ15:BC15) -> 2117.685 | BE15: =818-191 -> 627 | BF15: =898-202 -> 696 | BG15: =994-244 -> 750 | BH15: =1051-224 -> 827 | BI15: =SUM(BE15:BH15) -> 2900 | BJ15: =1226-237 -> 989 | BK15: =1234-247 -> 987 | BL15: =1404-311 -> 1093 | BM15: =1298-266 -> 1032 | BN15: =SUM(BJ15:BM15) -> 4101 | BO15: 1142 | BP15: 1281 | BQ15: 1527 | BR15: 1487 | BS15: 5437 | BT15: 1142 | BU15: 1163 | BV15: 1190 | BW15: 1314 | BX15: =SUM(BT15:BW15) -> 4809 | BY15: 1476 | BZ15: 1566 | CA15: 1564 | CB15: 1642 | CC15: 6248 | CD15: 1279 | CE15: 1365 | CF15: 1385 | CG15: =1933-466 -> 1467 | CH15: =7137-1641 -> 5496 | CI15: =2126-456 -> 1670 | CJ15: =2238-447 -> 1791 | CK15: =2655-666 -> 1989 | CL15: =2813-631 -> 2182 | CM15: =SUM(CI15:CL15) -> 7632 | CN15: =2753-615 -> 2138 | CO15: =2789-583 -> 2206 | CP15: =3230-741 -> 2489 | CQ15: =3510-739 -> 2771 | CR15: =SUM(CN15:CQ15) -> 9604 | CS15: =3367-739 -> 2628 | CT15: =3363-739 -> 2624 | CU15: =3596-922 -> 2674 | CV15: =3622-907 -> 2715 | CW15: =SUM(CS15:CV15) -> 10641 | CX15: =CX17-CX16 -> 2954.9128 | CY15: =CY17-CY16 -> 3187.8608 | CZ15: =CZ17-CZ16 -> 3310.7746 | DA15: =DA17-DA16 -> 3398.5087 | DB15: =SUM(CX15:DA15) -> 12852.057
A16: =CONCATENATE("SBC in ",A15) -> SBC in Research & development - non-GAAP | P16: 4.44 | U16: 8.746 | Z16: 138.377 | AE16: 169.532 | AJ16: 115.532 | AK16: =AK17-AK15 -> 73.086 | AL16: =AL17-AL15 -> 70.564 | AM16: =AM17-AM15 -> 61.714 | AN16: =AN17-AN15 -> 82.122 | AO16: =SUM(AK16:AN16) -> 287.486 | AP16: 120.787 | AQ16: 156.983 | AR16: 130.65 | AS16: 161.372 | AT16: =SUM(AP16:AS16) -> 569.792 | AU16: 193.8 | AV16: 187.281 | AW16: 169.263 | AX16: 182.075 | AY16: =SUM(AU16:AX16) -> 732.419 | AZ16: 168.561 | BA16: 182.209 | BB16: 195.624 | BC16: 178.948 | BD16: =SUM(AZ16:BC16) -> 725.342 | BE16: 191 | BF16: 202 | BG16: 244 | BH16: 224 | BI16: =SUM(BE16:BH16) -> 861 | BJ16: 237 | BK16: 247 | BL16: 311 | BM16: 266 | BN16: =SUM(BJ16:BM16) -> 1061 | BX16: =BX17-BX15 -> 1274 | CD16: =CD17-CD15 -> 338 | CE16: =CE17-CE15 -> 401 | CF16: =CF17-CF15 -> 436 | CG16: 466 | CH16: =SUM(CD16:CG16) -> 1641 | CI16: 456 | CJ16: 447 | CK16: 666 | CL16: 631 | CM16: =SUM(CI16:CL16) -> 2200 | CN16: 615 | CO16: 583 | CP16: 741 | CQ16: 739 | CR16: =SUM(CN16:CQ16) -> 2678 | CS16: 739 | CT16: 739 | CU16: 922 | CV16: 907 | CW16: =SUM(CS16:CV16) -> 3307 | CX16: =CV16/CV$24*CX$24 -> 987.08722 | CY16: =CX16/CX$24*CY$24 -> 984.13922 | CZ16: =CY16/CY$24*CZ$24 -> 894.22535 | DA16: =CZ16/CZ$24*DA$24 -> 907.49133 | DB16: =SUM(CX16:DA16) -> 3772.9431
A17: Research & development | P17: =SUM(P15:P16) -> 20.94 | U17: =SUM(U15:U16) -> 40.494 | Z17: =SUM(Z15:Z16) -> 229.605 | AE17: =SUM(AE15:AE16) -> 395.164 | AJ17: =SUM(AJ15:AJ16) -> 599.509 | AK17: =246.599 -> 246.599 | AL17: =282.552 -> 282.552 | AM17: =312.632 -> 312.632 | AN17: =386.806 -> 386.806 | AO17: =SUM(AO15:AO16) -> 1228.589 | AP17: =SUM(AP15:AP16) -> 408.384 | AQ17: =SUM(AQ15:AQ16) -> 532.106 | AR17: =SUM(AR15:AR16) -> 548.712 | AS17: =SUM(AS15:AS16) -> 630.783 | AT17: =SUM(AT15:AT16) -> 2119.985 | AU17: =SUM(AU15:AU16) -> 673.069 | AV17: =SUM(AV15:AV16) -> 682.21 | ... BN17: =SUM(BN15:BN16) -> 5162 | BX17: 6083 | CD17: =1617 -> 1617 | CE17: 1766 | CF17: 1821 | CG17: =SUM(CG15,CG16) -> 1933 | CH17: =SUM(CH15:CH16) -> 7137 | CI17: =SUM(CI15,CI16) -> 2126 | CJ17: =SUM(CJ15,CJ16) -> 2238 | CK17: =SUM(CK15,CK16) -> 2655 | CL17: =SUM(CL15,CL16) -> 2813 | CM17: =SUM(CM15:CM16) -> 9832 | CN17: =SUM(CN15,CN16) -> 2753 | CO17: =SUM(CO15,CO16) -> 2789 | CP17: =SUM(CP15,CP16) -> 3230 | CQ17: =SUM(CQ15,CQ16) -> 3510 | CR17: =SUM(CN17:CQ17) -> 12282 | CS17: =SUM(CS15,CS16) -> 3367 | CT17: =SUM(CT15,CT16) -> 3363 | CU17: =SUM(CU15,CU16) -> 3596 | CV17: =SUM(CV15,CV16) -> 3622 | CW17: =SUM(CS17:CV17) -> 13948 | CX17: 3942 | CY17: 4172 | CZ17: 4205 | DA17: 4306 | DB17: =SUM(CX17:DA17) -> 16625 | DC17: 5039 | DD17: 5114 | DE17: 5232 | DF17: 6034 | DG17: =SUM(DC17:DF17) -> 21419 | DH17: 6029 | DI17: 6213 | DJ17: 6554 | DK17: 7222 | DL17: =SUM(DH17:DK17) -> 26018 | DM17: 6820 | DN17: 6875 | DO17: 6856 | DP17: 7022 | DQ17: =SUM(DM17:DP17) -> 27573 | DR17: 7485 | DS17: 7675 | DT17: 7694 | DU17: 8708 | DV17: =SUM(DR17:DU17) -> 31562 | DW17: 9119 | DX17: 9841 | DY17: 10273 | DZ17: 10267 | EA17: =SUM(DW17:DZ17) -> 39500 | EB17: =11468 -> 11468 | EC17: 10588 | ED17: 11258 | EE17: 12113 | EF17: =SUM(EB17:EE17) -> 45427 | EG17: 11903 | EH17: 11860 | EI17: 12447 | EJ17: 13116 | EK17: =SUM(EG17:EJ17) -> 49326 | EL17: 13556 | EM17: 13808 | EN17: 15151 | EO17: =EO9*EO117 -> 15742.038 | EP17: =SUM(EL17:EO17) -> 58257.038 | EQ17: =EQ9*EQ117 -> 16267.472 | ER17: =ER9*ER117 -> 16539.005 | ES17: =ES9*ES117 -> 17975.966 | ET17: =ET9*ET117 -> 18630.933 | EU17: =SUM(EQ17:ET17) -> 69413.376 | EV17: =EV9*EV117 -> 77831.027 | EW17: =EW9*EW117 -> 85083.541 | EX17: =EX9*EX117 -> 92298.272 | EY17: =EY9*EY117 -> 99414.132 | FA17: =(EA17/DL17)^(1/3)-1 -> 0.14932026 | FB17: =(EF17/DQ17)^(1/3)-1 -> 0.18107283 | FC17: =(EK17/DV17)^(1/3)-1 -> 0.16047858 | FD17: =(EP17/EA17)^(1/3)-1 -> 0.13828349 | FE17: =(EU17/EF17)^(1/3)-1 -> 0.15179813 | FF17: =(EV17/EK17)^(1/3)-1 -> 0.16419471 | FG17: =(EK17/DL17)^(1/5)-1 -> 0.13647634 | FH17: =(EP17/DQ17)^(1/5)-1 -> 0.16137608 | FI17: =(EU17/DV17)^(1/5)-1 -> 0.17072726 | FJ17: =(EV17/EA17)^(1/5)-1 -> 0.14527857 | FK17: =(EW17/EF17)^(1/5)-1 -> 0.13372128 | FL17: =(EX17/EK17)^(1/5)-1 -> 0.13350525
A18: Sales & marketing - non-GAAP | F18: 1.677 | K18: 10.385 | P18: 20.076 | Q18: 7.294 | R18: 11.176 | S18: 11.704 | T18: 13.675 | U18: =SUM(Q18:T18) -> 43.849 | V18: 17.767 | W18: 24.822 | X18: 36.575 | Y18: 41.164 | Z18: =SUM(V18:Y18) -> 120.328 | AA18: 47.904 | AB18: 56.777 | AC18: 65.512 | AD18: 76.107 | AE18: =SUM(AA18:AD18) -> 246.3 | AF18: 82.952 | AG18: 97.024 | AH18: 104.996 | AI18: 154.769 | AJ18: =SUM(AF18:AI18) -> 439.741 | AK18: =190.943-15.929 -> 175.014 | AL18: =196.397-14.285 -> 182.112 | AM18: =206.972-14.673 -> 192.299 | AN18: =255.206-14.502 -> 240.704 | AO18: =SUM(AK18:AN18) -> 790.129 | AP18: =302.552-27.25 -> 275.302 | AQ18: =355.604-36.385 -> 319.219 | AR18: =380.82-29.918 -> 350.902 | AS18: =422.291-38.085 -> 384.206 | AT18: =SUM(AP18:AS18) -> 1329.629 | AU18: =446.898-42.576 -> 404.322 | AV18: =484.552-42.593 -> 441.959 | AW18: =508.801-64.497 -> 444.304 | AX18: =505.993-56.354 -> 449.639 | AY18: =SUM(AU18:AX18) -> 1740.224 | AZ18: =433.941-59.026 -> 374.915 | BA18: =469.039-57.294 -> 411.745 | BB18: =497.812-62.26 -> 435.552 | BC18: =583.149-52.439 -> 530.71 | BD18: =SUM(AZ18:BC18) -> 1752.922 | BE18: =607-54 -> 553 | BF18: =629-56 -> 573 | BG18: =661-75 -> 586 | BH18: =902-76 -> 826 | BI18: =SUM(BE18:BH18) -> 2538 | BJ18: =1026-78 -> 948 | BK18: =1091-74 -> 1017 | BL18: =1204-104 -> 1100 | BM18: =1268-105 -> 1163 | BN18: =SUM(BJ18:BM18) -> 4228 | BO18: 1172 | BP18: 1294 | BQ18: 1521 | BR18: 1611 | BS18: 5598 | BT18: 1172 | BU18: 1185 | BV18: 1259 | BW18: 1401 | BX18: =SUM(BT18:BW18) -> 5017 | BY18: 1461 | BZ18: 1601 | CA18: 1646 | CB18: 1970 | CC18: 6678 | CD18: 1317 | CE18: 1458 | CF18: 1473 | CG18: =1908-154 -> 1754 | CH18: =6554-552 -> 6002 | CI18: =1729-147 -> 1582 | CJ18: =1941-158 -> 1783 | CK18: =2084-197 -> 1887 | CL18: =2377-213 -> 2164 | CM18: =SUM(CI18:CL18) -> 7416 | CN18: =2065-205 -> 1860 | CO18: =2080-196 -> 1884 | CP18: =2223-250 -> 1973 | CQ18: =2679-240 -> 2439 | CR18: =SUM(CN18:CQ18) -> 8156 | CS18: =2387-242 -> 2145 | CT18: =2415-238 -> 2177 | CU18: =2565-297 -> 2268 | CV18: =3118-301 -> 2817 | CW18: =SUM(CS18:CV18) -> 9407 | CX18: =CX20-CX19 -> 2316.422 | CY18: =CY20-CY19 -> 2570.4003 | CZ18: =CZ20-CZ19 -> 2745.2394 | DA18: =DA20-DA19 -> 4008.8369 | DB18: =SUM(CX18:DA18) -> 11640.899 | FE18: =(EU18/EF18)^(1/3)-1 -> #DIV/0! | FF18: =(EV18/EK18)^(1/3)-1 -> #DIV/0! | FK18: =(EW18/EF18)^(1/5)-1 -> #DIV/0! | FL18: =(EX18/EK18)^(1/5)-1 -> #DIV/0!
A19: =CONCATENATE("SBC in ",A18) -> SBC in Sales & marketing - non-GAAP | P19: 1.667 | U19: 4.934 | Z19: 44.607 | AE19: 49.449 | AJ19: 28.411 | AK19: =AK20-AK18 -> 15.929 | AL19: =AL20-AL18 -> 14.285 | AM19: =AM20-AM18 -> 14.673 | AN19: =AN20-AN18 -> 14.502 | AO19: =SUM(AK19:AN19) -> 59.389 | AP19: 27.25 | AQ19: 36.385 | AR19: 29.818 | AS19: 38.085 | AT19: =SUM(AP19:AS19) -> 131.538 | AU19: 42.576 | AV19: 42.593 | AW19: 64.497 | AX19: 56.354 | AY19: =SUM(AU19:AX19) -> 206.02 | AZ19: 59.026 | BA19: 57.294 | BB19: 62.26 | BC19: 52.439 | BD19: =SUM(AZ19:BC19) -> 231.019 | BE19: 54 | BF19: 56 | BG19: 75 | BH19: 76 | BI19: =SUM(BE19:BH19) -> 261 | BJ19: 78 | BK19: 74 | BL19: 104 | BM19: 105 | BN19: =SUM(BJ19:BM19) -> 361 | BX19: =BX20-BX18 -> 448 | CD19: =CD20-CD18 -> 118 | CE19: =CE20-CE18 -> 125 | CF19: =CF20-CF18 -> 155 | CG19: 154 | CH19: =SUM(CD19:CG19) -> 552 | CI19: 147 | CJ19: 158 | CK19: 197 | CL19: 213 | CM19: =SUM(CI19:CL19) -> 715 | CN19: 205 | CO19: 196 | CP19: 250 | CQ19: 240 | CR19: =SUM(CN19:CQ19) -> 891 | CS19: 242 | CT19: 238 | CU19: 297 | CV19: 301 | CW19: =SUM(CS19:CV19) -> 1078 | CX19: =CV19/CV$24*CX$24 -> 327.57801 | CY19: =CX19/CX$24*CY$24 -> 326.59967 | CZ19: =CY19/CY$24*CZ$24 -> 296.76056 | DA19: =CZ19/CZ$24*DA$24 -> 301.16306 | DB19: =SUM(CX19:DA19) -> 1252.1013 | FE19: =(EU19/EF19)^(1/3)-1 -> #DIV/0! | FF19: =(EV19/EK19)^(1/3)-1 -> #DIV/0! | FK19: =(EW19/EF19)^(1/5)-1 -> #DIV/0! | FL19: =(EX19/EK19)^(1/5)-1 -> #DIV/0!
A20: Sales & marketing | P20: =SUM(P18:P19) -> 21.743 | U20: =SUM(U18:U19) -> 48.783 | Z20: =SUM(Z18:Z19) -> 164.935 | AE20: =SUM(AE18:AE19) -> 295.749 | AJ20: =SUM(AJ18:AJ19) -> 468.152 | AK20: =190.943 -> 190.943 | AL20: =196.397 -> 196.397 | AM20: =206.972 -> 206.972 | AN20: =255.206 -> 255.206 | AO20: =SUM(AO18:AO19) -> 849.518 | AP20: =SUM(AP18:AP19) -> 302.552 | AQ20: =SUM(AQ18:AQ19) -> 355.604 | AR20: =SUM(AR18:AR19) -> 380.72 | AS20: =SUM(AS18:AS19) -> 422.291 | AT20: =SUM(AT18:AT19) -> 1461.167 | AU20: =SUM(AU18:AU19) -> 446.898 | AV20: =SUM(AV18:AV19) -> 484.552 | ... BN20: =SUM(BN18:BN19) -> 4589 | BX20: 5465 | CD20: 1435 | CE20: 1583 | CF20: 1628 | CG20: =SUM(CG18,CG19) -> 1908 | CH20: =SUM(CH18,CH19) -> 6554 | CI20: =SUM(CI18,CI19) -> 1729 | CJ20: =SUM(CJ18,CJ19) -> 1941 | CK20: =SUM(CK18,CK19) -> 2084 | CL20: =SUM(CL18,CL19) -> 2377 | CM20: =SUM(CI20:CL20) -> 8131 | CN20: =SUM(CN18,CN19) -> 2065 | CO20: =SUM(CO18,CO19) -> 2080 | CP20: =SUM(CP18,CP19) -> 2223 | CQ20: =SUM(CQ18,CQ19) -> 2679 | CR20: =SUM(CN20:CQ20) -> 9047 | CS20: =SUM(CS18,CS19) -> 2387 | CT20: =SUM(CT18,CT19) -> 2415 | CU20: =SUM(CU18,CU19) -> 2565 | CV20: =SUM(CV18,CV19) -> 3118 | CW20: =SUM(CS20:CV20) -> 10485 | CX20: 2644 | CY20: 2897 | CZ20: 3042 | DA20: 4310 | DB20: =SUM(CX20:DA20) -> 12893 | DC20: 3604 | DD20: 3780 | DE20: 3849 | DF20: 5100 | DG20: =SUM(DC20:DF20) -> 16333 | DH20: 3905 | DI20: 4212 | DJ20: 4609 | DK20: 5738 | DL20: =SUM(DH20:DK20) -> 18464 | DM20: 4500 | DN20: 3901 | DO20: 4231 | DP20: 5314 | DQ20: =SUM(DM20:DP20) -> 17946 | DR20: 4516 | DS20: 5276 | DT20: 5516 | DU20: 7604 | DV20: =SUM(DR20:DU20) -> 22912 | DW20: 5825 | DX20: 6630 | DY20: 6929 | DZ20: 7183 | EA20: =SUM(DW20:DZ20) -> 26567 | EB20: =6533 -> 6533 | EC20: 6781 | ED20: 6884 | EE20: 7719 | EF20: =SUM(EB20:EE20) -> 27917 | EG20: 6426 | EH20: 6792 | EI20: 7227 | EJ20: 7363 | EK20: =SUM(EG20:EJ20) -> 27808 | EL20: 6172 | EM20: 7101 | EN20: 7205 | EO20: =EO9*EO120 -> 7583.0549 | EP20: =SUM(EL20:EO20) -> 28061.055 | EQ20: =EQ9*EQ120 -> 6452.4608 | ER20: =ER9*ER120 -> 7737.5462 | ES20: =ES9*ES120 -> 7703.9854 | ET20: =ET9*ET120 -> 8016.9471 | EU20: =SUM(EQ20:ET20) -> 29910.939 | EV20: =EV9*EV120 -> 32237.703 | EW20: =EW9*EW120 -> 34240.937 | EX20: =EX9*EX120 -> 36342.445 | EY20: =EY9*EY120 -> 38236.205 | FA20: =(EA20/DL20)^(1/3)-1 -> 0.12894359 | FB20: =(EF20/DQ20)^(1/3)-1 -> 0.15868938 | FC20: =(EK20/DV20)^(1/3)-1 -> 0.066683518 | FD20: =(EP20/EA20)^(1/3)-1 -> 0.018404929 | FE20: =(EU20/EF20)^(1/3)-1 -> 0.023262604 | FF20: =(EV20/EK20)^(1/3)-1 -> 0.050504976 | FG20: =(EK20/DL20)^(1/5)-1 -> 0.085347456 | FH20: =(EP20/DQ20)^(1/5)-1 -> 0.093521349 | FI20: =(EU20/DV20)^(1/5)-1 -> 0.054759415 | FJ20: =(EV20/EA20)^(1/5)-1 -> 0.039451705 | FK20: =(EW20/EF20)^(1/5)-1 -> 0.041682526 | FL20: =(EX20/EK20)^(1/5)-1 -> 0.054991296
A21: General & administrative - non-GAAP | F21: 1.221 | K21: 4.357 | P21: 12.275 | Q21: 4.135 | R21: 5.653 | S21: 7.313 | T21: 7.199 | U21: =SUM(Q21:T21) -> 24.3 | V21: 10.027 | W21: 12.535 | X21: 13.853 | Y21: 20.284 | Z21: =SUM(V21:Y21) -> 56.699 | AA21: 21.506 | AB21: 25.577 | AC21: 40.774 | AD21: 51.843 | AE21: =SUM(AA21:AD21) -> 139.7 | AF21: 57.266 | AG21: 71.568 | AH21: 92.434 | AI21: 114.077 | AJ21: =SUM(AF21:AI21) -> 335.345 | AK21: =169.395-23.366 -> 146.029 | AL21: =172.638-21.978 -> 150.66 | AM21: =190.01-21.324 -> 168.686 | AN21: =219.744-26.929 -> 192.815 | AO21: =SUM(AK21:AN21) -> 658.19 | AP21: =261.4-31.44 -> 229.96 | AQ21: =319.405-40.497 -> 278.908 | AR21: =321.398-33.352 -> 288.046 | AS21: =377.046-39.588 -> 337.458 | AT21: =SUM(AP21:AS21) -> 1134.372 | AU21: =409.305-35.255 -> 374.05 | AV21: =474.91-33.539 -> 441.371 | AW21: =507.064-35.55 -> 471.514 | AX21: =411.36-35.644 -> 375.716 | AY21: =SUM(AU21:AX21) -> 1662.651 | AZ21: =448.311-37.359 -> 410.952 | BA21: =364.367-39.975 -> 324.392 | BB21: =389.557-44.772 -> 344.785 | BC21: =465.059-38.536 -> 426.523 | BD21: =SUM(AZ21:BC21) -> 1506.652 | BE21: =410-40 -> 370 | BF21: =461-43 -> 418 | BG21: =532-53 -> 479 | BH21: =559-51 -> 508 | BI21: =SUM(BE21:BH21) -> 1775 | BJ21: =591-68 -> 523 | BK21: =648-63 -> 585 | BL21: =676-84 -> 592 | BM21: =809-88 -> 721 | BN21: =SUM(BJ21:BM21) -> 2421 | BO21: 671 | BP21: 771 | BQ21: 893 | BR21: 1007 | BS21: 3342 | BT21: 671 | BU21: 726 | BV21: 789 | BW21: 904 | BX21: =SUM(BT21:BW21) -> 3090 | BY21: 1018 | BZ21: 1084 | CA21: 1077 | CB21: 1138 | CC21: 4317 | CD21: 915 | CE21: 991 | CF21: 1003 | CG21: =1184-126 -> 1058 | CH21: =4432-465 -> 3967 | CI21: =1489-141 -> 1348 | CJ21: =1404-175 -> 1229 | CK21: =1365-223 -> 1142 | CL21: =1593-186 -> 1407 | CM21: =SUM(CI21:CL21) -> 5126 | CN21: =1637-223 -> 1414 | CO21: =1450-190 -> 1260 | CP21: =1477-210 -> 1267 | CQ21: =1572-205 -> 1367 | CR21: =SUM(CN21:CQ21) -> 5308 | CS21: =1513-272 -> 1241 | CT21: =1624-271 -> 1353 | CU21: =1824-316 -> 1508 | CV21: =2024-302 -> 1722 | CW21: =SUM(CS21:CV21) -> 5824 | CX21: =CX23-CX22 -> 1472.3337 | CY21: =CY23-CY22 -> 1372.3153 | CZ21: =CZ23-CZ22 -> 1297.2535 | DA21: =DA23-DA22 -> 1473.8364 | DB21: =SUM(CX21:DA21) -> 5615.7389 | FE21: =(EU21/EF21)^(1/3)-1 -> #DIV/0! | FF21: =(EV21/EK21)^(1/3)-1 -> #DIV/0! | FK21: =(EW21/EF21)^(1/5)-1 -> #DIV/0! | FL21: =(EX21/EK21)^(1/5)-1 -> #DIV/0!
A22: =CONCATENATE("SBC in ",A21) -> SBC in General & administrative - non-GAAP | P22: 5.4 | U22: 6.89 | Z22: 37.82 | AE22: 48.451 | AJ22: 51.187 | AK22: =AK23-AK21 -> 23.366 | AL22: =AL23-AL21 -> 21.978 | AM22: =AM23-AM21 -> 21.324 | AN22: =AN23-AN21 -> 26.929 | AO22: =SUM(AK22:AN22) -> 93.597 | AP22: 31.44 | AQ22: 40.497 | AR22: 33.352 | AS22: 39.588 | AT22: =SUM(AP22:AS22) -> 144.877 | AU22: 35.255 | AV22: 33.539 | AW22: 35.55 | AX22: 35.644 | AY22: =SUM(AU22:AX22) -> 139.988 | AZ22: 37.359 | BA22: 39.975 | BB22: 44.772 | BC22: 38.536 | BD22: =SUM(AZ22:BC22) -> 160.642 | BE22: 40 | BF22: 43 | BG22: 53 | BH22: 51 | BI22: =SUM(BE22:BH22) -> 187 | BJ22: 68 | BK22: 63 | BL22: 84 | BM22: 88 | BN22: =SUM(BJ22:BM22) -> 303 | BX22: =BX23-BX21 -> 391 | CD22: =CD23-CD21 -> 100 | CE22: =CE23-CE21 -> 107 | CF22: =CF23-CF21 -> 132 | CG22: 126 | CH22: =SUM(CD22:CG22) -> 465 | CI22: 141 | CJ22: 175 | CK22: 223 | CL22: 186 | CM22: =SUM(CI22:CL22) -> 725 | CN22: 223 | CO22: 190 | CP22: 210 | CQ22: 205 | CR22: =SUM(CN22:CQ22) -> 828 | CS22: 272 | CT22: 271 | CU22: 316 | CV22: 302 | CW22: =SUM(CS22:CV22) -> 1161 | CX22: =CV22/CV$24*CX$24 -> 328.66631 | CY22: =CX22/CX$24*CY$24 -> 327.68472 | CZ22: =CY22/CY$24*CZ$24 -> 297.74648 | DA22: =CZ22/CZ$24*DA$24 -> 302.1636 | DB22: =SUM(CX22:DA22) -> 1256.2611 | FE22: =(EU22/EF22)^(1/3)-1 -> #DIV/0! | FF22: =(EV22/EK22)^(1/3)-1 -> #DIV/0! | FK22: =(EW22/EF22)^(1/5)-1 -> #DIV/0! | FL22: =(EX22/EK22)^(1/5)-1 -> #DIV/0!
A23: General & administrative | P23: =SUM(P21:P22) -> 17.675 | U23: =SUM(U21:U22) -> 31.19 | Z23: =SUM(Z21:Z22) -> 94.519 | AE23: =SUM(AE21:AE22) -> 188.151 | AJ23: =SUM(AJ21:AJ22) -> 386.532 | AK23: =169.395 -> 169.395 | AL23: =172.638 -> 172.638 | AM23: =190.01 -> 190.01 | AN23: =219.744 -> 219.744 | AO23: =SUM(AO21:AO22) -> 751.787 | AP23: =SUM(AP21:AP22) -> 261.4 | AQ23: =SUM(AQ21:AQ22) -> 319.405 | AR23: =SUM(AR21:AR22) -> 321.398 | AS23: =SUM(AS21:AS22) -> 377.046 | AT23: =SUM(AT21:AT22) -> 1279.249 | AU23: =SUM(AU21:AU22) -> 409.305 | AV23: =SUM(AV21:AV22) -> 474.91 | ... BN23: =SUM(BN21:BN22) -> 2724 | BX23: 3481 | CD23: 1015 | CE23: 1098 | CF23: 1135 | CG23: =SUM(CG21,CG22) -> 1184 | CH23: =SUM(CH21,CH22) -> 4432 | CI23: =SUM(CI21,CI22) -> 1489 | CJ23: =SUM(CJ21,CJ22) -> 1404 | CK23: =SUM(CK21,CK22) -> 1365 | CL23: =SUM(CL21,CL22) -> 1593 | CM23: =SUM(CI23:CL23) -> 5851 | CN23: =SUM(CN21,CN22) -> 1637 | CO23: =SUM(CO21,CO22) -> 1450 | CP23: =SUM(CP21,CP22) -> 1477 | CQ23: =SUM(CQ21,CQ22) -> 1572 | CR23: =SUM(CN23:CQ23) -> 6136 | CS23: =SUM(CS21,CS22) -> 1513 | CT23: =SUM(CT21,CT22) -> 1624 | CU23: =SUM(CU21,CU22) -> 1824 | CV23: =SUM(CV21,CV22) -> 2024 | CW23: =SUM(CS23:CV23) -> 6985 | CX23: 1801 | CY23: 1700 | CZ23: 1595 | DA23: 1776 | DB23: =SUM(CX23:DA23) -> 6872 | DC23: =2035-632 -> 1403 | DD23: =2002-238 -> 1764 | DE23: =2068-315 -> 1753 | DF23: =2021-18 -> 2003 | DG23: =SUM(DC23:DF23) -> 6923 | DH23: 2088 | DI23: 2043 | DJ23: =2591 -> 2591 | DK23: 2829 | DL23: =SUM(DH23:DK23) -> 9551 | DM23: 2880 | DN23: 2585 | DO23: 2756 | DP23: 2831 | DQ23: =SUM(DM23:DP23) -> 11052 | DR23: 2773 | DS23: 3341 | DT23: 3256 | DU23: 4140 | DV23: =SUM(DR23:DU23) -> 13510 | DW23: 3374 | DX23: 3657 | DY23: 3597 | DZ23: 5096 | EA23: =SUM(DW23:DZ23) -> 15724 | EB23: =3759 -> 3759 | EC23: 3481 | ED23: 3979 | EE23: 5206 | EF23: =SUM(EB23:EE23) -> 16425 | EG23: 3026 | EH23: 3158 | EI23: 3599 | EJ23: 4405 | EK23: =SUM(EG23:EJ23) -> 14188 | EL23: 3539 | EM23: 5209 | EN23: =7393-EN25 -> 3936 | EO23: =EO9*EO123 -> 4895.3899 | EP23: =SUM(EL23:EO23) -> 17579.39 | EQ23: =EQ9*EQ123 -> 3771.5088 | ER23: =ER9*ER123 -> 3820.4134 | ES23: =ES9*ES123 -> 4057.4323 | ET23: =ET9*ET123 -> 5194.0784 | EU23: =SUM(EQ23:ET23) -> 16843.433 | EV23: =EV9*EV123 -> 18421.545 | EW23: =EW9*EW123 -> 19714.479 | EX23: =EX9*EX123 -> 20767.111 | EY23: =EY9*EY123 -> 21667.183 | FA23: =(EA23/DL23)^(1/3)-1 -> 0.18078655 | FB23: =(EF23/DQ23)^(1/3)-1 -> 0.14118179 | FC23: =(EK23/DV23)^(1/3)-1 -> 0.016456062 | FD23: =(EP23/EA23)^(1/3)-1 -> 0.037879469 | FE23: =(EU23/EF23)^(1/3)-1 -> 0.0084206825 | FF23: =(EV23/EK23)^(1/3)-1 -> 0.090941901 | FG23: =(EK23/DL23)^(1/5)-1 -> 0.082366811 | FH23: =(EP23/DQ23)^(1/5)-1 -> 0.097267673 | FI23: =(EU23/DV23)^(1/5)-1 -> 0.045093273 | FJ23: =(EV23/EA23)^(1/5)-1 -> 0.032173257 | FK23: =(EW23/EF23)^(1/5)-1 -> 0.037184421 | FL23: =(EX23/EK23)^(1/5)-1 -> 0.079172778
A24: Stock compensation expense (incl. above) | F24: 0 | K24: 2.506 | P24: 12.383 | Q24: 3.774 | R24: 3.735 | S24: 6.182 | T24: 7.944 | U24: =SUM(Q24:T24) -> 21.635 | V24: 36.418 | W24: 34.165 | X24: 73.794 | Y24: 84.984 | Z24: =SUM(V24:Y24) -> 229.361 | AA24: 76.473 | AB24: 74.761 | AC24: 67.981 | AD24: 59.531 | AE24: =SUM(AA24:AD24) -> 278.746 | AF24: 48.908 | AG24: 47.338 | AH24: 46.308 | AI24: 58.154 | AJ24: =SUM(AF24:AI24) -> 200.708 | AK24: =2.283+73.086+15.929+23.366 -> 114.664 | AL24: =2.322+70.564+14.285+21.978 -> 109.149 | AM24: =2.149+61.714+14.673+21.324 -> 99.86 | AN24: =10.874+82.122+14.502+26.929 -> 134.427 | AO24: =SUM(AK24:AN24) -> 458.1 | AP24: =4.389+120.787+27.25+31.44 -> 183.866 | AQ24: =7.659+156.983+36.385+40.497 -> 241.524 | AR24: =4.031+130.655+29.918+33.352 -> 197.956 | AS24: =6.255+161.372+38.085+39.588 -> 245.3 | AT24: =SUM(AP24:AS24) -> 868.646 | AU24: =9.148+193.8+42.576+35.255 -> 280.779 | AV24: =9.363+187.281+42.593+33.539 -> 272.776 | AW24: =10.729+169.263+64.497+35.55 -> 280.039 | AX24: =12.099+182.075+56.354+35.644 -> 286.172 | AY24: =SUM(AU24:AX24) -> 1119.766 | AZ24: =12.537+168.561+59.026+37.359 -> 277.483 | BA24: =13.592+182.209+57.294+39.975 -> 293.07 | BB24: =14.871+195.624+62.26+44.772 -> 317.527 | BC24: =6.051+178.948+52.439+38.536 -> 275.974 | BD24: =SUM(AZ24:BC24) -> 1164.054 | BE24: =6+191+54+40 -> 291 | BF24: =8+202+56+43 -> 309 | BG24: =8+244+75+53 -> 380 | BH24: =45+224+76+51 -> 396 | BI24: =SUM(BE24:BH24) -> 1376 | BJ24: =49+237+78+68 -> 432 | BK24: 435 | BL24: 571 | BM24: =77+266+105+88 -> 536 | BN24: =SUM(BJ24:BM24) -> 1974 | BO24: 556 | BP24: 747 | BQ24: 1064 | BR24: 878 | BS24: 3245 | BT24: 556 | BU24: 552 | BV24: 688 | BW24: 677 | BX24: =SUM(BT24:BW24) -> 2473 | BY24: 593 | BZ24: 783 | CA24: 886 | CB24: 917 | CC24: 3179 | CD24: =SUM(CD11,CD16,CD19,CD22) -> 655 | CE24: 743 | CF24: 856 | CG24: =SUM(CG11,CG16,CG19,CG22) -> 873 | CH24: =469+1641+552+465 -> 3127 | CI24: =SUM(CI11,CI16,CI19,CI22) -> 839 | CJ24: =SUM(CJ11,CJ16,CJ19,CJ22) -> 880 | CK24: =SUM(CK11,CK16,CK19,CK22) -> 1255 | CL24: =SUM(CL11,CL16,CL19,CL22) -> 1201 | CM24: =SUM(CI24:CL24) -> 4175 | CN24: =SUM(CN11,CN16,CN19,CN22) -> 1203 | CO24: =SUM(CO11,CO16,CO19,CO22) -> 1132 | CP24: =SUM(CP11,CP16,CP19,CP22) -> 1432 | CQ24: =SUM(CQ11,CQ16,CQ19,CQ22) -> 1436 | CR24: =SUM(CN24:CQ24) -> 5203 | CS24: =SUM(CS11,CS16,CS19,CS22) -> 1494 | CT24: =SUM(CT11,CT16,CT19,CT22) -> 1503 | CU24: =SUM(CU11,CU16,CU19,CU22) -> 1860 | CV24: =SUM(CV11,CV16,CV19,CV22) -> 1846 | CW24: =SUM(CS24:CV24) -> 6703 | CX24: 2009 | CY24: 2003 | CZ24: 1820 | DA24: 1847 | DB24: =SUM(CX24:DA24) -> 7679 | DC24: 2457 | DD24: 2413 | DE24: =2230 -> 2230 | DF24: 2253 | DG24: =SUM(DC24:DF24) -> 9353 | DH24: 2769 | DI24: 2756 | DJ24: 2624 | DK24: 2645 | DL24: =SUM(DH24:DK24) -> 10794 | DM24: 3191 | DN24: 3382 | DO24: 3195 | DP24: 3223 | DQ24: =SUM(DM24:DP24) -> 12991 | DR24: 3745 | DS24: 3803 | DT24: 3874 | DU24: 3954 | DV24: =SUM(DR24:DU24) -> 15376 | DW24: 4504 | DX24: 4782 | DY24: 4976 | DZ24: 5100 | EA24: =SUM(DW24:DZ24) -> 19362 | EB24: 5284 | EC24: 5774 | ED24: 5743 | EE24: 5659 | EF24: =SUM(EB24:EE24) -> 22460 | EG24: 5264 | EH24: 5865 | EI24: 5846 | EJ24: 5810 | EK24: =SUM(EG24:EJ24) -> 22785 | EL24: 5516 | EM24: 5998 | EN24: 6368 | EO24: =EO9*EO126 -> 6527.1865 | EP24: =SUM(EL24:EO24) -> 24409.187 | EQ24: =EQ9*EQ126 -> 6452.4608 | ER24: =ER9*ER126 -> 7098.6445 | ES24: =ES9*ES126 -> 7478.2179 | ET24: =ET9*ET126 -> 7452.3734 | EU24: =SUM(EQ24:ET24) -> 28481.697 | EV24: =EV9*EV126 -> 30856.088 | EW24: =EW9*EW126 -> 33307.093 | EX24: =EX9*EX126 -> 35765.58 | EY24: =EY9*EY126 -> 38299.932 | FA24: =(EA24/DL24)^(1/3)-1 -> 0.21503634 | FB24: =(EF24/DQ24)^(1/3)-1 -> 0.20020581 | FC24: =(EK24/DV24)^(1/3)-1 -> 0.14007972 | FD24: =(EP24/EA24)^(1/3)-1 -> 0.080275094 | FE24: =(EU24/EB24)^(1/3)-1 -> 0.75334622 | FF24: =(EV24/EC24)^(1/3)-1 -> 0.74832175 | FG24: =(EK24/DL24)^(1/5)-1 -> 0.16116336 | FH24: =(EP24/DQ24)^(1/5)-1 -> 0.1344416 | FI24: =(EU24/DV24)^(1/5)-1 -> 0.13121329 | FJ24: =(EV24/EA24)^(1/5)-1 -> 0.097686009 | FK24: =(EW24/EF24)^(1/5)-1 -> 0.081995355 | FL24: =(EX24/EG24)^(1/5)-1 -> 0.46699921
A25: Other 1x item, incl. Impairment charge | BX25: 0 | CD25: 0 | CE25: 0 | CF25: 0 | CG25: 0 | CH25: 0 | CI25: 0 | CJ25: 0 | CK25: =CK47 -> 378 | CL25: =CL47 -> 0 | CM25: =SUM(CI25:CL25) -> 378 | CN25: 0 | CO25: 0 | CP25: 0 | CQ25: 0 | CR25: =SUM(CN25:CQ25) -> 0 | CS25: 0 | CT25: 0 | CU25: 0 | CV25: 0 | CW25: =SUM(CS25:CV25) -> 0 | CX25: 0 | CY25: 2736 | CZ25: 0 | DA25: 0 | DB25: =SUM(CX25:DA25) -> 2736 | DD25: =5071 -> 5071 | DE25: 0 | DF25: 0 | DG25: =SUM(DC25:DF25) -> 5071 | DH25: 1697 | DI25: 0 | DJ25: 0 | DK25: 0 | DL25: =SUM(DH25:DK25) -> 1697 | DM25: 0 | DN25: 0 | DO25: 0 | DP25: 0 | DQ25: =SUM(DM25:DP25) -> 0 | DR25: 0 | DS25: 0 | DT25: 0 | DU25: 0 | DV25: =SUM(DR25:DU25) -> 0 | DW25: 0 | DX25: 0 | DY25: 0 | DZ25: 0 | EA25: =SUM(DW25:DZ25) -> 0 | EB25: 0 | EC25: 0 | ED25: 0 | EE25: 0 | EF25: =SUM(EB25:EE25) -> 0 | EG25: 0 | EH25: 0 | EI25: 0 | EJ25: 0 | EK25: =SUM(EG25:EJ25) -> 0 | EL25: 0 | EM25: 0 | EN25: 3457 | EO25: 0 | EP25: =SUM(EL25:EO25) -> 3457 | EQ25: 0 | ER25: 0 | ES25: 0 | ET25: 0 | EU25: =SUM(EQ25:ET25) -> 0
A26: Total operating expenses | F26: =SUM(F15,F18,F21,F24) -> 5.828 | K26: =SUM(K15,K18,K21,K24) -> 27.764 | P26: =SUM(P15,P18,P21,P24) -> 61.234 | Q26: =SUM(Q15:Q24) -> 21.386 | R26: =SUM(R15:R24) -> 27.021 | S26: =SUM(S15:S24) -> 34.252 | T26: =SUM(T15:T24) -> 38.873 | U26: =SUM(U15,U18,U21,U24) -> 121.532 | V26: =SUM(V15:V24) -> 76.717 | W26: =SUM(W15:W24) -> 89.014 | X26: =SUM(X15:X24) -> 156.996 | Y26: =SUM(Y15:Y24) -> 174.889 | Z26: =SUM(Z15,Z18,Z21,Z24) -> 497.616 | AA26: =SUM(AA15,AA18,AA21,AA24) -> 180.902 | AB26: =SUM(AB15,AB18,AB21,AB24) -> 202.877 | AC26: =SUM(AC15,AC18,AC21,AC24) -> 231.676 | AD26: =SUM(AD15,AD18,AD21,AD24) -> 274.923 | AE26: =SUM(AE15,AE18,AE21,AE24) -> 890.378 | AF26: =SUM(AF15,AF18,AF21,AF24) -> 268.538 | AG26: =SUM(AG15,AG18,AG21,AG24) -> 311.702 | ... BW26: =SUM(BW15,BW18,BW21,BW24) -> 4296 | BX26: =SUM(BX17,BX20,BX23) -> 15029 | BY26: 4548 | BZ26: 5034 | CA26: 5173 | CB26: 5667 | CC26: 20422 | CD26: =SUM(CD17,CD20,CD23) -> 4067 | CE26: =SUM(CE17,CE20,CE23) -> 4447 | CF26: =SUM(CF17,CF20,CF23) -> 4584 | CG26: =SUM(CG17,CG20,CG23) -> 5025 | CH26: =SUM(CH17,CH20,CH23) -> 18123 | CI26: =SUM(CI17,CI20,CI23) -> 5344 | CJ26: =SUM(CJ17,CJ20,CJ23) -> 5583 | CK26: =SUM(CK17,CK20,CK23) -> 6104 | ... CW26: =SUM(CW17,CW20,CW23) -> 31418 | CX26: =SUM(CX17,CX20,CX23,CX25) -> 8387 | CY26: =SUM(CY17,CY20,CY23,CY25) -> 11505 | CZ26: =SUM(CZ17,CZ20,CZ23,CZ25) -> 8842 | DA26: =SUM(DA17,DA20,DA23,DA25) -> 10392 | DB26: =SUM(DB17,DB20,DB23,DB25) -> 39126 | DC26: =SUM(DC17,DC20,DC23,DC25) -> 10046 | DD26: =SUM(DD17,DD20,DD23,DD25) -> 15729 | DE26: =SUM(DE17,DE20,DE23,DE25) -> 10834 | ... EY26: =SUM(EY17,EY20,EY23,EY25) -> 159317.52 | FA26: =(EA26/DL26)^(1/3)-1 -> 0.13641989 | FB26: =(EF26/DQ26)^(1/3)-1 -> 0.16639105 | FC26: =(EK26/DV26)^(1/3)-1 -> 0.10337439 | FD26: =(EP26/EA26)^(1/3)-1 -> 0.094892688 | FE26: =(EU26/EF26)^(1/3)-1 -> 0.08973206 | FF26: =(EV26/EK26)^(1/3)-1 -> 0.12055097 | FG26: =(EK26/DL26)^(1/5)-1 -> 0.1038175 | FH26: =(EP26/DQ26)^(1/5)-1 -> 0.13669844 | FI26: =(EU26/DV26)^(1/5)-1 -> 0.11310407 | FJ26: =(EV26/EA26)^(1/5)-1 -> 0.094543304 | FK26: =(EW26/EF26)^(1/5)-1 -> 0.09144542 | FL26: =(EX26/EK26)^(1/5)-1 -> 0.1034676
A27: GAAP Operating income | F27: =F13-F26 -> -6.516 | K27: =K13-K26 -> -14.737 | P27: =P13-P26 -> 10.964 | Q27: =Q13-Q26 -> 15.207 | R27: =R13-R26 -> 31.097 | S27: =S13-S26 -> 56.913 | T27: =T13-T26 -> 83.249 | U27: =U13-U26 -> 186.466 | V27: =V13-V26 -> 84.706 | W27: =W13-W26 -> 104.784 | ... BN27: =BN13-BN26 -> 12242 | BO27: 3389 | BP27: 3203 | BQ27: 2736 | BR27: 3394 | BS27: 12722 | BT27: =BT13-BT26 -> 3389 | BU27: =BU13-BU26 -> 3436 | BV27: =BV13-BV26 -> 3263 | BW27: =BW13-BW26 -> 3747 | BX27: =BX13-BX26 -> 13834 | BY27: 3477 | BZ27: 3123 | CA27: 3444 | CB27: 3922 | CC27: 13966 | CD27: =CD13-CD26 -> 3748 | CE27: =CE13-CE26 -> 3465 | CF27: =CF13-CF26 -> 3761 | CG27: =CG13-CG26 -> 4429 | CH27: =CH13-CH26 -> 15403 | CI27: =CI13-CI26 -> 4115 | CJ27: =CJ13-CJ26 -> 4258 | CK27: =CK13-CK26 -> 3724 | ... EY27: =EY13-EY26 -> 260643.46 | FA27: =(EA27/DL27)^(1/3)-1 -> 0.29790209 | FB27: =(EF27/DQ27)^(1/3)-1 -> 0.26924987 | FC27: =(EK27/DV27)^(1/3)-1 -> 0.1260523 | FD27: =(EP27/EA27)^(1/3)-1 -> 0.20344605 | FE27: =(EU27/EF27)^(1/3)-1 -> 0.23751582 | FF27: =(EV27/EK27)^(1/3)-1 -> 0.16714112 | FG27: =(EK27/DL27)^(1/5)-1 -> 0.26841572 | FH27: =(EP27/DQ27)^(1/5)-1 -> 0.25908493 | FI27: =(EU27/DV27)^(1/5)-1 -> 0.15206866 | FJ27: =(EV27/EA27)^(1/5)-1 -> 0.19011925 | FK27: =(EW27/EF27)^(1/5)-1 -> 0.19261221 | FL27: =(EX27/EK27)^(1/5)-1 -> 0.154154
A28: Non-GAAP Operating income | CR28: =CR27 -> 19360 | CS28: =CS27 -> 5342 | CT28: =CT27 -> 5968 | CU28: =CU27 -> 5767 | CV28: =CV27 -> 6639 | CW28: =CW27 -> 23716 | CX28: =CX27 -> 6568 | CY28: =CY27+CY25 -> 6868 | CZ28: =CZ27 -> 7782 | DA28: =DA27 -> 7664 | DB28: =SUM(CX28:DA28) -> 28882 | DC28: =DC27 -> 7633 | DD28: =DD27+DD25 -> 8116 | DE28: =DE27 -> 8625 | DF28: =DF27 -> 8221 | DG28: =SUM(DC28:DF28) -> 32595 | DH28: =DH27+DH25 -> 8305 | DI28: =DI27 -> 9180 | DJ28: =DJ27 -> 9177 | DK28: =DK27 -> 9266 | DL28: =SUM(DH28:DK28) -> 35928 | DM28: =DM27 -> 7977 | DN28: =DN27 -> 6383 | DO28: =DO27 -> 11213 | DP28: =DP27 -> 15651 | DQ28: =SUM(DM28:DP28) -> 41224 | DR28: =DR27 -> 16437 | DS28: =DS27 -> 19361 | DT28: =DT27 -> 21031 | DU28: =DU27 -> 21885 | DV28: =SUM(DR28:DU28) -> 78714 | DW28: =DW27 -> 20094 | DX28: =DX27 -> 19453 | DY28: =DY27 -> 17135 | DZ28: =DZ27 -> 18160 | EA28: =SUM(DW28:DZ28) -> 74842 | EB28: =EB27 -> 17415 | EC28: =EC27 -> 21838 | ED28: =ED27 -> 21343 | EE28: =EE27 -> 23697 | EF28: =SUM(EB28:EE28) -> 84293 | EG28: =EG27 -> 25472 | EH28: =EH27 -> 27425 | EI28: =EI27 -> 28521 | EJ28: =EJ27 -> 30972 | EK28: =SUM(EG28:EJ28) -> 112390 | EL28: =EL27 -> 30606 | EM28: =EM27 -> 31271 | EN28: =EN27 -> 31228 | EO28: =EO27 -> 37339.346 | EP28: =SUM(EL28:EO28) -> 130444.35 | EQ28: =EQ27 -> 37124.37 | ER28: =ER27 -> 38929.529 | ES28: =ES27 -> 40112.084 | ET28: =ET27 -> 43585.093 | EU28: =SUM(EQ28:ET28) -> 159751.08 | EV28: =EV27 -> 178688.98 | EW28: =EW27 -> 203370.41 | EX28: =EX27 -> 230168.82 | EY28: =EY27 -> 260643.46
A29: JPMe Adjusted Operating income | F29: =F13-SUM(F15:F21) -> -6.516 | K29: =K13-SUM(K15:K21) -> -12.231 | P29: =P13-SUM(P15:P21) -> -25.443 | Q29: =Q13-SUM(Q15:Q21) -> 18.981 | R29: =R13-SUM(R15:R21) -> 34.832 | S29: =S13-SUM(S15:S21) -> 63.095 | T29: =T13-SUM(T15:T21) -> 91.193 | U29: =SUM(Q29:T29) -> 208.101 | V29: =V13-SUM(V15:V21) -> 121.124 | W29: =W13-SUM(W15:W21) -> 138.949 | X29: =X13-SUM(X15:X21) -> 140.35 | Y29: =Y13-SUM(Y15:Y21) -> 171.402 | Z29: =SUM(V29:Y29) -> 571.825 | AA29: =AA13-SUM(AA15:AA21) -> 231.796 | AB29: =AB13-SUM(AB15:AB21) -> 245.719 | AC29: =AC13-SUM(AC15:AC21) -> 280.093 | AD29: =AD13-SUM(AD15:AD21) -> 362.33 | AE29: =SUM(AA29:AD29) -> 1119.938 | AF29: =AF13-SUM(AF15:AF21) -> 491.678 | AG29: =AG13-SUM(AG15:AG21) -> 523.036 | AH29: =AH13-SUM(AH15:AH21) -> 575.479 | AI29: =AI13-SUM(AI15:AI21) -> 717.794 | AJ29: =SUM(AF29:AI29) -> 2307.987 | AK29: =AK13-SUM(AK15:AK21) -> 330.806 | AL29: =AL13-SUM(AL15:AL21) -> 360.723 | AM29: =AM13-SUM(AM15:AM21) -> 435.2 | AN29: =AN13-SUM(AN15:AN21) -> 456.385 | AO29: =SUM(AK29:AN29) -> 1583.114 | AP29: =AP13-SUM(AP15:AP21) -> 546.102 | AQ29: =AQ13-SUM(AQ15:AQ21) -> 265.061 | AR29: =AR13-SUM(AR15:AR21) -> 425.893 | AS29: =AS13-SUM(AS15:AS21) -> 433.503 | AT29: =AT13-SUM(AT15:AT21) -> 1670.559 | AU29: =AU13-SUM(AU15:AU21) -> 470.671 | AV29: =AV13-SUM(AV15:AV21) -> 454.105 | AW29: =AW13-SUM(AW15:AW21) -> 480.472 | ... BD29: =BD13-SUM(BD15:BD21) -> 3692.911 | BE29: =BE9-SUM(BE10,BE15,BE18,BE21)+BE25 -> 2779 | BF29: =BF9-SUM(BF10,BF15,BF18,BF21)+BF25 -> 2674 | BG29: =BG9-SUM(BG10,BG15,BG18,BG21)+BG25 -> 2927 | BH29: =BH9-SUM(BH10,BH15,BH18,BH21)+BH25 -> 3378 | BI29: =BI9-SUM(BI10,BI15,BI18,BI21)+BI25 -> 11758 | BJ29: =BJ9-SUM(BJ10,BJ15,BJ18,BJ21)+BJ25 -> 3228 | BK29: =BK9-SUM(BK10,BK15,BK18,BK21)+BK25 -> 3316 | BL29: =BL9-SUM(BL10,BL15,BL18,BL21)+BL25 -> 3629 | ... BN29: =BN9-SUM(BN10,BN15,BN18,BN21)+BN25 -> 14216 | BO29: 3945 | BP29: 3950 | BQ29: 3800 | BR29: 4272 | BS29: 15967 | BT29: =BT9-SUM(BT10,BT15,BT18,BT21)+BT25 -> 3945 | BU29: =BU9-SUM(BU10,BU15,BU18,BU21)+BU25 -> 3988 | BV29: =BV9-SUM(BV10,BV15,BV18,BV21)+BV25 -> 3951 | BW29: =BW9-SUM(BW10,BW15,BW18,BW21)+BW25 -> 4424 | BX29: =BX9-SUM(BX10,BX15,BX18,BX21)+BX25 -> #REF! | BY29: 4070 | BZ29: 3990 | CA29: 4342 | CB29: 4839 | CC29: 17241 | CD29: =CD27+CD24+CD25 -> 4403 | CE29: =CE27+CE24+CE25+84 -> 4292 | CF29: =CF27+CF24+CF25+12 -> 4629 | CG29: =CG27+CG24+CG25 -> 5302 | CH29: =SUM(CD29:CG29) -> 18626 | CI29: =CI27+CI24+CI25 -> 4954 | CJ29: =CJ27+CJ24+CJ25 -> 5138 | CK29: =CK27+CK24+CK25 -> 5357 | CL29: =CL27+CL24+CL25 -> 5600 | CM29: =CM27+CM24+CM25 -> 21049 | CN29: =CN27+CN24+CN25 -> 5650 | CO29: =CO27+CO24+CO25 -> 5957 | CP29: =CP27+CP24+CP25 -> 6140 | ... EY29: =EY27+EY24+EY25 -> 298943.39 | FA29: =(EA29/DL29)^(1/3)-1 -> 0.26332757 | FB29: =(EF29/DQ29)^(1/3)-1 -> 0.25339188 | FC29: =(EK29/DV29)^(1/3)-1 -> 0.12836854 | FD29: =(EP29/EA29)^(1/3)-1 -> 0.18890409 | FE29: =(EU29/EF29)^(1/3)-1 -> 0.20810602 | FF29: =(EV29/EK29)^(1/3)-1 -> 0.15733839 | FG29: =(EK29/DL29)^(1/5)-1 -> 0.23673027 | FH29: =(EP29/DQ29)^(1/5)-1 -> 0.2390193 | FI29: =(EU29/DV29)^(1/5)-1 -> 0.14876277 | FJ29: =(EV29/EA29)^(1/5)-1 -> 0.17338794 | FK29: =(EW29/EF29)^(1/5)-1 -> 0.17261482 | FL29: =(EX29/EK29)^(1/5)-1 -> 0.14492128
A30: Other income, expense and other, net | F30: 0.44 | K30: 0.047 | P30: -0.896 | Q30: -0.501 | R30: -0.31 | S30: -0.677 | T30: -0.063 | U30: =SUM(Q30:T30) -> -1.551 | V30: -0.047 | W30: 0.766 | X30: 0.464 | Y30: 3.007 | Z30: =SUM(V30:Y30) -> 4.19 | AA30: 0.3 | AB30: -1.498 | AC30: 3.866 | AD30: 7.374 | AE30: =SUM(AA30:AD30) -> 10.042 | AF30: 13.686 | AG30: 19.722 | AH30: 20.797 | AI30: 70.193 | AJ30: =SUM(AF30:AI30) -> 124.398 | AK30: 67.919 | AL30: =160.805 -> 160.805 | AM30: 108.18 | AN30: 124.139 | AO30: =SUM(AK30:AN30) -> 461.043 | AP30: 130.728 | AQ30: 137.13 | AR30: 154.428 | AS30: 167.294 | AT30: =SUM(AP30:AS30) -> 589.58 | AU30: 167.343 | AV30: 57.923 | AW30: 21.217 | AX30: =69.899 -> 69.899 | AY30: =SUM(AU30:AX30) -> 316.382 | AZ30: 6.21 | BA30: -17.718 | BB30: -7.177 | BC30: 87.688 | BD30: =SUM(AZ30:BC30) -> 69.003 | BE30: 18 | BF30: 69 | BG30: 167 | BH30: 160 | BI30: =SUM(BE30:BH30) -> 414 | BJ30: 96 | BK30: 204 | BL30: 302 | BM30: -18 | BN30: =SUM(BJ30:BM30) -> 584 | BO30: 156 | BP30: 254 | BQ30: 63 | BR30: 152 | BS30: 625 | BT30: 156 | BU30: 254 | BV30: 63 | BW30: 152 | BX30: 635 | BY30: 134 | BZ30: 247 | CA30: 24 | CB30: 125 | CC30: 530 | CD30: 134 | CE30: 236 | CF30: 24 | CG30: 112 | CH30: 496 | CI30: 357 | CJ30: 145 | CK30: 133 | CL30: 128 | CM30: =SUM(CI30:CL30) -> 763 | CN30: 157 | CO30: 131 | CP30: 183 | CQ30: -180 | CR30: =SUM(CN30:CQ30) -> 291 | CS30: -213 | CT30: 151 | CU30: 278 | CV30: 218 | CW30: =SUM(CS30:CV30) -> 434 | CX30: 251 | CY30: 245 | CZ30: 197 | DA30: 354 | DB30: =SUM(CX30:DA30) -> 1047 | DC30: 2910 | DD30: =1408-DD221 -> 1170 | DE30: =1773-DE221 -> 1458 | DF30: =1869-DF221 -> 1851 | DG30: =SUM(DC30:DF30) -> 7389 | DH30: 1538 | DI30: 2967 | DJ30: -549 | DK30: 1438 | DL30: =SUM(DH30:DK30) -> 5394 | DM30: -220 | DN30: 1894 | DO30: 2146 | DP30: 3038 | DQ30: =SUM(DM30:DP30) -> 6858 | DR30: 4846 | DS30: 2624 | DT30: 2033 | DU30: 2517 | DV30: =SUM(DR30:DU30) -> 12020 | DW30: -1160 | DX30: -439 | DY30: -902 | DZ30: -1013 | EA30: =SUM(DW30:DZ30) -> -3514 | EB30: 790 | EC30: 65 | ED30: -146 | EE30: 715 | EF30: =SUM(EB30:EE30) -> 1424 | EG30: 2843 | EH30: 126 | EI30: 3185 | EJ30: 1271 | EK30: =SUM(EG30:EJ30) -> 7425 | EL30: 11183 | EM30: 2662 | EN30: 12759 | EO30: =EO198 -> 950.78376 | EP30: =SUM(EL30:EO30) -> 27554.784 | EQ30: =EQ198 -> 937.47105 | ER30: =ER198 -> 827.10196 | ES30: =ES198 -> 733.79092 | ET30: =ET198 -> 745.27348 | EU30: =SUM(EQ30:ET30) -> 3243.6374 | EV30: =EV198 -> 2731.6579 | EW30: =EW198 -> 2450.3181 | EX30: =EX198 -> 2714.1656 | EY30: =EY198 -> 3638.3159
A31: One-time items | F31: 0 | K31: 0 | P31: 0 | Q31: 0 | R31: 0 | S31: 0 | T31: 0 | U31: =SUM(Q31:T31) -> 0 | V31: 0 | W31: 0 | X31: 0 | Y31: 0 | Z31: =SUM(V31:Y31) -> 0 | AA31: 0 | AB31: 0 | AC31: -201 | AD31: 0 | AE31: =SUM(AA31:AD31) -> -201 | AF31: 0 | AG31: 0 | AH31: 0 | AI31: -90 | AJ31: =SUM(AF31:AI31) -> -90 | AK31: 0 | AL31: 0 | AM31: 0 | AN31: 0 | AO31: =SUM(AK31:AN31) -> 0 | AP31: 0 | AQ31: 0 | AR31: 0 | AS31: 0 | AT31: =SUM(AP31:AS31) -> 0 | AU31: 0 | AV31: 0 | AW31: 0 | AX31: -1094.757 | AY31: =SUM(AU31:AX31) -> -1094.757 | AZ31: 0 | BA31: 0 | BB31: 0 | BC31: 0 | BD31: =SUM(AZ31:BC31) -> 0 | BE31: 0 | BF31: 0 | BG31: 0 | BH31: 0 | BI31: =SUM(BE31:BH31) -> 0 | BJ31: -500 | BK31: 0 | BL31: 0 | BM31: 0 | BN31: 0 | BP31: 0 | BQ31: 0 | BR31: 0 | BS31: 0 | BU31: 0 | BV31: 0 | BW31: 0 | BX31: 0 | CB31: 0 | CC31: 0 | CD31: 0 | CE31: 0 | CF31: 0 | CG31: 0 | CH31: 0 | CI31: 0 | CJ31: 0 | CK31: =-CK47 -> -378 | CL31: =-CL47 -> 0 | CM31: =SUM(CI31:CL31) -> -378 | CN31: 0 | CO31: 0 | CP31: =-CP47 -> 0 | CQ31: =-CQ47 -> 0 | CR31: =SUM(CN31:CQ31) -> 0 | CS31: 0 | CT31: 0 | CU31: 0 | CV31: 0 | CW31: =SUM(CS31:CV31) -> 0 | CX31: 0 | CY31: 0 | CZ31: 0 | DA31: 0 | DB31: =SUM(CX31:DA31) -> 0 | DC31: 0 | DD31: 0 | DE31: 0 | DF31: 0 | DG31: =SUM(DC31:DF31) -> 0 | DH31: 0 | DI31: 0 | DJ31: 0 | DK31: 0 | DL31: =SUM(DH31:DK31) -> 0 | DM31: 0 | DN31: 0 | DO31: 0 | DP31: 0 | DQ31: =SUM(DM31:DP31) -> 0 | DR31: 0 | DS31: 0 | DT31: 0 | DU31: 0 | DV31: =SUM(DR31:DU31) -> 0 | DW31: 0 | DX31: 0 | DY31: 0 | DZ31: 0 | EA31: =SUM(DW31:DZ31) -> 0 | EB31: 0 | EC31: 0 | ED31: 0 | EE31: 0 | EF31: =SUM(EB31:EE31) -> 0 | EG31: 0 | EH31: 0 | EI31: 0 | EJ31: 0 | EK31: =SUM(EG31:EJ31) -> 0 | EL31: 0 | EM31: 0 | EN31: 0 | EP31: =SUM(EL31:EO31) -> 0 | EU31: =SUM(EQ31:ET31) -> 0
A32: Income before taxes | F32: =F27+F30 -> -6.076 | K32: =K27+K30 -> -14.69 | P32: =P27+P30 -> 10.068 | Q32: =Q27+Q30 -> 14.706 | R32: =R27+R30 -> 30.787 | S32: =S27+S30 -> 56.236 | T32: =T27+T30 -> 83.186 | U32: =SUM(Q32:T32) -> 184.915 | V32: =V27+V30 -> 84.659 | W32: =W27+W30 -> 105.55 | X32: =X27+X30 -> 67.02 | Y32: =Y27+Y30 -> 89.425 | Z32: =SUM(V32:Y32) -> 346.654 | AA32: =AA27+AA30 -> 155.623 | AB32: =AB27+AB30 -> 169.46 | AC32: =AC27+AC30+AC31 -> 14.978 | AD32: =AD27+AD30 -> 310.173 | AE32: =SUM(AA32:AD32) -> 650.234 | AF32: =AF27+AF30 -> 456.456 | AG32: =AG27+AG30 -> 495.42 | AH32: =AH27+AH30 -> 549.968 | AI32: =AI27+AI30+AI31 -> 639.833 | AJ32: =SUM(AF32:AI32) -> 2141.677 | AK32: =AK27+AK30 -> 810.618 | AL32: =AL27+AL30 -> 976.177 | AM32: =AM27+AM30 -> 1039.511 | AN32: =AN27+AN30 -> 1184.733 | AO32: =SUM(AK32:AN32) -> 4011.039 | AP32: =AP27+AP30+AP31 -> 1351.937 | AQ32: =AQ27+AQ30+AQ31 -> 1241.745 | AR32: =AR27+AR30+AR31 -> 1472.265 | AS32: =AS27+AS30+AS31 -> 1608.028 | AT32: =SUM(AP32:AS32) -> 5673.975 | AU32: =AU27+AU30+AU31 -> 1713.578 | AV32: =AV27+AV30+AV31 -> 1635.888 | AW32: =AW27+AW30+AW31 -> 1668.782 | AX32: =AX27+AX30+AX31 -> 835.346 | AY32: =SUM(AU32:AX32) -> 5853.594 | AZ32: =AZ27+AZ30+AZ31 -> 1889.801 | BA32: =BA27+BA30+BA31 -> 1856.176 | BB32: =BB27+BB30+BB31 -> 2066.541 | BC32: =BC27+BC30+BC31 -> 2568.671 | BD32: =SUM(AZ32:BC32) -> 8381.189 | BE32: =BE27+BE30+BE31 -> 2506 | BF32: =BF27+BF30+BF31 -> 2434 | BG32: =BG27+BG30+BG31 -> 2714 | BH32: =BH27+BH30+BH31 -> 3142 | BI32: =SUM(BE32:BH32) -> 10796 | BJ32: =BJ27+BJ30+BJ31 -> 2392 | BK32: =BK27+BK30+BK31 -> 3085 | BL32: =BL27+BL30+BL31 -> 3360 | BM32: =BM27+BM30+BM31 -> 3489 | BN32: =SUM(BJ32:BM32) -> 12326 | BO32: 3545 | BP32: 3457 | BQ32: 2799 | BR32: 3546 | BS32: 13347 | BT32: =BT27+BT30 -> 3545 | BU32: =BU27+BU30+BU31 -> 3690 | BV32: =BV27+BV30 -> 3326 | BW32: =BW27+BW30 -> 3899 | BX32: =BX27+BX30 -> 14469 | BY32: 3611 | BZ32: 3370 | CA32: 3468 | CB32: 4047 | CC32: 14496 | CD32: =CD27+CD30 -> 3882 | CE32: =CE27+CE30+CE31 -> 3701 | CF32: =CF27+CF30 -> 3785 | CG32: =CG27+CG30 -> 4541 | CH32: =CH27+CH30 -> 15899 | CI32: =CI27+CI30 -> 4472 | CJ32: =CJ27+CJ30 -> 4403 | CK32: =CK27+CK30 -> 3857 | CL32: =CL27+CL30 -> 4527 | CM32: =CM27+CM30 -> 17259 | ... CQ32: =CQ27+CQ30 -> 5200 | CR32: =SUM(CN32:CQ32) -> 19651 | CS32: =CS27+CS30 -> 5129 | CT32: =CT27+CT30 -> 6119 | CU32: =CU27+CU30 -> 6045 | CV32: =CV27+CV30+CV31 -> 6857 | CW32: =SUM(CS32:CV32) -> 24150 | CX32: =CX27+CX30 -> 6819 | CY32: =CY27+CY30 -> 4377 | CZ32: =CZ27+CZ30 -> 7979 | DA32: =DA27+DA30 -> 8018 | DB32: =SUM(CX32:DA32) -> 27193 | DC32: =DC27+DC30 -> 10543 | DD32: =DD27+DD30 -> 4215 | DE32: =DE27+DE30 -> 10083 | DF32: =DF27+DF30 -> 10072 | DG32: =SUM(DC32:DF32) -> 34913 | DH32: =DH27+DH30 -> 8146 | DI32: =DI27+DI30 -> 12147 | DJ32: =DJ27+DJ30 -> 8628 | DK32: =DK27+DK30 -> 10704 | DL32: =SUM(DH32:DK32) -> 39625 | DM32: =DM27+DM30 -> 7757 | DN32: =DN27+DN30 -> 8277 | DO32: =DO27+DO30 -> 13359 | DP32: =DP27+DP30 -> 18689 | DQ32: =SUM(DM32:DP32) -> 48082 | DR32: =DR27+DR30 -> 21283 | DS32: =DS27+DS30 -> 21985 | DT32: =DT27+DT30 -> 23064 | DU32: =DU27+DU30 -> 24402 | DV32: =SUM(DR32:DU32) -> 90734 | DW32: =DW27+DW30 -> 18934 | DX32: =DX27+DX30 -> 19014 | DY32: =DY27+DY30 -> 16233 | DZ32: =DZ27+DZ30 -> 17147 | EA32: =SUM(DW32:DZ32) -> 71328 | EB32: =EB27+EB30 -> 18205 | EC32: =EC27+EC30 -> 21903 | ED32: =ED27+ED30 -> 21197 | EE32: =EE27+EE30 -> 24412 | EF32: =SUM(EB32:EE32) -> 85717 | EG32: =EG27+EG30 -> 28315 | EH32: =EH27+EH30 -> 27551 | EI32: =EI27+EI30 -> 31706 | EJ32: =EJ27+EJ30 -> 32243 | EK32: =SUM(EG32:EJ32) -> 119815 | EL32: =EL27+EL30 -> 41789 | EM32: =EM27+EM30 -> 33933 | EN32: =EN27+EN30 -> 43987 | EO32: =EO27+EO30 -> 38290.13 | EP32: =SUM(EL32:EO32) -> 157999.13 | EQ32: =EQ27+EQ30 -> 38061.841 | ER32: =ER27+ER30 -> 39756.631 | ES32: =ES27+ES30 -> 40845.875 | ET32: =ET27+ET30 -> 44330.366 | EU32: =SUM(EQ32:ET32) -> 162994.71 | EV32: =EV27+EV30 -> 181420.64 | EW32: =EW27+EW30 -> 205820.73 | EX32: =EX27+EX30 -> 232882.98 | EY32: =EY27+EY30 -> 264281.78
A33: Provision for income taxes | F33: 0 | K33: 0 | P33: 3.083 | Q33: 6.78 | R33: 14.194 | S33: 25.929 | T33: 38.356 | U33: =SUM(Q33:T33) -> 85.259 | V33: 58.859 | W33: 73.382 | X33: 46.594 | Y33: 62.171 | Z33: =SUM(V33:Y33) -> 241.006 | AA33: 91.65 | AB33: 90.397 | AC33: =-37.005 -> -37.005 | AD33: =106.073 -> 106.073 | AE33: =SUM(AA33:AD33) -> 251.115 | AF33: 87.263 | AG33: 152.606 | AH33: 168.786 | AI33: 267.625 | AJ33: =SUM(AF33:AI33) -> 676.28 | AK33: 218.327 | AL33: 255.1 | AM33: 306.15 | AN33: 154.017 | AO33: =SUM(AK33:AN33) -> 933.594 | AP33: 349.775 | AQ33: 316.625 | AR33: 402.281 | AS33: 401.579 | AT33: =SUM(AP33:AS33) -> 1470.26 | AU33: 406.492 | AV33: 388.497 | AW33: =378.844 -> 378.844 | AX33: =452.904 -> 452.904 | AY33: =SUM(AU33:AX33) -> 1626.737 | AZ33: 466.973 | BA33: =371.631 -> 371.631 | BB33: 427.566 | BC33: 594.571 | BD33: =SUM(AZ33:BC33) -> 1860.741 | BE33: 551 | BF33: 594 | BG33: 547 | BH33: 599 | BI33: =SUM(BE33:BH33) -> 2291 | BJ33: 594 | BK33: 580 | BL33: 631 | BM33: 784 | BN33: =SUM(BJ33:BM33) -> 2589 | BO33: 655 | BP33: 672 | BQ33: 623 | BR33: 639 | BS33: 2589 | BT33: 655 | BU33: 672 | BV33: 623 | BW33: 639 | BX33: 2916 | BY33: 287 | BZ33: 816 | CA33: 513 | CB33: 666 | CC33: 2282 | CD33: 354 | CE33: 927 | CF33: 513 | CG33: 659 | CH33: 2552 | CI33: =+CI32*CI34 -> 903.344 | CJ33: =+CJ32*CJ34 -> 982.7496 | CK33: =+CK32*CK34 -> 933.394 | CL33: =+CL32*CL34 -> 819.387 | CM33: 3331 | CN33: =+CN32*CN34 -> 1089.7668 | CO33: 1025 | CP33: 912 | CQ33: 277 | CR33: =SUM(CN33:CQ33) -> 3303.7668 | CS33: 922 | CT33: 1242 | CU33: 984 | CV33: 1524 | CW33: =SUM(CS33:CV33) -> 4672 | CX33: 1393 | CY33: 853 | CZ33: 1247 | DA33: 11038 | DB33: =SUM(CX33:DA33) -> 14531 | DC33: 1142 | DD33: 1020 | DE33: 891 | DF33: 1124 | DG33: =SUM(DC33:DF33) -> 4177 | DH33: 1489 | DI33: 2200 | DJ33: 1560 | DK33: 33 | DL33: =SUM(DH33:DK33) -> 5282 | DM33: 921 | DN33: 1318 | DO33: 2112 | DP33: 3462 | DQ33: =SUM(DM33:DP33) -> 7813 | DR33: 3353 | DS33: 3460 | DT33: 4128 | DU33: 3760 | DV33: =SUM(DR33:DU33) -> 14701 | DW33: 2498 | DX33: 3012 | DY33: 2323 | DZ33: 3523 | EA33: =SUM(DW33:DZ33) -> 11356 | EB33: 3154 | EC33: 3535 | ED33: 1508 | EE33: 3725 | EF33: =SUM(EB33:EE33) -> 11922 | EG33: 4653 | EH33: 3932 | EI33: 5405 | EJ33: 5707 | EK33: =SUM(EG33:EJ33) -> 19697 | EL33: 7249 | EM33: 5737 | EN33: 9008 | EO33: =+EO32*EO34 -> 6509.3221 | EP33: =SUM(EL33:EO33) -> 28503.322 | EQ33: =+EQ32*EQ34 -> 6470.5129 | ER33: =+ER32*ER34 -> 6758.6273 | ES33: =+ES32*ES34 -> 6943.7987 | ET33: =+ET32*ET34 -> 7536.1622 | EU33: =SUM(EQ33:ET33) -> 27709.101 | EV33: =+EV32*EV34 -> 30841.509 | EW33: =+EW32*EW34 -> 34989.525 | EX33: =+EX32*EX34 -> 39590.107 | EY33: =+EY32*EY34 -> 44927.902 | FA33: =(EA33/DL33)^(1/3)-1 -> 0.29065152 | FB33: =(EF33/DQ33)^(1/3)-1 -> 0.15126976 | FC33: =(EK33/DV33)^(1/3)-1 -> 0.10243012 | FD33: =(EP33/EA33)^(1/3)-1 -> 0.35901223 | FE33: =(EU33/EF33)^(1/3)-1 -> 0.32461939 | FF33: =(EV33/EK33)^(1/3)-1 -> 0.16121288 | FG33: =(EK33/DL33)^(1/5)-1 -> 0.30112894 | FH33: =(EP33/DQ33)^(1/5)-1 -> 0.29543472 | FI33: =(EU33/DV33)^(1/5)-1 -> 0.13515486 | FJ33: =(EV33/EA33)^(1/5)-1 -> 0.22118665 | FK33: =(EW33/EF33)^(1/5)-1 -> 0.24027441 | FL33: =(EX33/EK33)^(1/5)-1 -> 0.14983975
A34: Effective tax rate | F34: =+F33/F32 -> 0 | K34: =+K33/K32 -> 0 | P34: =+P33/P32 -> 0.30621772 | Q34: =+Q33/Q32 -> 0.46103631 | R34: =+R33/R32 -> 0.46103875 | S34: =+S33/S32 -> 0.46107476 | T34: =+T33/T32 -> 0.4610872 | U34: =+U33/U32 -> 0.4610713 | V34: =+V33/V32 -> 0.69524799 | W34: =+W33/W32 -> 0.69523449 | ... AB34: =+AB33/AB32 -> 0.53344152 | AC34: NA | AD34: =+AD33/AD32 -> 0.34198012 | AE34: =+AE33/AE32 -> 0.38619174 | AF34: =+AF33/AF32 -> 0.19117505 | AG34: =+AG33/AG32 -> 0.30803359 | AH34: =+AH33/AH32 -> 0.30690149 | AI34: =+AI33/AI32 -> 0.41827321 | AJ34: =+AJ33/AJ32 -> 0.31577124 | AK34: =+AK33/AK32 -> 0.26933401 | ... BN34: =+BN33/BN32 -> 0.21004381 | BO34: 0.18476728 | BP34: 0.1943882 | BQ34: 0.22257949 | BR34: 0.18020305 | BS34: 0.19397617 | BT34: =+BT33/BT32 -> 0.18476728 | BU34: =+BU33/BU32 -> 0.18211382 | BV34: =+BV33/BV32 -> 0.18731209 | BW34: =+BW33/BW32 -> 0.16388818 | BX34: =+BX33/BX32 -> 0.20153431 | BY34: 0.079479369 | BZ34: 0.2421365 | CA34: 0.14792388 | CB34: 0.16456635 | CC34: 0.15742274 | CD34: =+CD33/CD32 -> 0.091190108 | CE34: =+CE33/CE32 -> 0.25047285 | CF34: =+CF33/CF32 -> 0.13553501 | CG34: =+CG33/CG32 -> 0.14512222 | CH34: 0.1715 | CI34: 0.202 | CJ34: 0.2232 | CK34: 0.242 | CL34: 0.181 | CM34: =+CM33/CM32 -> 0.19300075 | CN34: 0.2367 | CO34: =+CO33/CO32 -> 0.20682002 | CP34: =+CP33/CP32 -> 0.18646494 | CQ34: =+CQ33/CQ32 -> 0.053269231 | CR34: =+CR33/CR32 -> 0.16812207 | CS34: =+CS33/CS32 -> 0.17976214 | CT34: =+CT33/CT32 -> 0.20297434 | CU34: =+CU33/CU32 -> 0.16277916 | CV34: =+CV33/CV32 -> 0.22225463 | ... EN34: =+EN33/EN32 -> 0.20478778 | EO34: 0.17 | EP34: =+EP33/EP32 -> 0.18040177 | EQ34: 0.17 | ER34: 0.17 | ES34: 0.17 | ET34: 0.17 | EU34: =+EU33/EU32 -> 0.17 | EV34: =ET34 -> 0.17 | EW34: =EV34 -> 0.17 | EX34: =EW34 -> 0.17 | EY34: =EX34 -> 0.17
A35: Discontinued Operations - Motorola | BR35: -21 | BS35: -21 | BU35: -199 | BV35: -523 | BW35: -355 | BX35: -816 | BY35: 22 | BZ35: 674 | CA35: 15 | CB35: -5 | CC35: 706 | CD35: -182 | CE35: 454 | CF35: -302 | CG35: -506 | CH35: -427 | CI35: -198 | CJ35: -68 | CK35: -185 | CL35: 967 | CM35: 516 | CN35: 0 | CO35: 0 | CP35: 0 | CQ35: 0 | CR35: =SUM(CN35:CQ35) -> 0 | CS35: 0 | CT35: 0 | CU35: 0 | CV35: 0 | CW35: =SUM(CS35:CV35) -> 0 | CX35: 0 | CY35: 0 | CZ35: 0 | DA35: 0 | DB35: =SUM(CX35:DA35) -> 0
A36: GAAP Net Income (loss) | F36: =F32-F33 -> -6.076 | K36: =K32-K33 -> -14.69 | P36: =P32-P33 -> 6.985 | Q36: =Q32-Q33 -> 7.926 | R36: =R32-R33 -> 16.593 | S36: =S32-S33 -> 30.307 | T36: =T32-T33 -> 44.83 | U36: =U32-U33 -> 99.656 | V36: =V32-V33 -> 25.8 | W36: =W32-W33 -> 32.168 | ... BN36: =BN32-BN33 -> 9737 | BO36: 2890 | BP36: 2785 | BQ36: 2176 | BR36: 2886 | BS36: 10737 | BT36: =BT32-BT33 -> 2890 | BU36: =BU32-BU33 -> 3018 | BV36: =BV32-BV33 -> 2703 | BW36: =BW32-BW33+BW35 -> 2905 | BX36: =BX32-BX33+BX35 -> 10737 | BY36: 3346 | BZ36: 3228 | CA36: 2970 | CB36: 3376 | CC36: 12920 | CD36: =CD32-CD33+CD35 -> 3346 | CE36: =CE32-CE33+CE35 -> 3228 | CF36: =CF32-CF33+CF35 -> 2970 | CG36: =CG32-CG33+CG35 -> 3376 | CH36: =CH32-CH33+CH35 -> 12920 | CI36: =CI32-CI33+CI35 -> 3370.656 | CJ36: =CJ32-CJ33+CJ35 -> 3352.2504 | CK36: =CK32-CK33+CK35 -> 2738.606 | ... EY36: =EY32-EY33+EY35 -> 219353.88 | FA36: =(EA36/DL36)^(1/3)-1 -> 0.20421334 | FB36: =(EF36/DQ36)^(1/3)-1 -> 0.22372932 | FC36: =(EK36/DV36)^(1/3)-1 -> 0.096065933 | FD36: =(EP36/EA36)^(1/3)-1 -> 0.2925154 | FE36: =(EU36/EF36)^(1/3)-1 -> 0.22388766 | FF36: =(EV36/EK36)^(1/3)-1 -> 0.14573508 | FG36: =(EK36/DL36)^(1/5)-1 -> 0.23861058 | FH36: =(EP36/DQ36)^(1/5)-1 -> 0.26315595 | FI36: =(EU36/DV36)^(1/5)-1 -> 0.12214737 | FJ36: =(EV36/EA36)^(1/5)-1 -> 0.20216271 | FK36: =(EW36/EF36)^(1/5)-1 -> 0.18279112 | FL36: =(EX36/EK36)^(1/5)-1 -> 0.14061935
A37: GAAP EPS - Diluted | F37: =F36/F38 -> -0.0071574979 | K37: =K36/K38 -> -0.010957453 | P37: =P36/P38 -> 0.0018698869 | Q37: =+Q36/Q38 -> 0.0019815 | R37: =+R36/R38 -> 0.0038678322 | S37: =+S36/S38 -> 0.0065884783 | T37: =+T36/T38 -> 0.0094168802 | U37: =+U36/U38 -> 0.02258411 | V37: =+V36/V38 -> 0.0051872434 | W37: =+W36/W38 -> 0.0062495872 | X37: =+X36/X38 -> 0.0039683557 | ... BN37: =+BN36/BN38 -> 1.4878597 | BO37: 8.7539681 | BP37: 8.4191624 | BQ37: 6.5283786 | BR37: 8.6155169 | BS37: 32.310678 | BT37: =+BT36/BT38 -> 0.2188492 | BU37: =+BU36/BU38 -> 0.22808826 | BV37: =+BV36/BV38 -> 0.20273676 | BW37: =+BW36/BW38 -> 0.21680593 | BX37: =+BX36/BX38 -> 0.80776696 | BY37: 9.9387221 | BZ37: 9.5407833 | CA37: 8.7549929 | CB37: 9.9002062 | CC37: 38.133523 | CD37: =+CD36/CD38 -> 0.24846805 | CE37: =+CE36/CE38 -> 0.23851958 | CF37: =+CF36/CF38 -> 0.21887482 | CG37: =+CG36/CG38 -> 0.24750515 | CH37: =+CH$36/CH38 -> 0.95333949 | CI37: =+CI36/CI38 -> 0.24595716 | CJ37: =+CJ36/CJ38 -> 0.2442039 | CK37: =+CK36/CK38 -> 0.19896442 | CL37: =+CL36/CL38 -> 0.33948251 | CM37: =+CM$36/CM38 -> 1.0511302 | CN37: =+CN36/CN38 -> 0.25483999 | CO37: =+CO36/CO38 -> 0.28449307 | CP37: =+CP36/CP38 -> 0.28653976 | CQ37: =+CQ36/CQ38 -> 0.35314372 | CR37: =+CR36/CR38 -> 1.1795732 | CS37: =+CS36/CS38 -> 0.30079607 | CT37: =+CT36/CT38 -> 0.34993334 | CU37: =+CU36/CU38 -> 0.36230743 | CV37: =+(CV36-36)/CV38 -> 0.37823773 | CW37: =+(CW36-36)/CW38 -> 1.3912862 | CX37: =+CX36/CX38 -> 0.38644742 | CY37: =+CY36/CY38 -> 0.25046091 | CZ37: =+CZ36/CZ38 -> 0.47831796 | DA37: =+DA36/DA38 -> -0.21739005 | DB37: =+DB36/DB38 -> 0.89982149 | DC37: =+DC36/DC38 -> 0.66661089 | DD37: =+DD36/DD38 -> 0.22716059 | DE37: =+DE36/DE38 -> 0.65297169 | ... EY37: =+EY36/EY38 -> 18.653054 | FA37: =(EA37/DL37)^(1/3)-1 -> 0.22850924 | FB37: =(EF37/DQ37)^(1/3)-1 -> 0.25557751 | FC37: =(EK37/DV37)^(1/3)-1 -> 0.12761911 | FD37: =(EP37/EA37)^(1/3)-1 -> 0.32460646 | FE37: =(EU37/EF37)^(1/3)-1 -> 0.24060392 | FF37: =(EV37/EK37)^(1/3)-1 -> 0.15605525 | FG37: =(EK37/DL37)^(1/5)-1 -> 0.26755383 | FH37: =(EP37/DQ37)^(1/5)-1 -> 0.29302584 | FI37: =(EU37/DV37)^(1/5)-1 -> 0.14574778 | FJ37: =(EV37/EA37)^(1/5)-1 -> 0.22215562 | FK37: =(EW37/EF37)^(1/5)-1 -> 0.19646839 | FL37: =(EX37/EK37)^(1/5)-1 -> 0.15108958
A38: Diluted shares outstanding | F38: 848.9 | K38: 1340.64 | P38: 3735.52 | Q38: 4000 | R38: 4290 | S38: 4600 | T38: 4760.6 | U38: 4412.66 | V38: 4973.74 | W38: 5147.22 | X38: 5147.22 | Y38: 5251.22 | Z38: 5132.76 | AA38: 5283.66 | AB38: 5326 | AC38: 5494.7 | AD38: 5718.88 | AE38: =AVERAGE(AA38:AD38) -> 5455.81 | AF38: 5732.24 | AG38: 5744.76 | AH38: 5793.46 | AI38: 6079.44 | AJ38: =AVERAGE(AF38:AI38) -> 5837.475 | AK38: 6082.46 | AL38: 6200.76 | AM38: 6211.48 | AN38: 6269.18 | AO38: =AVERAGE(AK38:AN38) -> 6190.97 | AP38: 6297.4 | AQ38: 6309.38 | AR38: 6331.52 | AS38: 6358.5 | AT38: =AVERAGE(AP38:AS38) -> 6324.2 | AU38: 6347.84 | AV38: 6360.46 | AW38: 6355.52 | AX38: 6337.28 | AY38: =AVERAGE(AU38:AX38) -> 6350.275 | AZ38: 6344.42 | BA38: 6370.72 | BB38: 6394.92 | BC38: 6443.26 | BD38: =AVERAGE(AZ38:BC38) -> 6388.33 | BE38: 6452.16 | BF38: 6449.72 | BG38: 6447.54 | BH38: 6510.72 | BI38: =AVERAGE(BE38:BH38) -> 6465.035 | BJ38: 6527.66 | BK38: 6520.72 | BL38: 6548.78 | BM38: 6580.04 | BN38: =AVERAGE(BJ38:BM38) -> 6544.3 | BO38: 330.136 | BP38: 330.793 | BQ38: 333.314 | BR38: 334.977 | BS38: 332.305 | BT38: 13205.44 | BU38: 13231.72 | BV38: 13332.56 | BW38: 13399.08 | BX38: =AVERAGE(BT38:BW38) -> 13292.2 | BY38: 336.663 | BZ38: 338.337 | CA38: 339.235 | CB38: 341.003 | CC38: 338.8095 | CD38: 13466.52 | CE38: 13533.48 | CF38: 13569.4 | CG38: 13640.12 | CH38: 13552.36 | CI38: 13704.24 | CJ38: 13727.26 | CK38: 13764.3 | CL38: 13769.82 | CM38: 13741.4 | CN38: 13789.96 | CO38: 13817.56 | CP38: 13886.38 | CQ38: 13940.5 | CR38: =AVERAGE(CN38:CQ38) -> 13858.6 | CS38: 13986.22 | CT38: 13936.94 | CU38: 13968.8 | CV38: 14004.42 | CW38: 13974.12 | CX38: 14040.72 | CY38: 14070.06 | CZ38: 14074.32 | DA38: 13892.08 | DB38: 14071.68 | DC38: 14102.68 | DD38: 14064.94 | DE38: 14077.18 | DF38: 14017.98 | DG38: =AVERAGE(DC38:DF38) -> 14065.695 | DH38: 14017.58 | DI38: 13999.08 | DJ38: 13963.98 | DK38: 13903.88 | DL38: =AVERAGE(DH38:DK38) -> 13971.13 | DM38: 13845.34 | DN38: 13740.48 | DO38: 13717.02 | DP38: 13659.38 | DQ38: =AVERAGE(DM38:DP38) -> 13740.555 | DR38: 13641.42 | DS38: 13592.24 | DT38: 13530.38 | DU38: 13449.86 | DV38: =AVERAGE(DR38:DU38) -> 13553.475 | DW38: 13351.02 | DX38: 13239 | DY38: 13097 | DZ38: 12947 | EA38: =AVERAGE(DW38:DZ38) -> 13158.505 | EB38: 12823 | EC38: 12764 | ED38: 12696 | EE38: 12602 | EF38: =AVERAGE(EB38:EE38) -> 12721.25 | EG38: 12527 | EH38: 12495 | EI38: 12419 | EJ38: 12348 | EK38: =AVERAGE(EG38:EJ38) -> 12447.25 | EL38: 12291 | EM38: 12198 | EN38: 12203 | EO38: =EN38*(1.004)-CF!DQ102 -> 12208.479 | EP38: =AVERAGE(EL38:EO38) -> 12225.12 | EQ38: =EO38*(1.004)-CF!DS102 -> 12210.646 | ER38: =EQ38*(1.004)-CF!DT102 -> 12212.822 | ES38: =ER38*(1.004)-CF!DU102 -> 12215.006 | ET38: =ES38*(1.004)-CF!DV102 -> 12217.2 | EU38: =AVERAGE(EQ38:ET38) -> 12213.919 | EV38: =EU38*1.01-CF!DX102 -> 12116.865 | EW38: =EV38*1.01-CF!DY102 -> 12010.578 | EX38: =EW38*1.01-CF!DZ102 -> 11891.359 | EY38: =EX38*1.01-CF!EA102 -> 11759.676
A40: Alphabet Non-GAAP reconciliation
A41: Adj. for One-time item | CD41: =CD25 -> 0 | CE41: =CE25 -> 0 | CF41: =CF25 -> 0 | CG41: =CG25 -> 0 | CH41: =SUM(CD41:CG41) -> 0 | CI41: =CI25 -> 0 | CJ41: =CJ25 -> 0 | CK41: =CK25 -> 378 | CL41: =CL25 -> 0 | CM41: =SUM(CI41:CL41) -> 378 | CN41: =CN25 -> 0 | CO41: =CO25 -> 0 | CP41: =CP25 -> 0 | CQ41: =CQ25 -> 0 | CR41: =SUM(CN41:CQ41) -> 0 | CS41: =CS25 -> 0 | CT41: =CT25 -> 0 | CU41: =CU25 -> 0 | CV41: =CV25 -> 0 | CW41: =SUM(CS41:CV41) -> 0 | CX41: =CX25 -> 0 | CY41: 2736 | CZ41: 0 | DA41: 9857 | DB41: =SUM(CX41:DA41) -> 12593 | DC41: 0 | DD41: =DD25 -> 5071 | DE41: 0 | DF41: 0 | DG41: =SUM(DC41:DF41) -> 5071 | DH41: 1682 | DI41: =DI25 -> 0 | DJ41: 0 | DK41: =DK25 -> 0 | DL41: =SUM(DH41:DK41) -> 1682 | DM41: =DM25 -> 0 | DN41: =DN25 -> 0 | DO41: =DO25 -> 0 | DP41: =DP25 -> 0 | DQ41: =SUM(DM41:DP41) -> 0 | DR41: =DR25 -> 0 | DS41: =DS25 -> 0 | DT41: =DT25 -> 0 | DU41: =DU25 -> 0 | DV41: =SUM(DR41:DU41) -> 0 | DW41: =DW25 -> 0 | DX41: =DX25 -> 0 | DY41: =DY25 -> 0 | DZ41: =DZ25 -> 0 | EA41: =SUM(DW41:DZ41) -> 0 | EB41: =EB25 -> 0 | EC41: =EC25 -> 0 | ED41: =ED25 -> 0 | EE41: =EE25 -> 0 | EF41: =SUM(EB41:EE41) -> 0 | EG41: =EG25 -> 0 | EH41: =EH25 -> 0 | EI41: =EI25 -> 0 | EJ41: =EJ25 -> 0 | EK41: =SUM(EG41:EJ41) -> 0 | EL41: =EL25 -> 0 | EM41: =EM25 -> 0 | EN41: =EN25 -> 3457 | EO41: =EO25 -> 0 | EP41: =SUM(EL41:EO41) -> 3457 | EQ41: =EQ25 -> 0 | ER41: =ER25 -> 0 | ES41: =ES25 -> 0 | ET41: =ET25 -> 0 | EU41: =SUM(EQ41:ET41) -> 0 | EV41: =EV25 -> 0 | EW41: =EW25 -> 0 | EX41: =EX25 -> 0 | EY41: =EY25 -> 0
A42: Non-GAAP Net Income (loss) | CD42: =CD36+CD41 -> 3346 | CE42: =CE36+CE41 -> 3228 | CF42: =CF36+CF41 -> 2970 | CG42: =CG36+CG41 -> 3376 | CH42: =CH36+CH41 -> 12920 | CI42: =CI36+CI41 -> 3370.656 | CJ42: =CJ36+CJ41 -> 3352.2504 | CK42: =CK36+CK41 -> 3116.606 | ... EY42: =EY36+EY41 -> 219353.88 | FA42: =(EA42/DL42)^(1/3)-1 -> 0.18517236 | FB42: =(EF42/DQ42)^(1/3)-1 -> 0.22372932 | FC42: =(EK42/DV42)^(1/3)-1 -> 0.096065933 | FD42: =(EP42/EA42)^(1/3)-1 -> 0.30391614 | FE42: =(EU42/EF42)^(1/3)-1 -> 0.22388766 | FF42: =(EV42/EK42)^(1/3)-1 -> 0.14573508 | FG42: =(EK42/DL42)^(1/5)-1 -> 0.22682223 | FH42: =(EP42/DQ42)^(1/5)-1 -> 0.26982927 | FI42: =(EU42/DV42)^(1/5)-1 -> 0.12214737 | FJ42: =(EV42/EA42)^(1/5)-1 -> 0.20216271 | FK42: =(EW42/EF42)^(1/5)-1 -> 0.18279112 | FL42: =(EX42/EK42)^(1/5)-1 -> 0.14061935
A43: Non-GAAP EPS - Diluted | CD43: =+CD42/CD52 -> 0.24846805 | CE43: =+CE42/CE52 -> 0.23851958 | CF43: =+CF42/CF52 -> 0.21887482 | CG43: =+CG42/CG52 -> 0.24750515 | CH43: =+CH42/CH52 -> 0.95333949 | CI43: =+CI42/CI52 -> 0.24595716 | CJ43: =+CJ42/CJ52 -> 0.2442039 | CK43: =+CK42/CK52 -> 0.22642677 | ... EY43: =+EY42/EY52 -> 18.653054 | FA43: =(EA43/DL43)^(1/3)-1 -> 0.2090841 | FB43: =(EF43/DQ43)^(1/3)-1 -> 0.25557751 | FC43: =(EK43/DV43)^(1/3)-1 -> 0.12761911 | FD43: =(EP43/EA43)^(1/3)-1 -> 0.33629026 | FE43: =(EU43/EF43)^(1/3)-1 -> 0.24060392 | FF43: =(EV43/EK43)^(1/3)-1 -> 0.15605525 | FG43: =(EK43/DL43)^(1/5)-1 -> 0.25549 | FH43: =(EP43/DQ43)^(1/5)-1 -> 0.29985696 | FI43: =(EU43/DV43)^(1/5)-1 -> 0.14574778 | FJ43: =(EV43/EA43)^(1/5)-1 -> 0.22215562 | FK43: =(EW43/EF43)^(1/5)-1 -> 0.19646839 | FL43: =(EX43/EK43)^(1/5)-1 -> 0.15108958
A45: Non-recurring items:
A46: Stock compensation expense | F46: =F24 -> 0 | K46: =K24 -> 2.506 | P46: =P24 -> 12.383 | Q46: =Q24 -> 3.774 | R46: =R24 -> 3.735 | S46: =S24 -> 6.182 | T46: =T24 -> 7.944 | U46: =U24 -> 21.635 | V46: =V24 -> 36.418 | W46: =W24 -> 34.165 | ... BD46: =BD24 -> 1164.054 | BE46: 291 | BF46: =BF24 -> 309 | BG46: =BG24 -> 380 | BH46: =BH24 -> 396 | BI46: =BI24 -> 1376 | BJ46: =BJ24 -> 432 | BK46: =BK24 -> 435 | BL46: =BL24 -> 571 | BM46: =BM24 -> 536 | BN46: =BN24 -> 1974 | BO46: 556 | BP46: 747 | BQ46: 1064 | BR46: 878 | BS46: 3245 | BT46: =BT24 -> 556 | BU46: =BU24 -> 552 | BV46: =BV24 -> 688 | BW46: =BW24 -> 677 | BX46: =BX24 -> 2473 | BY46: 681 | BZ46: 778 | CA46: 886 | CB46: 917 | CC46: 3262 | CD46: =CD24 -> 655 | CE46: 778 | CF46: 886 | CG46: 917 | CH46: =SUM(CD46:CG46) -> 3236 | CI46: =CI24 -> 839 | CJ46: =CJ24 -> 880 | CK46: =CK24 -> 1255 | CL46: =CL24 -> 1201 | CM46: =SUM(CI46:CL46) -> 4175 | CN46: =CN24 -> 1203 | CO46: =+CO24 -> 1132 | CP46: =+CP24 -> 1432 | CQ46: =+CQ24 -> 1436 | CR46: =SUM(CN46:CQ46) -> 5203 | CS46: =CS24 -> 1494 | CT46: =CT24 -> 1503 | CU46: =CU24 -> 1860 | CV46: =CV24 -> 1846 | CW46: =SUM(CS46:CV46) -> 6703 | CX46: =CX24 -> 2009 | CY46: =CY24 -> 2003 | CZ46: =CZ24 -> 1820 | DA46: =DA24 -> 1847 | DB46: =SUM(CX46:DA46) -> 7679 | DC46: =DC24 -> 2457 | DD46: =DD24 -> 2413 | DE46: =DE24 -> 2230 | DF46: =DF24 -> 2253 | DG46: =SUM(DC46:DF46) -> 9353 | DH46: =DH24 -> 2769 | DI46: =DI24 -> 2756 | DJ46: =DJ24 -> 2624 | DK46: =DK24 -> 2645 | DL46: =SUM(DH46:DK46) -> 10794 | DM46: =DM24 -> 3191 | DN46: =DN24 -> 3382 | DO46: =DO24 -> 3195 | DP46: =DP24 -> 3223 | DQ46: =SUM(DM46:DP46) -> 12991 | DR46: =DR24 -> 3745 | DS46: =DS24 -> 3803 | DT46: =DT24 -> 3874 | DU46: =DU24 -> 3954 | DV46: =SUM(DR46:DU46) -> 15376 | DW46: =DW24 -> 4504 | DX46: =DX24 -> 4782 | DY46: =DY24 -> 4976 | DZ46: =DZ24 -> 5100 | EA46: =SUM(DW46:DZ46) -> 19362 | EB46: =EB24 -> 5284 | EC46: =EC24 -> 5774 | ED46: =ED24 -> 5743 | EE46: =EE24 -> 5659 | EF46: =SUM(EB46:EE46) -> 22460 | EG46: =EG24 -> 5264 | EH46: =EH24 -> 5865 | EI46: =EI24 -> 5846 | EJ46: =EJ24 -> 5810 | EK46: =SUM(EG46:EJ46) -> 22785 | EL46: =EL24 -> 5516 | EM46: =EM24 -> 5998 | EN46: =EN24 -> 6368 | EO46: =EO24 -> 6527.1865 | EP46: =SUM(EL46:EO46) -> 24409.187 | EQ46: =EQ24 -> 6452.4608 | ER46: =ER24 -> 7098.6445 | ES46: =ES24 -> 7478.2179 | ET46: =ET24 -> 7452.3734 | EU46: =SUM(EQ46:ET46) -> 28481.697 | EV46: =EV24 -> 30856.088 | EW46: =EW24 -> 33307.093 | EX46: =EX24 -> 35765.58 | EY46: =EY24 -> 38299.932
A47: One-time items | F47: 0 | K47: 0 | P47: 0 | Q47: 0 | R47: 0 | S47: 0 | T47: 0 | U47: =SUM(Q47:T47) -> 0 | V47: 0 | W47: 0 | X47: 0 | Y47: 0 | Z47: =SUM(V47:Y47) -> 0 | AA47: 0 | AB47: 0 | AC47: =(AC31*-1)-82-46 -> 73 | AD47: =-66+10.4 -> -55.6 | AE47: =SUM(AA47:AD47) -> 17.4 | AF47: -49 | AG47: 0 | AH47: 20.812 | AI47: =-AI31 -> 90 | AJ47: =SUM(AF47:AI47) -> 61.812 | AK47: =4+30 -> 34 | AL47: -54.85 | AM47: 0 | AN47: =-90.33-42.839 -> -133.169 | AO47: =SUM(AK47:AN47) -> -154.019 | AP47: 0 | AQ47: 0 | AR47: 0 | AS47: 0 | AT47: =SUM(AP47:AS47) -> 0 | AU47: 0 | AV47: 0 | AW47: 95.1 | AX47: =-AX31 -> 1094.757 | AY47: =SUM(AU47:AX47) -> 1189.857 | AZ47: =-AZ31 -> 0 | BA47: =-BA31 -> 0 | BB47: =-BB31 -> 0 | BC47: =-BC31 -> 0 | BD47: =SUM(AZ47:BC47) -> 0 | BE47: =-BE31 -> 0 | BF47: =-BF31 -> 0 | BG47: =-BG31 -> 0 | BH47: =-BH31 -> 0 | BI47: =SUM(BE47:BH47) -> 0 | BJ47: =-BJ31 -> 500 | BK47: =-BK31 -> 0 | BL47: =-BL31 -> 0 | BM47: =-BM31 -> 0 | BN47: =SUM(BJ47:BM47) -> 500 | BO47: 0 | BP47: 0 | BQ47: 0 | BR47: 0 | BS47: 0 | BT47: 0 | BU47: 0 | BV47: 0 | BW47: 0 | BX47: 0 | BY47: 0 | BZ47: 0 | CA47: 0 | CB47: 0 | CC47: 0 | CD47: 0 | CE47: 0 | CF47: 0 | CG47: 0 | CH47: 0 | CI47: 0 | CJ47: 0 | CK47: 378 | CL47: 0 | CM47: =SUM(CI47:CL47) -> 378 | CN47: 0 | CO47: 0 | CP47: 0 | CQ47: 0 | CR47: =SUM(CN47:CQ47) -> 0 | CS47: 0 | CT47: 0 | CU47: 0 | CV47: -36 | CW47: =SUM(CS47:CV47) -> -36 | CX47: 0 | CY47: =CY25 -> 2736 | CZ47: 0 | DA47: 9857 | DB47: =SUM(CX47:DA47) -> 12593 | DC47: =DC25-SUM(DC191:DC197) -> -2511 | DD47: =DD25-SUM(DD192:DD197) -> 4330 | DE47: =DE25-SUM(DE192:DE197) -> -1005 | DF47: =DF25-SUM(DF192:DF197) -> -1338 | DG47: =SUM(DC47:DF47) -> -524 | DH47: =DH25-SUM(DH192:DH197) -> 646 | DI47: =DI25-SUM(DI192:DI197) -> -2339 | DJ47: =DJ25-SUM(DJ191:DJ197) -> 1180 | DK47: =DK25-SUM(DK191:DK197) -> -817 | DL47: =SUM(DH47:DK47) -> -1330 | DM47: =DM25-SUM(DM191:DM197) -> 806 | DN47: =DN25-SUM(DN191:DN197) -> -1461 | DO47: =DO25-SUM(DO191:DO197) -> -1686 | DP47: =DP25-SUM(DP191:DP197) -> -2652 | DQ47: =SUM(DM47:DP47) -> -4993 | DR47: =DR25-SUM(DR191:DR197) -> -4501 | DS47: =DS25-SUM(DS191:DS197) -> -2235 | DT47: =DT25-SUM(DT191:DT197) -> -1646 | DU47: =DU25-SUM(DU191:DU197) -> -2139 | DV47: =SUM(DR47:DU47) -> -10521 | DW47: =DW25-SUM(DW191:DW197) -> 1574 | DX47: =DX25-SUM(DX191:DX197) -> 925 | DY47: =DY25-SUM(DY191:DY197) -> 1517 | DZ47: =DZ25-SUM(DZ191:DZ197) -> 1672 | EA47: =SUM(DW47:DZ47) -> 5688 | EB47: =EB25-SUM(EB191:EB197) -> 7 | EC47: =EC25-SUM(EC191:EC197) -> 827 | ED47: =ED25-SUM(ED191:ED197) -> 1212 | EE47: =EE25-SUM(EE191:EE197) -> 395 | EF47: =SUM(EB47:EE47) -> 2441 | EG47: =EG25-SUM(EG191:EG197) -> -1782 | EH47: =EH25-SUM(EH191:EH197) -> 964 | EI47: =EI25-SUM(EI191:EI197) -> -1942 | EJ47: =EJ25-SUM(EJ191:EJ197) -> -183 | EK47: =SUM(EG47:EJ47) -> -2943 | EL47: =EL25-SUM(EL191:EL197) -> -10182 | EM47: =EM25-SUM(EM191:EM197) -> -1612 | EN47: =EN25-SUM(EN191:EN197) -> -8226 | EO47: =EO25-SUM(EO191:EO197) -> 143 | EP47: =SUM(EL47:EO47) -> -19877 | EQ47: =EQ25-SUM(EQ191:EQ197) -> 143 | ER47: =ER25-SUM(ER191:ER197) -> 143 | ES47: =ES25-SUM(ES191:ES197) -> 143 | ET47: =ET25-SUM(ET191:ET197) -> 143 | EU47: =SUM(EQ47:ET47) -> 572 | EV47: =EV25-SUM(EV191:EV197) -> 503.41056 | EW47: =EW25-SUM(EW191:EW197) -> 429.64558 | EX47: =EX25-SUM(EX191:EX197) -> 429.64558 | EY47: =EY25-SUM(EY191:EY197) -> 429.64558
A48: Tax Effect | F48: =-(F32+F46)*F34 -> 0 | K48: =-(K32+K46)*K34 -> 0 | P48: =-(P46*P34) -> -3.791894 | Q48: 0 | R48: 0 | S48: 0 | T48: 0 | U48: =SUM(Q48:T48) -> 0 | V48: 0 | W48: 0 | X48: 0 | Y48: 0 | Z48: =SUM(V48:Y48) -> 0 | AA48: 0 | AB48: 0 | AC48: =-(AC46*0.24) -> -16.31544 | AD48: =-(AD46*0.24) -> -14.28744 | AE48: =SUM(AA48:AD48) -> -30.60288 | AF48: =-(AF46*0.24) -> -11.73792 | AG48: -9.403 | AH48: -11.11 | AI48: =-37.026-13.881 -> -50.907 | AJ48: =SUM(AF48:AI48) -> -83.15792 | AK48: =-27.444-12.342-(4*0.41) -> -41.426 | AL48: =-25.813+22.582 -> -3.231 | AM48: -20.938 | AN48: =-34.676 -> -34.676 | AO48: =SUM(AK48:AN48) -> -100.271 | AP48: -26.768 | AQ48: -42.997 | AR48: -31.011 | AS48: -42.253 | AT48: =SUM(AP48:AS48) -> -143.029 | AU48: -50.736 | AV48: =-47.764 -> -47.764 | AW48: =-63.1-38.9 -> -102 | AX48: =-65.161+-82.275 -> -147.436 | AY48: =SUM(AU48:AX48) -> -347.936 | AZ48: -64.016 | BA48: -69.4 | BB48: -72.582 | BC48: -62.011 | BD48: =SUM(AZ48:BC48) -> -268.009 | BE48: -65 | BF48: -70 | BG48: -85 | BH48: -89 | BI48: =SUM(BE48:BH48) -> -309 | BJ48: -92 | BK48: -91 | BL48: -116 | BM48: -114 | BN48: =SUM(BJ48:BM48) -> -413 | BO48: -118 | BP48: -186 | BQ48: -231 | BR48: -217 | BS48: -752 | BT48: -118 | BU48: =-135-51 -> -186 | BV48: =-155-76 -> -231 | BW48: =-152-65 -> -217 | BX48: =SUM(BT48:BW48) -> -752 | BY48: -106 | BZ48: -99 | CA48: -198 | CB48: -202 | CC48: -605 | CD48: -141 | CE48: -160 | CF48: =12-3-207 -> -198 | CG48: =-191-11 -> -202 | CH48: =SUM(CD48:CG48) -> -701 | CI48: -190 | CJ48: -195 | CK48: -258 | CL48: -255 | CM48: =SUM(CI48:CL48) -> -898 | CN48: -257 | CO48: -234 | CP48: -309 | CQ48: -316 | CR48: =SUM(CN48:CQ48) -> -1116 | CS48: -453 | CT48: -516 | CU48: =-595 -> -595 | CV48: -586 | CW48: =SUM(CS48:CV48) -> -2150 | CX48: =-(CX46+CX47)*CX34 -> -410.40284 | CY48: =-CY46*(CY33/(CY32+CY47)) -> -240.20231 | CZ48: =-(CZ46+CZ47)*CZ34 -> -284.43915 | DA48: =-(DA46)*0.15 -> -277.05 | DB48: =SUM(CX48:DA48) -> -1212.0943 | DC48: =-(DC46+DC47)*DC34 -> 5.849189 | DD48: =-(DD46+DD47-DD25)*DD34 -> -404.6121 | DE48: =-(DE46+DE47)*DE34 -> -108.24903 | DF48: =-(DF46+DF47)*DF34 -> -102.1108 | DG48: =SUM(DC48:DF48) -> -609.12275 | DH48: =-(DH46+DH47-DH25)*DH34 -> -314.03167 | DI48: =-(DI46+DI47)*DI34 -> -75.524821 | DJ48: =-(DJ46+DJ47)*DJ34 -> -687.7886 | DK48: =-(DK46+DK47)*DK34 -> -5.6356502 | DL48: =SUM(DH48:DK48) -> -1082.9807 | DM48: =-(DM46+DM47)*DM34 -> -474.56968 | DN48: =-(DN46+DN47)*DN34 -> -305.8932 | DO48: =-(DO46+DO47)*DO34 -> -238.56636 | DP48: =-(DP46+DP47)*DP34 -> -105.77356 | DQ48: =SUM(DM48:DP48) -> -1124.8028 | DR48: =-(DR46+DR47)*DR34 -> 119.10295 | DS48: =-(DS46+DS47)*DS34 -> -246.77189 | DT48: =-(DT46+DT47)*DT34 -> -398.76795 | DU48: =-(DU46+DU47)*DU34 -> -279.6656 | DV48: =SUM(DR48:DU48) -> -806.1025 | DW48: =-(DW46+DW47)*DW34 -> -801.88254 | DX48: =-(DX46+DX47)*DX34 -> -904.04355 | DY48: =-(DY46+DY47)*DY34 -> -929.17138 | DZ48: =-(DZ46+DZ47)*DZ34 -> -1391.3662 | EA48: =SUM(DW48:DZ48) -> -4026.4637 | EB48: =-(EB46+EB47)*EB34 -> -916.66103 | EC48: =-(EC46+EC47)*EC34 -> -1065.3579 | ED48: =-(ED46+ED47)*ED34 -> -494.7936 | EE48: =-(EE46+EE47)*EE34 -> -923.77314 | EF48: =SUM(EB48:EE48) -> -3400.5857 | EG48: =-(EG46+EG47)*EG34 -> -572.19657 | EH48: =-(EH46+EH47)*EH34 -> -974.61537 | EI48: =-(EI46+EI47)*EI34 -> -665.52451 | EJ48: =-(EJ46+EJ47)*EJ34 -> -995.97708 | EK48: =SUM(EG48:EJ48) -> -3208.3135 | EL48: =-(EL46+EL47)*EL34 -> 809.39563 | EM48: =-(EM46+EM47)*EM34 -> -741.53426 | EN48: =-(EN46+EN47)*EN34 -> 380.49569 | EO48: =-(EO46+EO47)*EO34 -> -1133.9317 | EP48: =SUM(EL48:EO48) -> -685.57465 | EQ48: =-(EQ46+EQ47)*EQ34 -> -1121.2283 | ER48: =-(ER46+ER47)*ER34 -> -1231.0796 | ES48: =-(ES46+ES47)*ES34 -> -1295.607 | ET48: =-(ET46+ET47)*ET34 -> -1291.2135 | EU48: =SUM(EQ48:ET48) -> -4939.1284 | EV48: =-(EV46+EV47)*EV34 -> -5331.1147 | EW48: =-(EW46+EW47)*EW34 -> -5735.2456 | EX48: =-(EX46+EX47)*EX34 -> -6153.1884 | EY48: =-(EY46+EY47)*EY34 -> -6584.0281
A49: Discontinued Operations - Motorola | BR49: 21 | BS49: 21 | BU49: =-BU35 -> 199 | BV49: =-BV35 -> 523 | BW49: =-BW35 -> 355 | BX49: =SUM(BT49:BW49) -> 1077 | BY49: -22 | BZ49: -674 | CA49: -15 | CB49: 5 | CC49: -706 | CD49: =-CD35 -> 182 | CE49: =-CE35 -> -454 | CF49: =-CF35 -> 302 | CG49: =-CG35 -> 506 | CH49: =SUM(CD49:CG49) -> 536 | CI49: =-CI35 -> 198 | CJ49: =-CJ35 -> 68 | CK49: =-CK35 -> 185 | CL49: =-CL35 -> -967 | CM49: =SUM(CI49:CL49) -> -516 | CN49: =-CN35 -> 0 | CO49: =-CO35 -> 0 | CP49: =-CP35 -> 0 | CQ49: =-CQ35 -> 0 | CR49: 0 | CS49: =-CS35 -> 0 | CT49: =-CT35 -> 0 | CU49: =-CU35 -> 0 | CV49: 0 | CW49: 0 | CX49: 0 | CY49: 0 | CZ49: 0 | DA49: 0 | DB49: 0
A50: Adjusted Net Income (loss) | F50: =F36+SUM(F46:F48) -> -6.076 | K50: =K36+SUM(K46:K48) -> -12.184 | P50: =P36+SUM(P46:P48) -> 15.576106 | Q50: =Q36+SUM(Q46:Q48) -> 11.7 | R50: =R36+SUM(R46:R48) -> 20.328 | S50: =S36+SUM(S46:S48) -> 36.489 | T50: =T36+SUM(T46:T48) -> 52.774 | U50: =U36+SUM(U46:U48) -> 121.291 | V50: =V36+SUM(V46:V48) -> 62.218 | W50: =W36+SUM(W46:W48) -> 66.333 | ... BN50: =BN36+SUM(BN46:BN48) -> 11798 | BO50: 3328 | BP50: 3346 | BQ50: 3009 | BR50: 3568 | BS50: 13251 | BT50: =BT36+SUM(BT46:BT48) -> 3328 | BU50: =BU36+SUM(BU46:BU48) -> 3384 | BV50: =BV36+SUM(BV46:BV48) -> 3160 | BW50: =BW36+SUM(BW46:BW48)+BW49 -> 3720 | BX50: =BX36+SUM(BX46:BX48)+BX49 -> 13535 | BY50: 3899 | BZ50: 3233 | CA50: 3643 | CB50: 4096 | CC50: 14871 | CD50: =CD36+SUM(CD46:CD48)+CD49 -> 4042 | CE50: =CE36+SUM(CE46:CE48)+CE49 -> 3392 | CF50: =CF36+SUM(CF46:CF48)+CF49 -> 3960 | CG50: =CG36+SUM(CG46:CG48)+CG49 -> 4597 | CH50: =CH36+SUM(CH46:CH48)+CH49 -> 15991 | CI50: =CI36+SUM(CI46:CI48)+CI49 -> 4217.656 | CJ50: =CJ36+SUM(CJ46:CJ48)+CJ49 -> 4105.2504 | CK50: =CK36+SUM(CK46:CK48)+CK49 -> 4298.606 | ... EY50: =EY36+SUM(EY46:EY48)+EY49 -> 251499.42 | FA50: =(EA50/DL50)^(1/3)-1 -> 0.23764567 | FB50: =(EF50/DQ50)^(1/3)-1 -> 0.26440846 | FC50: =(EK50/DV50)^(1/3)-1 -> 0.13390395 | FD50: =(EP50/EA50)^(1/3)-1 -> 0.18078026 | FE50: =(EU50/EF50)^(1/3)-1 -> 0.1870589 | FF50: =(EV50/EK50)^(1/3)-1 -> 0.14792983 | FG50: =(EK50/DL50)^(1/5)-1 -> 0.22269521 | FH50: =(EP50/DQ50)^(1/5)-1 -> 0.23115208 | FI50: =(EU50/DV50)^(1/5)-1 -> 0.14760093 | FJ50: =(EV50/EA50)^(1/5)-1 -> 0.1687177 | FK50: =(EW50/EF50)^(1/5)-1 -> 0.15846565 | FL50: =(EX50/EK50)^(1/5)-1 -> 0.13851483
A51: Adj. EPS - Diluted | F51: =F50/F52 -> -0.0071574979 | K51: =K50/K52 -> -0.0090881967 | P51: =P50/P52 -> 0.004169729 | Q51: =Q50/Q52 -> 0.002925 | R51: =R50/R52 -> 0.0047384615 | S51: =S50/S52 -> 0.0079323913 | T51: =T50/T52 -> 0.011085577 | U51: =U50/U52 -> 0.027487049 | V51: =V50/V52 -> 0.012509299 | W51: =W50/W52 -> 0.012887151 | ... BN51: =BN50/BN52 -> 1.8027902 | BO51: 10.080694 | BP51: 10.115087 | BQ51: 9.0275236 | BR51: 10.651478 | BS51: 39.876018 | BT51: =BT50/BT52 -> 0.25201735 | BU51: =BU50/BU52 -> 0.25574906 | BV51: =BV50/BV52 -> 0.23701375 | BW51: =BW50/BW52 -> 0.277631 | BX51: =BX50/BX52 -> 1.0182664 | BY51: 11.581314 | BZ51: 9.5555615 | CA51: 10.738868 | CB51: 12.011625 | CC51: 43.891922 | CD51: =CD50/CD52 -> 0.30015178 | CE51: =CE50/CE52 -> 0.25063768 | CF51: =CF50/CF52 -> 0.2918331 | CG51: =CG50/CG52 -> 0.3370205 | CH51: =CH$50/CH52 -> 1.1799421 | CI51: =CI50/CI52 -> 0.30776285 | CJ51: =CJ50/CJ52 -> 0.29905825 | CK51: =CK50/CK52 -> 0.3123011 | CL51: =CL50/CL52 -> 0.33795743 | CM51: =CM$50/CM52 -> 1.2795639 | CN51: =CN50/CN52 -> 0.32344062 | CO51: =CO50/CO52 -> 0.34948283 | CP51: =CP50/CP52 -> 0.36741037 | CQ51: =CQ50/CQ52 -> 0.43348517 | CR51: =CR50/CR52 -> 1.4744803 | CS51: =CS50/CS52 -> 0.37522647 | CT51: =CT50/CT52 -> 0.42075233 | CU51: =CU50/CU52 -> 0.45286639 | ... EY51: =EY50/EY52 -> 21.386594 | FA51: =(EA51/DL51)^(1/3)-1 -> 0.2626161 | FB51: =(EF51/DQ51)^(1/3)-1 -> 0.29731535 | FC51: =(EK51/DV51)^(1/3)-1 -> 0.1665464 | FD51: =(EP51/EA51)^(1/3)-1 -> 0.21009712 | FE51: =(EU51/EF51)^(1/3)-1 -> 0.20327213 | FF51: =(EV51/EK51)^(1/3)-1 -> 0.15826977 | FG51: =(EK51/DL51)^(1/5)-1 -> 0.25126655 | FH51: =(EP51/DQ51)^(1/5)-1 -> 0.26026517 | FI51: =(EU51/DV51)^(1/5)-1 -> 0.17173666 | FJ51: =(EV51/EA51)^(1/5)-1 -> 0.18815439 | FK51: =(EW51/EF51)^(1/5)-1 -> 0.17186164 | FL51: =(EX51/EK51)^(1/5)-1 -> 0.14896574
A52: =A38 -> Diluted shares outstanding | F52: =F38 -> 848.9 | K52: =K38 -> 1340.64 | P52: =P38 -> 3735.52 | Q52: =Q38 -> 4000 | R52: =R38 -> 4290 | S52: =S38 -> 4600 | T52: =T38 -> 4760.6 | U52: =U38 -> 4412.66 | V52: =V38 -> 4973.74 | W52: =W38 -> 5147.22 | ... BN52: =BN38 -> 6544.3 | BO52: 330.136 | BP52: 330.793 | BQ52: 333.314 | BR52: 334.977 | BS52: 332.305 | BT52: =BT38 -> 13205.44 | BU52: =BU38 -> 13231.72 | BV52: =BV38 -> 13332.56 | BW52: =BW38 -> 13399.08 | BX52: =BX38 -> 13292.2 | BY52: 336.663 | BZ52: 338.337 | CA52: 339.235 | CB52: 341.003 | CC52: 338.8095 | CD52: =CD38 -> 13466.52 | CE52: =CE38 -> 13533.48 | CF52: =CF38 -> 13569.4 | CG52: =CG38 -> 13640.12 | CH52: =CH38 -> 13552.36 | CI52: =CI38 -> 13704.24 | CJ52: =CJ38 -> 13727.26 | CK52: =CK38 -> 13764.3 | ... CZ52: =CZ38 -> 14074.32 | DA52: 705.079 | DB52: =DB38 -> 14071.68 | DC52: =DC38 -> 14102.68 | DD52: =DD38 -> 14064.94 | DE52: =DE38 -> 14077.18 | DF52: =DF38 -> 14017.98 | DG52: =DG38 -> 14065.695 | DH52: =DH38 -> 14017.58 | DI52: =DI38 -> 13999.08 | ... EY52: =EY38 -> 11759.676
A53: Adj. EBITDA Reconciliation
A54: Operating income (adj. for 1x item as noted) | P54: =P27 -> 10.964 | Q54: =Q27 -> 15.207 | R54: =R27 -> 31.097 | S54: =S27 -> 56.913 | T54: =T27 -> 83.249 | U54: =SUM(Q54:T54) -> 186.466 | V54: =V27 -> 84.706 | W54: =W27 -> 104.784 | X54: =X27 -> 66.556 | Y54: =Y27 -> 86.418 | Z54: =SUM(V54:Y54) -> 342.464 | AA54: =AA27 -> 155.323 | AB54: =AB27 -> 170.958 | AC54: =AC27 -> 212.112 | AD54: =AD27 -> 302.799 | AE54: =SUM(AA54:AD54) -> 841.192 | AF54: =AF27 -> 442.77 | AG54: =AG27 -> 475.698 | AH54: =AH27 -> 529.171 | AI54: =AI27 -> 659.64 | AJ54: =SUM(AF54:AI54) -> 2107.279 | AK54: =AK27+30 -> 772.699 | AL54: =AL27 -> 815.372 | AM54: =AM27 -> 931.331 | AN54: =AN27 -> 1060.594 | AO54: =SUM(AK54:AN54) -> 3579.996 | AP54: =AP27 -> 1221.209 | AQ54: =AQ27 -> 1104.615 | AR54: =AR27 -> 1317.837 | AS54: =AS27 -> 1440.734 | AT54: =SUM(AP54:AS54) -> 5084.395 | AU54: =AU27 -> 1546.235 | AV54: =AV27 -> 1577.965 | AW54: =AW27+AW47 -> 1742.665 | AX54: =AX27 -> 1860.204 | AY54: =SUM(AU54:AX54) -> 6727.069 | AZ54: =AZ27 -> 1883.591 | BA54: =BA27 -> 1873.894 | BB54: =BB27 -> 2073.718 | BC54: =BC27 -> 2480.983 | BD54: =SUM(AZ54:BC54) -> 8312.186 | BE54: =BE27 -> 2488 | BF54: =BF27 -> 2365 | BG54: =BG27 -> 2547 | BH54: =BH27 -> 2982 | BI54: =SUM(BE54:BH54) -> 10382 | BJ54: =BJ27 -> 2796 | BK54: =BK27 -> 2881 | BL54: =BL27 -> 3058 | BM54: =BM27 -> 3507 | BN54: =SUM(BJ54:BM54) -> 12242 | BO54: 3389 | BP54: 3203 | BQ54: 2736 | BR54: 3394 | BS54: 12722 | BT54: =BT27 -> 3389 | BU54: =BU27 -> 3436 | BV54: =BV27 -> 3263 | BW54: =BW27 -> 3747 | BX54: =SUM(BT54:BW54) -> 13835 | BY54: 3477 | BZ54: 3123 | CA54: 3444 | CB54: 3922 | CC54: 13966 | CD54: =CD27 -> 3748 | CE54: =CE27 -> 3465 | CF54: =CF27 -> 3761 | CG54: =CG27 -> 4429 | CH54: =SUM(CD54:CG54) -> 15403 | CI54: =CI27 -> 4115 | CJ54: =CJ27 -> 4258 | CK54: =CK27 -> 3724 | CL54: =CL27 -> 4399 | CM54: =SUM(CI54:CL54) -> 16496 | CN54: =CN27 -> 4447 | CO54: =CO27 -> 4825 | CP54: =CP27 -> 4708 | CQ54: =CQ27 -> 5380 | CR54: =SUM(CN54:CQ54) -> 19360 | CS54: =CS27 -> 5342 | CT54: =CT27 -> 5968 | CU54: =CU27 -> 5767 | CV54: =CV27 -> 6639 | CW54: =SUM(CS54:CV54) -> 23716 | CX54: =CX27 -> 6568 | CY54: =CY27+CY25 -> 6868 | CZ54: =CZ27 -> 7782 | DA54: =DA27 -> 7664 | DB54: =SUM(CX54:DA54) -> 28882 | DC54: =DC27+DC25 -> 7633 | DD54: =DD27+DD25 -> 8116 | DE54: =DE27+DE25 -> 8625 | DF54: =DF27+DF25 -> 8221 | DG54: =SUM(DC54:DF54) -> 32595 | DH54: =DH27+DH25 -> 8305 | DI54: =DI27+DI25 -> 9180 | DJ54: =DJ27+DJ25 -> 9177 | DK54: =DK27+DK25 -> 9266 | DL54: =SUM(DH54:DK54) -> 35928 | DM54: =DM27+DM25 -> 7977 | DN54: =DN27+DN25 -> 6383 | DO54: =DO27+DO25 -> 11213 | DP54: =DP27+DP25 -> 15651 | DQ54: =SUM(DM54:DP54) -> 41224 | DR54: =DR27+DR25 -> 16437 | DS54: =DS27+DS25 -> 19361 | DT54: =DT27+DT25 -> 21031 | DU54: =DU27+DU25 -> 21885 | DV54: =SUM(DR54:DU54) -> 78714 | DW54: =DW27+DW25 -> 20094 | DX54: =DX27+DX25 -> 19453 | DY54: =DY27+DY25 -> 17135 | DZ54: =DZ27+DZ25 -> 18160 | EA54: =SUM(DW54:DZ54) -> 74842 | EB54: =EB27+EB25 -> 17415 | EC54: =EC27+EC25 -> 21838 | ED54: =ED27+ED25 -> 21343 | EE54: =EE27+EE25 -> 23697 | EF54: =SUM(EB54:EE54) -> 84293 | EG54: =EG27+EG25 -> 25472 | EH54: =EH27+EH25 -> 27425 | EI54: =EI27+EI25 -> 28521 | EJ54: =EJ27+EJ25 -> 30972 | EK54: =SUM(EG54:EJ54) -> 112390 | EL54: =EL27+EL25 -> 30606 | EM54: =EM27+EM25 -> 31271 | EN54: =EN27+EN25 -> 34685 | EO54: =EO27+EO25 -> 37339.346 | EP54: =SUM(EL54:EO54) -> 133901.35 | EQ54: =EQ27+EQ25 -> 37124.37 | ER54: =ER27+ER25 -> 38929.529 | ES54: =ES27+ES25 -> 40112.084 | ET54: =ET27+ET25 -> 43585.093 | EU54: =SUM(EQ54:ET54) -> 159751.08 | EV54: =EV27+EV25 -> 178688.98 | EW54: =EW27+EW25 -> 203370.41 | EX54: =EX27+EX25 -> 230168.82 | EY54: =EY27+EY25 -> 260643.46 | FA54: =(EA54/DL54)^(1/3)-1 -> 0.27713688 | FB54: =(EF54/DQ54)^(1/3)-1 -> 0.26924987 | FC54: =(EK54/DV54)^(1/3)-1 -> 0.1260523 | FD54: =(EP54/EA54)^(1/3)-1 -> 0.21398462 | FE54: =(EU54/EF54)^(1/3)-1 -> 0.23751582 | FF54: =(EV54/EK54)^(1/3)-1 -> 0.16714112 | FG54: =(EK54/DL54)^(1/5)-1 -> 0.2562004 | FH54: =(EP54/DQ54)^(1/5)-1 -> 0.26568888 | FI54: =(EU54/DV54)^(1/5)-1 -> 0.15206866 | FJ54: =(EV54/EA54)^(1/5)-1 -> 0.19011925 | FK54: =(EW54/EF54)^(1/5)-1 -> 0.19261221 | FL54: =(EX54/EK54)^(1/5)-1 -> 0.154154
A55: Depreciation & amortization | P55: =SUM(CF!B11:B14) -> 14.182 | U55: =SUM(CF!G11:G14) -> 28.983 | V55: =SUM(CF!H11:H14) -> 10.694 | W55: =SUM(CF!I11:I14) -> 12.037 | X55: =SUM(CF!J11:J14) -> 26.065 | Y55: =SUM(CF!K11:K14) -> 17.871 | Z55: =SUM(CF!L11:L14) -> 66.667 | AA55: =SUM(CF!M11:M14) -> 23.675 | AB55: =SUM(CF!N11:N14) -> 31.962 | AC55: =SUM(CF!O11:O14) -> 41.326 | AD55: =SUM(CF!P11:P14)+0.001 -> 62.854 | AE55: =SUM(AA55:AD55) -> 159.817 | AF55: =46.478+9.715 -> 56.193 | AG55: =SUM(CF!S11:S14) -> 66.929 | AH55: =SUM(CF!T11:T14)+0.001 -> 96.778 | AI55: =SUM(CF!U11:U14) -> 95.953 | AJ55: =SUM(AF55:AI55) -> 315.853 | AK55: =95.868+15.29+4 -> 115.158 | AL55: =206.079+31.3+4-AK55 -> 126.221 | AM55: =335.629+47.06+10.8-AL55-AK55 -> 152.11 | AN55: =494.43+77.509+10.8-AM55-AL55-AK55 -> 189.25 | AO55: =SUM(AK55:AN55) -> 582.739 | AP55: =170.289+34.7032 -> 204.9922 | AQ55: =358.426+69.921+3.66-AP55 -> 227.0148 | AR55: =(565.841+111.881)-AQ55-AP55 -> 245.715 | AS55: =(807.743+159.915)-AR55-AQ55-AP55 -> 289.936 | AT55: =SUM(AP55:AS55) -> 967.658 | AU55: =280.564+55.96 -> 336.524 | AV55: =308.716+82.891 -> 391.607 | AW55: =309.482+76.764 -> 386.246 | AX55: =313.475+72.035 -> 385.51 | AY55: =SUM(CF!AK11:AK14) -> 1499.887 | AZ55: =321.129+82.093 -> 403.222 | BA55: =310.982+65.975 -> 376.957 | BB55: =311.102+67.521 -> 378.623 | BC55: =296.817+68.689 -> 365.506 | BD55: =SUM(AZ55:BC55) -> 1524.308 | BE55: =264+67 -> 331 | BF55: =266+76 -> 342 | BG55: =257+85 -> 342 | BH55: =280+101 -> 381 | BI55: =SUM(BE55:BH55) -> 1396 | BJ55: =SUM(CF!AV11:AV14) -> 401 | BK55: =SUM(CF!AW11:AW14) -> 455 | BL55: =SUM(CF!AX11:AX14) -> 492 | BM55: =SUM(CF!AY11:AY14) -> 503 | BN55: =SUM(BJ55:BM55) -> 1851 | BO55: 511 | BP55: 670 | BQ55: 828 | BR55: 953 | BS55: 2962 | BT55: =SUM(CF!BA11:BA14) -> 511 | BU55: =SUM(CF!BB11:BB14) -> 670 | BV55: =SUM(CF!BC11:BC14) -> 828 | BW55: =SUM(CF!BD11:BD14) -> 953 | BX55: =SUM(BT55:BW55) -> 2962 | BY55: 899 | BZ55: 1030 | CA55: 974 | CB55: 1036 | CC55: 3939 | CD55: =SUM(CF!BF11:BF14) -> 899 | CE55: =SUM(CF!BG11:BG14) -> 1030 | CF55: =SUM(CF!BH11:BH14) -> 974 | CG55: =SUM(CF!BI11:BI14) -> 1036 | CH55: =SUM(CD55:CG55) -> 3939 | CI55: =SUM(CF!BK11:BK14) -> 1086 | CJ55: =SUM(CF!BL11:BL14) -> 1079 | CK55: =SUM(CF!BM11:BM14) -> 1547 | CL55: =SUM(CF!BN11:BN14) -> 1267 | CM55: =SUM(CI55:CL55) -> 4979 | CN55: =SUM(CF!BP11:BP14) -> 1177 | CO55: =SUM(CF!BQ11:BQ14) -> 1234 | CP55: =SUM(CF!BR11:BR14) -> 1248 | CQ55: =SUM(CF!BS11:BS14) -> 1404 | CR55: =SUM(CN55:CQ55) -> 5063 | CS55: =SUM(CF!BU11:BU14) -> 1371 | CT55: =SUM(CF!BV11:BV14) -> 1490 | CU55: =SUM(CF!BW11:BW14) -> 1596 | CV55: =SUM(CF!BX11:BX14) -> 1687 | CW55: =SUM(CS55:CV55) -> 6144 | CX55: =SUM(CF!BZ11:BZ14) -> 1503 | CY55: =SUM(CF!CA11:CA14) -> 1625 | CZ55: =SUM(CF!CB11:CB14) -> 1761 | DA55: =SUM(CF!CC11:CC14) -> 2026 | DB55: =SUM(CX55:DA55) -> 6915 | DC55: =SUM(CF!CE11:CE14) -> 1986 | DD55: =SUM(CF!CF11:CF14) -> 2114 | DE55: =SUM(CF!CG11:CG14) -> 2355 | DF55: =SUM(CF!CH11:CH14) -> 2580 | DG55: =SUM(DC55:DF55) -> 9035 | DH55: =SUM(CF!CJ11:CJ14) -> 2613 | DI55: =SUM(CF!CK11:CK14) -> 2835 | DJ55: =SUM(CF!CL11:CL14) -> 2920 | DK55: =SUM(CF!CM11:CM14) -> 3413 | DL55: =SUM(DH55:DK55) -> 11781 | DM55: =SUM(CF!CO11:CO14) -> 3108 | DN55: =SUM(CF!CP11:CP14) -> 3386 | DO55: =SUM(CF!CQ11:CQ14) -> 3478 | DP55: =SUM(CF!CR11:CR14) -> 3725 | DQ55: =SUM(DM55:DP55) -> 13697 | DR55: =SUM(CF!CT11,CF!CT13) -> 2753 | DS55: =SUM(CF!CU11,CF!CU13) -> 2945 | DT55: =SUM(CF!CV11,CF!CV13) -> 3304 | DU55: =SUM(CF!CW11,CF!CW13) -> 3439 | DV55: =SUM(CF!CX11,CF!CX13) -> 12441 | DW55: =SUM(CF!CY11,CF!CY13) -> 3782 | DX55: =SUM(CF!CZ11,CF!CZ13) -> 3899 | DY55: =SUM(CF!DA11,CF!DA13) -> 4046 | ... EY55: =SUM(CF!EA11,CF!EA13) -> 66276.088 | FA55: =(EA55/DL55)^(1/3)-1 -> 0.105757 | FB55: =(EF55/DQ55)^(1/3)-1 -> 4.867009e-05 | FC55: =(EK55/DV55)^(1/3)-1 -> 0.07164125 | FD55: =(EP55/EA55)^(1/3)-1 -> 0.10562731 | FE55: =(EU55/EF55)^(1/3)-1 -> 0.39082887 | FF55: =(EV55/EK55)^(1/3)-1 -> 0.49011023 | FG55: =(EK55/DL55)^(1/5)-1 -> 0.053814767 | FH55: =(EP55/DQ55)^(1/5)-1 -> 0.094642767 | FI55: =(EU55/DV55)^(1/5)-1 -> 0.24259881 | FJ55: =(EV55/EA55)^(1/5)-1 -> 0.26037418 | FK55: =(EW55/EF55)^(1/5)-1 -> 0.33027401 | FL55: =(EX55/EK55)^(1/5)-1 -> 0.3215718
A56: Stock compensation expense | P56: =P24 -> 12.383 | Q56: =Q24 -> 3.774 | R56: =R24 -> 3.735 | S56: =S24 -> 6.182 | T56: =T24 -> 7.944 | U56: =SUM(Q56:T56) -> 21.635 | V56: =V24 -> 36.418 | W56: =W24 -> 34.165 | X56: =X24 -> 73.794 | Y56: =Y24 -> 84.984 | Z56: =SUM(V56:Y56) -> 229.361 | AA56: =AA24 -> 76.473 | AB56: =AB24 -> 74.761 | AC56: =AC24 -> 67.981 | AD56: =AD24 -> 59.531 | AE56: =SUM(AA56:AD56) -> 278.746 | AF56: =AF24 -> 48.908 | AG56: =AG24 -> 47.338 | AH56: =AH24 -> 46.308 | AI56: =AI24 -> 58.154 | AJ56: =SUM(AF56:AI56) -> 200.708 | AK56: =AK24 -> 114.664 | AL56: =AL24 -> 109.149 | AM56: =AM24 -> 99.86 | AN56: =AN24 -> 134.427 | AO56: =SUM(AK56:AN56) -> 458.1 | AP56: =AP24 -> 183.866 | AQ56: =AQ24 -> 241.524 | AR56: =AR24 -> 197.956 | AS56: =AS24 -> 245.3 | AT56: =SUM(AP56:AS56) -> 868.646 | AU56: =AU24 -> 280.779 | AV56: =AV24 -> 272.776 | AW56: =AW24 -> 280.039 | AX56: 286.172 | AY56: =AY24 -> 1119.766 | AZ56: =AZ24 -> 277.483 | BA56: =BA24 -> 293.07 | BB56: =BB24 -> 317.527 | BC56: =BC24 -> 275.974 | BD56: =SUM(AZ56:BC56) -> 1164.054 | BE56: =BE24 -> 291 | BF56: =BF24 -> 309 | BG56: =BG24 -> 380 | BH56: =BH24 -> 396 | BI56: =SUM(BE56:BH56) -> 1376 | BJ56: =BJ24 -> 432 | BK56: =BK24 -> 435 | BL56: =BL24 -> 571 | BM56: =BM24 -> 536 | BN56: =SUM(BJ56:BM56) -> 1974 | BO56: 556 | BP56: 747 | BQ56: 1064 | BR56: 878 | BS56: 3245 | BT56: =BT24 -> 556 | BU56: =BU24 -> 552 | BV56: =BV24 -> 688 | BW56: =BW24 -> 677 | BX56: =SUM(BT56:BW56) -> 2473 | BY56: 593 | BZ56: 783 | CA56: 886 | CB56: 917 | CC56: 3179 | CD56: =CD24 -> 655 | CE56: =CE24 -> 743 | CF56: =CF24 -> 856 | CG56: =CG24 -> 873 | CH56: =SUM(CD56:CG56) -> 3127 | CI56: =CI24 -> 839 | CJ56: =CJ24 -> 880 | CK56: =CK24 -> 1255 | CL56: =CL24 -> 1201 | CM56: =SUM(CI56:CL56) -> 4175 | CN56: =CN24 -> 1203 | CO56: =CO24 -> 1132 | CP56: =CP24 -> 1432 | CQ56: =CQ24 -> 1436 | CR56: =SUM(CN56:CQ56) -> 5203 | CS56: =CS24 -> 1494 | CT56: =CT24 -> 1503 | CU56: =CU24 -> 1860 | CV56: =CV24 -> 1846 | CW56: =SUM(CS56:CV56) -> 6703 | CX56: =CX24 -> 2009 | CY56: =CY24 -> 2003 | CZ56: =CZ24 -> 1820 | DA56: =DA24 -> 1847 | DB56: =SUM(CX56:DA56) -> 7679 | DC56: =DC24 -> 2457 | DD56: =DD24 -> 2413 | DE56: =DE24 -> 2230 | DF56: =DF24 -> 2253 | DG56: =SUM(DC56:DF56) -> 9353 | DH56: =DH24 -> 2769 | DI56: =DI24 -> 2756 | DJ56: =DJ24 -> 2624 | DK56: =DK24 -> 2645 | DL56: =SUM(DH56:DK56) -> 10794 | DM56: =DM24 -> 3191 | DN56: =DN24 -> 3382 | DO56: =DO24 -> 3195 | DP56: =DP24 -> 3223 | DQ56: =SUM(DM56:DP56) -> 12991 | DR56: =DR24 -> 3745 | DS56: =DS24 -> 3803 | DT56: =DT24 -> 3874 | DU56: =DU24 -> 3954 | DV56: =SUM(DR56:DU56) -> 15376 | DW56: =DW24 -> 4504 | DX56: =DX24 -> 4782 | DY56: =DY24 -> 4976 | DZ56: =DZ24 -> 5100 | EA56: =SUM(DW56:DZ56) -> 19362 | EB56: =EB24 -> 5284 | EC56: =EC24 -> 5774 | ED56: =ED24 -> 5743 | EE56: =EE24 -> 5659 | EF56: =SUM(EB56:EE56) -> 22460 | EG56: =EG24 -> 5264 | EH56: =EH24 -> 5865 | EI56: =EI24 -> 5846 | EJ56: =EJ24 -> 5810 | EK56: =SUM(EG56:EJ56) -> 22785 | EL56: =EL24 -> 5516 | EM56: =EM24 -> 5998 | EN56: =EN24 -> 6368 | EO56: =EO24 -> 6527.1865 | EP56: =SUM(EL56:EO56) -> 24409.187 | EQ56: =EQ24 -> 6452.4608 | ER56: =ER24 -> 7098.6445 | ES56: =ES24 -> 7478.2179 | ET56: =ET24 -> 7452.3734 | EU56: =SUM(EQ56:ET56) -> 28481.697 | EV56: =EV24 -> 30856.088 | EW56: =EW24 -> 33307.093 | EX56: =EX24 -> 35765.58 | EY56: =EY24 -> 38299.932 | FA56: =(EA56/DL56)^(1/3)-1 -> 0.21503634 | FB56: =(EF56/DQ56)^(1/3)-1 -> 0.20020581 | FC56: =(EK56/DV56)^(1/3)-1 -> 0.14007972 | FD56: =(EP56/EA56)^(1/3)-1 -> 0.080275094 | FE56: =(EU56/EF56)^(1/3)-1 -> 0.082393979 | FF56: =(EV56/EK56)^(1/3)-1 -> 0.10636206 | FG56: =(EK56/DL56)^(1/5)-1 -> 0.16116336 | FH56: =(EP56/DQ56)^(1/5)-1 -> 0.1344416 | FI56: =(EU56/DV56)^(1/5)-1 -> 0.13121329 | FJ56: =(EV56/EA56)^(1/5)-1 -> 0.097686009 | FK56: =(EW56/EF56)^(1/5)-1 -> 0.081995355 | FL56: =(EX56/EK56)^(1/5)-1 -> 0.094367656
A57: Adj. EBITDA | P57: =SUM(P54:P56) -> 37.529 | Q57: =SUM(Q54:Q56) -> 18.981 | R57: =SUM(R54:R56) -> 34.832 | S57: =SUM(S54:S56) -> 63.095 | T57: =SUM(T54:T56) -> 91.193 | U57: =SUM(U54:U56) -> 237.084 | V57: =SUM(V54:V56) -> 131.818 | W57: =SUM(W54:W56) -> 150.986 | ... AD57: =SUM(AD54:AD56) -> 425.184 | AE57: =SUM(AA57:AD57) -> 1279.755 | AF57: =SUM(AF54:AF56) -> 547.871 | AG57: =SUM(AG54:AG56) -> 589.965 | AH57: =SUM(AH54:AH56) -> 672.257 | AI57: =SUM(AI54:AI56) -> 813.747 | AJ57: =SUM(AF57:AI57) -> 2623.84 | AK57: =SUM(AK54:AK56) -> 1002.521 | AL57: =SUM(AL54:AL56) -> 1050.742 | AM57: =SUM(AM54:AM56) -> 1183.301 | AN57: =SUM(AN54:AN56) -> 1384.271 | AO57: =SUM(AO54:AO56) -> 4620.835 | AP57: =SUM(AP54:AP56) -> 1610.0672 | AQ57: =SUM(AQ54:AQ56) -> 1573.1538 | AR57: =SUM(AR54:AR56) -> 1761.508 | ... BN57: =SUM(BN54:BN56) -> 16067 | BO57: 4456 | BP57: 4620 | BQ57: 4628 | BR57: 5225 | BS57: 18929 | BT57: =SUM(BT54:BT56) -> 4456 | BU57: =SUM(BU54:BU56) -> 4658 | BV57: =SUM(BV54:BV56) -> 4779 | BW57: =SUM(BW54:BW56) -> 5377 | BX57: =SUM(BX54:BX56) -> 19270 | BY57: 4969 | BZ57: 4936 | CA57: 5304 | CB57: 5875 | CC57: 21084 | CD57: =SUM(CD54:CD56) -> 5302 | CE57: =SUM(CE54:CE56) -> 5238 | CF57: =SUM(CF54:CF56) -> 5591 | CG57: =SUM(CG54:CG56) -> 6338 | CH57: =SUM(CH54:CH56) -> 22469 | CI57: =SUM(CI54:CI56) -> 6040 | CJ57: =SUM(CJ54:CJ56) -> 6217 | CK57: =SUM(CK54:CK56) -> 6526 | ... EY57: =SUM(EY54:EY56) -> 365219.48 | FA57: =(EA57/DL57)^(1/3)-1 -> 0.23474837 | FB57: =(EF57/DQ57)^(1/3)-1 -> 0.21047502 | FC57: =(EK57/DV57)^(1/3)-1 -> 0.12203576 | FD57: =(EP57/EA57)^(1/3)-1 -> 0.17757641 | FE57: =(EU57/EF57)^(1/3)-1 -> 0.2317239 | FF57: =(EV57/EK57)^(1/3)-1 -> 0.200253 | FG57: =(EK57/DL57)^(1/5)-1 -> 0.2079907 | FH57: =(EP57/DQ57)^(1/5)-1 -> 0.2150296 | FI57: =(EU57/DV57)^(1/5)-1 -> 0.16138342 | FJ57: =(EV57/EA57)^(1/5)-1 -> 0.18762736 | FK57: =(EW57/EF57)^(1/5)-1 -> 0.19517503 | FL57: =(EX57/EK57)^(1/5)-1 -> 0.16838283
BY58: 3/13A | BZ58: 6/13A | CA58: 9/13A | CB58: 12/13A | CC58: 2013A
A59: Year/Year Growth | B59: =B6 -> 3/99A | C59: =C6 -> 6/99A | D59: =D6 -> 9/99A | E59: =E6 -> 12/99A | F59: =F6 -> 1999A | G59: =G6 -> 3/00A | H59: =H6 -> 6/00A | I59: =I6 -> 9/00A | ... EY59: =EY6 -> 2030E
A60: Gross Revenues (FXHN) | CD60: ='Revenue Drivers'!CD226 -> 0.22794118 | CE60: ='Revenue Drivers'!CE226 -> 0.22107875 | CF60: ='Revenue Drivers'!CF226 -> 0.2096127 | CG60: ='Revenue Drivers'!CG226 -> 0.23134908 | CH60: ='Revenue Drivers'!CH226 -> 0.22268293 | CI60: ='Revenue Drivers'!CI226 -> 0.20586869 | CJ60: ='Revenue Drivers'!CJ226 -> 0.21090881 | CK60: ='Revenue Drivers'!CK226 -> 0.19480047 | ... EY60: ='Revenue Drivers'!EY226 -> 0.099288857
A61: Gross Revenues | K61: =K7/F7-1 -> 85.854545 | P61: =P7/K7-1 -> 3.523027 | U61: =U7/P7-1 -> 4.0853678 | V61: =V7/Q7-1 -> 4.879579 | W61: =W7/R7-1 -> 2.9630564 | X61: =X7/S7-1 -> 2.0120884 | Y61: =Y7/T7-1 -> 1.7256254 | Z61: =Z7/U7-1 -> 2.3353978 | AA61: =AA7/V7-1 -> 1.6209808 | AB61: =AB7/W7-1 -> 1.2500458 | ... BN61: =BN7/BI7-1 -> 0.29275946 | BO61: 0.24139942 | BP61: 0.35320186 | BQ61: 0.45072016 | BR61: 0.36233938 | BS61: 0.35546762 | BT61: =BT7/BJ7-1 -> 0.24139942 | BU61: =BU7/BK7-1 -> 0.21471305 | BV61: =BV7/BL7-1 -> 0.18580247 | BW61: =BW7/BM7-1 -> 0.21929327 | BX61: =BX7/BN7-1 -> 0.2145891 | BY61: 0.31225928 | BZ61: 0.15482234 | CA61: 0.056166229 | CB61: 0.16915181 | CC61: 0.16259561 | CD61: =CD7/BT7-1 -> 0.21662752 | CE61: =CE7/BU7-1 -> 0.19545786 | CF61: =CF7/BV7-1 -> 0.1933021 | CG61: =CG7/BW7-1 -> 0.21712515 | CH61: =CH7/BX7-1 -> 0.20591238 | CI61: =CI7/CD7-1 -> 0.19064165 | CJ61: =CJ7/CE7-1 -> 0.21728847 | CK61: =CK7/CF7-1 -> 0.20132325 | CL61: =CL7/CG7-1 -> 0.15254345 | CM61: =CM7/CH7-1 -> 0.18880023 | CN61: =CN7/CI7-1 -> 0.11919585 | CO61: =CO7/CJ7-1 -> 0.11106236 | CP61: =CP7/CK7-1 -> 0.13024269 | ... EU61: =EU7/EP7-1 -> 0.16709431 | EV61: =EV7/EU7-1 -> 0.13331977 | EW61: =EW7/EV7-1 -> 0.11961968 | EX61: =EX7/EW7-1 -> 0.10580532 | EY61: =EY7/EX7-1 -> 0.099288857
A62: Traffic Acquisition Costs (TAC) | V62: =V8/Q8-1 -> #DIV/0! | W62: =W8/R8-1 -> 5.8970714 | X62: =X8/S8-1 -> 3.9478276 | Y62: =Y8/T8-1 -> 3.2010874 | Z62: =Z8/U8-1 -> 4.5717778 | AA62: =AA8/V8-1 -> 2.8642255 | AB62: =AB8/W8-1 -> 1.8690645 | AC62: =AC8/X8-1 -> 1.1109926 | ... BN62: =BN8/BI8-1 -> 0.20377204 | BO62: 0.23159961 | BP62: 0.23222749 | BQ62: 0.25339367 | BR62: 0.25714286 | BS62: 0.24432334 | BT62: =BT8/BJ8-1 -> 0.23159961 | BU62: =BU8/BK8-1 -> 0.23222749 | BV62: =BV8/BL8-1 -> 0.25339367 | BW62: =BW8/BM8-1 -> 0.25714286 | BX62: =BX8/BN8-1 -> 0.24386921 | BY62: 0.18007968 | BZ62: 0.15884615 | CA62: 0.072924188 | CB62: 0.074675325 | CC62: 0.11833942 | CD62: =CD8/BT8-1 -> 0.18007968 | CE62: =CE8/BU8-1 -> 0.15884615 | CF62: =CF8/BV8-1 -> 0.072924188 | CG62: =CG8/BW8-1 -> 0.074675325 | CH62: =CH8/BX8-1 -> 0.11883899 | CI62: =CI8/CD8-1 -> 0.091154625 | CJ62: =CJ8/CE8-1 -> 0.092930634 | CK62: =CK8/CF8-1 -> 0.12651413 | CL62: =CL8/CG8-1 -> 0.093655589 | CM62: =CM8/CH8-1 -> 0.10107685 | CN62: =CN8/CI8-1 -> 0.034962871 | CO62: =CO8/CJ8-1 -> 0.025508655 | CP62: =CP8/CK8-1 -> 0.065113501 | ... EU62: =EU8/EP8-1 -> 0.091978411 | EV62: =EV8/EU8-1 -> 0.078822997 | EW62: =EW8/EV8-1 -> 0.074404389 | EX62: =EX8/EW8-1 -> 0.063772615 | EY62: =EY8/EX8-1 -> 0.060279672
A63: Net Revenues | K63: =K9/F9-1 -> 85.854545 | P63: =P9/K9-1 -> 3.523027 | U63: =U9/P9-1 -> 2.9919469 | V63: =V9/Q9-1 -> 3.2210477 | W63: =W9/R9-1 -> 2.3264626 | X63: =X9/S9-1 -> 1.4605794 | Y63: =Y9/T9-1 -> 1.1685861 | Z63: =Z9/U9-1 -> 1.7228383 | AA63: =AA9/V9-1 -> 1.1324858 | AB63: =AB9/W9-1 -> 0.971571 | ... BN63: =BN9/BI9-1 -> 0.32235048 | BO63: 0.24445464 | BP63: 0.39010989 | BQ63: 0.50878828 | BR63: 0.39402508 | BS63: 0.38911228 | BT63: =BT9/BJ9-1 -> 0.24445464 | BU63: =BU9/BK9-1 -> 0.20936958 | BV63: =BV9/BL9-1 -> 0.16591212 | BW63: =BW9/BM9-1 -> 0.2078928 | BX63: =BX9/BN9-1 -> 0.20572568 | BY63: 0.35304241 | BZ63: 0.15373414 | CA63: 0.052069544 | CB63: 0.19481436 | CC63: 0.17687226 | CD63: =CD9/BT9-1 -> 0.22790412 | CE63: =CE9/BU9-1 -> 0.20683883 | CF63: =CF9/BV9-1 -> 0.23138419 | CG63: =CG9/BW9-1 -> 0.26178117 | CH63: =CH9/BX9-1 -> 0.23310435 | CI63: =CI9/CD9-1 -> 0.22014216 | CJ63: =CJ9/CE9-1 -> 0.25440856 | CK63: =CK9/CF9-1 -> 0.22194398 | CL63: =CL9/CG9-1 -> 0.16826652 | CM63: =CM9/CH9-1 -> 0.21365664 | CN63: =CN9/CI9-1 -> 0.14153266 | CO63: =CO9/CJ9-1 -> 0.13331227 | CP63: =CP9/CK9-1 -> 0.14679317 | ... EU63: =EU9/EP9-1 -> 0.18019465 | EV63: =EV9/EU9-1 -> 0.14211368 | EW63: =EW9/EV9-1 -> 0.12651155 | EX63: =EX9/EW9-1 -> 0.11191575 | EY63: =EY9/EX9-1 -> 0.10471421
A64: Other cost of revenues | BY64: =+#REF!/#REF!-1 -> #REF! | BZ64: =+#REF!/#REF!-1 -> #REF! | CA64: =+#REF!/#REF!-1 -> #REF! | CB64: =+#REF!/#REF!-1 -> #REF! | CC64: =+#REF!/#REF!-1 -> #REF! | CI64: =CI12/CD12-1 -> 0.25528979 | CJ64: =CJ12/CE12-1 -> 0.2928506 | CK64: =CK12/CF12-1 -> 0.37340993 | CL64: =CL12/CG12-1 -> 0.12164458 | CM64: =CM12/CH12-1 -> 0.25259373 | CN64: =CN12/CI12-1 -> 0.10333455 | CO64: =CO12/CJ12-1 -> 0.13647643 | CP64: =CP12/CK12-1 -> 0.037048103 | ... EU64: =EU12/EP12-1 -> 0.22573393 | EV64: =EV12/EU12-1 -> 0.20456834 | EW64: =EW12/EV12-1 -> 0.15019198 | EX64: =EX12/EW12-1 -> 0.11845643 | EY64: =EY12/EX12-1 -> 0.10148405
A65: Gross profit | V65: =V13/Q13-1 -> 3.4113082 | W65: =W13/R13-1 -> 2.3345607 | X65: =X13/S13-1 -> 1.4521691 | Y65: =Y13/T13-1 -> 1.1397209 | Z65: =Z13/U13-1 -> 1.7275502 | AA65: =AA13/V13-1 -> 1.0828816 | AB65: =AB13/W13-1 -> 0.92899308 | AC65: =AC13/X13-1 -> 0.98516676 | ... BN65: =BN13/BI13-1 -> 0.31600864 | BO65: 0.21835443 | BP65: 0.23556308 | BQ65: 0.20689118 | BR65: 0.20376491 | BS65: 0.21541296 | BT65: =BT13/BJ13-1 -> 0.21835443 | BU65: =BU13/BK13-1 -> 0.19593565 | BV65: =BV13/BL13-1 -> 0.12082944 | BW65: =BW13/BM13-1 -> 0.15576951 | BX65: =BX13/BN13-1 -> 0.15609229 | BY65: 0.15800866 | BZ65: 0.11800987 | CA65: 0.11316367 | CB65: 0.14468187 | CC65: 0.13327182 | CD65: =CD13/BT13-1 -> 0.12770563 | CE65: =CE13/BU13-1 -> 0.1203625 | CF65: =CF13/BV13-1 -> 0.16080122 | CG65: =CG13/BW13-1 -> 0.17543205 | CH65: =CH13/BX13-1 -> 0.16155632 | CI65: =CI13/CD13-1 -> 0.21036468 | CJ65: =CJ13/CE13-1 -> 0.24380688 | CK65: =CK13/CF13-1 -> 0.1777112 | CL65: =CL13/CG13-1 -> 0.18277978 | CM65: =CM13/CH13-1 -> 0.20235041 | CN65: =CN13/CI13-1 -> 0.15255312 | CO65: =CO13/CJ13-1 -> 0.13240524 | CP65: =CP13/CK13-1 -> 0.18416768 | ... EU65: =EU13/EP13-1 -> 0.16030354 | EV65: =EV13/EU13-1 -> 0.11329577 | EW65: =EW13/EV13-1 -> 0.11468909 | EX65: =EX13/EW13-1 -> 0.10854631 | EY65: =EY13/EX13-1 -> 0.1063931
A66: Research & development | BO66: 0.15470172 | BP66: 0.29787234 | BQ66: 0.39707228 | BR66: 0.44089147 | BS66: 0.3257742 | BY66: 0.29246935 | BZ66: 0.22248244 | CA66: 0.024230517 | CB66: 0.10423672 | CC66: 0.14916314 | CI66: =CI17/CD17-1 -> 0.31478046 | CJ66: =CJ17/CE17-1 -> 0.26727067 | CK66: =CK17/CF17-1 -> 0.45799012 | CL66: =CL17/CG17-1 -> 0.45525091 | CM66: =CM17/CH17-1 -> 0.37760964 | CN66: =CN17/CI17-1 -> 0.29492004 | CO66: =CO17/CJ17-1 -> 0.24620197 | CP66: =CP17/CK17-1 -> 0.2165725 | ... EU66: =EU17/EP17-1 -> 0.19150197 | EV66: =EV17/EU17-1 -> 0.12126843 | EW66: =EW17/EV17-1 -> 0.093182809 | EX66: =EX17/EW17-1 -> 0.084795852 | EY66: =EY17/EX17-1 -> 0.077096353
A67: Sales & marketing | BO67: 0.23628692 | BP67: 0.27236971 | BQ67: 0.38272727 | BR67: 0.38521066 | BS67: 0.32403027 | BY67: 0.24658703 | BZ67: 0.23724884 | CA67: 0.082182774 | CB67: 0.22284295 | CC67: 0.19292605 | CI67: =CI20/CD20-1 -> 0.20487805 | CJ67: =CJ20/CE20-1 -> 0.22615287 | CK67: =CK20/CF20-1 -> 0.28009828 | CL67: =CL20/CG20-1 -> 0.24580713 | CM67: =CM20/CH20-1 -> 0.24061642 | CN67: =CN20/CI20-1 -> 0.19433198 | CO67: =CO20/CJ20-1 -> 0.071612571 | CP67: =CP20/CK20-1 -> 0.066698656 | ... EU67: =EU20/EP20-1 -> 0.065923557 | EV67: =EV20/EU20-1 -> 0.077789732 | EW67: =EW20/EV20-1 -> 0.062139465 | EX67: =EX20/EW20-1 -> 0.061374123 | EY67: =EY20/EX20-1 -> 0.052108769
A68: General & administrative | BO68: 0.28298279 | BP68: 0.31794872 | BQ68: 0.50844595 | BR68: 0.39667129 | BS68: 0.38042131 | BY68: 0.5171386 | BZ68: 0.40596628 | CA68: 0.20604703 | CB68: 0.13008937 | CC68: 0.29174147 | CI68: =CI23/CD23-1 -> 0.46699507 | CJ68: =CJ23/CE23-1 -> 0.27868852 | CK68: =CK23/CF23-1 -> 0.20264317 | CL68: =CL23/CG23-1 -> 0.34543919 | CM68: =CM23/CH23-1 -> 0.32017148 | CN68: =CN23/CI23-1 -> 0.099395567 | CO68: =CO23/CJ23-1 -> 0.032763533 | CP68: =CP23/CK23-1 -> 0.082051282 | ... EU68: =EU23/EP23-1 -> -0.041864762 | EV68: =EV23/EU23-1 -> 0.093693009 | EW68: =EW23/EV23-1 -> 0.070185976 | EX68: =EX23/EW23-1 -> 0.053393866 | EY68: =EY23/EX23-1 -> 0.043341196
A69: Total operating expenses | K69: =K26/F26-1 -> 3.7638984 | P69: =P26/K26-1 -> 1.2055179 | U69: =U26/P26-1 -> 0.98471437 | V69: =V26/Q26-1 -> 2.5872533 | W69: =W26/R26-1 -> 2.2942526 | X69: =X26/S26-1 -> 3.5835572 | Y69: =Y26/T26-1 -> 3.4989839 | Z69: =Z26/U26-1 -> 3.0945265 | AA69: =AA26/V26-1 -> 1.3580432 | AB69: =AB26/W26-1 -> 1.2791583 | ... BN69: =BN26/BI26-1 -> 0.48142974 | BO69: 0.22441217 | BP69: 0.35350529 | BQ69: 0.49135876 | BR69: 0.44351101 | BS69: 0.38494184 | BT69: =BT26/BJ26-1 -> 0.22441217 | BU69: =BU26/BK26-1 -> 0.19907407 | BV69: =BV26/BL26-1 -> 0.16984505 | BW69: =BW26/BM26-1 -> 0.24449594 | BX69: =BX26/BN26-1 -> 0.18115373 | BY69: 0.28438294 | BZ69: 0.22990472 | CA69: 0.033566434 | CB69: 0.13726671 | CC69: 0.15889229 | CD69: =CD26/BT26-1 -> 0.14854561 | CE69: =CE26/BU26-1 -> 0.2264203 | CF69: =CF26/BV26-1 -> 0.16760061 | CG69: =CG26/BW26-1 -> 0.16969274 | CH69: =CH26/BX26-1 -> 0.20586865 | CI69: =CI26/CD26-1 -> 0.31399066 | CJ69: =CJ26/CE26-1 -> 0.25545311 | CK69: =CK26/CF26-1 -> 0.33158813 | CL69: =CL26/CG26-1 -> 0.34985075 | CM69: =CM26/CH26-1 -> 0.31402086 | CN69: =CN26/CI26-1 -> 0.20789671 | CO69: =CO26/CJ26-1 -> 0.13182877 | CP69: =CP26/CK26-1 -> 0.1353211 | ... CX69: =CX26/CS26-1 -> 0.15412137 | CY69: =(CY26-CY25)/CT26-1 -> 0.18467982 | CZ69: =CZ26/CU26-1 -> 0.10732624 | DA69: =DA26/CV26-1 -> 0.18575993 | DB69: =DB26/CW26-1 -> 0.24533707 | DC69: =DC26/CX26-1 -> 0.19780613 | DD69: =DD26/CY26-1 -> 0.36714472 | DE69: =DE26/CZ26-1 -> 0.2252884 | DF69: =DF26/DA26-1 -> 0.2641455 | DG69: =DG26/DB26-1 -> 0.27143076 | ... EU69: =EU26/EP26-1 -> 0.082094992 | EV69: =EV26/EU26-1 -> 0.10607528 | EW69: =EW26/EV26-1 -> 0.08209712 | EX69: =EX26/EW26-1 -> 0.074575294 | EY69: =EY26/EX26-1 -> 0.066326455
A70: Total operating expense ex. SBC | CM70: =(SUM(CM12,CM17,CM20,CM23)-CM24)/(SUM(CH12,CH17,CH20,CH23)-CH24)-1 -> 0.28716995 | CN70: =(SUM(CN12,CN17,CN20,CN23)-CN24)/(SUM(CI12,CI17,CI20,CI23)-CI24)-1 -> 0.14224495 | CO70: =(SUM(CO12,CO17,CO20,CO23)-CO24)/(SUM(CJ12,CJ17,CJ20,CJ23)-CJ24)-1 -> 0.11549708 | CP70: =(SUM(CP12,CP17,CP20,CP23)-CP24)/(SUM(CK12,CK17,CK20,CK23)-CK24)-1 -> 0.0943143 | CQ70: =(SUM(CQ12,CQ17,CQ20,CQ23)-CQ24)/(SUM(CL12,CL17,CL20,CL23)-CL24)-1 -> 0.17730496 | CR70: =(SUM(CR12,CR17,CR20,CR23)-CR24)/(SUM(CM12,CM17,CM20,CM23)-CM24)-1 -> 0.13350925 | CS70: =(SUM(CS12,CS17,CS20,CS23)-CS24)/(SUM(CN12,CN17,CN20,CN23)-CN24)-1 -> 0.16579935 | CT70: =(SUM(CT12,CT17,CT20,CT23)-CT24)/(SUM(CO12,CO17,CO20,CO23)-CO24)-1 -> 0.19790301 | ... EU70: =(SUM(EU12,EU17,EU20,EU23)-EU24)/(SUM(EP12,EP17,EP20,EP23)-EP24)-1 -> 0.17258365 | EV70: =(SUM(EV12,EV17,EV20,EV23)-EV24)/(SUM(EU12,EU17,EU20,EU23)-EU24)-1 -> 0.1674073 | EW70: =(SUM(EW12,EW17,EW20,EW23)-EW24)/(SUM(EV12,EV17,EV20,EV23)-EV24)-1 -> 0.12403116 | EX70: =(SUM(EX12,EX17,EX20,EX23)-EX24)/(SUM(EW12,EW17,EW20,EW23)-EW24)-1 -> 0.10210112 | EY70: =(SUM(EY12,EY17,EY20,EY23)-EY24)/(SUM(EX12,EX17,EX20,EX23)-EX24)-1 -> 0.088112751
A71: GAAP Operating income | K71: =K27/F27-1 -> 1.2616636 | P71: =P27/K27-1 -> -1.7439777 | U71: =U27/P27-1 -> 16.007114 | V71: =V27/Q27-1 -> 4.5701979 | W71: =W27/R27-1 -> 2.3695855 | X71: =X27/S27-1 -> 0.16943405 | Y71: =Y27/T27-1 -> 0.038066523 | Z71: =Z27/U27-1 -> 0.83660292 | AA71: =AA27/V27-1 -> 0.83367176 | AB71: =AB27/W27-1 -> 0.63152771 | ... BN71: =BN27/BI27-1 -> 0.17915623 | BO71: 0.2120887 | BP71: 0.11176675 | BQ71: -0.10529758 | BR71: -0.032221272 | BS71: 0.03920928 | BT71: =BT27/BJ27-1 -> 0.2120887 | BU71: =BU27/BK27-1 -> 0.19264144 | BV71: =BV27/BL27-1 -> 0.067037279 | BW71: =BW27/BM27-1 -> 0.068434559 | BX71: =BX27/BN27-1 -> 0.13004411 | BY71: 0.025966362 | BZ71: -0.024976584 | CA71: 0.25877193 | CB71: 0.15556865 | CC71: 0.097783367 | CD71: =CD27/BT27-1 -> 0.10593095 | CE71: =CE27/BU27-1 -> 0.0084400466 | CF71: =CF27/BV27-1 -> 0.15262029 | CG71: =CG27/BW27-1 -> 0.18201228 | CH71: =CH27/BX27-1 -> 0.11341622 | CI71: =CI27/CD27-1 -> 0.09791889 | CJ71: =CJ27/CE27-1 -> 0.22886003 | CK71: =CK27/CF27-1 -> -0.0098378091 | CL71: =CL27/CG27-1 -> -0.006773538 | CM71: =CM27/CH27-1 -> 0.070960203 | CN71: =CN27/CI27-1 -> 0.080680437 | CO71: =CO27/CJ27-1 -> 0.13316111 | CP71: =CP27/CK27-1 -> 0.26423201 | ... EU71: =EU27/EP27-1 -> 0.22466845 | EV71: =EV27/EU27-1 -> 0.11854637 | EW71: =EW27/EV27-1 -> 0.13812507 | EX71: =EX27/EW27-1 -> 0.13177139 | EY71: =EY27/EX27-1 -> 0.13240128
A72: Non-GAAP Operating income | CW72: =CW28/CR28-1 -> 0.225 | CX72: =CX28/CS28-1 -> 0.22950206 | CY72: =CY28/CT28-1 -> 0.15080429 | CZ72: =CZ28/CU28-1 -> 0.34940177 | DA72: =DA28/CV28-1 -> 0.15439072 | DB72: =DB28/CW28-1 -> 0.21782763 | DC72: =DC28/CX28-1 -> 0.16214982 | DD72: =DD28/CY28-1 -> 0.18171229 | ... EU72: =EU28/EP28-1 -> 0.22466845 | EV72: =EV28/EU28-1 -> 0.11854637 | EW72: =EW28/EV28-1 -> 0.13812507 | EX72: =EX28/EW28-1 -> 0.13177139 | EY72: =EY28/EX28-1 -> 0.13240128
A73: =A29 -> JPMe Adjusted Operating income | K73: =K29/F29-1 -> 0.87707182 | P73: =P29/K29-1 -> 1.080206 | U73: =U29/P29-1 -> -9.1791062 | V73: =V29/Q29-1 -> 5.3813287 | W73: =W29/R29-1 -> 2.9891192 | X73: =X29/S29-1 -> 1.2244235 | Y73: =Y29/T29-1 -> 0.87955216 | Z73: =Z29/U29-1 -> 1.7478244 | AA73: =AA29/V29-1 -> 0.91370827 | AB73: =AB29/W29-1 -> 0.76841143 | ... BN73: =BN29/BI29-1 -> 0.20904916 | BO73: 0.2120887 | BP73: 0.11176675 | BQ73: -0.10529758 | BR73: -0.032221272 | BS73: 0.03920928 | BT73: =BT29/BJ29-1 -> 0.22211896 | BU73: =BU29/BK29-1 -> 0.2026538 | BV73: =BV29/BL29-1 -> 0.088729678 | BW73: =BW29/BM29-1 -> 0.094236953 | BX73: =BX29/BN29-1 -> #REF! | BY73: 0.025966362 | BZ73: -0.024976584 | CA73: 0.25877193 | CB73: 0.15556865 | CC73: 0.097783367 | CD73: =CD29/BT29-1 -> 0.11609632 | CE73: =CE29/BU29-1 -> 0.076228686 | CF73: =CF29/BV29-1 -> 0.17160213 | CG73: =CG29/BW29-1 -> 0.19846293 | CH73: =CH29/BX29-1 -> #REF! | CI73: =CI29/CD29-1 -> 0.12514195 | CJ73: =CJ29/CE29-1 -> 0.1971109 | CK73: =CK29/CF29-1 -> 0.15726939 | CL73: =CL29/CG29-1 -> 0.056205206 | CM73: =CM29/CH29-1 -> 0.13008698 | CN73: =CN29/CI29-1 -> 0.14049253 | CO73: =CO29/CJ29-1 -> 0.15940054 | CP73: =CP29/CK29-1 -> 0.1461639 | ... EU73: =EU29/EP29-1 -> 0.18900978 | EV73: =EV29/EU29-1 -> 0.11322311 | EW73: =EW29/EV29-1 -> 0.12948257 | EX73: =EX29/EW29-1 -> 0.12361499 | EY73: =EY29/EX29-1 -> 0.12412459
A74: =A55 -> Depreciation & amortization | CI74: =CI55/CD55-1 -> 0.2080089 | CJ74: =CJ55/CE55-1 -> 0.047572816 | CK74: =CK55/CF55-1 -> 0.58829569 | CL74: =CL55/CG55-1 -> 0.22297297 | CM74: =CM55/CH55-1 -> 0.2640264 | CN74: =CN55/CI55-1 -> 0.083793738 | CO74: =CO55/CJ55-1 -> 0.14365153 | CP74: =CP55/CK55-1 -> -0.19327731 | ... EJ74: =EJ55/EE55-1 -> 0.26809409 | EK74: =EK55/(11946)-1 -> 0.28168425 | EL74: =EL55/EG55-1 -> 0.31467917 | EM74: =EM55/EH55-1 -> 0.34789644 | EN74: =EN55/EI55-1 -> 0.40803011 | EO74: =EO55/EJ55-1 -> 0.529417 | EP74: =EP55/EK55-1 -> 0.40599559 | EQ74: =EQ55/EL55-1 -> 0.68108259 | ER74: =ER55/EM55-1 -> 0.74164455 | ES74: =ES55/EN55-1 -> 0.72084507 | ... EU74: =EU55/EP55-1 -> 0.71207365 | EV74: =EV55/EU55-1 -> 0.37451278 | EW74: =EW55/EV55-1 -> 0.12651155 | EX74: =EX55/EW55-1 -> 0.081590773 | EY74: =EY55/EX55-1 -> 0.073740912
A75: Stock compensation expense | V75: =V24/Q24-1 -> 8.6497085 | W75: =W24/R24-1 -> 8.1472557 | X75: =X24/S24-1 -> 10.936914 | Y75: =Y24/T24-1 -> 9.6978852 | Z75: =Z24/U24-1 -> 9.6013866 | AA75: =AA24/V24-1 -> 1.0998682 | AB75: =AB24/W24-1 -> 1.1882336 | AC75: =AC24/X24-1 -> -0.078773342 | ... BN75: =BN24/BI24-1 -> 0.43459302 | BO75: 0.28298279 | BP75: 0.31794872 | BQ75: 0.50844595 | BR75: 0.39667129 | BS75: 0.38042131 | BT75: =BT24/BJ24-1 -> 0.28703704 | BU75: =BU24/BK24-1 -> 0.26896552 | BV75: =BV24/BL24-1 -> 0.20490368 | BW75: =BW24/BM24-1 -> 0.2630597 | BX75: =BX24/BN24-1 -> 0.25278622 | BY75: 0.5171386 | BZ75: 0.40596628 | CA75: 0.20604703 | CB75: 0.13008937 | CC75: 0.29174147 | CD75: =CD24/BT24-1 -> 0.17805755 | CE75: =CE24/BU24-1 -> 0.34601449 | CF75: =CF24/BV24-1 -> 0.24418605 | CG75: =CG24/BW24-1 -> 0.28951256 | CH75: =CH24/BX24-1 -> 0.26445613 | CI75: =CI24/CD24-1 -> 0.28091603 | CJ75: =CJ24/CE24-1 -> 0.18438762 | CK75: =CK24/CF24-1 -> 0.4661215 | CL75: =CL24/CG24-1 -> 0.37571592 | CM75: =CM24/CH24-1 -> 0.33514551 | CN75: =CN24/CI24-1 -> 0.43384982 | CO75: =CO24/CJ24-1 -> 0.28636364 | CP75: =CP24/CK24-1 -> 0.14103586 | ... EU75: =EU24/EP24-1 -> 0.16684333 | EV75: =EV24/EU24-1 -> 0.083365505 | EW75: =EW24/EV24-1 -> 0.079433459 | EX75: =EX24/EW24-1 -> 0.073812716 | EY75: =EY24/EX24-1 -> 0.070860063
A76: EBITDA | U76: =U57/P57-1 -> 5.3173546 | V76: =V57/Q57-1 -> 5.9447342 | W76: =W57/R57-1 -> 3.3346922 | X76: =X57/S57-1 -> 1.6375307 | Y76: =Y57/T57-1 -> 1.0755211 | Z76: =Z57/U57-1 -> 1.6931046 | AA76: =AA57/V57-1 -> 0.93805854 | AB76: =AB57/W57-1 -> 0.83911753 | ... BN76: =BN57/BI57-1 -> 0.22145355 | BO76: 0.22788647 | BP76: 0.22513922 | BQ76: 0.12302839 | BR76: 0.14936208 | BS76: 0.17812908 | BT76: =BT57/BJ57-1 -> 0.22788647 | BU76: =BU57/BK57-1 -> 0.23521612 | BV76: =BV57/BL57-1 -> 0.15966998 | BW76: =BW57/BM57-1 -> 0.18279806 | BX76: =BX57/BN57-1 -> 0.19935271 | BY76: 0.11512567 | BZ76: 0.068398268 | CA76: 0.14606742 | CB76: 0.12440191 | CC76: 0.11384648 | CD76: =CD57/BT57-1 -> 0.18985637 | CE76: =CE57/BU57-1 -> 0.12451696 | CF76: =CF57/BV57-1 -> 0.16991002 | CG76: =CG57/BW57-1 -> 0.1787242 | CH76: =CH57/BX57-1 -> 0.16600934 | CI76: =CI57/CD57-1 -> 0.13919276 | CJ76: =CJ57/CE57-1 -> 0.1869034 | CK76: =CK57/CF57-1 -> 0.16723305 | CL76: =CL57/CG57-1 -> 0.083464815 | CM76: =CM57/CH57-1 -> 0.14157283 | CN76: =CN57/CI57-1 -> 0.13029801 | CO76: =CO57/CJ57-1 -> 0.1566672 | CP76: =CP57/CK57-1 -> 0.13208704 | ... EU76: =EU57/EP57-1 -> 0.25162234 | EV76: =EV57/EU57-1 -> 0.15600679 | EW76: =EW57/EV57-1 -> 0.12890414 | EX76: =EX57/EW57-1 -> 0.11545063 | EY76: =EY57/EX57-1 -> 0.1146333
A77: GAAP Net Income (loss) | K77: =K36/F36-1 -> 1.417709 | P77: =P36/K36-1 -> -1.4754935 | U77: =U36/P36-1 -> 13.267144 | V77: =V36/Q36-1 -> 2.2551098 | W77: =W36/R36-1 -> 0.93864883 | X77: =X36/S36-1 -> -0.32603029 | Y77: =Y36/T36-1 -> -0.39205889 | Z77: =Z36/U36-1 -> 0.060126836 | AA77: =AA36/V36-1 -> 1.4795736 | AB77: =AB36/W36-1 -> 1.4578152 | ... BN77: =BN36/BI36-1 -> 0.14485597 | BO77: 0.58906916 | BP77: 0.095788441 | BQ77: -0.21669264 | BR77: 0.047882546 | BS77: 0.085810686 | BT77: =BT36/BJ36-1 -> 0.60734149 | BU77: =BU36/BK36-1 -> 0.20479042 | BV77: =BV36/BL36-1 -> -0.0095272994 | BW77: =BW36/BM36-1 -> 0.073937153 | BX77: =BX36/BN36-1 -> 0.10270104 | BY77: 0.13533909 | BZ77: 0.13322238 | CA77: 0.34106695 | CB77: 0.14911343 | CC77: 0.18021426 | CD77: =CD36/BT36-1 -> 0.15778547 | CE77: =CE36/BU36-1 -> 0.069582505 | CF77: =CF36/BV36-1 -> 0.098779134 | CG77: =CG36/BW36-1 -> 0.16213425 | CH77: =CH36/BX36-1 -> 0.20331564 | CI77: =CI36/CD36-1 -> 0.0073687986 | CJ77: =CJ36/CE36-1 -> 0.03849145 | CK77: =CK36/CF36-1 -> -0.077910438 | CL77: =CL36/CG36-1 -> 0.38466025 | CM77: =CM36/CH36-1 -> 0.11795666 | CN77: =CN36/CI36-1 -> 0.042596219 | CO77: =CO36/CJ36-1 -> 0.1726451 | CP77: =CP36/CK36-1 -> 0.45292897 | ... DB77: =DB36/CW36-1 -> -0.34993326 | DC77: =IF(AND(DC36>=0,CX36>0),DC36/CX36-1,"NA") -> 0.73258386 | DD77: =IF(AND(DD36>=0,CY36>0),DD36/CY36-1,"NA") -> -0.093359818 | DE77: =IF(AND(DE36>=0,CZ36>0),DE36/CZ36-1,"NA") -> 0.36541889 | DF77: =IF(AND(DF36>=0,DA36>0),DF36/DA36-1,"NA") -> NA | DG77: =IF(AND(DG36>=0,DB36>0),DG36/DB36-1,"NA") -> 1.4274206 | DH77: =IF(AND(DH36>=0,DC36>0),DH36/DC36-1,"NA") -> -0.29188384 | DI77: =IF(AND(DI36>=0,DD36>0),DI36/DD36-1,"NA") -> 2.113302 | DJ77: =IF(AND(DJ36>=0,DE36>0),DJ36/DE36-1,"NA") -> -0.2310705 | ... DU77: =IF(AND(DU36>=0,DP36>0),DU36/DP36-1,"NA") -> 0.35561831 | DV77: =DV36/DQ36-1 -> 0.88812734 | DW77: =IF(AND(DW36>=0,DR36>0),DW36/DR36-1,"NA") -> -0.083324038 | DX77: =IF(AND(DX36>=0,DS36>0),DX36/DS36-1,"NA") -> -0.13619433 | DY77: =IF(AND(DY36>=0,DT36>0),DY36/DT36-1,"NA") -> -0.26542036 | DZ77: =IF(AND(DZ36>=0,DU36>0),DZ36/DU36-1,"NA") -> -0.33998644 | EA77: =EA36/DV36-1 -> -0.21123723 | EB77: =IF(AND(EB36>=0,DW36>0),EB36/DW36-1,"NA") -> -0.084266245 | EC77: =IF(AND(EC36>=0,DX36>0),EC36/DX36-1,"NA") -> 0.14785652 | ED77: =IF(AND(ED36>=0,DY36>0),ED36/DY36-1,"NA") -> 0.41545651 | EE77: =IF(AND(EE36>=0,DZ36>0),EE36/DZ36-1,"NA") -> 0.51842337 | EF77: =EF36/EA36-1 -> 0.2304909 | EG77: =IF(AND(EG36>=0,EB36>0),EG36/EB36-1,"NA") -> 0.57212145 | EH77: =IF(AND(EH36>=0,EC36>0),EH36/EC36-1,"NA") -> 0.28587761 | EI77: =IF(AND(EI36>=0,ED36>0),EI36/ED36-1,"NA") -> 0.33582203 | EJ77: =IF(AND(EJ36>=0,EE36>0),EJ36/EE36-1,"NA") -> 0.28273795 | EK77: =EK36/EF36-1 -> 0.35670438 | EL77: =IF(AND(EL36>=0,EG36>0),EL36/EG36-1,"NA") -> 0.45972445 | EM77: =IF(AND(EM36>=0,EH36>0),EM36/EH36-1,"NA") -> 0.19378466 | EN77: =IF(AND(EN36>=0,EI36>0),EN36/EI36-1,"NA") -> 0.32994943 | EO77: =IF(AND(EO36>=0,EJ36>0),EO36/EJ36-1,"NA") -> 0.19764878 | EP77: =EP36/EK36-1 -> 0.29343183 | EQ77: =IF(AND(EQ36>=0,EL36>0),EQ36/EL36-1,"NA") -> -0.08536978 | ER77: =IF(AND(ER36>=0,EM36>0),ER36/EM36-1,"NA") -> 0.17030799 | ES77: =IF(AND(ES36>=0,EN36>0),ES36/EN36-1,"NA") -> -0.030787729 | ET77: =IF(AND(ET36>=0,EO36>0),ET36/EO36-1,"NA") -> 0.15774916 | EU77: =EU36/EP36-1 -> 0.044710356 | EV77: =EV36/EU36-1 -> 0.11304618 | EW77: =EW36/EV36-1 -> 0.13449456 | EX77: =EX36/EW36-1 -> 0.13148456 | EY77: =EY36/EX36-1 -> 0.1348265
A78: GAAP EPS | K78: =K37/F37-1 -> 0.53090553 | P78: =P37/K37-1 -> -1.1706498 | U78: =U37/P37-1 -> 11.077795 | V78: =V37/Q37-1 -> 1.6178367 | W78: =W37/R37-1 -> 0.61578551 | X78: =X37/S37-1 -> -0.3976825 | Y78: =Y37/T37-1 -> -0.44885866 | Z78: =Z37/U37-1 -> -0.088603542 | AA78: =AA37/V37-1 -> 1.334131 | AB78: =AB37/W37-1 -> 1.3753127 | ... BN78: =BN37/BI37-1 -> 0.13098939 | BO78: 0.58906916 | BP78: 0.095788441 | BQ78: -0.21669264 | BR78: 0.047882546 | BS78: 0.085810686 | BT78: =BT37/BJ37-1 -> -0.20546542 | BU78: =BU37/BK37-1 -> -0.40626759 | BV78: =BV37/BL37-1 -> -0.5134927 | BW78: =BW37/BM37-1 -> -0.47260936 | BX78: =BX37/BN37-1 -> -0.45709466 | BY78: 0.13533909 | BZ78: 0.13322238 | CA78: 0.34106695 | CB78: 0.14911343 | CC78: 0.18021426 | CD78: =CD37/BT37-1 -> 0.13533909 | CE78: =CE37/BU37-1 -> 0.045733708 | CF78: =CF37/BV37-1 -> 0.079601068 | CG78: =CG37/BW37-1 -> 0.14159771 | CH78: =CH37/BX37-1 -> 0.180216 | CI78: =CI37/CD37-1 -> -0.01010548 | CJ78: =CJ37/CE37-1 -> 0.023831651 | CK78: =CK37/CF37-1 -> -0.090967059 | CL78: =CL37/CG37-1 -> 0.37161793 | CM78: =CM37/CH37-1 -> 0.10257696 | CN78: =CN37/CI37-1 -> 0.036115319 | CO78: =CO37/CJ37-1 -> 0.16498167 | CP78: =CP37/CK37-1 -> 0.44015577 | ... DB78: =DB37/CW37-1 -> -0.35324486 | DC78: =IF(AND(DC37>=0,CX37>0),DC37/CX37-1,"NA") -> 0.72497176 | DD78: =IF(AND(DD37>=0,CY37>0),DD37/CY37-1,"NA") -> -0.093029778 | DE78: =IF(AND(DE37>=0,CZ37>0),DE37/CZ37-1,"NA") -> 0.36514149 | DF78: =IF(AND(DF37>=0,DA37>0),DF37/DA37-1,"NA") -> NA | DG78: =IF(AND(DG37>=0,DB37>0),DG37/DB37-1,"NA") -> 1.4284535 | DH78: =IF(AND(DH37>=0,DC37>0),DH37/DC37-1,"NA") -> -0.28758491 | DI78: =IF(AND(DI37>=0,DD37>0),DI37/DD37-1,"NA") -> 2.1279489 | DJ78: =IF(AND(DJ37>=0,DE37>0),DJ37/DE37-1,"NA") -> -0.22483711 | ... DU78: =IF(AND(DU37>=0,DP37>0),DU37/DP37-1,"NA") -> 0.37673594 | DV78: =DV37/DQ37-1 -> 0.91418936 | DW78: =IF(AND(DW37>=0,DR37>0),DW37/DR37-1,"NA") -> -0.063385284 | DX78: =IF(AND(DX37>=0,DS37>0),DX37/DS37-1,"NA") -> -0.11314646 | DY78: =IF(AND(DY37>=0,DT37>0),DY37/DT37-1,"NA") -> -0.24111311 | DZ78: =IF(AND(DZ37>=0,DU37>0),DZ37/DU37-1,"NA") -> -0.31435158 | EA78: =EA37/DV37-1 -> -0.18756146 | EB78: =IF(AND(EB37>=0,DW37>0),EB37/DW37-1,"NA") -> -0.046558553 | EC78: =IF(AND(EC37>=0,DX37>0),EC37/DX37-1,"NA") -> 0.1905729 | ED78: =IF(AND(ED37>=0,DY37>0),ED37/DY37-1,"NA") -> 0.46016335 | EE78: =IF(AND(EE37>=0,DZ37>0),EE37/DZ37-1,"NA") -> 0.55999265 | EF78: =EF37/EA37-1 -> 0.27278535 | EG78: =IF(AND(EG37>=0,EB37>0),EG37/EB37-1,"NA") -> 0.60926905 | EH78: =IF(AND(EH37>=0,EC37>0),EH37/EC37-1,"NA") -> 0.31356077 | EI78: =IF(AND(EI37>=0,ED37>0),EI37/ED37-1,"NA") -> 0.36561692 | EJ78: =IF(AND(EJ37>=0,EE37>0),EJ37/EE37-1,"NA") -> 0.30912404 | EK78: =EK37/EF37-1 -> 0.38656937 | EL78: =IF(AND(EL37>=0,EG37>0),EL37/EG37-1,"NA") -> 0.48775268 | EM78: =IF(AND(EM37>=0,EH37>0),EM37/EH37-1,"NA") -> 0.22285124 | EN78: =IF(AND(EN37>=0,EI37>0),EN37/EI37-1,"NA") -> 0.35349029 | EO78: =IF(AND(EO37>=0,EJ37>0),EO37/EJ37-1,"NA") -> 0.21133579 | EP78: =EP37/EK37-1 -> 0.31693348 | EQ78: =IF(AND(EQ37>=0,EL37>0),EQ37/EL37-1,"NA") -> -0.079350911 | ER78: =IF(AND(ER37>=0,EM37>0),ER37/EM37-1,"NA") -> 0.16888767 | ES78: =IF(AND(ES37>=0,EN37>0),ES37/EN37-1,"NA") -> -0.031740393 | ET78: =IF(AND(ET37>=0,EO37>0),ET37/EO37-1,"NA") -> 0.15692271 | EU78: =EU37/EP37-1 -> 0.045668441 | EV78: =EV37/EU37-1 -> 0.12196144 | EW78: =EW37/EV37-1 -> 0.1445342 | EX78: =EX37/EW37-1 -> 0.14282853 | EY78: =EY37/EX37-1 -> 0.14753405
A79: Non-GAAP Net Income (loss) | K79: =K42/F42-1 -> #DIV/0! | P79: =P42/K42-1 -> #DIV/0! | U79: =U42/P42-1 -> #DIV/0! | V79: =V42/Q42-1 -> #DIV/0! | W79: =W42/R42-1 -> #DIV/0! | X79: =X42/S42-1 -> #DIV/0! | Y79: =Y42/T42-1 -> #DIV/0! | Z79: =Z42/U42-1 -> #DIV/0! | AA79: =AA42/V42-1 -> #DIV/0! | AB79: =AB42/W42-1 -> #DIV/0! | ... BN79: =BN42/BI42-1 -> #DIV/0! | BO79: 0.2472203 | BP79: 0.15755793 | BQ79: -0.071619567 | BR79: 0.12067714 | BS79: 0.10595279 | BT79: =BT42/BJ42-1 -> #DIV/0! | BU79: =BU42/BK42-1 -> #DIV/0! | BV79: =BV42/BL42-1 -> #DIV/0! | BW79: =BW42/BM42-1 -> #DIV/0! | BX79: =BX42/BN42-1 -> #DIV/0! | BY79: 0.14886081 | BZ79: -0.055315946 | CA79: 0.18956968 | CB79: 0.12769561 | CC79: 0.10070976 | CI79: =CI42/CD42-1 -> 0.0073687986 | CJ79: =CJ42/CE42-1 -> 0.03849145 | CK79: =CK42/CF42-1 -> 0.04936229 | CL79: =CL42/CG42-1 -> 0.38466025 | CM79: =CM42/CH42-1 -> 0.14721362 | CN79: =CN42/CI42-1 -> 0.042596219 | CO79: =CO42/CJ42-1 -> 0.1726451 | CP79: =CP42/CK42-1 -> 0.27670934 | ... EU79: =EU42/EP42-1 -> 0.017546103 | EV79: =EV42/EU42-1 -> 0.11304618 | EW79: =EW42/EV42-1 -> 0.13449456 | EX79: =EX42/EW42-1 -> 0.13148456 | EY79: =EY42/EX42-1 -> 0.1348265
A80: Non-GAAP EPS | K80: =K43/F43-1 -> #DIV/0! | P80: =P43/K43-1 -> #DIV/0! | U80: =U43/P43-1 -> #DIV/0! | V80: =V43/Q43-1 -> #DIV/0! | W80: =W43/R43-1 -> #DIV/0! | X80: =X43/S43-1 -> #DIV/0! | Y80: =Y43/T43-1 -> #DIV/0! | Z80: =Z43/U43-1 -> #DIV/0! | AA80: =AA43/V43-1 -> #DIV/0! | AB80: =AB43/W43-1 -> #DIV/0! | ... BN80: =BN43/BI43-1 -> #DIV/0! | BO80: 0.2472203 | BP80: 0.15755793 | BQ80: -0.071619567 | BR80: 0.12067714 | BS80: 0.10595279 | BT80: =BT43/BJ43-1 -> #DIV/0! | BU80: =BU43/BK43-1 -> #DIV/0! | BV80: =BV43/BL43-1 -> #DIV/0! | BW80: =BW43/BM43-1 -> #DIV/0! | BX80: =BX43/BN43-1 -> #DIV/0! | BY80: 0.14886081 | BZ80: -0.055315946 | CA80: 0.18956968 | CB80: 0.12769561 | CC80: 0.10070976 | CI80: =CI43/CD43-1 -> -0.01010548 | CJ80: =CJ43/CE43-1 -> 0.023831651 | CK80: =CK43/CF43-1 -> 0.034503509 | CL80: =CL43/CG43-1 -> 0.37161793 | CM80: =CM43/CH43-1 -> 0.13143144 | CN80: =CN43/CI43-1 -> 0.036115319 | CO80: =CO43/CJ43-1 -> 0.16498167 | CP80: =CP43/CK43-1 -> 0.26548535 | ... EU80: =EU43/EP43-1 -> 0.018479276 | EV80: =EV43/EU43-1 -> 0.12196144 | EW80: =EW43/EV43-1 -> 0.1445342 | EX80: =EX43/EW43-1 -> 0.14282853 | EY80: =EY43/EX43-1 -> 0.14753405
A81: JPMe Adjusted Net Income (loss) | K81: =K50/F50-1 -> 1.0052666 | P81: =P50/K50-1 -> -2.2784066 | U81: =U50/P50-1 -> 6.7869912 | V81: =V50/Q50-1 -> 4.3177778 | W81: =W50/R50-1 -> 2.2631346 | X81: =X50/S50-1 -> 1.582148 | Y81: =Y50/T50-1 -> 1.126767 | Z81: =Z50/U50-1 -> 1.7620269 | AA81: =AA50/V50-1 -> 1.257321 | AB81: =AB50/W50-1 -> 1.3189664 | ... BN81: =BN50/BI50-1 -> 0.23255328 | BO81: 0.2472203 | BP81: 0.15755793 | BQ81: -0.071619567 | BR81: 0.12067714 | BS81: 0.10595279 | BT81: =BT50/BJ50-1 -> 0.26156179 | BU81: =BU50/BK50-1 -> 0.18778519 | BV81: =BV50/BL50-1 -> -0.0075376884 | BW81: =BW50/BM50-1 -> 0.18963863 | BX81: =BX50/BN50-1 -> 0.14722834 | BY81: 0.14886081 | BZ81: -0.055315946 | CA81: 0.18956968 | CB81: 0.12769561 | CC81: 0.10070976 | CD81: =CD50/BT50-1 -> 0.21454327 | CE81: =CE50/BU50-1 -> 0.0023640662 | CF81: =CF50/BV50-1 -> 0.25316456 | CG81: =CG50/BW50-1 -> 0.23575269 | CH81: =CH50/BX50-1 -> 0.18145549 | CI81: =CI50/CD50-1 -> 0.043457694 | CJ81: =CJ50/CE50-1 -> 0.21027429 | CK81: =CK50/CF50-1 -> 0.085506566 | CL81: =CL50/CG50-1 -> 0.012315206 | CM81: =CM50/CH50-1 -> 0.099556 | CN81: =CN50/CI50-1 -> 0.057514695 | CO81: =CO50/CJ50-1 -> 0.17629853 | CP81: =CP50/CK50-1 -> 0.1868964 | ... EU81: =EU50/EP50-1 -> 0.19541988 | EV81: =EV50/EU50-1 -> 0.10795055 | EW81: =EW50/EV50-1 -> 0.12584506 | EX81: =EX50/EW50-1 -> 0.12323029 | EY81: =EY50/EX50-1 -> 0.12610887
A82: JPMe Adjusted EPS | K82: =K51/F51-1 -> 0.26974492 | P82: =P51/K51-1 -> -1.4588071 | U82: =U51/P51-1 -> 5.5920468 | V82: =V51/Q51-1 -> 3.2766834 | W82: =W51/R51-1 -> 1.7196909 | X82: =X51/S51-1 -> 1.3076303 | Y82: =Y51/T51-1 -> 0.92806373 | Z82: =Z51/U51-1 -> 1.3745286 | AA82: =AA51/V51-1 -> 1.1249149 | AB82: =AB51/W51-1 -> 1.2411247 | ... BN82: =BN51/BI51-1 -> 0.21762451 | BO82: 0.2472203 | BP82: 0.15755793 | BQ82: -0.071619567 | BR82: 0.12067714 | BS82: 0.10595279 | BT82: =BT51/BJ51-1 -> -0.37638985 | BU82: =BU51/BK51-1 -> -0.41464793 | BV82: =BV51/BL51-1 -> -0.51251543 | BW82: =BW51/BM51-1 -> -0.4157905 | BX82: =BX51/BN51-1 -> -0.43517202 | BY82: 0.14886081 | BZ82: -0.055315946 | CA82: 0.18956968 | CB82: 0.12769561 | CC82: 0.10070976 | CD82: =CD51/BT51-1 -> 0.19099651 | CE82: =CE51/BU51-1 -> -0.019985941 | CF82: =CF51/BV51-1 -> 0.23129185 | CG82: =CG51/BW51-1 -> 0.21391521 | CH82: =CH51/BX51-1 -> 0.15877549 | CI82: =CI51/CD51-1 -> 0.025357401 | CJ82: =CJ51/CE51-1 -> 0.19318953 | CK82: =CK51/CF51-1 -> 0.070135989 | CL82: =CL51/CG51-1 -> 0.0027800568 | CM82: =CM51/CH51-1 -> 0.084429444 | CN82: =CN51/CI51-1 -> 0.050941061 | CO82: =CO51/CJ51-1 -> 0.16861123 | CP82: =CP51/CK51-1 -> 0.17646198 | ... EU82: =EU51/EP51-1 -> 0.19651618 | EV82: =EV51/EU51-1 -> 0.11682499 | EW82: =EW51/EV51-1 -> 0.13580816 | EX82: =EX51/EW51-1 -> 0.13449149 | EY82: =EY51/EX51-1 -> 0.1387188
A83: Sequential Growth
A84: Gross revenues | R84: =R7/Q7-1 -> 0.8570415 | S84: =S7/R7-1 -> 0.665546 | T84: =T7/S7-1 -> 0.43677124 | V84: =V7/T7-1 -> 0.32306251 | W84: =W7/V7-1 -> 0.25171548 | X84: =X7/W7-1 -> 0.26588453 | Y84: =Y7/X7-1 -> 0.30012794 | AA84: =AA7/Y7-1 -> 0.27226632 | AB84: =AB7/AA7-1 -> 0.074566122 | AC84: =AC7/AB7-1 -> 0.15091858 | AD84: =AD7/AC7-1 -> 0.27995736 | AF84: =AF7/AD7-1 -> 0.21814327 | AG84: =AG7/AF7-1 -> 0.10185226 | AH84: =AH7/AG7-1 -> 0.14009512 | AI84: =AI7/AH7-1 -> 0.21580392 | AK84: =AK7/AI7-1 -> 0.1743855 | AL84: =AL7/AK7-1 -> 0.089732912 | AM84: =AM7/AL7-1 -> 0.095147743 | AN84: =AN7/AM7-1 -> 0.19177982 | AP84: =AP7/AN7-1 -> 0.14302707 | AQ84: =AQ7/AP7-1 -> 0.056772829 | AR84: =AR7/AQ7-1 -> 0.092811826 | AS84: =AS7/AR7-1 -> 0.14069454 | AU84: =AU7/AS7-1 -> 0.074453677 | AV84: =AV7/AU7-1 -> 0.034933956 | AW84: =AW7/AV7-1 -> 0.032452417 | AX84: =AX7/AW7-1 -> 0.028785733 | AZ84: =AZ7/AX7-1 -> -0.033663784 | BA84: =BA7/AZ7-1 -> 0.0025244192 | BB84: =BB7/BA7-1 -> 0.076400845 | BC84: =BC7/BB7-1 -> 0.12262275 | BE84: =BE7/BC7-1 -> 0.015159972 | BF84: =BF7/BE7-1 -> 0.0066420664 | BG84: =BG7/BF7-1 -> 0.068328446 | BH84: =BH7/BG7-1 -> 0.15838595 | BJ84: =BJ7/BH7-1 -> 0.015995261 | BK84: =BK7/BJ7-1 -> 0.052594752 | BL84: =BL7/BK7-1 -> 0.076888987 | BM84: =BM7/BL7-1 -> 0.088888889 | BO84: 0.0057634165 | BP84: 0.14739314 | BQ84: 0.15449484 | BR84: 0.022551592 | BT84: =BT7/BM7-1 -> 0.0057634165 | BU84: =BU7/BT7-1 -> 0.029967121 | BV84: =BV7/BU7-1 -> 0.051258665 | BW84: =BW7/BV7-1 -> 0.11964255 | BY84: -0.031208822 | BZ84: 0.0097358437 | CA84: 0.055866714 | CB84: 0.13194118 | CD84: =CD7/BW7-1 -> 0.0035645099 | CE84: =CE7/CD7-1 -> 0.012045402 | CF84: =CF7/CE7-1 -> 0.049362936 | CG84: =CG7/CF7-1 -> 0.14199506 | CI84: =CI7/CG7-1 -> -0.018272108 | CJ84: =CJ7/CI7-1 -> 0.034695201 | CK84: =CK7/CJ7-1 -> 0.035600125 | CL84: =CL7/CK7-1 -> 0.095624281 | CN84: =CN7/CL7-1 -> -0.046677346 | CO84: =CO7/CN7-1 -> 0.027175803 | CP84: =CP7/CO7-1 -> 0.053477746 | CQ84: =CQ7/CP7-1 -> 0.14211513 | CS84: =CS7/CQ7-1 -> -0.050260209 | CT84: =CT7/CS7-1 -> 0.061361505 | CU84: =CU7/CT7-1 -> 0.044232558 | CV84: =CV7/CU7-1 -> 0.16092824 | CX84: =CX7/CV7-1 -> -0.050414365 | CY84: =CY7/CX7-1 -> 0.050909091 | CZ84: =CZ7/CY7-1 -> 0.067743176 | DA84: =DA7/CZ7-1 -> 0.16387008 | DC84: =DC7/DA7-1 -> -0.036413699 | DD84: =DD7/DC7-1 -> 0.048513453 | DE84: =DE7/DD7-1 -> 0.033162875 | DF84: =DF7/DE7-1 -> 0.16407825 | DH84: =DH7/DF7-1 -> -0.074778491 | DI84: =DI7/DH7-1 -> 0.071686067 | DJ84: =DJ7/DI7-1 -> 0.039929129 | DK84: =DK7/DJ7-1 -> 0.13768241 | DM84: =DM7/DK7-1 -> -0.1066956 | DN84: =DN7/DM7-1 -> -0.069535217 | DO84: =DO7/DN7-1 -> 0.2056558 | DP84: =DP7/DO7-1 -> 0.2322786 | DR84: =DR7/DP7-1 -> -0.027839291 | DS84: =DS7/DR7-1 -> 0.11870413 | DT84: =DT7/DS7-1 -> 0.052327085 | DU84: =DU7/DT7-1 -> 0.15674621 | DW84: =DW7/DU7-1 -> -0.097099237 | DX84: =DX7/DW7-1 -> 0.024613665 | DY84: =DY7/DX7-1 -> -0.0085097223 | DZ84: =DZ7/DY7-1 -> 0.10067736 | EB84: =EB7/DZ7-1 -> -0.082329581 | EC84: =EC7/EB7-1 -> 0.069024317 | ED84: =ED7/EC7-1 -> 0.02800118 | EE84: =EE7/ED7-1 -> 0.12539606 | EG84: =EG7/EE7-1 -> -0.066863631 | EH84: =EH7/EG7-1 -> 0.052185898 | EI84: =EI7/EH7-1 -> 0.041608647 | EJ84: =EJ7/EI7-1 -> 0.092910228 | EL84: =EL7/EJ7-1 -> -0.064632162 | EM84: =EM7/EL7-1 -> 0.068643748 | EN84: =EN7/EM7-1 -> 0.061372216 | EO84: =EO7/EN7-1 -> 0.096733964 | EQ84: =EQ7/EO7-1 -> -0.052757374 | ER84: =ER7/EQ7-1 -> 0.059148176 | ES84: =ES7/ER7-1 -> 0.055721985 | ET84: =ET7/ES7-1 -> 0.097459533
A85: Traffic Acquisition Costs (TAC) | S85: =S8/R8-1 -> 1.0714286 | T85: =T8/S8-1 -> 0.77586207 | V85: =V8/T8-1 -> 0.36176699 | W85: =W8/V8-1 -> 0.37683763 | X85: =X8/W8-1 -> 0.48600338 | Y85: =Y8/X8-1 -> 0.50784392 | AA85: =AA8/Y8-1 -> 0.25257446 | AB85: =AB8/AA8-1 -> 0.022258138 | AC85: =AC8/AB8-1 -> 0.093367601 | AD85: =AD8/AC8-1 -> 0.2469726 | AF85: =AF8/AD8-1 -> 0.22265613 | AG85: =AG8/AF8-1 -> 0.07040387 | AH85: =AH8/AG8-1 -> 0.071925069 | AI85: =AI8/AH8-1 -> 0.18696332 | AK85: =AK8/AI8-1 -> 0.14913164 | AL85: =AL8/AK8-1 -> 0.086370404 | AM85: =AM8/AL8-1 -> 0.051078826 | AN85: =AN8/AM8-1 -> 0.18218897 | AP85: =AP8/AN8-1 -> 0.15314806 | AQ85: =AQ8/AP8-1 -> 0.020338088 | AR85: =AR8/AQ8-1 -> 0.063773997 | AS85: =AS8/AR8-1 -> 0.17909296 | AU85: =AU8/AS8-1 -> 0.032344456 | AV85: =AV8/AU8-1 -> -0.0083450844 | AW85: =AW8/AV8-1 -> 0.014400467 | AX85: =AX8/AW8-1 -> -0.0079079404 | AZ85: =AZ8/AX8-1 -> -0.031968839 | BA85: =BA8/AZ8-1 -> 0.012113151 | BB85: =BB8/BA8-1 -> 0.07283979 | BC85: =BC8/BB8-1 -> 0.10368672 | BE85: =BE8/BC8-1 -> -0.0057447152 | BF85: =BF8/BE8-1 -> 0.012273524 | BG85: =BG8/BF8-1 -> 0.042147806 | BH85: =BH8/BG8-1 -> 0.14626039 | BJ85: =BJ8/BH8-1 -> -0.014983084 | BK85: =BK8/BJ8-1 -> 0.035328754 | BL85: =BL8/BK8-1 -> 0.047393365 | BM85: =BM8/BL8-1 -> 0.10859729 | BO85: 0.024489796 | BP85: 0.035856574 | BQ85: 0.065384615 | BR85: 0.11191336 | BT85: =BT8/BM8-1 -> 0.024489796 | BU85: =BU8/BT8-1 -> 0.035856574 | BV85: =BV8/BU8-1 -> 0.065384615 | BW85: =BW8/BV8-1 -> 0.11191336 | BY85: -0.038311688 | BZ85: 0.017218096 | CA85: -0.0136077 | CB85: 0.11372813 | CD85: =CD8/BW8-1 -> -0.038311688 | CE85: =CE8/CD8-1 -> 0.017218096 | CF85: =CF8/CE8-1 -> -0.0136077 | CG85: =CG8/CF8-1 -> 0.11372813 | CI85: =CI8/CG8-1 -> -0.023564955 | CJ85: =CJ8/CI8-1 -> 0.018873762 | CK85: =CK8/CJ8-1 -> 0.016702095 | CL85: =CL8/CK8-1 -> 0.081242533 | CN85: =CN8/CL8-1 -> -0.075966851 | CO85: =CO8/CN8-1 -> 0.0095665172 | CP85: =CP8/CO8-1 -> 0.055966834 | CQ85: =CQ8/CP8-1 -> 0.13712844 | CS85: =CS8/CQ8-1 -> -0.065844636 | CT85: =CT8/CS8-1 -> 0.04936642 | CU85: =CU8/CT8-1 -> 0.052075472 | CV85: =CV8/CU8-1 -> 0.15925395 | CX85: =CX8/CV8-1 -> -0.045173267 | CY85: =CY8/CX8-1 -> 0.099805574 | CZ85: =CZ8/CY8-1 -> 0.080730701 | DA85: =DA8/CZ8-1 -> 0.17230098 | DC85: =DC8/DA8-1 -> -0.025116279 | DD85: =DD8/DC8-1 -> 0.020992366 | DE85: =DE8/DD8-1 -> 0.025233645 | DF85: =DF8/DE8-1 -> 0.1297478 | DH85: =DH8/DF8-1 -> -0.077461001 | DI85: =DI8/DH8-1 -> 0.055102041 | DJ85: =DJ8/DI8-1 -> 0.034816248 | DK85: =DK8/DJ8-1 -> 0.13497997 | DM85: =DM8/DK8-1 -> -0.12339725 | DN85: =DN8/DM8-1 -> -0.10171766 | DO85: =DO8/DN8-1 -> 0.21989842 | DP85: =DP8/DO8-1 -> 0.28165565 | DR85: =DR8/DP8-1 -> -0.072042805 | DS85: =DS8/DR8-1 -> 0.1253089 | DT85: =DT8/DS8-1 -> 0.052063318 | DU85: =DU8/DT8-1 -> 0.16776831 | DW85: =DW8/DU8-1 -> -0.10702316 | DX85: =DX8/DW8-1 -> 0.018682235 | DY85: =DY8/DX8-1 -> -0.031766825 | DZ85: =DZ8/DY8-1 -> 0.09293083 | EB85: =EB8/DZ8-1 -> -0.093152805 | EC85: =EC8/EB8-1 -> 0.069618633 | ED85: =ED8/EC8-1 -> 0.0083752094 | EE85: =EE8/ED8-1 -> 0.10631229 | EG85: =EG8/EE8-1 -> -0.074360074 | EH85: =EH8/EG8-1 -> 0.034064576 | EI85: =EI8/EH8-1 -> 0.024800179 | EJ85: =EJ8/EI8-1 -> 0.082294628 | EL85: =EL8/EJ8-1 -> -0.074084052 | EM85: =EM8/EL8-1 -> 0.069610125 | EN85: =EN8/EM8-1 -> 0.011628698 | EO85: =EO8/EN8-1 -> 0.092921296 | EQ85: =EQ8/EO8-1 -> -0.050036894 | ER85: =ER8/EQ8-1 -> 0.029090948 | ES85: =ES8/ER8-1 -> 0.017274708 | ET85: =ET8/ES8-1 -> 0.086084521
A86: Net revenues | R86: =R9/Q9-1 -> 0.52595483 | S86: =S9/R9-1 -> 0.5774816 | T86: =T9/S9-1 -> 0.34016132 | V86: =V9/T9-1 -> 0.3084502 | W86: =W9/V9-1 -> 0.20255257 | X86: =X9/W9-1 -> 0.16686079 | Y86: =Y9/X9-1 -> 0.18112635 | AA86: =AA9/Y9-1 -> 0.28666854 | AB86: =AB9/AA9-1 -> 0.11180939 | AC86: =AC9/AB9-1 -> 0.1885944 | AD86: =AD9/AC9-1 -> 0.29982087 | AF86: =AF9/AD9-1 -> 0.21553611 | AG86: =AG9/AF9-1 -> 0.12012699 | AH86: =AH9/AG9-1 -> 0.1779504 | AI86: =AI9/AH9-1 -> 0.23037779 | AK86: =AK9/AI9-1 -> 0.18669661 | AL86: =AL9/AK9-1 -> 0.091320225 | AM86: =AM9/AL9-1 -> 0.11585665 | AN86: =AN9/AM9-1 -> 0.19602512 | AP86: =AP9/AN9-1 -> 0.13859894 | AQ86: =AQ9/AP9-1 -> 0.072917467 | AR86: =AR9/AQ9-1 -> 0.10504825 | AS86: =AS9/AR9-1 -> 0.12511797 | AU86: =AU9/AS9-1 -> 0.092355024 | AV86: =AV9/AU9-1 -> 0.052321849 | AW86: =AW9/AV9-1 -> 0.039286896 | AX86: =AX9/AW9-1 -> 0.04234532 | AZ86: =AZ9/AX9-1 -> -0.034259928 | BA86: =BA9/AZ9-1 -> -0.0008561194 | BB86: =BB9/BA9-1 -> 0.077672604 | BC86: =BC9/BB9-1 -> 0.12935504 | BE86: =BE9/BC9-1 -> 0.022423252 | BF86: =BF9/BE9-1 -> 0.0047393365 | BG86: =BG9/BF9-1 -> 0.077240566 | BH86: =BH9/BG9-1 -> 0.16237913 | BJ86: =BJ9/BH9-1 -> 0.026055564 | BK86: =BK9/BJ9-1 -> 0.057977666 | BL86: =BL9/BK9-1 -> 0.085887796 | BM86: =BM9/BL9-1 -> 0.083089214 | BO86: 0.00012294074 | BP86: 0.18180701 | BQ86: 0.17859372 | BR86: 0.00070602771 | BT86: =BT9/BM9-1 -> 0.00012294074 | BU86: =BU9/BT9-1 -> 0.028149969 | BV86: =BV9/BU9-1 -> 0.046867527 | BW86: =BW9/BV9-1 -> 0.12208771 | BY86: -0.029279478 | BZ86: 0.0077223585 | CA86: 0.07473855 | CB86: 0.13648184 | CD86: =CD9/BW9-1 -> 0.016692112 | CE86: =CE9/CD9-1 -> 0.010511563 | CF86: =CF9/CE9-1 -> 0.068159303 | CG86: =CG9/CF9-1 -> 0.14978668 | CI86: =CI9/CG9-1 -> -0.016858917 | CJ86: =CJ9/CI9-1 -> 0.038890712 | CK86: =CK9/CJ9-1 -> 0.040514927 | CL86: =CL9/CK9-1 -> 0.099278937 | CN86: =CN9/CL9-1 -> -0.039356487 | CO86: =CO9/CN9-1 -> 0.031409473 | CP86: =CP9/CO9-1 -> 0.052891986 | CQ86: =CQ9/CP9-1 -> 0.14329208 | CS86: =CS9/CQ9-1 -> -0.046601829 | CT86: =CT9/CS9-1 -> 0.064120469 | CU86: =CU9/CT9-1 -> 0.042453638 | CV86: =CV9/CU9-1 -> 0.16131151 | CX86: =CX9/CV9-1 -> -0.051611991 | CY86: =CY9/CX9-1 -> 0.039660057 | CZ86: =CZ9/CY9-1 -> 0.064582437 | DA86: =DA9/CZ9-1 -> 0.16178716 | DC86: =DC9/DA9-1 -> -0.039230085 | DD86: =DD9/DC9-1 -> 0.055475099 | DE86: =DE9/DD9-1 -> 0.035103099 | DF86: =DF9/DE9-1 -> 0.17239856 | DH86: =DH9/DF9-1 -> -0.07415201 | DI86: =DI9/DH9-1 -> 0.075545303 | DJ86: =DJ9/DI9-1 -> 0.041096322 | DK86: =DK9/DJ9-1 -> 0.13829562 | DM86: =DM9/DK9-1 -> -0.10291691 | DN86: =DN9/DM9-1 -> -0.062420269 | DO86: =DO9/DN9-1 -> 0.20263899 | DP86: =DP9/DO9-1 -> 0.22166969 | DR86: =DR9/DP9-1 -> -0.017875603 | DS86: =DS9/DR9-1 -> 0.11729749 | DT86: =DT9/DS9-1 -> 0.052383663 | DU86: =DU9/DT9-1 -> 0.15438269 | DW86: =DW9/DU9-1 -> -0.094946525 | DX86: =DX9/DW9-1 -> 0.025883151 | DY86: =DY9/DX9-1 -> -0.0035670164 | DZ86: =DZ9/DY9-1 -> 0.10227709 | EB86: =EB9/DZ9-1 -> -0.080113429 | EC86: =EC9/EB9-1 -> 0.06890435 | ED86: =ED9/EC9-1 -> 0.031965457 | EE86: =EE9/ED9-1 -> 0.1291627 | EG86: =EG9/EE9-1 -> -0.06541397 | EH86: =EH9/EG9-1 -> 0.055656651 | EI86: =EI9/EH9-1 -> 0.044762105 | EJ86: =EJ9/EI9-1 -> 0.094863781 | EL86: =EL9/EJ9-1 -> -0.062912731 | EM86: =EM9/EL9-1 -> 0.068470047 | EN86: =EN9/EM9-1 -> 0.07032292 | EO86: =EO9/EN9-1 -> 0.097382384 | EQ86: =EQ9/EO9-1 -> -0.053218164 | ER86: =ER9/EQ9-1 -> 0.064256327 | ES86: =ES9/ER9-1 -> 0.062040105 | ET86: =ET9/ES9-1 -> 0.099250022
A87: Other cost of revenues | BY87: -0.038311688 | BZ87: 0.017218096 | CA87: -0.0136077 | CB87: 0.11372813 | CE87: =CE12/CD12-1 -> 0.0036798528 | CF87: =CF12/CE12-1 -> 0.11686526 | CG87: =CG12/CF12-1 -> 0.20763233 | CI87: =CI12/CG12-1 -> -0.072714917 | CJ87: =CJ12/CI12-1 -> 0.033711982 | CK87: =CK12/CJ12-1 -> 0.1864587 | CL87: =CL12/CK12-1 -> -0.013743651 | CN87: =CN12/CL12-1 -> -0.087852166 | CO87: =CO12/CN12-1 -> 0.064762537 | CP87: =CP12/CO12-1 -> 0.082657517 | CQ87: =CQ12/CP12-1 -> 0.19072313 | CS87: =CS12/CQ12-1 -> -0.066053714 | CT87: =CT12/CS12-1 -> 0.07642487 | CU87: =CU12/CT12-1 -> 0.087123947 | CV87: =CV12/CU12-1 -> 0.28691609 | CX87: =CX12/CV12-1 -> -0.11130225 | CY87: =CY12/CX12-1 -> 0.02245451 | CZ87: =CZ12/CY12-1 -> 0.06891329 | DA87: =DA12/CZ12-1 -> 0.38452001 | DC87: =DC12/DA12-1 -> -0.081616989 | DD87: =DD12/DC12-1 -> 0.039559827 | DE87: =DE12/DD12-1 -> 0.031622672 | DF87: =DF12/DE12-1 -> 0.36147552 | DH87: =DH12/DF12-1 -> -0.12688418 | DI87: =DI12/DH12-1 -> 0.098994755 | DJ87: =DJ12/DI12-1 -> 0.0019884669 | DK87: =DK12/DJ12-1 -> 0.24221076 | DM87: =DM12/DK12-1 -> -0.07899992 | DN87: =DN12/DM12-1 -> 0.028534258 | DO87: =DO12/DN12-1 -> 0.092081963 | DP87: =DP12/DO12-1 -> 0.20562119 | DR87: =DR12/DP12-1 -> -0.078327142 | DS87: =DS12/DR12-1 -> 0.063025502 | DT87: =DT12/DS12-1 -> 0.053928618 | DU87: =DU12/DT12-1 -> 0.21323575 | DW87: =DW12/DU12-1 -> -0.099790399 | DX87: =DX12/DW12-1 -> 0.015957749 | DY87: =DY12/DX12-1 -> 0.080603689 | DZ87: =DZ12/DY12-1 -> 0.15957997 | EB87: =EB12/DZ12-1 -> -0.15729134 | EC87: =EC12/EB12-1 -> 0.025832407 | ED87: =ED12/EC12-1 -> 0.062335518 | EE87: =EE12/ED12-1 -> 0.14582018 | EG87: =EG12/EE12-1 -> -0.11967442 | EH87: =EH12/EG12-1 -> 0.065202735 | EI87: =EI12/EH12-1 -> 0.028707052 | EJ87: =EJ12/EI12-1 -> 0.13227862 | EL87: =EL12/EJ12-1 -> -0.1223365 | EM87: =EM12/EL12-1 -> 0.076106664 | EN87: =EN12/EM12-1 -> 0.088723597 | EO87: =EO12/EN12-1 -> 0.14853764 | EQ87: =EQ12/EO12-1 -> -0.10399195 | ER87: =ER12/EQ12-1 -> 0.089088975 | ES87: =ES12/ER12-1 -> 0.10701249 | ET87: =ET12/ES12-1 -> 0.1404719
A88: Gross profit | R88: =R13/Q13-1 -> 0.58822726 | S88: =S13/R13-1 -> 0.56861902 | T88: =T13/S13-1 -> 0.33957111 | V88: =V13/T13-1 -> 0.32181753 | W88: =W13/V13-1 -> 0.20056002 | X88: =X13/W13-1 -> 0.153531 | Y88: =Y13/X13-1 -> 0.16888688 | AA88: =AA13/Y13-1 -> 0.28670491 | AB88: =AB13/AA13-1 -> 0.11185962 | AC88: =AC13/AB13-1 -> 0.18712266 | AD88: =AD13/AC13-1 -> 0.30179725 | AF88: =AF13/AD13-1 -> 0.23122886 | AG88: =AG13/AF13-1 -> 0.10697476 | AH88: =AH13/AG13-1 -> 0.17428245 | AI88: =AI13/AH13-1 -> 0.23694018 | AK88: =AK13/AI13-1 -> 0.18204496 | AL88: =AL13/AK13-1 -> 0.086811414 | AM88: =AM13/AL13-1 -> 0.118298 | AN88: =AN13/AM13-1 -> 0.17657541 | AP88: =AP13/AN13-1 -> 0.13692671 | AQ88: =AQ13/AP13-1 -> 0.055258711 | AR88: =AR13/AQ13-1 -> 0.10925895 | AS88: =AS13/AR13-1 -> 0.118278 | AU88: =AU13/AS13-1 -> 0.072136996 | AV88: =AV13/AU13-1 -> 0.046794536 | AW88: =AW13/AV13-1 -> 0.046370393 | AX88: =AX13/AW13-1 -> 0.042698884 | AZ88: =AZ13/AX13-1 -> -0.029229367 | BA88: =BA13/AZ13-1 -> 0.0024839014 | BB88: =BB13/BA13-1 -> 0.088949219 | BC88: =BC13/BB13-1 -> 0.1440998 | BE88: =BE13/BC13-1 -> 0.013467008 | BF88: =BF13/BE13-1 -> 0.0073920074 | BG88: =BG13/BF13-1 -> 0.087365283 | BH88: =BH13/BG13-1 -> 0.16807254 | BJ88: =BJ13/BH13-1 -> 0.026900162 | BK88: =BK13/BJ13-1 -> 0.038150492 | BL88: =BL13/BK13-1 -> 0.086198137 | BM88: =BM13/BL13-1 -> 0.084970377 | BO88: 0.024489796 | BP88: 0.035856574 | BQ88: 0.065384615 | BR88: 0.11191336 | BT88: =BT13/BM13-1 -> -0.0041672654 | BU88: =BU13/BT13-1 -> 0.019047619 | BV88: =BV13/BU13-1 -> 0.017983574 | BW88: =BW13/BV13-1 -> 0.1187926 | BY88: -0.038311688 | BZ88: 0.017218096 | CA88: -0.0136077 | CB88: 0.11372813 | CD88: =CD13/BW13-1 -> -0.028347631 | CE88: =CE13/CD13-1 -> 0.012412028 | CF88: =CF13/CE13-1 -> 0.054726997 | CG88: =CG13/CF13-1 -> 0.13289395 | CI88: =CI13/CG13-1 -> 0.00052887667 | CJ88: =CJ13/CI13-1 -> 0.040384819 | CK88: =CK13/CJ13-1 -> -0.001321004 | CL88: =CL13/CK13-1 -> 0.13776964 | CN88: =CN13/CL13-1 -> -0.025040243 | CO88: =CO13/CN13-1 -> 0.022197762 | CP88: =CP13/CO13-1 -> 0.044328787 | CQ88: =CQ13/CP13-1 -> 0.1291459 | CS88: =CS13/CQ13-1 -> -0.040483981 | CT88: =CT13/CS13-1 -> 0.060353716 | CU88: =CU13/CT13-1 -> 0.028571429 | CV88: =CV13/CU13-1 -> 0.12005526 | CX88: =CX13/CV13-1 -> -0.029085243 | CY88: =CY13/CX13-1 -> 0.045603477 | CZ88: =CZ13/CY13-1 -> 0.063119524 | DA88: =DA13/CZ13-1 -> 0.08614052 | DC88: =DC13/DA13-1 -> -0.020879486 | DD88: =DD13/DC13-1 -> 0.061937892 | DE88: =DE13/DD13-1 -> 0.03648663 | DF88: =DF13/DE13-1 -> 0.097589804 | DH88: =DH13/DF13-1 -> -0.04827231 | DI88: =DI13/DH13-1 -> 0.064987455 | DJ88: =DJ13/DI13-1 -> 0.059266445 | DK88: =DK13/DJ13-1 -> 0.092625703 | DM88: =DM13/DK13-1 -> -0.11486729 | DN88: =DN13/DM13-1 -> -0.10970826 | DO88: =DO13/DN13-1 -> 0.26904376 | DP88: =DP13/DO13-1 -> 0.22996488 | DR88: =DR13/DP13-1 -> 0.012752288 | DS88: =DS13/DR13-1 -> 0.14232162 | DT88: =DT13/DS13-1 -> 0.051720753 | DU88: =DU13/DT13-1 -> 0.12907699 | DW88: =DW13/DU13-1 -> -0.092708506 | DX88: =DX13/DW13-1 -> 0.030433198 | DY88: =DY13/DX13-1 -> -0.041610874 | DZ88: =DZ13/DY13-1 -> 0.073074287 | EB88: =EB13/DZ13-1 -> -0.037611163 | EC88: =EC13/EB13-1 -> 0.089674537 | ED88: =ED13/EC13-1 -> 0.018178411 | EE88: =EE13/ED13-1 -> 0.12127278 | EG88: =EG13/EE13-1 -> -0.039150508 | EH88: =EH13/EG13-1 -> 0.051423324 | EI88: =EI13/EH13-1 -> 0.051975221 | EJ88: =EJ13/EI13-1 -> 0.078426073 | EL88: =EL13/EJ13-1 -> -0.035502005 | EM88: =EM13/EL13-1 -> 0.065264604 | EN88: =EN13/EM13-1 -> 0.062520692 | EO88: =EO13/EN13-1 -> 0.075156688 | EQ88: =EQ13/EO13-1 -> -0.029652584 | ER88: =ER13/EQ13-1 -> 0.053613764 | ES88: =ES13/ER13-1 -> 0.042117275 | ET88: =ET13/ES13-1 -> 0.079851492
A89: Research & development | CE89: =CE17/CD17-1 -> 0.092145949 | CF89: =CF17/CE17-1 -> 0.031143828 | CG89: =CG17/CF17-1 -> 0.061504668 | CI89: =CI17/CG17-1 -> 0.099844801 | CJ89: =CJ17/CI17-1 -> 0.052681091 | CK89: =CK17/CJ17-1 -> 0.18632708 | CL89: =CL17/CK17-1 -> 0.059510358 | CN89: =CN17/CL17-1 -> -0.021329541 | CO89: =CO17/CN17-1 -> 0.013076644 | CP89: =CP17/CO17-1 -> 0.15812119 | CQ89: =CQ17/CP17-1 -> 0.086687307 | CS89: =CS17/CQ17-1 -> -0.040740741 | CT89: =CT17/CS17-1 -> -0.0011880012 | CU89: =CU17/CT17-1 -> 0.069283378 | CV89: =CV17/CU17-1 -> 0.0072302558 | CX89: =CX17/CV17-1 -> 0.088348978 | CY89: =CY17/CX17-1 -> 0.058346017 | CZ89: =CZ17/CY17-1 -> 0.0079098754 | DA89: =DA17/CZ17-1 -> 0.024019025 | DC89: =DC17/DA17-1 -> 0.17022759 | DD89: =DD17/DC17-1 -> 0.014883906 | DE89: =DE17/DD17-1 -> 0.023073915 | DF89: =DF17/DE17-1 -> 0.15328746 | DH89: =DH17/DF17-1 -> -0.00082863772 | DI89: =DI17/DH17-1 -> 0.030519157 | DJ89: =DJ17/DI17-1 -> 0.054884919 | DK89: =DK17/DJ17-1 -> 0.10192249 | DM89: =DM17/DK17-1 -> -0.055663251 | DN89: =DN17/DM17-1 -> 0.0080645161 | DO89: =DO17/DN17-1 -> -0.0027636364 | DP89: =DP17/DO17-1 -> 0.024212369 | DR89: =DR17/DP17-1 -> 0.065935631 | DS89: =DS17/DR17-1 -> 0.025384102 | DT89: =DT17/DS17-1 -> 0.00247557 | DU89: =DU17/DT17-1 -> 0.13179101 | DW89: =DW17/DU17-1 -> 0.047197979 | DX89: =DX17/DW17-1 -> 0.079175348 | DY89: =DY17/DX17-1 -> 0.043897978 | DZ89: =DZ17/DY17-1 -> -0.00058405529 | EB89: =EB17/DZ17-1 -> 0.11697672 | EC89: =EC17/EB17-1 -> -0.076735263 | ED89: =ED17/EC17-1 -> 0.063279184 | EE89: =EE17/ED17-1 -> 0.075945994 | EG89: =EG17/EE17-1 -> -0.017336746 | EH89: =EH17/EG17-1 -> -0.0036125347 | EI89: =EI17/EH17-1 -> 0.049494098 | EJ89: =EJ17/EI17-1 -> 0.053747891 | EL89: =EL17/EJ17-1 -> 0.033546813 | EM89: =EM17/EL17-1 -> 0.018589554 | EN89: =EN17/EM17-1 -> 0.097262457 | EO89: =EO17/EN17-1 -> 0.03900984 | EQ89: =EQ17/EO17-1 -> 0.033377735 | ER89: =ER17/EQ17-1 -> 0.016691799 | ES89: =ES17/ER17-1 -> 0.086883149 | ET89: =ET17/ES17-1 -> 0.036435735
A90: Sales & marketing | CE90: =CE20/CD20-1 -> 0.10313589 | CF90: =CF20/CE20-1 -> 0.028427037 | CG90: =CG20/CF20-1 -> 0.17199017 | CI90: =CI20/CG20-1 -> -0.093815514 | CJ90: =CJ20/CI20-1 -> 0.12261423 | CK90: =CK20/CJ20-1 -> 0.073673364 | CL90: =CL20/CK20-1 -> 0.14059501 | CN90: =CN20/CL20-1 -> -0.13125789 | CO90: =CO20/CN20-1 -> 0.0072639225 | CP90: =CP20/CO20-1 -> 0.06875 | CQ90: =CQ20/CP20-1 -> 0.20512821 | CS90: =CS20/CQ20-1 -> -0.10899589 | CT90: =CT20/CS20-1 -> 0.011730205 | CU90: =CU20/CT20-1 -> 0.062111801 | CV90: =CV20/CU20-1 -> 0.21559454 | CX90: =CX20/CV20-1 -> -0.15202053 | CY90: =CY20/CX20-1 -> 0.095688351 | CZ90: =CZ20/CY20-1 -> 0.050051778 | DA90: =DA20/CZ20-1 -> 0.41683103 | DC90: =DC20/DA20-1 -> -0.1638051 | DD90: =DD20/DC20-1 -> 0.048834628 | DE90: =DE20/DD20-1 -> 0.018253968 | DF90: =DF20/DE20-1 -> 0.32501949 | DH90: =DH20/DF20-1 -> -0.23431373 | DI90: =DI20/DH20-1 -> 0.078617157 | DJ90: =DJ20/DI20-1 -> 0.094254511 | DK90: =DK20/DJ20-1 -> 0.24495552 | DM90: =DM20/DK20-1 -> -0.21575462 | DN90: =DN20/DM20-1 -> -0.13311111 | DO90: =DO20/DN20-1 -> 0.084593694 | DP90: =DP20/DO20-1 -> 0.25596786 | DR90: =DR20/DP20-1 -> -0.15016936 | DS90: =DS20/DR20-1 -> 0.16829052 | DT90: =DT20/DS20-1 -> 0.045489007 | DU90: =DU20/DT20-1 -> 0.37853517 | DW90: =DW20/DU20-1 -> -0.23395581 | DX90: =DX20/DW20-1 -> 0.13819742 | DY90: =DY20/DX20-1 -> 0.045098039 | DZ90: =DZ20/DY20-1 -> 0.036657526 | EB90: =EB20/DZ20-1 -> -0.090491438 | EC90: =EC20/EB20-1 -> 0.03796112 | ED90: =ED20/EC20-1 -> 0.0151895 | EE90: =EE20/ED20-1 -> 0.12129576 | EG90: =EG20/EE20-1 -> -0.16750874 | EH90: =EH20/EG20-1 -> 0.056956116 | EI90: =EI20/EH20-1 -> 0.064045936 | EJ90: =EJ20/EI20-1 -> 0.01881832 | EL90: =EL20/EJ20-1 -> -0.16175472 | EM90: =EM20/EL20-1 -> 0.15051847 | EN90: =EN20/EM20-1 -> 0.014645825 | EO90: =EO20/EN20-1 -> 0.052471191 | EQ90: =EQ20/EO20-1 -> -0.14909481 | ER90: =ER20/EQ20-1 -> 0.19916206 | ES90: =ES20/ER20-1 -> -0.0043374012 | ET90: =ET20/ES20-1 -> 0.040623354
A91: General & administrative | CE91: =CE23/CD23-1 -> 0.081773399 | CF91: =CF23/CE23-1 -> 0.033697632 | CG91: =CG23/CF23-1 -> 0.043171806 | CI91: =CI23/CG23-1 -> 0.25760135 | CJ91: =CJ23/CI23-1 -> -0.057085292 | CK91: =CK23/CJ23-1 -> -0.027777778 | CL91: =CL23/CK23-1 -> 0.16703297 | CN91: =CN23/CL23-1 -> 0.027620841 | CO91: =CO23/CN23-1 -> -0.11423335 | CP91: =CP23/CO23-1 -> 0.01862069 | CQ91: =CQ23/CP23-1 -> 0.064319567 | CS91: =CS23/CQ23-1 -> -0.037531807 | CT91: =CT23/CS23-1 -> 0.073364177 | CU91: =CU23/CT23-1 -> 0.12315271 | CV91: =CV23/CU23-1 -> 0.10964912 | CX91: =CX23/CV23-1 -> -0.11017787 | CY91: =CY23/CX23-1 -> -0.056079956 | CZ91: =CZ23/CY23-1 -> -0.061764706 | DA91: =DA23/CZ23-1 -> 0.11347962 | DC91: =DC23/DA23-1 -> -0.21002252 | DD91: =DD23/DC23-1 -> 0.25730577 | DE91: =DE23/DD23-1 -> -0.0062358277 | DF91: =DF23/DE23-1 -> 0.14261266 | DH91: =DH23/DF23-1 -> 0.042436345 | DI91: =DI23/DH23-1 -> -0.021551724 | DJ91: =DJ23/DI23-1 -> 0.26823299 | DK91: =DK23/DJ23-1 -> 0.091856426 | DM91: =DM23/DK23-1 -> 0.018027572 | DN91: =DN23/DM23-1 -> -0.10243056 | DO91: =DO23/DN23-1 -> 0.06615087 | DP91: =DP23/DO23-1 -> 0.027213353 | DR91: =DR23/DP23-1 -> -0.02048746 | DS91: =DS23/DR23-1 -> 0.20483231 | DT91: =DT23/DS23-1 -> -0.025441485 | DU91: =DU23/DT23-1 -> 0.27149877 | DW91: =DW23/DU23-1 -> -0.18502415 | DX91: =DX23/DW23-1 -> 0.083876704 | DY91: =DY23/DX23-1 -> -0.016406891 | DZ91: =DZ23/DY23-1 -> 0.41673617 | EB91: =EB23/DZ23-1 -> -0.26236264 | EC91: =EC23/EB23-1 -> -0.073955839 | ED91: =ED23/EC23-1 -> 0.14306234 | EE91: =EE23/ED23-1 -> 0.30836894 | EG91: =EG23/EE23-1 -> -0.4187476 | EH91: =EH23/EG23-1 -> 0.043621943 | EI91: =EI23/EH23-1 -> 0.13964535 | EJ91: =EJ23/EI23-1 -> 0.2239511 | EL91: =EL23/EJ23-1 -> -0.19659478 | EM91: =EM23/EL23-1 -> 0.47188471 | EN91: =EN23/EM23-1 -> -0.24438472 | EO91: =EO23/EN23-1 -> 0.24374743 | EQ91: =EQ23/EO23-1 -> -0.22957949 | ER91: =ER23/EQ23-1 -> 0.012966866 | ES91: =ES23/ER23-1 -> 0.062040105 | ET91: =ET23/ES23-1 -> 0.28013927
A92: Stock compensation expense | R92: =R24/Q24-1 -> -0.010333863 | S92: =S24/R24-1 -> 0.65515395 | T92: =T24/S24-1 -> 0.28502103 | V92: =V24/T24-1 -> 3.5843404 | W92: =W24/V24-1 -> -0.061865012 | X92: =X24/W24-1 -> 1.1599298 | Y92: =Y24/X24-1 -> 0.15163834 | AA92: =AA24/Y24-1 -> -0.10014826 | AB92: =AB24/AA24-1 -> -0.022386986 | AC92: =AC24/AB24-1 -> -0.090688996 | AD92: =AD24/AC24-1 -> -0.12429944 | AF92: =AF24/AD24-1 -> -0.17844484 | AG92: =AG24/AF24-1 -> -0.032101088 | AH92: =AH24/AG24-1 -> -0.021758418 | AI92: =AI24/AH24-1 -> 0.25580893 | AK92: =AK24/AI24-1 -> 0.97173023 | AL92: =AL24/AK24-1 -> -0.048097049 | AM92: =AM24/AL24-1 -> -0.085103849 | AN92: =AN24/AM24-1 -> 0.34615462 | AP92: =AP24/AN24-1 -> 0.36777582 | AQ92: =AQ24/AP24-1 -> 0.31358707 | AR92: =AR24/AQ24-1 -> -0.18038787 | AS92: =AS24/AR24-1 -> 0.23916426 | AU92: =AU24/AS24-1 -> 0.14463514 | AV92: =AV24/AU24-1 -> -0.028502844 | AW92: =AW24/AV24-1 -> 0.026626243 | AX92: =AX24/AW24-1 -> 0.021900521 | AZ92: =AZ24/AX24-1 -> -0.030362859 | BA92: =BA24/AZ24-1 -> 0.056172811 | BB92: =BB24/BA24-1 -> 0.083451053 | BC92: =BC24/BB24-1 -> -0.13086446 | BE92: =BE24/BC24-1 -> 0.054447158 | BF92: =BF24/BE24-1 -> 0.06185567 | BG92: =BG24/BF24-1 -> 0.22977346 | BH92: =BH24/BG24-1 -> 0.042105263 | BJ92: =BJ24/BH24-1 -> 0.090909091 | BK92: =BK24/BJ24-1 -> 0.0069444444 | BL92: =BL24/BK24-1 -> 0.31264368 | BM92: =BM24/BL24-1 -> -0.061295972 | BT92: =BT24/BM24-1 -> 0.037313433 | BU92: =BU24/BT24-1 -> -0.0071942446 | BV92: =BV24/BU24-1 -> 0.24637681 | BW92: =BW24/BV24-1 -> -0.015988372 | BY92: =+#REF!/#REF!-1 -> #REF! | BZ92: =+#REF!/#REF!-1 -> #REF! | CA92: =+#REF!/#REF!-1 -> #REF! | CB92: =+#REF!/#REF!-1 -> #REF! | CD92: =CD24/BW24-1 -> -0.032496307 | CE92: =CE24/CD24-1 -> 0.13435115 | CF92: =CF24/CE24-1 -> 0.15208614 | CG92: =CG24/CF24-1 -> 0.019859813 | CI92: =CI24/CG24-1 -> -0.038946163 | CJ92: =CJ24/CI24-1 -> 0.0488677 | CK92: =CK24/CJ24-1 -> 0.42613636 | CL92: =CL24/CK24-1 -> -0.043027888 | CN92: =CN24/CL24-1 -> 0.0016652789 | CO92: =CO24/CN24-1 -> -0.059019119 | CP92: =CP24/CO24-1 -> 0.26501767 | CQ92: =CQ24/CP24-1 -> 0.0027932961 | CS92: =CS24/CQ24-1 -> 0.040389972 | CT92: =CT24/CS24-1 -> 0.0060240964 | CU92: =CU24/CT24-1 -> 0.23752495 | CV92: =CV24/CU24-1 -> -0.0075268817 | CX92: =CX24/CV24-1 -> 0.088299025 | CY92: =CY24/CX24-1 -> -0.0029865605 | CZ92: =CZ24/CY24-1 -> -0.091362956 | DA92: =DA24/CZ24-1 -> 0.014835165 | DC92: =DC24/DA24-1 -> 0.3302653 | DD92: =DD24/DC24-1 -> -0.017908018 | DE92: =DE24/DD24-1 -> -0.075839204 | DF92: =DF24/DE24-1 -> 0.010313901 | DH92: =DH24/DF24-1 -> 0.22902796 | DI92: =DI24/DH24-1 -> -0.0046948357 | DJ92: =DJ24/DI24-1 -> -0.047895501 | DK92: =DK24/DJ24-1 -> 0.0080030488 | DM92: =DM24/DK24-1 -> 0.20642722 | DN92: =DN24/DM24-1 -> 0.059855845 | DO92: =DO24/DN24-1 -> -0.055292726 | DP92: =DP24/DO24-1 -> 0.0087636933 | DR92: =DR24/DP24-1 -> 0.16196091 | DS92: =DS24/DR24-1 -> 0.015487316 | DT92: =DT24/DS24-1 -> 0.018669471 | DU92: =DU24/DT24-1 -> 0.02065049 | DW92: =DW24/DU24-1 -> 0.13909965 | DX92: =DX24/DW24-1 -> 0.061722913 | DY92: =DY24/DX24-1 -> 0.0405688 | DZ92: =DZ24/DY24-1 -> 0.024919614 | EB92: =EB24/DZ24-1 -> 0.036078431 | EC92: =EC24/EB24-1 -> 0.092732778 | ED92: =ED24/EC24-1 -> -0.005368895 | EE92: =EE24/ED24-1 -> -0.014626502 | EG92: =EG24/EE24-1 -> -0.069800318 | EH92: =EH24/EG24-1 -> 0.11417173 | EI92: =EI24/EH24-1 -> -0.0032395567 | EJ92: =EJ24/EI24-1 -> -0.0061580568 | EL92: =EL24/EJ24-1 -> -0.05060241 | EM92: =EM24/EL24-1 -> 0.087382161 | EN92: =EN24/EM24-1 -> 0.061687229 | EO92: =EO24/EN24-1 -> 0.024997884 | EQ92: =EQ24/EO24-1 -> -0.011448377 | ER92: =ER24/EQ24-1 -> 0.10014531 | ES92: =ES24/ER24-1 -> 0.053471243 | ET92: =ET24/ES24-1 -> -0.0034559737
A93: Total operating expenses | R93: =R26/Q26-1 -> 0.26349013 | S93: =S26/R26-1 -> 0.26760668 | T93: =T26/S26-1 -> 0.13491183 | V93: =V26/T26-1 -> 0.97352918 | W93: =W26/V26-1 -> 0.16029042 | X93: =X26/W26-1 -> 0.76372256 | Y93: =Y26/X26-1 -> 0.11397106 | AA93: =AA26/Y26-1 -> 0.034381808 | AB93: =AB26/AA26-1 -> 0.12147461 | AC93: =AC26/AB26-1 -> 0.14195301 | AD93: =AD26/AC26-1 -> 0.18667018 | AF93: =AF26/AD26-1 -> -0.023224685 | AG93: =AG26/AF26-1 -> 0.16073703 | AH93: =AH26/AG26-1 -> 0.26870857 | AI93: =AI26/AH26-1 -> 0.22407633 | AK93: =AK26/AI26-1 -> 0.25853179 | AL93: =AL26/AK26-1 -> 0.073354453 | AM93: =AM26/AL26-1 -> 0.088474084 | AN93: =AN26/AM26-1 -> 0.22601203 | AP93: =AP26/AN26-1 -> 0.11928882 | AQ93: =AQ26/AP26-1 -> 0.24372162 | AR93: =AR26/AQ26-1 -> 0.03308599 | AS93: =AS26/AR26-1 -> 0.14455292 | AU93: =AU26/AS26-1 -> 0.071043425 | AV93: =AV26/AU26-1 -> 0.073201726 | AW93: =AW26/AV26-1 -> 0.048533193 | AX93: =AX26/AW26-1 -> -0.039494213 | AZ93: =AZ26/AX26-1 -> -0.075993779 | BA93: =BA26/AZ26-1 -> 0.01184042 | BB93: =BB26/BA26-1 -> 0.067630501 | BC93: =BC26/BB26-1 -> 0.078763607 | BE93: =BE26/BC26-1 -> 0.028208432 | BF93: =BF26/BE26-1 -> 0.084193373 | BG93: =BG26/BF26-1 -> 0.099699399 | BH93: =BH26/BG26-1 -> 0.16492027 | BJ93: =BJ26/BH26-1 -> 0.13101291 | BK93: =BK26/BJ26-1 -> 0.045643154 | BL93: =BL26/BK26-1 -> 0.10978836 | BM93: =BM26/BL26-1 -> 0.028605483 | BO93: 0.22441217 | BP93: 0.35350529 | BQ93: 0.49135876 | BR93: 0.44351101 | BS93: 0.38494184 | BT93: =BT26/BM26-1 -> 0.025782155 | BU93: =BU26/BT26-1 -> 0.024004518 | BV93: =BV26/BU26-1 -> 0.082735797 | BW93: =BW26/BV26-1 -> 0.094243505 | BY93: 0.28438294 | BZ93: 0.22990472 | CA93: 0.033566434 | CB93: 0.13726671 | CC93: 0.15889229 | CD93: =CD26/BW26-1 -> -0.0533054 | CE93: =CE26/CD26-1 -> 0.093434964 | CF93: =CF26/CE26-1 -> 0.030807286 | CG93: =CG26/CF26-1 -> 0.096204188 | CI93: =CI26/CG26-1 -> 0.063482587 | CJ93: =CJ26/CI26-1 -> 0.044723054 | CK93: =CK26/CJ26-1 -> 0.093319004 | CL93: =CL26/CK26-1 -> 0.11123853 | CN93: =CN26/CL26-1 -> -0.048356185 | CO93: =CO26/CN26-1 -> -0.021068939 | CP93: =CP26/CO26-1 -> 0.096692515 | CQ93: =CQ26/CP26-1 -> 0.11991342 | CS93: =CS26/CQ26-1 -> -0.063651591 | CT93: =CT26/CS26-1 -> 0.018577129 | CU93: =CU26/CT26-1 -> 0.078762497 | CV93: =CV26/CU26-1 -> 0.097557921 | CX93: =CX26/CV26-1 -> -0.043016887 | CY93: =CY26/CX26-1 -> 0.37176583 | CZ93: =CZ26/CY26-1 -> -0.23146458 | DA93: =DA26/CZ26-1 -> 0.17529971 | DC93: =DC26/DA26-1 -> -0.033294842 | DD93: =DD26/DC26-1 -> 0.56569779 | DE93: =DE26/DD26-1 -> -0.3112086 | DF93: =DF26/DE26-1 -> 0.21257153 | DH93: =DH26/DF26-1 -> 0.044302352 | DI93: =DI26/DH26-1 -> -0.091187404 | DJ93: =DJ26/DI26-1 -> 0.10314405 | DK93: =DK26/DJ26-1 -> 0.14795696 | DM93: =DM26/DK26-1 -> -0.10063969 | DN93: =DN26/DM26-1 -> -0.059084507 | DO93: =DO26/DN26-1 -> 0.036075144 | DP93: =DP26/DO26-1 -> 0.095644008 | DR93: =DR26/DP26-1 -> -0.025911518 | DS93: =DS26/DR26-1 -> 0.10274807 | DT93: =DT26/DS26-1 -> 0.010680088 | DU93: =DU26/DT26-1 -> 0.24207458 | DW93: =DW26/DU26-1 -> -0.10434187 | DX93: =DX26/DW26-1 -> 0.098809914 | DY93: =DY26/DX26-1 -> 0.033336645 | DZ93: =DZ26/DY26-1 -> 0.083994423 | EB93: =EB26/DZ26-1 -> -0.03486206 | EC93: =EC26/EB26-1 -> -0.041819853 | ED93: =ED26/EC26-1 -> 0.060959233 | EE93: =EE26/ED26-1 -> 0.13186565 | EG93: =EG26/EE26-1 -> -0.14709641 | EH93: =EH26/EG26-1 -> 0.021306486 | EI93: =EI26/EH26-1 -> 0.067079321 | EJ93: =EJ26/EI26-1 -> 0.069221845 | EL93: =EL26/EJ26-1 -> -0.064981514 | EM93: =EM26/EL26-1 -> 0.12253406 | EN93: =EN26/EM26-1 -> 0.1390229 | EO93: =EO26/EN26-1 -> -0.051380453 | EQ93: =EQ26/EO26-1 -> -0.06126903 | ER93: =ER26/EQ26-1 -> 0.060605362 | ES93: =ES26/ER26-1 -> 0.058384201 | ET93: =ET26/ES26-1 -> 0.070772042
A94: GAAP operating income | R94: =R27/Q27-1 -> 1.0449135 | S94: =S27/R27-1 -> 0.83017654 | T94: =T27/S27-1 -> 0.46274138 | V94: =V27/T27-1 -> 0.017501712 | W94: =W27/V27-1 -> 0.23703162 | X94: =X27/W27-1 -> -0.36482669 | Y94: =Y27/X27-1 -> 0.29842539 | AA94: =AA27/Y27-1 -> 0.79734546 | AB94: =AB27/AA27-1 -> 0.1006612 | AC94: =AC27/AB27-1 -> 0.24072579 | AD94: =AD27/AC27-1 -> 0.427543 | AF94: =AF27/AD27-1 -> 0.46225714 | AG94: =AG27/AF27-1 -> 0.074368182 | AH94: =AH27/AG27-1 -> 0.11240955 | AI94: =AI27/AH27-1 -> 0.24655357 | AK94: =AK27/AI27-1 -> 0.12591565 | AL94: =AL27/AK27-1 -> 0.097849869 | AM94: =AM27/AL27-1 -> 0.14221607 | AN94: =AN27/AM27-1 -> 0.13879383 | AP94: =AP27/AN27-1 -> 0.15143872 | AQ94: =AQ27/AP27-1 -> -0.095474239 | AR94: =AR27/AQ27-1 -> 0.19302834 | AS94: =AS27/AR27-1 -> 0.093256602 | AU94: =AU27/AS27-1 -> 0.073227258 | AV94: =AV27/AU27-1 -> 0.020520813 | AW94: =AW27/AV27-1 -> 0.044107442 | AX94: =AX27/AW27-1 -> 0.12906259 | AZ94: =AZ27/AX27-1 -> 0.012572277 | BA94: =BA27/AZ27-1 -> -0.0051481452 | BB94: =BB27/BA27-1 -> 0.1066357 | BC94: =BC27/BB27-1 -> 0.19639363 | BE94: =BE27/BC27-1 -> 0.0028283144 | BF94: =BF27/BE27-1 -> -0.049437299 | BG94: =BG27/BF27-1 -> 0.076955603 | BH94: =BH27/BG27-1 -> 0.17078916 | BJ94: =BJ27/BH27-1 -> -0.062374245 | BK94: =BK27/BJ27-1 -> 0.030400572 | BL94: =BL27/BK27-1 -> 0.061437001 | BM94: =BM27/BL27-1 -> 0.14682799 | BO94: 0.2120887 | BP94: 0.11176675 | BQ94: -0.10529758 | BR94: -0.032221272 | BS94: 0.03920928 | BT94: =BT27/BM27-1 -> -0.033646992 | BU94: =BU27/BT27-1 -> 0.013868398 | BV94: =BV27/BU27-1 -> -0.050349243 | BW94: =BW27/BV27-1 -> 0.14832976 | BY94: 0.025966362 | BZ94: -0.024976584 | CA94: 0.25877193 | CB94: 0.15556865 | CC94: 0.097783367 | CD94: =CD27/BW27-1 -> 0.00026688017 | CE94: =CE27/CD27-1 -> -0.075506937 | CF94: =CF27/CE27-1 -> 0.085425685 | CG94: =CG27/CF27-1 -> 0.17761234 | CI94: =CI27/CG27-1 -> -0.070896365 | CJ94: =CJ27/CI27-1 -> 0.034750911 | CK94: =CK27/CJ27-1 -> -0.12541099 | CL94: =CL27/CK27-1 -> 0.18125671 | CN94: =CN27/CL27-1 -> 0.010911571 | CO94: =CO27/CN27-1 -> 0.085001124 | CP94: =CP27/CO27-1 -> -0.024248705 | CQ94: =CQ27/CP27-1 -> 0.14273577 | CS94: =CS27/CQ27-1 -> -0.007063197 | CT94: =CT27/CS27-1 -> 0.11718458 | CU94: =CU27/CT27-1 -> -0.033679625 | CV94: =CV27/CU27-1 -> 0.15120513 | CX94: =CX27/CV27-1 -> -0.010694382 | CY94: =CY27/CX27-1 -> -0.37088916 | CZ94: =CZ27/CY27-1 -> 0.88334947 | DA94: =DA27/CZ27-1 -> -0.015163197 | DC94: =DC27/DA27-1 -> -0.0040448852 | DD94: =DD27/DC27-1 -> -0.60107428 | DE94: =DE27/DD27-1 -> 1.8325123 | DF94: =DF27/DE27-1 -> -0.04684058 | DH94: =DH27/DF27-1 -> -0.19620484 | DI94: =DI27/DH27-1 -> 0.38922518 | DJ94: =DJ27/DI27-1 -> -0.00032679739 | DK94: =DK27/DJ27-1 -> 0.0096981584 | DM94: =DM27/DK27-1 -> -0.13911073 | DN94: =DN27/DM27-1 -> -0.1998245 | DO94: =DO27/DN27-1 -> 0.75669748 | DP94: =DP27/DO27-1 -> 0.3957906 | DR94: =DR27/DP27-1 -> 0.050220433 | DS94: =DS27/DR27-1 -> 0.17789134 | DT94: =DT27/DS27-1 -> 0.086255875 | DU94: =DU27/DT27-1 -> 0.040606723 | DW94: =DW27/DU27-1 -> -0.081836875 | DX94: =DX27/DW27-1 -> -0.03190007 | DY94: =DY27/DX27-1 -> -0.119159 | DZ94: =DZ27/DY27-1 -> 0.059819084 | EB94: =EB27/DZ27-1 -> -0.041024229 | EC94: =EC27/EB27-1 -> 0.25397646 | ED94: =ED27/EC27-1 -> -0.022666911 | EE94: =EE27/ED27-1 -> 0.11029377 | EG94: =EG27/EE27-1 -> 0.074903996 | EH94: =EH27/EG27-1 -> 0.076672425 | EI94: =EI27/EH27-1 -> 0.039963537 | EJ94: =EJ27/EI27-1 -> 0.085936678 | EL94: =EL27/EJ27-1 -> -0.011817125 | EM94: =EM27/EL27-1 -> 0.021727766 | EN94: =EN27/EM27-1 -> -0.0013750759 | EO94: =EO27/EN27-1 -> 0.19570086 | EQ94: =EQ27/EO27-1 -> -0.0057573783 | ER94: =ER27/EQ27-1 -> 0.048624655 | ES94: =ES27/ER27-1 -> 0.030376798 | ET94: =ET27/ES27-1 -> 0.086582608
A95: EBITDA | V95: =V57/T57-1 -> 0.44548375 | W95: =W57/V57-1 -> 0.14541261 | X95: =X57/W57-1 -> 0.10218828 | Y95: =Y57/X57-1 -> 0.13735541 | AA95: =AA57/Y57-1 -> 0.34974878 | AB95: =AB57/AA57-1 -> 0.086937461 | AC95: =AC57/AB57-1 -> 0.15751168 | AD95: =AD57/AC57-1 -> 0.32283406 | AF95: =AF57/AD57-1 -> 0.28855037 | AG95: =AG57/AF57-1 -> 0.076831955 | AH95: =AH57/AG57-1 -> 0.13948624 | AI95: =AI57/AH57-1 -> 0.2104701 | AK95: =AK57/AI57-1 -> 0.23198119 | AL95: =AL57/AK57-1 -> 0.048099741 | AM95: =AM57/AL57-1 -> 0.12615752 | AN95: =AN57/AM57-1 -> 0.16983844 | AP95: =AP57/AN57-1 -> 0.1631156 | AQ95: =AQ57/AP57-1 -> -0.022926621 | AR95: =AR57/AQ57-1 -> 0.11973031 | AS95: =AS57/AR57-1 -> 0.12174909 | AU95: =AU57/AS57-1 -> 0.094924518 | AV95: =AV57/AU57-1 -> 0.036426446 | AW95: =AW57/AV57-1 -> 0.074298013 | AX95: =AX57/AW57-1 -> 0.051033023 | AZ95: =AZ57/AX57-1 -> 0.012800734 | BA95: =BA57/AZ57-1 -> -0.0079456506 | BB95: =BB57/BA57-1 -> 0.088818403 | BC95: =BC57/BB57-1 -> 0.12729668 | BE95: =BE57/BC57-1 -> -0.0039914004 | BF95: =BF57/BE57-1 -> -0.03022508 | BG95: =BG57/BF57-1 -> 0.083885942 | BH95: =BH57/BG57-1 -> 0.14989293 | BJ95: =BJ57/BH57-1 -> -0.034583666 | BK95: =BK57/BJ57-1 -> 0.039129237 | BL95: =BL57/BK57-1 -> 0.092813577 | BM95: =BM57/BL57-1 -> 0.10313031 | BO95: -0.019797624 | BP95: 0.036804309 | BQ95: 0.0017316017 | BR95: 0.12899741 | BT95: =BT57/BM57-1 -> -0.019797624 | BU95: =BU57/BT57-1 -> 0.045332136 | BV95: =BV57/BU57-1 -> 0.025976814 | BW95: =BW57/BV57-1 -> 0.12513078 | BY95: -0.048995215 | BZ95: -0.0066411753 | CA95: 0.074554295 | CB95: 0.1076546 | CD95: =CD57/BW57-1 -> -0.013948298 | CE95: =CE57/CD57-1 -> -0.012070917 | CF95: =CF57/CE57-1 -> 0.067392134 | CG95: =CG57/CF57-1 -> 0.13360758 | CI95: =CI57/CG57-1 -> -0.047017987 | CJ95: =CJ57/CI57-1 -> 0.029304636 | CK95: =CK57/CJ57-1 -> 0.049702429 | CL95: =CL57/CK57-1 -> 0.052252528 | CN95: =CN57/CL57-1 -> -0.00582496 | CO95: =CO57/CN57-1 -> 0.053317709 | CP95: =CP57/CO57-1 -> 0.027395355 | CQ95: =CQ57/CP57-1 -> 0.11261505 | CS95: =CS57/CQ57-1 -> -0.0015815085 | CT95: =CT57/CS57-1 -> 0.091872792 | CU95: =CU57/CT57-1 -> 0.029237808 | CV95: =CV57/CU57-1 -> 0.10289494 | CX95: =CX57/CV57-1 -> -0.0090444357 | CY95: =CY57/CX57-1 -> 0.041269841 | CZ95: =CZ57/CY57-1 -> 0.082602896 | DA95: =DA57/CZ57-1 -> 0.015312858 | DC95: =DC57/DA57-1 -> 0.046719251 | DD95: =DD57/DC57-1 -> 0.046952633 | DE95: =DE57/DD57-1 -> 0.044846951 | DF95: =DF57/DE57-1 -> -0.011809235 | DH95: =DH57/DF57-1 -> 0.048490884 | DI95: =DI57/DH57-1 -> 0.07919924 | DJ95: =DJ57/DI57-1 -> -0.0033850112 | DK95: =DK57/DJ57-1 -> 0.040961891 | DM95: =DM57/DK57-1 -> -0.068389454 | DN95: =DN57/DM57-1 -> -0.078803586 | DO95: =DO57/DN57-1 -> 0.36004867 | DP95: =DP57/DO57-1 -> 0.26350218 | DR95: =DR57/DP57-1 -> 0.014867915 | DS95: =DS57/DR57-1 -> 0.13839111 | DT95: =DT57/DS57-1 -> 0.080432035 | DU95: =DU57/DT57-1 -> 0.037895707 | DW95: =DW57/DU57-1 -> -0.030671494 | DX95: =DX57/DW57-1 -> -0.0086680761 | DY95: =DY57/DX57-1 -> -0.070270847 | DZ95: =DZ57/DY57-1 -> 0.049852812 | EB95: =EB57/DZ57-1 -> -0.057390481 | EC95: =EC57/EB57-1 -> 0.19795248 | ED95: =ED57/EC57-1 -> -0.0039665903 | EE95: =EE57/ED57-1 -> 0.057825552 | EG95: =EG57/EE57-1 -> 0.045206905 | EH95: =EH57/EG57-1 -> 0.083428504 | EI95: =EI57/EH57-1 -> 0.036596573 | EJ95: =EJ57/EI57-1 -> 0.068705674 | EL95: =EL57/EJ57-1 -> -0.0092224364 | EM95: =EM57/EL57-1 -> 0.040828388 | EN95: =EN57/EM57-1 -> 0.10402915 | EO95: =EO57/EN57-1 -> 0.077870123 | EQ95: =EQ57/EO57-1 -> 0.016345005 | ER95: =ER57/EQ57-1 -> 0.070678326 | ES95: =ES57/ER57-1 -> 0.045914785 | ET95: =ET57/ES57-1 -> 0.082874545
A96: GAAP EPS | V96: =V37/T37-1 -> -0.44915479 | W96: =W37/V37-1 -> 0.20479929 | X96: =X37/W37-1 -> -0.36502114 | Y96: =Y37/X37-1 -> 0.30785453 | AA96: =AA37/Y37-1 -> 1.3328769 | AB96: =AB37/AA37-1 -> 0.2260559 | AC96: =AC37/AB37-1 -> -0.36269808 | AD96: =AD37/AC37-1 -> 2.7723733 | AF96: =AF37/AD37-1 -> 0.80466698 | AG96: =AG37/AF37-1 -> -0.073474094 | AH96: =AH37/AG37-1 -> 0.10257391 | AI96: =AI37/AH37-1 -> -0.069475622 | AK96: =AK37/AI37-1 -> 0.59050026 | AL96: =AL37/AK37-1 -> 0.1942104 | AM96: =AM37/AL37-1 -> 0.015280391 | AN96: =AN37/AM37-1 -> 0.3925332 | AP96: =AP37/AN37-1 -> -0.032060143 | AQ96: =AQ37/AP37-1 -> -0.078628586 | AR96: =AR37/AQ37-1 -> 0.15254506 | AS96: =AS37/AR37-1 -> 0.12275498 | AU96: =AU37/AS37-1 -> 0.085235268 | AV96: =AV37/AU37-1 -> -0.04756381 | AW96: =AW37/AV37-1 -> 0.034912581 | AX96: =AX37/AW37-1 -> -0.70266575 | AZ96: =AZ37/AX37-1 -> 2.716189 | BA96: =BA37/AZ37-1 -> 0.03906896 | BB96: =BB37/BA37-1 -> 0.099847228 | BC96: =BC37/BB37-1 -> 0.19543586 | BE96: =BE37/BC37-1 -> -0.011041332 | BF96: =BF37/BE37-1 -> -0.058467472 | BG96: =BG37/BF37-1 -> 0.17811559 | BH96: =BH37/BG37-1 -> 0.16212401 | BJ96: =BJ37/BH37-1 -> -0.29479591 | BK96: =BK37/BJ37-1 -> 0.39469748 | BL96: =BL37/BK37-1 -> 0.084753241 | BM96: =BM37/BL37-1 -> -0.013503381 | BO96: -0.019797624 | BP96: 0.036804309 | BQ96: 0.0017316017 | BR96: 0.12899741 | BT96: =BT37/BM37-1 -> -0.467639 | BU96: =BU37/BT37-1 -> 0.042216554 | BV96: =BV37/BU37-1 -> -0.11114777 | BW96: =BW37/BV37-1 -> 0.069396252 | BY96: -0.048995215 | BZ96: -0.0066411753 | CA96: 0.074554295 | CB96: 0.1076546 | CD96: =CD37/BW37-1 -> 0.14603901 | CE96: =CE37/CD37-1 -> -0.040039232 | CF96: =CF37/CE37-1 -> -0.082361209 | CG96: =CG37/CF37-1 -> 0.13080688 | CI96: =CI37/CG37-1 -> -0.006254376 | CJ96: =CJ37/CI37-1 -> -0.0071283375 | CK96: =CK37/CJ37-1 -> -0.18525288 | CL96: =CL37/CK37-1 -> 0.70624729 | CN96: =CN37/CL37-1 -> -0.24932808 | CO96: =CO37/CN37-1 -> 0.11635961 | CP96: =CP37/CO37-1 -> 0.0071941831 | CQ96: =CQ37/CP37-1 -> 0.23244229 | CS96: =CS37/CQ37-1 -> -0.14823327 | CT96: =CT37/CS37-1 -> 0.16335743 | CU96: =CU37/CT37-1 -> 0.035361264 | CV96: =CV37/CU37-1 -> 0.043969012 | CX96: =CX37/CV37-1 -> 0.021705108 | CY96: =CY37/CX37-1 -> -0.35188878 | CZ96: =CZ37/CY37-1 -> 0.90975096 | DA96: =DA37/CZ37-1 -> -1.4544886 | DC96: =DC37/DA37-1 -> -4.0664277 | DD96: =DD37/DC37-1 -> -0.65923061 | DE96: =DE37/DD37-1 -> 1.8744938 | DF96: =DF37/DE37-1 -> -0.022433777 | DH96: =DH37/DF37-1 -> -0.25601364 | DI96: =DI37/DH37-1 -> 0.49619124 | DJ96: =DJ37/DI37-1 -> -0.28764791 | DK96: =DK37/DJ37-1 -> 0.51628831 | DM96: =DM37/DK37-1 -> -0.35667664 | DN96: =DN37/DM37-1 -> 0.025761757 | DO96: =DO37/DN37-1 -> 0.61894461 | DP96: =DP37/DO37-1 -> 0.35958523 | DR96: =DR37/DP37-1 -> 0.17906392 | DS96: =DS37/DR37-1 -> 0.036922918 | DT96: =DT37/DS37-1 -> 0.026859602 | DU96: =DU37/DT37-1 -> 0.096618982 | DW96: =DW37/DU37-1 -> -0.19786461 | DX96: =DX37/DW37-1 -> -0.018167513 | DY96: =DY37/DX37-1 -> -0.12130892 | DZ96: =DZ37/DY37-1 -> -0.0092132627 | EB96: =EB37/DZ37-1 -> 0.11542462 | EC96: =EC37/EB37-1 -> 0.2260251 | ED96: =ED37/EC37-1 -> 0.077659769 | EE96: =EE37/ED37-1 -> 0.058525425 | EG96: =EG37/EE37-1 -> 0.15065819 | EH96: =EH37/EG37-1 -> 0.00073911062 | EI96: =EI37/EH37-1 -> 0.12036721 | EJ96: =EJ37/EI37-1 -> 0.014736316 | EL96: =EL37/EJ37-1 -> 0.30766433 | EM96: =EM37/EL37-1 -> -0.17744725 | EN96: =EN37/EM37-1 -> 0.24005773 | EO96: =EO37/EN37-1 -> -0.0918395 | EQ96: =EQ37/EO37-1 -> -0.0061385269 | ER96: =ER37/EQ37-1 -> 0.044341189 | ES96: =ES37/ER37-1 -> 0.027214032 | ET96: =ET37/ES37-1 -> 0.085113436
A97: Non-GAAP EPS | V97: =V43/T43-1 -> #DIV/0! | W97: =W43/V43-1 -> #DIV/0! | X97: =X43/W43-1 -> #DIV/0! | Y97: =Y43/X43-1 -> #DIV/0! | AA97: =AA43/Y43-1 -> #DIV/0! | AB97: =AB43/AA43-1 -> #DIV/0! | AC97: =AC43/AB43-1 -> #DIV/0! | AD97: =AD43/AC43-1 -> #DIV/0! | AF97: =AF43/AD43-1 -> #DIV/0! | AG97: =AG43/AF43-1 -> #DIV/0! | AH97: =AH43/AG43-1 -> #DIV/0! | AI97: =AI43/AH43-1 -> #DIV/0! | AK97: =AK43/AI43-1 -> #DIV/0! | AL97: =AL43/AK43-1 -> #DIV/0! | AM97: =AM43/AL43-1 -> #DIV/0! | AN97: =AN43/AM43-1 -> #DIV/0! | AP97: =AP43/AN43-1 -> #DIV/0! | AQ97: =AQ43/AP43-1 -> #DIV/0! | AR97: =AR43/AQ43-1 -> #DIV/0! | AS97: =AS43/AR43-1 -> #DIV/0! | AU97: =AU43/AS43-1 -> #DIV/0! | AV97: =AV43/AU43-1 -> #DIV/0! | AW97: =AW43/AV43-1 -> #DIV/0! | AX97: =AX43/AW43-1 -> #DIV/0! | AZ97: =AZ43/AX43-1 -> #DIV/0! | BA97: =BA43/AZ43-1 -> #DIV/0! | BB97: =BB43/BA43-1 -> #DIV/0! | BC97: =BC43/BB43-1 -> #DIV/0! | BE97: =BE43/BC43-1 -> #DIV/0! | BF97: =BF43/BE43-1 -> #DIV/0! | BG97: =BG43/BF43-1 -> #DIV/0! | BH97: =BH43/BG43-1 -> #DIV/0! | BJ97: =BJ43/BH43-1 -> #DIV/0! | BK97: =BK43/BJ43-1 -> #DIV/0! | BL97: =BL43/BK43-1 -> #DIV/0! | BM97: =BM43/BL43-1 -> #DIV/0! | BO97: -0.019797624 | BP97: 0.036804309 | BQ97: 0.0017316017 | BR97: 0.12899741 | BT97: =BT43/BM43-1 -> #DIV/0! | BU97: =BU43/BT43-1 -> #DIV/0! | BV97: =BV43/BU43-1 -> #DIV/0! | BW97: =BW43/BV43-1 -> #DIV/0! | BY97: -0.048995215 | BZ97: -0.0066411753 | CA97: 0.074554295 | CB97: 0.1076546 | CD97: =CD43/BW43-1 -> #DIV/0! | CE97: =CE43/CD43-1 -> -0.040039232 | CF97: =CF43/CE43-1 -> -0.082361209 | CG97: =CG43/CF43-1 -> 0.13080688 | CI97: =CI43/CG43-1 -> -0.006254376 | CJ97: =CJ43/CI43-1 -> -0.0071283375 | CK97: =CK43/CJ43-1 -> -0.072796247 | CL97: =CL43/CK43-1 -> 0.49930375 | CN97: =CN43/CL43-1 -> -0.24932808 | CO97: =CO43/CN43-1 -> 0.11635961 | CP97: =CP43/CO43-1 -> 0.0071941831 | CQ97: =CQ43/CP43-1 -> 0.23244229 | CS97: =CS43/CQ43-1 -> -0.14823327 | CT97: =CT43/CS43-1 -> 0.16335743 | CU97: =CU43/CT43-1 -> 0.035361264 | CV97: =CV43/CU43-1 -> 0.051064139 | CX97: =CX43/CV43-1 -> 0.014808168 | CY97: =CY43/CX43-1 -> 0.15129859 | CZ97: =CZ43/CY43-1 -> 0.07507386 | DA97: =DA43/CZ43-1 -> 19.272678 | DC97: =DC43/DA43-1 -> -0.93125445 | DD97: =DD43/DC43-1 -> -0.11837253 | DE97: =DE43/DD43-1 -> 0.11105827 | DF97: =DF43/DE43-1 -> -0.022433777 | DH97: =DH43/DF43-1 -> -0.068033308 | DI97: =DI43/DH43-1 -> 0.19440522 | DJ97: =DJ43/DI43-1 -> -0.28764791 | DK97: =DK43/DJ43-1 -> 0.51628831 | DM97: =DM43/DK43-1 -> -0.35667664 | DN97: =DN43/DM43-1 -> 0.025761757 | DO97: =DO43/DN43-1 -> 0.61894461 | DP97: =DP43/DO43-1 -> 0.35958523 | DR97: =DR43/DP43-1 -> 0.17906392 | DS97: =DS43/DR43-1 -> 0.036922918 | DT97: =DT43/DS43-1 -> 0.026859602 | DU97: =DU43/DT43-1 -> 0.096618982 | DW97: =DW43/DU43-1 -> -0.19786461 | DX97: =DX43/DW43-1 -> -0.018167513 | DY97: =DY43/DX43-1 -> -0.12130892 | DZ97: =DZ43/DY43-1 -> -0.0092132627 | EB97: =EB43/DZ43-1 -> 0.11542462 | EC97: =EC43/EB43-1 -> 0.2260251 | ED97: =ED43/EC43-1 -> 0.077659769 | EE97: =EE43/ED43-1 -> 0.058525425 | EG97: =EG43/EE43-1 -> 0.15065819 | EH97: =EH43/EG43-1 -> 0.00073911062 | EI97: =EI43/EH43-1 -> 0.12036721 | EJ97: =EJ43/EI43-1 -> 0.014736316 | EL97: =EL43/EJ43-1 -> 0.30766433 | EM97: =EM43/EL43-1 -> -0.17744725 | EN97: =EN43/EM43-1 -> 0.36261354 | EO97: =EO43/EN43-1 -> -0.17352102 | EQ97: =EQ43/EO43-1 -> -0.0061385269 | ER97: =ER43/EQ43-1 -> 0.044341189 | ES97: =ES43/ER43-1 -> 0.027214032 | ET97: =ET43/ES43-1 -> 0.085113436
A98: JPMe Adjusted EPS | V98: =V51/T51-1 -> 0.12843006 | W98: =W51/V51-1 -> 0.030205681 | X98: =X51/W51-1 -> 0.42040915 | Y98: =Y51/X51-1 -> 0.167641 | AA98: =AA51/Y51-1 -> 0.24364035 | AB98: =AB51/AA51-1 -> 0.086546775 | AC98: =AC51/AB51-1 -> 0.11312305 | AD98: =AD51/AC51-1 -> 0.053780544 | AF98: =AF51/AD51-1 -> 0.84021694 | AG98: =AG51/AF51-1 -> 0.063118228 | AH98: =AH51/AG51-1 -> 0.13858986 | AI98: =AI51/AH51-1 -> 0.023284036 | AK98: =AK51/AI51-1 -> 0.4893476 | AL98: =AL51/AK51-1 -> 0.082748222 | AM98: =AM51/AL51-1 -> 0.050166915 | AN98: =AN51/AM51-1 -> 0.21647149 | AP98: =AP51/AN51-1 -> 0.15719184 | AQ98: =AQ51/AP51-1 -> -0.032560889 | AR98: =AR51/AQ51-1 -> 0.096967035 | AS98: =AS51/AR51-1 -> 0.13467734 | AU98: =AU51/AS51-1 -> 0.092383603 | AV98: =AV51/AU51-1 -> -0.044008957 | AW98: =AW51/AV51-1 -> 0.062407469 | AX98: =AX51/AW51-1 -> 0.03679217 | AZ98: =AZ51/AX51-1 -> 0.011459939 | BA98: =BA51/AZ51-1 -> 0.039643244 | BB98: =BB51/BA51-1 -> 0.098685334 | BC98: =BC51/BB51-1 -> 0.15272795 | BE98: =BE51/BC51-1 -> -0.0046028996 | BF98: =BF51/BE51-1 -> -0.04640692 | BG98: =BG51/BF51-1 -> 0.18462359 | BH98: =BH51/BG51-1 -> 0.14636215 | BJ98: =BJ51/BH51-1 -> -0.076788036 | BK98: =BK51/BJ51-1 -> 0.081134264 | BL98: =BL51/BK51-1 -> 0.11279653 | BM98: =BM51/BL51-1 -> -0.022567693 | BO98: -0.019797624 | BP98: 0.036804309 | BQ98: 0.0017315117 | BR98: 0.12899741 | BT98: =BT51/BM51-1 -> -0.46968844 | BU98: =BU51/BT51-1 -> 0.014807366 | BV98: =BV51/BU51-1 -> -0.073256639 | BW98: =BW51/BV51-1 -> 0.17137088 | BY98: -0.048995215 | BZ98: -0.0066411753 | CA98: 0.074554295 | CB98: 0.10765451 | CD98: =CD51/BW51-1 -> 0.081117678 | CE98: =CE51/CD51-1 -> -0.16496356 | CF98: =CF51/CE51-1 -> 0.16436243 | CG98: =CG51/CF51-1 -> 0.15483988 | CI98: =CI51/CG51-1 -> -0.08681265 | CJ98: =CJ51/CI51-1 -> -0.028283464 | CK98: =CK51/CJ51-1 -> 0.044281822 | CL98: =CL51/CK51-1 -> 0.082152557 | CN98: =CN51/CL51-1 -> -0.042954559 | CO98: =CO51/CN51-1 -> 0.08051621 | CP98: =CP51/CO51-1 -> 0.051297332 | CQ98: =CQ51/CP51-1 -> 0.17983924 | CS98: =CS51/CQ51-1 -> -0.13439605 | CT98: =CT51/CS51-1 -> 0.12132902 | CU98: =CU51/CT51-1 -> 0.07632532 | CV98: =CV51/CU51-1 -> 0.033879605 | CX98: =CX51/CV51-1 -> 0.068542962 | CY98: =CY51/CX51-1 -> 0.13971915 | CZ98: =CZ51/CY51-1 -> 0.030196541 | DA98: =DA51/CZ51-1 -> 19.297881 | DC98: =DC51/DA51-1 -> -0.94437864 | DD98: =DD51/DC51-1 -> 0.022038134 | DE98: =DE51/DD51-1 -> 0.080391115 | DF98: =DF51/DE51-1 -> -0.049146603 | DH98: =DH51/DF51-1 -> -0.00027071512 | DI98: =DI51/DH51-1 -> 0.055759889 | DJ98: =DJ51/DI51-1 -> -0.0076458987 | DK98: =DK51/DJ51-1 -> 0.23204113 | DM98: =DM51/DK51-1 -> -0.16737983 | DN98: =DN51/DM51-1 -> -0.16594122 | DO98: =DO51/DN51-1 -> 0.46240796 | DP98: =DP51/DO51-1 -> 0.25891977 | DR98: =DR51/DP51-1 -> 0.10346806 | DS98: =DS51/DR51-1 -> 0.15179078 | DT98: =DT51/DS51-1 -> 0.051089869 | DU98: =DU51/DT51-1 -> 0.074396999 | DW98: =DW51/DU51-1 -> -0.013729253 | DX98: =DX51/DW51-1 -> -0.033673487 | DY98: =DY51/DX51-1 -> -0.053832803 | DZ98: =DZ51/DY51-1 -> -0.012787054 | EB98: =EB51/DZ51-1 -> 0.032021169 | EC98: =EC51/EB51-1 -> 0.23622726 | ED98: =ED51/EC51-1 -> 0.099801526 | EE98: =EE51/ED51-1 -> -0.0053311523 | EG98: =EG51/EE51-1 -> 0.035389694 | EH98: =EH51/EG51-1 -> 0.11203843 | EI98: =EI51/EH51-1 -> 0.0083757693 | EJ98: =EJ51/EI51-1 -> 0.061164095 | EL98: =EL51/EJ51-1 -> -0.010951698 | EM98: =EM51/EL51-1 -> 0.045621685 | EN98: =EN51/EM51-1 -> 0.051736153 | EO98: =EO51/EN51-1 -> 0.11339257 | EQ98: =EQ51/EO51-1 -> -0.0069159057 | ER98: =ER51/EQ51-1 -> 0.052233357 | ES98: =ES51/ER51-1 -> 0.03106813 | ET98: =ET51/ES51-1 -> 0.071168383
A99: Seasonality
A100: Gross revenues | CI100: =CI7/CM7 -> 0.23363282 | CJ100: =CJ7/CM7 -> 0.24173876 | CK100: =CK7/CM7 -> 0.25034469 | CL100: =CL7/CM7 -> 0.27428372 | CM100: =SUM(CI100:CL100) -> 1 | CN100: =CN7/CR7 -> 0.23014042 | CO100: =CO7/CR7 -> 0.23639467 | CP100: =CP7/CR7 -> 0.24903653 | CQ100: =CQ7/CR7 -> 0.28442838 | CR100: =SUM(CN100:CQ100) -> 1 | CS100: =CS7/CW7 -> 0.22439959 | CT100: =CT7/CW7 -> 0.23816909 | CU100: =CU7/CW7 -> 0.24870392 | CV100: =CV7/CW7 -> 0.2887274 | CW100: =SUM(CS100:CV100) -> 1 | CX100: =CX7/DB7 -> 0.22326462 | CY100: =CY7/DB7 -> 0.23463082 | CZ100: =CZ7/DB7 -> 0.25052546 | DA100: =DA7/DB7 -> 0.29157909 | DB100: =SUM(CX100:DA100) -> 1 | DC100: =DC7/DG7 -> 0.22764382 | DD100: =DD7/DG7 -> 0.23868761 | DE100: =DE7/DG7 -> 0.24660318 | DF100: =DF7/DG7 -> 0.28706539 | DG100: =SUM(DC100:DF100) -> 1 | DH100: =DH7/DL7 -> 0.224513 | DI100: =DI7/DL7 -> 0.24060745 | DJ100: =DJ7/DL7 -> 0.2502147 | DK100: =DK7/DL7 -> 0.28466486 | DL100: =SUM(DH100:DK100) -> 1 | DM100: =DM7/DQ7 -> 0.22549541 | DN100: =DN7/DQ7 -> 0.20981553 | DO100: =DO7/DQ7 -> 0.25296531 | DP100: =DP7/DQ7 -> 0.31172374 | DQ100: =SUM(DM100:DP100) -> 1 | DR100: =DR7/DV7 -> 0.21469742 | DS100: =DS7/DV7 -> 0.24018289 | DT100: =DT7/DV7 -> 0.25275096 | DU100: =DU7/DV7 -> 0.29236872 | DV100: =SUM(DR100:DU100) -> 1 | DW100: =DW7/EA7 -> 0.2404609 | DX100: =DX7/EA7 -> 0.24637953 | DY100: =DY7/EA7 -> 0.24428291 | DZ100: =DZ7/EA7 -> 0.26887666 | EA100: =SUM(DW100:DZ100) -> 1 | EB100: =EB7/EF7 -> 0.22702785 | EC100: =EC7/EF7 -> 0.2426983 | ED100: =ED7/EF7 -> 0.24949413 | EE100: =EE7/EF7 -> 0.28077972 | EF100: =SUM(EB100:EE100) -> 1 | EG100: =EG7/EK7 -> 0.23009959 | EH100: =EH7/EK7 -> 0.24210755 | EI100: =EI7/EK7 -> 0.25218132 | EJ100: =EJ7/EK7 -> 0.27561154 | EK100: =SUM(EG100:EJ100) -> 1 | EL100: =EL7/EP7 -> 0.22487981 | EM100: =EM7/EP7 -> 0.24031641 | EN100: =EN7/EP7 -> 0.25506516 | EO100: =EO7/EP7 -> 0.27973862 | EP100: =SUM(EL100:EO100) -> 1 | EQ100: =EQ7/EU7 -> 0.22704279 | ER100: =ER7/EU7 -> 0.24047195 | ES100: =ES7/EU7 -> 0.25387153 | ET100: =ET7/EU7 -> 0.27861373 | EU100: =SUM(EQ100:ET100) -> 1
A101: Traffic Acquisition Costs (TAC) | CI101: =CI8/CM8 -> 0.23946062 | CJ101: =CJ8/CM8 -> 0.24398014 | CK101: =CK8/CM8 -> 0.24805512 | CL101: =CL8/CM8 -> 0.26820775 | CM101: =SUM(CI101:CL101) -> 0.99970364 | CN101: =CN8/CR8 -> 0.23321481 | CO101: =CO8/CR8 -> 0.23544586 | CP101: =CP8/CR8 -> 0.24862302 | CQ101: =CQ8/CR8 -> 0.28271631 | CR101: =SUM(CN101:CQ101) -> 1 | CS101: =CS8/CW8 -> 0.22557018 | CT101: =CT8/CW8 -> 0.23670577 | CU101: =CU8/CW8 -> 0.24903233 | CV101: =CV8/CW8 -> 0.28869172 | CW101: =SUM(CS101:CV101) -> 1 | CX101: =CX8/DB8 -> 0.21359358 | CY101: =CY8/DB8 -> 0.23491141 | CZ101: =CZ8/DB8 -> 0.25387597 | DA101: =DA8/DB8 -> 0.29761905 | DB101: =SUM(CX101:DA101) -> 1 | DC101: =DC8/DG8 -> 0.23527651 | DD101: =DD8/DG8 -> 0.24021552 | DE101: =DE8/DG8 -> 0.24627703 | DF101: =DF8/DG8 -> 0.27823094 | DG101: =SUM(DC101:DF101) -> 1 | DH101: =DH8/DL8 -> 0.2279903 | DI101: =DI8/DL8 -> 0.24055303 | DJ101: =DJ8/DL8 -> 0.24892818 | DK101: =DK8/DL8 -> 0.2825285 | DL101: =SUM(DH101:DK101) -> 1 | DM101: =DM8/DQ8 -> 0.22734761 | DN101: =DN8/DQ8 -> 0.20422234 | DO101: =DO8/DQ8 -> 0.24913051 | DP101: =DP8/DQ8 -> 0.31929953 | DQ101: =SUM(DM101:DP101) -> 1 | DR101: =DR8/DV8 -> 0.21314138 | DS101: =DS8/DV8 -> 0.23984989 | DT101: =DT8/DV8 -> 0.25233727 | DU101: =DU8/DV8 -> 0.29467147 | DV101: =SUM(DR101:DU101) -> 1 | DW101: =DW8/EA8 -> 0.2449188 | DX101: =DX8/EA8 -> 0.24949443 | DY101: =DY8/EA8 -> 0.24156879 | DZ101: =DZ8/EA8 -> 0.26401798 | EA101: =SUM(DW101:DZ101) -> 1 | EB101: =EB8/EF8 -> 0.2303384 | EC101: =EC8/EF8 -> 0.24637425 | ED101: =ED8/EF8 -> 0.24843768 | EE101: =EE8/EF8 -> 0.27484966 | EF101: =SUM(EB101:EE101) -> 1 | EG101: =EG8/EK8 -> 0.23581056 | EH101: =EH8/EK8 -> 0.24384335 | EI101: =EI8/EK8 -> 0.24989071 | EJ101: =EJ8/EK8 -> 0.27045537 | EK101: =SUM(EG101:EJ101) -> 1 | EL101: =EL8/EP8 -> 0.23072032 | EM101: =EM8/EP8 -> 0.24678079 | EN101: =EN8/EP8 -> 0.24965052 | EO101: =EO8/EP8 -> 0.27284837 | EP101: =SUM(EL101:EO101) -> 1 | EQ101: =EQ8/EU8 -> 0.23736357 | ER101: =ER8/EU8 -> 0.2442687 | ES101: =ES8/EU8 -> 0.24848837 | ET101: =ET8/EU8 -> 0.26987937 | EU101: =SUM(EQ101:ET101) -> 1
A102: Net revenues | CI102: =CI9/CM9 -> 0.23213469 | CJ102: =CJ9/CM9 -> 0.24116258 | CK102: =CK9/CM9 -> 0.25093326 | CL102: =CL9/CM9 -> 0.27584565 | CM102: =SUM(CI102:CL102) -> 1.0000762 | CN102: =CN9/CR9 -> 0.22941332 | CO102: =CO9/CR9 -> 0.23661907 | CP102: =CP9/CR9 -> 0.24913432 | CQ102: =CQ9/CR9 -> 0.28483329 | CR102: =SUM(CN102:CQ102) -> 1 | CS102: =CS9/CW9 -> 0.22413206 | CT102: =CT9/CW9 -> 0.23850352 | CU102: =CU9/CW9 -> 0.24862886 | CV102: =CV9/CW9 -> 0.28873556 | CW102: =SUM(CS102:CV102) -> 1 | CX102: =CX9/DB9 -> 0.22561475 | CY102: =CY9/DB9 -> 0.23456264 | CZ102: =CZ9/DB9 -> 0.24971127 | DA102: =DA9/DB9 -> 0.29011134 | DB102: =SUM(CX102:DA102) -> 1 | DC102: =DC9/DG9 -> 0.22579092 | DD102: =DD9/DG9 -> 0.2383167 | DE102: =DE9/DG9 -> 0.24668235 | DF102: =DF9/DG9 -> 0.28921003 | DG102: =SUM(DC102:DF102) -> 1 | DH102: =DH9/DL9 -> 0.22371896 | DI102: =DI9/DL9 -> 0.24061988 | DJ102: =DJ9/DL9 -> 0.25050847 | DK102: =DK9/DL9 -> 0.28515269 | DL102: =SUM(DH102:DK102) -> 1 | DM102: =DM9/DQ9 -> 0.22508998 | DN102: =DN9/DQ9 -> 0.21103981 | DO102: =DO9/DQ9 -> 0.2538047 | DP102: =DP9/DQ9 -> 0.31006551 | DQ102: =SUM(DM102:DP102) -> 1 | DR102: =DR9/DV9 -> 0.21503176 | DS102: =DS9/DV9 -> 0.24025444 | DT102: =DT9/DV9 -> 0.25283985 | DU102: =DU9/DV9 -> 0.29187395 | DV102: =SUM(DR102:DU102) -> 1 | DW102: =DW9/EA9 -> 0.23952779 | DX102: =DX9/EA9 -> 0.24572753 | DY102: =DY9/EA9 -> 0.24485101 | DZ102: =DZ9/EA9 -> 0.26989366 | EA102: =SUM(DW102:DZ102) -> 1 | EB102: =EB9/EF9 -> 0.22637111 | EC102: =EC9/EF9 -> 0.24196906 | ED102: =ED9/EF9 -> 0.24970371 | EE102: =EE9/EF9 -> 0.28195612 | EF102: =SUM(EB102:EE102) -> 1 | EG102: =EG9/EK9 -> 0.2290372 | EH102: =EH9/EK9 -> 0.24178464 | EI102: =EI9/EK9 -> 0.25260743 | EJ102: =EJ9/EK9 -> 0.27657073 | EK102: =SUM(EG102:EJ102) -> 1 | EL102: =EL9/EP9 -> 0.22386122 | EM102: =EM9/EP9 -> 0.23918901 | EN102: =EN9/EP9 -> 0.25600948 | EO102: =EO9/EP9 -> 0.28094029 | EP102: =SUM(EL102:EO102) -> 1 | EQ102: =EQ9/EU9 -> 0.22537737 | ER102: =ER9/EU9 -> 0.23985929 | ES102: =ES9/EU9 -> 0.25474019 | ET102: =ET9/EU9 -> 0.28002316 | EU102: =SUM(EQ102:ET102) -> 1
A103: Other cost of revenues | CI103: =CI12/CM12 -> 0.22379859 | CJ103: =CJ12/CM12 -> 0.23134328 | CK103: =CK12/CM12 -> 0.27447925 | CL103: =CL12/CM12 -> 0.27070691 | CM103: =SUM(CI103:CL103) -> 1.000328 | CN103: =CN12/CR12 -> 0.21785688 | CO103: =CO12/CR12 -> 0.23196585 | CP103: =CP12/CR12 -> 0.25113957 | CQ103: =CQ12/CR12 -> 0.2990377 | CR103: =SUM(CN103:CQ103) -> 1 | CS103: =CS12/CW12 -> 0.21041156 | CT103: =CT12/CW12 -> 0.22649223 | CU103: =CU12/CW12 -> 0.24622513 | CV103: =CV12/CW12 -> 0.31687108 | CW103: =SUM(CS103:CV103) -> 1 | CX103: =CX12/DB12 -> 0.21605119 | CY103: =CY12/DB12 -> 0.22090251 | CZ103: =CZ12/DB12 -> 0.23612563 | DA103: =DA12/DB12 -> 0.32692066 | DB103: =SUM(CX103:DA103) -> 1 | DC103: =DC12/DG12 -> 0.21871858 | DD103: =DD12/DG12 -> 0.22737105 | DE103: =DE12/DG12 -> 0.23456113 | DF103: =DF12/DG12 -> 0.31934924 | DG103: =SUM(DC103:DF103) -> 1 | DH103: =DH12/DL12 -> 0.21891071 | DI103: =DI12/DL12 -> 0.24058172 | DJ103: =DJ12/DL12 -> 0.24106011 | DK103: =DK12/DL12 -> 0.29944746 | DL103: =SUM(DH103:DK103) -> 1 | DM103: =DM12/DQ12 -> 0.22192709 | DN103: =DN12/DQ12 -> 0.22825961 | DO103: =DO12/DQ12 -> 0.24927821 | DP103: =DP12/DQ12 -> 0.30053509 | DQ103: =SUM(DM103:DP103) -> 1 | DR103: =DR12/DV12 -> 0.22013675 | DS103: =DS12/DV12 -> 0.23401098 | DT103: =DT12/DV12 -> 0.24663087 | DU103: =DU12/DV12 -> 0.29922139 | DV103: =SUM(DR103:DU103) -> 1 | DW103: =DW12/EA12 -> 0.22795412 | DX103: =DX12/EA12 -> 0.23159176 | DY103: =DY12/EA12 -> 0.25025891 | DZ103: =DZ12/EA12 -> 0.29019522 | EA103: =SUM(DW103:DZ103) -> 1 | EB103: =EB12/EF12 -> 0.2291318 | EC103: =EC12/EF12 -> 0.23505082 | ED103: =ED12/EF12 -> 0.24970284 | EE103: =EE12/EF12 -> 0.28611455 | EF103: =SUM(EB103:EE103) -> 1 | EG103: =EG12/EK12 -> 0.22718421 | EH103: =EH12/EK12 -> 0.24199724 | EI103: =EI12/EK12 -> 0.24894427 | EJ103: =EJ12/EK12 -> 0.28187428 | EK103: =SUM(EG103:EJ103) -> 1 | EL103: =EL12/EP12 -> 0.21770858 | EM103: =EM12/EP12 -> 0.23427765 | EN103: =EN12/EP12 -> 0.25506361 | EO103: =EO12/EP12 -> 0.29295016 | EP103: =SUM(EL103:EO103) -> 1 | EQ103: =EQ12/EU12 -> 0.21414574 | ER103: =ER12/EU12 -> 0.23322376 | ES103: =ES12/EU12 -> 0.25818162 | ET103: =ET12/EU12 -> 0.29444888 | EU103: =SUM(EQ103:ET103) -> 1
A104: Gross Profit | CI104: =CI13/CM13 -> 0.23465641 | CJ104: =CJ13/CM13 -> 0.24413297 | CK104: =CK13/CM13 -> 0.24381047 | CL104: =CL13/CM13 -> 0.27740015 | CM104: =SUM(CI104:CL104) -> 1 | CN104: =CN13/CR13 -> 0.23282435 | CO104: =CO13/CR13 -> 0.23799253 | CP104: =CP13/CR13 -> 0.24854245 | CQ104: =CQ13/CR13 -> 0.28064068 | CR104: =SUM(CN104:CQ104) -> 1 | CS104: =CS13/CW13 -> 0.22869736 | CT104: =CT13/CW13 -> 0.24250009 | CU104: =CU13/CW13 -> 0.24942866 | CV104: =CV13/CW13 -> 0.27937389 | CW104: =SUM(CS104:CV104) -> 1 | CX104: =CX13/DB13 -> 0.22911815 | CY104: =CY13/DB13 -> 0.23956674 | CZ104: =CZ13/DB13 -> 0.25468807 | DA104: =DA13/DB13 -> 0.27662704 | DB104: =SUM(CX104:DA104) -> 1 | DC104: =DC13/DG13 -> 0.22879513 | DD104: =DD13/DG13 -> 0.24296622 | DE104: =DE13/DG13 -> 0.25183124 | DF104: =DF13/DG13 -> 0.2764074 | DG104: =SUM(DC104:DF104) -> 1 | DH104: =DH13/DL13 -> 0.22595347 | DI104: =DI13/DL13 -> 0.24063761 | DJ104: =DJ13/DL13 -> 0.25489935 | DK104: =DK13/DL13 -> 0.27850958 | DL104: =SUM(DH104:DK104) -> 1 | DM104: =DM13/DQ13 -> 0.22677028 | DN104: =DN13/DQ13 -> 0.20189171 | DO104: =DO13/DQ13 -> 0.25620942 | DP104: =DP13/DQ13 -> 0.31512859 | DQ104: =SUM(DM104:DP104) -> 1 | DR104: =DR13/DV13 -> 0.21275682 | DS104: =DS13/DV13 -> 0.24303671 | DT104: =DT13/DV13 -> 0.25560676 | DU104: =DU13/DV13 -> 0.28859971 | DV104: =SUM(DR104:DU104) -> 1 | DW104: =DW13/EA13 -> 0.24523568 | DX104: =DX13/EA13 -> 0.25269898 | DY104: =DY13/EA13 -> 0.24218396 | DZ104: =DZ13/EA13 -> 0.25988138 | EA104: =SUM(DW104:DZ104) -> 1 | EB104: =EB13/EF13 -> 0.22506348 | EC104: =EC13/EF13 -> 0.24524595 | ED104: =ED13/EF13 -> 0.24970413 | EE104: =EE13/EF13 -> 0.27998644 | EF104: =SUM(EB104:EE104) -> 1 | EG104: =EG13/EK13 -> 0.22986864 | EH104: =EH13/EK13 -> 0.24168925 | EI104: =EI13/EK13 -> 0.2542511 | EJ104: =EJ13/EK13 -> 0.27419101 | EK104: =SUM(EG104:EJ104) -> 1 | EL104: =EL13/EP13 -> 0.22654863 | EM104: =EM13/EP13 -> 0.24133424 | EN104: =EN13/EP13 -> 0.25642262 | EO104: =EO13/EP13 -> 0.2756945 | EP104: =SUM(EL104:EO104) -> 1 | EQ104: =EQ13/EU13 -> 0.23055988 | ER104: =ER13/EU13 -> 0.24292106 | ES104: =ES13/EU13 -> 0.25315224 | ET104: =ET13/EU13 -> 0.27336682 | EU104: =SUM(EQ104:ET104) -> 1
...

Sheet Revenue Drivers
A2: =IS!A2 -> Alphabet Inc.
A3: Revenue Analysis | DC3: Updated Segment Disclosure
A4: ($ millions except where noted) | DC4: Not Provided for 1Q18 to 3Q18
FA5: 3 yr CAGR | FB5: 5 yr CAGR
A6: $ millions except where noted | B6: 3/99A | C6: 6/99A | D6: 9/99A | E6: 12/99A | F6: 1999A | G6: 3/00A | H6: 6/00A | I6: 9/00A | J6: 12/00A | K6: 2000A | L6: 3/01A | M6: 6/01A | N6: 9/01A | O6: 12/01A | P6: 2001A | Q6: 3/02A | R6: 6/02A | S6: 9/02A | T6: 12/02A | U6: 2002A | V6: 3/03A | W6: 6/03A | X6: 9/03A | Y6: 12/03A | Z6: 2003A | AA6: 3/04A | AB6: 6/04A | AC6: 9/04A | AD6: 12/04A | AE6: 2004A | AF6: 3/05A | AG6: 6/05A | AH6: 9/05A | AI6: 12/05A | AJ6: 2005A | AK6: 3/06A | AL6: 6/06A | AM6: 9/06A | AN6: 12/06A | AO6: 2006A | AP6: 3/07A | AQ6: 6/07A | AR6: 9/07A | AS6: 12/07A | AT6: 2007A | AU6: 3/08A | AV6: 6/08A | AW6: 9/08A | AX6: 12/08A | AY6: 2008A | AZ6: 3/09A | BA6: 6/09A | BB6: 9/09A | BC6: 12/09A | BD6: 2009A | BE6: 3/10A | BF6: 6/10A | BG6: 9/10A | BH6: 12/10A | BI6: 2010A | BJ6: 3/11A | BK6: 6/11A | BL6: 9/11A | BM6: 12/11A | BN6: 2011A | BT6: 3/12A | BU6: 6/12A | BV6: 9/12A | BW6: 12/12A | BX6: 2012A | CD6: 3/13A | CE6: 6/13A | CF6: 9/13A | CG6: 12/13A | CH6: 2013A | CI6: 3/14A | CJ6: 6/14A | CK6: 9/14A | CL6: 12/14A | CM6: 2014A | CN6: 3/15A | CO6: 6/15A | CP6: 9/15A | CQ6: 12/15A | CR6: 2015A | CS6: =IS!CS6 -> 3/16A | CT6: =IS!CT6 -> 6/16A | CU6: =IS!CU6 -> 9/16A | CV6: =IS!CV6 -> 12/16A | CW6: =IS!CW6 -> 2016A | CX6: =IS!CX6 -> 3/17A | CY6: =IS!CY6 -> 6/17A | CZ6: =IS!CZ6 -> 9/17A | ... EY6: =IS!EY6 -> 2030E | FA6: 2024-2027 | FB6: 2024-2029
A7: Gross Revenue Summary
A8: Google Search & other | DB8: 69811 | DF8: 23320 | DG8: 85296 | DH8: 22547 | DI8: 23642 | DJ8: 24741 | DK8: 27185 | DL8: =SUM(DH8:DK8) -> 98115 | DM8: 24502 | DN8: 21319 | DO8: 26338 | DP8: 31903 | DQ8: =SUM(DM8:DP8) -> 104062 | DR8: 31879 | DS8: 35845 | DT8: 37926 | DU8: 43301 | DV8: =SUM(DR8:DU8) -> 148951 | DW8: 39618 | DX8: 40689 | DY8: 39539 | DZ8: 42604 | EA8: =SUM(DW8:DZ8) -> 162450 | EB8: 40359 | EC8: 42628 | ED8: 44026 | EE8: 48020 | EF8: =SUM(EB8:EE8) -> 175033 | EG8: 46156 | EH8: 48509 | EI8: 49385 | EJ8: 54034 | EK8: =SUM(EG8:EJ8) -> 198084 | EL8: 50702 | EM8: 54190 | EN8: 56567 | EO8: =EO11+EO10 -> 61868.337 | EP8: =SUM(EL8:EO8) -> 223327.34 | EQ8: =EQ11+EQ10 -> 58831.489 | ER8: =ER11+ER10 -> 61318.583 | ES8: =ES11+ES10 -> 62982.762 | ET8: =ET11+ET10 -> 68842.303 | EU8: =SUM(EQ8:ET8) -> 251975.14 | EV8: =EV11+EV10 -> 277172.65 | EW8: =EW11+EW10 -> 302118.19 | EX8: =EX11+EX10 -> 326287.64 | EY8: =EY11+EY10 -> 350759.22 | FA8: =(EV8/EK8)^(1/3)-1 -> 0.118494 | FB8: =(EX8/EK8)^(1/5)-1 -> 0.10496939
A9: Y/Y growth | DB9: =IFERROR(DB8/CW8-1,"NA") -> NA | DC9: =IFERROR(DC8/CX8-1,"NA") -> NA | DD9: =IFERROR(DD8/CY8-1,"NA") -> NA | DE9: =IFERROR(DE8/CZ8-1,"NA") -> NA | DF9: =IFERROR(DF8/DA8-1,"NA") -> NA | DG9: =IFERROR(DG8/DB8-1,"NA") -> 0.22181318 | DH9: NA | DI9: NA | DJ9: NA | DK9: =IFERROR(DK8/DF8-1,"NA") -> 0.16573756 | DL9: =IFERROR(DL8/DG8-1,"NA") -> 0.15028841 | DM9: =IFERROR(DM8/DH8-1,"NA") -> 0.086707766 | DN9: =IFERROR(DN8/DI8-1,"NA") -> -0.098257339 | DO9: =IFERROR(DO8/DJ8-1,"NA") -> 0.064548725 | DP9: =IFERROR(DP8/DK8-1,"NA") -> 0.17355159 | DQ9: =IFERROR(DQ8/DL8-1,"NA") -> 0.060612547 | DR9: =IFERROR(DR8/DM8-1,"NA") -> 0.30107746 | ... EU9: =IFERROR(EU8/EP8-1,"NA") -> 0.12827718 | EV9: =EV8/EU8-1 -> 0.1 | EW9: =EW8/EV8-1 -> 0.09 | EX9: =EX8/EW8-1 -> 0.08 | EY9: =EY8/EX8-1 -> 0.075
