Workbook
Name A_ALL_GOOGL: #REF!
Name A_ALL_KEYWORDS_TYPE_ScalarContributed_EQTY_200007003: #REF!,#REF!,#REF!,#REF!,#REF!
Name A_ALL_KEYWORDS_TYPE_Vector_ISSR_208002492: #REF!,#REF!,#REF!,#REF!,#REF!,#REF!,#REF!,#REF!,#REF!,#REF!,#REF!,#REF!,#REF!
Name A_ALL_SECTION_KEYWORDS_EQTY_200007003_13A: #REF!
Name A_ALL_SECTION_KEYWORDS_ISSR_208002492_131O: #REF!,#REF!
Name E_ALL_GOOGL: #REF!
Name E_ALL_KEYWORDS_TYPE_ScalarContributed_EQTY_200007003: #REF!,#REF!,#REF!,#REF!,#REF!
Name E_ALL_KEYWORDS_TYPE_Vector_ISSR_208002492: #REF!,#REF!,#REF!,#REF!,#REF!,#REF!,#REF!,#REF!,#REF!,#REF!,#REF!,#REF!,#REF!
Name E_ALL_SECTION_KEYWORDS_EQTY_200007003_13A: #REF!
Name E_ALL_SECTION_KEYWORDS_ISSR_208002492_131O: #REF!,#REF!
Name L_ALL_GOOGL: #REF!
Name L_ALL_KEYWORDS_TYPE_ScalarContributed_EQTY_200007003: #REF!,#REF!,#REF!,#REF!,#REF!
Name L_ALL_KEYWORDS_TYPE_Vector_ISSR_208002492: #REF!,#REF!,#REF!,#REF!,#REF!,#REF!,#REF!,#REF!,#REF!,#REF!,#REF!,#REF!,#REF!
Name L_ALL_SECTION_KEYWORDS_EQTY_200007003_13A: #REF!
Name L_ALL_SECTION_KEYWORDS_ISSR_208002492_131O: #REF!,#REF!
Name V_ALL_GOOGL: #REF!
Name V_ALL_KEYWORDS_TYPE_ScalarContributed_EQTY_200007003: #REF!,#REF!,#REF!,#REF!,#REF!
Name V_ALL_KEYWORDS_TYPE_Vector_ISSR_208002492: #REF!,#REF!,#REF!,#REF!,#REF!,#REF!,#REF!,#REF!,#REF!,#REF!,#REF!,#REF!,#REF!
Name V_ALL_SECTION_KEYWORDS_EQTY_200007003_13A: #REF!
Name V_ALL_SECTION_KEYWORDS_ISSR_208002492_131O: #REF!,#REF!

Sheet Cover
D4: Alphabet, Inc. (GOOGL)
D5: US Internet
D10: Eric Sheridan
D11: eric.sheridan@gs.com
D12: 212-357-1849 (New York)
D14: Alex Vegliante, CFA
D15: alex.vegliante@gs.com
D16: 212-934-1878 (New York)
D18: Aarshiya Sachdeva
D19: aarshiya.sachdeva@gs.com
D20: 212-855-6184 (New York)

Sheet P&L Summary
A1: GOOGL
A2: P&L Summary
A3: (USD Millions) | B3: ='Income Statement'!BB1 -> 1Q23 | C3: ='Income Statement'!BC1 -> 2Q23 | D3: ='Income Statement'!BD1 -> 3Q23 | E3: ='Income Statement'!BE1 -> 4Q23 | F3: ='Income Statement'!BF1 -> 1Q24 | G3: ='Income Statement'!BG1 -> 2Q24 | H3: ='Income Statement'!BH1 -> 3Q24 | I3: ='Income Statement'!BI1 -> 4Q24 | ... Q3: ='Income Statement'!BQ1 -> 4Q26E | S3: ='Income Statement'!CU1 -> 2022 | T3: ='Income Statement'!CV1 -> 2023 | U3: ='Income Statement'!CW1 -> 2024 | V3: ='Income Statement'!CX1 -> 2025E | W3: ='Income Statement'!CY1 -> 2026E
A5: Consolidated Total Revenue | B5: ='Income Statement'!BB64 -> 69787 | C5: ='Income Statement'!BC64 -> 74604 | D5: ='Income Statement'!BD64 -> 76693 | E5: ='Income Statement'!BE64 -> 86310 | F5: ='Income Statement'!BF64 -> 80539 | G5: ='Income Statement'!BG64 -> 84742 | H5: ='Income Statement'!BH64 -> 88268 | I5: ='Income Statement'!BI64 -> 96469 | ... Q5: ='Income Statement'!BQ64 -> 125967.83 | S5: ='Income Statement'!CU64 -> 282836 | T5: ='Income Statement'!CV64 -> 307394 | U5: ='Income Statement'!CW64 -> 350018 | V5: ='Income Statement'!CX64 -> 401166.92 | W5: ='Income Statement'!CY64 -> 456079.88
A6: GAAP Gross Profit | B6: ='Income Statement'!BB172 -> 39175 | C6: ='Income Statement'!BC172 -> 42688 | D6: ='Income Statement'!BD172 -> 43464 | E6: ='Income Statement'!BE172 -> 48735 | F6: ='Income Statement'!BF172 -> 46827 | G6: ='Income Statement'!BG172 -> 49235 | H6: ='Income Statement'!BH172 -> 51794 | I6: ='Income Statement'!BI172 -> 55856 | ... Q6: ='Income Statement'!BQ172 -> 71645.602 | S6: ='Income Statement'!CU172 -> 156633 | T6: ='Income Statement'!CV172 -> 174062 | U6: ='Income Statement'!CW172 -> 203712 | V6: ='Income Statement'!CX172 -> 236648.18 | W6: ='Income Statement'!CY172 -> 266977.57
A7: Total GAAP Operating Expenses | B7: ='Income Statement'!BB196 -> -21760 | C7: ='Income Statement'!BC196 -> -20850 | D7: ='Income Statement'!BD196 -> -22121 | E7: ='Income Statement'!BE196 -> -25038 | F7: ='Income Statement'!BF196 -> -21355 | G7: ='Income Statement'!BG196 -> -21810 | H7: ='Income Statement'!BH196 -> -23273 | I7: ='Income Statement'!BI196 -> -24884 | ... Q7: ='Income Statement'!BQ196 -> -30587.085 | S7: ='Income Statement'!CU196 -> -81791 | T7: ='Income Statement'!CV196 -> -89769 | U7: ='Income Statement'!CW196 -> -91322 | V7: ='Income Statement'!CX196 -> -106843.18 | W7: ='Income Statement'!CY196 -> -112239.94
A8: R&D | B8: ='Income Statement'!BB179 -> -11468 | C8: ='Income Statement'!BC179 -> -10588 | D8: ='Income Statement'!BD179 -> -11258 | E8: ='Income Statement'!BE179 -> -12113 | F8: ='Income Statement'!BF179 -> -11903 | G8: ='Income Statement'!BG179 -> -11860 | H8: ='Income Statement'!BH179 -> -12447 | I8: ='Income Statement'!BI179 -> -13116 | ... Q8: ='Income Statement'!BQ179 -> -17645.939 | S8: ='Income Statement'!CU179 -> -39500 | T8: ='Income Statement'!CV179 -> -45427 | U8: ='Income Statement'!CW179 -> -49326 | V8: ='Income Statement'!CX179 -> -57926.3 | W8: ='Income Statement'!CY179 -> -66186.273
A9: Sales & Marketing | B9: ='Income Statement'!BB184 -> -6533 | C9: ='Income Statement'!BC184 -> -6781 | D9: ='Income Statement'!BD184 -> -6884 | E9: ='Income Statement'!BE184 -> -7719 | F9: ='Income Statement'!BF184 -> -6426 | G9: ='Income Statement'!BG184 -> -6792 | H9: ='Income Statement'!BH184 -> -7227 | I9: ='Income Statement'!BI184 -> -7363 | ... Q9: ='Income Statement'!BQ184 -> -8155.9951 | S9: ='Income Statement'!CU184 -> -26567 | T9: ='Income Statement'!CV184 -> -27917 | U9: ='Income Statement'!CW184 -> -27808 | V9: ='Income Statement'!CX184 -> -28282.78 | W9: ='Income Statement'!CY184 -> -29555.505
A10: G&A | B10: ='Income Statement'!BB189 -> -3759 | C10: ='Income Statement'!BC189 -> -3481 | D10: ='Income Statement'!BD189 -> -3979 | E10: ='Income Statement'!BE189 -> -5206 | F10: ='Income Statement'!BF189 -> -3026 | G10: ='Income Statement'!BG189 -> -3158 | H10: ='Income Statement'!BH189 -> -3599 | I10: ='Income Statement'!BI189 -> -4405 | ... Q10: ='Income Statement'!BQ189 -> -4785.1515 | S10: ='Income Statement'!CU189 -> -15724 | T10: ='Income Statement'!CV189 -> -16425 | U10: ='Income Statement'!CW189 -> -14188 | V10: ='Income Statement'!CX189 -> -20634.1 | W10: ='Income Statement'!CY189 -> -16498.162
A11: Stock-Based Comp | B11: ='Income Statement'!BB228 -> -5284 | C11: ='Income Statement'!BC228 -> -5774 | D11: ='Income Statement'!BD228 -> -5743 | E11: ='Income Statement'!BE228 -> -5659 | F11: ='Income Statement'!BF228 -> -5264 | G11: ='Income Statement'!BG228 -> -5865 | H11: ='Income Statement'!BH228 -> -5846 | I11: ='Income Statement'!BI228 -> -5810 | ... Q11: ='Income Statement'!BQ228 -> -6966.19 | S11: ='Income Statement'!CU228 -> -19362 | T11: ='Income Statement'!CV228 -> -22460 | U11: ='Income Statement'!CW228 -> -22785 | V11: ='Income Statement'!CX228 -> -24273 | W11: ='Income Statement'!CY228 -> -26457.57
A12: GAAP Operating Income | B12: ='Income Statement'!BB201 -> 17415 | C12: ='Income Statement'!BC201 -> 21838 | D12: ='Income Statement'!BD201 -> 21343 | E12: ='Income Statement'!BE201 -> 23697 | F12: ='Income Statement'!BF201 -> 25472 | G12: ='Income Statement'!BG201 -> 27425 | H12: ='Income Statement'!BH201 -> 28521 | I12: ='Income Statement'!BI201 -> 30972 | ... Q12: ='Income Statement'!BQ201 -> 41058.517 | S12: ='Income Statement'!CU201 -> 74842 | T12: ='Income Statement'!CV201 -> 84293 | U12: ='Income Statement'!CW201 -> 112390 | V12: ='Income Statement'!CX201 -> 129805 | W12: ='Income Statement'!CY201 -> 154737.63
A13: Google Services OI | B13: ='Income Statement'!BB207 -> 21737 | C13: ='Income Statement'!BC207 -> 23454 | D13: ='Income Statement'!BD207 -> 23937 | E13: ='Income Statement'!BE207 -> 26730 | F13: ='Income Statement'!BF207 -> 27897 | G13: ='Income Statement'!BG207 -> 29674 | H13: ='Income Statement'!BH207 -> 30856 | I13: ='Income Statement'!BI207 -> 32836 | ... Q13: ='Income Statement'!BQ207 -> 40968.629 | S13: ='Income Statement'!CU207 -> 82699 | T13: ='Income Statement'!CV207 -> 95858 | U13: ='Income Statement'!CW207 -> 121263 | V13: ='Income Statement'!CX207 -> 136359.17 | W13: ='Income Statement'!CY207 -> 154526.62
A14: Google Cloud OI | B14: ='Income Statement'!BB212 -> 191 | C14: ='Income Statement'!BC212 -> 395 | D14: ='Income Statement'!BD212 -> 266 | E14: ='Income Statement'!BE212 -> 864 | F14: ='Income Statement'!BF212 -> 900 | G14: ='Income Statement'!BG212 -> 1172 | H14: ='Income Statement'!BH212 -> 1947 | I14: ='Income Statement'!BI212 -> 2093 | ... Q14: ='Income Statement'!BQ212 -> 5648.7375 | S14: ='Income Statement'!CU212 -> -1922 | T14: ='Income Statement'!CV212 -> 1716 | U14: ='Income Statement'!CW212 -> 6112 | V14: ='Income Statement'!CX212 -> 12446.51 | W14: ='Income Statement'!CY212 -> 19553.8
A15: Other Bets OI | B15: ='Income Statement'!BB218 -> -1225 | C15: ='Income Statement'!BC218 -> -813 | D15: ='Income Statement'!BD218 -> -1194 | E15: ='Income Statement'!BE218 -> -863 | F15: ='Income Statement'!BF218 -> -1020 | G15: ='Income Statement'!BG218 -> -1134 | H15: ='Income Statement'!BH218 -> -1116 | I15: ='Income Statement'!BI218 -> -1174 | ... Q15: ='Income Statement'!BQ218 -> -1574 | S15: ='Income Statement'!CU218 -> -4636 | T15: ='Income Statement'!CV218 -> -4095 | U15: ='Income Statement'!CW218 -> -4444 | V15: ='Income Statement'!CX218 -> -5272 | W15: ='Income Statement'!CY218 -> -6072
A16: Net Income | B16: ='Income Statement'!BB267 -> 15051 | C16: ='Income Statement'!BC267 -> 18368 | D16: ='Income Statement'!BD267 -> 19689 | E16: ='Income Statement'!BE267 -> 20687 | F16: ='Income Statement'!BF267 -> 23662 | G16: ='Income Statement'!BG267 -> 23619 | H16: ='Income Statement'!BH267 -> 26301 | I16: ='Income Statement'!BI267 -> 26536 | ... Q16: ='Income Statement'!BQ267 -> 34324.048 | S16: ='Income Statement'!CU267 -> 59972 | T16: ='Income Statement'!CV267 -> 73795 | U16: ='Income Statement'!CW267 -> 100118 | V16: ='Income Statement'!CX267 -> 128170.63 | W16: ='Income Statement'!CY267 -> 129614.83
A17: GAAP EPS | B17: ='Income Statement'!BB278 -> 1.1737503 | C17: ='Income Statement'!BC278 -> 1.4390473 | D17: ='Income Statement'!BD278 -> 1.5508034 | E17: ='Income Statement'!BE278 -> 1.6415648 | F17: ='Income Statement'!BF278 -> 1.88888 | G17: ='Income Statement'!BG278 -> 1.8902761 | H17: ='Income Statement'!BH278 -> 2.1178034 | I17: ='Income Statement'!BI278 -> 2.149012 | ... Q17: ='Income Statement'!BQ278 -> 2.8453081 | S17: ='Income Statement'!CU278 -> 4.5576606 | T17: ='Income Statement'!CV278 -> 5.8009237 | U17: ='Income Statement'!CW278 -> 8.0433831 | V17: ='Income Statement'!CX278 -> 10.492102 | W17: ='Income Statement'!CY278 -> 10.710306
A18: GAAP EBITDA | B18: ='Cash Flow Statement'!BB61 -> 20601 | C18: ='Cash Flow Statement'!BC61 -> 25235 | D18: ='Cash Flow Statement'!BD61 -> 25143 | E18: ='Cash Flow Statement'!BE61 -> 27013 | F18: ='Cash Flow Statement'!BF61 -> 28885 | G18: ='Cash Flow Statement'!BG61 -> 31133 | H18: ='Cash Flow Statement'!BH61 -> 32506 | I18: ='Cash Flow Statement'!BI61 -> 35177 | ... Q18: ='Cash Flow Statement'!BQ61 -> 52318.644 | S18: ='Cash Flow Statement'!CU61 -> 90770 | T18: ='Cash Flow Statement'!CV61 -> 97992 | U18: ='Cash Flow Statement'!CW61 -> 127701 | V18: ='Cash Flow Statement'!CX61 -> 153229.02 | W18: ='Cash Flow Statement'!CY61 -> 191078.28
A19: Capex | B19: ='Capex & Depreciation'!BB4 -> -6289 | C19: ='Capex & Depreciation'!BC4 -> -6888 | D19: ='Capex & Depreciation'!BD4 -> -8055 | E19: ='Capex & Depreciation'!BE4 -> -11019 | F19: ='Capex & Depreciation'!BF4 -> -12012 | G19: ='Capex & Depreciation'!BG4 -> -13186 | H19: ='Capex & Depreciation'!BH4 -> -13061 | I19: ='Capex & Depreciation'!BI4 -> -14276 | ... Q19: ='Capex & Depreciation'!BQ4 -> -37688.64 | S19: ='Capex & Depreciation'!CU4 -> -31485 | T19: ='Capex & Depreciation'!CV4 -> -32251 | U19: ='Capex & Depreciation'!CW4 -> -52535 | V19: ='Capex & Depreciation'!CX4 -> -92148 | W19: ='Capex & Depreciation'!CY4 -> -121635.36
A20: FCF | B20: ='Cash Flow Statement'!BB76 -> 17220 | C20: ='Cash Flow Statement'!BC76 -> 21778 | D20: ='Cash Flow Statement'!BD76 -> 22601 | E20: ='Cash Flow Statement'!BE76 -> 7896 | F20: ='Cash Flow Statement'!BF76 -> 16836 | G20: ='Cash Flow Statement'!BG76 -> 13454 | H20: ='Cash Flow Statement'!BH76 -> 17637 | I20: ='Cash Flow Statement'!BI76 -> 24837 | ... Q20: ='Cash Flow Statement'!BQ76 -> 16947.867 | S20: ='Cash Flow Statement'!CU76 -> 60010 | T20: ='Cash Flow Statement'!CV76 -> 69495 | U20: ='Cash Flow Statement'!CW76 -> 72764 | V20: ='Cash Flow Statement'!CX76 -> 48256.588 | W20: ='Cash Flow Statement'!CY76 -> 72643.967
A21: FCF Minus SBC | B21: ='Cash Flow Statement'!BB83 -> 11936 | C21: ='Cash Flow Statement'!BC83 -> 16004 | D21: ='Cash Flow Statement'!BD83 -> 16858 | E21: ='Cash Flow Statement'!BE83 -> 2237 | F21: ='Cash Flow Statement'!BF83 -> 11572 | G21: ='Cash Flow Statement'!BG83 -> 7589 | H21: ='Cash Flow Statement'!BH83 -> 11791 | I21: ='Cash Flow Statement'!BI83 -> 19027 | ... Q21: ='Cash Flow Statement'!BQ83 -> 9981.6768 | S21: ='Cash Flow Statement'!CU83 -> 40648 | T21: ='Cash Flow Statement'!CV83 -> 47035 | U21: ='Cash Flow Statement'!CW83 -> 49979 | V21: ='Cash Flow Statement'!CX83 -> 23983.588 | W21: ='Cash Flow Statement'!CY83 -> 46186.397
A23: As % of Revenue
A25: GAAP Gross Profit | B25: ='Income Statement'!BB173 -> 0.67466331 | C25: ='Income Statement'!BC173 -> 0.68777289 | D25: ='Income Statement'!BD173 -> 0.67858425 | E25: ='Income Statement'!BE173 -> 0.67384271 | F25: ='Income Statement'!BF173 -> 0.69277884 | G25: ='Income Statement'!BG173 -> 0.6900007 | H25: ='Income Statement'!BH173 -> 0.69476452 | I25: ='Income Statement'!BI173 -> 0.68433369 | ... Q25: ='Income Statement'!BQ173 -> 0.66183369 | S25: ='Income Statement'!CU173 -> 0.66971238 | T25: ='Income Statement'!CV173 -> 0.67858312 | U25: ='Income Statement'!CW173 -> 0.69027304 | V25: ='Income Statement'!CX173 -> 0.69358774 | W25: ='Income Statement'!CY173 -> 0.68120077
A26: Total GAAP Operating Expenses | B26: ='Income Statement'!BB197 -> -0.37474598 | C26: ='Income Statement'!BC197 -> -0.3359273 | D26: ='Income Statement'!BD197 -> -0.34536541 | E26: ='Income Statement'!BE197 -> -0.34619214 | F26: ='Income Statement'!BF197 -> -0.31593508 | G26: ='Income Statement'!BG197 -> -0.30565482 | H26: ='Income Statement'!BH197 -> -0.31218393 | I26: ='Income Statement'!BI197 -> -0.30487252 | ... Q26: ='Income Statement'!BQ197 -> -0.28255138 | S26: ='Income Statement'!CU197 -> -0.34971203 | T26: ='Income Statement'!CV197 -> -0.34996569 | U26: ='Income Statement'!CW197 -> -0.30944232 | V26: ='Income Statement'!CX197 -> -0.31314468 | W26: ='Income Statement'!CY197 -> -0.28638336
A27: R&D | B27: ='Income Statement'!BB180 -> -0.1974994 | C27: ='Income Statement'!BC180 -> -0.17058985 | D27: ='Income Statement'!BD180 -> -0.17576619 | E27: ='Income Statement'!BE180 -> -0.16748244 | F27: ='Income Statement'!BF180 -> -0.17609812 | G27: ='Income Statement'!BG180 -> -0.1662112 | H27: ='Income Statement'!BH180 -> -0.16696401 | I27: ='Income Statement'!BI180 -> -0.16069394 | ... Q27: ='Income Statement'!BQ180 -> -0.16300619 | S27: ='Income Statement'!CU180 -> -0.16888931 | T27: ='Income Statement'!CV180 -> -0.17709779 | U27: ='Income Statement'!CW180 -> -0.16713992 | V27: ='Income Statement'!CX180 -> -0.16977511 | W27: ='Income Statement'!CY180 -> -0.16887613
A28: Sales & Marketing | B28: ='Income Statement'!BB185 -> -0.1125099 | C28: ='Income Statement'!BC185 -> -0.1092529 | D28: ='Income Statement'!BD185 -> -0.10747685 | E28: ='Income Statement'!BE185 -> -0.10672806 | F28: ='Income Statement'!BF185 -> -0.095069016 | G28: ='Income Statement'!BG185 -> -0.095186042 | H28: ='Income Statement'!BH185 -> -0.09694295 | I28: ='Income Statement'!BI185 -> -0.090209627 | ... Q28: ='Income Statement'!BQ185 -> -0.075341852 | S28: ='Income Statement'!CU185 -> -0.11359195 | T28: ='Income Statement'!CV185 -> -0.10883481 | U28: ='Income Statement'!CW185 -> -0.094226716 | V28: ='Income Statement'!CX185 -> -0.082893473 | W28: ='Income Statement'!CY185 -> -0.075411701
A29: G&A | B29: ='Income Statement'!BB190 -> -0.064736679 | C29: ='Income Statement'!BC190 -> -0.056084554 | D29: ='Income Statement'!BD190 -> -0.062122371 | E29: ='Income Statement'!BE190 -> -0.071981638 | F29: ='Income Statement'!BF190 -> -0.044767949 | G29: ='Income Statement'!BG190 -> -0.044257585 | H29: ='Income Statement'!BH190 -> -0.048276972 | I29: ='Income Statement'!BI190 -> -0.053968954 | ... Q29: ='Income Statement'!BQ190 -> -0.044203334 | S29: ='Income Statement'!CU190 -> -0.067230771 | T29: ='Income Statement'!CV190 -> -0.064033091 | U29: ='Income Statement'!CW190 -> -0.048075685 | V29: ='Income Statement'!CX190 -> -0.060476099 | W29: ='Income Statement'!CY190 -> -0.042095522
A30: Stock-Based Comp | B30: ='Income Statement'!BB229 -> -0.090999897 | C30: ='Income Statement'!BC229 -> -0.093028501 | D30: ='Income Statement'!BD229 -> -0.089662925 | E30: ='Income Statement'!BE229 -> -0.078245119 | F30: ='Income Statement'!BF229 -> -0.077877887 | G30: ='Income Statement'!BG229 -> -0.082194661 | H30: ='Income Statement'!BH229 -> -0.078418222 | I30: ='Income Statement'!BI229 -> -0.071182661 | ... Q30: ='Income Statement'!BQ229 -> -0.064350904 | S30: ='Income Statement'!CU229 -> -0.08278569 | T30: ='Income Statement'!CV229 -> -0.087560622 | U30: ='Income Statement'!CW229 -> -0.077206406 | V30: ='Income Statement'!CX229 -> -0.071141283 | W30: ='Income Statement'!CY229 -> -0.067507232
A31: GAAP Operating Income | B31: ='Income Statement'!BB202 -> 0.29991734 | C31: ='Income Statement'!BC202 -> 0.35184559 | D31: ='Income Statement'!BD202 -> 0.33321884 | E31: ='Income Statement'!BE202 -> 0.32765057 | F31: ='Income Statement'!BF202 -> 0.37684376 | G31: ='Income Statement'!BG202 -> 0.38434588 | H31: ='Income Statement'!BH202 -> 0.38258058 | I31: ='Income Statement'!BI202 -> 0.37946117 | ... Q31: ='Income Statement'!BQ202 -> 0.37928231 | S31: ='Income Statement'!CU202 -> 0.32000034 | T31: ='Income Statement'!CV202 -> 0.32861743 | U31: ='Income Statement'!CW202 -> 0.38083072 | V31: ='Income Statement'!CX202 -> 0.38044306 | W31: ='Income Statement'!CY202 -> 0.39481741
A32: Google Services OI | B32: ='Income Statement'!BB208 -> 0.37676361 | C32: ='Income Statement'!BC208 -> 0.37964357 | D32: ='Income Statement'!BD208 -> 0.37545291 | E32: ='Income Statement'!BE208 -> 0.37375729 | F32: ='Income Statement'!BF208 -> 0.41621162 | G32: ='Income Statement'!BG208 -> 0.418604 | H32: ='Income Statement'!BH208 -> 0.41616314 | I32: ='Income Statement'!BI208 -> 0.40437926 | ... Q32: ='Income Statement'!BQ208 -> 0.38 | S32: ='Income Statement'!CU208 -> 0.3582323 | T32: ='Income Statement'!CV208 -> 0.37629002 | U32: ='Income Statement'!CW208 -> 0.41350138 | V32: ='Income Statement'!CX208 -> 0.40145039 | W32: ='Income Statement'!CY208 -> 0.39596253
A33: Google Cloud OI | B33: ='Income Statement'!BB213 -> 0.025623826 | C33: ='Income Statement'!BC213 -> 0.04918441 | D33: ='Income Statement'!BD213 -> 0.031625253 | E33: ='Income Statement'!BE213 -> 0.093994778 | F33: ='Income Statement'!BF213 -> 0.094004596 | G33: ='Income Statement'!BG213 -> 0.11326955 | H33: ='Income Statement'!BH213 -> 0.17149652 | I33: ='Income Statement'!BI213 -> 0.17507319 | ... Q33: ='Income Statement'!BQ213 -> 0.27 | S33: ='Income Statement'!CU213 -> -0.073135464 | T33: ='Income Statement'!CV213 -> 0.051861702 | U33: ='Income Statement'!CW213 -> 0.14138657 | V33: ='Income Statement'!CX213 -> 0.21541954 | W33: ='Income Statement'!CY213 -> 0.25388644
A34: Other Bets OI | B34: ='Income Statement'!BB219 -> -4.2534722 | C34: ='Income Statement'!BC219 -> -2.8526316 | D34: ='Income Statement'!BD219 -> -4.020202 | E34: ='Income Statement'!BE219 -> -1.3135464 | F34: ='Income Statement'!BF219 -> -2.0606061 | G34: ='Income Statement'!BG219 -> -3.1068493 | H34: ='Income Statement'!BH219 -> -2.8762887 | I34: ='Income Statement'!BI219 -> -2.935 | ... Q34: ='Income Statement'!BQ219 -> -3.569161 | S34: ='Income Statement'!CU219 -> -4.340824 | T34: ='Income Statement'!CV219 -> -2.6817289 | U34: ='Income Statement'!CW219 -> -2.6966019 | V34: ='Income Statement'!CX219 -> -3.3219912 | W34: ='Income Statement'!CY219 -> -3.6438923
A35: Net Income | B35: ='Income Statement'!BB268 -> 0.25920504 | C35: ='Income Statement'!BC268 -> 0.29593826 | D35: ='Income Statement'!BD268 -> 0.30739567 | E35: ='Income Statement'!BE268 -> 0.2860323 | F35: ='Income Statement'!BF268 -> 0.35006584 | G35: ='Income Statement'!BG268 -> 0.33100694 | H35: ='Income Statement'!BH268 -> 0.35280151 | I35: ='Income Statement'!BI268 -> 0.32511241 | ... Q35: ='Income Statement'!BQ268 -> 0.31707196 | S35: ='Income Statement'!CU268 -> 0.256421 | T35: ='Income Statement'!CV268 -> 0.28769083 | U35: ='Income Statement'!CW268 -> 0.33924735 | V35: ='Income Statement'!CX268 -> 0.37565291 | W35: ='Income Statement'!CY268 -> 0.33071588
A36: GAAP EBITDA | B36: ='Cash Flow Statement'!BB62 -> 0.35478593 | C36: ='Cash Flow Statement'!BC62 -> 0.40657676 | D36: ='Cash Flow Statement'!BD62 -> 0.39254656 | E36: ='Cash Flow Statement'!BE62 -> 0.37349981 | F36: ='Cash Flow Statement'!BF62 -> 0.42733715 | G36: ='Cash Flow Statement'!BG62 -> 0.4363114 | H36: ='Cash Flow Statement'!BH62 -> 0.43603536 | I36: ='Cash Flow Statement'!BI62 -> 0.43097977 | ... Q36: ='Cash Flow Statement'!BQ62 -> 0.48329891 | S36: ='Cash Flow Statement'!CU62 -> 0.38810335 | T36: ='Cash Flow Statement'!CV62 -> 0.38202317 | U36: ='Cash Flow Statement'!CW62 -> 0.43271166 | V36: ='Cash Flow Statement'!CX62 -> 0.44909609 | W36: ='Cash Flow Statement'!CY62 -> 0.4875416
A37: Capex | B37: ='Capex & Depreciation'!BB5 -> -0.10830779 | C37: ='Capex & Depreciation'!BC5 -> -0.11097685 | D37: ='Capex & Depreciation'!BD5 -> -0.12575916 | E37: ='Capex & Depreciation'!BE5 -> -0.15235606 | F37: ='Capex & Depreciation'!BF5 -> -0.17771071 | G37: ='Capex & Depreciation'!BG5 -> -0.18479434 | H37: ='Capex & Depreciation'!BH5 -> -0.1752002 | I37: ='Capex & Depreciation'!BI5 -> -0.17490597 | ... Q37: ='Capex & Depreciation'!BQ5 -> -0.34815273 | S37: ='Capex & Depreciation'!CU5 -> -0.13461974 | T37: ='Capex & Depreciation'!CV5 -> -0.12573097 | U37: ='Capex & Depreciation'!CW5 -> -0.17801354 | V37: ='Capex & Depreciation'!CX5 -> -0.27007486 | W37: ='Capex & Depreciation'!CY5 -> -0.31035604
A38: FCF | B38: ='Cash Flow Statement'!BB77 -> 0.29655909 | C38: ='Cash Flow Statement'!BC77 -> 0.35087889 | D38: ='Cash Flow Statement'!BD77 -> 0.35285944 | E38: ='Cash Flow Statement'!BE77 -> 0.10917538 | F38: ='Cash Flow Statement'!BF77 -> 0.24907905 | G38: ='Cash Flow Statement'!BG77 -> 0.18855021 | H38: ='Cash Flow Statement'!BH77 -> 0.23658265 | I38: ='Cash Flow Statement'!BI77 -> 0.30429669 | ... Q38: ='Cash Flow Statement'!BQ77 -> 0.15655768 | S38: ='Cash Flow Statement'!CU77 -> 0.25658348 | T38: ='Cash Flow Statement'!CV77 -> 0.27092722 | U38: ='Cash Flow Statement'!CW77 -> 0.246559 | V38: ='Cash Flow Statement'!CX77 -> 0.14143434 | W38: ='Cash Flow Statement'!CY77 -> 0.18535312
A39: FCF Minus SBC | B39: ='Cash Flow Statement'!BB84 -> 0.20555919 | C39: ='Cash Flow Statement'!BC84 -> 0.25785039 | D39: ='Cash Flow Statement'!BD84 -> 0.26319652 | E39: ='Cash Flow Statement'!BE84 -> 0.030930258 | F39: ='Cash Flow Statement'!BF84 -> 0.17120116 | G39: ='Cash Flow Statement'!BG84 -> 0.10635555 | H39: ='Cash Flow Statement'!BH84 -> 0.15816443 | I39: ='Cash Flow Statement'!BI84 -> 0.23311403 | ... Q39: ='Cash Flow Statement'!BQ84 -> 0.092206776 | S39: ='Cash Flow Statement'!CU84 -> 0.17379779 | T39: ='Cash Flow Statement'!CV84 -> 0.1833666 | U39: ='Cash Flow Statement'!CW84 -> 0.1693526 | V39: ='Cash Flow Statement'!CX84 -> 0.070293052 | W39: ='Cash Flow Statement'!CY84 -> 0.11784589
A41: Year-on-Year Growth
A43: Consolidated Total Revenue | B43: ='Income Statement'!BB66 -> 0.026113423 | C43: ='Income Statement'!BC66 -> 0.070589079 | D43: ='Income Statement'!BD66 -> 0.11001274 | E43: ='Income Statement'!BE66 -> 0.13494109 | F43: ='Income Statement'!BF66 -> 0.15406881 | G43: ='Income Statement'!BG66 -> 0.13589084 | H43: ='Income Statement'!BH66 -> 0.15092642 | I43: ='Income Statement'!BI66 -> 0.11770363 | ... Q43: ='Income Statement'!BQ66 -> 0.12311913 | S43: ='Income Statement'!CU66 -> 0.097808156 | T43: ='Income Statement'!CV66 -> 0.086827702 | U43: ='Income Statement'!CW66 -> 0.13866243 | V43: ='Income Statement'!CX66 -> 0.14613225 | W43: ='Income Statement'!CY66 -> 0.13688308
A44: GAAP Gross Profit | B44: ='Income Statement'!BB176 -> 0.019863584 | C44: ='Income Statement'!BC176 -> 0.078497259 | D44: ='Income Statement'!BD176 -> 0.14577951 | E44: ='Income Statement'!BE176 -> 0.19724365 | F44: ='Income Statement'!BF176 -> 0.19532865 | G44: ='Income Statement'!BG176 -> 0.15336863 | H44: ='Income Statement'!BH176 -> 0.19165286 | I44: ='Income Statement'!BI176 -> 0.14611675 | ... Q44: ='Income Statement'!BQ176 -> 0.11235075 | S44: ='Income Statement'!CU176 -> 0.067724168 | T44: ='Income Statement'!CV176 -> 0.11127285 | U44: ='Income Statement'!CW176 -> 0.1703416 | V44: ='Income Statement'!CX176 -> 0.16168013 | W44: ='Income Statement'!CY176 -> 0.12816237
A45: GAAP Gross Profit Margin (bps) | B45: ='Income Statement'!BB174 -> -110.0813 | C45: ='Income Statement'!BC174 -> -9.3967749 | D45: ='Income Statement'!BD174 -> 161.66763 | E45: ='Income Statement'!BE174 -> 289.74752 | F45: ='Income Statement'!BF174 -> 181.15524 | G45: ='Income Statement'!BG174 -> 22.278101 | H45: ='Income Statement'!BH174 -> 161.80264 | I45: ='Income Statement'!BI174 -> 104.90981 | ... Q45: ='Income Statement'!BQ174 -> -125 | S45: ='Income Statement'!CU174 -> -220.27655 | T45: ='Income Statement'!CV174 -> 88.70749 | U45: ='Income Statement'!CW174 -> 116.89919 | V45: ='Income Statement'!CX174 -> 33.147002 | W45: ='Income Statement'!CY174 -> -123.86973
A46: Total GAAP Operating Expenses | B46: ='Income Statement'!BB199 -> 0.18790261 | C46: ='Income Statement'!BC199 -> 0.035870429 | D46: ='Income Statement'!BD199 -> 0.063560748 | E46: ='Income Statement'!BE199 -> 0.11052958 | F46: ='Income Statement'!BF199 -> -0.018612132 | G46: ='Income Statement'!BG199 -> 0.046043165 | H46: ='Income Statement'!BH199 -> 0.052077212 | I46: ='Income Statement'!BI199 -> -0.006150651 | ... Q46: ='Income Statement'!BQ199 -> 0.10386107 | S46: ='Income Statement'!CU199 -> 0.2030919 | T46: ='Income Statement'!CV199 -> 0.097541294 | U46: ='Income Statement'!CW199 -> 0.017299959 | V46: ='Income Statement'!CX199 -> 0.16996102 | W46: ='Income Statement'!CY199 -> 0.05051104
A47: R&D | B47: ='Income Statement'!BB182 -> 0.25759403 | C47: ='Income Statement'!BC182 -> 0.07590692 | D47: ='Income Statement'!BD182 -> 0.09588241 | E47: ='Income Statement'!BE182 -> 0.17979936 | F47: ='Income Statement'!BF182 -> 0.037931636 | G47: ='Income Statement'!BG182 -> 0.120136 | H47: ='Income Statement'!BH182 -> 0.10561379 | I47: ='Income Statement'!BI182 -> 0.082803599 | ... Q47: ='Income Statement'!BQ182 -> 0.145 | S47: ='Income Statement'!CU182 -> 0.25150497 | T47: ='Income Statement'!CV182 -> 0.15005063 | U47: ='Income Statement'!CW182 -> 0.085830013 | V47: ='Income Statement'!CX182 -> 0.17435632 | W47: ='Income Statement'!CY182 -> 0.14259453
A48: Sales & Marketing | B48: ='Income Statement'!BB187 -> 0.12154506 | C48: ='Income Statement'!BC187 -> 0.022775264 | D48: ='Income Statement'!BD187 -> -0.0064944436 | E48: ='Income Statement'!BE187 -> 0.074620632 | F48: ='Income Statement'!BF187 -> -0.016378387 | G48: ='Income Statement'!BG187 -> 0.0016221796 | H48: ='Income Statement'!BH187 -> 0.049825683 | I48: ='Income Statement'!BI187 -> -0.046119964 | ... Q48: ='Income Statement'!BQ187 -> 0.045 | S48: ='Income Statement'!CU187 -> 0.15952339 | T48: ='Income Statement'!CV187 -> 0.050814921 | U48: ='Income Statement'!CW187 -> -0.003904431 | V48: ='Income Statement'!CX187 -> 0.017073504 | W48: ='Income Statement'!CY187 -> 0.045
A49: G&A | B49: ='Income Statement'!BB192 -> 0.11410788 | C49: ='Income Statement'!BC192 -> -0.04812688 | D49: ='Income Statement'!BD192 -> 0.10619961 | E49: ='Income Statement'!BE192 -> 0.021585557 | F49: ='Income Statement'!BF192 -> -0.19499867 | G49: ='Income Statement'!BG192 -> -0.092789428 | H49: ='Income Statement'!BH192 -> -0.095501382 | I49: ='Income Statement'!BI192 -> -0.15386093 | ... Q49: ='Income Statement'!BQ192 -> 0.065 | S49: ='Income Statement'!CU192 -> 0.16387861 | T49: ='Income Statement'!CV192 -> 0.044581531 | U49: ='Income Statement'!CW192 -> -0.13619482 | V49: ='Income Statement'!CX192 -> 0.45433465 | W49: ='Income Statement'!CY192 -> -0.20044191
A50: Stock-Based Comp | B50: ='Income Statement'!BB231 -> 0.1731794 | C50: ='Income Statement'!BC231 -> 0.20744458 | D50: ='Income Statement'!BD231 -> 0.15413987 | E50: ='Income Statement'!BE231 -> 0.10960784 | F50: ='Income Statement'!BF231 -> -0.0037850114 | G50: ='Income Statement'!BG231 -> 0.015760305 | H50: ='Income Statement'!BH231 -> 0.017934877 | I50: ='Income Statement'!BI231 -> 0.02668316 | ... Q50: ='Income Statement'!BQ231 -> 0.09 | S50: ='Income Statement'!CU231 -> 0.25923517 | T50: ='Income Statement'!CV231 -> 0.16000413 | U50: ='Income Statement'!CW231 -> 0.014470169 | V50: ='Income Statement'!CX231 -> 0.065306122 | W50: ='Income Statement'!CY231 -> 0.09
A51: GAAP Operating Income | B51: ='Income Statement'!BB204 -> -0.13332338 | C51: ='Income Statement'!BC204 -> 0.1226032 | D51: ='Income Statement'!BD204 -> 0.24557922 | E51: ='Income Statement'!BE204 -> 0.30490088 | F51: ='Income Statement'!BF204 -> 0.46264714 | G51: ='Income Statement'!BG204 -> 0.25583845 | H51: ='Income Statement'!BH204 -> 0.33631636 | I51: ='Income Statement'!BI204 -> 0.30700089 | ... Q51: ='Income Statement'!BQ204 -> 0.11876062 | S51: ='Income Statement'!CU204 -> -0.049190741 | T51: ='Income Statement'!CV204 -> 0.12627936 | U51: ='Income Statement'!CW204 -> 0.33332542 | V51: ='Income Statement'!CX204 -> 0.15495152 | W51: ='Income Statement'!CY204 -> 0.19207758
A52: Google Services OI | B52: ='Income Statement'!BB210 -> -0.010740454 | C52: ='Income Statement'!BC210 -> 0.084778687 | D52: ='Income Statement'!BD210 -> 0.26764815 | E52: ='Income Statement'!BE210 -> 0.32182771 | F52: ='Income Statement'!BF210 -> 0.28338777 | G52: ='Income Statement'!BG210 -> 0.26519997 | H52: ='Income Statement'!BH210 -> 0.28905042 | I52: ='Income Statement'!BI210 -> 0.22843247 | ... Q52: ='Income Statement'!BQ210 -> 0.10465786 | S52: ='Income Statement'!CU210 -> -0.061646167 | T52: ='Income Statement'!CV210 -> 0.15911922 | U52: ='Income Statement'!CW210 -> 0.26502744 | V52: ='Income Statement'!CX210 -> 0.12449111 | W52: ='Income Statement'!CY210 -> 0.13323235
A53: Google Cloud OI | B53: ='Income Statement'!BB216 -> n/a | C53: ='Income Statement'!BC216 -> n/a | D53: ='Income Statement'!BD216 -> n/a | E53: ='Income Statement'!BE216 -> n/a | F53: ='Income Statement'!BF216 -> 3.7120419 | G53: ='Income Statement'!BG216 -> 1.9670886 | H53: ='Income Statement'!BH216 -> 6.3195489 | I53: ='Income Statement'!BI216 -> 1.4224537 | ... Q53: ='Income Statement'!BQ216 -> 0.4673913 | S53: ='Income Statement'!CU216 -> -0.15775635 | T53: ='Income Statement'!CV216 -> n/a | U53: ='Income Statement'!CW216 -> 2.5617716 | V53: ='Income Statement'!CX216 -> 1.0364054 | W53: ='Income Statement'!CY216 -> 0.57102675
A54: Other Bets OI | B54: ='Income Statement'!BB221 -> 0.46706587 | C54: ='Income Statement'!BC221 -> -0.39283047 | D54: ='Income Statement'!BD221 -> -0.025306122 | E54: ='Income Statement'!BE221 -> -0.30234438 | F54: ='Income Statement'!BF221 -> -0.16734694 | G54: ='Income Statement'!BG221 -> 0.39483395 | H54: ='Income Statement'!BH221 -> -0.065326633 | I54: ='Income Statement'!BI221 -> 0.3603708 | ... Q54: ='Income Statement'!BQ221 -> 0.14556041 | S54: ='Income Statement'!CU221 -> 0.14440879 | T54: ='Income Statement'!CV221 -> -0.11669543 | U54: ='Income Statement'!CW221 -> 0.085225885 | V54: ='Income Statement'!CX221 -> 0.18631863 | W54: ='Income Statement'!CY221 -> 0.15174507
A55: Net Income | B55: ='Income Statement'!BB270 -> -0.084266245 | C55: ='Income Statement'!BC270 -> 0.14785652 | D55: ='Income Statement'!BD270 -> 0.41545651 | E55: ='Income Statement'!BE270 -> 0.51842337 | F55: ='Income Statement'!BF270 -> 0.57212145 | G55: ='Income Statement'!BG270 -> 0.28587761 | H55: ='Income Statement'!BH270 -> 0.33582203 | I55: ='Income Statement'!BI270 -> 0.28273795 | ... Q55: ='Income Statement'!BQ270 -> 0.12701815 | S55: ='Income Statement'!CU270 -> -0.21123723 | T55: ='Income Statement'!CV270 -> 0.2304909 | U55: ='Income Statement'!CW270 -> 0.35670438 | V55: ='Income Statement'!CX270 -> 0.28019567 | W55: ='Income Statement'!CY270 -> 0.011267802
A56: GAAP EPS | B56: ='Income Statement'!BB280 -> -0.046558553 | C56: ='Income Statement'!BC280 -> 0.1905729 | D56: ='Income Statement'!BD280 -> 0.46016335 | E56: ='Income Statement'!BE280 -> 0.55999265 | F56: ='Income Statement'!BF280 -> 0.60926905 | G56: ='Income Statement'!BG280 -> 0.31356077 | H56: ='Income Statement'!BH280 -> 0.36561692 | I56: ='Income Statement'!BI280 -> 0.30912404 | ... Q56: ='Income Statement'!BQ280 -> 0.13713387 | S56: ='Income Statement'!CU280 -> -0.18756146 | T56: ='Income Statement'!CV280 -> 0.27278535 | U56: ='Income Statement'!CW280 -> 0.38656937 | V56: ='Income Statement'!CX280 -> 0.30443892 | W56: ='Income Statement'!CY280 -> 0.020796993
A57: GAAP EBITDA | B57: ='Cash Flow Statement'!BB64 -> -0.13716703 | C57: ='Cash Flow Statement'!BC64 -> 0.080635492 | D57: ='Cash Flow Statement'!BD64 -> 0.18705444 | E57: ='Cash Flow Statement'!BE64 -> 0.20804079 | F57: ='Cash Flow Statement'!BF64 -> 0.4021164 | G57: ='Cash Flow Statement'!BG64 -> 0.233723 | H57: ='Cash Flow Statement'!BH64 -> 0.29284493 | I57: ='Cash Flow Statement'!BI64 -> 0.30222485 | ... Q57: ='Cash Flow Statement'!BQ64 -> 0.16191293 | S57: ='Cash Flow Statement'!CU64 -> -0.0042235752 | T57: ='Cash Flow Statement'!CV64 -> 0.079563733 | U57: ='Cash Flow Statement'!CW64 -> 0.30317781 | V57: ='Cash Flow Statement'!CX64 -> 0.19990466 | W57: ='Cash Flow Statement'!CY64 -> 0.24701102
A58: Capex | B58: ='Capex & Depreciation'!BB6 -> -0.35734723 | C58: ='Capex & Depreciation'!BC6 -> 0.0087873462 | D58: ='Capex & Depreciation'!BD6 -> 0.10706432 | E58: ='Capex & Depreciation'!BE6 -> 0.45082291 | F58: ='Capex & Depreciation'!BF6 -> 0.91000159 | G58: ='Capex & Depreciation'!BG6 -> 0.91434379 | H58: ='Capex & Depreciation'!BH6 -> 0.62147734 | I58: ='Capex & Depreciation'!BI6 -> 0.29558036 | ... Q58: ='Capex & Depreciation'!BQ6 -> 0.32 | S58: ='Capex & Depreciation'!CU6 -> 0.27780032 | T58: ='Capex & Depreciation'!CV6 -> 0.024329046 | U58: ='Capex & Depreciation'!CW6 -> 0.62894174 | V58: ='Capex & Depreciation'!CX6 -> 0.75403065 | W58: ='Capex & Depreciation'!CY6 -> 0.32
A59: FCF | B59: ='Cash Flow Statement'!BB79 -> 0.12402089 | C59: ='Cash Flow Statement'!BC79 -> 0.72923614 | D59: ='Cash Flow Statement'!BD79 -> 0.4057971 | E59: ='Cash Flow Statement'!BE79 -> -0.50708534 | F59: ='Cash Flow Statement'!BF79 -> -0.022299652 | G59: ='Cash Flow Statement'!BG79 -> -0.38222059 | H59: ='Cash Flow Statement'!BH79 -> -0.2196363 | I59: ='Cash Flow Statement'!BI79 -> 2.1455167 | ... Q59: ='Cash Flow Statement'!BQ79 -> n/a | S59: ='Cash Flow Statement'!CU79 -> -0.10448875 | T59: ='Cash Flow Statement'!CV79 -> 0.15805699 | U59: ='Cash Flow Statement'!CW79 -> 0.047039355 | V59: ='Cash Flow Statement'!CX79 -> -0.33680682 | W59: ='Cash Flow Statement'!CY79 -> 0.50536889
A60: FCF Minus SBC | B60: ='Cash Flow Statement'!BB86 -> 0.1035503 | C60: ='Cash Flow Statement'!BC86 -> 1.0486431 | D60: ='Cash Flow Statement'!BD86 -> 0.51860193 | E60: ='Cash Flow Statement'!BE86 -> -0.79512776 | F60: ='Cash Flow Statement'!BF86 -> -0.030495979 | G60: ='Cash Flow Statement'!BG86 -> -0.52580605 | H60: ='Cash Flow Statement'!BH86 -> -0.30056946 | I60: ='Cash Flow Statement'!BI86 -> 7.5055878 | ... Q60: ='Cash Flow Statement'!BQ86 -> n/a | S60: ='Cash Flow Statement'!CU86 -> -0.21279727 | T60: ='Cash Flow Statement'!CV86 -> 0.1571295 | U60: ='Cash Flow Statement'!CW86 -> 0.062591687 | V60: ='Cash Flow Statement'!CX86 -> -0.52012669 | W60: ='Cash Flow Statement'!CY86 -> 0.92575006

Sheet Revenue Summary
A1: GOOGL
A2: Revenue & Key Metrics Summary
A3: (USD millions) | B3: ='Income Statement'!BB1 -> 1Q23 | C3: ='Income Statement'!BC1 -> 2Q23 | D3: ='Income Statement'!BD1 -> 3Q23 | E3: ='Income Statement'!BE1 -> 4Q23 | F3: ='Income Statement'!BF1 -> 1Q24 | G3: ='Income Statement'!BG1 -> 2Q24 | H3: ='Income Statement'!BH1 -> 3Q24 | I3: ='Income Statement'!BI1 -> 4Q24 | ... Q3: ='Income Statement'!BQ1 -> 4Q26E | S3: ='Income Statement'!CU1 -> 2022 | T3: ='Income Statement'!CV1 -> 2023 | U3: ='Income Statement'!CW1 -> 2024 | V3: ='Income Statement'!CX1 -> 2025E | W3: ='Income Statement'!CY1 -> 2026E
A5: Gross Consolidated Revenue | B5: ='Income Statement'!BB64 -> 69787 | C5: ='Income Statement'!BC64 -> 74604 | D5: ='Income Statement'!BD64 -> 76693 | E5: ='Income Statement'!BE64 -> 86310 | F5: ='Income Statement'!BF64 -> 80539 | G5: ='Income Statement'!BG64 -> 84742 | H5: ='Income Statement'!BH64 -> 88268 | I5: ='Income Statement'!BI64 -> 96469 | ... Q5: ='Income Statement'!BQ64 -> 125967.83 | S5: ='Income Statement'!CU64 -> 282836 | T5: ='Income Statement'!CV64 -> 307394 | U5: ='Income Statement'!CW64 -> 350018 | V5: ='Income Statement'!CX64 -> 401166.92 | W5: ='Income Statement'!CY64 -> 456079.88
A6: Google Segment Revenues | B6: ='Income Statement'!BB3 -> 69415 | C6: ='Income Statement'!BC3 -> 74316 | D6: ='Income Statement'!BD3 -> 76397 | E6: ='Income Statement'!BE3 -> 85503 | F6: ='Income Statement'!BF3 -> 79972 | G6: ='Income Statement'!BG3 -> 84275 | H6: ='Income Statement'!BH3 -> 87863 | I6: ='Income Statement'!BI3 -> 96049 | ... Q6: ='Income Statement'!BQ3 -> 125526.83 | S6: ='Income Statement'!CU3 -> 279808 | T6: ='Income Statement'!CV3 -> 305631 | U6: ='Income Statement'!CW3 -> 348159 | V6: ='Income Statement'!CX3 -> 399638.92 | W6: ='Income Statement'!CY3 -> 454413.53
A7: Google Services Revenue | B7: ='Income Statement'!BB8 -> 61961 | C7: ='Income Statement'!BC8 -> 66285 | D7: ='Income Statement'!BD8 -> 67986 | E7: ='Income Statement'!BE8 -> 76311 | F7: ='Income Statement'!BF8 -> 70398 | G7: ='Income Statement'!BG8 -> 73928 | H7: ='Income Statement'!BH8 -> 76510 | I7: ='Income Statement'!BI8 -> 84094 | ... Q7: ='Income Statement'!BQ8 -> 104605.58 | S7: ='Income Statement'!CU8 -> 253528 | T7: ='Income Statement'!CV8 -> 272543 | U7: ='Income Statement'!CW8 -> 304930 | V7: ='Income Statement'!CX8 -> 341860.92 | W7: ='Income Statement'!CY8 -> 377395.63
A8: Google Advertising Revenue | B8: ='Income Statement'!BB14 -> 54548 | C8: ='Income Statement'!BC14 -> 58143 | D8: ='Income Statement'!BD14 -> 59647 | E8: ='Income Statement'!BE14 -> 65517 | F8: ='Income Statement'!BF14 -> 61659 | G8: ='Income Statement'!BG14 -> 64616 | H8: ='Income Statement'!BH14 -> 65854 | I8: ='Income Statement'!BI14 -> 72461 | ... Q8: ='Income Statement'!BQ14 -> 89157.995 | S8: ='Income Statement'!CU14 -> 224473 | T8: ='Income Statement'!CV14 -> 237855 | U8: ='Income Statement'!CW14 -> 264590 | V8: ='Income Statement'!CX14 -> 293595.4 | W8: ='Income Statement'!CY14 -> 322907.25
A9: Google Search & Other | B9: ='Income Statement'!BB20 -> 40359 | C9: ='Income Statement'!BC20 -> 42628 | D9: ='Income Statement'!BD20 -> 44026 | E9: ='Income Statement'!BE20 -> 48020 | F9: ='Income Statement'!BF20 -> 46156 | G9: ='Income Statement'!BG20 -> 48509 | H9: ='Income Statement'!BH20 -> 49385 | I9: ='Income Statement'!BI20 -> 54034 | ... Q9: ='Income Statement'!BQ20 -> 68066.63 | S9: ='Income Statement'!CU20 -> 162450 | T9: ='Income Statement'!CV20 -> 175033 | U9: ='Income Statement'!CW20 -> 198084 | V9: ='Income Statement'!CX20 -> 223057.76 | W9: ='Income Statement'!CY20 -> 247793.14
A10: Youtube Ads | B10: ='Income Statement'!BB27 -> 6693 | C10: ='Income Statement'!BC27 -> 7665 | D10: ='Income Statement'!BD27 -> 7952 | E10: ='Income Statement'!BE27 -> 9200 | F10: ='Income Statement'!BF27 -> 8090 | G10: ='Income Statement'!BG27 -> 8663 | H10: ='Income Statement'!BH27 -> 8921 | I10: ='Income Statement'!BI27 -> 10473 | ... Q10: ='Income Statement'!BQ27 -> 13491.319 | S10: ='Income Statement'!CU27 -> 29243 | T10: ='Income Statement'!CV27 -> 31510 | U10: ='Income Statement'!CW27 -> 36147 | V10: ='Income Statement'!CX27 -> 40818.49 | W10: ='Income Statement'!CY27 -> 45989.344
A11: Google Network Members' Properties | B11: ='Income Statement'!BB34 -> 7496 | C11: ='Income Statement'!BC34 -> 7850 | D11: ='Income Statement'!BD34 -> 7669 | E11: ='Income Statement'!BE34 -> 8297 | F11: ='Income Statement'!BF34 -> 7413 | G11: ='Income Statement'!BG34 -> 7444 | H11: ='Income Statement'!BH34 -> 7548 | I11: ='Income Statement'!BI34 -> 7954 | ... Q11: ='Income Statement'!BQ34 -> 7600.047 | S11: ='Income Statement'!CU34 -> 32780 | T11: ='Income Statement'!CV34 -> 31312 | U11: ='Income Statement'!CW34 -> 30359 | V11: ='Income Statement'!CX34 -> 29719.15 | W11: ='Income Statement'!CY34 -> 29124.767
A12: Google Other | B12: ='Income Statement'!BB41 -> 7413 | C12: ='Income Statement'!BC41 -> 8142 | D12: ='Income Statement'!BD41 -> 8339 | E12: ='Income Statement'!BE41 -> 10794 | F12: ='Income Statement'!BF41 -> 8739 | G12: ='Income Statement'!BG41 -> 9312 | H12: ='Income Statement'!BH41 -> 10656 | I12: ='Income Statement'!BI41 -> 11633 | ... Q12: ='Income Statement'!BQ41 -> 15447.581 | S12: ='Income Statement'!CU41 -> 29055 | T12: ='Income Statement'!CV41 -> 34688 | U12: ='Income Statement'!CW41 -> 40340 | V12: ='Income Statement'!CX41 -> 48265.518 | W12: ='Income Statement'!CY41 -> 54488.381
A13: Google Cloud | B13: ='Income Statement'!BB47 -> 7454 | C13: ='Income Statement'!BC47 -> 8031 | D13: ='Income Statement'!BD47 -> 8411 | E13: ='Income Statement'!BE47 -> 9192 | F13: ='Income Statement'!BF47 -> 9574 | G13: ='Income Statement'!BG47 -> 10347 | H13: ='Income Statement'!BH47 -> 11353 | I13: ='Income Statement'!BI47 -> 11955 | ... Q13: ='Income Statement'!BQ47 -> 20921.25 | S13: ='Income Statement'!CU47 -> 26280 | T13: ='Income Statement'!CV47 -> 33088 | U13: ='Income Statement'!CW47 -> 43229 | V13: ='Income Statement'!CX47 -> 57778 | W13: ='Income Statement'!CY47 -> 77017.9
A14: Other Bets | B14: ='Income Statement'!BB53 -> 288 | C14: ='Income Statement'!BC53 -> 285 | D14: ='Income Statement'!BD53 -> 297 | E14: ='Income Statement'!BE53 -> 657 | F14: ='Income Statement'!BF53 -> 495 | G14: ='Income Statement'!BG53 -> 365 | H14: ='Income Statement'!BH53 -> 388 | I14: ='Income Statement'!BI53 -> 400 | ... Q14: ='Income Statement'!BQ53 -> 441 | S14: ='Income Statement'!CU53 -> 1068 | T14: ='Income Statement'!CV53 -> 1527 | U14: ='Income Statement'!CW53 -> 1648 | V14: ='Income Statement'!CX53 -> 1587 | W14: ='Income Statement'!CY53 -> 1666.35
A15: Total TAC | B15: ='Income Statement'!BB68 -> -11721 | C15: ='Income Statement'!BC68 -> -12537 | D15: ='Income Statement'!BD68 -> -12642 | E15: ='Income Statement'!BE68 -> -13986 | F15: ='Income Statement'!BF68 -> -12946 | G15: ='Income Statement'!BG68 -> -13387 | H15: ='Income Statement'!BH68 -> -13719 | I15: ='Income Statement'!BI68 -> -14848 | ... Q15: ='Income Statement'!BQ68 -> -17714.646 | S15: ='Income Statement'!CU68 -> -48955 | T15: ='Income Statement'!CV68 -> -50886 | U15: ='Income Statement'!CW68 -> -54900 | V15: ='Income Statement'!CX68 -> -59972.622 | W15: ='Income Statement'!CY68 -> -64157.875
A16: Net Consolidated Revenue | B16: ='Income Statement'!BB85 -> 58066 | C16: ='Income Statement'!BC85 -> 62067 | D16: ='Income Statement'!BD85 -> 64051 | E16: ='Income Statement'!BE85 -> 72324 | F16: ='Income Statement'!BF85 -> 67593 | G16: ='Income Statement'!BG85 -> 71355 | H16: ='Income Statement'!BH85 -> 74549 | I16: ='Income Statement'!BI85 -> 81621 | ... Q16: ='Income Statement'!BQ85 -> 108253.18 | S16: ='Income Statement'!CU85 -> 233881 | T16: ='Income Statement'!CV85 -> 256508 | U16: ='Income Statement'!CW85 -> 295118 | V16: ='Income Statement'!CX85 -> 341194.3 | W16: ='Income Statement'!CY85 -> 391922.01
A18: Year-on-Year Growth
A20: Gross Consolidated Revenue | B20: ='Income Statement'!BB66 -> 0.026113423 | C20: ='Income Statement'!BC66 -> 0.070589079 | D20: ='Income Statement'!BD66 -> 0.11001274 | E20: ='Income Statement'!BE66 -> 0.13494109 | F20: ='Income Statement'!BF66 -> 0.15406881 | G20: ='Income Statement'!BG66 -> 0.13589084 | H20: ='Income Statement'!BH66 -> 0.15092642 | I20: ='Income Statement'!BI66 -> 0.11770363 | ... Q20: ='Income Statement'!BQ66 -> 0.12311913 | S20: ='Income Statement'!CU66 -> 0.097808156 | T20: ='Income Statement'!CV66 -> 0.086827702 | U20: ='Income Statement'!CW66 -> 0.13866243 | V20: ='Income Statement'!CX66 -> 0.14613225 | W20: ='Income Statement'!CY66 -> 0.13688308
A21: Google Segment Revenues | B21: ='Income Statement'!BB5 -> 0.031533741 | C21: ='Income Statement'!BC5 -> 0.075220279 | D21: ='Income Statement'!BD5 -> 0.11945197 | E21: ='Income Statement'!BE5 -> 0.13771905 | F21: ='Income Statement'!BF5 -> 0.15208528 | G21: ='Income Statement'!BG5 -> 0.13400883 | H21: ='Income Statement'!BH5 -> 0.15008443 | I21: ='Income Statement'!BI5 -> 0.1233407 | ... Q21: ='Income Statement'!BQ5 -> 0.12339397 | S21: ='Income Statement'!CU5 -> 0.089870879 | T21: ='Income Statement'!CV5 -> 0.092288283 | U21: ='Income Statement'!CW5 -> 0.13914819 | V21: ='Income Statement'!CX5 -> 0.14786324 | W21: ='Income Statement'!CY5 -> 0.13706026
A22: Google Services Revenue | B22: ='Income Statement'!BB10 -> 0.0079548412 | C22: ='Income Statement'!BC10 -> 0.054804984 | D22: ='Income Statement'!BD10 -> 0.10767877 | E22: ='Income Statement'!BE10 -> 0.1249005 | F22: ='Income Statement'!BF10 -> 0.1361663 | G22: ='Income Statement'!BG10 -> 0.11530512 | H22: ='Income Statement'!BH10 -> 0.12537875 | I22: ='Income Statement'!BI10 -> 0.10199054 | ... Q22: ='Income Statement'!BQ10 -> 0.1010891 | S22: ='Income Statement'!CU10 -> 0.067355986 | T22: ='Income Statement'!CV10 -> 0.075001578 | U22: ='Income Statement'!CW10 -> 0.11883262 | V22: ='Income Statement'!CX10 -> 0.12111277 | W22: ='Income Statement'!CY10 -> 0.10394494
A23: Google Advertising Revenue | B23: ='Income Statement'!BB16 -> -0.0020672875 | C23: ='Income Statement'!BC16 -> 0.032955514 | D23: ='Income Statement'!BD16 -> 0.094801953 | E23: ='Income Statement'!BE16 -> 0.10966769 | F23: ='Income Statement'!BF16 -> 0.13036225 | G23: ='Income Statement'!BG16 -> 0.11132896 | H23: ='Income Statement'!BH16 -> 0.10406223 | I23: ='Income Statement'!BI16 -> 0.10598776 | ... Q23: ='Income Statement'!BQ16 -> 0.09816175 | S23: ='Income Statement'!CU16 -> 0.071485511 | T23: ='Income Statement'!CV16 -> 0.059615188 | U23: ='Income Statement'!CW16 -> 0.11240041 | V23: ='Income Statement'!CX16 -> 0.10962395 | W23: ='Income Statement'!CY16 -> 0.099837567
A24: Google Search & Other | B24: ='Income Statement'!BB22 -> 0.01870362 | C24: ='Income Statement'!BC22 -> 0.047654157 | D24: ='Income Statement'!BD22 -> 0.11348289 | E24: ='Income Statement'!BE22 -> 0.12712421 | F24: ='Income Statement'!BF22 -> 0.14363587 | G24: ='Income Statement'!BG22 -> 0.13796096 | H24: ='Income Statement'!BH22 -> 0.12172353 | I24: ='Income Statement'!BI22 -> 0.12523948 | ... Q24: ='Income Statement'!BQ22 -> 0.105 | S24: ='Income Statement'!CU22 -> 0.090627119 | T24: ='Income Statement'!CV22 -> 0.077457679 | U24: ='Income Statement'!CW22 -> 0.13169517 | V24: ='Income Statement'!CX22 -> 0.12607661 | W24: ='Income Statement'!CY22 -> 0.11089226
A25: Youtube Ads | B25: ='Income Statement'!BB29 -> -0.025622361 | C25: ='Income Statement'!BC29 -> 0.044277929 | D25: ='Income Statement'!BD29 -> 0.12459341 | E25: ='Income Statement'!BE29 -> 0.15534346 | F25: ='Income Statement'!BF29 -> 0.20872553 | G25: ='Income Statement'!BG29 -> 0.13020222 | H25: ='Income Statement'!BH29 -> 0.12185614 | I25: ='Income Statement'!BI29 -> 0.13836957 | ... Q25: ='Income Statement'!BQ29 -> 0.14 | S25: ='Income Statement'!CU29 -> 0.013797885 | T25: ='Income Statement'!CV29 -> 0.077522826 | U25: ='Income Statement'!CW29 -> 0.14715963 | V25: ='Income Statement'!CX29 -> 0.1292359 | W25: ='Income Statement'!CY29 -> 0.1266792
A26: Google Network Members' Properties | B26: ='Income Statement'!BB36 -> -0.082945926 | C26: ='Income Statement'!BC36 -> -0.049521734 | D26: ='Income Statement'!BD36 -> -0.025787602 | E26: ='Income Statement'!BE36 -> -0.02100295 | F26: ='Income Statement'!BF36 -> -0.011072572 | G26: ='Income Statement'!BG36 -> -0.051719745 | H26: ='Income Statement'!BH36 -> -0.015777807 | I26: ='Income Statement'!BI36 -> -0.041340243 | ... Q26: ='Income Statement'!BQ36 -> -0.02 | S26: ='Income Statement'!CU36 -> 0.034036781 | T26: ='Income Statement'!CV36 -> -0.044783405 | U26: ='Income Statement'!CW36 -> -0.030435616 | V26: ='Income Statement'!CX36 -> -0.021076122 | W26: ='Income Statement'!CY36 -> -0.02
A27: Google Other | B27: ='Income Statement'!BB43 -> 0.088386434 | C27: ='Income Statement'!BC43 -> 0.24248436 | D27: ='Income Statement'!BD43 -> 0.20942712 | E27: ='Income Statement'!BE43 -> 0.2271487 | F27: ='Income Statement'!BF43 -> 0.17887495 | G27: ='Income Statement'!BG43 -> 0.14369934 | H27: ='Income Statement'!BH43 -> 0.27785106 | I27: ='Income Statement'!BI43 -> 0.077728368 | ... Q27: ='Income Statement'!BQ43 -> 0.11829448 | S27: ='Income Statement'!CU43 -> 0.036494007 | T27: ='Income Statement'!CV43 -> 0.19387369 | U27: ='Income Statement'!CW43 -> 0.16293819 | V27: ='Income Statement'!CX43 -> 0.19646797 | W27: ='Income Statement'!CY43 -> 0.1289298
A28: Google Cloud | B28: ='Income Statement'!BB49 -> 0.28053599 | C28: ='Income Statement'!BC49 -> 0.27963671 | D28: ='Income Statement'!BD49 -> 0.22466511 | E28: ='Income Statement'!BE49 -> 0.25659604 | F28: ='Income Statement'!BF49 -> 0.28441105 | G28: ='Income Statement'!BG49 -> 0.28838252 | H28: ='Income Statement'!BH49 -> 0.34978005 | I28: ='Income Statement'!BI49 -> 0.30058747 | ... Q28: ='Income Statement'!BQ49 -> 0.25 | S28: ='Income Statement'!CU49 -> 0.3683224 | T28: ='Income Statement'!CV49 -> 0.25905632 | U28: ='Income Statement'!CW49 -> 0.30648574 | V28: ='Income Statement'!CX49 -> 0.33655648 | W28: ='Income Statement'!CY49 -> 0.33299699
A29: Other Bets | B29: ='Income Statement'!BB55 -> -0.34545455 | C29: ='Income Statement'!BC55 -> 0.47668394 | D29: ='Income Statement'!BD55 -> 0.42105263 | E29: ='Income Statement'!BE55 -> 1.9070796 | F29: ='Income Statement'!BF55 -> 0.71875 | G29: ='Income Statement'!BG55 -> 0.28070175 | H29: ='Income Statement'!BH55 -> 0.30639731 | I29: ='Income Statement'!BI55 -> -0.39117199 | ... Q29: ='Income Statement'!BQ55 -> 0.05 | S29: ='Income Statement'!CU55 -> 0.41832669 | T29: ='Income Statement'!CV55 -> 0.42977528 | U29: ='Income Statement'!CW55 -> 0.079240341 | V29: ='Income Statement'!CX55 -> -0.037014563 | W29: ='Income Statement'!CY55 -> 0.05
A30: Total TAC | B30: ='Income Statement'!BB70 -> -0.022435363 | C30: ='Income Statement'!BC70 -> 0.026445063 | D30: ='Income Statement'!BD70 -> 0.069000507 | E30: ='Income Statement'!BE70 -> 0.082088975 | F30: ='Income Statement'!BF70 -> 0.10451327 | G30: ='Income Statement'!BG70 -> 0.067799314 | H30: ='Income Statement'!BH70 -> 0.085192216 | I30: ='Income Statement'!BI70 -> 0.061633062 | ... Q30: ='Income Statement'!BQ70 -> 0.064350398 | S30: ='Income Statement'!CU70 -> 0.074375631 | T30: ='Income Statement'!CV70 -> 0.039444388 | U30: ='Income Statement'!CW70 -> 0.078882207 | V30: ='Income Statement'!CX70 -> 0.092397486 | W30: ='Income Statement'!CY70 -> 0.069786062
A31: Net Consolidated Revenue | B31: ='Income Statement'!BB87 -> 0.036504168 | C31: ='Income Statement'!BC87 -> 0.079970768 | D31: ='Income Statement'!BD87 -> 0.11848217 | E31: ='Income Statement'!BE87 -> 0.14576303 | F31: ='Income Statement'!BF87 -> 0.16407192 | G31: ='Income Statement'!BG87 -> 0.14964474 | H31: ='Income Statement'!BH87 -> 0.16390064 | I31: ='Income Statement'!BI87 -> 0.12854654 | ... Q31: ='Income Statement'!BQ87 -> 0.13335963 | S31: ='Income Statement'!CU87 -> 0.10284292 | T31: ='Income Statement'!CV87 -> 0.096745781 | U31: ='Income Statement'!CW87 -> 0.15052162 | V31: ='Income Statement'!CX87 -> 0.15612838 | W31: ='Income Statement'!CY87 -> 0.1486769
A33: Quarter-on-Quarter Growth
A35: Gross Consolidated Revenue | B35: ='Income Statement'!BB65 -> -0.082329581 | C35: ='Income Statement'!BC65 -> 0.069024317 | D35: ='Income Statement'!BD65 -> 0.02800118 | E35: ='Income Statement'!BE65 -> 0.12539606 | F35: ='Income Statement'!BF65 -> -0.066863631 | G35: ='Income Statement'!BG65 -> 0.052185898 | H35: ='Income Statement'!BH65 -> 0.041608647 | I35: ='Income Statement'!BI65 -> 0.092910228 | ... Q35: ='Income Statement'!BQ65 -> 0.081490786
A36: Google Segment Revenues | B36: ='Income Statement'!BB4 -> -0.076350911 | C36: ='Income Statement'!BC4 -> 0.070604336 | D36: ='Income Statement'!BD4 -> 0.028002045 | E36: ='Income Statement'!BE4 -> 0.11919316 | F36: ='Income Statement'!BF4 -> -0.064687789 | G36: ='Income Statement'!BG4 -> 0.053806332 | H36: ='Income Statement'!BH4 -> 0.042574904 | I36: ='Income Statement'!BI4 -> 0.093167773 | ... Q36: ='Income Statement'!BQ4 -> 0.08105703
A37: Google Services Revenue | B37: ='Income Statement'!BB9 -> -0.086632861 | C37: ='Income Statement'!BC9 -> 0.069785833 | D37: ='Income Statement'!BD9 -> 0.025661914 | E37: ='Income Statement'!BE9 -> 0.12245168 | F37: ='Income Statement'!BF9 -> -0.077485553 | G37: ='Income Statement'!BG9 -> 0.05014347 | H37: ='Income Statement'!BH9 -> 0.034925874 | I37: ='Income Statement'!BI9 -> 0.099124297 | ... Q37: ='Income Statement'!BQ9 -> 0.090140073
A38: Google Advertising Revenue | B38: ='Income Statement'!BB15 -> -0.076115308 | C38: ='Income Statement'!BC15 -> 0.065905258 | D38: ='Income Statement'!BD15 -> 0.025867258 | E38: ='Income Statement'!BE15 -> 0.098412326 | F38: ='Income Statement'!BF15 -> -0.05888548 | G38: ='Income Statement'!BG15 -> 0.047957314 | H38: ='Income Statement'!BH15 -> 0.019159341 | I38: ='Income Statement'!BI15 -> 0.100328 | ... Q38: ='Income Statement'!BQ15 -> 0.094116041
A39: Google Search & Other | B39: ='Income Statement'!BB21 -> -0.052694583 | C39: ='Income Statement'!BC21 -> 0.056220422 | D39: ='Income Statement'!BD21 -> 0.032795346 | E39: ='Income Statement'!BE21 -> 0.090719121 | F39: ='Income Statement'!BF21 -> -0.03881716 | G39: ='Income Statement'!BG21 -> 0.050979288 | H39: ='Income Statement'!BH21 -> 0.018058505 | I39: ='Income Statement'!BI21 -> 0.094137896 | ... Q39: ='Income Statement'!BQ21 -> 0.084047026
A40: Youtube Ads | B40: ='Income Statement'!BB28 -> -0.15948763 | C40: ='Income Statement'!BC28 -> 0.14522636 | D40: ='Income Statement'!BD28 -> 0.037442922 | E40: ='Income Statement'!BE28 -> 0.15694165 | F40: ='Income Statement'!BF28 -> -0.12065217 | G40: ='Income Statement'!BG28 -> 0.070828183 | H40: ='Income Statement'!BH28 -> 0.029781831 | I40: ='Income Statement'!BI28 -> 0.17397153 | ... Q40: ='Income Statement'!BQ28 -> 0.17394213
A41: Google Network Members' Properties | B41: ='Income Statement'!BB35 -> -0.11551622 | C41: ='Income Statement'!BC35 -> 0.047225187 | D41: ='Income Statement'!BD35 -> -0.023057325 | E41: ='Income Statement'!BE35 -> 0.081888121 | F41: ='Income Statement'!BF35 -> -0.10654453 | G41: ='Income Statement'!BG35 -> 0.0041818427 | H41: ='Income Statement'!BH35 -> 0.013970983 | I41: ='Income Statement'!BI35 -> 0.053789083 | ... Q41: ='Income Statement'!BQ35 -> 0.054548545
A42: Google Other | B42: ='Income Statement'!BB42 -> -0.15723056 | C42: ='Income Statement'!BC42 -> 0.098340753 | D42: ='Income Statement'!BD42 -> 0.024195529 | E42: ='Income Statement'!BE42 -> 0.29439981 | F42: ='Income Statement'!BF42 -> -0.19038355 | G42: ='Income Statement'!BG42 -> 0.065568143 | H42: ='Income Statement'!BH42 -> 0.1443299 | I42: ='Income Statement'!BI42 -> 0.091685435 | ... Q42: ='Income Statement'!BQ42 -> 0.06774528
A43: Google Cloud | B43: ='Income Statement'!BB48 -> 0.019002051 | C43: ='Income Statement'!BC48 -> 0.077408103 | D43: ='Income Statement'!BD48 -> 0.047316648 | E43: ='Income Statement'!BE48 -> 0.092854595 | F43: ='Income Statement'!BF48 -> 0.041557876 | G43: ='Income Statement'!BG48 -> 0.080739503 | H43: ='Income Statement'!BH48 -> 0.097226249 | I43: ='Income Statement'!BI48 -> 0.053025632 | ... Q43: ='Income Statement'!BQ48 -> 0.037821677
A44: Other Bets | B44: ='Income Statement'!BB54 -> 0.27433628 | C44: ='Income Statement'!BC54 -> -0.010416667 | D44: ='Income Statement'!BD54 -> 0.042105263 | E44: ='Income Statement'!BE54 -> 1.2121212 | F44: ='Income Statement'!BF54 -> -0.24657534 | G44: ='Income Statement'!BG54 -> -0.26262626 | H44: ='Income Statement'!BH54 -> 0.063013699 | I44: ='Income Statement'!BI54 -> 0.030927835 | ... Q44: ='Income Statement'!BQ54 -> 0.22093023
A45: Total TAC | B45: ='Income Statement'!BB69 -> -0.093152805 | C45: ='Income Statement'!BC69 -> 0.069618633 | D45: ='Income Statement'!BD69 -> 0.0083752094 | E45: ='Income Statement'!BE69 -> 0.10631229 | F45: ='Income Statement'!BF69 -> -0.074360074 | G45: ='Income Statement'!BG69 -> 0.034064576 | H45: ='Income Statement'!BH69 -> 0.024800179 | I45: ='Income Statement'!BI69 -> 0.082294628 | ... Q45: ='Income Statement'!BQ69 -> 0.094116041
A46: Net Consolidated Revenue | B46: ='Income Statement'!BB86 -> -0.080113429 | C46: ='Income Statement'!BC86 -> 0.06890435 | D46: ='Income Statement'!BD86 -> 0.031965457 | E46: ='Income Statement'!BE86 -> 0.1291627 | F46: ='Income Statement'!BF86 -> -0.06541397 | G46: ='Income Statement'!BG86 -> 0.055656651 | H46: ='Income Statement'!BH86 -> 0.044762105 | I46: ='Income Statement'!BI86 -> 0.094863781 | ... Q46: ='Income Statement'!BQ86 -> 0.079452467

Sheet NTM Valuation
B3: Last Reported Quarter | C3: 3Q25
B4: NTM | C4: =OFFSET('Income Statement'!A1,0,MATCH('NTM Valuation'!C3,'Income Statement'!1:1,0)+3) -> 3Q26E
B5: NTM Diluted Shares (mm) | C5: =HLOOKUP($C$4,'Shares Outstanding & Corporate'!A1:CC26,ROW('Shares Outstanding & Corporate'!A9),FALSE) -> 12087.925
B6: NTM Net Debt (Cash) | C6: =HLOOKUP(C4,'Balance Sheet'!A1:CC51,ROW('Balance Sheet'!A51),FALSE) -> -72036.651
C8: =+D8-1 -> -4 | D8: =+E8-1 -> -3 | E8: =+F8-1 -> -2 | F8: -1 | H8: 0 | J8: 1 | K8: =+J8+1 -> 2 | L8: =+K8+1 -> 3 | M8: =+L8+1 -> 4 | O8: =+M8+1 -> 5 | P8: =+O8+1 -> 6 | Q8: =+P8+1 -> 7 | R8: =+Q8+1 -> 8 | T8: =+R8+1 -> 9 | U8: =+T8+1 -> 10 | V8: =+U8+1 -> 11 | W8: =+V8+1 -> 12 | Y8: =+W8+1 -> 13 | Z8: =+Y8+1 -> 14 | AA8: =+Z8+1 -> 15 | AB8: =+AA8+1 -> 16 | AD8: =+AB8+1 -> 17 | AE8: =+AD8+1 -> 18 | AF8: =+AE8+1 -> 19 | AG8: =+AF8+1 -> 20
C10: LTM | H10: Current | J10: NTM | O10: NTM +1 | T10: NTM +2 | Y10: NTM + 3 | AD10: NTM +4
C11: =CONCATENATE(IF(LEFT(C12,2)="4Q","12/31",IF(LEFT(C12,2)="1Q","3/31",IF(LEFT(C12,2)="2Q","6/30","9/30"))),"/",MID(C12,3,3)) -> 9/30/24 | D11: =CONCATENATE(IF(LEFT(D12,2)="4Q","12/31",IF(LEFT(D12,2)="1Q","3/31",IF(LEFT(D12,2)="2Q","6/30","9/30"))),"/",MID(D12,3,3)) -> 12/31/24 | E11: =CONCATENATE(IF(LEFT(E12,2)="4Q","12/31",IF(LEFT(E12,2)="1Q","3/31",IF(LEFT(E12,2)="2Q","6/30","9/30"))),"/",MID(E12,3,3)) -> 3/31/25 | F11: =CONCATENATE(IF(LEFT(F12,2)="4Q","12/31",IF(LEFT(F12,2)="1Q","3/31",IF(LEFT(F12,2)="2Q","6/30","9/30"))),"/",MID(F12,3,3)) -> 6/30/25 | H11: =CONCATENATE(IF(LEFT(H12,2)="4Q","12/31",IF(LEFT(H12,2)="1Q","3/31",IF(LEFT(H12,2)="2Q","6/30","9/30"))),"/",MID(H12,3,3)) -> 9/30/25 | J11: =CONCATENATE(IF(LEFT(J12,2)="4Q","12/31",IF(LEFT(J12,2)="1Q","3/31",IF(LEFT(J12,2)="2Q","6/30","9/30"))),"/",MID(J12,3,3)) -> 12/31/25E | K11: =CONCATENATE(IF(LEFT(K12,2)="4Q","12/31",IF(LEFT(K12,2)="1Q","3/31",IF(LEFT(K12,2)="2Q","6/30","9/30"))),"/",MID(K12,3,3)) -> 3/31/26E | L11: =CONCATENATE(IF(LEFT(L12,2)="4Q","12/31",IF(LEFT(L12,2)="1Q","3/31",IF(LEFT(L12,2)="2Q","6/30","9/30"))),"/",MID(L12,3,3)) -> 6/30/26E | M11: =CONCATENATE(IF(LEFT(M12,2)="4Q","12/31",IF(LEFT(M12,2)="1Q","3/31",IF(LEFT(M12,2)="2Q","6/30","9/30"))),"/",MID(M12,3,3)) -> 9/30/26E | O11: =CONCATENATE(IF(LEFT(O12,2)="4Q","12/31",IF(LEFT(O12,2)="1Q","3/31",IF(LEFT(O12,2)="2Q","6/30","9/30"))),"/",MID(O12,3,3)) -> 12/31/26E | P11: =CONCATENATE(IF(LEFT(P12,2)="4Q","12/31",IF(LEFT(P12,2)="1Q","3/31",IF(LEFT(P12,2)="2Q","6/30","9/30"))),"/",MID(P12,3,3)) -> 3/31/27E | Q11: =CONCATENATE(IF(LEFT(Q12,2)="4Q","12/31",IF(LEFT(Q12,2)="1Q","3/31",IF(LEFT(Q12,2)="2Q","6/30","9/30"))),"/",MID(Q12,3,3)) -> 6/30/27E | R11: =CONCATENATE(IF(LEFT(R12,2)="4Q","12/31",IF(LEFT(R12,2)="1Q","3/31",IF(LEFT(R12,2)="2Q","6/30","9/30"))),"/",MID(R12,3,3)) -> 9/30/27E | T11: =CONCATENATE(IF(LEFT(T12,2)="4Q","12/31",IF(LEFT(T12,2)="1Q","3/31",IF(LEFT(T12,2)="2Q","6/30","9/30"))),"/",MID(T12,3,3)) -> 12/31/27E | U11: =CONCATENATE(IF(LEFT(U12,2)="4Q","12/31",IF(LEFT(U12,2)="1Q","3/31",IF(LEFT(U12,2)="2Q","6/30","9/30"))),"/",MID(U12,3,3)) -> 3/31/28E | V11: =CONCATENATE(IF(LEFT(V12,2)="4Q","12/31",IF(LEFT(V12,2)="1Q","3/31",IF(LEFT(V12,2)="2Q","6/30","9/30"))),"/",MID(V12,3,3)) -> 6/30/28E | W11: =CONCATENATE(IF(LEFT(W12,2)="4Q","12/31",IF(LEFT(W12,2)="1Q","3/31",IF(LEFT(W12,2)="2Q","6/30","9/30"))),"/",MID(W12,3,3)) -> 9/30/28E | Y11: =CONCATENATE(IF(LEFT(Y12,2)="4Q","12/31",IF(LEFT(Y12,2)="1Q","3/31",IF(LEFT(Y12,2)="2Q","6/30","9/30"))),"/",MID(Y12,3,3)) -> 12/31/28E | Z11: =CONCATENATE(IF(LEFT(Z12,2)="4Q","12/31",IF(LEFT(Z12,2)="1Q","3/31",IF(LEFT(Z12,2)="2Q","6/30","9/30"))),"/",MID(Z12,3,3)) -> 3/31/29E | AA11: =CONCATENATE(IF(LEFT(AA12,2)="4Q","12/31",IF(LEFT(AA12,2)="1Q","3/31",IF(LEFT(AA12,2)="2Q","6/30","9/30"))),"/",MID(AA12,3,3)) -> 6/30/29E | AB11: =CONCATENATE(IF(LEFT(AB12,2)="4Q","12/31",IF(LEFT(AB12,2)="1Q","3/31",IF(LEFT(AB12,2)="2Q","6/30","9/30"))),"/",MID(AB12,3,3)) -> 9/30/29E | AD11: =CONCATENATE(IF(LEFT(AD12,2)="4Q","12/31",IF(LEFT(AD12,2)="1Q","3/31",IF(LEFT(AD12,2)="2Q","6/30","9/30"))),"/",MID(AD12,3,3)) -> 12/31/29E | AE11: =CONCATENATE(IF(LEFT(AE12,2)="4Q","12/31",IF(LEFT(AE12,2)="1Q","3/31",IF(LEFT(AE12,2)="2Q","6/30","9/30"))),"/",MID(AE12,3,3)) -> 3/31/30E | AF11: =CONCATENATE(IF(LEFT(AF12,2)="4Q","12/31",IF(LEFT(AF12,2)="1Q","3/31",IF(LEFT(AF12,2)="2Q","6/30","9/30"))),"/",MID(AF12,3,3)) -> 6/30/30E | AG11: =CONCATENATE(IF(LEFT(AG12,2)="4Q","12/31",IF(LEFT(AG12,2)="1Q","3/31",IF(LEFT(AG12,2)="2Q","6/30","9/30"))),"/",MID(AG12,3,3)) -> 9/30/30E
C12: =OFFSET('Income Statement'!$A1,0,MATCH('NTM Valuation'!$C3,'Income Statement'!1:1,0)+C8-1) -> 3Q24 | D12: =OFFSET('Income Statement'!$A1,0,MATCH('NTM Valuation'!$C3,'Income Statement'!1:1,0)+D8-1) -> 4Q24 | E12: =OFFSET('Income Statement'!$A1,0,MATCH('NTM Valuation'!$C3,'Income Statement'!1:1,0)+E8-1) -> 1Q25 | F12: =OFFSET('Income Statement'!$A1,0,MATCH('NTM Valuation'!$C3,'Income Statement'!1:1,0)+F8-1) -> 2Q25 | H12: =OFFSET('Income Statement'!$A1,0,MATCH('NTM Valuation'!$C3,'Income Statement'!1:1,0)+H8-1) -> 3Q25 | J12: =OFFSET('Income Statement'!$A1,0,MATCH('NTM Valuation'!$C3,'Income Statement'!1:1,0)+J8-1) -> 4Q25E | K12: =OFFSET('Income Statement'!$A1,0,MATCH('NTM Valuation'!$C3,'Income Statement'!1:1,0)+K8-1) -> 1Q26E | L12: =OFFSET('Income Statement'!$A1,0,MATCH('NTM Valuation'!$C3,'Income Statement'!1:1,0)+L8-1) -> 2Q26E | M12: =OFFSET('Income Statement'!$A1,0,MATCH('NTM Valuation'!$C3,'Income Statement'!1:1,0)+M8-1) -> 3Q26E | O12: =OFFSET('Income Statement'!$A1,0,MATCH('NTM Valuation'!$C3,'Income Statement'!1:1,0)+O8-1) -> 4Q26E | P12: =OFFSET('Income Statement'!$A1,0,MATCH('NTM Valuation'!$C3,'Income Statement'!1:1,0)+P8-1) -> 1Q27E | Q12: =OFFSET('Income Statement'!$A1,0,MATCH('NTM Valuation'!$C3,'Income Statement'!1:1,0)+Q8-1) -> 2Q27E | R12: =OFFSET('Income Statement'!$A1,0,MATCH('NTM Valuation'!$C3,'Income Statement'!1:1,0)+R8-1) -> 3Q27E | T12: =OFFSET('Income Statement'!$A1,0,MATCH('NTM Valuation'!$C3,'Income Statement'!1:1,0)+T8-1) -> 4Q27E | U12: =OFFSET('Income Statement'!$A1,0,MATCH('NTM Valuation'!$C3,'Income Statement'!1:1,0)+U8-1) -> 1Q28E | V12: =OFFSET('Income Statement'!$A1,0,MATCH('NTM Valuation'!$C3,'Income Statement'!1:1,0)+V8-1) -> 2Q28E | W12: =OFFSET('Income Statement'!$A1,0,MATCH('NTM Valuation'!$C3,'Income Statement'!1:1,0)+W8-1) -> 3Q28E | Y12: =OFFSET('Income Statement'!$A1,0,MATCH('NTM Valuation'!$C3,'Income Statement'!1:1,0)+Y8-1) -> 4Q28E | Z12: =OFFSET('Income Statement'!$A1,0,MATCH('NTM Valuation'!$C3,'Income Statement'!1:1,0)+Z8-1) -> 1Q29E | AA12: =OFFSET('Income Statement'!$A1,0,MATCH('NTM Valuation'!$C3,'Income Statement'!1:1,0)+AA8-1) -> 2Q29E | AB12: =OFFSET('Income Statement'!$A1,0,MATCH('NTM Valuation'!$C3,'Income Statement'!1:1,0)+AB8-1) -> 3Q29E | AD12: =OFFSET('Income Statement'!$A1,0,MATCH('NTM Valuation'!$C3,'Income Statement'!1:1,0)+AD8-1) -> 4Q29E | AE12: =OFFSET('Income Statement'!$A1,0,MATCH('NTM Valuation'!$C3,'Income Statement'!1:1,0)+AE8-1) -> 1Q30E | AF12: =OFFSET('Income Statement'!$A1,0,MATCH('NTM Valuation'!$C3,'Income Statement'!1:1,0)+AF8-1) -> 2Q30E | AG12: =OFFSET('Income Statement'!$A1,0,MATCH('NTM Valuation'!$C3,'Income Statement'!1:1,0)+AG8-1) -> 3Q30E
B14: Sales | C14: =+HLOOKUP(C$12,'Income Statement'!$A$1:CH85,ROW('Income Statement'!$A85),FALSE) -> 74549 | D14: =+HLOOKUP(D$12,'Income Statement'!$A$1:CH85,ROW('Income Statement'!$A85),FALSE) -> 81621 | E14: =+HLOOKUP(E$12,'Income Statement'!$A$1:CH85,ROW('Income Statement'!$A85),FALSE) -> 76486 | F14: =+HLOOKUP(F$12,'Income Statement'!$A$1:CH85,ROW('Income Statement'!$A85),FALSE) -> 81723 | H14: =+HLOOKUP(H$12,'Income Statement'!$A$1:CH85,ROW('Income Statement'!$A85),FALSE) -> 87470 | J14: =+HLOOKUP(J$12,'Income Statement'!$A$1:CH85,ROW('Income Statement'!$A85),FALSE) -> 95515.296 | K14: =+HLOOKUP(K$12,'Income Statement'!$A$1:CH85,ROW('Income Statement'!$A85),FALSE) -> 89042.104 | L14: =+HLOOKUP(L$12,'Income Statement'!$A$1:CH85,ROW('Income Statement'!$A85),FALSE) -> 94341.454 | M14: =+HLOOKUP(M$12,'Income Statement'!$A$1:CH85,ROW('Income Statement'!$A85),FALSE) -> 100285.27 | O14: =+HLOOKUP(O$12,'Income Statement'!$A$1:CH85,ROW('Income Statement'!$A85),FALSE) -> 108253.18 | P14: =+HLOOKUP(P$12,'Income Statement'!$A$1:CH85,ROW('Income Statement'!$A85),FALSE) -> 101958.57 | Q14: =+HLOOKUP(Q$12,'Income Statement'!$A$1:CH85,ROW('Income Statement'!$A85),FALSE) -> 107600.44 | R14: =+HLOOKUP(R$12,'Income Statement'!$A$1:CH85,ROW('Income Statement'!$A85),FALSE) -> 114525.07 | T14: =+HLOOKUP(T$12,'Income Statement'!$A$1:CH85,ROW('Income Statement'!$A85),FALSE) -> 123228.19 | U14: =+HLOOKUP(U$12,'Income Statement'!$A$1:CH85,ROW('Income Statement'!$A85),FALSE) -> 116051.45 | V14: =+HLOOKUP(V$12,'Income Statement'!$A$1:CH85,ROW('Income Statement'!$A85),FALSE) -> 122012.27 | W14: =+HLOOKUP(W$12,'Income Statement'!$A$1:CH85,ROW('Income Statement'!$A85),FALSE) -> 130037.9 | Y14: =+HLOOKUP(Y$12,'Income Statement'!$A$1:CH85,ROW('Income Statement'!$A85),FALSE) -> 139488.54 | Z14: =+HLOOKUP(Z$12,'Income Statement'!$A$1:CH85,ROW('Income Statement'!$A85),FALSE) -> 130920.79 | AA14: =+HLOOKUP(AA$12,'Income Statement'!$A$1:CH85,ROW('Income Statement'!$A85),FALSE) -> 137151.82 | AB14: =+HLOOKUP(AB$12,'Income Statement'!$A$1:CH85,ROW('Income Statement'!$A85),FALSE) -> 146353.52 | AD14: =+HLOOKUP(AD$12,'Income Statement'!$A$1:CH85,ROW('Income Statement'!$A85),FALSE) -> 156533.25 | AE14: =+HLOOKUP(AE$12,'Income Statement'!$A$1:CH85,ROW('Income Statement'!$A85),FALSE) -> 146375.81 | AF14: =+HLOOKUP(AF$12,'Income Statement'!$A$1:CH85,ROW('Income Statement'!$A85),FALSE) -> 152817.15 | AG14: =+HLOOKUP(AG$12,'Income Statement'!$A$1:CH85,ROW('Income Statement'!$A85),FALSE) -> 163252.15
B15: YoY Growth | M15: =+SUM(J14:M14)/SUM(C14:F14)-1 -> 0.20613693 | R15: =+SUM(O14:R14)/SUM(J14:M14)-1 -> 0.14017766 | W15: =+SUM(T14:W14)/SUM(O14:R14)-1 -> 0.13645031 | AB15: =+SUM(Y14:AB14)/SUM(T14:W14)-1 -> 0.12737851 | AG15: =+SUM(AD14:AG14)/SUM(Y14:AB14)-1 -> 0.11746157
B19: Gross Profit | C19: =+HLOOKUP(C$12,'Income Statement'!$A$1:CH172,ROW('Income Statement'!A172),FALSE) -> 51794 | D19: =+HLOOKUP(D$12,'Income Statement'!$A$1:CH172,ROW('Income Statement'!B172),FALSE) -> 55856 | E19: =+HLOOKUP(E$12,'Income Statement'!$A$1:CH172,ROW('Income Statement'!C172),FALSE) -> 53873 | F19: =+HLOOKUP(F$12,'Income Statement'!$A$1:CH172,ROW('Income Statement'!D172),FALSE) -> 57389 | H19: =+HLOOKUP(H$12,'Income Statement'!$A$1:CH172,ROW('Income Statement'!F172),FALSE) -> 60977 | J19: =+HLOOKUP(J$12,'Income Statement'!$A$1:CH172,ROW('Income Statement'!H172),FALSE) -> 64409.182 | K19: =+HLOOKUP(K$12,'Income Statement'!$A$1:CH172,ROW('Income Statement'!I172),FALSE) -> 61603.879 | L19: =+HLOOKUP(L$12,'Income Statement'!$A$1:CH172,ROW('Income Statement'!J172),FALSE) -> 65070.89 | M19: =+HLOOKUP(M$12,'Income Statement'!$A$1:CH172,ROW('Income Statement'!K172),FALSE) -> 68657.201 | O19: =+HLOOKUP(O$12,'Income Statement'!$A$1:CH172,ROW('Income Statement'!M172),FALSE) -> 71645.602 | P19: =+HLOOKUP(P$12,'Income Statement'!$A$1:CH172,ROW('Income Statement'!N172),FALSE) -> 69520.567 | Q19: =+HLOOKUP(Q$12,'Income Statement'!$A$1:CH172,ROW('Income Statement'!O172),FALSE) -> 73140.113 | R19: =+HLOOKUP(R$12,'Income Statement'!$A$1:CH172,ROW('Income Statement'!P172),FALSE) -> 77260.791 | T19: =+HLOOKUP(T$12,'Income Statement'!$A$1:CH172,ROW('Income Statement'!R172),FALSE) -> 80324.286 | U19: =+HLOOKUP(U$12,'Income Statement'!$A$1:CH172,ROW('Income Statement'!S172),FALSE) -> 78259.427 | V19: =+HLOOKUP(V$12,'Income Statement'!$A$1:CH172,ROW('Income Statement'!T172),FALSE) -> 82021.292 | W19: =+HLOOKUP(W$12,'Income Statement'!$A$1:CH172,ROW('Income Statement'!U172),FALSE) -> 86750.757 | Y19: =+HLOOKUP(Y$12,'Income Statement'!$A$1:CH172,ROW('Income Statement'!W172),FALSE) -> 89877.168 | Z19: =+HLOOKUP(Z$12,'Income Statement'!$A$1:CH172,ROW('Income Statement'!X172),FALSE) -> 87828.359 | AA19: =+HLOOKUP(AA$12,'Income Statement'!$A$1:CH172,ROW('Income Statement'!Y172),FALSE) -> 91718.639 | AB19: =+HLOOKUP(AB$12,'Income Statement'!$A$1:CH172,ROW('Income Statement'!Z172),FALSE) -> 97122.981 | AD19: =+HLOOKUP(AD$12,'Income Statement'!$A$1:CH172,ROW('Income Statement'!AB172),FALSE) -> 100311.78 | AE19: =+HLOOKUP(AE$12,'Income Statement'!$A$1:CH172,ROW('Income Statement'!AC172),FALSE) -> 97830.44 | AF19: =+HLOOKUP(AF$12,'Income Statement'!$A$1:CH172,ROW('Income Statement'!AD172),FALSE) -> 101812.6 | AG19: =+HLOOKUP(AG$12,'Income Statement'!$A$1:CH172,ROW('Income Statement'!AE172),FALSE) -> 107929.1
M20: =+SUM(J19:M19)/SUM(C19:F19)-1 -> 0.18650943 | R20: =+SUM(O19:R19)/SUM(J19:M19)-1 -> 0.12252937 | W20: =+SUM(T19:W19)/SUM(O19:R19)-1 -> 0.12274599 | AB20: =+SUM(Y19:AB19)/SUM(T19:W19)-1 -> 0.11972108 | AG20: =+SUM(AD19:AG19)/SUM(Y19:AB19)-1 -> 0.11277341
B25: GAAP EBITDA | C25: =+HLOOKUP(C$12,'Cash Flow Statement'!$A$1:CH61,ROW('Cash Flow Statement'!A61),FALSE) -> 32506 | D25: =+HLOOKUP(D$12,'Cash Flow Statement'!$A$1:CH61,ROW('Cash Flow Statement'!B61),FALSE) -> 35177 | E25: =+HLOOKUP(E$12,'Cash Flow Statement'!$A$1:CH61,ROW('Cash Flow Statement'!C61),FALSE) -> 35093 | F25: =+HLOOKUP(F$12,'Cash Flow Statement'!$A$1:CH61,ROW('Cash Flow Statement'!D61),FALSE) -> 36269 | H25: =+HLOOKUP(H$12,'Cash Flow Statement'!$A$1:CH61,ROW('Cash Flow Statement'!F61),FALSE) -> 36839 | J25: =+HLOOKUP(J$12,'Cash Flow Statement'!$A$1:CH61,ROW('Cash Flow Statement'!H61),FALSE) -> 45028.025 | K25: =+HLOOKUP(K$12,'Cash Flow Statement'!$A$1:CH61,ROW('Cash Flow Statement'!I61),FALSE) -> 42984.716 | L25: =+HLOOKUP(L$12,'Cash Flow Statement'!$A$1:CH61,ROW('Cash Flow Statement'!J61),FALSE) -> 46836.374 | M25: =+HLOOKUP(M$12,'Cash Flow Statement'!$A$1:CH61,ROW('Cash Flow Statement'!K61),FALSE) -> 48938.549 | O25: =+HLOOKUP(O$12,'Cash Flow Statement'!$A$1:CH61,ROW('Cash Flow Statement'!M61),FALSE) -> 52318.644 | P25: =+HLOOKUP(P$12,'Cash Flow Statement'!$A$1:CH61,ROW('Cash Flow Statement'!N61),FALSE) -> 51067.761 | Q25: =+HLOOKUP(Q$12,'Cash Flow Statement'!$A$1:CH61,ROW('Cash Flow Statement'!O61),FALSE) -> 55799.834 | R25: =+HLOOKUP(R$12,'Cash Flow Statement'!$A$1:CH61,ROW('Cash Flow Statement'!P61),FALSE) -> 58424.954 | T25: =+HLOOKUP(T$12,'Cash Flow Statement'!$A$1:CH61,ROW('Cash Flow Statement'!R61),FALSE) -> 62496.641 | U25: =+HLOOKUP(U$12,'Cash Flow Statement'!$A$1:CH61,ROW('Cash Flow Statement'!S61),FALSE) -> 60078.068 | V25: =+HLOOKUP(V$12,'Cash Flow Statement'!$A$1:CH61,ROW('Cash Flow Statement'!T61),FALSE) -> 65737.456 | W25: =+HLOOKUP(W$12,'Cash Flow Statement'!$A$1:CH61,ROW('Cash Flow Statement'!U61),FALSE) -> 68966.509 | Y25: =+HLOOKUP(Y$12,'Cash Flow Statement'!$A$1:CH61,ROW('Cash Flow Statement'!W61),FALSE) -> 73765.608 | Z25: =+HLOOKUP(Z$12,'Cash Flow Statement'!$A$1:CH61,ROW('Cash Flow Statement'!X61),FALSE) -> 69748.075 | AA25: =+HLOOKUP(AA$12,'Cash Flow Statement'!$A$1:CH61,ROW('Cash Flow Statement'!Y61),FALSE) -> 76346.799 | AB25: =+HLOOKUP(AB$12,'Cash Flow Statement'!$A$1:CH61,ROW('Cash Flow Statement'!Z61),FALSE) -> 80225.34 | AD25: =+HLOOKUP(AD$12,'Cash Flow Statement'!$A$1:CH61,ROW('Cash Flow Statement'!AB61),FALSE) -> 85769.417 | AE25: =+HLOOKUP(AE$12,'Cash Flow Statement'!$A$1:CH61,ROW('Cash Flow Statement'!AC61),FALSE) -> 79751.33 | AF25: =+HLOOKUP(AF$12,'Cash Flow Statement'!$A$1:CH61,ROW('Cash Flow Statement'!AD61),FALSE) -> 87468.176 | AG25: =+HLOOKUP(AG$12,'Cash Flow Statement'!$A$1:CH61,ROW('Cash Flow Statement'!AE61),FALSE) -> 91935.732
M26: =+SUM(J25:M25)/SUM(C25:F25)-1 -> 0.32178549 | R26: =+SUM(O25:R25)/SUM(J25:M25)-1 -> 0.18403591 | W26: =+SUM(T25:W25)/SUM(O25:R25)-1 -> 0.18228604 | AB26: =+SUM(Y25:AB25)/SUM(T25:W25)-1 -> 0.16638436 | AG26: =+SUM(AD25:AG25)/SUM(Y25:AB25)-1 -> 0.14942003
B31: GAAP EBIT | C31: =+HLOOKUP(C$12,'Income Statement'!$A$1:CH201,ROW('Income Statement'!A201),FALSE) -> 28521 | D31: =+HLOOKUP(D$12,'Income Statement'!$A$1:CH201,ROW('Income Statement'!B201),FALSE) -> 30972 | E31: =+HLOOKUP(E$12,'Income Statement'!$A$1:CH201,ROW('Income Statement'!C201),FALSE) -> 30606 | F31: =+HLOOKUP(F$12,'Income Statement'!$A$1:CH201,ROW('Income Statement'!D201),FALSE) -> 31271 | H31: =+HLOOKUP(H$12,'Income Statement'!$A$1:CH201,ROW('Income Statement'!F201),FALSE) -> 31228 | J31: =+HLOOKUP(J$12,'Income Statement'!$A$1:CH201,ROW('Income Statement'!H201),FALSE) -> 36700.002 | K31: =+HLOOKUP(K$12,'Income Statement'!$A$1:CH201,ROW('Income Statement'!I201),FALSE) -> 36202.689 | L31: =+HLOOKUP(L$12,'Income Statement'!$A$1:CH201,ROW('Income Statement'!J201),FALSE) -> 37984.285 | M31: =+HLOOKUP(M$12,'Income Statement'!$A$1:CH201,ROW('Income Statement'!K201),FALSE) -> 39492.141 | O31: =+HLOOKUP(O$12,'Income Statement'!$A$1:CH201,ROW('Income Statement'!M201),FALSE) -> 41058.517 | P31: =+HLOOKUP(P$12,'Income Statement'!$A$1:CH201,ROW('Income Statement'!N201),FALSE) -> 41633.728 | Q31: =+HLOOKUP(Q$12,'Income Statement'!$A$1:CH201,ROW('Income Statement'!O201),FALSE) -> 43486.274 | R31: =+HLOOKUP(R$12,'Income Statement'!$A$1:CH201,ROW('Income Statement'!P201),FALSE) -> 45284.676 | T31: =+HLOOKUP(T$12,'Income Statement'!$A$1:CH201,ROW('Income Statement'!R201),FALSE) -> 46833.416 | U31: =+HLOOKUP(U$12,'Income Statement'!$A$1:CH201,ROW('Income Statement'!S201),FALSE) -> 47812.363 | V31: =+HLOOKUP(V$12,'Income Statement'!$A$1:CH201,ROW('Income Statement'!T201),FALSE) -> 49727.919 | W31: =+HLOOKUP(W$12,'Income Statement'!$A$1:CH201,ROW('Income Statement'!U201),FALSE) -> 51882.109 | Y31: =+HLOOKUP(Y$12,'Income Statement'!$A$1:CH201,ROW('Income Statement'!W201),FALSE) -> 53400.986 | Z31: =+HLOOKUP(Z$12,'Income Statement'!$A$1:CH201,ROW('Income Statement'!X201),FALSE) -> 54566.396 | AA31: =+HLOOKUP(AA$12,'Income Statement'!$A$1:CH201,ROW('Income Statement'!Y201),FALSE) -> 56531.251 | AB31: =+HLOOKUP(AB$12,'Income Statement'!$A$1:CH201,ROW('Income Statement'!Z201),FALSE) -> 59079.398 | AD31: =+HLOOKUP(AD$12,'Income Statement'!$A$1:CH201,ROW('Income Statement'!AB201),FALSE) -> 60563.433 | AE31: =+HLOOKUP(AE$12,'Income Statement'!$A$1:CH201,ROW('Income Statement'!AC201),FALSE) -> 61856.902 | AF31: =+HLOOKUP(AF$12,'Income Statement'!$A$1:CH201,ROW('Income Statement'!AD201),FALSE) -> 64111.874 | AG31: =+HLOOKUP(AG$12,'Income Statement'!$A$1:CH201,ROW('Income Statement'!AE201),FALSE) -> 67011.313
M32: =+SUM(J31:M31)/SUM(C31:F31)-1 -> 0.23901391 | R32: =+SUM(O31:R31)/SUM(J31:M31)-1 -> 0.14020615 | W32: =+SUM(T31:W31)/SUM(O31:R31)-1 -> 0.14459437 | AB32: =+SUM(Y31:AB31)/SUM(T31:W31)-1 -> 0.1392174 | AG32: =+SUM(AD31:AG31)/SUM(Y31:AB31)-1 -> 0.13402699
B37: GAAP Net Income | C37: =+HLOOKUP(C$12,'Income Statement'!$A$1:CH267,ROW('Income Statement'!A267),FALSE) -> 26301 | D37: =+HLOOKUP(D$12,'Income Statement'!$A$1:CH267,ROW('Income Statement'!B267),FALSE) -> 26536 | E37: =+HLOOKUP(E$12,'Income Statement'!$A$1:CH267,ROW('Income Statement'!C267),FALSE) -> 34540 | F37: =+HLOOKUP(F$12,'Income Statement'!$A$1:CH267,ROW('Income Statement'!D267),FALSE) -> 28196 | H37: =+HLOOKUP(H$12,'Income Statement'!$A$1:CH267,ROW('Income Statement'!F267),FALSE) -> 34979 | J37: =+HLOOKUP(J$12,'Income Statement'!$A$1:CH267,ROW('Income Statement'!H267),FALSE) -> 30455.63 | K37: =+HLOOKUP(K$12,'Income Statement'!$A$1:CH267,ROW('Income Statement'!I267),FALSE) -> 30344.4 | L37: =+HLOOKUP(L$12,'Income Statement'!$A$1:CH267,ROW('Income Statement'!J267),FALSE) -> 31973.72 | M37: =+HLOOKUP(M$12,'Income Statement'!$A$1:CH267,ROW('Income Statement'!K267),FALSE) -> 32972.664 | O37: =+HLOOKUP(O$12,'Income Statement'!$A$1:CH267,ROW('Income Statement'!M267),FALSE) -> 34324.048 | P37: =+HLOOKUP(P$12,'Income Statement'!$A$1:CH267,ROW('Income Statement'!N267),FALSE) -> 34881.653 | Q37: =+HLOOKUP(Q$12,'Income Statement'!$A$1:CH267,ROW('Income Statement'!O267),FALSE) -> 36655.353 | R37: =+HLOOKUP(R$12,'Income Statement'!$A$1:CH267,ROW('Income Statement'!P267),FALSE) -> 37907.141 | T37: =+HLOOKUP(T$12,'Income Statement'!$A$1:CH267,ROW('Income Statement'!R267),FALSE) -> 39366.167 | U37: =+HLOOKUP(U$12,'Income Statement'!$A$1:CH267,ROW('Income Statement'!S267),FALSE) -> 40414.951 | V37: =+HLOOKUP(V$12,'Income Statement'!$A$1:CH267,ROW('Income Statement'!T267),FALSE) -> 42461.103 | W37: =+HLOOKUP(W$12,'Income Statement'!$A$1:CH267,ROW('Income Statement'!U267),FALSE) -> 43859.983 | Y37: =+HLOOKUP(Y$12,'Income Statement'!$A$1:CH267,ROW('Income Statement'!W267),FALSE) -> 45334.642 | Z37: =+HLOOKUP(Z$12,'Income Statement'!$A$1:CH267,ROW('Income Statement'!X267),FALSE) -> 46647.092 | AA37: =+HLOOKUP(AA$12,'Income Statement'!$A$1:CH267,ROW('Income Statement'!Y267),FALSE) -> 48864.026 | AB37: =+HLOOKUP(AB$12,'Income Statement'!$A$1:CH267,ROW('Income Statement'!Z267),FALSE) -> 50404.456 | AD37: =+HLOOKUP(AD$12,'Income Statement'!$A$1:CH267,ROW('Income Statement'!AB267),FALSE) -> 51889.34 | AE37: =+HLOOKUP(AE$12,'Income Statement'!$A$1:CH267,ROW('Income Statement'!AC267),FALSE) -> 53444.951 | AF37: =+HLOOKUP(AF$12,'Income Statement'!$A$1:CH267,ROW('Income Statement'!AD267),FALSE) -> 56052.313 | AG37: =+HLOOKUP(AG$12,'Income Statement'!$A$1:CH267,ROW('Income Statement'!AE267),FALSE) -> 57647.266
M38: =+SUM(J37:M37)/SUM(C37:F37)-1 -> 0.088025871 | R38: =+SUM(O37:R37)/SUM(J37:M37)-1 -> 0.14331845 | W38: =+SUM(T37:W37)/SUM(O37:R37)-1 -> 0.15534736 | AB38: =+SUM(Y37:AB37)/SUM(T37:W37)-1 -> 0.15140083 | AG38: =+SUM(AD37:AG37)/SUM(Y37:AB37)-1 -> 0.14527384
B44: FCF minus SBC | C44: =+HLOOKUP(C$12,'Cash Flow Statement'!$A$1:CH83,ROW('Cash Flow Statement'!A83),FALSE) -> 11791 | D44: =+HLOOKUP(D$12,'Cash Flow Statement'!$A$1:CH83,ROW('Cash Flow Statement'!B83),FALSE) -> 19027 | E44: =+HLOOKUP(E$12,'Cash Flow Statement'!$A$1:CH83,ROW('Cash Flow Statement'!C83),FALSE) -> 13437 | F44: =+HLOOKUP(F$12,'Cash Flow Statement'!$A$1:CH83,ROW('Cash Flow Statement'!D83),FALSE) -> -697 | H44: =+HLOOKUP(H$12,'Cash Flow Statement'!$A$1:CH83,ROW('Cash Flow Statement'!F83),FALSE) -> 18093 | J44: =+HLOOKUP(J$12,'Cash Flow Statement'!$A$1:CH83,ROW('Cash Flow Statement'!H83),FALSE) -> -6849.4117 | K44: =+HLOOKUP(K$12,'Cash Flow Statement'!$A$1:CH83,ROW('Cash Flow Statement'!I83),FALSE) -> 27365.95 | L44: =+HLOOKUP(L$12,'Cash Flow Statement'!$A$1:CH83,ROW('Cash Flow Statement'!J83),FALSE) -> -9027.0837 | M44: =+HLOOKUP(M$12,'Cash Flow Statement'!$A$1:CH83,ROW('Cash Flow Statement'!K83),FALSE) -> 17865.854 | O44: =+HLOOKUP(O$12,'Cash Flow Statement'!$A$1:CH83,ROW('Cash Flow Statement'!M83),FALSE) -> 9981.6768 | P44: =+HLOOKUP(P$12,'Cash Flow Statement'!$A$1:CH83,ROW('Cash Flow Statement'!N83),FALSE) -> 32972.932 | Q44: =+HLOOKUP(Q$12,'Cash Flow Statement'!$A$1:CH83,ROW('Cash Flow Statement'!O83),FALSE) -> -10479.705 | R44: =+HLOOKUP(R$12,'Cash Flow Statement'!$A$1:CH83,ROW('Cash Flow Statement'!P83),FALSE) -> 22899.765 | T44: =+HLOOKUP(T$12,'Cash Flow Statement'!$A$1:CH83,ROW('Cash Flow Statement'!R83),FALSE) -> 12438.863 | U44: =+HLOOKUP(U$12,'Cash Flow Statement'!$A$1:CH83,ROW('Cash Flow Statement'!S83),FALSE) -> 45575.293 | V44: =+HLOOKUP(V$12,'Cash Flow Statement'!$A$1:CH83,ROW('Cash Flow Statement'!T83),FALSE) -> -9912.891 | W44: =+HLOOKUP(W$12,'Cash Flow Statement'!$A$1:CH83,ROW('Cash Flow Statement'!U83),FALSE) -> 30500.968 | Y44: =+HLOOKUP(Y$12,'Cash Flow Statement'!$A$1:CH83,ROW('Cash Flow Statement'!W83),FALSE) -> 17418.065 | Z44: =+HLOOKUP(Z$12,'Cash Flow Statement'!$A$1:CH83,ROW('Cash Flow Statement'!X83),FALSE) -> 59142.709 | AA44: =+HLOOKUP(AA$12,'Cash Flow Statement'!$A$1:CH83,ROW('Cash Flow Statement'!Y83),FALSE) -> -8329.3167 | AB44: =+HLOOKUP(AB$12,'Cash Flow Statement'!$A$1:CH83,ROW('Cash Flow Statement'!Z83),FALSE) -> 39355.065 | AD44: =+HLOOKUP(AD$12,'Cash Flow Statement'!$A$1:CH83,ROW('Cash Flow Statement'!AB83),FALSE) -> 23771.737 | AE44: =+HLOOKUP(AE$12,'Cash Flow Statement'!$A$1:CH83,ROW('Cash Flow Statement'!AC83),FALSE) -> 75310.556 | AF44: =+HLOOKUP(AF$12,'Cash Flow Statement'!$A$1:CH83,ROW('Cash Flow Statement'!AD83),FALSE) -> -5608.1709 | AG44: =+HLOOKUP(AG$12,'Cash Flow Statement'!$A$1:CH83,ROW('Cash Flow Statement'!AE83),FALSE) -> 49552.895
M45: =+SUM(J44:M44)/SUM(C44:F44)-1 -> -0.32606391 | R45: =+SUM(O44:R44)/SUM(J44:M44)-1 -> 0.88635962 | W45: =+SUM(T44:W44)/SUM(O44:R44)-1 -> 0.41946193 | AB45: =+SUM(Y44:AB44)/SUM(T44:W44)-1 -> 0.36874639 | AG45: =+SUM(AD44:AG44)/SUM(Y44:AB44)-1 -> 0.32941388
B50: FCF | C50: =+HLOOKUP(C$12,'Cash Flow Statement'!$A$1:CH76,ROW('Cash Flow Statement'!A76),FALSE) -> 17637 | D50: =+HLOOKUP(D$12,'Cash Flow Statement'!$A$1:CH76,ROW('Cash Flow Statement'!B76),FALSE) -> 24837 | E50: =+HLOOKUP(E$12,'Cash Flow Statement'!$A$1:CH76,ROW('Cash Flow Statement'!C76),FALSE) -> 18953 | F50: =+HLOOKUP(F$12,'Cash Flow Statement'!$A$1:CH76,ROW('Cash Flow Statement'!D76),FALSE) -> 5301 | H50: =+HLOOKUP(H$12,'Cash Flow Statement'!$A$1:CH76,ROW('Cash Flow Statement'!F76),FALSE) -> 24461 | J50: =+HLOOKUP(J$12,'Cash Flow Statement'!$A$1:CH76,ROW('Cash Flow Statement'!H76),FALSE) -> -458.41165 | K50: =+HLOOKUP(K$12,'Cash Flow Statement'!$A$1:CH76,ROW('Cash Flow Statement'!I76),FALSE) -> 33378.39 | L50: =+HLOOKUP(L$12,'Cash Flow Statement'!$A$1:CH76,ROW('Cash Flow Statement'!J76),FALSE) -> -2489.2637 | M50: =+HLOOKUP(M$12,'Cash Flow Statement'!$A$1:CH76,ROW('Cash Flow Statement'!K76),FALSE) -> 24806.974 | O50: =+HLOOKUP(O$12,'Cash Flow Statement'!$A$1:CH76,ROW('Cash Flow Statement'!M76),FALSE) -> 16947.867 | P50: =+HLOOKUP(P$12,'Cash Flow Statement'!$A$1:CH76,ROW('Cash Flow Statement'!N76),FALSE) -> 39466.367 | Q50: =+HLOOKUP(Q$12,'Cash Flow Statement'!$A$1:CH76,ROW('Cash Flow Statement'!O76),FALSE) -> -3418.8594 | R50: =+HLOOKUP(R$12,'Cash Flow Statement'!$A$1:CH76,ROW('Cash Flow Statement'!P76),FALSE) -> 30396.174 | T50: =+HLOOKUP(T$12,'Cash Flow Statement'!$A$1:CH76,ROW('Cash Flow Statement'!R76),FALSE) -> 19962.348 | U50: =+HLOOKUP(U$12,'Cash Flow Statement'!$A$1:CH76,ROW('Cash Flow Statement'!S76),FALSE) -> 52588.203 | V50: =+HLOOKUP(V$12,'Cash Flow Statement'!$A$1:CH76,ROW('Cash Flow Statement'!T76),FALSE) -> -2428.3946 | W50: =+HLOOKUP(W$12,'Cash Flow Statement'!$A$1:CH76,ROW('Cash Flow Statement'!U76),FALSE) -> 38447.162 | Y50: =+HLOOKUP(Y$12,'Cash Flow Statement'!$A$1:CH76,ROW('Cash Flow Statement'!W76),FALSE) -> 25392.96 | Z50: =+HLOOKUP(Z$12,'Cash Flow Statement'!$A$1:CH76,ROW('Cash Flow Statement'!X76),FALSE) -> 66576.394 | AA50: =+HLOOKUP(AA$12,'Cash Flow Statement'!$A$1:CH76,ROW('Cash Flow Statement'!Y76),FALSE) -> -470.59559 | AB50: =+HLOOKUP(AB$12,'Cash Flow Statement'!$A$1:CH76,ROW('Cash Flow Statement'!Z76),FALSE) -> 47698.569 | AD50: =+HLOOKUP(AD$12,'Cash Flow Statement'!$A$1:CH76,ROW('Cash Flow Statement'!AB76),FALSE) -> 32145.376 | AE50: =+HLOOKUP(AE$12,'Cash Flow Statement'!$A$1:CH76,ROW('Cash Flow Statement'!AC76),FALSE) -> 83115.925 | AF50: =+HLOOKUP(AF$12,'Cash Flow Statement'!$A$1:CH76,ROW('Cash Flow Statement'!AD76),FALSE) -> 2643.4863 | AG50: =+HLOOKUP(AG$12,'Cash Flow Statement'!$A$1:CH76,ROW('Cash Flow Statement'!AE76),FALSE) -> 58313.574
M51: =+SUM(J50:M50)/SUM(C50:F50)-1 -> -0.17219626 | R51: =+SUM(O50:R50)/SUM(J50:M50)-1 -> 0.50968571 | W51: =+SUM(T50:W50)/SUM(O50:R50)-1 -> 0.30192233 | AB51: =+SUM(Y50:AB50)/SUM(T50:W50)-1 -> 0.28210556 | AG51: =+SUM(AD50:AG50)/SUM(Y50:AB50)-1 -> 0.26596081
B56: SBC | C56: =+HLOOKUP(C$12,'Income Statement'!$A$1:CH228,ROW('Income Statement'!A228),FALSE)*-1 -> 5846 | D56: =+HLOOKUP(D$12,'Income Statement'!$A$1:CH228,ROW('Income Statement'!B228),FALSE)*-1 -> 5810 | E56: =+HLOOKUP(E$12,'Income Statement'!$A$1:CH228,ROW('Income Statement'!C228),FALSE)*-1 -> 5516 | F56: =+HLOOKUP(F$12,'Income Statement'!$A$1:CH228,ROW('Income Statement'!D228),FALSE)*-1 -> 5998 | H56: =+HLOOKUP(H$12,'Income Statement'!$A$1:CH228,ROW('Income Statement'!F228),FALSE)*-1 -> 6368 | J56: =+HLOOKUP(J$12,'Income Statement'!$A$1:CH228,ROW('Income Statement'!H228),FALSE)*-1 -> 6391 | K56: =+HLOOKUP(K$12,'Income Statement'!$A$1:CH228,ROW('Income Statement'!I228),FALSE)*-1 -> 6012.44 | L56: =+HLOOKUP(L$12,'Income Statement'!$A$1:CH228,ROW('Income Statement'!J228),FALSE)*-1 -> 6537.82 | M56: =+HLOOKUP(M$12,'Income Statement'!$A$1:CH228,ROW('Income Statement'!K228),FALSE)*-1 -> 6941.12 | O56: =+HLOOKUP(O$12,'Income Statement'!$A$1:CH228,ROW('Income Statement'!M228),FALSE)*-1 -> 6966.19 | P56: =+HLOOKUP(P$12,'Income Statement'!$A$1:CH228,ROW('Income Statement'!N228),FALSE)*-1 -> 6493.4352 | Q56: =+HLOOKUP(Q$12,'Income Statement'!$A$1:CH228,ROW('Income Statement'!O228),FALSE)*-1 -> 7060.8456 | R56: =+HLOOKUP(R$12,'Income Statement'!$A$1:CH228,ROW('Income Statement'!P228),FALSE)*-1 -> 7496.4096 | T56: =+HLOOKUP(T$12,'Income Statement'!$A$1:CH228,ROW('Income Statement'!R228),FALSE)*-1 -> 7523.4852 | U56: =+HLOOKUP(U$12,'Income Statement'!$A$1:CH228,ROW('Income Statement'!S228),FALSE)*-1 -> 7012.91 | V56: =+HLOOKUP(V$12,'Income Statement'!$A$1:CH228,ROW('Income Statement'!T228),FALSE)*-1 -> 7484.4963 | W56: =+HLOOKUP(W$12,'Income Statement'!$A$1:CH228,ROW('Income Statement'!U228),FALSE)*-1 -> 7946.1942 | Y56: =+HLOOKUP(Y$12,'Income Statement'!$A$1:CH228,ROW('Income Statement'!W228),FALSE)*-1 -> 7974.8943 | Z56: =+HLOOKUP(Z$12,'Income Statement'!$A$1:CH228,ROW('Income Statement'!X228),FALSE)*-1 -> 7433.6846 | AA56: =+HLOOKUP(AA$12,'Income Statement'!$A$1:CH228,ROW('Income Statement'!Y228),FALSE)*-1 -> 7858.7212 | AB56: =+HLOOKUP(AB$12,'Income Statement'!$A$1:CH228,ROW('Income Statement'!Z228),FALSE)*-1 -> 8343.5039 | AD56: =+HLOOKUP(AD$12,'Income Statement'!$A$1:CH228,ROW('Income Statement'!AB228),FALSE)*-1 -> 8373.639 | AE56: =+HLOOKUP(AE$12,'Income Statement'!$A$1:CH228,ROW('Income Statement'!AC228),FALSE)*-1 -> 7805.3688 | AF56: =+HLOOKUP(AF$12,'Income Statement'!$A$1:CH228,ROW('Income Statement'!AD228),FALSE)*-1 -> 8251.6572 | AG56: =+HLOOKUP(AG$12,'Income Statement'!$A$1:CH228,ROW('Income Statement'!AE228),FALSE)*-1 -> 8760.6791
M57: =+SUM(J56:M56)/SUM(C56:F56)-1 -> 0.11706431 | R57: =+SUM(O56:R56)/SUM(J56:M56)-1 -> 0.082469247 | W57: =+SUM(T56:W56)/SUM(O56:R56)-1 -> 0.069608225 | AB57: =+SUM(Y56:AB56)/SUM(T56:W56)-1 -> 0.054850787 | AG57: =+SUM(AD56:AG56)/SUM(Y56:AB56)-1 -> 0.05
B61: Dividends | C61: =+HLOOKUP(C$12,'Cash Flow Statement'!$A$1:CH105,ROW('Cash Flow Statement'!A102),FALSE) -> 2455 | D61: =+HLOOKUP(D$12,'Cash Flow Statement'!$A$1:CI105,ROW('Cash Flow Statement'!B102),FALSE) -> 2442 | E61: =+HLOOKUP(E$12,'Cash Flow Statement'!$A$1:CJ105,ROW('Cash Flow Statement'!C102),FALSE) -> 2434 | F61: =+HLOOKUP(F$12,'Cash Flow Statement'!$A$1:CK105,ROW('Cash Flow Statement'!D102),FALSE) -> 2543 | H61: =+HLOOKUP(H$12,'Cash Flow Statement'!$A$1:CM105,ROW('Cash Flow Statement'!F102),FALSE) -> 2537 | J61: =+HLOOKUP(J$12,'Cash Flow Statement'!$A$1:CO105,ROW('Cash Flow Statement'!H102),FALSE) -> 2531.479 | K61: =+HLOOKUP(K$12,'Cash Flow Statement'!$A$1:CP105,ROW('Cash Flow Statement'!I102),FALSE) -> 2525.3241 | L61: =+HLOOKUP(L$12,'Cash Flow Statement'!$A$1:CQ105,ROW('Cash Flow Statement'!J102),FALSE) -> 2519.3394 | M61: =+HLOOKUP(M$12,'Cash Flow Statement'!$A$1:CR105,ROW('Cash Flow Statement'!K102),FALSE) -> 2513.8942 | O61: =+HLOOKUP(O$12,'Cash Flow Statement'!$A$1:CT105,ROW('Cash Flow Statement'!M102),FALSE) -> 2508.7409 | P61: =+HLOOKUP(P$12,'Cash Flow Statement'!$A$1:CU105,ROW('Cash Flow Statement'!N102),FALSE) -> 2503.5639 | Q61: =+HLOOKUP(Q$12,'Cash Flow Statement'!$A$1:CV105,ROW('Cash Flow Statement'!O102),FALSE) -> 2504.0801 | R61: =+HLOOKUP(R$12,'Cash Flow Statement'!$A$1:CW105,ROW('Cash Flow Statement'!P102),FALSE) -> 2510.5066 | T61: =+HLOOKUP(T$12,'Cash Flow Statement'!$A$1:CY105,ROW('Cash Flow Statement'!R102),FALSE) -> 2517.0276 | U61: =+HLOOKUP(U$12,'Cash Flow Statement'!$A$1:CZ105,ROW('Cash Flow Statement'!S102),FALSE) -> 2523.2349 | V61: =+HLOOKUP(V$12,'Cash Flow Statement'!$A$1:DA105,ROW('Cash Flow Statement'!T102),FALSE) -> 2529.3181 | W61: =+HLOOKUP(W$12,'Cash Flow Statement'!$A$1:DB105,ROW('Cash Flow Statement'!U102),FALSE) -> 2535.6845 | Y61: =+HLOOKUP(Y$12,'Cash Flow Statement'!$A$1:DE105,ROW('Cash Flow Statement'!W102),FALSE) -> 2542.1446 | Z61: =+HLOOKUP(Z$12,'Cash Flow Statement'!$A$1:DF105,ROW('Cash Flow Statement'!X102),FALSE) -> 2548.2938 | AA61: =+HLOOKUP(AA$12,'Cash Flow Statement'!$A$1:DG105,ROW('Cash Flow Statement'!Y102),FALSE) -> 2554.2911 | AB61: =+HLOOKUP(AB$12,'Cash Flow Statement'!$A$1:DH105,ROW('Cash Flow Statement'!Z102),FALSE) -> 2560.5386 | AD61: =+HLOOKUP(AD$12,'Cash Flow Statement'!$A$1:DJ105,ROW('Cash Flow Statement'!AB102),FALSE) -> 2566.8779 | AE61: =+HLOOKUP(AE$12,'Cash Flow Statement'!$A$1:DK105,ROW('Cash Flow Statement'!AC102),FALSE) -> 2572.9122 | AF61: =+HLOOKUP(AF$12,'Cash Flow Statement'!$A$1:DL105,ROW('Cash Flow Statement'!AD102),FALSE) -> 2578.7974 | AG61: =+HLOOKUP(AG$12,'Cash Flow Statement'!$A$1:DM105,ROW('Cash Flow Statement'!AE102),FALSE) -> 2584.928
R62: =+SUM(O61:R61)/SUM(J61:M61)-1 -> -0.0062581799 | W62: =+SUM(T61:W61)/SUM(O61:R61)-1 -> 0.0078163476 | AB62: =+SUM(Y61:AB61)/SUM(T61:W61)-1 -> 0.0098961329 | AG62: =+SUM(AD61:AG61)/SUM(Y61:AB61)-1 -> 0.0096271186

Sheet Valuation
A2: Ticker | B2: GOOGL
A3: Stock Price | B3: 293
A4: Diluted Shares (mm) | B4: =HLOOKUP('NTM Valuation'!$C$3,'Shares Outstanding & Corporate'!A1:CH9,ROW('Shares Outstanding & Corporate'!A9),FALSE) -> 12203
A5: Market Cap (mm) | B5: =B3*B4 -> 3575479
A6: Net Debt (Cash) | B6: =HLOOKUP('NTM Valuation'!C3,'Balance Sheet'!A1:CH51,ROW('Balance Sheet'!A51),FALSE) -> -76889
A7: Enterprise Value (mm) | B7: =B5+B6 -> 3498590
B9: ='Income Statement'!CU1 -> 2022 | C9: ='Income Statement'!CV1 -> 2023 | D9: ='Income Statement'!CW1 -> 2024 | E9: ='Income Statement'!CX1 -> 2025E | F9: ='Income Statement'!CY1 -> 2026E | G9: ='Income Statement'!CZ1 -> 2027E | H9: ='Income Statement'!DA1 -> 2028E | I9: ='Income Statement'!DB1 -> 2029E | J9: ='Income Statement'!DC1 -> 2030E
A10: Sales | B10: ='Income Statement'!CU85 -> 233881 | C10: ='Income Statement'!CV85 -> 256508 | D10: ='Income Statement'!CW85 -> 295118 | E10: ='Income Statement'!CX85 -> 341194.3 | F10: ='Income Statement'!CY85 -> 391922.01 | G10: ='Income Statement'!CZ85 -> 447312.27 | H10: ='Income Statement'!DA85 -> 507590.17 | I10: ='Income Statement'!DB85 -> 570959.38 | J10: ='Income Statement'!DC85 -> 636580.16
A11: YoY Growth | B11: ='Income Statement'!CU87 -> 0.10284292 | C11: ='Income Statement'!CV87 -> 0.096745781 | D11: ='Income Statement'!CW87 -> 0.15052162 | E11: ='Income Statement'!CX87 -> 0.15612838 | F11: ='Income Statement'!CY87 -> 0.1486769 | G11: ='Income Statement'!CZ87 -> 0.14132982 | H11: ='Income Statement'!DA87 -> 0.13475574 | I11: ='Income Statement'!DB87 -> 0.12484327 | J11: ='Income Statement'!DC87 -> 0.11493072
A12: EV/Sales | B12: =$B$7/B10 -> 14.958847 | C12: =$B$7/C10 -> 13.639302 | D12: =$B$7/D10 -> 11.854885 | E12: =$B$7/E10 -> 10.253952 | F12: =$B$7/F10 -> 8.9267506 | G12: =$B$7/G10 -> 7.8213593 | H12: =$B$7/H10 -> 6.8925488 | I12: =$B$7/I10 -> 6.1275637 | J12: =$B$7/J10 -> 5.4959143
A13: EV/Sales to Growth | B13: =B12/(B11*100) -> 1.4545335 | C13: =C12/(C11*100) -> 1.4098084 | D13: =D12/(D11*100) -> 0.78758686 | E13: =E12/(E11*100) -> 0.65676414 | F13: =F12/(F11*100) -> 0.60041274 | G13: =G12/(G11*100) -> 0.5534118 | H13: =H12/(H11*100) -> 0.51148463 | I13: =I12/(I11*100) -> 0.49082052 | J13: =J12/(J11*100) -> 0.47819368
A15: GAAP EBITDA | B15: ='Cash Flow Statement'!CU61 -> 90770 | C15: ='Cash Flow Statement'!CV61 -> 97992 | D15: ='Cash Flow Statement'!CW61 -> 127701 | E15: ='Cash Flow Statement'!CX61 -> 153229.02 | F15: ='Cash Flow Statement'!CY61 -> 191078.28 | G15: ='Cash Flow Statement'!CZ61 -> 227789.19 | H15: ='Cash Flow Statement'!DA61 -> 268547.64 | I15: ='Cash Flow Statement'!DB61 -> 312089.63 | J15: ='Cash Flow Statement'!DC61 -> 357307.46
A16: GAAP EBITDA Margin | B16: ='Cash Flow Statement'!CU62 -> 0.38810335 | C16: ='Cash Flow Statement'!CV62 -> 0.38202317 | D16: ='Cash Flow Statement'!CW62 -> 0.43271166 | E16: ='Cash Flow Statement'!CX62 -> 0.44909609 | F16: ='Cash Flow Statement'!CY62 -> 0.4875416 | G16: ='Cash Flow Statement'!CZ62 -> 0.50923975 | H16: ='Cash Flow Statement'!DA62 -> 0.52906391 | I16: ='Cash Flow Statement'!DB62 -> 0.54660566 | J16: ='Cash Flow Statement'!DC62 -> 0.56129217
A17: YoY Growth | B17: ='Cash Flow Statement'!CU64 -> -0.0042235752 | C17: ='Cash Flow Statement'!CV64 -> 0.079563733 | D17: ='Cash Flow Statement'!CW64 -> 0.30317781 | E17: ='Cash Flow Statement'!CX64 -> 0.19990466 | F17: ='Cash Flow Statement'!CY64 -> 0.24701102 | G17: ='Cash Flow Statement'!CZ64 -> 0.19212496 | H17: ='Cash Flow Statement'!DA64 -> 0.17893058 | I17: ='Cash Flow Statement'!DB64 -> 0.16213879 | J17: ='Cash Flow Statement'!DC64 -> 0.14488731
A18: EV/GAAP EBITDA | B18: =$B$7/B15 -> 38.543461 | C18: =$B$7/C15 -> 35.702812 | D18: =$B$7/D15 -> 27.396731 | E18: =$B$7/E15 -> 22.832424 | F18: =$B$7/F15 -> 18.309721 | G18: =$B$7/G15 -> 15.358894 | H18: =$B$7/H15 -> 13.027819 | I18: =$B$7/I15 -> 11.210209 | J18: =$B$7/J15 -> 9.7915392
A19: EV/GAAP EBITDA to Growth | B19: =B18/(B17*100) -> -91.257902 | C19: =C18/(C17*100) -> 4.4873225 | D19: =D18/(D17*100) -> 0.90365226 | E19: =E18/(E17*100) -> 1.1421657 | F19: =F18/(F17*100) -> 0.74125117 | G19: =G18/(G17*100) -> 0.7994221 | H19: =H18/(H17*100) -> 0.72809348 | I19: =I18/(I17*100) -> 0.69139585 | J19: =J18/(J17*100) -> 0.67580378
A21: GAAP Net Income | B21: ='Income Statement'!CU267 -> 59972 | C21: ='Income Statement'!CV267 -> 73795 | D21: ='Income Statement'!CW267 -> 100118 | E21: ='Income Statement'!CX267 -> 128170.63 | F21: ='Income Statement'!CY267 -> 129614.83 | G21: ='Income Statement'!CZ267 -> 148810.31 | H21: ='Income Statement'!DA267 -> 172070.68 | I21: ='Income Statement'!DB267 -> 197804.91 | J21: ='Income Statement'!DC267 -> 226271.18
A22: GAAP Net Income Margin | B22: ='Income Statement'!CU268 -> 0.256421 | C22: ='Income Statement'!CV268 -> 0.28769083 | D22: ='Income Statement'!CW268 -> 0.33924735 | E22: ='Income Statement'!CX268 -> 0.37565291 | F22: ='Income Statement'!CY268 -> 0.33071588 | G22: ='Income Statement'!CZ268 -> 0.33267657 | H22: ='Income Statement'!DA268 -> 0.3389953 | I22: ='Income Statement'!DB268 -> 0.34644306 | J22: ='Income Statement'!DC268 -> 0.35544805
A23: GAAP EPS | B23: ='Income Statement'!CU278 -> 4.5576606 | C23: ='Income Statement'!CV278 -> 5.8009237 | D23: ='Income Statement'!CW278 -> 8.0433831 | E23: ='Income Statement'!CX278 -> 10.492102 | F23: ='Income Statement'!CY278 -> 10.710306 | G23: ='Income Statement'!CZ278 -> 12.33544 | H23: ='Income Statement'!DA278 -> 14.129291 | I23: ='Income Statement'!DB278 -> 16.085922 | J23: ='Income Statement'!DC278 -> 18.228431
A24: YoY Growth | B24: ='Income Statement'!CU280 -> -0.18756146 | C24: ='Income Statement'!CV280 -> 0.27278535 | D24: ='Income Statement'!CW280 -> 0.38656937 | E24: ='Income Statement'!CX280 -> 0.30443892 | F24: ='Income Statement'!CY280 -> 0.020796993 | G24: ='Income Statement'!CZ280 -> 0.15173551 | H24: ='Income Statement'!DA280 -> 0.14542256 | I24: ='Income Statement'!DB280 -> 0.13848048 | J24: ='Income Statement'!DC280 -> 0.13319158
A25: P/E (GAAP) | B25: =$B$3/B23 -> 64.287367 | C25: =$B$3/C23 -> 50.509198 | D25: =$B$3/D23 -> 36.427458 | E25: =$B$3/E23 -> 27.925768 | F25: =$B$3/F23 -> 27.356828 | G25: =$B$3/G23 -> 23.7527 | H25: =$B$3/H23 -> 20.737063 | I25: =$B$3/I23 -> 18.214685 | J25: =$B$3/J23 -> 16.073791
A26: PEG (GAAP) | B26: =B25/(B24*100) -> -3.427536 | C26: =C25/(C24*100) -> 1.8516096 | D26: =D25/(D24*100) -> 0.94232654 | E26: =E25/(E24*100) -> 0.9172864 | F26: =F25/(F24*100) -> 13.154223 | G26: =G25/(G24*100) -> 1.5654015 | H26: =H25/(H24*100) -> 1.4259867 | I26: =I25/(I24*100) -> 1.3153251 | J26: =J25/(J24*100) -> 1.2068174
A28: FCF minus SBC | B28: ='Cash Flow Statement'!CU83 -> 40648 | C28: ='Cash Flow Statement'!CV83 -> 47035 | D28: ='Cash Flow Statement'!CW83 -> 49979 | E28: ='Cash Flow Statement'!CX83 -> 23983.588 | F28: ='Cash Flow Statement'!CY83 -> 46186.397 | G28: ='Cash Flow Statement'!CZ83 -> 57831.854 | H28: ='Cash Flow Statement'!DA83 -> 83581.436 | I28: ='Cash Flow Statement'!DB83 -> 113940.19 | J28: ='Cash Flow Statement'!DC83 -> 150768.66
A29: (FCF-SBC) Margin % | B29: ='Cash Flow Statement'!CU84 -> 0.17379779 | C29: ='Cash Flow Statement'!CV84 -> 0.1833666 | D29: ='Cash Flow Statement'!CW84 -> 0.1693526 | E29: ='Cash Flow Statement'!CX84 -> 0.070293052 | F29: ='Cash Flow Statement'!CY84 -> 0.11784589 | G29: ='Cash Flow Statement'!CZ84 -> 0.12928743 | H29: ='Cash Flow Statement'!DA84 -> 0.16466323 | I29: ='Cash Flow Statement'!DB84 -> 0.19955919 | J29: ='Cash Flow Statement'!DC84 -> 0.2368416
A30: YoY Growth | B30: ='Cash Flow Statement'!CU86 -> -0.21279727 | C30: ='Cash Flow Statement'!CV86 -> 0.1571295 | D30: ='Cash Flow Statement'!CW86 -> 0.062591687 | E30: ='Cash Flow Statement'!CX86 -> -0.52012669 | F30: ='Cash Flow Statement'!CY86 -> 0.92575006 | G30: ='Cash Flow Statement'!CZ86 -> 0.25214042 | H30: ='Cash Flow Statement'!DA86 -> 0.44524912 | I30: ='Cash Flow Statement'!DB86 -> 0.3632237 | J30: ='Cash Flow Statement'!DC86 -> 0.32322628
A31: EV/(FCF-SBC) | B31: =$B$7/B28 -> 86.070409 | C31: =$B$7/C28 -> 74.382694 | D31: =$B$7/D28 -> 70.001201 | E31: =$B$7/E28 -> 145.87433 | F31: =$B$7/F28 -> 75.74936 | G31: =$B$7/G28 -> 60.495899 | H31: =$B$7/H28 -> 41.858458 | I31: =$B$7/I28 -> 30.705494 | J31: =$B$7/J28 -> 23.205022
A32: EV/(FCF-SBC) to Growth | B32: =B31/(B30*100) -> -4.0447139 | C32: =C31/(C30*100) -> 4.7338465 | D32: =D31/(D30*100) -> 11.183786 | E32: =E31/(E30*100) -> -2.8045924 | F32: =F31/(F30*100) -> 0.81824851 | G32: =G31/(G30*100) -> 2.399294 | H32: =H31/(H30*100) -> 0.9401132 | I32: =I31/(I30*100) -> 0.84536044 | J32: =J31/(J30*100) -> 0.71791877
A34: FCF | B34: ='Cash Flow Statement'!CU76 -> 60010 | C34: ='Cash Flow Statement'!CV76 -> 69495 | D34: ='Cash Flow Statement'!CW76 -> 72764 | E34: ='Cash Flow Statement'!CX76 -> 48256.588 | F34: ='Cash Flow Statement'!CY76 -> 72643.967 | G34: ='Cash Flow Statement'!CZ76 -> 86406.029 | H34: ='Cash Flow Statement'!DA76 -> 113999.93 | I34: ='Cash Flow Statement'!DB76 -> 145949.74 | J34: ='Cash Flow Statement'!DC76 -> 184378.69
A35: FCF Margin % | B35: ='Cash Flow Statement'!CU77 -> 0.25658348 | C35: ='Cash Flow Statement'!CV77 -> 0.27092722 | D35: ='Cash Flow Statement'!CW77 -> 0.246559 | E35: ='Cash Flow Statement'!CX77 -> 0.14143434 | F35: ='Cash Flow Statement'!CY77 -> 0.18535312 | G35: ='Cash Flow Statement'!CZ77 -> 0.19316713 | H35: ='Cash Flow Statement'!DA77 -> 0.2245905 | I35: ='Cash Flow Statement'!DB77 -> 0.25562194 | J35: ='Cash Flow Statement'!DC77 -> 0.28963939
A36: YoY Growth | B36: ='Cash Flow Statement'!CU79 -> -0.10448875 | C36: ='Cash Flow Statement'!CV79 -> 0.15805699 | D36: ='Cash Flow Statement'!CW79 -> 0.047039355 | E36: ='Cash Flow Statement'!CX79 -> -0.33680682 | F36: ='Cash Flow Statement'!CY79 -> 0.50536889 | G36: ='Cash Flow Statement'!CZ79 -> 0.18944537 | H36: ='Cash Flow Statement'!DA79 -> 0.31935157 | I36: ='Cash Flow Statement'!DB79 -> 0.28026168 | J36: ='Cash Flow Statement'!DC79 -> 0.26330257
A37: EV/FCF | B37: =$B$7/B34 -> 58.300117 | C37: =$B$7/C34 -> 50.343046 | D37: =$B$7/D34 -> 48.081331 | E37: =$B$7/E34 -> 72.499738 | F37: =$B$7/F34 -> 48.160779 | G37: =$B$7/G34 -> 40.490114 | H37: =$B$7/H34 -> 30.689405 | I37: =$B$7/I34 -> 23.971197 | J37: =$B$7/J34 -> 18.975024
A38: EV/FCF to Growth | B38: =B37/(B36*100) -> -5.5795593 | C38: =C37/(C36*100) -> 3.1851199 | D38: =D37/(D36*100) -> 10.221512 | E38: =E37/(E36*100) -> -2.1525614 | F38: =F37/(F36*100) -> 0.95298266 | G38: =G37/(G36*100) -> 2.1372977 | H38: =H37/(H36*100) -> 0.96099119 | I38: =I37/(I36*100) -> 0.85531482 | J38: =J37/(J36*100) -> 0.72065471
A40: SBC | B40: =-'Income Statement'!CU228 -> 19362 | C40: =-'Income Statement'!CV228 -> 22460 | D40: =-'Income Statement'!CW228 -> 22785 | E40: =-'Income Statement'!CX228 -> 24273 | F40: =-'Income Statement'!CY228 -> 26457.57 | G40: =-'Income Statement'!CZ228 -> 28574.176 | H40: =-'Income Statement'!DA228 -> 30418.495 | I40: =-'Income Statement'!DB228 -> 32009.549 | J40: =-'Income Statement'!DC228 -> 33610.026
A41: YoY Growth | B41: ='Income Statement'!CU231 -> 0.25923517 | C41: ='Income Statement'!CV231 -> 0.16000413 | D41: ='Income Statement'!CW231 -> 0.014470169 | E41: ='Income Statement'!CX231 -> 0.065306122 | F41: ='Income Statement'!CY231 -> 0.09 | G41: ='Income Statement'!CZ231 -> 0.08 | H41: ='Income Statement'!DA231 -> 0.064544968 | I41: ='Income Statement'!DB231 -> 0.052305476 | J41: ='Income Statement'!DC231 -> 0.05
A44: Scenario Analysis
B45: Downside | C45: Base | D45: Upside
A46: Valuation | B46: =MROUND((B75-B77+B78)/B79,5) -> 210 | C46: =MROUND((C75-C77+C78)/C79,5) -> 330 | D46: =MROUND((D75-D77+D78)/D79,5) -> 435
A47: % upside/downside | B47: =B46/$B$3-1 -> -0.28327645 | C47: =C46/$B$3-1 -> 0.12627986 | D47: =D46/$B$3-1 -> 0.48464164
A48: Sales (NTM) | B48: =$C48*(1+B49) -> 348849.39 | C48: =SUM('NTM Valuation'!$J$14:$M$14) -> 379184.12 | D48: =$C48*(1+D49) -> 409518.85
A49: Downside/Upside Adjustment | B49: -0.08 | C49: - | D49: 0.08
A50: Sales (NTM + 1 year) | B50: =$C50*(1+B51) -> 389103.54 | C50: =SUM('NTM Valuation'!$O$14:$R$14) -> 432337.26 | D50: =$C50*(1+D51) -> 475570.99
A51: Downside/Upside Adjustment | B51: -0.1 | C51: - | D51: 0.1
A52: EV / Sales (Implied) | B52: =B75/B50 -> 6.2899102 | C52: =C75/C50 -> 9.0688 | D52: =D75/D50 -> 10.90819
A53: Sales CAGR | B53: =(B50/SUM('NTM Valuation'!$D$14:$F$14,'NTM Valuation'!$H$14))^0.5-1 -> 0.090334081 | C53: =(C50/SUM('NTM Valuation'!$D$14:$F$14,'NTM Valuation'!$H$14))^0.5-1 -> 0.14931304 | D53: =(D50/SUM('NTM Valuation'!$D$14:$F$14,'NTM Valuation'!$H$14))^0.5-1 -> 0.20540968
A54: EV / Sales to Growth (Implied) | B54: =B52/(B53*100) -> 0.69629425 | C54: =C52/(C53*100) -> 0.60736827 | D54: =D52/(D53*100) -> 0.53104559
A55: GAAP EBITDA (NTM) | B55: =B48*B56 -> 160470.72 | C55: =SUM('NTM Valuation'!$J$25:$M$25) -> 183787.66 | D55: =D48*D56 -> 200664.24
A56: EBITDA Margin % | B56: 0.46 | C56: =C55/C48 -> 0.4846924 | D56: 0.49
A57: GAAP EBITDA (NTM + 1 year) | B57: =B50*B58 -> 190660.73 | C57: =SUM('NTM Valuation'!$O$25:$R$25) -> 217611.19 | D57: =D50*D58 -> 242541.21
A58: EBITDA Margin % | B58: 0.49 | C58: =C57/C50 -> 0.50333666 | D58: 0.51
A59: EV / GAAP EBITDA | B59: 15 | C59: 22 | D59: 26
A60: EBITDA CAGR | B60: =(B57/SUM('NTM Valuation'!$D$25:$F$25,'NTM Valuation'!$H$25))^0.5-1 -> 0.15315947 | C60: =(C57/SUM('NTM Valuation'!$D$25:$F$25,'NTM Valuation'!$H$25))^0.5-1 -> 0.2319678 | D60: =(D57/SUM('NTM Valuation'!$D$25:$F$25,'NTM Valuation'!$H$25))^0.5-1 -> 0.30062323
A61: EV / GAAP EBITDA to Growth | B61: =B59/(B60*100) -> 0.97937135 | C61: =C59/(C60*100) -> 0.94840751 | D61: =D59/(D60*100) -> 0.86486995
A62: Enterprise Value | B62: =B57*B59 -> 2859911 | C62: =C57*C59 -> 4787446.2 | D62: =D57*D59 -> 6306071.3
A63: FCF-SBC (NTM + 4 years) | B63: =B64*SUM('NTM Valuation'!$AD$14:$AG$14) -> 123795.67 | C63: =SUM('NTM Valuation'!$AD$44:$AG$44) -> 143027.02 | D63: =D64*SUM('NTM Valuation'!$AD$14:$AG$14) -> 154744.59
A64: FCF % of Sales | B64: 0.2 | C64: =C63/SUM('NTM Valuation'!$AD$14:$AG$14) -> 0.23106949 | D64: 0.25
A65: EV / FCF-SBC | B65: 25 | C65: 30 | D65: 35
A66: FCF-SBC CAGR | B66: =(B63/SUM('NTM Valuation'!$O$44:$R$44))^(1/3)-1 -> 0.30756948 | C66: =(C63/SUM('NTM Valuation'!$O$44:$R$44))^(1/3)-1 -> 0.37204698 | D66: =(D63/SUM('NTM Valuation'!$O$44:$R$44))^(1/3)-1 -> 0.40853653
A67: EV / FCF-SBC-to-Growth | B67: =B65/(B66*100) -> 0.81282446 | C67: =C65/(C66*100) -> 0.80634979 | D67: =D65/(D66*100) -> 0.85671654
A68: Discount Rate | B68: 0.15 | C68: 0.12 | D68: 0.1
A69: Discount Period (Years) | B69: 3 | C69: 3 | D69: 3
A70: Enterprise Value (NTM + 3 years) | B70: =B63*B65 -> 3094891.8 | C70: =C63*C65 -> 4290810.5 | D70: =D63*D65 -> 5416060.7
A71: Discounted Enterprise Value | B71: =B70/(1+B68)^B69 -> 2034941.6 | C71: =C70/(1+C68)^C69 -> 3054114.2 | D71: =D70/(1+D68)^D69 -> 4069166.6
A72: Weightings
A73: EV derived from GAAP EBITDA | B73: =$C73 -> 0.5 | C73: 0.5 | D73: =$C73 -> 0.5
A74: EV derived from (FCF-SBC) | B74: =$C74 -> 0.5 | C74: 0.5 | D74: =$C74 -> 0.5
A75: Enterprise Value | B75: =(B62*B73)+(B71*B74) -> 2447426.3 | C75: =(C62*C73)+(C71*C74) -> 3920780.2 | D75: =(D62*D73)+(D71*D74) -> 5187619
A76: Capital Structure Adjustments
A77: Adjusted Net Debt - NTM Ending | B77: =$C77 -> -72036.651 | C77: ='NTM Valuation'!C6 -> -72036.651 | D77: =$C77 -> -72036.651
A78: Dividends | B78: =C78 -> 10090.037 | C78: =SUM('NTM Valuation'!$J$61:$M$61) -> 10090.037 | D78: =C78 -> 10090.037
A79: Adjusted Shares Outstanding - NTM Ending | B79: =$C79 -> 12087.925 | C79: ='NTM Valuation'!C5 -> 12087.925 | D79: =$C79 -> 12087.925

Sheet Income Statement
A1: Income Statement (USD Millions) | B1: 1Q10 | C1: 2Q10 | D1: 3Q10 | E1: 4Q10 | F1: 1Q11 | G1: 2Q11 | H1: 3Q11 | I1: 4Q11 | J1: 1Q12 | K1: 2Q12 | L1: 3Q12 | M1: 4Q12 | N1: 1Q13 | O1: 2Q13 | P1: 3Q13 | Q1: 4Q13 | R1: 1Q14 | S1: 2Q14 | T1: 3Q14 | U1: 4Q14 | V1: 1Q15 | W1: 2Q15 | X1: 3Q15 | Y1: 4Q15 | Z1: 1Q16 | AA1: 2Q16 | AB1: 3Q16 | AC1: 4Q16 | AD1: 1Q17 | AE1: 2Q17 | AF1: 3Q17 | AG1: 4Q17 | AH1: 1Q18 | AI1: 2Q18 | AJ1: 3Q18 | AK1: 4Q18 | AL1: 1Q19 | AM1: 2Q19 | AN1: 3Q19 | AO1: 4Q19 | AP1: 1Q20 | AQ1: 2Q20 | AR1: 3Q20 | AS1: 4Q20 | AT1: 1Q21 | AU1: 2Q21 | AV1: 3Q21 | AW1: 4Q21 | AX1: 1Q22 | AY1: 2Q22 | AZ1: 3Q22 | BA1: 4Q22 | BB1: 1Q23 | BC1: 2Q23 | BD1: 3Q23 | BE1: 4Q23 | BF1: 1Q24 | BG1: 2Q24 | BH1: 3Q24 | BI1: 4Q24 | BJ1: 1Q25 | BK1: 2Q25 | BL1: 3Q25 | BM1: 4Q25E | BN1: 1Q26E | BO1: 2Q26E | BP1: 3Q26E | BQ1: 4Q26E | BR1: 1Q27E | BS1: 2Q27E | BT1: 3Q27E | BU1: 4Q27E | BV1: 1Q28E | BW1: 2Q28E | BX1: 3Q28E | BY1: 4Q28E | BZ1: 1Q29E | CA1: 2Q29E | CB1: 3Q29E | CC1: 4Q29E | CD1: 1Q30E | CE1: 2Q30E | CF1: 3Q30E | CG1: 4Q30E | CI1: 2010 | CJ1: 2011 | CK1: 2012 | CL1: 2013 | CM1: 2014 | CN1: 2015 | CO1: 2016 | CP1: 2017 | CQ1: 2018 | CR1: 2019 | CS1: 2020 | CT1: 2021 | CU1: 2022 | CV1: 2023 | CW1: 2024 | CX1: 2025E | CY1: 2026E | CZ1: 2027E | DA1: 2028E | DB1: 2029E | DC1: 2030E
A3: Google Segment Revenues (Gross) | B3: =SUM(B14,B121) -> 6775 | C3: =SUM(C14,C121) -> 6820 | D3: =SUM(D14,D121) -> 7286 | E3: =SUM(E14,E121) -> 8440 | F3: =SUM(F14,F121) -> 8575 | G3: =SUM(G14,G121) -> 9026 | H3: =SUM(H14,H121) -> 9720 | I3: =SUM(I14,I121) -> 10584 | ... AJ3: =SUM(AJ14,AJ121) -> 33594 | AK3: =SUM(AK8,AK47) -> 38998 | AL3: =SUM(AL8,AL47) -> 36032 | AM3: =SUM(AM8,AM47) -> 38674 | AN3: =SUM(AN8,AN47) -> 40225 | AO3: =SUM(AO8,AO47) -> 45812 | AP3: =SUM(AP8,AP47) -> 40975 | AQ3: =SUM(AQ8,AQ47) -> 37998 | AR3: =SUM(AR8,AR47) -> 46017 | ... CG3: =SUM(CG8,CG47) -> 196153.11 | CI3: =SUM(B3:E3) -> 29321 | CJ3: =SUM(F3:I3) -> 37905 | CK3: =SUM(J3:M3) -> 46040 | CL3: =SUM(N3:Q3) -> 55519 | CM3: =SUM(R3:U3) -> 65895 | CN3: =SUM(V3:Y3) -> 74542 | CO3: =SUM(Z3:AC3) -> 89462 | CP3: =SUM(AD3:AG3) -> 110378 | CQ3: =SUM(AH3:AK3) -> 136100 | CR3: =SUM(AL3:AO3) -> 160743 | CS3: =SUM(AP3:AS3) -> 181694 | CT3: =SUM(AT3:AW3) -> 256735 | CU3: =SUM(AX3:BA3) -> 279808 | CV3: =SUM(BB3:BE3) -> 305631 | CW3: =SUM(BF3:BI3) -> 348159 | CX3: =SUM(BJ3:BM3) -> 399638.92 | CY3: =SUM(BN3:BQ3) -> 454413.53 | CZ3: =SUM(BR3:BU3) -> 514506.89 | DA3: =SUM(BV3:BY3) -> 579454.64 | DB3: =SUM(BZ3:CC3) -> 647341.21 | DC3: =SUM(CD3:CG3) -> 717427.87
A4: QoQ Growth | B4: n/a | C4: =IF(AND(B3<0,C3>0),"n/a",C3/B3-1) -> 0.0066420664 | D4: =IF(AND(C3<0,D3>0),"n/a",D3/C3-1) -> 0.068328446 | E4: =IF(AND(D3<0,E3>0),"n/a",E3/D3-1) -> 0.15838595 | F4: =IF(AND(E3<0,F3>0),"n/a",F3/E3-1) -> 0.015995261 | G4: =IF(AND(F3<0,G3>0),"n/a",G3/F3-1) -> 0.052594752 | H4: =IF(AND(G3<0,H3>0),"n/a",H3/G3-1) -> 0.076888987 | I4: =IF(AND(H3<0,I3>0),"n/a",I3/H3-1) -> 0.088888889 | J4: =IF(AND(I3<0,J3>0),"n/a",J3/I3-1) -> 0.0057634165 | ... CG4: =IF(AND(CF3<0,CG3>0),"n/a",CG3/CF3-1) -> 0.067917661 | CI4: n/a | CJ4: n/a | CK4: n/a | CL4: n/a | CM4: n/a | CN4: n/a | CO4: n/a | CP4: n/a | CQ4: n/a | CR4: n/a | CS4: n/a | CT4: n/a | CU4: n/a | CV4: n/a | CW4: n/a | CX4: n/a | CY4: n/a | CZ4: n/a | DA4: n/a | DB4: n/a | DC4: n/a
A5: YoY Growth | B5: n/a | C5: n/a | D5: n/a | E5: n/a | F5: =IF(AND(B3<0,F3>0),"n/a",F3/B3-1) -> 0.26568266 | G5: =IF(AND(C3<0,G3>0),"n/a",G3/C3-1) -> 0.32346041 | H5: =IF(AND(D3<0,H3>0),"n/a",H3/D3-1) -> 0.33406533 | I5: =IF(AND(E3<0,I3>0),"n/a",I3/E3-1) -> 0.25402844 | J5: =IF(AND(F3<0,J3>0),"n/a",J3/F3-1) -> 0.24139942 | K5: =IF(AND(G3<0,K3>0),"n/a",K3/G3-1) -> 0.21471305 | L5: =IF(AND(H3<0,L3>0),"n/a",L3/H3-1) -> 0.18580247 | M5: =IF(AND(I3<0,M3>0),"n/a",M3/I3-1) -> 0.21929327 | ... CG5: =IF(AND(CC3<0,CG3>0),"n/a",CG3/CC3-1) -> 0.1056105 | CI5: n/a | CJ5: =IF(AND(CI3<0,CJ3>0),"n/a",CJ3/CI3-1) -> 0.29275946 | CK5: =IF(AND(CJ3<0,CK3>0),"n/a",CK3/CJ3-1) -> 0.21461549 | CL5: =IF(AND(CK3<0,CL3>0),"n/a",CL3/CK3-1) -> 0.20588619 | CM5: =IF(AND(CL3<0,CM3>0),"n/a",CM3/CL3-1) -> 0.18689097 | CN5: =IF(AND(CM3<0,CN3>0),"n/a",CN3/CM3-1) -> 0.13122392 | CO5: =IF(AND(CN3<0,CO3>0),"n/a",CO3/CN3-1) -> 0.20015562 | CP5: =IF(AND(CO3<0,CP3>0),"n/a",CP3/CO3-1) -> 0.23379759 | CQ5: =IF(AND(CP3<0,CQ3>0),"n/a",CQ3/CP3-1) -> 0.23303557 | ... DC5: =IF(AND(DB3<0,DC3>0),"n/a",DC3/DB3-1) -> 0.10826849
A6: % of Consolidated Gross Revenues | B6: =B3/B$64 -> 1 | C6: =C3/C$64 -> 1 | D6: =D3/D$64 -> 1 | E6: =E3/E$64 -> 1 | F6: =F3/F$64 -> 1 | G6: =G3/G$64 -> 1 | H6: =H3/H$64 -> 1 | I6: =I3/I$64 -> 1 | ... CG6: =CG3/CG$64 -> 0.99727469 | CI6: =CI3/CI$64 -> 1 | CJ6: =CJ3/CJ$64 -> 1 | CK6: =CK3/CK$64 -> 1 | CL6: =CL3/CL$64 -> 1 | CM6: =CM3/CM$64 -> 0.99839396 | CN6: =CN3/CN$64 -> 0.99403913 | CO6: =CO3/CO$64 -> 0.99102712 | CP6: =CP3/CP$64 -> 0.99569708 | ... DC6: =DC3/DC$64 -> 0.99718473
A8: Google Services | AK8: =SUM(AK14,AK41) -> 37289 | AL8: =SUM(AL14,AL41) -> 34207 | AM8: =SUM(AM14,AM41) -> 36574 | AN8: =SUM(AN14,AN41) -> 37846 | AO8: =SUM(AO14,AO41) -> 43198 | AP8: =SUM(AP14,AP41) -> 38198 | AQ8: =SUM(AQ14,AQ41) -> 34991 | AR8: =SUM(AR14,AR41) -> 42573 | ... CG8: =SUM(CG14,CG41) -> 145961.14 | CQ8: 130524 | CR8: =SUM(AL8:AO8) -> 151825 | CS8: =SUM(AP8:AS8) -> 168635 | CT8: =SUM(AT8:AW8) -> 237529 | CU8: =SUM(AX8:BA8) -> 253528 | CV8: =SUM(BB8:BE8) -> 272543 | CW8: =SUM(BF8:BI8) -> 304930 | CX8: =SUM(BJ8:BM8) -> 341860.92 | CY8: =SUM(BN8:BQ8) -> 377395.63 | CZ8: =SUM(BR8:BU8) -> 415153.8 | DA8: =SUM(BV8:BY8) -> 454269.75 | DB8: =SUM(BZ8:CC8) -> 493363.79 | DC8: =SUM(CD8:CG8) -> 532654.97
A9: QoQ Growth | AK9: n/a | AL9: =IF(AND(AK8<0,AL8>0),"n/a",AL8/AK8-1) -> -0.08265172 | AM9: =IF(AND(AL8<0,AM8>0),"n/a",AM8/AL8-1) -> 0.069196363 | AN9: =IF(AND(AM8<0,AN8>0),"n/a",AN8/AM8-1) -> 0.034778805 | AO9: =IF(AND(AN8<0,AO8>0),"n/a",AO8/AN8-1) -> 0.14141521 | AP9: =IF(AND(AO8<0,AP8>0),"n/a",AP8/AO8-1) -> -0.1157461 | AQ9: =IF(AND(AP8<0,AQ8>0),"n/a",AQ8/AP8-1) -> -0.083957275 | AR9: =IF(AND(AQ8<0,AR8>0),"n/a",AR8/AQ8-1) -> 0.21668429 | AS9: =IF(AND(AR8<0,AS8>0),"n/a",AS8/AR8-1) -> 0.24193738 | ... CG9: =IF(AND(CF8<0,CG8>0),"n/a",CG8/CF8-1) -> 0.078674214 | CQ9: n/a | CR9: n/a | CS9: n/a | CT9: n/a | CU9: n/a | CV9: n/a | CW9: n/a | CX9: n/a | CY9: n/a | CZ9: n/a | DA9: n/a | DB9: n/a | DC9: n/a
A10: YoY Growth | AK10: n/a | AL10: n/a | AM10: n/a | AN10: n/a | AO10: =IF(AND(AK8<0,AO8>0),"n/a",AO8/AK8-1) -> 0.15846496 | AP10: =IF(AND(AL8<0,AP8>0),"n/a",AP8/AL8-1) -> 0.11667203 | AQ10: =IF(AND(AM8<0,AQ8>0),"n/a",AQ8/AM8-1) -> -0.043282113 | AR10: =IF(AND(AN8<0,AR8>0),"n/a",AR8/AN8-1) -> 0.12490091 | AS10: =IF(AND(AO8<0,AS8>0),"n/a",AS8/AO8-1) -> 0.2239687 | AT10: =IF(AND(AP8<0,AT8>0),"n/a",AT8/AP8-1) -> 0.33980837 | AU10: =IF(AND(AQ8<0,AU8>0),"n/a",AU8/AQ8-1) -> 0.63090509 | AV10: =IF(AND(AR8<0,AV8>0),"n/a",AV8/AR8-1) -> 0.40661922 | ... CG10: =IF(AND(CC8<0,CG8>0),"n/a",CG8/CC8-1) -> 0.076493221 | CQ10: n/a | CR10: =IF(AND(CQ8<0,CR8>0),"n/a",CR8/CQ8-1) -> 0.16319604 | CS10: =IF(AND(CR8<0,CS8>0),"n/a",CS8/CR8-1) -> 0.11071958 | CT10: =IF(AND(CS8<0,CT8>0),"n/a",CT8/CS8-1) -> 0.40853915 | CU10: =IF(AND(CT8<0,CU8>0),"n/a",CU8/CT8-1) -> 0.067355986 | CV10: =IF(AND(CU8<0,CV8>0),"n/a",CV8/CU8-1) -> 0.075001578 | CW10: =IF(AND(CV8<0,CW8>0),"n/a",CW8/CV8-1) -> 0.11883262 | CX10: =IF(AND(CW8<0,CX8>0),"n/a",CX8/CW8-1) -> 0.12111277 | CY10: =IF(AND(CX8<0,CY8>0),"n/a",CY8/CX8-1) -> 0.10394494 | ... DC10: =IF(AND(DB8<0,DC8>0),"n/a",DC8/DB8-1) -> 0.079639356
A11: % of Google Segment Revs (Gross) | AK11: =AK8/AK$3 -> 0.95617724 | AL11: =AL8/AL$3 -> 0.94935058 | AM11: =AM8/AM$3 -> 0.94569995 | AN11: =AN8/AN$3 -> 0.94085768 | AO11: =AO8/AO$3 -> 0.94294071 | AP11: =AP8/AP$3 -> 0.93222697 | AQ11: =AQ8/AQ$3 -> 0.92086426 | AR11: =AR8/AR$3 -> 0.92515809 | ... CG11: =CG8/CG$3 -> 0.7441184 | CQ11: =CQ8/CQ$3 -> 0.95903012 | CR11: =CR8/CR$3 -> 0.94452013 | CS11: =CS8/CS$3 -> 0.92812641 | CT11: =CT8/CT$3 -> 0.92519135 | CU11: =CU8/CU$3 -> 0.90607845 | CV11: =CV8/CV$3 -> 0.89173873 | CW11: =CW8/CW$3 -> 0.87583547 | CX11: =CX8/CX$3 -> 0.85542449 | ... DC11: =DC8/DC$3 -> 0.7424509
A12: % of Consolidated Gross Revenues | AK12: =AK8/AK$64 -> 0.94940931 | AL12: =AL8/AL$64 -> 0.94133025 | AM12: =AM8/AM$64 -> 0.93914339 | AN12: =AN8/AN$64 -> 0.93449221 | AO12: =AO8/AO$64 -> 0.93755833 | AP12: =AP8/AP$64 -> 0.92805948 | AQ12: =AQ8/AQ$64 -> 0.9136747 | AR12: =AR8/AR$64 -> 0.92203236 | ... CG12: =CG8/CG$64 -> 0.74209045 | CQ12: =CQ8/CQ$64 -> 0.95399031 | CR12: =CR8/CR$64 -> 0.93801936 | CS12: =CS8/CS$64 -> 0.92389071 | CT12: =CT8/CT$64 -> 0.9219522 | CU12: =CU8/CU$64 -> 0.89637811 | CV12: =CV8/CV$64 -> 0.88662433 | CW12: =CW8/CW$64 -> 0.87118377 | CX12: =CX8/CX$64 -> 0.85216627 | ... DC12: =DC8/DC$64 -> 0.74036069
A14: Google Advertising (Gross) | B14: =SUM(B91,B106) -> 6475 | C14: =SUM(C91,C106) -> 6562 | D14: =SUM(D91,D106) -> 7032 | E14: =SUM(E91,E106) -> 8167 | F14: =SUM(F91,F106) -> 8306 | G14: =SUM(G91,G106) -> 8716 | H14: =SUM(H91,H106) -> 9335 | I14: =SUM(I91,I106) -> 10174 | ... AJ14: =SUM(AJ91,AJ106) -> 28954 | AK14: =SUM(AK20,AK27,AK34) -> 32518 | AL14: =SUM(AL20,AL27,AL34) -> 30587 | AM14: =SUM(AM20,AM27,AM34) -> 32494 | AN14: =SUM(AN20,AN27,AN34) -> 33796 | AO14: =SUM(AO20,AO27,AO34) -> 37934 | AP14: =SUM(AP20,AP27,AP34) -> 33763 | AQ14: =SUM(AQ20,AQ27,AQ34) -> 29867 | AR14: =SUM(AR20,AR27,AR34) -> 37095 | ... CG14: =SUM(CG20,CG27,CG34) -> 121032.82 | CI14: =SUM(B14:E14) -> 28236 | CJ14: =SUM(F14:I14) -> 36531 | CK14: =SUM(J14:M14) -> 43686 | CL14: =SUM(N14:Q14) -> 51072 | CM14: =SUM(R14:U14) -> 59624 | CN14: =SUM(V14:Y14) -> 67390 | CO14: =SUM(Z14:AC14) -> 79383 | CP14: =SUM(AD14:AG14) -> 95375 | CQ14: =SUM(AH14:AK14) -> 116201 | CR14: =SUM(AL14:AO14) -> 134811 | CS14: =SUM(AP14:AS14) -> 146924 | CT14: =SUM(AT14:AW14) -> 209497 | CU14: =SUM(AX14:BA14) -> 224473 | CV14: =SUM(BB14:BE14) -> 237855 | CW14: =SUM(BF14:BI14) -> 264590 | CX14: =SUM(BJ14:BM14) -> 293595.4 | CY14: =SUM(BN14:BQ14) -> 322907.25 | CZ14: =SUM(BR14:BU14) -> 353845.37 | DA14: =SUM(BV14:BY14) -> 384633.04 | DB14: =SUM(BZ14:CC14) -> 414875.64 | DC14: =SUM(CD14:CG14) -> 444725.1
A15: QoQ Growth | B15: n/a | C15: =IF(AND(B14<0,C14>0),"n/a",C14/B14-1) -> 0.013436293 | D15: =IF(AND(C14<0,D14>0),"n/a",D14/C14-1) -> 0.071624505 | E15: =IF(AND(D14<0,E14>0),"n/a",E14/D14-1) -> 0.16140501 | F15: =IF(AND(E14<0,F14>0),"n/a",F14/E14-1) -> 0.017019713 | G15: =IF(AND(F14<0,G14>0),"n/a",G14/F14-1) -> 0.049361907 | H15: =IF(AND(G14<0,H14>0),"n/a",H14/G14-1) -> 0.071018816 | I15: =IF(AND(H14<0,I14>0),"n/a",I14/H14-1) -> 0.089876808 | J15: =IF(AND(I14<0,J14>0),"n/a",J14/I14-1) -> 0.0050127777 | ... CG15: =IF(AND(CF14<0,CG14>0),"n/a",CG14/CF14-1) -> 0.080953017 | CI15: n/a | CJ15: n/a | CK15: n/a | CL15: n/a | CM15: n/a | CN15: n/a | CO15: n/a | CP15: n/a | CQ15: n/a | CR15: n/a | CS15: n/a | CT15: n/a | CU15: n/a | CV15: n/a | CW15: n/a | CX15: n/a | CY15: n/a | CZ15: n/a | DA15: n/a | DB15: n/a | DC15: n/a
A16: YoY Growth | B16: n/a | C16: n/a | D16: n/a | E16: n/a | F16: =IF(AND(B14<0,F14>0),"n/a",F14/B14-1) -> 0.28277992 | G16: =IF(AND(C14<0,G14>0),"n/a",G14/C14-1) -> 0.32825358 | H16: =IF(AND(D14<0,H14>0),"n/a",H14/D14-1) -> 0.32750284 | I16: =IF(AND(E14<0,I14>0),"n/a",I14/E14-1) -> 0.24574507 | J16: =IF(AND(F14<0,J14>0),"n/a",J14/F14-1) -> 0.2310378 | K16: =IF(AND(G14<0,K14>0),"n/a",K14/G14-1) -> 0.20754933 | L16: =IF(AND(H14<0,L14>0),"n/a",L14/H14-1) -> 0.16336369 | M16: =IF(AND(I14<0,M14>0),"n/a",M14/I14-1) -> 0.18694712 | ... CG16: =IF(AND(CC14<0,CG14>0),"n/a",CG14/CC14-1) -> 0.067893672 | CI16: n/a | CJ16: =IF(AND(CI14<0,CJ14>0),"n/a",CJ14/CI14-1) -> 0.29377391 | CK16: =IF(AND(CJ14<0,CK14>0),"n/a",CK14/CJ14-1) -> 0.19586105 | CL16: =IF(AND(CK14<0,CL14>0),"n/a",CL14/CK14-1) -> 0.16907018 | CM16: =IF(AND(CL14<0,CM14>0),"n/a",CM14/CL14-1) -> 0.16744987 | CN16: =IF(AND(CM14<0,CN14>0),"n/a",CN14/CM14-1) -> 0.13024956 | CO16: =IF(AND(CN14<0,CO14>0),"n/a",CO14/CN14-1) -> 0.17796409 | CP16: =IF(AND(CO14<0,CP14>0),"n/a",CP14/CO14-1) -> 0.20145371 | CQ16: =IF(AND(CP14<0,CQ14>0),"n/a",CQ14/CP14-1) -> 0.21835911 | ... DC16: =IF(AND(DB14<0,DC14>0),"n/a",DC14/DB14-1) -> 0.071947958
A17: % of Google Services | B17: n/a | C17: n/a | D17: n/a | E17: n/a | F17: n/a | G17: n/a | H17: n/a | I17: n/a | J17: n/a | K17: n/a | L17: n/a | M17: n/a | N17: n/a | O17: n/a | P17: n/a | Q17: n/a | R17: n/a | S17: n/a | T17: n/a | U17: n/a | V17: n/a | W17: n/a | X17: n/a | Y17: n/a | Z17: n/a | AA17: n/a | AB17: n/a | AC17: n/a | AD17: n/a | AE17: n/a | AF17: n/a | AG17: n/a | AH17: n/a | AI17: n/a | AJ17: n/a | AK17: =AK14/AK$8 -> 0.87205342 | AL17: =AL14/AL$8 -> 0.89417371 | AM17: =AM14/AM$8 -> 0.88844534 | AN17: =AN14/AN$8 -> 0.89298737 | AO17: =AO14/AO$8 -> 0.87814251 | AP17: =AP14/AP$8 -> 0.88389444 | AQ17: =AQ14/AQ$8 -> 0.85356234 | AR17: =AR14/AR$8 -> 0.8713269 | ... CG17: =CG14/CG$8 -> 0.82921263 | CI17: =CI14/CI$8 -> #DIV/0! | CJ17: =CJ14/CJ$8 -> #DIV/0! | CK17: =CK14/CK$8 -> #DIV/0! | CL17: =CL14/CL$8 -> #DIV/0! | CM17: =CM14/CM$8 -> #DIV/0! | CN17: =CN14/CN$8 -> #DIV/0! | CO17: =CO14/CO$8 -> #DIV/0! | CP17: =CP14/CP$8 -> #DIV/0! | ... DC17: =DC14/DC$8 -> 0.83492153
A18: % of Google Segment Revs (Gross) | B18: =B14/B$3 -> 0.95571956 | C18: =C14/C$3 -> 0.96217009 | D18: =D14/D$3 -> 0.96513862 | E18: =E14/E$3 -> 0.96765403 | F18: =F14/F$3 -> 0.96862974 | G18: =G14/G$3 -> 0.96565478 | H18: =H14/H$3 -> 0.96039095 | I18: =I14/I$3 -> 0.96126228 | ... CG18: =CG14/CG$3 -> 0.61703238 | CI18: =CI14/CI$3 -> 0.96299581 | CJ18: =CJ14/CJ$3 -> 0.96375148 | CK18: =CK14/CK$3 -> 0.94887055 | CL18: =CL14/CL$3 -> 0.9199013 | CM18: =CM14/CM$3 -> 0.90483345 | CN18: =CN14/CN$3 -> 0.90405409 | CO18: =CO14/CO$3 -> 0.88733764 | CP18: =CP14/CP$3 -> 0.86407617 | ... DC18: =DC14/DC$3 -> 0.61988824
A20: Google Search & Other | AK20: 23320 | AL20: 22547 | AM20: 23642 | AN20: 24741 | AO20: 27185 | AP20: 24502 | AQ20: 21319 | AR20: 26338 | AS20: 31903 | AT20: 31879 | AU20: 35845 | AV20: 37926 | AW20: 43301 | AX20: 39618 | AY20: 40689 | AZ20: 39539 | BA20: 42604 | BB20: 40359 | BC20: 42628 | BD20: 44026 | BE20: 48020 | BF20: 46156 | BG20: 48509 | BH20: 49385 | BI20: 54034 | BJ20: 50702 | BK20: 54190 | BL20: 56567 | BM20: =BI20*(1+BM22) -> 61598.76 | BN20: =BJ20*(1+BN22) -> 56786.24 | BO20: =BK20*(1+BO22) -> 60150.9 | BP20: =BL20*(1+BP22) -> 62789.37 | BQ20: =BM20*(1+BQ22) -> 68066.63 | BR20: =BN20*(1+BR22) -> 63174.692 | BS20: =BO20*(1+BS22) -> 66316.367 | BT20: =BP20*(1+BT22) -> 69225.28 | ... CG20: =CC20*(1+CG22) -> 93013.259 | CP20: 69811 | CQ20: 85296 | CR20: =SUM(AL20:AO20) -> 98115 | CS20: =SUM(AP20:AS20) -> 104062 | CT20: =SUM(AT20:AW20) -> 148951 | CU20: =SUM(AX20:BA20) -> 162450 | CV20: =SUM(BB20:BE20) -> 175033 | CW20: =SUM(BF20:BI20) -> 198084 | CX20: =SUM(BJ20:BM20) -> 223057.76 | CY20: =SUM(BN20:BQ20) -> 247793.14 | CZ20: =SUM(BR20:BU20) -> 273419.47 | DA20: =SUM(BV20:BY20) -> 298285.45 | DB20: =SUM(BZ20:CC20) -> 322437.94 | DC20: =SUM(CD20:CG20) -> 346136.5
A21: QoQ Growth | AK21: n/a | AL21: =IF(AND(AK20<0,AL20>0),"n/a",AL20/AK20-1) -> -0.033147513 | AM21: =IF(AND(AL20<0,AM20>0),"n/a",AM20/AL20-1) -> 0.048565219 | AN21: =IF(AND(AM20<0,AN20>0),"n/a",AN20/AM20-1) -> 0.046485069 | AO21: =IF(AND(AN20<0,AO20>0),"n/a",AO20/AN20-1) -> 0.098783396 | AP21: =IF(AND(AO20<0,AP20>0),"n/a",AP20/AO20-1) -> -0.098694133 | AQ21: =IF(AND(AP20<0,AQ20>0),"n/a",AQ20/AP20-1) -> -0.12990776 | AR21: =IF(AND(AQ20<0,AR20>0),"n/a",AR20/AQ20-1) -> 0.2354238 | AS21: =IF(AND(AR20<0,AS20>0),"n/a",AS20/AR20-1) -> 0.21129167 | ... CG21: =IF(AND(CF20<0,CG20>0),"n/a",CG20/CF20-1) -> 0.064222863 | CP21: n/a | CQ21: n/a | CR21: n/a | CS21: n/a | CT21: n/a | CU21: n/a | CV21: n/a | CW21: n/a | CX21: n/a | CY21: n/a | CZ21: n/a | DA21: n/a | DB21: n/a | DC21: n/a
A22: YoY Growth | AK22: n/a | AL22: n/a | AM22: n/a | AN22: n/a | AO22: =IF(AND(AK20<0,AO20>0),"n/a",AO20/AK20-1) -> 0.16573756 | AP22: =IF(AND(AL20<0,AP20>0),"n/a",AP20/AL20-1) -> 0.086707766 | AQ22: =IF(AND(AM20<0,AQ20>0),"n/a",AQ20/AM20-1) -> -0.098257339 | AR22: =IF(AND(AN20<0,AR20>0),"n/a",AR20/AN20-1) -> 0.064548725 | AS22: =IF(AND(AO20<0,AS20>0),"n/a",AS20/AO20-1) -> 0.17355159 | AT22: =IF(AND(AP20<0,AT20>0),"n/a",AT20/AP20-1) -> 0.30107746 | AU22: =IF(AND(AQ20<0,AU20>0),"n/a",AU20/AQ20-1) -> 0.68136404 | AV22: =IF(AND(AR20<0,AV20>0),"n/a",AV20/AR20-1) -> 0.43997266 | ... BL22: =IF(AND(BH20<0,BL20>0),"n/a",BL20/BH20-1) -> 0.14542877 | BM22: 0.14 | BN22: 0.12 | BO22: 0.11 | BP22: 0.11 | BQ22: 0.105 | BR22: =BN22-0.0075 -> 0.1125 | BS22: =BO22-0.0075 -> 0.1025 | BT22: =BP22-0.0075 -> 0.1025 | BU22: =BQ22-0.0075 -> 0.0975 | BV22: =BR22-0.0125 -> 0.1 | BW22: =BS22-0.0125 -> 0.09 | BX22: =BT22-0.0125 -> 0.09 | BY22: =BU22-0.0125 -> 0.085 | BZ22: =BV22-0.01 -> 0.09 | CA22: =BW22-0.01 -> 0.08 | CB22: =BX22-0.01 -> 0.08 | CC22: =BY22-0.01 -> 0.075 | CD22: =BZ22-0.0075 -> 0.0825 | CE22: =CA22-0.0075 -> 0.0725 | CF22: =CB22-0.0075 -> 0.0725 | CG22: =CC22-0.0075 -> 0.0675 | CP22: n/a | CQ22: =IF(AND(CP20<0,CQ20>0),"n/a",CQ20/CP20-1) -> 0.22181318 | CR22: =IF(AND(CQ20<0,CR20>0),"n/a",CR20/CQ20-1) -> 0.15028841 | CS22: =IF(AND(CR20<0,CS20>0),"n/a",CS20/CR20-1) -> 0.060612547 | CT22: =IF(AND(CS20<0,CT20>0),"n/a",CT20/CS20-1) -> 0.43136784 | CU22: =IF(AND(CT20<0,CU20>0),"n/a",CU20/CT20-1) -> 0.090627119 | CV22: =IF(AND(CU20<0,CV20>0),"n/a",CV20/CU20-1) -> 0.077457679 | CW22: =IF(AND(CV20<0,CW20>0),"n/a",CW20/CV20-1) -> 0.13169517 | CX22: =IF(AND(CW20<0,CX20>0),"n/a",CX20/CW20-1) -> 0.12607661 | ... DC22: =IF(AND(DB20<0,DC20>0),"n/a",DC20/DB20-1) -> 0.073498038
A23: 3yr stack | AK23: n/a | AL23: n/a | AM23: n/a | AN23: n/a | AO23: n/a | AP23: n/a | AQ23: n/a | AR23: n/a | AS23: n/a | AT23: n/a | AU23: n/a | AV23: n/a | AW23: =AW22+AS22+AO22 -> 0.69655963 | AX23: =AX22+AT22+AP22 -> 0.63054692 | AY23: =AY22+AU22+AQ22 -> 0.7182441 | AZ23: =AZ22+AV22+AR22 -> 0.54705158 | BA23: =BA22+AW22+AS22 -> 0.51472544 | BB23: =BB22+AX22+AT22 -> 0.56254278 | BC23: =BC22+AY22+AU22 -> 0.8641556 | BD23: =BD22+AZ22+AV22 -> 0.59598574 | ... CG23: =CG22+CC22+BY22 -> 0.2275 | CP23: n/a | CQ23: n/a | CR23: n/a | CS23: =CS22+CQ22+CR22 -> 0.43271414 | CT23: =CT22+CR22+CS22 -> 0.64226879 | CU23: =CU22+CS22+CT22 -> 0.5826075 | CV23: =CV22+CT22+CU22 -> 0.59945264 | CW23: =CW22+CU22+CV22 -> 0.29977996 | CX23: =CX22+CV22+CW22 -> 0.33522946 | CY23: =CY22+CW22+CX22 -> 0.36866404 | CZ23: =CZ22+CX22+CY22 -> 0.3403871 | ... DC23: =DC22+DA22+DB22 -> 0.24541356
A24: % of Google Advertising | AK24: =AK20/AK$14 -> 0.71714128 | AL24: =AL20/AL$14 -> 0.73714323 | AM24: =AM20/AM$14 -> 0.72758048 | AN24: =AN20/AN$14 -> 0.73206888 | AO24: =AO20/AO$14 -> 0.71663943 | AP24: =AP20/AP$14 -> 0.72570565 | AQ24: =AQ20/AQ$14 -> 0.71379784 | AR24: =AR20/AR$14 -> 0.71001483 | ... CG24: =CG20/CG$14 -> 0.7684962 | CP24: =CP20/CP$14 -> 0.7319633 | CQ24: =CQ20/CQ$14 -> 0.73403843 | CR24: =CR20/CR$14 -> 0.72779669 | CS24: =CS20/CS$14 -> 0.70827094 | CT24: =CT20/CT$14 -> 0.71099347 | CU24: =CU20/CU$14 -> 0.72369505 | CV24: =CV20/CV$14 -> 0.7358811 | CW24: =CW20/CW$14 -> 0.74864507 | ... DC24: =DC20/DC$14 -> 0.77831563
A25: % of Google Segment Revs (Gross) | AK25: =AK20/AK$3 -> 0.59797938 | AL25: =AL20/AL$3 -> 0.62574933 | AM25: =AM20/AM$3 -> 0.6113151 | AN25: =AN20/AN$3 -> 0.61506526 | AO25: =AO20/AO$3 -> 0.59340348 | AP25: =AP20/AP$3 -> 0.59797437 | AQ25: =AQ20/AQ$3 -> 0.56105585 | AR25: =AR20/AR$3 -> 0.5723537 | ... CG25: =CG20/CG$3 -> 0.47418703 | CP25: =CP20/CP$3 -> 0.63247205 | CQ25: =CQ20/CQ$3 -> 0.62671565 | CR25: =CR20/CR$3 -> 0.61038428 | CS25: =CS20/CS$3 -> 0.57273218 | CT25: =CT20/CT$3 -> 0.58017411 | CU25: =CU20/CU$3 -> 0.58057668 | CV25: =CV20/CV$3 -> 0.57269387 | CW25: =CW20/CW$3 -> 0.56894695 | ... DC25: =DC20/DC$3 -> 0.48246871
AZ26: =AZ22-AY22 -> -0.092607207 | BA26: =BA22-AZ22 -> -0.058626816 | BB26: =BB22-BA22 -> 0.034800246 | BC26: =BC22-BB22 -> 0.028950538 | BD26: =BD22-BC22 -> 0.065828733 | BE26: =BE22-BD22 -> 0.013641323 | BF26: =BF22-BE22 -> 0.016511654 | BG26: =BG22-BF22 -> -0.0056749035 | ... BQ26: =BQ22-BP22 -> -0.005
A27: YouTube Ads | AK27: 3605 | AL27: 3025 | AM27: 3603 | AN27: 3804 | AO27: 4717 | AP27: 4038 | AQ27: 3812 | AR27: 5037 | AS27: 6885 | AT27: 6005 | AU27: 7002 | AV27: 7205 | AW27: 8633 | AX27: 6869 | AY27: 7340 | AZ27: 7071 | BA27: 7963 | BB27: 6693 | BC27: 7665 | BD27: 7952 | BE27: 9200 | BF27: 8090 | BG27: 8663 | BH27: 8921 | BI27: 10473 | BJ27: 8927 | BK27: 9796 | BL27: 10261 | BM27: =BI27*(1+BM29) -> 11834.49 | BN27: =BJ27*(1+BN29) -> 10132.145 | BO27: =BK27*(1+BO29) -> 10873.56 | BP27: =BL27*(1+BP29) -> 11492.32 | BQ27: =BM27*(1+BQ29) -> 13491.319 | BR27: =BN27*(1+BR29) -> 11398.663 | BS27: =BO27*(1+BS29) -> 12232.755 | BT27: =BP27*(1+BT29) -> 12928.86 | ... CG27: =CC27*(1+CG29) -> 20755.854 | CP27: 8150 | CQ27: 11115 | CR27: =SUM(AL27:AO27) -> 15149 | CS27: =SUM(AP27:AS27) -> 19772 | CT27: =SUM(AT27:AW27) -> 28845 | CU27: =SUM(AX27:BA27) -> 29243 | CV27: =SUM(BB27:BE27) -> 31510 | CW27: =SUM(BF27:BI27) -> 36147 | CX27: =SUM(BJ27:BM27) -> 40818.49 | CY27: =SUM(BN27:BQ27) -> 45989.344 | CZ27: =SUM(BR27:BU27) -> 51738.012 | DA27: =SUM(BV27:BY27) -> 57946.573 | DB27: =SUM(BZ27:CC27) -> 64320.696 | DC27: =SUM(CD27:CG27) -> 70752.766
A28: QoQ Growth | AK28: n/a | AL28: =IF(AND(AK27<0,AL27>0),"n/a",AL27/AK27-1) -> -0.16088766 | AM28: =IF(AND(AL27<0,AM27>0),"n/a",AM27/AL27-1) -> 0.19107438 | AN28: =IF(AND(AM27<0,AN27>0),"n/a",AN27/AM27-1) -> 0.055786844 | AO28: =IF(AND(AN27<0,AO27>0),"n/a",AO27/AN27-1) -> 0.24001052 | AP28: =IF(AND(AO27<0,AP27>0),"n/a",AP27/AO27-1) -> -0.14394742 | AQ28: =IF(AND(AP27<0,AQ27>0),"n/a",AQ27/AP27-1) -> -0.055968301 | AR28: =IF(AND(AQ27<0,AR27>0),"n/a",AR27/AQ27-1) -> 0.32135362 | AS28: =IF(AND(AR27<0,AS27>0),"n/a",AS27/AR27-1) -> 0.36688505 | ... CG28: =IF(AND(CF27<0,CG27>0),"n/a",CG27/CF27-1) -> 0.17394213 | CP28: n/a | CQ28: n/a | CR28: n/a | CS28: n/a | CT28: n/a | CU28: n/a | CV28: n/a | CW28: n/a | CX28: n/a | CY28: n/a | CZ28: n/a | DA28: n/a | DB28: n/a | DC28: n/a
A29: YoY Growth | AK29: n/a | AL29: n/a | AM29: n/a | AN29: n/a | AO29: =IF(AND(AK27<0,AO27>0),"n/a",AO27/AK27-1) -> 0.30846047 | AP29: =IF(AND(AL27<0,AP27>0),"n/a",AP27/AL27-1) -> 0.33487603 | AQ29: =IF(AND(AM27<0,AQ27>0),"n/a",AQ27/AM27-1) -> 0.058007216 | AR29: =IF(AND(AN27<0,AR27>0),"n/a",AR27/AN27-1) -> 0.32413249 | AS29: =IF(AND(AO27<0,AS27>0),"n/a",AS27/AO27-1) -> 0.45961416 | AT29: =IF(AND(AP27<0,AT27>0),"n/a",AT27/AP27-1) -> 0.48712234 | AU29: =IF(AND(AQ27<0,AU27>0),"n/a",AU27/AQ27-1) -> 0.83683106 | AV29: =IF(AND(AR27<0,AV27>0),"n/a",AV27/AR27-1) -> 0.43041493 | ... BL29: =IF(AND(BH27<0,BL27>0),"n/a",BL27/BH27-1) -> 0.15020738 | BM29: 0.13 | BN29: 0.135 | BO29: 0.11 | BP29: 0.12 | BQ29: 0.14 | BR29: 0.125 | BS29: 0.125 | BT29: 0.125 | BU29: 0.125 | BV29: 0.12 | BW29: 0.12 | BX29: 0.12 | BY29: 0.12 | BZ29: 0.11 | CA29: 0.11 | CB29: 0.11 | CC29: 0.11 | CD29: 0.1 | CE29: 0.1 | CF29: 0.1 | CG29: 0.1 | CP29: n/a | CQ29: =IF(AND(CP27<0,CQ27>0),"n/a",CQ27/CP27-1) -> 0.36380368 | CR29: =IF(AND(CQ27<0,CR27>0),"n/a",CR27/CQ27-1) -> 0.36293297 | CS29: =IF(AND(CR27<0,CS27>0),"n/a",CS27/CR27-1) -> 0.30516866 | CT29: =IF(AND(CS27<0,CT27>0),"n/a",CT27/CS27-1) -> 0.45888125 | CU29: =IF(AND(CT27<0,CU27>0),"n/a",CU27/CT27-1) -> 0.013797885 | CV29: =IF(AND(CU27<0,CV27>0),"n/a",CV27/CU27-1) -> 0.077522826 | CW29: =IF(AND(CV27<0,CW27>0),"n/a",CW27/CV27-1) -> 0.14715963 | CX29: =IF(AND(CW27<0,CX27>0),"n/a",CX27/CW27-1) -> 0.1292359 | ... DC29: =IF(AND(DB27<0,DC27>0),"n/a",DC27/DB27-1) -> 0.1
A30: 3yr stack | AK30: n/a | AL30: n/a | AM30: n/a | AN30: n/a | AO30: n/a | AP30: n/a | AQ30: n/a | AR30: n/a | AS30: n/a | AT30: n/a | AU30: n/a | AV30: n/a | AW30: =AW29+AS29+AO29 -> 1.0219599 | AX30: =AX29+AT29+AP29 -> 0.96587847 | AY30: =AY29+AU29+AQ29 -> 0.9431102 | AZ30: =AZ29+AV29+AR29 -> 0.73594923 | BA30: =BA29+AW29+AS29 -> 0.63589025 | BB30: =BB29+AX29+AT29 -> 0.60538008 | BC30: =BC29+AY29+AU29 -> 0.92938091 | BD30: =BD29+AZ29+AV29 -> 0.53641014 | ... CG30: =CG29+CC29+BY29 -> 0.33 | CP30: n/a | CQ30: n/a | CR30: n/a | CS30: =CS29+CQ29+CR29 -> 1.0319053 | CT30: =CT29+CR29+CS29 -> 1.1269829 | CU30: =CU29+CS29+CT29 -> 0.77784779 | CV30: =CV29+CT29+CU29 -> 0.55020196 | CW30: =CW29+CU29+CV29 -> 0.23848034 | CX30: =CX29+CV29+CW29 -> 0.35391836 | CY30: =CY29+CW29+CX29 -> 0.40307473 | CZ30: =CZ29+CX29+CY29 -> 0.3809151 | ... DC30: =DC29+DA29+DB29 -> 0.33
A31: % of Google Advertising | AK31: =AK27/AK$14 -> 0.11086168 | AL31: =AL27/AL$14 -> 0.098898225 | AM31: =AM27/AM$14 -> 0.11088201 | AN31: =AN27/AN$14 -> 0.1125577 | AO31: =AO27/AO$14 -> 0.12434755 | AP31: =AP27/AP$14 -> 0.11959838 | AQ31: =AQ27/AQ$14 -> 0.1276325 | AR31: =AR27/AR$14 -> 0.13578649 | ... CG31: =CG27/CG$14 -> 0.17148947 | CP31: =CP27/CP$14 -> 0.085452163 | CQ31: =CQ27/CQ$14 -> 0.095653222 | CR31: =CR27/CR$14 -> 0.11237214 | CS31: =CS27/CS$14 -> 0.13457298 | CT31: =CT27/CT$14 -> 0.13768694 | CU31: =CU27/CU$14 -> 0.13027402 | CV31: =CV27/CV$14 -> 0.13247567 | CW31: =CW27/CW$14 -> 0.13661514 | ... DC31: =DC27/DC$14 -> 0.15909326
A32: % of Google Segment Revs (Gross) | AK32: =AK27/AK$3 -> 0.092440638 | AL32: =AL27/AL$3 -> 0.083953153 | AM32: =AM27/AM$3 -> 0.093163366 | AN32: =AN27/AN$3 -> 0.094568055 | AO32: =AO27/AO$3 -> 0.10296429 | AP32: =AP27/AP$3 -> 0.098547895 | AQ32: =AQ27/AQ$3 -> 0.10032107 | AR32: =AR27/AR$3 -> 0.10945955 | ... CG32: =CG27/CG$3 -> 0.10581456 | CP32: =CP27/CP$3 -> 0.073837178 | CQ32: =CQ27/CQ$3 -> 0.081667891 | CR32: =CR27/CR$3 -> 0.094243606 | CS32: =CS27/CS$3 -> 0.10882032 | CT32: =CT27/CT$3 -> 0.1123532 | CU32: =CU27/CU$3 -> 0.10451095 | CV32: =CV27/CV$3 -> 0.10309818 | CW32: =CW27/CW$3 -> 0.10382325 | ... DC32: =DC27/DC$3 -> 0.09862004
AZ33: =AZ29-AY29 -> -0.066870118 | BA33: =BA29-AZ29 -> -0.059010978 | BB33: =BB29-BA29 -> 0.051986813 | BC33: =BC29-BB29 -> 0.06990029 | BD33: =BD29-BC29 -> 0.080315481 | BE33: =BE29-BD29 -> 0.030750054 | BF33: =BF29-BE29 -> 0.053382071 | BG33: =BG29-BF29 -> -0.078523316 | ... BQ33: =BQ29-BP29 -> 0.02
A34: Google Network Members' Properties | AK34: 5593 | AL34: 5015 | AM34: 5249 | AN34: 5251 | AO34: 6032 | AP34: 5223 | AQ34: 4736 | AR34: 5720 | AS34: 7411 | AT34: 6800 | AU34: 7597 | AV34: 7999 | AW34: 9305 | AX34: 8174 | AY34: 8259 | AZ34: 7872 | BA34: 8475 | BB34: 7496 | BC34: 7850 | BD34: 7669 | BE34: 8297 | BF34: 7413 | BG34: 7444 | BH34: 7548 | BI34: 7954 | BJ34: 7256 | BK34: 7354 | BL34: 7354 | BM34: =BI34*(1+BM36) -> 7755.15 | BN34: =BJ34*(1+BN36) -> 7110.88 | BO34: =BK34*(1+BO36) -> 7206.92 | BP34: =BL34*(1+BP36) -> 7206.92 | BQ34: =BM34*(1+BQ36) -> 7600.047 | BR34: =BN34*(1+BR36) -> 7004.2168 | BS34: =BO34*(1+BS36) -> 7098.8162 | BT34: =BP34*(1+BT36) -> 7098.8162 | ... CG34: =CC34*(1+CG36) -> 7263.7032 | CP34: 17616 | CQ34: 20010 | CR34: =SUM(AL34:AO34) -> 21547 | CS34: =SUM(AP34:AS34) -> 23090 | CT34: =SUM(AT34:AW34) -> 31701 | CU34: =SUM(AX34:BA34) -> 32780 | CV34: =SUM(BB34:BE34) -> 31312 | CW34: =SUM(BF34:BI34) -> 30359 | CX34: =SUM(BJ34:BM34) -> 29719.15 | CY34: =SUM(BN34:BQ34) -> 29124.767 | CZ34: =SUM(BR34:BU34) -> 28687.895 | DA34: =SUM(BV34:BY34) -> 28401.017 | DB34: =SUM(BZ34:CC34) -> 28117.006 | DC34: =SUM(CD34:CG34) -> 27835.836
A35: QoQ Growth | AK35: n/a | AL35: =IF(AND(AK34<0,AL34>0),"n/a",AL34/AK34-1) -> -0.10334347 | AM35: =IF(AND(AL34<0,AM34>0),"n/a",AM34/AL34-1) -> 0.04666002 | AN35: =IF(AND(AM34<0,AN34>0),"n/a",AN34/AM34-1) -> 0.00038102496 | AO35: =IF(AND(AN34<0,AO34>0),"n/a",AO34/AN34-1) -> 0.14873357 | AP35: =IF(AND(AO34<0,AP34>0),"n/a",AP34/AO34-1) -> -0.13411804 | AQ35: =IF(AND(AP34<0,AQ34>0),"n/a",AQ34/AP34-1) -> -0.093241432 | AR35: =IF(AND(AQ34<0,AR34>0),"n/a",AR34/AQ34-1) -> 0.20777027 | AS35: =IF(AND(AR34<0,AS34>0),"n/a",AS34/AR34-1) -> 0.29562937 | ... CG35: =IF(AND(CF34<0,CG34>0),"n/a",CG34/CF34-1) -> 0.054548545 | CP35: n/a | CQ35: n/a | CR35: n/a | CS35: n/a | CT35: n/a | CU35: n/a | CV35: n/a | CW35: n/a | CX35: n/a | CY35: n/a | CZ35: n/a | DA35: n/a | DB35: n/a | DC35: n/a
A36: YoY Growth | AK36: n/a | AL36: n/a | AM36: n/a | AN36: n/a | AO36: =IF(AND(AK34<0,AO34>0),"n/a",AO34/AK34-1) -> 0.078490971 | AP36: =IF(AND(AL34<0,AP34>0),"n/a",AP34/AL34-1) -> 0.041475573 | AQ36: =IF(AND(AM34<0,AQ34>0),"n/a",AQ34/AM34-1) -> -0.097732902 | AR36: =IF(AND(AN34<0,AR34>0),"n/a",AR34/AN34-1) -> 0.089316321 | AS36: =IF(AND(AO34<0,AS34>0),"n/a",AS34/AO34-1) -> 0.22861406 | AT36: =IF(AND(AP34<0,AT34>0),"n/a",AT34/AP34-1) -> 0.30193375 | AU36: =IF(AND(AQ34<0,AU34>0),"n/a",AU34/AQ34-1) -> 0.60409628 | AV36: =IF(AND(AR34<0,AV34>0),"n/a",AV34/AR34-1) -> 0.39842657 | ... BL36: =IF(AND(BH34<0,BL34>0),"n/a",BL34/BH34-1) -> -0.025702173 | BM36: -0.025 | BN36: -0.02 | BO36: -0.02 | BP36: -0.02 | BQ36: -0.02 | BR36: -0.015 | BS36: -0.015 | BT36: -0.015 | BU36: -0.015 | BV36: -0.01 | BW36: -0.01 | BX36: -0.01 | BY36: -0.01 | BZ36: -0.01 | CA36: -0.01 | CB36: -0.01 | CC36: -0.01 | CD36: -0.01 | CE36: -0.01 | CF36: -0.01 | CG36: -0.01 | CP36: n/a | CQ36: =IF(AND(CP34<0,CQ34>0),"n/a",CQ34/CP34-1) -> 0.13589918 | CR36: =IF(AND(CQ34<0,CR34>0),"n/a",CR34/CQ34-1) -> 0.076811594 | CS36: =IF(AND(CR34<0,CS34>0),"n/a",CS34/CR34-1) -> 0.071610897 | CT36: =IF(AND(CS34<0,CT34>0),"n/a",CT34/CS34-1) -> 0.37293201 | CU36: =IF(AND(CT34<0,CU34>0),"n/a",CU34/CT34-1) -> 0.034036781 | CV36: =IF(AND(CU34<0,CV34>0),"n/a",CV34/CU34-1) -> -0.044783405 | CW36: =IF(AND(CV34<0,CW34>0),"n/a",CW34/CV34-1) -> -0.030435616 | CX36: =IF(AND(CW34<0,CX34>0),"n/a",CX34/CW34-1) -> -0.021076122 | ... DC36: =IF(AND(DB34<0,DC34>0),"n/a",DC34/DB34-1) -> -0.01
A37: 3yr stack | AK37: n/a | AL37: n/a | AM37: n/a | AN37: n/a | AO37: n/a | AP37: n/a | AQ37: n/a | AR37: n/a | AS37: n/a | AT37: n/a | AU37: n/a | AV37: n/a | AW37: =AW36+AS36+AO36 -> 0.56267108 | AX37: =AX36+AT36+AP36 -> 0.54546815 | AY37: =AY36+AU36+AQ36 -> 0.59350304 | AZ37: =AZ36+AV36+AR36 -> 0.47186591 | BA37: =BA36+AW36+AS36 -> 0.39498075 | BB37: =BB36+AX36+AT36 -> 0.42104665 | BC37: =BC36+AY36+AU36 -> 0.64171421 | BD37: =BD36+AZ36+AV36 -> 0.35676199 | ... CG37: =CG36+CC36+BY36 -> -0.03 | CP37: n/a | CQ37: n/a | CR37: n/a | CS37: =CS36+CQ36+CR36 -> 0.28432167 | CT37: =CT36+CR36+CS36 -> 0.5213545 | CU37: =CU36+CS36+CT36 -> 0.47857968 | CV37: =CV36+CT36+CU36 -> 0.36218538 | CW37: =CW36+CU36+CV36 -> -0.041182239 | CX37: =CX36+CV36+CW36 -> -0.096295143 | CY37: =CY36+CW36+CX36 -> -0.071511738 | CZ37: =CZ36+CX36+CY36 -> -0.056076122 | ... DC37: =DC36+DA36+DB36 -> -0.03
A38: % of Google Advertising | AK38: =AK34/AK$14 -> 0.17199705 | AL38: =AL34/AL$14 -> 0.16395854 | AM38: =AM34/AM$14 -> 0.16153751 | AN38: =AN34/AN$14 -> 0.15537342 | AO38: =AO34/AO$14 -> 0.15901302 | AP38: =AP34/AP$14 -> 0.15469597 | AQ38: =AQ34/AQ$14 -> 0.15856966 | AR38: =AR34/AR$14 -> 0.15419868 | ... CG38: =CG34/CG$14 -> 0.060014329 | CP38: =CP34/CP$14 -> 0.18470249 | CQ38: =CQ34/CQ$14 -> 0.17220162 | CR38: =CR34/CR$14 -> 0.15983117 | CS38: =CS34/CS$14 -> 0.15715608 | CT38: =CT34/CT$14 -> 0.15131959 | CU38: =CU34/CU$14 -> 0.14603093 | CV38: =CV34/CV$14 -> 0.13164323 | CW38: =CW34/CW$14 -> 0.11473979 | ... DC38: =DC34/DC$14 -> 0.062591107
A39: % of Google Segment Revs (Gross) | AK39: =AK34/AK$3 -> 0.14341761 | AL39: =AL34/AL$3 -> 0.13918184 | AM39: =AM34/AM$3 -> 0.13572426 | AN39: =AN34/AN$3 -> 0.13054071 | AO39: =AO34/AO$3 -> 0.13166856 | AP39: =AP34/AP$3 -> 0.12746797 | AQ39: =AQ34/AQ$3 -> 0.12463814 | AR39: =AR34/AR$3 -> 0.12430189 | ... CG39: =CG34/CG$3 -> 0.037030784 | CP39: =CP34/CP$3 -> 0.15959702 | CQ39: =CQ34/CQ$3 -> 0.14702425 | CR39: =CR34/CR$3 -> 0.13404627 | CS39: =CS34/CS$3 -> 0.1270818 | CT39: =CT34/CT$3 -> 0.12347752 | CU39: =CU34/CU$3 -> 0.11715176 | CV39: =CV34/CV$3 -> 0.10245034 | CW39: =CW34/CW$3 -> 0.087198665 | ... DC39: =DC34/DC$3 -> 0.038799491
AZ40: =AZ36-AY36 -> -0.10301665 | BA40: =BA36-AZ36 -> -0.073322371 | BB40: =BB36-BA36 -> 0.0062534291 | BC40: =BC36-BB36 -> 0.033424192 | BD40: =BD36-BC36 -> 0.023734132 | BE40: =BE36-BD36 -> 0.0047846518 | BF40: =BF36-BE36 -> 0.0099303778 | BG40: =BG36-BF36 -> -0.040647173 | ... BQ40: =BQ36-BP36 -> 0
A41: Google Subscriptions, Platforms & Devices | AK41: 4771 | AL41: 3620 | AM41: 4080 | AN41: 4050 | AO41: 5264 | AP41: 4435 | AQ41: 5124 | AR41: 5478 | AS41: 6674 | AT41: 6494 | AU41: 6623 | AV41: 6754 | AW41: 8161 | AX41: 6811 | AY41: 6553 | AZ41: 6895 | BA41: 8796 | BB41: 7413 | BC41: 8142 | BD41: 8339 | BE41: 10794 | BF41: 8739 | BG41: 9312 | BH41: 10656 | BI41: 11633 | BJ41: 10379 | BK41: 11203 | BL41: 12870 | BM41: =BI41*(1+BM43) -> 13813.518 | BN41: =BJ41*(1+BN43) -> 11839.883 | BO41: =BK41*(1+BO43) -> 12733.44 | BP41: =BL41*(1+BP43) -> 14467.477 | BQ41: =BM41*(1+BQ43) -> 15447.581 | BR41: =BN41*(1+BR43) -> 13321.824 | BS41: =BO41*(1+BS43) -> 14327.222 | BT41: =BP41*(1+BT43) -> 16278.301 | ... CG41: =CC41*(1+CG43) -> 24928.319 | CP41: 10914 | CQ41: 14063 | CR41: =SUM(AL41:AO41) -> 17014 | CS41: =SUM(AP41:AS41) -> 21711 | CT41: =SUM(AT41:AW41) -> 28032 | CU41: =SUM(AX41:BA41) -> 29055 | CV41: =SUM(BB41:BE41) -> 34688 | CW41: =SUM(BF41:BI41) -> 40340 | CX41: =SUM(BJ41:BM41) -> 48265.518 | CY41: =SUM(BN41:BQ41) -> 54488.381 | CZ41: =SUM(BR41:BU41) -> 61308.425 | DA41: =SUM(BV41:BY41) -> 69636.711 | DB41: =SUM(BZ41:CC41) -> 78488.149 | DC41: =SUM(CD41:CG41) -> 87929.868
A42: QoQ Growth | AK42: n/a | AL42: =IF(AND(AK41<0,AL41>0),"n/a",AL41/AK41-1) -> -0.24124921 | AM42: =IF(AND(AL41<0,AM41>0),"n/a",AM41/AL41-1) -> 0.12707182 | AN42: =IF(AND(AM41<0,AN41>0),"n/a",AN41/AM41-1) -> -0.0073529412 | AO42: =IF(AND(AN41<0,AO41>0),"n/a",AO41/AN41-1) -> 0.29975309 | AP42: =IF(AND(AO41<0,AP41>0),"n/a",AP41/AO41-1) -> -0.1574848 | AQ42: =IF(AND(AP41<0,AQ41>0),"n/a",AQ41/AP41-1) -> 0.15535513 | AR42: =IF(AND(AQ41<0,AR41>0),"n/a",AR41/AQ41-1) -> 0.069086651 | AS42: =IF(AND(AR41<0,AS41>0),"n/a",AS41/AR41-1) -> 0.21832786 | ... CG42: =IF(AND(CF41<0,CG41>0),"n/a",CG41/CF41-1) -> 0.06774528 | CP42: n/a | CQ42: n/a | CR42: n/a | CS42: n/a | CT42: n/a | CU42: n/a | CV42: n/a | CW42: n/a | CX42: n/a | CY42: n/a | CZ42: n/a | DA42: n/a | DB42: n/a | DC42: n/a
A43: YoY Growth | AK43: n/a | AL43: n/a | AM43: n/a | AN43: n/a | AO43: =IF(AND(AK41<0,AO41>0),"n/a",AO41/AK41-1) -> 0.10333263 | AP43: =IF(AND(AL41<0,AP41>0),"n/a",AP41/AL41-1) -> 0.22513812 | AQ43: =IF(AND(AM41<0,AQ41>0),"n/a",AQ41/AM41-1) -> 0.25588235 | AR43: =IF(AND(AN41<0,AR41>0),"n/a",AR41/AN41-1) -> 0.35259259 | AS43: =IF(AND(AO41<0,AS41>0),"n/a",AS41/AO41-1) -> 0.26785714 | AT43: =IF(AND(AP41<0,AT41>0),"n/a",AT41/AP41-1) -> 0.46426156 | AU43: =IF(AND(AQ41<0,AU41>0),"n/a",AU41/AQ41-1) -> 0.29254489 | AV43: =IF(AND(AR41<0,AV41>0),"n/a",AV41/AR41-1) -> 0.23293173 | ... BL43: =IF(AND(BH41<0,BL41>0),"n/a",BL41/BH41-1) -> 0.20777027 | BM43: 0.18744243 | BN43: 0.14075377 | BO43: 0.13660981 | BP43: 0.12412412 | BQ43: 0.11829448 | BR43: 0.1251651 | BS43: 0.1251651 | BT43: 0.1251651 | BU43: 0.1251651 | BV43: 0.13584245 | BW43: 0.13584245 | BX43: 0.13584245 | BY43: 0.13584245 | BZ43: 0.12710879 | CA43: 0.12710879 | CB43: 0.12710879 | CC43: 0.12710879 | CD43: 0.12029484 | CE43: 0.12029484 | CF43: 0.12029484 | CG43: 0.12029484 | CP43: n/a | CQ43: =IF(AND(CP41<0,CQ41>0),"n/a",CQ41/CP41-1) -> 0.2885285 | CR43: =IF(AND(CQ41<0,CR41>0),"n/a",CR41/CQ41-1) -> 0.20984143 | CS43: =IF(AND(CR41<0,CS41>0),"n/a",CS41/CR41-1) -> 0.27606677 | CT43: =IF(AND(CS41<0,CT41>0),"n/a",CT41/CS41-1) -> 0.29114274 | CU43: =IF(AND(CT41<0,CU41>0),"n/a",CU41/CT41-1) -> 0.036494007 | CV43: =IF(AND(CU41<0,CV41>0),"n/a",CV41/CU41-1) -> 0.19387369 | CW43: =IF(AND(CV41<0,CW41>0),"n/a",CW41/CV41-1) -> 0.16293819 | CX43: =IF(AND(CW41<0,CX41>0),"n/a",CX41/CW41-1) -> 0.19646797 | ... DC43: =IF(AND(DB41<0,DC41>0),"n/a",DC41/DB41-1) -> 0.12029484
A44: % of Google Services | AK44: =AK41/AK$8 -> 0.12794658 | AL44: =AL41/AL$8 -> 0.10582629 | AM44: =AM41/AM$8 -> 0.11155466 | AN44: =AN41/AN$8 -> 0.10701263 | AO44: =AO41/AO$8 -> 0.12185749 | AP44: =AP41/AP$8 -> 0.11610556 | AQ44: =AQ41/AQ$8 -> 0.14643766 | AR44: =AR41/AR$8 -> 0.1286731 | ... CG44: =CG41/CG$8 -> 0.17078737 | CP44: n/a | CQ44: =CQ41/CQ$8 -> 0.10774264 | CR44: =CR41/CR$8 -> 0.11206323 | CS44: =CS41/CS$8 -> 0.12874552 | CT44: =CT41/CT$8 -> 0.11801506 | CU44: =CU41/CU$8 -> 0.11460273 | CV44: =CV41/CV$8 -> 0.12727533 | CW44: =CW41/CW$8 -> 0.13229266 | CX44: =CX41/CX$8 -> 0.14118466 | ... DC44: =DC41/DC$8 -> 0.16507847
A45: % of Google Segment Revs (Gross) | AK45: =AK41/AK$3 -> 0.12233961 | AL45: =AL41/AL$3 -> 0.10046625 | AM45: =AM41/AM$3 -> 0.10549723 | AN45: =AN41/AN$3 -> 0.10068365 | AO45: =AO41/AO$3 -> 0.11490439 | AP45: =AP41/AP$3 -> 0.10823673 | AQ45: =AQ41/AQ$3 -> 0.1348492 | AR45: =AR41/AR$3 -> 0.11904296 | ... CG45: =CG41/CG$3 -> 0.12708603 | CP45: =CP41/CP$3 -> 0.0988784 | CQ45: =CQ41/CQ$3 -> 0.10332843 | CR45: =CR41/CR$3 -> 0.10584598 | CS45: =CS41/CS$3 -> 0.11949211 | CT45: =CT41/CT$3 -> 0.10918652 | CU45: =CU41/CU$3 -> 0.10383906 | CV45: =CV41/CV$3 -> 0.11349634 | CW45: =CW41/CW$3 -> 0.1158666 | ... DC45: =DC41/DC$3 -> 0.12256266
A47: Google Cloud | AK47: 1709 | AL47: 1825 | AM47: 2100 | AN47: 2379 | AO47: 2614 | AP47: 2777 | AQ47: 3007 | AR47: 3444 | AS47: 3831 | AT47: 4047 | AU47: 4628 | AV47: 4990 | AW47: 5541 | AX47: 5821 | AY47: 6276 | AZ47: 6868 | BA47: 7315 | BB47: 7454 | BC47: 8031 | BD47: 8411 | BE47: 9192 | BF47: 9574 | BG47: 10347 | BH47: 11353 | BI47: 11955 | BJ47: 12260 | BK47: 13624 | BL47: 15157 | BM47: =BI47*(1+BM49) -> 16737 | BN47: =BJ47*(1+BN49) -> 17409.2 | BO47: =BK47*(1+BO49) -> 18528.64 | BP47: =BL47*(1+BP49) -> 20158.81 | BQ47: =BM47*(1+BQ49) -> 20921.25 | BR47: =BN47*(1+BR49) -> 22457.868 | BS47: =BO47*(1+BS49) -> 23901.946 | BT47: =BP47*(1+BT49) -> 26004.865 | ... CG47: =CC47*(1+CG49) -> 50191.97 | CP47: 4056 | CQ47: 5838 | CR47: =SUM(AL47:AO47) -> 8918 | CS47: =SUM(AP47:AS47) -> 13059 | CT47: =SUM(AT47:AW47) -> 19206 | CU47: =SUM(AX47:BA47) -> 26280 | CV47: =SUM(BB47:BE47) -> 33088 | CW47: =SUM(BF47:BI47) -> 43229 | CX47: =SUM(BJ47:BM47) -> 57778 | CY47: =SUM(BN47:BQ47) -> 77017.9 | CZ47: =SUM(BR47:BU47) -> 99353.091 | DA47: =SUM(BV47:BY47) -> 125184.89 | DB47: =SUM(BZ47:CC47) -> 153977.42 | DC47: =SUM(CD47:CG47) -> 184772.9
A48: QoQ Growth | AK48: n/a | AL48: =IF(AND(AK47<0,AL47>0),"n/a",AL47/AK47-1) -> 0.067875951 | AM48: =IF(AND(AL47<0,AM47>0),"n/a",AM47/AL47-1) -> 0.15068493 | AN48: =IF(AND(AM47<0,AN47>0),"n/a",AN47/AM47-1) -> 0.13285714 | AO48: =IF(AND(AN47<0,AO47>0),"n/a",AO47/AN47-1) -> 0.098781 | AP48: =IF(AND(AO47<0,AP47>0),"n/a",AP47/AO47-1) -> 0.062356542 | AQ48: =IF(AND(AP47<0,AQ47>0),"n/a",AQ47/AP47-1) -> 0.08282319 | AR48: =IF(AND(AQ47<0,AR47>0),"n/a",AR47/AQ47-1) -> 0.14532757 | AS48: =IF(AND(AR47<0,AS47>0),"n/a",AS47/AR47-1) -> 0.11236934 | ... CG48: =IF(AND(CF47<0,CG47>0),"n/a",CG47/CF47-1) -> 0.037821677 | CP48: n/a | CQ48: n/a | CR48: n/a | CS48: n/a | CT48: n/a | CU48: n/a | CV48: n/a | CW48: n/a | CX48: n/a | CY48: n/a | CZ48: n/a | DA48: n/a | DB48: n/a | DC48: n/a
A49: YoY Growth | AK49: n/a | AL49: n/a | AM49: n/a | AN49: n/a | AO49: =IF(AND(AK47<0,AO47>0),"n/a",AO47/AK47-1) -> 0.52954944 | AP49: =IF(AND(AL47<0,AP47>0),"n/a",AP47/AL47-1) -> 0.52164384 | AQ49: =IF(AND(AM47<0,AQ47>0),"n/a",AQ47/AM47-1) -> 0.43190476 | AR49: =IF(AND(AN47<0,AR47>0),"n/a",AR47/AN47-1) -> 0.44766709 | AS49: =IF(AND(AO47<0,AS47>0),"n/a",AS47/AO47-1) -> 0.46557001 | AT49: =IF(AND(AP47<0,AT47>0),"n/a",AT47/AP47-1) -> 0.45732805 | AU49: =IF(AND(AQ47<0,AU47>0),"n/a",AU47/AQ47-1) -> 0.53907549 | AV49: =IF(AND(AR47<0,AV47>0),"n/a",AV47/AR47-1) -> 0.44889663 | ... BL49: =IF(AND(BH47<0,BL47>0),"n/a",BL47/BH47-1) -> 0.33506562 | BM49: 0.4 | BN49: 0.42 | BO49: 0.36 | BP49: 0.33 | BQ49: 0.25 | BR49: 0.29 | BS49: 0.29 | BT49: 0.29 | BU49: 0.29 | BV49: =BR49-0.03 -> 0.26 | BW49: =BS49-0.03 -> 0.26 | BX49: =BT49-0.03 -> 0.26 | BY49: =BU49-0.03 -> 0.26 | BZ49: =BV49-0.03 -> 0.23 | CA49: =BW49-0.03 -> 0.23 | CB49: =BX49-0.03 -> 0.23 | CC49: =BY49-0.03 -> 0.23 | ... CG49: =CC49-0.03 -> 0.2 | CP49: n/a | CQ49: =IF(AND(CP47<0,CQ47>0),"n/a",CQ47/CP47-1) -> 0.43934911 | CR49: =IF(AND(CQ47<0,CR47>0),"n/a",CR47/CQ47-1) -> 0.52757794 | CS49: =IF(AND(CR47<0,CS47>0),"n/a",CS47/CR47-1) -> 0.46434178 | CT49: =IF(AND(CS47<0,CT47>0),"n/a",CT47/CS47-1) -> 0.47070986 | CU49: =IF(AND(CT47<0,CU47>0),"n/a",CU47/CT47-1) -> 0.3683224 | CV49: =IF(AND(CU47<0,CV47>0),"n/a",CV47/CU47-1) -> 0.25905632 | CW49: =IF(AND(CV47<0,CW47>0),"n/a",CW47/CV47-1) -> 0.30648574 | CX49: =IF(AND(CW47<0,CX47>0),"n/a",CX47/CW47-1) -> 0.33655648 | ... DC49: =IF(AND(DB47<0,DC47>0),"n/a",DC47/DB47-1) -> 0.2
A50: % of Google Segment Revs (Gross) | AK50: =AK47/AK$3 -> 0.04382276 | AL50: =AL47/AL$3 -> 0.050649423 | AM50: =AM47/AM$3 -> 0.054300047 | AN50: =AN47/AN$3 -> 0.059142324 | AO50: =AO47/AO$3 -> 0.057059286 | AP50: =AP47/AP$3 -> 0.067773032 | AQ50: =AQ47/AQ$3 -> 0.079135744 | AR50: =AR47/AR$3 -> 0.074841906 | ... CG50: =CG47/CG$3 -> 0.2558816 | CP50: =CP47/CP$3 -> 0.036746453 | CQ50: =CQ47/CQ$3 -> 0.04289493 | CR50: =CR47/CR$3 -> 0.055479865 | CS50: =CS47/CS$3 -> 0.07187359 | CT50: =CT47/CT$3 -> 0.074808655 | CU50: =CU47/CU$3 -> 0.093921546 | CV50: =CV47/CV$3 -> 0.10826127 | CW50: =CW47/CW$3 -> 0.12416453 | ... DC50: =DC47/DC$3 -> 0.2575491
A51: % of Consolidated Gross Revenues | AK51: =AK47/AK$64 -> 0.043512578 | AL51: =AL47/AL$64 -> 0.050221525 | AM51: =AM47/AM$64 -> 0.053923583 | AN51: =AN47/AN$64 -> 0.058742191 | AO51: =AO47/AO$64 -> 0.056733587 | AP51: =AP47/AP$64 -> 0.067470055 | AQ51: =AQ47/AQ$64 -> 0.0785179 | AR51: =AR47/AR$64 -> 0.074589046 | ... CG51: =CG47/CG$64 -> 0.25518424 | CP51: =CP47/CP$64 -> 0.036588336 | CQ51: =CQ47/CQ$64 -> 0.042669512 | CR51: =CR47/CR$64 -> 0.055098019 | CS51: =CS47/CS$64 -> 0.07154558 | CT51: =CT47/CT$64 -> 0.074546746 | CU51: =CU47/CU$64 -> 0.092916036 | CV51: =CV47/CV$64 -> 0.10764036 | CW51: =CW47/CW$64 -> 0.12350508 | ... DC51: =DC47/DC$64 -> 0.25682403
AR52: =AR49-AQ49 -> 0.015762325 | AS52: =AS49-AR49 -> 0.017902921 | AT52: =AT49-AS49 -> -0.0082419558 | AU52: =AU49-AT49 -> 0.081747439 | AV52: =AV49-AU49 -> -0.090178859 | AW52: =AW49-AV49 -> -0.0025379787 | AX52: =AX49-AW49 -> -0.0080092585 | AY52: =AY49-AX49 -> -0.08225605 | ... BQ52: =BQ49-BP49 -> -0.08
A53: Other Bets | U53: 106 | V53: 80 | W53: 74 | X53: 142 | Y53: 151 | Z53: 166 | AA53: 185 | AB53: 197 | AC53: 262 | AD53: 132 | AE53: 97 | AF53: 117 | AG53: 131 | AH53: 150 | AI53: 145 | AJ53: 146 | AK53: 154 | AL53: 170 | AM53: 162 | AN53: 155 | AO53: 172 | AP53: 135 | AQ53: 148 | AR53: 178 | AS53: 196 | AT53: 198 | AU53: 192 | AV53: 182 | AW53: 181 | AX53: 440 | AY53: 193 | AZ53: 209 | BA53: 226 | BB53: 288 | BC53: 285 | BD53: 297 | BE53: 657 | BF53: 495 | BG53: 365 | BH53: 388 | BI53: 400 | BJ53: 450 | BK53: 373 | BL53: 344 | BM53: =BI53*(1+BM55) -> 420 | BN53: =BJ53*(1+BN55) -> 472.5 | BO53: =BK53*(1+BO55) -> 391.65 | BP53: =BL53*(1+BP55) -> 361.2 | BQ53: =BM53*(1+BQ55) -> 441 | BR53: =BN53*(1+BR55) -> 496.125 | BS53: =BO53*(1+BS55) -> 411.2325 | BT53: =BP53*(1+BT55) -> 379.26 | ... CG53: =CC53*(1+CG55) -> 536.03826 | CL53: 12 | CM53: 327 | CN53: =SUM(V53:Y53) -> 447 | CO53: =SUM(Z53:AC53) -> 810 | CP53: =SUM(AD53:AG53) -> 477 | CQ53: =SUM(AH53:AK53) -> 595 | CR53: =SUM(AL53:AO53) -> 659 | CS53: =SUM(AP53:AS53) -> 657 | CT53: =SUM(AT53:AW53) -> 753 | CU53: =SUM(AX53:BA53) -> 1068 | CV53: =SUM(BB53:BE53) -> 1527 | CW53: =SUM(BF53:BI53) -> 1648 | CX53: =SUM(BJ53:BM53) -> 1587 | CY53: =SUM(BN53:BQ53) -> 1666.35 | CZ53: =SUM(BR53:BU53) -> 1749.6675 | DA53: =SUM(BV53:BY53) -> 1837.1509 | DB53: =SUM(BZ53:CC53) -> 1929.0084 | DC53: =SUM(CD53:CG53) -> 2025.4588
A54: QoQ Growth | U54: n/a | V54: =IF(AND(U53<0,V53>0),"n/a",V53/U53-1) -> -0.24528302 | W54: =IF(AND(V53<0,W53>0),"n/a",W53/V53-1) -> -0.075 | X54: =IF(AND(W53<0,X53>0),"n/a",X53/W53-1) -> 0.91891892 | Y54: =IF(AND(X53<0,Y53>0),"n/a",Y53/X53-1) -> 0.063380282 | Z54: =IF(AND(Y53<0,Z53>0),"n/a",Z53/Y53-1) -> 0.099337748 | AA54: =IF(AND(Z53<0,AA53>0),"n/a",AA53/Z53-1) -> 0.11445783 | AB54: =IF(AND(AA53<0,AB53>0),"n/a",AB53/AA53-1) -> 0.064864865 | AC54: =IF(AND(AB53<0,AC53>0),"n/a",AC53/AB53-1) -> 0.32994924 | ... CG54: =IF(AND(CF53<0,CG53>0),"n/a",CG53/CF53-1) -> 0.22093023 | CL54: n/a | CM54: n/a | CN54: n/a | CO54: n/a | CP54: n/a | CQ54: n/a | CR54: n/a | CS54: n/a | CT54: n/a | CU54: n/a | CV54: n/a | CW54: n/a | CX54: n/a | CY54: n/a | CZ54: n/a | DA54: n/a | DB54: n/a | DC54: n/a
A55: YoY Growth | U55: n/a | V55: n/a | W55: n/a | X55: n/a | Y55: =IF(AND(U53<0,Y53>0),"n/a",Y53/U53-1) -> 0.4245283 | Z55: =IF(AND(V53<0,Z53>0),"n/a",Z53/V53-1) -> 1.075 | AA55: =IF(AND(W53<0,AA53>0),"n/a",AA53/W53-1) -> 1.5 | AB55: =IF(AND(X53<0,AB53>0),"n/a",AB53/X53-1) -> 0.38732394 | AC55: =IF(AND(Y53<0,AC53>0),"n/a",AC53/Y53-1) -> 0.73509934 | AD55: =IF(AND(Z53<0,AD53>0),"n/a",AD53/Z53-1) -> -0.20481928 | AE55: =IF(AND(AA53<0,AE53>0),"n/a",AE53/AA53-1) -> -0.47567568 | AF55: =IF(AND(AB53<0,AF53>0),"n/a",AF53/AB53-1) -> -0.40609137 | ... BL55: =IF(AND(BH53<0,BL53>0),"n/a",BL53/BH53-1) -> -0.11340206 | BM55: 0.05 | BN55: 0.05 | BO55: 0.05 | BP55: 0.05 | BQ55: 0.05 | BR55: 0.05 | BS55: 0.05 | BT55: 0.05 | BU55: 0.05 | BV55: 0.05 | BW55: 0.05 | BX55: 0.05 | BY55: 0.05 | BZ55: 0.05 | CA55: 0.05 | CB55: 0.05 | CC55: 0.05 | CD55: 0.05 | CE55: 0.05 | CF55: 0.05 | CG55: 0.05 | CL55: n/a | CM55: =IF(AND(CL53<0,CM53>0),"n/a",CM53/CL53-1) -> 26.25 | CN55: =IF(AND(CM53<0,CN53>0),"n/a",CN53/CM53-1) -> 0.36697248 | CO55: =IF(AND(CN53<0,CO53>0),"n/a",CO53/CN53-1) -> 0.81208054 | CP55: =IF(AND(CO53<0,CP53>0),"n/a",CP53/CO53-1) -> -0.41111111 | CQ55: =IF(AND(CP53<0,CQ53>0),"n/a",CQ53/CP53-1) -> 0.24737945 | CR55: =IF(AND(CQ53<0,CR53>0),"n/a",CR53/CQ53-1) -> 0.10756303 | CS55: =IF(AND(CR53<0,CS53>0),"n/a",CS53/CR53-1) -> -0.0030349014 | CT55: =IF(AND(CS53<0,CT53>0),"n/a",CT53/CS53-1) -> 0.14611872 | ... DC55: =IF(AND(DB53<0,DC53>0),"n/a",DC53/DB53-1) -> 0.05
A56: % of Consolidated Gross Revenues | U56: =U53/U$64 -> 0.0058553831 | V56: =V53/V$64 -> 0.0046355313 | W56: =W53/W$64 -> 0.0041744232 | X56: =X53/X$64 -> 0.0076037483 | Y56: =Y53/Y$64 -> 0.007079563 | Z56: =Z53/Z$64 -> 0.0081946981 | AA56: =AA53/AA$64 -> 0.0086046512 | AB56: =AB53/AB$64 -> 0.0087746648 | ... CG56: =CG53/CG$64 -> 0.0027253068 | CL56: =CL53/CL$64 -> 0.00021614222 | CM56: =CM53/CM$64 -> 0.0049544704 | CN56: =CN53/CN$64 -> 0.0059608743 | CO56: =CO53/CO$64 -> 0.008972882 | CP56: =CP53/CP$64 -> 0.0043029182 | CQ56: =CQ53/CQ$64 -> 0.0043488112 | CR56: =CR53/CR$64 -> 0.0040714952 | CS56: =CS53/CS$64 -> 0.0035994675 | ... DC56: =DC53/DC$64 -> 0.0028152748
A57: % of Consolidated Net Revenues | U57: =U53/U$85 -> 0.0073209476 | V57: =V53/V$85 -> 0.005750018 | W57: =W53/W$85 -> 0.0051567944 | X57: =X53/X$85 -> 0.0093983718 | Y57: =Y53/Y$85 -> 0.0087414612 | Z57: =Z53/Z$85 -> 0.010079543 | AA57: =AA53/AA$85 -> 0.010556348 | AB57: =AB53/AB$85 -> 0.010783294 | ... CG57: =CG53/CG$85 -> 0.0030782905 | CL57: =CL53/CL$85 -> 0.0002773861 | CM57: =CM53/CM$85 -> 0.0062280969 | CN57: =CN53/CN$85 -> 0.0073706427 | CO57: =CO53/CO$85 -> 0.011023558 | CP57: =CP53/CP$85 -> 0.005348553 | CQ57: =CQ53/CQ$85 -> 0.0054045216 | CR57: =CR53/CR$85 -> 0.0050012143 | CS57: =CS53/CS$85 -> 0.0043873415 | ... DC57: =DC53/DC$85 -> 0.0031817813
AR58: =AR55-AQ55 -> 0.23480685 | AS58: =AS55-AR55 -> -0.0088522131 | AT58: =AT55-AS55 -> 0.32713178 | AU58: =AU55-AT55 -> -0.16936937 | AV58: =AV55-AU55 -> -0.27482539 | AW58: =AW55-AV55 -> -0.099002522 | AX58: =AX55-AW55 -> 1.2987528 | AY58: =AY55-AX55 -> -1.2170139 | ... BA58: =BA55-AZ55 -> 0.10026714
A59: Hedging Gains (Losses) | AK59: 124 | AL59: 137 | AM59: 108 | AN59: 119 | AO59: 91 | AP59: 49 | AQ59: 151 | AR59: -22 | AS59: -2 | AT59: -109 | AU59: -7 | AV59: 62 | AW59: 203 | AX59: 278 | AY59: 375 | AZ59: 638 | BA59: 669 | BB59: 84 | BC59: 3 | BD59: -1 | BE59: 150 | BF59: 72 | BG59: 102 | BH59: 17 | BI59: 20 | BJ59: 260 | BK59: -112 | BL59: -207 | BM59: 0 | BN59: 0 | BO59: 0 | BP59: 0 | BQ59: 0 | BR59: 0 | BS59: 0 | BT59: 0 | BU59: 0 | BV59: 0 | BW59: 0 | BX59: 0 | BY59: 0 | BZ59: 0 | CA59: 0 | CB59: 0 | CC59: 0 | CD59: 0 | CE59: 0 | CF59: 0 | CG59: 0 | CP59: -169 | CQ59: -138 | CR59: =SUM(AL59:AO59) -> 455 | CS59: =SUM(AP59:AS59) -> 176 | CT59: =SUM(AT59:AW59) -> 149 | CU59: =SUM(AX59:BA59) -> 1960 | CV59: =SUM(BB59:BE59) -> 236 | CW59: =SUM(BF59:BI59) -> 211 | CX59: =SUM(BJ59:BM59) -> -59 | CY59: =SUM(BN59:BQ59) -> 0 | CZ59: =SUM(BR59:BU59) -> 0 | DA59: =SUM(BV59:BY59) -> 0 | DB59: =SUM(BZ59:CC59) -> 0 | DC59: =SUM(CD59:CG59) -> 0
A60: QoQ Growth | AK60: n/a | AL60: =IF(AND(AK59<0,AL59>0),"n/a",AL59/AK59-1) -> 0.10483871 | AM60: =IF(AND(AL59<0,AM59>0),"n/a",AM59/AL59-1) -> -0.21167883 | AN60: =IF(AND(AM59<0,AN59>0),"n/a",AN59/AM59-1) -> 0.10185185 | AO60: =IF(AND(AN59<0,AO59>0),"n/a",AO59/AN59-1) -> -0.23529412 | AP60: =IF(AND(AO59<0,AP59>0),"n/a",AP59/AO59-1) -> -0.46153846 | AQ60: =IF(AND(AP59<0,AQ59>0),"n/a",AQ59/AP59-1) -> 2.0816327 | AR60: =IF(AND(AQ59<0,AR59>0),"n/a",AR59/AQ59-1) -> -1.1456954 | AS60: =IF(AND(AR59<0,AS59>0),"n/a",AS59/AR59-1) -> -0.90909091 | ... BB60: =IF(AND(BA59<0,BB59>0),"n/a",BB59/BA59-1) -> -0.87443946 | BC60: n/a | BD60: n/a | BE60: n/a | BF60: n/a | BG60: n/a | BH60: n/a | BI60: n/a | BJ60: n/a | BK60: n/a | BL60: n/a | BM60: n/a | BN60: n/a | BO60: n/a | BP60: n/a | BQ60: n/a | BR60: n/a | BS60: n/a | BT60: n/a | BU60: n/a | BV60: n/a | BW60: n/a | BX60: n/a | BY60: n/a | BZ60: n/a | CA60: n/a | CB60: n/a | CC60: n/a | CD60: n/a | CE60: n/a | CF60: n/a | CG60: n/a | CP60: n/a | CQ60: n/a | CR60: n/a | CS60: n/a | CT60: n/a | CU60: n/a | CV60: n/a | CW60: n/a | CX60: n/a | CY60: n/a | CZ60: n/a | DA60: n/a | DB60: n/a | DC60: n/a
A61: YoY Growth | AK61: n/a | AL61: n/a | AM61: n/a | AN61: n/a | AO61: =IF(AND(AK59<0,AO59>0),"n/a",AO59/AK59-1) -> -0.26612903 | AP61: =IF(AND(AL59<0,AP59>0),"n/a",AP59/AL59-1) -> -0.64233577 | AQ61: =IF(AND(AM59<0,AQ59>0),"n/a",AQ59/AM59-1) -> 0.39814815 | AR61: =IF(AND(AN59<0,AR59>0),"n/a",AR59/AN59-1) -> -1.1848739 | AS61: =IF(AND(AO59<0,AS59>0),"n/a",AS59/AO59-1) -> -1.021978 | AT61: =IF(AND(AP59<0,AT59>0),"n/a",AT59/AP59-1) -> -3.2244898 | AU61: =IF(AND(AQ59<0,AU59>0),"n/a",AU59/AQ59-1) -> -1.0463576 | AV61: =IF(AND(AR59<0,AV59>0),"n/a",AV59/AR59-1) -> n/a | ... BB61: =IF(AND(AX59<0,BB59>0),"n/a",BB59/AX59-1) -> -0.69784173 | BC61: n/a | BD61: n/a | BE61: n/a | BF61: n/a | BG61: n/a | BH61: n/a | BI61: n/a | BJ61: n/a | BK61: n/a | BL61: n/a | BM61: n/a | BN61: n/a | BO61: n/a | BP61: n/a | BQ61: n/a | BR61: n/a | BS61: n/a | BT61: n/a | BU61: n/a | BV61: n/a | BW61: n/a | BX61: n/a | BY61: n/a | BZ61: n/a | CA61: n/a | CB61: n/a | CC61: n/a | CD61: n/a | CE61: n/a | CF61: n/a | CG61: n/a | CP61: n/a | CQ61: =IF(AND(CP59<0,CQ59>0),"n/a",CQ59/CP59-1) -> -0.18343195 | CR61: =IF(AND(CQ59<0,CR59>0),"n/a",CR59/CQ59-1) -> n/a | CS61: =IF(AND(CR59<0,CS59>0),"n/a",CS59/CR59-1) -> -0.61318681 | CT61: =IF(AND(CS59<0,CT59>0),"n/a",CT59/CS59-1) -> -0.15340909 | CU61: =IF(AND(CT59<0,CU59>0),"n/a",CU59/CT59-1) -> 12.154362 | CV61: =IF(AND(CU59<0,CV59>0),"n/a",CV59/CU59-1) -> -0.87959184 | CW61: =IF(AND(CV59<0,CW59>0),"n/a",CW59/CV59-1) -> -0.1059322 | CX61: =IF(AND(CW59<0,CX59>0),"n/a",CX59/CW59-1) -> -1.2796209 | ... DC61: =IF(AND(DB59<0,DC59>0),"n/a",DC59/DB59-1) -> #DIV/0!
A62: % of Consolidated Gross Revenues | AK62: =AK59/AK$64 -> 0.0031571443 | AL62: =AL59/AL$64 -> 0.0037700542 | AM62: =AM59/AM$64 -> 0.0027732128 | AN62: =AN59/AN$64 -> 0.0029383442 | AO62: =AO59/AO$64 -> 0.0019750407 | AP62: =AP59/AP$64 -> 0.0011905051 | AQ62: =AQ59/AQ$64 -> 0.0039428676 | AR62: =AR59/AR$64 -> -0.00047646893 | ... BB62: =BB59/BB$64 -> 0.0012036626 | BC62: n/a | BD62: n/a | BE62: n/a | BF62: n/a | BG62: n/a | BH62: n/a | BI62: n/a | BJ62: n/a | BK62: n/a | BL62: n/a | BM62: n/a | BN62: n/a | BO62: n/a | BP62: n/a | BQ62: n/a | BR62: n/a | BS62: n/a | BT62: n/a | BU62: n/a | BV62: n/a | BW62: n/a | BX62: n/a | BY62: n/a | BZ62: n/a | CA62: n/a | CB62: n/a | CC62: n/a | CD62: n/a | CE62: n/a | CF62: n/a | CG62: n/a | CP62: =CP59/CP$64 -> -0.001524514 | CQ62: =CQ59/CQ$64 -> -0.0010086318 | CR62: =CR59/CR$64 -> 0.0028111234 | CS62: =CS59/CS$64 -> 0.00096424091 | CT62: =CT59/CT$64 -> 0.00057833308 | CU62: =CU59/CU$64 -> 0.0069298109 | CV62: =CV59/CV$64 -> 0.00076774433 | CW62: =CW59/CW$64 -> 0.00060282614 | ... DC62: =DC59/DC$64 -> 0
A64: Consolidated Revenues (Gross) | B64: =SUM(B3,B53,B59) -> 6775 | C64: =SUM(C3,C53,C59) -> 6820 | D64: =SUM(D3,D53,D59) -> 7286 | E64: =SUM(E3,E53,E59) -> 8440 | F64: =SUM(F3,F53,F59) -> 8575 | G64: =SUM(G3,G53,G59) -> 9026 | H64: =SUM(H3,H53,H59) -> 9720 | I64: =SUM(I3,I53,I59) -> 10584 | ... CG64: =SUM(CG3,CG53,CG59) -> 196689.14 | CI64: =SUM(B64:E64) -> 29321 | CJ64: =SUM(F64:I64) -> 37905 | CK64: =SUM(J64:M64) -> 46040 | CL64: =SUM(N64:Q64) -> 55519 | CM64: =SUM(R64:U64) -> 66001 | CN64: =SUM(V64:Y64) -> 74989 | CO64: =SUM(Z64:AC64) -> 90272 | CP64: =SUM(AD64:AG64) -> 110855 | CQ64: =SUM(AH64:AK64) -> 136819 | CR64: =SUM(AL64:AO64) -> 161857 | CS64: =SUM(AP64:AS64) -> 182527 | CT64: =SUM(AT64:AW64) -> 257637 | CU64: =SUM(AX64:BA64) -> 282836 | CV64: =SUM(BB64:BE64) -> 307394 | CW64: =SUM(BF64:BI64) -> 350018 | CX64: =SUM(BJ64:BM64) -> 401166.92 | CY64: =SUM(BN64:BQ64) -> 456079.88 | CZ64: =SUM(BR64:BU64) -> 516256.56 | DA64: =SUM(BV64:BY64) -> 581291.8 | DB64: =SUM(BZ64:CC64) -> 649270.22 | DC64: =SUM(CD64:CG64) -> 719453.33
A65: QoQ Growth | B65: n/a | C65: =IF(AND(B64<0,C64>0),"n/a",C64/B64-1) -> 0.0066420664 | D65: =IF(AND(C64<0,D64>0),"n/a",D64/C64-1) -> 0.068328446 | E65: =IF(AND(D64<0,E64>0),"n/a",E64/D64-1) -> 0.15838595 | F65: =IF(AND(E64<0,F64>0),"n/a",F64/E64-1) -> 0.015995261 | G65: =IF(AND(F64<0,G64>0),"n/a",G64/F64-1) -> 0.052594752 | H65: =IF(AND(G64<0,H64>0),"n/a",H64/G64-1) -> 0.076888987 | I65: =IF(AND(H64<0,I64>0),"n/a",I64/H64-1) -> 0.088888889 | J65: =IF(AND(I64<0,J64>0),"n/a",J64/I64-1) -> 0.0057634165 | ... CG65: =IF(AND(CF64<0,CG64>0),"n/a",CG64/CF64-1) -> 0.068282531 | CI65: n/a | CJ65: n/a | CK65: n/a | CL65: n/a | CM65: n/a | CN65: n/a | CO65: n/a | CP65: n/a | CQ65: n/a | CR65: n/a | CS65: n/a | CT65: n/a | CU65: n/a | CV65: n/a | CW65: n/a | CX65: n/a | CY65: n/a | CZ65: n/a | DA65: n/a | DB65: n/a | DC65: n/a
A66: YoY Growth | B66: n/a | C66: n/a | D66: n/a | E66: n/a | F66: =IF(AND(B64<0,F64>0),"n/a",F64/B64-1) -> 0.26568266 | G66: =IF(AND(C64<0,G64>0),"n/a",G64/C64-1) -> 0.32346041 | H66: =IF(AND(D64<0,H64>0),"n/a",H64/D64-1) -> 0.33406533 | I66: =IF(AND(E64<0,I64>0),"n/a",I64/E64-1) -> 0.25402844 | J66: =IF(AND(F64<0,J64>0),"n/a",J64/F64-1) -> 0.24139942 | K66: =IF(AND(G64<0,K64>0),"n/a",K64/G64-1) -> 0.21471305 | L66: =IF(AND(H64<0,L64>0),"n/a",L64/H64-1) -> 0.18580247 | M66: =IF(AND(I64<0,M64>0),"n/a",M64/I64-1) -> 0.21929327 | ... CG66: =IF(AND(CC64<0,CG64>0),"n/a",CG64/CC64-1) -> 0.10545094 | CI66: n/a | CJ66: =IF(AND(CI64<0,CJ64>0),"n/a",CJ64/CI64-1) -> 0.29275946 | CK66: =IF(AND(CJ64<0,CK64>0),"n/a",CK64/CJ64-1) -> 0.21461549 | CL66: =IF(AND(CK64<0,CL64>0),"n/a",CL64/CK64-1) -> 0.20588619 | CM66: =IF(AND(CL64<0,CM64>0),"n/a",CM64/CL64-1) -> 0.18880023 | CN66: =IF(AND(CM64<0,CN64>0),"n/a",CN64/CM64-1) -> 0.13617975 | CO66: =IF(AND(CN64<0,CO64>0),"n/a",CO64/CN64-1) -> 0.20380322 | CP66: =IF(AND(CO64<0,CP64>0),"n/a",CP64/CO64-1) -> 0.2280109 | CQ66: =IF(AND(CP64<0,CQ64>0),"n/a",CQ64/CP64-1) -> 0.23421587 | ... DC66: =IF(AND(DB64<0,DC64>0),"n/a",DC64/DB64-1) -> 0.10809538
A68: TAC (Total) | B68: =SUM(B96,B111) -> -1711 | C68: =SUM(C96,C111) -> -1732 | D68: =SUM(D96,D111) -> -1805 | E68: =SUM(E96,E111) -> -2069 | F68: =SUM(F96,F111) -> -2039 | G68: =SUM(G96,G111) -> -2112 | H68: =SUM(H96,H111) -> -2208 | I68: =SUM(I96,I111) -> -2452 | ... AN68: =SUM(AN96,AN111) -> -7490 | AO68: -8501 | AP68: -7452 | AQ68: -6694 | AR68: -8166 | AS68: -10466 | AT68: -9712 | AU68: -10929 | AV68: -11498 | AW68: -13427 | AX68: -11990 | AY68: -12214 | AZ68: -11826 | BA68: -12925 | BB68: -11721 | BC68: -12537 | BD68: -12642 | BE68: -13986 | BF68: -12946 | BG68: -13387 | BH68: -13719 | BI68: -14848 | BJ68: -13748 | BK68: -14705 | BL68: -14876 | BM68: =BM14*BM71 -> -16643.622 | BN68: =BN14*BN71 -> -14708.745 | BO68: =BO14*BO71 -> -15543.656 | BP68: =BP14*BP71 -> -16190.829 | BQ68: =BQ14*BQ71 -> -17714.646 | BR68: =BR14*BR71 -> -15894.816 | BS68: =BS14*BS71 -> -16687.898 | BT68: =BT14*BT71 -> -17390.311 | ... CG68: =CG14*CG71 -> -22554.099 | CI68: =SUM(B68:E68) -> -7317 | CJ68: =SUM(F68:I68) -> -8811 | CK68: =SUM(J68:M68) -> -10959 | CL68: =SUM(N68:Q68) -> -12258 | CM68: =SUM(R68:U68) -> -13497 | CN68: =SUM(V68:Y68) -> -14343 | CO68: =SUM(Z68:AC68) -> -16793 | CP68: =SUM(AD68:AG68) -> -21672 | CQ68: =SUM(AH68:AK68) -> -26726 | CR68: =SUM(AL68:AO68) -> -30089 | CS68: =SUM(AP68:AS68) -> -32778 | CT68: =SUM(AT68:AW68) -> -45566 | CU68: =SUM(AX68:BA68) -> -48955 | CV68: =SUM(BB68:BE68) -> -50886 | CW68: =SUM(BF68:BI68) -> -54900 | CX68: =SUM(BJ68:BM68) -> -59972.622 | CY68: =SUM(BN68:BQ68) -> -64157.875 | CZ68: =SUM(BR68:BU68) -> -68944.281 | DA68: =SUM(BV68:BY68) -> -73701.626 | DB68: =SUM(BZ68:CC68) -> -78310.838 | DC68: =SUM(CD68:CG68) -> -82873.175
A69: QoQ Growth | B69: n/a | C69: =IF(AND(B68<0,C68>0),"n/a",C68/B68-1) -> 0.012273524 | D69: =IF(AND(C68<0,D68>0),"n/a",D68/C68-1) -> 0.042147806 | E69: =IF(AND(D68<0,E68>0),"n/a",E68/D68-1) -> 0.14626039 | F69: =IF(AND(E68<0,F68>0),"n/a",F68/E68-1) -> -0.014499758 | G69: =IF(AND(F68<0,G68>0),"n/a",G68/F68-1) -> 0.035801864 | H69: =IF(AND(G68<0,H68>0),"n/a",H68/G68-1) -> 0.045454545 | I69: =IF(AND(H68<0,I68>0),"n/a",I68/H68-1) -> 0.11050725 | J69: =IF(AND(I68<0,J68>0),"n/a",J68/I68-1) -> 0.02324633 | ... CG69: =IF(AND(CF68<0,CG68>0),"n/a",CG68/CF68-1) -> 0.080953017 | CI69: n/a | CJ69: n/a | CK69: n/a | CL69: n/a | CM69: n/a | CN69: n/a | CO69: n/a | CP69: n/a | CQ69: n/a | CR69: n/a | CS69: n/a | CT69: n/a | CU69: n/a | CV69: n/a | CW69: n/a | CX69: n/a | CY69: n/a | CZ69: n/a | DA69: n/a | DB69: n/a | DC69: n/a
A70: YoY Growth | B70: n/a | C70: n/a | D70: n/a | E70: n/a | F70: =IF(AND(B68<0,F68>0),"n/a",F68/B68-1) -> 0.19170076 | G70: =IF(AND(C68<0,G68>0),"n/a",G68/C68-1) -> 0.21939954 | H70: =IF(AND(D68<0,H68>0),"n/a",H68/D68-1) -> 0.2232687 | I70: =IF(AND(E68<0,I68>0),"n/a",I68/E68-1) -> 0.18511358 | J70: =IF(AND(F68<0,J68>0),"n/a",J68/F68-1) -> 0.23050515 | K70: =IF(AND(G68<0,K68>0),"n/a",K68/G68-1) -> 0.23248106 | L70: =IF(AND(H68<0,L68>0),"n/a",L68/H68-1) -> 0.25634058 | M70: =IF(AND(I68<0,M68>0),"n/a",M68/I68-1) -> 0.25326264 | ... CG70: =IF(AND(CC68<0,CG68>0),"n/a",CG68/CC68-1) -> 0.054256821 | CI70: n/a | CJ70: =IF(AND(CI68<0,CJ68>0),"n/a",CJ68/CI68-1) -> 0.20418204 | CK70: =IF(AND(CJ68<0,CK68>0),"n/a",CK68/CJ68-1) -> 0.24378618 | CL70: =IF(AND(CK68<0,CL68>0),"n/a",CL68/CK68-1) -> 0.11853271 | CM70: =IF(AND(CL68<0,CM68>0),"n/a",CM68/CL68-1) -> 0.10107685 | CN70: =IF(AND(CM68<0,CN68>0),"n/a",CN68/CM68-1) -> 0.062680596 | CO70: =IF(AND(CN68<0,CO68>0),"n/a",CO68/CN68-1) -> 0.17081503 | CP70: =IF(AND(CO68<0,CP68>0),"n/a",CP68/CO68-1) -> 0.29053772 | CQ70: =IF(AND(CP68<0,CQ68>0),"n/a",CQ68/CP68-1) -> 0.23320413 | ... DC70: =IF(AND(DB68<0,DC68>0),"n/a",DC68/DB68-1) -> 0.058259335
A71: % of Google Advertising (Gross) | B71: =B68/B$14 -> -0.2642471 | C71: =C68/C$14 -> -0.26394392 | D71: =D68/D$14 -> -0.25668373 | E71: =E68/E$14 -> -0.2533366 | F71: =F68/F$14 -> -0.24548519 | G71: =G68/G$14 -> -0.24231299 | H71: =H68/H$14 -> -0.23652919 | I71: =I68/I$14 -> -0.24100649 | ... BL71: =BL68/BL$14 -> -0.20053382 | BM71: -0.205 | BN71: -0.19868825 | BO71: -0.19868825 | BP71: -0.19868825 | BQ71: -0.19868825 | BR71: -0.19484296 | BS71: -0.19484296 | BT71: -0.19484296 | BU71: -0.19484296 | BV71: -0.19161543 | BW71: -0.19161543 | BX71: -0.19161543 | BY71: -0.19161543 | BZ71: -0.18875737 | CA71: -0.18875737 | CB71: -0.18875737 | CC71: -0.18875737 | CD71: -0.18634697 | CE71: -0.18634697 | CF71: -0.18634697 | CG71: -0.18634697 | CI71: =CI68/CI$14 -> -0.25913727 | CJ71: =CJ68/CJ$14 -> -0.24119241 | CK71: =CK68/CK$14 -> -0.2508584 | CL71: =CL68/CL$14 -> -0.2400141 | CM71: =CM68/CM$14 -> -0.22636858 | CN71: =CN68/CN$14 -> -0.21283573 | CO71: =CO68/CO$14 -> -0.21154403 | CP71: =CP68/CP$14 -> -0.22722936 | ... DC71: =DC68/DC$14 -> -0.18634697
A72: % of Consolidated Gross Revenues | B72: =B68/B64 -> -0.25254613 | C72: =C68/C64 -> -0.25395894 | D72: =D68/D64 -> -0.24773538 | E72: =E68/E64 -> -0.24514218 | F72: =F68/F64 -> -0.23778426 | G72: =G68/G64 -> -0.23399069 | H72: =H68/H64 -> -0.22716049 | I72: =I68/I64 -> -0.23167045 | ... CG72: =CG68/CG64 -> -0.11466875 | CI72: =CI68/CI$64 -> -0.24954811 | CJ72: =CJ68/CJ$64 -> -0.23244954 | CK72: =CK68/CK$64 -> -0.23803215 | CL72: =CL68/CL$64 -> -0.22078928 | CM72: =CM68/CM$64 -> -0.2044969 | CN72: =CN68/CN$64 -> -0.19126805 | CO72: =CO68/CO$64 -> -0.18602667 | CP72: =CP68/CP$64 -> -0.19549862 | ... DC72: =DC68/DC$64 -> -0.11518909
A74: Google Advertising (Net) | B74: =B14+B68 -> 4764 | C74: =C14+C68 -> 4830 | D74: =D14+D68 -> 5227 | E74: =E14+E68 -> 6098 | F74: =F14+F68 -> 6267 | G74: =G14+G68 -> 6604 | H74: =H14+H68 -> 7127 | I74: =I14+I68 -> 7722 | ... CG74: =CG14+CG68 -> 98478.718 | CI74: =SUM(B74:E74) -> 20919 | CJ74: =SUM(F74:I74) -> 27720 | CK74: =SUM(J74:M74) -> 32727 | CL74: =SUM(N74:Q74) -> 38814 | CM74: =SUM(R74:U74) -> 46127 | CN74: =SUM(V74:Y74) -> 53047 | CO74: =SUM(Z74:AC74) -> 62590 | CP74: =SUM(AD74:AG74) -> 73703 | CQ74: =SUM(AH74:AK74) -> 89475 | CR74: =SUM(AL74:AO74) -> 104722 | CS74: =SUM(AP74:AS74) -> 114146 | CT74: =SUM(AT74:AW74) -> 163931 | CU74: =SUM(AX74:BA74) -> 175518 | CV74: =SUM(BB74:BE74) -> 186969 | CW74: =SUM(BF74:BI74) -> 209690 | CX74: =SUM(BJ74:BM74) -> 233622.78 | CY74: =SUM(BN74:BQ74) -> 258749.38 | CZ74: =SUM(BR74:BU74) -> 284901.09 | DA74: =SUM(BV74:BY74) -> 310931.41 | DB74: =SUM(BZ74:CC74) -> 336564.81 | DC74: =SUM(CD74:CG74) -> 361851.93
A75: QoQ Growth | B75: n/a | C75: =IF(AND(B74<0,C74>0),"n/a",C74/B74-1) -> 0.013853904 | D75: =IF(AND(C74<0,D74>0),"n/a",D74/C74-1) -> 0.082194617 | E75: =IF(AND(D74<0,E74>0),"n/a",E74/D74-1) -> 0.16663478 | F75: =IF(AND(E74<0,F74>0),"n/a",F74/E74-1) -> 0.027714005 | G75: =IF(AND(F74<0,G74>0),"n/a",G74/F74-1) -> 0.053773735 | H75: =IF(AND(G74<0,H74>0),"n/a",H74/G74-1) -> 0.079194428 | I75: =IF(AND(H74<0,I74>0),"n/a",I74/H74-1) -> 0.083485337 | J75: =IF(AND(I74<0,J74>0),"n/a",J74/I74-1) -> -0.00077700078 | ... CG75: =IF(AND(CF74<0,CG74>0),"n/a",CG74/CF74-1) -> 0.080953017 | CI75: n/a | CJ75: n/a | CK75: n/a | CL75: n/a | CM75: n/a | CN75: n/a | CO75: n/a | CP75: n/a | CQ75: n/a | CR75: n/a | CS75: n/a | CT75: n/a | CU75: n/a | CV75: n/a | CW75: n/a | CX75: n/a | CY75: n/a | CZ75: n/a | DA75: n/a | DB75: n/a | DC75: n/a
A76: YoY Growth | B76: n/a | C76: n/a | D76: n/a | E76: n/a | F76: =IF(AND(B74<0,F74>0),"n/a",F74/B74-1) -> 0.31549118 | G76: =IF(AND(C74<0,G74>0),"n/a",G74/C74-1) -> 0.36728778 | H76: =IF(AND(D74<0,H74>0),"n/a",H74/D74-1) -> 0.36349723 | I76: =IF(AND(E74<0,I74>0),"n/a",I74/E74-1) -> 0.26631683 | J76: =IF(AND(F74<0,J74>0),"n/a",J74/F74-1) -> 0.23121111 | K76: =IF(AND(G74<0,K74>0),"n/a",K74/G74-1) -> 0.19957601 | L76: =IF(AND(H74<0,L74>0),"n/a",L74/H74-1) -> 0.13455872 | M76: =IF(AND(I74<0,M74>0),"n/a",M74/I74-1) -> 0.16588967 | ... CG76: =IF(AND(CC74<0,CG74>0),"n/a",CG74/CC74-1) -> 0.071066651 | CI76: n/a | CJ76: =IF(AND(CI74<0,CJ74>0),"n/a",CJ74/CI74-1) -> 0.32511114 | CK76: =IF(AND(CJ74<0,CK74>0),"n/a",CK74/CJ74-1) -> 0.18062771 | CL76: =IF(AND(CK74<0,CL74>0),"n/a",CL74/CK74-1) -> 0.18599322 | CM76: =IF(AND(CL74<0,CM74>0),"n/a",CM74/CL74-1) -> 0.1884114 | CN76: =IF(AND(CM74<0,CN74>0),"n/a",CN74/CM74-1) -> 0.1500206 | CO76: =IF(AND(CN74<0,CO74>0),"n/a",CO74/CN74-1) -> 0.17989707 | CP76: =IF(AND(CO74<0,CP74>0),"n/a",CP74/CO74-1) -> 0.17755232 | CQ76: =IF(AND(CP74<0,CQ74>0),"n/a",CQ74/CP74-1) -> 0.213994 | ... DC76: =IF(AND(DB74<0,DC74>0),"n/a",DC74/DB74-1) -> 0.075132984
A77: % of Google Services | B77: n/a | C77: n/a | D77: n/a | E77: n/a | F77: n/a | G77: n/a | H77: n/a | I77: n/a | J77: n/a | K77: n/a | L77: n/a | M77: n/a | N77: n/a | O77: n/a | P77: n/a | Q77: n/a | R77: n/a | S77: n/a | T77: n/a | U77: n/a | V77: n/a | W77: n/a | X77: n/a | Y77: n/a | Z77: n/a | AA77: n/a | AB77: n/a | AC77: n/a | AD77: n/a | AE77: n/a | AF77: n/a | AG77: n/a | AH77: n/a | AI77: n/a | AJ77: n/a | AK77: =AK74/AK$8 -> 0.67263804 | AL77: =AL74/AL$8 -> 0.69362996 | AM77: =AM74/AM$8 -> 0.6905452 | AN77: =AN74/AN$8 -> 0.69508006 | AO77: =AO74/AO$8 -> 0.68135099 | AP77: =AP74/AP$8 -> 0.6888057 | AQ77: =AQ74/AQ$8 -> 0.66225601 | AR77: =AR74/AR$8 -> 0.67951519 | ... CG77: =CG74/CG$8 -> 0.67469137 | CI77: n/a | CJ77: n/a | CK77: n/a | CL77: n/a | CM77: n/a | CN77: n/a | CO77: n/a | CP77: n/a | CQ77: =CQ74/CQ$8 -> 0.68550611 | CR77: =CR74/CR$8 -> 0.68975465 | CS77: =CS74/CS$8 -> 0.67688202 | CT77: =CT74/CT$8 -> 0.69015152 | CU77: =CU74/CU$8 -> 0.69230223 | CV77: =CV74/CV$8 -> 0.68601652 | CW77: =CW74/CW$8 -> 0.68766602 | CX77: =CX74/CX$8 -> 0.68338545 | ... DC77: =DC74/DC$8 -> 0.67933643
A78: % of Google Segment Revs (Net) | B78: =B74/B$80 -> 0.94075829 | C78: =C74/C$80 -> 0.94929245 | D78: =D74/D$80 -> 0.95365809 | E78: =E74/E$80 -> 0.95714958 | F78: =F74/F$80 -> 0.95884333 | G78: =G74/G$80 -> 0.95516344 | H78: =H74/H$80 -> 0.94874867 | I78: =I74/I$80 -> 0.9495819 | ... CG78: =CG74/CG$80 -> 0.56727697 | CI78: n/a | CJ78: n/a | CK78: n/a | CL78: n/a | CM78: n/a | CN78: n/a | CO78: n/a | CP78: n/a | CQ78: =CQ74/CQ$80 -> 0.81806462 | CR78: =CR74/CR$80 -> 0.80152158 | CS78: =CS74/CS$80 -> 0.76651266 | CT78: =CT74/CT$80 -> 0.77630239 | CU78: =CU74/CU$80 -> 0.76030201 | CV78: =CV74/CV$80 -> 0.73394571 | CW78: =CW74/CW$80 -> 0.71503347 | CX78: =CX74/CX$80 -> 0.68780088 | ... DC78: =DC74/DC$80 -> 0.57024544
A80: Google Segment Revenues (Net) | B80: =B3+B68 -> 5064 | C80: =C3+C68 -> 5088 | D80: =D3+D68 -> 5481 | E80: =E3+E68 -> 6371 | F80: =F3+F68 -> 6536 | G80: =G3+G68 -> 6914 | H80: =H3+H68 -> 7512 | I80: =I3+I68 -> 8132 | ... CG80: =CG3+CG68 -> 173599.01 | CI80: =SUM(B80:E80) -> 22004 | CJ80: =SUM(F80:I80) -> 29094 | CK80: =SUM(J80:M80) -> 35081 | CL80: =SUM(N80:Q80) -> 43261 | CM80: =SUM(R80:U80) -> 52398 | CN80: =SUM(V80:Y80) -> 60199 | CO80: =SUM(Z80:AC80) -> 72669 | CP80: =SUM(AD80:AG80) -> 88706 | CQ80: =SUM(AH80:AK80) -> 109374 | CR80: =SUM(AL80:AO80) -> 130654 | CS80: =SUM(AP80:AS80) -> 148916 | CT80: =SUM(AT80:AW80) -> 211169 | CU80: =SUM(AX80:BA80) -> 230853 | CV80: =SUM(BB80:BE80) -> 254745 | CW80: =SUM(BF80:BI80) -> 293259 | CX80: =SUM(BJ80:BM80) -> 339666.3 | CY80: =SUM(BN80:BQ80) -> 390255.66 | CZ80: =SUM(BR80:BU80) -> 445562.61 | DA80: =SUM(BV80:BY80) -> 505753.02 | DB80: =SUM(BZ80:CC80) -> 569030.38 | DC80: =SUM(CD80:CG80) -> 634554.7
A81: QoQ Growth | B81: n/a | C81: =IF(AND(B80<0,C80>0),"n/a",C80/B80-1) -> 0.0047393365 | D81: =IF(AND(C80<0,D80>0),"n/a",D80/C80-1) -> 0.077240566 | E81: =IF(AND(D80<0,E80>0),"n/a",E80/D80-1) -> 0.16237913 | F81: =IF(AND(E80<0,F80>0),"n/a",F80/E80-1) -> 0.025898603 | G81: =IF(AND(F80<0,G80>0),"n/a",G80/F80-1) -> 0.057833537 | H81: =IF(AND(G80<0,H80>0),"n/a",H80/G80-1) -> 0.086491177 | I81: =IF(AND(H80<0,I80>0),"n/a",I80/H80-1) -> 0.082534611 | J81: =IF(AND(I80<0,J80>0),"n/a",J80/I80-1) -> 0.00049188392 | ... CG81: =IF(AND(CF80<0,CG80>0),"n/a",CG80/CF80-1) -> 0.066247139 | CI81: n/a | CJ81: n/a | CK81: n/a | CL81: n/a | CM81: n/a | CN81: n/a | CO81: n/a | CP81: n/a | CQ81: n/a | CR81: n/a | CS81: n/a | CT81: n/a | CU81: n/a | CV81: n/a | CW81: n/a | CX81: n/a | CY81: n/a | CZ81: n/a | DA81: n/a | DB81: n/a | DC81: n/a
A82: YoY Growth | B82: n/a | C82: n/a | D82: n/a | E82: n/a | F82: =IF(AND(B80<0,F80>0),"n/a",F80/B80-1) -> 0.2906793 | G82: =IF(AND(C80<0,G80>0),"n/a",G80/C80-1) -> 0.35888365 | H82: =IF(AND(D80<0,H80>0),"n/a",H80/D80-1) -> 0.37055282 | I82: =IF(AND(E80<0,I80>0),"n/a",I80/E80-1) -> 0.27640873 | J82: =IF(AND(F80<0,J80>0),"n/a",J80/F80-1) -> 0.24479804 | K82: =IF(AND(G80<0,K80>0),"n/a",K80/G80-1) -> 0.20928551 | L82: =IF(AND(H80<0,L80>0),"n/a",L80/H80-1) -> 0.16506922 | M82: =IF(AND(I80<0,M80>0),"n/a",M80/I80-1) -> 0.20905066 | ... CG82: =IF(AND(CC80<0,CG80>0),"n/a",CG80/CC80-1) -> 0.11265196 | CI82: n/a | CJ82: =IF(AND(CI80<0,CJ80>0),"n/a",CJ80/CI80-1) -> 0.32221414 | CK82: =IF(AND(CJ80<0,CK80>0),"n/a",CK80/CJ80-1) -> 0.20578126 | CL82: =IF(AND(CK80<0,CL80>0),"n/a",CL80/CK80-1) -> 0.23317465 | CM82: =IF(AND(CL80<0,CM80>0),"n/a",CM80/CL80-1) -> 0.2112064 | CN82: =IF(AND(CM80<0,CN80>0),"n/a",CN80/CM80-1) -> 0.14887973 | CO82: =IF(AND(CN80<0,CO80>0),"n/a",CO80/CN80-1) -> 0.2071463 | CP82: =IF(AND(CO80<0,CP80>0),"n/a",CP80/CO80-1) -> 0.22068557 | CQ82: =IF(AND(CP80<0,CQ80>0),"n/a",CQ80/CP80-1) -> 0.23299439 | ... DC82: =IF(AND(DB80<0,DC80>0),"n/a",DC80/DB80-1) -> 0.11515083
A83: % of Consolidated Net Revenues | B83: =B80/B$85 -> 1 | C83: =C80/C$85 -> 1 | D83: =D80/D$85 -> 1 | E83: =E80/E$85 -> 1 | F83: =F80/F$85 -> 1 | G83: =G80/G$85 -> 1 | H83: =H80/H$85 -> 1 | I83: =I80/I$85 -> 1 | ... CG83: =CG80/CG$85 -> 0.99692171 | CI83: =CI80/CI$85 -> 1 | CJ83: =CJ80/CJ$85 -> 1 | CK83: =CK80/CK$85 -> 1 | CL83: =CL80/CL$85 -> 1 | CM83: =CM80/CM$85 -> 0.99798111 | CN83: =CN80/CN$85 -> 0.99262936 | CO83: =CO80/CO$85 -> 0.98897644 | CP83: =CP80/CP$85 -> 0.99465145 | ... DC83: =DC80/DC$85 -> 0.99681822
A85: Consolidated Revenues (Net) | B85: =B64+B68 -> 5064 | C85: =C64+C68 -> 5088 | D85: =D64+D68 -> 5481 | E85: =E64+E68 -> 6371 | F85: =F64+F68 -> 6536 | G85: =G64+G68 -> 6914 | H85: =H64+H68 -> 7512 | I85: =I64+I68 -> 8132 | ... CG85: =CG64+CG68 -> 174135.05 | CI85: =SUM(B85:E85) -> 22004 | CJ85: =SUM(F85:I85) -> 29094 | CK85: =SUM(J85:M85) -> 35081 | CL85: =SUM(N85:Q85) -> 43261 | CM85: =SUM(R85:U85) -> 52504 | CN85: =SUM(V85:Y85) -> 60646 | CO85: =SUM(Z85:AC85) -> 73479 | CP85: =SUM(AD85:AG85) -> 89183 | CQ85: =SUM(AH85:AK85) -> 110093 | CR85: =SUM(AL85:AO85) -> 131768 | CS85: =SUM(AP85:AS85) -> 149749 | CT85: =SUM(AT85:AW85) -> 212071 | CU85: =SUM(AX85:BA85) -> 233881 | CV85: =SUM(BB85:BE85) -> 256508 | CW85: =SUM(BF85:BI85) -> 295118 | CX85: =SUM(BJ85:BM85) -> 341194.3 | CY85: =SUM(BN85:BQ85) -> 391922.01 | CZ85: =SUM(BR85:BU85) -> 447312.27 | DA85: =SUM(BV85:BY85) -> 507590.17 | DB85: =SUM(BZ85:CC85) -> 570959.38 | DC85: =SUM(CD85:CG85) -> 636580.16
A86: QoQ Growth | B86: n/a | C86: =IF(AND(B85<0,C85>0),"n/a",C85/B85-1) -> 0.0047393365 | D86: =IF(AND(C85<0,D85>0),"n/a",D85/C85-1) -> 0.077240566 | E86: =IF(AND(D85<0,E85>0),"n/a",E85/D85-1) -> 0.16237913 | F86: =IF(AND(E85<0,F85>0),"n/a",F85/E85-1) -> 0.025898603 | G86: =IF(AND(F85<0,G85>0),"n/a",G85/F85-1) -> 0.057833537 | H86: =IF(AND(G85<0,H85>0),"n/a",H85/G85-1) -> 0.086491177 | I86: =IF(AND(H85<0,I85>0),"n/a",I85/H85-1) -> 0.082534611 | J86: =IF(AND(I85<0,J85>0),"n/a",J85/I85-1) -> 0.00049188392 | ... CG86: =IF(AND(CF85<0,CG85>0),"n/a",CG85/CF85-1) -> 0.066663135 | CI86: n/a | CJ86: n/a | CK86: n/a | CL86: n/a | CM86: n/a | CN86: n/a | CO86: n/a | CP86: n/a | CQ86: n/a | CR86: n/a | CS86: n/a | CT86: n/a | CU86: n/a | CV86: n/a | CW86: n/a | CX86: n/a | CY86: n/a | CZ86: n/a | DA86: n/a | DB86: n/a | DC86: n/a
A87: YoY Growth | B87: n/a | C87: n/a | D87: n/a | E87: n/a | F87: =IF(AND(B85<0,F85>0),"n/a",F85/B85-1) -> 0.2906793 | G87: =IF(AND(C85<0,G85>0),"n/a",G85/C85-1) -> 0.35888365 | H87: =IF(AND(D85<0,H85>0),"n/a",H85/D85-1) -> 0.37055282 | I87: =IF(AND(E85<0,I85>0),"n/a",I85/E85-1) -> 0.27640873 | J87: =IF(AND(F85<0,J85>0),"n/a",J85/F85-1) -> 0.24479804 | K87: =IF(AND(G85<0,K85>0),"n/a",K85/G85-1) -> 0.20928551 | L87: =IF(AND(H85<0,L85>0),"n/a",L85/H85-1) -> 0.16506922 | M87: =IF(AND(I85<0,M85>0),"n/a",M85/I85-1) -> 0.20905066 | ... CG87: =IF(AND(CC85<0,CG85>0),"n/a",CG85/CC85-1) -> 0.11244763 | CI87: n/a | CJ87: =IF(AND(CI85<0,CJ85>0),"n/a",CJ85/CI85-1) -> 0.32221414 | CK87: =IF(AND(CJ85<0,CK85>0),"n/a",CK85/CJ85-1) -> 0.20578126 | CL87: =IF(AND(CK85<0,CL85>0),"n/a",CL85/CK85-1) -> 0.23317465 | CM87: =IF(AND(CL85<0,CM85>0),"n/a",CM85/CL85-1) -> 0.21365664 | CN87: =IF(AND(CM85<0,CN85>0),"n/a",CN85/CM85-1) -> 0.1550739 | CO87: =IF(AND(CN85<0,CO85>0),"n/a",CO85/CN85-1) -> 0.21160505 | CP87: =IF(AND(CO85<0,CP85>0),"n/a",CP85/CO85-1) -> 0.21372093 | CQ87: =IF(AND(CP85<0,CQ85>0),"n/a",CQ85/CP85-1) -> 0.23446172 | ... DC87: =IF(AND(DB85<0,DC85>0),"n/a",DC85/DB85-1) -> 0.11493072
A90: HISTORICAL NET REVENUE BUILD (OLD):
A91: Google Websites (Gross) - OLD | B91: 4439 | C91: 4499 | D91: 4833 | E91: 5672 | F91: 5879 | G91: 6232 | H91: 6740 | I91: 7294 | J91: 7312 | K91: 7542 | L91: 7727 | M91: 8640 | N91: 8637 | O91: 8865 | P91: 9373 | Q91: 10547 | R91: 10469 | S91: 10935 | T91: 11252 | U91: 12429 | V91: 11932 | W91: 12402 | X91: 13087 | Y91: 14936 | Z91: 14328 | AA91: 15400 | AB91: 16089 | AC91: 17968 | AD91: 17403 | AE91: 18425 | AF91: 19723 | AG91: 22237 | AH91: 21998 | AI91: 23262 | AJ91: 24054 | CI91: =SUM(B91:E91) -> 19443 | CJ91: =SUM(F91:I91) -> 26145 | CK91: =SUM(J91:M91) -> 31221 | CL91: =SUM(N91:Q91) -> 37422 | CM91: =SUM(R91:U91) -> 45085 | CN91: =SUM(V91:Y91) -> 52357 | CO91: =SUM(Z91:AC91) -> 63785 | CP91: =SUM(AD91:AG91) -> 77788
A92: QoQ Growth | B92: n/a | C92: =IF(AND(B91<0,C91>0),"n/a",C91/B91-1) -> 0.013516558 | D92: =IF(AND(C91<0,D91>0),"n/a",D91/C91-1) -> 0.07423872 | E92: =IF(AND(D91<0,E91>0),"n/a",E91/D91-1) -> 0.17359818 | F92: =IF(AND(E91<0,F91>0),"n/a",F91/E91-1) -> 0.036495063 | G92: =IF(AND(F91<0,G91>0),"n/a",G91/F91-1) -> 0.060044225 | H92: =IF(AND(G91<0,H91>0),"n/a",H91/G91-1) -> 0.081514763 | I92: =IF(AND(H91<0,I91>0),"n/a",I91/H91-1) -> 0.082195846 | J92: =IF(AND(I91<0,J91>0),"n/a",J91/I91-1) -> 0.0024677817 | ... AJ92: =IF(AND(AI91<0,AJ91>0),"n/a",AJ91/AI91-1) -> 0.034046944 | CI92: n/a | CJ92: n/a | CK92: n/a | CL92: n/a | CM92: n/a | CN92: n/a | CO92: n/a | CP92: n/a
A93: YoY Growth | B93: n/a | C93: n/a | D93: n/a | E93: n/a | F93: =IF(AND(B91<0,F91>0),"n/a",F91/B91-1) -> 0.32439739 | G93: =IF(AND(C91<0,G91>0),"n/a",G91/C91-1) -> 0.38519671 | H93: =IF(AND(D91<0,H91>0),"n/a",H91/D91-1) -> 0.39457894 | I93: =IF(AND(E91<0,I91>0),"n/a",I91/E91-1) -> 0.28596615 | J93: =IF(AND(F91<0,J91>0),"n/a",J91/F91-1) -> 0.24374894 | K93: =IF(AND(G91<0,K91>0),"n/a",K91/G91-1) -> 0.21020539 | L93: =IF(AND(H91<0,L91>0),"n/a",L91/H91-1) -> 0.14643917 | M93: =IF(AND(I91<0,M91>0),"n/a",M91/I91-1) -> 0.18453523 | ... AJ93: =IF(AND(AF91<0,AJ91>0),"n/a",AJ91/AF91-1) -> 0.21959134 | CI93: n/a | CJ93: =IF(AND(CI91<0,CJ91>0),"n/a",CJ91/CI91-1) -> 0.34469989 | CK93: =IF(AND(CJ91<0,CK91>0),"n/a",CK91/CJ91-1) -> 0.19414802 | CL93: =IF(AND(CK91<0,CL91>0),"n/a",CL91/CK91-1) -> 0.19861632 | CM93: =IF(AND(CL91<0,CM91>0),"n/a",CM91/CL91-1) -> 0.20477259 | CN93: =IF(AND(CM91<0,CN91>0),"n/a",CN91/CM91-1) -> 0.16129533 | CO93: =IF(AND(CN91<0,CO91>0),"n/a",CO91/CN91-1) -> 0.21827072 | CP93: =IF(AND(CO91<0,CP91>0),"n/a",CP91/CO91-1) -> 0.21953437
A94: % of Google Segment Revs (Gross) | B94: =B91/B$3 -> 0.65520295 | C94: =C91/C$3 -> 0.65967742 | D94: =D91/D$3 -> 0.66332693 | E94: =E91/E$3 -> 0.67203791 | F94: =F91/F$3 -> 0.68559767 | G94: =G91/G$3 -> 0.69044981 | H94: =H91/H$3 -> 0.69341564 | I94: =I91/I$3 -> 0.68915344 | ... AJ94: =AJ91/AJ$3 -> 0.71602072 | CI94: =CI91/CI$3 -> 0.66310835 | CJ94: =CJ91/CJ$3 -> 0.68975069 | CK94: =CK91/CK$3 -> 0.67812772 | CL94: =CL91/CL$3 -> 0.67403952 | CM94: =CM91/CM$3 -> 0.68419455 | CN94: =CN91/CN$3 -> 0.70238255 | CO94: =CO91/CO$3 -> 0.71298428 | CP94: =CP91/CP$3 -> 0.70474189
A96: Distribution TAC - OLD | B96: -265 | C96: -269 | D96: -285 | E96: -333 | F96: -337 | G96: -355 | H96: -383 | I96: -442 | J96: -468 | K96: -507 | L96: -556 | M96: -634 | N96: -680 | O96: -706 | P96: -755 | Q96: -824 | R96: -845 | S96: -893 | T96: -927 | U96: -968 | V96: -913 | W96: -945 | X96: -1052 | Y96: -1191 | Z96: -1217 | AA96: -1352 | AB96: -1559 | AC96: -1766 | AD96: -1805 | AE96: -2049 | AF96: -2401 | AG96: -2776 | AH96: -2902 | AI96: -3009 | AJ96: -3155 | AK96: -3506 | AL96: -3383 | AM96: -3617 | AN96: -3856 | CI96: =SUM(B96:E96) -> -1152 | CJ96: =SUM(F96:I96) -> -1517 | CK96: =SUM(J96:M96) -> -2165 | CL96: =SUM(N96:Q96) -> -2965 | CM96: =SUM(R96:U96) -> -3633 | CN96: =SUM(V96:Y96) -> -4101 | CO96: =SUM(Z96:AC96) -> -5894 | CP96: =SUM(AD96:AG96) -> -9031
A97: QoQ Growth | B97: n/a | C97: =IF(AND(B96<0,C96>0),"n/a",C96/B96-1) -> 0.01509434 | D97: =IF(AND(C96<0,D96>0),"n/a",D96/C96-1) -> 0.059479554 | E97: =IF(AND(D96<0,E96>0),"n/a",E96/D96-1) -> 0.16842105 | F97: =IF(AND(E96<0,F96>0),"n/a",F96/E96-1) -> 0.012012012 | G97: =IF(AND(F96<0,G96>0),"n/a",G96/F96-1) -> 0.053412463 | H97: =IF(AND(G96<0,H96>0),"n/a",H96/G96-1) -> 0.078873239 | I97: =IF(AND(H96<0,I96>0),"n/a",I96/H96-1) -> 0.154047 | J97: =IF(AND(I96<0,J96>0),"n/a",J96/I96-1) -> 0.058823529 | ... AN97: =IF(AND(AM96<0,AN96>0),"n/a",AN96/AM96-1) -> 0.066076859 | CI97: n/a | CJ97: n/a | CK97: n/a | CL97: n/a | CM97: n/a | CN97: n/a | CO97: n/a | CP97: n/a
A98: YoY Growth | B98: n/a | C98: n/a | D98: n/a | E98: n/a | F98: =IF(AND(B96<0,F96>0),"n/a",F96/B96-1) -> 0.27169811 | G98: =IF(AND(C96<0,G96>0),"n/a",G96/C96-1) -> 0.3197026 | H98: =IF(AND(D96<0,H96>0),"n/a",H96/D96-1) -> 0.34385965 | I98: =IF(AND(E96<0,I96>0),"n/a",I96/E96-1) -> 0.32732733 | J98: =IF(AND(F96<0,J96>0),"n/a",J96/F96-1) -> 0.38872404 | K98: =IF(AND(G96<0,K96>0),"n/a",K96/G96-1) -> 0.42816901 | L98: =IF(AND(H96<0,L96>0),"n/a",L96/H96-1) -> 0.45169713 | M98: =IF(AND(I96<0,M96>0),"n/a",M96/I96-1) -> 0.43438914 | ... AN98: =IF(AND(AJ96<0,AN96>0),"n/a",AN96/AJ96-1) -> 0.222187 | CI98: n/a | CJ98: =IF(AND(CI96<0,CJ96>0),"n/a",CJ96/CI96-1) -> 0.31684028 | CK98: =IF(AND(CJ96<0,CK96>0),"n/a",CK96/CJ96-1) -> 0.42715887 | CL98: =IF(AND(CK96<0,CL96>0),"n/a",CL96/CK96-1) -> 0.36951501 | CM98: =IF(AND(CL96<0,CM96>0),"n/a",CM96/CL96-1) -> 0.22529511 | CN98: =IF(AND(CM96<0,CN96>0),"n/a",CN96/CM96-1) -> 0.12881916 | CO98: =IF(AND(CN96<0,CO96>0),"n/a",CO96/CN96-1) -> 0.43721044 | CP98: =IF(AND(CO96<0,CP96>0),"n/a",CP96/CO96-1) -> 0.53223617
A99: % of Google Websites Revs (Gross) | B99: =B96/B91 -> -0.05969813 | C99: =C96/C91 -> -0.059791065 | D99: =D96/D91 -> -0.058969584 | E99: =E96/E91 -> -0.05870945 | F99: =F96/F91 -> -0.057322674 | G99: =G96/G91 -> -0.056964056 | H99: =H96/H91 -> -0.056824926 | I99: =I96/I91 -> -0.060597752 | ... AN99: =AN96/AN91 -> #DIV/0! | CI99: =CI96/CI$91 -> -0.059250116 | CJ99: =CJ96/CJ$91 -> -0.058022566 | CK99: =CK96/CK$91 -> -0.069344352 | CL99: =CL96/CL$91 -> -0.079231468 | CM99: =CM96/CM$91 -> -0.080581125 | CN99: =CN96/CN$91 -> -0.078327635 | CO99: =CO96/CO$91 -> -0.09240417 | CP99: =CP96/CP$91 -> -0.1160976
A101: Google Websites (Net) - OLD | B101: =B91+B96 -> 4174 | C101: =C91+C96 -> 4230 | D101: =D91+D96 -> 4548 | E101: =E91+E96 -> 5339 | F101: =F91+F96 -> 5542 | G101: =G91+G96 -> 5877 | H101: =H91+H96 -> 6357 | I101: =I91+I96 -> 6852 | ... AJ101: =AJ91+AJ96 -> 20899 | CI101: =SUM(B101:E101) -> 18291 | CJ101: =SUM(F101:I101) -> 24628 | CK101: =SUM(J101:M101) -> 29056 | CL101: =SUM(N101:Q101) -> 34457 | CM101: =SUM(R101:U101) -> 41452 | CN101: =SUM(V101:Y101) -> 48256 | CO101: =SUM(Z101:AC101) -> 57891 | CP101: =SUM(AD101:AG101) -> 68757
A102: QoQ Growth | B102: n/a | C102: =IF(AND(B101<0,C101>0),"n/a",C101/B101-1) -> 0.013416387 | D102: =IF(AND(C101<0,D101>0),"n/a",D101/C101-1) -> 0.075177305 | E102: =IF(AND(D101<0,E101>0),"n/a",E101/D101-1) -> 0.1739226 | F102: =IF(AND(E101<0,F101>0),"n/a",F101/E101-1) -> 0.038022102 | G102: =IF(AND(F101<0,G101>0),"n/a",G101/F101-1) -> 0.060447492 | H102: =IF(AND(G101<0,H101>0),"n/a",H101/G101-1) -> 0.081674324 | I102: =IF(AND(H101<0,I101>0),"n/a",I101/H101-1) -> 0.077866918 | J102: =IF(AND(I101<0,J101>0),"n/a",J101/I101-1) -> -0.0011675423 | ... AJ102: =IF(AND(AI101<0,AJ101>0),"n/a",AJ101/AI101-1) -> 0.031896509 | CI102: n/a | CJ102: n/a | CK102: n/a | CL102: n/a | CM102: n/a | CN102: n/a | CO102: n/a | CP102: n/a
A103: YoY Growth | B103: n/a | C103: n/a | D103: n/a | E103: n/a | F103: =IF(AND(B101<0,F101>0),"n/a",F101/B101-1) -> 0.32774317 | G103: =IF(AND(C101<0,G101>0),"n/a",G101/C101-1) -> 0.3893617 | H103: =IF(AND(D101<0,H101>0),"n/a",H101/D101-1) -> 0.39775726 | I103: =IF(AND(E101<0,I101>0),"n/a",I101/E101-1) -> 0.2833864 | J103: =IF(AND(F101<0,J101>0),"n/a",J101/F101-1) -> 0.23493324 | K103: =IF(AND(G101<0,K101>0),"n/a",K101/G101-1) -> 0.19703931 | L103: =IF(AND(H101<0,L101>0),"n/a",L101/H101-1) -> 0.12804782 | M103: =IF(AND(I101<0,M101>0),"n/a",M101/I101-1) -> 0.16841798 | ... AJ103: =IF(AND(AF101<0,AJ101>0),"n/a",AJ101/AF101-1) -> 0.2065004 | CI103: n/a | CJ103: =IF(AND(CI101<0,CJ101>0),"n/a",CJ101/CI101-1) -> 0.34645454 | CK103: =IF(AND(CJ101<0,CK101>0),"n/a",CK101/CJ101-1) -> 0.17979535 | CL103: =IF(AND(CK101<0,CL101>0),"n/a",CL101/CK101-1) -> 0.18588243 | CM103: =IF(AND(CL101<0,CM101>0),"n/a",CM101/CL101-1) -> 0.20300665 | CN103: =IF(AND(CM101<0,CN101>0),"n/a",CN101/CM101-1) -> 0.16414166 | CO103: =IF(AND(CN101<0,CO101>0),"n/a",CO101/CN101-1) -> 0.19966429 | CP103: =IF(AND(CO101<0,CP101>0),"n/a",CP101/CO101-1) -> 0.18769757
A104: % of Google Segment Revs (Net) | B104: =B101/B$80 -> 0.82424961 | C104: =C101/C$80 -> 0.83136792 | D104: =D101/D$80 -> 0.82977559 | E104: =E101/E$80 -> 0.83801601 | F104: =F101/F$80 -> 0.84791922 | G104: =G101/G$80 -> 0.85001446 | H104: =H101/H$80 -> 0.84624601 | I104: =I101/I$80 -> 0.84259715 | ... AJ104: =AJ101/AJ$80 -> 0.77369317 | CI104: =CI101/CI$80 -> 0.83125795 | CJ104: =CJ101/CJ$80 -> 0.84649756 | CK104: =CK101/CK$80 -> 0.82825461 | CL104: =CL101/CL$80 -> 0.79649107 | CM104: =CM101/CM$80 -> 0.7910989 | CN104: =CN101/CN$80 -> 0.801608 | CO104: =CO101/CO$80 -> 0.79663956 | CP104: =CP101/CP$80 -> 0.77511104
A106: Google Network (Gross) - OLD | B106: 2036 | C106: 2063 | D106: 2199 | E106: 2495 | F106: 2427 | G106: 2484 | H106: 2595 | I106: 2880 | J106: 2913 | K106: 2983 | L106: 3133 | M106: 3436 | N106: 3391 | O106: 3313 | P106: 3278 | Q106: 3668 | R106: 3528 | S106: 3563 | T106: 3568 | U106: 3880 | V106: 3576 | W106: 3621 | X106: 3694 | Y106: 4142 | Z106: 3692 | AA106: 3743 | AB106: 3732 | AC106: 4431 | AD106: 4008 | AE106: 4247 | AF106: 4342 | AG106: 4990 | AH106: 4644 | AI106: 4825 | AJ106: 4900 | CI106: =SUM(B106:E106) -> 8793 | CJ106: =SUM(F106:I106) -> 10386 | CK106: =SUM(J106:M106) -> 12465 | CL106: =SUM(N106:Q106) -> 13650 | CM106: =SUM(R106:U106) -> 14539 | CN106: =SUM(V106:Y106) -> 15033 | CO106: =SUM(Z106:AC106) -> 15598 | CP106: =SUM(AD106:AG106) -> 17587
A107: QoQ Growth | B107: n/a | C107: =IF(AND(B106<0,C106>0),"n/a",C106/B106-1) -> 0.013261297 | D107: =IF(AND(C106<0,D106>0),"n/a",D106/C106-1) -> 0.065923413 | E107: =IF(AND(D106<0,E106>0),"n/a",E106/D106-1) -> 0.13460664 | F107: =IF(AND(E106<0,F106>0),"n/a",F106/E106-1) -> -0.027254509 | G107: =IF(AND(F106<0,G106>0),"n/a",G106/F106-1) -> 0.023485785 | H107: =IF(AND(G106<0,H106>0),"n/a",H106/G106-1) -> 0.04468599 | I107: =IF(AND(H106<0,I106>0),"n/a",I106/H106-1) -> 0.10982659 | J107: =IF(AND(I106<0,J106>0),"n/a",J106/I106-1) -> 0.011458333 | ... AJ107: =IF(AND(AI106<0,AJ106>0),"n/a",AJ106/AI106-1) -> 0.015544041 | CI107: n/a | CJ107: n/a | CK107: n/a | CL107: n/a | CM107: n/a | CN107: n/a | CO107: n/a | CP107: n/a
A108: YoY Growth | B108: n/a | C108: n/a | D108: n/a | E108: n/a | F108: =IF(AND(B106<0,F106>0),"n/a",F106/B106-1) -> 0.19204322 | G108: =IF(AND(C106<0,G106>0),"n/a",G106/C106-1) -> 0.20407174 | H108: =IF(AND(D106<0,H106>0),"n/a",H106/D106-1) -> 0.18008186 | I108: =IF(AND(E106<0,I106>0),"n/a",I106/E106-1) -> 0.15430862 | J108: =IF(AND(F106<0,J106>0),"n/a",J106/F106-1) -> 0.20024722 | K108: =IF(AND(G106<0,K106>0),"n/a",K106/G106-1) -> 0.20088567 | L108: =IF(AND(H106<0,L106>0),"n/a",L106/H106-1) -> 0.20732177 | M108: =IF(AND(I106<0,M106>0),"n/a",M106/I106-1) -> 0.19305556 | ... AJ108: =IF(AND(AF106<0,AJ106>0),"n/a",AJ106/AF106-1) -> 0.12851221 | CI108: n/a | CJ108: =IF(AND(CI106<0,CJ106>0),"n/a",CJ106/CI106-1) -> 0.18116684 | CK108: =IF(AND(CJ106<0,CK106>0),"n/a",CK106/CJ106-1) -> 0.20017331 | CL108: =IF(AND(CK106<0,CL106>0),"n/a",CL106/CK106-1) -> 0.095066185 | CM108: =IF(AND(CL106<0,CM106>0),"n/a",CM106/CL106-1) -> 0.065128205 | CN108: =IF(AND(CM106<0,CN106>0),"n/a",CN106/CM106-1) -> 0.033977578 | CO108: =IF(AND(CN106<0,CO106>0),"n/a",CO106/CN106-1) -> 0.037583982 | CP108: =IF(AND(CO106<0,CP106>0),"n/a",CP106/CO106-1) -> 0.12751635
A109: % of Google Segment Revs (Gross) | B109: =B106/B$3 -> 0.30051661 | C109: =C106/C$3 -> 0.30249267 | D109: =D106/D$3 -> 0.30181169 | E109: =E106/E$3 -> 0.29561611 | F109: =F106/F$3 -> 0.28303207 | G109: =G106/G$3 -> 0.27520496 | H109: =H106/H$3 -> 0.26697531 | I109: =I106/I$3 -> 0.27210884 | ... AJ109: =AJ106/AJ$3 -> 0.14585938 | CI109: =CI106/CI$3 -> 0.29988745 | CJ109: =CJ106/CJ$3 -> 0.27400079 | CK109: =CK106/CK$3 -> 0.27074283 | CL109: =CL106/CL$3 -> 0.24586178 | CM109: =CM106/CM$3 -> 0.2206389 | CN109: =CN106/CN$3 -> 0.20167154 | CO109: =CO106/CO$3 -> 0.17435336 | CP109: =CP106/CP$3 -> 0.15933429
A111: Network TAC - OLD | B111: -1446 | C111: -1463 | D111: -1520 | E111: -1736 | F111: -1702 | G111: -1757 | H111: -1825 | I111: -2010 | J111: -2041 | K111: -2096 | L111: -2218 | M111: -2439 | N111: -2284 | O111: -2307 | P111: -2218 | Q111: -2484 | R111: -2386 | S111: -2401 | T111: -2421 | U111: -2656 | V111: -2432 | W111: -2432 | X111: -2514 | Y111: -2864 | Z111: -2571 | AA111: -2623 | AB111: -2623 | AC111: -3082 | AD111: -2824 | AE111: -3042 | AF111: -3101 | AG111: -3674 | AH111: -3386 | AI111: -3411 | AJ111: -3427 | AK111: -3930 | AL111: -3477 | AM111: -3621 | AN111: -3634 | CI111: =SUM(B111:E111) -> -6165 | CJ111: =SUM(F111:I111) -> -7294 | CK111: =SUM(J111:M111) -> -8794 | CL111: =SUM(N111:Q111) -> -9293 | CM111: =SUM(R111:U111) -> -9864 | CN111: =SUM(V111:Y111) -> -10242 | CO111: =SUM(Z111:AC111) -> -10899 | CP111: =SUM(AD111:AG111) -> -12641
A112: QoQ Growth | B112: n/a | C112: =IF(AND(B111<0,C111>0),"n/a",C111/B111-1) -> 0.01175657 | D112: =IF(AND(C111<0,D111>0),"n/a",D111/C111-1) -> 0.038961039 | E112: =IF(AND(D111<0,E111>0),"n/a",E111/D111-1) -> 0.14210526 | F112: =IF(AND(E111<0,F111>0),"n/a",F111/E111-1) -> -0.019585253 | G112: =IF(AND(F111<0,G111>0),"n/a",G111/F111-1) -> 0.032314924 | H112: =IF(AND(G111<0,H111>0),"n/a",H111/G111-1) -> 0.038702334 | I112: =IF(AND(H111<0,I111>0),"n/a",I111/H111-1) -> 0.10136986 | J112: =IF(AND(I111<0,J111>0),"n/a",J111/I111-1) -> 0.015422886 | ... AN112: =IF(AND(AM111<0,AN111>0),"n/a",AN111/AM111-1) -> 0.0035901685 | CI112: n/a | CJ112: n/a | CK112: n/a | CL112: n/a | CM112: n/a | CN112: n/a | CO112: n/a | CP112: n/a
A113: YoY Growth | B113: n/a | C113: n/a | D113: n/a | E113: n/a | F113: =IF(AND(B111<0,F111>0),"n/a",F111/B111-1) -> 0.17704011 | G113: =IF(AND(C111<0,G111>0),"n/a",G111/C111-1) -> 0.20095694 | H113: =IF(AND(D111<0,H111>0),"n/a",H111/D111-1) -> 0.20065789 | I113: =IF(AND(E111<0,I111>0),"n/a",I111/E111-1) -> 0.1578341 | J113: =IF(AND(F111<0,J111>0),"n/a",J111/F111-1) -> 0.19917744 | K113: =IF(AND(G111<0,K111>0),"n/a",K111/G111-1) -> 0.19294252 | L113: =IF(AND(H111<0,L111>0),"n/a",L111/H111-1) -> 0.21534247 | M113: =IF(AND(I111<0,M111>0),"n/a",M111/I111-1) -> 0.21343284 | ... AN113: =IF(AND(AJ111<0,AN111>0),"n/a",AN111/AJ111-1) -> 0.060402685 | CI113: n/a | CJ113: =IF(AND(CI111<0,CJ111>0),"n/a",CJ111/CI111-1) -> 0.18313058 | CK113: =IF(AND(CJ111<0,CK111>0),"n/a",CK111/CJ111-1) -> 0.20564848 | CL113: =IF(AND(CK111<0,CL111>0),"n/a",CL111/CK111-1) -> 0.056743234 | CM113: =IF(AND(CL111<0,CM111>0),"n/a",CM111/CL111-1) -> 0.061444098 | CN113: =IF(AND(CM111<0,CN111>0),"n/a",CN111/CM111-1) -> 0.038321168 | CO113: =IF(AND(CN111<0,CO111>0),"n/a",CO111/CN111-1) -> 0.064147627 | CP113: =IF(AND(CO111<0,CP111>0),"n/a",CP111/CO111-1) -> 0.15983118
A114: % of Google Network Revs (Gross) | B114: =B111/B106 -> -0.71021611 | C114: =C111/C106 -> -0.70916142 | D114: =D111/D106 -> -0.69122328 | E114: =E111/E106 -> -0.69579158 | F114: =F111/F106 -> -0.7012773 | G114: =G111/G106 -> -0.70732689 | H114: =H111/H106 -> -0.70327553 | I114: =I111/I106 -> -0.69791667 | ... AN114: =AN111/AN106 -> #DIV/0! | CI114: =CI111/CI$106 -> -0.7011259 | CJ114: =CJ111/CJ$106 -> -0.70229155 | CK114: =CK111/CK$106 -> -0.70549539 | CL114: =CL111/CL$106 -> -0.68080586 | CM114: =CM111/CM$106 -> -0.67845106 | CN114: =CN111/CN$106 -> -0.68130114 | CO114: =CO111/CO$106 -> -0.69874343 | CP114: =CP111/CP$106 -> -0.71876955
A116: Google Network (Net) - OLD | B116: =B106+B111 -> 590 | C116: =C106+C111 -> 600 | D116: =D106+D111 -> 679 | E116: =E106+E111 -> 759 | F116: =F106+F111 -> 725 | G116: =G106+G111 -> 727 | H116: =H106+H111 -> 770 | I116: =I106+I111 -> 870 | ... AJ116: =AJ106+AJ111 -> 1473 | CI116: =SUM(B116:E116) -> 2628 | CJ116: =SUM(F116:I116) -> 3092 | CK116: =SUM(J116:M116) -> 3671 | CL116: =SUM(N116:Q116) -> 4357 | CM116: =SUM(R116:U116) -> 4675 | CN116: =SUM(V116:Y116) -> 4791 | CO116: =SUM(Z116:AC116) -> 4699 | CP116: =SUM(AD116:AG116) -> 4946
A117: QoQ Growth | B117: n/a | C117: =IF(AND(B116<0,C116>0),"n/a",C116/B116-1) -> 0.016949153 | D117: =IF(AND(C116<0,D116>0),"n/a",D116/C116-1) -> 0.13166667 | E117: =IF(AND(D116<0,E116>0),"n/a",E116/D116-1) -> 0.11782032 | F117: =IF(AND(E116<0,F116>0),"n/a",F116/E116-1) -> -0.044795784 | G117: =IF(AND(F116<0,G116>0),"n/a",G116/F116-1) -> 0.0027586207 | H117: =IF(AND(G116<0,H116>0),"n/a",H116/G116-1) -> 0.05914718 | I117: =IF(AND(H116<0,I116>0),"n/a",I116/H116-1) -> 0.12987013 | J117: =IF(AND(I116<0,J116>0),"n/a",J116/I116-1) -> 0.0022988506 | ... AJ117: =IF(AND(AI116<0,AJ116>0),"n/a",AJ116/AI116-1) -> 0.041725601 | CI117: n/a | CJ117: n/a | CK117: n/a | CL117: n/a | CM117: n/a | CN117: n/a | CO117: n/a | CP117: n/a
...

Sheet Cash Flow Statement
A1: Free Cash Flow | B1: ='Income Statement'!B1 -> 1Q10 | C1: ='Income Statement'!C1 -> 2Q10 | D1: ='Income Statement'!D1 -> 3Q10 | E1: ='Income Statement'!E1 -> 4Q10 | F1: ='Income Statement'!F1 -> 1Q11 | G1: ='Income Statement'!G1 -> 2Q11 | H1: ='Income Statement'!H1 -> 3Q11 | I1: ='Income Statement'!I1 -> 4Q11 | ... CG1: ='Income Statement'!CG1 -> 4Q30E | CI1: ='Income Statement'!CI1 -> 2010 | CJ1: ='Income Statement'!CJ1 -> 2011 | CK1: ='Income Statement'!CK1 -> 2012 | CL1: ='Income Statement'!CL1 -> 2013 | CM1: ='Income Statement'!CM1 -> 2014 | CN1: ='Income Statement'!CN1 -> 2015 | CO1: ='Income Statement'!CO1 -> 2016 | CP1: ='Income Statement'!CP1 -> 2017 | ... DC1: ='Income Statement'!DC1 -> 2030E
A3: Net Income | B3: ='Income Statement'!B260 -> 1955 | C3: ='Income Statement'!C260 -> 1840 | D3: ='Income Statement'!D260 -> 2167 | E3: ='Income Statement'!E260 -> 2543 | F3: ='Income Statement'!F260 -> 1798 | G3: ='Income Statement'!G260 -> 2505 | H3: ='Income Statement'!H260 -> 2729 | I3: ='Income Statement'!I260 -> 2705 | J3: 2890 | K3: 2785 | L3: 2176 | M3: 2886 | N3: 3346 | O3: 3228 | P3: 2970 | Q3: 3376 | R3: 3371 | S3: 3351 | T3: 2739 | U3: 4675 | V3: ='Income Statement'!V260 -> 3515 | W3: ='Income Statement'!W260 -> 3931 | X3: ='Income Statement'!X260 -> 3979 | Y3: ='Income Statement'!Y260 -> 4923 | Z3: ='Income Statement'!Z260 -> 4207 | AA3: ='Income Statement'!AA260 -> 4877 | AB3: ='Income Statement'!AB260 -> 5061 | AC3: ='Income Statement'!AC260 -> 5333 | ... CG3: ='Income Statement'!CG260 -> 59126.647 | CI3: =SUM(B3:E3) -> 8505 | CJ3: =SUM(F3:I3) -> 9737 | CK3: =SUM(J3:M3) -> 10737 | CL3: =SUM(N3:Q3) -> 12920 | CM3: =SUM(R3:U3) -> 14136 | CN3: =SUM(V3:Y3) -> 16348 | CO3: =SUM(Z3:AC3) -> 19478 | CP3: =SUM(AD3:AG3) -> 12662 | CQ3: =SUM(AH3:AK3) -> 30736 | CR3: =SUM(AL3:AO3) -> 34343 | CS3: =SUM(AP3:AS3) -> 40269 | CT3: =SUM(AT3:AW3) -> 76033 | CU3: =SUM(AX3:BA3) -> 59972 | CV3: =SUM(BB3:BE3) -> 73795 | CW3: =SUM(BF3:BI3) -> 100118 | CX3: =SUM(BJ3:BM3) -> 128170.63 | CY3: =SUM(BN3:BQ3) -> 129614.83 | CZ3: =SUM(BR3:BU3) -> 148810.31 | DA3: =SUM(BV3:BY3) -> 172070.68 | DB3: =SUM(BZ3:CC3) -> 197804.91 | DC3: =SUM(CD3:CG3) -> 226271.18
A5: Depreciation of property and equipment | B5: 264 | C5: 266 | D5: 257 | E5: 280 | F5: 301 | G5: 347 | H5: 363 | I5: 385 | J5: 378 | K5: 473 | L5: 507 | M5: 630 | N5: 584 | O5: 747 | P5: 693 | Q5: 757 | R5: 816 | S5: 813 | T5: 884 | U5: 1010 | V5: 938 | W5: 1011 | X5: 1030 | Y5: 1153 | Z5: 1155 | AA5: 1271 | AB5: 1377 | AC5: 1464 | AD5: 1287 | AE5: 1424 | AF5: 1561 | AG5: 1831 | AH5: 1791 | AI5: 1862 | AJ5: 2138 | AK5: 2373 | AL5: 2416 | AM5: 2626 | AN5: 2732 | AO5: 3082 | AP5: 2899 | AQ5: 3178 | AR5: 3289 | AS5: 3539 | AT5: 2525 | AU5: 2730 | AV5: 3085 | AW5: 3215 | AX5: 3591 | AY5: 3698 | AZ5: 3933 | BA5: 4065 | BB5: 3060 | BC5: 3279 | BD5: 3671 | BE5: 3316 | BF5: 3413 | BG5: 3708 | BH5: 3985 | BI5: 4205 | BJ5: 4487 | BK5: 4998 | BL5: 5611 | BM5: ='Capex & Depreciation'!BM20 -> 8328.0231 | BN5: ='Capex & Depreciation'!BN20 -> 6782.0262 | BO5: ='Capex & Depreciation'!BO20 -> 8852.0882 | BP5: ='Capex & Depreciation'!BP20 -> 9446.4078 | BQ5: ='Capex & Depreciation'!BQ20 -> 11260.128 | BR5: ='Capex & Depreciation'!BR20 -> 9434.0322 | BS5: ='Capex & Depreciation'!BS20 -> 12313.56 | BT5: ='Capex & Depreciation'!BT20 -> 13140.279 | ... CG5: ='Capex & Depreciation'!CG20 -> 29709.933 | CI5: =SUM(B5:E5) -> 1067 | CJ5: =SUM(F5:I5) -> 1396 | CK5: =SUM(J5:M5) -> 1988 | CL5: =SUM(N5:Q5) -> 2781 | CM5: =SUM(R5:U5) -> 3523 | CN5: =SUM(V5:Y5) -> 4132 | CO5: =SUM(Z5:AC5) -> 5267 | CP5: =SUM(AD5:AG5) -> 6103 | CQ5: =SUM(AH5:AK5) -> 8164 | CR5: =SUM(AL5:AO5) -> 10856 | CS5: =SUM(AP5:AS5) -> 12905 | CT5: =SUM(AT5:AW5) -> 11555 | CU5: =SUM(AX5:BA5) -> 15287 | CV5: =SUM(BB5:BE5) -> 13326 | CW5: =SUM(BF5:BI5) -> 15311 | CX5: =SUM(BJ5:BM5) -> 23424.023 | CY5: =SUM(BN5:BQ5) -> 36340.65 | CZ5: =SUM(BR5:BU5) -> 50551.096 | DA5: =SUM(BV5:BY5) -> 65724.263 | DB5: =SUM(BZ5:CC5) -> 81349.154 | DC5: =SUM(CD5:CG5) -> 95885.082
