Workbook

Sheet Summary
A1: Phillips 66 (PSX) - Elliott Activist Value Creation Model
A2: Investment Thesis: Streamline 66 Campaign
A4: CURRENT SITUATION
A5: Current Stock Price ($/share) | B5: 120.3 | C5: Source: Elliott Feb 2025
A6: Shares Outstanding (mm) | B6: 408
A7: Market Cap ($mm) | B7: =B5*B6 -> 49082.4
A8: Net Debt ($mm) | B8: 19100
A9: Total Enterprise Value ($mm) | B9: =B7+B8 -> 68182.4
A10: 2026E Consensus EBITDA ($mm) | B10: 10500 | C10: Elliott est. excl. TAR
A11: Current TEV/EBITDA Multiple | B11: =B9/B10 -> 6.4935619
A13: ELLIOTT VALUE CREATION PILLARS
A14: Pillar | B14: Value ($mm) | C14: Value ($/share) | D14: Description
A15: 1. Portfolio Streamline | B15: 14688 | C15: =B15/B6 -> 36 | D15: Sell Midstream, CPChem 50%, JET assets | F15: << where is this from
A16: 2. Refining Performance | B16: 7344 | C16: =B16/B6 -> 18 | D16: Close $3.75/bbl gap to Valero | F16: << where is this from
A17: 3. Enhanced Oversight | B17: 9792 | C17: =B17/B6 -> 24 | D17: Independent directors, CEO review | F17: << where is this from
A18: Total Value Creation | B18: =SUM(B15:B17) -> 31824 | C18: =SUM(C15:C17) -> 78
A20: TARGET PRICES
A21: Scenario | B21: Price ($/sh) | C21: Upside % | D21: IRR (3yr)
A22: Base Case | B22: =B5+C18 -> 198.3 | C22: =(B22-B5)/B5 -> 0.64837905 | D22: 0.22
A23: Bull Case (Marathon Path) | B23: 300 | C23: =(B23-B5)/B5 -> 1.4937656 | D23: 0.35
A24: Bear Case (Status Quo) | B24: 95 | C24: =(B24-B5)/B5 -> -0.21030756 | D24: -0.08
A26: INVESTMENT RECOMMENDATION
A27: Decision: | B27: INVEST (with conditions)
A28: Key Conditions: | B28: 1) Elliott board representation achieved
B29: 2) Midstream sale process initiated within 6 months
B30: 3) Refining cost cuts show evidence in Q1/Q2

Sheet Income Statement
A1: Phillips 66 - Consolidated Income Statement
A2: $ in millions, except per share data | I2: Major errors in financials, bad formatting
A4: Income Statement | B4: FY2022A | C4: FY2023A | D4: FY2024A | E4: FY2025E | F4: FY2026E | G4: FY2027E
A5: Revenue | B5: 169990 | C5: 147399 | D5: 143153 | E5: =D5*0.97 -> 138858.41 | F5: =E5*0.98 -> 136081.24 | G5: =F5*1.02 -> 138802.87
A6: Cost of Revenue | B6: 151561 | C6: 130063 | D6: 122654 | E6: =E5*0.87 -> 120806.82 | F6: =F5*0.86 -> 117029.87 | G6: =G5*0.85 -> 117982.44
A7: Gross Profit | B7: =B5-B6 -> 18429 | C7: =C5-C6 -> 17336 | D7: =D5-D6 -> 20499 | E7: =E5-E6 -> 18051.593 | F7: =F5-F6 -> 19051.374 | G7: =G5-G6 -> 20820.43 | I7: << FY24A is wrong
A8: Operating Expenses | B8: 8809 | C8: 9386 | D8: 9514 | E8: =D8*0.95 -> 9038.3 | F8: =E8*0.93 -> 8405.619 | G8: =F8*0.95 -> 7985.3381
A9: Operating Income (EBIT) | B9: =B7-B8 -> 9620 | C9: =C7-C8 -> 7950 | D9: =D7-D8 -> 10985 | E9: =E7-E8 -> 9013.2933 | F9: =F7-F8 -> 10645.755 | G9: =G7-G8 -> 12835.092 | I9: << FY24A is wrong
A10: Depreciation & Amortization | B10: 2800 | C10: 3000 | D10: 3300 | E10: 3400 | F10: 3200 | G10: 3000
A11: EBITDA | B11: =B9+B10 -> 12420 | C11: =C9+C10 -> 10950 | D11: =D9+D10 -> 14285 | E11: =E9+E10 -> 12413.293 | F11: =F9+F10 -> 13845.755 | G11: =G9+G10 -> 15835.092 | I11: << FY24A is wrong
A12: Interest Expense | B12: -560 | C12: -657 | D12: -819 | E12: -850 | F12: -750 | G12: -650
A13: Other Income | B13: 5579 | C13: 1718 | D13: 2189 | E13: 2000 | F13: 1800 | G13: 1500
A14: Pre-tax Income | B14: =B9+B12+B13 -> 14639 | C14: =C9+C12+C13 -> 9011 | D14: =D9+D12+D13 -> 12355 | E14: =E9+E12+E13 -> 10163.293 | F14: =F9+F12+F13 -> 11695.755 | G14: =G9+G12+G13 -> 13685.092
A15: Income Tax Expense | B15: -3248 | C15: -500 | D15: -340 | E15: =E14*-0.22 -> -2235.9245 | F15: =F14*-0.22 -> -2573.0661 | G15: =G14*-0.22 -> -3010.7202
A16: Net Income | B16: =B14+B15 -> 11391 | C16: =C14+C15 -> 8511 | D16: =D14+D15 -> 12015 | E16: =E14+E15 -> 7927.3688 | F16: =F14+F15 -> 9122.6888 | G16: =G14+G15 -> 10674.372
A18: Shares Outstanding (mm) | B18: 466 | C18: 430 | D18: 408 | E18: 390 | F18: 360 | G18: 330
A19: EPS | B19: =B16/B18 -> 24.444206 | C19: =C16/C18 -> 19.793023 | D19: =D16/D18 -> 29.448529 | E19: =E16/E18 -> 20.326587 | F19: =F16/F18 -> 25.340802 | G19: =G16/G18 -> 32.346581

Sheet Balance Sheet
A1: Phillips 66 - Consolidated Balance Sheet
A2: $ in millions | I2: hardcoded future values
I3: historicals are all correct
A4: Balance Sheet | B4: FY2022A | C4: FY2023A | D4: FY2024A | E4: FY2025E | F4: FY2026E | G4: FY2027E
A5: ASSETS
A6: Cash & Equivalents | B6: 6133 | C6: 3323 | D6: 1738 | E6: 2500 | F6: 4000 | G6: 5500
A7: Accounts Receivable | B7: 10985 | C7: 11730 | D7: 11033 | E7: 10500 | F7: 10000 | G7: 10200
A8: Inventory | B8: 3276 | C8: 3750 | D8: 3995 | E8: 3800 | F8: 3600 | G8: 3700
A9: Other Current Assets | B9: 1528 | C9: 1138 | D9: 1144 | E9: 1100 | F9: 1100 | G9: 1100
A10: Total Current Assets | B10: =SUM(B6:B9) -> 21922 | C10: =SUM(C6:C9) -> 19941 | D10: =SUM(D6:D9) -> 17910 | E10: =SUM(E6:E9) -> 17900 | F10: =SUM(F6:F9) -> 18700 | G10: =SUM(G6:G9) -> 20500
A12: PP&E, net | B12: 36158 | C12: 36828 | D12: 36564 | E12: 35000 | F12: 33000 | G12: 31500
A13: Long-Term Investments | B13: 14621 | C13: 14923 | D13: 14204 | E13: 8000 | F13: 7500 | G13: 7000
A14: Goodwill & Intangibles | B14: 2317 | C14: 2470 | D14: 2736 | E14: 2500 | F14: 2300 | G14: 2100
A15: Other Long-Term Assets | B15: 1095 | C15: 960 | D15: 994 | E15: 900 | F15: 850 | G15: 800
A16: Total Assets | B16: =B10+B12+B13+B14+B15 -> 76113 | C16: =C10+C12+C13+C14+C15 -> 75122 | D16: =D10+D12+D13+D14+D15 -> 72408 | E16: =E10+E12+E13+E14+E15 -> 64300 | F16: =F10+F12+F13+F14+F15 -> 62350 | G16: =G10+G12+G13+G14+G15 -> 61900
A18: LIABILITIES
A19: Accounts Payable | B19: 11323 | C19: 10901 | D19: 10304 | E19: 10000 | F19: 9500 | G19: 9700
A20: Short-Term Debt | B20: 506 | C20: 1457 | D20: 1801 | E20: 1500 | F20: 1200 | G20: 1000
A21: Other Current Liabilities | B21: 4060 | C21: 3498 | D21: 2982 | E21: 2800 | F21: 2600 | G21: 2500
A22: Total Current Liabilities | B22: =SUM(B19:B21) -> 15889 | C22: =SUM(C19:C21) -> 15856 | D22: =SUM(D19:D21) -> 15087 | E22: =SUM(E19:E21) -> 14300 | F22: =SUM(F19:F21) -> 13300 | G22: =SUM(G19:G21) -> 13200
A24: Long-Term Debt | B24: 17406 | C24: 18667 | D24: 19165 | E24: 16000 | F24: 13000 | G24: 10000
A25: Deferred Tax Liabilities | B25: 6671 | C25: 7424 | D25: 7101 | E25: 7000 | F25: 6800 | G25: 6600
A26: Other Long-Term Liabilities | B26: 2370 | C26: 1904 | D26: 2766 | E26: 2500 | F26: 2300 | G26: 2200
A27: Total Liabilities | B27: =B22+B24+B25+B26 -> 42336 | C27: =C22+C24+C25+C26 -> 43851 | D27: =D22+D24+D25+D26 -> 44119 | E27: =E22+E24+E25+E26 -> 39800 | F27: =F22+F24+F25+F26 -> 35400 | G27: =G22+G24+G25+G26 -> 32000
A29: SHAREHOLDERS' EQUITY
A30: Total Equity | B30: =B16-B27 -> 33777 | C30: =C16-C27 -> 31271 | D30: =D16-D27 -> 28289 | E30: =E16-E27 -> 24500 | F30: =F16-F27 -> 26950 | G30: =G16-G27 -> 29900
A32: Total Liab. & Equity | B32: =B27+B30 -> 76113 | C32: =C27+C30 -> 75122 | D32: =D27+D30 -> 72408 | E32: =E27+E30 -> 64300 | F32: =F27+F30 -> 62350 | G32: =G27+G30 -> 61900
A33: Balance Check | B33: =B16-B32 -> 0 | C33: =C16-C32 -> 0 | D33: =D16-D32 -> 0 | E33: =E16-E32 -> 0 | F33: =F16-F32 -> 0 | G33: =G16-G32 -> 0
A35: KEY RATIOS
A36: Total Debt | B36: =B20+B24 -> 17912 | C36: =C20+C24 -> 20124 | D36: =D20+D24 -> 20966 | E36: =E20+E24 -> 17500 | F36: =F20+F24 -> 14200 | G36: =G20+G24 -> 11000
A37: Net Debt | B37: =B36-B6 -> 11779 | C37: =C36-C6 -> 16801 | D37: =D36-D6 -> 19228 | E37: =E36-E6 -> 15000 | F37: =F36-F6 -> 10200 | G37: =G36-G6 -> 5500
A38: Debt/Equity | B38: =B36/B30 -> 0.53030168 | C38: =C36/C30 -> 0.64353554 | D38: =D36/D30 -> 0.74113613 | E38: =E36/E30 -> 0.71428571 | F38: =F36/F30 -> 0.52690167 | G38: =G36/G30 -> 0.36789298

Sheet Cash Flow
A1: Phillips 66 - Cash Flow Statement
A2: $ in millions
A4: Cash Flow Statement | B4: FY2022A | C4: FY2023A | D4: FY2024A | E4: FY2025E | F4: FY2026E | G4: FY2027E
A5: OPERATING ACTIVITIES | I5: Cash flow model not linked
A6: Net Income | B6: ='Income Statement'!B16 -> 11391 | C6: ='Income Statement'!C16 -> 8511 | D6: ='Income Statement'!D16 -> 12015 | E6: ='Income Statement'!E16 -> 7927.3688 | F6: ='Income Statement'!F16 -> 9122.6888 | G6: ='Income Statement'!G16 -> 10674.372 | I6: Historicals incorrect
A7: Depreciation & Amortization | B7: ='Income Statement'!B10 -> 2800 | C7: ='Income Statement'!C10 -> 3000 | D7: ='Income Statement'!D10 -> 3300 | E7: ='Income Statement'!E10 -> 3400 | F7: ='Income Statement'!F10 -> 3200 | G7: ='Income Statement'!G10 -> 3000
A8: Changes in Working Capital | B8: -1500 | C8: 800 | D8: 500 | E8: 300 | F8: 400 | G8: 200
A9: Other Operating Adjustments | B9: -200 | C9: 400 | D9: 200 | E9: 100 | F9: 100 | G9: 100
A10: Cash from Operations | B10: =SUM(B6:B9) -> 12491 | C10: =SUM(C6:C9) -> 12711 | D10: =SUM(D6:D9) -> 16015 | E10: =SUM(E6:E9) -> 11727.369 | F10: =SUM(F6:F9) -> 12822.689 | G10: =SUM(G6:G9) -> 13974.372
A12: INVESTING ACTIVITIES
A13: Capital Expenditures | B13: -2500 | C13: -2200 | D13: -2100 | E13: -2000 | F13: -1800 | G13: -1700
A14: Asset Sales / Dispositions | B14: 500 | C14: 392 | D14: 3500 | E14: 12000 | F14: 20000 | G14: 5000
A15: Cash from Investing | B15: =B13+B14 -> -2000 | C15: =C13+C14 -> -1808 | D15: =D13+D14 -> 1400 | E15: =E13+E14 -> 10000 | F15: =F13+F14 -> 18200 | G15: =G13+G14 -> 3300
A17: FINANCING ACTIVITIES
A18: Debt Issuance / (Repayment) | B18: -1500 | C18: 1200 | D18: 500 | E18: -4000 | F18: -4500 | G18: -4000
A19: Share Repurchases | B19: -3000 | C19: -4100 | D19: -3800 | E19: -6000 | F19: -10000 | G19: -3000
A20: Dividends Paid | B20: -1700 | C20: -1800 | D20: -1700 | E20: -1800 | F20: -1900 | G20: -2000
A21: Cash from Financing | B21: =SUM(B18:B20) -> -6200 | C21: =SUM(C18:C20) -> -4700 | D21: =SUM(D18:D20) -> -5000 | E21: =SUM(E18:E20) -> -11800 | F21: =SUM(F18:F20) -> -16400 | G21: =SUM(G18:G20) -> -9000
A23: Net Change in Cash | B23: =B10+B15+B21 -> 4291 | C23: =C10+C15+C21 -> 6203 | D23: =D10+D15+D21 -> 12415 | E23: =E10+E15+E21 -> 9927.3688 | F23: =F10+F15+F21 -> 14622.689 | G23: =G10+G15+G21 -> 8274.3717
A25: FREE CASH FLOW
A26: Operating Cash Flow | B26: =B10 -> 12491 | C26: =C10 -> 12711 | D26: =D10 -> 16015 | E26: =E10 -> 11727.369 | F26: =F10 -> 12822.689 | G26: =G10 -> 13974.372
A27: Less: CapEx | B27: =B13 -> -2500 | C27: =C13 -> -2200 | D27: =D13 -> -2100 | E27: =E13 -> -2000 | F27: =F13 -> -1800 | G27: =G13 -> -1700
A28: Free Cash Flow | B28: =B26+B27 -> 9991 | C28: =C26+C27 -> 10511 | D28: =D26+D27 -> 13915 | E28: =E26+E27 -> 9727.3688 | F28: =F26+F27 -> 11022.689 | G28: =G26+G27 -> 12274.372

Sheet Assumptions
A1: Phillips 66 - Key Assumptions
A3: ELLIOTT THESIS ASSUMPTIONS
A4: Assumption | B4: Value | C4: Units | D4: Source / Notes
A5: Current Stock Price | B5: 120.3 | C5: $/share | D5: Elliott presentation Feb 2025 | E5: correct
A6: Shares Outstanding | B6: 408 | C6: mm | D6: 10-K FY24
A7: 2026E Consensus EBITDA | B7: 10500 | C7: $mm | D7: Elliott estimate excl. TAR
A8: Management 2025 Mid-Cycle Target | B8: 14000 | C8: $mm | D8: Management guidance (missed)
A9: Current TEV/EBITDA | B9: 6.6 | C9: x | D9: Calculated
A11: PILLAR 1: PORTFOLIO STREAMLINE
A12: Midstream Sale Value (Gross) | B12: 50000 | C12: $mm | D12: 10.2x EBITDA multiple
A13: CPChem 50% Stake Value (Gross) | B13: 15000 | C13: $mm | D13: 7.5x EBITDA
A14: JET Germany/Austria Value (Gross) | B14: 3000 | C14: $mm | D14: Market estimate
A15: Tax Leakage Rate | B15: 0.22 | C15: % | D15: Elliott assumption
A16: Net Proceeds from Sales | B16: 48000 | C16: $mm | D16: After-tax
A18: PILLAR 2: REFINING PERFORMANCE
A19: PSX 2026E Refining EBITDA/bbl | B19: 4.87 | C19: $/bbl | D19: Elliott estimate
A20: VLO 2026E Refining EBITDA/bbl | B20: 6.76 | C20: $/bbl | D20: Valero benchmark
A21: Performance Gap | B21: 1.89 | C21: $/bbl | D21: PSX underperformance
A22: Refining Throughput | B22: 602 | C22: mm bbl/yr | D22: Capacity
A23: EBITDA Improvement Potential | B23: 1138 | C23: $mm/yr | D23: Gap closure opportunity
A25: PILLAR 3: ENHANCED OVERSIGHT
A26: Consultants Spent Since 2022 | B26: 300 | C26: $mm | D26: Elliott estimate
A27: Target Share Buyback Premium | B27: 0.15 | C27: % | D27: 15% above market
A28: Target Leverage Post-Restructure | B28: 1.2 | C28: x | D28: Net Debt/EBITDA
A30: VALUATION ASSUMPTIONS
A31: Target Multiple (Refining Pure-Play) | B31: 6 | C31: x | D31: Peer average
A32: Target Multiple (Midstream) | B32: 10.2 | C32: x | D32: MLP precedent
A33: Buyback Price Range Low | B33: 130 | C33: $/share | D33: 10% premium
A34: Buyback Price Range High | B34: 150 | C34: $/share | D34: 25% premium

Sheet Returns
A1: Phillips 66 - Investment Returns Analysis
A3: SCENARIO ANALYSIS
B4: Bear | C4: Base | D4: Bull
A5: Scenario Description | B5: Status Quo | C5: Elliott Plan Executed | D5: Marathon Path
A6: Entry Price ($/share) | B6: 120.3 | C6: 120.3 | D6: 120.3
A7: Exit Price ($/share) | B7: 95 | C7: 198 | D7: 300
A8: Holding Period (years) | B8: 3 | C8: 3 | D8: 3
A9: Dividends Received ($/share) | B9: 12 | C9: 15 | D9: 18
A10: Total Return ($) | B10: =B7-B6+B9 -> -13.3 | C10: =C7-C6+C9 -> 92.7 | D10: =D7-D6+D9 -> 197.7
A11: Total Return (%) | B11: =(B7+B9-B6)/B6 -> -0.11055694 | C11: =(C7+C9-C6)/C6 -> 0.77057357 | D11: =(D7+D9-D6)/D6 -> 1.6433915
A12: IRR | B12: -0.08 | C12: 0.22 | D12: 0.37
A13: MOIC | B13: =(B7+B9)/B6 -> 0.88944306 | C13: =(C7+C9)/C6 -> 1.7705736 | D13: =(D7+D9)/D6 -> 2.6433915
A16: PROBABILITY-WEIGHTED RETURN
A17: Scenario | B17: Probability | C17: Return % | D17: Weighted Return
A18: Bear Case | B18: 0.2 | C18: =B11 -> -0.11055694 | D18: =B18*C18 -> -0.022111388
A19: Base Case | B19: 0.55 | C19: =C11 -> 0.77057357 | D19: =B19*C19 -> 0.42381546
A20: Bull Case | B20: 0.25 | C20: =D11 -> 1.6433915 | D20: =B20*C20 -> 0.41084788
A21: Expected Return | D21: =SUM(D18:D20) -> 0.81255195
A24: KEY RISKS
A25: 1. Execution Risk | B25: Management track record is poor; $14B EBITDA target missed by $5.7B
A26: 2. Refining Cycle | B26: Weak crack spreads could delay value realization
A27: 3. Tax Leakage | B27: Asset sales may trigger higher taxes than 22% assumed
A28: 4. Buyer Interest | B28: CPChem sale requires Chevron cooperation; Midstream needs buyer
A29: 5. Board Resistance | B29: Management defending conglomerate structure
A30: 6. Multiple Compression | B30: Energy sector de-rating could offset operational gains
A32: INVESTMENT DECISION
A33: Recommendation: | B33: INVEST
A34: Rationale: | B34: Probability-weighted expected return of ~50%+ over 3 years is attractive
B35: Elliott's track record with activist campaigns is strong
B36: Downside protected by asset values and dividend yield (~4%)
A38: Key Conditions for Investment: | B38: 1. Elliott achieves board representation
B39: 2. Midstream sale/spin process initiated within 6 months
B40: 3. Evidence of refining cost improvements in Q1/Q2 results
B41: 4. Management commits to specific buyback targets
