Workbook

Sheet Summary

Sheet Income Statement
A1: Income Statement (USD mm)
A3: EBITDA | B3: =Assumptions!B3 | C3: =Assumptions!B4 | D3: =Assumptions!B5
A4: D&A | B4: =B3*0.25 | C4: =C3*0.25 | D4: =D3*0.25
A5: EBIT | B5: =B3-B4 | C5: =C3-C4 | D5: =D3-D4
A6: Taxes | B6: =B5*Assumptions!B7 | C6: =C5*Assumptions!B7 | D6: =D5*Assumptions!B7
A7: Net Income | B7: =B5-B6 | C7: =C5-C6 | D7: =D5-D6

Sheet Balance Sheet
A1: Balance Sheet (USD mm)
A3: Net Debt | B3: 20000 | C3: =B3-Income Statement!C7 | D3: =C3-Income Statement!D7

Sheet Cash Flow
A1: Cash Flow (USD mm)
A3: Net Income | B3: =Income Statement!B7 | C3: =Income Statement!C7 | D3: =Income Statement!D7
A4: Add: D&A | B4: =Income Statement!B4 | C4: =Income Statement!C4 | D4: =Income Statement!D4
A5: Operating Cash Flow | B5: =B3+B4 | C5: =C3+C4 | D5: =D3+D4
A6: Capex | B6: =Income Statement!B3*Assumptions!B6 | C6: =Income Statement!C3*Assumptions!B6 | D6: =Income Statement!D3*Assumptions!B6
A7: Free Cash Flow | B7: =B5-B6 | C7: =C5-C6 | D7: =D5-D6

Sheet Assumptions
A1: Key Assumptions (USD mm)
A3: FY24A EBITDA | B3: 10488
A4: FY25E EBITDA (Consensus) | B4: 11626
A5: FY26E EBITDA (Post-Activist Base) | B5: 13000
A6: Capex % of EBITDA | B6: 0.08
A7: Tax Rate | B7: 0.22

Sheet Returns
A1: Returns Analysis
A3: Entry EV/EBITDA | B3: 6.6
A4: Exit EV/EBITDA (Base) | B4: 8
A5: Implied IRR (Base) | B5: High-teens to 20%
