Workbook
Name circ: vDIA!$T$10
Name IQ_CH: 110000
Name IQ_CQ: 5000
Name IQ_CY: 10000
Name IQ_DAILY: 500000
Name IQ_EXPENSE_CODE_: "NB12825"
Name IQ_FH: 100000
Name IQ_FQ: 500
Name IQ_FY: 1000
Name IQ_LTM: 2000
Name IQ_MONTH: 15000
Name IQ_NTM: 6000
Name IQ_WEEK: 50000
Name IQ_YTD: 3000
Name tax: #REF!

Sheet Financials
B2: Bolthouse Farms Financial Summary
B3: ($ millions, FYE March 31st)
C5: Historical | F5: Budget | G5: Projected
C6: 2003 | D6: 2004 | E6: 2005 | F6: 2006 | G6: 2007 | H6: 2008 | I6: 2009 | J6: 2010 | K6: 2011
B7: Revenue:
B8: Cut & Peel | C8: 211.9 | D8: 217 | E8: 207.5 | F8: 231.2 | G8: 254 | H8: 269.2 | I8: 282.7 | J8: 291.1 | K8: 299.74959
B9: Organic | C9: 19 | D9: 20.9 | E9: 26.5 | F9: 40.6 | G9: 51.4 | H9: 57.8 | I9: 64.7 | J9: 71.1 | K9: 78.133076
B10: Beverage | C10: 0.1 | D10: 7.4 | E10: 37.8 | F10: 88 | G10: 169.6 | H10: 219.6 | I10: 270.8 | J10: 321.4 | K10: 381.4548
B11: Other | C11: 98.8 | D11: 106.3 | E11: 123.3 | F11: 126.4 | G11: 133.1 | H11: 136.1 | I11: 139.5 | J11: 144.1 | K11: 148.85168
B12: Total Revenue | C12: 329.8 | D12: 351.6 | E12: 395.1 | F12: 486.2 | G12: 608.1 | H12: 682.7 | I12: 757.7 | J12: 827.7 | K12: 908.18915
B14: Gross Profit:
B15: Cut & Peel | C15: 72.4 | D15: 76.3 | E15: 61 | F15: 70.3 | G15: 78.2 | H15: 83.4 | I15: 87.6 | J15: 90.3 | K15: 92.983127
B16: Organic | C16: 6 | D16: 6.9 | E16: 8.2 | F16: 12.7 | G16: 16.2 | H16: 18.3 | I16: 20.6 | J16: 22.6 | K16: 24.835549
B17: Beverage | C17: -1.5 | D17: -4.1 | E17: 6.3 | F17: 33.3 | G17: 57.6 | H17: 75.5 | I17: 97.2 | J17: 122.1 | K17: 144.91484
B18: Other | C18: 13 | D18: 6.7 | E18: 10.2 | F18: 14.8 | G18: 20.3 | H18: 22.7 | I18: 25.6 | J18: 29 | K18: 29.956272
B19: Gross Profit | C19: 89.9 | D19: 85.8 | E19: 85.7 | F19: 131.1 | G19: 172.3 | H19: 199.9 | I19: 231 | J19: 264 | K19: 292.68979
B21: Operating Expenses | C21: 24 | D21: 27.3 | E21: 28 | F21: 35.9 | G21: 41.4 | H21: 44.9 | I21: 48.8 | J21: 53.1 | K21: 61.280958
B23: EBIT | C23: 65.9 | D23: 58.5 | E23: 57.7 | F23: 95.2 | G23: 130.9 | H23: 155 | I23: 182.2 | J23: 210.9 | K23: 231.40883
B25: Plus: D&A | C25: 28 | D25: 34.7 | E25: 32.6 | F25: 30.9 | G25: 38.8 | H25: 43.7 | I25: 48.4 | J25: 52.7 | K25: 57.824778
B27: EBITDA | C27: 93.9 | D27: 93.2 | E27: 90.3 | F27: 126.1 | G27: 169.7 | H27: 198.7 | I27: 230.6 | J27: 263.6 | K27: 289.23361
B29: Clean SG&A | C29: =+C21-C25 -> -4 | D29: =+D21-D25 -> -7.4 | E29: =+E21-E25 -> -4.6 | F29: =+F21-F25 -> 5 | G29: =+G21-G25 -> 2.6 | H29: =+H21-H25 -> 1.2 | I29: =+I21-I25 -> 0.4 | J29: =+J21-J25 -> 0.4 | K29: =+K21-K25 -> 3.4561805
B32: Capital Expenditures
B33: Maintenance | C33: 5.9 | D33: 4.9 | E33: 5.3 | F33: 8.4 | G33: 6.5 | H33: 6.5 | I33: 6.5 | J33: 6.5 | K33: 6.5
B34: Expansion | C34: 51.8 | D34: 30.5 | E34: 42.2 | F34: 109 | G34: 20.5 | H34: 23.5 | I34: 8.5 | J34: 8.5 | K34: 8.5
B35: Total Capital Expenditures | C35: 57.7 | D35: 35.4 | E35: 47.5 | F35: 117.4 | G35: 27 | H35: 30 | I35: 15 | J35: 15 | K35: 15
C37: Historical | F37: Budget
C38: 2003 | D38: 2004 | E38: 2005 | F38: 2006
B39: Assets:
B40: Cash | D40: 4.4 | E40: 3 | F40: 0
B41: Accounts Receivable | D41: 33.1 | E41: 38.6 | F41: 47.500177
B42: Inventory | D42: 45.8 | E42: 56.3 | F42: 69.281346
B43: Prepayments and Other Current Assets | D43: 6.5 | E43: 7.4 | F43: 9.1062516
B44: Total Current Assets | D44: 89.8 | E44: 105.3 | F44: 125.88778
B45: PP&E | D45: 232.7 | E45: 238.1 | F45: 324.6
B46: Other | D46: 9.1 | E46: 16.9 | F46: 20.79671
B47: Total Assets | D47: 331.6 | E47: 360.3 | F47: 471.28448
B49: Liabilities and Shareholder Equity
B50: Accounts Payable | D50: 17.3 | E50: 26.3 | F50: 30.184648
B51: Other Current Liabilities | D51: 12.2 | E51: 18.8 | F51: 23.134801
B52: Total Current Liabilities | D52: 29.5 | E52: 45.1 | F52: 53.319449
B53: Long-Term Debt | D53: 28.8 | E53: 24.8 | F53: 60.860556
B54: Other Long-Term Liabilities | D54: 19.5 | E54: 16.5 | F54: 20.30448
B55: Total Liabilities | D55: 77.8 | E55: 86.4 | F55: 134.48448
B56: Shareholder Equity | D56: 253.8 | E56: 273.9 | F56: 336.8
B57: Total Liabilities and Shareholder Equity | D57: 331.6 | E57: 360.3 | F57: 471.28448

Sheet vDIA
A1: in USDm unless otherwise stated
A3: x | B3: Txn assumptions
B5: Financing | C5: xEBITDA | D5: Floor | E5: Margin | F5: Interest rate | G5: Term | H5: Amort' | I5: Fee
B6: TLB | C6: 3 | D6: 0.03 | E6: 0.05 | F6: =+E6+D6 -> 0.08 | G6: 8 | H6: =+G6 -> 8 | I6: 0.04
B7: Snr sub | C7: 1.5 | F7: 0.1 | I7: 0.05
B9: Deal parameters | G9: S&U | L9: Purchase accounting | Q9: Switches
B10: FY26 EBITDA | E10: =+I44 -> 126.1 | G10: TLB | J10: =+C6*$I$44 -> 378.3 | L10: Purchase price | O10: =+J15 -> 947.93944 | Q10: Circularity | T10: 1
B11: Entry multiple | E11: 8 | G11: Snr sub | J11: =+C7*$I$44 -> 189.15 | L11: (-) net identifieable assets | O11: =+I70 -> 336.8 | Q11: Snr sub sweep | T11: 1
B12: Entry EV | E12: =+E11*E10 -> 1008.8 | G12: Sponsor equity | J12: =+J13-J11-J10 -> 465.9395 | L12: Goodwill | O12: =+O10-O11 -> 611.13944
G13: Total sources | J13: =+J18 -> 1033.3895
B14: (-) net debt | E14: =+I66-I50 -> 60.860556 | L14: Other assumptions
B15: Purchase EqV | E15: =+E12-E14 -> 947.93944 | G15: Purchase equity | J15: =+E15 -> 947.93944 | L15: Amort of DFF | O15: 5
G16: Refi debt | J16: =+I66 -> 60.860556 | L16: MIP | O16: 0.1
G17: Financing fees | J17: =+I6*J10+J11*I7 -> 24.5895 | L17: Tax | O17: 0.37
G18: Total uses | J18: =SUM(J15:J17) -> 1033.3895 | L18: Exit multiple | O18: 7
F20: Historical | G20: Historical | H20: Historical | I20: Budget | L20: Projected | M20: Projected | N20: Projected | O20: Projected | P20: Projected
A21: x | B21: P&L | F21: 2003 | G21: =+F21+1 -> 2004 | H21: =+G21+1 -> 2005 | I21: =+H21+1 -> 2006 | L21: =+I21+1 -> 2007 | M21: =+L21+1 -> 2008 | N21: =+M21+1 -> 2009 | O21: =+N21+1 -> 2010 | P21: =+O21+1 -> 2011
B22: Revenue | F22: =+Financials!C12 -> 329.8 | G22: =+Financials!D12 -> 351.6 | H22: =+Financials!E12 -> 395.1 | I22: =+Financials!F12 -> 486.2 | L22: =+Financials!G12 -> 608.1 | M22: =+Financials!H12 -> 682.7 | N22: =+Financials!I12 -> 757.7 | O22: =+Financials!J12 -> 827.7 | P22: =+Financials!K12 -> 908.18915
B23: % YoY
B25: Gross profit | F25: =+Financials!C19 -> 89.9 | G25: =+Financials!D19 -> 85.8 | H25: =+Financials!E19 -> 85.7 | I25: =+Financials!F19 -> 131.1 | L25: =+Financials!G19 -> 172.3 | M25: =+Financials!H19 -> 199.9 | N25: =+Financials!I19 -> 231 | O25: =+Financials!J19 -> 264 | P25: =+Financials!K19 -> 292.68979
B26: % margin | F26: =+F25/F22 -> 0.27258945 | G26: =+G25/G22 -> 0.2440273 | H26: =+H25/H22 -> 0.21690711 | I26: =+I25/I22 -> 0.26964212 | L26: =+L25/L22 -> 0.28334156 | M26: =+M25/M22 -> 0.29280797 | N26: =+N25/N22 -> 0.30487 | O26: =+O25/O22 -> 0.31895614 | P26: =+P25/P22 -> 0.32227845
B28: Opex | F28: =+Financials!C21*-1 -> -24 | G28: =+Financials!D21*-1 -> -27.3 | H28: =+Financials!E21*-1 -> -28 | I28: =+Financials!F21*-1 -> -35.9 | L28: =+Financials!G21*-1 -> -41.4 | M28: =+Financials!H21*-1 -> -44.9 | N28: =+Financials!I21*-1 -> -48.8 | O28: =+Financials!J21*-1 -> -53.1 | P28: =+Financials!K21*-1 -> -61.280958
B30: EBIT | F30: =+F28+F25 -> 65.9 | G30: =+G28+G25 -> 58.5 | H30: =+H28+H25 -> 57.7 | I30: =+I28+I25 -> 95.2 | L30: =+L28+L25 -> 130.9 | M30: =+M28+M25 -> 155 | N30: =+N28+N25 -> 182.2 | O30: =+O28+O25 -> 210.9 | P30: =+P28+P25 -> 231.40883
B31: % margin | F31: =+F30/F22 -> 0.19981807 | G31: =+G30/G22 -> 0.16638225 | H31: =+H30/H22 -> 0.14603898 | I31: =+I30/I22 -> 0.1958042 | L31: =+L30/L22 -> 0.21526065 | M31: =+M30/M22 -> 0.2270397 | N31: =+N30/N22 -> 0.24046456 | O31: =+O30/O22 -> 0.25480246 | P31: =+P30/P22 -> 0.25480246
B33: Interest | L33: =+IF(circ=1, L107+L112, 0) -> -46.737906 | M33: =+IF(circ=1, M107+M112, 0) -> -40.452487 | N33: =+IF(circ=1, N107+N112, 0) -> -33.436081 | O33: =+IF(circ=1, O107+O112, 0) -> -30.264 | P33: =+IF(circ=1, P107+P112, 0) -> -30.264
B34: Amort DFF | L34: =+MIN($J$17/$O$15, $J$17+SUM($J$34:K34))*-1 -> -4.9179 | M34: =+MIN($J$17/$O$15, $J$17+SUM($J$34:L34))*-1 -> -4.9179 | N34: =+MIN($J$17/$O$15, $J$17+SUM($J$34:M34))*-1 -> -4.9179 | O34: =+MIN($J$17/$O$15, $J$17+SUM($J$34:N34))*-1 -> -4.9179 | P34: =+MIN($J$17/$O$15, $J$17+SUM($J$34:O34))*-1 -> -4.9179
B36: EBT | L36: =+L34+L33+L30 -> 79.244194 | M36: =+M34+M33+M30 -> 109.62961 | N36: =+N34+N33+N30 -> 143.84602 | O36: =+O34+O33+O30 -> 175.7181 | P36: =+P34+P33+P30 -> 196.22693
B38: Tax rate | L38: =+$O$17 -> 0.37 | M38: =+$O$17 -> 0.37 | N38: =+$O$17 -> 0.37 | O38: =+$O$17 -> 0.37 | P38: =+$O$17 -> 0.37
B40: Net income | L40: =+L36*(1-L38) -> 49.923842 | M40: =+M36*(1-M38) -> 69.066656 | N40: =+N36*(1-N38) -> 90.622992 | O40: =+O36*(1-O38) -> 110.7024 | P40: =+P36*(1-P38) -> 123.62297
B42: Memo
B43: D&A | F43: =+Financials!C25 -> 28 | G43: =+Financials!D25 -> 34.7 | H43: =+Financials!E25 -> 32.6 | I43: =+Financials!F25 -> 30.9 | L43: =+Financials!G25 -> 38.8 | M43: =+Financials!H25 -> 43.7 | N43: =+Financials!I25 -> 48.4 | O43: =+Financials!J25 -> 52.7 | P43: =+Financials!K25 -> 57.824778
B44: EBITDA | F44: =+F43+F30 -> 93.9 | G44: =+G43+G30 -> 93.2 | H44: =+H43+H30 -> 90.3 | I44: =+I43+I30 -> 126.1 | L44: =+L43+L30 -> 169.7 | M44: =+M43+M30 -> 198.7 | N44: =+N43+N30 -> 230.6 | O44: =+O43+O30 -> 263.6 | P44: =+P43+P30 -> 289.23361
B46: Capex | F46: =+Financials!C35 -> 57.7 | G46: =+Financials!D35 -> 35.4 | H46: =+Financials!E35 -> 47.5 | I46: =+Financials!F35 -> 117.4 | L46: =+Financials!G35 -> 27 | M46: =+Financials!H35 -> 30 | N46: =+Financials!I35 -> 15 | O46: =+Financials!J35 -> 15 | P46: =+Financials!K35 -> 15
I48: Budget | J48: Adj. | K48: PF | L48: Projected | M48: Projected | N48: Projected | O48: Projected | P48: Projected
A49: x | B49: BS | I49: 2006 | K49: 2006 | L49: =+I49+1 -> 2007 | M49: =+L49+1 -> 2008 | N49: =+M49+1 -> 2009 | O49: =+N49+1 -> 2010 | P49: =+O49+1 -> 2011
B50: =+Financials!B40 -> Cash | I50: =+Financials!F40 -> 0 | K50: =+I50+J50 -> 0 | L50: =+K50+L114 -> 0 | M50: =+L50+M114 -> 0 | N50: =+M50+N114 -> 54.793978 | O50: =+N50+O114 -> 198.30128 | P50: =+O50+P114 -> 357.96747
B51: =+Financials!B41 -> Accounts Receivable | I51: =+Financials!F41 -> 47.500177 | K51: =+I51+J51 -> 47.500177 | L51: =+L77/365*L22 -> 59.409415 | M51: =+M77/365*M22 -> 66.697596 | N51: =+N77/365*N22 -> 74.024854 | O51: =+O77/365*O22 -> 80.863629 | P51: =+P77/365*P22 -> 88.727161
B52: =+Financials!B42 -> Inventory | I52: =+Financials!F42 -> 69.281346 | K52: =+I52+J52 -> 69.281346 | L52: =+L78/365*(L22-L25) -> 85.02622 | M52: =+M78/365*(M22-M25) -> 94.196097 | N52: =+N78/365*(N22-N25) -> 102.76115 | O52: =+O78/365*(O22-O25) -> 109.97999 | P52: =+P78/365*(P22-P25) -> 120.08624
B53: =+Financials!B43 -> Prepayments and Other Current Assets | I53: =+Financials!F43 -> 9.1062516 | K53: =+I53+J53 -> 9.1062516 | L53: =+L79*L22 -> 11.38937 | M53: =+M79*M22 -> 12.786586 | N53: =+N79*N22 -> 14.191293 | O53: =+O79*O22 -> 15.502354 | P53: =+P79*P22 -> 17.00987
B54: Current assets | I54: =+I53+I52+I51+I50 -> 125.88778 | K54: =+K53+K52+K51+K50 -> 125.88778 | L54: =+L53+L52+L51+L50 -> 155.82501 | M54: =+M53+M52+M51+M50 -> 173.68028 | N54: =+N53+N52+N51+N50 -> 245.77128 | O54: =+O53+O52+O51+O50 -> 404.64725 | P54: =+P53+P52+P51+P50 -> 583.79075
B56: Deferred financing fees | J56: =+J17 -> 24.5895 | K56: =+I56+J56 -> 24.5895 | L56: =+K56+L34 -> 19.6716 | M56: =+L56+M34 -> 14.7537 | N56: =+M56+N34 -> 9.8358 | O56: =+N56+O34 -> 4.9179 | P56: =+O56+P34 -> 0
B57: Goodwill | J57: =+O12 -> 611.13944 | K57: =+I57+J57 -> 611.13944 | L57: =+K57 -> 611.13944 | M57: =+L57 -> 611.13944 | N57: =+M57 -> 611.13944 | O57: =+N57 -> 611.13944 | P57: =+O57 -> 611.13944
B58: PPE | I58: =+Financials!F45 -> 324.6 | K58: =+I58+J58 -> 324.6 | L58: =+K58+L46-L43 -> 312.8 | M58: =+L58+M46-M43 -> 299.1 | N58: =+M58+N46-N43 -> 265.7 | O58: =+N58+O46-O43 -> 228 | P58: =+O58+P46-P43 -> 185.17522
B59: Other | I59: =+Financials!F46 -> 20.79671 | K59: =+I59+J59 -> 20.79671 | L59: =+K59 -> 20.79671 | M59: =+L59 -> 20.79671 | N59: =+M59 -> 20.79671 | O59: =+N59 -> 20.79671 | P59: =+O59 -> 20.79671
B60: Total assets | I60: =+I59+I58+I54+I57+I56 -> 471.28448 | K60: =+K59+K58+K54+K57+K56 -> 1107.0134 | L60: =+L59+L58+L54+L57+L56 -> 1120.2328 | M60: =+M59+M58+M54+M57+M56 -> 1119.4701 | N60: =+N59+N58+N54+N57+N56 -> 1153.2432 | O60: =+O59+O58+O54+O57+O56 -> 1269.5013 | P60: =+P59+P58+P54+P57+P56 -> 1400.9021
B62: =+Financials!B50 -> Accounts Payable | I62: =+Financials!F50 -> 30.184648 | K62: =+I62+J62 -> 30.184648 | L62: =+L80/365*(L22-L25) -> 37.044409 | M62: =+M80/365*(M22-M25) -> 41.03956 | N62: =+N80/365*(N22-N25) -> 44.771202 | O62: =+O80/365*(O22-O25) -> 47.916322 | P62: =+P80/365*(P22-P25) -> 52.319435
B63: =+Financials!B51 -> Other Current Liabilities | I63: =+Financials!F51 -> 23.134801 | K63: =+I63+J63 -> 23.134801 | L63: =+L81*(L22-L25) -> 28.392415 | M63: =+M81*(M22-M25) -> 31.454469 | N63: =+N81*(N22-N25) -> 34.314559 | O63: =+O81*(O22-O25) -> 36.725113 | P63: =+P81*(P22-P25) -> 40.099846
B64: Current liabilities | I64: =+I63+I62 -> 53.319449 | K64: =+K63+K62 -> 53.319449 | L64: =+L63+L62 -> 65.436823 | M64: =+M63+M62 -> 72.49403 | N64: =+N63+N62 -> 79.085761 | O64: =+O63+O62 -> 84.641435 | P64: =+P63+P62 -> 92.419281
B66: LT debt | I66: =+Financials!F53 -> 60.860556 | J66: =-I66+J10+J11 -> 506.58944 | K66: =+I66+J66 -> 567.45 | L66: =+L106+L111 -> 518.62811 | M66: =+M106+M111 -> 441.74162 | N66: =+N106+N111 -> 378.3 | O66: =+O106+O111 -> 378.3 | P66: =+P106+P111 -> 378.3
B67: Other LT liabilities | I67: =+Financials!F54 -> 20.30448 | K67: =+I67+J67 -> 20.30448 | L67: =+K67 -> 20.30448 | M67: =+L67 -> 20.30448 | N67: =+M67 -> 20.30448 | O67: =+N67 -> 20.30448 | P67: =+O67 -> 20.30448
B68: Total liabilities | I68: =+I67+I66+I64 -> 134.48448 | K68: =+K67+K66+K64 -> 641.07393 | L68: =+L67+L66+L64 -> 604.36942 | M68: =+M67+M66+M64 -> 534.54013 | N68: =+N67+N66+N64 -> 477.69024 | O68: =+O67+O66+O64 -> 483.24591 | P68: =+P67+P66+P64 -> 491.02376
B70: SHE | I70: =+Financials!F56 -> 336.8 | J70: =-I70+J12 -> 129.1395 | K70: =+I70+J70 -> 465.9395 | L70: =+K70+L40 -> 515.86334 | M70: =+L70+M40 -> 584.93 | N70: =+M70+N40 -> 675.55299 | O70: =+N70+O40 -> 786.25539 | P70: =+O70+P40 -> 909.87836
B72: CHECK | I72: =+I70+I68-I60 -> 0 | K72: =+K70+K68-K60 -> 0 | L72: =+L70+L68-L60 -> 0 | M72: =+M70+M68-M60 -> 0 | N72: =+N70+N68-N60 -> 0 | O72: =+O70+O68-O60 -> 0 | P72: =+P70+P68-P60 -> 0
B74: Memo
B75: NWC | K75: =+SUM(K51:K53)-SUM(K62:K63) -> 72.568326 | L75: =+SUM(L51:L53)-SUM(L62:L63) -> 90.388182 | M75: =+SUM(M51:M53)-SUM(M62:M63) -> 101.18625 | N75: =+SUM(N51:N53)-SUM(N62:N63) -> 111.89154 | O75: =+SUM(O51:O53)-SUM(O62:O63) -> 121.70454 | P75: =+SUM(P51:P53)-SUM(P62:P63) -> 133.40399
B77: DSO | I77: =+I51/I22*365 -> 35.659327 | L77: =+$I$77 -> 35.659327 | M77: =+$I$77 -> 35.659327 | N77: =+$I$77 -> 35.659327 | O77: =+$I$77 -> 35.659327 | P77: =+$I$77 -> 35.659327
B78: Inventory days | I78: =+I52/(I22-I25)*365 -> 71.212874 | L78: =+$I$78 -> 71.212874 | M78: =+$I$78 -> 71.212874 | N78: =+$I$78 -> 71.212874 | O78: =+$I$78 -> 71.212874 | P78: =+$I$78 -> 71.212874
B79: Prepayments and others as a % of revenue | I79: =+I53/I22 -> 0.018729436 | L79: =+$I$79 -> 0.018729436 | M79: =+$I$79 -> 0.018729436 | N79: =+$I$79 -> 0.018729436 | O79: =+$I$79 -> 0.018729436 | P79: =+$I$79 -> 0.018729436
B80: DPO | I80: =+I62/(I22-I25)*365 -> 31.02618 | L80: =+$I$80 -> 31.02618 | M80: =+$I$80 -> 31.02618 | N80: =+$I$80 -> 31.02618 | O80: =+$I$80 -> 31.02618 | P80: =+$I$80 -> 31.02618
B81: Other current liabilities as a % of COGS | I81: =+I63/(I22-I25) -> 0.065150102 | L81: =+$I$81 -> 0.065150102 | M81: =+$I$81 -> 0.065150102 | N81: =+$I$81 -> 0.065150102 | O81: =+$I$81 -> 0.065150102 | P81: =+$I$81 -> 0.065150102
L83: Projected | M83: Projected | N83: Projected | O83: Projected | P83: Projected
A84: x | B84: CFS | L84: 2007 | M84: =+L84+1 -> 2008 | N84: =+M84+1 -> 2009 | O84: =+N84+1 -> 2010 | P84: =+O84+1 -> 2011
B85: Net income | L85: =+L40 -> 49.923842 | M85: =+M40 -> 69.066656 | N85: =+N40 -> 90.622992 | O85: =+O40 -> 110.7024 | P85: =+P40 -> 123.62297
B86: D&A | L86: =+L43 -> 38.8 | M86: =+M43 -> 43.7 | N86: =+N43 -> 48.4 | O86: =+O43 -> 52.7 | P86: =+P43 -> 57.824778
B87: Amort of DFF | L87: =+L34*-1 -> 4.9179 | M87: =+M34*-1 -> 4.9179 | N87: =+N34*-1 -> 4.9179 | O87: =+O34*-1 -> 4.9179 | P87: =+P34*-1 -> 4.9179
B88: Chg in NWC | L88: =+K75-L75 -> -17.819856 | M88: =+L75-M75 -> -10.798066 | N88: =+M75-N75 -> -10.70529 | O88: =+N75-O75 -> -9.8130014 | P88: =+O75-P75 -> -11.699452
B89: Operating CF | L89: =+SUM(L85:L88) -> 75.821886 | M89: =+SUM(M85:M88) -> 106.88649 | N89: =+SUM(N85:N88) -> 133.2356 | O89: =+SUM(O85:O88) -> 158.5073 | P89: =+SUM(P85:P88) -> 174.66619
B91: Capex | L91: =+L46*-1 -> -27 | M91: =+M46*-1 -> -30 | N91: =+N46*-1 -> -15 | O91: =+O46*-1 -> -15 | P91: =+P46*-1 -> -15
B92: Repayment of debt | L92: =+L105+L110 -> -48.821886 | M92: =+M105+M110 -> -76.88649 | N92: =+N105+N110 -> -63.441624 | O92: =+O105+O110 -> 0 | P92: =+P105+P110 -> 0
B94: Net cash flows | L94: =+L92+L91+L89 -> 0 | M94: =+M92+M91+M89 -> 0 | N94: =+N92+N91+N89 -> 54.793978 | O94: =+O92+O91+O89 -> 143.5073 | P94: =+P92+P91+P89 -> 159.66619
K96: PF | L96: Projected | M96: Projected | N96: Projected | O96: Projected | P96: Projected
A97: x | B97: Debt schedule | K97: 2006 | L97: =+K97+1 -> 2007 | M97: =+L97+1 -> 2008 | N97: =+M97+1 -> 2009 | O97: =+N97+1 -> 2010 | P97: =+O97+1 -> 2011
B98: FCF | L98: =+L89+L91 -> 48.821886 | M98: =+M89+M91 -> 76.88649 | N98: =+N89+N91 -> 118.2356 | O98: =+O89+O91 -> 143.5073 | P98: =+P89+P91 -> 159.66619
B99: BoP cash | L99: =+K50 -> 0 | M99: =+L50 -> 0 | N99: =+M50 -> 0 | O99: =+N50 -> 54.793978 | P99: =+O50 -> 198.30128
B100: CFADS | L100: =+L99+L98 -> 48.821886 | M100: =+M99+M98 -> 76.88649 | N100: =+N99+N98 -> 118.2356 | O100: =+O99+O98 -> 198.30128 | P100: =+P99+P98 -> 357.96747
B102: Year | L102: 1 | M102: =+L102+1 -> 2 | N102: =+M102+1 -> 3 | O102: =+N102+1 -> 4 | P102: =+O102+1 -> 5
B104: BoP TLB | L104: =+K106 -> 378.3 | M104: =+L106 -> 378.3 | N104: =+M106 -> 378.3 | O104: =+N106 -> 378.3 | P104: =+O106 -> 378.3
B105: Repayment | L105: =+IF(L102=$G$6, L104, 0)*-1 -> 0 | M105: =+IF(M102=$G$6, M104, 0)*-1 -> 0 | N105: =+IF(N102=$G$6, N104, 0)*-1 -> 0 | O105: =+IF(O102=$G$6, O104, 0)*-1 -> 0 | P105: =+IF(P102=$G$6, P104, 0)*-1 -> 0
B106: EoP TLB | K106: =+$J$10 -> 378.3 | L106: =SUM(L104:L105) -> 378.3 | M106: =SUM(M104:M105) -> 378.3 | N106: =SUM(N104:N105) -> 378.3 | O106: =SUM(O104:O105) -> 378.3 | P106: =SUM(P104:P105) -> 378.3
B107: Interest | L107: =+AVERAGE(K106:L106)*$F$6*-1 -> -30.264 | M107: =+AVERAGE(L106:M106)*$F$6*-1 -> -30.264 | N107: =+AVERAGE(M106:N106)*$F$6*-1 -> -30.264 | O107: =+AVERAGE(N106:O106)*$F$6*-1 -> -30.264 | P107: =+AVERAGE(O106:P106)*$F$6*-1 -> -30.264
B109: BoP Snr sub | L109: =+K111 -> 189.15 | M109: =+L111 -> 140.32811 | N109: =+M111 -> 63.441624 | O109: =+N111 -> 0 | P109: =+O111 -> 0
B110: Repayment | L110: =+MIN(L109, L100+L105)*-1*$T$11 -> -48.821886 | M110: =+MIN(M109, M100+M105)*-1*$T$11 -> -76.88649 | N110: =+MIN(N109, N100+N105)*-1*$T$11 -> -63.441624 | O110: =+MIN(O109, O100+O105)*-1*$T$11 -> 0 | P110: =+MIN(P109, P100+P105)*-1*$T$11 -> 0
B111: EoP Snr sub | K111: =+J11 -> 189.15 | L111: =SUM(L109:L110) -> 140.32811 | M111: =SUM(M109:M110) -> 63.441624 | N111: =SUM(N109:N110) -> 0 | O111: =SUM(O109:O110) -> 0 | P111: =SUM(P109:P110) -> 0
B112: Interest | L112: =+AVERAGE(K111:L111)*$F$7*-1 -> -16.473906 | M112: =+AVERAGE(L111:M111)*$F$7*-1 -> -10.188487 | N112: =+AVERAGE(M111:N111)*$F$7*-1 -> -3.1720812 | O112: =+AVERAGE(N111:O111)*$F$7*-1 -> 0 | P112: =+AVERAGE(O111:P111)*$F$7*-1 -> 0
B114: Net cash flows | L114: =+L110+L105+L98 -> 0 | M114: =+M110+M105+M98 -> 0 | N114: =+N110+N105+N98 -> 54.793978 | O114: =+O110+O105+O98 -> 143.5073 | P114: =+P110+P105+P98 -> 159.66619
L116: Projected | M116: Projected | N116: Projected | O116: Projected | P116: Projected
A117: x | B117: LBO | L117: 2007 | M117: =+L117+1 -> 2008 | N117: =+M117+1 -> 2009 | O117: =+N117+1 -> 2010 | P117: =+O117+1 -> 2011
B118: EBITDA | L118: =+L44 -> 169.7 | M118: =+M44 -> 198.7 | N118: =+N44 -> 230.6 | O118: =+O44 -> 263.6 | P118: =+P44 -> 289.23361
B119: Exit multiple | L119: =+$O$18 -> 7 | M119: =+$O$18 -> 7 | N119: =+$O$18 -> 7 | O119: =+$O$18 -> 7 | P119: =+$O$18 -> 7
B120: Exit EV | L120: =+L119*L118 -> 1187.9 | M120: =+M119*M118 -> 1390.9 | N120: =+N119*N118 -> 1614.2 | O120: =+O119*O118 -> 1845.2 | P120: =+P119*P118 -> 2024.6353
B122: (-) net debt | L122: =+L66-L50 -> 518.62811 | M122: =+M66-M50 -> 441.74162 | N122: =+N66-N50 -> 323.50602 | O122: =+O66-O50 -> 179.99872 | P122: =+P66-P50 -> 20.332526
B123: Exit EqV | L123: =+L120-L122 -> 669.27189 | M123: =+M120-M122 -> 949.15838 | N123: =+N120-N122 -> 1290.694 | O123: =+O120-O122 -> 1665.2013 | P123: =+P120-P122 -> 2004.3028
B125: Mgmt options | L125: =+L123*$O$16*-1 -> -66.927189 | M125: =+M123*$O$16*-1 -> -94.915838 | N125: =+N123*$O$16*-1 -> -129.0694 | O125: =+O123*$O$16*-1 -> -166.52013 | P125: =+P123*$O$16*-1 -> -200.43028
B126: EqV to sponsor | L126: =+L125+L123 -> 602.3447 | M126: =+M125+M123 -> 854.24254 | N126: =+N125+N123 -> 1161.6246 | O126: =+O125+O123 -> 1498.6812 | P126: =+P125+P123 -> 1803.8725
B128: MOIC | L128: =+L126/$J$12 -> 1.292753 | M128: =+M126/$J$12 -> 1.8333765 | N128: =+N126/$J$12 -> 2.4930803 | O128: =+O126/$J$12 -> 3.2164716 | P128: =+P126/$J$12 -> 3.8714736
B129: IRR | L129: =+L128^(1/L102)-1 -> 0.29275302 | M129: =+M128^(1/M102)-1 -> 0.35402235 | N129: =+N128^(1/N102)-1 -> 0.35595545 | O129: =+O128^(1/O102)-1 -> 0.33919842 | P129: =+P128^(1/P102)-1 -> 0.3109172
B130: Sponsor profit | L130: =+L126-$J$12 -> 136.4052 | M130: =+M126-$J$12 -> 388.30304 | N130: =+N126-$J$12 -> 695.68508 | O130: =+O126-$J$12 -> 1032.7417 | P130: =+P126-$J$12 -> 1337.933
A132: x | B132: Sensitivity
L133: Exit multiple
K134: =+P129 -> 0.3109172 | L134: 5 | M134: =+L134+1 -> 6 | N134: =+M134+1 -> 7 | O134: =+N134+1 -> 8 | P134: =+O134+1 -> 9
...
