Workbook
Name IQ_CH: 110000
Name IQ_CQ: 5000
Name IQ_CY: 10000
Name IQ_DAILY: 500000
Name IQ_FH: 100000
Name IQ_FQ: 500
Name IQ_FY: 1000
Name IQ_LTM: 2000
Name IQ_MONTH: 15000
Name IQ_NTM: 6000
Name IQ_WEEK: 50000
Name IQ_YTD: 3000

Sheet 1. Business Assessment
C3: Q1: Business Assessment
D7: Recommendation
D8: Do NOT invest in this business on account of an unfavourable risk-reward:
D9: Low base case returns, extremely sensitive to changes in COGS spend and revenue/store. Bulk of returns driven by EBITDA growth, which will require a lot of conviction / potential portfolio management
D10: Cannot lever up much as a result
D11: Complete wipe-out of returns in a relatively mild downside case (e.g. not assuming a business collapse)
D12: Potential remedies include ability to enter at a more attractive valuation or new value creation levers to make the base case more compelling
D14: Strengths
D15: #1 net promoter score and brand warmth, increased traffic from Fresh Look marketing initiative
D16: 3rd lowest exposure to food delivery growth in spheres of influence among UK supermarkets
D17: Captive fuel revenues diversify revenue streams
D18: Low capital intensity (capex spend did not meaningfully increase despite store openings during COVID)
D19: Negative NWC business model is a source of cash as the business grows
... D56: Ability to structure an investment with more downside protection, e.g. 1x liq pref convertible preferred stock

Sheet 2. Operating Model
C3: Q2: Operating Model | H3: The below populated model serves as a template, but you can amend as you see fit (if needed) | W3: Operating case | Y3: 1 | Z3: (1) = Base Case; (2) = Downside Case
C7: Entry assumptions | I7: Sources | K7: £m | L7: xEBITDA | N7: Uses | R7: £m
C9: Undisturbed share price (£p) | F9: 175 | I9: Net debt at closing | K9: =L9*$J$107 -> 2824 | L9: 4 | N9: Cash consideration to shareholders | R9: =+F12 -> 5489.575
C10: Premium to current share price (%) | F10: 0.3 | I10: o/w acquisition financing | K10: =+K9+K11 -> 3074 | L10: =K10/$J$107 -> 4.3541076 | N10: Repay existing net debt | R10: =+F13 -> 1836
C11: Diluted TSO (m) | F11: 2413 | I11: o/w min cash | K11: 250 | L11: =K11/$J$107 -> 0.35410765 | N11: Transaction fees | R11: =+R12*F14 -> 73.25575
C12: Equity purchase price | F12: =+F9*(1+F10)*F11/100 -> 5489.575 | I12: Equity | K12: =$R$13-K9 -> 4574.8308 | L12: =K12/$J$107 -> 6.4799302 | N12: Memo: transaction fees as % of EV | R12: 0.01
C13: Plus: Net debt and debt-like items¹ | F13: =54+1986+36-240 -> 1836 | I13: Total Sources | K13: =+K9+K12 -> 7398.8308 | L13: =K13/$J$107 -> 10.47993 | N13: Total Uses | R13: =SUM(R9:R11) -> 7398.8308
C14: Enterprise Value ¹ | F14: =+F12+F13 -> 7325.575
C15: Implied EV / FY22 EBITDA | F15: =+F14/$K$107 -> 8.8520776 | I15: IRR | J15: =F205 -> 0.1371174
C16: Implied EV / FY21 EBITDA | F16: =+F14/$J$107 -> 10.376169 | I16: MOIC | J16: =F206 -> 1.9018639
C17: ¹ Excludes leases (EBITDA shown net of lease costs)
H18: Actuals | K18: ="Projections - "&CHOOSE($Y$3,C78,C79) -> Projections - Base Case | Q18: CAGR
C19: As of Jan, £m | H19: 43496 | I19: =EOMONTH(H19,12) -> 43861 | J19: =EOMONTH(I19,12) -> 44227 | K19: =EOMONTH(J19,12) -> 44592 | L19: =EOMONTH(K19,12) -> 44957 | M19: =EOMONTH(L19,12) -> 45322 | N19: =EOMONTH(M19,12) -> 45688 | O19: =EOMONTH(N19,12) -> 46053 | Q19: '19-'21 | R19: '21-'26
B21: x | C21: KPIs | U21: Step-up
C23: Total number of stores | H23: 494 | I23: 492 | J23: 497 | K23: =J23+K24 -> 501 | L23: =K23+L24 -> 506 | M23: =L23+M24 -> 512 | N23: =M23+N24 -> 519 | O23: =N23+O24 -> 527 | Q23: =IFERROR((J23/H23)^0.5-1,"n.a.") -> 0.0030318412 | R23: =IFERROR((O23/J23)^(1/5)-1,"n.a.") -> 0.011791078
C24: =+"Change in no. of stores: "&CHOOSE($Y$3,C25,C26) -> Change in no. of stores: Base Case | H24: n.a. | I24: =I23-H23 -> -2 | J24: =J23-I23 -> 5 | K24: =+CHOOSE($Y$3,K25,K26) -> 4 | L24: =+CHOOSE($Y$3,L25,L26) -> 5 | M24: =+CHOOSE($Y$3,M25,M26) -> 6 | N24: =+CHOOSE($Y$3,N25,N26) -> 7 | O24: =+CHOOSE($Y$3,O25,O26) -> 8
C25: Base Case | K25: =4+$U$25 -> 4 | L25: =K25+1 -> 5 | M25: =L25+1 -> 6 | N25: =M25+1 -> 7 | O25: =N25+1 -> 8 | U25: 0
C26: Downside Case | K26: 4 | L26: =L25-1 -> 4 | M26: =M25-1 -> 5 | N26: =N25-1 -> 6 | O26: =O25-1 -> 7
C28: Petrol filling stations | H28: 335 | I28: 335 | J28: 338 | K28: =J28+K29 -> 341 | L28: =K28+L29 -> 344 | M28: =L28+M29 -> 347 | N28: =M28+N29 -> 350 | O28: =N28+O29 -> 353 | Q28: =IFERROR((J28/H28)^0.5-1,"n.a.") -> 0.0044676321 | R28: =IFERROR((O28/J28)^(1/5)-1,"n.a.") -> 0.0087222514
C29: =+"Change in no. of stations: "&CHOOSE($Y$3,C30,C31) -> Change in no. of stations: Base Case | H29: n.a. | I29: =I28-H28 -> 0 | J29: =J28-I28 -> 3 | K29: =+CHOOSE($Y$3,K30,K31) -> 3 | L29: =+CHOOSE($Y$3,L30,L31) -> 3 | M29: =+CHOOSE($Y$3,M30,M31) -> 3 | N29: =+CHOOSE($Y$3,N30,N31) -> 3 | O29: =+CHOOSE($Y$3,O30,O31) -> 3
C30: Base Case | K30: 3 | L30: 3 | M30: 3 | N30: 3 | O30: 3
C31: Downside Case | K31: =K30-1 -> 2 | L31: =L30-1 -> 2 | M31: =M30-1 -> 2 | N31: =N30-1 -> 2 | O31: =O30-1 -> 2
C33: Employees (FTE) | H33: 72120 | I33: 71263 | J33: 76991 | K33: =ROUND(+J33*(1+K34),0) -> 81927 | L33: =ROUND(+K33*(1+L34),0) -> 83391 | M33: =ROUND(+L33*(1+M34),0) -> 84613 | N33: =ROUND(+M33*(1+N34),0) -> 85567 | O33: =ROUND(+N33*(1+O34),0) -> 86226 | Q33: =IFERROR((J33/H33)^0.5-1,"n.a.") -> 0.033218375 | R33: =IFERROR((O33/J33)^(1/5)-1,"n.a.") -> 0.022915256
C34: =+"% growth: "&CHOOSE($Y$3,C35,C36) -> % growth: Base Case | I34: =IFERROR(I33/H33-1,"n.a.") -> -0.011882973 | J34: =IFERROR(J33/I33-1,"n.a.") -> 0.080378317 | K34: =+CHOOSE($Y$3,K35,K36) -> 0.064117607 | L34: =+CHOOSE($Y$3,L35,L36) -> 0.017864807 | M34: =+CHOOSE($Y$3,M35,M36) -> 0.014659158 | N34: =+CHOOSE($Y$3,N35,N36) -> 0.011271169 | O34: =+CHOOSE($Y$3,O35,O36) -> 0.0076972627
C35: Base Case | K35: =K74*0.6 -> 0.064117607 | L35: =L74*0.5 -> 0.017864807 | M35: =M74*0.4 -> 0.014659158 | N35: =N74*0.3 -> 0.011271169 | O35: =O74*0.2 -> 0.0076972627
C36: Downside Case | K36: =K74*0.3 -> 0.032058804 | L36: =L74*0.2 -> 0.0071459228 | M36: =M74*0.1 -> 0.0036647896 | N36: =M36 -> 0.0036647896 | O36: =N36 -> 0.0036647896
C38: % LfL revenue growth (excl. fuel) | H38: 0.048 | I38: -0.008 | J38: 0.086 | K38: =+CHOOSE($Y$3,K39,K40) -> 0 | L38: =+CHOOSE($Y$3,L39,L40) -> 0 | M38: =+CHOOSE($Y$3,M39,M40) -> 0 | N38: =+CHOOSE($Y$3,N39,N40) -> 0 | O38: =+CHOOSE($Y$3,O39,O40) -> 0
C39: Base Case
C40: Downside Case
C42: Revenue/Store | H42: =H67/H23 -> 28.279352 | I42: =I67/I23 -> 28.180894 | J42: =J67/J23 -> 30.392354 | K42: =+CHOOSE($Y$3,K43,K44) -> 31.392354 | L42: =+CHOOSE($Y$3,L43,L44) -> 32.392354 | M42: =+CHOOSE($Y$3,M43,M44) -> 33.392354 | N42: =+CHOOSE($Y$3,N43,N44) -> 34.392354 | O42: =+CHOOSE($Y$3,O43,O44) -> 35.392354
C43: Base Case | K43: =J42+1 -> 31.392354 | L43: =K43+1 -> 32.392354 | M43: =L43+1 -> 33.392354 | N43: =M43+1 -> 34.392354 | O43: =N43+1 -> 35.392354
C44: Downside Case | K44: =J42 -> 30.392354 | L44: =K44+0.25 -> 30.642354 | M44: =L44+0.25 -> 30.892354 | N44: =M44+0.25 -> 31.142354 | O44: =N44+0.25 -> 31.392354
C46: Revenue/Petrol Station | H46: =H70/H28 -> 11.238806 | I46: =I70/I28 -> 10.958209 | J46: =J70/J28 -> 7.3757396 | K46: =+CHOOSE($Y$3,K47,K48) -> 11 | L46: =+CHOOSE($Y$3,L47,L48) -> 11 | M46: =+CHOOSE($Y$3,M47,M48) -> 11 | N46: =+CHOOSE($Y$3,N47,N48) -> 11 | O46: =+CHOOSE($Y$3,O47,O48) -> 11
C47: Base Case | K47: 11 | L47: =K47 -> 11 | M47: =L47 -> 11 | N47: =M47 -> 11 | O47: =N47 -> 11
C48: Downside Case | K48: 11 | L48: =K48 -> 11 | M48: =L48 -> 11 | N48: =M48 -> 11 | O48: =N48 -> 11
C50: Comp/FTE | H50: =-(H89*10^6)/H33 -> 26344.981 | I50: =-(I89*10^6)/I33 -> 25890.013 | J50: =-(J89*10^6)/J33 -> 27769.48 | K50: =ROUND(+J50*(1+K51),0) -> 29713 | L50: =ROUND(+K50*(1+L51),0) -> 31199 | M50: =ROUND(+L50*(1+M51),0) -> 32135 | N50: =ROUND(+M50*(1+N51),0) -> 32456 | O50: =ROUND(+N50*(1+O51),0) -> 32781
C51: =+"% growth: "&CHOOSE($Y$3,C52,C53) -> % growth: Base Case | I51: =IFERROR(I50/H50-1,"n.a.") -> -0.01726961 | J51: =IFERROR(J50/I50-1,"n.a.") -> 0.072594266 | K51: =+CHOOSE($Y$3,K52,K53) -> 0.07 | L51: =+CHOOSE($Y$3,L52,L53) -> 0.05 | M51: =+CHOOSE($Y$3,M52,M53) -> 0.03 | N51: =+CHOOSE($Y$3,N52,N53) -> 0.01 | O51: =+CHOOSE($Y$3,O52,O53) -> 0.01
C52: Base Case | K52: 0.07 | L52: =K52-2% -> 0.05 | M52: =L52-2% -> 0.03 | N52: =M52-2% -> 0.01 | O52: 0.01
C53: Downside Case | K53: =K52 -> 0.07 | L53: =L52 -> 0.05 | M53: =M52 -> 0.03 | N53: =N52 -> 0.01 | O53: =O52 -> 0.01
C55: Maintenance Capex | K55: =K56*K$73 -> -584.35708 | L55: =L56*L73 -> -605.23594 | M55: =M56*M73 -> -627.41656 | N55: =N56*N73 -> -650.98895 | O55: =O56*O73 -> -676.04312
C56: =+"% sales: "&CHOOSE($Y$3,C57,C58) -> % sales: Base Case | I56: =I124/I73 -> -0.029083029 | J56: =I56 -> -0.029083029 | K56: =+CHOOSE($Y$3,K57,K58) -> -0.03 | L56: =+CHOOSE($Y$3,L57,L58) -> -0.03 | M56: =+CHOOSE($Y$3,M57,M58) -> -0.03 | N56: =+CHOOSE($Y$3,N57,N58) -> -0.03 | O56: =+CHOOSE($Y$3,O57,O58) -> -0.03
C57: Base Case | K57: -0.03 | L57: =K57 -> -0.03 | M57: =L57 -> -0.03 | N57: =M57 -> -0.03 | O57: =N57 -> -0.03
C58: Downside Case | K58: =K57 -> -0.03 | L58: =K58 -> -0.03 | M58: =L58 -> -0.03 | N58: =M58 -> -0.03 | O58: =N58 -> -0.03
C60: Implied Growth Capex | J60: =J124-J56*J73 -> -26.196852 | K60: =K61*K$73 -> -28.996318 | L60: =L61*L$73 -> -30.032345 | M60: =M61*M$73 -> -31.132968 | N60: =N61*N$73 -> -32.302651 | O60: =O61*O$73 -> -33.545861
C61: =+"% sales: "&CHOOSE($Y$3,C62,C63) -> % sales: Base Case | J61: =J60/J73 -> -0.0014886267 | K61: =+CHOOSE($Y$3,K62,K63) -> -0.0014886267 | L61: =+CHOOSE($Y$3,L62,L63) -> -0.0014886267 | M61: =+CHOOSE($Y$3,M62,M63) -> -0.0014886267 | N61: =+CHOOSE($Y$3,N62,N63) -> -0.0014886267 | O61: =+CHOOSE($Y$3,O62,O63) -> -0.0014886267
C62: Base Case | K62: =J61 -> -0.0014886267 | L62: =K62 -> -0.0014886267 | M62: =L62 -> -0.0014886267 | N62: =M62 -> -0.0014886267 | O62: =N62 -> -0.0014886267
C63: Downside Case | K63: =K62 -> -0.0014886267 | L63: =K63 -> -0.0014886267 | M63: =L63 -> -0.0014886267 | N63: =M63 -> -0.0014886267 | O63: =N63 -> -0.0014886267
B65: x | C65: P&L
C67: Revenue excl. fuel (stores) | H67: 13970 | I67: 13865 | J67: 15105 | K67: =K23*K42 -> 15727.569 | L67: =L23*L42 -> 16390.531 | M67: =M23*M42 -> 17096.885 | N67: =N23*N42 -> 17849.632 | O67: =O23*O42 -> 18651.771 | Q67: =IFERROR((J67/H67)^0.5-1,"n.a.") -> 0.039829566 | R67: =IFERROR((O67/J67)^(1/5)-1,"n.a.") -> 0.043085401
C68: =+"% growth: "&CHOOSE($Y$3,C43,C44) -> % growth: Base Case | I68: =IFERROR(I67/H67-1,"n.a.") -> -0.0075161059 | J68: =IFERROR(J67/I67-1,"n.a.") -> 0.089433826 | K68: =IFERROR(K67/J67-1,"n.a.") -> 0.041216115 | L68: =IFERROR(L67/K67-1,"n.a.") -> 0.042152843 | M68: =IFERROR(M67/L67-1,"n.a.") -> 0.043095255 | N68: =IFERROR(N67/M67-1,"n.a.") -> 0.044028281 | O68: =IFERROR(O67/N67-1,"n.a.") -> 0.044938677
C70: Fuel revenues | H70: 3765 | I70: 3671 | J70: 2493 | K70: =K28*K46 -> 3751 | L70: =L28*L46 -> 3784 | M70: =M28*M46 -> 3817 | N70: =N28*N46 -> 3850 | O70: =O28*O46 -> 3883 | Q70: =IFERROR((J70/H70)^0.5-1,"n.a.") -> -0.18627315 | R70: =IFERROR((O70/J70)^(1/5)-1,"n.a.") -> 0.092670008
C71: =+"% growth: "&CHOOSE($Y$3,C47,C48) -> % growth: Base Case | I71: =IFERROR(I70/H70-1,"n.a.") -> -0.024966799 | J71: =IFERROR(J70/I70-1,"n.a.") -> -0.32089349 | K71: =IFERROR(K70/J70-1,"n.a.") -> 0.50461292 | L71: =IFERROR(L70/K70-1,"n.a.") -> 0.008797654 | M71: =IFERROR(M70/L70-1,"n.a.") -> 0.0087209302 | N71: =IFERROR(N70/M70-1,"n.a.") -> 0.0086455331 | O71: =IFERROR(O70/N70-1,"n.a.") -> 0.0085714286
H72: =H70/H67 -> 0.26950608 | I72: =I70/I67 -> 0.2647674 | J72: =J70/J67 -> 0.16504469 | K72: =K70/K67 -> 0.23849839 | L72: =L70/L67 -> 0.230865 | M72: =M70/M67 -> 0.22325704 | N72: =N70/N67 -> 0.21569072 | O72: =O70/O67 -> 0.20818399
C73: Total revenue | H73: =H67+H70 -> 17735 | I73: =I67+I70 -> 17536 | J73: =J67+J70 -> 17598 | K73: =K67+K70 -> 19478.569 | L73: =L67+L70 -> 20174.531 | M73: =M67+M70 -> 20913.885 | N73: =N67+N70 -> 21699.632 | O73: =O67+O70 -> 22534.771 | Q73: =IFERROR((J73/H73)^0.5-1,"n.a.") -> -0.003869907 | R73: =IFERROR((O73/J73)^(1/5)-1,"n.a.") -> 0.050698145
C74: % growth | I74: =IFERROR(I73/H73-1,"n.a.") -> -0.01122075 | J74: =IFERROR(J73/I73-1,"n.a.") -> 0.0035355839 | K74: =IFERROR(K73/J73-1,"n.a.") -> 0.10686268 | L74: =IFERROR(L73/K73-1,"n.a.") -> 0.035729614 | M74: =IFERROR(M73/L73-1,"n.a.") -> 0.036647896 | N74: =IFERROR(N73/M73-1,"n.a.") -> 0.037570565 | O74: =IFERROR(O73/N73-1,"n.a.") -> 0.038486314
C76: COGS | H76: -13772 | I76: -13608 | J76: -13472 | K76: =K77*K$73 -> -14872.697 | L76: =L77*L$73 -> -15363.744 | M76: =M77*M$73 -> -15884.965 | N76: =N77*N$73 -> -16438.372 | O76: =O77*O$73 -> -17025.955 | Q76: =IFERROR((J76/H76)^0.5-1,"n.a.") -> -0.010951633 | R76: =IFERROR((O76/J76)^(1/5)-1,"n.a.") -> 0.047938709
C77: =+"% of revenues: "&CHOOSE($Y$3,C78,C79) -> % of revenues: Base Case | H77: =H76/H$73 -> -0.77654356 | I77: =I76/I$73 -> -0.77600365 | J77: =J76/J$73 -> -0.76554154 | K77: =+CHOOSE($Y$3,K78,K79) -> -0.76354154 | L77: =+CHOOSE($Y$3,L78,L79) -> -0.76154154 | M77: =+CHOOSE($Y$3,M78,M79) -> -0.75954154 | N77: =+CHOOSE($Y$3,N78,N79) -> -0.75754154 | O77: =+CHOOSE($Y$3,O78,O79) -> -0.75554154
C78: Base Case | K78: =J77-$U$78+0.2% -> -0.76354154 | L78: =K78+0.2% -> -0.76154154 | M78: =L78+0.2% -> -0.75954154 | N78: =M78+0.2% -> -0.75754154 | O78: =N78+0.2% -> -0.75554154 | U78: 0
C79: Downside Case | K79: =J77-$U$78 -> -0.76554154 | L79: =K79 -> -0.76554154 | M79: =L79 -> -0.76554154 | N79: =M79 -> -0.76554154 | O79: =N79 -> -0.76554154
C81: Gross profit | H81: =+H73+H76 -> 3963 | I81: =+I73+I76 -> 3928 | J81: =+J73+J76 -> 4126 | K81: =+K73+K76 -> 4605.8726 | L81: =+L73+L76 -> 4810.7877 | M81: =+M73+M76 -> 5028.9207 | N81: =+N73+N76 -> 5261.2593 | O81: =+O73+O76 -> 5508.8153 | Q81: =IFERROR((J81/H81)^0.5-1,"n.a.") -> 0.020358004 | R81: =IFERROR((O81/J81)^(1/5)-1,"n.a.") -> 0.059511801
C82: % gross margin | H82: =+H81/H73 -> 0.22345644 | I82: =+I81/I73 -> 0.22399635 | J82: =+J81/J73 -> 0.23445846 | K82: =+K81/K73 -> 0.23645846 | L82: =+L81/L73 -> 0.23845846 | M82: =+M81/M73 -> 0.24045846 | N82: =+N81/N73 -> 0.24245846 | O82: =+O81/O73 -> 0.24445846
C84: Other operating income | H84: 88 | I84: 94 | J84: 92 | K84: =K85*K$73 -> 97.392847 | L84: =L85*L$73 -> 100.87266 | M84: =M85*M$73 -> 104.56943 | N84: =N85*N$73 -> 108.49816 | O84: =O85*O$73 -> 112.67385 | Q84: =IFERROR((J84/H84)^0.5-1,"n.a.") -> 0.022474716 | R84: =IFERROR((O84/J84)^(1/5)-1,"n.a.") -> 0.041374799
C85: =+"% of revenues: "&CHOOSE($Y$3,C86,C87) -> % of revenues: Base Case | H85: =H84/H$73 -> 0.0049619397 | I85: =I84/I$73 -> 0.0053604015 | J85: =J84/J$73 -> 0.0052278668 | K85: =+CHOOSE($Y$3,K86,K87) -> 0.005 | L85: =+CHOOSE($Y$3,L86,L87) -> 0.005 | M85: =+CHOOSE($Y$3,M86,M87) -> 0.005 | N85: =+CHOOSE($Y$3,N86,N87) -> 0.005 | O85: =+CHOOSE($Y$3,O86,O87) -> 0.005
C86: Base Case | K86: 0.005 | L86: =K86 -> 0.005 | M86: =L86 -> 0.005 | N86: =M86 -> 0.005 | O86: =N86 -> 0.005
C87: Downside Case | K87: =K86 -> 0.005 | L87: =L86 -> 0.005 | M87: =M86 -> 0.005 | N87: =N86 -> 0.005 | O87: =O86 -> 0.005
C89: Employee costs | H89: -1900 | I89: -1845 | J89: -2138 | K89: =-K50*K33/10^6 -> -2434.297 | L89: =-L50*L33/10^6 -> -2601.7158 | M89: =-M50*M33/10^6 -> -2719.0388 | N89: =-N50*N33/10^6 -> -2777.1626 | O89: =-O50*O33/10^6 -> -2826.5745 | Q89: =IFERROR((J89/H89)^0.5-1,"n.a.") -> 0.060784218 | R89: =IFERROR((O89/J89)^(1/5)-1,"n.a.") -> 0.05742737
C90: =+"% of revenues: "&CHOOSE($Y$3,C86,C87) -> % of revenues: Base Case | H90: =H89/H$73 -> -0.10713279 | I90: =I89/I$73 -> -0.10521214 | J90: =J89/J$73 -> -0.12149108 | K90: =K89/K$73 -> -0.12497309 | L90: =L89/L$73 -> -0.12896041 | M90: =M89/M$73 -> -0.13001117 | N90: =N89/N$73 -> -0.12798201 | O90: =O89/O$73 -> -0.1254317
C92: Administrative expenses | H92: -274 | I92: -262 | J92: -287 | K92: =K93*K$73 -> -311.65711 | L92: =L93*L$73 -> -322.7925 | M92: =M93*M$73 -> -334.62216 | N92: =N93*N$73 -> -347.19411 | O92: =O93*O$73 -> -360.55633 | Q92: =IFERROR((J92/H92)^0.5-1,"n.a.") -> 0.02344773 | R92: =IFERROR((O92/J92)^(1/5)-1,"n.a.") -> 0.046690411
C93: =+"% of revenues: "&CHOOSE($Y$3,C94,C95) -> % of revenues: Base Case | H93: =H92/H$73 -> -0.015449676 | I93: =I92/I$73 -> -0.014940693 | J93: =J92/J$73 -> -0.016308671 | K93: =+CHOOSE($Y$3,K94,K95) -> -0.016 | L93: =+CHOOSE($Y$3,L94,L95) -> -0.016 | M93: =+CHOOSE($Y$3,M94,M95) -> -0.016 | N93: =+CHOOSE($Y$3,N94,N95) -> -0.016 | O93: =+CHOOSE($Y$3,O94,O95) -> -0.016
C94: Base Case | K94: -0.016 | L94: =K94 -> -0.016 | M94: =L94 -> -0.016 | N94: =M94 -> -0.016 | O94: =N94 -> -0.016
C95: Downside Case | K95: =K94 -> -0.016 | L95: =L94 -> -0.016 | M95: =M94 -> -0.016 | N95: =N94 -> -0.016 | O95: =O94 -> -0.016
C97: Other costs | H97: -866 | I97: -877 | J97: -946 | K97: =K98*K$73 -> -973.92847 | L97: =L98*L$73 -> -1008.7266 | M97: =M98*M$73 -> -1045.6943 | N97: =N98*N$73 -> -1084.9816 | O97: =O98*O$73 -> -1126.7385 | Q97: =IFERROR((J97/H97)^0.5-1,"n.a.") -> 0.045169246 | R97: =IFERROR((O97/J97)^(1/5)-1,"n.a.") -> 0.035586552
C98: =+"% of revenues: "&CHOOSE($Y$3,C99,C100) -> % of revenues: Base Case | H98: =H97/H$73 -> -0.048829997 | I98: =I97/I$73 -> -0.050011405 | J98: =J97/J$73 -> -0.053756109 | K98: =+CHOOSE($Y$3,K99,K100) -> -0.05 | L98: =+CHOOSE($Y$3,L99,L100) -> -0.05 | M98: =+CHOOSE($Y$3,M99,M100) -> -0.05 | N98: =+CHOOSE($Y$3,N99,N100) -> -0.05 | O98: =+CHOOSE($Y$3,O99,O100) -> -0.05
C99: Base Case | K99: -0.05 | L99: =K99 -> -0.05 | M99: =L99 -> -0.05 | N99: =M99 -> -0.05 | O99: =N99 -> -0.05
C100: Downside Case | K100: =K99 -> -0.05 | L100: =L99 -> -0.05 | M100: =M99 -> -0.05 | N100: =N99 -> -0.05 | O100: =O99 -> -0.05
C102: Rent expense | H102: -134 | I102: -130 | J102: -141 | K102: =K103*K$73 -> -155.82856 | L102: =L103*L$73 -> -161.39625 | M102: =M103*M$73 -> -167.31108 | N102: =N103*N$73 -> -173.59705 | O102: =O103*O$73 -> -180.27816 | Q102: =IFERROR((J102/H102)^0.5-1,"n.a.") -> 0.02578692 | R102: =IFERROR((O102/J102)^(1/5)-1,"n.a.") -> 0.050376032
C103: =+"% of revenues: "&CHOOSE($Y$3,C104,C105) -> % of revenues: Base Case | H103: =H102/H$73 -> -0.0075556809 | I103: =I102/I$73 -> -0.0074133212 | J103: =J102/J$73 -> -0.0080122741 | K103: =+CHOOSE($Y$3,K104,K105) -> -0.008 | L103: =+CHOOSE($Y$3,L104,L105) -> -0.008 | M103: =+CHOOSE($Y$3,M104,M105) -> -0.008 | N103: =+CHOOSE($Y$3,N104,N105) -> -0.008 | O103: =+CHOOSE($Y$3,O104,O105) -> -0.008
C104: Base Case | K104: -0.008 | L104: =K104 -> -0.008 | M104: =L104 -> -0.008 | N104: =M104 -> -0.008 | O104: =N104 -> -0.008
C105: Downside Case | K105: =K104 -> -0.008 | L105: =L104 -> -0.008 | M105: =M104 -> -0.008 | N105: =N104 -> -0.008 | O105: =O104 -> -0.008
C107: Adj. EBITDA (pre IFRS-16) | H107: =+H81+H84+H89+H92+H97+H102 -> 877 | I107: =+I81+I84+I89+I92+I97+I102 -> 908 | J107: =+J81+J84+J89+J92+J97+J102 -> 706 | K107: =+K81+K84+K89+K92+K97+K102 -> 827.55431 | L107: =+L81+L84+L89+L92+L97+L102 -> 817.0292 | M107: =+M81+M84+M89+M92+M97+M102 -> 866.82384 | N107: =+N81+N84+N89+N92+N97+N102 -> 986.82219 | O107: =+O81+O84+O89+O92+O97+O102 -> 1127.3417 | Q107: =IFERROR((J107/H107)^0.5-1,"n.a.") -> -0.10277255 | R107: =IFERROR((O107/J107)^(1/5)-1,"n.a.") -> 0.098120937
C108: % margin | H108: =H107/H$73 -> 0.04945024 | I108: =I107/I$73 -> 0.051779197 | J108: =J107/J$73 -> 0.040118195 | K108: =K107/K$73 -> 0.042485374 | L108: =L107/L$73 -> 0.040498051 | M108: =M107/M$73 -> 0.041447288 | N108: =N107/N$73 -> 0.045476448 | O108: =O107/O$73 -> 0.050026765
C109: % growth | I109: =IFERROR(I108/H108-1,"n.a.") -> 0.04709699 | J109: =IFERROR(J108/I108-1,"n.a.") -> -0.22520631 | K109: =IFERROR(K108/J108-1,"n.a.") -> 0.059005119 | L109: =IFERROR(L108/K108-1,"n.a.") -> -0.046776633 | M109: =IFERROR(M108/L108-1,"n.a.") -> 0.02343908 | N109: =IFERROR(N108/M108-1,"n.a.") -> 0.097211666 | O109: =IFERROR(O108/N108-1,"n.a.") -> 0.10005875
C111: D&A | H111: -443 | I111: -465 | J111: -478 | K111: =K112*K73 -> -490.68272 | L111: =L112*L73 -> -508.21462 | M111: =M112*M73 -> -526.83962 | N111: =N112*N73 -> -546.63328 | O111: =O112*O73 -> -567.67118 | Q111: =IFERROR((J111/H111)^0.5-1,"n.a.") -> 0.038752508 | R111: =IFERROR((O111/J111)^(1/5)-1,"n.a.") -> 0.034984368
C112: =+"% of revenues: "&CHOOSE($Y$3,C113,C114) -> % of revenues: Base Case | H112: =H111/H$73 -> -0.024978855 | I112: =I111/I$73 -> -0.02651688 | J112: =J111/J$73 -> -0.027162178 | K112: =+CHOOSE($Y$3,K113,K114) -> -0.025190901 | L112: =+CHOOSE($Y$3,L113,L114) -> -0.025190901 | M112: =+CHOOSE($Y$3,M113,M114) -> -0.025190901 | N112: =+CHOOSE($Y$3,N113,N114) -> -0.025190901 | O112: =+CHOOSE($Y$3,O113,O114) -> -0.025190901
C113: Base Case | K113: =K126*80% -> -0.025190901 | L113: =L126*80% -> -0.025190901 | M113: =M126*80% -> -0.025190901 | N113: =N126*80% -> -0.025190901 | O113: =O126*80% -> -0.025190901
C114: Downside Case | K114: =K127*80% -> -0.025190901 | L114: =L127*80% -> -0.025190901 | M114: =M127*80% -> -0.025190901 | N114: =N127*80% -> -0.025190901 | O114: =O127*80% -> -0.025190901
C116: Adj. EBIT | H116: =+H107+H111 -> 434 | I116: =+I107+I111 -> 443 | J116: =+J107+J111 -> 228 | K116: =+K107+K111 -> 336.87159 | L116: =+L107+L111 -> 308.81458 | M116: =+M107+M111 -> 339.98422 | N116: =+N107+N111 -> 440.1889 | O116: =+O107+O111 -> 559.67049 | Q116: =IFERROR((J116/H116)^0.5-1,"n.a.") -> -0.2751927 | R116: =IFERROR((O116/J116)^(1/5)-1,"n.a.") -> 0.19673919
C117: % margin | H117: =H116/H$73 -> 0.024471384 | I117: =I116/I$73 -> 0.025262318 | J117: =J116/J$73 -> 0.012956018 | K117: =K116/K$73 -> 0.017294473 | L117: =L116/L$73 -> 0.01530715 | M117: =M116/M$73 -> 0.016256387 | N117: =N116/N$73 -> 0.020285547 | O117: =O116/O$73 -> 0.024835864
C118: % growth | I118: =IFERROR(I117/H117-1,"n.a.") -> 0.03232074 | J118: =IFERROR(J117/I117-1,"n.a.") -> -0.48714057 | K118: =IFERROR(K117/J117-1,"n.a.") -> 0.33486023 | L118: =IFERROR(L117/K117-1,"n.a.") -> -0.11491086 | M118: =IFERROR(M117/L117-1,"n.a.") -> 0.062012659 | N118: =IFERROR(N117/M117-1,"n.a.") -> 0.24785089 | O118: =IFERROR(O117/N117-1,"n.a.") -> 0.22431322
C120: Cash Flows
C122: Adj. EBITDA | H122: =+H107 -> 877 | I122: =+I107 -> 908 | J122: =+J107 -> 706 | K122: =+K107 -> 827.55431 | L122: =+L107 -> 817.0292 | M122: =+M107 -> 866.82384 | N122: =+N107 -> 986.82219 | O122: =+O107 -> 1127.3417 | Q122: =IFERROR((J122/H122)^0.5-1,"n.a.") -> -0.10277255 | R122: =IFERROR((O122/J122)^(1/5)-1,"n.a.") -> 0.098120937
C124: Capex | H124: -458 | I124: -510 | J124: -538 | K124: =K125*K73 -> -613.3534 | L124: =L125*L73 -> -635.26828 | M124: =M125*M73 -> -658.54953 | N124: =N125*N73 -> -683.2916 | O124: =O125*O73 -> -709.58898
C125: =+"% of revenues: "&CHOOSE($Y$3,C126,C127) -> % of revenues: Base Case | H125: =H124/H$73 -> -0.025824641 | I125: =I124/I$73 -> -0.029083029 | J125: =J124/J$73 -> -0.030571656 | K125: =+CHOOSE($Y$3,K126,K127) -> -0.031488627 | L125: =+CHOOSE($Y$3,L126,L127) -> -0.031488627 | M125: =+CHOOSE($Y$3,M126,M127) -> -0.031488627 | N125: =+CHOOSE($Y$3,N126,N127) -> -0.031488627 | O125: =+CHOOSE($Y$3,O126,O127) -> -0.031488627
C126: Base Case | K126: =K57+K62 -> -0.031488627 | L126: =L57+L62 -> -0.031488627 | M126: =M57+M62 -> -0.031488627 | N126: =N57+N62 -> -0.031488627 | O126: =O57+O62 -> -0.031488627
C127: Downside Case | K127: =K58+K63 -> -0.031488627 | L127: =L58+L63 -> -0.031488627 | M127: =M58+M63 -> -0.031488627 | N127: =N58+N63 -> -0.031488627 | O127: =O58+O63 -> -0.031488627
C129: Change in working capital | H129: -2 | I129: 68 | J129: -424 | K129: =-(K150-J150) -> 396.13547 | L129: =-(L150-K150) -> 67.745579 | M129: =-(M150-L150) -> 71.896262 | N129: =-(N150-M150) -> 76.321668 | O129: =-(O150-N150) -> 81.017823
C130: Taxes | F130: 0.23 | H130: -76 | I130: -87 | J130: -81 | K130: =-$F$130*(K116+K136) -> -52.821022 | L130: =-$F$130*(L116+L136) -> -49.978347 | M130: =-$F$130*(M116+M136) -> -58.011974 | N130: =-$F$130*(N116+N136) -> -82.135359 | O130: =-$F$130*(O116+O136) -> -111.33609
C131: % ETR | H131: =H130/(H116+H136) -> -0.2 | I131: =I130/(I116+I136) -> -0.21641791 | J131: =J130/(J116+J136) -> -0.47093023 | K131: =K130/(K116+K136) -> -0.23 | L131: =L130/(L116+L136) -> -0.23 | M131: =M130/(M116+M136) -> -0.23 | N131: =N130/(N116+N136) -> -0.23 | O131: =O130/(O116+O136) -> -0.23
C132: Others & exceptionals | H132: 36 | I132: -22 | J132: -56 | K132: 0 | L132: 0 | M132: 0 | N132: 0 | O132: 0
C133: Unlevered FCF | H133: =H122+H124+SUM(H129:H132) -> 376.8 | I133: =I122+I124+SUM(I129:I132) -> 356.78358 | J133: =J122+J124+SUM(J129:J132) -> -393.47093 | K133: =K122+K124+SUM(K129:K132) -> 557.28536 | L133: =L122+L124+SUM(L129:L132) -> 199.29815 | M133: =M122+M124+SUM(M129:M132) -> 221.9286 | N133: =N122+N124+SUM(N129:N132) -> 297.48689 | O133: =O122+O124+SUM(O129:O132) -> 387.20442
...

Sheet 3. Valuation
C3: Q3: Valuation
D12: LBO Ability to Pay Analysis (5Y Hold)
D14: Target IRR | G14: 0.2
D15: Exit Equity Value | G15: ='2. Operating Model'!O199 -> 8700.7053
D16: Required Entry Equity Value | G16: =G15/(1+G14)^5 -> 3496.6183
D17: (+) Net Debt | G17: ='2. Operating Model'!K9 -> 2824
D18: Required Sources | G18: =G16+G17 -> 6320.6183
D19: (-) Refi Existing Debt | G19: =-'2. Operating Model'!R10 -> -1836
D20: (-) Transaction Fees | G20: =-'2. Operating Model'!R11 -> -73.25575
D21: Required Equity Purchase Price | G21: =SUM(G18:G20) -> 4411.3626
D22: (+) Existing Net Debt | G22: ='2. Operating Model'!R10 -> 1836
D23: Implied Purchase EV | G23: =G21+G22 -> 6247.3626
D24: LTM EBITDA | G24: ='2. Operating Model'!J107 -> 706
D25: Entry LTM EBITDA Multiple | G25: =G23/G24 -> 8.8489555
D26: Implied Premium | G26: =G21/('2. Operating Model'!F9*'2. Operating Model'!F11/100)-1 -> 0.044665816
D28: Comps
D29: Current Trading Comps | G29: =AVERAGE(6.7,6.9,5.7) -> 6.4333333
D30: 5Y Avg. Trading Comps | G30: =AVERAGE(7,7.6,5) -> 6.5333333
D31: Current Transaction Comps | G31: 11.5
D32: 5Y Avg. Transaction Comps | G32: 10.4
D34: A 9-12x LTM EBITDA multiple is appropriate for this transaction, taking recent transactions and targeted returns into account
D35: DCF is not very meaningful in this instance as we are solving for a 5Y hold
