Workbook
Name circ: Input!$E$16
Name IQ_CH: 110000
Name IQ_CQ: 5000
Name IQ_CY: 10000
Name IQ_DAILY: 500000
Name IQ_FH: 100000
Name IQ_FQ: 500
Name IQ_FY: 1000
Name IQ_LTM: 2000
Name IQ_MONTH: 15000
Name IQ_NTM: 6000
Name IQ_WEEK: 50000
Name IQ_YTD: 3000

Sheet Instructions
B5: Instructions
A7: x | B7: Build a 5 year full three-statement annual LBO model (on the 'Input' tab)
A8: x | B8: Target private equity like returns of 20-25% IRR
A9: x | B9: Assume stable gross margins
A10: x | B10: Use the opex growth rates suggested
A11: x | B11: Determine an appropriate level of debt, based on the assumptions provided (including cash sweep). Please include 1.0x EBITDA of mezzanine financing (the rest can be senior debt - up to the level you deem appropriate)
A12: x | B12: Supply entry valuation metrics (EBITDA, EBITDA - Capex, EBIT, Unlevered FCF)
A13: x | B13: Supply relevant credit metrics (gross leverage, net leverage, interest coverage, cash flow coverage, etc.)
A14: x | B14: Show IRR% and Multiple-of-Money for a 3, 4, and 5 year exit
A15: x | B15: Please break out the components of value creation between multiples expansion, revenue growth, margin expansion, and deleveraging (i.e. what % of equity value created came from each effect?)
B16: Time limit: 3 hours
B18: Year 1 Assumptions
B20: P&L
A21: x | B21: Revenue | D21: 200
A22: x | B22: 5-yr Growth | D22: 0.11 | E22: CAGR
A23: x | B23: Gross Margin | D23: 0.5 | E23: of sales
A24: x | B24: EBITDA Margin | D24: 0.2 | E24: of sales | F24: 5-year growth CAGR
A25: x | B25: Opex - S&M | D25: 0.12 | E25: of sales | F25: 0.11
A26: x | B26: Opex - R&D | D26: 0.08 | E26: of sales | F26: 0.07
A27: x | B27: Opex - G&A | D27: =D23-D24-D25-D26 -> 0.1 | E27: of sales | F27: 0.05
A28: x | B28: Capex | D28: 0.04 | E28: of sales
A29: x | B29: Tax Rate | D29: 0.3 | E29: of PBT
B31: Balance Sheet
A32: x | B32: Min Cash / Opening Cash | D32: 15
A33: x | B33: Accounts Receivables | D33: 40
A34: x | B34: Other Current Assets | D34: 10
A35: x | B35: PP&E | D35: 50
A36: x | B36: Accounts Payables | D36: 20
A37: x | B37: Deferred Revenue | D37: 20
B39: Leverage Assumptions
B40: Senior debt assumptions
A41: x | B41: Cash Interest | D41: 0.07
A42: x | B42: Mandatory Amortization | D42: 0.05
A43: x | B43: Free Cash Flow Sweep | D43: 0.5 | E43: of cash flow after mandatory amortization
B45: Mezz debt assumptions
A46: x | B46: Cash Interest | D46: 0.06
A47: x | B47: PIK Interest | D47: 0.06
A48: x | B48: Total Mezz Interest | D48: =SUM(D46:D47) -> 0.12
B50: Deal
A51: x | B51: Entry | D51: 12 | E51: NTM basis
A52: x | B52: Exit Multiple | D52: 11 | E52: NTM basis
A53: x | B53: Fees | D53: 0.03 | E53: of TEV
A54: x | B54: Management Equity Plan Dilution | D54: 0.05 | E54: of common equity

Sheet Input
B2: Deal parameters | I2: Sources | M2: Uses | Q2: Entry valuation
C3: Entry multiple | E3: =+Instructions!D51 -> 12 | I3: Senior debt | K3: =+K13*I40 -> 180.18018 | M3: Purchase EV | O3: =+E5 -> 480 | Q3: EV / EBITDA, NTM | T3: =+O3/J40 -> 12
C4: NTM EBITDA | E4: =+J40 -> 40 | I4: Mezz debt | K4: =+K18*I40 -> 36.036036 | M4: M&A fees | O4: =+$O$3*E8 -> 4.8 | Q4: EV / EBITDA - Capex, NTM | T4: =+O3/(J40+J126) -> 15
C5: Entry EV | E5: =+E4*E3 -> 480 | I5: Sponsor equity | K5: =+K7-K3-K4 -> 293.18378 | M5: Financing fees | O5: =+$O$3*E9 -> 9.6 | Q5: EV EBIT, NTM | T5: =+O3/J45 -> 14.304636
M6: Min cash | O6: =+Instructions!D32 -> 15
C7: Deal fees | E7: =+Instructions!D53 -> 0.03 | I7: Total | K7: =+O7 -> 509.4 | M7: Total | O7: =SUM(O3:O6) -> 509.4 | Q7: UFCF yield, NTM | T7: =+(J56+J120+J123)/$O$3 -> 0.060069444
C8: o/w M&A | E8: =0.333333333333333*$E$7 -> 0.01 | F8: << own assumptions
C9: o/w financing | E9: =(2/3)*$E$7 -> 0.02 | F9: << own assumptions | I9: Senior debt | M9: Credit metrics | O9: =+I20 -> 0 | P9: =+O9+1 -> 1 | Q9: =+P9+1 -> 2 | R9: =+Q9+1 -> 3 | S9: =+R9+1 -> 4 | T9: =+S9+1 -> 5
I10: Cash interest | K10: =+Instructions!D41 -> 0.07 | M10: Gross debt | O10: =+I166 -> 216.21622 | P10: =+J166 -> 207.99383 | Q10: =+K166 -> 197.12073 | R10: =+L166 -> 182.58514 | S10: =+M166 -> 163.5169 | T10: =+N166 -> 139.06416
C11: Assume cash free, debt free basis | I11: Mandatory amort' | K11: =+Instructions!D42 -> 0.05 | M11: Net debt | O11: =+I167 -> 201.21622 | P11: =+J167 -> 191.61829 | Q11: =+K167 -> 177.96475 | R11: =+L167 -> 159.62915 | S11: =+M167 -> 135.8825 | T11: =+N167 -> 105.89075
I12: Sweep | K12: =+Instructions!D43 -> 0.5 | M12: Senior debt | O12: =+I75 -> 180.18018 | P12: =+J75 -> 169.79563 | Q12: =+K75 -> 156.63064 | R12: =+L75 -> 139.66564 | S12: =+M75 -> 118.02223 | T12: =+N75 -> 90.839813
C13: Exit multiple, NTM | E13: =+Instructions!D52 -> 11 | I13: Quantum, LTM EBITDA | K13: 5
C14: MIP | E14: =+Instructions!D54 -> 0.05 | M14: Gross debt / EBITDA | O14: =+O10/I40 -> 6 | P14: =+P10/J40 -> 5.1998458 | Q14: =+Q10/K40 -> 4.2629917 | R14: =+R10/L40 -> 3.4274643 | S14: =+S10/M40 -> 2.6724225 | T14: =+T10/N40 -> 1.984066
I15: Mezz debt | M15: ND/EBITDA | O15: =+O11/I40 -> 5.58375 | P15: =+P11/J40 -> 4.7904574 | Q15: =+Q11/K40 -> 3.8487187 | R15: =+R11/L40 -> 2.9965375 | S15: =+S11/M40 -> 2.2207824 | T15: =+T11/N40 -> 1.510772
B16: Circularity | E16: 1 | I16: Cash interest | K16: =+Instructions!D46 -> 0.06
I17: PIK | K17: =+Instructions!D47 -> 0.06 | M17: EBIT / cash interest | P17: =+K45/(J147+J154+J159)*-1 -> 2.680879 | Q17: =+L45/(K147+K154+K159)*-1 -> 3.2457776 | R17: =+M45/(L147+L154+L159)*-1 -> 3.9964385 | S17: =+N45/(M147+M154+M159)*-1 -> 5.0549722 | T17: =+O45/(N147+N154+N159)*-1 -> 6.6696773
I18: Quantum, LTM EBITDA | K18: 1 | M18: OCF / ND | P18: =+J124/P11 -> 0.10312212 | Q18: =+K124/Q11 -> 0.13949634 | R18: =+L124/R11 -> 0.19183096 | S18: =+M124/S11 -> 0.27422861 | T18: =+N124/T11 -> 0.42370078
H20: Year | I20: 0 | J20: =+I20+1 -> 1 | K20: =+J20+1 -> 2 | L20: =+K20+1 -> 3 | M20: =+L20+1 -> 4 | N20: =+M20+1 -> 5 | O20: =+N20+1 -> 6
A21: x | B21: Income statement
C22: Revenue | I22: =+J22/(1+J23) -> 180.18018 | J22: =+Instructions!D21 -> 200 | K22: =+(1+K23)*J22 -> 222 | L22: =+(1+L23)*K22 -> 246.42 | M22: =+(1+M23)*L22 -> 273.5262 | N22: =+(1+N23)*M22 -> 303.61408 | O22: =+(1+O23)*N22 -> 337.01163
C23: % YoY | J23: =+K23 -> 0.11 | K23: =+Instructions!D22 -> 0.11 | L23: =+K23 -> 0.11 | M23: =+L23 -> 0.11 | N23: =+M23 -> 0.11 | O23: =+N23 -> 0.11
C25: Gross profit | I25: =+I26*I22 -> 90.09009 | J25: =+J26*J22 -> 100 | K25: =+K26*K22 -> 111 | L25: =+L26*L22 -> 123.21 | M25: =+M26*M22 -> 136.7631 | N25: =+N26*N22 -> 151.80704 | O25: =+O26*O22 -> 168.50582
C26: % margin | I26: =+J26 -> 0.5 | J26: =+Instructions!D23 -> 0.5 | K26: =+J26 -> 0.5 | L26: =+K26 -> 0.5 | M26: =+L26 -> 0.5 | N26: =+M26 -> 0.5 | O26: =+N26 -> 0.5
C28: Opex - S&M | J28: =+J29*J22*-1 -> -24 | K28: =+(1+K30)*J28 -> -26.64 | L28: =+(1+L30)*K28 -> -29.5704 | M28: =+(1+M30)*L28 -> -32.823144 | N28: =+(1+N30)*M28 -> -36.43369 | O28: =+(1+O30)*N28 -> -40.441396
C29: % of sales | J29: =+Instructions!D25 -> 0.12 | K29: =+K28/K22*-1 -> 0.12 | L29: =+L28/L22*-1 -> 0.12 | M29: =+M28/M22*-1 -> 0.12 | N29: =+N28/N22*-1 -> 0.12 | O29: =+O28/O22*-1 -> 0.12
C30: % YoY | K30: =+Instructions!$F$25 -> 0.11 | L30: =+Instructions!$F$25 -> 0.11 | M30: =+Instructions!$F$25 -> 0.11 | N30: =+Instructions!$F$25 -> 0.11 | O30: =+Instructions!$F$25 -> 0.11
C32: Opex - R&D | J32: =+J33*J22*-1 -> -16 | K32: =+(1+K34)*J32 -> -17.12 | L32: =+(1+L34)*K32 -> -18.3184 | M32: =+(1+M34)*L32 -> -19.600688 | N32: =+(1+N34)*M32 -> -20.972736 | O32: =+(1+O34)*N32 -> -22.440828
C33: % of sales | J33: =+Instructions!D26 -> 0.08 | K33: =+K32/K22*-1 -> 0.077117117 | L33: =+L32/L22*-1 -> 0.074338122 | M33: =+M32/M22*-1 -> 0.071659271 | N33: =+N32/N22*-1 -> 0.069076955 | O33: =+O32/O22*-1 -> 0.066587695
C34: % YoY | K34: =+Instructions!$F$26 -> 0.07 | L34: =+Instructions!$F$26 -> 0.07 | M34: =+Instructions!$F$26 -> 0.07 | N34: =+Instructions!$F$26 -> 0.07 | O34: =+Instructions!$F$26 -> 0.07
C36: Opex - G&A | J36: =+J37*J22*-1 -> -20 | K36: =+(1+K38)*J36 -> -21 | L36: =+(1+L38)*K36 -> -22.05 | M36: =+(1+M38)*L36 -> -23.1525 | N36: =+(1+N38)*M36 -> -24.310125 | O36: =+(1+O38)*N36 -> -25.525631
C37: % of sales | J37: =+Instructions!D27 -> 0.1 | K37: =+K36/K22*-1 -> 0.094594595 | L37: =+L36/L22*-1 -> 0.089481373 | M37: =+M36/M22*-1 -> 0.084644542 | N37: =+N36/N22*-1 -> 0.080069162 | O37: =+O36/O22*-1 -> 0.075741099
C38: % YoY | K38: =+Instructions!$F$27 -> 0.05 | L38: =+Instructions!$F$27 -> 0.05 | M38: =+Instructions!$F$27 -> 0.05 | N38: =+Instructions!$F$27 -> 0.05 | O38: =+Instructions!$F$27 -> 0.05
C40: EBITDA | I40: =+I41*I22 -> 36.036036 | J40: =+J36+J32+J28+J25 -> 40 | K40: =+K36+K32+K28+K25 -> 46.24 | L40: =+L36+L32+L28+L25 -> 53.2712 | M40: =+M36+M32+M28+M25 -> 61.186768 | N40: =+N36+N32+N28+N25 -> 70.09049 | O40: =+O36+O32+O28+O25 -> 80.097961
C41: % margin | I41: =+J41 -> 0.2 | J41: =+J40/J22 -> 0.2 | K41: =+K40/K22 -> 0.20828829 | L41: =+L40/L22 -> 0.2161805 | M41: =+M40/M22 -> 0.22369619 | N41: =+N40/N22 -> 0.23085388 | O41: =+O40/O22 -> 0.23767121
C43: D&A | J43: =+J104 -> -6.4444444 | K43: =+K104 -> -7.4311111 | L43: =+L104 -> -8.5263111 | M43: =+M104 -> -9.7419831 | N43: =+N104 -> -11.091379 | O43: =+O104 -> -12.589209
C45: EBIT | J45: =+J40+J43 -> 33.555556 | K45: =+K40+K43 -> 38.808889 | L45: =+L40+L43 -> 44.744889 | M45: =+M40+M43 -> 51.444785 | N45: =+N40+N43 -> 58.999111 | O45: =+O40+O43 -> 67.508752
C47: Net interest | J47: =+IF(circ=1, J147+J154+J159+J160, 0) -> -16.638343 | K47: =+IF(circ=1, K147+K154+K159+K160, 0) -> -16.07746 | L47: =+IF(circ=1, L147+L154+L159+L160, 0) -> -15.302063 | M47: =+IF(circ=1, M147+M154+M159+M160, 0) -> -14.24667 | N47: =+IF(circ=1, N147+N154+N159+N160, 0) -> -12.851422 | O47: =+IF(circ=1, O147+O154+O159+O160, 0) -> -11.055466
C48: Amort' financing fees | J48: =+J99 -> -1.3714286 | K48: =+K99 -> -1.3714286 | L48: =+L99 -> -1.3714286 | M48: =+M99 -> -1.3714286 | N48: =+N99 -> -1.3714286 | O48: =+O99 -> -1.3714286
C50: EBT | J50: =+J48+J47+J45 -> 15.545784 | K50: =+K48+K47+K45 -> 21.36 | L50: =+L48+L47+L45 -> 28.071397 | M50: =+M48+M47+M45 -> 35.826686 | N50: =+N48+N47+N45 -> 44.776261 | O50: =+O48+O47+O45 -> 55.081858
C52: Tax rate | J52: =+Instructions!$D$29 -> 0.3 | K52: =+Instructions!$D$29 -> 0.3 | L52: =+Instructions!$D$29 -> 0.3 | M52: =+Instructions!$D$29 -> 0.3 | N52: =+Instructions!$D$29 -> 0.3 | O52: =+Instructions!$D$29 -> 0.3
C54: Net income | J54: =+J50*(1-J52) -> 10.882049 | K54: =+K50*(1-K52) -> 14.952 | L54: =+L50*(1-L52) -> 19.649978 | M54: =+M50*(1-M52) -> 25.07868 | N54: =+N50*(1-N52) -> 31.343382 | O54: =+O50*(1-O52) -> 38.557301
C56: NOPAT | J56: =+J45*(1-J52) -> 23.488889 | K56: =+K45*(1-K52) -> 27.166222 | L56: =+L45*(1-L52) -> 31.321422 | M56: =+M45*(1-M52) -> 36.011349 | N56: =+N45*(1-N52) -> 41.299378 | O56: =+O45*(1-O52) -> 47.256127
A58: x | B58: Balance sheet | F58: Pre txn | G58: Debit | H58: Credit | I58: =+I$20 -> 0 | J58: =+J$20 -> 1 | K58: =+K$20 -> 2 | L58: =+L$20 -> 3 | M58: =+M$20 -> 4 | N58: =+N$20 -> 5 | O58: =+O$20 -> 6
C59: Cash | F59: 0 | G59: =+O6 -> 15 | I59: =+F59+G59-H59 -> 15 | J59: =+J164 -> 16.375538 | K59: =+K164 -> 19.15598 | L59: =+L164 -> 22.955992 | M59: =+M164 -> 27.634401 | N59: =+N164 -> 33.173411 | O59: =+O164 -> 39.620885
C60: AR | F60: =+Instructions!D33 -> 40 | I60: =+F60+G60-H60 -> 40 | J60: =+J93/365*J22 -> 44.4 | K60: =+K93/365*K22 -> 49.284 | L60: =+L93/365*L22 -> 54.70524 | M60: =+M93/365*M22 -> 60.722816 | N60: =+N93/365*N22 -> 67.402326 | O60: =+O93/365*O22 -> 74.816582
C61: Other current assets | F61: =+Instructions!D34 -> 10 | I61: =+F61+G61-H61 -> 10 | J61: =+J94*J22 -> 11.1 | K61: =+K94*K22 -> 12.321 | L61: =+L94*L22 -> 13.67631 | M61: =+M94*M22 -> 15.180704 | N61: =+N94*N22 -> 16.850582 | O61: =+O94*O22 -> 18.704146
C62: Total CA | F62: =SUM(F59:F61) -> 50 | I62: =SUM(I59:I61) -> 65 | J62: =SUM(J59:J61) -> 71.875538 | K62: =SUM(K59:K61) -> 80.76098 | L62: =SUM(L59:L61) -> 91.337542 | M62: =SUM(M59:M61) -> 103.53792 | N62: =SUM(N59:N61) -> 117.42632 | O62: =SUM(O59:O61) -> 133.14161
C64: PPE | F64: =+Instructions!D35 -> 50 | I64: =+F64+G64-H64 -> 50 | J64: =+J105 -> 51.555556 | K64: =+K105 -> 53.004444 | L64: =+L105 -> 54.334933 | M64: =+M105 -> 55.533998 | N64: =+N105 -> 56.587182 | O64: =+O105 -> 57.478439
C65: Goodwill | F65: 0 | G65: =+E88 -> 420 | I65: =+F65+G65-H65 -> 420 | J65: =+I65 -> 420 | K65: =+J65 -> 420 | L65: =+K65 -> 420 | M65: =+L65 -> 420 | N65: =+M65 -> 420 | O65: =+N65 -> 420
C66: Deferred fin' fees | F66: 0 | G66: =+O5 -> 9.6 | I66: =+F66+G66-H66 -> 9.6 | J66: =+J100 -> 8.2285714 | K66: =+K100 -> 6.8571429 | L66: =+L100 -> 5.4857143 | M66: =+M100 -> 4.1142857 | N66: =+N100 -> 2.7428571 | O66: =+O100 -> 1.3714286
C67: Total assets | F67: =+F66+F65+F64+F62 -> 100 | I67: =+I66+I65+I64+I62 -> 544.6 | J67: =+J66+J65+J64+J62 -> 551.65966 | K67: =+K66+K65+K64+K62 -> 560.62257 | L67: =+L66+L65+L64+L62 -> 571.15819 | M67: =+M66+M65+M64+M62 -> 583.18621 | N67: =+N66+N65+N64+N62 -> 596.75636 | O67: =+O66+O65+O64+O62 -> 611.99148
C69: Revolver | F69: 0 | I69: =+F69-G69+H69 -> 0 | J69: =+J146 -> 0 | K69: =+K146 -> 0 | L69: =+L146 -> 0 | M69: =+M146 -> 0 | N69: =+N146 -> 0 | O69: =+O146 -> 0
C70: AP | F70: =+Instructions!D36 -> 20 | I70: =+F70-G70+H70 -> 20 | J70: =+J95/365*(J22-J25) -> 22.2 | K70: =+K95/365*(K22-K25) -> 24.642 | L70: =+L95/365*(L22-L25) -> 27.35262 | M70: =+M95/365*(M22-M25) -> 30.361408 | N70: =+N95/365*(N22-N25) -> 33.701163 | O70: =+O95/365*(O22-O25) -> 37.408291
C71: Deferred revenue | F71: =+Instructions!D37 -> 20 | I71: =+F71-G71+H71 -> 20 | J71: =+J96*J22 -> 22.2 | K71: =+K96*K22 -> 24.642 | L71: =+L96*L22 -> 27.35262 | M71: =+M96*M22 -> 30.361408 | N71: =+N96*N22 -> 33.701163 | O71: =+O96*O22 -> 37.408291
C72: Total CL | F72: =+F71+F70+F69 -> 40 | I72: =+I71+I70+I69 -> 40 | J72: =+J71+J70+J69 -> 44.4 | K72: =+K71+K70+K69 -> 49.284 | L72: =+L71+L70+L69 -> 54.70524 | M72: =+M71+M70+M69 -> 60.722816 | N72: =+N71+N70+N69 -> 67.402326 | O72: =+O71+O70+O69 -> 74.816582
C74: Existing debt | F74: 0
C75: Senior debt | F75: 0 | H75: =+K3 -> 180.18018 | I75: =+F75-G75+H75 -> 180.18018 | J75: =+J153 -> 169.79563 | K75: =+K153 -> 156.63064 | L75: =+L153 -> 139.66564 | M75: =+M153 -> 118.02223 | N75: =+N153 -> 90.839813 | O75: =+O153 -> 57.209919
C76: Mezz | F76: 0 | H76: =+K4 -> 36.036036 | I76: =+F76-G76+H76 -> 36.036036 | J76: =+J158 -> 38.198198 | K76: =+K158 -> 40.49009 | L76: =+L158 -> 42.919495 | M76: =+M158 -> 45.494665 | N76: =+N158 -> 48.224345 | O76: =+O158 -> 51.117806
C77: Total liabilities | F77: =+F76+F75+F74+F72 -> 40 | I77: =+I76+I75+I74+I72 -> 256.21622 | J77: =+J76+J75+J74+J72 -> 252.39383 | K77: =+K76+K75+K74+K72 -> 246.40473 | L77: =+L76+L75+L74+L72 -> 237.29038 | M77: =+M76+M75+M74+M72 -> 224.23971 | N77: =+N76+N75+N74+N72 -> 206.46648 | O77: =+O76+O75+O74+O72 -> 183.14431
C79: Common equity | F79: =+F67-F77 -> 60 | G79: =+F79+O4 -> 64.8 | H79: =+K5 -> 293.18378 | I79: =+F79-G79+H79 -> 288.38378 | J79: =+I79+J54 -> 299.26583 | K79: =+J79+K54 -> 314.21783 | L79: =+K79+L54 -> 333.86781 | M79: =+L79+M54 -> 358.94649 | N79: =+M79+N54 -> 390.28987 | O79: =+N79+O54 -> 428.84717
C81: L + E | F81: =+F79+F77 -> 100 | I81: =+I79+I77 -> 544.6 | J81: =+J79+J77 -> 551.65966 | K81: =+K79+K77 -> 560.62257 | L81: =+L79+L77 -> 571.15819 | M81: =+M79+M77 -> 583.18621 | N81: =+N79+N77 -> 596.75636 | O81: =+O79+O77 -> 611.99148
C83: CHECK | F83: =+F81-F67 -> 0 | I83: =+I81-I67 -> 0 | J83: =+J81-J67 -> 0 | K83: =+K81-K67 -> 0 | L83: =+L81-L67 -> 0 | M83: =+M81-M67 -> 0 | N83: =+N81-N67 -> 0 | O83: =+O81-O67 -> 0
C85: Goowill calcs
C86: Puchase price | E86: =+O3 -> 480
C87: Net identifieable asset | E87: =+(F79-F65)*-1 -> -60
C88: Excess purchase price | E88: =SUM(E86:E87) -> 420 | F88: We assume no write ups hence all excess purchase price is set as goodwill
C90: NWC | I90: =+I62-I59-I72+I69 -> 10 | J90: =+J62-J59-J72+J69 -> 11.1 | K90: =+K62-K59-K72+K69 -> 12.321 | L90: =+L62-L59-L72+L69 -> 13.67631 | M90: =+M62-M59-M72+M69 -> 15.180704 | N90: =+N62-N59-N72+N69 -> 16.850582 | O90: =+O62-O59-O72+O69 -> 18.704146
A92: x | B92: Balance sheeet calcs | I92: =+I$20 -> 0 | J92: =+J$20 -> 1 | K92: =+K$20 -> 2 | L92: =+L$20 -> 3 | M92: =+M$20 -> 4 | N92: =+N$20 -> 5 | O92: =+O$20 -> 6
C93: AR days | I93: =+I60/I22*365 -> 81.03 | J93: =+I93 -> 81.03 | K93: =+J93 -> 81.03 | L93: =+K93 -> 81.03 | M93: =+L93 -> 81.03 | N93: =+M93 -> 81.03 | O93: =+N93 -> 81.03
C94: Other CA % of revenue | I94: =+I61/I22 -> 0.0555 | J94: =+I94 -> 0.0555 | K94: =+J94 -> 0.0555 | L94: =+K94 -> 0.0555 | M94: =+L94 -> 0.0555 | N94: =+M94 -> 0.0555 | O94: =+N94 -> 0.0555
C95: AP days | I95: =+I70/(I22-I25)*365 -> 81.03 | J95: =+I95 -> 81.03 | K95: =+J95 -> 81.03 | L95: =+K95 -> 81.03 | M95: =+L95 -> 81.03 | N95: =+M95 -> 81.03 | O95: =+N95 -> 81.03
C96: Deferred revenue % of revenue | I96: =+I71/I22 -> 0.111 | J96: =+I96 -> 0.111 | K96: =+J96 -> 0.111 | L96: =+K96 -> 0.111 | M96: =+L96 -> 0.111 | N96: =+M96 -> 0.111 | O96: =+N96 -> 0.111
C98: BoP deferred fin' fees | J98: =+I100 -> 9.6 | K98: =+J100 -> 8.2285714 | L98: =+K100 -> 6.8571429 | M98: =+L100 -> 5.4857143 | N98: =+M100 -> 4.1142857 | O98: =+N100 -> 2.7428571
C99: Amort' deferred fin' fees | F99: Useful life, fees (years) | H99: 7 | J99: =+MIN($J$98/$H$99, J98)*-1 -> -1.3714286 | K99: =+MIN($J$98/$H$99, K98)*-1 -> -1.3714286 | L99: =+MIN($J$98/$H$99, L98)*-1 -> -1.3714286 | M99: =+MIN($J$98/$H$99, M98)*-1 -> -1.3714286 | N99: =+MIN($J$98/$H$99, N98)*-1 -> -1.3714286 | O99: =+MIN($J$98/$H$99, O98)*-1 -> -1.3714286
C100: EoP deferred fin' fees | I100: =+I66 -> 9.6 | J100: =SUM(J98:J99) -> 8.2285714 | K100: =SUM(K98:K99) -> 6.8571429 | L100: =SUM(L98:L99) -> 5.4857143 | M100: =SUM(M98:M99) -> 4.1142857 | N100: =SUM(N98:N99) -> 2.7428571 | O100: =SUM(O98:O99) -> 1.3714286
C102: BoP PPE | J102: =+I105 -> 50 | K102: =+J105 -> 51.555556 | L102: =+K105 -> 53.004444 | M102: =+L105 -> 54.334933 | N102: =+M105 -> 55.533998 | O102: =+N105 -> 56.587182
C103: Capex | F103: % of sales | H103: =+Instructions!D28 -> 0.04 | J103: =+$H$103*J22 -> 8 | K103: =+$H$103*K22 -> 8.88 | L103: =+$H$103*L22 -> 9.8568 | M103: =+$H$103*M22 -> 10.941048 | N103: =+$H$103*N22 -> 12.144563 | O103: =+$H$103*O22 -> 13.480465
C104: Depreciation | J104: =+(J107+J116)*-1 -> -6.4444444 | K104: =+(K107+K116)*-1 -> -7.4311111 | L104: =+(L107+L116)*-1 -> -8.5263111 | M104: =+(M107+M116)*-1 -> -9.7419831 | N104: =+(N107+N116)*-1 -> -11.091379 | O104: =+(O107+O116)*-1 -> -12.589209
C105: EoP PPE | I105: =+I64 -> 50 | J105: =SUM(J102:J104) -> 51.555556 | K105: =SUM(K102:K104) -> 53.004444 | L105: =SUM(L102:L104) -> 54.334933 | M105: =SUM(M102:M104) -> 55.533998 | N105: =SUM(N102:N104) -> 56.587182 | O105: =SUM(O102:O104) -> 57.478439
C107: Depreciation of existing PPE | F107: Useful life, PPE (years) | H107: 9 | J107: =+MIN($I$105/$H$107, $I$105-SUM(I107:$J107)) -> 5.5555556 | K107: =+MIN($I$105/$H$107, $I$105-SUM(J107:$J107)) -> 5.5555556 | L107: =+MIN($I$105/$H$107, $I$105-SUM($J107:K107)) -> 5.5555556 | M107: =+MIN($I$105/$H$107, $I$105-SUM($J107:L107)) -> 5.5555556 | N107: =+MIN($I$105/$H$107, $I$105-SUM($J107:M107)) -> 5.5555556 | O107: =+MIN($I$105/$H$107, $I$105-SUM($J107:N107)) -> 5.5555556
C109: Year | D109: Capex
C110: {=+TRANSPOSE(J58:O58)} -> 1 | D110: {=+TRANSPOSE(J103:O103)} -> 8 | J110: =+$D110/$H$107 -> 0.88888889 | K110: =+MIN($D110/$H$107, $D110-SUM($I110:J110)) -> 0.88888889 | L110: =+MIN($D110/$H$107, $D110-SUM($I110:K110)) -> 0.88888889 | M110: =+MIN($D110/$H$107, $D110-SUM($I110:L110)) -> 0.88888889 | N110: =+MIN($D110/$H$107, $D110-SUM($I110:M110)) -> 0.88888889 | O110: =+MIN($D110/$H$107, $D110-SUM($I110:N110)) -> 0.88888889
C111: 2 | D111: 8.88 | K111: =+$D111/$H$107 -> 0.98666667 | L111: =+MIN($D111/$H$107, $D111-SUM($I111:K111)) -> 0.98666667 | M111: =+MIN($D111/$H$107, $D111-SUM($I111:L111)) -> 0.98666667 | N111: =+MIN($D111/$H$107, $D111-SUM($I111:M111)) -> 0.98666667 | O111: =+MIN($D111/$H$107, $D111-SUM($I111:N111)) -> 0.98666667
C112: 3 | D112: 9.8568 | L112: =+$D112/$H$107 -> 1.0952 | M112: =+MIN($D112/$H$107, $D112-SUM($I112:L112)) -> 1.0952 | N112: =+MIN($D112/$H$107, $D112-SUM($I112:M112)) -> 1.0952 | O112: =+MIN($D112/$H$107, $D112-SUM($I112:N112)) -> 1.0952
C113: 4 | D113: 10.941048 | M113: =+$D113/$H$107 -> 1.215672 | N113: =+MIN($D113/$H$107, $D113-SUM($I113:M113)) -> 1.215672 | O113: =+MIN($D113/$H$107, $D113-SUM($I113:N113)) -> 1.215672
C114: 5 | D114: 12.144563 | N114: =+$D114/$H$107 -> 1.3493959 | O114: =+MIN($D114/$H$107, $D114-SUM($I114:N114)) -> 1.3493959
C115: 6 | D115: 13.480465 | O115: =+$D115/$H$107 -> 1.4978295
C116: Depreciation of PPE from capex | J116: =+SUM(J110:J115) -> 0.88888889 | K116: =+SUM(K110:K115) -> 1.8755556 | L116: =+SUM(L110:L115) -> 2.9707556 | M116: =+SUM(M110:M115) -> 4.1864276 | N116: =+SUM(N110:N115) -> 5.5358235 | O116: =+SUM(O110:O115) -> 7.0336529
A118: x | B118: Cash flow statement | I118: =+I$20 -> 0 | J118: =+J$20 -> 1 | K118: =+K$20 -> 2 | L118: =+L$20 -> 3 | M118: =+M$20 -> 4 | N118: =+N$20 -> 5 | O118: =+O$20 -> 6
C119: Net income | J119: =+J54 -> 10.882049 | K119: =+K54 -> 14.952 | L119: =+L54 -> 19.649978 | M119: =+M54 -> 25.07868 | N119: =+N54 -> 31.343382 | O119: =+O54 -> 38.557301
C120: (+) Depreciation | J120: =+J104*-1 -> 6.4444444 | K120: =+K104*-1 -> 7.4311111 | L120: =+L104*-1 -> 8.5263111 | M120: =+M104*-1 -> 9.7419831 | N120: =+N104*-1 -> 11.091379 | O120: =+O104*-1 -> 12.589209
C121: (+) Amortization of fin' fees | J121: =+J99*-1 -> 1.3714286 | K121: =+K99*-1 -> 1.3714286 | L121: =+L99*-1 -> 1.3714286 | M121: =+M99*-1 -> 1.3714286 | N121: =+N99*-1 -> 1.3714286 | O121: =+O99*-1 -> 1.3714286
C122: (+) PIK interest | J122: =+J160*-1 -> 2.1621622 | K122: =+K160*-1 -> 2.2918919 | L122: =+L160*-1 -> 2.4294054 | M122: =+M160*-1 -> 2.5751697 | N122: =+N160*-1 -> 2.7296799 | O122: =+O160*-1 -> 2.8934607
C123: Chg in NWC | J123: =+I90-J90 -> -1.1 | K123: =+J90-K90 -> -1.221 | L123: =+K90-L90 -> -1.35531 | M123: =+L90-M90 -> -1.5043941 | N123: =+M90-N90 -> -1.6698775 | O123: =+N90-O90 -> -1.853564
C124: Operating CF | J124: =+J123+J122+J121+J120+J119 -> 19.760084 | K124: =+K123+K122+K121+K120+K119 -> 24.825432 | L124: =+L123+L122+L121+L120+L119 -> 30.621813 | M124: =+M123+M122+M121+M120+M119 -> 37.262868 | N124: =+N123+N122+N121+N120+N119 -> 44.865992 | O124: =+O123+O122+O121+O120+O119 -> 53.557834
C126: Capex | J126: =+J103*-1 -> -8 | K126: =+K103*-1 -> -8.88 | L126: =+L103*-1 -> -9.8568 | M126: =+M103*-1 -> -10.941048 | N126: =+N103*-1 -> -12.144563 | O126: =+O103*-1 -> -13.480465
C127: Investing CF | J127: =+J126 -> -8 | K127: =+K126 -> -8.88 | L127: =+L126 -> -9.8568 | M127: =+M126 -> -10.941048 | N127: =+N126 -> -12.144563 | O127: =+O126 -> -13.480465
C129: Debt (paydown) / drawdown | J129: =+J145+J151+J152 -> -10.384547 | K129: =+K145+K151+K152 -> -13.164989 | L129: =+L145+L151+L152 -> -16.965001 | M129: =+M145+M151+M152 -> -21.64341 | N129: =+N145+N151+N152 -> -27.18242 | O129: =+O145+O151+O152 -> -33.629894
C130: Financing CF | J130: =+J129 -> -10.384547 | K130: =+K129 -> -13.164989 | L130: =+L129 -> -16.965001 | M130: =+M129 -> -21.64341 | N130: =+N129 -> -27.18242 | O130: =+O129 -> -33.629894
C132: Net cash flows | J132: =+J130+J127+J124 -> 1.3755376 | K132: =+K130+K127+K124 -> 2.7804425 | L132: =+L130+L127+L124 -> 3.800012 | M132: =+M130+M127+M124 -> 4.6784092 | N132: =+N130+N127+N124 -> 5.5390094 | O132: =+O130+O127+O124 -> 6.4474747
...
