Workbook
Name \P: #REF!
Name _: #REF!
Name __EPS01: [2]XOM!$F$34
Name __EPS02: [2]XOM!$G$34
Name __EPS03: [2]XOM!$H$34
Name __EPS04: [2]XOM!$I$34
Name __EPS98: [2]XOM!$C$34
Name __EPS99: [2]XOM!$D$34
Name __lag1: [3]Chart!$C$28:$D$108
Name __lag2: [3]Chart!$G$28:$H$108
Name __ta1: #REF!
Name __TA27: #REF!
Name _1_bbl_CFPS: #REF!
Name _1_bbl_DACF: #REF!
Name _1_bbl_EPS: #REF!
Name _10_mmcf_d_CFPS: #REF!
Name _10_mmcf_d_EPS: #REF!
Name _1000_b_d_CFPS: #REF!
Name _1000_b_d_EPS: #REF!
Name _10c_mcf_CFPS: #REF!
Name _10c_mcf_DACF: #REF!
Name _10c_mcf_EPS: #REF!
Name _10Module1_.INTERNAL: #N/A
Name _10Module2_.CLIENTS: #N/A
Name _11Module1_.INTERNAL: #N/A
Name _11Module2_.CLIENTS: #N/A
Name _12Module1_.INTERNAL: #N/A
Name _12Module2_.CLIENTS: #N/A
Name _13Module1_.INTERNAL: #N/A
Name _13Module2_.CLIENTS: #N/A
Name _14Module1_.INTERNAL: #N/A
Name _14Module2_.CLIENTS: #N/A
Name _14Module2_.INTERNAL: #N/A
Name _15Module1_.INTERNAL: #N/A
Name _15Module2_.CLIENTS: #N/A
Name _15Module2_.INTERNAL: #N/A
Name _16Module1_.INTERNAL: #N/A
Name _16Module2_.INTERNAL: #N/A
Name _17Module1_.INTERNAL: #N/A
Name _17Module2_.CLIENTS: #N/A
Name _18Module1_.INTERNAL: #N/A
Name _18Module2_.CLIENTS: #N/A
Name _19Module2_.CLIENTS: #N/A
Name _19Module2_.INTERNAL: #N/A
Name _1Module1_.CLIENTS: #N/A
Name _20Module2_.CLIENTS: #N/A
Name _20Module2_.INTERNAL: #N/A
Name _21Module2_.CLIENTS: #N/A
Name _21Module2_.INTERNAL: #N/A
Name _22Module2_.CLIENTS: #N/A
Name _23Module2_.CLIENTS: #N/A
Name _23Module2_.INTERNAL: #N/A
Name _24Module2_.CLIENTS: #N/A
Name _24Module2_.INTERNAL: #N/A
Name _25_0_0Loan_Loss_Provision_f: #REF!
Name _25Module2_.CLIENTS: #N/A
Name _26_0_0Loan_Loss_Provision_f: #REF!
Name _26Module2_.CLIENTS: #N/A
Name _27_0_0Loan_Loss_Provision_f: #REF!
Name _27Module2_.CLIENTS: #N/A

Sheet MW UPLOAD
A1: Uploaded 244/244 values at 12/18/2024, 1:44:13 PM | D1: Period | E1: Q1 | F1: Q2 | G1: Q3 | H1: Q4 | I1: Q1 | J1: Q2 | K1: Q3 | L1: Q4 | M1: Q1 | N1: Q2 | O1: Q3 | P1: Q4 | Q1: Q1 | R1: Q2 | S1: Q3 | T1: Q4 | U1: Q1 | V1: Q2 | W1: Q3 | X1: Q4 | Y1: Q1 | Z1: Q2 | AA1: Q3 | AB1: Q4 | AC1: FY | AD1: FY | AE1: FY
A2: Namespace | B2: SecurityID | C2: Full metric name in model | D2: Metric name in MW database | E2: 2021 | F2: 2021 | G2: 2021 | H2: 2021 | I2: 2022 | J2: 2022 | K2: 2022 | L2: 2022 | M2: 2023 | N2: 2023 | O2: 2023 | P2: 2023 | Q2: 2024 | R2: 2024 | S2: 2024 | T2: 2024 | U2: 2025 | V2: 2025 | W2: 2025 | X2: 2025 | Y2: 2026 | Z2: 2026 | AA2: 2026 | AB2: 2026 | AC2: 2024 | AD2: 2025 | AE2: 2026
A3: AZAFAR | B3: 3626 | C3: Investment thesis | D3: THESIS
C4: Revenue | D4: SALES
A5: Company | B5: BBTicker | C5: Gross profit | D5: GP
A6: CAT US EQUITY | B6: CAT US | C6: EBITDA | D6: EBITDA | Q6: =Model!AT45 -> 4043 | R6: =Model!AU45 -> 4013 | S6: =Model!AV45 -> 3690 | T6: =Model!AW45 -> 3691.3916 | U6: =Model!AZ45 -> 3773.7288 | V6: =Model!BA45 -> 4000.4081 | W6: =Model!BB45 -> 3696.4937 | X6: =Model!BC45 -> 3804.2113 | Y6: =Model!BF45 -> 4058.7463 | Z6: =Model!BG45 -> 4304.3283 | AA6: =Model!BH45 -> 3995.0545 | AB6: =Model!BI45 -> 4114.994 | AC6: =SUM(Q6:T6) -> 15437.392 | AD6: =SUM(U6:X6) -> 15274.842 | AE6: =SUM(Y6:AB6) -> 16473.123
C7: Operating profit | D7: EBIT | Q7: =Model!AT35 -> 3519 | R7: =Model!AU35 -> 3482 | S7: =Model!AV35 -> 3147 | T7: =Model!AW35 -> 3100.1916 | U7: =Model!AZ35 -> 3231.5688 | V7: =Model!BA35 -> 3450.8981 | W7: =Model!BB35 -> 3134.4737 | X7: =Model!BC35 -> 3192.0793 | Y7: =Model!BF35 -> 3497.6791 | Z7: =Model!BG35 -> 3735.5436 | AA7: =Model!BH35 -> 3413.2261 | AB7: =Model!BI35 -> 3481.056 | AC7: =SUM(Q7:T7) -> 13248.192 | AD7: =SUM(U7:X7) -> 13009.02 | AE7: =SUM(Y7:AB7) -> 14127.505
C8: Adjusted operating profit | D8: AEBIT
C9: Pre-tax profit | D9: PBT
C10: Post-tax profit | D10: PAT
C11: Diluted weighted average shares | D11: WAS | Q11: =Model!AT81 -> 496.9 | R11: =Model!AU81 -> 489.5 | S11: =Model!AV81 -> 486.7 | T11: =Model!AW81 -> 484.47778 | U11: =Model!AZ81 -> 480.31111 | V11: =Model!BA81 -> 476.14444 | W11: =Model!BB81 -> 471.97778 | X11: =Model!BC81 -> 467.81111 | Y11: =Model!BF81 -> 463.64444 | Z11: =Model!BG81 -> 459.47778 | AA11: =Model!BH81 -> 454.61667 | AB11: =Model!BI81 -> 449.75556 | AC11: =T11 -> 484.47778 | AD11: =X11 -> 467.81111 | AE11: =AB11 -> 449.75556
C12: Reported diluted EPS | D12: EPS | Q12: =Model!AT65 -> 5.7476353 | R12: =Model!AU65 -> 5.4770174 | S12: =Model!AV65 -> 5.0626669 | T12: =Model!AW65 -> 4.9192627 | U12: =Model!AZ65 -> 5.1976532 | V12: =Model!BA65 -> 5.6001301 | W12: =Model!BB65 -> 5.1299912 | X12: =Model!BC65 -> 5.2711152 | Y12: =Model!BF65 -> 5.8293077 | Z12: =Model!BG65 -> 6.2833748 | AA12: =Model!BH65 -> 5.8010961 | AB12: =Model!BI65 -> 5.9806781 | AC12: =SUM(Q12:T12) -> 21.206582 | AD12: =SUM(U12:X12) -> 21.19889 | AE12: =SUM(Y12:AB12) -> 23.894457
C13: Adjusted diluted EPS | D13: AEPS | Q13: =Model!AT78 -> 5.598712 | R13: =Model!AU78 -> 5.9918284 | S13: =Model!AV78 -> 5.1736182 | T13: =Model!AW78 -> 5.1070939 | U13: =Model!AZ78 -> 5.1976532 | V13: =Model!BA78 -> 5.6001301 | W13: =Model!BB78 -> 5.1299912 | X13: =Model!BC78 -> 5.2711152 | Y13: =Model!BF78 -> 5.8293077 | Z13: =Model!BG78 -> 6.2833748 | AA13: =Model!BH78 -> 5.8010961 | AB13: =Model!BI78 -> 5.9806781 | AC13: =SUM(Q13:T13) -> 21.871253 | AD13: =SUM(U13:X13) -> 21.19889 | AE13: =SUM(Y13:AB13) -> 23.894457
C14: Dividend per share | D14: DPS
C15: Free Cash Flow | D15: FCF | Q15: =Model!AT162+Model!AT165 -> 1552 | R15: =Model!AU162+Model!AU165 -> 2680 | S15: =Model!AV162+Model!AV165 -> 3125 | T15: =Model!AW162+Model!AW165 -> 3568.6433 | U15: =Model!AZ162+Model!AZ165 -> 679.32546 | V15: =Model!BA162+Model!BA165 -> 2876.0156 | W15: =Model!BB162+Model!BB165 -> 2890.2851 | X15: =Model!BC162+Model!BC165 -> 3607.5332 | Y15: =Model!BF162+Model!BF165 -> 531.52503 | Z15: =Model!BG162+Model!BG165 -> 3077.9689 | AA15: =Model!BH162+Model!BH165 -> 3108.0668 | AB15: =Model!BI162+Model!BI165 -> 3834.5733 | AC15: =SUM(Q15:T15) -> 10925.643 | AD15: =SUM(U15:X15) -> 10053.159 | AE15: =SUM(Y15:AB15) -> 10552.134
C16: Net debt including lease liabilities | D16: ND | Q16: =Model!AT122-Model!AT99 -> 19872 | R16: =Model!AU122-Model!AU99 -> 19495 | S16: =Model!AV122-Model!AV99 -> 20146 | T16: =Model!AW122-Model!AW99 -> 18156.945 | U16: =Model!AZ122-Model!AZ99 -> 19732.334 | V16: =Model!BA122-Model!BA99 -> 19215.157 | W16: =Model!BB122-Model!BB99 -> 18619.792 | X16: =Model!BC122-Model!BC99 -> 17320.835 | Y16: =Model!BF122-Model!BF99 -> 19072.541 | Z16: =Model!BG122-Model!BG99 -> 18381.457 | AA16: =Model!BH122-Model!BH99 -> 17846.953 | AB16: =Model!BI122-Model!BI99 -> 16597.946 | AC16: =T16 -> 18156.945 | AD16: =X16 -> 17320.835 | AE16: =AB16 -> 16597.946
C17: Net debt ex lease liabilities | D17: NDXL
C18: Shareholders' funds | D18: EQUITY
C19: M&A sales growth | D19: MAG
C20: Organic sales growth | D20: OSG
C21: Adj gross profit | D21: GPA
C22: Share of adj assocs in EBIT | D22: JVEBIT
C23: Other income/expense in EBIT | D23: OTHEREBIT
C24: Total one-offs in EBIT | D24: EXINEBIT
C25: Net interest on debt | D25: NINT
C26: Net finance charge | D26: NFC
C27: Share of adj assocs below EBIT | D27: JVPBTA
C28: Other income/expense below EBIT | D28: OTHERPBT
... C35: Reported PAT | D35: RPAT
C36: Net capex | D36: CAPEX | Q36: =-Model!AT86 -> 500 | R36: =-Model!AU86 -> 341 | S36: =-Model!AV86 -> 444 | T36: =-Model!AW86 -> 647.8 | U36: =-Model!AZ86 -> 541.14 | V36: =-Model!BA86 -> 386.3 | W36: =-Model!BB86 -> 491.12 | X36: =-Model!BC86 -> 709.166 | Y36: =-Model!BF86 -> 584.0238 | Z36: =-Model!BG86 -> 433.652 | AA36: =-Model!BH86 -> 540.4154 | AB36: =-Model!BI86 -> 773.46182 | AC36: =-[52]Model!BG97 -> 884.57722 | AD36: =-[52]Model!BH97 -> 883.5114 | AE36: =-[52]Model!BI97 -> 904.45938
C37: Change in WC | D37: DWC
C38: New capitalised leases | D38: CFLEASE
C39: Acquisitions | D39: ACQS
C40: Disposals | D40: DISP
C41: Dividends paid | D41: DIVP
C42: Net equity issues/buy-backs | D42: SBB
C43: Property, plant and equipment | D43: PPE
C44: Intangible fixed assets | D44: INTANGIBLES
C45: Operating net working capital | D45: OWC
C46: Invested capital | D46: IC
C47: Other Debt | D47: OD | Q47: =Model!AT127+Model!AT123 -> 9731 | R47: =Model!AU127+Model!AU123 -> 9510 | S47: =Model!AV127+Model!AV123 -> 9613 | T47: =Model!AW127+Model!AW123 -> 9613 | U47: =Model!AZ127+Model!AZ123 -> 9613 | V47: =Model!BA127+Model!BA123 -> 9613 | W47: =Model!BB127+Model!BB123 -> 9613 | X47: =Model!BC127+Model!BC123 -> 9613 | Y47: =Model!BF127+Model!BF123 -> 9613 | Z47: =Model!BG127+Model!BG123 -> 9613 | AA47: =Model!BH127+Model!BH123 -> 9613 | AB47: =Model!BI127+Model!BI123 -> 9613 | AC47: =T47 -> 9613 | AD47: =Y47 -> 9613 | AE47: =AB47 -> 9613
C48: CFO | D48: CFO | Q48: =Model!AT162 -> 2052 | R48: =Model!AU162 -> 3021 | S48: =Model!AV162 -> 3569 | T48: =Model!AW162 -> 4216.4433 | U48: =Model!AZ162 -> 1220.4655 | V48: =Model!BA162 -> 3262.3156 | W48: =Model!BB162 -> 3381.4051 | X48: =Model!BC162 -> 4316.6992 | Y48: =Model!BF162 -> 1115.5488 | Z48: =Model!BG162 -> 3511.6209 | AA48: =Model!BH162 -> 3648.4822 | AB48: =Model!BI162 -> 4608.0351 | AC48: =SUM(Q48:T48) -> 12858.443 | AD48: =SUM(U48:X48) -> 12180.885 | AE48: =SUM(Y48:AB48) -> 12883.687
C49: ADJEBITDA | D49: ADJEBITDA | Q49: =Model!AT50 -> 4037 | R49: =Model!AU50 -> 4271 | S49: =Model!AV50 -> 3760 | T49: =Model!AW50 -> 3771.3916 | U49: =Model!AZ50 -> 3773.7288 | V49: =Model!BA50 -> 4000.4081 | W49: =Model!BB50 -> 3696.4937 | X49: =Model!BC50 -> 3804.2113 | Y49: =Model!BF50 -> 4058.7463 | Z49: =Model!BG50 -> 4304.3283 | AA49: =Model!BH50 -> 3995.0545 | AB49: =Model!BI50 -> 4114.994 | AC49: =SUM(Q49:T49) -> 15839.392 | AD49: =SUM(U49:X49) -> 15274.842 | AE49: =SUM(Y49:AB49) -> 16473.123
C50: CFPS | D50: CFPS | Q50: =Q48/Q11 -> 4.1296035 | R50: =R48/R11 -> 6.1716037 | S50: =S48/S11 -> 7.3330594 | T50: =T48/T11 -> 8.7030686 | U50: =U48/U11 -> 2.5409894 | V50: =V48/V11 -> 6.851525 | W50: =W48/W11 -> 7.1643313 | X50: =X48/X11 -> 9.2274405 | ... AB50: =AB48/AB11 -> 10.245643 | AC50: =SUM(Q50:T50) -> 26.337335 | AD50: =SUM(U50:X50) -> 25.784286 | AE50: =SUM(Y50:AB50) -> 28.319726
C51: Dividend | D51: Dividend | Q51: =Model!AT83 -> 1.3 | R51: =Model!AU83 -> 1.3 | S51: =Model!AV83 -> 1.41 | T51: =Model!AW83 -> 1.41 | U51: =Model!AZ83 -> 1.41 | V51: =Model!BA83 -> 1.41 | W51: =Model!BB83 -> 1.5228 | X51: =Model!BC83 -> 1.5228 | Y51: =Model!BF83 -> 1.5228 | Z51: =Model!BG83 -> 1.5228 | AA51: =Model!BH83 -> 1.644624 | AB51: =Model!BI83 -> 1.644624 | AC51: =SUM(Q51:T51) -> 5.42 | AD51: =SUM(U51:X51) -> 5.8656 | AE51: =SUM(Y51:AB51) -> 6.334848
C52: Oratioo | D52: Oratioo | M52: ='Business Build-up'!AN40 -> 0.19089648 | N52: ='Business Build-up'!AO40 -> 0.15019055 | O52: ='Business Build-up'!AP40 -> 0.16525877 | P52: ='Business Build-up'!AQ40 -> 0.17106034 | Q52: ='Business Build-up'!AT40 -> 0.16570669 | R52: ='Business Build-up'!AU40 -> 0.18317455 | S52: ='Business Build-up'!AV40 -> 0.1796225 | T52: ='Business Build-up'!AW40 -> 0.176 | U52: ='Business Build-up'!AZ40 -> 0.16569025 | V52: ='Business Build-up'!BA40 -> 0.18398719 | W52: ='Business Build-up'!BB40 -> 0.17579652 | X52: ='Business Build-up'!BC40 -> 0.1758 | Y52: ='Business Build-up'!BG40 -> 0.18378719 | Z52: ='Business Build-up'!BH40 -> 0.17559652 | AA52: ='Business Build-up'!BI40 -> 0.1756 | AB52: ='Business Build-up'!BJ40 -> 0.17527641 | AC52: =AVERAGE(Q52:T52) -> 0.17612593 | AD52: =AVERAGE(U52:X52) -> 0.17531849 | AE52: =AVERAGE(Y52:AB52) -> 0.17756503
C53: Intermodal | D53: Intermodal
C54: Coal | D54: Coal
C55: Grains | D55: Grains
C56: MM | D56: MM
C57: Auto | D57: Auto
C58: Chemicals | D58: Chemicals
C59: Volumes | D59: Volumes
C60: Pricing | D60: Pricing

Sheet Capitalization
A1: TO Fix this sheet --> TEV does it include Finco? Likely need to edit it out of debt assuming street does not count it. | S1: BEST_CONSENSUS_STAT_OVERRIDE
B2: CAT US EQUITY | C2: KEX | F2: Int. Rate | G2: Int. Exp | H2: / | I2: / | J2: Facility | S2: MEAN
E3: ($mm) | F3: (%) | G3: ($mm) | H3: 22 EBITDA | I3: 23 EBITDA | J3: ($mm) | S3: BEST_FPERIOD_OVERRIDE
B5: Revolving Credit Facility ($mm) | E5: 0 | F5: 0.02 | G5: =E5*F5 -> 0 | J5: 850
B6: Term Loan Due 2024 ($mm) | E6: 305 | F6: 0.02 | G6: =E6*F6 -> 6.1
B7: 3.29% Senior Notes due Feb 2023 ($mm) | E7: 350 | F7: 0.0329 | G7: =E7*F7 -> 11.515
B8: 4.2% Senior Notes due March 2028 ($mm) | E8: 500 | F8: 0.042 | G8: =E8*F8 -> 21
E9: 0 | F9: 0.08625 | G9: =E9*F9 -> 0
E10: 0 | F10: 0.081 | G10: =E10*F10 -> 0
E11: 0 | F11: 0.06251 | G11: =E11*F11 -> 0
E12: 0 | F12: 0.034 | G12: =E12*F12 -> 0
E13: 0 | F13: 0.0335 | G13: =E13*F13 -> 0
E14: 0 | F14: 0.026 | G14: =E14*F14 -> 0
E15: 0 | F15: 0.0725 | G15: =E15*F15 -> 0
E16: 0 | F16: 0.0795 | G16: =E16*F16 -> 0
E17: 0 | F17: 0.0325 | G17: =E17*F17 -> 0
E18: 0 | F18: 0.038 | G18: =E18*F18 -> 0
E19: 0 | F19: 0.068 | G19: =E19*F19 -> 0
E20: 0 | F20: 0.0425 | G20: =E20*F20 -> 0
... E41: 0 | F41: 0.0465 | G41: =E41*F41 -> 0
B74: Others ($mm) | E74: 3.097 | F74: 0.02 | G74: =E74*F74 -> 0.06194
B75: Total Debt ($mm) | E75: =SUM(E5:E74) -> 1158.097 | G75: =SUM(G5:G74) -> 38.67694 | H75: =$E75/$E$88 -> #NAME? | I75: =$E75/$E$89 -> #NAME?
B76: Less: Investments ($mm) | E76: 0
B77: Less: Cash ($mm) | E77: =-32.398 -> -32.398
B78: Net Debt ($mm) | E78: =E75+E77+E76 -> 1125.699 | H78: =$E78/$E$88 -> #NAME? | I78: =$E78/$E$89 -> #NAME?
B80: Shares Outstanding (mm) | E80: 60.3
B81: Share Price ($/share) | E81: {=_xll.BDP("kex us equity","px_last")} -> #NAME?
B82: Equity Value ($mm) | E82: =E80*E81 -> #NAME? | H82: =$E82/$E$88 -> #NAME? | I82: =$E82/$E$89 -> #NAME?
B84: Enterprise Value ($mm) | E84: =E82+E78 -> #NAME? | H84: =$E84/$E$88 -> #NAME? | I84: =$E84/$E$89 -> #NAME?
E87: Consensus
B88: 2022 EBITDA ($mm) | D88: =Model!AL35 -> 7904 | E88: ='Relative to Street'!R18 -> #NAME? | H88: FY2
B89: 2023 EBITDA ($mm) | D89: =Model!AR35 -> 12966 | E89: ='Relative to Street'!S18 -> #NAME? | F89: =E89/E88-1 -> #NAME? | H89: FY3
B90: 2022 CFPS ($mm) | D90: =Model!AL162/Model!AL81 -> 14.646958 | E90: ='Relative to Street'!R47 -> #NAME? | F90: =$E$80/E90 -> #NAME?
B91: 2023 CFPS ($mm) | D91: =Model!AR162/Model!AR81 -> 25.092502 | E91: ='Relative to Street'!S47 -> #NAME? | F91: =$E$80/E91 -> #NAME?
B92: 2022 EPS ($) | D92: =Model!AL78 -> 13.84162 | E92: ='Relative to Street'!R41 -> #NAME? | F92: =$E$81/E92 -> #NAME? | G92: =D92/E92-1 -> #NAME?
B93: 2023 EPS ($) | D93: =Model!AR78 -> 21.2074 | E93: ='Relative to Street'!S41 -> #NAME? | F93: =$E$81/E93 -> #NAME? | G93: =D93/E93-1 -> #NAME?

Sheet Relative to Street
F1: 2 | R1: 2 | S1: 3
B2: CAT US EQUITY | F2: 22Q1 | G2: 22Q2 | H2: 22Q3 | I2: 22Q4 | J2: 23Q1 | K2: 23Q2 | L2: 23Q3 | M2: 23Q4 | N2: 24Q1 | O2: 24Q2 | P2: 24Q3 | Q2: 24Q4 | R2: 22Y | S2: 23Y | T2: 24Y | U2: 25Y | V2: 26Y
F3: Q1 2022 | G3: Q2 2022 | H3: Q3 2022 | I3: Q4 2022 | J3: Q1 2023 | K3: Q2 2023 | L3: Q3 2023 | M3: Q4 2023 | N3: Q1 2024 | O3: Q2 2024 | P3: Q3 2024 | Q3: Q4 2024 | R3: 2022 | S3: 2023 | T3: 2024 | U3: 2025 | V3: 2026
C5: Revenue ($mm)
D6: Asad Zafar | F6: =Model!AH9 -> 13589 | G6: =Model!AI9 -> 14247 | H6: =Model!AJ9 -> 14994 | I6: =Model!AK9 -> 16597 | J6: =Model!AN9 -> 15862 | K6: =Model!AO9 -> 17318 | L6: =Model!AP9 -> 16810 | M6: =Model!AQ9 -> 17070 | N6: =Model!AT9 -> 15799 | O6: =Model!AU9 -> 16689 | P6: =Model!AV9 -> 16106 | Q6: =Model!AW9 -> 16687.25 | R6: =Model!AL9 -> 59427 | S6: =Model!AR9 -> 67060 | T6: =Model!AX9 -> 65281.25 | U6: =Model!BD9 -> 64977.725 | V6: =Model!BJ9 -> 68040.728
D7: Street | F7: =_xll.BDP($B$2, "BEST_Sales","BEST_CONSENSUS_STAT_OVERRIDE","MEAN","BEST_FPERIOD_OVERRIDE",F$2) -> #NAME? | G7: =_xll.BDP($B$2, "BEST_Sales","BEST_CONSENSUS_STAT_OVERRIDE","MEAN","BEST_FPERIOD_OVERRIDE",G$2) -> #NAME? | H7: =_xll.BDP($B$2, "BEST_Sales","BEST_CONSENSUS_STAT_OVERRIDE","MEAN","BEST_FPERIOD_OVERRIDE",H$2) -> #NAME? | I7: =_xll.BDP($B$2, "BEST_Sales","BEST_CONSENSUS_STAT_OVERRIDE","MEAN","BEST_FPERIOD_OVERRIDE",I$2) -> #NAME? | J7: =_xll.BDP($B$2, "BEST_Sales","BEST_CONSENSUS_STAT_OVERRIDE","MEAN","BEST_FPERIOD_OVERRIDE",J$2) -> #NAME? | K7: =_xll.BDP($B$2, "BEST_Sales","BEST_CONSENSUS_STAT_OVERRIDE","MEAN","BEST_FPERIOD_OVERRIDE",K$2) -> #NAME? | L7: =_xll.BDP($B$2, "BEST_Sales","BEST_CONSENSUS_STAT_OVERRIDE","MEAN","BEST_FPERIOD_OVERRIDE",L$2) -> #NAME? | M7: =_xll.BDP($B$2, "BEST_Sales","BEST_CONSENSUS_STAT_OVERRIDE","MEAN","BEST_FPERIOD_OVERRIDE",M$2) -> #NAME? | ... V7: =_xll.BDP($B$2, "BEST_Sales","BEST_CONSENSUS_STAT_OVERRIDE","MEAN","BEST_FPERIOD_OVERRIDE",V$2) -> #NAME?
D8: Guidance | Z8: =_xll.snt("","SE.Gross_Margin") -> #NAME?
D9: Asad Zafar relative to Street (%) | F9: =F6/F7-1 -> #NAME? | G9: =G6/G7-1 -> #NAME? | H9: =H6/H7-1 -> #NAME? | I9: =I6/I7-1 -> #NAME? | J9: =J6/J7-1 -> #NAME? | K9: =K6/K7-1 -> #NAME? | L9: =L6/L7-1 -> #NAME? | M9: =M6/M7-1 -> #NAME? | ... V9: =V6/V7-1 -> #NAME?
C11: Gross Margin (%)
D12: Asad Zafar | F12: =Model!AK24 -> 0.30023498 | G12: =Model!AL24 -> 0.30418833 | H12: =Model!AM24 -> 0 | I12: =Model!AN24 -> 0.36306897 | J12: =Model!AO24 -> 0.36106941 | K12: =Model!AP24 -> 0.37043427 | L12: =Model!AQ24 -> 0.35465729 | M12: =Model!AR24 -> 0.36225768 | ... Q12: =Model!AV24 -> 0.37501552 | R12: =Model!AR24 -> 0.36225768 | S12: =Model!DD24 -> 0 | T12: =Model!AY24 -> 0 | U12: =Model!AZ24 -> 0.37561348 | V12: =Model!BA24 -> 0.39379119
D13: Street | F13: =_xll.snt("ODFL","SE.Gross_Margin",,"FQ"&F$1)/100 -> #NAME? | G13: =_xll.snt("ODFL","SE.Gross_Margin",,"FQ"&G$1)/100 -> #NAME? | H13: =_xll.snt("ODFL","SE.Gross_Margin",,"FQ"&H$1)/100 -> #NAME? | I13: =_xll.snt("ODFL","SE.Gross_Margin",,"FQ"&I$1)/100 -> #NAME? | J13: =_xll.snt("ODFL","SE.Gross_Margin",,"FQ"&J$1)/100 -> #NAME? | K13: =_xll.snt("ODFL","SE.Gross_Margin",,"FQ"&K$1)/100 -> #NAME? | L13: =_xll.snt("ODFL","SE.Gross_Margin",,"FQ"&L$1)/100 -> #NAME? | M13: =_xll.snt("ODFL","SE.Gross_Margin",,"FQ"&M$1)/100 -> #NAME? | ... Q13: =_xll.snt("ODFL","SE.Gross_Margin",,"FQ"&Q$1)/100 -> #NAME? | R13: =_xll.snt("ODFL","SE.Gross_Margin",,"FY"&R$1)/100 -> #NAME? | S13: =_xll.snt("ODFL","SE.Gross_Margin",,"FY"&S$1)/100 -> #NAME? | T13: =_xll.snt("ODFL","SE.Gross_Margin",,"FY"&T$1)/100 -> #NAME? | U13: =_xll.snt("ODFL","SE.Gross_Margin",,"FY"&U$1)/100 -> #NAME? | V13: =_xll.snt("ODFL","SE.Gross_Margin",,"FY"&V$1)/100 -> #NAME?
D14: Asad Zafar relative to Street (%) | F14: =F12/F13-1 -> #NAME? | G14: =G12/G13-1 -> #NAME? | H14: =H12/H13-1 -> #NAME? | I14: =I12/I13-1 -> #NAME? | J14: =J12/J13-1 -> #NAME? | K14: =K12/K13-1 -> #NAME? | L14: =L12/L13-1 -> #NAME? | M14: =M12/M13-1 -> #NAME? | ... V14: =V12/V13-1 -> #NAME?
C16: Adjusted EBITDA ($mm)
D17: Asad Zafar | F17: =Model!AH50 -> 2425 | G17: =Model!AI50 -> 2525 | H17: =Model!AJ50 -> 3025 | I17: =Model!AK50 -> 3372 | J17: =Model!AN50 -> 3874 | K17: =Model!AO50 -> 4225 | L17: =Model!AP50 -> 4020 | M17: =Model!AQ50 -> 3771 | N17: =Model!AT50 -> 4037 | O17: =Model!AU50 -> 4271 | P17: =Model!AV50 -> 3760 | Q17: =Model!AW50 -> 3771.3916 | R17: =Model!AL50 -> 11347 | S17: =Model!AR50 -> 15890 | T17: =Model!AX50 -> 15839.392 | U17: =Model!BD50 -> 15274.842 | V17: =Model!BJ50 -> 16473.123
D18: Street | F18: =_xll.BDP($B$2, "BEST_EBITDA","BEST_CONSENSUS_STAT_OVERRIDE","MEAN","BEST_FPERIOD_OVERRIDE",F$2) -> #NAME? | G18: =_xll.BDP($B$2, "BEST_EBITDA","BEST_CONSENSUS_STAT_OVERRIDE","MEAN","BEST_FPERIOD_OVERRIDE",G$2) -> #NAME? | H18: =_xll.BDP($B$2, "BEST_EBITDA","BEST_CONSENSUS_STAT_OVERRIDE","MEAN","BEST_FPERIOD_OVERRIDE",H$2) -> #NAME? | I18: =_xll.BDP($B$2, "BEST_EBITDA","BEST_CONSENSUS_STAT_OVERRIDE","MEAN","BEST_FPERIOD_OVERRIDE",I$2) -> #NAME? | J18: =_xll.BDP($B$2, "BEST_EBITDA","BEST_CONSENSUS_STAT_OVERRIDE","MEAN","BEST_FPERIOD_OVERRIDE",J$2) -> #NAME? | K18: =_xll.BDP($B$2, "BEST_EBITDA","BEST_CONSENSUS_STAT_OVERRIDE","MEAN","BEST_FPERIOD_OVERRIDE",K$2) -> #NAME? | L18: =_xll.BDP($B$2, "BEST_EBITDA","BEST_CONSENSUS_STAT_OVERRIDE","MEAN","BEST_FPERIOD_OVERRIDE",L$2) -> #NAME? | M18: =_xll.BDP($B$2, "BEST_EBITDA","BEST_CONSENSUS_STAT_OVERRIDE","MEAN","BEST_FPERIOD_OVERRIDE",M$2) -> #NAME? | ... R18: =_xll.BDP($B$2, "BEST_EBITDA","BEST_CONSENSUS_STAT_OVERRIDE","MEAN","BEST_FPERIOD_OVERRIDE",R$2) -> #NAME? | S18: =_xll.BDP($B$2, "BEST_EBITDA","BEST_CONSENSUS_STAT_OVERRIDE","MEdian","BEST_FPERIOD_OVERRIDE",S$2) -> #NAME? | T18: =_xll.BDP($B$2, "BEST_EBITDA","BEST_CONSENSUS_STAT_OVERRIDE","MEdian","BEST_FPERIOD_OVERRIDE",T$2) -> #NAME? | U18: =_xll.BDP($B$2, "BEST_EBITDA","BEST_CONSENSUS_STAT_OVERRIDE","MEdian","BEST_FPERIOD_OVERRIDE",U$2) -> #NAME? | V18: =_xll.BDP($B$2, "BEST_EBITDA","BEST_CONSENSUS_STAT_OVERRIDE","MEdian","BEST_FPERIOD_OVERRIDE",V$2) -> #NAME?
D19: Guidance
D20: Asad Zafar relative to Street (%) | F20: =F17/F18-1 -> #NAME? | G20: =G17/G18-1 -> #NAME? | H20: =H17/H18-1 -> #NAME? | I20: =I17/I18-1 -> #NAME? | J20: =J17/J18-1 -> #NAME? | K20: =K17/K18-1 -> #NAME? | L20: =L17/L18-1 -> #NAME? | M20: =M17/M18-1 -> #NAME? | ... V20: =V17/V18-1 -> #NAME?
C22: Capital Expenditure:
D23: Asad Zafar | F23: =Model!AH86 -> -346 | G23: =Model!AI86 -> -240 | H23: =Model!AJ86 -> -282 | I23: =Model!AK86 -> -428 | J23: =Model!AN86 -> -422 | K23: =Model!AO86 -> -261 | L23: =Model!AP86 -> -378 | M23: =Model!AQ86 -> -536 | N23: =Model!AT86 -> -500 | O23: =Model!AU86 -> -341 | P23: =Model!AV86 -> -444 | Q23: =Model!AW86 -> -647.8 | R23: =Model!AL86 -> -1296 | S23: =Model!AR86 -> -1597 | T23: =Model!AX86 -> -1932.8 | U23: =Model!BD86 -> -2127.726 | V23: =Model!BJ86 -> -2331.553
D24: Street | F24: =-_xll.BDP($B$2, "BEST_Capex","BEST_CONSENSUS_STAT_OVERRIDE","MEAN","BEST_FPERIOD_OVERRIDE",F$2) -> #NAME? | G24: =-_xll.BDP($B$2, "BEST_Capex","BEST_CONSENSUS_STAT_OVERRIDE","MEAN","BEST_FPERIOD_OVERRIDE",G$2) -> #NAME? | H24: =-_xll.BDP($B$2, "BEST_Capex","BEST_CONSENSUS_STAT_OVERRIDE","MEAN","BEST_FPERIOD_OVERRIDE",H$2) -> #NAME? | I24: =-_xll.BDP($B$2, "BEST_Capex","BEST_CONSENSUS_STAT_OVERRIDE","MEAN","BEST_FPERIOD_OVERRIDE",I$2) -> #NAME? | J24: =-_xll.BDP($B$2, "BEST_Capex","BEST_CONSENSUS_STAT_OVERRIDE","MEAN","BEST_FPERIOD_OVERRIDE",J$2) -> #NAME? | K24: =-_xll.BDP($B$2, "BEST_Capex","BEST_CONSENSUS_STAT_OVERRIDE","MEAN","BEST_FPERIOD_OVERRIDE",K$2) -> #NAME? | L24: =-_xll.BDP($B$2, "BEST_Capex","BEST_CONSENSUS_STAT_OVERRIDE","MEAN","BEST_FPERIOD_OVERRIDE",L$2) -> #NAME? | M24: =-_xll.BDP($B$2, "BEST_Capex","BEST_CONSENSUS_STAT_OVERRIDE","MEAN","BEST_FPERIOD_OVERRIDE",M$2) -> #NAME? | ... V24: =-_xll.BDP($B$2, "BEST_Capex","BEST_CONSENSUS_STAT_OVERRIDE","MEAN","BEST_FPERIOD_OVERRIDE",V$2) -> #NAME?
D25: Asad Zafar relative to Street (%) | F25: =F23/F24-1 -> #NAME? | G25: =G23/G24-1 -> #NAME? | H25: =H23/H24-1 -> #NAME? | I25: =I23/I24-1 -> #NAME? | J25: =J23/J24-1 -> #NAME? | K25: =K23/K24-1 -> #NAME? | L25: =L23/L24-1 -> #NAME? | M25: =M23/M24-1 -> #NAME? | ... V25: =V23/V24-1 -> #NAME?
C27: Adjusted EBITDA Margin (%)
D28: Asad Zafar | F28: =Model!AH51 -> 0.17845316 | G28: =Model!AI51 -> 0.17723029 | H28: =Model!AJ51 -> 0.20174737 | I28: =Model!AK51 -> 0.20316925 | J28: =Model!AN51 -> 0.2442315 | K28: =Model!AO51 -> 0.24396582 | L28: =Model!AP51 -> 0.23914337 | M28: =Model!AQ51 -> 0.22091388 | N28: =Model!AT51 -> 0.2555225 | O28: =Model!AU51 -> 0.25591707 | P28: =Model!AV51 -> 0.23345337 | Q28: =Model!AW51 -> 0.22600438 | R28: =Model!AL51 -> 0.19094015 | S28: =Model!AR51 -> 0.23695198 | T28: =Model!AX51 -> 0.24263309 | U28: =Model!BD51 -> 0.23507813 | V28: =Model!BJ51 -> 0.2421068
D29: Street | F29: =F18/F7 -> #NAME? | G29: =G18/G7 -> #NAME? | H29: =H18/H7 -> #NAME? | I29: =I18/I7 -> #NAME? | J29: =J18/J7 -> #NAME? | K29: =K18/K7 -> #NAME? | L29: =L18/L7 -> #NAME? | M29: =M18/M7 -> #NAME? | ... V29: =V18/V7 -> #NAME?
D30: Guidance
D31: Asad Zafar relative to Street (%) | F31: =F28/F29-1 -> #NAME? | G31: =G28/G29-1 -> #NAME? | H31: =H28/H29-1 -> #NAME? | I31: =I28/I29-1 -> #NAME? | J31: =J28/J29-1 -> #NAME? | K31: =K28/K29-1 -> #NAME? | L31: =L28/L29-1 -> #NAME? | M31: =M28/M29-1 -> #NAME? | ... V31: =V28/V29-1 -> #NAME?
C33: Adjusted EBIT ($mm)
D34: Asad Zafar | F34: =Model!AH40 -> 1868 | G34: =Model!AI40 -> 1972 | H34: =Model!AJ40 -> 2474 | I34: =Model!AK40 -> 2814 | J34: =Model!AN40 -> 3342 | K34: =Model!AO40 -> 3683 | L34: =Model!AP40 -> 3495 | M34: =Model!AQ40 -> 3226 | N34: =Model!AT40 -> 3513 | O34: =Model!AU40 -> 3740 | P34: =Model!AV40 -> 3217 | Q34: =Model!AW40 -> 3180.1916 | R34: =Model!AL40 -> 9128 | S34: =Model!AR40 -> 13746 | T34: =Model!AX40 -> 13650.192 | U34: =Model!BD40 -> 13009.02 | V34: =Model!BJ40 -> 14127.505
D35: Street | F35: =_xll.BDP($B$2, "BEST_EBIT","BEST_CONSENSUS_STAT_OVERRIDE","MEAN","BEST_FPERIOD_OVERRIDE",F$2) -> #NAME? | G35: =_xll.BDP($B$2, "BEST_EBIT","BEST_CONSENSUS_STAT_OVERRIDE","MEAN","BEST_FPERIOD_OVERRIDE",G$2) -> #NAME? | H35: =_xll.BDP($B$2, "BEST_EBIT","BEST_CONSENSUS_STAT_OVERRIDE","MEAN","BEST_FPERIOD_OVERRIDE",H$2) -> #NAME? | I35: =_xll.BDP($B$2, "BEST_EBIT","BEST_CONSENSUS_STAT_OVERRIDE","MEAN","BEST_FPERIOD_OVERRIDE",I$2) -> #NAME? | J35: =_xll.BDP($B$2, "BEST_EBIT","BEST_CONSENSUS_STAT_OVERRIDE","MEAN","BEST_FPERIOD_OVERRIDE",J$2) -> #NAME? | K35: =_xll.BDP($B$2, "BEST_EBIT","BEST_CONSENSUS_STAT_OVERRIDE","MEAN","BEST_FPERIOD_OVERRIDE",K$2) -> #NAME? | L35: =_xll.BDP($B$2, "BEST_EBIT","BEST_CONSENSUS_STAT_OVERRIDE","MEAN","BEST_FPERIOD_OVERRIDE",L$2) -> #NAME? | M35: =_xll.BDP($B$2, "BEST_EBIT","BEST_CONSENSUS_STAT_OVERRIDE","MEAN","BEST_FPERIOD_OVERRIDE",M$2) -> #NAME? | ... V35: =_xll.BDP($B$2, "BEST_EBIT","BEST_CONSENSUS_STAT_OVERRIDE","MEAN","BEST_FPERIOD_OVERRIDE",V$2) -> #NAME?
D36: Guidance
D37: Asad Zafar relative to Street (%) | F37: =F34/F35-1 -> #NAME? | G37: =G34/G35-1 -> #NAME? | H37: =H34/H35-1 -> #NAME? | I37: =I34/I35-1 -> #NAME? | J37: =J34/J35-1 -> #NAME? | K37: =K34/K35-1 -> #NAME? | L37: =L34/L35-1 -> #NAME? | M37: =M34/M35-1 -> #NAME? | ... V37: =V34/V35-1 -> #NAME?
C39: Adjusted EPS ($/share)
D40: Asad Zafar | F40: =Model!AH78 -> 2.8757199 | G40: =Model!AI78 -> 3.1810522 | H40: =Model!AJ78 -> 3.9446498 | I40: =Model!AK78 -> 3.8606258 | J40: =Model!AN78 -> 4.9075857 | K40: =Model!AO78 -> 5.5514563 | L40: =Model!AP78 -> 5.520874 | M40: =Model!AQ78 -> 5.2307692 | N40: =Model!AT78 -> 5.598712 | O40: =Model!AU78 -> 5.9918284 | P40: =Model!AV78 -> 5.1736182 | Q40: =Model!AW78 -> 5.1070939 | R40: =Model!AL78 -> 13.84162 | S40: =Model!AR78 -> 21.2074 | T40: =Model!AX78 -> 21.878617 | U40: =Model!BD78 -> 21.199987 | V40: =Model!BJ78 -> 23.894826
D41: Street | F41: =_xll.BDP($B$2, "BEST_EPS","BEST_CONSENSUS_STAT_OVERRIDE","MEAN","BEST_FPERIOD_OVERRIDE",F$2) -> #NAME? | G41: =_xll.BDP($B$2, "BEST_EPS","BEST_CONSENSUS_STAT_OVERRIDE","MEAN","BEST_FPERIOD_OVERRIDE",G$2) -> #NAME? | H41: =_xll.BDP($B$2, "BEST_EPS","BEST_CONSENSUS_STAT_OVERRIDE","MEAN","BEST_FPERIOD_OVERRIDE",H$2) -> #NAME? | I41: =_xll.BDP($B$2, "BEST_EPS","BEST_CONSENSUS_STAT_OVERRIDE","MEAN","BEST_FPERIOD_OVERRIDE",I$2) -> #NAME? | J41: =_xll.BDP($B$2, "BEST_EPS","BEST_CONSENSUS_STAT_OVERRIDE","MEAN","BEST_FPERIOD_OVERRIDE",J$2) -> #NAME? | K41: =_xll.BDP($B$2, "BEST_EPS","BEST_CONSENSUS_STAT_OVERRIDE","MEAN","BEST_FPERIOD_OVERRIDE",K$2) -> #NAME? | L41: =_xll.BDP($B$2, "BEST_EPS","BEST_CONSENSUS_STAT_OVERRIDE","MEAN","BEST_FPERIOD_OVERRIDE",L$2) -> #NAME? | M41: =_xll.BDP($B$2, "BEST_EPS","BEST_CONSENSUS_STAT_OVERRIDE","MEAN","BEST_FPERIOD_OVERRIDE",M$2) -> #NAME? | ... V41: =_xll.BDP($B$2, "BEST_EPS","BEST_CONSENSUS_STAT_OVERRIDE","MEAN","BEST_FPERIOD_OVERRIDE",V$2) -> #NAME?
D42: Guidance
D43: Asad Zafar relative to Street (%) | F43: =F40/F41-1 -> #NAME? | G43: =G40/G41-1 -> #NAME? | H43: =H40/H41-1 -> #NAME? | I43: =I40/I41-1 -> #NAME? | J43: =J40/J41-1 -> #NAME? | K43: =K40/K41-1 -> #NAME? | L43: =L40/L41-1 -> #NAME? | M43: =M40/M41-1 -> #NAME? | ... V43: =V40/V41-1 -> #NAME?
C45: CFPS ($/share)
D46: Asad Zafar | F46: =(Model!AH162)/Model!AH81 -> 0.58146015 | G46: =(Model!AI162)/Model!AI81 -> 4.180865 | H46: =(Model!AJ162)/Model!AJ81 -> 4.7028718 | I46: =(Model!AK162)/Model!AK81 -> 5.2582069 | J46: =(Model!AN162)/Model!AN81 -> 3.0284944 | K46: =(Model!AO162)/Model!AO81 -> 6.3087379 | L46: =(Model!AP162)/Model!AP81 -> 7.9204058 | M46: =(Model!AQ162)/Model!AQ81 -> 7.8954635 | N46: =(Model!AT162)/Model!AT81 -> 4.1296035 | O46: =(Model!AU162)/Model!AU81 -> 6.1716037 | P46: =(Model!AV162)/Model!AV81 -> 7.3330594 | Q46: =(Model!AW162)/Model!AW81 -> 8.7030686 | R46: =(Model!AL162)/Model!AL81 -> 14.646958 | S46: =(Model!AR162)/Model!AR81 -> 25.092502 | T46: =Model!AX162/Model!AX81 -> 26.274191 | U46: =(Model!BD162)/Model!BD81 -> 25.694758 | V46: =(Model!BJ162)/Model!BJ81 -> 28.199674
D47: Street | F47: =_xll.BDP($B$2, "BEST_CPS","BEST_CONSENSUS_STAT_OVERRIDE","MEAN","BEST_FPERIOD_OVERRIDE",F$2) -> #NAME? | G47: =_xll.BDP($B$2, "BEST_CPS","BEST_CONSENSUS_STAT_OVERRIDE","MEAN","BEST_FPERIOD_OVERRIDE",G$2) -> #NAME? | H47: =_xll.BDP($B$2, "BEST_CPS","BEST_CONSENSUS_STAT_OVERRIDE","MEAN","BEST_FPERIOD_OVERRIDE",H$2) -> #NAME? | I47: =_xll.BDP($B$2, "BEST_CPS","BEST_CONSENSUS_STAT_OVERRIDE","MEAN","BEST_FPERIOD_OVERRIDE",I$2) -> #NAME? | J47: =_xll.BDP($B$2, "BEST_CPS","BEST_CONSENSUS_STAT_OVERRIDE","MEAN","BEST_FPERIOD_OVERRIDE",J$2) -> #NAME? | K47: =_xll.BDP($B$2, "BEST_CPS","BEST_CONSENSUS_STAT_OVERRIDE","MEAN","BEST_FPERIOD_OVERRIDE",K$2) -> #NAME? | L47: =_xll.BDP($B$2, "BEST_CPS","BEST_CONSENSUS_STAT_OVERRIDE","MEAN","BEST_FPERIOD_OVERRIDE",L$2) -> #NAME? | M47: =_xll.BDP($B$2, "BEST_CPS","BEST_CONSENSUS_STAT_OVERRIDE","MEAN","BEST_FPERIOD_OVERRIDE",M$2) -> #NAME? | ... V47: =_xll.BDP($B$2, "BEST_CPS","BEST_CONSENSUS_STAT_OVERRIDE","MEAN","BEST_FPERIOD_OVERRIDE",V$2) -> #NAME?
D48: Guidance
D49: Asad Zafar relative to Street (%) | F49: =F46/F47-1 -> #NAME? | G49: =G46/G47-1 -> #NAME? | H49: =H46/H47-1 -> #NAME? | I49: =I46/I47-1 -> #NAME? | J49: =J46/J47-1 -> #NAME? | K49: =K46/K47-1 -> #NAME? | L49: =L46/L47-1 -> #NAME? | M49: =M46/M47-1 -> #NAME? | ... V49: =V46/V47-1 -> #NAME?
C51: FCF ($mm)
D52: Asad Zafar | F52: =Model!AH162+Model!AH165 -> -33 | G52: =Model!AI162+Model!AI165 -> 1993 | H52: =Model!AJ162+Model!AJ165 -> 2199 | I52: =Model!AK162+Model!AK165 -> 2311 | J52: =Model!AN162+Model!AN165 -> 1151 | K52: =Model!AO162+Model!AO165 -> 2988 | L52: =Model!AP162+Model!AP165 -> 3682 | M52: =Model!AQ162+Model!AQ165 -> 3467 | N52: =Model!AT162+Model!AT165 -> 1552 | O52: =Model!AU162+Model!AU165 -> 2680 | P52: =Model!AV162+Model!AV165 -> 3125 | Q52: =Model!AW162+Model!AW165 -> 3568.6433 | R52: =Model!AL162+Model!AL165 -> 6470 | S52: =Model!AR162+Model!AR165 -> 11288 | T52: =Model!AX162+Model!AX165 -> 10925.643 | U52: =Model!BD162+Model!BD165 -> 10053.159 | V52: =Model!BJ162+Model!BJ165 -> 10552.134
D53: Street | F53: =_xll.BDP($B$2, "BEST_estimate_FCF","BEST_CONSENSUS_STAT_OVERRIDE","MEAN","BEST_FPERIOD_OVERRIDE",F$2) -> #NAME? | G53: =_xll.BDP($B$2, "BEST_estimate_FCF","BEST_CONSENSUS_STAT_OVERRIDE","MEAN","BEST_FPERIOD_OVERRIDE",G$2) -> #NAME? | H53: =_xll.BDP($B$2, "BEST_estimate_FCF","BEST_CONSENSUS_STAT_OVERRIDE","MEAN","BEST_FPERIOD_OVERRIDE",H$2) -> #NAME? | I53: =_xll.BDP($B$2, "BEST_estimate_FCF","BEST_CONSENSUS_STAT_OVERRIDE","MEAN","BEST_FPERIOD_OVERRIDE",I$2) -> #NAME? | J53: =_xll.BDP($B$2, "BEST_estimate_FCF","BEST_CONSENSUS_STAT_OVERRIDE","MEAN","BEST_FPERIOD_OVERRIDE",J$2) -> #NAME? | K53: =_xll.BDP($B$2, "BEST_estimate_FCF","BEST_CONSENSUS_STAT_OVERRIDE","MEAN","BEST_FPERIOD_OVERRIDE",K$2) -> #NAME? | L53: =_xll.BDP($B$2, "BEST_estimate_FCF","BEST_CONSENSUS_STAT_OVERRIDE","MEAN","BEST_FPERIOD_OVERRIDE",L$2) -> #NAME? | M53: =_xll.BDP($B$2, "BEST_estimate_FCF","BEST_CONSENSUS_STAT_OVERRIDE","MEAN","BEST_FPERIOD_OVERRIDE",M$2) -> #NAME? | ... V53: =_xll.BDP($B$2, "BEST_estimate_FCF","BEST_CONSENSUS_STAT_OVERRIDE","MEAN","BEST_FPERIOD_OVERRIDE",V$2) -> #NAME?
D54: Guidance
D55: Asad Zafar relative to Street (%) | F55: =F52/F53-1 -> #NAME? | G55: =G52/G53-1 -> #NAME? | H55: =H52/H53-1 -> #NAME? | I55: =I52/I53-1 -> #NAME? | J55: =J52/J53-1 -> #NAME? | K55: =K52/K53-1 -> #NAME? | L55: =L52/L53-1 -> #NAME? | M55: =M52/M53-1 -> #NAME? | ... V55: =V52/V53-1 -> #NAME?

Sheet Business Build-up
C2: 42735 | D2: =EOMONTH(C2,3) -> 42825 | E2: =EOMONTH(D2,3) -> 42916 | F2: =EOMONTH(E2,3) -> 43008 | G2: =EOMONTH(F2,3) -> 43100 | J2: =EOMONTH(G2,3) -> 43190 | K2: =EOMONTH(J2,3) -> 43281 | L2: =EOMONTH(K2,3) -> 43373 | M2: =EOMONTH(L2,3) -> 43465 | P2: =EOMONTH(M2,3) -> 43555 | Q2: =EOMONTH(P2,3) -> 43646 | R2: =EOMONTH(Q2,3) -> 43738 | S2: =EOMONTH(R2,3) -> 43830 | V2: =EOMONTH(S2,3) -> 43921 | W2: =EOMONTH(V2,3) -> 44012 | X2: =EOMONTH(W2,3) -> 44104 | Y2: =EOMONTH(X2,3) -> 44196 | AB2: =EOMONTH(Y2,3) -> 44286 | AC2: =EOMONTH(AB2,3) -> 44377 | AD2: =EOMONTH(AC2,3) -> 44469 | AE2: =EOMONTH(AD2,3) -> 44561 | AH2: =EOMONTH(AE2,3) -> 44651 | AI2: =EOMONTH(AH2,3) -> 44742 | AJ2: =EOMONTH(AI2,3) -> 44834 | AK2: =EOMONTH(AJ2,3) -> 44926 | AN2: =EOMONTH(AK2,3) -> 45016 | AO2: =EOMONTH(AN2,3) -> 45107 | AP2: =EOMONTH(AO2,3) -> 45199 | AQ2: =EOMONTH(AP2,3) -> 45291 | AT2: =EOMONTH(AQ2,3) -> 45382 | AU2: =EOMONTH(AT2,3) -> 45473 | AV2: =EOMONTH(AU2,3) -> 45565 | AW2: =EOMONTH(AV2,3) -> 45657 | AZ2: =EOMONTH(AW2,3) -> 45747 | BA2: =EOMONTH(AZ2,3) -> 45838 | BB2: =EOMONTH(BA2,3) -> 45930 | BC2: =EOMONTH(BB2,3) -> 46022 | BF2: =EOMONTH(BC2,3) -> 46112 | BG2: =EOMONTH(BF2,3) -> 46203 | BH2: =EOMONTH(BG2,3) -> 46295 | BI2: =EOMONTH(BH2,3) -> 46387 | BL2: =EOMONTH(BI2,3) -> 46477 | BM2: =EOMONTH(BL2,3) -> 46568 | BN2: =EOMONTH(BM2,3) -> 46660 | BO2: =EOMONTH(BN2,3) -> 46752 | BR2: =EOMONTH(BO2,3) -> 46843 | BS2: =EOMONTH(BR2,3) -> 46934 | BT2: =EOMONTH(BS2,3) -> 47026 | BU2: =EOMONTH(BT2,3) -> 47118 | BX2: =EOMONTH(BU2,3) -> 47208 | BY2: =EOMONTH(BX2,3) -> 47299 | BZ2: =EOMONTH(BY2,3) -> 47391 | CA2: =EOMONTH(BZ2,3) -> 47483 | CD2: =EOMONTH(CA2,3) -> 47573 | CE2: =EOMONTH(CD2,3) -> 47664 | CF2: =EOMONTH(CE2,3) -> 47756 | CG2: =EOMONTH(CF2,3) -> 47848 | CJ2: =EOMONTH(CG2,3) -> 47938 | CK2: =EOMONTH(CJ2,3) -> 48029 | CL2: =EOMONTH(CK2,3) -> 48121 | CM2: =EOMONTH(CL2,3) -> 48213
D3: 1-2017 | E3: 2-2017 | F3: 3-2017 | G3: 4-2017 | J3: 1-2018 | K3: 2-2018 | L3: 3-2018 | M3: 4-2018 | P3: 1-2019 | Q3: 2-2019 | R3: 3-2019 | S3: 4-2019 | V3: 1-2020 | W3: 2-2020 | X3: 3-2020 | Y3: 4-2020 | AB3: 1-2021 | AC3: 2-2021 | AD3: 3-2021 | AE3: 4-2021 | AH3: 1-2022 | AI3: 2-2022 | AJ3: 3-2022 | AK3: 4-2022 | AN3: 1-2023 | AO3: 2-2023 | AP3: 3-2023 | AQ3: 4-2023 | AT3: 1-2024 | AU3: 2-2024 | AV3: 3-2024 | AW3: 4-2024 | AZ3: =CONCATENATE(RIGHT(AZ4,1),"-",RIGHT(AW3,4)+1) -> 1-2025 | BA3: =CONCATENATE(RIGHT(BA4,1),"-",RIGHT(AZ3,4)) -> 2-2025 | BB3: =CONCATENATE(RIGHT(BB4,1),"-",RIGHT(BA3,4)) -> 3-2025 | BC3: =CONCATENATE(RIGHT(BC4,1),"-",RIGHT(BB3,4)) -> 4-2025 | BF3: =CONCATENATE(RIGHT(BF4,1),"-",RIGHT(BC3,4)+1) -> 1-2026 | BG3: =CONCATENATE(RIGHT(BG4,1),"-",RIGHT(BF3,4)) -> 2-2026 | BH3: =CONCATENATE(RIGHT(BH4,1),"-",RIGHT(BG3,4)) -> 3-2026 | BI3: =CONCATENATE(RIGHT(BI4,1),"-",RIGHT(BH3,4)) -> 4-2026 | BL3: =CONCATENATE(RIGHT(BL4,1),"-",RIGHT(BI3,4)+1) -> 1-2027 | BM3: =CONCATENATE(RIGHT(BM4,1),"-",RIGHT(BL3,4)) -> 2-2027 | BN3: =CONCATENATE(RIGHT(BN4,1),"-",RIGHT(BM3,4)) -> 3-2027 | BO3: =CONCATENATE(RIGHT(BO4,1),"-",RIGHT(BN3,4)) -> 4-2027 | BR3: =CONCATENATE(RIGHT(BR4,1),"-",RIGHT(BO3,4)+1) -> 1-2028 | BS3: =CONCATENATE(RIGHT(BS4,1),"-",RIGHT(BR3,4)) -> 2-2028 | BT3: =CONCATENATE(RIGHT(BT4,1),"-",RIGHT(BS3,4)) -> 3-2028 | BU3: =CONCATENATE(RIGHT(BU4,1),"-",RIGHT(BT3,4)) -> 4-2028 | BX3: =CONCATENATE(RIGHT(BX4,1),"-",RIGHT(BU3,4)+1) -> 1-2029 | BY3: =CONCATENATE(RIGHT(BY4,1),"-",RIGHT(BX3,4)) -> 2-2029 | BZ3: =CONCATENATE(RIGHT(BZ4,1),"-",RIGHT(BY3,4)) -> 3-2029 | CA3: =CONCATENATE(RIGHT(CA4,1),"-",RIGHT(BZ3,4)) -> 4-2029 | CD3: =CONCATENATE(RIGHT(CD4,1),"-",RIGHT(CA3,4)+1) -> 1-2030 | CE3: =CONCATENATE(RIGHT(CE4,1),"-",RIGHT(CD3,4)) -> 2-2030 | CF3: =CONCATENATE(RIGHT(CF4,1),"-",RIGHT(CE3,4)) -> 3-2030 | CG3: =CONCATENATE(RIGHT(CG4,1),"-",RIGHT(CF3,4)) -> 4-2030 | CJ3: =CONCATENATE(RIGHT(CJ4,1),"-",RIGHT(CG3,4)+1) -> 1-2031 | CK3: =CONCATENATE(RIGHT(CK4,1),"-",RIGHT(CJ3,4)) -> 2-2031 | CL3: =CONCATENATE(RIGHT(CL4,1),"-",RIGHT(CK3,4)) -> 3-2031 | CM3: =CONCATENATE(RIGHT(CM4,1),"-",RIGHT(CL3,4)) -> 4-2031
D4: Q1 | E4: Q2 | F4: Q3 | G4: Q4 | H4: 2017 | J4: Q1 | K4: Q2 | L4: Q3 | M4: Q4 | N4: 2018 | P4: Q1 | Q4: Q2 | R4: Q3 | S4: Q4 | T4: =N4+1 -> 2019 | V4: Q1 | W4: Q2 | X4: Q3 | Y4: Q4 | Z4: =T4+1 -> 2020 | AB4: Q1 | AC4: Q2 | AD4: Q3 | AE4: Q4 | AF4: =Z4+1 -> 2021 | AH4: Q1 | AI4: Q2 | AJ4: Q3 | AK4: Q4 | AL4: =AF4+1 -> 2022 | AN4: Q1 | AO4: Q2 | AP4: Q3 | AQ4: Q4 | AR4: =AL4+1 -> 2023 | AT4: Q1 | AU4: Q2 | AV4: Q3 | AW4: Q4 | AX4: =AR4+1 -> 2024 | AZ4: Q1 | BA4: Q2 | BB4: Q3 | BC4: Q4 | BD4: =AX4+1 -> 2025 | BF4: Q1 | BG4: Q2 | BH4: Q3 | BI4: Q4 | BJ4: =BD4+1 -> 2026 | BL4: Q1 | BM4: Q2 | BN4: Q3 | BO4: Q4 | BP4: =BJ4+1 -> 2027 | BR4: Q1 | BS4: Q2 | BT4: Q3 | BU4: Q4 | BV4: =BP4+1 -> 2028 | BX4: Q1 | BY4: Q2 | BZ4: Q3 | CA4: Q4 | CB4: =BV4+1 -> 2029 | CD4: Q1 | CE4: Q2 | CF4: Q3 | CG4: Q4 | CH4: =CB4+1 -> 2030 | CJ4: Q1 | CK4: Q2 | CL4: Q3 | CM4: Q4 | CN4: =CH4+1 -> 2031
B5: Days | D5: =D2-C2 -> 90 | E5: =E2-D2 -> 91 | F5: =F2-E2 -> 92 | G5: =G2-F2 -> 92 | H5: =SUM(D5:G5) -> 365 | J5: =J2-G2 -> 90 | K5: =K2-J2 -> 91 | L5: =L2-K2 -> 92 | M5: =M2-L2 -> 92 | N5: =SUM(J5:M5) -> 365 | P5: =P2-M2 -> 90 | Q5: =Q2-P2 -> 91 | R5: =R2-Q2 -> 92 | S5: =S2-R2 -> 92 | T5: =SUM(P5:S5) -> 365 | V5: =V2-S2 -> 91 | W5: =W2-V2 -> 91 | X5: =X2-W2 -> 92 | Y5: =Y2-X2 -> 92 | Z5: =SUM(V5:Y5) -> 366 | AB5: =AB2-Y2 -> 90 | AC5: =AC2-AB2 -> 91 | AD5: =AD2-AC2 -> 92 | AE5: =AE2-AD2 -> 92 | AF5: =SUM(AB5:AE5) -> 365 | AH5: =AH2-AE2 -> 90 | AI5: =AI2-AH2 -> 91 | AJ5: =AJ2-AI2 -> 92 | AK5: =AK2-AJ2 -> 92 | AL5: =SUM(AH5:AK5) -> 365 | AN5: =AN2-AK2 -> 90 | AO5: =AO2-AN2 -> 91 | AP5: =AP2-AO2 -> 92 | AQ5: =AQ2-AP2 -> 92 | AR5: =SUM(AN5:AQ5) -> 365 | AT5: =AT2-AQ2 -> 91 | AU5: =AU2-AT2 -> 91 | AV5: =AV2-AU2 -> 92 | AW5: =AW2-AV2 -> 92 | AX5: =SUM(AT5:AW5) -> 366 | AZ5: =AZ2-AW2 -> 90 | BA5: =BA2-AZ2 -> 91 | BB5: =BB2-BA2 -> 92 | BC5: =BC2-BB2 -> 92 | BD5: =SUM(AZ5:BC5) -> 365 | BF5: =BF2-BC2 -> 90 | BG5: =BG2-BF2 -> 91 | BH5: =BH2-BG2 -> 92 | BI5: =BI2-BH2 -> 92 | BJ5: =SUM(BF5:BI5) -> 365 | BL5: =BL2-BI2 -> 90 | BM5: =BM2-BL2 -> 91 | BN5: =BN2-BM2 -> 92 | BO5: =BO2-BN2 -> 92 | BP5: =SUM(BL5:BO5) -> 365 | BR5: =BR2-BO2 -> 91 | BS5: =BS2-BR2 -> 91 | BT5: =BT2-BS2 -> 92 | BU5: =BU2-BT2 -> 92 | BV5: =SUM(BR5:BU5) -> 366 | BX5: =BX2-BU2 -> 90 | BY5: =BY2-BX2 -> 91 | BZ5: =BZ2-BY2 -> 92 | CA5: =CA2-BZ2 -> 92 | CB5: =SUM(BX5:CA5) -> 365 | CD5: =CD2-CA2 -> 90 | CE5: =CE2-CD2 -> 91 | CF5: =CF2-CE2 -> 92 | CG5: =CG2-CF2 -> 92 | CH5: =SUM(CD5:CG5) -> 365 | CJ5: =CJ2-CG2 -> 90 | CK5: =CK2-CJ2 -> 91 | CL5: =CL2-CK2 -> 92 | CM5: =CM2-CL2 -> 92 | CN5: =SUM(CJ5:CM5) -> 365
B6: Revenue Buildup:
B7: ME&T | D7: 9130 | E7: 10639 | F7: 10713 | G7: 12194 | H7: =SUM(D7:G7) -> 42676 | J7: 12150 | K7: 13279 | L7: 12763 | M7: 13630 | N7: =SUM(J7:M7) -> 51822 | P7: 12724 | Q7: 13671 | R7: 11974 | S7: 12386 | T7: =SUM(P7:S7) -> 50755 | V7: 9914 | W7: 9310 | X7: 9228 | Y7: 10570 | Z7: =SUM(V7:Y7) -> 39022 | AB7: 11191 | AC7: 12193 | AD7: 11707 | AE7: 13097 | AF7: =SUM(AB7:AE7) -> 48188 | AH7: 12886 | AI7: 13539 | AJ7: 14278 | AK7: 15871 | AL7: =SUM(AH7:AK7) -> 56574 | AN7: 15099 | AO7: 16545 | AP7: 15988 | AQ7: 16237 | AR7: =SUM(AN7:AQ7) -> 63869 | AT7: 14960 | AU7: 15840 | AV7: 15231 | AW7: =AW57 -> 15812.6 | AX7: =SUM(AT7:AW7) -> 61843.6 | AZ7: =AZ57 -> 14513.1 | BA7: =BA57 -> 15556.75 | BB7: =BB57 -> 15263.14 | BC7: =BC57 -> 16035.202 | BD7: =SUM(AZ7:BC7) -> 61368.192 | BF7: =BF57 -> 15199.025 | BG7: =BG57 -> 16291.806 | BH7: =BH57 -> 15982.659 | BI7: =BI57 -> 16787.549 | BJ7: =SUM(BF7:BI7) -> 64261.039 | BL7: =BL57 -> 15820.402 | BM7: =BM57 -> 16961.505 | BN7: =BN57 -> 16637.861 | BO7: =BO57 -> 17479.691 | BP7: =SUM(BL7:BO7) -> 66899.46 | BR7: =BR57 -> 16468.267 | BS7: =BS57 -> 17659.897 | BT7: =BT57 -> 17321.065 | BU7: =BU57 -> 18201.645 | BV7: =SUM(BR7:BU7) -> 69650.874 | BX7: =BX57 -> 17143.787 | BY7: =BY57 -> 18388.252 | BZ7: =BZ57 -> 18033.508 | CA7: =CA57 -> 18954.739 | CB7: =SUM(BX7:CA7) -> 72520.286 | CD7: =CD57 -> 17848.183 | CE7: =CE57 -> 19147.898 | CF7: =CF57 -> 18776.482 | CG7: =CG57 -> 19740.361 | CH7: =SUM(CD7:CG7) -> 75512.925 | CJ7: =CJ57 -> 18582.73 | CK7: =CK57 -> 19940.224 | CL7: =CL57 -> 19551.34 | CM7: =CM57 -> 20559.965 | CN7: =SUM(CJ7:CM7) -> 78634.258
B8: Financial Products | D8: 692 | E8: 692 | F8: 700 | G8: 702 | H8: =SUM(D8:G8) -> 2786 | J8: 709 | K8: 732 | L8: 747 | M8: 712 | N8: =SUM(J8:M8) -> 2900 | P8: 742 | Q8: 761 | R8: 784 | S8: 758 | T8: =SUM(P8:S8) -> 3045 | V8: 721 | W8: 687 | X8: 653 | Y8: 665 | Z8: =SUM(V8:Y8) -> 2726 | AB8: 696 | AC8: 696 | AD8: 690 | AE8: 701 | AF8: =SUM(AB8:AE8) -> 2783 | AH8: 703 | AI8: 708 | AJ8: 716 | AK8: 726 | AL8: =SUM(AH8:AK8) -> 2853 | AN8: 763 | AO8: 773 | AP8: 822 | AQ8: 833 | AR8: =SUM(AN8:AQ8) -> 3191 | AT8: 839 | AU8: 849 | AV8: 875 | AW8: =AW277 -> 874.65 | AX8: =SUM(AT8:AW8) -> 3437.65 | AZ8: =AZ277 -> 880.95 | BA8: =BA277 -> 891.45 | BB8: =BB277 -> 918.75 | BC8: =BC277 -> 918.3825 | BD8: =SUM(AZ8:BC8) -> 3609.5325 | BF8: =BF277 -> 922.58588 | BG8: =BG277 -> 933.57099 | BH8: =BH277 -> 962.06073 | BI8: =BI277 -> 961.47162 | BJ8: =SUM(BF8:BI8) -> 3779.6892 | BL8: =BL277 -> 960.30369 | BM8: =BM277 -> 971.94684 | BN8: =BN277 -> 1001.5 | BO8: =BO277 -> 1001.1126 | BP8: =SUM(BL8:BO8) -> 3934.8631 | BR8: =BR277 -> 999.6293 | BS8: =BS277 -> 1011.9669 | BT8: =BT277 -> 1042.6248 | BU8: =BU277 -> 1042.4609 | BV8: =SUM(BR8:BU8) -> 4096.6819 | BX8: =BX277 -> 1040.6336 | BY8: =BY277 -> 1053.7039 | BZ8: =BZ277 -> 1085.5096 | CA8: =CA277 -> 1085.5928 | CB8: =SUM(BX8:CA8) -> 4265.4399 | CD8: =CD277 -> 1083.3907 | CE8: =CE277 -> 1097.2339 | CF8: =CF277 -> 1130.2322 | CG8: =CG277 -> 1130.5877 | CH8: =SUM(CD8:CG8) -> 4441.4445 | CJ8: =CJ277 -> 1127.9779 | CK8: =CK277 -> 1142.6366 | CL8: =CL277 -> 1176.8741 | CM8: =CM277 -> 1177.5288 | CN8: =SUM(CJ8:CM8) -> 4625.0174
B9: Total Revenue ($mm) | D9: =SUM(D7:D8) -> 9822 | E9: =SUM(E7:E8) -> 11331 | F9: =SUM(F7:F8) -> 11413 | G9: =SUM(G7:G8) -> 12896 | H9: =SUM(H7:H8) -> 45462 | J9: =SUM(J7:J8) -> 12859 | K9: =SUM(K7:K8) -> 14011 | L9: =SUM(L7:L8) -> 13510 | M9: =SUM(M7:M8) -> 14342 | N9: =SUM(N7:N8) -> 54722 | P9: =SUM(P7:P8) -> 13466 | Q9: =SUM(Q7:Q8) -> 14432 | R9: =SUM(R7:R8) -> 12758 | S9: =SUM(S7:S8) -> 13144 | T9: =SUM(T7:T8) -> 53800 | V9: =SUM(V7:V8) -> 10635 | W9: =SUM(W7:W8) -> 9997 | X9: =SUM(X7:X8) -> 9881 | Y9: =SUM(Y7:Y8) -> 11235 | Z9: =SUM(Z7:Z8) -> 41748 | AB9: =SUM(AB7:AB8) -> 11887 | AC9: =SUM(AC7:AC8) -> 12889 | AD9: =SUM(AD7:AD8) -> 12397 | AE9: =SUM(AE7:AE8) -> 13798 | AF9: =SUM(AF7:AF8) -> 50971 | AH9: =SUM(AH7:AH8) -> 13589 | AI9: =SUM(AI7:AI8) -> 14247 | AJ9: =SUM(AJ7:AJ8) -> 14994 | AK9: =SUM(AK7:AK8) -> 16597 | AL9: =SUM(AL7:AL8) -> 59427 | AN9: =SUM(AN7:AN8) -> 15862 | AO9: =SUM(AO7:AO8) -> 17318 | AP9: =SUM(AP7:AP8) -> 16810 | AQ9: =SUM(AQ7:AQ8) -> 17070 | AR9: =SUM(AR7:AR8) -> 67060 | AT9: =SUM(AT7:AT8) -> 15799 | AU9: =SUM(AU7:AU8) -> 16689 | AV9: =SUM(AV7:AV8) -> 16106 | AW9: =SUM(AW7:AW8) -> 16687.25 | AX9: =SUM(AX7:AX8) -> 65281.25 | AZ9: =SUM(AZ7:AZ8) -> 15394.05 | BA9: =SUM(BA7:BA8) -> 16448.2 | BB9: =SUM(BB7:BB8) -> 16181.89 | BC9: =SUM(BC7:BC8) -> 16953.585 | BD9: =SUM(BD7:BD8) -> 64977.725 | BF9: =SUM(BF7:BF8) -> 16121.611 | BG9: =SUM(BG7:BG8) -> 17225.377 | BH9: =SUM(BH7:BH8) -> 16944.719 | BI9: =SUM(BI7:BI8) -> 17749.021 | BJ9: =SUM(BJ7:BJ8) -> 68040.728 | BL9: =SUM(BL7:BL8) -> 16780.706 | BM9: =SUM(BM7:BM8) -> 17933.452 | BN9: =SUM(BN7:BN8) -> 17639.361 | BO9: =SUM(BO7:BO8) -> 18480.803 | BP9: =SUM(BP7:BP8) -> 70834.323 | BR9: =SUM(BR7:BR8) -> 17467.897 | BS9: =SUM(BS7:BS8) -> 18671.864 | BT9: =SUM(BT7:BT8) -> 18363.69 | BU9: =SUM(BU7:BU8) -> 19244.106 | BV9: =SUM(BV7:BV8) -> 73747.556 | BX9: =SUM(BX7:BX8) -> 18184.421 | BY9: =SUM(BY7:BY8) -> 19441.956 | BZ9: =SUM(BZ7:BZ8) -> 19119.017 | CA9: =SUM(CA7:CA8) -> 20040.332 | CB9: =SUM(CB7:CB8) -> 76785.726 | CD9: =SUM(CD7:CD8) -> 18931.574 | CE9: =SUM(CE7:CE8) -> 20245.132 | CF9: =SUM(CF7:CF8) -> 19906.714 | CG9: =SUM(CG7:CG8) -> 20870.949 | CH9: =SUM(CH7:CH8) -> 79954.369 | CJ9: =SUM(CJ7:CJ8) -> 19710.708 | CK9: =SUM(CK7:CK8) -> 21082.861 | CL9: =SUM(CL7:CL8) -> 20728.214 | CM9: =SUM(CM7:CM8) -> 21737.493 | CN9: =SUM(CN7:CN8) -> 83259.276
B10: Growth YoY (%) | J10: =J9/D9-1 -> 0.30920383 | K10: =K9/E9-1 -> 0.23651928 | L10: =L9/F9-1 -> 0.18373784 | M10: =M9/G9-1 -> 0.11212779 | N10: =N9/H9-1 -> 0.2036866 | P10: =P9/J9-1 -> 0.047204293 | Q10: =Q9/K9-1 -> 0.03004782 | R10: =R9/L9-1 -> -0.055662472 | S10: =S9/M9-1 -> -0.083530888 | T10: =T9/N9-1 -> -0.016848799 | V10: =V9/P9-1 -> -0.21023318 | W10: =W9/Q9-1 -> -0.30730322 | X10: =X9/R9-1 -> -0.22550557 | Y10: =Y9/S9-1 -> -0.14523737 | Z10: =Z9/T9-1 -> -0.22401487 | AB10: =AB9/V9-1 -> 0.11772449 | AC10: =AC9/W9-1 -> 0.28928679 | AD10: =AD9/X9-1 -> 0.2546301 | AE10: =AE9/Y9-1 -> 0.22812639 | AF10: =AF9/Z9-1 -> 0.22092076 | AH10: =AH9/AB9-1 -> 0.14318163 | AI10: =AI9/AC9-1 -> 0.10536116 | AJ10: =AJ9/AD9-1 -> 0.20948617 | AK10: =AK9/AE9-1 -> 0.20285549 | AL10: =AL9/AF9-1 -> 0.16589826 | AN10: =AN9/AH9-1 -> 0.16726764 | AO10: =AO9/AI9-1 -> 0.21555415 | AP10: =AP9/AJ9-1 -> 0.12111511 | AQ10: =AQ9/AK9-1 -> 0.028499126 | AR10: =AR9/AL9-1 -> 0.1284433 | AT10: =AT9/AN9-1 -> -0.0039717564 | AU10: =AU9/AO9-1 -> -0.036320591 | AV10: =AV9/AP9-1 -> -0.041879833 | AW10: =AW9/AQ9-1 -> -0.022422378 | AX10: =AX9/AR9-1 -> -0.026524754 | AZ10: =AZ9/AT9-1 -> -0.025631369 | BA10: =BA9/AU9-1 -> -0.014428666 | BB10: =BB9/AV9-1 -> 0.0047119086 | BC10: =BC9/AW9-1 -> 0.015960359 | BD10: =BD9/AX9-1 -> -0.004649505 | BF10: =BF9/AZ9-1 -> 0.047262473 | BG10: =BG9/BA9-1 -> 0.047249972 | BH10: =BH9/BB9-1 -> 0.047140929 | BI10: =BI9/BC9-1 -> 0.046918491 | BJ10: =BJ9/BD9-1 -> 0.04713929 | BL10: =BL9/BF9-1 -> 0.040882712 | BM10: =BM9/BG9-1 -> 0.041106523 | BN10: =BN9/BH9-1 -> 0.04099458 | BO10: =BO9/BI9-1 -> 0.041229443 | BP10: =BP9/BJ9-1 -> 0.04105768 | BR10: =BR9/BL9-1 -> 0.040951229 | BS10: =BS9/BM9-1 -> 0.041175115 | BT10: =BT9/BN9-1 -> 0.041063214 | BU10: =BU9/BO9-1 -> 0.041302438 | BV10: =BV9/BP9-1 -> 0.041127429 | BX10: =BX9/BR9-1 -> 0.0410195 | BY10: =BY9/BS9-1 -> 0.041243436 | BZ10: =BZ9/BT9-1 -> 0.041131574 | CA10: =CA9/BU9-1 -> 0.041375056 | CB10: =CB9/BV9-1 -> 0.041196886 | CD10: =CD9/BX9-1 -> 0.04108752 | CE10: =CE9/BY9-1 -> 0.041311483 | CF10: =CF9/BZ9-1 -> 0.041199658 | CG10: =CG9/CA9-1 -> 0.041447296 | CH10: =CH9/CB9-1 -> 0.041266046 | CJ10: =CJ9/CD9-1 -> 0.041155287 | CK10: =CK9/CE9-1 -> 0.04137925 | CL10: =CL9/CF9-1 -> 0.041267461 | CM10: =CM9/CG9-1 -> 0.041519155 | CN10: =CN9/CH9-1 -> 0.041334908
B11: Growth YoY ($mm) | J11: =J9-D9 -> 3037 | K11: =K9-E9 -> 2680 | L11: =L9-F9 -> 2097 | M11: =M9-G9 -> 1446 | N11: =N9-H9 -> 9260 | P11: =P9-J9 -> 607 | Q11: =Q9-K9 -> 421 | R11: =R9-L9 -> -752 | S11: =S9-M9 -> -1198 | T11: =T9-N9 -> -922 | V11: =V9-P9 -> -2831 | W11: =W9-Q9 -> -4435 | X11: =X9-R9 -> -2877 | Y11: =Y9-S9 -> -1909 | Z11: =Z9-T9 -> -12052 | AB11: =AB9-V9 -> 1252 | AC11: =AC9-W9 -> 2892 | AD11: =AD9-X9 -> 2516 | AE11: =AE9-Y9 -> 2563 | AF11: =AF9-Z9 -> 9223 | AH11: =AH9-AB9 -> 1702 | AI11: =AI9-AC9 -> 1358 | AJ11: =AJ9-AD9 -> 2597 | AK11: =AK9-AE9 -> 2799 | AL11: =AL9-AF9 -> 8456 | AN11: =AN9-AH9 -> 2273 | AO11: =AO9-AI9 -> 3071 | AP11: =AP9-AJ9 -> 1816 | AQ11: =AQ9-AK9 -> 473 | AR11: =AR9-AL9 -> 7633 | AT11: =AT9-AN9 -> -63 | AU11: =AU9-AO9 -> -629 | AV11: =AV9-AP9 -> -704 | AW11: =AW9-AQ9 -> -382.75 | AX11: =AX9-AR9 -> -1778.75 | AZ11: =AZ9-AT9 -> -404.95 | BA11: =BA9-AU9 -> -240.8 | BB11: =BB9-AV9 -> 75.89 | BC11: =BC9-AW9 -> 266.3345 | BD11: =BD9-AX9 -> -303.5255 | BF11: =BF9-AZ9 -> 727.56088 | BG11: =BG9-BA9 -> 777.17699 | BH11: =BH9-BB9 -> 762.82933 | BI11: =BI9-BC9 -> 795.4366 | BJ11: =BJ9-BD9 -> 3063.0038 | BL11: =BL9-BF9 -> 659.09517 | BM11: =BM9-BG9 -> 708.07535 | BN11: =BN9-BH9 -> 694.64164 | BO11: =BO9-BI9 -> 731.78226 | BP11: =BP9-BJ9 -> 2793.5944 | BR11: =BR9-BL9 -> 687.19054 | BS11: =BS9-BM9 -> 738.41197 | BT11: =BT9-BN9 -> 724.32885 | BU11: =BU9-BO9 -> 763.30223 | BV11: =BV9-BP9 -> 2913.2336 | BX11: =BX9-BR9 -> 716.52438 | BY11: =BY9-BS9 -> 770.09185 | BZ11: =BZ9-BT9 -> 755.32747 | CA11: =CA9-BU9 -> 796.22595 | CB11: =CB9-BV9 -> 3038.1696 | CD11: =CD9-BX9 -> 747.15276 | CE11: =CE9-BY9 -> 803.17603 | CF11: =CF9-BZ9 -> 787.69697 | CG11: =CG9-CA9 -> 830.61756 | CH11: =CH9-CB9 -> 3168.6433 | CJ11: =CJ9-CD9 -> 779.13434 | CK11: =CK9-CE9 -> 837.72839 | CL11: =CL9-CF9 -> 821.49956 | CM11: =CM9-CG9 -> 866.54417 | CN11: =CN9-CH9 -> 3304.9065
B12: Growth QoQ (%) | J12: =J9/G9-1 -> -0.0028691067 | K12: =K9/J9-1 -> 0.08958706 | L12: =L9/K9-1 -> -0.035757619 | M12: =M9/L9-1 -> 0.061584012 | N12: =AVERAGE(J12:M12) -> 0.028136086 | P12: =P9/M9-1 -> -0.061079347 | Q12: =Q9/P9-1 -> 0.071736225 | R12: =R9/Q9-1 -> -0.11599224 | S12: =S9/R9-1 -> 0.030255526 | T12: =AVERAGE(P12:S12) -> -0.018769959 | V12: =V9/S9-1 -> -0.19088558 | W12: =W9/V9-1 -> -0.059990597 | X12: =X9/W9-1 -> -0.011603481 | Y12: =Y9/X9-1 -> 0.13703066 | Z12: =AVERAGE(V12:Y12) -> -0.031362247 | AB12: =AB9/Y9-1 -> 0.058032933 | AC12: =AC9/AB9-1 -> 0.084293766 | AD12: =AD9/AC9-1 -> -0.038172085 | AE12: =AE9/AD9-1 -> 0.11301121 | AF12: =AVERAGE(AB12:AE12) -> 0.054291457 | AH12: =AH9/AE9-1 -> -0.015147123 | AI12: =AI9/AH9-1 -> 0.048421517 | AJ12: =AJ9/AI9-1 -> 0.052432091 | AK12: =AK9/AJ9-1 -> 0.10690943 | AL12: =AVERAGE(AH12:AK12) -> 0.048153979 | AN12: =AN9/AK9-1 -> -0.044285112 | AO12: =AO9/AN9-1 -> 0.091791703 | AP12: =AP9/AO9-1 -> -0.029333641 | AQ12: =AQ9/AP9-1 -> 0.015466984 | AR12: =AVERAGE(AN12:AQ12) -> 0.0084099836 | AT12: =AT9/AQ9-1 -> -0.074458114 | AU12: =AU9/AT9-1 -> 0.056332679 | AV12: =AV9/AU9-1 -> -0.03493319 | AW12: =AW9/AV9-1 -> 0.036089035 | AX12: =AVERAGE(AT12:AW12) -> -0.0042423972 | AZ12: =AZ9/AW9-1 -> -0.077496292 | BA12: =BA9/AZ9-1 -> 0.068477756 | BB12: =BB9/BA9-1 -> -0.016190829 | BC12: =BC9/BB9-1 -> 0.047688774 | BD12: =AVERAGE(AZ12:BC12) -> 0.0056198522 | BF12: =BF9/BC9-1 -> -0.049073612 | BG12: =BG9/BF9-1 -> 0.068465001 | BH12: =BH9/BG9-1 -> -0.016293267 | BI12: =BI9/BH9-1 -> 0.04746622 | BJ12: =AVERAGE(BF12:BI12) -> 0.012641086 | BL12: =BL9/BI9-1 -> -0.054555969 | BM12: =BM9/BL9-1 -> 0.068694743 | BN12: =BN9/BM9-1 -> -0.016399038 | BO12: =BO9/BN9-1 -> 0.047702544 | BP12: =AVERAGE(BL12:BO12) -> 0.01136057 | BR12: =BR9/BO9-1 -> -0.05480859 | BS12: =BS9/BR9-1 -> 0.068924596 | BT12: =BT9/BS9-1 -> -0.016504752 | BU12: =BU9/BT9-1 -> 0.047943293 | BV12: =AVERAGE(BR12:BU12) -> 0.011388637 | BX12: =BX9/BU9-1 -> -0.055065413 | BY12: =BY9/BX9-1 -> 0.069154536 | BZ12: =BZ9/BY9-1 -> -0.01661041 | CA12: =CA9/BZ9-1 -> 0.048188368 | CB12: =AVERAGE(BX12:CA12) -> 0.01141677 | CD12: =CD9/CA9-1 -> -0.055326321 | CE12: =CE9/CD9-1 -> 0.069384536 | CF12: =CF9/CE9-1 -> -0.016716015 | CG12: =CG9/CF9-1 -> 0.048437669 | CH12: =AVERAGE(CD12:CG12) -> 0.011444967 | CJ12: =CJ9/CG9-1 -> -0.055591196 | CK12: =CK9/CJ9-1 -> 0.069614573 | CL12: =CL9/CK9-1 -> -0.016821568 | CM12: =CM9/CL9-1 -> 0.048691096 | CN12: =AVERAGE(CJ12:CM12) -> 0.011473226
B13: Growth QoQ ($mm) | J13: =J9-G9 -> -37 | K13: =K9-J9 -> 1152 | L13: =L9-K9 -> -501 | M13: =M9-L9 -> 832 | N13: =AVERAGE(J13:M13) -> 361.5 | P13: =P9-M9 -> -876 | Q13: =Q9-P9 -> 966 | R13: =R9-Q9 -> -1674 | S13: =S9-R9 -> 386 | T13: =AVERAGE(P13:S13) -> -299.5 | V13: =V9-S9 -> -2509 | W13: =W9-V9 -> -638 | X13: =X9-W9 -> -116 | Y13: =Y9-X9 -> 1354 | Z13: =AVERAGE(V13:Y13) -> -477.25 | AB13: =AB9-Y9 -> 652 | AC13: =AC9-AB9 -> 1002 | AD13: =AD9-AC9 -> -492 | AE13: =AE9-AD9 -> 1401 | AF13: =AVERAGE(AB13:AE13) -> 640.75 | AH13: =AH9-AE9 -> -209 | AI13: =AI9-AH9 -> 658 | AJ13: =AJ9-AI9 -> 747 | AK13: =AK9-AJ9 -> 1603 | AL13: =AVERAGE(AH13:AK13) -> 699.75 | AN13: =AN9-AK9 -> -735 | AO13: =AO9-AN9 -> 1456 | AP13: =AP9-AO9 -> -508 | AQ13: =AQ9-AP9 -> 260 | AR13: =AVERAGE(AN13:AQ13) -> 118.25 | AT13: =AT9-AQ9 -> -1271 | AU13: =AU9-AT9 -> 890 | AV13: =AV9-AU9 -> -583 | AW13: =AW9-AV9 -> 581.25 | AX13: =AVERAGE(AT13:AW13) -> -95.6875 | AZ13: =AZ9-AW9 -> -1293.2 | BA13: =BA9-AZ9 -> 1054.15 | BB13: =BB9-BA9 -> -266.31 | BC13: =BC9-BB9 -> 771.6945 | BD13: =AVERAGE(AZ13:BC13) -> 66.583625 | BF13: =BF9-BC9 -> -831.97362 | BG13: =BG9-BF9 -> 1103.7661 | BH13: =BH9-BG9 -> -280.65766 | BI13: =BI9-BH9 -> 804.30177 | BJ13: =AVERAGE(BF13:BI13) -> 198.85915 | BL13: =BL9-BI9 -> -968.31505 | BM13: =BM9-BL9 -> 1152.7463 | BN13: =BN9-BM9 -> -294.09137 | BO13: =BO9-BN9 -> 841.44239 | BP13: =AVERAGE(BL13:BO13) -> 182.94556 | BR13: =BR9-BO9 -> -1012.9068 | BS13: =BS9-BR9 -> 1203.9677 | BT13: =BT9-BS9 -> -308.17449 | BU13: =BU9-BT9 -> 880.41577 | BV13: =AVERAGE(BR13:BU13) -> 190.82556 | BX13: =BX9-BU9 -> -1059.6846 | BY13: =BY9-BX9 -> 1257.5352 | BZ13: =BZ9-BY9 -> -322.93887 | CA13: =CA9-BZ9 -> 921.31425 | CB13: =AVERAGE(BX13:CA13) -> 199.05649 | CD13: =CD9-CA9 -> -1108.7578 | CE13: =CE9-CD9 -> 1313.5585 | CF13: =CF9-CE9 -> -338.41793 | CG13: =CG9-CF9 -> 964.23484 | CH13: =AVERAGE(CD13:CG13) -> 207.65439 | CJ13: =CJ9-CG9 -> -1160.241 | CK13: =CK9-CJ9 -> 1372.1525 | CL13: =CL9-CK9 -> -354.64676 | CM13: =CM9-CL9 -> 1009.2795 | CN13: =AVERAGE(CJ13:CM13) -> 216.63604
B15: Cost of Goods Sold ($mm) | D15: 6801 | E15: 7816 | F15: 7678 | G15: =H15-SUM(D15:F15) -> 8965 | H15: 31260 | J15: 8566 | K15: 9422 | L15: 9022 | M15: =N15-SUM(J15:L15) -> 9987 | N15: 36997 | P15: 9003 | Q15: 9941 | R15: 8569 | S15: =T15-SUM(P15:R15) -> 9117 | T15: 36630 | V15: 7266 | W15: 7113 | X15: 6919 | Y15: =Z15-SUM(V15:X15) -> 7784 | Z15: 29082 | AB15: 8012 | AC15: 8881 | AD15: 8617 | AE15: =AF15-SUM(AB15:AD15) -> 10003 | AF15: 35513 | AH15: 9559 | AI15: 9975 | AJ15: 10202 | AK15: =AL15-SUM(AH15:AJ15) -> 11614 | AL15: 41350 | AN15: 10103 | AO15: 11065 | AP15: 10583 | AQ15: =AR15-SUM(AN15:AP15) -> 11016 | AR15: 42767 | AT15: 9662 | AU15: 10150 | AV15: 10066 | AW15: =AW9-AW17 -> 10650.102 | AX15: =AX9-AX17 -> 40528.102 | AZ15: =AZ9-AZ17 -> 9611.8373 | BA15: =BA9-BA17 -> 9971.0438 | BB15: =BB9-BB17 -> 10202.696 | BC15: =BC9-BC17 -> 10781.065 | BD15: =BD9-BD17 -> 40566.642 | BF15: =BF9-BF17 -> 9955.9624 | BG15: =BG9-BG17 -> 10324.03 | BH15: =BH9-BH17 -> 10556.059 | BI15: =BI9-BI17 -> 11151.237 | BJ15: =BJ9-BJ17 -> 41987.289 | BL15: =BL9-BL17 -> 10310.133 | BM15: =BM9-BM17 -> 10692.063 | BN15: =BN9-BN17 -> 10923.02 | BO15: =BO9-BO17 -> 11540.478 | BP15: =BP9-BP17 -> 43465.694 | BR15: =BR9-BR17 -> 10676.277 | BS15: =BS9-BS17 -> 11072.537 | BT15: =BT9-BT17 -> 11302.235 | BU15: =BU9-BU17 -> 11943.129 | BV15: =BV9-BV17 -> 44994.177 | BX15: =BX9-BX17 -> 11058.352 | BY15: =BY9-BY17 -> 11469.66 | BZ15: =BZ9-BZ17 -> 11697.99 | CA15: =CA9-CA17 -> 12363.464 | CB15: =CB9-CB17 -> 46589.466 | CD15: =CD9-CD17 -> 11457.075 | CE15: =CE9-CE17 -> 11884.184 | CF15: =CF9-CF17 -> 12111.031 | CG15: =CG9-CG17 -> 12802.284 | CH15: =CH9-CH17 -> 48254.574 | CJ15: =CJ9-CJ17 -> 11867.555 | CK15: =CK9-CK17 -> 12311.181 | CL15: =CL9-CL17 -> 12536.252 | CM15: =CM9-CM17 -> 13254.54 | CN15: =CN9-CN17 -> 49969.529
B17: Gross Margin ($mm) | D17: =D9-D15 -> 3021 | E17: =E9-E15 -> 3515 | F17: =F9-F15 -> 3735 | G17: =G9-G15 -> 3931 | H17: =H9-H15 -> 14202 | J17: =J9-J15 -> 4293 | K17: =K9-K15 -> 4589 | L17: =L9-L15 -> 4488 | M17: =M9-M15 -> 4355 | N17: =N9-N15 -> 17725 | P17: =P9-P15 -> 4463 | Q17: =Q9-Q15 -> 4491 | R17: =R9-R15 -> 4189 | S17: =S9-S15 -> 4027 | T17: =T9-T15 -> 17170 | V17: =V9-V15 -> 3369 | W17: =W9-W15 -> 2884 | X17: =X9-X15 -> 2962 | Y17: =Y9-Y15 -> 3451 | Z17: =Z9-Z15 -> 12666 | AB17: =AB9-AB15 -> 3875 | AC17: =AC9-AC15 -> 4008 | AD17: =AD9-AD15 -> 3780 | AE17: =AE9-AE15 -> 3795 | AF17: =AF9-AF15 -> 15458 | AH17: =AH9-AH15 -> 4030 | AI17: =AI9-AI15 -> 4272 | AJ17: =AJ9-AJ15 -> 4792 | AK17: =AK9-AK15 -> 4983 | AL17: =AL9-AL15 -> 18077 | AN17: =AN9-AN15 -> 5759 | AO17: =AO9-AO15 -> 6253 | AP17: =AP9-AP15 -> 6227 | AQ17: =AQ9-AQ15 -> 6054 | AR17: =AR9-AR15 -> 24293 | AT17: =AT9-AT15 -> 6137 | AU17: =AU9-AU15 -> 6539 | AV17: =AV9-AV15 -> 6040 | AW17: =AW42+AW39 -> 6037.1476 | AX17: =AX42+AX39 -> 24753.148 | AZ17: =AZ42+AZ39 -> 5782.2127 | BA17: =BA42+BA39 -> 6477.1562 | BB17: =BB42+BB39 -> 5979.1937 | BC17: =BC42+BC39 -> 6172.5195 | BD17: =BD42+BD39 -> 24411.082 | BF17: =BF42+BF39 -> 6165.6485 | BG17: =BG42+BG39 -> 6901.3473 | BH17: =BH42+BH39 -> 6388.6599 | BI17: =BI42+BI39 -> 6597.7841 | BJ17: =BJ42+BJ39 -> 26053.44 | BL17: =BL42+BL39 -> 6470.5727 | BM17: =BM42+BM39 -> 7241.3894 | BN17: =BN42+BN39 -> 6716.3407 | BO17: =BO42+BO39 -> 6940.3258 | BP17: =BP42+BP39 -> 27368.629 | BR17: =BR42+BR39 -> 6791.6199 | BS17: =BS42+BS39 -> 7599.3272 | BT17: =BT42+BT39 -> 7061.4549 | BU17: =BU42+BU39 -> 7300.9768 | BV17: =BV42+BV39 -> 28753.379 | BX17: =BX42+BX39 -> 7126.0689 | BY17: =BY42+BY39 -> 7972.296 | BZ17: =BZ42+BZ39 -> 7421.0269 | CA17: =CA42+CA39 -> 7676.868 | CB17: =CB42+CB39 -> 30196.26 | CD17: =CD42+CD39 -> 7474.4985 | CE17: =CE42+CE39 -> 8360.9484 | CF17: =CF42+CF39 -> 7795.6829 | CG17: =CG42+CG39 -> 8068.6655 | CH17: =CH42+CH39 -> 31699.795 | CJ17: =CJ42+CJ39 -> 7843.1531 | CK17: =CK42+CK39 -> 8771.6795 | CL17: =CL42+CL39 -> 8191.9614 | CM17: =CM42+CM39 -> 8482.953 | CN17: =CN42+CN39 -> 33289.747
B18: Gross Margin (%) | D18: =D17/D9 -> 0.30757483 | E18: =E17/E9 -> 0.31021093 | F18: =F17/F9 -> 0.32725839 | G18: =G17/G9 -> 0.3048232 | H18: =H17/H9 -> 0.31239277 | J18: =J17/J9 -> 0.33385178 | K18: =K17/K9 -> 0.32752837 | L18: =L17/L9 -> 0.33219837 | M18: =M17/M9 -> 0.3036536 | N18: =N17/N9 -> 0.32390994 | P18: =P17/P9 -> 0.3314273 | Q18: =Q17/Q9 -> 0.31118348 | R18: =R17/R9 -> 0.328343 | S18: =S17/S9 -> 0.30637553 | T18: =T17/T9 -> 0.31914498 | V18: =V17/V9 -> 0.3167842 | W18: =W17/W9 -> 0.28848655 | X18: =X17/X9 -> 0.29976723 | Y18: =Y17/Y9 -> 0.30716511 | Z18: =Z17/Z9 -> 0.30339178 | AB18: =AB17/AB9 -> 0.32598637 | AC18: =AC17/AC9 -> 0.31096284 | AD18: =AD17/AD9 -> 0.30491248 | AE18: =AE17/AE9 -> 0.27503986 | AF18: =AF17/AF9 -> 0.30327049 | AH18: =AH17/AH9 -> 0.2965634 | AI18: =AI17/AI9 -> 0.2998526 | AJ18: =AJ17/AJ9 -> 0.3195945 | AK18: =AK17/AK9 -> 0.30023498 | AL18: =AL17/AL9 -> 0.30418833 | AN18: =AN17/AN9 -> 0.36306897 | AO18: =AO17/AO9 -> 0.36106941 | AP18: =AP17/AP9 -> 0.37043427 | AQ18: =AQ17/AQ9 -> 0.35465729 | AR18: =AR17/AR9 -> 0.36225768 | AT18: =AT17/AT9 -> 0.38844231 | AU18: =AU17/AU9 -> 0.39181497 | AV18: =AV17/AV9 -> 0.37501552 | AW18: =AW17/AW9 -> 0.36178205 | AX18: =AX17/AX9 -> 0.37917699 | AZ18: =AZ17/AZ9 -> 0.37561348 | BA18: =BA17/BA9 -> 0.39379119 | BB18: =BB17/BB9 -> 0.36949909 | BC18: =BC17/BC9 -> 0.36408345 | BD18: =BD17/BD9 -> 0.37568385 | BF18: =BF17/BF9 -> 0.38244618 | BG18: =BG17/BG9 -> 0.40065 | BH18: =BH17/BH9 -> 0.37702955 | BI18: =BI17/BI9 -> 0.37172665 | BJ18: =BJ17/BJ9 -> 0.38290948 | BL18: =BL17/BL9 -> 0.38559597 | BM18: =BM17/BM9 -> 0.40379227 | BN18: =BN17/BN9 -> 0.38075873 | BO18: =BO17/BO9 -> 0.37554243 | BP18: =BP17/BP9 -> 0.38637524 | BR18: =BR17/BR9 -> 0.38880582 | BS18: =BS17/BS9 -> 0.40699349 | BT18: =BT17/BT9 -> 0.38453355 | BU18: =BU17/BU9 -> 0.37938769 | BV18: =BV17/BV9 -> 0.38988924 | BX18: =BX17/BX9 -> 0.39187769 | BY18: =BY17/BY9 -> 0.41005627 | BZ18: =BZ17/BZ9 -> 0.38814897 | CA18: =CA17/CA9 -> 0.38307091 | CB18: =CB17/CB9 -> 0.39325356 | CD18: =CD17/CD9 -> 0.39481654 | CE18: =CE17/CE9 -> 0.41298562 | CF18: =CF17/CF9 -> 0.39161073 | CG18: =CG17/CG9 -> 0.38659792 | CH18: =CH17/CH9 -> 0.39647358 | CJ18: =CJ17/CJ9 -> 0.39791331 | CK18: =CK17/CK9 -> 0.41605737 | CL18: =CL17/CL9 -> 0.39520826 | CM18: =CM17/CM9 -> 0.39024523 | CN18: =CN17/CN9 -> 0.39983229
B20: Expenses:
B21: SG&A ($mm) | D21: 1061 | E21: 1304 | F21: 1254 | G21: =H21-SUM(D21:F21) -> 1380 | H21: 4999 | J21: 1276 | K21: 1440 | L21: 1299 | M21: =N21-SUM(J21:L21) -> 1463 | N21: 5478 | P21: 1319 | Q21: 1309 | R21: 1251 | S21: 1283 | T21: =+SUM(P21:S21) -> 5162 | V21: 1121 | W21: 1179 | X21: 1126 | Y21: =Z21-SUM(V21:X21) -> 1216 | Z21: 4642 | AB21: 1239 | AC21: 1364 | AD21: 1340 | AE21: =AF21-SUM(AB21:AD21) -> 1422 | AF21: 5365 | AH21: 1346 | AI21: 1425 | AJ21: 1401 | AK21: =AL21-SUM(AH21:AJ21) -> 1479 | AL21: 5651 | AN21: 1463 | AO21: 1528 | AP21: 1624 | AQ21: =AR21-SUM(AN21:AP21) -> 1756 | AR21: 6371 | AT21: 1577 | AU21: 1652 | AV21: 1669 | AW21: =AW$9*AW22 -> 1668.725 | AX21: =SUM(AT21:AW21) -> 6566.725 | AZ21: =AZ$9*AZ22 -> 1539.405 | BA21: =BA$9*BA22 -> 1644.82 | BB21: =BB$9*BB22 -> 1618.189 | BC21: =BC$9*BC22 -> 1695.3585 | BD21: =SUM(AZ21:BC21) -> 6497.7725 | BF21: =BF$9*BF22 -> 1612.1611 | BG21: =BG$9*BG22 -> 1722.5377 | BH21: =BH$9*BH22 -> 1694.4719 | BI21: =BI$9*BI22 -> 1774.9021 | BJ21: =SUM(BF21:BI21) -> 6804.0728 | BL21: =BL$9*BL22 -> 1678.0706 | BM21: =BM$9*BM22 -> 1793.3452 | BN21: =BN$9*BN22 -> 1763.9361 | BO21: =BO$9*BO22 -> 1848.0803 | BP21: =SUM(BL21:BO21) -> 7083.4323 | BR21: =BR$9*BR22 -> 1746.7897 | BS21: =BS$9*BS22 -> 1867.1864 | BT21: =BT$9*BT22 -> 1836.369 | BU21: =BU$9*BU22 -> 1924.4106 | BV21: =SUM(BR21:BU21) -> 7374.7556 | BX21: =BX$9*BX22 -> 1818.4421 | BY21: =BY$9*BY22 -> 1944.1956 | BZ21: =BZ$9*BZ22 -> 1911.9017 | CA21: =CA$9*CA22 -> 2004.0332 | CB21: =SUM(BX21:CA21) -> 7678.5726 | CD21: =CD$9*CD22 -> 1893.1574 | CE21: =CE$9*CE22 -> 2024.5132 | CF21: =CF$9*CF22 -> 1990.6714 | CG21: =CG$9*CG22 -> 2087.0949 | CH21: =SUM(CD21:CG21) -> 7995.4369 | CJ21: =CJ$9*CJ22 -> 1971.0708 | CK21: =CK$9*CK22 -> 2108.2861 | CL21: =CL$9*CL22 -> 2072.8214 | CM21: =CM$9*CM22 -> 2173.7493 | CN21: =SUM(CJ21:CM21) -> 8325.9276
B22: % of Revenue | D22: =D21/D$9 -> 0.10802281 | E22: =E21/E$9 -> 0.11508252 | F22: =F21/F$9 -> 0.1098747 | G22: =G21/G$9 -> 0.10700993 | H22: =H21/H$9 -> 0.10995997 | J22: =J21/J$9 -> 0.099230111 | K22: =K21/K$9 -> 0.10277639 | L22: =L21/L$9 -> 0.096150999 | M22: =M21/M$9 -> 0.10200809 | N22: =N21/N$9 -> 0.10010599 | P22: =P21/P$9 -> 0.097950394 | Q22: =Q21/Q$9 -> 0.09070122 | R22: =R21/R$9 -> 0.098056122 | S22: =S21/S$9 -> 0.097611077 | T22: =T21/T$9 -> 0.095947955 | V22: =V21/V$9 -> 0.10540668 | W22: =W21/W$9 -> 0.11793538 | X22: =X21/X$9 -> 0.11395608 | Y22: =Y21/Y$9 -> 0.1082332 | Z22: =Z21/Z$9 -> 0.11119096 | AB22: =AB21/AB$9 -> 0.10423151 | AC22: =AC21/AC$9 -> 0.10582667 | AD22: =AD21/AD$9 -> 0.10809067 | AE22: =AE21/AE$9 -> 0.10305841 | AF22: =AF21/AF$9 -> 0.10525593 | AH22: =AH21/AH$9 -> 0.099050703 | AI22: =AI21/AI$9 -> 0.10002106 | AJ22: =AJ21/AJ$9 -> 0.093437375 | AK22: =AK21/AK$9 -> 0.08911249 | AL22: =AL21/AL$9 -> 0.095091457 | AN22: =AN21/AN$9 -> 0.09223301 | AO22: =AO21/AO$9 -> 0.088231897 | AP22: =AP21/AP$9 -> 0.096609161 | AQ22: =AQ21/AQ$9 -> 0.10287053 | AR22: =AR21/AR$9 -> 0.095004474 | AT22: =AT21/AT$9 -> 0.099816444 | AU22: =AU21/AU$9 -> 0.098987357 | AV22: =AV21/AV$9 -> 0.10362598 | AW22: 0.1 | AX22: =AX21/AX$9 -> 0.10059129 | AZ22: 0.1 | BA22: 0.1 | BB22: 0.1 | BC22: 0.1 | BD22: =BD21/BD$9 -> 0.1 | BF22: 0.1 | BG22: 0.1 | BH22: 0.1 | BI22: 0.1 | BJ22: =BJ21/BJ$9 -> 0.1 | BL22: 0.1 | BM22: 0.1 | BN22: 0.1 | BO22: 0.1 | BP22: =BP21/BP$9 -> 0.1 | BR22: 0.1 | BS22: 0.1 | BT22: 0.1 | BU22: 0.1 | BV22: =BV21/BV$9 -> 0.1 | BX22: 0.1 | BY22: 0.1 | BZ22: 0.1 | CA22: 0.1 | CB22: =CB21/CB$9 -> 0.1 | CD22: 0.1 | CE22: 0.1 | CF22: 0.1 | CG22: 0.1 | CH22: =CH21/CH$9 -> 0.1 | CJ22: 0.1 | CK22: 0.1 | CL22: 0.1 | CM22: 0.1 | CN22: =CN21/CN$9 -> 0.1
B23: Change YoY ($mm) | J23: =J21-D21 -> 215 | K23: =K21-E21 -> 136 | L23: =L21-F21 -> 45 | M23: =M21-G21 -> 83 | N23: =N21-H21 -> 479 | P23: =P21-J21 -> 43 | Q23: =Q21-K21 -> -131 | R23: =R21-L21 -> -48 | S23: =S21-M21 -> -180 | T23: =T21-N21 -> -316 | V23: =V21-P21 -> -198 | W23: =W21-Q21 -> -130 | X23: =X21-R21 -> -125 | Y23: =Y21-S21 -> -67 | Z23: =Z21-T21 -> -520 | AB23: =AB21-V21 -> 118 | AC23: =AC21-W21 -> 185 | AD23: =AD21-X21 -> 214 | AE23: =AE21-Y21 -> 206 | AF23: =AF21-Z21 -> 723 | AH23: =AH21-AB21 -> 107 | AI23: =AI21-AC21 -> 61 | AJ23: =AJ21-AD21 -> 61 | AK23: =AK21-AE21 -> 57 | AL23: =AL21-AF21 -> 286 | AN23: =AN21-AH21 -> 117 | AO23: =AO21-AI21 -> 103 | AP23: =AP21-AJ21 -> 223 | AQ23: =AQ21-AK21 -> 277 | AR23: =AR21-AL21 -> 720 | AT23: =AT21-AN21 -> 114 | AU23: =AU21-AO21 -> 124 | AV23: =AV21-AP21 -> 45 | AW23: =AW21-AQ21 -> -87.275 | AX23: =AX21-AR21 -> 195.725 | AZ23: =AZ21-AT21 -> -37.595 | BA23: =BA21-AU21 -> -7.18 | BB23: =BB21-AV21 -> -50.811 | BC23: =BC21-AW21 -> 26.63345 | BD23: =BD21-AX21 -> -68.95255 | BF23: =BF21-AZ21 -> 72.756088 | BG23: =BG21-BA21 -> 77.717699 | BH23: =BH21-BB21 -> 76.282933 | BI23: =BI21-BC21 -> 79.54366 | BJ23: =BJ21-BD21 -> 306.30038 | BL23: =BL21-BF21 -> 65.909517 | BM23: =BM21-BG21 -> 70.807535 | BN23: =BN21-BH21 -> 69.464164 | BO23: =BO21-BI21 -> 73.178226 | BP23: =BP21-BJ21 -> 279.35944 | BR23: =BR21-BL21 -> 68.719054 | BS23: =BS21-BM21 -> 73.841197 | BT23: =BT21-BN21 -> 72.432885 | BU23: =BU21-BO21 -> 76.330223 | BV23: =BV21-BP21 -> 291.32336 | BX23: =BX21-BR21 -> 71.652438 | BY23: =BY21-BS21 -> 77.009185 | BZ23: =BZ21-BT21 -> 75.532747 | CA23: =CA21-BU21 -> 79.622595 | CB23: =CB21-BV21 -> 303.81696 | CD23: =CD21-BX21 -> 74.715276 | CE23: =CE21-BY21 -> 80.317603 | CF23: =CF21-BZ21 -> 78.769697 | CG23: =CG21-CA21 -> 83.061756 | CH23: =CH21-CB21 -> 316.86433 | CJ23: =CJ21-CD21 -> 77.913434 | CK23: =CK21-CE21 -> 83.772839 | CL23: =CL21-CF21 -> 82.149956 | CM23: =CM21-CG21 -> 86.654417 | CN23: =CN21-CH21 -> 330.49065
B24: Change YoY (%) | J24: =J22-D22 -> -0.0087926947 | K24: =K22-E22 -> -0.012306127 | L24: =L22-F22 -> -0.013723705 | M24: =M22-G22 -> -0.0050018374 | N24: =N22-H22 -> -0.0098539763 | P24: =P22-J22 -> -0.0012797176 | Q24: =Q22-K22 -> -0.01207517 | R24: =R22-L22 -> 0.0019051224 | S24: =S22-M22 -> -0.0043970108 | T24: =T22-N22 -> -0.0041580349 | V24: =V22-P22 -> 0.0074562825 | W24: =W22-Q22 -> 0.027234161 | X24: =X22-R22 -> 0.015899956 | Y24: =Y22-S22 -> 0.010622123 | Z24: =Z22-T22 -> 0.015243 | AB24: =AB22-V22 -> -0.0011751627 | AC24: =AC22-W22 -> -0.012108707 | AD24: =AD22-X22 -> -0.0058654102 | AE24: =AE22-Y22 -> -0.0051747856 | AF24: =AF22-Z22 -> -0.0059350254 | AH24: =AH22-AB22 -> -0.0051808106 | AI24: =AI22-AC22 -> -0.0058056168 | AJ24: =AJ22-AD22 -> -0.014653292 | AK24: =AK22-AE22 -> -0.013945924 | AL24: =AL22-AF22 -> -0.010164473 | AN24: =AN22-AH22 -> -0.0068176931 | AO24: =AO22-AI22 -> -0.01178916 | AP24: =AP22-AJ22 -> 0.0031717863 | AQ24: =AQ22-AK22 -> 0.013758043 | AR24: =AR22-AL22 -> -8.698314e-05 | AT24: =AT22-AN22 -> 0.0075834344 | AU24: =AU22-AO22 -> 0.010755459 | AV24: =AV22-AP22 -> 0.0070168167 | AW24: =AW22-AQ22 -> -0.0028705331 | AX24: =AX22-AR22 -> 0.0055868141 | AZ24: =AZ22-AT22 -> 0.00018355592 | BA24: =BA22-AU22 -> 0.0010126431 | BB24: =BB22-AV22 -> -0.0036259779 | BC24: =BC22-AW22 -> 0 | BD24: =BD22-AX22 -> -0.0005912877 | BF24: =BF22-AZ22 -> 0 | BG24: =BG22-BA22 -> 0 | BH24: =BH22-BB22 -> 0 | BI24: =BI22-BC22 -> 0 | BJ24: =BJ22-BD22 -> 0 | BL24: =BL22-BF22 -> 0 | BM24: =BM22-BG22 -> 0 | BN24: =BN22-BH22 -> 0 | BO24: =BO22-BI22 -> 0 | BP24: =BP22-BJ22 -> 0 | BR24: =BR22-BL22 -> 0 | BS24: =BS22-BM22 -> 0 | BT24: =BT22-BN22 -> 0 | BU24: =BU22-BO22 -> 0 | BV24: =BV22-BP22 -> 0 | BX24: =BX22-BR22 -> 0 | BY24: =BY22-BS22 -> 0 | BZ24: =BZ22-BT22 -> 0 | CA24: =CA22-BU22 -> 0 | CB24: =CB22-BV22 -> 0 | CD24: =CD22-BX22 -> 0 | CE24: =CE22-BY22 -> 0 | CF24: =CF22-BZ22 -> 0 | CG24: =CG22-CA22 -> 0 | CH24: =CH22-CB22 -> 0 | CJ24: =CJ22-CD22 -> 0 | CK24: =CK22-CE22 -> 0 | CL24: =CL22-CF22 -> 0 | CM24: =CM22-CG22 -> 0 | CN24: =CN22-CH22 -> 0
B25: R&D Expenses ($mm) | D25: 425 | E25: 458 | F25: 461 | G25: =H25-SUM(D25:F25) -> 498 | H25: 1842 | J25: 443 | K25: 462 | L25: 479 | M25: 466 | N25: =+SUM(J25:M25) -> 1850 | P25: 435 | Q25: 441 | R25: 431 | S25: 386 | T25: =+SUM(P25:S25) -> 1693 | V25: 356 | W25: 341 | X25: 344 | Y25: 374 | Z25: =+SUM(V25:Y25) -> 1415 | AB25: 374 | AC25: 446 | AD25: 427 | AE25: 439 | AF25: =+SUM(AB25:AE25) -> 1686 | AH25: 457 | AI25: 480 | AJ25: 476 | AK25: 401 | AL25: =+SUM(AH25:AK25) -> 1814 | AN25: 472 | AO25: 528 | AP25: 554 | AQ25: =AR25-SUM(AN25:AP25) -> 554 | AR25: 2108 | AT25: 520 | AU25: 535 | AV25: 533 | AW25: =AW$9*AW26 -> 550.67925 | AX25: =SUM(AT25:AW25) -> 2138.6793 | AZ25: =AZ$9*AZ26 -> 503.59288 | BA25: =BA$9*BA26 -> 523.99102 | BB25: =BB$9*BB26 -> 532.27507 | BC25: =BC$9*BC26 -> 556.07757 | BD25: =SUM(AZ25:BC25) -> 2115.9365 | BF25: =BF$9*BF26 -> 524.1696 | BG25: =BG$9*BG26 -> 545.30451 | BH25: =BH$9*BH26 -> 553.97807 | BI25: =BI$9*BI26 -> 578.61809 | BJ25: =SUM(BF25:BI25) -> 2202.0703 | BL25: =BL$9*BL26 -> 542.24293 | BM25: =BM$9*BM26 -> 564.13339 | BN25: =BN$9*BN26 -> 573.16029 | BO25: =BO$9*BO26 -> 598.77803 | BP25: =SUM(BL25:BO25) -> 2278.3146 | BR25: =BR$9*BR26 -> 560.95487 | BS25: =BS$9*BS26 -> 583.62728 | BT25: =BT$9*BT26 -> 593.02336 | BU25: =BU$9*BU26 -> 619.6602 | BV25: =SUM(BR25:BU25) -> 2357.2657 | BX25: =BX$9*BX26 -> 580.32807 | BY25: =BY$9*BY26 -> 603.80968 | BZ25: =BZ$9*BZ26 -> 613.59154 | CA25: =CA$9*CA26 -> 641.29061 | CB25: =SUM(BX25:CA25) -> 2439.0199 | CD25: =CD$9*CD26 -> 600.386 | CE25: =CE$9*CE26 -> 624.70493 | CF25: =CF$9*CF26 -> 634.88996 | CG25: =CG$9*CG26 -> 663.69618 | CH25: =SUM(CD25:CG25) -> 2523.6771 | CJ25: =CJ$9*CJ26 -> 621.15292 | CK25: =CK$9*CK26 -> 646.33818 | CL25: =CL$9*CL26 -> 656.94461 | CM25: =CM$9*CM26 -> 686.90479 | CN25: =SUM(CJ25:CM25) -> 2611.3405
B26: % of Revenue | D26: =D25/D$9 -> 0.04327021 | E26: =E25/E$9 -> 0.040420086 | F26: =F25/F$9 -> 0.040392535 | G26: =G25/G$9 -> 0.038616625 | H26: =H25/H$9 -> 0.040517355 | J26: =J25/J$9 -> 0.034450579 | K26: =K25/K$9 -> 0.032974092 | L26: =L25/L$9 -> 0.035455218 | M26: =M25/M$9 -> 0.032491982 | N26: =N25/N$9 -> 0.033807244 | P26: =P25/P$9 -> 0.032303579 | Q26: =Q25/Q$9 -> 0.030557095 | R26: =R25/R$9 -> 0.033782725 | S26: =S25/S$9 -> 0.029367012 | T26: =T25/T$9 -> 0.031468401 | V26: =V25/V$9 -> 0.033474377 | W26: =W25/W$9 -> 0.034110233 | X26: =X25/X$9 -> 0.03481429 | Y26: =Y25/Y$9 -> 0.03328883 | Z26: =Z25/Z$9 -> 0.033893839 | AB26: =AB25/AB$9 -> 0.031462943 | AC26: =AC25/AC$9 -> 0.03460315 | AD26: =AD25/AD$9 -> 0.034443817 | AE26: =AE25/AE$9 -> 0.031816205 | AF26: =AF25/AF$9 -> 0.033077632 | AH26: =AH25/AH$9 -> 0.033630142 | AI26: =AI25/AI$9 -> 0.033691303 | AJ26: =AJ25/AJ$9 -> 0.031746032 | AK26: =AK25/AK$9 -> 0.024160993 | AL26: =AL25/AL$9 -> 0.030524846 | AN26: =AN25/AN$9 -> 0.029756651 | AO26: =AO25/AO$9 -> 0.030488509 | AP26: =AP25/AP$9 -> 0.032956573 | AQ26: =AQ25/AQ$9 -> 0.032454599 | AR26: =AR25/AR$9 -> 0.031434536 | AT26: =AT25/AT$9 -> 0.032913476 | AU26: =AU25/AU$9 -> 0.032057044 | AV26: =AV25/AV$9 -> 0.033093257 | AW26: 0.033 | AX26: =AX25/AX$9 -> 0.032761003 | AZ26: =AT26-0.0002 -> 0.032713476 | BA26: =AU26-0.0002 -> 0.031857044 | BB26: =AV26-0.0002 -> 0.032893257 | BC26: =AW26-0.0002 -> 0.0328 | BD26: =BD25/BD$9 -> 0.03256403 | BF26: =AZ26-0.0002 -> 0.032513476 | BG26: =BA26-0.0002 -> 0.031657044 | BH26: =BB26-0.0002 -> 0.032693257 | BI26: =BC26-0.0002 -> 0.0326 | BJ26: =BJ25/BJ$9 -> 0.032364002 | BL26: =BF26-0.0002 -> 0.032313476 | BM26: =BG26-0.0002 -> 0.031457044 | BN26: =BH26-0.0002 -> 0.032493257 | BO26: =BI26-0.0002 -> 0.0324 | BP26: =BP25/BP$9 -> 0.032163993 | BR26: =BL26-0.0002 -> 0.032113476 | BS26: =BM26-0.0002 -> 0.031257044 | BT26: =BN26-0.0002 -> 0.032293257 | BU26: =BO26-0.0002 -> 0.0322 | BV26: =BV25/BV$9 -> 0.031963984 | BX26: =BR26-0.0002 -> 0.031913476 | BY26: =BS26-0.0002 -> 0.031057044 | BZ26: =BT26-0.0002 -> 0.032093257 | CA26: =BU26-0.0002 -> 0.032 | CB26: =CB25/CB$9 -> 0.031763975 | CD26: =BX26-0.0002 -> 0.031713476 | CE26: =BY26-0.0002 -> 0.030857044 | CF26: =BZ26-0.0002 -> 0.031893257 | CG26: =CA26-0.0002 -> 0.0318 | CH26: =CH25/CH$9 -> 0.031563967 | CJ26: =CD26-0.0002 -> 0.031513476 | CK26: =CE26-0.0002 -> 0.030657044 | CL26: =CF26-0.0002 -> 0.031693257 | CM26: =CG26-0.0002 -> 0.0316 | CN26: =CN25/CN$9 -> 0.031363959
B27: Change YoY ($mm) | J27: =J25-D25 -> 18 | K27: =K25-E25 -> 4 | L27: =L25-F25 -> 18 | M27: =M25-G25 -> -32 | N27: =N25-H25 -> 8 | P27: =P25-J25 -> -8 | Q27: =Q25-K25 -> -21 | R27: =R25-L25 -> -48 | S27: =S25-M25 -> -80 | T27: =T25-N25 -> -157 | V27: =V25-P25 -> -79 | W27: =W25-Q25 -> -100 | X27: =X25-R25 -> -87 | Y27: =Y25-S25 -> -12 | Z27: =Z25-T25 -> -278 | AB27: =AB25-V25 -> 18 | AC27: =AC25-W25 -> 105 | AD27: =AD25-X25 -> 83 | AE27: =AE25-Y25 -> 65 | AF27: =AF25-Z25 -> 271 | AH27: =AH25-AB25 -> 83 | AI27: =AI25-AC25 -> 34 | AJ27: =AJ25-AD25 -> 49 | AK27: =AK25-AE25 -> -38 | AL27: =AL25-AF25 -> 128 | AN27: =AN25-AH25 -> 15 | AO27: =AO25-AI25 -> 48 | AP27: =AP25-AJ25 -> 78 | AQ27: =AQ25-AK25 -> 153 | AR27: =AR25-AL25 -> 294 | AT27: =AT25-AN25 -> 48 | AU27: =AU25-AO25 -> 7 | AV27: =AV25-AP25 -> -21 | AW27: =AW25-AQ25 -> -3.32075 | AX27: =AX25-AR25 -> 30.67925 | AZ27: =AZ25-AT25 -> -16.407122 | BA27: =BA25-AU25 -> -11.008976 | BB27: =BB25-AV25 -> -0.72493071 | BC27: =BC25-AW25 -> 5.3983216 | BD27: =BD25-AX25 -> -22.742707 | BF27: =BF25-AZ25 -> 20.576723 | BG27: =BG25-BA25 -> 21.313486 | BH27: =BH25-BB25 -> 21.702997 | BI27: =BI25-BC25 -> 22.540516 | BJ27: =BJ25-BD25 -> 86.133722 | BL27: =BL25-BF25 -> 18.073334 | BM27: =BM25-BG25 -> 18.828882 | BN27: =BN25-BH25 -> 19.182226 | BO27: =BO25-BI25 -> 20.159941 | BP27: =BP25-BJ25 -> 76.244382 | BR27: =BR25-BL25 -> 18.711935 | BS27: =BS25-BM25 -> 19.493885 | BT27: =BT25-BN25 -> 19.863066 | BU27: =BU25-BO25 -> 20.882171 | BV27: =BV25-BP25 -> 78.951056 | BX27: =BX25-BR25 -> 19.373204 | BY27: =BY25-BS25 -> 20.182403 | BZ27: =BZ25-BT25 -> 20.568181 | CA27: =CA25-BU25 -> 21.630409 | CB27: =CB25-BV25 -> 81.754197 | CD27: =CD25-BX25 -> 20.057927 | CE27: =CE25-BY25 -> 20.895247 | CF27: =CF25-BZ25 -> 21.298419 | CG27: =CG25-CA25 -> 22.405572 | CH27: =CH25-CB25 -> 84.657164 | CJ27: =CJ25-CD25 -> 20.766916 | CK27: =CK25-CE25 -> 21.633249 | CL27: =CL25-CF25 -> 22.054654 | CM27: =CM25-CG25 -> 23.208606 | CN27: =CN25-CH25 -> 87.663426
B28: Change YoY (%) | J28: =J26-D26 -> -0.0088196304 | K28: =K26-E26 -> -0.0074459947 | L28: =L26-F26 -> -0.0049373165 | M28: =M26-G26 -> -0.0061246437 | N28: =N26-H26 -> -0.0067101113 | P28: =P26-J26 -> -0.002147 | Q28: =Q26-K26 -> -0.0024169964 | R28: =R26-L26 -> -0.0016724938 | S28: =S26-M26 -> -0.00312497 | T28: =T26-N26 -> -0.0023388424 | V28: =V26-P26 -> 0.0011707977 | W28: =W26-Q26 -> 0.0035531377 | X28: =X26-R26 -> 0.0010315655 | Y28: =Y26-S26 -> 0.003921818 | Z28: =Z26-T26 -> 0.0024254377 | AB28: =AB26-V26 -> -0.0020114343 | AC28: =AC26-W26 -> 0.0004929169 | AD28: =AD26-X26 -> -0.000370473 | AE28: =AE26-Y26 -> -0.0014726243 | AF28: =AF26-Z26 -> -0.00081620685 | AH28: =AH26-AB26 -> 0.0021671993 | AI28: =AI26-AC26 -> -0.00091184654 | AJ28: =AJ26-AD26 -> -0.0026977853 | AK28: =AK26-AE26 -> -0.0076552123 | AL28: =AL26-AF26 -> -0.0025527868 | AN28: =AN26-AH26 -> -0.0038734909 | AO28: =AO26-AI26 -> -0.0032027944 | AP28: =AP26-AJ26 -> 0.0012105417 | AQ28: =AQ26-AK26 -> 0.0082936058 | AR28: =AR26-AL26 -> 0.00090969063 | AT28: =AT26-AN26 -> 0.0031568244 | AU28: =AU26-AO26 -> 0.0015685345 | AV28: =AV26-AP26 -> 0.0001366837 | AW28: =AW26-AQ26 -> 0.00054540129 | AX28: =AX26-AR26 -> 0.0013264671 | AZ28: =AZ26-AT26 -> -0.0002 | BA28: =BA26-AU26 -> -0.0002 | BB28: =BB26-AV26 -> -0.0002 | BC28: =BC26-AW26 -> -0.0002 | BD28: =BD26-AX26 -> -0.00019697377 | BF28: =BF26-AZ26 -> -0.0002 | BG28: =BG26-BA26 -> -0.0002 | BH28: =BH26-BB26 -> -0.0002 | BI28: =BI26-BC26 -> -0.0002 | BJ28: =BJ26-BD26 -> -0.00020002761 | BL28: =BL26-BF26 -> -0.0002 | BM28: =BM26-BG26 -> -0.0002 | BN28: =BN26-BH26 -> -0.0002 | BO28: =BO26-BI26 -> -0.0002 | BP28: =BP26-BJ26 -> -0.00020000916 | BR28: =BR26-BL26 -> -0.0002 | BS28: =BS26-BM26 -> -0.0002 | BT28: =BT26-BN26 -> -0.0002 | BU28: =BU26-BO26 -> -0.0002 | BV28: =BV26-BP26 -> -0.0002000089 | BX28: =BX26-BR26 -> -0.0002 | BY28: =BY26-BS26 -> -0.0002 | BZ28: =BZ26-BT26 -> -0.0002 | CA28: =CA26-BU26 -> -0.0002 | CB28: =CB26-BV26 -> -0.00020000864 | CD28: =CD26-BX26 -> -0.0002 | CE28: =CE26-BY26 -> -0.0002 | CF28: =CF26-BZ26 -> -0.0002 | CG28: =CG26-CA26 -> -0.0002 | CH28: =CH26-CB26 -> -0.00020000839 | CJ28: =CJ26-CD26 -> -0.0002 | CK28: =CK26-CE26 -> -0.0002 | CL28: =CL26-CF26 -> -0.0002 | CM28: =CM26-CG26 -> -0.0002 | CN28: =CN26-CH26 -> -0.00020000814
B29: Interest expense of Financial Products ($mm) | D29: 159 | E29: 162 | F29: 163 | G29: =H29-SUM(D29:F29) -> 162 | H29: 646 | J29: 166 | K29: 182 | L29: 185 | M29: =N29-SUM(J29:L29) -> 189 | N29: 722 | P29: 190 | Q29: 192 | R29: 189 | S29: =T29-SUM(P29:R29) -> 183 | T29: 754 | V29: 175 | W29: 149 | X29: 137 | Y29: =Z29-SUM(V29:X29) -> 128 | Z29: 589 | AB29: 125 | AC29: 116 | AD29: 111 | AE29: 103 | AF29: =SUM(AB29:AE29) -> 455 | AH29: 106 | AI29: 120 | AJ29: 151 | AK29: 188 | AL29: =SUM(AH29:AK29) -> 565 | AN29: 217 | AO29: 245 | AP29: 280 | AQ29: =AR29-SUM(AN29:AP29) -> 288 | AR29: 1030 | AT29: 298 | AU29: 314 | AV29: 336 | AW29: =AW$9*AW30 -> 350.43225 | AX29: =SUM(AT29:AW29) -> 1298.4323 | AZ29: =AZ$9*AZ30 -> 290.36185 | BA29: =BA$9*BA30 -> 309.4694 | BB29: =BB$9*BB30 -> 337.5832 | BC29: =BC$9*BC30 -> 356.02527 | BD29: =SUM(AZ29:BC29) -> 1293.4397 | BF29: =BF$9*BF30 -> 304.08507 | BG29: =BG$9*BG30 -> 324.09182 | BH29: =BH$9*BH30 -> 353.49719 | BI29: =BI$9*BI30 -> 372.72944 | BJ29: =SUM(BF29:BI29) -> 1354.4035 | BL29: =BL$9*BL30 -> 316.51689 | BM29: =BM$9*BM30 -> 337.41411 | BN29: =BN$9*BN30 -> 367.98866 | BO29: =BO$9*BO30 -> 388.09687 | BP29: =SUM(BL29:BO29) -> 1410.0165 | BR29: =BR$9*BR30 -> 329.47865 | BS29: =BS$9*BS30 -> 351.30717 | BT29: =BT$9*BT30 -> 383.09945 | BU29: =BU$9*BU30 -> 404.12622 | BV29: =SUM(BR29:BU29) -> 1468.0115 | BX29: =BX$9*BX30 -> 342.9937 | BY29: =BY$9*BY30 -> 365.79629 | BZ29: =BZ$9*BZ30 -> 398.85694 | CA29: =CA$9*CA30 -> 420.84696 | CB29: =SUM(BX29:CA29) -> 1528.4939 | CD29: =CD$9*CD30 -> 357.08646 | CE29: =CE$9*CE30 -> 380.90787 | CF29: =CF$9*CF30 -> 415.28971 | CG29: =CG$9*CG30 -> 438.28993 | CH29: =SUM(CD29:CG29) -> 1591.574 | CJ29: =CJ$9*CJ30 -> 371.78245 | CK29: =CK$9*CK30 -> 396.66956 | CL29: =CL$9*CL30 -> 432.42766 | CM29: =CM$9*CM30 -> 456.48736 | CN29: =SUM(CJ29:CM29) -> 1657.367
B30: % of Revenue | D30: =D29/D$9 -> 0.016188149 | E30: =E29/E$9 -> 0.014297061 | F30: =F29/F$9 -> 0.014281959 | G30: =G29/G$9 -> 0.012562035 | H30: =H29/H$9 -> 0.01420967 | J30: =J29/J$9 -> 0.012909246 | K30: =K29/K$9 -> 0.012989794 | L30: =L29/L$9 -> 0.01369356 | M30: =M29/M$9 -> 0.013178078 | N30: =N29/N$9 -> 0.013193962 | P30: =P29/P$9 -> 0.014109609 | Q30: =Q29/Q$9 -> 0.013303769 | R30: =R29/R$9 -> 0.014814234 | S30: =S29/S$9 -> 0.013922702 | T30: =T29/T$9 -> 0.01401487 | V30: =V29/V$9 -> 0.016455101 | W30: =W29/W$9 -> 0.014904471 | X30: =X29/X$9 -> 0.013864993 | Y30: =Y29/Y$9 -> 0.011392968 | Z30: =Z29/Z$9 -> 0.01410846 | AB30: =AB29/AB$9 -> 0.010515689 | AC30: =AC29/AC$9 -> 0.0089999224 | AD30: =AD29/AD$9 -> 0.0089537791 | AE30: =AE29/AE$9 -> 0.00746485 | AF30: =AF29/AF$9 -> 0.0089266446 | AH30: =AH29/AH$9 -> 0.0078004268 | AI30: =AI29/AI$9 -> 0.0084228259 | AJ30: =AJ29/AJ$9 -> 0.010070695 | AK30: =AK29/AK$9 -> 0.011327348 | AL30: =AL29/AL$9 -> 0.0095074629 | AN30: =AN29/AN$9 -> 0.013680494 | AO30: =AO29/AO$9 -> 0.01414713 | AP30: =AP29/AP$9 -> 0.016656752 | AQ30: =AQ29/AQ$9 -> 0.016871705 | AR30: =AR29/AR$9 -> 0.01535938 | AT30: =AT29/AT$9 -> 0.018861953 | AU30: =AU29/AU$9 -> 0.018814788 | AV30: =AV29/AV$9 -> 0.020861791 | AW30: 0.021 | AX30: =AX29/AX$9 -> 0.019889819 | AZ30: =AT30 -> 0.018861953 | BA30: =AU30 -> 0.018814788 | BB30: =AV30 -> 0.020861791 | BC30: =AW30 -> 0.021 | BD30: =BD29/BD$9 -> 0.019905894 | BF30: =AZ30 -> 0.018861953 | BG30: =BA30 -> 0.018814788 | BH30: =BB30 -> 0.020861791 | BI30: =BC30 -> 0.021 | BJ30: =BJ29/BJ$9 -> 0.019905776 | BL30: =BF30 -> 0.018861953 | BM30: =BG30 -> 0.018814788 | BN30: =BH30 -> 0.020861791 | BO30: =BI30 -> 0.021 | BP30: =BP29/BP$9 -> 0.019905838 | BR30: =BL30 -> 0.018861953 | BS30: =BM30 -> 0.018814788 | BT30: =BN30 -> 0.020861791 | BU30: =BO30 -> 0.021 | BV30: =BV29/BV$9 -> 0.0199059 | BX30: =BR30 -> 0.018861953 | BY30: =BS30 -> 0.018814788 | BZ30: =BT30 -> 0.020861791 | CA30: =BU30 -> 0.021 | CB30: =CB29/CB$9 -> 0.019905964 | CD30: =BX30 -> 0.018861953 | CE30: =BY30 -> 0.018814788 | CF30: =BZ30 -> 0.020861791 | CG30: =CA30 -> 0.021 | CH30: =CH29/CH$9 -> 0.019906029 | CJ30: =CD30 -> 0.018861953 | CK30: =CE30 -> 0.018814788 | CL30: =CF30 -> 0.020861791 | CM30: =CG30 -> 0.021 | CN30: =CN29/CN$9 -> 0.019906095
B31: Change YoY ($mm) | J31: =J29-D29 -> 7 | K31: =K29-E29 -> 20 | L31: =L29-F29 -> 22 | M31: =M29-G29 -> 27 | N31: =N29-H29 -> 76 | P31: =P29-J29 -> 24 | Q31: =Q29-K29 -> 10 | R31: =R29-L29 -> 4 | S31: =S29-M29 -> -6 | T31: =T29-N29 -> 32 | V31: =V29-P29 -> -15 | W31: =W29-Q29 -> -43 | X31: =X29-R29 -> -52 | Y31: =Y29-S29 -> -55 | Z31: =Z29-T29 -> -165 | AB31: =AB29-V29 -> -50 | AC31: =AC29-W29 -> -33 | AD31: =AD29-X29 -> -26 | AE31: =AE29-Y29 -> -25 | AF31: =AF29-Z29 -> -134 | AH31: =AH29-AB29 -> -19 | AI31: =AI29-AC29 -> 4 | AJ31: =AJ29-AD29 -> 40 | AK31: =AK29-AE29 -> 85 | AL31: =AL29-AF29 -> 110 | AN31: =AN29-AH29 -> 111 | AO31: =AO29-AI29 -> 125 | AP31: =AP29-AJ29 -> 129 | AQ31: =AQ29-AK29 -> 100 | AR31: =AR29-AL29 -> 465 | AT31: =AT29-AN29 -> 81 | AU31: =AU29-AO29 -> 69 | AV31: =AV29-AP29 -> 56 | AW31: =AW29-AQ29 -> 62.43225 | AX31: =AX29-AR29 -> 268.43225 | AZ31: =AZ29-AT29 -> -7.638148 | BA31: =BA29-AU29 -> -4.530601 | BB31: =BB29-AV29 -> 1.5832013 | BC31: =BC29-AW29 -> 5.5930245 | BD31: =BD29-AX29 -> -4.9925232 | BF31: =BF29-AZ29 -> 13.723219 | BG31: =BG29-BA29 -> 14.62242 | BH31: =BH29-BB29 -> 15.913986 | BI31: =BI29-BC29 -> 16.704169 | BJ31: =BJ29-BD29 -> 60.963794 | BL31: =BL29-BF29 -> 12.431822 | BM31: =BM29-BG29 -> 13.322288 | BN31: =BN29-BH29 -> 14.491469 | BO31: =BO29-BI29 -> 15.367427 | BP31: =BP29-BJ29 -> 55.613006 | BR31: =BR29-BL29 -> 12.961756 | BS31: =BS29-BM29 -> 13.893065 | BT31: =BT29-BN29 -> 15.110797 | BU31: =BU29-BO29 -> 16.029347 | BV31: =BV29-BP29 -> 57.994964 | BX31: =BX29-BR29 -> 13.515049 | BY31: =BY29-BS29 -> 14.489115 | BZ31: =BZ29-BT29 -> 15.757484 | CA31: =CA29-BU29 -> 16.720745 | CB31: =CB29-BV29 -> 60.482393 | CD31: =CD29-BX29 -> 14.09276 | CE31: =CE29-BY29 -> 15.111587 | CF31: =CF29-BZ29 -> 16.432769 | CG31: =CG29-CA29 -> 17.442969 | CH31: =CH29-CB29 -> 63.080085 | CJ31: =CJ29-CD29 -> 14.695996 | CK31: =CK29-CE29 -> 15.761682 | CL31: =CL29-CF29 -> 17.137952 | CM31: =CM29-CG29 -> 18.197428 | CN31: =CN29-CH29 -> 65.793057
B32: Goodwill impairment charge ($mm) | D32: 0 | E32: 0 | F32: 0 | G32: =H32-SUM(D32:F32) -> 0 | H32: 0 | J32: 0 | K32: 0 | L32: 0 | M32: =N32-SUM(J32:L32) -> 0 | N32: 0 | P32: 0 | Q32: 0 | R32: 0 | S32: =T32-SUM(P32:R32) -> 0 | T32: 0 | V32: 0 | W32: 0 | X32: 0 | Y32: =Z32-SUM(V32:X32) -> 0 | Z32: 0 | AB32: 0 | AC32: 0 | AD32: 0 | AE32: =AF32-SUM(AB32:AD32) -> 0 | AF32: 0 | AH32: 0 | AI32: 0 | AJ32: 0 | AK32: =AL32-SUM(AH32:AJ32) -> 925 | AL32: 925 | AN32: 0 | AO32: 0 | AP32: 0 | AQ32: =AR32-SUM(AN32:AP32) -> 0 | AR32: 0 | AW32: =AW$9*AW33 -> 0 | AX32: =SUM(AT32:AW32) -> 0 | AZ32: =AZ$9*AZ33 -> 0 | BA32: =BA$9*BA33 -> 0 | BB32: =BB$9*BB33 -> 0 | BC32: =BC$9*BC33 -> 0 | BD32: =SUM(AZ32:BC32) -> 0 | BF32: =BF$9*BF33 -> 0 | BG32: =BG$9*BG33 -> 0 | BH32: =BH$9*BH33 -> 0 | BI32: =BI$9*BI33 -> 0 | BJ32: =SUM(BF32:BI32) -> 0 | BL32: =BL$9*BL33 -> 0 | BM32: =BM$9*BM33 -> 0 | BN32: =BN$9*BN33 -> 0 | BO32: =BO$9*BO33 -> 0 | BP32: =SUM(BL32:BO32) -> 0 | BR32: =BR$9*BR33 -> 0 | BS32: =BS$9*BS33 -> 0 | BT32: =BT$9*BT33 -> 0 | BU32: =BU$9*BU33 -> 0 | BV32: =SUM(BR32:BU32) -> 0 | BX32: =BX$9*BX33 -> 0 | BY32: =BY$9*BY33 -> 0 | BZ32: =BZ$9*BZ33 -> 0 | CA32: =CA$9*CA33 -> 0 | CB32: =SUM(BX32:CA32) -> 0 | CD32: =CD$9*CD33 -> 0 | CE32: =CE$9*CE33 -> 0 | CF32: =CF$9*CF33 -> 0 | CG32: =CG$9*CG33 -> 0 | CH32: =SUM(CD32:CG32) -> 0 | CJ32: =CJ$9*CJ33 -> 0 | CK32: =CK$9*CK33 -> 0 | CL32: =CL$9*CL33 -> 0 | CM32: =CM$9*CM33 -> 0 | CN32: =SUM(CJ32:CM32) -> 0
B33: % of Revenue | D33: =D32/D$9 -> 0 | E33: =E32/E$9 -> 0 | F33: =F32/F$9 -> 0 | G33: =G32/G$9 -> 0 | H33: =H32/H$9 -> 0 | J33: =J32/J$9 -> 0 | K33: =K32/K$9 -> 0 | L33: =L32/L$9 -> 0 | M33: =M32/M$9 -> 0 | N33: =N32/N$9 -> 0 | P33: =P32/P$9 -> 0 | Q33: =Q32/Q$9 -> 0 | R33: =R32/R$9 -> 0 | S33: =S32/S$9 -> 0 | T33: =T32/T$9 -> 0 | V33: =V32/V$9 -> 0 | W33: =W32/W$9 -> 0 | X33: =X32/X$9 -> 0 | Y33: =Y32/Y$9 -> 0 | Z33: =Z32/Z$9 -> 0 | AB33: =AB32/AB$9 -> 0 | AC33: =AC32/AC$9 -> 0 | AD33: =AD32/AD$9 -> 0 | AE33: =AE32/AE$9 -> 0 | AF33: =AF32/AF$9 -> 0 | AH33: =AH32/AH$9 -> 0 | AI33: =AI32/AI$9 -> 0 | AJ33: =AJ32/AJ$9 -> 0 | AK33: =AK32/AK$9 -> 0.055732964 | AL33: =AL32/AL$9 -> 0.015565315 | AN33: =AN32/AN$9 -> 0 | AO33: =AO32/AO$9 -> 0 | AP33: =AP32/AP$9 -> 0 | AQ33: =AQ32/AQ$9 -> 0 | AR33: =AR32/AR$9 -> 0 | AT33: =AT32/AT$9 -> 0 | AU33: =AU32/AU$9 -> 0 | AV33: =AV32/AV$9 -> 0 | AW33: 0 | AX33: =AX32/AX$9 -> 0 | AZ33: 0 | BA33: 0 | BB33: 0 | BC33: 0 | BD33: =BD32/BD$9 -> 0 | BF33: 0 | BG33: 0 | BH33: 0 | BI33: 0 | BJ33: =BJ32/BJ$9 -> 0 | BL33: 0 | BM33: 0 | BN33: 0 | BO33: 0 | BP33: =BP32/BP$9 -> 0 | BR33: 0 | BS33: 0 | BT33: 0 | BU33: 0 | BV33: =BV32/BV$9 -> 0 | BX33: 0 | BY33: 0 | BZ33: 0 | CA33: 0 | CB33: =CB32/CB$9 -> 0 | CD33: 0 | CE33: 0 | CF33: 0 | CG33: 0 | CH33: =CH32/CH$9 -> 0 | CJ33: 0 | CK33: 0 | CL33: 0 | CM33: 0 | CN33: =CN32/CN$9 -> 0
B34: Change YoY ($mm) | J34: =J32-D32 -> 0 | K34: =K32-E32 -> 0 | L34: =L32-F32 -> 0 | M34: =M32-G32 -> 0 | N34: =N32-H32 -> 0 | P34: =P32-J32 -> 0 | Q34: =Q32-K32 -> 0 | R34: =R32-L32 -> 0 | S34: =S32-M32 -> 0 | T34: =T32-N32 -> 0 | V34: =V32-P32 -> 0 | W34: =W32-Q32 -> 0 | X34: =X32-R32 -> 0 | Y34: =Y32-S32 -> 0 | Z34: =Z32-T32 -> 0 | AB34: =AB32-V32 -> 0 | AC34: =AC32-W32 -> 0 | AD34: =AD32-X32 -> 0 | AE34: =AE32-Y32 -> 0 | AF34: =AF32-Z32 -> 0 | AH34: =AH32-AB32 -> 0 | AI34: =AI32-AC32 -> 0 | AJ34: =AJ32-AD32 -> 0 | AK34: =AK32-AE32 -> 925 | AL34: =AL32-AF32 -> 925 | AN34: =AN32-AH32 -> 0 | AO34: =AO32-AI32 -> 0 | AP34: =AP32-AJ32 -> 0 | AQ34: =AQ32-AK32 -> -925 | AR34: =AR32-AL32 -> -925 | AT34: =AT32-AN32 -> 0 | AU34: =AU32-AO32 -> 0 | AV34: =AV32-AP32 -> 0 | AW34: =AW32-AQ32 -> 0 | AX34: =AX32-AR32 -> 0 | AZ34: =AZ32-AT32 -> 0 | BA34: =BA32-AU32 -> 0 | BB34: =BB32-AV32 -> 0 | BC34: =BC32-AW32 -> 0 | BD34: =BD32-AX32 -> 0 | BF34: =BF32-AZ32 -> 0 | BG34: =BG32-BA32 -> 0 | BH34: =BH32-BB32 -> 0 | BI34: =BI32-BC32 -> 0 | BJ34: =BJ32-BD32 -> 0 | BL34: =BL32-BF32 -> 0 | BM34: =BM32-BG32 -> 0 | BN34: =BN32-BH32 -> 0 | BO34: =BO32-BI32 -> 0 | BP34: =BP32-BJ32 -> 0 | BR34: =BR32-BL32 -> 0 | BS34: =BS32-BM32 -> 0 | BT34: =BT32-BN32 -> 0 | BU34: =BU32-BO32 -> 0 | BV34: =BV32-BP32 -> 0 | BX34: =BX32-BR32 -> 0 | BY34: =BY32-BS32 -> 0 | BZ34: =BZ32-BT32 -> 0 | CA34: =CA32-BU32 -> 0 | CB34: =CB32-BV32 -> 0 | CD34: =CD32-BX32 -> 0 | CE34: =CE32-BY32 -> 0 | CF34: =CF32-BZ32 -> 0 | CG34: =CG32-CA32 -> 0 | CH34: =CH32-CB32 -> 0 | CJ34: =CJ32-CD32 -> 0 | CK34: =CK32-CE32 -> 0 | CL34: =CL32-CF32 -> 0 | CM34: =CM32-CG32 -> 0 | CN34: =CN32-CH32 -> 0
B35: Other operating (income) expenses ($mm) | D35: 996 | E35: 407 | F35: 348 | G35: =H35-SUM(D35:F35) -> 504 | H35: 2255 | J35: 300 | K35: 338 | L35: 390 | M35: =N35-SUM(J35:L35) -> 354 | N35: 1382 | P35: 312 | Q35: 336 | R35: 298 | S35: =T35-SUM(P35:R35) -> 325 | T35: 1271 | V35: 313 | W35: 431 | X35: 370 | Y35: =Z35-SUM(V35:X35) -> 353 | Z35: 1467 | AB35: 323 | AC35: 293 | AD35: 238 | AE35: =AF35-SUM(AB35:AD35) -> 220 | AF35: 1074 | AH35: 266 | AI35: 303 | AJ35: 339 | AK35: =AL35-SUM(AH35:AJ35) -> 310 | AL35: 1218 | AN35: 876 | AO35: 300 | AP35: 320 | AQ35: =AR35-SUM(AN35:AP35) -> 322 | AR35: 1818 | AT35: 223 | AU35: 556 | AV35: 355 | AW35: =AW$9*AW36 -> 367.1195 | AX35: =SUM(AT35:AW35) -> 1501.1195 | AZ35: =AZ$9*AZ36 -> 217.2842 | BA35: =BA$9*BA36 -> 547.97766 | BB35: =BB$9*BB36 -> 356.67273 | BC35: =BC$9*BC36 -> 372.97886 | BD35: =SUM(AZ35:BC35) -> 1494.9135 | BF35: =BF$9*BF36 -> 227.55359 | BG35: =BG$9*BG36 -> 573.86959 | BH35: =BH$9*BH36 -> 373.48661 | BI35: =BI$9*BI36 -> 390.47846 | BJ35: =SUM(BF35:BI35) -> 1565.3883 | BL35: =BL$9*BL36 -> 236.8566 | BM35: =BM$9*BM36 -> 597.45937 | BN35: =BN$9*BN36 -> 388.79754 | BO35: =BO$9*BO36 -> 406.57767 | BP35: =SUM(BL35:BO35) -> 1629.6912 | BR35: =BR$9*BR36 -> 246.55617 | BS35: =BS$9*BS36 -> 622.05983 | BT35: =BT$9*BT36 -> 404.76281 | BU35: =BU$9*BU36 -> 423.37032 | BV35: =SUM(BR35:BU35) -> 1696.7491 | BX35: =BX$9*BX36 -> 256.66978 | BY35: =BY$9*BY36 -> 647.71572 | BZ35: =BZ$9*BZ36 -> 421.41135 | CA35: =CA$9*CA36 -> 440.88729 | CB35: =SUM(BX35:CA35) -> 1766.6841 | CD35: =CD$9*CD36 -> 267.21571 | CE35: =CE$9*CE36 -> 674.47381 | CF35: =CF$9*CF36 -> 438.77335 | CG35: =CG$9*CG36 -> 459.16088 | CH35: =SUM(CD35:CG35) -> 1839.6238 | CJ35: =CJ$9*CJ36 -> 278.21305 | CK35: =CK$9*CK36 -> 702.38304 | CL35: =CL$9*CL36 -> 456.88041 | CM35: =CM$9*CM36 -> 478.22485 | CN35: =SUM(CJ35:CM35) -> 1915.7013
B36: % of Revenue | D36: =D35/D$9 -> 0.10140501 | E36: =E35/E$9 -> 0.03591916 | F36: =F35/F$9 -> 0.030491545 | G36: =G35/G$9 -> 0.039081886 | H36: =H35/H$9 -> 0.049601865 | J36: =J35/J$9 -> 0.023329963 | K36: =K35/K$9 -> 0.024123903 | L36: =L35/L$9 -> 0.028867506 | M36: =M35/M$9 -> 0.02468275 | N36: =N35/N$9 -> 0.025254925 | P36: =P35/P$9 -> 0.023169464 | Q36: =Q35/Q$9 -> 0.023281596 | R36: =R35/R$9 -> 0.023357893 | S36: =S35/S$9 -> 0.024726111 | T36: =T35/T$9 -> 0.023624535 | V36: =V35/V$9 -> 0.029431124 | W36: =W35/W$9 -> 0.043112934 | X36: =X35/X$9 -> 0.037445603 | Y36: =Y35/Y$9 -> 0.031419671 | Z36: =Z35/Z$9 -> 0.035139408 | AB36: =AB35/AB$9 -> 0.027172541 | AC36: =AC35/AC$9 -> 0.022732563 | AD36: =AD35/AD$9 -> 0.019198193 | AE36: =AE35/AE$9 -> 0.01594434 | AF36: =AF35/AF$9 -> 0.021070805 | AH36: =AH35/AH$9 -> 0.019574656 | AI36: =AI35/AI$9 -> 0.021267635 | AJ36: =AJ35/AJ$9 -> 0.022609044 | AK36: =AK35/AK$9 -> 0.018678074 | AL36: =AL35/AL$9 -> 0.020495734 | AN36: =AN35/AN$9 -> 0.055226327 | AO36: =AO35/AO$9 -> 0.017323017 | AP36: =AP35/AP$9 -> 0.019036288 | AQ36: =AQ35/AQ$9 -> 0.018863503 | AR36: =AR35/AR$9 -> 0.027110051 | AT36: =AT35/AT$9 -> 0.014114817 | AU36: =AU35/AU$9 -> 0.033315357 | AV36: =AV35/AV$9 -> 0.022041475 | AW36: 0.022 | AX36: =AX35/AX$9 -> 0.02299465 | AZ36: =AT36 -> 0.014114817 | BA36: =AU36 -> 0.033315357 | BB36: =AV36 -> 0.022041475 | BC36: =AW36 -> 0.022 | BD36: =BD35/BD$9 -> 0.023006553 | BF36: =AZ36 -> 0.014114817 | BG36: =BA36 -> 0.033315357 | BH36: =BB36 -> 0.022041475 | BI36: =BC36 -> 0.022 | BJ36: =BJ35/BJ$9 -> 0.023006636 | BL36: =BF36 -> 0.014114817 | BM36: =BG36 -> 0.033315357 | BN36: =BH36 -> 0.022041475 | BO36: =BI36 -> 0.022 | BP36: =BP35/BP$9 -> 0.023007084 | BR36: =BL36 -> 0.014114817 | BS36: =BM36 -> 0.033315357 | BT36: =BN36 -> 0.022041475 | BU36: =BO36 -> 0.022 | BV36: =BV35/BV$9 -> 0.02300753 | BX36: =BR36 -> 0.014114817 | BY36: =BS36 -> 0.033315357 | BZ36: =BT36 -> 0.022041475 | CA36: =BU36 -> 0.022 | CB36: =CB35/CB$9 -> 0.023007976 | CD36: =BX36 -> 0.014114817 | CE36: =BY36 -> 0.033315357 | CF36: =BZ36 -> 0.022041475 | CG36: =CA36 -> 0.022 | CH36: =CH35/CH$9 -> 0.023008421 | CJ36: =CD36 -> 0.014114817 | CK36: =CE36 -> 0.033315357 | CL36: =CF36 -> 0.022041475 | CM36: =CG36 -> 0.022 | CN36: =CN35/CN$9 -> 0.023008864
B37: Change YoY ($mm) | J37: =J35-D35 -> -696 | K37: =K35-E35 -> -69 | L37: =L35-F35 -> 42 | M37: =M35-G35 -> -150 | N37: =N35-H35 -> -873 | P37: =P35-J35 -> 12 | Q37: =Q35-K35 -> -2 | R37: =R35-L35 -> -92 | S37: =S35-M35 -> -29 | T37: =T35-N35 -> -111 | V37: =V35-P35 -> 1 | W37: =W35-Q35 -> 95 | X37: =X35-R35 -> 72 | Y37: =Y35-S35 -> 28 | Z37: =Z35-T35 -> 196 | AB37: =AB35-V35 -> 10 | AC37: =AC35-W35 -> -138 | AD37: =AD35-X35 -> -132 | AE37: =AE35-Y35 -> -133 | AF37: =AF35-Z35 -> -393 | AH37: =AH35-AB35 -> -57 | AI37: =AI35-AC35 -> 10 | AJ37: =AJ35-AD35 -> 101 | AK37: =AK35-AE35 -> 90 | AL37: =AL35-AF35 -> 144 | AN37: =AN35-AH35 -> 610 | AO37: =AO35-AI35 -> -3 | AP37: =AP35-AJ35 -> -19 | AQ37: =AQ35-AK35 -> 12 | AR37: =AR35-AL35 -> 600 | AT37: =AT35-AN35 -> -653 | AU37: =AU35-AO35 -> 256 | AV37: =AV35-AP35 -> 35 | AW37: =AW35-AQ35 -> 45.1195 | AX37: =AX35-AR35 -> -316.8805 | AZ37: =AZ35-AT35 -> -5.7157953 | BA37: =BA35-AU35 -> -8.0223381 | BB37: =BB35-AV35 -> 1.6727276 | BC37: =BC35-AW35 -> 5.859359 | BD37: =BD35-AX35 -> -6.2060468 | BF37: =BF35-AZ35 -> 10.269389 | BG37: =BG35-BA35 -> 25.891929 | BH37: =BH35-BB35 -> 16.813884 | BI37: =BI35-BC35 -> 17.499605 | BJ37: =BJ35-BD35 -> 70.474807 | BL37: =BL35-BF35 -> 9.303008 | BM37: =BM35-BG35 -> 23.589783 | BN37: =BN35-BH35 -> 15.310927 | BO37: =BO35-BI35 -> 16.09921 | BP37: =BP35-BJ35 -> 64.302928 | BR37: =BR35-BL35 -> 9.6995689 | BS37: =BS35-BM35 -> 24.600459 | BT37: =BT35-BN35 -> 15.965276 | BU37: =BU35-BO35 -> 16.792649 | BV37: =BV35-BP35 -> 67.057953 | BX37: =BX35-BR35 -> 10.113611 | BY37: =BY35-BS35 -> 25.655885 | BZ37: =BZ35-BT35 -> 16.648532 | CA37: =CA35-BU35 -> 17.516971 | CB37: =CB35-BV35 -> 69.934999 | CD37: =CD35-BX35 -> 10.545925 | CE37: =CE35-BY35 -> 26.758097 | CF37: =CF35-BZ35 -> 17.362003 | CG37: =CG35-CA35 -> 18.273586 | CH37: =CH35-CB35 -> 72.939611 | CJ37: =CJ35-CD35 -> 10.997339 | CK37: =CK35-CE35 -> 27.909221 | CL37: =CL35-CF35 -> 18.107062 | CM37: =CM35-CG35 -> 19.063972 | CN37: =CN35-CH35 -> 76.077594
B39: Operating Expense ($mm) | D39: =D21+D32+D25+D29+D35 -> 2641 | E39: =E21+E32+E25+E29+E35 -> 2331 | F39: =F21+F32+F25+F29+F35 -> 2226 | G39: =G21+G32+G25+G29+G35 -> 2544 | H39: =H21+H32+H25+H29+H35 -> 9742 | J39: =J21+J32+J25+J29+J35 -> 2185 | K39: =K21+K32+K25+K29+K35 -> 2422 | L39: =L21+L32+L25+L29+L35 -> 2353 | M39: =M21+M32+M25+M29+M35 -> 2472 | N39: =N21+N32+N25+N29+N35 -> 9432 | P39: =P21+P32+P25+P29+P35 -> 2256 | Q39: =Q21+Q32+Q25+Q29+Q35 -> 2278 | R39: =R21+R32+R25+R29+R35 -> 2169 | S39: =S21+S32+S25+S29+S35 -> 2177 | T39: =T21+T32+T25+T29+T35 -> 8880 | V39: =V21+V32+V25+V29+V35 -> 1965 | W39: =W21+W32+W25+W29+W35 -> 2100 | X39: =X21+X32+X25+X29+X35 -> 1977 | Y39: =Y21+Y32+Y25+Y29+Y35 -> 2071 | Z39: =Z21+Z32+Z25+Z29+Z35 -> 8113 | AB39: =AB21+AB32+AB25+AB29+AB35 -> 2061 | AC39: =AC21+AC32+AC25+AC29+AC35 -> 2219 | AD39: =AD21+AD32+AD25+AD29+AD35 -> 2116 | AE39: =AE21+AE32+AE25+AE29+AE35 -> 2184 | AF39: =AF21+AF32+AF25+AF29+AF35 -> 8580 | AH39: =AH21+AH32+AH25+AH29+AH35 -> 2175 | AI39: =AI21+AI32+AI25+AI29+AI35 -> 2328 | AJ39: =AJ21+AJ32+AJ25+AJ29+AJ35 -> 2367 | AK39: =AK21+AK32+AK25+AK29+AK35 -> 3303 | AL39: =AL21+AL32+AL25+AL29+AL35 -> 10173 | AN39: =AN21+AN32+AN25+AN29+AN35 -> 3028 | AO39: =AO21+AO32+AO25+AO29+AO35 -> 2601 | AP39: =AP21+AP32+AP25+AP29+AP35 -> 2778 | AQ39: =AQ21+AQ32+AQ25+AQ29+AQ35 -> 2920 | AR39: =AR21+AR32+AR25+AR29+AR35 -> 11327 | AT39: =AT21+AT32+AT25+AT29+AT35 -> 2618 | AU39: =AU21+AU32+AU25+AU29+AU35 -> 3057 | AV39: =AV21+AV32+AV25+AV29+AV35 -> 2893 | AW39: =AW21+AW32+AW25+AW29+AW35 -> 2936.956 | AX39: =AX21+AX32+AX25+AX29+AX35 -> 11504.956 | AZ39: =AZ21+AZ32+AZ25+AZ29+AZ35 -> 2550.6439 | BA39: =BA21+BA32+BA25+BA29+BA35 -> 3026.2581 | BB39: =BB21+BB32+BB25+BB29+BB35 -> 2844.72 | BC39: =BC21+BC32+BC25+BC29+BC35 -> 2980.4402 | BD39: =BD21+BD32+BD25+BD29+BD35 -> 11402.062 | BF39: =BF21+BF32+BF25+BF29+BF35 -> 2667.9694 | BG39: =BG21+BG32+BG25+BG29+BG35 -> 3165.8036 | BH39: =BH21+BH32+BH25+BH29+BH35 -> 2975.4338 | BI39: =BI21+BI32+BI25+BI29+BI35 -> 3116.7281 | BJ39: =BJ21+BJ32+BJ25+BJ29+BJ35 -> 11925.935 | BL39: =BL21+BL32+BL25+BL29+BL35 -> 2773.687 | BM39: =BM21+BM32+BM25+BM29+BM35 -> 3292.3521 | BN39: =BN21+BN32+BN25+BN29+BN35 -> 3093.8826 | BO39: =BO21+BO32+BO25+BO29+BO35 -> 3241.5329 | BP39: =BP21+BP32+BP25+BP29+BP35 -> 12401.455 | BR39: =BR21+BR32+BR25+BR29+BR35 -> 2883.7793 | BS39: =BS21+BS32+BS25+BS29+BS35 -> 3424.1807 | BT39: =BT21+BT32+BT25+BT29+BT35 -> 3217.2546 | BU39: =BU21+BU32+BU25+BU29+BU35 -> 3371.5673 | BV39: =BV21+BV32+BV25+BV29+BV35 -> 12896.782 | BX39: =BX21+BX32+BX25+BX29+BX35 -> 2998.4336 | BY39: =BY21+BY32+BY25+BY29+BY35 -> 3561.5173 | BZ39: =BZ21+BZ32+BZ25+BZ29+BZ35 -> 3345.7615 | CA39: =CA21+CA32+CA25+CA29+CA35 -> 3507.058 | CB39: =CB21+CB32+CB25+CB29+CB35 -> 13412.771 | CD39: =CD21+CD32+CD25+CD29+CD35 -> 3117.8455 | CE39: =CE21+CE32+CE25+CE29+CE35 -> 3704.5998 | CF39: =CF21+CF32+CF25+CF29+CF35 -> 3479.6244 | CG39: =CG21+CG32+CG25+CG29+CG35 -> 3648.2419 | CH39: =CH21+CH32+CH25+CH29+CH35 -> 13950.312 | CJ39: =CJ21+CJ32+CJ25+CJ29+CJ35 -> 3242.2192 | CK39: =CK21+CK32+CK25+CK29+CK35 -> 3853.6768 | CL39: =CL21+CL32+CL25+CL29+CL35 -> 3619.0741 | CM39: =CM21+CM32+CM25+CM29+CM35 -> 3795.3663 | CN39: =CN21+CN32+CN25+CN29+CN35 -> 14510.336
B40: Operating Ratio (%) | D40: =D39/D9 -> 0.26888617 | E40: =E39/E9 -> 0.20571882 | F40: =F39/F9 -> 0.19504074 | G40: =G39/G9 -> 0.19727047 | H40: =H39/H9 -> 0.21428886 | J40: =J39/J9 -> 0.1699199 | K40: =K39/K9 -> 0.17286418 | L40: =L39/L9 -> 0.17416728 | M40: =M39/M9 -> 0.1723609 | N40: =N39/N9 -> 0.17236212 | P40: =P39/P9 -> 0.16753305 | Q40: =Q39/Q9 -> 0.15784368 | R40: =R39/R9 -> 0.17001097 | S40: =S39/S9 -> 0.1656269 | T40: =T39/T9 -> 0.16505576 | V40: =V39/V9 -> 0.18476728 | W40: =W39/W9 -> 0.21006302 | X40: =X39/X9 -> 0.20008096 | Y40: =Y39/Y9 -> 0.18433467 | Z40: =Z39/Z9 -> 0.19433266 | AB40: =AB39/AB9 -> 0.17338269 | AC40: =AC39/AC9 -> 0.17216231 | AD40: =AD39/AD9 -> 0.17068646 | AE40: =AE39/AE9 -> 0.15828381 | AF40: =AF39/AF9 -> 0.16833101 | AH40: =AH39/AH9 -> 0.16005593 | AI40: =AI39/AI9 -> 0.16340282 | AJ40: =AJ39/AJ9 -> 0.15786315 | AK40: =AK39/AK9 -> 0.19901187 | AL40: =AL39/AL9 -> 0.17118481 | AN40: =AN39/AN9 -> 0.19089648 | AO40: =AO39/AO9 -> 0.15019055 | AP40: =AP39/AP9 -> 0.16525877 | AQ40: =AQ39/AQ9 -> 0.17106034 | AR40: =AR39/AR9 -> 0.16890844 | AT40: =AT39/AT9 -> 0.16570669 | AU40: =AU39/AU9 -> 0.18317455 | AV40: =AV39/AV9 -> 0.1796225 | AW40: =AW39/AW9 -> 0.176 | AX40: =AX39/AX9 -> 0.17623676 | AZ40: =AZ39/AZ9 -> 0.16569025 | BA40: =BA39/BA9 -> 0.18398719 | BB40: =BB39/BB9 -> 0.17579652 | BC40: =BC39/BC9 -> 0.1758 | BD40: =BD39/BD9 -> 0.17547648 | BF40: =BF39/BF9 -> 0.16549025 | BG40: =BG39/BG9 -> 0.18378719 | BH40: =BH39/BH9 -> 0.17559652 | BI40: =BI39/BI9 -> 0.1756 | BJ40: =BJ39/BJ9 -> 0.17527641 | BL40: =BL39/BL9 -> 0.16529025 | BM40: =BM39/BM9 -> 0.18358719 | BN40: =BN39/BN9 -> 0.17539652 | BO40: =BO39/BO9 -> 0.1754 | BP40: =BP39/BP9 -> 0.17507691 | BR40: =BR39/BR9 -> 0.16509025 | BS40: =BS39/BS9 -> 0.18338719 | BT40: =BT39/BT9 -> 0.17519652 | BU40: =BU39/BU9 -> 0.1752 | BV40: =BV39/BV9 -> 0.17487741 | BX40: =BX39/BX9 -> 0.16489025 | BY40: =BY39/BY9 -> 0.18318719 | BZ40: =BZ39/BZ9 -> 0.17499652 | CA40: =CA39/CA9 -> 0.175 | CB40: =CB39/CB9 -> 0.17467792 | CD40: =CD39/CD9 -> 0.16469025 | CE40: =CE39/CE9 -> 0.18298719 | CF40: =CF39/CF9 -> 0.17479652 | CG40: =CG39/CG9 -> 0.1748 | CH40: =CH39/CH9 -> 0.17447842 | CJ40: =CJ39/CJ9 -> 0.16449025 | CK40: =CK39/CK9 -> 0.18278719 | CL40: =CL39/CL9 -> 0.17459652 | CM40: =CM39/CM9 -> 0.1746 | CN40: =CN39/CN9 -> 0.17427892
B42: EBIT ($mm) | D42: =D17-D39 -> 380 | E42: =E17-E39 -> 1184 | F42: =F17-F39 -> 1509 | G42: =G17-G39 -> 1387 | H42: =H17-H39 -> 4460 | J42: =J17-J39 -> 2108 | K42: =K17-K39 -> 2167 | L42: =L17-L39 -> 2135 | M42: =M17-M39 -> 1883 | N42: =N17-N39 -> 8293 | P42: =P17-P39 -> 2207 | Q42: =Q17-Q39 -> 2213 | R42: =R17-R39 -> 2020 | S42: =S17-S39 -> 1850 | T42: =T17-T39 -> 8290 | V42: =V17-V39 -> 1404 | W42: =W17-W39 -> 784 | X42: =X17-X39 -> 985 | Y42: =Y17-Y39 -> 1380 | Z42: =Z17-Z39 -> 4553 | AB42: =AB17-AB39 -> 1814 | AC42: =AC17-AC39 -> 1789 | AD42: =AD17-AD39 -> 1664 | AE42: =AE17-AE39 -> 1611 | AF42: =AF17-AF39 -> 6878 | AH42: =AH17-AH39 -> 1855 | AI42: =AI17-AI39 -> 1944 | AJ42: =AJ17-AJ39 -> 2425 | AK42: =AK17-AK39 -> 1680 | AL42: =AL17-AL39 -> 7904 | AN42: =AN17-AN39 -> 2731 | AO42: =AO17-AO39 -> 3652 | AP42: =AP17-AP39 -> 3449 | AQ42: =AQ17-AQ39 -> 3134 | AR42: =AR17-AR39 -> 12966 | AT42: =AT17-AT39 -> 3519 | AU42: =AU17-AU39 -> 3482 | AV42: =AV17-AV39 -> 3147 | AW42: =AW114+AW283+AW296 -> 3100.1916 | AX42: =AX114+AX283+AX296 -> 13248.192 | AZ42: =AZ114+AZ283+AZ296 -> 3231.5688 | BA42: =BA114+BA283+BA296 -> 3450.8981 | BB42: =BB114+BB283+BB296 -> 3134.4737 | BC42: =BC114+BC283+BC296 -> 3192.0793 | BD42: =BD114+BD283+BD296 -> 13009.02 | BF42: =BF114+BF283+BF296 -> 3497.6791 | BG42: =BG114+BG283+BG296 -> 3735.5436 | BH42: =BH114+BH283+BH296 -> 3413.2261 | BI42: =BI114+BI283+BI296 -> 3481.056 | BJ42: =BJ114+BJ283+BJ296 -> 14127.505 | BL42: =BL114+BL283+BL296 -> 3696.8857 | BM42: =BM114+BM283+BM296 -> 3949.0373 | BN42: =BN114+BN283+BN296 -> 3622.4582 | BO42: =BO114+BO283+BO296 -> 3698.7929 | BP42: =BP114+BP283+BP296 -> 14967.174 | BR42: =BR114+BR283+BR296 -> 3907.8405 | BS42: =BS114+BS283+BS296 -> 4175.1465 | BT42: =BT114+BT283+BT296 -> 3844.2003 | BU42: =BU114+BU283+BU296 -> 3929.4095 | BV42: =BV114+BV283+BV296 -> 15856.597 | BX42: =BX114+BX283+BX296 -> 4127.6353 | BY42: =BY114+BY283+BY296 -> 4410.7787 | BZ42: =BZ114+BZ283+BZ296 -> 4075.2653 | CA42: =CA114+CA283+CA296 -> 4169.81 | CB42: =CB114+CB283+CB296 -> 16783.489 | CD42: =CD114+CD283+CD296 -> 4356.653 | CE42: =CE114+CE283+CE296 -> 4656.3486 | CF42: =CF114+CF283+CF296 -> 4316.0584 | CG42: =CG114+CG283+CG296 -> 4420.4236 | CH42: =CH114+CH283+CH296 -> 17749.484 | CJ42: =CJ114+CJ283+CJ296 -> 4600.9339 | CK42: =CK114+CK283+CK296 -> 4918.0026 | CL42: =CL114+CL283+CL296 -> 4572.8873 | CM42: =CM114+CM283+CM296 -> 4687.5867 | CN42: =CN114+CN283+CN296 -> 18779.411
B43: EBIT Margin (%) | D43: =D42/D9 -> 0.038688658 | E43: =E42/E9 -> 0.1044921 | F43: =F42/F9 -> 0.13221765 | G43: =G42/G9 -> 0.10755273 | H43: =H42/H9 -> 0.098103911 | J43: =J42/J9 -> 0.16393188 | K43: =K42/K9 -> 0.15466419 | L43: =L42/L9 -> 0.15803109 | M43: =M42/M9 -> 0.13129271 | N43: =N42/N9 -> 0.15154782 | P43: =P42/P9 -> 0.16389425 | Q43: =Q42/Q9 -> 0.1533398 | R43: =R42/R9 -> 0.15833203 | S43: =S42/S9 -> 0.14074863 | T43: =T42/T9 -> 0.15408922 | V43: =V42/V9 -> 0.13201693 | W43: =W42/W9 -> 0.078423527 | X43: =X42/X9 -> 0.099686267 | Y43: =Y42/Y9 -> 0.12283044 | Z43: =Z42/Z9 -> 0.10905912 | AB43: =AB42/AB9 -> 0.15260368 | AC43: =AC42/AC9 -> 0.13880053 | AD43: =AD42/AD9 -> 0.13422602 | AE43: =AE42/AE9 -> 0.11675605 | AF43: =AF42/AF9 -> 0.13493948 | AH43: =AH42/AH9 -> 0.13650747 | AI43: =AI42/AI9 -> 0.13644978 | AJ43: =AJ42/AJ9 -> 0.16173136 | AK43: =AK42/AK9 -> 0.10122311 | AL43: =AL42/AL9 -> 0.13300352 | AN43: =AN42/AN9 -> 0.17217249 | AO43: =AO42/AO9 -> 0.21087885 | AP43: =AP42/AP9 -> 0.20517549 | AQ43: =AQ42/AQ9 -> 0.18359695 | AR43: =AR42/AR9 -> 0.19334924 | AT43: =AT42/AT9 -> 0.22273562 | AU43: =AU42/AU9 -> 0.20864042 | AV43: =AV42/AV9 -> 0.19539302 | AW43: =AW42/AW9 -> 0.18578205 | AX43: =AX42/AX9 -> 0.20294023 | AZ43: =AZ42/AZ9 -> 0.20992323 | BA43: =BA42/BA9 -> 0.209804 | BB43: =BB42/BB9 -> 0.19370257 | BC43: =BC42/BC9 -> 0.18828345 | BD43: =BD42/BD9 -> 0.20020738 | BF43: =BF42/BF9 -> 0.21695593 | BG43: =BG42/BG9 -> 0.21686281 | BH43: =BH42/BH9 -> 0.20143302 | BI43: =BI42/BI9 -> 0.19612665 | BJ43: =BJ42/BJ9 -> 0.20763306 | BL43: =BL42/BL9 -> 0.22030573 | BM43: =BM42/BM9 -> 0.22020508 | BN43: =BN42/BN9 -> 0.20536221 | BO43: =BO42/BO9 -> 0.20014243 | BP43: =BP42/BP9 -> 0.21129833 | BR43: =BR42/BR9 -> 0.22371558 | BS43: =BS42/BS9 -> 0.2236063 | BT43: =BT42/BT9 -> 0.20933703 | BU43: =BU42/BU9 -> 0.20418769 | BV43: =BV42/BV9 -> 0.21501183 | BX43: =BX42/BX9 -> 0.22698745 | BY43: =BY42/BY9 -> 0.22686908 | BZ43: =BZ42/BZ9 -> 0.21315245 | CA43: =CA42/CA9 -> 0.20807091 | CB43: =CB42/CB9 -> 0.21857564 | CD43: =CD42/CD9 -> 0.2301263 | CE43: =CE42/CE9 -> 0.22999843 | CF43: =CF42/CF9 -> 0.21681421 | CG43: =CG42/CG9 -> 0.21179792 | CH43: =CH42/CH9 -> 0.22199517 | CJ43: =CJ42/CJ9 -> 0.23342307 | CK43: =CK42/CK9 -> 0.23327018 | CL43: =CL42/CL9 -> 0.22061174 | CM43: =CM42/CM9 -> 0.21564523 | CN43: =CN42/CN9 -> 0.22555337
B44: Check | D44: =IF(D114+D283+D296-D42=0,"OK",D114+D283+D296-D42) -> OK | E44: =IF(E114+E283+E296-E42=0,"OK",E114+E283+E296-E42) -> OK | F44: =IF(F114+F283+F296-F42=0,"OK",F114+F283+F296-F42) -> OK | G44: =IF(G114+G283+G296-G42=0,"OK",G114+G283+G296-G42) -> OK | H44: =IF(H114+H283+H296-H42=0,"OK",H114+H283+H296-H42) -> OK | J44: =IF(J114+J283+J296-J42=0,"OK",J114+J283+J296-J42) -> OK | K44: =IF(K114+K283+K296-K42=0,"OK",K114+K283+K296-K42) -> OK | L44: =IF(L114+L283+L296-L42=0,"OK",L114+L283+L296-L42) -> OK | M44: =IF(M114+M283+M296-M42=0,"OK",M114+M283+M296-M42) -> OK | N44: =IF(N114+N283+N296-N42=0,"OK",N114+N283+N296-N42) -> OK | P44: =IF(P114+P283+P296-P42=0,"OK",P114+P283+P296-P42) -> OK | Q44: =IF(Q114+Q283+Q296-Q42=0,"OK",Q114+Q283+Q296-Q42) -> OK | R44: =IF(R114+R283+R296-R42=0,"OK",R114+R283+R296-R42) -> OK | S44: =IF(S114+S283+S296-S42=0,"OK",S114+S283+S296-S42) -> OK | T44: =IF(T114+T283+T296-T42=0,"OK",T114+T283+T296-T42) -> OK | V44: =IF(V114+V283+V296-V42=0,"OK",V114+V283+V296-V42) -> OK | W44: =IF(W114+W283+W296-W42=0,"OK",W114+W283+W296-W42) -> OK | X44: =IF(X114+X283+X296-X42=0,"OK",X114+X283+X296-X42) -> OK | Y44: =IF(Y114+Y283+Y296-Y42=0,"OK",Y114+Y283+Y296-Y42) -> OK | Z44: =IF(Z114+Z283+Z296-Z42=0,"OK",Z114+Z283+Z296-Z42) -> OK | AB44: =IF(AB114+AB283+AB296-AB42=0,"OK",AB114+AB283+AB296-AB42) -> OK | AC44: =IF(AC114+AC283+AC296-AC42=0,"OK",AC114+AC283+AC296-AC42) -> OK | AD44: =IF(AD114+AD283+AD296-AD42=0,"OK",AD114+AD283+AD296-AD42) -> OK | AE44: =IF(AE114+AE283+AE296-AE42=0,"OK",AE114+AE283+AE296-AE42) -> OK | AF44: =IF(AF114+AF283+AF296-AF42=0,"OK",AF114+AF283+AF296-AF42) -> OK | AH44: =IF(AH114+AH283+AH296-AH42=0,"OK",AH114+AH283+AH296-AH42) -> OK | AI44: =IF(AI114+AI283+AI296-AI42=0,"OK",AI114+AI283+AI296-AI42) -> OK | AJ44: =IF(AJ114+AJ283+AJ296-AJ42=0,"OK",AJ114+AJ283+AJ296-AJ42) -> OK | AK44: =IF(AK114+AK283+AK296-AK42=0,"OK",AK114+AK283+AK296-AK42) -> OK | AL44: =IF(AL114+AL283+AL296-AL42=0,"OK",AL114+AL283+AL296-AL42) -> OK | AN44: =IF(AN114+AN283+AN296-AN42=0,"OK",AN114+AN283+AN296-AN42) -> OK | AO44: =IF(AO114+AO283+AO296-AO42=0,"OK",AO114+AO283+AO296-AO42) -> OK | AP44: =IF(AP114+AP283+AP296-AP42=0,"OK",AP114+AP283+AP296-AP42) -> OK | AQ44: =IF(AQ114+AQ283+AQ296-AQ42=0,"OK",AQ114+AQ283+AQ296-AQ42) -> OK | AR44: =IF(AR114+AR283+AR296-AR42=0,"OK",AR114+AR283+AR296-AR42) -> OK | AT44: =IF(AT114+AT283+AT296-AT42=0,"OK",AT114+AT283+AT296-AT42) -> OK | AU44: =IF(AU114+AU283+AU296-AU42=0,"OK",AU114+AU283+AU296-AU42) -> OK | AV44: =IF(AV114+AV283+AV296-AV42=0,"OK",AV114+AV283+AV296-AV42) -> OK | AW44: =IF(AW114+AW283+AW296-AW42=0,"OK",AW114+AW283+AW296-AW42) -> OK | AX44: =IF(AX114+AX283+AX296-AX42=0,"OK",AX114+AX283+AX296-AX42) -> OK | AZ44: =IF(AZ114+AZ283+AZ296-AZ42=0,"OK",AZ114+AZ283+AZ296-AZ42) -> OK | BA44: =IF(BA114+BA283+BA296-BA42=0,"OK",BA114+BA283+BA296-BA42) -> OK | BB44: =IF(BB114+BB283+BB296-BB42=0,"OK",BB114+BB283+BB296-BB42) -> OK | BC44: =IF(BC114+BC283+BC296-BC42=0,"OK",BC114+BC283+BC296-BC42) -> OK | BD44: =IF(BD114+BD283+BD296-BD42=0,"OK",BD114+BD283+BD296-BD42) -> OK | BF44: =IF(BF114+BF283+BF296-BF42=0,"OK",BF114+BF283+BF296-BF42) -> OK | BG44: =IF(BG114+BG283+BG296-BG42=0,"OK",BG114+BG283+BG296-BG42) -> OK | BH44: =IF(BH114+BH283+BH296-BH42=0,"OK",BH114+BH283+BH296-BH42) -> OK | BI44: =IF(BI114+BI283+BI296-BI42=0,"OK",BI114+BI283+BI296-BI42) -> OK | BJ44: =IF(BJ114+BJ283+BJ296-BJ42=0,"OK",BJ114+BJ283+BJ296-BJ42) -> OK | BL44: =IF(BL114+BL283+BL296-BL42=0,"OK",BL114+BL283+BL296-BL42) -> OK | BM44: =IF(BM114+BM283+BM296-BM42=0,"OK",BM114+BM283+BM296-BM42) -> OK | BN44: =IF(BN114+BN283+BN296-BN42=0,"OK",BN114+BN283+BN296-BN42) -> OK | BO44: =IF(BO114+BO283+BO296-BO42=0,"OK",BO114+BO283+BO296-BO42) -> OK | BP44: =IF(BP114+BP283+BP296-BP42=0,"OK",BP114+BP283+BP296-BP42) -> OK | BR44: =IF(BR114+BR283+BR296-BR42=0,"OK",BR114+BR283+BR296-BR42) -> OK | BS44: =IF(BS114+BS283+BS296-BS42=0,"OK",BS114+BS283+BS296-BS42) -> OK | BT44: =IF(BT114+BT283+BT296-BT42=0,"OK",BT114+BT283+BT296-BT42) -> OK | BU44: =IF(BU114+BU283+BU296-BU42=0,"OK",BU114+BU283+BU296-BU42) -> OK | BV44: =IF(BV114+BV283+BV296-BV42=0,"OK",BV114+BV283+BV296-BV42) -> OK | BX44: =IF(BX114+BX283+BX296-BX42=0,"OK",BX114+BX283+BX296-BX42) -> OK | BY44: =IF(BY114+BY283+BY296-BY42=0,"OK",BY114+BY283+BY296-BY42) -> OK | BZ44: =IF(BZ114+BZ283+BZ296-BZ42=0,"OK",BZ114+BZ283+BZ296-BZ42) -> OK | CA44: =IF(CA114+CA283+CA296-CA42=0,"OK",CA114+CA283+CA296-CA42) -> OK | CB44: =IF(CB114+CB283+CB296-CB42=0,"OK",CB114+CB283+CB296-CB42) -> OK | CD44: =IF(CD114+CD283+CD296-CD42=0,"OK",CD114+CD283+CD296-CD42) -> OK | CE44: =IF(CE114+CE283+CE296-CE42=0,"OK",CE114+CE283+CE296-CE42) -> OK | CF44: =IF(CF114+CF283+CF296-CF42=0,"OK",CF114+CF283+CF296-CF42) -> OK | CG44: =IF(CG114+CG283+CG296-CG42=0,"OK",CG114+CG283+CG296-CG42) -> OK | CH44: =IF(CH114+CH283+CH296-CH42=0,"OK",CH114+CH283+CH296-CH42) -> OK | CJ44: =IF(CJ114+CJ283+CJ296-CJ42=0,"OK",CJ114+CJ283+CJ296-CJ42) -> OK | CK44: =IF(CK114+CK283+CK296-CK42=0,"OK",CK114+CK283+CK296-CK42) -> OK | CL44: =IF(CL114+CL283+CL296-CL42=0,"OK",CL114+CL283+CL296-CL42) -> OK | CM44: =IF(CM114+CM283+CM296-CM42=0,"OK",CM114+CM283+CM296-CM42) -> OK | CN44: =IF(CN114+CN283+CN296-CN42=0,"OK",CN114+CN283+CN296-CN42) -> OK
B46: Reported D&A | D46: =SUM(D119+D286+D299) -> 710 | E46: =SUM(E119+E286+E299) -> 720 | F46: =SUM(F119+F286+F299) -> 723 | G46: =SUM(G119+G286+G299) -> 724 | H46: =SUM(H119+H286+H299) -> 2877 | J46: =SUM(J119+J286+J299) -> 681 | K46: =SUM(K119+K286+K299) -> 686 | L46: =SUM(L119+L286+L299) -> 698 | M46: =SUM(M119+M286+M299) -> 701 | N46: =SUM(N119+N286+N299) -> 2766 | P46: =SUM(P119+P286+P299) -> 641 | Q46: =SUM(Q119+Q286+Q299) -> 647 | R46: =SUM(R119+R286+R299) -> 645 | S46: =SUM(S119+S286+S299) -> 644 | T46: =SUM(T119+T286+T299) -> 2577 | V46: =SUM(V119+V286+V299) -> 614 | W46: =SUM(W119+W286+W299) -> 608 | X46: =SUM(X119+X286+X299) -> 593 | Y46: =SUM(Y119+Y286+Y299) -> 421 | Z46: =SUM(Z119+Z286+Z299) -> 2432 | AB46: =SUM(AB119+AB286+AB299) -> 586 | AC46: =SUM(AC119+AC286+AC299) -> 587 | AD46: =SUM(AD119+AD286+AD299) -> 593 | AE46: =SUM(AE119+AE286+AE299) -> 586 | AF46: =SUM(AF119+AF286+AF299) -> 2352 | AH46: =SUM(AH119+AH286+AH299) -> 557 | AI46: =SUM(AI119+AI286+AI299) -> 553 | AJ46: =SUM(AJ119+AJ286+AJ299) -> 551 | AK46: =SUM(AK119+AK286+AK299) -> 558 | AL46: =SUM(AL119+AL286+AL299) -> 2219 | AN46: =SUM(AN119+AN286+AN299) -> 532 | AO46: =SUM(AO119+AO286+AO299) -> 542 | AP46: =SUM(AP119+AP286+AP299) -> 525 | AQ46: =SUM(AQ119+AQ286+AQ299) -> 545 | AR46: =SUM(AR119+AR286+AR299) -> 2144 | AT46: =SUM(AT119+AT286+AT299) -> 524 | AU46: =SUM(AU119+AU286+AU299) -> 531 | AV46: =SUM(AV119+AV286+AV299) -> 543 | AW46: =SUM(AW119+AW286+AW299) -> 591.2 | AX46: =SUM(AX119+AX286+AX299) -> 2189.2 | AZ46: =SUM(AZ119+AZ286+AZ299) -> 542.16 | BA46: =SUM(BA119+BA286+BA299) -> 549.51 | BB46: =SUM(BB119+BB286+BB299) -> 562.02 | BC46: =SUM(BC119+BC286+BC299) -> 612.132 | BD46: =SUM(BD119+BD286+BD299) -> 2265.822 | BF46: =SUM(BF119+BF286+BF299) -> 561.0672 | BG46: =SUM(BG119+BG286+BG299) -> 568.7847 | BH46: =SUM(BH119+BH286+BH299) -> 581.8284 | BI46: =SUM(BI119+BI286+BI299) -> 633.93804 | BJ46: =SUM(BJ119+BJ286+BJ299) -> 2345.6183 | BL46: =SUM(BL119+BL286+BL299) -> 576.22447 | BM46: =SUM(BM119+BM286+BM299) -> 584.12939 | BN46: =SUM(BN119+BN286+BN299) -> 597.63242 | BO46: =SUM(BO119+BO286+BO299) -> 651.201 | BP46: =SUM(BP119+BP286+BP299) -> 2409.1873 | BR46: =SUM(BR119+BR286+BR299) -> 587.74896 | BS46: =SUM(BS119+BS286+BS299) -> 595.81198 | BT46: =SUM(BT119+BT286+BT299) -> 609.58507 | BU46: =SUM(BU119+BU286+BU299) -> 664.22502 | BV46: =SUM(BV119+BV286+BV299) -> 2457.371 | BX46: =SUM(BX119+BX286+BX299) -> 599.50394 | BY46: =SUM(BY119+BY286+BY299) -> 607.72822 | BZ46: =SUM(BZ119+BZ286+BZ299) -> 621.77677 | CA46: =SUM(CA119+CA286+CA299) -> 677.50952 | CB46: =SUM(CB119+CB286+CB299) -> 2506.5184 | CD46: =SUM(CD119+CD286+CD299) -> 611.49402 | CE46: =SUM(CE119+CE286+CE299) -> 619.88279 | CF46: =SUM(CF119+CF286+CF299) -> 634.2123 | CG46: =SUM(CG119+CG286+CG299) -> 691.05971 | CH46: =SUM(CH119+CH286+CH299) -> 2556.6488 | CJ46: =SUM(CJ119+CJ286+CJ299) -> 623.7239 | CK46: =SUM(CK119+CK286+CK299) -> 632.28044 | CL46: =SUM(CL119+CL286+CL299) -> 646.89655 | CM46: =SUM(CM119+CM286+CM299) -> 704.8809 | CN46: =SUM(CN119+CN286+CN299) -> 2607.7818
B48: EBITDA ($mm) | D48: =D42+D46 -> 1090 | E48: =E42+E46 -> 1904 | F48: =F42+F46 -> 2232 | G48: =G42+G46 -> 2111 | H48: =H42+H46 -> 7337 | J48: =J42+J46 -> 2789 | K48: =K42+K46 -> 2853 | L48: =L42+L46 -> 2833 | M48: =M42+M46 -> 2584 | N48: =N42+N46 -> 11059 | P48: =P42+P46 -> 2848 | Q48: =Q42+Q46 -> 2860 | R48: =R42+R46 -> 2665 | S48: =S42+S46 -> 2494 | T48: =T42+T46 -> 10867 | V48: =V42+V46 -> 2018 | W48: =W42+W46 -> 1392 | X48: =X42+X46 -> 1578 | Y48: =Y42+Y46 -> 1801 | Z48: =Z42+Z46 -> 6985 | AB48: =AB42+AB46 -> 2400 | AC48: =AC42+AC46 -> 2376 | AD48: =AD42+AD46 -> 2257 | AE48: =AE42+AE46 -> 2197 | AF48: =AF42+AF46 -> 9230 | AH48: =AH42+AH46 -> 2412 | AI48: =AI42+AI46 -> 2497 | AJ48: =AJ42+AJ46 -> 2976 | AK48: =AK42+AK46 -> 2238 | AL48: =AL42+AL46 -> 10123 | AN48: =AN42+AN46 -> 3263 | AO48: =AO42+AO46 -> 4194 | AP48: =AP42+AP46 -> 3974 | AQ48: =AQ42+AQ46 -> 3679 | AR48: =AR42+AR46 -> 15110 | AT48: =AT42+AT46 -> 4043 | AU48: =AU42+AU46 -> 4013 | AV48: =AV42+AV46 -> 3690 | AW48: =AW42+AW46 -> 3691.3916 | AX48: =AX42+AX46 -> 15437.392 | AZ48: =AZ42+AZ46 -> 3773.7288 | BA48: =BA42+BA46 -> 4000.4081 | BB48: =BB42+BB46 -> 3696.4937 | BC48: =BC42+BC46 -> 3804.2113 | BD48: =BD42+BD46 -> 15274.842 | BF48: =BF42+BF46 -> 4058.7463 | BG48: =BG42+BG46 -> 4304.3283 | BH48: =BH42+BH46 -> 3995.0545 | BI48: =BI42+BI46 -> 4114.994 | BJ48: =BJ42+BJ46 -> 16473.123 | BL48: =BL42+BL46 -> 4273.1101 | BM48: =BM42+BM46 -> 4533.1667 | BN48: =BN42+BN46 -> 4220.0906 | BO48: =BO42+BO46 -> 4349.9939 | BP48: =BP42+BP46 -> 17376.361 | BR48: =BR42+BR46 -> 4495.5895 | BS48: =BS42+BS46 -> 4770.9585 | BT48: =BT42+BT46 -> 4453.7854 | BU48: =BU42+BU46 -> 4593.6345 | BV48: =BV42+BV46 -> 18313.968 | BX48: =BX42+BX46 -> 4727.1392 | BY48: =BY42+BY46 -> 5018.5069 | BZ48: =BZ42+BZ46 -> 4697.0421 | CA48: =CA42+CA46 -> 4847.3195 | CB48: =CB42+CB46 -> 19290.008 | CD48: =CD42+CD46 -> 4968.147 | CE48: =CE42+CE46 -> 5276.2314 | CF48: =CF42+CF46 -> 4950.2707 | CG48: =CG42+CG46 -> 5111.4833 | CH48: =CH42+CH46 -> 20306.132 | CJ48: =CJ42+CJ46 -> 5224.6578 | CK48: =CK42+CK46 -> 5550.2831 | CL48: =CL42+CL46 -> 5219.7839 | CM48: =CM42+CM46 -> 5392.4676 | CN48: =CN42+CN46 -> 21387.192
B49: EBITDA Margin (%) | D49: =D48/D9 -> 0.11097536 | E49: =E48/E9 -> 0.1680346 | F49: =F48/F9 -> 0.19556646 | G49: =G48/G9 -> 0.16369417 | H49: =H48/H9 -> 0.16138753 | J49: =J48/J9 -> 0.21689089 | K49: =K48/K9 -> 0.20362572 | L49: =L48/L9 -> 0.20969652 | M49: =M48/M9 -> 0.18017013 | N49: =N48/N9 -> 0.20209422 | P49: =P48/P9 -> 0.21149562 | Q49: =Q48/Q9 -> 0.19817073 | R49: =R48/R9 -> 0.20888854 | S49: =S48/S9 -> 0.18974437 | T49: =T48/T9 -> 0.20198885 | V49: =V48/V9 -> 0.18975082 | W49: =W48/W9 -> 0.13924177 | X49: =X48/X9 -> 0.15970044 | Y49: =Y48/Y9 -> 0.16030263 | Z49: =Z48/Z9 -> 0.1673134 | AB49: =AB48/AB9 -> 0.20190124 | AC49: =AC48/AC9 -> 0.18434324 | AD49: =AD48/AD9 -> 0.18206018 | AE49: =AE48/AE9 -> 0.15922597 | AF49: =AF48/AF9 -> 0.18108336 | AH49: =AH48/AH9 -> 0.1774965 | AI49: =AI48/AI9 -> 0.17526497 | AJ49: =AJ48/AJ9 -> 0.19847939 | AK49: =AK48/AK9 -> 0.13484365 | AL49: =AL48/AL9 -> 0.17034345 | AN49: =AN48/AN9 -> 0.20571176 | AO49: =AO48/AO9 -> 0.24217577 | AP49: =AP48/AP9 -> 0.2364069 | AQ49: =AQ48/AQ9 -> 0.21552431 | AR49: =AR48/AR9 -> 0.22532061 | AT49: =AT48/AT9 -> 0.25590227 | AU49: =AU48/AU9 -> 0.24045779 | AV49: =AV48/AV9 -> 0.22910717 | AW49: =AW48/AW9 -> 0.2212103 | AX49: =AX48/AX9 -> 0.23647512 | AZ49: =AZ48/AZ9 -> 0.24514204 | BA49: =BA48/BA9 -> 0.24321252 | BB49: =BB48/BB9 -> 0.22843399 | BC49: =BC48/BC9 -> 0.22438979 | BD49: =BD48/BD9 -> 0.23507813 | BF49: =BF48/BF9 -> 0.25175811 | BG49: =BG48/BG9 -> 0.24988297 | BH49: =BH48/BH9 -> 0.23576988 | BI49: =BI48/BI9 -> 0.23184344 | BJ49: =BJ48/BJ9 -> 0.2421068 | BL49: =BL48/BL9 -> 0.25464424 | BM49: =BM48/BM9 -> 0.25277714 | BN49: =BN48/BN9 -> 0.23924283 | BO49: =BO48/BO9 -> 0.23537905 | BP49: =BP48/BP9 -> 0.24530991 | BR49: =BR48/BR9 -> 0.25736296 | BS49: =BS48/BS9 -> 0.25551592 | BT49: =BT48/BT9 -> 0.24253216 | BU49: =BU48/BU9 -> 0.23870346 | BV49: =BV48/BV9 -> 0.24833322 | BX49: =BX48/BX9 -> 0.25995544 | BY49: =BY48/BY9 -> 0.25812767 | BZ49: =BZ48/BZ9 -> 0.24567382 | CA49: =CA48/CA9 -> 0.24187821 | CB49: =CB48/CB9 -> 0.25121867 | CD49: =CD48/CD9 -> 0.26242652 | CE49: =CE48/CE9 -> 0.26061729 | CF49: =CF48/CF9 -> 0.24867342 | CG49: =CG48/CG9 -> 0.244909 | CH49: =CH48/CH9 -> 0.25397152 | CJ49: =CJ48/CJ9 -> 0.26506698 | CK49: =CK48/CK9 -> 0.26326044 | CL49: =CL48/CL9 -> 0.25182024 | CM49: =CM48/CM9 -> 0.24807219 | CN49: =CN48/CN9 -> 0.25687459
A51: 1 | B51: ME&T Segment Summary
B52: NA | D52: =D127+D168+D209 -> 4233 | E52: =E127+E168+E209 -> 4912 | F52: =F127+F168+F209 -> 4674 | G52: =G127+G168+G209 -> 5464 | H52: =H127+H168+H209 -> 19283 | J52: =J127+J168+J209 -> 5643 | K52: =K127+K168+K209 -> 6125 | L52: =L127+L168+L209 -> 5804 | M52: =M127+M168+M209 -> 6224 | N52: =N127+N168+N209 -> 23796 | P52: =P127+P168+P209 -> 6067 | Q52: =Q127+Q168+Q209 -> 6868 | R52: =R127+R168+R209 -> 5646 | S52: =S127+S168+S209 -> 5370 | T52: =T127+T168+T209 -> 23951 | V52: =V127+V168+V209 -> 4519 | W52: =W127+W168+W209 -> 3927 | X52: =X127+X168+X209 -> 3852 | Y52: =Y127+Y168+Y209 -> 4196 | Z52: =Z127+Z168+Z209 -> 16494 | AB52: =AB127+AB168+AB209 -> 4565 | AC52: =AC127+AC168+AC209 -> 5289 | AD52: =AD127+AD168+AD209 -> 5015 | AE52: =AE127+AE168+AE209 -> 5405 | AF52: =AF127+AF168+AF209 -> 20274 | AH52: =AH127+AH168+AH209 -> 5676 | AI52: =AI127+AI168+AI209 -> 6310 | AJ52: =AJ127+AJ168+AJ209 -> 6650 | AK52: =AK127+AK168+AK209 -> 7437 | AL52: =AL127+AL168+AL209 -> 26073 | AN52: =AN127+AN168+AN209 -> 7488 | AO52: =AO127+AO168+AO209 -> 8430 | AP52: =AP127+AP168+AP209 -> 8410 | AQ52: =AQ127+AQ168+AQ209 -> 8253 | AR52: =AR127+AR168+AR209 -> 32581 | AT52: =AT127+AT168+AT209 -> 8048 | AU52: =AU127+AU168+AU209 -> 8471 | AV52: =AV127+AV168+AV209 -> 7974 | AW52: =AW127+AW168+AW209 -> 8092.5 | AX52: =SUM(AT52:AW52) -> 32585.5 | AZ52: =AZ127+AZ168+AZ209 -> 7833.4 | BA52: =BA127+BA168+BA209 -> 8406.1 | BB52: =BB127+BB168+BB209 -> 7998.49 | BC52: =BC127+BC168+BC209 -> 8319.96 | BD52: =SUM(AZ52:BC52) -> 32557.95 | BF52: =BF127+BF168+BF209 -> 8213.694 | BG52: =BG127+BG168+BG209 -> 8814.345 | BH52: =BH127+BH168+BH209 -> 8386.6521 | BI52: =BI127+BI168+BI209 -> 8724.3516 | BJ52: =SUM(BF52:BI52) -> 34139.043 | BL52: =BL127+BL168+BL209 -> 8540.104 | BM52: =BM127+BM168+BM209 -> 9167.7326 | BN52: =BN127+BN168+BN209 -> 8721.3533 | BO52: =BO127+BO168+BO209 -> 9078.7764 | BP52: =SUM(BL52:BO52) -> 35507.966 | BR52: =BR127+BR168+BR209 -> 8880.1879 | BS52: =BS127+BS168+BS209 -> 9536.0442 | BT52: =BT127+BT168+BT209 -> 9070.1282 | BU52: =BU127+BU168+BU209 -> 9448.348 | BV52: =SUM(BR52:BU52) -> 36934.708 | BX52: =BX127+BX168+BX209 -> 9234.5453 | BY52: =BY127+BY168+BY209 -> 9919.9387 | BZ52: =BZ127+BZ168+BZ209 -> 9433.5959 | CA52: =CA127+CA168+CA209 -> 9833.7416 | CB52: =SUM(BX52:CA52) -> 38421.821 | CD52: =CD127+CD168+CD209 -> 9603.8031 | CE52: =CE127+CE168+CE209 -> 10320.105 | CF52: =CF127+CF168+CF209 -> 9812.4035 | CG52: =CG127+CG168+CG209 -> 10235.664 | CH52: =SUM(CD52:CG52) -> 39971.975 | CJ52: =CJ127+CJ168+CJ209 -> 9988.6165 | CK52: =CK127+CK168+CK209 -> 10737.264 | CL52: =CL127+CL168+CL209 -> 10207.228 | CM52: =CM127+CM168+CM209 -> 10654.853 | CN52: =SUM(CJ52:CM52) -> 41587.961
B53: LATAM | D53: =D128+D169+D210 -> 794 | E53: =E128+E169+E210 -> 975 | F53: =F128+F169+F210 -> 1019 | G53: =G128+G169+G210 -> 1150 | H53: =H128+H169+H210 -> 3938 | J53: =J128+J169+J210 -> 984 | K53: =K128+K169+K210 -> 1073 | L53: =L128+L169+L210 -> 1126 | M53: =M128+M169+M210 -> 1274 | N53: =N128+N169+N210 -> 4457 | P53: =P128+P169+P210 -> 1074 | Q53: =Q128+Q169+Q210 -> 1165 | R53: =R128+R169+R210 -> 1140 | S53: =S128+S169+S210 -> 1076 | T53: =T128+T169+T210 -> 4455 | V53: =V128+V169+V210 -> 834 | W53: =W128+W169+W210 -> 679 | X53: =X128+X169+X210 -> 720 | Y53: =Y128+Y169+Y210 -> 983 | Z53: =Z128+Z169+Z210 -> 3216 | AB53: =AB128+AB169+AB210 -> 1053 | AC53: =AC128+AC169+AC210 -> 1167 | AD53: =AD128+AD169+AD210 -> 1274 | AE53: =AE128+AE169+AE210 -> 1376 | AF53: =AF128+AF169+AF210 -> 4870 | AH53: =AH128+AH169+AH210 -> 1336 | AI53: =AI128+AI169+AI210 -> 1483 | AJ53: =AJ128+AJ169+AJ210 -> 1739 | AK53: =AK128+AK169+AK210 -> 1909 | AL53: =AL128+AL169+AL210 -> 6467 | AN53: =AN128+AN169+AN210 -> 1453 | AO53: =AO128+AO169+AO210 -> 1563 | AP53: =AP128+AP169+AP210 -> 1514 | AQ53: =AQ128+AQ169+AQ210 -> 1800 | AR53: =AR128+AR169+AR210 -> 6330 | AT53: =AT128+AT169+AT210 -> 1479 | AU53: =AU128+AU169+AU210 -> 1640 | AV53: =AV128+AV169+AV210 -> 1605 | AW53: =AW128+AW169+AW210 -> 1856.75 | AX53: =SUM(AT53:AW53) -> 6580.75 | AZ53: =AZ128+AZ169+AZ210 -> 1434.8 | BA53: =BA128+BA169+BA210 -> 1584.2 | BB53: =BB128+BB169+BB210 -> 1559.12 | BC53: =BC128+BC169+BC210 -> 1806.412 | BD53: =SUM(AZ53:BC53) -> 6384.532 | BF53: =BF128+BF169+BF210 -> 1490.39 | BG53: =BG128+BG169+BG210 -> 1645.6585 | BH53: =BH128+BH169+BH210 -> 1618.4268 | BI53: =BI128+BI169+BI210 -> 1872.0121 | BJ53: =SUM(BF53:BI53) -> 6626.4874 | BL53: =BL128+BL169+BL210 -> 1542.0986 | BM53: =BM128+BM169+BM210 -> 1702.977 | BN53: =BN128+BN169+BN210 -> 1674.0043 | BO53: =BO128+BO169+BO210 -> 1933.6366 | BP53: =SUM(BL53:BO53) -> 6852.7165 | BR53: =BR128+BR169+BR210 -> 1595.7173 | BS53: =BS128+BS169+BS210 -> 1762.4181 | BT53: =BT128+BT169+BT210 -> 1731.6217 | BU53: =BU128+BU169+BU210 -> 1997.4611 | BV53: =SUM(BR53:BU53) -> 7087.2182 | BX53: =BX128+BX169+BX210 -> 1651.3195 | BY53: =BY128+BY169+BY210 -> 1824.0633 | BZ53: =BZ128+BZ169+BZ210 -> 1791.3569 | CA53: =CA128+CA169+CA210 -> 2063.5681 | CB53: =SUM(BX53:CA53) -> 7330.3078 | CD53: =CD128+CD169+CD210 -> 1708.9813 | CE53: =CE128+CE169+CE210 -> 1887.9973 | CF53: =CF128+CF169+CF210 -> 1853.2909 | CG53: =CG128+CG169+CG210 -> 2132.0435 | CH53: =SUM(CD53:CG53) -> 7582.313 | CJ53: =CJ128+CJ169+CJ210 -> 1768.7817 | CK53: =CK128+CK169+CK210 -> 1954.308 | CL53: =CL128+CL169+CL210 -> 1917.5079 | CM53: =CM128+CM169+CM210 -> 2202.9766 | CN53: =SUM(CJ53:CM53) -> 7843.5742
B54: EAME | D54: =D129+D170+D211 -> 2128 | E54: =E129+E170+E211 -> 2439 | F54: =F129+F170+F211 -> 2662 | G54: =G129+G170+G211 -> 2737 | H54: =H129+H170+H211 -> 9966 | J54: =J129+J170+J211 -> 2679 | K54: =K129+K170+K211 -> 2893 | L54: =L129+L170+L211 -> 2863 | M54: =M129+M170+M211 -> 3126 | N54: =N129+N170+N211 -> 11561 | P54: =P129+P170+P211 -> 2506 | Q54: =Q129+Q170+Q211 -> 2714 | R54: =R129+R170+R211 -> 2668 | S54: =S129+S170+S211 -> 2954 | T54: =T129+T170+T211 -> 10842 | V54: =V129+V170+V211 -> 2337 | W54: =W129+W170+W211 -> 2241 | X54: =X129+X170+X211 -> 2293 | Y54: =Y129+Y170+Y211 -> 2613 | Z54: =Z129+Z170+Z211 -> 9484 | AB54: =AB129+AB170+AB211 -> 2648 | AC54: =AC129+AC170+AC211 -> 3012 | AD54: =AD129+AD170+AD211 -> 2840 | AE54: =AE129+AE170+AE211 -> 3253 | AF54: =AF129+AF170+AF211 -> 11753 | AH54: =AH129+AH170+AH211 -> 3055 | AI54: =AI129+AI170+AI211 -> 2906 | AJ54: =AJ129+AJ170+AJ211 -> 3053 | AK54: =AK129+AK170+AK211 -> 3522 | AL54: =AL129+AL170+AL211 -> 12536 | AN54: =AN129+AN170+AN211 -> 3319 | AO54: =AO129+AO170+AO211 -> 3434 | AP54: =AP129+AP170+AP211 -> 3287 | AQ54: =AQ129+AQ170+AQ211 -> 3212 | AR54: =AR129+AR170+AR211 -> 13252 | AT54: =AT129+AT170+AT211 -> 2755 | AU54: =AU129+AU170+AU211 -> 2910 | AV54: =AV129+AV170+AV211 -> 3078 | AW54: =AW129+AW170+AW211 -> 3054.6 | AX54: =SUM(AT54:AW54) -> 11797.6 | AZ54: =AZ129+AZ170+AZ211 -> 2673.6 | BA54: =BA129+BA170+BA211 -> 2876.35 | BB54: =BB129+BB170+BB211 -> 3112.48 | BC54: =BC129+BC170+BC211 -> 3101.715 | BD54: =SUM(AZ54:BC54) -> 11764.145 | BF54: =BF129+BF170+BF211 -> 2803.095 | BG54: =BG129+BG170+BG211 -> 3015.7475 | BH54: =BH129+BH170+BH211 -> 3263.5072 | BI54: =BI129+BI170+BI211 -> 3252.6355 | BJ54: =SUM(BF54:BI54) -> 12334.985 | BL54: =BL129+BL170+BL211 -> 2929.4852 | BM54: =BM129+BM170+BM211 -> 3152.0439 | BN54: =BN129+BN170+BN211 -> 3410.4306 | BO54: =BO129+BO170+BO211 -> 3400.7999 | BP54: =SUM(BL54:BO54) -> 12892.76 | BR54: =BR129+BR170+BR211 -> 3061.6442 | BS54: =BS129+BS170+BS211 -> 3294.5755 | BT54: =BT129+BT170+BT211 -> 3564.0502 | BU54: =BU129+BU170+BU211 -> 3555.7938 | BV54: =SUM(BR54:BU54) -> 13476.064 | BX54: =BX129+BX170+BX211 -> 3199.8386 | BY54: =BY129+BY170+BY211 -> 3443.6309 | BZ54: =BZ129+BZ170+BZ211 -> 3724.6746 | CA54: =CA129+CA170+CA211 -> 3717.9356 | CB54: =SUM(BX54:CA54) -> 14086.08 | CD54: =CD129+CD170+CD211 -> 3344.3473 | CE54: =CE129+CE170+CE211 -> 3599.5121 | CF54: =CF129+CF170+CF211 -> 3892.6271 | CG54: =CG129+CG170+CG211 -> 3887.5585 | CH54: =SUM(CD54:CG54) -> 14724.045 | CJ54: =CJ129+CJ170+CJ211 -> 3495.462 | CK54: =CK129+CK170+CK211 -> 3762.5353 | CL54: =CL129+CL170+CL211 -> 4068.246 | CM54: =CM129+CM170+CM211 -> 4065.0116 | CN54: =SUM(CJ54:CM54) -> 15391.255
B55: APAC | D55: =D130+D171+D212 -> 1962 | E55: =E130+E171+E212 -> 2304 | F55: =F130+F171+F212 -> 2330 | G55: =G130+G171+G212 -> 2818 | H55: =H130+H171+H212 -> 9414 | J55: =J130+J171+J212 -> 2837 | K55: =K130+K171+K212 -> 3191 | L55: =L130+L171+L212 -> 2976 | M55: =M130+M171+M212 -> 3018 | N55: =N130+N171+N212 -> 12022 | P55: =P130+P171+P212 -> 3085 | Q55: =Q130+Q171+Q212 -> 2934 | R55: =R130+R171+R212 -> 2562 | S55: =S130+S171+S212 -> 3025 | T55: =T130+T171+T212 -> 11606 | V55: =V130+V171+V212 -> 2219 | W55: =W130+W171+W212 -> 2436 | X55: =X130+X171+X212 -> 2362 | Y55: =Y130+Y171+Y212 -> 2775 | Z55: =Z130+Z171+Z212 -> 9792 | AB55: =AB130+AB171+AB212 -> 2930 | AC55: =AC130+AC171+AC212 -> 2726 | AD55: =AD130+AD171+AD212 -> 2564 | AE55: =AE130+AE171+AE212 -> 3049 | AF55: =AF130+AF171+AF212 -> 11269 | AH55: =AH130+AH171+AH212 -> 2810 | AI55: =AI130+AI171+AI212 -> 2827 | AJ55: =AJ130+AJ171+AJ212 -> 2804 | AK55: =AK130+AK171+AK212 -> 2960 | AL55: =AL130+AL171+AL212 -> 11401 | AN55: =AN130+AN171+AN212 -> 2858 | AO55: =AO130+AO171+AO212 -> 3124 | AP55: =AP130+AP171+AP212 -> 2784 | AQ55: =AQ130+AQ171+AQ212 -> 2964 | AR55: =AR130+AR171+AR212 -> 11730 | AT55: =AT130+AT171+AT212 -> 2718 | AU55: =AU130+AU171+AU212 -> 2837 | AV55: =AV130+AV171+AV212 -> 2594 | AW55: =AW130+AW171+AW212 -> 2808.75 | AX55: =SUM(AT55:AW55) -> 10957.75 | AZ55: =AZ130+AZ171+AZ212 -> 2571.3 | BA55: =BA130+BA171+BA212 -> 2690.1 | BB55: =BB130+BB171+BB212 -> 2593.05 | BC55: =BC130+BC171+BC212 -> 2807.115 | BD55: =SUM(AZ55:BC55) -> 10661.565 | BF55: =BF130+BF171+BF212 -> 2691.846 | BG55: =BG130+BG171+BG212 -> 2816.055 | BH55: =BH130+BH171+BH212 -> 2714.0725 | BI55: =BI130+BI171+BI212 -> 2938.5503 | BJ55: =SUM(BF55:BI55) -> 11160.524 | BL55: =BL130+BL171+BL212 -> 2808.7147 | BM55: =BM130+BM171+BM212 -> 2938.752 | BN55: =BN130+BN171+BN212 -> 2832.0728 | BO55: =BO130+BO171+BO212 -> 3066.4778 | BP55: =SUM(BL55:BO55) -> 11646.017 | BR55: =BR130+BR171+BR212 -> 2930.7179 | BS55: =BS130+BS171+BS212 -> 3066.8596 | BT55: =BT130+BT171+BT212 -> 2955.265 | BU55: =BU130+BU171+BU212 -> 3200.0417 | BV55: =SUM(BR55:BU55) -> 12152.884 | BX55: =BX130+BX171+BX212 -> 3058.0839 | BY55: =BY130+BY171+BY212 -> 3200.6194 | BZ55: =BZ130+BZ171+BZ212 -> 3083.8803 | CA55: =CA130+CA171+CA212 -> 3339.4935 | CB55: =SUM(BX55:CA55) -> 12682.077 | CD55: =CD130+CD171+CD212 -> 3191.0515 | CE55: =CE130+CE171+CE212 -> 3340.2839 | CF55: =CF130+CF171+CF212 -> 3218.1605 | CG55: =CG130+CG171+CG212 -> 3485.0958 | CH55: =SUM(CD55:CG55) -> 13234.592 | CJ55: =CJ130+CJ171+CJ212 -> 3329.8699 | CK55: =CK130+CK171+CK212 -> 3486.1169 | CL55: =CL130+CL171+CL212 -> 3358.3581 | CM55: =CM130+CM171+CM212 -> 3637.1233 | CN55: =SUM(CJ55:CM55) -> 13811.468
B56: All other, Corporate, & Eliminations | D56: =D57-SUM(D52:D55) -> 13 | E56: =E57-SUM(E52:E55) -> 9 | F56: =F57-SUM(F52:F55) -> 28 | G56: =G57-SUM(G52:G55) -> 25 | H56: =H57-SUM(H52:H55) -> 75 | J56: =J57-SUM(J52:J55) -> 7 | K56: =K57-SUM(K52:K55) -> -3 | L56: =L57-SUM(L52:L55) -> -6 | M56: =M57-SUM(M52:M55) -> -12 | N56: =N57-SUM(N52:N55) -> -14 | P56: =P57-SUM(P52:P55) -> -8 | Q56: =Q57-SUM(Q52:Q55) -> -10 | R56: =R57-SUM(R52:R55) -> -42 | S56: =S57-SUM(S52:S55) -> -39 | T56: =T57-SUM(T52:T55) -> -99 | V56: =V57-SUM(V52:V55) -> 5 | W56: =W57-SUM(W52:W55) -> 27 | X56: =X57-SUM(X52:X55) -> 1 | Y56: =Y57-SUM(Y52:Y55) -> 3 | Z56: =Z57-SUM(Z52:Z55) -> 36 | AB56: =AB57-SUM(AB52:AB55) -> -5 | AC56: =AC57-SUM(AC52:AC55) -> -1 | AD56: =AD57-SUM(AD52:AD55) -> 14 | AE56: =AE57-SUM(AE52:AE55) -> 14 | AF56: =AF57-SUM(AF52:AF55) -> 22 | AH56: =AH57-SUM(AH52:AH55) -> 9 | AI56: =AI57-SUM(AI52:AI55) -> 13 | AJ56: =AJ57-SUM(AJ52:AJ55) -> 32 | AK56: =AK57-SUM(AK52:AK55) -> 43 | AL56: =AL57-SUM(AL52:AL55) -> 97 | AN56: =AN57-SUM(AN52:AN55) -> -19 | AO56: =AO57-SUM(AO52:AO55) -> -6 | AP56: =AP57-SUM(AP52:AP55) -> -7 | AQ56: =AQ57-SUM(AQ52:AQ55) -> 8 | AR56: =AR57-SUM(AR52:AR55) -> -24 | AT56: =AT57-SUM(AT52:AT55) -> -40 | AU56: =AU57-SUM(AU52:AU55) -> -18 | AV56: =AV57-SUM(AV52:AV55) -> -20 | AW56: 0 | AX56: =SUM(AT56:AW56) -> -78 | AZ56: 0 | BA56: 0 | BB56: 0 | BC56: 0 | BD56: =SUM(AZ56:BC56) -> 0 | BF56: 0 | BG56: 0 | BH56: 0 | BI56: 0 | BJ56: =SUM(BF56:BI56) -> 0 | BL56: 0 | BM56: 0 | BN56: 0 | BO56: 0 | BP56: =SUM(BL56:BO56) -> 0 | BR56: 0 | BS56: 0 | BT56: 0 | BU56: 0 | BV56: =SUM(BR56:BU56) -> 0 | BX56: 0 | BY56: 0 | BZ56: 0 | CA56: 0 | CB56: =SUM(BX56:CA56) -> 0 | CD56: 0 | CE56: 0 | CF56: 0 | CG56: 0 | CH56: =SUM(CD56:CG56) -> 0 | CJ56: 0 | CK56: 0 | CL56: 0 | CM56: 0 | CN56: =SUM(CJ56:CM56) -> 0
B57: Revenue ($mm) | D57: =D7 -> 9130 | E57: =E7 -> 10639 | F57: =F7 -> 10713 | G57: =G7 -> 12194 | H57: =H7 -> 42676 | J57: =J7 -> 12150 | K57: =K7 -> 13279 | L57: =L7 -> 12763 | M57: =M7 -> 13630 | N57: =N7 -> 51822 | P57: =P7 -> 12724 | Q57: =Q7 -> 13671 | R57: =R7 -> 11974 | S57: =S7 -> 12386 | T57: =T7 -> 50755 | V57: =V7 -> 9914 | W57: =W7 -> 9310 | X57: =X7 -> 9228 | Y57: =Y7 -> 10570 | Z57: =Z7 -> 39022 | AB57: =AB7 -> 11191 | AC57: =AC7 -> 12193 | AD57: =AD7 -> 11707 | AE57: =AE7 -> 13097 | AF57: =AF7 -> 48188 | AH57: =AH7 -> 12886 | AI57: =AI7 -> 13539 | AJ57: =AJ7 -> 14278 | AK57: =AK7 -> 15871 | AL57: =AL7 -> 56574 | AN57: =AN7 -> 15099 | AO57: =AO7 -> 16545 | AP57: =AP7 -> 15988 | AQ57: =AQ7 -> 16237 | AR57: =AR7 -> 63869 | AT57: =AT7 -> 14960 | AU57: =AU7 -> 15840 | AV57: =AV7 -> 15231 | AW57: =SUM(AW52:AW56) -> 15812.6 | AX57: =SUM(AX52:AX56) -> 61843.6 | AZ57: =SUM(AZ52:AZ56) -> 14513.1 | BA57: =SUM(BA52:BA56) -> 15556.75 | BB57: =SUM(BB52:BB56) -> 15263.14 | BC57: =SUM(BC52:BC56) -> 16035.202 | BD57: =SUM(BD52:BD56) -> 61368.192 | BF57: =SUM(BF52:BF56) -> 15199.025 | BG57: =SUM(BG52:BG56) -> 16291.806 | BH57: =SUM(BH52:BH56) -> 15982.659 | BI57: =SUM(BI52:BI56) -> 16787.549 | BJ57: =SUM(BJ52:BJ56) -> 64261.039 | BL57: =SUM(BL52:BL56) -> 15820.402 | BM57: =SUM(BM52:BM56) -> 16961.505 | BN57: =SUM(BN52:BN56) -> 16637.861 | BO57: =SUM(BO52:BO56) -> 17479.691 | BP57: =SUM(BP52:BP56) -> 66899.46 | BR57: =SUM(BR52:BR56) -> 16468.267 | BS57: =SUM(BS52:BS56) -> 17659.897 | BT57: =SUM(BT52:BT56) -> 17321.065 | BU57: =SUM(BU52:BU56) -> 18201.645 | BV57: =SUM(BV52:BV56) -> 69650.874 | BX57: =SUM(BX52:BX56) -> 17143.787 | BY57: =SUM(BY52:BY56) -> 18388.252 | BZ57: =SUM(BZ52:BZ56) -> 18033.508 | CA57: =SUM(CA52:CA56) -> 18954.739 | CB57: =SUM(CB52:CB56) -> 72520.286 | CD57: =SUM(CD52:CD56) -> 17848.183 | CE57: =SUM(CE52:CE56) -> 19147.898 | CF57: =SUM(CF52:CF56) -> 18776.482 | CG57: =SUM(CG52:CG56) -> 19740.361 | CH57: =SUM(CH52:CH56) -> 75512.925 | CJ57: =SUM(CJ52:CJ56) -> 18582.73 | CK57: =SUM(CK52:CK56) -> 19940.224 | CL57: =SUM(CL52:CL56) -> 19551.34 | CM57: =SUM(CM52:CM56) -> 20559.965 | CN57: =SUM(CN52:CN56) -> 78634.258
B58: Growth YoY (%) | J58: =J57/D57-1 -> 0.33077766 | K58: =K57/E57-1 -> 0.24814362 | L58: =L57/F57-1 -> 0.1913563 | M58: =M57/G57-1 -> 0.11776283 | N58: =N57/H57-1 -> 0.21431249 | P58: =P57/J57-1 -> 0.047242798 | Q58: =Q57/K57-1 -> 0.029520295 | R58: =R57/L57-1 -> -0.061819321 | S58: =S57/M57-1 -> -0.091269259 | T58: =T57/N57-1 -> -0.020589711 | V58: =V57/P57-1 -> -0.2208425 | W58: =W57/Q57-1 -> -0.31899642 | X58: =X57/R57-1 -> -0.22933022 | Y58: =Y57/S57-1 -> -0.14661715 | Z58: =Z57/T57-1 -> -0.23116934 | AB58: =AB57/V57-1 -> 0.12880775 | AC58: =AC57/W57-1 -> 0.30966702 | AD58: =AD57/X57-1 -> 0.26863893 | AE58: =AE57/Y57-1 -> 0.23907285 | AF58: =AF57/Z57-1 -> 0.23489314 | AH58: =AH57/AB57-1 -> 0.151461 | AI58: =AI57/AC57-1 -> 0.11039121 | AJ58: =AJ57/AD57-1 -> 0.2196122 | AK58: =AK57/AE57-1 -> 0.21180423 | AL58: =AL57/AF57-1 -> 0.17402673 | AN58: =AN57/AH57-1 -> 0.17173677 | AO58: =AO57/AI57-1 -> 0.22202526 | AP58: =AP57/AJ57-1 -> 0.11976467 | AQ58: =AQ57/AK57-1 -> 0.023060929 | AR58: =AR57/AL57-1 -> 0.12894616 | AT58: =AT57/AN57-1 -> -0.0092059077 | AU58: =AU57/AO57-1 -> -0.042611061 | AV58: =AV57/AP57-1 -> -0.047348011 | AW58: =AW57/AQ57-1 -> -0.026137833 | AX58: =AX57/AR57-1 -> -0.031711785 | AZ58: =AZ57/AT57-1 -> -0.029872995 | BA58: =BA57/AU57-1 -> -0.017881944 | BB58: =BB57/AV57-1 -> 0.00211017 | BC58: =BC57/AW57-1 -> 0.014077508 | BD58: =BD57/AX57-1 -> -0.0076872627 | BF58: =BF57/AZ57-1 -> 0.047262473 | BG58: =BG57/BA57-1 -> 0.047249972 | BH58: =BH57/BB57-1 -> 0.047140929 | BI58: =BI57/BC57-1 -> 0.046918491 | BJ58: =BJ57/BD57-1 -> 0.047139194 | BL58: =BL57/BF57-1 -> 0.040882712 | BM58: =BM57/BG57-1 -> 0.041106523 | BN58: =BN57/BH57-1 -> 0.04099458 | BO58: =BO57/BI57-1 -> 0.041229443 | BP58: =BP57/BJ57-1 -> 0.041057857 | BR58: =BR57/BL57-1 -> 0.040951229 | BS58: =BS57/BM57-1 -> 0.041175115 | BT58: =BT57/BN57-1 -> 0.041063214 | BU58: =BU57/BO57-1 -> 0.041302438 | BV58: =BV57/BP57-1 -> 0.041127608 | BX58: =BX57/BR57-1 -> 0.0410195 | BY58: =BY57/BS57-1 -> 0.041243436 | BZ58: =BZ57/BT57-1 -> 0.041131574 | CA58: =CA57/BU57-1 -> 0.041375056 | CB58: =CB57/BV57-1 -> 0.041197066 | CD58: =CD57/BX57-1 -> 0.04108752 | CE58: =CE57/BY57-1 -> 0.041311483 | CF58: =CF57/BZ57-1 -> 0.041199658 | CG58: =CG57/CA57-1 -> 0.041447296 | CH58: =CH57/CB57-1 -> 0.041266228 | CJ58: =CJ57/CD57-1 -> 0.041155287 | CK58: =CK57/CE57-1 -> 0.04137925 | CL58: =CL57/CF57-1 -> 0.041267461 | CM58: =CM57/CG57-1 -> 0.041519155 | CN58: =CN57/CH57-1 -> 0.041335091
B59: Growth YoY ($mm) | J59: =J57-D57 -> 3020 | K59: =K57-E57 -> 2640 | L59: =L57-F57 -> 2050 | M59: =M57-G57 -> 1436 | N59: =N57-H57 -> 9146 | P59: =P57-J57 -> 574 | Q59: =Q57-K57 -> 392 | R59: =R57-L57 -> -789 | S59: =S57-M57 -> -1244 | T59: =T57-N57 -> -1067 | V59: =V57-P57 -> -2810 | W59: =W57-Q57 -> -4361 | X59: =X57-R57 -> -2746 | Y59: =Y57-S57 -> -1816 | Z59: =Z57-T57 -> -11733 | AB59: =AB57-V57 -> 1277 | AC59: =AC57-W57 -> 2883 | AD59: =AD57-X57 -> 2479 | AE59: =AE57-Y57 -> 2527 | AF59: =AF57-Z57 -> 9166 | AH59: =AH57-AB57 -> 1695 | AI59: =AI57-AC57 -> 1346 | AJ59: =AJ57-AD57 -> 2571 | AK59: =AK57-AE57 -> 2774 | AL59: =AL57-AF57 -> 8386 | AN59: =AN57-AH57 -> 2213 | AO59: =AO57-AI57 -> 3006 | AP59: =AP57-AJ57 -> 1710 | AQ59: =AQ57-AK57 -> 366 | AR59: =AR57-AL57 -> 7295 | AT59: =AT57-AN57 -> -139 | AU59: =AU57-AO57 -> -705 | AV59: =AV57-AP57 -> -757 | AW59: =AW57-AQ57 -> -424.4 | AX59: =AX57-AR57 -> -2025.4 | AZ59: =AZ57-AT57 -> -446.9 | BA59: =BA57-AU57 -> -283.25 | BB59: =BB57-AV57 -> 32.14 | BC59: =BC57-AW57 -> 222.602 | BD59: =BD57-AX57 -> -475.408 | BF59: =BF57-AZ57 -> 685.925 | BG59: =BG57-BA57 -> 735.056 | BH59: =BH57-BB57 -> 719.5186 | BI59: =BI57-BC57 -> 752.34748 | BJ59: =BJ57-BD57 -> 2892.8471 | BL59: =BL57-BF57 -> 621.37736 | BM59: =BM57-BG57 -> 669.6995 | BN59: =BN57-BH57 -> 655.20237 | BO59: =BO57-BI57 -> 692.14132 | BP59: =BP57-BJ57 -> 2638.4205 | BR59: =BR57-BL57 -> 647.86492 | BS59: =BS57-BM57 -> 698.39195 | BT59: =BT57-BN57 -> 683.20404 | BU59: =BU57-BO57 -> 721.95384 | BV59: =BV57-BP57 -> 2751.4147 | BX59: =BX57-BR57 -> 675.52008 | BY59: =BY57-BS57 -> 728.35486 | BZ59: =BZ57-BT57 -> 712.44267 | CA59: =CA57-BU57 -> 753.09407 | CB59: =CB57-BV57 -> 2869.4117 | CD59: =CD57-BX57 -> 704.39571 | CE59: =CE57-BY57 -> 759.64596 | CF59: =CF57-BZ57 -> 742.97434 | CG59: =CG57-CA57 -> 785.62267 | CH59: =CH57-CB57 -> 2992.6387 | CJ59: =CJ57-CD57 -> 734.54709 | CK59: =CK57-CE57 -> 792.32567 | CL59: =CL57-CF57 -> 774.85775 | CM59: =CM57-CG57 -> 819.60313 | CN59: =CN57-CH57 -> 3121.3336
B60: Growth QoQ (%) | J60: =J57/G57-1 -> -0.003608332 | K60: =K57/J57-1 -> 0.092921811 | L60: =L57/K57-1 -> -0.038858348 | M60: =M57/L57-1 -> 0.067930737 | N60: =AVERAGE(J60:M60) -> 0.029596467 | P60: =P57/M57-1 -> -0.06647102 | Q60: =Q57/P57-1 -> 0.074426281 | R60: =R57/Q57-1 -> -0.12413137 | S60: =S57/R57-1 -> 0.034407884 | T60: =AVERAGE(P60:S60) -> -0.020442057 | V60: =V57/S57-1 -> -0.19958017 | W60: =W57/V57-1 -> -0.060923946 | X60: =X57/W57-1 -> -0.0088077336 | Y60: =Y57/X57-1 -> 0.14542696 | Z60: =AVERAGE(V60:Y60) -> -0.030971222 | AB60: =AB57/Y57-1 -> 0.058751183 | AC60: =AC57/AB57-1 -> 0.089536234 | AD60: =AD57/AC57-1 -> -0.039858935 | AE60: =AE57/AD57-1 -> 0.11873238 | AF60: =AVERAGE(AB60:AE60) -> 0.056790216 | AH60: =AH57/AE57-1 -> -0.01611056 | AI60: =AI57/AH57-1 -> 0.050675151 | AJ60: =AJ57/AI57-1 -> 0.054583056 | AK60: =AK57/AJ57-1 -> 0.11157025 | AL60: =AVERAGE(AH60:AK60) -> 0.050179474 | AN60: =AN57/AK57-1 -> -0.048642178 | AO60: =AO57/AN57-1 -> 0.095767932 | AP60: =AP57/AO57-1 -> -0.03366576 | AQ60: =AQ57/AP57-1 -> 0.015574181 | AR60: =AVERAGE(AN60:AQ60) -> 0.0072585437 | AT60: =AT57/AQ57-1 -> -0.078647533 | AU60: =AU57/AT57-1 -> 0.058823529 | AV60: =AV57/AU57-1 -> -0.03844697 | AW60: =AW57/AV57-1 -> 0.03818528 | AX60: =AVERAGE(AT60:AW60) -> -0.0050214234 | AZ60: =AZ57/AW57-1 -> -0.082181298 | BA60: =BA57/AZ57-1 -> 0.071910894 | BB60: =BB57/BA57-1 -> -0.018873479 | BC60: =BC57/BB57-1 -> 0.050583432 | BD60: =AVERAGE(AZ60:BC60) -> 0.005359887 | BF60: =BF57/BC57-1 -> -0.052146334 | BG60: =BG57/BF57-1 -> 0.071898099 | BH60: =BH57/BG57-1 -> -0.018975637 | BI60: =BI57/BH57-1 -> 0.050360262 | BJ60: =AVERAGE(BF60:BI60) -> 0.012784097 | BL60: =BL57/BI57-1 -> -0.057610977 | BM60: =BM57/BL57-1 -> 0.072128579 | BN60: =BN57/BM57-1 -> -0.01908112 | BO60: =BO57/BN57-1 -> 0.050597239 | BP60: =AVERAGE(BL60:BO60) -> 0.01150843 | BR60: =BR57/BO57-1 -> -0.057862781 | BS60: =BS57/BR57-1 -> 0.07235917 | BT60: =BT57/BS57-1 -> -0.019186546 | BU60: =BU57/BT57-1 -> 0.050838654 | BV60: =AVERAGE(BR60:BU60) -> 0.011537124 | BX60: =BX57/BU57-1 -> -0.058118774 | BY60: =BY57/BX57-1 -> 0.072589849 | BZ60: =BZ57/BY57-1 -> -0.019291916 | CA60: =CA57/BZ57-1 -> 0.051084406 | CB60: =AVERAGE(BX60:CA60) -> 0.011565891 | CD60: =CD57/CA57-1 -> -0.058378839 | CE60: =CE57/CD57-1 -> 0.072820588 | CF60: =CF57/CE57-1 -> -0.019397233 | CG60: =CG57/CF57-1 -> 0.051334396 | CH60: =AVERAGE(CD60:CG60) -> 0.011594728 | CJ60: =CJ57/CG57-1 -> -0.058642859 | CK60: =CK57/CJ57-1 -> 0.073051364 | CL60: =CL57/CK57-1 -> -0.019502498 | CM60: =CM57/CL57-1 -> 0.051588523 | CN60: =AVERAGE(CJ60:CM60) -> 0.011623633
B61: Growth QoQ ($mm) | J61: =J57-G57 -> -44 | K61: =K57-J57 -> 1129 | L61: =L57-K57 -> -516 | M61: =M57-L57 -> 867 | N61: =AVERAGE(J61:M61) -> 359 | P61: =P57-M57 -> -906 | Q61: =Q57-P57 -> 947 | R61: =R57-Q57 -> -1697 | S61: =S57-R57 -> 412 | T61: =AVERAGE(P61:S61) -> -311 | V61: =V57-S57 -> -2472 | W61: =W57-V57 -> -604 | X61: =X57-W57 -> -82 | Y61: =Y57-X57 -> 1342 | Z61: =AVERAGE(V61:Y61) -> -454 | AB61: =AB57-Y57 -> 621 | AC61: =AC57-AB57 -> 1002 | AD61: =AD57-AC57 -> -486 | AE61: =AE57-AD57 -> 1390 | AF61: =AVERAGE(AB61:AE61) -> 631.75 | AH61: =AH57-AE57 -> -211 | AI61: =AI57-AH57 -> 653 | AJ61: =AJ57-AI57 -> 739 | AK61: =AK57-AJ57 -> 1593 | AL61: =AVERAGE(AH61:AK61) -> 693.5 | AN61: =AN57-AK57 -> -772 | AO61: =AO57-AN57 -> 1446 | AP61: =AP57-AO57 -> -557 | AQ61: =AQ57-AP57 -> 249 | AR61: =AVERAGE(AN61:AQ61) -> 91.5 | AT61: =AT57-AQ57 -> -1277 | AU61: =AU57-AT57 -> 880 | AV61: =AV57-AU57 -> -609 | AW61: =AW57-AV57 -> 581.6 | AX61: =AVERAGE(AT61:AW61) -> -106.1 | AZ61: =AZ57-AW57 -> -1299.5 | BA61: =BA57-AZ57 -> 1043.65 | BB61: =BB57-BA57 -> -293.61 | BC61: =BC57-BB57 -> 772.062 | BD61: =AVERAGE(AZ61:BC61) -> 55.6505 | BF61: =BF57-BC57 -> -836.177 | BG61: =BG57-BF57 -> 1092.781 | BH61: =BH57-BG57 -> -309.1474 | BI61: =BI57-BH57 -> 804.89088 | BJ61: =AVERAGE(BF61:BI61) -> 188.08687 | BL61: =BL57-BI57 -> -967.14712 | BM61: =BM57-BL57 -> 1141.1031 | BN61: =BN57-BM57 -> -323.64453 | BO61: =BO57-BN57 -> 841.82983 | BP61: =AVERAGE(BL61:BO61) -> 173.03533 | BR61: =BR57-BO57 -> -1011.4235 | BS61: =BS57-BR57 -> 1191.6302 | BT61: =BT57-BS57 -> -338.83243 | BU61: =BU57-BT57 -> 880.57963 | BV61: =AVERAGE(BR61:BU61) -> 180.48846 | BX61: =BX57-BU57 -> -1057.8573 | BY61: =BY57-BX57 -> 1244.4649 | BZ61: =BZ57-BY57 -> -354.74462 | CA61: =CA57-BZ57 -> 921.23103 | CB61: =AVERAGE(BX61:CA61) -> 188.27352 | CD61: =CD57-CA57 -> -1106.5556 | CE61: =CE57-CD57 -> 1299.7152 | CF61: =CF57-CE57 -> -371.41624 | CG61: =CG57-CF57 -> 963.87936 | CH61: =AVERAGE(CD61:CG61) -> 196.40567 | CJ61: =CJ57-CG57 -> -1157.6312 | CK61: =CK57-CJ57 -> 1357.4938 | CL61: =CL57-CK57 -> -388.88417 | CM61: =CM57-CL57 -> 1008.6247 | CN61: =AVERAGE(CJ61:CM61) -> 204.90078
B63: Regional Revenue Growth YoY (%)
B64: NA | J64: =J52/D52-1 -> 0.33309709 | K64: =K52/E52-1 -> 0.24694625 | L64: =L52/F52-1 -> 0.24176294 | M64: =M52/G52-1 -> 0.13909224 | N64: =N52/H52-1 -> 0.23404035 | P64: =P52/J52-1 -> 0.075137338 | Q64: =Q52/K52-1 -> 0.12130612 | R64: =R52/L52-1 -> -0.027222605 | S64: =S52/M52-1 -> -0.1372108 | T64: =T52/N52-1 -> 0.0065136998 | V64: =V52/P52-1 -> -0.25515082 | W64: =W52/Q52-1 -> -0.42821782 | X64: =X52/R52-1 -> -0.31774708 | Y64: =Y52/S52-1 -> -0.21862197 | Z64: =Z52/T52-1 -> -0.31134399 | AB64: =AB52/V52-1 -> 0.010179243 | AC64: =AC52/W52-1 -> 0.34682964 | AD64: =AD52/X52-1 -> 0.30192108 | AE64: =AE52/Y52-1 -> 0.28813155 | AF64: =AF52/Z52-1 -> 0.22917425 | AH64: =AH52/AB52-1 -> 0.24337349 | AI64: =AI52/AC52-1 -> 0.19304216 | AJ64: =AJ52/AD52-1 -> 0.32602193 | AK64: =AK52/AE52-1 -> 0.3759482 | AL64: =AL52/AF52-1 -> 0.28603137 | AN64: =AN52/AH52-1 -> 0.3192389 | AO64: =AO52/AI52-1 -> 0.33597464 | AP64: =AP52/AJ52-1 -> 0.26466165 | AQ64: =AQ52/AK52-1 -> 0.10972166 | AR64: =AR52/AL52-1 -> 0.24960687 | AT64: =AT52/AN52-1 -> 0.074786325 | AU64: =AU52/AO52-1 -> 0.0048635824 | AV64: =AV52/AP52-1 -> -0.051843044 | AW64: =AW52/AQ52-1 -> -0.019447474 | AX64: =AX52/AR52-1 -> 0.00013811731 | AZ64: =AZ52/AT52-1 -> -0.02666501 | BA64: =BA52/AU52-1 -> -0.0076614331 | BB64: =BB52/AV52-1 -> 0.0030712315 | BC64: =BC52/AW52-1 -> 0.028107507 | BD64: =BD52/AX52-1 -> -0.00084546808 | BF64: =BF52/AZ52-1 -> 0.048547757 | BG64: =BG52/BA52-1 -> 0.048565328 | BH64: =BH52/BB52-1 -> 0.048529422 | BI64: =BI52/BC52-1 -> 0.048604993 | BJ64: =BJ52/BD52-1 -> 0.048562416 | BL64: =BL52/BF52-1 -> 0.039739727 | BM64: =BM52/BG52-1 -> 0.040092321 | BN64: =BN52/BH52-1 -> 0.039908793 | BO64: =BO52/BI52-1 -> 0.040624775 | BP64: =BP52/BJ52-1 -> 0.040098473 | BR64: =BR52/BL52-1 -> 0.039821987 | BS64: =BS52/BM52-1 -> 0.040174777 | BT64: =BT52/BN52-1 -> 0.03999092 | BU64: =BU52/BO52-1 -> 0.040707201 | BV64: =BV52/BP52-1 -> 0.0401809 | BX64: =BX52/BR52-1 -> 0.039904271 | BY64: =BY52/BS52-1 -> 0.040257207 | BZ64: =BZ52/BT52-1 -> 0.040073049 | CA64: =CA52/BU52-1 -> 0.040789522 | CB64: =CB52/BV52-1 -> 0.040263299 | CD64: =CD52/BX52-1 -> 0.039986567 | CE64: =CE52/BY52-1 -> 0.040339598 | CF64: =CF52/BZ52-1 -> 0.040155165 | CG64: =CG52/CA52-1 -> 0.040871728 | CH64: =CH52/CB52-1 -> 0.040345659 | CJ64: =CJ52/CD52-1 -> 0.040068865 | CK64: =CK52/CE52-1 -> 0.040421939 | CL64: =CL52/CF52-1 -> 0.040237258 | CM64: =CM52/CG52-1 -> 0.040953806 | CN64: =CN52/CH52-1 -> 0.040427968
B65: LATAM | J65: =J53/D53-1 -> 0.23929471 | K65: =K53/E53-1 -> 0.10051282 | L65: =L53/F53-1 -> 0.10500491 | M65: =M53/G53-1 -> 0.10782609 | N65: =N53/H53-1 -> 0.13179279 | P65: =P53/J53-1 -> 0.091463415 | Q65: =Q53/K53-1 -> 0.085740913 | R65: =R53/L53-1 -> 0.012433393 | S65: =S53/M53-1 -> -0.15541601 | T65: =T53/N53-1 -> -0.00044873233 | V65: =V53/P53-1 -> -0.22346369 | W65: =W53/Q53-1 -> -0.41716738 | X65: =X53/R53-1 -> -0.36842105 | Y65: =Y53/S53-1 -> -0.086431227 | Z65: =Z53/T53-1 -> -0.27811448 | AB65: =AB53/V53-1 -> 0.26258993 | AC65: =AC53/W53-1 -> 0.71870398 | AD65: =AD53/X53-1 -> 0.76944444 | AE65: =AE53/Y53-1 -> 0.39979654 | AF65: =AF53/Z53-1 -> 0.51430348 | AH65: =AH53/AB53-1 -> 0.26875594 | AI65: =AI53/AC53-1 -> 0.27077978 | AJ65: =AJ53/AD53-1 -> 0.36499215 | AK65: =AK53/AE53-1 -> 0.38735465 | AL65: =AL53/AF53-1 -> 0.32792608 | AN65: =AN53/AH53-1 -> 0.08757485 | AO65: =AO53/AI53-1 -> 0.053944707 | AP65: =AP53/AJ53-1 -> -0.1293847 | AQ65: =AQ53/AK53-1 -> -0.057097957 | AR65: =AR53/AL53-1 -> -0.021184475 | AT65: =AT53/AN53-1 -> 0.017894012 | AU65: =AU53/AO53-1 -> 0.049264235 | AV65: =AV53/AP53-1 -> 0.06010568 | AW65: =AW53/AQ53-1 -> 0.031527778 | AX65: =AX53/AR53-1 -> 0.039612954 | AZ65: =AZ53/AT53-1 -> -0.029885057 | BA65: =BA53/AU53-1 -> -0.03402439 | BB65: =BB53/AV53-1 -> -0.02858567 | BC65: =BC53/AW53-1 -> -0.027110812 | BD65: =BD53/AX53-1 -> -0.029816966 | BF65: =BF53/AZ53-1 -> 0.038744076 | BG65: =BG53/BA53-1 -> 0.03879466 | BH65: =BH53/BB53-1 -> 0.038038637 | BI65: =BI53/BC53-1 -> 0.036315126 | BJ65: =BJ53/BD53-1 -> 0.037897121 | BL65: =BL53/BF53-1 -> 0.03469465 | BM65: =BM53/BG53-1 -> 0.034830142 | BN65: =BN53/BH53-1 -> 0.03434043 | BO65: =BO53/BI53-1 -> 0.032918892 | BP65: =BP53/BJ53-1 -> 0.034140126 | BR65: =BR53/BL53-1 -> 0.034769997 | BS65: =BS53/BM53-1 -> 0.034904232 | BT65: =BT53/BN53-1 -> 0.034418896 | BU65: =BU53/BO53-1 -> 0.033007456 | BV65: =BV53/BP53-1 -> 0.03422025 | BX65: =BX53/BR53-1 -> 0.034844648 | BY65: =BY53/BS53-1 -> 0.034977619 | BZ65: =BZ53/BT53-1 -> 0.034496692 | CA65: =CA53/BU53-1 -> 0.033095505 | CB65: =CB53/BV53-1 -> 0.03429972 | CD65: =CD53/BX53-1 -> 0.034918601 | CE65: =CE53/BY53-1 -> 0.0350503 | CF65: =CF53/BZ53-1 -> 0.034573811 | CG65: =CG53/CA53-1 -> 0.033183027 | CH65: =CH53/CB53-1 -> 0.034378529 | CJ65: =CJ53/CD53-1 -> 0.03499185 | CK65: =CK53/CE53-1 -> 0.035122272 | CL65: =CL53/CF53-1 -> 0.034650249 | CM65: =CM53/CG53-1 -> 0.033270009 | CN65: =CN53/CH53-1 -> 0.034456671
B66: EAME | J66: =J54/D54-1 -> 0.25892857 | K66: =K54/E54-1 -> 0.18614186 | L66: =L54/F54-1 -> 0.075507137 | M66: =M54/G54-1 -> 0.14212642 | N66: =N54/H54-1 -> 0.16004415 | P66: =P54/J54-1 -> -0.064576334 | Q66: =Q54/K54-1 -> -0.061873488 | R66: =R54/L54-1 -> -0.068110374 | S66: =S54/M54-1 -> -0.055022393 | T66: =T54/N54-1 -> -0.062191852 | V66: =V54/P54-1 -> -0.067438148 | W66: =W54/Q54-1 -> -0.1742815 | X66: =X54/R54-1 -> -0.14055472 | Y66: =Y54/S54-1 -> -0.1154367 | Z66: =Z54/T54-1 -> -0.12525364 | AB66: =AB54/V54-1 -> 0.13307659 | AC66: =AC54/W54-1 -> 0.34404284 | AD66: =AD54/X54-1 -> 0.23855212 | AE66: =AE54/Y54-1 -> 0.2449292 | AF66: =AF54/Z54-1 -> 0.23924504 | AH66: =AH54/AB54-1 -> 0.15370091 | AI66: =AI54/AC54-1 -> -0.035192563 | AJ66: =AJ54/AD54-1 -> 0.075 | AK66: =AK54/AE54-1 -> 0.082692899 | AL66: =AL54/AF54-1 -> 0.066621288 | AN66: =AN54/AH54-1 -> 0.086415712 | AO66: =AO54/AI54-1 -> 0.18169305 | AP66: =AP54/AJ54-1 -> 0.076645922 | AQ66: =AQ54/AK54-1 -> -0.088018171 | AR66: =AR54/AL54-1 -> 0.057115507 | AT66: =AT54/AN54-1 -> -0.1699307 | AU66: =AU54/AO54-1 -> -0.15259173 | AV66: =AV54/AP54-1 -> -0.063583815 | AW66: =AW54/AQ54-1 -> -0.049003736 | AX66: =AX54/AR54-1 -> -0.10974947 | AZ66: =AZ54/AT54-1 -> -0.029546279 | BA66: =BA54/AU54-1 -> -0.011563574 | BB66: =BB54/AV54-1 -> 0.011202079 | BC66: =BC54/AW54-1 -> 0.015424278 | BD66: =BD54/AX54-1 -> -0.0028357463 | BF66: =BF54/AZ54-1 -> 0.048434695 | BG66: =BG54/BA54-1 -> 0.04846333 | BH66: =BH54/BB54-1 -> 0.048523107 | BI66: =BI54/BC54-1 -> 0.04865713 | BJ66: =BJ54/BD54-1 -> 0.048523735 | BL66: =BL54/BF54-1 -> 0.045089499 | BM66: =BM54/BG54-1 -> 0.045194906 | BN66: =BN54/BH54-1 -> 0.045020105 | BO66: =BO54/BI54-1 -> 0.045552098 | BP66: =BP54/BJ54-1 -> 0.045218894 | BR66: =BR54/BL54-1 -> 0.045113413 | BS66: =BS54/BM54-1 -> 0.045218789 | BT66: =BT54/BN54-1 -> 0.045044028 | BU66: =BU54/BO54-1 -> 0.045575717 | BV66: =BV54/BP54-1 -> 0.045242766 | BX66: =BX54/BR54-1 -> 0.045137322 | BY66: =BY54/BS54-1 -> 0.045242661 | BZ66: =BZ54/BT54-1 -> 0.045067949 | CA66: =CA54/BU54-1 -> 0.04559931 | CB66: =CB54/BV54-1 -> 0.045266628 | CD66: =CD54/BX54-1 -> 0.045161224 | CE66: =CE54/BY54-1 -> 0.045266523 | CF66: =CF54/BZ54-1 -> 0.045091866 | CG66: =CG54/CA54-1 -> 0.045622876 | CH66: =CH54/CB54-1 -> 0.045290477 | CJ66: =CJ54/CD54-1 -> 0.045185119 | CK66: =CK54/CE54-1 -> 0.045290372 | CL66: =CL54/CF54-1 -> 0.045115779 | CM66: =CM54/CG54-1 -> 0.045646415 | CN66: =CN54/CH54-1 -> 0.045314313
B67: APAC | J67: =J55/D55-1 -> 0.4459735 | K67: =K55/E55-1 -> 0.38498264 | L67: =L55/F55-1 -> 0.27725322 | M67: =M55/G55-1 -> 0.070972321 | N67: =N55/H55-1 -> 0.2770342 | P67: =P55/J55-1 -> 0.087416285 | Q67: =Q55/K55-1 -> -0.080539016 | R67: =R55/L55-1 -> -0.1391129 | S67: =S55/M55-1 -> 0.0023194168 | T67: =T55/N55-1 -> -0.034603227 | V67: =V55/P55-1 -> -0.28071313 | W67: =W55/Q55-1 -> -0.16973415 | X67: =X55/R55-1 -> -0.078064012 | Y67: =Y55/S55-1 -> -0.082644628 | Z67: =Z55/T55-1 -> -0.15629847 | AB67: =AB55/V55-1 -> 0.3204146 | AC67: =AC55/W55-1 -> 0.11904762 | AD67: =AD55/X55-1 -> 0.085520745 | AE67: =AE55/Y55-1 -> 0.098738739 | AF67: =AF55/Z55-1 -> 0.15083742 | AH67: =AH55/AB55-1 -> -0.040955631 | AI67: =AI55/AC55-1 -> 0.037050624 | AJ67: =AJ55/AD55-1 -> 0.093603744 | AK67: =AK55/AE55-1 -> -0.029189898 | AL67: =AL55/AF55-1 -> 0.01171355 | AN67: =AN55/AH55-1 -> 0.017081851 | AO67: =AO55/AI55-1 -> 0.10505837 | AP67: =AP55/AJ55-1 -> -0.0071326676 | AQ67: =AQ55/AK55-1 -> 0.0013513514 | AR67: =AR55/AL55-1 -> 0.028857118 | AT67: =AT55/AN55-1 -> -0.048985304 | AU67: =AU55/AO55-1 -> -0.091869398 | AV67: =AV55/AP55-1 -> -0.068247126 | AW67: =AW55/AQ55-1 -> -0.052378543 | AX67: =AX55/AR55-1 -> -0.065835465 | AZ67: =AZ55/AT55-1 -> -0.05397351 | BA67: =BA55/AU55-1 -> -0.051780049 | BB67: =BB55/AV55-1 -> -0.00036622976 | BC67: =BC55/AW55-1 -> -0.00058210948 | BD67: =BD55/AX55-1 -> -0.027029728 | BF67: =BF55/AZ55-1 -> 0.046881344 | BG67: =BG55/BA55-1 -> 0.046821679 | BH67: =BH55/BB55-1 -> 0.046671873 | BI67: =BI55/BC55-1 -> 0.046822182 | BJ67: =BJ55/BD55-1 -> 0.046799766 | BL67: =BL55/BF55-1 -> 0.043415816 | BM67: =BM55/BG55-1 -> 0.043570527 | BN67: =BN55/BH55-1 -> 0.04347721 | BO67: =BO55/BI55-1 -> 0.043534243 | BP67: =BP55/BJ55-1 -> 0.043500965 | BR67: =BR55/BL55-1 -> 0.04343737 | BS67: =BS55/BM55-1 -> 0.043592525 | BT67: =BT55/BN55-1 -> 0.043498946 | BU67: =BU55/BO55-1 -> 0.043556141 | BV67: =BV55/BP55-1 -> 0.043522769 | BX67: =BX55/BR55-1 -> 0.043458989 | BY67: =BY55/BS55-1 -> 0.043614582 | BZ67: =BZ55/BT55-1 -> 0.043520745 | CA67: =CA55/BU55-1 -> 0.0435781 | CB67: =CB55/BV55-1 -> 0.043544635 | CD67: =CD55/BX55-1 -> 0.043480672 | CE67: =CE55/BY55-1 -> 0.043636698 | CF67: =CF55/BZ55-1 -> 0.043542605 | CG67: =CG55/CA55-1 -> 0.043600119 | CH67: =CH55/CB55-1 -> 0.043566562 | CJ67: =CJ55/CD55-1 -> 0.043502419 | CK67: =CK55/CE55-1 -> 0.043658872 | CL67: =CL55/CF55-1 -> 0.043564527 | CM67: =CM55/CG55-1 -> 0.043622196 | CN67: =CN55/CH55-1 -> 0.04358855
B68: Total Growth Rate | J68: =J57/D57-1 -> 0.33077766 | K68: =K57/E57-1 -> 0.24814362 | L68: =L57/F57-1 -> 0.1913563 | M68: =M57/G57-1 -> 0.11776283 | N68: =N57/H57-1 -> 0.21431249 | P68: =P57/J57-1 -> 0.047242798 | Q68: =Q57/K57-1 -> 0.029520295 | R68: =R57/L57-1 -> -0.061819321 | S68: =S57/M57-1 -> -0.091269259 | T68: =T57/N57-1 -> -0.020589711 | V68: =V57/P57-1 -> -0.2208425 | W68: =W57/Q57-1 -> -0.31899642 | X68: =X57/R57-1 -> -0.22933022 | Y68: =Y57/S57-1 -> -0.14661715 | Z68: =Z57/T57-1 -> -0.23116934 | AB68: =AB57/V57-1 -> 0.12880775 | AC68: =AC57/W57-1 -> 0.30966702 | AD68: =AD57/X57-1 -> 0.26863893 | AE68: =AE57/Y57-1 -> 0.23907285 | AF68: =AF57/Z57-1 -> 0.23489314 | AH68: =AH57/AB57-1 -> 0.151461 | AI68: =AI57/AC57-1 -> 0.11039121 | AJ68: =AJ57/AD57-1 -> 0.2196122 | AK68: =AK57/AE57-1 -> 0.21180423 | AL68: =AL57/AF57-1 -> 0.17402673 | AN68: =AN57/AH57-1 -> 0.17173677 | AO68: =AO57/AI57-1 -> 0.22202526 | AP68: =AP57/AJ57-1 -> 0.11976467 | AQ68: =AQ57/AK57-1 -> 0.023060929 | AR68: =AR57/AL57-1 -> 0.12894616 | AT68: =AT57/AN57-1 -> -0.0092059077 | AU68: =AU57/AO57-1 -> -0.042611061 | AV68: =AV57/AP57-1 -> -0.047348011 | AW68: =AW57/AQ57-1 -> -0.026137833 | AX68: =AX57/AR57-1 -> -0.031711785 | AZ68: =AZ57/AT57-1 -> -0.029872995 | BA68: =BA57/AU57-1 -> -0.017881944 | BB68: =BB57/AV57-1 -> 0.00211017 | BC68: =BC57/AW57-1 -> 0.014077508 | BD68: =BD57/AX57-1 -> -0.0076872627 | BF68: =BF57/AZ57-1 -> 0.047262473 | BG68: =BG57/BA57-1 -> 0.047249972 | BH68: =BH57/BB57-1 -> 0.047140929 | BI68: =BI57/BC57-1 -> 0.046918491 | BJ68: =BJ57/BD57-1 -> 0.047139194 | BL68: =BL57/BF57-1 -> 0.040882712 | BM68: =BM57/BG57-1 -> 0.041106523 | BN68: =BN57/BH57-1 -> 0.04099458 | BO68: =BO57/BI57-1 -> 0.041229443 | BP68: =BP57/BJ57-1 -> 0.041057857 | BR68: =BR57/BL57-1 -> 0.040951229 | BS68: =BS57/BM57-1 -> 0.041175115 | BT68: =BT57/BN57-1 -> 0.041063214 | BU68: =BU57/BO57-1 -> 0.041302438 | BV68: =BV57/BP57-1 -> 0.041127608 | BX68: =BX57/BR57-1 -> 0.0410195 | BY68: =BY57/BS57-1 -> 0.041243436 | BZ68: =BZ57/BT57-1 -> 0.041131574 | CA68: =CA57/BU57-1 -> 0.041375056 | CB68: =CB57/BV57-1 -> 0.041197066 | CD68: =CD57/BX57-1 -> 0.04108752 | CE68: =CE57/BY57-1 -> 0.041311483 | CF68: =CF57/BZ57-1 -> 0.041199658 | CG68: =CG57/CA57-1 -> 0.041447296 | CH68: =CH57/CB57-1 -> 0.041266228 | CJ68: =CJ57/CD57-1 -> 0.041155287 | CK68: =CK57/CE57-1 -> 0.04137925 | CL68: =CL57/CF57-1 -> 0.041267461 | CM68: =CM57/CG57-1 -> 0.041519155 | CN68: =CN57/CH57-1 -> 0.041335091
B70: Regional Revenue Mix (%)
B71: NA | J71: =J52/J$57 -> 0.46444444 | K71: =K52/K$57 -> 0.46125461 | L71: =L52/L$57 -> 0.45475202 | M71: =M52/M$57 -> 0.45663977 | N71: =N52/N$57 -> 0.45918722 | P71: =P52/P$57 -> 0.47681547 | Q71: =Q52/Q$57 -> 0.5023773 | R71: =R52/R$57 -> 0.47152163 | S71: =S52/S$57 -> 0.43355401 | T71: =T52/T$57 -> 0.47189439 | V71: =V52/V$57 -> 0.45582005 | W71: =W52/W$57 -> 0.42180451 | X71: =X52/X$57 -> 0.41742523 | Y71: =Y52/Y$57 -> 0.39697256 | Z71: =Z52/Z$57 -> 0.42268464 | AB71: =AB52/AB$57 -> 0.40791708 | AC71: =AC52/AC$57 -> 0.43377348 | AD71: =AD52/AD$57 -> 0.42837619 | AE71: =AE52/AE$57 -> 0.41268993 | AF71: =AF52/AF$57 -> 0.42072715 | AH71: =AH52/AH$57 -> 0.44047804 | AI71: =AI52/AI$57 -> 0.46606101 | AJ71: =AJ52/AJ$57 -> 0.46575151 | AK71: =AK52/AK$57 -> 0.46859051 | AL71: =AL52/AL$57 -> 0.46086542 | AN71: =AN52/AN$57 -> 0.49592688 | AO71: =AO52/AO$57 -> 0.50951949 | AP71: =AP52/AP$57 -> 0.52601951 | AQ71: =AQ52/AQ$57 -> 0.50828355 | AR71: =AR52/AR$57 -> 0.51012228 | AT71: =AT52/AT$57 -> 0.53796791 | AU71: =AU52/AU$57 -> 0.53478535 | AV71: =AV52/AV$57 -> 0.52353752 | AW71: =AW52/AW$57 -> 0.51177542 | AX71: =AX52/AX$57 -> 0.52690173 | AZ71: =AZ52/AZ$57 -> 0.53974685 | BA71: =BA52/BA$57 -> 0.54035065 | BB71: =BB52/BB$57 -> 0.52403961 | BC71: =BC52/BC$57 -> 0.51885595 | BD71: =BD52/BD$57 -> 0.53053461 | BF71: =BF52/BF$57 -> 0.54040927 | BG71: =BG52/BG$57 -> 0.54102934 | BH71: =BH52/BH$57 -> 0.52473448 | BI71: =BI52/BI$57 -> 0.51969179 | BJ71: =BJ52/BJ$57 -> 0.53125569 | BL71: =BL52/BL$57 -> 0.53981585 | BM71: =BM52/BM$57 -> 0.54050229 | BN71: =BN52/BN$57 -> 0.52418717 | BO71: =BO52/BO$57 -> 0.51938999 | BP71: =BP52/BP$57 -> 0.53076611 | BR71: =BR52/BR$57 -> 0.53923025 | BS71: =BS52/BS$57 -> 0.53998299 | BT71: =BT52/BT$57 -> 0.52364726 | BU71: =BU52/BU$57 -> 0.51909309 | BV71: =BV52/BV$57 -> 0.53028348 | BX71: =BX52/BX$57 -> 0.53865258 | BY71: =BY52/BY$57 -> 0.53947153 | BZ71: =BZ52/BZ$57 -> 0.52311486 | CA71: =CA52/CA$57 -> 0.51880122 | CB71: =CB52/CB$57 -> 0.52980791 | CD71: =CD52/CD$57 -> 0.53808295 | CE71: =CE52/CE$57 -> 0.53896803 | CF71: =CF52/CF$57 -> 0.52259009 | CG71: =CG52/CG$57 -> 0.5185145 | CH71: =CH52/CH$57 -> 0.52933952 | CJ71: =CJ52/CJ$57 -> 0.53752148 | CK71: =CK52/CK$57 -> 0.53847257 | CL71: =CL52/CL$57 -> 0.52207306 | CM71: =CM52/CM$57 -> 0.51823304 | CN71: =CN52/CN$57 -> 0.5288784
B72: LATAM | J72: =J53/J$57 -> 0.080987654 | K72: =K53/K$57 -> 0.080804277 | L72: =L53/L$57 -> 0.088223772 | M72: =M53/M$57 -> 0.093470286 | N72: =N53/N$57 -> 0.086005943 | P72: =P53/P$57 -> 0.084407419 | Q72: =Q53/Q$57 -> 0.085216882 | R72: =R53/R$57 -> 0.09520628 | S72: =S53/S$57 -> 0.086872275 | T72: =T53/T$57 -> 0.087774603 | V72: =V53/V$57 -> 0.084123462 | W72: =W53/W$57 -> 0.072932331 | X72: =X53/X$57 -> 0.078023407 | Y72: =Y53/Y$57 -> 0.092999054 | Z72: =Z53/Z$57 -> 0.082415048 | AB72: =AB53/AB$57 -> 0.094093468 | AC72: =AC53/AC$57 -> 0.095710654 | AD72: =AD53/AD$57 -> 0.10882378 | AE72: =AE53/AE$57 -> 0.10506223 | AF72: =AF53/AF$57 -> 0.10106251 | AH72: =AH53/AH$57 -> 0.10367841 | AI72: =AI53/AI$57 -> 0.10953542 | AJ72: =AJ53/AJ$57 -> 0.12179577 | AK72: =AK53/AK$57 -> 0.12028228 | AL72: =AL53/AL$57 -> 0.11431046 | AN72: =AN53/AN$57 -> 0.096231539 | AO72: =AO53/AO$57 -> 0.094469628 | AP72: =AP53/AP$57 -> 0.094696022 | AQ72: =AQ53/AQ$57 -> 0.11085792 | AR72: =AR53/AR$57 -> 0.099109114 | AT72: =AT53/AT$57 -> 0.098863636 | AU72: =AU53/AU$57 -> 0.10353535 | AV72: =AV53/AV$57 -> 0.10537719 | AW72: =AW53/AW$57 -> 0.11742218 | AX72: =AX53/AX$57 -> 0.10640956 | AZ72: =AZ53/AZ$57 -> 0.098862407 | BA72: =BA53/BA$57 -> 0.10183361 | BB72: =BB53/BB$57 -> 0.10214936 | BC72: =BC53/BC$57 -> 0.1126529 | BD72: =BD53/BD$57 -> 0.1040365 | BF72: =BF53/BF$57 -> 0.098058264 | BG72: =BG53/BG$57 -> 0.10101142 | BH72: =BH53/BH$57 -> 0.10126143 | BI72: =BI53/BI$57 -> 0.11151193 | BJ72: =BJ53/BJ$57 -> 0.10311827 | BL72: =BL53/BL$57 -> 0.097475306 | BM72: =BM53/BM$57 -> 0.10040247 | BN72: =BN53/BN$57 -> 0.10061415 | BO72: =BO53/BO$57 -> 0.1106219 | BP72: =BP53/BP$57 -> 0.10243306 | BR72: =BR53/BR$57 -> 0.096896492 | BS72: =BS53/BS$57 -> 0.099797755 | BT72: =BT53/BT$57 -> 0.099972008 | BU72: =BU53/BU$57 -> 0.10974069 | BV72: =BV53/BV$57 -> 0.10175347 | BX72: =BX53/BX$57 -> 0.096321746 | BY72: =BY53/BY$57 -> 0.099197209 | BZ72: =BZ53/BZ$57 -> 0.09933491 | CA72: =CA53/CA$57 -> 0.10886819 | CB72: =CB53/CB$57 -> 0.10107941 | CD72: =CD53/CD$57 -> 0.095750996 | CE72: =CE53/CE$57 -> 0.098600758 | CF72: =CF53/CF$57 -> 0.098702776 | CG72: =CG53/CG$57 -> 0.10800428 | CH72: =CH53/CH$57 -> 0.1004108 | CJ72: =CJ53/CJ$57 -> 0.095184168 | CK72: =CK53/CK$57 -> 0.098008329 | CL72: =CL53/CL$57 -> 0.098075524 | CM72: =CM53/CM$57 -> 0.10714885 | CN72: =CN53/CN$57 -> 0.099747545
B73: EAME | J73: =J54/J$57 -> 0.22049383 | K73: =K54/K$57 -> 0.21786279 | L73: =L54/L$57 -> 0.2243203 | M73: =M54/M$57 -> 0.22934703 | N73: =N54/N$57 -> 0.22309058 | P73: =P54/P$57 -> 0.19695064 | Q73: =Q54/Q$57 -> 0.19852242 | R73: =R54/R$57 -> 0.2228161 | S73: =S54/S$57 -> 0.23849508 | T73: =T54/T$57 -> 0.21361442 | V73: =V54/V$57 -> 0.23572725 | W73: =W54/W$57 -> 0.24070892 | X73: =X54/X$57 -> 0.24848288 | Y73: =Y54/Y$57 -> 0.24720908 | Z73: =Z54/Z$57 -> 0.24304239 | AB73: =AB54/AB$57 -> 0.23661871 | AC73: =AC54/AC$57 -> 0.24702698 | AD73: =AD54/AD$57 -> 0.2425899 | AE73: =AE54/AE$57 -> 0.24837749 | AF73: =AF54/AF$57 -> 0.2438989 | AH73: =AH54/AH$57 -> 0.237079 | AI73: =AI54/AI$57 -> 0.21463919 | AJ73: =AJ54/AJ$57 -> 0.21382547 | AK73: =AK54/AK$57 -> 0.22191418 | AL73: =AL54/AL$57 -> 0.22158589 | AN73: =AN54/AN$57 -> 0.21981588 | AO73: =AO54/AO$57 -> 0.20755515 | AP73: =AP54/AP$57 -> 0.20559169 | AQ73: =AQ54/AQ$57 -> 0.19781979 | AR73: =AR54/AR$57 -> 0.2074872 | AT73: =AT54/AT$57 -> 0.18415775 | AU73: =AU54/AU$57 -> 0.18371212 | AV73: =AV54/AV$57 -> 0.20208785 | AW73: =AW54/AW$57 -> 0.19317506 | AX73: =AX54/AX$57 -> 0.19076509 | AZ73: =AZ54/AZ$57 -> 0.18421977 | BA73: =BA54/BA$57 -> 0.18489402 | BB73: =BB54/BB$57 -> 0.20392134 | BC73: =BC54/BC$57 -> 0.19343161 | BD73: =BD54/BD$57 -> 0.19169776 | BF73: =BF54/BF$57 -> 0.18442597 | BG73: =BG54/BG$57 -> 0.18510824 | BH73: =BH54/BH$57 -> 0.20419051 | BI73: =BI54/BI$57 -> 0.19375285 | BJ73: =BJ54/BJ$57 -> 0.19195123 | BL73: =BL54/BL$57 -> 0.18517134 | BM73: =BM54/BM$57 -> 0.18583515 | BN73: =BN54/BN$57 -> 0.20498011 | BO73: =BO54/BO$57 -> 0.19455721 | BP73: =BP54/BP$57 -> 0.19271844 | BR73: =BR54/BR$57 -> 0.18591174 | BS73: =BS54/BS$57 -> 0.18655689 | BT73: =BT54/BT$57 -> 0.20576392 | BU73: =BU54/BU$57 -> 0.19535563 | BV73: =BV54/BV$57 -> 0.19348018 | BX73: =BX54/BX$57 -> 0.18664713 | BY73: =BY54/BY$57 -> 0.18727342 | BZ73: =BZ54/BZ$57 -> 0.20654188 | CA73: =CA54/CA$57 -> 0.19614808 | CB73: =CB54/CB$57 -> 0.19423641 | CD73: =CD54/CD$57 -> 0.18737746 | CE73: =CE54/CE$57 -> 0.18798471 | CF73: =CF54/CF$57 -> 0.20731398 | CG73: =CG54/CG$57 -> 0.19693451 | CH73: =CH54/CH$57 -> 0.19498708 | CJ73: =CJ54/CJ$57 -> 0.18810272 | CK73: =CK54/CK$57 -> 0.18869073 | CL73: =CL54/CL$57 -> 0.20808017 | CM73: =CM54/CM$57 -> 0.19771491 | CN73: =CN54/CN$57 -> 0.19573218
B74: APAC | J74: =J55/J$57 -> 0.23349794 | K74: =K55/K$57 -> 0.24030424 | L74: =L55/L$57 -> 0.23317402 | M74: =M55/M$57 -> 0.22142333 | N74: =N55/N$57 -> 0.23198642 | P74: =P55/P$57 -> 0.2424552 | Q74: =Q55/Q$57 -> 0.21461488 | R74: =R55/R$57 -> 0.21396359 | S74: =S55/S$57 -> 0.24422735 | T74: =T55/T$57 -> 0.22866713 | V74: =V55/V$57 -> 0.22382489 | W74: =W55/W$57 -> 0.26165414 | X74: =X55/X$57 -> 0.25596012 | Y74: =Y55/Y$57 -> 0.26253548 | Z74: =Z55/Z$57 -> 0.25093537 | AB74: =AB55/AB$57 -> 0.26181753 | AC74: =AC55/AC$57 -> 0.2235709 | AD74: =AD55/AD$57 -> 0.21901426 | AE74: =AE55/AE$57 -> 0.2328014 | AF74: =AF55/AF$57 -> 0.2338549 | AH74: =AH55/AH$57 -> 0.21806612 | AI74: =AI55/AI$57 -> 0.2088042 | AJ74: =AJ55/AJ$57 -> 0.19638605 | AK74: =AK55/AK$57 -> 0.18650369 | AL74: =AL55/AL$57 -> 0.20152367 | AN74: =AN55/AN$57 -> 0.18928406 | AO74: =AO55/AO$57 -> 0.18881837 | AP74: =AP55/AP$57 -> 0.1741306 | AQ74: =AQ55/AQ$57 -> 0.18254604 | AR74: =AR55/AR$57 -> 0.18365717 | AT74: =AT55/AT$57 -> 0.18168449 | AU74: =AU55/AU$57 -> 0.17910354 | AV74: =AV55/AV$57 -> 0.17031055 | AW74: =AW55/AW$57 -> 0.17762734 | AX74: =AX55/AX$57 -> 0.17718487 | AZ74: =AZ55/AZ$57 -> 0.17717097 | BA74: =BA55/BA$57 -> 0.17292172 | BB74: =BB55/BB$57 -> 0.16988968 | BC74: =BC55/BC$57 -> 0.17505953 | BD74: =BD55/BD$57 -> 0.17373112 | BF74: =BF55/BF$57 -> 0.17710649 | BG74: =BG55/BG$57 -> 0.172851 | BH74: =BH55/BH$57 -> 0.16981358 | BI74: =BI55/BI$57 -> 0.17504343 | BJ74: =BJ55/BJ$57 -> 0.17367481 | BL74: =BL55/BL$57 -> 0.1775375 | BM74: =BM55/BM$57 -> 0.17326009 | BN74: =BN55/BN$57 -> 0.17021856 | BO74: =BO55/BO$57 -> 0.1754309 | BP74: =BP55/BP$57 -> 0.17408238 | BR74: =BR55/BR$57 -> 0.17796152 | BS74: =BS55/BS$57 -> 0.17366237 | BT74: =BT55/BT$57 -> 0.17061682 | BU74: =BU55/BU$57 -> 0.17581058 | BV74: =BV55/BV$57 -> 0.17448287 | BX74: =BX55/BX$57 -> 0.17837855 | BY74: =BY55/BY$57 -> 0.17405784 | BZ74: =BZ55/BZ$57 -> 0.17100835 | CA74: =CA55/CA$57 -> 0.17618251 | CB74: =CB55/CB$57 -> 0.17487627 | CD74: =CD55/CD$57 -> 0.17878859 | CE74: =CE55/CE$57 -> 0.1744465 | CF74: =CF55/CF$57 -> 0.17139316 | CG74: =CG55/CG$57 -> 0.17654671 | CH74: =CH55/CH$57 -> 0.1752626 | CJ74: =CJ55/CJ$57 -> 0.17919164 | CK74: =CK55/CK$57 -> 0.17482837 | CL74: =CL55/CL$57 -> 0.17177125 | CM74: =CM55/CM$57 -> 0.17690319 | CN74: =CN55/CN$57 -> 0.17564187
B75: Intersegment | J75: =J56/J$57 -> 0.00057613169 | K75: =K56/K$57 -> -0.00022592063 | L75: =L56/L$57 -> -0.00047010891 | M75: =M56/M$57 -> -0.00088041086 | N75: =N56/N$57 -> -0.00027015553 | P75: =P56/P$57 -> -0.0006287331 | Q75: =Q56/Q$57 -> -0.00073147539 | R75: =R56/R$57 -> -0.0035075998 | S75: =S56/S$57 -> -0.0031487163 | T75: =T56/T$57 -> -0.0019505467 | V75: =V56/V$57 -> 0.0005043373 | W75: =W56/W$57 -> 0.0029001074 | X75: =X56/X$57 -> 0.00010836584 | Y75: =Y56/Y$57 -> 0.00028382214 | Z75: =Z56/Z$57 -> 0.00092255651 | AB75: =AB56/AB$57 -> -0.0004467876 | AC75: =AC56/AC$57 -> -8.201427e-05 | AD75: =AD56/AD$57 -> 0.0011958657 | AE75: =AE56/AE$57 -> 0.0010689471 | AF75: =AF56/AF$57 -> 0.0004565452 | AH75: =AH56/AH$57 -> 0.00069843241 | AI75: =AI56/AI$57 -> 0.00096018908 | AJ75: =AJ56/AJ$57 -> 0.0022412103 | AK75: =AK56/AK$57 -> 0.0027093441 | AL75: =AL56/AL$57 -> 0.0017145685 | AN75: =AN56/AN$57 -> -0.0012583615 | AO75: =AO56/AO$57 -> -0.00036264733 | AP75: =AP56/AP$57 -> -0.00043782837 | AQ75: =AQ56/AQ$57 -> 0.00049270185 | AR75: =AR56/AR$57 -> -0.00037576915 | AT75: =AT56/AT$57 -> -0.0026737968 | AU75: =AU56/AU$57 -> -0.0011363636 | AV75: =AV56/AV$57 -> -0.0013131114 | AW75: =AW56/AW$57 -> 0 | AX75: =AX56/AX$57 -> -0.0012612461 | AZ75: =AZ56/AZ$57 -> 0 | BA75: =BA56/BA$57 -> 0 | BB75: =BB56/BB$57 -> 0 | BC75: =BC56/BC$57 -> 0 | BD75: =BD56/BD$57 -> 0 | BF75: =BF56/BF$57 -> 0 | BG75: =BG56/BG$57 -> 0 | BH75: =BH56/BH$57 -> 0 | BI75: =BI56/BI$57 -> 0 | BJ75: =BJ56/BJ$57 -> 0 | BL75: =BL56/BL$57 -> 0 | BM75: =BM56/BM$57 -> 0 | BN75: =BN56/BN$57 -> 0 | BO75: =BO56/BO$57 -> 0 | BP75: =BP56/BP$57 -> 0 | BR75: =BR56/BR$57 -> 0 | BS75: =BS56/BS$57 -> 0 | BT75: =BT56/BT$57 -> 0 | BU75: =BU56/BU$57 -> 0 | BV75: =BV56/BV$57 -> 0 | BX75: =BX56/BX$57 -> 0 | BY75: =BY56/BY$57 -> 0 | BZ75: =BZ56/BZ$57 -> 0 | CA75: =CA56/CA$57 -> 0 | CB75: =CB56/CB$57 -> 0 | CD75: =CD56/CD$57 -> 0 | CE75: =CE56/CE$57 -> 0 | CF75: =CF56/CF$57 -> 0 | CG75: =CG56/CG$57 -> 0 | CH75: =CH56/CH$57 -> 0 | CJ75: =CJ56/CJ$57 -> 0 | CK75: =CK56/CK$57 -> 0 | CL75: =CL56/CL$57 -> 0 | CM75: =CM56/CM$57 -> 0 | CN75: =CN56/CN$57 -> 0
B76: Total Mix | J76: =SUM(J71:J75) -> 1 | K76: =SUM(K71:K75) -> 1 | L76: =SUM(L71:L75) -> 1 | M76: =SUM(M71:M75) -> 1 | N76: =SUM(N71:N75) -> 1 | P76: =SUM(P71:P75) -> 1 | Q76: =SUM(Q71:Q75) -> 1 | R76: =SUM(R71:R75) -> 1 | S76: =SUM(S71:S75) -> 1 | T76: =SUM(T71:T75) -> 1 | V76: =SUM(V71:V75) -> 1 | W76: =SUM(W71:W75) -> 1 | X76: =SUM(X71:X75) -> 1 | Y76: =SUM(Y71:Y75) -> 1 | Z76: =SUM(Z71:Z75) -> 1 | AB76: =SUM(AB71:AB75) -> 1 | AC76: =SUM(AC71:AC75) -> 1 | AD76: =SUM(AD71:AD75) -> 1 | AE76: =SUM(AE71:AE75) -> 1 | AF76: =SUM(AF71:AF75) -> 1 | AH76: =SUM(AH71:AH75) -> 1 | AI76: =SUM(AI71:AI75) -> 1 | AJ76: =SUM(AJ71:AJ75) -> 1 | AK76: =SUM(AK71:AK75) -> 1 | AL76: =SUM(AL71:AL75) -> 1 | AN76: =SUM(AN71:AN75) -> 1 | AO76: =SUM(AO71:AO75) -> 1 | AP76: =SUM(AP71:AP75) -> 1 | AQ76: =SUM(AQ71:AQ75) -> 1 | AR76: =SUM(AR71:AR75) -> 1 | AT76: =SUM(AT71:AT75) -> 1 | AU76: =SUM(AU71:AU75) -> 1 | AV76: =SUM(AV71:AV75) -> 1 | AW76: =SUM(AW71:AW75) -> 1 | AX76: =SUM(AX71:AX75) -> 1 | AZ76: =SUM(AZ71:AZ75) -> 1 | BA76: =SUM(BA71:BA75) -> 1 | BB76: =SUM(BB71:BB75) -> 1 | BC76: =SUM(BC71:BC75) -> 1 | BD76: =SUM(BD71:BD75) -> 1 | BF76: =SUM(BF71:BF75) -> 1 | BG76: =SUM(BG71:BG75) -> 1 | BH76: =SUM(BH71:BH75) -> 1 | BI76: =SUM(BI71:BI75) -> 1 | BJ76: =SUM(BJ71:BJ75) -> 1 | BL76: =SUM(BL71:BL75) -> 1 | BM76: =SUM(BM71:BM75) -> 1 | BN76: =SUM(BN71:BN75) -> 1 | BO76: =SUM(BO71:BO75) -> 1 | BP76: =SUM(BP71:BP75) -> 1 | BR76: =SUM(BR71:BR75) -> 1 | BS76: =SUM(BS71:BS75) -> 1 | BT76: =SUM(BT71:BT75) -> 1 | BU76: =SUM(BU71:BU75) -> 1 | BV76: =SUM(BV71:BV75) -> 1 | BX76: =SUM(BX71:BX75) -> 1 | BY76: =SUM(BY71:BY75) -> 1 | BZ76: =SUM(BZ71:BZ75) -> 1 | CA76: =SUM(CA71:CA75) -> 1 | CB76: =SUM(CB71:CB75) -> 1 | CD76: =SUM(CD71:CD75) -> 1 | CE76: =SUM(CE71:CE75) -> 1 | CF76: =SUM(CF71:CF75) -> 1 | CG76: =SUM(CG71:CG75) -> 1 | CH76: =SUM(CH71:CH75) -> 1 | CJ76: =SUM(CJ71:CJ75) -> 1 | CK76: =SUM(CK71:CK75) -> 1 | CL76: =SUM(CL71:CL75) -> 1 | CM76: =SUM(CM71:CM75) -> 1 | CN76: =SUM(CN71:CN75) -> 1
B78: Revenue by Application
B79: Construction Industries | D79: =D132 -> 4100 | E79: =E132 -> 4959 | F79: =F132 -> 4886 | G79: =G132 -> 5295 | H79: =H132 -> 19240 | J79: =J132 -> 5677 | K79: =K132 -> 6172 | L79: =L132 -> 5683 | M79: =M132 -> 5705 | N79: =N132 -> 23237 | P79: =P132 -> 5873 | Q79: =Q132 -> 6467 | R79: =R132 -> 5289 | S79: =S132 -> 5020 | T79: =T132 -> 22649 | V79: =V132 -> 4306 | W79: =W132 -> 4048 | X79: =X132 -> 4056 | Y79: =Y132 -> 4508 | Z79: =Z132 -> 16918 | AB79: =AB132 -> 5459 | AC79: =AC132 -> 5656 | AD79: =AD132 -> 5255 | AE79: =AE132 -> 5736 | AF79: =AF132 -> 22106 | AH79: =AH132 -> 6115 | AI79: =AI132 -> 6033 | AJ79: =AJ132 -> 6276 | AK79: =AK132 -> 6845 | AL79: =AL132 -> 25269 | AN79: =AN132 -> 6746 | AO79: =AO132 -> 7154 | AP79: =AP132 -> 6999 | AQ79: =AQ132 -> 6519 | AR79: =AR132 -> 27418 | AT79: =AT132 -> 6424 | AU79: =AU132 -> 6683 | AV79: =AV132 -> 6345 | AW79: =AW132 -> 6040.3 | AX79: =AX132 -> 25492.3 | AZ79: =AZ132 -> 5859.8 | BA79: =BA132 -> 6049.25 | BB79: =BB132 -> 5988.5 | BC79: =BC132 -> 5870.32 | BD79: =BD132 -> 23767.87 | BF79: =BF132 -> 6151.54 | BG79: =BG132 -> 6350.4625 | BH79: =BH132 -> 6286.675 | BI79: =BI132 -> 6162.586 | BJ79: =BJ132 -> 24951.264 | BL79: =BL132 -> 6360.3798 | BM79: =BM132 -> 6566.0873 | BN79: =BN132 -> 6500.9427 | BO79: =BO132 -> 6373.2284 | BP79: =BP132 -> 25800.638 | BR79: =BR132 -> 6576.4864 | BS79: =BS132 -> 6789.2154 | BT79: =BT132 -> 6722.6952 | BU79: =BU132 -> 6591.2506 | BV79: =BV132 -> 26679.648 | BX79: =BX132 -> 6800.1181 | BY79: =BY132 -> 7020.1131 | BZ79: =BZ132 -> 6952.1992 | CA79: =CA132 -> 6816.9166 | CB79: =CB132 -> 27589.347 | CD79: =CD132 -> 7031.5423 | CE79: =CE132 -> 7259.0565 | CF79: =CF132 -> 7189.7312 | CG79: =CG132 -> 7050.4996 | CH79: =CH132 -> 28530.83 | CJ79: =CJ132 -> 7271.0359 | CK79: =CK132 -> 7506.3319 | CL79: =CL132 -> 7435.5779 | CM79: =CM132 -> 7292.2832 | CN79: =CN132 -> 29505.229
B80: Resource Industries | D80: =D173 -> 1761 | E80: =E173 -> 1836 | F80: =F173 -> 1956 | G80: =G173 -> 2308 | H80: =H173 -> 7861 | J80: =J173 -> 2309 | K80: =K173 -> 2526 | L80: =L173 -> 2638 | M80: =M173 -> 2797 | N80: =N173 -> 10270 | P80: =P173 -> 2752 | Q80: =Q173 -> 2819 | R80: =R173 -> 2310 | S80: =S173 -> 2395 | T80: =T173 -> 10276 | V80: =V173 -> 2084 | W80: =W173 -> 1826 | X80: =X173 -> 1816 | Y80: =Y173 -> 2180 | Z80: =Z173 -> 7906 | AB80: =AB173 -> 2178 | AC80: =AC173 -> 2547 | AD80: =AD173 -> 2366 | AE80: =AE173 -> 2719 | AF80: =AF173 -> 9810 | AH80: =AH173 -> 2830 | AI80: =AI173 -> 2961 | AJ80: =AJ173 -> 3087 | AK80: =AK173 -> 3436 | AL80: =AL173 -> 12314 | AN80: =AN173 -> 3427 | AO80: =AO173 -> 3563 | AP80: =AP173 -> 3351 | AQ80: =AQ173 -> 3242 | AR80: =AR173 -> 13583 | AT80: =AT173 -> 3193 | AU80: =AU173 -> 3206 | AV80: =AV173 -> 3028 | AW80: =AW173 -> 2991.1 | AX80: =AX173 -> 12418.1 | AZ80: =AZ173 -> 2890.2 | BA80: =BA173 -> 3107 | BB80: =BB173 -> 3096.84 | BC80: =BC173 -> 3071.862 | BD80: =BD173 -> 12165.902 | BF80: =BF173 -> 3002.608 | BG80: =BG173 -> 3228.08 | BH80: =BH173 -> 3217.5136 | BI80: =BI173 -> 3191.5365 | BJ80: =BJ173 -> 12639.738 | BL80: =BL173 -> 3119.5123 | BM80: =BM173 -> 3354.0032 | BN80: =BN173 -> 3343.0141 | BO80: =BO173 -> 3315.9979 | BP80: =BP173 -> 13132.528 | BR80: =BR173 -> 3241.0928 | BS80: =BS173 -> 3484.9633 | BT80: =BT173 -> 3473.5347 | BU80: =BU173 -> 3445.4379 | BV80: =BV173 -> 13645.029 | BX80: =BX173 -> 3367.5365 | BY80: =BY173 -> 3621.1619 | BZ80: =BZ173 -> 3609.2761 | CA80: =CA173 -> 3580.0554 | CB80: =CB173 -> 14178.03 | CD80: =CD173 -> 3499.038 | CE80: =CE173 -> 3762.8083 | CF80: =CF173 -> 3750.4471 | CG80: =CG173 -> 3720.0576 | CH80: =CH173 -> 14732.351 | CJ80: =CJ173 -> 3635.7995 | CK80: =CK173 -> 3910.1207 | CL80: =CL173 -> 3897.265 | CM80: =CM173 -> 3865.6599 | CN80: =CN173 -> 15308.845
B81: Energy & Transportation | D81: =D214 -> 4136 | E81: =E214 -> 4768 | F81: =F214 -> 4838 | G81: =G214 -> 5640 | H81: =H214 -> 19382 | J81: =J214 -> 5219 | K81: =K214 -> 5724 | L81: =L214 -> 5555 | M81: =M214 -> 6287 | N81: =N214 -> 22785 | P81: =P214 -> 5210 | Q81: =Q214 -> 5486 | R81: =R214 -> 5452 | S81: =S214 -> 5949 | T81: =T214 -> 22097 | V81: =V214 -> 4349 | W81: =W214 -> 4149 | X81: =X214 -> 4161 | Y81: =Y214 -> 4811 | Z81: =Z214 -> 17470 | AB81: =AB214 -> 4507 | AC81: =AC214 -> 4975 | AD81: =AD214 -> 5077 | AE81: =AE214 -> 5728 | AF81: =AF214 -> 20287 | AH81: =AH214 -> 5038 | AI81: =AI214 -> 5705 | AJ81: =AJ214 -> 6186 | AK81: =AK214 -> 6823 | AL81: =AL214 -> 23752 | AN81: =AN214 -> 6254 | AO81: =AO214 -> 7219 | AP81: =AP214 -> 6859 | AQ81: =AQ214 -> 7669 | AR81: =AR214 -> 28001 | AT81: =AT214 -> 6681 | AU81: =AU214 -> 7337 | AV81: =AV214 -> 7187 | AW81: =AW214 -> 7928.9207 | AX81: =AX214 -> 29133.921 | AZ81: =AZ214 -> 7000.8124 | BA81: =BA214 -> 7733.7714 | BB81: =BB214 -> 7492.3102 | BC81: =BC214 -> 8281.8551 | BD81: =BD214 -> 30508.749 | BF81: =BF214 -> 7332.8135 | BG81: =BG214 -> 8101.0477 | BH81: =BH214 -> 7846.657 | BI81: =BI214 -> 8670.3547 | BJ81: =BJ214 -> 31950.873 | BL81: =BL214 -> 7671.5551 | BM81: =BM214 -> 8475.997 | BN81: =BN214 -> 8208.2532 | BO81: =BO214 -> 9068.8084 | BP81: =BP214 -> 33424.614 | BR81: =BR214 -> 8026.4536 | BS81: =BS214 -> 8868.849 | BT81: =BT214 -> 8587.076 | BU81: =BU214 -> 9486.2703 | BV81: =BV214 -> 34968.649 | BX81: =BX214 -> 8398.2922 | BY81: =BY214 -> 9280.4722 | BZ81: =BZ214 -> 8983.9601 | CA81: =CA214 -> 9923.664 | CB81: =CB214 -> 36586.389 | CD81: =CD214 -> 8787.8928 | CE81: =CE214 -> 9711.7778 | CF81: =CF214 -> 9399.7811 | CG81: =CG214 -> 10381.958 | CH81: =CH214 -> 38281.41 | CJ81: =CJ214 -> 9196.117 | CK81: =CK214 -> 10163.721 | CL81: =CL214 -> 9835.4574 | CM81: =CM214 -> 10862.17 | CN81: =CN214 -> 40057.465
B82: Intersegment Eliminations | D82: =-SUM(D131,D172,D213) -> -880 | E82: =-SUM(E131,E172,E213) -> -933 | F82: =-SUM(F131,F172,F213) -> -995 | G82: =-SUM(G131,G172,G213) -> -1074 | H82: =-SUM(H131,H172,H213) -> -3882 | J82: =-SUM(J131,J172,J213) -> -1062 | K82: =-SUM(K131,K172,K213) -> -1140 | L82: =-SUM(L131,L172,L213) -> -1107 | M82: =-SUM(M131,M172,M213) -> -1147 | N82: =-SUM(N131,N172,N213) -> -4456 | P82: =-SUM(P131,P172,P213) -> -1103 | Q82: =-SUM(Q131,Q172,Q213) -> -1091 | R82: =-SUM(R131,R172,R213) -> -1035 | S82: =-SUM(S131,S172,S213) -> -939 | T82: =-SUM(T131,T172,T213) -> -4168 | V82: =-SUM(V131,V172,V213) -> -830 | W82: =-SUM(W131,W172,W213) -> -740 | X82: =-SUM(X131,X172,X213) -> -806 | Y82: =-SUM(Y131,Y172,Y213) -> -932 | Z82: =-SUM(Z131,Z172,Z213) -> -3308 | AB82: =-SUM(AB131,AB172,AB213) -> -948 | AC82: =-SUM(AC131,AC172,AC213) -> -984 | AD82: =-SUM(AD131,AD172,AD213) -> -1005 | AE82: =-SUM(AE131,AE172,AE213) -> -1100 | AF82: =-SUM(AF131,AF172,AF213) -> -4037 | AH82: =-SUM(AH131,AH172,AH213) -> -1106 | AI82: =-SUM(AI131,AI172,AI213) -> -1173 | AJ82: =-SUM(AJ131,AJ172,AJ213) -> -1303 | AK82: =-SUM(AK131,AK172,AK213) -> -1276 | AL82: =-SUM(AL131,AL172,AL213) -> -4858 | AN82: =-SUM(AN131,AN172,AN213) -> -1309 | AO82: =-SUM(AO131,AO172,AO213) -> -1385 | AP82: =-SUM(AP131,AP172,AP213) -> -1214 | AQ82: =-SUM(AQ131,AQ172,AQ213) -> -1201 | AR82: =-SUM(AR131,AR172,AR213) -> -5109 | AT82: =-SUM(AT131,AT172,AT213) -> -1298 | AU82: =-SUM(AU131,AU172,AU213) -> -1368 | AV82: =-SUM(AV131,AV172,AV213) -> -1309 | AW82: =-SUM(AW131,AW172,AW213) -> -1147.7207 | AX82: =-SUM(AX131,AX172,AX213) -> -5122.7207 | AZ82: =-SUM(AZ131,AZ172,AZ213) -> -1237.7124 | BA82: =-SUM(BA131,BA172,BA213) -> -1333.2714 | BB82: =-SUM(BB131,BB172,BB213) -> -1314.5102 | BC82: =-SUM(BC131,BC172,BC213) -> -1188.8351 | BD82: =-SUM(BD131,BD172,BD213) -> -5074.329 | BF82: =-SUM(BF131,BF172,BF213) -> -1287.9365 | BG82: =-SUM(BG131,BG172,BG213) -> -1387.7842 | BH82: =-SUM(BH131,BH172,BH213) -> -1368.187 | BI82: =-SUM(BI131,BI172,BI213) -> -1236.9277 | BJ82: =-SUM(BJ131,BJ172,BJ213) -> -5280.8355 | BL82: =-SUM(BL131,BL172,BL213) -> -1331.0448 | BM82: =-SUM(BM131,BM172,BM213) -> -1434.582 | BN82: =-SUM(BN131,BN172,BN213) -> -1414.3491 | BO82: =-SUM(BO131,BO172,BO213) -> -1278.3439 | BP82: =-SUM(BP131,BP172,BP213) -> -5458.3198 | BR82: =-SUM(BR131,BR172,BR213) -> -1375.7655 | BS82: =-SUM(BS131,BS172,BS213) -> -1483.1303 | BT82: =-SUM(BT131,BT172,BT213) -> -1462.2409 | BU82: =-SUM(BU131,BU172,BU213) -> -1321.3142 | BV82: =-SUM(BV131,BV172,BV213) -> -5642.4508 | BX82: =-SUM(BX131,BX172,BX213) -> -1422.1595 | BY82: =-SUM(BY131,BY172,BY213) -> -1533.4949 | BZ82: =-SUM(BZ131,BZ172,BZ213) -> -1511.9277 | CA82: =-SUM(CA131,CA172,CA213) -> -1365.8972 | CB82: =-SUM(CB131,CB172,CB213) -> -5833.4794 | CD82: =-SUM(CD131,CD172,CD213) -> -1470.2899 | CE82: =-SUM(CE131,CE172,CE213) -> -1585.7444 | CF82: =-SUM(CF131,CF172,CF213) -> -1563.4774 | CG82: =-SUM(CG131,CG172,CG213) -> -1412.1541 | CH82: =-SUM(CH131,CH172,CH213) -> -6031.6659 | CJ82: =-SUM(CJ131,CJ172,CJ213) -> -1520.2222 | CK82: =-SUM(CK131,CK172,CK213) -> -1639.95 | CL82: =-SUM(CL131,CL172,CL213) -> -1616.9605 | CM82: =-SUM(CM131,CM172,CM213) -> -1460.1482 | CN82: =-SUM(CN131,CN172,CN213) -> -6237.2809
B83: All other, Corporate, & Eliminations | D83: =D56 -> 13 | E83: =E56 -> 9 | F83: =F56 -> 28 | G83: =G56 -> 25 | H83: =H56 -> 75 | J83: =J56 -> 7 | K83: =K56 -> -3 | L83: =L56 -> -6 | M83: =M56 -> -12 | N83: =N56 -> -14 | P83: =P56 -> -8 | Q83: =Q56 -> -10 | R83: =R56 -> -42 | S83: =S56 -> -39 | T83: =T56 -> -99 | V83: =V56 -> 5 | W83: =W56 -> 27 | X83: =X56 -> 1 | Y83: =Y56 -> 3 | Z83: =Z56 -> 36 | AB83: =AB56 -> -5 | AC83: =AC56 -> -1 | AD83: =AD56 -> 14 | AE83: =AE56 -> 14 | AF83: =AF56 -> 22 | AH83: =AH56 -> 9 | AI83: =AI56 -> 13 | AJ83: =AJ56 -> 32 | AK83: =AK56 -> 43 | AL83: =AL56 -> 97 | AN83: =AN56 -> -19 | AO83: =AO56 -> -6 | AP83: =AP56 -> -7 | AQ83: =AQ56 -> 8 | AR83: =AR56 -> -24 | AT83: =AT56 -> -40 | AU83: =AU56 -> -18 | AV83: =AV56 -> -20 | AW83: =AW56 -> 0 | AX83: =AX56 -> -78 | AZ83: =AZ56 -> 0 | BA83: =BA56 -> 0 | BB83: =BB56 -> 0 | BC83: =BC56 -> 0 | BD83: =BD56 -> 0 | BF83: =BF56 -> 0 | BG83: =BG56 -> 0 | BH83: =BH56 -> 0 | BI83: =BI56 -> 0 | BJ83: =BJ56 -> 0 | BL83: =BL56 -> 0 | BM83: =BM56 -> 0 | BN83: =BN56 -> 0 | BO83: =BO56 -> 0 | BP83: =BP56 -> 0 | BR83: =BR56 -> 0 | BS83: =BS56 -> 0 | BT83: =BT56 -> 0 | BU83: =BU56 -> 0 | BV83: =BV56 -> 0 | BX83: =BX56 -> 0 | BY83: =BY56 -> 0 | BZ83: =BZ56 -> 0 | CA83: =CA56 -> 0 | CB83: =CB56 -> 0 | CD83: =CD56 -> 0 | CE83: =CE56 -> 0 | CF83: =CF56 -> 0 | CG83: =CG56 -> 0 | CH83: =CH56 -> 0 | CJ83: =CJ56 -> 0 | CK83: =CK56 -> 0 | CL83: =CL56 -> 0 | CM83: =CM56 -> 0 | CN83: =CN56 -> 0
B84: Revenue ($mm) | D84: =SUM(D79:D83) -> 9130 | E84: =SUM(E79:E83) -> 10639 | F84: =SUM(F79:F83) -> 10713 | G84: =SUM(G79:G83) -> 12194 | H84: =SUM(H79:H83) -> 42676 | J84: =SUM(J79:J83) -> 12150 | K84: =SUM(K79:K83) -> 13279 | L84: =SUM(L79:L83) -> 12763 | M84: =SUM(M79:M83) -> 13630 | N84: =SUM(N79:N83) -> 51822 | P84: =SUM(P79:P83) -> 12724 | Q84: =SUM(Q79:Q83) -> 13671 | R84: =SUM(R79:R83) -> 11974 | S84: =SUM(S79:S83) -> 12386 | T84: =SUM(T79:T83) -> 50755 | V84: =SUM(V79:V83) -> 9914 | W84: =SUM(W79:W83) -> 9310 | X84: =SUM(X79:X83) -> 9228 | Y84: =SUM(Y79:Y83) -> 10570 | Z84: =SUM(Z79:Z83) -> 39022 | AB84: =SUM(AB79:AB83) -> 11191 | AC84: =SUM(AC79:AC83) -> 12193 | AD84: =SUM(AD79:AD83) -> 11707 | AE84: =SUM(AE79:AE83) -> 13097 | AF84: =SUM(AF79:AF83) -> 48188 | AH84: =SUM(AH79:AH83) -> 12886 | AI84: =SUM(AI79:AI83) -> 13539 | AJ84: =SUM(AJ79:AJ83) -> 14278 | AK84: =SUM(AK79:AK83) -> 15871 | AL84: =SUM(AL79:AL83) -> 56574 | AN84: =SUM(AN79:AN83) -> 15099 | AO84: =SUM(AO79:AO83) -> 16545 | AP84: =SUM(AP79:AP83) -> 15988 | AQ84: =SUM(AQ79:AQ83) -> 16237 | AR84: =SUM(AR79:AR83) -> 63869 | AT84: =SUM(AT79:AT83) -> 14960 | AU84: =SUM(AU79:AU83) -> 15840 | AV84: =SUM(AV79:AV83) -> 15231 | AW84: =SUM(AW79:AW83) -> 15812.6 | AX84: =SUM(AX79:AX83) -> 61843.6 | AZ84: =SUM(AZ79:AZ83) -> 14513.1 | BA84: =SUM(BA79:BA83) -> 15556.75 | BB84: =SUM(BB79:BB83) -> 15263.14 | BC84: =SUM(BC79:BC83) -> 16035.202 | BD84: =SUM(BD79:BD83) -> 61368.192 | BF84: =SUM(BF79:BF83) -> 15199.025 | BG84: =SUM(BG79:BG83) -> 16291.806 | BH84: =SUM(BH79:BH83) -> 15982.659 | BI84: =SUM(BI79:BI83) -> 16787.549 | BJ84: =SUM(BJ79:BJ83) -> 64261.039 | BL84: =SUM(BL79:BL83) -> 15820.402 | BM84: =SUM(BM79:BM83) -> 16961.505 | BN84: =SUM(BN79:BN83) -> 16637.861 | BO84: =SUM(BO79:BO83) -> 17479.691 | BP84: =SUM(BP79:BP83) -> 66899.46 | BR84: =SUM(BR79:BR83) -> 16468.267 | BS84: =SUM(BS79:BS83) -> 17659.897 | BT84: =SUM(BT79:BT83) -> 17321.065 | BU84: =SUM(BU79:BU83) -> 18201.645 | BV84: =SUM(BV79:BV83) -> 69650.874 | BX84: =SUM(BX79:BX83) -> 17143.787 | BY84: =SUM(BY79:BY83) -> 18388.252 | BZ84: =SUM(BZ79:BZ83) -> 18033.508 | CA84: =SUM(CA79:CA83) -> 18954.739 | CB84: =SUM(CB79:CB83) -> 72520.286 | CD84: =SUM(CD79:CD83) -> 17848.183 | CE84: =SUM(CE79:CE83) -> 19147.898 | CF84: =SUM(CF79:CF83) -> 18776.482 | CG84: =SUM(CG79:CG83) -> 19740.361 | CH84: =SUM(CH79:CH83) -> 75512.925 | CJ84: =SUM(CJ79:CJ83) -> 18582.73 | CK84: =SUM(CK79:CK83) -> 19940.224 | CL84: =SUM(CL79:CL83) -> 19551.34 | CM84: =SUM(CM79:CM83) -> 20559.965 | CN84: =SUM(CN79:CN83) -> 78634.258
B86: Application Revenue Growth YoY (%)
B87: Construction Industries | J87: =J79/D79-1 -> 0.38463415 | K87: =K79/E79-1 -> 0.24460577 | L87: =L79/F79-1 -> 0.16311912 | M87: =M79/G79-1 -> 0.077431539 | N87: =N79/H79-1 -> 0.20774428 | P87: =P79/J79-1 -> 0.034525277 | Q87: =Q79/K79-1 -> 0.0477965 | R87: =R79/L79-1 -> -0.069329579 | S87: =S79/M79-1 -> -0.12007011 | T87: =T79/N79-1 -> -0.025304471 | V87: =V79/P79-1 -> -0.26681423 | W87: =W79/Q79-1 -> -0.37405288 | X87: =X79/R79-1 -> -0.23312535 | Y87: =Y79/S79-1 -> -0.10199203 | Z87: =Z79/T79-1 -> -0.25303545 | AB87: =AB79/V79-1 -> 0.26776591 | AC87: =AC79/W79-1 -> 0.3972332 | AD87: =AD79/X79-1 -> 0.29561144 | AE87: =AE79/Y79-1 -> 0.27240461 | AF87: =AF79/Z79-1 -> 0.30665563 | AH87: =AH79/AB79-1 -> 0.12016853 | AI87: =AI79/AC79-1 -> 0.06665488 | AJ87: =AJ79/AD79-1 -> 0.19429115 | AK87: =AK79/AE79-1 -> 0.19334031 | AL87: =AL79/AF79-1 -> 0.14308333 | AN87: =AN79/AH79-1 -> 0.10318888 | AO87: =AO79/AI79-1 -> 0.18581137 | AP87: =AP79/AJ79-1 -> 0.11520076 | AQ87: =AQ79/AK79-1 -> -0.047626004 | AR87: =AR79/AL79-1 -> 0.085044917 | AT87: =AT79/AN79-1 -> -0.047731989 | AU87: =AU79/AO79-1 -> -0.065837294 | AV87: =AV79/AP79-1 -> -0.09344192 | AW87: =AW79/AQ79-1 -> -0.073431508 | AX87: =AX79/AR79-1 -> -0.070234882 | AZ87: =AZ79/AT79-1 -> -0.087826899 | BA87: =BA79/AU79-1 -> -0.094830166 | BB87: =BB79/AV79-1 -> -0.056185973 | BC87: =BC79/AW79-1 -> -0.028140986 | BD87: =BD79/AX79-1 -> -0.067645132 | BF87: =BF79/AZ79-1 -> 0.049786682 | BG87: =BG79/BA79-1 -> 0.049793363 | BH87: =BH79/BB79-1 -> 0.049791267 | BI87: =BI79/BC79-1 -> 0.049787064 | BJ87: =BJ79/BD79-1 -> 0.049789632 | BL87: =BL79/BF79-1 -> 0.033949182 | BM87: =BM79/BG79-1 -> 0.033954196 | BN87: =BN79/BH79-1 -> 0.034082838 | BO87: =BO79/BI79-1 -> 0.034180844 | BP87: =BP79/BJ79-1 -> 0.034041351 | BR87: =BR79/BL79-1 -> 0.03397701 | BS87: =BS79/BM79-1 -> 0.033981886 | BT87: =BT79/BN79-1 -> 0.034110815 | BU87: =BU79/BO79-1 -> 0.034209076 | BV87: =BV79/BP79-1 -> 0.03406929 | BX87: =BX79/BR79-1 -> 0.034004738 | BY87: =BY79/BS79-1 -> 0.034009481 | BZ87: =BZ79/BT79-1 -> 0.034138688 | CA87: =CA79/BU79-1 -> 0.034237196 | CB87: =CB79/BV79-1 -> 0.034097127 | CD87: =CD79/BX79-1 -> 0.034032369 | CE87: =CE79/BY79-1 -> 0.034036983 | CF87: =CF79/BZ79-1 -> 0.034166461 | CG87: =CG79/CA79-1 -> 0.034265206 | CH87: =CH79/CB79-1 -> 0.034124863 | CJ87: =CJ79/CD79-1 -> 0.034059908 | CK87: =CK79/CE79-1 -> 0.034064396 | CL87: =CL79/CF79-1 -> 0.034194136 | CM87: =CM79/CG79-1 -> 0.034293111 | CN87: =CN79/CH79-1 -> 0.034152504
B88: Resource Industries | J88: =J80/D80-1 -> 0.31118683 | K88: =K80/E80-1 -> 0.37581699 | L88: =L80/F80-1 -> 0.34867076 | M88: =M80/G80-1 -> 0.21187175 | N88: =N80/H80-1 -> 0.30644956 | P88: =P80/J80-1 -> 0.19185795 | Q88: =Q80/K80-1 -> 0.11599367 | R88: =R80/L80-1 -> -0.12433662 | S88: =S80/M80-1 -> -0.14372542 | T88: =T80/N80-1 -> 0.0005842259 | V88: =V80/P80-1 -> -0.24273256 | W88: =W80/Q80-1 -> -0.35225257 | X88: =X80/R80-1 -> -0.21385281 | Y88: =Y80/S80-1 -> -0.089770355 | Z88: =Z80/T80-1 -> -0.23063449 | AB88: =AB80/V80-1 -> 0.045105566 | AC88: =AC80/W80-1 -> 0.39485214 | AD88: =AD80/X80-1 -> 0.30286344 | AE88: =AE80/Y80-1 -> 0.24724771 | AF88: =AF80/Z80-1 -> 0.24082975 | AH88: =AH80/AB80-1 -> 0.29935721 | AI88: =AI80/AC80-1 -> 0.16254417 | AJ88: =AJ80/AD80-1 -> 0.30473373 | AK88: =AK80/AE80-1 -> 0.26369989 | AL88: =AL80/AF80-1 -> 0.25524975 | AN88: =AN80/AH80-1 -> 0.21095406 | AO88: =AO80/AI80-1 -> 0.20330969 | AP88: =AP80/AJ80-1 -> 0.085519922 | AQ88: =AQ80/AK80-1 -> -0.056461001 | AR88: =AR80/AL80-1 -> 0.10305344 | AT88: =AT80/AN80-1 -> -0.068281296 | AU88: =AU80/AO80-1 -> -0.10019646 | AV88: =AV80/AP80-1 -> -0.096389138 | AW88: =AW80/AQ80-1 -> -0.0773905 | AX88: =AX80/AR80-1 -> -0.085761614 | AZ88: =AZ80/AT80-1 -> -0.094832446 | BA88: =BA80/AU80-1 -> -0.030879601 | BB88: =BB80/AV80-1 -> 0.022734478 | BC88: =BC80/AW80-1 -> 0.027000769 | BD88: =BD80/AX80-1 -> -0.020308904 | BF88: =BF80/AZ80-1 -> 0.03889281 | BG88: =BG80/BA80-1 -> 0.038970068 | BH88: =BH80/BB80-1 -> 0.038966689 | BI88: =BI80/BC80-1 -> 0.038958287 | BJ88: =BJ80/BD80-1 -> 0.038947879 | BL88: =BL80/BF80-1 -> 0.03893426 | BM88: =BM80/BG80-1 -> 0.039008699 | BN88: =BN80/BH80-1 -> 0.039005443 | BO88: =BO80/BI80-1 -> 0.038997348 | BP88: =BP80/BJ80-1 -> 0.038987321 | BR88: =BR80/BL80-1 -> 0.038974199 | BS88: =BS80/BM80-1 -> 0.039045916 | BT88: =BT80/BN80-1 -> 0.03904278 | BU88: =BU80/BO80-1 -> 0.039034981 | BV88: =BV80/BP80-1 -> 0.039025321 | BX88: =BX80/BR80-1 -> 0.039012679 | BY88: =BY80/BS80-1 -> 0.039081769 | BZ88: =BZ80/BT80-1 -> 0.039078748 | CA88: =CA80/BU80-1 -> 0.039071236 | CB88: =CB80/BV80-1 -> 0.039061929 | CD88: =CD80/BX80-1 -> 0.03904975 | CE88: =CE80/BY80-1 -> 0.039116306 | CF88: =CF80/BZ80-1 -> 0.039113396 | CG88: =CG80/CA80-1 -> 0.039106159 | CH88: =CH80/CB80-1 -> 0.039097195 | CJ88: =CJ80/CD80-1 -> 0.039085463 | CK88: =CK80/CE80-1 -> 0.039149571 | CL88: =CL80/CF80-1 -> 0.039146768 | CM88: =CM80/CG80-1 -> 0.039139798 | CN88: =CN80/CH80-1 -> 0.039131164
B89: Energy & Transportation | J89: =J81/D81-1 -> 0.2618472 | K89: =K81/E81-1 -> 0.20050336 | L89: =L81/F81-1 -> 0.14820174 | M89: =M81/G81-1 -> 0.11471631 | N89: =N81/H81-1 -> 0.17557528 | P89: =P81/J81-1 -> -0.0017244683 | Q89: =Q81/K81-1 -> -0.041579315 | R89: =R81/L81-1 -> -0.018541854 | S89: =S81/M81-1 -> -0.053761731 | T89: =T81/N81-1 -> -0.030195304 | V89: =V81/P81-1 -> -0.16525912 | W89: =W81/Q81-1 -> -0.24371127 | X89: =X81/R81-1 -> -0.23679384 | Y89: =Y81/S81-1 -> -0.19129265 | Z89: =Z81/T81-1 -> -0.20939494 | AB89: =AB81/V81-1 -> 0.036330191 | AC89: =AC81/W81-1 -> 0.19908412 | AD89: =AD81/X81-1 -> 0.22013939 | AE89: =AE81/Y81-1 -> 0.19060486 | AF89: =AF81/Z81-1 -> 0.16124785 | AH89: =AH81/AB81-1 -> 0.11781673 | AI89: =AI81/AC81-1 -> 0.14673367 | AJ89: =AJ81/AD81-1 -> 0.21843608 | AK89: =AK81/AE81-1 -> 0.1911662 | AL89: =AL81/AF81-1 -> 0.17079903 | AN89: =AN81/AH81-1 -> 0.24136562 | AO89: =AO81/AI81-1 -> 0.26538124 | AP89: =AP81/AJ81-1 -> 0.10879405 | AQ89: =AQ81/AK81-1 -> 0.12399238 | AR89: =AR81/AL81-1 -> 0.1788902 | AT89: =AT81/AN81-1 -> 0.068276303 | AU89: =AU81/AO81-1 -> 0.016345754 | AV89: =AV81/AP81-1 -> 0.047820382 | AW89: =AW81/AQ81-1 -> 0.033892386 | AX89: =AX81/AR81-1 -> 0.040460009 | AZ89: =AZ81/AT81-1 -> 0.047868937 | BA89: =BA81/AU81-1 -> 0.054078153 | BB89: =BB81/AV81-1 -> 0.042480891 | BC89: =BC81/AW81-1 -> 0.044512283 | BD89: =BD81/AX81-1 -> 0.047189952 | BF89: =BF81/AZ81-1 -> 0.047423236 | BG89: =BG81/BA81-1 -> 0.047489934 | BH89: =BH81/BB81-1 -> 0.047294735 | BI89: =BI81/BC81-1 -> 0.046909739 | BJ89: =BJ81/BD81-1 -> 0.047269193 | BL89: =BL81/BF81-1 -> 0.046195302 | BM89: =BM81/BG81-1 -> 0.046284047 | BN89: =BN81/BH81-1 -> 0.046082833 | BO89: =BO81/BI81-1 -> 0.045955869 | BP89: =BP81/BJ81-1 -> 0.046125208 | BR89: =BR81/BL81-1 -> 0.046261607 | BS89: =BS81/BM81-1 -> 0.046348767 | BT89: =BT81/BN81-1 -> 0.046151453 | BU89: =BU81/BO81-1 -> 0.046032718 | BV89: =BV81/BP81-1 -> 0.046194556 | BX89: =BX81/BR81-1 -> 0.046326647 | BY89: =BY81/BS81-1 -> 0.046412253 | BZ89: =BZ81/BT81-1 -> 0.046218775 | CA89: =CA81/BU81-1 -> 0.046108075 | CB89: =CB81/BV81-1 -> 0.046262575 | CD89: =CD81/BX81-1 -> 0.046390446 | CE89: =CE81/BY81-1 -> 0.046474528 | CF89: =CF81/BZ81-1 -> 0.046284821 | CG89: =CG81/CA81-1 -> 0.046181963 | CH89: =CH81/CB81-1 -> 0.046329289 | CJ89: =CJ81/CD81-1 -> 0.046453026 | CK89: =CK81/CE81-1 -> 0.046535615 | CL89: =CL81/CF81-1 -> 0.046349616 | CM89: =CM81/CG81-1 -> 0.046254407 | CN89: =CN81/CH81-1 -> 0.046394721
B90: Intersegment Eliminations | J90: =J82/D82-1 -> 0.20681818 | K90: =K82/E82-1 -> 0.22186495 | L90: =L82/F82-1 -> 0.11256281 | M90: =M82/G82-1 -> 0.067970205 | N90: =N82/H82-1 -> 0.14786193 | P90: =P82/J82-1 -> 0.038606403 | Q90: =Q82/K82-1 -> -0.042982456 | R90: =R82/L82-1 -> -0.06504065 | S90: =S82/M82-1 -> -0.18134263 | T90: =T82/N82-1 -> -0.064631957 | V90: =V82/P82-1 -> -0.2475068 | W90: =W82/Q82-1 -> -0.32172319 | X90: =X82/R82-1 -> -0.22125604 | Y90: =Y82/S82-1 -> -0.0074547391 | Z90: =Z82/T82-1 -> -0.20633397 | AB90: =AB82/V82-1 -> 0.14216867 | AC90: =AC82/W82-1 -> 0.32972973 | AD90: =AD82/X82-1 -> 0.24689826 | AE90: =AE82/Y82-1 -> 0.18025751 | AF90: =AF82/Z82-1 -> 0.22037485 | AH90: =AH82/AB82-1 -> 0.16666667 | AI90: =AI82/AC82-1 -> 0.19207317 | AJ90: =AJ82/AD82-1 -> 0.29651741 | AK90: =AK82/AE82-1 -> 0.16 | AL90: =AL82/AF82-1 -> 0.20336884 | AN90: =AN82/AH82-1 -> 0.1835443 | AO90: =AO82/AI82-1 -> 0.18073316 | AP90: =AP82/AJ82-1 -> -0.068303914 | AQ90: =AQ82/AK82-1 -> -0.058777429 | AR90: =AR82/AL82-1 -> 0.051667353 | AT90: =AT82/AN82-1 -> -0.0084033613 | AU90: =AU82/AO82-1 -> -0.012274368 | AV90: =AV82/AP82-1 -> 0.078253707 | AW90: =AW82/AQ82-1 -> -0.044362444 | AX90: =AX82/AR82-1 -> 0.002685595 | AZ90: =AZ82/AT82-1 -> -0.046446555 | BA90: =BA82/AU82-1 -> -0.025386395 | BB90: =BB82/AV82-1 -> 0.0042094473 | BC90: =BC82/AW82-1 -> 0.035822621 | BD90: =BD82/AX82-1 -> -0.0094464816 | BF90: =BF82/AZ82-1 -> 0.040578231 | BG90: =BG82/BA82-1 -> 0.040886493 | BH90: =BH82/BB82-1 -> 0.040834089 | BI90: =BI82/BC82-1 -> 0.040453603 | BJ90: =BJ82/BD82-1 -> 0.040696308 | BL90: =BL82/BF82-1 -> 0.033470782 | BM90: =BM82/BG82-1 -> 0.033721255 | BN90: =BN82/BH82-1 -> 0.033739601 | BO90: =BO82/BI82-1 -> 0.03348313 | BP90: =BP82/BJ82-1 -> 0.033609145 | BR90: =BR82/BL82-1 -> 0.033598212 | BS90: =BS82/BM82-1 -> 0.033841374 | BT90: =BT82/BN82-1 -> 0.033861369 | BU90: =BU82/BO82-1 -> 0.033613986 | BV90: =BV82/BP82-1 -> 0.033734004 | BX90: =BX82/BR82-1 -> 0.033722322 | BY90: =BY82/BS82-1 -> 0.033958333 | BZ90: =BZ82/BT82-1 -> 0.033979934 | CA90: =CA82/BU82-1 -> 0.033741439 | CB90: =CB82/BV82-1 -> 0.033855595 | CD90: =CD82/BX82-1 -> 0.033843183 | CE90: =CE82/BY82-1 -> 0.034072203 | CF90: =CF82/BZ82-1 -> 0.034095367 | CG90: =CG82/CA82-1 -> 0.033865561 | CH90: =CH82/CB82-1 -> 0.033973989 | CJ90: =CJ82/CD82-1 -> 0.033960866 | CK90: =CK82/CE82-1 -> 0.034183054 | CL90: =CL82/CF82-1 -> 0.034207738 | CM90: =CM82/CG82-1 -> 0.033986421 | CN90: =CN82/CH82-1 -> 0.034089255
B91: All other, Corporate, & Eliminations | J91: =J83/D83-1 -> -0.46153846 | K91: =K83/E83-1 -> -1.3333333 | L91: =L83/F83-1 -> -1.2142857 | M91: =M83/G83-1 -> -1.48 | N91: =N83/H83-1 -> -1.1866667 | P91: =P83/J83-1 -> -2.1428571 | Q91: =Q83/K83-1 -> 2.3333333 | R91: =R83/L83-1 -> 6 | S91: =S83/M83-1 -> 2.25 | T91: =T83/N83-1 -> 6.0714286 | V91: =V83/P83-1 -> -1.625 | W91: =W83/Q83-1 -> -3.7 | X91: =X83/R83-1 -> -1.0238095 | Y91: =Y83/S83-1 -> -1.0769231 | Z91: =Z83/T83-1 -> -1.3636364 | AB91: =AB83/V83-1 -> -2 | AC91: =AC83/W83-1 -> -1.037037 | AD91: =AD83/X83-1 -> 13 | AE91: =AE83/Y83-1 -> 3.6666667 | AF91: =AF83/Z83-1 -> -0.38888889 | AH91: =AH83/AB83-1 -> -2.8 | AI91: =AI83/AC83-1 -> -14 | AJ91: =AJ83/AD83-1 -> 1.2857143 | AK91: =AK83/AE83-1 -> 2.0714286 | AL91: =AL83/AF83-1 -> 3.4090909 | AN91: =AN83/AH83-1 -> -3.1111111 | AO91: =AO83/AI83-1 -> -1.4615385 | AP91: =AP83/AJ83-1 -> -1.21875 | AQ91: =AQ83/AK83-1 -> -0.81395349 | AR91: =AR83/AL83-1 -> -1.2474227 | AT91: =AT83/AN83-1 -> 1.1052632 | AU91: =AU83/AO83-1 -> 2 | AV91: =AV83/AP83-1 -> 1.8571429 | AW91: =AW83/AQ83-1 -> -1 | AX91: =AX83/AR83-1 -> 2.25 | AZ91: =AZ83/AT83-1 -> -1 | BA91: =BA83/AU83-1 -> -1 | BB91: =BB83/AV83-1 -> -1 | BC91: =BC83/AW83-1 -> #DIV/0! | BD91: =BD83/AX83-1 -> -1 | BF91: =BF83/AZ83-1 -> #DIV/0! | BG91: =BG83/BA83-1 -> #DIV/0! | BH91: =BH83/BB83-1 -> #DIV/0! | BI91: =BI83/BC83-1 -> #DIV/0! | BJ91: =BJ83/BD83-1 -> #DIV/0! | BL91: =BL83/BF83-1 -> #DIV/0! | BM91: =BM83/BG83-1 -> #DIV/0! | BN91: =BN83/BH83-1 -> #DIV/0! | BO91: =BO83/BI83-1 -> #DIV/0! | BP91: =BP83/BJ83-1 -> #DIV/0! | BR91: =BR83/BL83-1 -> #DIV/0! | BS91: =BS83/BM83-1 -> #DIV/0! | BT91: =BT83/BN83-1 -> #DIV/0! | BU91: =BU83/BO83-1 -> #DIV/0! | BV91: =BV83/BP83-1 -> #DIV/0! | BX91: =BX83/BR83-1 -> #DIV/0! | BY91: =BY83/BS83-1 -> #DIV/0! | BZ91: =BZ83/BT83-1 -> #DIV/0! | CA91: =CA83/BU83-1 -> #DIV/0! | CB91: =CB83/BV83-1 -> #DIV/0! | CD91: =CD83/BX83-1 -> #DIV/0! | CE91: =CE83/BY83-1 -> #DIV/0! | CF91: =CF83/BZ83-1 -> #DIV/0! | CG91: =CG83/CA83-1 -> #DIV/0! | CH91: =CH83/CB83-1 -> #DIV/0! | CJ91: =CJ83/CD83-1 -> #DIV/0! | CK91: =CK83/CE83-1 -> #DIV/0! | CL91: =CL83/CF83-1 -> #DIV/0! | CM91: =CM83/CG83-1 -> #DIV/0! | CN91: =CN83/CH83-1 -> #DIV/0!
B92: Growth YoY (%) | J92: =J84/D84-1 -> 0.33077766 | K92: =K84/E84-1 -> 0.24814362 | L92: =L84/F84-1 -> 0.1913563 | M92: =M84/G84-1 -> 0.11776283 | N92: =N84/H84-1 -> 0.21431249 | P92: =P84/J84-1 -> 0.047242798 | Q92: =Q84/K84-1 -> 0.029520295 | R92: =R84/L84-1 -> -0.061819321 | S92: =S84/M84-1 -> -0.091269259 | T92: =T84/N84-1 -> -0.020589711 | V92: =V84/P84-1 -> -0.2208425 | W92: =W84/Q84-1 -> -0.31899642 | X92: =X84/R84-1 -> -0.22933022 | Y92: =Y84/S84-1 -> -0.14661715 | Z92: =Z84/T84-1 -> -0.23116934 | AB92: =AB84/V84-1 -> 0.12880775 | AC92: =AC84/W84-1 -> 0.30966702 | AD92: =AD84/X84-1 -> 0.26863893 | AE92: =AE84/Y84-1 -> 0.23907285 | AF92: =AF84/Z84-1 -> 0.23489314 | AH92: =AH84/AB84-1 -> 0.151461 | AI92: =AI84/AC84-1 -> 0.11039121 | AJ92: =AJ84/AD84-1 -> 0.2196122 | AK92: =AK84/AE84-1 -> 0.21180423 | AL92: =AL84/AF84-1 -> 0.17402673 | AN92: =AN84/AH84-1 -> 0.17173677 | AO92: =AO84/AI84-1 -> 0.22202526 | AP92: =AP84/AJ84-1 -> 0.11976467 | AQ92: =AQ84/AK84-1 -> 0.023060929 | AR92: =AR84/AL84-1 -> 0.12894616 | AT92: =AT84/AN84-1 -> -0.0092059077 | AU92: =AU84/AO84-1 -> -0.042611061 | AV92: =AV84/AP84-1 -> -0.047348011 | AW92: =AW84/AQ84-1 -> -0.026137833 | AX92: =AX84/AR84-1 -> -0.031711785 | AZ92: =AZ84/AT84-1 -> -0.029872995 | BA92: =BA84/AU84-1 -> -0.017881944 | BB92: =BB84/AV84-1 -> 0.00211017 | BC92: =BC84/AW84-1 -> 0.014077508 | BD92: =BD84/AX84-1 -> -0.0076872627 | BF92: =BF84/AZ84-1 -> 0.047262473 | BG92: =BG84/BA84-1 -> 0.047249972 | BH92: =BH84/BB84-1 -> 0.047140929 | BI92: =BI84/BC84-1 -> 0.046918491 | BJ92: =BJ84/BD84-1 -> 0.047139194 | BL92: =BL84/BF84-1 -> 0.040882712 | BM92: =BM84/BG84-1 -> 0.041106523 | BN92: =BN84/BH84-1 -> 0.04099458 | BO92: =BO84/BI84-1 -> 0.041229443 | BP92: =BP84/BJ84-1 -> 0.041057857 | BR92: =BR84/BL84-1 -> 0.040951229 | BS92: =BS84/BM84-1 -> 0.041175115 | BT92: =BT84/BN84-1 -> 0.041063214 | BU92: =BU84/BO84-1 -> 0.041302438 | BV92: =BV84/BP84-1 -> 0.041127608 | BX92: =BX84/BR84-1 -> 0.0410195 | BY92: =BY84/BS84-1 -> 0.041243436 | BZ92: =BZ84/BT84-1 -> 0.041131574 | CA92: =CA84/BU84-1 -> 0.041375056 | CB92: =CB84/BV84-1 -> 0.041197066 | CD92: =CD84/BX84-1 -> 0.04108752 | CE92: =CE84/BY84-1 -> 0.041311483 | CF92: =CF84/BZ84-1 -> 0.041199658 | CG92: =CG84/CA84-1 -> 0.041447296 | CH92: =CH84/CB84-1 -> 0.041266228 | CJ92: =CJ84/CD84-1 -> 0.041155287 | CK92: =CK84/CE84-1 -> 0.04137925 | CL92: =CL84/CF84-1 -> 0.041267461 | CM92: =CM84/CG84-1 -> 0.041519155 | CN92: =CN84/CH84-1 -> 0.041335091
B94: Application Revenue Mix (%)
B95: Construction Industries | D95: =D79/D$84 -> 0.449069 | E95: =E79/E$84 -> 0.46611524 | F95: =F79/F$84 -> 0.4560814 | G95: =G79/G$84 -> 0.43422995 | H95: =H79/H$84 -> 0.45083888 | J95: =J79/J$84 -> 0.4672428 | K95: =K79/K$84 -> 0.46479404 | L95: =L79/L$84 -> 0.44527149 | M95: =M79/M$84 -> 0.418562 | N95: =N79/N$84 -> 0.44840029 | P95: =P79/P$84 -> 0.46156869 | Q95: =Q79/Q$84 -> 0.47304513 | R95: =R79/R$84 -> 0.44170703 | S95: =S79/S$84 -> 0.4052963 | T95: =T79/T$84 -> 0.44624175 | V95: =V79/V$84 -> 0.43433528 | W95: =W79/W$84 -> 0.43480129 | X95: =X79/X$84 -> 0.43953186 | Y95: =Y79/Y$84 -> 0.42649007 | Z95: =Z79/Z$84 -> 0.4335503 | AB95: =AB79/AB$84 -> 0.4878027 | AC95: =AC79/AC$84 -> 0.46387271 | AD95: =AD79/AD$84 -> 0.44887674 | AE95: =AE79/AE$84 -> 0.43796289 | AF95: =AF79/AF$84 -> 0.45874492 | AH95: =AH79/AH$84 -> 0.47454602 | AI95: =AI79/AI$84 -> 0.4456016 | AJ95: =AJ79/AJ$84 -> 0.43955736 | AK95: =AK79/AK$84 -> 0.43128977 | AL95: =AL79/AL$84 -> 0.44665394 | AN95: =AN79/AN$84 -> 0.44678456 | AO95: =AO79/AO$84 -> 0.43239649 | AP95: =AP79/AP$84 -> 0.43776582 | AQ95: =AQ79/AQ$84 -> 0.40149042 | AR95: =AR79/AR$84 -> 0.42928494 | AT95: =AT79/AT$84 -> 0.42941176 | AU95: =AU79/AU$84 -> 0.42190657 | AV95: =AV79/AV$84 -> 0.4165846 | AW95: =AW79/AW$84 -> 0.38199284 | AX95: =AX79/AX$84 -> 0.41220595 | AZ95: =AZ79/AZ$84 -> 0.40375936 | BA95: =BA79/BA$84 -> 0.3888505 | BB95: =BB79/BB$84 -> 0.39235046 | BC95: =BC79/BC$84 -> 0.36608956 | BD95: =BD79/BD$84 -> 0.3872995 | BF95: =BF79/BF$84 -> 0.40473254 | BG95: =BG79/BG$84 -> 0.38979488 | BH95: =BH79/BH$84 -> 0.39334351 | BI95: =BI79/BI$84 -> 0.36709265 | BJ95: =BJ79/BJ$84 -> 0.3882798 | BL95: =BL79/BL$84 -> 0.40203654 | BM95: =BM79/BM$84 -> 0.38711701 | BN95: =BN79/BN$84 -> 0.39073188 | BO95: =BO79/BO$84 -> 0.36460762 | BP95: =BP79/BP$84 -> 0.38566288 | BR95: =BR79/BR$84 -> 0.39934295 | BS95: =BS79/BS$84 -> 0.38444251 | BT95: =BT79/BT$84 -> 0.38812251 | BU95: =BU79/BU$84 -> 0.36212391 | BV95: =BV79/BV$84 -> 0.38304828 | BX95: =BX79/BX$84 -> 0.39665203 | BY95: =BY79/BY$84 -> 0.38177163 | BZ95: =BZ79/BZ$84 -> 0.38551564 | CA95: =CA79/CA$84 -> 0.35964181 | CB95: =CB79/CB$84 -> 0.38043627 | CD95: =CD79/CD$84 -> 0.39396404 | CE95: =CE79/CE$84 -> 0.37910461 | CF95: =CF79/CF$84 -> 0.38291152 | CG95: =CG79/CG$84 -> 0.35716163 | CH95: =CH79/CH$84 -> 0.3778271 | CJ95: =CJ79/CJ$84 -> 0.39127921 | CK95: =CK79/CK$84 -> 0.37644171 | CL95: =CL79/CL$84 -> 0.3803104 | CM95: =CM79/CM$84 -> 0.35468365 | CN95: =CN79/CN$84 -> 0.37522105
B96: Resource Industries | D96: =D80/D$84 -> 0.19288061 | E96: =E80/E$84 -> 0.17257261 | F96: =F80/F$84 -> 0.18258191 | G96: =G80/G$84 -> 0.18927341 | H96: =H80/H$84 -> 0.18420189 | J96: =J80/J$84 -> 0.19004115 | K96: =K80/K$84 -> 0.19022517 | L96: =L80/L$84 -> 0.20669122 | M96: =M80/M$84 -> 0.2052091 | N96: =N80/N$84 -> 0.19817838 | P96: =P80/P$84 -> 0.21628419 | Q96: =Q80/Q$84 -> 0.20620291 | R96: =R80/R$84 -> 0.19291799 | S96: =S80/S$84 -> 0.19336347 | T96: =T80/T$84 -> 0.20246281 | V96: =V80/V$84 -> 0.21020779 | W96: =W80/W$84 -> 0.19613319 | X96: =X80/X$84 -> 0.19679237 | Y96: =Y80/Y$84 -> 0.20624409 | Z96: =Z80/Z$84 -> 0.20260366 | AB96: =AB80/AB$84 -> 0.19462068 | AC96: =AC80/AC$84 -> 0.20889035 | AD96: =AD80/AD$84 -> 0.20210131 | AE96: =AE80/AE$84 -> 0.20760479 | AF96: =AF80/AF$84 -> 0.20357765 | AH96: =AH80/AH$84 -> 0.21961819 | AI96: =AI80/AI$84 -> 0.21870153 | AJ96: =AJ80/AJ$84 -> 0.21620675 | AK96: =AK80/AK$84 -> 0.21649549 | AL96: =AL80/AL$84 -> 0.21766182 | AN96: =AN80/AN$84 -> 0.22696867 | AO96: =AO80/AO$84 -> 0.21535207 | AP96: =AP80/AP$84 -> 0.2095947 | AQ96: =AQ80/AQ$84 -> 0.19966743 | AR96: =AR80/AR$84 -> 0.21266968 | AT96: =AT80/AT$84 -> 0.21343583 | AU96: =AU80/AU$84 -> 0.20239899 | AV96: =AV80/AV$84 -> 0.19880507 | AW96: =AW80/AW$84 -> 0.18915928 | AX96: =AX80/AX$84 -> 0.20079847 | AZ96: =AZ80/AZ$84 -> 0.19914422 | BA96: =BA80/BA$84 -> 0.19972038 | BB96: =BB80/BB$84 -> 0.20289665 | BC96: =BC80/BC$84 -> 0.1915699 | BD96: =BD80/BD$84 -> 0.19824443 | BF96: =BF80/BF$84 -> 0.19755267 | BG96: =BG80/BG$84 -> 0.19814132 | BH96: =BH80/BH$84 -> 0.20131279 | BI96: =BI80/BI$84 -> 0.1901133 | BJ96: =BJ80/BJ$84 -> 0.19669365 | BL96: =BL80/BL$84 -> 0.19718287 | BM96: =BM80/BM$84 -> 0.19774207 | BN96: =BN80/BN$84 -> 0.20092812 | BO96: =BO80/BO$84 -> 0.18970575 | BP96: =BP80/BP$84 -> 0.19630245 | BR96: =BR80/BR$84 -> 0.19680837 | BS96: =BS80/BS$84 -> 0.19733769 | BT96: =BT80/BT$84 -> 0.20053817 | BU96: =BU80/BU$84 -> 0.18929267 | BV96: =BV80/BV$84 -> 0.19590606 | BX96: =BX80/BX$84 -> 0.19642897 | BY96: =BY80/BY$84 -> 0.19692801 | BZ96: =BZ80/BZ$84 -> 0.20014277 | CA96: =CA80/CA$84 -> 0.1888739 | CB96: =CB80/CB$84 -> 0.19550433 | CD96: =CD80/CD$84 -> 0.19604449 | CE96: =CE80/CE$84 -> 0.19651286 | CF96: =CF80/CF$84 -> 0.19974174 | CG96: =CG80/CG$84 -> 0.18844932 | CH96: =CH80/CH$84 -> 0.19509708 | CJ96: =CJ80/CJ$84 -> 0.19565475 | CK96: =CK80/CK$84 -> 0.19609211 | CL96: =CL80/CL$84 -> 0.19933493 | CM96: =CM80/CM$84 -> 0.1880188 | CN96: =CN80/CN$84 -> 0.19468417
