Workbook
Name circ: Cover!#REF!
Name g: #REF!
Name IQ_CH: 110000
Name IQ_CQ: 5000
Name IQ_CY: 10000
Name IQ_DAILY: 500000
Name IQ_FH: 100000
Name IQ_FQ: 500
Name IQ_FY: 1000
Name IQ_LTM: 2000
Name IQ_MONTH: 15000
Name IQ_NTM: 6000
Name IQ_WEEK: 50000
Name IQ_YTD: 3000
Name wacc: #REF!

Sheet Cover
A1: =Cover!C3 -> TechCo
B3: Company name: | C3: TechCo
B4: Last Actual Year End: | C4: 42735
B5: Name: | C5: <Analyst Name>

Sheet IS
A1: =Cover!C3 -> TechCo | C1: Hist. | D1: Hist.
C2: =DATE(YEAR($D$2)-1,MONTH($D$2),DAY($D$2)) -> 42369 | D2: =Cover!C4 -> 42735
A3: Assumptions
B5: Lightspeed Market Growth | D5: =+D25/C25-1 -> 0.1
B6: Lightspeed Market Share | C6: =+C26/C25 -> 0.06 | D6: =+D26/D25 -> 0.1
B7: Lightspeed Unit Price Growth
B9: Support Services % Sell-Through
B10: Churn
B11: Support Services Monthly ARPU Per Unit ($)
B12: Customer Service Cost Per Unit Per Month ($)
B14: Cost of goods sold as % of sales | C14: =C43/C41*(-1) -> 0.33333333 | D14: =D43/D41*(-1) -> 0.20779221
B15: SG&A Growth | D15: =+D45/C45-1 -> 0.1
B17: Amortization amount | C17: =IS!C49 -> -50 | D17: =IS!D49 -> -50
B18: Effective tax rate | C18: =-C55/C53 -> 0 | D18: =-D55/D53 -> 0.3
B19: Dividend payout ratio | C19: =C58/C56*(-1) -> 0 | D19: =D58/D56*(-1) -> 0
A21: Income statement
B23: Lightspeed
B25: Semi Chip Market Size (MM units) | C25: 5000 | D25: 5500
B26: Units Sold (MM) | C26: 300 | D26: 550
B27: Lightspeed Unit Price ($) | C27: 1 | D27: 1.05
B28: Lightspeed Revenue | C28: =+C26*C27 -> 300 | D28: =+D26*D27 -> 577.5
B30: Subscription Services
B35: SS EoP | D35: 0
B37: Subscription Services Revenue | D37: 0
B38: SS Penetration % | D38: =+D35/SUM($C26:D26) -> 0
B41: Revenue | C41: =+C28+C37 -> 300 | D41: =+D28+D37 -> 577.5
B43: Cost of goods sold | C43: -100 | D43: -120
B44: Customer Support | C44: 0 | D44: 0
B45: SG&A | C45: -100 | D45: -110
B46: EBITDA | C46: =SUM(C41:C45) -> 100 | D46: =SUM(D41:D45) -> 347.5
B48: Amortization | C48: -25 | D48: -25
B49: Depreciation | C49: -50 | D49: -50
B50: EBIT | C50: =SUM(C46, C48:C49) -> 25 | D50: =SUM(D46, D48:D49) -> 272.5
B52: Interest expense | C52: -56.25 | D52: -56.25
B53: Profit before tax | C53: =SUM(C50, C52:C52) -> -31.25 | D53: =SUM(D50, D52:D52) -> 216.25
B55: Tax expense | C55: =MIN(0,-C53*0.3) -> 0 | D55: =MIN(0,-D53*0.3) -> -64.875
B56: Net income | C56: =C53+C55 -> -31.25 | D56: =D53+D55 -> 151.375
B58: Dividends | C58: 0 | D58: 0

Sheet BS
A1: =Cover!C3 -> TechCo | C1: Hist. | D1: Hist.
C2: =DATE(YEAR($D$2)-1,MONTH($D$2),DAY($D$2)) -> 42369 | D2: =Cover!C4 -> 42735
A3: Assumptions
B4: Accounts Receivable Days | C4: =+C12/IS!C41*365 -> 60.833333 | D4: =+D12/IS!D41*365 -> 63.203463
B5: Inventory Days | C5: =-C13/IS!C43*365 -> 36.5 | D5: =-D13/IS!D43*365 -> 36.5
B6: Other current assets % of sales | C6: =C14/IS!C41 -> 0.16666667 | D6: =D14/IS!D41 -> 0.17316017
B7: Accounts Payable Days | C7: =-C26/IS!C43*365 -> 36.5 | D7: =-D26/IS!D43*365 -> 36.5
B8: Other current liabilities % of sales | C8: =C27/IS!C41 -> 0.16666667 | D8: =D27/IS!D41 -> 0.17316017
A10: Balance sheet
B11: Cash | C11: 600 | D11: 541.375
B12: Accounts receivable | C12: 50 | D12: 100
B13: Inventories | C13: 10 | D13: 12
B14: Other current assets | C14: 50 | D14: 100
B15: Total current assets | C15: =SUM(C11:C14) -> 710 | D15: =SUM(D11:D14) -> 753.375
B17: Intangible Assets | C17: 100 | D17: 120
B18: Property, plant & equipment, net | C18: 250 | D18: 350
B19: Other assets | C19: 25 | D19: 80
B20: Goodwill
B21: Capitalised fees
B22: Total non-current assets | C22: =SUM(C17:C21) -> 375 | D22: =SUM(D17:D21) -> 550
B24: TOTAL ASSETS | C24: =+C22+C15 -> 1085 | D24: =+D22+D15 -> 1303.375
B26: Accounts payable | C26: 10 | D26: 12
B27: Other current liabilities | C27: 50 | D27: 100
B28: Total current liabilities | C28: =SUM(C26:C27) -> 60 | D28: =SUM(D26:D27) -> 112
B30: Long-term debt, including current maturities | C30: 750 | D30: 750
B31: Other long-term liabilities | C31: 30 | D31: 45
B32: Total non-current liabilities | C32: =SUM(C30:C31) -> 780 | D32: =SUM(D30:D31) -> 795
B34: Equity | C34: 245 | D34: 396.375
B35: TOTAL LIABILITIES & EQUITY | C35: =+C32+C34+C28 -> 1085 | D35: =+D32+D34+D28 -> 1303.375
B37: Balance check | C37: =+C35=C24 -> TRUE | D37: =+D35=D24 -> TRUE
C38: =C35-C24 -> 0 | D38: =D35-D24 -> 0

Sheet CF
A1: =Cover!C3 -> TechCo | C1: Hist. | D1: Hist.
C2: =DATE(YEAR($D$2)-1,MONTH($D$2),DAY($D$2)) -> 42369 | D2: =Cover!C4 -> 42735
B10: Operating cash flow
B13: Investing cash flow
B19: Financing cash flow
B21: Net cash flow
A23: Cash analysis
B25: BoP Cash
B26: Net Cash Flow
B27: EoP Cash

Sheet Calcs
A1: =Cover!C3 -> TechCo | C1: Hist. | D1: Hist.
C2: =DATE(YEAR($D$2)-1,MONTH($D$2),DAY($D$2)) -> 42369 | D2: =Cover!C4 -> 42735
A3: Net Intangibles
B5: Capital expenditure % of sales | C5: =C9/IS!C41 -> 0.16666667 | D5: =D9/IS!D41 -> 0.20779221
B6: Amortization % of beginning Intangible Assets | D6: =IS!D48/BS!C17*(-1) -> 0.25
B8: Beginning Intangibles
B9: Capex | C9: 50 | D9: 120
B10: Depreciation
B11: Ending Intangibles | D11: =BS!D17 -> 120
A13: Equity
A15: NWC
A17: Long term debt

Sheet Returns
A1: =Cover!C3 -> TechCo
B4: Share price
B5: Premium (%)
B6: Purchase price | C6: =+C4*(1+C5) -> 0
B7: NOSH
B8: Equity value | C8: =+C6*C7 -> 0
B9: Net debt
B10: EV
