Workbook
Name circ: Model!$T$6
Name IQ_CH: 110000
Name IQ_CQ: 5000
Name IQ_CY: 10000
Name IQ_DAILY: 500000
Name IQ_FH: 100000
Name IQ_FQ: 500
Name IQ_FY: 1000
Name IQ_LTM: 2000
Name IQ_MONTH: 15000
Name IQ_NTM: 6000
Name IQ_WEEK: 50000
Name IQ_YTD: 3000

Sheet Model
A1: unless otherwise stated, in HKDm
A2: Dec year end, assume txn close on 31 Dec 2017
A3: x | B3: Transaction assumptions
C4: Entry assumptions | H4: Sources | L4: Uses | P4: Switches
C5: FY17 EBITDA | F5: =+K44 -> 376.3 | H5: 1L debt | J5: =+F11*G44 -> 1899 | L5: Purchase EV | N5: =+F7 -> 3988.78 | P5: Revenue case | T5: 2 | U5: =+CHOOSE(T5, "Mgmt. case", "Adj. mgmt. case") -> Adj. mgmt. case
C6: EBITDA multiple | F6: 10.6 | H6: 2L debt | J6: =+F17*G44 -> 633 | L6: Refi existing debt | N6: =+H82 -> 1511 | P6: Circularity | T6: 1
C7: Purchase EV | F7: =+F6*F5 -> 3988.78 | H7: Total equity | J7: =+J11-J5-J6-J10 -> 2843.6278 | L7: M&A fees | N7: =+N5*L14 -> 39.8878 | P7: Adjsutments to mgmt. case
H8: Sponsor equity | J8: =+J7-J9 -> 2132.7209 | L8: Financing fees | N8: =+L15*(J6+J5) -> 75.96 | P8: Growth of customers | T8: =+RevBuild!R8 -> 1
H9: Mgmt roll | J9: =+L13*J7 -> 710.90695 | L9: Minimum cash | N9: 150 | P9: Expansion of SoW | T9: =+RevBuild!R9 -> 1
C10: 1L TL assumptions | H10: Cash on BS | J10: =+H63 -> 390 | P10: E-commerce | T10: =+RevBuild!R10 -> 1
C11: Quantum, FY16 EBITDA | F11: 6 | H11: Total | J11: =+N11 -> 5765.6278 | L11: Total | N11: =+SUM(N5:N9) -> 5765.6278 | P11: Cross selling | T11: =+RevBuild!R11 -> 0
C12: Cash interest | F12: 0.07 | P12: Growth from other customers | T12: =+RevBuild!R12 -> 0
C13: Maturity (years) | F13: 5 | H13: Mgmt roll | L13: 0.25
C14: Sweep | F14: 1 | H14: M&A fees % of EV | L14: 0.01
H15: Financing fees % of debt load | L15: 0.03
C16: 2L assumptions
C17: Quantum, FY16 EBITDA | F17: 2 | H17: HKD/USD | L17: 0.13
C18: Cash interest | F18: 0.09
C19: Maturity (years) | F19: 7 | H19: PG equity ticket (USDm) | L19: =+J8*L17 -> 277.25371
C20: Sweep | F20: 0
F22: Investment year count | K22: 0 | L22: =+K22+1 -> 1 | M22: =+L22+1 -> 2 | N22: =+M22+1 -> 3 | O22: =+N22+1 -> 4 | P22: =+O22+1 -> 5 | V22: 0 | W22: =+V22+1 -> 1 | X22: =+W22+1 -> 2 | Y22: =+X22+1 -> 3 | Z22: =+Y22+1 -> 4 | AA22: =+Z22+1 -> 5
F23: Year | G23: =+K23-1 -> 2016 | K23: 2017 | L23: =+K23+1 -> 2018 | M23: =+L23+1 -> 2019 | N23: =+M23+1 -> 2020 | O23: =+N23+1 -> 2021 | P23: =+O23+1 -> 2022 | Q23: 5Y CAGR | V23: 2017 | W23: =+V23+1 -> 2018 | X23: =+W23+1 -> 2019 | Y23: =+X23+1 -> 2020 | Z23: =+Y23+1 -> 2021 | AA23: =+Z23+1 -> 2022
A24: x | B24: Income statement | T24: LBO output and credit metrics
C25: Revenue | G25: 1220 | K25: =+CHOOSE($T$5, K27,K28) -> 1296 | L25: =+CHOOSE($T$5, L27,L28) -> 1400.6 | M25: =+CHOOSE($T$5, M27,M28) -> 1505.2 | N25: =+CHOOSE($T$5, N27,N28) -> 1609.8 | O25: =+CHOOSE($T$5, O27,O28) -> 1714.4 | P25: =+CHOOSE($T$5, P27,P28) -> 1819 | Q25: =+(P25/K25)^(1/$P$22)-1 -> 0.070152177 | T25: EBITDA | Y25: =+N44 -> 483.65953 | Z25: =+O44 -> 525.38852 | AA25: =+P44 -> 569.54035
C26: YoY % | K26: =+K25/G25-1 -> 0.062295082 | L26: =+L25/K25-1 -> 0.080709877 | M26: =+M25/L25-1 -> 0.074682279 | N26: =+N25/M25-1 -> 0.069492426 | O26: =+O25/N25-1 -> 0.064977016 | P26: =+P25/O25-1 -> 0.061012599 | T26: Exit multiple | Y26: 14 | Z26: 14 | AA26: 14 | AB26: << Avery trading price
C27: Memo: mgmt. projections | K27: 1296 | L27: 1384 | M27: 1490 | N27: 1621 | O27: 1769 | P27: 1938 | T27: Exit EV | Y27: =+Y26*Y25 -> 6771.2334 | Z27: =+Z26*Z25 -> 7355.4393 | AA27: =+AA26*AA25 -> 7973.5649
C28: Adj. mgmt. projections | K28: =+RevBuild!K13 -> 1296 | L28: =+RevBuild!L13 -> 1400.6 | M28: =+RevBuild!M13 -> 1505.2 | N28: =+RevBuild!N13 -> 1609.8 | O28: =+RevBuild!O13 -> 1714.4 | P28: =+RevBuild!P13 -> 1819
T29: (-) net debt | Y29: =+Y37 -> 1669.3782 | Z29: =+Z37 -> 1312.5689 | AA29: =+AA37 -> 885.84878
C30: COGS | G30: -600 | K30: =+CHOOSE($T$5, K32,K33) -> -618 | L30: =+CHOOSE($T$5, L32,L33) -> -668.92818 | M30: =+CHOOSE($T$5, M32,M33) -> -719.26336 | N30: =+CHOOSE($T$5, N32,N33) -> -769.64528 | O30: =+CHOOSE($T$5, O32,O33) -> -820.85743 | P30: =+CHOOSE($T$5, P32,P33) -> -872.89474 | T30: Exit EqV | Y30: =+Y27-Y29 -> 5101.8553 | Z30: =+Z27-Z29 -> 6042.8705 | AA30: =+AA27-AA29 -> 7087.7161
C31: % of sales | G31: =+G30/G25*-1 -> 0.49180328 | K31: =+K30/K25*-1 -> 0.47685185 | L31: =+L30/L25*-1 -> 0.47760116 | M31: =+M30/M25*-1 -> 0.47785235 | N31: =+N30/N25*-1 -> 0.47809994 | O31: =+O30/O25*-1 -> 0.47880158 | P31: =+P30/P25*-1 -> 0.47987616
C32: Memo: mgmt. projections | K32: -618 | L32: -661 | M32: -712 | N32: -775 | O32: -847 | P32: -930 | T32: MOIC | Y32: =+Y30/$J$7 -> 1.7941361 | Z32: =+Z30/$J$7 -> 2.1250568 | AA32: =+AA30/$J$7 -> 2.4924908
C33: Adj. mgmt. projections | K33: =+K32/K$27*K$28 -> -618 | L33: =+L32/L$27*L$28 -> -668.92818 | M33: =+M32/M$27*M$28 -> -719.26336 | N33: =+N32/N$27*N$28 -> -769.64528 | O33: =+O32/O$27*O$28 -> -820.85743 | P33: =+P32/P$27*P$28 -> -872.89474 | T33: IRR | Y33: =+Y32^(1/Y22)-1 -> 0.21511802 | Z33: =+Z32^(1/Z22)-1 -> 0.20737626 | AA33: =+AA32^(1/AA22)-1 -> 0.20040201
C35: Gross profit | G35: =+G30+G25 -> 620 | K35: =+K30+K25 -> 678 | L35: =+L30+L25 -> 731.67182 | M35: =+M30+M25 -> 785.93664 | N35: =+N30+N25 -> 840.15472 | O35: =+O30+O25 -> 893.54257 | P35: =+P30+P25 -> 946.10526 | Q35: =+(P35/K35)^(1/$P$22)-1 -> 0.068912001 | T35: Credit metrics
T36: Total debt | V36: =+K77+K80+K81 -> 2532 | W36: =+L77+L80+L81 -> 2349.4784 | X36: =+M77+M80+M81 -> 2113.3458 | Y36: =+N77+N80+N81 -> 1819.3782 | Z36: =+O77+O80+O81 -> 1462.5689 | AA36: =+P77+P80+P81 -> 1035.8488
C37: SG&A | G37: -317 | K37: =+CHOOSE($T$5, K39,K40) -> -316 | L37: =+CHOOSE($T$5, L39,L40) -> -341.04205 | M37: =+CHOOSE($T$5, M39,M40) -> -359.63168 | N37: =+CHOOSE($T$5, N39,N40) -> -374.39519 | O37: =+CHOOSE($T$5, O39,O40) -> -387.65404 | P37: =+CHOOSE($T$5, P39,P40) -> -397.96491 | T37: Net debt | V37: =+V36-K63 -> 2382 | W37: =+W36-L63 -> 2199.4784 | X37: =+X36-M63 -> 1963.3458 | Y37: =+Y36-N63 -> 1669.3782 | Z37: =+Z36-O63 -> 1312.5689 | AA37: =+AA36-P63 -> 885.84878
C38: % of sales | K38: =+K37/K25*-1 -> 0.24382716 | L38: =+L37/L25*-1 -> 0.24349711 | M38: =+M37/M25*-1 -> 0.23892617 | N38: =+N37/N25*-1 -> 0.23257249 | O38: =+O37/O25*-1 -> 0.22611645 | P38: =+P37/P25*-1 -> 0.21878225
C39: Memo: mgmt. projections | K39: -316 | L39: -337 | M39: -356 | N39: -377 | O39: -400 | P39: -424 | T39: Debt / EBITDA | V39: =+V36/K44 -> 6.7286739 | W39: =+W36/L44 -> 5.7878938 | X39: =+X36/M44 -> 4.7737115 | Y39: =+Y36/N44 -> 3.7616919 | Z39: =+Z36/O44 -> 2.7837853 | AA39: =+AA36/P44 -> 1.8187452
C40: Adj. mgmt. projections | K40: =+K39/K$27*K$28 -> -316 | L40: =+L39/L$27*L$28 -> -341.04205 | M40: =+M39/M$27*M$28 -> -359.63168 | N40: =+N39/N$27*N$28 -> -374.39519 | O40: =+O39/O$27*O$28 -> -387.65404 | P40: =+P39/P$27*P$28 -> -397.96491 | T40: ND / EBITDA | V40: =+V37/K44 -> 6.3300558 | W40: =+W37/L44 -> 5.4183717 | X40: =+X37/M44 -> 4.4348853 | Y40: =+Y37/N44 -> 3.4515564 | Z40: =+Z37/O44 -> 2.4982823 | AA40: =+AA37/P44 -> 1.5553749
C42: Other income / (losses) | G42: 13.5 | K42: 14.3 | L42: 15.3 | M42: 16.4 | N42: 17.9 | O42: 19.5 | P42: 21.4 | T42: EBIT / interest | W42: =+L50/L53*-1 -> 1.4213116 | X42: =+M50/M53*-1 -> 1.7599562 | Y42: =+N50/N53*-1 -> 2.2468951 | Z42: =+O50/O53*-1 -> 2.9721355 | AA42: =+P50/P53*-1 -> 4.2232253
C44: EBITDA | G44: =+G42+G37+G35 -> 316.5 | K44: =+K42+K37+K35 -> 376.3 | L44: =+L42+L37+L35 -> 405.92977 | M44: =+M42+M37+M35 -> 442.70497 | N44: =+N42+N37+N35 -> 483.65953 | O44: =+O42+O37+O35 -> 525.38852 | P44: =+P42+P37+P35 -> 569.54035 | Q44: =+(P44/K44)^(1/$P$22)-1 -> 0.086420761 | T44: Ability to pay analysis
C45: % margin | K45: =+K44/K25 -> 0.29035494 | L45: =+L44/L25 -> 0.28982562 | M45: =+M44/M25 -> 0.29411704 | N45: =+N44/N25 -> 0.30044697 | O45: =+O44/O25 -> 0.30645621 | P45: =+P44/P25 -> 0.3131063 | T45: IRR target | Y45: 0.2 | Z45: 0.2 | AA45: 0.2
T46: Exit EqV | Y46: =+Y30 -> 5101.8553 | Z46: =+Z30 -> 6042.8705 | AA46: =+AA30 -> 7087.7161
C47: Depreciation & amortization | K47: -83 | L47: =+L116 -> -145.1024 | M47: =+M116 -> -145.5208 | N47: =+N116 -> -145.9392 | O47: =+O116 -> -146.3576 | P47: =+P116 -> -146.776
C48: Memo: mgmt. projections | K48: -83 | L48: -88 | M48: -95 | N48: -103 | O48: -113 | P48: -124 | T48: Required entry sponsor equity | Y48: =+Y46/(1+Y45)^Y22 -> 2952.4625 | Z48: =+Z46/(1+Z45)^Z22 -> 2914.1929 | AA48: =+AA46/(1+AA45)^AA22 -> 2848.3941
T49: (+) acquisition ND | Y49: =+$J$5+$J$6-$N$9 -> 2382 | Z49: =+$J$5+$J$6-$N$9 -> 2382 | AA49: =+$J$5+$J$6-$N$9 -> 2382
C50: EBIT | K50: =+K47+K44 -> 293.3 | L50: =+L47+L44 -> 260.82737 | M50: =+M47+M44 -> 297.18417 | N50: =+N47+N44 -> 337.72033 | O50: =+O47+O44 -> 379.03092 | P50: =+P47+P44 -> 422.76435 | T50: (-) fees | Y50: =+$N$7+$N$8 -> 115.8478 | Z50: =+$N$7+$N$8 -> 115.8478 | AA50: =+$N$7+$N$8 -> 115.8478
T51: (-) in place ND | Y51: =+$N$6-$J$10 -> 1121 | Z51: =+$N$6-$J$10 -> 1121 | AA51: =+$N$6-$J$10 -> 1121
C52: Amortization of DFF | L52: =+L119 -> -10.851429 | M52: =+M119 -> -10.851429 | N52: =+N119 -> -10.851429 | O52: =+O119 -> -10.851429 | P52: =+P119 -> -10.851429 | T52: Purchase price | Y52: =+Y48+Y49-Y50-Y51 -> 4097.6147 | Z52: =+Z48+Z49-Z50-Z51 -> 4059.3451 | AA52: =+AA48+AA49-AA50-AA51 -> 3993.5463
C53: Net interest expense | L53: =+IF(circ=1, L171, 0) -> -183.51174 | M53: =+IF(circ=1, M171, 0) -> -168.85885 | N53: =+IF(circ=1, N171, 0) -> -150.30534 | O53: =+IF(circ=1, O171, 0) -> -127.52815 | P53: =+IF(circ=1, P171, 0) -> -100.10462
T54: Entry EBITDA | Y54: =+$K$44 -> 376.3 | Z54: =+$K$44 -> 376.3 | AA54: =+$K$44 -> 376.3
C55: PBT | L55: =+L53+L52+L50 -> 66.464197 | M55: =+M53+M52+M50 -> 117.47389 | N55: =+N53+N52+N50 -> 176.56357 | O55: =+O53+O52+O50 -> 240.65135 | P55: =+P53+P52+P50 -> 311.8083 | T55: Entry multiple | Y55: =+Y52/Y54 -> 10.889223 | Z55: =+Z52/Z54 -> 10.787524 | AA55: =+AA52/AA54 -> 10.612666
C56: Tax rate | L56: 0.28 | M56: 0.28 | N56: 0.28 | O56: 0.28 | P56: 0.28
C58: Net income | L58: =+L55+(1-L56) -> 67.184197 | M58: =+M55+(1-M56) -> 118.19389 | N58: =+N55+(1-N56) -> 177.28357 | O58: =+O55+(1-O56) -> 241.37135 | P58: =+P55+(1-P56) -> 312.5283
K60: =+K22 -> 0 | L60: =+L22 -> 1 | M60: =+M22 -> 2 | N60: =+N22 -> 3 | O60: =+O22 -> 4 | P60: =+P22 -> 5
G61: =+K61-1 -> 2016 | K61: =+K23 -> 2017 | L61: =+L23 -> 2018 | M61: =+M23 -> 2019 | N61: =+N23 -> 2020 | O61: =+O23 -> 2021 | P61: =+P23 -> 2022
A62: x | B62: Balance Sheet | H62: 42916 | I62: Debit | J62: Credit | K62: PF
C63: Cash and equivalents | G63: 326 | H63: 390 | I63: =+N9 -> 150 | J63: =+H63 -> 390 | K63: =+H63+I63-J63 -> 150 | L63: =+L168 -> 150 | M63: =+M168 -> 150 | N63: =+N168 -> 150 | O63: =+O168 -> 150 | P63: =+P168 -> 150
C64: Inventories | G64: 92 | H64: 98 | K64: =+H64+I64-J64 -> 98 | L64: =+L98/365*L30*-1 -> 106.29544 | M64: =+M98/365*M30*-1 -> 114.2939 | N64: =+N98/365*N30*-1 -> 122.2998 | O64: =+O98/365*O30*-1 -> 130.43762 | P64: =+P98/365*P30*-1 -> 138.70656
C65: Trade receivables | G65: 173 | H65: 183 | K65: =+H65+I65-J65 -> 183 | L65: =+L99/365*L25 -> 199.53753 | M65: =+M99/365*M25 -> 214.43945 | N65: =+N99/365*N25 -> 229.34137 | O65: =+O99/365*O25 -> 244.24329 | P65: =+P99/365*P25 -> 259.14521
C66: Current assets | G66: =SUM(G63:G65) -> 591 | H66: =SUM(H63:H65) -> 671 | K66: =SUM(K63:K65) -> 431 | L66: =SUM(L63:L65) -> 455.83297 | M66: =SUM(M63:M65) -> 478.73336 | N66: =SUM(N63:N65) -> 501.64117 | O66: =SUM(O63:O65) -> 524.68091 | P66: =SUM(P63:P65) -> 547.85177
C68: PPE | G68: 128 | H68: 123 | K68: =+H68+I68-J68 -> 123 | L68: =+L109 -> 139.8072 | M68: =+M109 -> 157.8696 | N68: =+N109 -> 177.1872 | O68: =+O109 -> 197.76 | P68: =+P109 -> 219.588
C69: Intangible assets | G69: 1675 | H69: 1674 | K69: =+H69+I69-J69 -> 1674 | L69: =+L114 -> 1534.5 | M69: =+M114 -> 1395 | N69: =+N114 -> 1255.5 | O69: =+O114 -> 1116 | P69: =+P114 -> 976.5
C70: Other assets | G70: 45 | H70: 47 | K70: =+H70+I70-J70 -> 47 | L70: =+K70 -> 47 | M70: =+L70 -> 47 | N70: =+M70 -> 47 | O70: =+N70 -> 47 | P70: =+O70 -> 47
C71: Deferred financing fees | I71: =+N8 -> 75.96 | K71: =+H71+I71-J71 -> 75.96 | L71: =+L120 -> 65.108571 | M71: =+M120 -> 54.257143 | N71: =+N120 -> 43.405714 | O71: =+O120 -> 32.554286 | P71: =+P120 -> 21.702857
C72: Goodwill | I72: =+F95 -> 3539.78 | K72: =+H72+I72-J72 -> 3539.78 | L72: =+K72 -> 3539.78 | M72: =+L72 -> 3539.78 | N72: =+M72 -> 3539.78 | O72: =+N72 -> 3539.78 | P72: =+O72 -> 3539.78
C73: Non current assets | G73: =SUM(G68:G72) -> 1848 | H73: =SUM(H68:H72) -> 1844 | K73: =SUM(K68:K72) -> 5459.74 | L73: =SUM(L68:L72) -> 5326.1958 | M73: =SUM(M68:M72) -> 5193.9067 | N73: =SUM(N68:N72) -> 5062.8729 | O73: =SUM(O68:O72) -> 4933.0943 | P73: =SUM(P68:P72) -> 4804.5709
C75: Total assets | G75: =+G73+G66 -> 2439 | H75: =+H73+H66 -> 2515 | K75: =+K73+K66 -> 5890.74 | L75: =+L73+L66 -> 5782.0287 | M75: =+M73+M66 -> 5672.6401 | N75: =+N73+N66 -> 5564.5141 | O75: =+O73+O66 -> 5457.7752 | P75: =+P73+P66 -> 5352.4226
C77: Revolver | H77: 0 | K77: =+H77-I77+J77 -> 0 | L77: =+L151 -> 0 | M77: =+M151 -> 0 | N77: =+N151 -> 0 | O77: =+O151 -> 0 | P77: =+P151 -> 402.84878
C78: Accounts payables | G78: 108 | H78: 107 | K78: =+H78-I78+J78 -> 107 | L78: =+L100/365*L30*-1 -> 113.62616 | M78: =+M100/365*M30*-1 -> 122.17624 | N78: =+N100/365*N30*-1 -> 130.73427 | O78: =+O100/365*O30*-1 -> 139.43332 | P78: =+P100/365*P30*-1 -> 148.27253
C80: 1L debt | J80: =+J5 -> 1899 | K80: =+H80-I80+J80 -> 1899 | L80: =+L157 -> 1716.4784 | M80: =+M157 -> 1480.3458 | N80: =+N157 -> 1186.3782 | O80: =+O157 -> 829.56887 | P80: =+P157 -> 0
C81: 2L debt | J81: =+J6 -> 633 | K81: =+H81-I81+J81 -> 633 | L81: =+L163 -> 633 | M81: =+M163 -> 633 | N81: =+N163 -> 633 | O81: =+O163 -> 633 | P81: =+P163 -> 633
C82: Total borrowings | G82: 1566 | H82: 1511 | I82: =+H82 -> 1511 | K82: =+H82-I82+J82 -> 0
C83: Other liabilities | G83: 427 | H83: 448 | K83: =+H83-I83+J83 -> 448 | L83: =+K83 -> 448 | M83: =+L83 -> 448 | N83: =+M83 -> 448 | O83: =+N83 -> 448 | P83: =+O83 -> 448
C84: Total liabilities | G84: =SUM(G77:G83) -> 2101 | H84: =SUM(H77:H83) -> 2066 | K84: =SUM(K77:K83) -> 3087 | L84: =SUM(L77:L83) -> 2911.1045 | M84: =SUM(M77:M83) -> 2683.522 | N84: =SUM(N77:N83) -> 2398.1124 | O84: =SUM(O77:O83) -> 2050.0022 | P84: =SUM(P77:P83) -> 1632.1213
C86: Total equity | G86: =+G75-G84 -> 338 | H86: =+H75-H84 -> 449 | I86: =+H86+N7 -> 488.8878 | J86: =+J7 -> 2843.6278 | K86: =+H86-I86+J86 -> 2803.74 | L86: =+K86+L58 -> 2870.9242 | M86: =+L86+M58 -> 2989.1181 | N86: =+M86+N58 -> 3166.4017 | O86: =+N86+O58 -> 3407.773 | P86: =+O86+P58 -> 3720.3013
C88: CHECK | G88: =+G86+G84-G75 -> 0 | H88: =+H86+H84-H75 -> 0 | K88: =+K86+K84-K75 -> 0 | L88: =+L86+L84-L75 -> 0 | M88: =+M86+M84-M75 -> 0 | N88: =+N86+N84-N75 -> 0 | O88: =+O86+O84-O75 -> 0 | P88: =+P86+P84-P75 -> 0
C90: NWC | K90: =+K65+K64-K78 -> 174 | L90: =+L65+L64-L78 -> 192.20681 | M90: =+M65+M64-M78 -> 206.55711 | N90: =+N65+N64-N78 -> 220.9069 | O90: =+O65+O64-O78 -> 235.24759 | P90: =+P65+P64-P78 -> 249.57924
C92: Goodwill calcs
C93: Purchase price | F93: =+N5 -> 3988.78
C94: Net identifiable assets | F94: =+H86-H72 -> 449
C95: Goodwill | F95: =+F93-F94 -> 3539.78
A97: x | B97: Balance Sheet Calcs
C98: Inventory days | L98: 58 | M98: 58 | N98: 58 | O98: 58 | P98: 58
C99: Receivable days | L99: 52 | M99: 52 | N99: 52 | O99: 52 | P99: 52
C100: Payable days | L100: 62 | M100: 62 | N100: 62 | O100: 62 | P100: 62
C102: Maintenance capex % of revenue | L102: 0.004 | M102: 0.004 | N102: 0.004 | O102: 0.004 | P102: 0.004
C103: Growth capex % of revenue | L103: 0.012 | M103: 0.012 | N103: 0.012 | O103: 0.012 | P103: 0.012
C104: Total capex % of revenue | L104: =+L103+L102 -> 0.016 | M104: =+M103+M102 -> 0.016 | N104: =+N103+N102 -> 0.016 | O104: =+O103+O102 -> 0.016 | P104: =+P103+P102 -> 0.016
C106: BoP PPE | L106: =+K109 -> 123 | M106: =+L109 -> 139.8072 | N106: =+M109 -> 157.8696 | O106: =+N109 -> 177.1872 | P106: =+O109 -> 197.76
C107: Capex | L107: =+L104*L25 -> 22.4096 | M107: =+M104*M25 -> 24.0832 | N107: =+N104*N25 -> 25.7568 | O107: =+O104*O25 -> 27.4304 | P107: =+P104*P25 -> 29.104
C108: Depreciation | G108: % of revenue | I108: 0.004 | L108: =+$I$108*L25*-1 -> -5.6024 | M108: =+$I$108*M25*-1 -> -6.0208 | N108: =+$I$108*N25*-1 -> -6.4392 | O108: =+$I$108*O25*-1 -> -6.8576 | P108: =+$I$108*P25*-1 -> -7.276
C109: EoP PPE | K109: =+K68 -> 123 | L109: =+SUM(L106:L108) -> 139.8072 | M109: =+SUM(M106:M108) -> 157.8696 | N109: =+SUM(N106:N108) -> 177.1872 | O109: =+SUM(O106:O108) -> 197.76 | P109: =+SUM(P106:P108) -> 219.588
C111: BoP Intangibles | L111: =+K114 -> 1674 | M111: =+L114 -> 1534.5 | N111: =+M114 -> 1395 | O111: =+N114 -> 1255.5 | P111: =+O114 -> 1116
C112: Addition | L112: 0 | M112: 0 | N112: 0 | O112: 0 | P112: 0
C113: Amortization | G113: Useful life (years) | I113: 12 | L113: =+MIN(L111, $K$114/$I$113)*-1 -> -139.5 | M113: =+MIN(M111, $K$114/$I$113)*-1 -> -139.5 | N113: =+MIN(N111, $K$114/$I$113)*-1 -> -139.5 | O113: =+MIN(O111, $K$114/$I$113)*-1 -> -139.5 | P113: =+MIN(P111, $K$114/$I$113)*-1 -> -139.5
C114: EoP Intangibles | K114: =+K69 -> 1674 | L114: =+SUM(L111:L113) -> 1534.5 | M114: =+SUM(M111:M113) -> 1395 | N114: =+SUM(N111:N113) -> 1255.5 | O114: =+SUM(O111:O113) -> 1116 | P114: =+SUM(P111:P113) -> 976.5
C116: D&A (excl. DFF) | L116: =+L113+L108 -> -145.1024 | M116: =+M113+M108 -> -145.5208 | N116: =+N113+N108 -> -145.9392 | O116: =+O113+O108 -> -146.3576 | P116: =+P113+P108 -> -146.776
C118: BoP deferred financing fees | L118: =+K120 -> 75.96 | M118: =+L120 -> 65.108571 | N118: =+M120 -> 54.257143 | O118: =+N120 -> 43.405714 | P118: =+O120 -> 32.554286
C119: Amortization | G119: Useful life (years) | I119: 7 | L119: =+MIN(L118, $K$120/$I$119)*-1 -> -10.851429 | M119: =+MIN(M118, $K$120/$I$119)*-1 -> -10.851429 | N119: =+MIN(N118, $K$120/$I$119)*-1 -> -10.851429 | O119: =+MIN(O118, $K$120/$I$119)*-1 -> -10.851429 | P119: =+MIN(P118, $K$120/$I$119)*-1 -> -10.851429
C120: EoP deferred financing fees | K120: =+K71 -> 75.96 | L120: =SUM(L118:L119) -> 65.108571 | M120: =SUM(M118:M119) -> 54.257143 | N120: =SUM(N118:N119) -> 43.405714 | O120: =SUM(O118:O119) -> 32.554286 | P120: =SUM(P118:P119) -> 21.702857
...

Sheet RevBuild
K6: =+Model!K23 -> 2017 | L6: =+Model!L23 -> 2018 | M6: =+Model!M23 -> 2019 | N6: =+Model!N23 -> 2020 | O6: =+Model!O23 -> 2021 | P6: =+Model!P23 -> 2022 | R6: Switch
E7: 2017 revenue | K7: =+Model!K25 -> 1296 | P7: =+K7 -> 1296
E8: Growth of top 50 customers (excl e-comm) | P8: =248*R8 -> 248 | R8: 1
E9: Expansion of wallet share of top 50 customers (excl e-comm) | P9: =78*R9 -> 78 | R9: 1
E10: E-Commerce | P10: =197*R10 -> 197 | R10: 1
E11: Cross-selling | P11: =18*R11 -> 0 | R11: 0 | S11: << lack of evidence for ability to cross sell
E12: Revenue growth from other customers and new customers | P12: =102*R12 -> 0 | R12: 0 | S12: << lack of evidence on other customers and new customers
E13: Discounted mgmt base case | K13: =+SUM(K7:K12) -> 1296 | L13: =+($P$13-$K$13)/COUNTA($L$6:$P$6)+K13 -> 1400.6 | M13: =+($P$13-$K$13)/COUNTA($L$6:$P$6)+L13 -> 1505.2 | N13: =+($P$13-$K$13)/COUNTA($L$6:$P$6)+M13 -> 1609.8 | O13: =+($P$13-$K$13)/COUNTA($L$6:$P$6)+N13 -> 1714.4 | P13: =+SUM(P7:P12) -> 1819 | S13: << linear interpolation in years in between
