Workbook
Name _MailAutoSig: 'P&L'!$I$13
Name Case: Output!$C$6
Name Circ: Output!$C$7
Name IQ_CH: 110000
Name IQ_CQ: 5000
Name IQ_CY: 10000
Name IQ_DAILY: 500000
Name IQ_FH: 100000
Name IQ_FQ: 500
Name IQ_FY: 1000
Name IQ_LTM: 2000
Name IQ_MONTH: 15000
Name IQ_NTM: 6000
Name IQ_WEEK: 50000
Name IQ_YTD: 3000

Sheet Output
A1: in CADm unless otherwise stated
A2: FYE June
J3: 2023 | K3: =+J3+1 -> 2024 | L3: =+K3+1 -> 2025 | M3: =+L3+1 -> 2026 | N3: =+M3+1 -> 2027 | O3: =+N3+1 -> 2028 | P3: =+O3+1 -> 2029 | Q3: =+P3+1 -> 2030 | R3: =+Q3+1 -> 2031 | S3: =+R3+1 -> 2032
A5: x | B5: Cover
B6: Operating case | C6: 1 | D6: =+CHOOSE(Case, "Base", "Upside", "Downside") -> Base
B7: Circularity | C7: 1
B8: FX USDCAD (Bloomberg fwd) | J8: 1.3503 | K8: 1.344 | L8: 1.3365 | M8: 1.3303 | N8: 1.3236 | O8: 1.3172 | P8: 1.3128 | Q8: 1.3102 | R8: 1.3098 | S8: 1.3089
B10: Exit multiple (Content business)
B11: Base | C11: 15
B12: Upside | C12: 15
B13: Downside | C13: 11
A15: x | B15: Entry | G15: x | H15: Valuation
D16: 44958 | K16: 45473 | L16: =+EDATE(K16,12) -> 45838 | M16: =+EDATE(L16,12) -> 46203
B17: Capitalization | K17: FY2024 | L17: FY2025 | M17: FY2026 | O17: Bridge | P17: 2022 Entry | Q17: 2026 Exit | R17: Value | S17: % of value | T17: Bridge to TP
B18: Current share price (CAD) | D18: 2.81 | H18: Content | K18: =+K20-K19 -> 87.941836 | L18: =+L20-L19 -> 104.79601 | M18: =+M20-M19 -> 116.24059 | O18: Revenue | P18: =+'P&L'!I6 -> 507.223 | Q18: =+'P&L'!M6 -> 706.85889 | R18: =+(Q18-P18)*P19*P20/$M$31 -> 2.5559885 | S18: =+R18/$R$22 -> 1.0125636 | T18: =+$R$22*S18 -> 2.5559885
B19: Shares outstanding (mm) | D19: 173.117 | H19: TV | K19: =+'P&L'!K76 -> 14.970383 | L19: =+'P&L'!L76 -> 13.971568 | M19: =+'P&L'!M76 -> 13.012705 | O19: Margin | P19: =+'P&L'!I72 -> 0.14259043 | Q19: =+'P&L'!M72 -> 0.18285587 | R19: =+(Q19-P19)*Q18*P20/$M$31 -> 2.5556131 | S19: =+R19/$R$22 -> 1.0124149 | T19: =+$R$22*S19 -> 2.5556131
B20: Market cap (CADm) | D20: =+D18*D19 -> 486.45877 | H20: Total proportionate Adj. EBITDA | K20: =+'P&L'!K71 -> 102.91222 | L20: =+'P&L'!L71 -> 118.76757 | M20: =+'P&L'!M71 -> 129.25329 | O20: Multiple | P20: =+D28 -> 15.543886 | Q20: =+M26 -> 13.99324 | R20: =+(Q20-P20)*Q19*Q18/$M$31 -> -1.157776 | S20: =+R20/$R$22 -> -0.45865696 | T20: =+$R$22*S20 -> -1.157776
O21: FCF | R21: =+R22-SUM(R18:R20) -> -1.4295511 | S21: =+R21/$R$22 -> -0.56632158 | T21: =+$R$22*S21 -> -1.4295511
B22: (+) Net debt (incl leases) | D22: =+Quarterly!E96 -> 637.755 | H22: Content | I22: =+CHOOSE(Case,C11,C12,C13) -> 15 | K22: =+K18*$I22 -> 1319.1275 | L22: =+L18*$I22 -> 1571.9401 | M22: =+M18*$I22 -> 1743.6088 | O22: Total value per share | R22: =+M33-D18 -> 2.5242744
B23: (+) NCI | D23: =+Quarterly!E82 -> 260.503 | H23: TV | I23: 5 | K23: =+K19*$I23 -> 74.851917 | L23: =+L19*$I23 -> 69.85784 | M23: =+M19*$I23 -> 65.063527
B24: EV (CADm) | D24: =+D22+D20+D23 -> 1384.7168 | H24: EV (excl. NCI) | K24: =SUM(K22:K23) -> 1393.9795 | L24: =SUM(L22:L23) -> 1641.7979 | M24: =SUM(M22:M23) -> 1808.6724
B25: LTM EBITDA | D25: =+D24/Summary!I19 -> 14.469501
H26: Implied multiple | K26: =+K24/K20 -> 13.545325 | L26: =+L24/L20 -> 13.823621 | M26: =+M24/M20 -> 13.99324
B27: EV excl NCI (CADm) | D27: =+D24-D23 -> 1124.2138
B28: LTM EBITDA | D28: =+D27/Summary!I22 -> 15.543886 | H28: (-) Net debt (incl leases) | K28: =+'BS & CFS'!K50 -> 730.22839 | L28: =+'BS & CFS'!L50 -> 808.11808 | M28: =+'BS & CFS'!M50 -> 885.24012
H29: Equity value | K29: =+K24-K28 -> 663.75107 | L29: =+L24-L28 -> 833.67985 | M29: =+M24-M28 -> 923.43225
H31: Shares out (mm) | K31: =+'P&L'!K41 -> 173.113 | L31: =+'P&L'!L41 -> 173.113 | M31: =+'P&L'!M41 -> 173.113
H33: Price per share (CAD) | K33: =+K29/K31 -> 3.834207 | L33: =+L29/L31 -> 4.8158131 | M33: =+M29/M31 -> 5.3342744
H34: Upside % | K34: =+K33/$D$18-1 -> 0.36448646 | L34: =+L33/$D$18-1 -> 0.71381248 | M34: =+M33/$D$18-1 -> 0.8983183
H35: MOIC | K35: =+K33/$D$18 -> 1.3644865 | L35: =+L33/$D$18 -> 1.7138125 | M35: =+M33/$D$18 -> 1.8983183
H36: IRR % | K36: =+K35^(1/(YEARFRAC($D$16,K16)))-1 -> 0.24583226 | L36: =+L35^(1/(YEARFRAC($D$16,L16)))-1 -> 0.2500397 | M36: =+M35^(1/(YEARFRAC($D$16,M16)))-1 -> 0.20653564

Sheet Summary
A1: in CADm unless otherwise stated
A2: FYE June
E3: 2018 | F3: =+E3+1 -> 2019 | G3: =+F3+1 -> 2020 | H3: =+G3+1 -> 2021 | I3: =+H3+1 -> 2022 | J3: =+I3+1 -> 2023 | K3: =+J3+1 -> 2024 | L3: =+K3+1 -> 2025 | M3: =+L3+1 -> 2026 | ... S3: =+R3+1 -> 2032 | U3: '18-'22 CAGR | V3: '22-'26 CAGR
A4: x | B4: Profit model
B5: =+'RevBuild Calcs'!B7 -> Content production and distribution | E5: =+'RevBuild Calcs'!E7 -> 164.374 | F5: =+'RevBuild Calcs'!F7 -> 143.763 | G5: =+'RevBuild Calcs'!G7 -> 145.225 | H5: =+'RevBuild Calcs'!H7 -> 185.084 | I5: =+'RevBuild Calcs'!I7 -> 206.572 | J5: =+'RevBuild Calcs'!J7 -> 216.9006 | K5: =+'RevBuild Calcs'!K7 -> 238.59066 | L5: =+'RevBuild Calcs'!L7 -> 262.44973 | ... S5: =+'RevBuild Calcs'!S7 -> 329.04763 | U5: =+(I5/E5)^(0.166666666666667)-1 -> 0.038818611 | V5: =+(M5/I5)^(0.166666666666667)-1 -> 0.049205749
B6: =+'RevBuild Calcs'!B8 -> WildBrain Spark | E6: =+'RevBuild Calcs'!E8 -> 57.282 | F6: =+'RevBuild Calcs'!F8 -> 68.996 | G6: =+'RevBuild Calcs'!G8 -> 62.278 | H6: =+'RevBuild Calcs'!H8 -> 45.754 | I6: =+'RevBuild Calcs'!I8 -> 55.41 | J6: =+'RevBuild Calcs'!J8 -> 45.65784 | K6: =+'RevBuild Calcs'!K8 -> 54.081711 | L6: =+'RevBuild Calcs'!L8 -> 69.630204 | ... S6: =+'RevBuild Calcs'!S8 -> 108.38647 | U6: =+(I6/E6)^(0.166666666666667)-1 -> -0.005522421 | V6: =+(M6/I6)^(0.166666666666667)-1 -> 0.052460987
B7: =+'RevBuild Calcs'!B9 -> Consumer Products | E7: =+'RevBuild Calcs'!E9 -> 157.746 | F7: =+'RevBuild Calcs'!F9 -> 174.572 | G7: =+'RevBuild Calcs'!G9 -> 168.604 | H7: =+'RevBuild Calcs'!H9 -> 175.194 | I7: =+'RevBuild Calcs'!I9 -> 203.557 | J7: =+'RevBuild Calcs'!J9 -> 223.9127 | K7: =+'RevBuild Calcs'!K9 -> 252.34961 | L7: =+'RevBuild Calcs'!L9 -> 284.41615 | ... S7: =+'RevBuild Calcs'!S9 -> 491.1406 | U7: =+(I7/E7)^(0.166666666666667)-1 -> 0.043409086 | V7: =+(M7/I7)^(0.166666666666667)-1 -> 0.078634948
B8: Canadian TV | E8: =+'RevBuild Calcs'!E12 -> 55.014 | F8: =+'RevBuild Calcs'!F12 -> 52.469 | G8: =+'RevBuild Calcs'!G12 -> 49.527 | H8: =+'RevBuild Calcs'!H12 -> 46.502 | I8: =+'RevBuild Calcs'!I12 -> 41.684 | J8: =+'RevBuild Calcs'!J12 -> 40.01664 | K8: =+'RevBuild Calcs'!K12 -> 38.415974 | L8: =+'RevBuild Calcs'!L12 -> 36.879335 | ... S8: =+'RevBuild Calcs'!S12 -> 28.867587 | U8: =+(I8/E8)^(0.166666666666667)-1 -> -0.045192048 | V8: =+(M8/I8)^(0.166666666666667)-1 -> -0.026847681
B9: Total revenue | E9: =SUM(E5:E8) -> 434.416 | F9: =SUM(F5:F8) -> 439.8 | G9: =SUM(G5:G8) -> 425.634 | H9: =SUM(H5:H8) -> 452.534 | I9: =SUM(I5:I8) -> 507.223 | J9: =SUM(J5:J8) -> 526.48778 | K9: =SUM(K5:K8) -> 583.43796 | L9: =SUM(L5:L8) -> 653.37542 | ... S9: =SUM(S5:S8) -> 957.4423 | U9: =+(I9/E9)^(0.166666666666667)-1 -> 0.026161038 | V9: =+(M9/I9)^(0.166666666666667)-1 -> 0.056871769
B10: % YoY | F10: =+F9/E9-1 -> 0.01239365 | G10: =+G9/F9-1 -> -0.032210095 | H10: =+H9/G9-1 -> 0.063199838 | I10: =+I9/H9-1 -> 0.12085059 | J10: =+J9/I9-1 -> 0.037980888 | K10: =+K9/J9-1 -> 0.10816999 | L10: =+L9/K9-1 -> 0.11987128 | M10: =+M9/L9-1 -> 0.081857183 | ... S10: =+S9/R9-1 -> 0.049855806
B12: Content business | H12: =+'RevBuild Calcs'!H18 -> 162.692 | I12: =+'RevBuild Calcs'!I18 -> 193.455 | J12: =+'RevBuild Calcs'!J18 -> 194.58846 | K12: =+'RevBuild Calcs'!K18 -> 223.45901 | L12: =+'RevBuild Calcs'!L18 -> 252.76339 | M12: =+'RevBuild Calcs'!M18 -> 275.29644 | N12: =+'RevBuild Calcs'!N18 -> 294.18696 | O12: =+'RevBuild Calcs'!O18 -> 310.88787 | ... S12: =+'RevBuild Calcs'!S18 -> 380.71563
B13: TV business | H13: =+'RevBuild Calcs'!H21 -> 32.195 | I13: =+'RevBuild Calcs'!I21 -> 28.106 | J13: =+'RevBuild Calcs'!J21 -> 26.010816 | K13: =+'RevBuild Calcs'!K21 -> 24.970383 | L13: =+'RevBuild Calcs'!L21 -> 23.971568 | M13: =+'RevBuild Calcs'!M21 -> 23.012705 | N13: =+'RevBuild Calcs'!N21 -> 22.092197 | O13: =+'RevBuild Calcs'!O21 -> 21.208509 | ... S13: =+'RevBuild Calcs'!S21 -> 18.763932
B14: Total gross profit | E14: =+'P&L'!E13 -> 190.172 | F14: =+'P&L'!F13 -> 186.797 | G14: =+'P&L'!G13 -> 187.845 | H14: =+'P&L'!H13 -> 199.259 | I14: =+'P&L'!I13 -> 221.561 | J14: =+'P&L'!J13 -> 220.59927 | K14: =+'P&L'!K13 -> 248.4294 | L14: =+'P&L'!L13 -> 276.73496 | ... S14: =+'P&L'!S13 -> 399.47956
B15: Gross margin % | E15: =+'P&L'!E14 -> 0.43776472 | F15: =+'P&L'!F14 -> 0.4247317 | G15: =+'P&L'!G14 -> 0.44132987 | H15: =+'P&L'!H14 -> 0.4403183 | I15: =+'P&L'!I14 -> 0.43681182 | J15: =+'P&L'!J14 -> 0.41900169 | K15: =+'P&L'!K14 -> 0.4258026 | L15: =+'P&L'!L14 -> 0.42354664 | ... S15: =+'P&L'!S14 -> 0.41723618
B17: Cash SG&A | E17: =+(E14-E19)*-1 -> -91.712 | F17: =+(F14-F19)*-1 -> -74.516 | G17: =+(G14-G19)*-1 -> -111.445 | H17: =+(H14-H19)*-1 -> -95.453 | I17: =+(I14-I19)*-1 -> -125.862 | J17: =+(J14-J19)*-1 -> -114.52635 | K17: =+(K14-K19)*-1 -> -114.40279 | L17: =+(L14-L19)*-1 -> -122.0593 | ... S17: =+(S14-S19)*-1 -> -172.33469
B19: Adj. EBITDA | E19: =+'P&L'!E68 -> 98.46 | F19: =+'P&L'!F68 -> 112.281 | G19: =+'P&L'!G68 -> 76.4 | H19: =+'P&L'!H68 -> 103.806 | I19: =+'P&L'!I68 -> 95.699 | J19: =+'P&L'!J68 -> 106.07292 | K19: =+'P&L'!K68 -> 134.02661 | L19: =+'P&L'!L68 -> 154.67566 | ... S19: =+'P&L'!S68 -> 227.14487
B20: EBITDA margin % | E20: =+E19/E9 -> 0.22664911 | F20: =+F19/F9 -> 0.25530014 | G20: =+G19/G9 -> 0.17949694 | H20: =+H19/H9 -> 0.22938829 | I20: =+I19/I9 -> 0.18867244 | J20: =+J19/J9 -> 0.20147271 | K20: =+K19/K9 -> 0.2297187 | L20: =+L19/L9 -> 0.23673321 | ... S20: =+S19/S9 -> 0.23724132
B22: Proportionate Adj. EBITDA | E22: =+'P&L'!E71 -> 89.64964 | F22: =+'P&L'!F71 -> 83.105748 | G22: =+'P&L'!G71 -> 56.018389 | H22: =+'P&L'!H71 -> 72.621356 | I22: =+'P&L'!I71 -> 72.325143 | J22: =+'P&L'!J71 -> 81.447999 | K22: =+'P&L'!K71 -> 102.91222 | L22: =+'P&L'!L71 -> 118.76757 | ... S22: =+'P&L'!S71 -> 174.413
A24: x | B24: Mgmt compensation analysis
E25: 2018 | F25: =+E25+1 -> 2019 | G25: =+F25+1 -> 2020 | H25: =+G25+1 -> 2021 | I25: =+H25+1 -> 2022
B26: Salaries & benefits | E26: 4.205 | F26: 3.392 | G26: 4.709 | H26: 4.443 | I26: 4.071
B27: SBC | E27: 2.146 | F27: 1.838 | G27: 3.798 | H27: 2.895 | I27: 2.74
B28: Termination and other | E28: 2.899 | F28: 0.732 | G28: 1.388 | H28: 0 | I28: 0
B29: Total | E29: =+SUM(E26:E28) -> 9.25 | F29: =+SUM(F26:F28) -> 5.962 | G29: =+SUM(G26:G28) -> 9.895 | H29: =+SUM(H26:H28) -> 7.338 | I29: =+SUM(I26:I28) -> 6.811
B30: % SBC | E30: =+E27/E29 -> 0.232 | F30: =+F27/F29 -> 0.30828581 | G30: =+G27/G29 -> 0.38383022 | H30: =+H27/H29 -> 0.39452167 | I30: =+I27/I29 -> 0.40229041
A32: x | B32: Model Drivers

Sheet P&L
A1: in CADm unless otherwise stated
A2: FYE June
E3: 2018 | F3: =+E3+1 -> 2019 | G3: =+F3+1 -> 2020 | H3: =+G3+1 -> 2021 | I3: =+H3+1 -> 2022 | J3: =+I3+1 -> 2023 | K3: =+J3+1 -> 2024 | L3: =+K3+1 -> 2025 | M3: =+L3+1 -> 2026 | ... S3: =+R3+1 -> 2032
A5: x | B5: P&L
B6: Revenues | E6: 434.416 | F6: 439.8 | G6: 425.634 | H6: 452.534 | I6: 507.223 | J6: =+'RevBuild Calcs'!J14 -> 526.48778 | K6: =+'RevBuild Calcs'!K14 -> 583.43796 | L6: =+'RevBuild Calcs'!L14 -> 653.37542 | M6: =+'RevBuild Calcs'!M14 -> 706.85889 | N6: =+'RevBuild Calcs'!N14 -> 751.51717 | O6: =+'RevBuild Calcs'!O14 -> 790.89156 | P6: =+'RevBuild Calcs'!P14 -> 829.92286 | Q6: =+'RevBuild Calcs'!Q14 -> 870.20443 | ... S6: =+'RevBuild Calcs'!S14 -> 957.4423
B7: % YoY | F7: =+F6/E6-1 -> 0.01239365 | G7: =+G6/F6-1 -> -0.032210095 | H7: =+H6/G6-1 -> 0.063199838 | I7: =+I6/H6-1 -> 0.12085059 | J7: =+J6/I6-1 -> 0.037980888 | K7: =+K6/J6-1 -> 0.10816999 | L7: =+L6/K6-1 -> 0.11987128 | M7: =+M6/L6-1 -> 0.081857183 | ... S7: =+S6/R6-1 -> 0.049855806
B9: Income from litigation settlement | H9: 4.372
B11: Direct production costs and expense of film and television produced | E11: -244.244 | F11: -253.003 | G11: -237.789 | H11: -257.647 | I11: -285.662 | J11: =+J13-J6 -> -305.88851 | K11: =+K13-K6 -> -335.00856 | L11: =+L13-L6 -> -376.64045 | M11: =+M13-M6 -> -408.54974 | N11: =+N13-N6 -> -435.23801 | O11: =+O13-O6 -> -458.79519 | P11: =+P13-P6 -> -482.13689 | Q11: =+Q13-Q6 -> -506.20372 | ... S11: =+S13-S6 -> -557.96273
B13: Gross profit | E13: =+E6+E9+E11 -> 190.172 | F13: =+F6+F9+F11 -> 186.797 | G13: =+G6+G9+G11 -> 187.845 | H13: =+H6+H9+H11 -> 199.259 | I13: =+I6+I9+I11 -> 221.561 | J13: =+'RevBuild Calcs'!J26 -> 220.59927 | K13: =+'RevBuild Calcs'!K26 -> 248.4294 | L13: =+'RevBuild Calcs'!L26 -> 276.73496 | M13: =+'RevBuild Calcs'!M26 -> 298.30914 | N13: =+'RevBuild Calcs'!N26 -> 316.27916 | O13: =+'RevBuild Calcs'!O26 -> 332.09637 | P13: =+'RevBuild Calcs'!P26 -> 347.78597 | Q13: =+'RevBuild Calcs'!Q26 -> 364.00071 | ... S13: =+'RevBuild Calcs'!S26 -> 399.47956
B14: % margin | E14: =+E13/E6 -> 0.43776472 | F14: =+F13/F6 -> 0.4247317 | G14: =+G13/G6 -> 0.44132987 | H14: =+H13/H6 -> 0.4403183 | I14: =+I13/I6 -> 0.43681182 | J14: =+J13/J6 -> 0.41900169 | K14: =+K13/K6 -> 0.4258026 | L14: =+L13/L6 -> 0.42354664 | ... S14: =+S13/S6 -> 0.41723618
B16: Amortization of acquired and library content | E16: -15.916 | F16: -14.431 | G16: -12.082 | H16: -11.1 | I16: -10.241 | J16: =+'FS Calcs'!J44 -> -10 | K16: =+'FS Calcs'!K44 -> -10 | L16: =+'FS Calcs'!L44 -> -10 | M16: =+'FS Calcs'!M44 -> -10 | N16: =+'FS Calcs'!N44 -> -10 | O16: =+'FS Calcs'!O44 -> -10 | P16: =+'FS Calcs'!P44 -> -10 | Q16: =+'FS Calcs'!Q44 -> -10 | ... S16: =+'FS Calcs'!S44 -> -10
B17: Amortization of property and equipment and intangible assets | E17: -24.174 | F17: -22.651 | G17: -24.171 | H17: -22.924 | I17: -23.979 | J17: =+'FS Calcs'!J53+'FS Calcs'!J64 -> -31.589267 | K17: =+'FS Calcs'!K53+'FS Calcs'!K64 -> -29.79701 | L17: =+'FS Calcs'!L53+'FS Calcs'!L64 -> -29.985265 | M17: =+'FS Calcs'!M53+'FS Calcs'!M64 -> -28.779255 | N17: =+'FS Calcs'!N53+'FS Calcs'!N64 -> -29.523889 | O17: =+'FS Calcs'!O53+'FS Calcs'!O64 -> -29.940895 | P17: =+'FS Calcs'!P53+'FS Calcs'!P64 -> -30.232904 | Q17: =+'FS Calcs'!Q53+'FS Calcs'!Q64 -> -30.457155 | ... S17: =+'FS Calcs'!S53+'FS Calcs'!S64 -> -33.51048
B18: Write-down of investment in film and television programs, acquired and library content, and property and equipment | E18: -12.027 | F18: -104.871 | G18: -196.122 | H18: -7.832 | I18: -0.788 | J18: =+'FS Calcs'!J32+'FS Calcs'!J43+'FS Calcs'!J54+'FS Calcs'!J65 -> 0 | K18: =+'FS Calcs'!K32+'FS Calcs'!K43+'FS Calcs'!K54+'FS Calcs'!K65 -> -10 | L18: =+'FS Calcs'!L32+'FS Calcs'!L43+'FS Calcs'!L54+'FS Calcs'!L65 -> 0 | M18: =+'FS Calcs'!M32+'FS Calcs'!M43+'FS Calcs'!M54+'FS Calcs'!M65 -> 0 | N18: =+'FS Calcs'!N32+'FS Calcs'!N43+'FS Calcs'!N54+'FS Calcs'!N65 -> 0 | O18: =+'FS Calcs'!O32+'FS Calcs'!O43+'FS Calcs'!O54+'FS Calcs'!O65 -> 0 | P18: =+'FS Calcs'!P32+'FS Calcs'!P43+'FS Calcs'!P54+'FS Calcs'!P65 -> 0 | Q18: =+'FS Calcs'!Q32+'FS Calcs'!Q43+'FS Calcs'!Q54+'FS Calcs'!Q65 -> 0 | ... S18: =+'FS Calcs'!S32+'FS Calcs'!S43+'FS Calcs'!S54+'FS Calcs'!S65 -> 0
B20: Selling, general and administrative | E20: -86.2 | F20: -81.121 | G20: -83.098 | H20: -80.539 | I20: -104.129 | J20: =+'FS Calcs'!J104 -> -101.23057 | K20: =+'FS Calcs'!K104 -> -112.18068 | L20: =+'FS Calcs'!L104 -> -125.62792 | M20: =+'FS Calcs'!M104 -> -135.91147 | N20: =+'FS Calcs'!N104 -> -144.49815 | O20: =+'FS Calcs'!O104 -> -152.06887 | P20: =+'FS Calcs'!P104 -> -159.57362 | Q20: =+'FS Calcs'!Q104 -> -167.31877 | ... S20: =+'FS Calcs'!S104 -> -184.09246
B21: Share-based compensation | H21: -5.075 | I21: -7.414 | J21: -5 | K21: -5 | L21: -5 | M21: -5 | N21: -5 | O21: -5 | P21: -5 | Q21: -5 | R21: -5 | S21: -5
B22: Finance costs, net | E22: -50.109 | F22: -52.236 | G22: -49.404 | H22: -42.139 | I22: -30.486 | J22: =+IF(Circ=1, 'Debt Calcs'!J22, 0) -> -34.661458 | K22: =+IF(Circ=1, 'Debt Calcs'!K22, 0) -> -38.510699 | L22: =+IF(Circ=1, 'Debt Calcs'!L22, 0) -> -43.212747 | M22: =+IF(Circ=1, 'Debt Calcs'!M22, 0) -> -47.553075 | N22: =+IF(Circ=1, 'Debt Calcs'!N22, 0) -> -51.872817 | O22: =+IF(Circ=1, 'Debt Calcs'!O22, 0) -> -56.25353 | P22: =+IF(Circ=1, 'Debt Calcs'!P22, 0) -> -60.793885 | Q22: =+IF(Circ=1, 'Debt Calcs'!Q22, 0) -> -65.548026 | ... S22: =+IF(Circ=1, 'Debt Calcs'!S22, 0) -> -75.729165
B23: Change in fair value of embedded derivatives | E23: 11.251 | F23: 7.185 | G23: 1.955 | H23: -26.206 | I23: 13.716 | J23: 0 | K23: 0 | L23: 0 | M23: 0 | N23: 0 | O23: 0 | P23: 0 | Q23: 0 | R23: 0 | S23: 0
B24: Foreign exchange (loss) / gain | E24: -7.7 | F24: 1.081 | G24: -14.047 | H24: 24.979 | I24: -21.754 | J24: -12.5 | K24: -5 | L24: -5 | M24: -5 | N24: -5 | O24: -5 | P24: -5 | Q24: -5 | R24: -5 | S24: -5
B25: Reorganization, development and other expense | E25: -10.554 | F25: -1.661 | G25: -17.961 | H25: -8.612 | I25: -6.281 | J25: -2.5 | K25: -2.5 | L25: -2.5 | M25: -2.5 | N25: -2.5 | O25: -2.5 | P25: -2.5 | Q25: -2.5 | R25: -2.5 | S25: -2.5
B27: EBT | E27: =+E13+SUM(E16:E18,E20:E25) -> -5.257 | F27: =+F13+SUM(F16:F18,F20:F25) -> -81.908 | G27: =+G13+SUM(G16:G18,G20:G25) -> -207.085 | H27: =+H13+SUM(H16:H18,H20:H25) -> 19.811 | I27: =+I13+SUM(I16:I18,I20:I25) -> 30.205 | J27: =+J13+SUM(J16:J18,J20:J25) -> 23.117979 | K27: =+K13+SUM(K16:K18,K20:K25) -> 35.441009 | L27: =+L13+SUM(L16:L18,L20:L25) -> 55.409029 | ... S27: =+S13+SUM(S16:S18,S20:S25) -> 83.647462
B28: % margin | E28: =+E27/E6 -> -0.012101304 | F28: =+F27/F6 -> -0.1862392 | G28: =+G27/G6 -> -0.48653303 | H28: =+H27/H6 -> 0.043777926 | I28: =+I27/I6 -> 0.059549744 | J28: =+J27/J6 -> 0.043909811 | K28: =+K27/K6 -> 0.060745121 | L28: =+L27/L6 -> 0.084804276 | ... S28: =+S27/S6 -> 0.087365538
B30: Current income taxes (paid) / recovered | E30: -2.166 | F30: 1.77 | G30: -0.489 | H30: -3.049 | I30: -0.347 | J30: =+'FS Calcs'!J107 -> -6.7042139 | K30: =+'FS Calcs'!K107 -> -10.277893 | L30: =+'FS Calcs'!L107 -> -16.068618 | M30: =+'FS Calcs'!M107 -> -18.43395 | N30: =+'FS Calcs'!N107 -> -19.686448 | O30: =+'FS Calcs'!O107 -> -20.686593 | P30: =+'FS Calcs'!P107 -> -21.658812 | Q30: =+'FS Calcs'!Q107 -> -22.67126 | ... S30: =+'FS Calcs'!S107 -> -24.257764
B31: Deferred income taxes (paid) / recovered | E31: 0.675 | F31: 1.936 | G31: -1.217 | H31: 6.347 | I31: 1.904 | J31: =+'FS Calcs'!J108 -> 0 | K31: =+'FS Calcs'!K108 -> 0 | L31: =+'FS Calcs'!L108 -> 0 | M31: =+'FS Calcs'!M108 -> 0 | N31: =+'FS Calcs'!N108 -> 0 | O31: =+'FS Calcs'!O108 -> 0 | P31: =+'FS Calcs'!P108 -> 0 | Q31: =+'FS Calcs'!Q108 -> 0 | ... S31: =+'FS Calcs'!S108 -> 0
B32: Total | E32: =SUM(E30:E31) -> -1.491 | F32: =SUM(F30:F31) -> 3.706 | G32: =SUM(G30:G31) -> -1.706 | H32: =SUM(H30:H31) -> 3.298 | I32: =SUM(I30:I31) -> 1.557 | J32: =SUM(J30:J31) -> -6.7042139 | K32: =SUM(K30:K31) -> -10.277893 | L32: =SUM(L30:L31) -> -16.068618 | ... S32: =SUM(S30:S31) -> -24.257764
B34: Net income | E34: =+E32+E27 -> -6.748 | F34: =+F32+F27 -> -78.202 | G34: =+G32+G27 -> -208.791 | H34: =+H32+H27 -> 23.109 | I34: =+I32+I27 -> 31.762 | J34: =+J32+J27 -> 16.413765 | K34: =+K32+K27 -> 25.163117 | L34: =+L32+L27 -> 39.34041 | ... S34: =+S32+S27 -> 59.389698
B35: Attributable to NCI | E35: 7.312 | F35: 23.292 | G35: 27.175 | H35: 30.186 | I35: 26.122 | J35: =+'FS Calcs'!J98 -> 26.899258 | K35: =+'FS Calcs'!K98 -> 27.706235 | L35: =+'FS Calcs'!L98 -> 28.537422 | M35: =+'FS Calcs'!M98 -> 29.393545 | N35: =+'FS Calcs'!N98 -> 30.275351 | O35: =+'FS Calcs'!O98 -> 31.183612 | P35: =+'FS Calcs'!P98 -> 32.11912 | Q35: =+'FS Calcs'!Q98 -> 33.082694 | ... S35: =+'FS Calcs'!S98 -> 35.09743
B36: Attributable to common | E36: =+E34-E35 -> -14.06 | F36: =+F34-F35 -> -101.494 | G36: =+G34-G35 -> -235.966 | H36: =+H34-H35 -> -7.077 | I36: =+I34-I35 -> 5.64 | J36: =+J34-J35 -> -10.485493 | K36: =+K34-K35 -> -2.5431185 | L36: =+L34-L35 -> 10.802988 | ... S36: =+S34-S35 -> 24.292268
B38: Basic EPS (CAD) | E38: -0.1 | F38: -0.75 | G38: -1.51 | H38: -0.04 | I38: 0.03 | J38: =+J$36/J41 -> -0.06057022 | K38: =+K$36/K41 -> -0.014690511 | L38: =+L$36/L41 -> 0.062404257 | M38: =+M$36/M41 -> 0.090910847 | N38: =+N$36/N41 -> 0.10353066 | O38: =+O$36/O41 -> 0.11242872 | P38: =+P$36/P41 -> 0.12077445 | Q38: =+Q$36/Q41 -> 0.12952698 | ... S38: =+S$36/S41 -> 0.14032608
B39: Diluted EPS (CAD) | E39: -0.1 | F39: -0.75 | G39: -1.51 | H39: -0.04 | I39: -0.01 | J39: =+J$36/J42 -> -0.055084172 | K39: =+K$36/K42 -> -0.013359943 | L39: =+L$36/L42 -> 0.056752094 | M39: =+M$36/M42 -> 0.082676747 | N39: =+N$36/N42 -> 0.094153545 | O39: =+O$36/O42 -> 0.10224568 | P39: =+P$36/P42 -> 0.1098355 | Q39: =+Q$36/Q42 -> 0.11779529 | ... S39: =+S$36/S42 -> 0.12761627
B41: Basic - WASO | E41: 134.506 | F41: 134.828 | G41: 156.748 | H41: 171.222 | I41: 172.584 | J41: 173.113 | K41: =+J41 -> 173.113 | L41: =+K41 -> 173.113 | M41: =+L41 -> 173.113 | N41: =+M41 -> 173.113 | O41: =+N41 -> 173.113 | P41: =+O41 -> 173.113 | Q41: =+P41 -> 173.113 | R41: =+Q41 -> 173.113 | S41: =+R41 -> 173.113
B42: Diluted - WASO | E42: 134.506 | F42: 134.828 | G42: 156.748 | H42: 171.222 | I42: 197.403 | J42: 190.354 | K42: =+J42 -> 190.354 | L42: =+K42 -> 190.354 | M42: =+L42 -> 190.354 | N42: =+M42 -> 190.354 | O42: =+N42 -> 190.354 | P42: =+O42 -> 190.354 | Q42: =+P42 -> 190.354 | R42: =+Q42 -> 190.354 | S42: =+R42 -> 190.354
B44: Dividend to common | E44: 0 | F44: 0 | G44: 0 | H44: 0 | I44: 0 | J44: =+'FS Calcs'!J76 -> 0 | K44: =+'FS Calcs'!K76 -> 0 | L44: =+'FS Calcs'!L76 -> 0 | M44: =+'FS Calcs'!M76 -> 0 | N44: =+'FS Calcs'!N76 -> 0 | O44: =+'FS Calcs'!O76 -> 0 | P44: =+'FS Calcs'!P76 -> 0 | Q44: =+'FS Calcs'!Q76 -> 0 | ... S44: =+'FS Calcs'!S76 -> 0
B45: Distribution to NCI | F45: -26.657 | G45: -33.46 | H45: -31.457 | I45: -33.609 | J45: =+'FS Calcs'!J82 -> -34.28118 | K45: =+'FS Calcs'!K82 -> -34.966804 | L45: =+'FS Calcs'!L82 -> -35.66614 | M45: =+'FS Calcs'!M82 -> -36.379462 | N45: =+'FS Calcs'!N82 -> -37.107052 | O45: =+'FS Calcs'!O82 -> -37.849193 | P45: =+'FS Calcs'!P82 -> -38.606177 | Q45: =+'FS Calcs'!Q82 -> -39.3783 | ... S45: =+'FS Calcs'!S82 -> -40.969183
A47: x | B47: Adj. EBITDA reconcillation
B48: EBT | E48: =+E27 -> -5.257 | F48: =+F27 -> -81.908 | G48: =+G27 -> -207.085 | H48: =+H27 -> 19.811 | I48: =+I27 -> 30.205 | J48: =+J27 -> 23.117979 | K48: =+K27 -> 35.441009 | L48: =+L27 -> 55.409029 | ... S48: =+S27 -> 83.647462
B49: Tax expense | E49: =+IF(E32<0,E32*-1, 0) -> 1.491 | F49: =+IF(F32<0,F32*-1, 0) -> 0 | G49: =+IF(G32<0,G32*-1, 0) -> 1.706 | H49: =+IF(H32<0,H32*-1, 0) -> 0 | I49: =+IF(I32<0,I32*-1, 0) -> 0 | J49: =+IF(J32<0,J32*-1, 0) -> 6.7042139 | K49: =+IF(K32<0,K32*-1, 0) -> 10.277893 | L49: =+IF(L32<0,L32*-1, 0) -> 16.068618 | ... S49: =+IF(S32<0,S32*-1, 0) -> 24.257764
B50: Interest | E50: =+E22*-1 -> 50.109 | F50: =+F22*-1 -> 52.236 | G50: =+G22*-1 -> 49.404 | H50: =+H22*-1 -> 42.139 | I50: =+I22*-1 -> 30.486 | J50: =+J22*-1 -> 34.661458 | K50: =+K22*-1 -> 38.510699 | L50: =+L22*-1 -> 43.212747 | ... S50: =+S22*-1 -> 75.729165
B51: D&A | E51: =+SUM(E16:E17)*-1 -> 40.09 | F51: =+SUM(F16:F17)*-1 -> 37.082 | G51: =+SUM(G16:G17)*-1 -> 36.253 | H51: =+SUM(H16:H17)*-1 -> 34.024 | I51: =+SUM(I16:I17)*-1 -> 34.22 | J51: =+SUM(J16:J17)*-1 -> 41.589267 | K51: =+SUM(K16:K17)*-1 -> 39.79701 | L51: =+SUM(L16:L17)*-1 -> 39.985265 | ... S51: =+SUM(S16:S17)*-1 -> 43.51048
B52: SBC | E52: =+E21*-1 -> 0 | F52: =+F21*-1 -> 0 | G52: =+G21*-1 -> 0 | H52: =+H21*-1 -> 5.075 | I52: =+I21*-1 -> 7.414 | J52: =+J21*-1 -> 5 | K52: =+K21*-1 -> 5 | L52: =+L21*-1 -> 5 | ... S52: =+S21*-1 -> 5
B53: Writedowns | E53: =+E18*-1 -> 12.027 | F53: =+F18*-1 -> 104.871 | G53: =+G18*-1 -> 196.122 | H53: =+H18*-1 -> 7.832 | I53: =+I18*-1 -> 0.788 | J53: =+J18*-1 -> 0 | K53: =+K18*-1 -> 10 | L53: =+L18*-1 -> 0 | ... S53: =+S18*-1 -> 0
B54: Derivatives, FX | E54: =+(E23+E24)*-1 -> -3.551 | F54: =+(F23+F24)*-1 -> -8.266 | G54: =+(G23+G24)*-1 -> 12.092 | H54: =+(H23+H24)*-1 -> 1.227 | I54: =+(I23+I24)*-1 -> 8.038 | J54: =+(J23+J24)*-1 -> 12.5 | K54: =+(K23+K24)*-1 -> 5 | L54: =+(L23+L24)*-1 -> 5 | ... S54: =+(S23+S24)*-1 -> 5
B55: Reorg, dev and other | E55: =+E25*-1 -> 10.554 | F55: =+F25*-1 -> 1.661 | G55: =+G25*-1 -> 17.961 | H55: =+H25*-1 -> 8.612 | I55: =+I25*-1 -> 6.281 | J55: =+J25*-1 -> 2.5 | K55: =+K25*-1 -> 2.5 | L55: =+L25*-1 -> 2.5 | ... S55: =+S25*-1 -> 2.5
B56: Adj EBITDA (company defined) | E56: =SUM(E48:E55) -> 105.463 | F56: =SUM(F48:F55) -> 105.676 | G56: =SUM(G48:G55) -> 106.453 | H56: =SUM(H48:H55) -> 118.72 | I56: =SUM(I48:I55) -> 117.432 | J56: =SUM(J48:J55) -> 126.07292 | K56: =SUM(K48:K55) -> 146.52661 | L56: =SUM(L48:L55) -> 167.17566 | ... S56: =SUM(S48:S55) -> 239.64487
B57: % margin | E57: =+E56/E$6 -> 0.2427696 | F57: =+F56/F$6 -> 0.24028195 | G57: =+G56/G$6 -> 0.25010455 | H57: =+H56/H$6 -> 0.26234493 | I57: =+I56/I$6 -> 0.23151947 | J57: =+J56/J$6 -> 0.23946029 | K57: =+K56/K$6 -> 0.25114343 | L57: =+L56/L$6 -> 0.25586463 | ... S57: =+S56/S$6 -> 0.25029693
B59: Attributable to NCI | E59: -9.437 | F59: -27.459 | G59: -28.399 | H59: -35.665 | I59: -28.682 | J59: =+J60*J56*-1 -> -29.267935 | K59: =+K60*K56*-1 -> -34.016277 | L59: =+L60*L56*-1 -> -38.809971 | M59: =+M60*M56*-1 -> -41.980215 | N59: =+N60*N56*-1 -> -44.449333 | O59: =+O60*O56*-1 -> -46.595948 | P59: =+P60*P56*-1 -> -48.721768 | Q59: =+Q60*Q56*-1 -> -50.923031 | ... S59: =+S60*S56*-1 -> -55.63376
B60: % attributable | E60: =+E59/E56*-1 -> 0.089481619 | F60: =+F59/F56*-1 -> 0.2598414 | G60: =+G59/G56*-1 -> 0.26677501 | H60: =+H59/H56*-1 -> 0.30041274 | I60: =+I59/I56*-1 -> 0.24424348 | J60: =+AVERAGE(E60:I60) -> 0.23215085 | K60: =+J60 -> 0.23215085 | L60: =+K60 -> 0.23215085 | M60: =+L60 -> 0.23215085 | N60: =+M60 -> 0.23215085 | O60: =+N60 -> 0.23215085 | P60: =+O60 -> 0.23215085 | Q60: =+P60 -> 0.23215085 | R60: =+Q60 -> 0.23215085 | S60: =+R60 -> 0.23215085
B62: Proportionate Adj EBITDA (company defined) | E62: =+E56+E59 -> 96.026 | F62: =+F56+F59 -> 78.217 | G62: =+G56+G59 -> 78.054 | H62: =+H56+H59 -> 83.055 | I62: =+I56+I59 -> 88.75 | J62: =+J56+J59 -> 96.804982 | K62: =+K56+K59 -> 112.51033 | L62: =+L56+L59 -> 128.36569 | ... S62: =+S56+S59 -> 184.01111
B63: % margin | E63: =+E62/E$6 -> 0.22104619 | F63: =+F62/F$6 -> 0.17784675 | G63: =+G62/G$6 -> 0.18338291 | H63: =+H62/H$6 -> 0.18353317 | I63: =+I62/I$6 -> 0.17497235 | J63: =+J62/J$6 -> 0.18386938 | K63: =+K62/K$6 -> 0.19284027 | L63: =+L62/L$6 -> 0.19646544 | ... S63: =+S62/S$6 -> 0.19219029
B65: (-) SBC | E65: =+E52*-1 -> 0 | F65: =+F52*-1 -> 0 | G65: =+G52*-1 -> 0 | H65: =+H52*-1 -> -5.075 | I65: =+I52*-1 -> -7.414 | J65: =+J52*-1 -> -5 | K65: =+K52*-1 -> -5 | L65: =+L52*-1 -> -5 | ... S65: =+S52*-1 -> -5
B66: (-) Derivatives, FX | E66: =+E54*-1 -> 3.551 | F66: =+F54*-1 -> 8.266 | G66: =+G54*-1 -> -12.092 | H66: =+H54*-1 -> -1.227 | I66: =+I54*-1 -> -8.038 | J66: =+J54*-1 -> -12.5 | K66: =+K54*-1 -> -5 | L66: =+L54*-1 -> -5 | ... S66: =+S54*-1 -> -5
B67: (-) Reorg, dev and other | E67: =+E55*-1 -> -10.554 | F67: =+F55*-1 -> -1.661 | G67: =+G55*-1 -> -17.961 | H67: =+H55*-1 -> -8.612 | I67: =+I55*-1 -> -6.281 | J67: =+J55*-1 -> -2.5 | K67: =+K55*-1 -> -2.5 | L67: =+L55*-1 -> -2.5 | ... S67: =+S55*-1 -> -2.5
B68: Adj EBITDA (Danial Azmi defined) | E68: =+E56+E65+E66+E67 -> 98.46 | F68: =+F56+F65+F66+F67 -> 112.281 | G68: =+G56+G65+G66+G67 -> 76.4 | H68: =+H56+H65+H66+H67 -> 103.806 | I68: =+I56+I65+I66+I67 -> 95.699 | J68: =+J56+J65+J66+J67 -> 106.07292 | K68: =+K56+K65+K66+K67 -> 134.02661 | L68: =+L56+L65+L66+L67 -> 154.67566 | ... S68: =+S56+S65+S66+S67 -> 227.14487
B69: % margin | E69: =+E68/E6 -> 0.22664911 | F69: =+F68/F6 -> 0.25530014 | G69: =+G68/G6 -> 0.17949694 | H69: =+H68/H6 -> 0.22938829 | I69: =+I68/I6 -> 0.18867244 | J69: =+J68/J6 -> 0.20147271 | K69: =+K68/K6 -> 0.2297187 | L69: =+L68/L6 -> 0.23673321 | ... S69: =+S68/S6 -> 0.23724132
B71: Proportionate Adj. EBITDA (DA defined) | E71: =+E68*(1-E60) -> 89.64964 | F71: =+F68*(1-F60) -> 83.105748 | G71: =+G68*(1-G60) -> 56.018389 | H71: =+H68*(1-H60) -> 72.621356 | I71: =+I68*(1-I60) -> 72.325143 | J71: =+J68*(1-J60) -> 81.447999 | K71: =+K68*(1-K60) -> 102.91222 | L71: =+L68*(1-L60) -> 118.76757 | ... S71: =+S68*(1-S60) -> 174.413
B72: % margin to common | E72: =+E71/E6 -> 0.20636818 | F72: =+F71/F6 -> 0.18896259 | G72: =+G71/G6 -> 0.13161164 | H72: =+H71/H6 -> 0.16047713 | I72: =+I71/I6 -> 0.14259043 | J72: =+J71/J6 -> 0.15470065 | K72: =+K71/K6 -> 0.17638931 | L72: =+L71/L6 -> 0.18177539 | ... S72: =+S71/S6 -> 0.18216554
B74: TV gross margin | H74: =+'RevBuild Calcs'!H21 -> 32.195 | I74: =+'RevBuild Calcs'!I21 -> 28.106 | J74: =+'RevBuild Calcs'!J21 -> 26.010816 | K74: =+'RevBuild Calcs'!K21 -> 24.970383 | L74: =+'RevBuild Calcs'!L21 -> 23.971568 | M74: =+'RevBuild Calcs'!M21 -> 23.012705 | N74: =+'RevBuild Calcs'!N21 -> 22.092197 | O74: =+'RevBuild Calcs'!O21 -> 21.208509 | ... S74: =+'RevBuild Calcs'!S21 -> 18.763932
B75: TV SG&A | H75: -10 | I75: -10 | J75: -10 | K75: -10 | L75: -10 | M75: -10 | N75: -5 | O75: -5 | P75: -5 | Q75: -5 | R75: -5 | S75: -5
B76: TV EBITDA | H76: =+H75+H74 -> 22.195 | I76: =+I75+I74 -> 18.106 | J76: =+J75+J74 -> 16.010816 | K76: =+K75+K74 -> 14.970383 | L76: =+L75+L74 -> 13.971568 | M76: =+M75+M74 -> 13.012705 | N76: =+N75+N74 -> 17.092197 | O76: =+O75+O74 -> 16.208509 | ... S76: =+S75+S74 -> 13.763932

Sheet BS & CFS
A1: in CADm unless otherwise stated
A2: FYE June
E3: 2018 | F3: =+E3+1 -> 2019 | G3: =+F3+1 -> 2020 | H3: =+G3+1 -> 2021 | I3: =+H3+1 -> 2022 | J3: =+I3+1 -> 2023 | K3: =+J3+1 -> 2024 | L3: =+K3+1 -> 2025 | M3: =+L3+1 -> 2026 | ... S3: =+R3+1 -> 2032
A5: x | B5: BS
B6: Cash & Equivalents | E6: 46.55 | F6: 39.999 | G6: 67.889 | H6: 78.431 | I6: 59.899 | J6: =+'Debt Calcs'!J70 -> 35 | K6: =+'Debt Calcs'!K70 -> 35 | L6: =+'Debt Calcs'!L70 -> 35 | M6: =+'Debt Calcs'!M70 -> 35 | N6: =+'Debt Calcs'!N70 -> 35 | O6: =+'Debt Calcs'!O70 -> 35 | P6: =+'Debt Calcs'!P70 -> 35 | Q6: =+'Debt Calcs'!Q70 -> 35 | ... S6: =+'Debt Calcs'!S70 -> 35
B7: Restricted Cash | E7: 0 | F7: 0 | G7: 16.637 | H7: 13.626 | I7: 8.835 | J7: =+I7 -> 8.835 | K7: =+J7 -> 8.835 | L7: =+K7 -> 8.835 | M7: =+L7 -> 8.835 | N7: =+M7 -> 8.835 | O7: =+N7 -> 8.835 | P7: =+O7 -> 8.835 | Q7: =+P7 -> 8.835 | ... S7: =+R7 -> 8.835
B8: Accounts Receivable | E8: 251.538 | F8: 265.71 | G8: 200.217 | H8: 195.24 | I8: 249.66 | J8: =+'FS Calcs'!J15 -> 259.14231 | K8: =+'FS Calcs'!K15 -> 287.17373 | L8: =+'FS Calcs'!L15 -> 321.59761 | M8: =+'FS Calcs'!M15 -> 347.92269 | N8: =+'FS Calcs'!N15 -> 369.90392 | O8: =+'FS Calcs'!O15 -> 389.28437 | P8: =+'FS Calcs'!P15 -> 408.49595 | Q8: =+'FS Calcs'!Q15 -> 428.32292 | ... S8: =+'FS Calcs'!S15 -> 471.26223
B9: Prepaid Expenses and Deposits | E9: 8.58 | F9: 7.182 | G9: 8.779 | H9: 6.184 | I9: 8.583 | J9: =+'FS Calcs'!J18 -> 8.583 | K9: =+'FS Calcs'!K18 -> 8.583 | L9: =+'FS Calcs'!L18 -> 8.583 | M9: =+'FS Calcs'!M18 -> 8.583 | N9: =+'FS Calcs'!N18 -> 8.583 | O9: =+'FS Calcs'!O18 -> 8.583 | P9: =+'FS Calcs'!P18 -> 8.583 | Q9: =+'FS Calcs'!Q18 -> 8.583 | ... S9: =+'FS Calcs'!S18 -> 8.583
B10: Investment in Film and Television Programs | E10: 186.008 | F10: 148.561 | G10: 140.548 | H10: 147.783 | I10: 163.563 | J10: =+'FS Calcs'!J35 -> 184.69614 | K10: =+'FS Calcs'!K35 -> 200.72025 | L10: =+'FS Calcs'!L35 -> 230.37205 | M10: =+'FS Calcs'!M35 -> 258.89098 | N10: =+'FS Calcs'!N35 -> 285.37913 | O10: =+'FS Calcs'!O35 -> 310.56192 | P10: =+'FS Calcs'!P35 -> 334.58462 | Q10: =+'FS Calcs'!Q35 -> 357.40746 | ... S10: =+'FS Calcs'!S35 -> 398.99204
B11: Total Current Assets | E11: =SUM(E6:E10) -> 492.676 | F11: =SUM(F6:F10) -> 461.452 | G11: =SUM(G6:G10) -> 434.07 | H11: =SUM(H6:H10) -> 441.264 | I11: =SUM(I6:I10) -> 490.54 | J11: =SUM(J6:J10) -> 496.25645 | K11: =SUM(K6:K10) -> 540.31198 | L11: =SUM(L6:L10) -> 604.38766 | ... S11: =SUM(S6:S10) -> 922.67227
B13: LT receivables | E13: 18.789 | F13: 14.318 | G13: 21.035 | H13: 51.997 | I13: 84.79 | J13: =+'FS Calcs'!J26 -> 88.0104 | K13: =+'FS Calcs'!K26 -> 97.530484 | L13: =+'FS Calcs'!L26 -> 109.22159 | M13: =+'FS Calcs'!M26 -> 118.16216 | N13: =+'FS Calcs'!N26 -> 125.62747 | O13: =+'FS Calcs'!O26 -> 132.20949 | P13: =+'FS Calcs'!P26 -> 138.73416 | Q13: =+'FS Calcs'!Q26 -> 145.46784 | ... S13: =+'FS Calcs'!S26 -> 160.05097
B14: Acquired and library content | E14: 147.088 | F14: 118.247 | G14: 109.076 | H14: 100.653 | I14: 92.732 | J14: =+'FS Calcs'!J46 -> 93.261756 | K14: =+'FS Calcs'!K46 -> 94.930515 | L14: =+'FS Calcs'!L46 -> 97.998023 | M14: =+'FS Calcs'!M46 -> 102.1352 | N14: =+'FS Calcs'!N46 -> 107.16554 | O14: =+'FS Calcs'!O46 -> 112.98338 | P14: =+'FS Calcs'!P46 -> 119.58183 | Q14: =+'FS Calcs'!Q46 -> 126.98592 | ... S14: =+'FS Calcs'!S46 -> 144.37427
B15: Property, Plant & Equipment | E15: 30.436 | F15: 19.352 | G15: 54.245 | H15: 47.229 | I15: 39.287 | J15: =+'FS Calcs'!J56 -> 31.389683 | K15: =+'FS Calcs'!K56 -> 27.013899 | L15: =+'FS Calcs'!L56 -> 24.563741 | M15: =+'FS Calcs'!M56 -> 24.563741 | N15: =+'FS Calcs'!N56 -> 24.563741 | O15: =+'FS Calcs'!O56 -> 24.563741 | P15: =+'FS Calcs'!P56 -> 24.563741 | Q15: =+'FS Calcs'!Q56 -> 24.563741 | ... S15: =+'FS Calcs'!S56 -> 24.563741
B16: Derivative assets | I16: 8.845 | J16: =+I16 -> 8.845 | K16: =+J16 -> 8.845 | L16: =+K16 -> 8.845 | M16: =+L16 -> 8.845 | N16: =+M16 -> 8.845 | O16: =+N16 -> 8.845 | P16: =+O16 -> 8.845 | Q16: =+P16 -> 8.845 | ... S16: =+R16 -> 8.845
B17: Intangible Assets | E17: 546.997 | F17: 465.832 | G17: 472.531 | H17: 433.595 | I17: 448.947 | J17: =+'FS Calcs'!J67 -> 443.68212 | K17: =+'FS Calcs'!K67 -> 438.68123 | L17: =+'FS Calcs'!L67 -> 434.01426 | M17: =+'FS Calcs'!M67 -> 429.97506 | N17: =+'FS Calcs'!N67 -> 426.75428 | O17: =+'FS Calcs'!O67 -> 424.49459 | P17: =+'FS Calcs'!P67 -> 423.30898 | Q17: =+'FS Calcs'!Q67 -> 423.30898 | ... S17: =+'FS Calcs'!S67 -> 423.30898
B18: Goodwill | E18: 240.806 | F18: 239.754 | G18: 55.344 | H18: 53.164 | I18: 54.033 | J18: =+I18 -> 54.033 | K18: =+J18 -> 54.033 | L18: =+K18 -> 54.033 | M18: =+L18 -> 54.033 | N18: =+M18 -> 54.033 | O18: =+N18 -> 54.033 | P18: =+O18 -> 54.033 | Q18: =+P18 -> 54.033 | ... S18: =+R18 -> 54.033
B19: Total Assets | E19: =+SUM(E13:E18,E11) -> 1476.792 | F19: =+SUM(F13:F18,F11) -> 1318.955 | G19: =+SUM(G13:G18,G11) -> 1146.301 | H19: =+SUM(H13:H18,H11) -> 1127.902 | I19: =+SUM(I13:I18,I11) -> 1219.174 | J19: =+SUM(J13:J18,J11) -> 1215.4784 | K19: =+SUM(K13:K18,K11) -> 1261.3461 | L19: =+SUM(L13:L18,L11) -> 1333.0633 | ... S19: =+SUM(S13:S18,S11) -> 1737.8482
B21: Bank Indebtedness | E21: 16.35 | F21: 0 | G21: 10 | H21: 0 | I21: 9.087 | J21: =+'Debt Calcs'!J7 -> 40.509 | K21: =+'Debt Calcs'!K7 -> 40.509 | L21: =+'Debt Calcs'!L7 -> 40.509 | M21: =+'Debt Calcs'!M7 -> 40.509 | N21: =+'Debt Calcs'!N7 -> 40.509 | O21: =+'Debt Calcs'!O7 -> 40.509 | P21: =+'Debt Calcs'!P7 -> 40.509 | Q21: =+'Debt Calcs'!Q7 -> 40.509 | ... S21: =+'Debt Calcs'!S7 -> 40.509
B22: Accounts Payable and Accrued Liabilities | E22: 130.545 | F22: 103.487 | G22: 98.927 | H22: 130.299 | I22: 180.956 | J22: =+'FS Calcs'!J20 -> 193.76872 | K22: =+'FS Calcs'!K20 -> 212.21517 | L22: =+'FS Calcs'!L20 -> 238.58739 | M22: =+'FS Calcs'!M20 -> 258.80071 | N22: =+'FS Calcs'!N20 -> 275.70671 | O22: =+'FS Calcs'!O20 -> 290.62928 | P22: =+'FS Calcs'!P20 -> 305.41536 | Q22: =+'FS Calcs'!Q20 -> 320.66078 | ... S22: =+'FS Calcs'!S20 -> 353.44815
B23: Deferred Revenue | E23: 47.552 | F23: 64.299 | G23: 48.371 | H23: 42.004 | I23: 58.116 | J23: =+'FS Calcs'!J23 -> 52.648778 | K23: =+'FS Calcs'!K23 -> 58.343796 | L23: =+'FS Calcs'!L23 -> 65.337542 | M23: =+'FS Calcs'!M23 -> 70.685889 | N23: =+'FS Calcs'!N23 -> 75.151717 | O23: =+'FS Calcs'!O23 -> 79.089156 | P23: =+'FS Calcs'!P23 -> 82.992286 | Q23: =+'FS Calcs'!Q23 -> 87.020443 | ... S23: =+'FS Calcs'!S23 -> 95.74423
B24: Production Financing | E24: 93.683 | F24: 92.448 | G24: 66.688 | H24: 65.403 | I24: 84.235 | J24: =+'Debt Calcs'!J8 -> 90 | K24: =+'Debt Calcs'!K8 -> 90 | L24: =+'Debt Calcs'!L8 -> 90 | M24: =+'Debt Calcs'!M8 -> 90 | N24: =+'Debt Calcs'!N8 -> 90 | O24: =+'Debt Calcs'!O8 -> 90 | P24: =+'Debt Calcs'!P8 -> 90 | Q24: =+'Debt Calcs'!Q8 -> 90 | ... S24: =+'Debt Calcs'!S8 -> 90
B25: Current Portion of Lease Liabilities | E25: 0 | F25: 0 | G25: 9.274 | H25: 9.428 | I25: 10.183 | J25: =+'Debt Calcs'!J9 -> 0 | K25: =+'Debt Calcs'!K9 -> 0 | L25: =+'Debt Calcs'!L9 -> 0 | M25: =+'Debt Calcs'!M9 -> 0 | N25: =+'Debt Calcs'!N9 -> 0 | O25: =+'Debt Calcs'!O9 -> 0 | P25: =+'Debt Calcs'!P9 -> 0 | Q25: =+'Debt Calcs'!Q9 -> 0 | ... S25: =+'Debt Calcs'!S9 -> 0
B26: Current Portion of Long-Term Debt | E26: 10.524 | F26: 11.007 | G26: 0 | H26: 3.532 | I26: 26.335 | J26: =+'Debt Calcs'!J10 -> 0 | K26: =+'Debt Calcs'!K10 -> 0 | L26: =+'Debt Calcs'!L10 -> 0 | M26: =+'Debt Calcs'!M10 -> 0 | N26: =+'Debt Calcs'!N10 -> 0 | O26: =+'Debt Calcs'!O10 -> 0 | P26: =+'Debt Calcs'!P10 -> 0 | Q26: =+'Debt Calcs'!Q10 -> 0 | ... S26: =+'Debt Calcs'!S10 -> 0
B27: Total Current Liabilities | E27: =SUM(E21:E26) -> 298.654 | F27: =SUM(F21:F26) -> 271.241 | G27: =SUM(G21:G26) -> 233.26 | H27: =SUM(H21:H26) -> 250.666 | I27: =SUM(I21:I26) -> 368.912 | J27: =SUM(J21:J26) -> 376.9265 | K27: =SUM(K21:K26) -> 401.06796 | L27: =SUM(L21:L26) -> 434.43393 | ... S27: =SUM(S21:S26) -> 579.70138
B29: Long-Term Debt | E29: 746.046 | F29: 523.061 | G29: 502.006 | H29: 478.862 | I29: 477.804 | J29: =+'Debt Calcs'!J13 -> 508.43978 | K29: =+'Debt Calcs'!K13 -> 598.48039 | L29: =+'Debt Calcs'!L13 -> 676.37008 | M29: =+'Debt Calcs'!M13 -> 753.49212 | N29: =+'Debt Calcs'!N13 -> 830.64655 | O29: =+'Debt Calcs'!O13 -> 909.94618 | P29: =+'Debt Calcs'!P13 -> 992.80209 | Q29: =+'Debt Calcs'!Q13 -> 1079.7369 | ... S29: =+'Debt Calcs'!S13 -> 1265.5376
B30: Long-Term Lease Liabilities | E30: 0 | F30: 0 | G30: 41.552 | H30: 34.407 | I30: 26.056 | J30: =+'Debt Calcs'!J14 -> 36.239 | K30: =+'Debt Calcs'!K14 -> 36.239 | L30: =+'Debt Calcs'!L14 -> 36.239 | M30: =+'Debt Calcs'!M14 -> 36.239 | N30: =+'Debt Calcs'!N14 -> 36.239 | O30: =+'Debt Calcs'!O14 -> 36.239 | P30: =+'Debt Calcs'!P14 -> 36.239 | Q30: =+'Debt Calcs'!Q14 -> 36.239 | ... S30: =+'Debt Calcs'!S14 -> 36.239
B31: Deferred Taxes | E31: 17.679 | F31: 16.406 | G31: 18.261 | H31: 10.328 | I31: 7.761 | J31: =+I31 -> 7.761 | K31: =+J31 -> 7.761 | L31: =+K31 -> 7.761 | M31: =+L31 -> 7.761 | N31: =+M31 -> 7.761 | O31: =+N31 -> 7.761 | P31: =+O31 -> 7.761 | Q31: =+P31 -> 7.761 | ... S31: =+R31 -> 7.761
B32: Other Long-Term Liabilities (incl. derivatives) | E32: 13.621 | F32: 8.269 | G32: 9.736 | H32: 50.726 | I32: 23.238 | J32: =+I32 -> 23.238 | K32: =+J32 -> 23.238 | L32: =+K32 -> 23.238 | M32: =+L32 -> 23.238 | N32: =+M32 -> 23.238 | O32: =+N32 -> 23.238 | P32: =+O32 -> 23.238 | Q32: =+P32 -> 23.238 | ... S32: =+R32 -> 23.238
B33: Total Liabilities | E33: =+SUM(E29:E32,E27) -> 1076 | F33: =+SUM(F29:F32,F27) -> 818.977 | G33: =+SUM(G29:G32,G27) -> 804.815 | H33: =+SUM(H29:H32,H27) -> 824.989 | I33: =+SUM(I29:I32,I27) -> 903.771 | J33: =+SUM(J29:J32,J27) -> 952.60428 | K33: =+SUM(K29:K32,K27) -> 1066.7864 | L33: =+SUM(L29:L32,L27) -> 1178.042 | ... S33: =+SUM(S29:S32,S27) -> 1912.477
B35: Equity to common | E35: 315.078 | F35: 243.033 | G35: 81.351 | H35: 68.588 | I35: 79.428 | J35: =+'FS Calcs'!J78 -> 68.942507 | K35: =+'FS Calcs'!K78 -> 66.399389 | L35: =+'FS Calcs'!L78 -> 77.202377 | M35: =+'FS Calcs'!M78 -> 92.940227 | N35: =+'FS Calcs'!N78 -> 110.86273 | O35: =+'FS Calcs'!O78 -> 130.3256 | P35: =+'FS Calcs'!P78 -> 151.23323 | Q35: =+'FS Calcs'!Q78 -> 173.65604 | ... S35: =+'FS Calcs'!S78 -> 221.05787
B36: NCI | E36: 85.714 | F36: 256.945 | G36: 260.135 | H36: 234.325 | I36: 235.975 | J36: =+'FS Calcs'!J84 -> 228.59308 | K36: =+'FS Calcs'!K84 -> 221.33251 | L36: =+'FS Calcs'!L84 -> 214.20379 | M36: =+'FS Calcs'!M84 -> 207.21787 | N36: =+'FS Calcs'!N84 -> 200.38617 | O36: =+'FS Calcs'!O84 -> 193.72059 | P36: =+'FS Calcs'!P84 -> 187.23354 | Q36: =+'FS Calcs'!Q84 -> 180.93793 | ... S36: =+'FS Calcs'!S84 -> 168.97549
B37: Total Equity | E37: =+E36+E35 -> 400.792 | F37: =+F36+F35 -> 499.978 | G37: =+G36+G35 -> 341.486 | H37: =+H36+H35 -> 302.913 | I37: =+I36+I35 -> 315.403 | J37: =+J36+J35 -> 297.53558 | K37: =+K36+K35 -> 287.7319 | L37: =+L36+L35 -> 291.40617 | ... S37: =+S36+S35 -> 390.03336
B39: Balance | E39: =+E19=E33+E37 -> TRUE | F39: =+F19=F33+F37 -> TRUE | G39: =+G19=G33+G37 -> TRUE | H39: =+H19=H33+H37 -> TRUE | I39: =+I19=I33+I37 -> TRUE | J39: =+J19=J33+J37 -> FALSE | K39: =+K19=K33+K37 -> FALSE | L39: =+L19=L33+L37 -> FALSE | ... S39: =+S19=S33+S37 -> FALSE
B41: NWC (excl. investment in film and TV) | E41: =+SUM(E8:E9,E13)-SUM(E22:E23) -> 100.81 | F41: =+SUM(F8:F9,F13)-SUM(F22:F23) -> 119.424 | G41: =+SUM(G8:G9,G13)-SUM(G22:G23) -> 82.733 | H41: =+SUM(H8:H9,H13)-SUM(H22:H23) -> 81.118 | I41: =+SUM(I8:I9,I13)-SUM(I22:I23) -> 103.961 | J41: =+SUM(J8:J9,J13)-SUM(J22:J23) -> 109.31821 | K41: =+SUM(K8:K9,K13)-SUM(K22:K23) -> 122.72825 | L41: =+SUM(L8:L9,L13)-SUM(L22:L23) -> 135.47727 | ... S41: =+SUM(S8:S9,S13)-SUM(S22:S23) -> 190.70383
B42: NWC (incl. investment in film and TV) | E42: =+E41+E10 -> 286.818 | F42: =+F41+F10 -> 267.985 | G42: =+G41+G10 -> 223.281 | H42: =+H41+H10 -> 228.901 | I42: =+I41+I10 -> 267.524 | J42: =+J41+J10 -> 294.01435 | K42: =+K41+K10 -> 323.4485 | L42: =+L41+L10 -> 365.84932 | ... S42: =+S41+S10 -> 589.69587
B44: Total cash excl restricted cash | E44: =+E6 -> 46.55 | F44: =+F6 -> 39.999 | G44: =+G6 -> 67.889 | H44: =+H6 -> 78.431 | I44: =+I6 -> 59.899 | J44: =+J6 -> 35 | K44: =+K6 -> 35 | L44: =+L6 -> 35 | ... S44: =+S6 -> 35
B45: Total cash incl restricted cash | E45: =+E44+E7 -> 46.55 | F45: =+F44+F7 -> 39.999 | G45: =+G44+G7 -> 84.526 | H45: =+H44+H7 -> 92.057 | I45: =+I44+I7 -> 68.734 | J45: =+J44+J7 -> 43.835 | K45: =+K44+K7 -> 43.835 | L45: =+L44+L7 -> 43.835 | ... S45: =+S44+S7 -> 43.835
B47: Total debt excl lease | E47: =+E21+E26+E29+E24 -> 866.603 | F47: =+F21+F26+F29+F24 -> 626.516 | G47: =+G21+G26+G29+G24 -> 578.694 | H47: =+H21+H26+H29+H24 -> 547.797 | I47: =+I21+I26+I29+I24 -> 597.461 | J47: =+J21+J26+J29+J24 -> 638.94878 | K47: =+K21+K26+K29+K24 -> 728.98939 | L47: =+L21+L26+L29+L24 -> 806.87908 | ... S47: =+S21+S26+S29+S24 -> 1396.0466
B48: Total debt incl lease | E48: =+E47+E25+E30 -> 866.603 | F48: =+F47+F25+F30 -> 626.516 | G48: =+G47+G25+G30 -> 629.52 | H48: =+H47+H25+H30 -> 591.632 | I48: =+I47+I25+I30 -> 633.7 | J48: =+J47+J25+J30 -> 675.18778 | K48: =+K47+K25+K30 -> 765.22839 | L48: =+L47+L25+L30 -> 843.11808 | ... S48: =+S47+S25+S30 -> 1432.2856
B50: Net debt (excl restricted cash, incl leases) | E50: =+E48-E44 -> 820.053 | F50: =+F48-F44 -> 586.517 | G50: =+G48-G44 -> 561.631 | H50: =+H48-H44 -> 513.201 | I50: =+I48-I44 -> 573.801 | J50: =+J48-J44 -> 640.18778 | K50: =+K48-K44 -> 730.22839 | L50: =+L48-L44 -> 808.11808 | ... S50: =+S48-S44 -> 1397.2856
B52: ND / EBITDA | E52: =+E50/'P&L'!E56 -> 7.7757413 | F52: =+F50/'P&L'!F56 -> 5.5501438 | G52: =+G50/'P&L'!G56 -> 5.2758588 | H52: =+H50/'P&L'!H56 -> 4.3227847 | I52: =+I50/'P&L'!I56 -> 4.8862405 | J52: =+J50/'P&L'!J56 -> 5.0779168 | K52: =+K50/'P&L'!K56 -> 4.9835889 | L52: =+L50/'P&L'!L56 -> 4.8339458 | ... S52: =+S50/'P&L'!S56 -> 5.8306512
J53: 2023 | K53: =+J53+1 -> 2024 | L53: =+K53+1 -> 2025 | M53: =+L53+1 -> 2026 | N53: =+M53+1 -> 2027
A55: x | B55: CFS
B56: Net income to common and NCI | I56: =+'P&L'!I34 -> 31.762 | J56: =+'P&L'!J34 -> 16.413765 | K56: =+'P&L'!K34 -> 25.163117 | L56: =+'P&L'!L34 -> 39.34041 | M56: =+'P&L'!M34 -> 45.131394 | N56: =+'P&L'!N34 -> 48.197855 | O56: =+'P&L'!O34 -> 50.646485 | P56: =+'P&L'!P34 -> 53.026747 | ... S56: =+'P&L'!S34 -> 59.389698
B57: Depreciation of PPE | I57: =+'FS Calcs'!I53*-1 -> 13.378 | J57: =+'FS Calcs'!J53*-1 -> 15.794633 | K57: =+'FS Calcs'!K53*-1 -> 13.127354 | L57: =+'FS Calcs'!L53*-1 -> 12.250789 | M57: =+'FS Calcs'!M53*-1 -> 10.602883 | N57: =+'FS Calcs'!N53*-1 -> 11.272758 | O57: =+'FS Calcs'!O53*-1 -> 11.863373 | P57: =+'FS Calcs'!P53*-1 -> 12.448843 | ... S57: =+'FS Calcs'!S53*-1 -> 14.361634
B58: Amort of intangibles | I58: =+'FS Calcs'!I64*-1 -> 10.601 | J58: =+'FS Calcs'!J64*-1 -> 15.794633 | K58: =+'FS Calcs'!K64*-1 -> 16.669656 | L58: =+'FS Calcs'!L64*-1 -> 17.734476 | M58: =+'FS Calcs'!M64*-1 -> 18.176371 | N58: =+'FS Calcs'!N64*-1 -> 18.251131 | O58: =+'FS Calcs'!O64*-1 -> 18.077521 | P58: =+'FS Calcs'!P64*-1 -> 17.784061 | ... S58: =+'FS Calcs'!S64*-1 -> 19.148846
B59: Amort of acquired and library content | I59: =+'FS Calcs'!I44*-1 -> 10.241 | J59: =+'FS Calcs'!J44*-1 -> 10 | K59: =+'FS Calcs'!K44*-1 -> 10 | L59: =+'FS Calcs'!L44*-1 -> 10 | M59: =+'FS Calcs'!M44*-1 -> 10 | N59: =+'FS Calcs'!N44*-1 -> 10 | O59: =+'FS Calcs'!O44*-1 -> 10 | P59: =+'FS Calcs'!P44*-1 -> 10 | ... S59: =+'FS Calcs'!S44*-1 -> 10
B60: Net investment in TV and film programs | I60: =+('FS Calcs'!I31+'FS Calcs'!I33)*-1 -> -24.197 | J60: =+('FS Calcs'!J31+'FS Calcs'!J33)*-1 -> -21.133143 | K60: =+('FS Calcs'!K31+'FS Calcs'!K33)*-1 -> -26.024104 | L60: =+('FS Calcs'!L31+'FS Calcs'!L33)*-1 -> -29.651799 | M60: =+('FS Calcs'!M31+'FS Calcs'!M33)*-1 -> -28.518936 | N60: =+('FS Calcs'!N31+'FS Calcs'!N33)*-1 -> -26.488149 | O60: =+('FS Calcs'!O31+'FS Calcs'!O33)*-1 -> -25.182787 | P60: =+('FS Calcs'!P31+'FS Calcs'!P33)*-1 -> -24.022702 | ... S60: =+('FS Calcs'!S31+'FS Calcs'!S33)*-1 -> -20.026506
B61: Chg in NWC | I61: =+H41-I41 -> -22.843 | J61: =+I41-J41 -> -5.3572074 | K61: =+J41-K41 -> -13.410042 | L61: =+K41-L41 -> -12.749023 | M61: =+L41-M41 -> -9.7039792 | N61: =+M41-N41 -> -8.0747122 | O61: =+N41-O41 -> -7.1024631 | P61: =+O41-P41 -> -7.0470418 | ... S61: =+R41-S41 -> -8.4401831
B62: Writedown and impairements | I62: =+'P&L'!I18 -> -0.788 | J62: =+'P&L'!J18 -> 0 | K62: =+'P&L'!K18 -> -10 | L62: =+'P&L'!L18 -> 0 | M62: =+'P&L'!M18 -> 0 | N62: =+'P&L'!N18 -> 0 | O62: =+'P&L'!O18 -> 0 | P62: =+'P&L'!P18 -> 0 | ... S62: =+'P&L'!S18 -> 0
B63: Adjustments | I63: =+I64-SUM(I56:I62) -> 14.946 | J63: 0 | K63: 0 | L63: 0 | M63: 0 | N63: 0 | O63: 0 | P63: 0 | Q63: 0 | R63: 0 | S63: 0
B64: OCF | I64: =+I100 -> 33.1 | J64: =SUM(J56:J63) -> 31.512681 | K64: =SUM(K56:K63) -> 15.52598 | L64: =SUM(L56:L63) -> 36.924852 | M64: =SUM(M56:M63) -> 45.687734 | N64: =SUM(N56:N63) -> 53.158883 | O64: =SUM(O56:O63) -> 58.302131 | P64: =SUM(P56:P63) -> 62.189908 | Q64: =SUM(Q56:Q63) -> 65.852747 | ... S64: =SUM(S56:S63) -> 74.433489
B66: Addition of PPE incl leases | I66: =+('FS Calcs'!I52*-1)+'Debt Calcs'!I62 -> -2.995 | J66: =+('FS Calcs'!J52*-1)+'Debt Calcs'!J62 -> -5.5843167 | K66: =+('FS Calcs'!K52*-1)+'Debt Calcs'!K62 -> -6.4385694 | L66: =+('FS Calcs'!L52*-1)+'Debt Calcs'!L62 -> -7.4876312 | M66: =+('FS Calcs'!M52*-1)+'Debt Calcs'!M62 -> -8.2898833 | N66: =+('FS Calcs'!N52*-1)+'Debt Calcs'!N62 -> -8.9597576 | O66: =+('FS Calcs'!O52*-1)+'Debt Calcs'!O62 -> -9.5503734 | P66: =+('FS Calcs'!P52*-1)+'Debt Calcs'!P62 -> -10.135843 | ... S66: =+('FS Calcs'!S52*-1)+'Debt Calcs'!S62 -> -12.048634
B67: Addition of intangibles | I67: =+'FS Calcs'!I63*-1 -> -14.309 | J67: =+'FS Calcs'!J63*-1 -> -10.529756 | K67: =+'FS Calcs'!K63*-1 -> -11.668759 | L67: =+'FS Calcs'!L63*-1 -> -13.067508 | M67: =+'FS Calcs'!M63*-1 -> -14.137178 | N67: =+'FS Calcs'!N63*-1 -> -15.030343 | O67: =+'FS Calcs'!O63*-1 -> -15.817831 | P67: =+'FS Calcs'!P63*-1 -> -16.598457 | ... S67: =+'FS Calcs'!S63*-1 -> -19.148846
B68: Addition of content | I68: =+'FS Calcs'!I42*-1 -> -1 | J68: =+'FS Calcs'!J42*-1 -> -10.529756 | K68: =+'FS Calcs'!K42*-1 -> -11.668759 | L68: =+'FS Calcs'!L42*-1 -> -13.067508 | M68: =+'FS Calcs'!M42*-1 -> -14.137178 | N68: =+'FS Calcs'!N42*-1 -> -15.030343 | O68: =+'FS Calcs'!O42*-1 -> -15.817831 | P68: =+'FS Calcs'!P42*-1 -> -16.598457 | ... S68: =+'FS Calcs'!S42*-1 -> -19.148846
B69: Adjustments | I69: =+I70-SUM(I66:I68) -> 7.465 | J69: 0 | K69: 0 | L69: 0 | M69: 0 | N69: 0 | O69: 0 | P69: 0 | Q69: 0 | R69: 0 | S69: 0
B70: Investing cash flow | I70: =+I105 -> -10.839 | J70: =SUM(J67:J69) -> -21.059511 | K70: =SUM(K67:K69) -> -23.337518 | L70: =SUM(L67:L69) -> -26.135017 | M70: =SUM(M67:M69) -> -28.274355 | N70: =SUM(N67:N69) -> -30.060687 | O70: =SUM(O67:O69) -> -31.635662 | P70: =SUM(P67:P69) -> -33.196914 | Q70: =SUM(Q67:Q69) -> -34.808177 | ... S70: =SUM(S67:S69) -> -38.297692
B72: Debt draw / (repayments) | I72: =+I111+I112+I116 -> 24.299 | J72: =+'Debt Calcs'!J39+'Debt Calcs'!J45+'Debt Calcs'!J51+'Debt Calcs'!J56 -> 41.487784 | K72: =+'Debt Calcs'!K39+'Debt Calcs'!K45+'Debt Calcs'!K51+'Debt Calcs'!K56 -> 90.04061 | L72: =+'Debt Calcs'!L39+'Debt Calcs'!L45+'Debt Calcs'!L51+'Debt Calcs'!L56 -> 77.889682 | M72: =+'Debt Calcs'!M39+'Debt Calcs'!M45+'Debt Calcs'!M51+'Debt Calcs'!M56 -> 77.122043 | N72: =+'Debt Calcs'!N39+'Debt Calcs'!N45+'Debt Calcs'!N51+'Debt Calcs'!N56 -> 77.15443 | O72: =+'Debt Calcs'!O39+'Debt Calcs'!O45+'Debt Calcs'!O51+'Debt Calcs'!O56 -> 79.299628 | P72: =+'Debt Calcs'!P39+'Debt Calcs'!P45+'Debt Calcs'!P51+'Debt Calcs'!P56 -> 82.855911 | Q72: =+'Debt Calcs'!Q39+'Debt Calcs'!Q45+'Debt Calcs'!Q51+'Debt Calcs'!Q56 -> 86.934823 | ... S72: =+'Debt Calcs'!S39+'Debt Calcs'!S45+'Debt Calcs'!S51+'Debt Calcs'!S56 -> 94.924186
B73: Lease repayments | I73: =+'Debt Calcs'!I63 -> -9.495 | J73: =+'Debt Calcs'!J63 -> -2.313 | K73: =+'Debt Calcs'!K63 -> -2.313 | L73: =+'Debt Calcs'!L63 -> -2.313 | M73: =+'Debt Calcs'!M63 -> -2.313 | N73: =+'Debt Calcs'!N63 -> -2.313 | O73: =+'Debt Calcs'!O63 -> -2.313 | P73: =+'Debt Calcs'!P63 -> -2.313 | ... S73: =+'Debt Calcs'!S63 -> -2.313
B74: Dividend to common | I74: =+'P&L'!I44 -> 0 | J74: =+'P&L'!J44 -> 0 | K74: =+'P&L'!K44 -> 0 | L74: =+'P&L'!L44 -> 0 | M74: =+'P&L'!M44 -> 0 | N74: =+'P&L'!N44 -> 0 | O74: =+'P&L'!O44 -> 0 | P74: =+'P&L'!P44 -> 0 | ... S74: =+'P&L'!S44 -> 0
B75: Dictribution to NCI | I75: =+'P&L'!I45 -> -33.609 | J75: =+'P&L'!J45 -> -34.28118 | K75: =+'P&L'!K45 -> -34.966804 | L75: =+'P&L'!L45 -> -35.66614 | M75: =+'P&L'!M45 -> -36.379462 | N75: =+'P&L'!N45 -> -37.107052 | O75: =+'P&L'!O45 -> -37.849193 | P75: =+'P&L'!P45 -> -38.606177 | ... S75: =+'P&L'!S45 -> -40.969183
B76: Finance cost | I76: =+'P&L'!I22 -> -30.486 | J76: =+'P&L'!J22 -> -34.661458 | K76: =+'P&L'!K22 -> -38.510699 | L76: =+'P&L'!L22 -> -43.212747 | M76: =+'P&L'!M22 -> -47.553075 | N76: =+'P&L'!N22 -> -51.872817 | O76: =+'P&L'!O22 -> -56.25353 | P76: =+'P&L'!P22 -> -60.793885 | ... S76: =+'P&L'!S22 -> -75.729165
B77: Adjustments | I77: =+I78-SUM(I72:I76) -> 3.16 | J77: 0 | K77: 0 | L77: 0 | M77: 0 | N77: 0 | O77: 0 | P77: 0 | Q77: 0 | R77: 0 | S77: 0
B78: Financing cash flow | I78: =+I117 -> -46.131 | J78: =+SUM(J72:J77) -> -29.767854 | K78: =+SUM(K72:K77) -> 14.250107 | L78: =+SUM(L72:L77) -> -3.3022046 | M78: =+SUM(M72:M77) -> -9.123495 | N78: =+SUM(N72:N77) -> -14.138439 | O78: =+SUM(O72:O77) -> -17.116095 | P78: =+SUM(P72:P77) -> -18.857151 | Q78: =+SUM(Q72:Q77) -> -20.304503 | ... S78: =+SUM(S72:S77) -> -24.087162
A82: x | B82: CFS (based on FS)
B83: Net income for the year | I83: 31.762
B84: Amortization of property and equipment | I84: 13.378
B85: Amortization of intangible assets | I85: 10.601
B86: Amortization of acquired and library content | I86: 10.241
B87: Accretion expense and amortization of deferred financing fees | I87: 12.813
B88: Unrealized foreign exchange loss (gain) | I88: 16.667
B89: Share-based compensation | I89: 7.414
B90: Change in fair value of embedded derivatives | I90: -13.716
B91: Change in fair value of interest rate swap | I91: -9.086
B92: Interest income | I92: -3.041
B93: Interest expense | I93: 29.8
B94: Deferred tax recovery | I94: -1.904
... B99: Net change in non-cash balances related to operations (note 25) | I99: -48.42
B100: OCF | I100: =SUM(I83:I99) -> 33.1
B102: Acquisition of acquired and library content (note 5) | I102: -0.3
B103: Acquisition of property and equipment | I103: -2.995
B104: Acquisition of intangible assets | I104: -7.544
B105: Investing cash flow | I105: =SUM(I102:I104) -> -10.839
B107: Common shares issued, net of issuance costs | I107: 0.416
B108: Payroll taxes remitted on net share settlement | I108: -1.46
B109: Common share purchased held in trust, net | I109: -0.06
B110: Distributions to non-controlling interests | I110: -33.609
B111: Proceeds from (repayment of) bank indebtedness | I111: 9.087
B112: (Repayment of) proceeds from long-term debt | I112: -3.62
B113: Interest paid on long-term debt | I113: -26.256
B114: Realized foreign exchange on long term debt repayment | I114: 0.034
B115: Repayment of obligations under finance leases | I115: -9.495
B116: Proceeds from (repayment of) interim production financing, net (note 25) | I116: 18.832
B117: Financing cash flow | I117: =SUM(I107:I116) -> -46.131
B119: FX impact | I119: 0.545
B121: Net change in cash | I121: =+I119+I117+I105+I100 -> -23.325

Sheet RevBuild Calcs
A1: in CADm unless otherwise stated
A2: FYE June
E4: 2018 | F4: =+E4+1 -> 2019 | G4: =+F4+1 -> 2020 | H4: =+G4+1 -> 2021 | I4: =+H4+1 -> 2022 | J4: =+I4+1 -> 2023 | K4: =+J4+1 -> 2024 | L4: =+K4+1 -> 2025 | M4: =+L4+1 -> 2026 | ... S4: =+R4+1 -> 2032
A6: x | B6: Segmental Revenue
B7: Content production and distribution | E7: 164.374 | F7: 143.763 | G7: 145.225 | H7: 185.084 | I7: 206.572 | J7: =+J29 -> 216.9006 | K7: =+K29 -> 238.59066 | L7: =+L29 -> 262.44973 | M7: =+M29 -> 275.57221 | N7: =+N29 -> 283.83938 | O7: =+O29 -> 292.35456 | P7: =+P29 -> 301.1252 | Q7: =+Q29 -> 310.15895 | ... S7: =+S29 -> 329.04763
B8: WildBrain Spark | E8: 57.282 | F8: 68.996 | G8: 62.278 | H8: 45.754 | I8: 55.41 | J8: =+J36 -> 45.65784 | K8: =+K36 -> 54.081711 | L8: =+L36 -> 69.630204 | M8: =+M36 -> 75.305065 | N8: =+N36 -> 81.054607 | O8: =+O36 -> 86.825695 | P8: =+P36 -> 92.560532 | Q8: =+Q36 -> 98.197468 | ... S8: =+S36 -> 108.38647
B9: Consumer Products | E9: 157.746 | F9: 174.572 | G9: 168.604 | H9: 175.194 | I9: 203.557 | J9: =+J64 -> 223.9127 | K9: =+K64 -> 252.34961 | L9: =+L64 -> 284.41615 | M9: =+M64 -> 320.57745 | N9: =+N64 -> 352.63519 | O9: =+O64 -> 379.08283 | P9: =+P64 -> 404.91379 | Q9: =+Q64 -> 431.7776 | ... S9: =+S64 -> 491.1406
B10: Total content | E10: =SUM(E7:E9) -> 379.402 | F10: =SUM(F7:F9) -> 387.331 | G10: =SUM(G7:G9) -> 376.107 | H10: =SUM(H7:H9) -> 406.032 | I10: =SUM(I7:I9) -> 465.539 | J10: =SUM(J7:J9) -> 486.47114 | K10: =SUM(K7:K9) -> 545.02198 | L10: =SUM(L7:L9) -> 616.49608 | ... S10: =SUM(S7:S9) -> 928.57471
B12: Canadian Television Broadcasting | E12: 55.014 | F12: 52.469 | G12: 49.527 | H12: 46.502 | I12: 41.684 | J12: =+J82 -> 40.01664 | K12: =+K82 -> 38.415974 | L12: =+L82 -> 36.879335 | M12: =+M82 -> 35.404162 | N12: =+N82 -> 33.987996 | O12: =+O82 -> 32.628476 | P12: =+P82 -> 31.323337 | Q12: =+Q82 -> 30.070403 | ... S12: =+S82 -> 28.867587
B14: Total revenue | E14: =+E12+E10 -> 434.416 | F14: =+F12+F10 -> 439.8 | G14: =+G12+G10 -> 425.634 | H14: =+H12+H10 -> 452.534 | I14: =+I12+I10 -> 507.223 | J14: =+J12+J10 -> 526.48778 | K14: =+K12+K10 -> 583.43796 | L14: =+L12+L10 -> 653.37542 | ... S14: =+S12+S10 -> 957.4423
B15: Check | E15: =+E14='P&L'!E6 -> TRUE | F15: =+F14='P&L'!F6 -> TRUE | G15: =+G14='P&L'!G6 -> TRUE | H15: =+H14='P&L'!H6 -> TRUE | I15: =+I14='P&L'!I6 -> TRUE
A17: x | B17: Segmental gross profit
B18: Content | H18: 162.692 | I18: 193.455 | J18: =+J19*J10 -> 194.58846 | K18: =+K19*K10 -> 223.45901 | L18: =+L19*L10 -> 252.76339 | M18: =+M19*M10 -> 275.29644 | N18: =+N19*N10 -> 294.18696 | O18: =+O19*O10 -> 310.88787 | P18: =+P19*P10 -> 327.4258 | Q18: =+Q19*Q10 -> 344.45495 | ... S18: =+S19*S10 -> 380.71563
B19: % margin | H19: =+H18/H10 -> 0.40068763 | I19: =+I18/I10 -> 0.41555058 | J19: 0.4 | K19: 0.41 | L19: 0.41 | M19: 0.41 | N19: 0.41 | O19: 0.41 | P19: 0.41 | Q19: 0.41 | R19: 0.41 | S19: 0.41
B21: Canadian TV business | H21: 32.195 | I21: 28.106 | J21: =+J22*J12 -> 26.010816 | K21: =+K22*K12 -> 24.970383 | L21: =+L22*L12 -> 23.971568 | M21: =+M22*M12 -> 23.012705 | N21: =+N22*N12 -> 22.092197 | O21: =+O22*O12 -> 21.208509 | P21: =+P22*P12 -> 20.360169 | Q21: =+Q22*Q12 -> 19.545762 | ... S21: =+S22*S12 -> 18.763932
B22: % margin | H22: =+H21/H12 -> 0.69233581 | I22: =+I21/I12 -> 0.67426351 | J22: 0.65 | K22: =+J22 -> 0.65 | L22: =+K22 -> 0.65 | M22: =+L22 -> 0.65 | N22: =+M22 -> 0.65 | O22: =+N22 -> 0.65 | P22: =+O22 -> 0.65 | Q22: =+P22 -> 0.65 | R22: =+Q22 -> 0.65 | S22: =+R22 -> 0.65
B24: Adjustments | H24: =+'P&L'!H9 -> 4.372
B26: Total gross profit | H26: =+H21+H18+H24 -> 199.259 | I26: =+I21+I18+I24 -> 221.561 | J26: =+J21+J18+J24 -> 220.59927 | K26: =+K21+K18+K24 -> 248.4294 | L26: =+L21+L18+L24 -> 276.73496 | M26: =+M21+M18+M24 -> 298.30914 | N26: =+N21+N18+N24 -> 316.27916 | O26: =+O21+O18+O24 -> 332.09637 | ... S26: =+S21+S18+S24 -> 399.47956
H27: =+ROUND(H26-'P&L'!H13, 1)=0 -> TRUE | I27: =+I26='P&L'!I13 -> TRUE
A28: x | B28: Content production and distribution
B29: Revenue | E29: =+E7 -> 164.374 | F29: =+F7 -> 143.763 | G29: =+G7 -> 145.225 | H29: =+H7 -> 185.084 | I29: =+I7 -> 206.572 | J29: =+(1+J30)*I29 -> 216.9006 | K29: =+(1+K30)*J29 -> 238.59066 | L29: =+(1+L30)*K29 -> 262.44973 | M29: =+(1+M30)*L29 -> 275.57221 | N29: =+(1+N30)*M29 -> 283.83938 | O29: =+(1+O30)*N29 -> 292.35456 | P29: =+(1+P30)*O29 -> 301.1252 | Q29: =+(1+Q30)*P29 -> 310.15895 | ... S29: =+(1+S30)*R29 -> 329.04763
B30: % YoY | F30: =+F29/E29-1 -> -0.12539088 | G30: =+G29/F29-1 -> 0.010169515 | H30: =+H29/G29-1 -> 0.27446376 | I30: =+I29/H29-1 -> 0.11609864 | J30: =+CHOOSE(Case, J31,J32,J33) -> 0.05 | K30: =+CHOOSE(Case, K31,K32,K33) -> 0.1 | L30: =+CHOOSE(Case, L31,L32,L33) -> 0.1 | M30: =+CHOOSE(Case, M31,M32,M33) -> 0.05 | N30: =+CHOOSE(Case, N31,N32,N33) -> 0.03 | O30: =+CHOOSE(Case, O31,O32,O33) -> 0.03 | P30: =+CHOOSE(Case, P31,P32,P33) -> 0.03 | Q30: =+CHOOSE(Case, Q31,Q32,Q33) -> 0.03 | ... S30: =+CHOOSE(Case, S31,S32,S33) -> 0.03
B31: Base | J31: 0.05 | K31: 0.1 | L31: 0.1 | M31: 0.05 | N31: 0.03 | O31: 0.03 | P31: 0.03 | Q31: 0.03 | R31: 0.03 | S31: 0.03
B32: Upside | J32: 0.05 | K32: 0.15 | L32: 0.1 | M32: 0.05 | N32: 0.05 | O32: 0.05 | P32: 0.05 | Q32: 0.05 | R32: 0.05 | S32: 0.05
B33: Downside | J33: 0.05 | K33: 0.05 | L33: 0.05 | M33: 0.05 | N33: 0.05 | O33: 0.05 | P33: 0.05 | Q33: 0.05 | R33: 0.05 | S33: 0.05
A35: x | B35: Wildbrain Spark
B36: Revenue | E36: =+E8 -> 57.282 | F36: =+F8 -> 68.996 | G36: =+G8 -> 62.278 | H36: =+H8 -> 45.754 | I36: =+I8 -> 55.41 | J36: =+J39*J45 -> 45.65784 | K36: =+K39*K45 -> 54.081711 | L36: =+L39*L45 -> 69.630204 | M36: =+M39*M45 -> 75.305065 | N36: =+N39*N45 -> 81.054607 | O36: =+O39*O45 -> 86.825695 | P36: =+P39*P45 -> 92.560532 | Q36: =+Q39*Q45 -> 98.197468 | ... S36: =+S39*S45 -> 108.38647
B37: % YoY | F37: =+F36/E36-1 -> 0.20449705 | G37: =+G36/F36-1 -> -0.097367963 | H37: =+H36/G36-1 -> -0.26532644 | I37: =+I36/H36-1 -> 0.21104166 | J37: =+J36/I36-1 -> -0.176 | K37: =+K36/J36-1 -> 0.1845 | L37: =+L36/K36-1 -> 0.2875 | M37: =+M36/L36-1 -> 0.0815 | ... S37: =+S36/R36-1 -> 0.0506
B39: Views (billions) | E39: 25 | F39: =7.2+7+8.7+9.3 -> 32.2 | G39: =12+9.9+10.3+11.6 -> 43.8 | H39: 35 | I39: 32.9 | J39: =+(1+J40)*I39 -> 33.887 | K39: =+(1+K40)*J39 -> 34.90361 | L39: =+(1+L40)*K39 -> 35.950718 | M39: =+(1+M40)*L39 -> 37.02924 | N39: =+(1+N40)*M39 -> 38.140117 | O39: =+(1+O40)*N39 -> 39.284321 | P39: =+(1+P40)*O39 -> 40.46285 | Q39: =+(1+Q40)*P39 -> 41.676736 | ... S39: =+(1+S40)*R39 -> 44.214849
B40: % YoY | F40: =+F39/E39-1 -> 0.288 | G40: =+G39/F39-1 -> 0.36024845 | H40: =+H39/G39-1 -> -0.20091324 | I40: =+I39/H39-1 -> -0.06 | J40: =+CHOOSE(Case, J41,J42,J43) -> 0.03 | K40: =+CHOOSE(Case, K41,K42,K43) -> 0.03 | L40: =+CHOOSE(Case, L41,L42,L43) -> 0.03 | M40: =+CHOOSE(Case, M41,M42,M43) -> 0.03 | N40: =+CHOOSE(Case, N41,N42,N43) -> 0.03 | O40: =+CHOOSE(Case, O41,O42,O43) -> 0.03 | P40: =+CHOOSE(Case, P41,P42,P43) -> 0.03 | Q40: =+CHOOSE(Case, Q41,Q42,Q43) -> 0.03 | ... S40: =+CHOOSE(Case, S41,S42,S43) -> 0.03
B41: Base | J41: 0.03 | K41: 0.03 | L41: 0.03 | M41: 0.03 | N41: 0.03 | O41: 0.03 | P41: 0.03 | Q41: 0.03 | R41: 0.03 | S41: 0.03
B42: Upside | J42: 0.05 | K42: 0.05 | L42: 0.05 | M42: 0.05 | N42: 0.05 | O42: 0.05 | P42: 0.05 | Q42: 0.05 | R42: 0.05 | S42: 0.05
B43: Downside | J43: 0 | K43: 0.03 | L43: 0.03 | M43: 0.03 | N43: 0.03 | O43: 0.03 | P43: 0.03 | Q43: 0.03 | R43: 0.03 | S43: 0.03
B45: CPM (CAD) | E45: =+E36/E39 -> 2.29128 | F45: =+F36/F39 -> 2.1427329 | G45: =+G36/G39 -> 1.4218721 | H45: =+H36/H39 -> 1.3072571 | I45: =+I36/I39 -> 1.6841945 | J45: =+(1+J46)*I45 -> 1.3473556 | K45: =+(1+K46)*J45 -> 1.549459 | L45: =+(1+L46)*K45 -> 1.9368237 | M45: =+(1+M46)*L45 -> 2.0336649 | N45: =+(1+N46)*M45 -> 2.1251798 | O45: =+(1+O46)*N45 -> 2.210187 | P45: =+(1+P46)*O45 -> 2.2875436 | Q45: =+(1+Q46)*P45 -> 2.3561699 | ... S45: =+(1+S46)*R45 -> 2.4513591
B46: % YoY | F46: =+F45/E45-1 -> -0.064831483 | G46: =+G45/F45-1 -> -0.3364212 | H46: =+H45/G45-1 -> -0.080608516 | I46: =+I45/H45-1 -> 0.28834219 | J46: =+CHOOSE(Case, J47,J48,J49) -> -0.2 | K46: =+CHOOSE(Case, K47,K48,K49) -> 0.15 | L46: =+CHOOSE(Case, L47,L48,L49) -> 0.25 | M46: =+CHOOSE(Case, M47,M48,M49) -> 0.05 | N46: =+CHOOSE(Case, N47,N48,N49) -> 0.045 | O46: =+CHOOSE(Case, O47,O48,O49) -> 0.04 | P46: =+CHOOSE(Case, P47,P48,P49) -> 0.035 | Q46: =+CHOOSE(Case, Q47,Q48,Q49) -> 0.03 | ... S46: =+CHOOSE(Case, S47,S48,S49) -> 0.02
B47: Base | J47: -0.2 | K47: 0.15 | L47: 0.25 | M47: 0.05 | N47: 0.045 | O47: 0.04 | P47: 0.035 | Q47: 0.03 | R47: 0.02 | S47: 0.02
B48: Upside | J48: -0.2 | K48: 0.2 | L48: 0.3 | M48: 0.1 | N48: 0.05 | O48: 0.045 | P48: 0.04 | Q48: 0.03 | R48: 0.02 | S48: 0.02
B49: Downside | J49: -0.3 | K49: 0.1 | L49: 0.1 | M49: 0.05 | N49: 0.045 | O49: 0.04 | P49: 0.035 | Q49: 0.03 | R49: 0.02 | S49: 0.02
B51: Memo (based on Morgan Stanley analyst on Google)
B52: Youtube mobile CPM (USD) | E52: 1.3600422 | F52: 1.3511736 | G52: 1.4737851 | H52: 1.6806006 | I52: 1.4820115 | J52: 1.4822099 | K52: 1.5684875 | L52: 1.6575047 | M52: 1.7374636 | N52: 1.8087073 | O52: 1.8717475 | P52: 1.9271994 | Q52: 1.9757298 | R52: 1.9757298 | S52: 1.9757298
B53: Youtube dekstop CPM (USD) | E53: 1.824527 | F53: 1.7463245 | G53: 1.8424133 | H53: 2.1068821 | I53: 1.8286951 | J53: 1.7842481 | K53: 1.9290466 | L53: 2.0277097 | M53: 2.1009688 | N53: 2.1787009 | O53: 2.2611488 | P53: 2.348556 | Q53: 2.4309662 | R53: 2.4309662 | S53: 2.4309662
B55: FX - USDCAD | J55: =+Output!J8 -> 1.3503 | K55: =+Output!K8 -> 1.344 | L55: =+Output!L8 -> 1.3365 | M55: =+Output!M8 -> 1.3303 | N55: =+Output!N8 -> 1.3236 | O55: =+Output!O8 -> 1.3172 | P55: =+Output!P8 -> 1.3128 | Q55: =+Output!Q8 -> 1.3102 | ... S55: =+Output!S8 -> 1.3089
B57: Youtube mobile CPM (CAD) | J57: =+J52/J$55 -> 1.0976894 | K57: =+K52/K$55 -> 1.1670294 | L57: =+L52/L$55 -> 1.2401831 | M57: =+M52/M$55 -> 1.306069 | N57: =+N52/N$55 -> 1.366506 | O57: =+O52/O$55 -> 1.4210048 | P57: =+P52/P$55 -> 1.4680068 | Q57: =+Q52/Q$55 -> 1.5079605 | ... S57: =+S52/S$55 -> 1.5094582
B58: Youtube dekstop CPM (CAD) | J58: =+J53/J$55 -> 1.3213716 | K58: =+K53/K$55 -> 1.4353026 | L58: =+L53/L$55 -> 1.517179 | M58: =+M53/M$55 -> 1.5793195 | N58: =+N53/N$55 -> 1.6460418 | O58: =+O53/O$55 -> 1.7166328 | P58: =+P53/P$55 -> 1.7889671 | Q58: =+Q53/Q$55 -> 1.8554161 | ... S58: =+S53/S$55 -> 1.8572589
B60: Youtube mobile CPM (CAD) growth % | K60: =+K57/J57-1 -> 0.063169104 | L60: =+L57/K57-1 -> 0.062683686 | M60: =+M57/L57-1 -> 0.053125934 | N60: =+N57/M57-1 -> 0.046273941 | O60: =+O57/N57-1 -> 0.039881901 | P60: =+P57/O57-1 -> 0.033076607 | Q60: =+Q57/P57-1 -> 0.027216245 | R60: =+R57/Q57-1 -> 0.00030539014 | S60: =+S57/R57-1 -> 0.00068760028
B61: Youtube dekstop CPM (CAD) growth % | K61: =+K58/J58-1 -> 0.086221734 | L61: =+L58/K58-1 -> 0.057044736 | M61: =+M58/L58-1 -> 0.040957925 | N61: =+N58/M58-1 -> 0.042247464 | O61: =+O58/N58-1 -> 0.042885345 | P61: =+P58/O58-1 -> 0.042137282 | Q61: =+Q58/P58-1 -> 0.037143817 | R61: =+R58/Q58-1 -> 0.00030539014 | S61: =+S58/R58-1 -> 0.00068760028
A63: x | B63: Consumer Products
B64: Revenue | E64: =+E9 -> 157.746 | F64: =+F9 -> 174.572 | G64: =+G9 -> 168.604 | H64: =+H9 -> 175.194 | I64: =+I9 -> 203.557 | J64: =+J67+J74 -> 223.9127 | K64: =+K67+K74 -> 252.34961 | L64: =+L67+L74 -> 284.41615 | M64: =+M67+M74 -> 320.57745 | N64: =+N67+N74 -> 352.63519 | O64: =+O67+O74 -> 379.08283 | P64: =+P67+P74 -> 404.91379 | Q64: =+Q67+Q74 -> 431.7776 | ... S64: =+S67+S74 -> 491.1406
B65: % YoY | F65: =+F64/E64-1 -> 0.10666515 | G65: =+G64/F64-1 -> -0.034186467 | H65: =+H64/G64-1 -> 0.039085668 | I65: =+I64/H64-1 -> 0.16189481 | J65: =+J64/I64-1 -> 0.1 | K65: =+K64/J64-1 -> 0.127 | L65: =+L64/K64-1 -> 0.12707187 | M65: =+M64/L64-1 -> 0.1271422 | ... S65: =+S64/R64-1 -> 0.066589852
B67: Peanuts franchise | E67: =+E68*E64 -> 110.4222 | F67: =+F68*F64 -> 122.2004 | G67: =+G68*G64 -> 126.453 | H67: =+H68*H64 -> 157.6746 | I67: =+I68*I64 -> 183.2013 | J67: =+(1+J69)*I67 -> 201.52143 | K67: =+(1+K69)*J67 -> 227.71922 | L67: =+(1+L69)*K67 -> 257.32271 | M67: =+(1+M69)*L67 -> 290.77467 | N67: =+(1+N69)*M67 -> 319.85213 | O67: =+(1+O69)*N67 -> 343.84104 | P67: =+(1+P69)*O67 -> 367.90992 | Q67: =+(1+Q69)*P67 -> 393.66361 | ... S67: =+(1+S69)*R67 -> 450.70547
B68: % of total | E68: 0.7 | F68: 0.7 | G68: 0.75 | H68: 0.9 | I68: 0.9 | J68: =+J67/J64 -> 0.9 | K68: =+K67/K64 -> 0.90239574 | L68: =+L67/L64 -> 0.90474016 | M68: =+M67/M64 -> 0.90703407 | N68: =+N67/N64 -> 0.90703407 | O68: =+O67/O64 -> 0.90703407 | P68: =+P67/P64 -> 0.90861295 | Q68: =+Q67/Q64 -> 0.91172772 | ... S68: =+S67/S64 -> 0.91767096
B69: % YoY | F69: =+F67/E67-1 -> 0.10666515 | G69: =+G67/F67-1 -> 0.034800213 | H69: =+H67/G67-1 -> 0.2469028 | I69: =+I67/H67-1 -> 0.16189481 | J69: =+CHOOSE(Case, J70,J71,J72) -> 0.1 | K69: =+CHOOSE(Case, K70,K71,K72) -> 0.13 | L69: =+CHOOSE(Case, L70,L71,L72) -> 0.13 | M69: =+CHOOSE(Case, M70,M71,M72) -> 0.13 | N69: =+CHOOSE(Case, N70,N71,N72) -> 0.1 | O69: =+CHOOSE(Case, O70,O71,O72) -> 0.075 | P69: =+CHOOSE(Case, P70,P71,P72) -> 0.07 | Q69: =+CHOOSE(Case, Q70,Q71,Q72) -> 0.07 | ... S69: =+CHOOSE(Case, S70,S71,S72) -> 0.07
B70: Base | J70: 0.1 | K70: 0.13 | L70: 0.13 | M70: 0.13 | N70: 0.1 | O70: 0.075 | P70: 0.07 | Q70: 0.07 | R70: 0.07 | S70: 0.07
B71: Upside | J71: 0.1 | K71: 0.13 | L71: 0.13 | M71: 0.13 | N71: 0.1 | O71: 0.075 | P71: 0.07 | Q71: 0.07 | R71: 0.07 | S71: 0.07
B72: Downside | J72: 0.05 | K72: 0.1 | L72: 0.075 | M72: 0.05 | N72: 0.05 | O72: 0.05 | P72: 0.05 | Q72: 0.05 | R72: 0.05 | S72: 0.05
B74: Other franchise | E74: =+E64-E67 -> 47.3238 | F74: =+F64-F67 -> 52.3716 | G74: =+G64-G67 -> 42.151 | H74: =+H64-H67 -> 17.5194 | I74: =+I64-I67 -> 20.3557 | J74: =+(1+J76)*I74 -> 22.39127 | K74: =+(1+K76)*J74 -> 24.630397 | L74: =+(1+L76)*K74 -> 27.093437 | M74: =+(1+M76)*L74 -> 29.80278 | N74: =+(1+N76)*M74 -> 32.783058 | O74: =+(1+O76)*N74 -> 35.241788 | P74: =+(1+P76)*O74 -> 37.003877 | Q74: =+(1+Q76)*P74 -> 38.113993 | ... S74: =+(1+S76)*R74 -> 40.435136
B75: % of total | E75: =+E74/E64 -> 0.3 | F75: =+F74/F64 -> 0.3 | G75: =+G74/G64 -> 0.25 | H75: =+H74/H64 -> 0.1 | I75: =+I74/I64 -> 0.1 | J75: =+J74/J64 -> 0.1 | K75: =+K74/K64 -> 0.097604259 | L75: =+L74/L64 -> 0.095259839 | ... S75: =+S74/S64 -> 0.082329043
B76: % YoY | F76: =+F74/E74-1 -> 0.10666515 | G76: =+G74/F74-1 -> -0.19515539 | H76: =+H74/G74-1 -> -0.58436573 | I76: =+I74/H74-1 -> 0.16189481 | J76: =+CHOOSE(Case, J77,J78,J79) -> 0.1 | K76: =+CHOOSE(Case, K77,K78,K79) -> 0.1 | L76: =+CHOOSE(Case, L77,L78,L79) -> 0.1 | M76: =+CHOOSE(Case, M77,M78,M79) -> 0.1 | N76: =+CHOOSE(Case, N77,N78,N79) -> 0.1 | O76: =+CHOOSE(Case, O77,O78,O79) -> 0.075 | P76: =+CHOOSE(Case, P77,P78,P79) -> 0.05 | Q76: =+CHOOSE(Case, Q77,Q78,Q79) -> 0.03 | ... S76: =+CHOOSE(Case, S77,S78,S79) -> 0.03
B77: Base | J77: 0.1 | K77: 0.1 | L77: 0.1 | M77: 0.1 | N77: 0.1 | O77: 0.075 | P77: 0.05 | Q77: 0.03 | R77: 0.03 | S77: 0.03
B78: Upside | J78: =+J77+5% -> 0.15 | K78: =+K77+5% -> 0.15 | L78: =+L77+5% -> 0.15 | M78: =+M77+5% -> 0.15 | N78: =+N77+5% -> 0.15 | O78: =+O77+5% -> 0.125 | P78: =+P77+5% -> 0.1 | Q78: =+Q77+5% -> 0.08 | ... S78: =+S77+5% -> 0.08
B79: Downside | J79: 0 | K79: 0.1 | L79: 0.1 | M79: 0.1 | N79: 0.1 | O79: 0.075 | P79: 0.05 | Q79: 0.03 | R79: 0.03 | S79: 0.03
A81: x | B81: Canadian Television Broadcasting
B82: Revenue | E82: =+E12 -> 55.014 | F82: =+F12 -> 52.469 | G82: =+G12 -> 49.527 | H82: =+H12 -> 46.502 | I82: =+I12 -> 41.684 | J82: =+(1+J83)*I82 -> 40.01664 | K82: =+(1+K83)*J82 -> 38.415974 | L82: =+(1+L83)*K82 -> 36.879335 | M82: =+(1+M83)*L82 -> 35.404162 | N82: =+(1+N83)*M82 -> 33.987996 | O82: =+(1+O83)*N82 -> 32.628476 | P82: =+(1+P83)*O82 -> 31.323337 | Q82: =+(1+Q83)*P82 -> 30.070403 | ... S82: =+(1+S83)*R82 -> 28.867587
B83: % YoY | F83: =+F82/E82-1 -> -0.046260952 | G83: =+G82/F82-1 -> -0.056071204 | H83: =+H82/G82-1 -> -0.061077796 | I83: =+I82/H82-1 -> -0.10360845 | J83: =+CHOOSE(Case, J84,J85,J86) -> -0.04 | K83: =+CHOOSE(Case, K84,K85,K86) -> -0.04 | L83: =+CHOOSE(Case, L84,L85,L86) -> -0.04 | M83: =+CHOOSE(Case, M84,M85,M86) -> -0.04 | N83: =+CHOOSE(Case, N84,N85,N86) -> -0.04 | O83: =+CHOOSE(Case, O84,O85,O86) -> -0.04 | P83: =+CHOOSE(Case, P84,P85,P86) -> -0.04 | Q83: =+CHOOSE(Case, Q84,Q85,Q86) -> -0.04 | ... S83: =+CHOOSE(Case, S84,S85,S86) -> 0
B84: Base | J84: -0.04 | K84: -0.04 | L84: -0.04 | M84: -0.04 | N84: -0.04 | O84: -0.04 | P84: -0.04 | Q84: -0.04 | R84: -0.04 | S84: 0
B85: Upside | J85: -0.03 | K85: -0.03 | L85: -0.03 | M85: -0.03 | N85: -0.03 | O85: -0.03 | P85: -0.03 | Q85: -0.03 | R85: -0.03 | S85: 0
B86: Downside | J86: -0.05 | K86: -0.05 | L86: -0.05 | M86: -0.05 | N86: -0.05 | O86: -0.05 | P86: -0.05 | Q86: -0.05 | R86: -0.05 | S86: 0
A88: x | B88: Gross profit analysis
B89: Direct production and new media cost | H89: 191.879 | I89: 226.375 | J89: =+J93-J90 -> 144.12715 | K89: =+K93-K90 -> 173.05247 | L89: =+L93-L90 -> 201.40687 | M89: =+M93-M90 -> 216.59919 | N89: =+N93-N90 -> 229.23156 | O89: =+O93-O90 -> 240.33734 | P89: =+P93-P90 -> 251.3586 | Q89: =+Q93-Q90 -> 262.75997 | ... S89: =+S93-S90 -> 287.88702
B90: Expense of film, TV and broadcasting rights | H90: =+H91+H92 -> 65.768 | I90: =+I91+I92 -> 59.287 | J90: =+'FS Calcs'!J33*-1 -> 76.472127 | K90: =+'FS Calcs'!K33*-1 -> 75.376926 | L90: =+'FS Calcs'!L33*-1 -> 75.328091 | M90: =+'FS Calcs'!M33*-1 -> 81.709949 | N90: =+'FS Calcs'!N33*-1 -> 87.047603 | O90: =+'FS Calcs'!O33*-1 -> 91.759037 | P90: =+'FS Calcs'!P33*-1 -> 96.427377 | Q90: =+'FS Calcs'!Q33*-1 -> 101.24074 | ... S90: =+'FS Calcs'!S33*-1 -> 111.59255
B91: Expense of film and TV | H91: 55.387 | I91: 50.457
B92: Expense of film and broadcast risghts for broadcasting | H92: 10.381 | I92: 8.83
B93: Total COGS | H93: =+H90+H89 -> 257.647 | I93: =+I90+I89 -> 285.662 | J93: =+'RevBuild Calcs'!J26 -> 220.59927 | K93: =+'RevBuild Calcs'!K26 -> 248.4294 | L93: =+'RevBuild Calcs'!L26 -> 276.73496 | M93: =+'RevBuild Calcs'!M26 -> 298.30914 | N93: =+'RevBuild Calcs'!N26 -> 316.27916 | O93: =+'RevBuild Calcs'!O26 -> 332.09637 | P93: =+'RevBuild Calcs'!P26 -> 347.78597 | Q93: =+'RevBuild Calcs'!Q26 -> 364.00071 | ... S93: =+'RevBuild Calcs'!S26 -> 399.47956
H94: =+H93='P&L'!H11*-1 -> TRUE | I94: =+I93='P&L'!I11*-1 -> TRUE
B96: Direct production and new media cost as % of content revenue ex Spark | H96: =+H89/(H7+H9) -> 0.53258595 | I96: =+I89/(I7+I9) -> 0.55196048 | J96: =+J89/(J7+J9) -> 0.32695734 | K96: =+K89/(K7+K9) -> 0.3524919 | L96: =+L89/(L7+L9) -> 0.36829299 | M96: =+M89/(M7+M9) -> 0.36333023 | N96: =+N89/(N7+N9) -> 0.36015823 | O96: =+O89/(O7+O9) -> 0.35794452 | ... S96: =+S89/(S7+S9) -> 0.35100115

Sheet FS Calcs
A1: in CADm unless otherwise stated
A2: FYE June
E4: 2018 | F4: =+E4+1 -> 2019 | G4: =+F4+1 -> 2020 | H4: =+G4+1 -> 2021 | I4: =+H4+1 -> 2022 | J4: =+I4+1 -> 2023 | K4: =+J4+1 -> 2024 | L4: =+K4+1 -> 2025 | M4: =+L4+1 -> 2026 | ... S4: =+R4+1 -> 2032
B6: Content production and distribution | E6: =+'RevBuild Calcs'!E7 -> 164.374 | F6: =+'RevBuild Calcs'!F7 -> 143.763 | G6: =+'RevBuild Calcs'!G7 -> 145.225 | H6: =+'RevBuild Calcs'!H7 -> 185.084 | I6: =+'RevBuild Calcs'!I7 -> 206.572 | J6: =+'RevBuild Calcs'!J7 -> 216.9006 | K6: =+'RevBuild Calcs'!K7 -> 238.59066 | L6: =+'RevBuild Calcs'!L7 -> 262.44973 | ... S6: =+'RevBuild Calcs'!S7 -> 329.04763
B7: WildBrain Spark | E7: =+'RevBuild Calcs'!E8 -> 57.282 | F7: =+'RevBuild Calcs'!F8 -> 68.996 | G7: =+'RevBuild Calcs'!G8 -> 62.278 | H7: =+'RevBuild Calcs'!H8 -> 45.754 | I7: =+'RevBuild Calcs'!I8 -> 55.41 | J7: =+'RevBuild Calcs'!J8 -> 45.65784 | K7: =+'RevBuild Calcs'!K8 -> 54.081711 | L7: =+'RevBuild Calcs'!L8 -> 69.630204 | ... S7: =+'RevBuild Calcs'!S8 -> 108.38647
B8: Consumer Products | E8: =+'RevBuild Calcs'!E9 -> 157.746 | F8: =+'RevBuild Calcs'!F9 -> 174.572 | G8: =+'RevBuild Calcs'!G9 -> 168.604 | H8: =+'RevBuild Calcs'!H9 -> 175.194 | I8: =+'RevBuild Calcs'!I9 -> 203.557 | J8: =+'RevBuild Calcs'!J9 -> 223.9127 | K8: =+'RevBuild Calcs'!K9 -> 252.34961 | L8: =+'RevBuild Calcs'!L9 -> 284.41615 | ... S8: =+'RevBuild Calcs'!S9 -> 491.1406
B9: Canadian Television Broadcasting | E9: =+'RevBuild Calcs'!E12 -> 55.014 | F9: =+'RevBuild Calcs'!F12 -> 52.469 | G9: =+'RevBuild Calcs'!G12 -> 49.527 | H9: =+'RevBuild Calcs'!H12 -> 46.502 | I9: =+'RevBuild Calcs'!I12 -> 41.684 | J9: =+'RevBuild Calcs'!J12 -> 40.01664 | K9: =+'RevBuild Calcs'!K12 -> 38.415974 | L9: =+'RevBuild Calcs'!L12 -> 36.879335 | ... S9: =+'RevBuild Calcs'!S12 -> 28.867587
B10: Revenue | E10: =SUM(E6:E9) -> 434.416 | F10: =SUM(F6:F9) -> 439.8 | G10: =SUM(G6:G9) -> 425.634 | H10: =SUM(H6:H9) -> 452.534 | I10: =SUM(I6:I9) -> 507.223 | J10: =SUM(J6:J9) -> 526.48778 | K10: =SUM(K6:K9) -> 583.43796 | L10: =SUM(L6:L9) -> 653.37542 | ... S10: =SUM(S6:S9) -> 957.4423
B11: COGS | E11: =+'P&L'!E11 -> -244.244 | F11: =+'P&L'!F11 -> -253.003 | G11: =+'P&L'!G11 -> -237.789 | H11: =+'P&L'!H11 -> -257.647 | I11: =+'P&L'!I11 -> -285.662 | J11: =+'P&L'!J11 -> -305.88851 | K11: =+'P&L'!K11 -> -335.00856 | L11: =+'P&L'!L11 -> -376.64045 | ... S11: =+'P&L'!S11 -> -557.96273
B12: EBT | E12: =+'P&L'!E27 -> -5.257 | F12: =+'P&L'!F27 -> -81.908 | G12: =+'P&L'!G27 -> -207.085 | H12: =+'P&L'!H27 -> 19.811 | I12: =+'P&L'!I27 -> 30.205 | J12: =+'P&L'!J27 -> 23.117979 | K12: =+'P&L'!K27 -> 35.441009 | L12: =+'P&L'!L27 -> 55.409029 | ... S12: =+'P&L'!S27 -> 83.647462
A14: x | B14: WC items
B15: Account receivables | E15: =+'BS & CFS'!E8 -> 251.538 | F15: =+'BS & CFS'!F8 -> 265.71 | G15: =+'BS & CFS'!G8 -> 200.217 | H15: =+'BS & CFS'!H8 -> 195.24 | I15: =+'BS & CFS'!I8 -> 249.66 | J15: =+J16/365*J10 -> 259.14231 | K15: =+K16/365*K10 -> 287.17373 | L15: =+L16/365*L10 -> 321.59761 | M15: =+M16/365*M10 -> 347.92269 | N15: =+N16/365*N10 -> 369.90392 | O15: =+O16/365*O10 -> 389.28437 | P15: =+P16/365*P10 -> 408.49595 | Q15: =+Q16/365*Q10 -> 428.32292 | ... S15: =+S16/365*S10 -> 471.26223
B16: AR days | E16: =+E15/E10*365 -> 211.34436 | F16: =+F15/F10*365 -> 220.51876 | G16: =+G15/G10*365 -> 171.69494 | H16: =+H15/H10*365 -> 157.47458 | I16: =+I15/I10*365 -> 179.65648 | J16: =+I16 -> 179.65648 | K16: =+J16 -> 179.65648 | L16: =+K16 -> 179.65648 | M16: =+L16 -> 179.65648 | N16: =+M16 -> 179.65648 | O16: =+N16 -> 179.65648 | P16: =+O16 -> 179.65648 | Q16: =+P16 -> 179.65648 | ... S16: =+R16 -> 179.65648
B18: Prepaid expense and deposits | E18: =+'BS & CFS'!E9 -> 8.58 | F18: =+'BS & CFS'!F9 -> 7.182 | G18: =+'BS & CFS'!G9 -> 8.779 | H18: =+'BS & CFS'!H9 -> 6.184 | I18: =+'BS & CFS'!I9 -> 8.583 | J18: =+I18 -> 8.583 | K18: =+J18 -> 8.583 | L18: =+K18 -> 8.583 | M18: =+L18 -> 8.583 | N18: =+M18 -> 8.583 | O18: =+N18 -> 8.583 | P18: =+O18 -> 8.583 | Q18: =+P18 -> 8.583 | ... S18: =+R18 -> 8.583
B20: Accounts payables and accrued liabilities | E20: =+'BS & CFS'!E22 -> 130.545 | F20: =+'BS & CFS'!F22 -> 103.487 | G20: =+'BS & CFS'!G22 -> 98.927 | H20: =+'BS & CFS'!H22 -> 130.299 | I20: =+'BS & CFS'!I22 -> 180.956 | J20: =+J21/365*J11*-1 -> 193.76872 | K20: =+K21/365*K11*-1 -> 212.21517 | L20: =+L21/365*L11*-1 -> 238.58739 | M20: =+M21/365*M11*-1 -> 258.80071 | N20: =+N21/365*N11*-1 -> 275.70671 | O20: =+O21/365*O11*-1 -> 290.62928 | P20: =+P21/365*P11*-1 -> 305.41536 | Q20: =+Q21/365*Q11*-1 -> 320.66078 | ... S20: =+S21/365*S11*-1 -> 353.44815
B21: AP days | E21: =+E20/E11*365*-1 -> 195.08739 | F21: =+F20/F11*365*-1 -> 149.29766 | G21: =+G20/G11*365*-1 -> 151.8504 | H21: =+H20/H11*365*-1 -> 184.59029 | I21: =+I20/I11*365*-1 -> 231.2136 | J21: =+I21 -> 231.2136 | K21: =+J21 -> 231.2136 | L21: =+K21 -> 231.2136 | M21: =+L21 -> 231.2136 | N21: =+M21 -> 231.2136 | O21: =+N21 -> 231.2136 | P21: =+O21 -> 231.2136 | Q21: =+P21 -> 231.2136 | ... S21: =+R21 -> 231.2136
B23: Deferred revenue | E23: =+'BS & CFS'!E23 -> 47.552 | F23: =+'BS & CFS'!F23 -> 64.299 | G23: =+'BS & CFS'!G23 -> 48.371 | H23: =+'BS & CFS'!H23 -> 42.004 | I23: =+'BS & CFS'!I23 -> 58.116 | J23: =+J24*J10 -> 52.648778 | K23: =+K24*K10 -> 58.343796 | L23: =+L24*L10 -> 65.337542 | M23: =+M24*M10 -> 70.685889 | N23: =+N24*N10 -> 75.151717 | O23: =+O24*O10 -> 79.089156 | P23: =+P24*P10 -> 82.992286 | Q23: =+Q24*Q10 -> 87.020443 | ... S23: =+S24*S10 -> 95.74423
B24: % of total revenue | E24: =+E23/E10 -> 0.1094619 | F24: =+F23/F10 -> 0.14620055 | G24: =+G23/G10 -> 0.11364459 | H24: =+H23/H10 -> 0.092819545 | I24: =+I23/I10 -> 0.11457682 | J24: 0.1 | K24: 0.1 | L24: 0.1 | M24: 0.1 | N24: 0.1 | O24: 0.1 | P24: 0.1 | Q24: 0.1 | R24: 0.1 | S24: 0.1
B26: LT acccount receivables | E26: =+'BS & CFS'!E13 -> 18.789 | F26: =+'BS & CFS'!F13 -> 14.318 | G26: =+'BS & CFS'!G13 -> 21.035 | H26: =+'BS & CFS'!H13 -> 51.997 | I26: =+'BS & CFS'!I13 -> 84.79 | J26: =+J27/365*J10 -> 88.0104 | K26: =+K27/365*K10 -> 97.530484 | L26: =+L27/365*L10 -> 109.22159 | M26: =+M27/365*M10 -> 118.16216 | N26: =+N27/365*N10 -> 125.62747 | O26: =+O27/365*O10 -> 132.20949 | P26: =+P27/365*P10 -> 138.73416 | Q26: =+Q27/365*Q10 -> 145.46784 | ... S26: =+S27/365*S10 -> 160.05097
B27: AR days | E27: =+E26/E10*365 -> 15.786677 | F27: =+F26/F10*365 -> 11.882833 | G27: =+G26/G10*365 -> 18.038444 | H27: =+H26/H10*365 -> 41.93918 | I27: =+I26/I10*365 -> 61.015273 | J27: =+I27 -> 61.015273 | K27: =+J27 -> 61.015273 | L27: =+K27 -> 61.015273 | M27: =+L27 -> 61.015273 | N27: =+M27 -> 61.015273 | O27: =+N27 -> 61.015273 | P27: =+O27 -> 61.015273 | Q27: =+P27 -> 61.015273 | ... S27: =+R27 -> 61.015273
A29: x | B29: ST assets
B30: BoP investment in film and TV | F30: =+E35 -> 186.008 | G30: =+F35 -> 148.561 | H30: =+G35 -> 140.548 | I30: =+H35 -> 147.783 | J30: =+I35 -> 163.563 | K30: =+J35 -> 184.69614 | L30: =+K35 -> 200.72025 | M30: =+L35 -> 230.37205 | ... S30: =+R35 -> 378.96553
B31: Development cost | H31: =1.908+73.165+4.434 -> 79.507 | I31: =0.203+71.115+12.166 -> 83.484 | J31: =+J37*J6 -> 97.60527 | K31: =+K37*K6 -> 101.40103 | L31: =+L37*L6 -> 104.97989 | M31: =+M37*M6 -> 110.22888 | N31: =+N37*N6 -> 113.53575 | O31: =+O37*O6 -> 116.94182 | P31: =+P37*P6 -> 120.45008 | Q31: =+Q37*Q6 -> 124.06358 | ... S31: =+S37*S6 -> 131.61905
B32: Write down | H32: -7.453 | I32: -1.208 | J32: 0 | K32: -10 | L32: 0 | M32: =+L32 -> 0 | N32: =+M32 -> 0 | O32: =+N32 -> 0 | P32: =+O32 -> 0 | Q32: =+P32 -> 0 | R32: =+Q32 -> 0 | S32: =+R32 -> 0
B33: Expense | H33: =+'RevBuild Calcs'!H90*-1 -> -65.768 | I33: =+'RevBuild Calcs'!I90*-1 -> -59.287 | J33: =+J38*J11 -> -76.472127 | K33: =+K38*K11 -> -75.376926 | L33: =+L38*L11 -> -75.328091 | M33: =+M38*M11 -> -81.709949 | N33: =+N38*N11 -> -87.047603 | O33: =+O38*O11 -> -91.759037 | P33: =+P38*P11 -> -96.427377 | Q33: =+Q38*Q11 -> -101.24074 | ... S33: =+S38*S11 -> -111.59255
B34: FX & Other | H34: =+H35-SUM(H30:H33) -> 0.949 | I34: =+I35-SUM(I30:I33) -> -7.209 | J34: 0 | K34: =+J34 -> 0 | L34: =+K34 -> 0 | M34: =+L34 -> 0 | N34: =+M34 -> 0 | O34: =+N34 -> 0 | P34: =+O34 -> 0 | Q34: =+P34 -> 0 | R34: =+Q34 -> 0 | S34: =+R34 -> 0
B35: EoP investment in film and TV | E35: =+'BS & CFS'!E10 -> 186.008 | F35: =+'BS & CFS'!F10 -> 148.561 | G35: =+'BS & CFS'!G10 -> 140.548 | H35: =+'BS & CFS'!H10 -> 147.783 | I35: =+'BS & CFS'!I10 -> 163.563 | J35: =+SUM(J30:J34) -> 184.69614 | K35: =+SUM(K30:K34) -> 200.72025 | L35: =+SUM(L30:L34) -> 230.37205 | M35: =+SUM(M30:M34) -> 258.89098 | N35: =+SUM(N30:N34) -> 285.37913 | O35: =+SUM(O30:O34) -> 310.56192 | P35: =+SUM(P30:P34) -> 334.58462 | Q35: =+SUM(Q30:Q34) -> 357.40746 | ... S35: =+SUM(S30:S34) -> 398.99204
B37: Development cost as a % of content revenue | H37: =+H31/H6 -> 0.42957252 | I37: =+I31/I6 -> 0.40413996 | J37: 0.45 | K37: 0.425 | L37: 0.4 | M37: 0.4 | N37: 0.4 | O37: 0.4 | P37: 0.4 | Q37: 0.4 | R37: 0.4 | S37: 0.4
B38: Expense as a % of COGS | H38: =+H33/H11 -> 0.25526399 | I38: =+I33/I11 -> 0.20754248 | J38: 0.25 | K38: 0.225 | L38: 0.2 | M38: 0.2 | N38: 0.2 | O38: 0.2 | P38: 0.2 | Q38: 0.2 | R38: 0.2 | S38: 0.2
A40: x | B40: LT assets | J40: =+J39*J6 -> 0 | K40: =+K39*K6 -> 0 | L40: =+L39*L6 -> 0 | M40: =+M39*M6 -> 0 | N40: =+N39*N6 -> 0 | O40: =+O39*O6 -> 0 | P40: =+P39*P6 -> 0 | Q40: =+Q39*Q6 -> 0 | ... S40: =+S39*S6 -> 0
B41: BoP acquired and library content | F41: =+E46 -> 147.088 | G41: =+F46 -> 118.247 | H41: =+G46 -> 109.076 | I41: =+H46 -> 100.653 | J41: =+I46 -> 92.732 | K41: =+J46 -> 93.261756 | L41: =+K46 -> 94.930515 | M41: =+L46 -> 97.998023 | ... S41: =+R46 -> 135.22542
B42: Additions | H42: 8.918 | I42: 1 | J42: =+J48*J10 -> 10.529756 | K42: =+K48*K10 -> 11.668759 | L42: =+L48*L10 -> 13.067508 | M42: =+M48*M10 -> 14.137178 | N42: =+N48*N10 -> 15.030343 | O42: =+O48*O10 -> 15.817831 | P42: =+P48*P10 -> 16.598457 | Q42: =+Q48*Q10 -> 17.404089 | ... S42: =+S48*S10 -> 19.148846
B43: Write down | H43: -0.379 | I43: 0 | J43: 0 | K43: =+J43 -> 0 | L43: =+K43 -> 0 | M43: =+L43 -> 0 | N43: =+M43 -> 0 | O43: =+N43 -> 0 | P43: =+O43 -> 0 | Q43: =+P43 -> 0 | R43: =+Q43 -> 0 | S43: =+R43 -> 0
B44: Amortization | H44: -11.1 | I44: -10.241 | J44: =+J49 -> -10 | K44: =+K49 -> -10 | L44: =+L49 -> -10 | M44: =+M49 -> -10 | N44: =+N49 -> -10 | O44: =+O49 -> -10 | P44: =+P49 -> -10 | Q44: =+Q49 -> -10 | ... S44: =+S49 -> -10
B45: FX & Other | H45: =+H46-SUM(H41:H44) -> -5.862 | I45: =+I46-SUM(I41:I44) -> 1.32 | J45: 0 | K45: =+J45 -> 0 | L45: =+K45 -> 0 | M45: =+L45 -> 0 | N45: =+M45 -> 0 | O45: =+N45 -> 0 | P45: =+O45 -> 0 | Q45: =+P45 -> 0 | R45: =+Q45 -> 0 | S45: =+R45 -> 0
B46: EoP acquired and library content | E46: =+'BS & CFS'!E14 -> 147.088 | F46: =+'BS & CFS'!F14 -> 118.247 | G46: =+'BS & CFS'!G14 -> 109.076 | H46: =+'BS & CFS'!H14 -> 100.653 | I46: =+'BS & CFS'!I14 -> 92.732 | J46: =+SUM(J41:J45) -> 93.261756 | K46: =+SUM(K41:K45) -> 94.930515 | L46: =+SUM(L41:L45) -> 97.998023 | M46: =+SUM(M41:M45) -> 102.1352 | N46: =+SUM(N41:N45) -> 107.16554 | O46: =+SUM(O41:O45) -> 112.98338 | P46: =+SUM(P41:P45) -> 119.58183 | Q46: =+SUM(Q41:Q45) -> 126.98592 | ... S46: =+SUM(S41:S45) -> 144.37427
B48: Additions as a % of revenue | H48: =+H42/H10 -> 0.019706807 | I48: =+I42/I10 -> 0.0019715194 | J48: 0.02 | K48: 0.02 | L48: 0.02 | M48: 0.02 | N48: 0.02 | O48: 0.02 | P48: 0.02 | Q48: 0.02 | R48: 0.02 | S48: 0.02
B49: Amortization | H49: =+H44 -> -11.1 | I49: =+I44 -> -10.241 | J49: -10 | K49: -10 | L49: -10 | M49: -10 | N49: -10 | O49: -10 | P49: -10 | Q49: -10 | R49: -10 | S49: -10
B51: BoP PPE | F51: =+E56 -> 30.436 | G51: =+F56 -> 19.352 | H51: =+G56 -> 54.245 | I51: =+H56 -> 47.229 | J51: =+I56 -> 39.287 | K51: =+J56 -> 31.389683 | L51: =+K56 -> 27.013899 | M51: =+L56 -> 24.563741 | ... S51: =+R56 -> 24.563741
B52: Additions | H52: 5.733 | I52: 5.308 | J52: =+J59*J10 -> 7.8973167 | K52: =+K59*K10 -> 8.7515694 | L52: =+L59*L10 -> 9.8006312 | M52: =+M59*M10 -> 10.602883 | N52: =+N59*N10 -> 11.272758 | O52: =+O59*O10 -> 11.863373 | P52: =+P59*P10 -> 12.448843 | Q52: =+Q59*Q10 -> 13.053066 | ... S52: =+S59*S10 -> 14.361634
B53: Depreciation | H53: -12.382 | I53: -13.378 | J53: =+J52*J60*-1 -> -15.794633 | K53: =+K52*K60*-1 -> -13.127354 | L53: =+L52*L60*-1 -> -12.250789 | M53: =+M52*M60*-1 -> -10.602883 | N53: =+N52*N60*-1 -> -11.272758 | O53: =+O52*O60*-1 -> -11.863373 | P53: =+P52*P60*-1 -> -12.448843 | Q53: =+Q52*Q60*-1 -> -13.053066 | ... S53: =+S52*S60*-1 -> -14.361634
B54: Impairement | H54: 0 | I54: 0.42 | J54: 0 | K54: 0 | L54: 0 | M54: 0 | N54: 0 | O54: 0 | P54: 0 | Q54: 0 | R54: 0 | S54: 0
B55: FX & other | H55: -0.367 | I55: -0.292 | J55: 0 | K55: =+J55 -> 0 | L55: =+K55 -> 0 | M55: =+L55 -> 0 | N55: =+M55 -> 0 | O55: =+N55 -> 0 | P55: =+O55 -> 0 | Q55: =+P55 -> 0 | R55: =+Q55 -> 0 | S55: =+R55 -> 0
B56: EoP PPE | E56: =+'BS & CFS'!E15 -> 30.436 | F56: =+'BS & CFS'!F15 -> 19.352 | G56: =+'BS & CFS'!G15 -> 54.245 | H56: =+'BS & CFS'!H15 -> 47.229 | I56: =+'BS & CFS'!I15 -> 39.287 | J56: =+SUM(J51:J55) -> 31.389683 | K56: =+SUM(K51:K55) -> 27.013899 | L56: =+SUM(L51:L55) -> 24.563741 | M56: =+SUM(M51:M55) -> 24.563741 | N56: =+SUM(N51:N55) -> 24.563741 | O56: =+SUM(O51:O55) -> 24.563741 | P56: =+SUM(P51:P55) -> 24.563741 | Q56: =+SUM(Q51:Q55) -> 24.563741 | ... S56: =+SUM(S51:S55) -> 24.563741
H57: =+H56=SUM(H51:H55) -> TRUE | I57: =+I56=SUM(I51:I55) -> TRUE
B59: Additions as a % of revenue | H59: =+H52/'P&L'!H6 -> 0.012668661 | I59: =+I52/'P&L'!I6 -> 0.010464825 | J59: 0.015 | K59: 0.015 | L59: 0.015 | M59: 0.015 | N59: 0.015 | O59: 0.015 | P59: 0.015 | Q59: 0.015 | R59: 0.015 | S59: 0.015
B60: Depreciation as a % of additions | H60: =+H53/H52*-1 -> 2.1597767 | I60: =+I53/I52*-1 -> 2.5203466 | J60: 2 | K60: 1.5 | L60: 1.25 | M60: 1 | N60: 1 | O60: 1 | P60: 1 | Q60: 1 | R60: 1 | S60: 1
B62: BoP intangibles | F62: =+E67 -> 546.997 | G62: =+F67 -> 465.832 | H62: =+G67 -> 472.531 | I62: =+H67 -> 433.595 | J62: =+I67 -> 448.947 | K62: =+J67 -> 443.68212 | L62: =+K67 -> 438.68123 | M62: =+L67 -> 434.01426 | ... S62: =+R67 -> 423.30898
B63: Addition | H63: 4.279 | I63: 14.309 | J63: =+J70*J10 -> 10.529756 | K63: =+K70*K10 -> 11.668759 | L63: =+L70*L10 -> 13.067508 | M63: =+M70*M10 -> 14.137178 | N63: =+N70*N10 -> 15.030343 | O63: =+O70*O10 -> 15.817831 | P63: =+P70*P10 -> 16.598457 | Q63: =+Q70*Q10 -> 17.404089 | ... S63: =+S70*S10 -> 19.148846
B64: Amortization | H64: -10.542 | I64: -10.601 | J64: =+J63*J71*-1 -> -15.794633 | K64: =+K63*K71*-1 -> -16.669656 | L64: =+L63*L71*-1 -> -17.734476 | M64: =+M63*M71*-1 -> -18.176371 | N64: =+N63*N71*-1 -> -18.251131 | O64: =+O63*O71*-1 -> -18.077521 | P64: =+P63*P71*-1 -> -17.784061 | Q64: =+Q63*Q71*-1 -> -17.404089 | ... S64: =+S63*S71*-1 -> -19.148846
B65: Impairement | H65: 0 | I65: 0 | J65: 0 | K65: 0 | L65: 0 | M65: 0 | N65: 0 | O65: 0 | P65: 0 | Q65: 0 | R65: 0 | S65: 0
B66: FX | H66: -32.673 | I66: 11.644 | J66: 0 | K66: =+J66 -> 0 | L66: =+K66 -> 0 | M66: =+L66 -> 0 | N66: =+M66 -> 0 | O66: =+N66 -> 0 | P66: =+O66 -> 0 | Q66: =+P66 -> 0 | R66: =+Q66 -> 0 | S66: =+R66 -> 0
B67: EoP intangibles | E67: =+'BS & CFS'!E17 -> 546.997 | F67: =+'BS & CFS'!F17 -> 465.832 | G67: =+'BS & CFS'!G17 -> 472.531 | H67: =+'BS & CFS'!H17 -> 433.595 | I67: =+'BS & CFS'!I17 -> 448.947 | J67: =+SUM(J62:J66) -> 443.68212 | K67: =+SUM(K62:K66) -> 438.68123 | L67: =+SUM(L62:L66) -> 434.01426 | M67: =+SUM(M62:M66) -> 429.97506 | N67: =+SUM(N62:N66) -> 426.75428 | O67: =+SUM(O62:O66) -> 424.49459 | P67: =+SUM(P62:P66) -> 423.30898 | Q67: =+SUM(Q62:Q66) -> 423.30898 | ... S67: =+SUM(S62:S66) -> 423.30898
H68: =+H67=SUM(H62:H66) -> TRUE | I68: =+I67=SUM(I62:I66) -> TRUE
B70: Additions as a % of revenue | H70: =+H63/H10 -> 0.0094556431 | I70: =+I63/I10 -> 0.028210472 | J70: 0.02 | K70: 0.02 | L70: 0.02 | M70: 0.02 | N70: 0.02 | O70: 0.02 | P70: 0.02 | Q70: 0.02 | R70: 0.02 | S70: 0.02
B71: Depreciation as a % of additions | H71: =+H64/H63 -> -2.4636597 | I71: =+I64/I63 -> -0.74086239 | J71: 1.5 | K71: 1.4285714 | L71: 1.3571429 | M71: 1.2857143 | N71: 1.2142857 | O71: 1.1428571 | P71: 1.0714286 | Q71: 1 | R71: 1 | S71: 1
A73: x | B73: Equity
B74: BoP common equity | F74: =+E78 -> 315.078 | G74: =+F78 -> 243.033 | H74: =+G78 -> 81.351 | I74: =+H78 -> 68.588 | J74: =+I78 -> 79.428 | K74: =+J78 -> 68.942507 | L74: =+K78 -> 66.399389 | M74: =+L78 -> 77.202377 | ... S74: =+R78 -> 196.7656
B75: Net income | F75: =+'P&L'!F36 -> -101.494 | G75: =+'P&L'!G36 -> -235.966 | H75: =+'P&L'!H36 -> -7.077 | I75: =+'P&L'!I36 -> 5.64 | J75: =+'P&L'!J36 -> -10.485493 | K75: =+'P&L'!K36 -> -2.5431185 | L75: =+'P&L'!L36 -> 10.802988 | M75: =+'P&L'!M36 -> 15.737849 | ... S75: =+'P&L'!S36 -> 24.292268
B76: Dividends | F76: =+'P&L'!F44 -> 0 | G76: =+'P&L'!G44 -> 0 | H76: =+'P&L'!H44 -> 0 | I76: =+'P&L'!I44 -> 0 | J76: 0 | K76: 0 | L76: 0 | M76: 0 | N76: 0 | O76: 0 | P76: 0 | Q76: 0 | R76: 0 | S76: 0
B77: Others | F77: =+F78-SUM(F74:F76) -> 29.449 | G77: =+G78-SUM(G74:G76) -> 74.284 | H77: =+H78-SUM(H74:H76) -> -5.686 | I77: =+I78-SUM(I74:I76) -> 5.2 | J77: 0 | K77: =+J77 -> 0 | L77: =+K77 -> 0 | M77: =+L77 -> 0 | N77: =+M77 -> 0 | O77: =+N77 -> 0 | P77: =+O77 -> 0 | Q77: =+P77 -> 0 | R77: =+Q77 -> 0 | S77: =+R77 -> 0
B78: EoP common equity | E78: =+'BS & CFS'!E35 -> 315.078 | F78: =+'BS & CFS'!F35 -> 243.033 | G78: =+'BS & CFS'!G35 -> 81.351 | H78: =+'BS & CFS'!H35 -> 68.588 | I78: =+'BS & CFS'!I35 -> 79.428 | J78: =SUM(J74:J77) -> 68.942507 | K78: =SUM(K74:K77) -> 66.399389 | L78: =SUM(L74:L77) -> 77.202377 | M78: =SUM(M74:M77) -> 92.940227 | N78: =SUM(N74:N77) -> 110.86273 | O78: =SUM(O74:O77) -> 130.3256 | P78: =SUM(P74:P77) -> 151.23323 | Q78: =SUM(Q74:Q77) -> 173.65604 | ... S78: =SUM(S74:S77) -> 221.05787
B80: BoP NCI | F80: =+E84 -> 85.714 | G80: =+F84 -> 256.945 | H80: =+G84 -> 260.135 | I80: =+H84 -> 234.325 | J80: =+I84 -> 235.975 | K80: =+J84 -> 228.59308 | L80: =+K84 -> 221.33251 | M80: =+L84 -> 214.20379 | ... S80: =+R84 -> 174.84724
B81: Net income to NCI | F81: =+'P&L'!F35 -> 23.292 | G81: =+'P&L'!G35 -> 27.175 | H81: =+'P&L'!H35 -> 30.186 | I81: =+'P&L'!I35 -> 26.122 | J81: =+'P&L'!J35 -> 26.899258 | K81: =+'P&L'!K35 -> 27.706235 | L81: =+'P&L'!L35 -> 28.537422 | M81: =+'P&L'!M35 -> 29.393545 | ... S81: =+'P&L'!S35 -> 35.09743
B82: Distributions | F82: =+'P&L'!F45 -> -26.657 | G82: =+'P&L'!G45 -> -33.46 | H82: =+'P&L'!H45 -> -31.457 | I82: =+'P&L'!I45 -> -33.609 | J82: =+(1+J101)*I82 -> -34.28118 | K82: =+(1+K101)*J82 -> -34.966804 | L82: =+(1+L101)*K82 -> -35.66614 | M82: =+(1+M101)*L82 -> -36.379462 | N82: =+(1+N101)*M82 -> -37.107052 | O82: =+(1+O101)*N82 -> -37.849193 | P82: =+(1+P101)*O82 -> -38.606177 | Q82: =+(1+Q101)*P82 -> -39.3783 | ... S82: =+(1+S101)*R82 -> -40.969183
B83: Others | F83: =+F84-SUM(F80:F82) -> 174.596 | G83: =+G84-SUM(G80:G82) -> 9.475 | H83: =+H84-SUM(H80:H82) -> -24.539 | I83: =+I84-SUM(I80:I82) -> 9.137 | J83: 0 | K83: =+J83 -> 0 | L83: =+K83 -> 0 | M83: =+L83 -> 0 | N83: =+M83 -> 0 | O83: =+N83 -> 0 | P83: =+O83 -> 0 | Q83: =+P83 -> 0 | R83: =+Q83 -> 0 | S83: =+R83 -> 0
B84: EoP NCI | E84: =+'BS & CFS'!E36 -> 85.714 | F84: =+'BS & CFS'!F36 -> 256.945 | G84: =+'BS & CFS'!G36 -> 260.135 | H84: =+'BS & CFS'!H36 -> 234.325 | I84: =+'BS & CFS'!I36 -> 235.975 | J84: =SUM(J80:J83) -> 228.59308 | K84: =SUM(K80:K83) -> 221.33251 | L84: =SUM(L80:L83) -> 214.20379 | M84: =SUM(M80:M83) -> 207.21787 | N84: =SUM(N80:N83) -> 200.38617 | O84: =SUM(O80:O83) -> 193.72059 | P84: =SUM(P80:P83) -> 187.23354 | Q84: =SUM(Q80:Q83) -> 180.93793 | ... S84: =SUM(S80:S83) -> 168.97549
B86: Peanuts ownership | F86: =+SUM(F87:F89) -> 1 | G86: =+SUM(G87:G89) -> 1 | H86: =+SUM(H87:H89) -> 1 | I86: =+SUM(I87:I89) -> 1 | J86: =+SUM(J87:J89) -> 1 | K86: =+SUM(K87:K89) -> 1 | L86: =+SUM(L87:L89) -> 1 | M86: =+SUM(M87:M89) -> 1 | ... S86: =+SUM(S87:S89) -> 1
B87: WILD | F87: =0.51*0.8 -> 0.408 | G87: =0.51*0.8 -> 0.408 | H87: =0.51*0.8 -> 0.408 | I87: =0.51*0.8 -> 0.408 | J87: =0.51*0.8 -> 0.408 | K87: =0.51*0.8 -> 0.408 | L87: =0.51*0.8 -> 0.408 | M87: =0.51*0.8 -> 0.408 | ... S87: =0.51*0.8 -> 0.408
B88: Sony | F88: =0.49*0.8 -> 0.392 | G88: =0.49*0.8 -> 0.392 | H88: =0.49*0.8 -> 0.392 | I88: =0.49*0.8 -> 0.392 | J88: =0.49*0.8 -> 0.392 | K88: =0.49*0.8 -> 0.392 | L88: =0.49*0.8 -> 0.392 | M88: =0.49*0.8 -> 0.392 | ... S88: =0.49*0.8 -> 0.392
B89: Charles M Schulz | F89: 0.2 | G89: 0.2 | H89: 0.2 | I89: 0.2 | J89: 0.2 | K89: 0.2 | L89: 0.2 | M89: 0.2 | N89: 0.2 | O89: 0.2 | P89: 0.2 | Q89: 0.2 | R89: 0.2 | S89: 0.2
B91: Peanuts revenue | F91: 149.625 | G91: 151.705 | H91: 193.817 | I91: 176.458 | J91: =+(1+J95)*I91 -> 181.75174 | K91: =+(1+K95)*J91 -> 187.20429 | L91: =+(1+L95)*K91 -> 192.82042 | M91: =+(1+M95)*L91 -> 198.60503 | N91: =+(1+N95)*M91 -> 204.56318 | O91: =+(1+O95)*N91 -> 210.70008 | P91: =+(1+P95)*O91 -> 217.02108 | Q91: =+(1+Q95)*P91 -> 223.53172 | ... S91: =+(1+S95)*R91 -> 237.1448
B92: Peanuts total expense | F92: -108.667 | G92: -108.891 | H92: -144.354 | I92: -143.968 | J92: =+J96*J91*-1 -> -136.31381 | K92: =+K96*K91*-1 -> -140.40322 | L92: =+L96*L91*-1 -> -144.61532 | M92: =+M96*M91*-1 -> -148.95378 | N92: =+N96*N91*-1 -> -153.42239 | O92: =+O96*O91*-1 -> -158.02506 | P92: =+P96*P91*-1 -> -162.76581 | Q92: =+Q96*Q91*-1 -> -167.64879 | ... S92: =+S96*S91*-1 -> -177.8586
B93: Peanuts net income | F93: =SUM(F91:F92) -> 40.958 | G93: =SUM(G91:G92) -> 42.814 | H93: =SUM(H91:H92) -> 49.463 | I93: =SUM(I91:I92) -> 32.49 | J93: =SUM(J91:J92) -> 45.437935 | K93: =SUM(K91:K92) -> 46.801073 | L93: =SUM(L91:L92) -> 48.205105 | M93: =SUM(M91:M92) -> 49.651258 | ... S93: =SUM(S91:S92) -> 59.286199
B95: Revenue growth | G95: =+G91/F91-1 -> 0.01390142 | H95: =+H91/G91-1 -> 0.27759138 | I95: =+I91/H91-1 -> -0.089563867 | J95: 0.03 | K95: 0.03 | L95: 0.03 | M95: 0.03 | N95: 0.03 | O95: 0.03 | P95: 0.03 | Q95: 0.03 | R95: 0.03 | S95: 0.03
B96: Expense % of revenue | G96: =+G92/G91*-1 -> 0.71778122 | H96: =+H92/H91*-1 -> 0.74479535 | I96: =+I92/I91*-1 -> 0.81587687 | J96: 0.75 | K96: 0.75 | L96: 0.75 | M96: 0.75 | N96: 0.75 | O96: 0.75 | P96: 0.75 | Q96: 0.75 | R96: 0.75 | S96: 0.75
B98: NI to NCI | F98: =+'P&L'!E35 -> 7.312 | G98: =+'P&L'!F35 -> 23.292 | H98: =+'P&L'!G35 -> 27.175 | I98: =+'P&L'!H35 -> 30.186 | J98: =+J99*J93 -> 26.899258 | K98: =+K99*K93 -> 27.706235 | L98: =+L99*L93 -> 28.537422 | M98: =+M99*M93 -> 29.393545 | N98: =+N99*N93 -> 30.275351 | O98: =+O99*O93 -> 31.183612 | P98: =+P99*P93 -> 32.11912 | Q98: =+Q99*Q93 -> 33.082694 | ... S98: =+S99*S93 -> 35.09743
B99: % of total | F99: =+F98/F93 -> 0.17852434 | G99: =+G98/G93 -> 0.54402765 | H99: =+H98/H93 -> 0.54940056 | I99: =+I98/I93 -> 0.92908587 | J99: =+J88+J89 -> 0.592 | K99: =+K88+K89 -> 0.592 | L99: =+L88+L89 -> 0.592 | M99: =+M88+M89 -> 0.592 | N99: =+N88+N89 -> 0.592 | O99: =+O88+O89 -> 0.592 | P99: =+P88+P89 -> 0.592 | Q99: =+Q88+Q89 -> 0.592 | ... S99: =+S88+S89 -> 0.592
B101: Distributions to NCI growth | G101: =+G82/F82-1 -> 0.25520501 | H101: =+H82/G82-1 -> -0.059862522 | I101: =+I82/H82-1 -> 0.068410847 | J101: 0.02 | K101: 0.02 | L101: 0.02 | M101: 0.02 | N101: 0.02 | O101: 0.02 | P101: 0.02 | Q101: 0.02 | R101: 0.02 | S101: 0.02
A103: x | B103: P&L
B104: SG&A | E104: =+'P&L'!E20 -> -86.2 | F104: =+'P&L'!F20 -> -81.121 | G104: =+'P&L'!G20 -> -83.098 | H104: =+'P&L'!H20 -> -80.539 | I104: =+'P&L'!I20 -> -104.129 | J104: =+J105*J10*-1 -> -101.23057 | K104: =+K105*K10*-1 -> -112.18068 | L104: =+L105*L10*-1 -> -125.62792 | M104: =+M105*M10*-1 -> -135.91147 | N104: =+N105*N10*-1 -> -144.49815 | O104: =+O105*O10*-1 -> -152.06887 | P104: =+P105*P10*-1 -> -159.57362 | Q104: =+Q105*Q10*-1 -> -167.31877 | ... S104: =+S105*S10*-1 -> -184.09246
B105: % of revenue | E105: =+E104/E10*-1 -> 0.19842731 | F105: =+F104/F10*-1 -> 0.18444975 | G105: =+G104/G10*-1 -> 0.19523346 | H105: =+H104/H10*-1 -> 0.17797337 | I105: =+I104/I10*-1 -> 0.20529235 | J105: =+AVERAGE(E105:I105) -> 0.19227525 | K105: =+J105 -> 0.19227525 | L105: =+K105 -> 0.19227525 | M105: =+L105 -> 0.19227525 | N105: =+M105 -> 0.19227525 | O105: =+N105 -> 0.19227525 | P105: =+O105 -> 0.19227525 | Q105: =+P105 -> 0.19227525 | R105: =+Q105 -> 0.19227525 | S105: =+R105 -> 0.19227525
B107: Current taxes | E107: =+'P&L'!E30 -> -2.166 | F107: =+'P&L'!F30 -> 1.77 | G107: =+'P&L'!G30 -> -0.489 | H107: =+'P&L'!H30 -> -3.049 | I107: =+'P&L'!I30 -> -0.347 | J107: =+(J109*J12-J108)*-1 -> -6.7042139 | K107: =+(K109*K12-K108)*-1 -> -10.277893 | L107: =+(L109*L12-L108)*-1 -> -16.068618 | M107: =+(M109*M12-M108)*-1 -> -18.43395 | N107: =+(N109*N12-N108)*-1 -> -19.686448 | O107: =+(O109*O12-O108)*-1 -> -20.686593 | P107: =+(P109*P12-P108)*-1 -> -21.658812 | Q107: =+(Q109*Q12-Q108)*-1 -> -22.67126 | ... S107: =+(S109*S12-S108)*-1 -> -24.257764
B108: Deferred taxes | E108: =+'P&L'!E31 -> 0.675 | F108: =+'P&L'!F31 -> 1.936 | G108: =+'P&L'!G31 -> -1.217 | H108: =+'P&L'!H31 -> 6.347 | I108: =+'P&L'!I31 -> 1.904 | J108: 0 | K108: 0 | L108: 0 | M108: 0 | N108: 0 | O108: 0 | P108: 0 | Q108: 0 | R108: 0 | S108: 0
B109: ETR | E109: =+SUM(E107:E108)/E12*-1 -> -0.28362184 | F109: =+SUM(F107:F108)/F12*-1 -> 0.045245886 | G109: =+SUM(G107:G108)/G12*-1 -> -0.0082381631 | H109: =+SUM(H107:H108)/H12*-1 -> -0.16647317 | I109: =+SUM(I107:I108)/I12*-1 -> -0.051547757 | J109: 0.29 | K109: 0.29 | L109: 0.29 | M109: 0.29 | N109: 0.29 | O109: 0.29 | P109: 0.29 | Q109: 0.29 | R109: 0.29 | S109: 0.29

Sheet Debt Calcs
A1: in CADm unless otherwise stated
A2: FYE June
E4: 2018 | F4: =+E4+1 -> 2019 | G4: =+F4+1 -> 2020 | H4: =+G4+1 -> 2021 | I4: =+H4+1 -> 2022 | J4: =+I4+1 -> 2023 | K4: =+J4+1 -> 2024 | L4: =+K4+1 -> 2025 | M4: =+L4+1 -> 2026 | ... S4: =+R4+1 -> 2032
A6: x | B6: Current debt
B7: Bank indebtedness | E7: =+'BS & CFS'!E21 -> 16.35 | F7: =+'BS & CFS'!F21 -> 0 | G7: =+'BS & CFS'!G21 -> 10 | H7: =+'BS & CFS'!H21 -> 0 | I7: =+'BS & CFS'!I21 -> 9.087 | J7: =+J40 -> 40.509 | K7: =+K40 -> 40.509 | L7: =+L40 -> 40.509 | M7: =+M40 -> 40.509 | N7: =+N40 -> 40.509 | O7: =+O40 -> 40.509 | P7: =+P40 -> 40.509 | Q7: =+Q40 -> 40.509 | ... S7: =+S40 -> 40.509
B8: Production Financing | E8: =+'BS & CFS'!E24 -> 93.683 | F8: =+'BS & CFS'!F24 -> 92.448 | G8: =+'BS & CFS'!G24 -> 66.688 | H8: =+'BS & CFS'!H24 -> 65.403 | I8: =+'BS & CFS'!I24 -> 84.235 | J8: =+J46 -> 90 | K8: =+K46 -> 90 | L8: =+L46 -> 90 | M8: =+M46 -> 90 | N8: =+N46 -> 90 | O8: =+O46 -> 90 | P8: =+P46 -> 90 | Q8: =+Q46 -> 90 | ... S8: =+S46 -> 90
B9: Current Portion of Lease Liabilities | E9: =+'BS & CFS'!E25 -> 0 | F9: =+'BS & CFS'!F25 -> 0 | G9: =+'BS & CFS'!G25 -> 9.274 | H9: =+'BS & CFS'!H25 -> 9.428 | I9: =+'BS & CFS'!I25 -> 10.183 | J9: 0 | K9: 0 | L9: 0 | M9: 0 | N9: 0 | O9: 0 | P9: 0 | Q9: 0 | R9: 0 | S9: 0
B10: Current Portion of Long-Term Debt | E10: =+'BS & CFS'!E26 -> 10.524 | F10: =+'BS & CFS'!F26 -> 11.007 | G10: =+'BS & CFS'!G26 -> 0 | H10: =+'BS & CFS'!H26 -> 3.532 | I10: =+'BS & CFS'!I26 -> 26.335 | J10: =+J52 -> 0 | K10: =+K52 -> 0 | L10: =+L52 -> 0 | M10: =+M52 -> 0 | N10: =+N52 -> 0 | O10: =+O52 -> 0 | P10: =+P52 -> 0 | Q10: =+Q52 -> 0 | ... S10: =+S52 -> 0
A12: x | B12: LT debt
B13: Long-Term Debt | E13: =+'BS & CFS'!E29 -> 746.046 | F13: =+'BS & CFS'!F29 -> 523.061 | G13: =+'BS & CFS'!G29 -> 502.006 | H13: =+'BS & CFS'!H29 -> 478.862 | I13: =+'BS & CFS'!I29 -> 477.804 | J13: =+J57 -> 508.43978 | K13: =+K57 -> 598.48039 | L13: =+L57 -> 676.37008 | M13: =+M57 -> 753.49212 | N13: =+N57 -> 830.64655 | O13: =+O57 -> 909.94618 | P13: =+P57 -> 992.80209 | Q13: =+Q57 -> 1079.7369 | ... S13: =+S57 -> 1265.5376
B14: Long-Term Lease Liabilities | E14: =+'BS & CFS'!E30 -> 0 | F14: =+'BS & CFS'!F30 -> 0 | G14: =+'BS & CFS'!G30 -> 41.552 | H14: =+'BS & CFS'!H30 -> 34.407 | I14: =+'BS & CFS'!I30 -> 26.056 | J14: =+J64-J9 -> 36.239 | K14: =+K64-K9 -> 36.239 | L14: =+L64-L9 -> 36.239 | M14: =+M64-M9 -> 36.239 | N14: =+N64-N9 -> 36.239 | O14: =+O64-O9 -> 36.239 | P14: =+P64-P9 -> 36.239 | Q14: =+Q64-Q9 -> 36.239 | ... S14: =+S64-S9 -> 36.239
A16: x | B16: Finance cost
B17: Canadian prime rate | J17: 0.037 | K17: 0.037 | L17: 0.037 | M17: 0.037 | N17: 0.037 | O17: 0.037 | P17: 0.037 | Q17: 0.037 | R17: 0.037 | S17: 0.037
B18: Blended production financing rate | J18: 0.0575 | K18: 0.0575 | L18: 0.0575 | M18: 0.0575 | N18: 0.0575 | O18: 0.0575 | P18: 0.0575 | Q18: 0.0575 | R18: 0.0575 | S18: 0.0575
B19: Blended LT debt rate | J19: 0.056 | K19: 0.056 | L19: 0.056 | M19: 0.056 | N19: 0.056 | O19: 0.056 | P19: 0.056 | Q19: 0.056 | R19: 0.056 | S19: 0.056
B20: Blended lease liability rate | J20: 0.059 | K20: 0.059 | L20: 0.059 | M20: 0.059 | N20: 0.059 | O20: 0.059 | P20: 0.059 | Q20: 0.059 | R20: 0.059 | S20: 0.059
B22: Net finance cost | J22: =+J41+J47+J53+J58+J65+J71 -> -34.661458 | K22: =+K41+K47+K53+K58+K65+K71 -> -38.510699 | L22: =+L41+L47+L53+L58+L65+L71 -> -43.212747 | M22: =+M41+M47+M53+M58+M65+M71 -> -47.553075 | N22: =+N41+N47+N53+N58+N65+N71 -> -51.872817 | O22: =+O41+O47+O53+O58+O65+O71 -> -56.25353 | P22: =+P41+P47+P53+P58+P65+P71 -> -60.793885 | Q22: =+Q41+Q47+Q53+Q58+Q65+Q71 -> -65.548026 | ... S22: =+S41+S47+S53+S58+S65+S71 -> -75.729165
A24: x | B24: Debt calcs
B25: OCF | J25: =+'BS & CFS'!J64 -> 31.512681 | K25: =+'BS & CFS'!K64 -> 15.52598 | L25: =+'BS & CFS'!L64 -> 36.924852 | M25: =+'BS & CFS'!M64 -> 45.687734 | N25: =+'BS & CFS'!N64 -> 53.158883 | O25: =+'BS & CFS'!O64 -> 58.302131 | P25: =+'BS & CFS'!P64 -> 62.189908 | Q25: =+'BS & CFS'!Q64 -> 65.852747 | ... S25: =+'BS & CFS'!S64 -> 74.433489
B26: Finance costs | J26: =+'P&L'!J22 -> -34.661458 | K26: =+'P&L'!K22 -> -38.510699 | L26: =+'P&L'!L22 -> -43.212747 | M26: =+'P&L'!M22 -> -47.553075 | N26: =+'P&L'!N22 -> -51.872817 | O26: =+'P&L'!O22 -> -56.25353 | P26: =+'P&L'!P22 -> -60.793885 | Q26: =+'P&L'!Q22 -> -65.548026 | ... S26: =+'P&L'!S22 -> -75.729165
B27: Capex, addition of content and intangibles | J27: =+'BS & CFS'!J66+'BS & CFS'!J67+'BS & CFS'!J68 -> -26.643828 | K27: =+'BS & CFS'!K66+'BS & CFS'!K67+'BS & CFS'!K68 -> -29.776088 | L27: =+'BS & CFS'!L66+'BS & CFS'!L67+'BS & CFS'!L68 -> -33.622648 | M27: =+'BS & CFS'!M66+'BS & CFS'!M67+'BS & CFS'!M68 -> -36.564239 | N27: =+'BS & CFS'!N66+'BS & CFS'!N67+'BS & CFS'!N68 -> -39.020445 | O27: =+'BS & CFS'!O66+'BS & CFS'!O67+'BS & CFS'!O68 -> -41.186036 | P27: =+'BS & CFS'!P66+'BS & CFS'!P67+'BS & CFS'!P68 -> -43.332757 | Q27: =+'BS & CFS'!Q66+'BS & CFS'!Q67+'BS & CFS'!Q68 -> -45.548244 | ... S27: =+'BS & CFS'!S66+'BS & CFS'!S67+'BS & CFS'!S68 -> -50.346326
B28: Dicstribution to NCI | J28: =+'FS Calcs'!J82 -> -34.28118 | K28: =+'FS Calcs'!K82 -> -34.966804 | L28: =+'FS Calcs'!L82 -> -35.66614 | M28: =+'FS Calcs'!M82 -> -36.379462 | N28: =+'FS Calcs'!N82 -> -37.107052 | O28: =+'FS Calcs'!O82 -> -37.849193 | P28: =+'FS Calcs'!P82 -> -38.606177 | Q28: =+'FS Calcs'!Q82 -> -39.3783 | ... S28: =+'FS Calcs'!S82 -> -40.969183
B29: Lease liability repayment | J29: =+J63 -> -2.313 | K29: =+K63 -> -2.313 | L29: =+L63 -> -2.313 | M29: =+M63 -> -2.313 | N29: =+N63 -> -2.313 | O29: =+O63 -> -2.313 | P29: =+P63 -> -2.313 | Q29: =+Q63 -> -2.313 | ... S29: =+S63 -> -2.313
B30: FCF | J30: =SUM(J25:J29) -> -66.386784 | K30: =SUM(K25:K29) -> -90.04061 | L30: =SUM(L25:L29) -> -77.889682 | M30: =SUM(M25:M29) -> -77.122043 | N30: =SUM(N25:N29) -> -77.15443 | O30: =SUM(O25:O29) -> -79.299628 | P30: =SUM(P25:P29) -> -82.855911 | Q30: =SUM(Q25:Q29) -> -86.934823 | ... S30: =SUM(S25:S29) -> -94.924186
B32: BoP cash | J32: =+J68 -> 59.899 | K32: =+K68 -> 35 | L32: =+L68 -> 35 | M32: =+M68 -> 35 | N32: =+N68 -> 35 | O32: =+O68 -> 35 | P32: =+P68 -> 35 | Q32: =+Q68 -> 35 | ... S32: =+S68 -> 35
B33: Minimum cash | J33: -35 | K33: =+J33 -> -35 | L33: =+K33 -> -35 | M33: =+L33 -> -35 | N33: =+M33 -> -35 | O33: =+N33 -> -35 | P33: =+O33 -> -35 | Q33: =+P33 -> -35 | R33: =+Q33 -> -35 | S33: =+R33 -> -35
B34: CFADS | J34: =+J33+J32+J30 -> -41.487784 | K34: =+K33+K32+K30 -> -90.04061 | L34: =+L33+L32+L30 -> -77.889682 | M34: =+M33+M32+M30 -> -77.122043 | N34: =+N33+N32+N30 -> -77.15443 | O34: =+O33+O32+O30 -> -79.299628 | P34: =+P33+P32+P30 -> -82.855911 | Q34: =+Q33+Q32+Q30 -> -86.934823 | ... S34: =+S33+S32+S30 -> -94.924186
B36: Mandatory payments | J36: =+J51 -> -26.335 | K36: =+K51 -> 0 | L36: =+L51 -> 0 | M36: =+M51 -> 0 | N36: =+N51 -> 0 | O36: =+O51 -> 0 | P36: =+P51 -> 0 | Q36: =+Q51 -> 0 | ... S36: =+S51 -> 0
B38: BoP bank indebtedness | J38: =+I40 -> 9.087 | K38: =+J40 -> 40.509 | L38: =+K40 -> 40.509 | M38: =+L40 -> 40.509 | N38: =+M40 -> 40.509 | O38: =+N40 -> 40.509 | P38: =+O40 -> 40.509 | Q38: =+P40 -> 40.509 | ... S38: =+R40 -> 40.509
B39: Draw / (repayment) | J39: =+IF(MIN(J36+J34,J38)*-1>=(J42-J38),J42-J38,MIN(J36+J34,J38)*-1) -> 31.422 | K39: =+IF(MIN(K36+K34,K38)*-1>=(K42-K38),K42-K38,MIN(K36+K34,K38)*-1) -> 0 | L39: =+IF(MIN(L36+L34,L38)*-1>=(L42-L38),L42-L38,MIN(L36+L34,L38)*-1) -> 0 | M39: =+IF(MIN(M36+M34,M38)*-1>=(M42-M38),M42-M38,MIN(M36+M34,M38)*-1) -> 0 | N39: =+IF(MIN(N36+N34,N38)*-1>=(N42-N38),N42-N38,MIN(N36+N34,N38)*-1) -> 0 | O39: =+IF(MIN(O36+O34,O38)*-1>=(O42-O38),O42-O38,MIN(O36+O34,O38)*-1) -> 0 | P39: =+IF(MIN(P36+P34,P38)*-1>=(P42-P38),P42-P38,MIN(P36+P34,P38)*-1) -> 0 | Q39: =+IF(MIN(Q36+Q34,Q38)*-1>=(Q42-Q38),Q42-Q38,MIN(Q36+Q34,Q38)*-1) -> 0 | ... S39: =+IF(MIN(S36+S34,S38)*-1>=(S42-S38),S42-S38,MIN(S36+S34,S38)*-1) -> 0
B40: EoP bank indebtedness | I40: =+I7 -> 9.087 | J40: =SUM(J38:J39) -> 40.509 | K40: =SUM(K38:K39) -> 40.509 | L40: =SUM(L38:L39) -> 40.509 | M40: =SUM(M38:M39) -> 40.509 | N40: =SUM(N38:N39) -> 40.509 | O40: =SUM(O38:O39) -> 40.509 | P40: =SUM(P38:P39) -> 40.509 | Q40: =SUM(Q38:Q39) -> 40.509 | ... S40: =SUM(S38:S39) -> 40.509
B41: Interest | J41: =+AVERAGE(I40:J40)*J17*-1 -> -0.917526 | K41: =+AVERAGE(J40:K40)*K17*-1 -> -1.498833 | L41: =+AVERAGE(K40:L40)*L17*-1 -> -1.498833 | M41: =+AVERAGE(L40:M40)*M17*-1 -> -1.498833 | N41: =+AVERAGE(M40:N40)*N17*-1 -> -1.498833 | O41: =+AVERAGE(N40:O40)*O17*-1 -> -1.498833 | P41: =+AVERAGE(O40:P40)*P17*-1 -> -1.498833 | Q41: =+AVERAGE(P40:Q40)*Q17*-1 -> -1.498833 | ... S41: =+AVERAGE(R40:S40)*S17*-1 -> -1.498833
B42: Credit limit | J42: =30*Output!$J$8 -> 40.509 | K42: =30*Output!$J$8 -> 40.509 | L42: =30*Output!$J$8 -> 40.509 | M42: =30*Output!$J$8 -> 40.509 | N42: =30*Output!$J$8 -> 40.509 | O42: =30*Output!$J$8 -> 40.509 | P42: =30*Output!$J$8 -> 40.509 | Q42: =30*Output!$J$8 -> 40.509 | ... S42: =30*Output!$J$8 -> 40.509
B44: BoP production financing | J44: =+I46 -> 84.235 | K44: =+J46 -> 90 | L44: =+K46 -> 90 | M44: =+L46 -> 90 | N44: =+M46 -> 90 | O44: =+N46 -> 90 | P44: =+O46 -> 90 | Q44: =+P46 -> 90 | ... S44: =+R46 -> 90
B45: Draw / (repayment) | J45: =+IF(MIN(J44, J34+J36+J39)*-1>=(J48-J44), J48-J44, MIN(J44, J34+J36+J39)*-1) -> 5.765 | K45: =+IF(MIN(K44, K34+K36+K39)*-1>=(K48-K44), K48-K44, MIN(K44, K34+K36+K39)*-1) -> 0 | L45: =+IF(MIN(L44, L34+L36+L39)*-1>=(L48-L44), L48-L44, MIN(L44, L34+L36+L39)*-1) -> 0 | M45: =+IF(MIN(M44, M34+M36+M39)*-1>=(M48-M44), M48-M44, MIN(M44, M34+M36+M39)*-1) -> 0 | N45: =+IF(MIN(N44, N34+N36+N39)*-1>=(N48-N44), N48-N44, MIN(N44, N34+N36+N39)*-1) -> 0 | O45: =+IF(MIN(O44, O34+O36+O39)*-1>=(O48-O44), O48-O44, MIN(O44, O34+O36+O39)*-1) -> 0 | P45: =+IF(MIN(P44, P34+P36+P39)*-1>=(P48-P44), P48-P44, MIN(P44, P34+P36+P39)*-1) -> 0 | Q45: =+IF(MIN(Q44, Q34+Q36+Q39)*-1>=(Q48-Q44), Q48-Q44, MIN(Q44, Q34+Q36+Q39)*-1) -> 0 | ... S45: =+IF(MIN(S44, S34+S36+S39)*-1>=(S48-S44), S48-S44, MIN(S44, S34+S36+S39)*-1) -> 0
B46: EoP production fianncing | I46: =+I8 -> 84.235 | J46: =SUM(J44:J45) -> 90 | K46: =SUM(K44:K45) -> 90 | L46: =SUM(L44:L45) -> 90 | M46: =SUM(M44:M45) -> 90 | N46: =SUM(N44:N45) -> 90 | O46: =SUM(O44:O45) -> 90 | P46: =SUM(P44:P45) -> 90 | Q46: =SUM(Q44:Q45) -> 90 | ... S46: =SUM(S44:S45) -> 90
B47: Interest | J47: =+AVERAGE(I46:J46)*J18*-1 -> -5.0092563 | K47: =+AVERAGE(J46:K46)*K18*-1 -> -5.175 | L47: =+AVERAGE(K46:L46)*L18*-1 -> -5.175 | M47: =+AVERAGE(L46:M46)*M18*-1 -> -5.175 | N47: =+AVERAGE(M46:N46)*N18*-1 -> -5.175 | O47: =+AVERAGE(N46:O46)*O18*-1 -> -5.175 | P47: =+AVERAGE(O46:P46)*P18*-1 -> -5.175 | Q47: =+AVERAGE(P46:Q46)*Q18*-1 -> -5.175 | ... S47: =+AVERAGE(R46:S46)*S18*-1 -> -5.175
B48: Credit limit | J48: 90 | K48: 90 | L48: 90 | M48: 90 | N48: 90 | O48: 90 | P48: 90 | Q48: 90 | R48: 90 | S48: 90
B50: BoP curent portion of LT debt | J50: =+I52 -> 26.335 | K50: =+J52 -> 0 | L50: =+K52 -> 0 | M50: =+L52 -> 0 | N50: =+M52 -> 0 | O50: =+N52 -> 0 | P50: =+O52 -> 0 | Q50: =+P52 -> 0 | ... S50: =+R52 -> 0
B51: Mandatory payment | J51: =+J50*-1 -> -26.335 | K51: =+K50*-1 -> 0 | L51: =+L50*-1 -> 0 | M51: =+M50*-1 -> 0 | N51: =+N50*-1 -> 0 | O51: =+O50*-1 -> 0 | P51: =+P50*-1 -> 0 | Q51: =+Q50*-1 -> 0 | ... S51: =+S50*-1 -> 0
B52: EoP curent portion of LT debt | I52: =+I10 -> 26.335 | J52: =SUM(J50:J51) -> 0 | K52: =SUM(K50:K51) -> 0 | L52: =SUM(L50:L51) -> 0 | M52: =SUM(M50:M51) -> 0 | N52: =SUM(N50:N51) -> 0 | O52: =SUM(O50:O51) -> 0 | P52: =SUM(P50:P51) -> 0 | Q52: =SUM(Q50:Q51) -> 0 | ... S52: =SUM(S50:S51) -> 0
B53: Interest | J53: =+AVERAGE(I52:J52)*J19*-1 -> -0.73738 | K53: =+AVERAGE(J52:K52)*K19*-1 -> 0 | L53: =+AVERAGE(K52:L52)*L19*-1 -> 0 | M53: =+AVERAGE(L52:M52)*M19*-1 -> 0 | N53: =+AVERAGE(M52:N52)*N19*-1 -> 0 | O53: =+AVERAGE(N52:O52)*O19*-1 -> 0 | P53: =+AVERAGE(O52:P52)*P19*-1 -> 0 | Q53: =+AVERAGE(P52:Q52)*Q19*-1 -> 0 | ... S53: =+AVERAGE(R52:S52)*S19*-1 -> 0
B55: BoP LT debt | J55: =+I57 -> 477.804 | K55: =+J57 -> 508.43978 | L55: =+K57 -> 598.48039 | M55: =+L57 -> 676.37008 | N55: =+M57 -> 753.49212 | O55: =+N57 -> 830.64655 | P55: =+O57 -> 909.94618 | Q55: =+P57 -> 992.80209 | ... S55: =+R57 -> 1170.6135
B56: Draw / repayment | J56: =+MIN(J55, J34+J39+J45+J36)*-1 -> 30.635784 | K56: =+MIN(K55, K34+K39+K45+K36)*-1 -> 90.04061 | L56: =+MIN(L55, L34+L39+L45+L36)*-1 -> 77.889682 | M56: =+MIN(M55, M34+M39+M45+M36)*-1 -> 77.122043 | N56: =+MIN(N55, N34+N39+N45+N36)*-1 -> 77.15443 | O56: =+MIN(O55, O34+O39+O45+O36)*-1 -> 79.299628 | P56: =+MIN(P55, P34+P39+P45+P36)*-1 -> 82.855911 | Q56: =+MIN(Q55, Q34+Q39+Q45+Q36)*-1 -> 86.934823 | ... S56: =+MIN(S55, S34+S39+S45+S36)*-1 -> 94.924186
B57: EoP LT debt | I57: =+I13 -> 477.804 | J57: =SUM(J55:J56) -> 508.43978 | K57: =SUM(K55:K56) -> 598.48039 | L57: =SUM(L55:L56) -> 676.37008 | M57: =SUM(M55:M56) -> 753.49212 | N57: =SUM(N55:N56) -> 830.64655 | O57: =SUM(O55:O56) -> 909.94618 | P57: =SUM(P55:P56) -> 992.80209 | Q57: =SUM(Q55:Q56) -> 1079.7369 | ... S57: =SUM(S55:S56) -> 1265.5376
B58: Interest | J58: =+AVERAGE(I57:J57)*J19*-1 -> -27.614826 | K58: =+AVERAGE(J57:K57)*K19*-1 -> -30.993765 | L58: =+AVERAGE(K57:L57)*L19*-1 -> -35.695813 | M58: =+AVERAGE(L57:M57)*M19*-1 -> -40.036141 | N58: =+AVERAGE(M57:N57)*N19*-1 -> -44.355883 | O58: =+AVERAGE(N57:O57)*O19*-1 -> -48.736596 | P58: =+AVERAGE(O57:P57)*P19*-1 -> -53.276951 | Q58: =+AVERAGE(P57:Q57)*Q19*-1 -> -58.031092 | ... S58: =+AVERAGE(R57:S57)*S19*-1 -> -68.212231
A60: x | B60: Lease calcs
B61: BoP lease liabilities | J61: =+I64 -> 36.239 | K61: =+J64 -> 36.239 | L61: =+K64 -> 36.239 | M61: =+L64 -> 36.239 | N61: =+M64 -> 36.239 | O61: =+N64 -> 36.239 | P61: =+O64 -> 36.239 | Q61: =+P64 -> 36.239 | ... S61: =+R64 -> 36.239
B62: Addition | I62: 2.313 | J62: =+I62 -> 2.313 | K62: =+J62 -> 2.313 | L62: =+K62 -> 2.313 | M62: =+L62 -> 2.313 | N62: =+M62 -> 2.313 | O62: =+N62 -> 2.313 | P62: =+O62 -> 2.313 | Q62: =+P62 -> 2.313 | ... S62: =+R62 -> 2.313
B63: Repayment | I63: -9.495 | J63: =+J62*-1 -> -2.313 | K63: =+K62*-1 -> -2.313 | L63: =+L62*-1 -> -2.313 | M63: =+M62*-1 -> -2.313 | N63: =+N62*-1 -> -2.313 | O63: =+O62*-1 -> -2.313 | P63: =+P62*-1 -> -2.313 | Q63: =+Q62*-1 -> -2.313 | ... S63: =+S62*-1 -> -2.313
B64: EoP lease liabilities | I64: =+I9+I14 -> 36.239 | J64: =SUM(J61:J63) -> 36.239 | K64: =SUM(K61:K63) -> 36.239 | L64: =SUM(L61:L63) -> 36.239 | M64: =SUM(M61:M63) -> 36.239 | N64: =SUM(N61:N63) -> 36.239 | O64: =SUM(O61:O63) -> 36.239 | P64: =SUM(P61:P63) -> 36.239 | Q64: =SUM(Q61:Q63) -> 36.239 | ... S64: =SUM(S61:S63) -> 36.239
B65: Interest | J65: =+AVERAGE(I64:J64)*J20*-1 -> -2.138101 | K65: =+AVERAGE(J64:K64)*K20*-1 -> -2.138101 | L65: =+AVERAGE(K64:L64)*L20*-1 -> -2.138101 | M65: =+AVERAGE(L64:M64)*M20*-1 -> -2.138101 | N65: =+AVERAGE(M64:N64)*N20*-1 -> -2.138101 | O65: =+AVERAGE(N64:O64)*O20*-1 -> -2.138101 | P65: =+AVERAGE(O64:P64)*P20*-1 -> -2.138101 | Q65: =+AVERAGE(P64:Q64)*Q20*-1 -> -2.138101 | ... S65: =+AVERAGE(R64:S64)*S20*-1 -> -2.138101
A67: x | B67: Cash calcs
B68: BoP cash | J68: =+I70 -> 59.899 | K68: =+J70 -> 35 | L68: =+K70 -> 35 | M68: =+L70 -> 35 | N68: =+M70 -> 35 | O68: =+N70 -> 35 | P68: =+O70 -> 35 | Q68: =+P70 -> 35 | ... S68: =+R70 -> 35
B69: Net cash flow | J69: =+J30+J39+J45+J51+J56 -> -24.899 | K69: =+K30+K39+K45+K51+K56 -> 0 | L69: =+L30+L39+L45+L51+L56 -> 0 | M69: =+M30+M39+M45+M51+M56 -> 0 | N69: =+N30+N39+N45+N51+N56 -> 0 | O69: =+O30+O39+O45+O51+O56 -> 0 | P69: =+P30+P39+P45+P51+P56 -> 0 | Q69: =+Q30+Q39+Q45+Q51+Q56 -> 0 | ... S69: =+S30+S39+S45+S51+S56 -> 0
B70: EoP cash | I70: =+'BS & CFS'!I6 -> 59.899 | J70: =SUM(J68:J69) -> 35 | K70: =SUM(K68:K69) -> 35 | L70: =SUM(L68:L69) -> 35 | M70: =SUM(M68:M69) -> 35 | N70: =SUM(N68:N69) -> 35 | O70: =SUM(O68:O69) -> 35 | P70: =SUM(P68:P69) -> 35 | Q70: =SUM(Q68:Q69) -> 35 | ... S70: =SUM(S68:S69) -> 35
B71: Interest | J71: =+AVERAGE(I70:J70)*J17 -> 1.7556315 | K71: =+AVERAGE(J70:K70)*K17 -> 1.295 | L71: =+AVERAGE(K70:L70)*L17 -> 1.295 | M71: =+AVERAGE(L70:M70)*M17 -> 1.295 | N71: =+AVERAGE(M70:N70)*N17 -> 1.295 | O71: =+AVERAGE(N70:O70)*O17 -> 1.295 | P71: =+AVERAGE(O70:P70)*P17 -> 1.295 | Q71: =+AVERAGE(P70:Q70)*Q17 -> 1.295 | ... S71: =+AVERAGE(R70:S70)*S17 -> 1.295

Sheet Quarterly
A1: in CADm unless otherwise stated
A2: FYE June
E4: Q1/FY23 | F4: Q2/FY23 | G4: Q3/FY23 | H4: Q4/FY23
A6: x | B6: P&L
B7: Content production and distribution | E7: 52.761
B8: WildBrain Spark | E8: 11.617
B9: Consumer Products | E9: 52.101
B10: Canadian Television | E10: 10.173
B11: Total revenue | E11: =SUM(E7:E10) -> 126.652
B13: Content | E13: 48.723
B14: Canadian TV | E14: 6.554
B15: Gross profits | E15: =+E14+E13 -> 55.277
B16: Gross margins % | E16: =+E15/E11 -> 0.4364479
B17: Content GM % | E17: =+E13/SUM(E7:E9) -> 0.41829858
B18: TV GM % | E18: =+E14/E10 -> 0.6442544
B20: =+'P&L'!B16 -> Amortization of acquired and library content | E20: -2.349
B21: =+'P&L'!B17 -> Amortization of property and equipment and intangible assets | E21: -6.274
B22: =+'P&L'!B18 -> Write-down of investment in film and television programs, acquired and library content, and property and equipment | E22: 0
B24: =+'P&L'!B20 -> Selling, general and administrative | E24: -25.728
B25: =+'P&L'!B21 -> Share-based compensation | E25: -1.327
B26: =+'P&L'!B22 -> Finance costs, net | E26: -8.803
B27: =+'P&L'!B23 -> Change in fair value of embedded derivatives | E27: 6.034
B28: =+'P&L'!B24 -> Foreign exchange (loss) / gain | E28: -12.456
B29: =+'P&L'!B25 -> Reorganization, development and other expense | E29: -1.568
B31: EBT | E31: =+E15+SUM(E20:E22,E24:E29) -> 2.806
B32: % margin | E32: =+E31/E11 -> 0.022155197
B34: Current income taxes (paid) / recovered | E34: -0.613
B35: Deferred income taxes (paid) / recovered | E35: 1.545
B36: Total | E36: =SUM(E34:E35) -> 0.932
B38: Net income | E38: =+E31+E36 -> 3.738
B39: Attributable to NCI | E39: 11.31
B40: Attributable to common | E40: =+E38-E39 -> -7.572
B42: Basic EPS (CAD) | E42: -0.04
B43: Diluted EPS (CAD) | E43: -0.06
B45: Basic - WASO | E45: 173.113
B46: Diluted - WASO | E46: 190.354
B48: Dividend to common | E48: 0
B49: Distribution to NCI | E49: -2.378
A51: x | B51: BS
B52: Cash & Equivalents | E52: 62.075
B53: Restricted Cash | E53: 8.764
B54: Accounts Receivable | E54: 299.003
B55: Prepaid Expenses and Deposits | E55: 7.636
B56: Investment in Film and Television Programs | E56: 165.982
B57: Total Current Assets | E57: =SUM(E52:E56) -> 543.46
B59: LT receivables | E59: 95.827
B60: Acquired and library content | E60: 95.52
B61: Property, Plant & Equipment | E61: 38.039
B62: Derivative assets | E62: 11.864
B63: Intangible Assets | E63: 466.614
B64: Goodwill | E64: 55.484
B65: Total Assets | E65: =SUM(E59:E64)+E57 -> 1306.808
B67: Bank Indebtedness | E67: 21.392
B68: Accounts Payable and Accrued Liabilities | E68: 168.288
B69: Deferred Revenue | E69: 70.387
B70: Production Financing | E70: 112.527
B71: Current Portion of Lease Liabilities | E71: 10.208
B72: Current Portion of Long-Term Debt | E72: 29.51
B73: Total Current Liabilities | E73: =SUM(E67:E72) -> 412.312
B75: Long-Term Debt | E75: 501.258
B76: Long-Term Lease Liabilities | E76: 24.935
B77: Deferred Taxes | E77: 5.431
B78: Other Long-Term Liabilities (incl. derivatives) | E78: =(1764+19742)/1000 -> 21.506
B79: Total Liabilities | E79: =SUM(E75:E78)+E73 -> 965.442
B81: Equity to common | E81: 80.863
B82: NCI | E82: 260.503
B83: Total Equity | E83: =SUM(E81:E82) -> 341.366
B85: Balance | E85: =+E65=E79+E83 -> TRUE
B87: NWC (excl. investment in film and TV) | E87: =+SUM(E54:E55,E59)-SUM(E68:E69) -> 163.791
B88: NWC (incl. investment in film and TV) | E88: =+E87+E56 -> 329.773
B90: Total cash excl restricted cash | E90: =+E52 -> 62.075
B91: Total cash incl restricted cash | E91: =+E90+E53 -> 70.839
B93: Total debt excl lease | E93: =+E67+E72+E75+E70 -> 664.687
B94: Total debt incl lease | E94: =+E93+E71+E76 -> 699.83
B96: Net debt (excl restricted cash, incl leases) | E96: =+E94-E90 -> 637.755
A98: x | B98: CFS (based on FS)
B99: Net income for the year | E99: 3.738
B100: Amortization of property and equipment | E100: 2.709
B101: Amortization of intangible assets | E101: 3.565
B102: Amortization of acquired and library content | E102: 2.349
B103: Accretion expense and amortization of deferred financing fees | E103: 3.477
B104: Unrealized foreign exchange loss (gain) | E104: 24.322
B105: Share-based compensation | E105: 1.327
B106: Change in fair value of embedded derivatives | E106: -6.034
B107: Change in fair value of interest rate swap | E107: -3.019
B108: Interest income | E108: -1.303
B109: Interest expense | E109: 9.648
B110: Deferred tax recovery | E110: -1.545
... B115: Net change in non-cash balances related to operations (note 25) | E115: -57.303
B116: OCF | E116: =SUM(E99:E115) -> -23.324
B118: Acquisition of acquired and library content (note 5) | E118: -0.24
B119: Acquisition of property and equipment | E119: 0
B120: Acquisition of intangible assets | E120: -1.696
B121: Investing cash flow | E121: =SUM(E118:E120) -> -1.936
B123: Common shares issued, net of issuance costs | E123: 0.018
B124: Payroll taxes remitted on net share settlement | E124: 0
B125: Common share purchased held in trust, net | E125: -0.045
B126: Distributions to non-controlling interests | E126: -2.378
B127: Proceeds from (repayment of) bank indebtedness | E127: 12.305
B128: (Repayment of) proceeds from long-term debt | E128: -0.977
...

Sheet Reference
A1: in CADm unless otherwise stated
A2: FYE June
E4: FY2022 | F4: FY2023 | G4: FY2024 | H4: FY2025 | I4: FY2026 | J4: FY2027
A6: x | B6: Mgmt guidance
B7: Revenue | E7: CAD480 - 500m | F7: CAD525 - 575m
B8: Midpoint | E8: 490 | F8: 550
B10: Proportionate Adj EBITDA (co defined) | E10: CAD87 - 93m | F10: CAD95 - 105m
B11: Midpoint | E11: 90 | F11: 100
A13: x | B13: Street view
B14: Benchmark | E14: 498.75 | F14: 545.956 | G14: 600.17
B15: RBC | E15: 503.4 | F15: 543 | G15: 599 | H15: 640.2
B16: NBC | E16: 505.6 | F16: 550.8 | G16: 605.7 | H16: 640
B17: BMO | E17: 497 | F17: 538 | G17: 570
B18: Cannacord | E18: 509.9 | F18: 537.2 | G18: 593.4
B19: Comark | E19: 500.1 | F19: 530.3 | G19: 576.1
B20: Average revenue | E20: =+AVERAGE(E14:E19) -> 502.45833 | F20: =+AVERAGE(F14:F19) -> 540.876 | G20: =+AVERAGE(G14:G19) -> 590.72833 | H20: =+AVERAGE(H14:H19) -> 640.1
B21: Median revenue | E21: =+MEDIAN(E14:E19) -> 501.75 | F21: =+MEDIAN(F14:F19) -> 540.5 | G21: =+MEDIAN(G14:G19) -> 596.2 | H21: =+MEDIAN(H14:H19) -> 640.1
B23: Benchmark | E23: 88.26 | F23: 100.18 | G23: 113.15
B24: RBC | E24: 92.8 | F24: 93 | G24: 112 | H24: 123
B25: NBC | E25: 92.6 | F25: 99.7 | G25: 113.7
B26: BMO | E26: 93 | F26: 95 | G26: 102
B27: Cannacord | E27: 94.2 | F27: 100.2 | G27: 114.9
B28: Comark | E28: 91.82 | F28: 99.1 | G28: 108.8
B29: Average porportionate Adj EBITDA | E29: =+AVERAGE(E23:E28) -> 92.113333 | F29: =+AVERAGE(F23:F28) -> 97.863333 | G29: =+AVERAGE(G23:G28) -> 110.75833 | H29: =+AVERAGE(H23:H28) -> 123
B30: Median porportionate Adj EBITDA | E30: =+MEDIAN(E23:E28) -> 92.7 | F30: =+MEDIAN(F23:F28) -> 99.4 | G30: =+MEDIAN(G23:G28) -> 112.575 | H30: =+MEDIAN(H23:H28) -> 123
A32: x | B32: Actual / forecast
B33: Revenue | E33: =+'P&L'!I6 -> 507.223 | F33: =+'P&L'!J6 -> 526.48778 | G33: =+'P&L'!K6 -> 583.43796 | H33: =+'P&L'!L6 -> 653.37542 | I33: =+'P&L'!M6 -> 706.85889 | J33: =+'P&L'!N6 -> 751.51717
B34: Proportionate Adj EBITDA (co defined) | E34: =+'P&L'!I62 -> 88.75 | F34: =+'P&L'!J62 -> 96.804982 | G34: =+'P&L'!K62 -> 112.51033 | H34: =+'P&L'!L62 -> 128.36569 | I34: =+'P&L'!M62 -> 138.85141 | J34: =+'P&L'!N62 -> 147.01812
