Workbook

Sheet Assumptions
A1: 3S Model Drivers
A2: Assumptions & Drivers
A4: Fiscal Year | B4: FY2023 | C4: FY2024 | D4: FY2025 | E4: FY2026E | F4: FY2027E | G4: FY2028E
A6: Revenue Growth Assumptions
A7: Revenue Growth Rate | E7: 0.25 | F7: 0.2 | G7: 0.15
A9: Margin Assumptions
A10: Gross Margin | E10: 0.73 | F10: 0.72 | G10: 0.71
A11: R&D as % of Revenue | E11: 0.1 | F11: 0.1 | G11: 0.1
A12: SG&A as % of Revenue | E12: 0.03 | F12: 0.03 | G12: 0.03
A14: Other Assumptions
A15: Effective Tax Rate | E15: 0.12 | F15: 0.13 | G15: 0.14
A16: Depreciation as % of PP&E | E16: 0.2 | F16: 0.2 | G16: 0.2
A17: CapEx as % of Revenue | E17: 0.02 | F17: 0.02 | G17: 0.02
A19: Working Capital Assumptions
A20: Days Sales Outstanding (DSO) | E20: 45 | F20: 45 | G20: 45
A21: Days Inventory Outstanding (DIO) | E21: 90 | F21: 85 | G21: 80
A22: Days Payable Outstanding (DPO) | E22: 30 | F22: 30 | G22: 30

Sheet Income Statement
A1: Income Statement
A2: ($ in millions)
A4: Fiscal Year | D4: FY2025 | E4: FY2026E | F4: FY2027E | G4: FY2028E
A5: Revenue | D5: 130497 | E5: =D5*(1+Assumptions!E7) -> 163121.25 | F5: =E5*(1+Assumptions!F7) -> 195745.5 | G5: =F5*(1+Assumptions!G7) -> 225107.32
A6: Cost of Revenue | D6: 35312 | E6: =E5*(1-Assumptions!E10) -> 44042.738 | F6: =F5*(1-Assumptions!F10) -> 54808.74 | G6: =G5*(1-Assumptions!G10) -> 65281.124
A7: Gross Profit | D7: =D5-D6 -> 95185 | E7: =E5-E6 -> 119078.51 | F7: =F5-F6 -> 140936.76 | G7: =G5-G6 -> 159826.2
A8: Gross Margin % | D8: =D7/D5 -> 0.72940374 | E8: =E7/E5 -> 0.73 | F8: =F7/F5 -> 0.72 | G8: =G7/G5 -> 0.71
A10: Operating Expenses:
A11: Research & Development | D11: 12912 | E11: =E5*Assumptions!E11 -> 16312.125 | F11: =F5*Assumptions!F11 -> 19574.55 | G11: =G5*Assumptions!G11 -> 22510.732
A12: Selling, General & Admin | D12: 3667 | E12: =E5*Assumptions!E12 -> 4893.6375 | F12: =F5*Assumptions!F12 -> 5872.365 | G12: =G5*Assumptions!G12 -> 6753.2197
A13: Total Operating Expenses | D13: =D11+D12 -> 16579 | E13: =E11+E12 -> 21205.763 | F13: =F11+F12 -> 25446.915 | G13: =G11+G12 -> 29263.952
A15: Operating Income (EBIT) | D15: =D7-D13 -> 78606 | E15: =E7-E13 -> 97872.75 | F15: =F7-F13 -> 115489.85 | G15: =G7-G13 -> 130562.25
A16: Operating Margin % | D16: =D15/D5 -> 0.60235867 | E16: =E15/E5 -> 0.6 | F16: =F15/F5 -> 0.59 | G16: =G15/G5 -> 0.58
A18: Interest Income (Expense), net | D18: 1500 | E18: 1800 | F18: 2000 | G18: 2200
A19: Other Income (Expense) | D19: 500 | E19: 400 | F19: 400 | G19: 400
A21: Income Before Taxes | D21: =D15+D18+D19 -> 80606 | E21: =E15+E18+E19 -> 100072.75 | F21: =F15+F18+F19 -> 117889.85 | G21: =G15+G18+G19 -> 133162.25
A22: Income Tax Expense | D22: -8935 | E22: =-E21*Assumptions!E15 -> -12008.73 | F22: =-F21*Assumptions!F15 -> -15325.68 | G22: =-G21*Assumptions!G15 -> -18642.715
A24: Net Income | D24: =D21+D22 -> 71671 | E24: =E21+E22 -> 88064.02 | F24: =F21+F22 -> 102564.17 | G24: =G21+G22 -> 114519.53
A25: Net Margin % | D25: =D24/D5 -> 0.54921569 | E25: =E24/E5 -> 0.53986847 | F25: =F24/F5 -> 0.52396691 | G25: =G24/G5 -> 0.50873304
A27: Shares Outstanding (millions) | D27: 24610 | E27: 24500 | F27: 24400 | G27: 24300
A28: Earnings Per Share (EPS) | D28: =D24/D27 -> 2.9122714 | E28: =E24/E27 -> 3.5944498 | F28: =F24/F27 -> 4.2034494 | G28: =G24/G27 -> 4.712738

Sheet Balance Sheet
A1: Balance Sheet
A2: ($ in millions)
A4: Fiscal Year | D4: FY2025 | E4: FY2026E | F4: FY2027E | G4: FY2028E
A5: ASSETS
A6: Current Assets:
A7: Cash & Cash Equivalents | D7: 105627 | E7: =+'Cash Flow'!E27 -> #VALUE! | F7: =+'Cash Flow'!F27 -> #VALUE! | G7: =+'Cash Flow'!G27 -> #VALUE!
A8: Short-term Investments | D8: 34255 | E8: =+D8 -> 34255 | F8: =+E8 -> 34255 | G8: =+F8 -> 34255
A9: Accounts Receivable | D9: 17693 | E9: =+'Income Statement'!E5*Assumptions!E20/365 -> 20110.839 | F9: =+'Income Statement'!F5*Assumptions!F20/365 -> 24133.007
A10: Inventories | D10: 8669 | E10: =+'Income Statement'!E6*Assumptions!E21/365 -> 10859.853 | F10: =+'Income Statement'!F6*Assumptions!F21/365 -> 12763.679
A11: Other Current Assets | D11: 2468 | E11: =+D11 -> 2468 | F11: =+E11 -> 2468 | G11: =+F11 -> 2468
A12: Total Current Assets | D12: =SUM(D7:D11) -> 168712 | E12: =SUM(E7:E11) -> #VALUE! | F12: =SUM(F7:F11) -> #VALUE! | G12: =SUM(G7:G11) -> #VALUE!
A14: Non-Current Assets:
A15: Property, Plant & Equipment, net | D15: 5769 | E15: =D15+('Income Statement'!E5*Assumptions!E17)-D15*Assumptions!E16 -> 7877.625 | F15: =E15+('Income Statement'!F5*Assumptions!F17)-E15*Assumptions!F16 -> 10217.01
A16: Goodwill & Intangibles | D16: 4943 | E16: =+D16 -> 4943 | F16: =+E16 -> 4943 | G16: =+F16 -> 4943
A17: Other Non-Current Assets | D17: 21946 | E17: =+D17 -> 21946 | F17: =+E17 -> 21946 | G17: =+F17 -> 21946
A18: Total Non-Current Assets | D18: =SUM(D15:D17) -> 32658 | E18: =SUM(E15:E17) -> 34766.625 | F18: =SUM(F15:F17) -> 37106.01 | G18: =SUM(G15:G17) -> 26889
A20: TOTAL ASSETS | D20: =D12+D18 -> 201370 | E20: =E12+E18 -> #VALUE! | F20: =F12+F18 -> #VALUE! | G20: =G12+G18 -> #VALUE!
A22: LIABILITIES & EQUITY
A23: Current Liabilities:
A24: Accounts Payable | D24: 3546 | E24: =+'Income Statement'!E6*Assumptions!E22/365 -> 3619.951 | F24: =+'Income Statement'!F6*Assumptions!F22/365 -> 4504.8279
A25: Accrued Liabilities | D25: 13709 | E25: =+D25 -> 13709 | F25: =+E25 -> 13709 | G25: =+F25 -> 13709
A26: Deferred Revenue | D26: 985 | E26: =+D26 -> 985 | F26: =+E26 -> 985 | G26: =+F26 -> 985
A27: Short-term Debt | D27: 99 | E27: 100 | F27: 100 | G27: 100
A28: Total Current Liabilities | D28: =SUM(D24:D27) -> 18339 | E28: =SUM(E24:E27) -> 18413.951 | F28: =SUM(F24:F27) -> 19298.828 | G28: =SUM(G24:G27) -> 14794
A30: Non-Current Liabilities:
A31: Long-term Debt | D31: 8458 | E31: 8000 | F31: 7500 | G31: 7000
A32: Other Non-Current Liabilities | D32: 3719 | E32: =+D32 -> 3719 | F32: =+E32 -> 3719 | G32: =+F32 -> 3719
A33: Total Non-Current Liabilities | D33: =D31+D32 -> 12177 | E33: =E31+E32 -> 11719 | F33: =F31+F32 -> 11219 | G33: =G31+G32 -> 10719
A35: Total Liabilities | D35: =D28+D33 -> 30516 | E35: =E28+E33 -> 30132.951 | F35: =F28+F33 -> 30517.828 | G35: =G28+G33 -> 25513
A37: Shareholders' Equity:
A38: Common Stock & APIC | D38: 16377
A39: Retained Earnings | D39: 154544 | E39: =D39+'Income Statement'!E24-E43 -> 227608.02 | F39: =E39+'Income Statement'!F24-F43 -> 312172.19
A40: AOCI & Other | D40: -67 | E40: =+D40 -> -67 | F40: =+E40 -> -67 | G40: =+F40 -> -67
A41: Total Shareholders' Equity | D41: =SUM(D38:D40) -> 170854 | E41: =SUM(E38:E40) -> 227541.02 | F41: =SUM(F38:F40) -> 312105.19 | G41: =SUM(G38:G40) -> -67
A43: Dividends & Buybacks (estimate) | E43: 15000 | F43: 18000 | G43: 20000
A45: TOTAL LIABILITIES & EQUITY | D45: =D35+D41 -> 201370 | E45: =E35+E41 -> 257673.97 | F45: =F35+F41 -> 342623.01 | G45: =G35+G41 -> 25446
A47: Balance Check (Assets - L&E) | D47: =D20-D45 -> 0 | E47: =E20-E45 -> #VALUE! | F47: =F20-F45 -> #VALUE! | G47: =G20-G45 -> #VALUE!

Sheet Cash Flow
A1: Cash Flow Statement
A2: ($ in millions)
A4: Fiscal Year | D4: FY2025 | E4: FY2026E | F4: FY2027E | G4: FY2028E
A5: Operating Activities
A6: Net Income | E6: =+'Income Statement'!E24 -> 88064.02 | F6: =+'Income Statement'!F24 -> 102564.17 | G6: =+'Income Statement'!G24 -> 114519.53
A8: Adjustments:
A9: Depreciation & Amortization | E9: =D15*Assumptions!E16 -> 0 | F9: =E15*Assumptions!F16 -> 0
A10: Stock-Based Compensation | E10: 5000 | F10: 5500 | G10: 6000
A12: Changes in Working Capital:
A13: (Increase) Decrease in A/R | E13: =D9-E9 -> 0 | F13: =E9-F9 -> 0
A14: (Increase) Decrease in Inventory | E14: =D10-E10 -> -5000 | F14: =E10-F10 -> -500
A15: Increase (Decrease) in A/P | E15: =E24-D24 -> 0 | F15: =F24-E24 -> 0
A16: Other Working Capital Changes
A18: Net Cash from Operating Activities | E18: =E6+E9+E10+E13+E14+E15+E16 -> 88064.02 | F18: =F6+F9+F10+F13+F14+F15+F16 -> 107564.17 | G18: =G6+G9+G10+G13+G14+G15+G16 -> 120519.53
A20: Investing Activities
A21: Capital Expenditures | E21: =-'Income Statement'!E5*Assumptions!E17 -> -3262.425 | F21: =-'Income Statement'!F5*Assumptions!F17 -> -3914.91
A22: Net Cash from Investing Activities | E22: =+E21 -> -3262.425 | F22: =+F21 -> -3914.91 | G22: =+G21 -> 0
A24: Financing Activities
A25: Dividends & Share Repurchases | E25: =-'Balance Sheet'!E43 -> -15000 | F25: =-'Balance Sheet'!F43 -> -18000
A26: Debt & Other Financing | E26: =E31-D31+E27-D27 -> #VALUE! | F26: =F31-E31+F27-E27 -> #VALUE!
A27: Ending Cash & Equivalents | D27: =+'Balance Sheet'!D7 -> 105627 | E27: =D27+E18+E22+E25+E26 -> #VALUE! | F27: =E27+F18+F22+F25+F26 -> #VALUE! | G27: =F27+G18+G22+G25+G26 -> #VALUE!
A29: Free Cash Flow (CFO - CapEx) | E29: =E18+E21 -> 84801.595 | F29: =F18+F21 -> 103649.26 | G29: =G18+G21 -> 120519.53
