Workbook

Sheet Assumptions
A1: 3S Model Drivers
A2: Assumptions & Drivers
A4: Fiscal Year | B4: FY2023 | C4: FY2024 | D4: FY2025 | E4: FY2026E | F4: FY2027E | G4: FY2028E
A6: Revenue Growth Assumptions
A7: Revenue Growth Rate | E7: 0.25 | F7: 0.2 | G7: 0.15
A9: Margin Assumptions
A10: Gross Margin | E10: 0.73 | F10: 0.72 | G10: 0.71
A11: R&D as % of Revenue | E11: 0.1 | F11: 0.1 | G11: 0.1
A12: SG&A as % of Revenue | E12: 0.03 | F12: 0.03 | G12: 0.03
A14: Other Assumptions
A15: Effective Tax Rate | E15: 0.12 | F15: 0.13 | G15: 0.14
A16: Depreciation as % of PP&E | E16: 0.2 | F16: 0.2 | G16: 0.2
A17: CapEx as % of Revenue | E17: 0.02 | F17: 0.02 | G17: 0.02
A19: Working Capital Assumptions
A20: Days Sales Outstanding (DSO) | E20: 45 | F20: 45 | G20: 45
A21: Days Inventory Outstanding (DIO) | E21: 90 | F21: 85 | G21: 80
A22: Days Payable Outstanding (DPO) | E22: 30 | F22: 30 | G22: 30

Sheet Income Statement
A1: Income Statement
A2: ($ in millions)
A4: Fiscal Year | D4: FY2025 | E4: FY2026E | F4: FY2027E | G4: FY2028E
A5: Revenue | D5: 130497 | E5: =D5*(1+Assumptions!E7) | F5: =E5*(1+Assumptions!F7) | G5: =F5*(1+Assumptions!G7)
A6: Cost of Revenue | D6: 35312 | E6: =E5*(1-Assumptions!E10) | F6: =F5*(1-Assumptions!F10) | G6: =G5*(1-Assumptions!G10)
A7: Gross Profit | D7: =D5-D6 | E7: =E5-E6 | F7: =F5-F6 | G7: =G5-G6
A8: Gross Margin % | D8: =D7/D5 | E8: =E7/E5 | F8: =F7/F5 | G8: =G7/G5
A10: Operating Expenses:
A11: Research & Development | D11: 12912 | E11: =E5*Assumptions!E11 | F11: =F5*Assumptions!F11 | G11: =G5*Assumptions!G11
A12: Selling, General & Admin | D12: 3667 | E12: =E5*Assumptions!E12 | F12: =F5*Assumptions!F12 | G12: =G5*Assumptions!G12
A13: Total Operating Expenses | D13: =D11+D12 | E13: =E11+E12 | F13: =F11+F12 | G13: =G11+G12
A15: Operating Income (EBIT) | D15: =D7-D13 | E15: =E7-E13 | F15: =F7-F13 | G15: =G7-G13
A16: Operating Margin % | D16: =D15/D5 | E16: =E15/E5 | F16: =F15/F5 | G16: =G15/G5
A18: Interest Income (Expense), net | D18: 1500 | E18: 1800 | F18: 2000 | G18: 2200
A19: Other Income (Expense) | D19: 500 | E19: 400 | F19: 400 | G19: 400
A21: Income Before Taxes | D21: =D15+D18+D19 | E21: =E15+E18+E19 | F21: =F15+F18+F19 | G21: =G15+G18+G19
A22: Income Tax Expense | D22: -8935 | E22: =-E21*Assumptions!E15 | F22: =-F21*Assumptions!F15 | G22: =-G21*Assumptions!G15
A24: Net Income | D24: =D21+D22 | E24: =E21+E22 | F24: =F21+F22 | G24: =G21+G22
A25: Net Margin % | D25: =D24/D5 | E25: =E24/E5 | F25: =F24/F5 | G25: =G24/G5
A27: Shares Outstanding (millions) | D27: 24610 | E27: 24500 | F27: 24400 | G27: 24300
A28: Earnings Per Share (EPS) | D28: =D24/D27 | E28: =E24/E27 | F28: =F24/F27 | G28: =G24/G27

Sheet Balance Sheet
A1: Balance Sheet
A2: ($ in millions)
A4: Fiscal Year | D4: FY2025 | E4: FY2026E | F4: FY2027E | G4: FY2028E
A5: ASSETS
A6: Current Assets:
A7: Cash & Cash Equivalents | D7: =Cash Flow!D27 | E7: =+'Cash Flow'!E27 | F7: =+'Cash Flow'!F27 | G7: =+'Cash Flow'!G27
A8: Short-term Investments | D8: 34255 | E8: =+D8 | F8: =+E8 | G8: =+F8
A9: Accounts Receivable | D9: 17693
A10: Inventories | D10: 8669
A11: Other Current Assets | D11: 2468 | E11: =+D11 | F11: =+E11 | G11: =+F11
A12: Total Current Assets | D12: =SUM(D7:D11) | E12: =SUM(E7:E11) | F12: =SUM(F7:F11) | G12: =SUM(G7:G11)
A14: Non-Current Assets:
A15: Property, Plant & Equipment, net | D15: 5769
A16: Goodwill & Intangibles | D16: 4943 | E16: =+D16 | F16: =+E16 | G16: =+F16
A17: Other Non-Current Assets | D17: 21946 | E17: =+D17 | F17: =+E17 | G17: =+F17
A18: Total Non-Current Assets | D18: =SUM(D15:D17) | E18: =SUM(E15:E17) | F18: =SUM(F15:F17) | G18: =SUM(G15:G17)
A20: TOTAL ASSETS | D20: =D12+D18 | E20: =E12+E18 | F20: =F12+F18 | G20: =G12+G18
A22: LIABILITIES & EQUITY
A23: Current Liabilities:
A24: Accounts Payable | D24: 3546
A25: Accrued Liabilities | D25: 13709 | E25: =+D25 | F25: =+E25 | G25: =+F25
A26: Deferred Revenue | D26: 985 | E26: =+D26 | F26: =+E26 | G26: =+F26
A27: Short-term Debt | D27: 99 | E27: 100 | F27: 100 | G27: 100
A28: Total Current Liabilities | D28: =SUM(D24:D27) | E28: =SUM(E24:E27) | F28: =SUM(F24:F27) | G28: =SUM(G24:G27)
A30: Non-Current Liabilities:
A31: Long-term Debt | D31: 8458 | E31: 8000 | F31: 7500 | G31: 7000
A32: Other Non-Current Liabilities | D32: 3719 | E32: =+D32 | F32: =+E32 | G32: =+F32
A33: Total Non-Current Liabilities | D33: =D31+D32 | E33: =E31+E32 | F33: =F31+F32 | G33: =G31+G32
A35: Total Liabilities | D35: =SUM(D28:D34) | E35: =E28+E33 | F35: =F28+F33 | G35: =G28+G33
A37: Shareholders' Equity:
A38: Common Stock & APIC | D38: 16377
A39: Retained Earnings | D39: 154544
A40: AOCI & Other | D40: -67 | E40: =+D40 | F40: =+E40 | G40: =+F40
A41: Total Shareholders' Equity | D41: =SUM(D36:D40) | E41: =SUM(E38:E40) | F41: =SUM(F38:F40) | G41: =SUM(G38:G40)
A43: Dividends & Buybacks (estimate) | E43: 15000 | F43: 18000 | G43: 20000
A45: TOTAL LIABILITIES & EQUITY | D45: =D35+D41 | E45: =E35+E41 | F45: =F35+F41 | G45: =G35+G41
A47: Balance Check (Assets - L&E) | D47: =D20-D45 | E47: =E20-E45 | F47: =F20-F45 | G47: =G20-G45

Sheet Cash Flow
A1: Cash Flow Statement
A2: ($ in millions)
A4: Fiscal Year | D4: FY2025 | E4: FY2026E | F4: FY2027E | G4: FY2028E
A5: Operating Activities
A6: Net Income | E6: =+'Income Statement'!E24 | F6: =+'Income Statement'!F24 | G6: =+'Income Statement'!G24
A8: Adjustments:
A9: Depreciation & Amortization
A10: Stock-Based Compensation | E10: 5000 | F10: 5500 | G10: 6000
A12: Changes in Working Capital:
A13: (Increase) Decrease in A/R
A14: (Increase) Decrease in Inventory
A15: Increase (Decrease) in A/P
A16: Other Working Capital Changes
A18: Net Cash from Operating Activities | E18: =E4 + E5 + E6 + E7 + E8 + E9 + E10 + E11 + E12 + E13 + E14 + E15 + E16 + E17 | F18: =F6+F9+F10+F13+F14+F15+F16 | G18: =G6+G9+G10+G13+G14+G15+G16
A20: Investing Activities
A21: Capital Expenditures
A22: Net Cash from Investing Activities | E22: =E19 + E20 + E21 | F22: =+F21 | G22: =+G21
A24: Financing Activities
A25: Dividends & Share Repurchases
A26: Debt & Other Financing
A27: Ending Cash & Equivalents | D27: =+'Balance Sheet'!D7 | E27: =E23 + E24 + E25 + E26 | F27: =E27+F18+F22+F25+F26 | G27: =F27+G18+G22+G25+G26
A29: Free Cash Flow (CFO - CapEx) | E29: =E18+E21 | F29: =F18+F21 | G29: =G18+G21
