Workbook

Sheet Data
B2: Summary P&L
B3: (€m, FYE 31-Dec) | C3: 2017A | D3: 2018A | E3: 2019A | F3: 2020E
C4: GAAP | D4: GAAP | E4: IFRS | F4: IFRS
B5: Output
B6: AMS Europe | C6: 31.5 | D6: 32.4 | E6: 37.3 | F6: 53.946401
B7: ECS Europe | C7: 31 | D7: 32.9 | E7: 38.9 | F7: 42.650783
B8: Americas & Asia | C8: 18.6 | D8: 22.8 | E8: 28.3 | F8: 32.533501
B9: Others | C9: 62.8 | D9: 57.9 | E9: 42.6 | F9: 36.202339
B10: Total Output | C10: 143.9 | D10: 146 | E10: 147.1 | F10: 165.33302
B12: Gross profit
B13: AMS Europe | C13: 9.5 | D13: 9.2 | E13: 11.2 | F13: 15.564811
B14: ECS Europe | C14: 11.1 | D14: 10.3 | E14: 14.4 | F14: 15.21323
B15: Americas & Asia | C15: 4 | D15: 3.8 | E15: 5.4 | F15: 6.9185281
B16: Others | C16: 16 | D16: 15.6 | E16: 15 | F16: 14.528397
B17: Total Gross Profit | C17: 40.6 | D17: 38.9 | E17: 46 | F17: 52.224966
B19: Overheads and Other
B20: Personnel expenses | C20: -23.774162 | D20: -24.428558 | E20: -25.728552 | F20: -26.453284
B21: Other operating expenses | C21: -11.355504 | D21: -9.1910144 | E21: -9.1900621 | F21: -9.3418151
B22: Other operating income | C22: 1.9575444 | D22: 1.9168258 | E22: 1.9825992 | F22: 2.1493293
B23: Total Overheads and Other | C23: -33.172121 | D23: -31.702747 | E23: -32.936015 | F23: -33.64577
B25: EBITDA | C25: 7.4278788 | D25: 7.1972532 | E25: 13.063985 | F25: 18.579196
B27: Other items:
B28: D&A | C28: -3.2109359 | D28: -2.9779364 | E28: -5.5279112 | F28: -4.3133125
B29: Capex | C29: -2 | D29: -2.7 | E29: -2.8 | F29: -3.140329
B30: IFRS-16 leasing costs | C30: n.a. | D30: n.a. | E30: -1.4 | F30: -1.5701645
B31: Financial lease costs (IAS 17) | C31: n.a. | D31: -1 | E31: -1.4 | F31: -1.4
B32: Factoring (fees and interest) | C32: n.a. | D32: -1.4432411 | E32: -1.7267365 | F32: -1.9366145
B34: % Growth
B35: Total Output | C35: n.a. | D35: =+D10/C10-1 -> 0.014593468 | E35: =+E10/D10-1 -> 0.0075342466 | F35: =+F10/E10-1 -> 0.12394986
B36: Total Gross Profit | D36: =D17/C17-1 -> -0.041871921 | E36: =E17/D17-1 -> 0.18251928 | F36: =F17/E17-1 -> 0.13532535
B37: Total Overheads and Other | D37: =D23/C23-1 -> -0.044295459 | E37: =E23/D23-1 -> 0.038900995 | F37: =F23/E23-1 -> 0.021549491
B38: EBITDA | D38: =D25/C25-1 -> -0.031048658 | E38: =E25/D25-1 -> 0.81513481 | F38: =F25/E25-1 -> 0.42216917
B40: % of Total Output
B41: Total Gross Profit | C41: =+C17/C10 -> 0.28214038 | D41: =+D17/D10 -> 0.26643836 | E41: =+E17/E10 -> 0.31271244 | F41: =+F17/F10 -> 0.3158774
B42: Total Overheads and Other | C42: =C23/C10 -> -0.23052204 | D42: =D23/D10 -> -0.2171421 | E42: =E23/E10 -> -0.22390221 | F42: =F23/F10 -> -0.20350302
B43: EBITDA | C43: =C25/C10 -> 0.051618338 | D43: =D25/D10 -> 0.049296254 | E43: =E25/E10 -> 0.088810229 | F43: =F25/F10 -> 0.11237438
B45: Summary Balance sheet
B46: (€m) | D46: =D3 -> 2018A | E46: =E3 -> 2019A | F46: =F3 -> 2020E
B47: Assets
B48: Tangible assets(1) | D48: 3.0813375 | E48: 7.1965907 | F48: 7.4236071
B49: Intangible assets | D49: 44.430985 | E49: 46.330678 | F49: 46.330678
B50: Financial assets | D50: 5.5237092 | E50: 7.4368547 | F50: 8.3340342
B51: Inventories | D51: 4.8956701 | E51: 1.2501711 | F51: 0.95922502
B52: Trade receivables | D52: 14.432411 | E52: 17.267365 | F52: 19.366145
B53: Factor receivables(2) | D53: 1.4432411 | E53: 1.7267365 | F53: 1.9366145
B54: Cash | D54: 17.410773 | E54: 21.633166 | F54: 25.892916
B55: Deferred tax assets | D55: 2.4459022 | E55: 0.61386157 | F55: 0.68847402
B56: Other assets | D56: 1.9192558 | E56: 1.752548 | F56: 1.9655633
B57: Total | D57: 95.583285 | E57: 105.20797 | F57: 112.89726
B59: Liabilities
B60: Provisions(3) | D60: 5.8420197 | E60: 2.1252234 | F60: 4.8344713
B61: Bank debt | D61: 25.364503 | E61: 25.882796 | F61: 28.133635
B62: Shareholder loans | D62: 8.7 | E62: 13.279203 | F62: 15.139317
B63: Other financial liabilities | D63: 17.22571 | E63: 17.292548 | F63: 17.504447
B64: Financial lease liabilties (IAS 17) | D64: 1.2305627 | E64: 1.8583791 | F64: 1.8583791
B65: IFRS 16 leasing liabilities | D65: 0 | E65: 3.7733252 | F65: 3.7733252
B66: Trade payables | D66: 23.503779 | E66: 26.824981 | F66: 29.951474
B67: Deferred tax liabilities | D67: 0.56064377 | E67: 0.52455577 | F67: 0.58831346
B68: Accruals short term (tax and other provisions) | D68: 0.79652329 | E68: 1.0315279 | F68: 1.1569061
B69: Income tax liabilities | D69: 0.32406812 | E69: 1.1894241 | F69: 1.3339939
B70: Total | D70: 83.54781 | E70: 93.781962 | F70: 104.27426
B72: Net assets | D72: 12.035475 | E72: 11.42601 | F72: 8.6229954
B74: Due diligence findings:
B75: (1) Tangible asset base underinvested. DD estimated a capex underinvestment of c.€1.75m.
B76: (2) Non-recourse factoring of 50% of annual receivables. Terms include 80% cash upfront with 10% all-in interest cost (incl. discount and fees)
B77: (3) FY20E includes a management transaction bonus of €4.5m.

Sheet Model
B2: Reverse Logistics Group (RLG) - LBO Model (July 2020)
B4: €m, FY Dec | C4: 2017 | D4: 2018 | E4: 2019 | F4: 2020 | G4: 2021 | H4: 2022 | I4: 2023 | J4: 2024 | K4: 2025
B6: Key Assumptions (Inputs)
B7: Entry EV / EBITDA multiple | C7: 8
B8: Exit EV / EBITDA multiple | C8: 8
B9: Entry date (FY2020E base) | C9: 2020
B10: Exit year | C10: 2025
B11: Tax rate | C11: 0.25
B12: D&A as % of revenue | C12: 0.0261
B13: Capex as % of revenue (incl. catch-up) | C13: 0.03
B14: NWC as % of revenue (Trade WC) | C14: 0.03
B15: Transaction fees (% of EV) | C15: 0.02
B16: Financing fees (% of new debt) | C16: 0.02
B17: Revolver (max) | C17: 10
B18: Cash minimum | C18: 5
... B22: Amortization (% of opening senior debt) | C22: 0.05
B25: Revenue Growth Assumptions (CAGR 2020-2025)
B26: Europe AMS | C26: 0.07
B27: Europe ECS | C27: 0.05
B28: Americas & Asia | C28: 0.12
B29: Others | C29: -0.05
B31: Operating Forecast
B32: Revenue
B33: Europe AMS | C33: =Data!C6 -> 31.5 | D33: =Data!D6 -> 32.4 | E33: =Data!E6 -> 37.3 | F33: =Data!F6 -> 53.946401 | G33: =F33*(1+$C$26) -> 57.722649 | H33: =G33*(1+$C$26) -> 61.763235 | I33: =H33*(1+$C$26) -> 66.086661 | J33: =I33*(1+$C$26) -> 70.712727 | K33: =J33*(1+$C$26) -> 75.662618
B34: Europe ECS | C34: =Data!C7 -> 31 | D34: =Data!D7 -> 32.9 | E34: =Data!E7 -> 38.9 | F34: =Data!F7 -> 42.650783 | G34: =F34*(1+$C$27) -> 44.783322 | H34: =G34*(1+$C$27) -> 47.022488 | I34: =H34*(1+$C$27) -> 49.373613 | J34: =I34*(1+$C$27) -> 51.842293 | K34: =J34*(1+$C$27) -> 54.434408
B35: Americas & Asia | C35: =Data!C8 -> 18.6 | D35: =Data!D8 -> 22.8 | E35: =Data!E8 -> 28.3 | F35: =Data!F8 -> 32.533501 | G35: =F35*(1+$C$28) -> 36.437521 | H35: =G35*(1+$C$28) -> 40.810024 | I35: =H35*(1+$C$28) -> 45.707227 | J35: =I35*(1+$C$28) -> 51.192094 | K35: =J35*(1+$C$28) -> 57.335145
B36: Others | C36: =Data!C9 -> 62.8 | D36: =Data!D9 -> 57.9 | E36: =Data!E9 -> 42.6 | F36: =Data!F9 -> 36.202339 | G36: =F36*(1+$C$29) -> 34.392222 | H36: =G36*(1+$C$29) -> 32.672611 | I36: =H36*(1+$C$29) -> 31.03898 | J36: =I36*(1+$C$29) -> 29.487031 | K36: =J36*(1+$C$29) -> 28.01268
B37: Total Revenue | C37: =Data!C10 -> 143.9 | D37: =Data!D10 -> 146 | E37: =Data!E10 -> 147.1 | F37: =Data!F10 -> 165.33302 | G37: =SUM(G33:G36) -> 173.33571 | H37: =SUM(H33:H36) -> 182.26836 | I37: =SUM(I33:I36) -> 192.20648 | J37: =SUM(J33:J36) -> 203.23415 | K37: =SUM(K33:K36) -> 215.44485
B39: Cost of Sales (variable)
B40: Gross margin (based on 2020E) | C40: =Data!F17/Data!F10 -> 0.3158774
B41: COGS | C41: =-C37*(1-$C$40) -> -98.445242 | D41: =-D37*(1-$C$40) -> -99.881899 | E41: =-E37*(1-$C$40) -> -100.63443 | F41: =-F37*(1-$C$40) -> -113.10806 | G41: =-G37*(1-$C$40) -> -118.58288 | H41: =-H37*(1-$C$40) -> -124.6939 | I41: =-I37*(1-$C$40) -> -131.4928 | J41: =-J37*(1-$C$40) -> -139.03707 | K41: =-K37*(1-$C$40) -> -147.39069
B42: Gross Profit | C42: =C37+C41 -> 45.454758 | D42: =D37+D41 -> 46.118101 | E42: =E37+E41 -> 46.465566 | F42: =F37+F41 -> 52.224966 | G42: =G37+G41 -> 54.752835 | H42: =H37+H41 -> 57.574455 | I42: =I37+I41 -> 60.713684 | J42: =J37+J41 -> 64.197074 | K42: =K37+K41 -> 68.05416
B44: Operating Expenses (fixed / semi-fixed)
B45: Personnel expenses (% revenue) | C45: =Data!F20/Data!F10 -> -0.16
B46: Other operating expenses (% revenue) | C46: =Data!F21/Data!F10 -> -0.05650302
B47: Other operating income (% revenue) | C47: =Data!F22/Data!F10 -> 0.013
B49: Personnel expenses | C49: =C37*$C$45 -> -23.024 | D49: =D37*$C$45 -> -23.36 | E49: =E37*$C$45 -> -23.536 | F49: =F37*$C$45 -> -26.453284 | G49: =G37*$C$45 -> -27.733714 | H49: =H37*$C$45 -> -29.162937 | I49: =I37*$C$45 -> -30.753037 | J49: =J37*$C$45 -> -32.517463 | K49: =K37*$C$45 -> -34.471176
B50: Other operating expenses | C50: =C37*$C$46 -> -8.1307845 | D50: =D37*$C$46 -> -8.2494409 | E50: =E37*$C$46 -> -8.3115942 | F50: =F37*$C$46 -> -9.3418151 | G50: =G37*$C$46 -> -9.7939913 | H50: =H37*$C$46 -> -10.298713 | I50: =I37*$C$46 -> -10.860247 | J50: =J37*$C$46 -> -11.483343 | K50: =K37*$C$46 -> -12.173285
B51: Other operating income | C51: =C37*$C$47 -> 1.8707 | D51: =D37*$C$47 -> 1.898 | E51: =E37*$C$47 -> 1.9123 | F51: =F37*$C$47 -> 2.1493293 | G51: =G37*$C$47 -> 2.2533643 | H51: =H37*$C$47 -> 2.3694886 | I51: =I37*$C$47 -> 2.4986842 | J51: =J37*$C$47 -> 2.6420439 | K51: =K37*$C$47 -> 2.8007831
B52: Total Opex | C52: =SUM(C49:C51) -> -29.284085 | D52: =SUM(D49:D51) -> -29.711441 | E52: =SUM(E49:E51) -> -29.935294 | F52: =SUM(F49:F51) -> -33.64577 | G52: =SUM(G49:G51) -> -35.274341 | H52: =SUM(H49:H51) -> -37.092161 | I52: =SUM(I49:I51) -> -39.114599 | J52: =SUM(J49:J51) -> -41.358762 | K52: =SUM(K49:K51) -> -43.843678
B54: EBITDA | C54: =C42+C52 -> 16.170673 | D54: =D42+D52 -> 16.40666 | E54: =E42+E52 -> 16.530271 | F54: =F42+F52 -> 18.579196 | G54: =G42+G52 -> 19.478494 | H54: =H42+H52 -> 20.482294 | I54: =I42+I52 -> 21.599084 | J54: =J42+J52 -> 22.838311 | K54: =K42+K52 -> 24.210482
B55: D&A | C55: =-C37*$C$12 -> -3.75579 | D55: =-D37*$C$12 -> -3.8106 | E55: =-E37*$C$12 -> -3.83931 | F55: =-F37*$C$12 -> -4.3151919 | G55: =-G37*$C$12 -> -4.5240621 | H55: =-H37*$C$12 -> -4.7572041 | I55: =-I37*$C$12 -> -5.0165891 | J55: =-J37*$C$12 -> -5.3044112 | K55: =-K37*$C$12 -> -5.6231106
B56: EBIT | C56: =C54+C55 -> 12.414883 | D56: =D54+D55 -> 12.59606 | E56: =E54+E55 -> 12.690961 | F56: =F54+F55 -> 14.264004 | G56: =G54+G55 -> 14.954432 | H56: =H54+H55 -> 15.72509 | I56: =I54+I55 -> 16.582495 | J56: =J54+J55 -> 17.5339 | K56: =K54+K55 -> 18.587371
B57: Cash taxes | C57: =-MAX(0,C56)*$C$11 -> -3.1037209 | D57: =-MAX(0,D56)*$C$11 -> -3.1490149 | E57: =-MAX(0,E56)*$C$11 -> -3.1727404 | F57: =-MAX(0,F56)*$C$11 -> -3.5660011 | G57: =-MAX(0,G56)*$C$11 -> -3.7386079 | H57: =-MAX(0,H56)*$C$11 -> -3.9312724 | I57: =-MAX(0,I56)*$C$11 -> -4.1456238 | J57: =-MAX(0,J56)*$C$11 -> -4.383475 | K57: =-MAX(0,K56)*$C$11 -> -4.6468428
B58: NOPAT | C58: =C56+C57 -> 9.3111626 | D58: =D56+D57 -> 9.4470448 | E58: =E56+E57 -> 9.5182211 | F58: =F56+F57 -> 10.698003 | G58: =G56+G57 -> 11.215824 | H58: =H56+H57 -> 11.793817 | I58: =I56+I57 -> 12.436871 | J58: =J56+J57 -> 13.150425 | K58: =K56+K57 -> 13.940528
B60: Unlevered Free Cash Flow
B61: NOPAT | C61: =C58 -> 9.3111626 | D61: =D58 -> 9.4470448 | E61: =E58 -> 9.5182211 | F61: =F58 -> 10.698003 | G61: =G58 -> 11.215824 | H61: =H58 -> 11.793817 | I61: =I58 -> 12.436871 | J61: =J58 -> 13.150425 | K61: =K58 -> 13.940528
B62: + D&A | C62: =-C55 -> 3.75579 | D62: =-D55 -> 3.8106 | E62: =-E55 -> 3.83931 | F62: =-F55 -> 4.3151919 | G62: =-G55 -> 4.5240621 | H62: =-H55 -> 4.7572041 | I62: =-I55 -> 5.0165891 | J62: =-J55 -> 5.3044112 | K62: =-K55 -> 5.6231106
B63: - Capex | C63: =-C37*$C$13 -> -4.317 | D63: =-D37*$C$13 -> -4.38 | E63: =-E37*$C$13 -> -4.413 | F63: =-F37*$C$13 -> -4.9599907 | G63: =-G37*$C$13 -> -5.2000714 | H63: =-H37*$C$13 -> -5.4680507 | I63: =-I37*$C$13 -> -5.7661944 | J63: =-J37*$C$13 -> -6.0970244 | K63: =-K37*$C$13 -> -6.4633455
B64: - Change in NWC | C64: 0 | D64: =-(D37*$C$14-C37*$C$14) -> -0.063 | E64: =-(E37*$C$14-D37*$C$14) -> -0.033 | F64: =-(F37*$C$14-E37*$C$14) -> -0.54699072 | G64: =-(G37*$C$14-F37*$C$14) -> -0.24008071 | H64: =-(H37*$C$14-G37*$C$14) -> -0.26797929 | I64: =-(I37*$C$14-H37*$C$14) -> -0.29814369 | J64: =-(J37*$C$14-I37*$C$14) -> -0.33082995 | K64: =-(K37*$C$14-J37*$C$14) -> -0.36632116
B65: Unlevered FCF | C65: =SUM(C61:C64) -> 8.7499526 | D65: =SUM(D61:D64) -> 8.8146448 | E65: =SUM(E61:E64) -> 8.9115311 | F65: =SUM(F61:F64) -> 9.5062138 | G65: =SUM(G61:G64) -> 10.299734 | H65: =SUM(H61:H64) -> 10.814991 | I65: =SUM(I61:I64) -> 11.389122 | J65: =SUM(J61:J64) -> 12.026982 | K65: =SUM(K61:K64) -> 12.733972
B68: Valuation & EV-to-Equity Bridge (Entry)
B69: Entry EBITDA (2020E) | C69: =F54 -> 18.579196
B70: Entry EV / EBITDA | C70: =$C$7 -> 8
B71: Enterprise Value | C71: =C69*C70 -> 148.63357
B73: Less: Net Debt / (Cash)
B74: Bank debt | C74: =Data!F61 -> 28.133635
B75: Shareholder loans | C75: =Data!F62 -> 15.139317
B76: Other financial liabilities | C76: =Data!F63 -> 17.504447
B77: Lease liabilities (IAS17 + IFRS16) | C77: =Data!F64+Data!F65 -> 5.6317044
B78: Less: Cash | C78: =-Data!F53 -> -1.9366145
B79: Net Debt | C79: =SUM(C74:C78) -> 64.472489
B81: Equity Value (pre-fees) | C81: =C71-C79 -> 84.161081
B84: Sources & Uses
B85: Uses
B86: Equity purchase price | C86: =C81 -> 84.161081
B87: Transaction fees | C87: =C71*$C$15 -> 2.9726714
B88: Financing fees | C88: =(C93+C94)*$C$16 -> #VALUE!
B89: Total Uses | C89: =SUM(C86:C88) -> #VALUE!
B91: Sources
B92: Senior debt | C92: =C96*C69*$C$20 -> 7.4316785
B93: Subordinated debt | C93: =C96*C69*(1-$C$20) -> 85.464303
B94: Sponsor equity | C94: =C89-C92-C93 -> #VALUE!
B95: Total Sources | C95: =SUM(C92:C94) -> #VALUE!
B96: Total debt (x EBITDA) | C96: 5
B99: Debt Schedule & Equity Returns
B100: Senior debt - opening | C100: 0 | D100: 0 | E100: 0 | F100: =C92 -> 7.4316785 | G100: =F102 -> 7.4316785 | H100: =G102 -> 1.8579196 | I100: =H102 -> 0.46447991 | J100: =I102 -> 0.11611998 | K100: =J102 -> 0.029029994
B101: Senior debt - amortization | C101: 0 | D101: 0 | E101: 0 | F101: 0 | G101: =-MIN(G100*$C$21, G108) -> -5.5737589 | H101: =-MIN(H100*$C$21, H108) -> -1.3934397 | I101: =-MIN(I100*$C$21, I108) -> -0.34835993 | J101: =-MIN(J100*$C$21, J108) -> -0.087089983 | K101: =-MIN(K100*$C$21, K108) -> -0.021772496
B102: Senior debt - closing | C102: =C100+C101 -> 0 | D102: =D100+D101 -> 0 | E102: =E100+E101 -> 0 | F102: =F100+F101 -> 7.4316785 | G102: =G100+G101 -> 1.8579196 | H102: =H100+H101 -> 0.46447991 | I102: =I100+I101 -> 0.11611998 | J102: =J100+J101 -> 0.029029994 | K102: =K100+K101 -> 0.0072574986
B104: Sub debt - opening | C104: 0 | D104: 0 | E104: 0 | F104: =C93 -> 85.464303 | G104: =F106 -> 85.464303 | H104: =G106 -> 80.738328 | I104: =H106 -> 71.316776 | J104: =I106 -> 60.276014 | K104: =J106 -> 48.336122
B105: Sub debt - amortization | C105: 0 | D105: 0 | E105: 0 | F105: 0 | G105: =-MAX(0, MIN(G104, G108+G101)) -> -4.7259748 | H105: =-MAX(0, MIN(H104, H108+H101)) -> -9.4215517 | I105: =-MAX(0, MIN(I104, I108+I101)) -> -11.040763 | J105: =-MAX(0, MIN(J104, J108+J101)) -> -11.939892 | K105: =-MAX(0, MIN(K104, K108+K101)) -> -12.7122
B106: Sub debt - closing | C106: =C104+C105 -> 0 | D106: =D104+D105 -> 0 | E106: =E104+E105 -> 0 | F106: =F104+F105 -> 85.464303 | G106: =G104+G105 -> 80.738328 | H106: =H104+H105 -> 71.316776 | I106: =I104+I105 -> 60.276014 | J106: =J104+J105 -> 48.336122 | K106: =K104+K105 -> 35.623922
B108: Cash available for debt paydown | C108: =MAX(0,C65) -> 8.7499526 | D108: =MAX(0,D65) -> 8.8146448 | E108: =MAX(0,E65) -> 8.9115311 | F108: =MAX(0,F65) -> 9.5062138 | G108: =MAX(0,G65) -> 10.299734 | H108: =MAX(0,H65) -> 10.814991 | I108: =MAX(0,I65) -> 11.389122 | J108: =MAX(0,J65) -> 12.026982 | K108: =MAX(0,K65) -> 12.733972
B109: Interest expense | C109: =-(C100+C102)/2*$C$18-(C104+C106)/2*$C$19 -> 0 | D109: =-(D100+D102)/2*$C$18-(D104+D106)/2*$C$19 -> 0 | E109: =-(E100+E102)/2*$C$18-(E104+E106)/2*$C$19 -> 0 | F109: =-(F100+F102)/2*$C$18-(F104+F106)/2*$C$19 -> -41.431608 | G109: =-(G100+G102)/2*$C$18-(G104+G106)/2*$C$19 -> -27.379061 | H109: =-(H100+H102)/2*$C$18-(H104+H106)/2*$C$19 -> -9.6073765 | I109: =-(I100+I102)/2*$C$18-(I104+I106)/2*$C$19 -> -4.7413195 | J109: =-(J100+J102)/2*$C$18-(J104+J106)/2*$C$19 -> -3.0781783 | K109: =-(K100+K102)/2*$C$18-(K104+K106)/2*$C$19 -> -2.1897198
B110: Levered FCF (after interest) | C110: =C65+C109 -> 8.7499526 | D110: =D65+D109 -> 8.8146448 | E110: =E65+E109 -> 8.9115311 | F110: =F65+F109 -> -31.925394 | G110: =G65+G109 -> -17.079327 | H110: =H65+H109 -> 1.207615 | I110: =I65+I109 -> 6.647803 | J110: =J65+J109 -> 8.9488037 | K110: =K65+K109 -> 10.544253
B113: Exit & Returns (End of 2025)
B114: Exit EBITDA (2025) | C114: =K54 -> 24.210482
B115: Exit EV / EBITDA | C115: =$C$8 -> 8
B116: Exit Enterprise Value | C116: =C114*C115 -> 193.68385
B117: Less: Net Debt at exit | C117: =K102+K106-$C$17 -> 25.63118
B118: Exit Equity Value | C118: =C116-C117 -> 168.05268
B120: Sponsor equity invested | C120: =C94 -> #VALUE!
B121: Sponsor equity proceeds | C121: =C118 -> 168.05268
B122: MOIC | C122: =C121/C120 -> #VALUE!
B123: IRR
B126: IRR Sensitivities
B127: Entry x Exit Multiple (IRR %)
C128: Entry \ Exit | D128: 7 | E128: 8 | F128: 9
B129: 7 | C129: =((7*C114)-(K102+K106-$C$17))/(((7*C69)-C79)+(7*C69)*$C$15+((96*C69)*$C$16))^(1/5)-1 -> 55.833027 | D129: =((8*C114)-(K102+K106-$C$17))/(((7*C69)-C79)+(7*C69)*$C$15+((96*C69)*$C$16))^(1/5)-1 -> 65.398753 | E129: =((9*C114)-(K102+K106-$C$17))/(((7*C69)-C79)+(7*C69)*$C$15+((96*C69)*$C$16))^(1/5)-1 -> 74.964479
B130: 8 | C130: =((7*C114)-(K102+K106-$C$17))/(((8*C69)-C79)+(8*C69)*$C$15+((96*C69)*$C$16))^(1/5)-1 -> 53.959467 | D130: =((8*C114)-(K102+K106-$C$17))/(((8*C69)-C79)+(8*C69)*$C$15+((96*C69)*$C$16))^(1/5)-1 -> 63.209849 | E130: =((9*C114)-(K102+K106-$C$17))/(((8*C69)-C79)+(8*C69)*$C$15+((96*C69)*$C$16))^(1/5)-1 -> 72.460231
...
