Workbook
Name IQ_CH: 110000
Name IQ_CQ: 5000
Name IQ_CY: 10000
Name IQ_DAILY: 500000
Name IQ_FH: 100000
Name IQ_FQ: 500
Name IQ_FY: 1000
Name IQ_LTM: 2000
Name IQ_MONTH: 15000
Name IQ_NTM: 6000
Name IQ_WEEK: 50000
Name IQ_YTD: 3000

Sheet LBO
A1: as of 3Q2021
B2: Dave & Buster's (Public-to-Private) | Q2: Additional work / comments
B3: (in US$m unless otherwise stated)
A5: x | B5: Transaction Dashboard | E5: Last Close Price | F5: 39.82 | H5: Equity Purchase Price | I5: =F8 -> 2647.923
E6: FDSO (m) | F6: 49.257269 | H6: (-) Acquired BV | I6: =-G120 -> -153.232
B7: Sources | E7: Control Premium | F7: 0.35 | H7: (+) Existing Goodwill | I7: =G105 -> 272.597
B8: Existing Cash | C8: =G100 -> 11.891 | E8: Equity Purchase Price | F8: =F5*(1+F7)*F6 -> 2647.923 | H8: Pro Forma Goodwill | I8: =SUM(I5:I7) -> 2767.288
B9: Rollover Leases | C9: =G113 -> 1267.791 | E9: (+) Existing Debt | F9: =G114+G113 -> 1864.179
B10: Term Loan | C10: =I11*$I$18 -> 992.084 | E10: (-) Existing Cash | F10: =-G100 -> -11.891 | H10: Instrument | I10: xEBITDA | J10: Margin | K10: Floor | L10: DFF | M10: Amort | N10: PIK | O10: Sweep
B11: Senior Notes | C11: =I12*$I$18 -> 496.042 | E11: Acquisition EV | F11: =F8+F9 -> 4512.102 | H11: Term Loan | I11: 4 | J11: 400 | K11: 0.0125 | L11: 0.01 | M11: 0 | N11: 0 | O11: 1
B12: Common Equity | C12: =C24-SUM(C8:C11) -> 1787.4149 | E12: Implied LTM EBITDA Multiple | F12: =F11/I18 -> 18.192419 | H12: Senior Notes | I12: 2 | J12: 0.09 | L12: 0.01 | M12: 0 | N12: 0 | O12: 1
B13: o/w Sponsor | C13: =C12*(1-F17) -> 1698.0441 | E13: Implied FY22 EBITDA Multiple | F13: =F11/L92 -> 18.64984 | H13: RCF | I13: 0 | J13: 350 | K13: 0.0125
B14: o/w Management | C14: =C12*F17 -> 89.370744
B15: Total | C15: =SUM(C8:C12) -> 4555.2229 | E15: Hold Period | F15: 5 | H15: 9M21 Adjusted EBITDA | I15: 264.066
E16: Entry Date | F16: 44227 | H16: FY20 Adjusted EBITDA | I16: =K92 -> -81.273
B17: Uses | E17: Management Rollover | F17: 0.05 | H17: 9M20 Adjusted EBITDA | I17: -65.228
B18: EPP | C18: =F8 -> 2647.923 | E18: Sweet Equity Pot | F18: 0.05 | H18: LTM EBITDA | I18: =I15+I16-I17 -> 248.021
B19: Refi Debt | C19: =G114 -> 596.388 | E19: Cash Interest | F19: 0.01
B20: Rollover Leases | C20: =G113 -> 1267.791 | E20: Circularity Toggle | F20: 1
B21: Fund Cash Balance | C21: =F21 -> 15 | E21: Min. Cash Balance | F21: 15
B22: Financing Fees | C22: =SUMPRODUCT(L11:L12,C10:C11) -> 14.88126 | E22: Transaction Fees | F22: 0.005
B23: Transaction Fees | C23: =F22*C18 -> 13.239615 | E23: DFF Amortisation | F23: 8
B24: Total | C24: =SUM(C18:C23) -> 4555.2229
A26: x | B26: Operating Assumptions | I26: 2019 | J26: =I26+1 -> 2020 | K26: =J26+1 -> 2021 | L26: =K26+1 -> 2022 | M26: =L26+1 -> 2023 | N26: =M26+1 -> 2024 | O26: =N26+1 -> 2025 | P26: =O26+1 -> 2026 | R26: 9MFY22 | S26: Step-Up
B28: Number of Stores | H28: 106 | I28: 121 | J28: 136 | K28: 140 | L28: =K28+L29 -> 144 | M28: =L28+M29 -> 149 | N28: =M28+N29 -> 155 | O28: =N28+O29 -> 162 | P28: =O28+P29 -> 170
B29: New Stores | I29: =I28-H28 -> 15 | J29: =J28-I28 -> 15 | K29: =K28-J28 -> 4 | L29: 4 | M29: =L29+1+$S$29 -> 5 | N29: =M29+1 -> 6 | O29: =N29+1 -> 7 | P29: =O29+1 -> 8 | S29: 0
B30: F&B / Store | I30: =I63/I28 -> 4.4336281 | J30: =J63/J28 -> 4.1439412 | K30: =K63/K28 -> 1.1392929 | L30: =R30 -> 2.2132867 | M30: =L30+0.25+$S$30 -> 2.4632867 | N30: =M30+0.25 -> 2.7132867 | O30: =N30+0.25 -> 2.9632867 | P30: =O30+0.25 -> 3.2132867 | R30: =316.5/143 -> 2.2132867 | S30: 0
B31: Amusement / Store | I31: =I64/I28 -> 6.023405 | J31: =J64/J28 -> 5.8170221 | K31: =K64/K28 -> 1.97865 | L31: =R31 -> 4.5065944 | M31: =L31+0.25+$S$30 -> 4.7565944 | N31: =M31+0.25 -> 5.0065944 | O31: =N31+0.25 -> 5.2565944 | P31: =O31+0.25 -> 5.5065944 | R31: =644.443/143 -> 4.5065944
B32: COGS Spend - F&B | I32: =I67/I63 -> 0.25947259 | J32: =J67/J63 -> 0.26295655 | K32: =K67/K63 -> 0.28342769 | L32: 0.28 | M32: =L32 -> 0.28 | N32: =M32 -> 0.28 | O32: =N32 -> 0.28 | P32: =O32 -> 0.28 | R32: =86.366/316.5 -> 0.27287836
B33: COGS Spend - Amusement | I33: =I68/I64 -> 0.11122453 | J33: =J68/J64 -> 0.10758866 | K33: =K68/K64 -> 0.10720874 | L33: 0.1 | M33: =L33 -> 0.1 | N33: =M33 -> 0.1 | O33: =N33 -> 0.1 | P33: =O33 -> 0.1 | R33: =63.729/644.443 -> 0.098890049
B34: SG&A Spend | I34: =I71/I65 -> 0.58689592 | J34: =J71/J65 -> 0.60668448 | K34: =K71/K65 -> 1.0633247 | L34: 0.6 | M34: 0.595 | N34: 0.59 | O34: 0.58 | P34: 0.57 | R34: 0.5832173
B35: SBC / Sales | I35: =I88/I65 -> 0.0058657979 | J35: =J88/J65 -> 0.0050616709 | K35: =K88/K65 -> 0.016001851 | L35: =AVERAGE(I35:J35) -> 0.0054637344 | M35: =L35 -> 0.0054637344 | N35: =M35 -> 0.0054637344 | O35: =N35 -> 0.0054637344 | P35: =O35 -> 0.0054637344
B36: Pre-Opening Cost / Sales | I36: =I89/I65 -> 0.018306316 | J36: =J89/J65 -> 0.014003932 | K36: =K89/K65 -> 0.02583205 | L36: =AVERAGE(I36:J36) -> 0.016155124 | M36: =L36 -> 0.016155124 | N36: =M36 -> 0.016155124 | O36: =N36 -> 0.016155124 | P36: =O36 -> 0.016155124
B37: D&A Spend | I37: =I72/I65 -> 0.093475782 | J37: =J72/J65 -> 0.097778755 | K37: =K72/K65 -> 0.31795002 | L37: 0.12 | M37: 0.095 | N37: 0.095 | O37: 0.095 | P37: 0.095
B38: Effective Tax Rate | I38: =I81 -> 0.20736103 | J38: =J81 -> 0.21140929 | K38: =K81 -> 0.28729434 | L38: 0.21 | M38: =L38 -> 0.21 | N38: =M38 -> 0.21 | O38: =N38 -> 0.21 | P38: =O38 -> 0.21
B40: Maintenance Capex | I40: =29+22.5 -> 51.5 | J40: =19+22 -> 41 | K40: 19 | L40: =L41*L65 -> 33.868201 | M40: =M41*M65 -> 37.65168 | N40: =N41*N65 -> 41.880355 | O40: =O41*O65 -> 46.606726 | P40: =P41*P65 -> 51.883293
B41: Maintenance Capex / Sales | I41: =I40/I65 -> 0.040701778 | J41: =J40/J65 -> 0.030265204 | K41: =K40/K65 -> 0.043526868 | L41: 0.035 | M41: 0.035 | N41: 0.035 | O41: 0.035 | P41: 0.035
B42: Growth Capex | I42: 164.5 | J42: 187 | K42: 64 | L42: =+L43*L29 -> 46.866667 | M42: =+M43*M29 -> 58.583333 | N42: =+N43*N29 -> 70.3 | O42: =+O43*O29 -> 82.016667 | P42: =+P43*P29 -> 93.733333
B43: Growth Capex / New Stores | I43: =I42/I29 -> 10.966667 | J43: =J42/J29 -> 12.466667 | K43: =K42/K29 -> 16 | L43: =AVERAGE(I43:J43) -> 11.716667 | M43: =L43 -> 11.716667 | N43: =M43 -> 11.716667 | O43: =N43 -> 11.716667 | P43: =O43 -> 11.716667
B44: Total Capex | I44: =I40+I42 -> 216 | J44: =J40+J42 -> 228 | K44: =K40+K42 -> 83 | L44: =L40+L42 -> 80.734868 | M44: =M40+M42 -> 96.235013 | N44: =N40+N42 -> 112.18036 | O44: =O40+O42 -> 128.62339 | P44: =P40+P42 -> 145.61663
B46: Inventory Days | J46: =F101/J69*365 -> 53.937041 | K46: =G101/K69*365 -> 116.00768 | L46: =J46 -> 53.937041 | M46: =L46 -> 53.937041 | N46: =M46 -> 53.937041 | O46: =N46 -> 53.937041 | P46: =O46 -> 53.937041
B47: OCA / Sales | J47: =F102/J65 -> 0.014649097 | K47: =G102/K65 -> 0.19054001 | L47: =J47 -> 0.014649097 | M47: =L47 -> 0.014649097 | N47: =M47 -> 0.014649097 | O47: =N47 -> 0.014649097 | P47: =O47 -> 0.014649097
B48: Payable Days | J48: =F110/J69*365 -> 102.24994 | K48: =G110/K69*365 -> 177.37134 | L48: =J48 -> 102.24994 | M48: =L48 -> 102.24994 | N48: =M48 -> 102.24994 | O48: =N48 -> 102.24994 | P48: =O48 -> 102.24994
B49: Accrued Liabilities / Sales | J49: =F111/J65 -> 0.15313603 | K49: =G111/K65 -> 0.53787754 | L49: =J49 -> 0.15313603 | M49: =L49 -> 0.15313603 | N49: =M49 -> 0.15313603 | O49: =N49 -> 0.15313603 | P49: =O49 -> 0.15313603
B50: OCL / Sales | J50: =F112/J65 -> 0.0022543886 | K50: =G112/K65 -> 0.0010217359 | L50: =J50 -> 0.0022543886 | M50: =L50 -> 0.0022543886 | N50: =M50 -> 0.0022543886 | O50: =N50 -> 0.0022543886 | P50: =O50 -> 0.0022543886
B52: BoP DFF | L52: =K54 -> 14.88126 | M52: =L54 -> 13.021103 | N52: =M54 -> 11.160945 | O52: =N54 -> 9.3007875 | P52: =O54 -> 7.44063
B53: (-) Amortisation | L53: =-$C$22/$F$23 -> -1.8601575 | M53: =-$C$22/$F$23 -> -1.8601575 | N53: =-$C$22/$F$23 -> -1.8601575 | O53: =-$C$22/$F$23 -> -1.8601575 | P53: =-$C$22/$F$23 -> -1.8601575
B54: EoP DFF | K54: =K106 -> 14.88126 | L54: =SUM(L52:L53) -> 13.021103 | M54: =SUM(M52:M53) -> 11.160945 | N54: =SUM(N52:N53) -> 9.3007875 | O54: =SUM(O52:O53) -> 7.44063 | P54: =SUM(P52:P53) -> 5.5804725
B56: BoP PP&E | L56: =K59 -> 815.027 | M56: =L59 -> 779.64232 | N56: =M59 -> 773.67992 | O56: =N59 -> 772.18502 | P56: =O59 -> 774.30445
B57: (+) Capex | L57: =L44 -> 80.734868 | M57: =M44 -> 96.235013 | N57: =N44 -> 112.18036 | O57: =O44 -> 128.62339 | P57: =P44 -> 145.61663
B58: (-) D&A | L58: =-L37*L65 -> -116.11955 | M58: =-M37*M65 -> -102.19742 | N58: =-N37*N65 -> -113.67525 | O58: =-O37*O65 -> -126.50397 | P58: =-P37*P65 -> -140.82608
B59: EoP PP&E | K59: =K103 -> 815.027 | L59: =SUM(L56:L58) -> 779.64232 | M59: =SUM(M56:M58) -> 773.67992 | N59: =SUM(N56:N58) -> 772.18502 | O59: =SUM(O56:O58) -> 774.30445 | P59: =SUM(P56:P58) -> 779.09499
A61: x | B61: Income Statement | I61: 2019 | J61: =I61+1 -> 2020 | K61: =J61+1 -> 2021 | L61: =K61+1 -> 2022 | M61: =L61+1 -> 2023 | N61: =M61+1 -> 2024 | O61: =N61+1 -> 2025 | P61: =O61+1 -> 2026
B63: Food and beverage revenues | I63: 536.469 | J63: 563.576 | K63: 159.501 | L63: =L28*L30 -> 318.71329 | M63: =M28*M30 -> 367.02972 | N63: =N28*N30 -> 420.55944 | O63: =O28*O30 -> 480.05245 | P63: =P28*P30 -> 546.25874
B64: Amusement and other revenues | I64: 728.832 | J64: 791.115 | K64: 277.011 | L64: =L28*L31 -> 648.94959 | M64: =M28*M31 -> 708.73257 | N64: =N28*N31 -> 776.02213 | O64: =O28*O31 -> 851.56829 | P64: =P28*P31 -> 936.12105
B65: Total revenues | I65: =SUM(I63:I64) -> 1265.301 | J65: =SUM(J63:J64) -> 1354.691 | K65: =SUM(K63:K64) -> 436.512 | L65: =SUM(L63:L64) -> 967.66288 | M65: =SUM(M63:M64) -> 1075.7623 | N65: =SUM(N63:N64) -> 1196.5816 | O65: =SUM(O63:O64) -> 1331.6207 | P65: =SUM(P63:P64) -> 1482.3798
B66: % growth | J66: =J65/I65-1 -> 0.070647221 | K66: =K65/J65-1 -> -0.67777744 | L66: =L65/K65-1 -> 1.2168071 | M66: =M65/L65-1 -> 0.11171184 | N66: =N65/M65-1 -> 0.11231039 | O66: =O65/N65-1 -> 0.11285413 | P66: =P65/O65-1 -> 0.1132147
B67: Cost of food and beverage | I67: 139.199 | J67: 148.196 | K67: 45.207 | L67: =L32*L63 -> 89.23972 | M67: =M32*M63 -> 102.76832 | N67: =N32*N63 -> 117.75664 | O67: =O32*O63 -> 134.41469 | P67: =P32*P63 -> 152.95245
B68: Cost of amusement and other | I68: 81.064 | J68: 85.115 | K68: 29.698 | L68: =L33*L64 -> 64.894959 | M68: =M33*M64 -> 70.873257 | N68: =N33*N64 -> 77.602213 | O68: =O33*O64 -> 85.156829 | P68: =P33*P64 -> 93.612105
B69: Total cost of products | I69: =SUM(I67:I68) -> 220.263 | J69: =SUM(J67:J68) -> 233.311 | K69: =SUM(K67:K68) -> 74.905 | L69: =SUM(L67:L68) -> 154.13468 | M69: =SUM(M67:M68) -> 173.64158 | N69: =SUM(N67:N68) -> 195.35886 | O69: =SUM(O67:O68) -> 219.57151 | P69: =SUM(P67:P68) -> 246.56455
B70: % margin | I70: =I69/I$65 -> 0.17407953 | J70: =J69/J$65 -> 0.17222451 | K70: =K69/K$65 -> 0.17159895 | L70: =L69/L$65 -> 0.15928551 | M70: =M69/M$65 -> 0.16141259 | N70: =N69/N$65 -> 0.16326414 | O70: =O69/O$65 -> 0.16489043 | P70: =P69/P$65 -> 0.16633022
B71: SG&A | I71: 742.6 | J71: 821.87 | K71: 464.154 | L71: =L34*L65 -> 580.59773 | M71: =M34*M65 -> 640.07856 | N71: =N34*N65 -> 705.98313 | O71: =O34*O65 -> 772.34003 | P71: =P34*P65 -> 844.95648
B72: Depreciation and amortization expense | I72: 118.275 | J72: 132.46 | K72: 138.789 | L72: =L37*L65 -> 116.11955 | M72: =M37*M65 -> 102.19742 | N72: =N37*N65 -> 113.67525 | O72: =O37*O65 -> 126.50397 | P72: =P37*P65 -> 140.82608
B73: DFF Amortisation | I73: 0 | J73: 0 | K73: 0 | L73: =L53 -> -1.8601575 | M73: =M53 -> -1.8601575 | N73: =N53 -> -1.8601575 | O73: =O53 -> -1.8601575 | P73: =P53 -> -1.8601575
B74: Pre-opening costs | I74: 23.163 | J74: 18.971 | K74: 11.276 | L74: =L36*L65 -> 15.632714 | M74: =M36*M65 -> 17.379073 | N74: =N36*N65 -> 19.330923 | O74: =O36*O65 -> 21.512498 | P74: =P36*P65 -> 23.948029
B75: Operating income (loss) | I75: =I65-I69-SUM(I71:I74) -> 161 | J75: =J65-J69-SUM(J71:J74) -> 148.079 | K75: =K65-K69-SUM(K71:K74) -> -252.612 | L75: =L65-L69-SUM(L71:L74) -> 103.03837 | M75: =M65-M69-SUM(M71:M74) -> 144.32582 | N75: =N65-N69-SUM(N71:N74) -> 164.09357 | O75: =O65-O69-SUM(O71:O74) -> 193.55289 | P75: =P65-P69-SUM(P71:P74) -> 227.94481
B76: % margin | I76: =I75/I$65 -> 0.12724245 | J76: =J75/J$65 -> 0.10930832 | K76: =K75/K$65 -> -0.57870574 | L76: =L75/L$65 -> 0.10648168 | M76: =M75/M$65 -> 0.13416144 | N76: =N75/N$65 -> 0.1371353 | O76: =O75/O$65 -> 0.14535136 | P76: =P75/P$65 -> 0.1537695
B77: Interest expense, net | I77: 13.113 | J77: 20.937 | K77: 36.89 | L77: =IF($F$20=1,L177,0) -> 95.659165 | M77: =IF($F$20=1,M177,0) -> 95.364631 | N77: =IF($F$20=1,N177,0) -> 93.55837 | O77: =IF($F$20=1,O177,0) -> 90.215274 | P77: =IF($F$20=1,P177,0) -> 84.662797
B78: Loss on debt refinance | I78: 0 | J78: 0 | K78: 0.904 | L78: 0 | M78: 0 | N78: 0 | O78: 0 | P78: 0
B79: Income (loss) before provision (benefit) for income taxes | I79: =I75-SUM(I77:I78) -> 147.887 | J79: =J75-SUM(J77:J78) -> 127.142 | K79: =K75-SUM(K77:K78) -> -290.406 | L79: =L75-SUM(L77:L78) -> 7.3792054 | M79: =M75-SUM(M77:M78) -> 48.961184 | N79: =N75-SUM(N77:N78) -> 70.535203 | O79: =O75-SUM(O77:O78) -> 103.33761 | P79: =P75-SUM(P77:P78) -> 143.28201
B80: Provision (benefit) for income taxes | I80: 30.666 | J80: 26.879 | K80: -83.432 | L80: =L38*L79 -> 1.5496331 | M80: =M38*M79 -> 10.281849 | N80: =N38*N79 -> 14.812393 | O80: =O38*O79 -> 21.700898 | P80: =P38*P79 -> 30.089222
B81: % ETR | I81: =I80/I79 -> 0.20736103 | J81: =J80/J79 -> 0.21140929 | K81: =K80/K79 -> 0.28729434 | L81: =L80/L79 -> 0.21 | M81: =M80/M79 -> 0.21 | N81: =N80/N79 -> 0.21 | O81: =O80/O79 -> 0.21 | P81: =P80/P79 -> 0.21
B82: Net income (loss) | I82: =I79-I80 -> 117.221 | J82: =J79-J80 -> 100.263 | K82: =K79-K80 -> -206.974 | L82: =L79-L80 -> 5.8295722 | M82: =M79-M80 -> 38.679336 | N82: =N79-N80 -> 55.72281 | O82: =O79-O80 -> 81.636713 | P82: =P79-P80 -> 113.19279
B83: % margin | I83: =I82/I$65 -> 0.092642778 | J83: =J82/J$65 -> 0.074011712 | K83: =K82/K$65 -> -0.4741542 | L83: =L82/L$65 -> 0.0060243834 | M83: =M82/M$65 -> 0.035955281 | N83: =N82/N$65 -> 0.046568334 | O83: =O82/O$65 -> 0.061306279 | P83: =P82/P$65 -> 0.07635883
B85: EBITDA | I85: =I82+I77+I78+I80+I72 -> 279.275 | J85: =J82+J77+J78+J80+J72 -> 280.539 | K85: =K82+K77+K78+K80+K72 -> -113.823 | L85: =L82+L77+L78+L80+L72 -> 219.15792 | M85: =M82+M77+M78+M80+M72 -> 246.52323 | N85: =N82+N77+N78+N80+N72 -> 277.76882 | O85: =O82+O77+O78+O80+O72 -> 320.05686 | P85: =P82+P77+P78+P80+P72 -> 368.77089
B86: Loss on asset disposal | I86: 1.121 | J86: 1.813 | K86: 0.577 | L86: 0 | M86: 0 | N86: 0 | O86: 0 | P86: 0
B87: Impairment of long-lived assets and lease termination costs | I87: 0 | J87: 0 | K87: 13.727 | L87: 0 | M87: 0 | N87: 0 | O87: 0 | P87: 0
B88: Share-based compensation | I88: 7.422 | J88: 6.857 | K88: 6.985 | L88: =L35*L65 -> 5.287053 | M88: =M35*M65 -> 5.8776794 | N88: =N35*N65 -> 6.5378039 | O88: =O35*O65 -> 7.2756221 | P88: =P35*P65 -> 8.0993295
B89: Pre-opening costs | I89: =I74 -> 23.163 | J89: =J74 -> 18.971 | K89: =K74 -> 11.276 | L89: =L74 -> 15.632714 | M89: =M74 -> 17.379073 | N89: =N74 -> 19.330923 | O89: =O74 -> 21.512498 | P89: =P74 -> 23.948029
B90: Other costs | I90: 0.136 | J90: 0.042 | K90: -0.015 | L90: 0 | M90: 0 | N90: 0 | O90: 0 | P90: 0
B91: DFF Amortisation | I91: =-I73 -> 0 | J91: =-J73 -> 0 | K91: =-K73 -> 0 | L91: =-L73 -> 1.8601575 | M91: =-M73 -> 1.8601575 | N91: =-N73 -> 1.8601575 | O91: =-O73 -> 1.8601575 | P91: =-P73 -> 1.8601575
B92: Adjusted EBITDA | I92: =SUM(I85:I91) -> 311.117 | J92: =SUM(J85:J91) -> 308.222 | K92: =SUM(K85:K91) -> -81.273 | L92: =SUM(L85:L91) -> 241.93784 | M92: =SUM(M85:M91) -> 271.64014 | N92: =SUM(N85:N91) -> 305.49771 | O92: =SUM(O85:O91) -> 350.70513 | P92: =SUM(P85:P91) -> 402.6784
B93: % margin | I93: =I92/I$65 -> 0.24588379 | J93: =J92/J$65 -> 0.227522 | K93: =K92/K$65 -> -0.18618732 | L93: =L92/L$65 -> 0.25002286 | M93: =M92/M$65 -> 0.25250945 | N93: =N92/N$65 -> 0.25530872 | O93: =O92/O$65 -> 0.26336713 | P93: =P92/P$65 -> 0.27164321
B95: NOPAT | I95: =(I92-I72)*(1-I81) -> 152.85409 | J95: =(J92-J72)*(1-J81) -> 138.60428 | K95: =(K92-K72)*(1-K81) -> -156.83943 | L95: =(L92-L72)*(1-L81) -> 99.396453 | M95: =(M92-M72)*(1-M81) -> 133.85975 | N95: =(N92-N72)*(1-N81) -> 151.53974 | O95: =(O92-O72)*(1-O81) -> 177.11892 | P95: =(P92-P72)*(1-P81) -> 206.86333
B96: % margin | I96: =I95/I$65 -> 0.12080452 | J96: =J95/J$65 -> 0.10231431 | K96: =K95/K$65 -> -0.35930154 | L96: =L95/L$65 -> 0.10271806 | M96: =M95/M$65 -> 0.12443246 | N96: =N95/N$65 -> 0.12664389 | O96: =O95/O$65 -> 0.13301003 | P96: =P95/P$65 -> 0.13954813
A98: x | B98: Balance Sheet | F98: 2020 | G98: =F98+1 -> 2021 | I98: Debit | J98: Credit | K98: PF FY2021 | L98: =G98+1 -> 2022 | M98: =L98+1 -> 2023 | N98: =M98+1 -> 2024 | O98: =N98+1 -> 2025 | P98: =O98+1 -> 2026
B100: Cash and cash equivalents | F100: 24.655 | G100: 11.891 | I100: =F21 -> 15 | J100: =G100 -> 11.891 | K100: =G100+I100-J100 -> 15 | L100: =IF($F$20=1,L150,0) -> 15 | M100: =IF($F$20=1,M150,0) -> 15 | N100: =IF($F$20=1,N150,0) -> 15 | O100: =IF($F$20=1,O150,0) -> 15 | P100: =IF($F$20=1,P150,0) -> 15
B101: Inventories | F101: 34.477 | G101: 23.807 | K101: =G101+I101-J101 -> 23.807 | L101: =L46*L69/365 -> 22.7769 | M101: =M46*M69/365 -> 25.659488 | N101: =N46*N69/365 -> 28.868709 | O101: =O46*O69/365 -> 32.446679 | P101: =P46*P69/365 -> 36.435513
B102: Other current assets | F102: 19.845 | G102: 83.173 | K102: =G102+I102-J102 -> 83.173 | L102: =L47*L65 -> 14.175388 | M102: =M47*M65 -> 15.758946 | N102: =N47*N65 -> 17.52884 | O102: =O47*O65 -> 19.507042 | P102: =P47*P65 -> 21.715525
B103: PP&E | F103: 900.637 | G103: 815.027 | K103: =G103+I103-J103 -> 815.027 | L103: =L59 -> 779.64232 | M103: =M59 -> 773.67992 | N103: =N59 -> 772.18502 | O103: =O59 -> 774.30445 | P103: =P59 -> 779.09499
B104: Operating Leases | F104: 1011.568 | G104: 1037.569 | K104: =G104+I104-J104 -> 1037.569 | L104: =K104 -> 1037.569 | M104: =L104 -> 1037.569 | N104: =M104 -> 1037.569 | O104: =N104 -> 1037.569 | P104: =O104 -> 1037.569 | Q104: << assumed future increase offset by repayments
B105: Goodwill | F105: 272.636 | G105: 272.597 | I105: =I8 -> 2767.288 | J105: =G105 -> 272.597 | K105: =G105+I105-J105 -> 2767.288 | L105: =K105 -> 2767.288 | M105: =L105 -> 2767.288 | N105: =M105 -> 2767.288 | O105: =N105 -> 2767.288 | P105: =O105 -> 2767.288
B106: Deferred Financing Fees | F106: 0 | G106: 0 | I106: =C22 -> 14.88126 | K106: =G106+I106-J106 -> 14.88126 | L106: =K106+L73 -> 13.021103 | M106: =L106+M73 -> 11.160945 | N106: =M106+N73 -> 9.3007875 | O106: =N106+O73 -> 7.44063 | P106: =O106+P73 -> 5.5804725
B107: Other Non-Current Assets | F107: 106.321 | G107: 108.76 | K107: =G107+I107-J107 -> 108.76 | L107: =K107 -> 108.76 | M107: =L107 -> 108.76 | N107: =M107 -> 108.76 | O107: =N107 -> 108.76 | P107: =O107 -> 108.76
B108: Total Assets | F108: =SUM(F100:F107) -> 2370.139 | G108: =SUM(G100:G107) -> 2352.824 | K108: =SUM(K100:K107) -> 4865.5053 | L108: =SUM(L100:L107) -> 4758.2327 | M108: =SUM(M100:M107) -> 4754.8763 | N108: =SUM(N100:N107) -> 4756.5004 | O108: =SUM(O100:O107) -> 4762.3158 | P108: =SUM(P100:P107) -> 4771.4435
B110: Accounts payable | F110: 65.359 | G110: 36.4 | K110: =G110+J110-I110 -> 36.4 | L110: =L48*L69/365 -> 43.178798 | M110: =M48*M69/365 -> 48.643398 | N110: =N48*N69/365 -> 54.727208 | O110: =O48*O69/365 -> 61.510064 | P110: =P48*P69/365 -> 69.071808
B111: Accrued liabilities | F111: 207.452 | G111: 234.79 | K111: =G111+J111-I111 -> 234.79 | L111: =L49*L65 -> 148.18405 | M111: =M49*M65 -> 164.73796 | N111: =N49*N65 -> 183.23975 | O111: =O49*O65 -> 203.91911 | P111: =P49*P65 -> 227.00575
B112: Other current liabilities | F112: 3.054 | G112: 0.446 | K112: =G112+J112-I112 -> 0.446 | L112: =L50*L65 -> 2.1814882 | M112: =M50*M65 -> 2.4251863 | N112: =N50*N65 -> 2.6975599 | O112: =O50*O65 -> 3.0019907 | P112: =P50*P65 -> 3.3418602
B113: Operating Leases | F113: 1222.054 | G113: 1267.791 | K113: =G113+J113-I113 -> 1267.791 | L113: =K113 -> 1267.791 | M113: =L113 -> 1267.791 | N113: =M113 -> 1267.791 | O113: =N113 -> 1267.791 | P113: =O113 -> 1267.791
B114: Existing Debt | F114: =(632689+15000)/1000 -> 647.689 | G114: 596.388 | I114: =G114 -> 596.388 | K114: =G114+J114-I114 -> 0 | L114: =K114 -> 0 | M114: =L114 -> 0 | N114: =M114 -> 0 | O114: =N114 -> 0 | P114: =O114 -> 0
...

Sheet Mgmt Return Analysis
B2: Assumptions and guide
B3: Assume FY26 exit
B4: Exit multiple range from 15x to 19x; 0.5x increments
B5: Use circularity
B6: Mgmt has sweet equity hurdle rate of 200% - meaning total exit equity value has to be at least 200% higher than entry equity value for mgmt to earn their sweet equity
B8: Mgmt return analysis
B9: ($ in millions, except per share values)
B11: Key Inputs
B12: LTM Adjusted EBITDA (FY26) | C12: =LBO!P92 -> 402.6784
B13: Net Debt (FY26) | C13: =LBO!P179-LBO!P100 -> 1056.2196
B14: Entry Equity Value | C14: =LBO!C12 -> 1787.4149
B15: Management Rollover % | C15: =LBO!F17 -> 0.05
B16: Sweet Equity Pot % | C16: =LBO!F18 -> 0.05
B17: Sweet Equity Hurdle | C17: 2
B18: Hurdle Threshold (3x Entry Equity) | C18: =C14*(1+C17) -> 5362.2447
B20: Exit Multiple Sensitivity Analysis
B22: Exit Multiple | C22: 15.0x | D22: 15.5x | E22: 16.0x | F22: 16.5x | G22: 17.0x | H22: 17.5x | I22: 18.0x | J22: 18.5x | K22: 19.0x
B23: Exit Enterprise Value | C23: =$C$12*15 -> 6040.176 | D23: =$C$12*15.5 -> 6241.5152 | E23: =$C$12*16 -> 6442.8544 | F23: =$C$12*16.5 -> 6644.1936 | G23: =$C$12*17 -> 6845.5328 | H23: =$C$12*17.5 -> 7046.872 | I23: =$C$12*18 -> 7248.2112 | J23: =$C$12*18.5 -> 7449.5504 | K23: =$C$12*19 -> 7650.8896
B24: Exit Equity Value | C24: =C23-$C$13 -> 4983.9564 | D24: =D23-$C$13 -> 5185.2956 | E24: =E23-$C$13 -> 5386.6348 | F24: =F23-$C$13 -> 5587.974 | G24: =G23-$C$13 -> 5789.3132 | H24: =H23-$C$13 -> 5990.6524 | I24: =I23-$C$13 -> 6191.9916 | J24: =J23-$C$13 -> 6393.3308 | K24: =K23-$C$13 -> 6594.67
B25: Equity Gain | C25: =C24-$C$14 -> 3196.5415 | D25: =D24-$C$14 -> 3397.8807 | E25: =E24-$C$14 -> 3599.2199 | F25: =F24-$C$14 -> 3800.5591 | G25: =G24-$C$14 -> 4001.8983 | H25: =H24-$C$14 -> 4203.2375 | I25: =I24-$C$14 -> 4404.5767 | J25: =J24-$C$14 -> 4605.9159 | K25: =K24-$C$14 -> 4807.2551
B26: Hurdle Met? | C26: =IF(C24>=$C$18,"Yes","No") -> No | D26: =IF(D24>=$C$18,"Yes","No") -> No | E26: =IF(E24>=$C$18,"Yes","No") -> Yes | F26: =IF(F24>=$C$18,"Yes","No") -> Yes | G26: =IF(G24>=$C$18,"Yes","No") -> Yes | H26: =IF(H24>=$C$18,"Yes","No") -> Yes | I26: =IF(I24>=$C$18,"Yes","No") -> Yes | J26: =IF(J24>=$C$18,"Yes","No") -> Yes | K26: =IF(K24>=$C$18,"Yes","No") -> Yes
B28: Management Returns
B29: Mgmt Rollover Value at Exit | C29: =$C$15*C24 -> 249.19782 | D29: =$C$15*D24 -> 259.26478 | E29: =$C$15*E24 -> 269.33174 | F29: =$C$15*F24 -> 279.3987 | G29: =$C$15*G24 -> 289.46566 | H29: =$C$15*H24 -> 299.53262 | I29: =$C$15*I24 -> 309.59958 | J29: =$C$15*J24 -> 319.66654 | K29: =$C$15*K24 -> 329.7335
B30: Sweet Equity Value | C30: =IF(C24>=$C$18,$C$16*C25,0) -> 0 | D30: =IF(D24>=$C$18,$C$16*D25,0) -> 0 | E30: =IF(E24>=$C$18,$C$16*E25,0) -> 179.961 | F30: =IF(F24>=$C$18,$C$16*F25,0) -> 190.02796 | G30: =IF(G24>=$C$18,$C$16*G25,0) -> 200.09492 | H30: =IF(H24>=$C$18,$C$16*H25,0) -> 210.16188 | I30: =IF(I24>=$C$18,$C$16*I25,0) -> 220.22884 | J30: =IF(J24>=$C$18,$C$16*J25,0) -> 230.2958 | K30: =IF(K24>=$C$18,$C$16*K25,0) -> 240.36276
B31: Total Mgmt Equity Value at Exit | C31: =C29+C30 -> 249.19782 | D31: =D29+D30 -> 259.26478 | E31: =E29+E30 -> 449.29274 | F31: =F29+F30 -> 469.42666 | G31: =G29+G30 -> 489.56058 | H31: =H29+H30 -> 509.6945 | I31: =I29+I30 -> 529.82842 | J31: =J29+J30 -> 549.96234 | K31: =K29+K30 -> 570.09626
