Workbook

Sheet BBPTACShadowWks0001
S5: =#REF!
V27: =#REF! | W27: =#REF! | X27: =#REF!
V28: =#REF! | W28: =#REF! | X28: =#REF!
T29: =#REF! | V29: =#REF! | W29: =#REF! | X29: =#REF!
L36: =#REF! | M36: =#REF!
J37: =#REF! | K37: =#REF!
G128: =#REF! | H128: =#REF! | I128: =#REF! | J128: =#REF! | K128: =#REF! | L128: =#REF! | M128: =#REF!
G129: =#REF! | H129: =#REF! | I129: =#REF! | J129: =#REF! | K129: =#REF! | L129: =#REF! | M129: =#REF!
G130: =#REF! | H130: =#REF! | I130: =#REF! | J130: =#REF! | K130: =#REF! | L130: =#REF! | M130: =#REF!
G131: =#REF! | H131: =#REF! | I131: =#REF! | J131: =#REF! | K131: =#REF! | L131: =#REF! | M131: =#REF!
K134: =#REF!
G147: =#REF!
G148: =#REF!
G149: =#REF!
E192: =#REF!
G193: =#REF!
G194: =#REF! | H194: =#REF!
G195: =#REF! | H195: =#REF!
G196: =#REF!
G197: =#REF!
G198: =#REF!
G199: =#REF! | H199: =#REF! | I199: =#REF! | J199: =#REF!
G200: =#REF! | H200: =#REF! | I200: =#REF! | J200: =#REF!
G201: =#REF! | H201: =#REF! | I201: =#REF! | J201: =#REF!
G202: =#REF! | H202: =#REF! | I202: =#REF! | J202: =#REF!
G203: =#REF!
G204: =#REF! | H204: =#REF!
G205: =#REF!
P242: =#REF!
P243: =#REF!
P244: =#REF!
M245: =#REF! | N245: =#REF! | O245: =#REF! | P245: =#REF!
M246: =#REF! | N246: =#REF!
L247: =#REF!
K282: =#REF! | L282: =#REF! | M282: =#REF! | N282: =#REF! | O282: =#REF!
P285: =#REF!
P286: =#REF!

Sheet Model Shell
A1: Kirby Corp
A2: US$mm unless otherwise specified | G2: 2Q24 LQA | J2: Act. | K2: Act. | L2: Act. | M2: Act. | N2: Act. | O2: Act. | P2: Est. | R2: Act. | S2: Act. | T2: Act. | U2: Act. | V2: Act. | W2: Act. | X2: Act. | Y2: Act. | Z2: Act. | AA2: Act. | AB2: Act. | AC2: Act. | AD2: Act. | AE2: Act. | AF2: Act. | AG2: Act. | AH2: Act. | AI2: Act. | AJ2: Act. | AK2: Act. | AL2: Act. | AM2: Act. | AN2: Act. | AO2: Act. | AP2: Act. | AQ2: Est. | AR2: Est. | AS2: Est. | AT2: Est. | AU2: Est. | AV2: Est. | AW2: Est.
G3: LQA | H3: LTM | J3: 2018 | K3: =J3+1 | L3: =K3+1 | M3: =L3+1 | N3: =M3+1 | O3: =N3+1 | P3: =O3+1 | R3: 1Q18 | S3: 2Q18 | T3: 3Q18 | U3: 4Q18 | V3: 1Q19 | W3: 2Q19 | X3: 3Q19 | Y3: 4Q19 | Z3: 1Q20 | AA3: 2Q20 | AB3: 3Q20 | AC3: 4Q20 | AD3: 1Q21 | AE3: 2Q21 | AF3: 3Q21 | AG3: 4Q21 | AH3: 1Q22 | AI3: 2Q22 | AJ3: 3Q22 | AK3: 4Q22 | AL3: 1Q23 | AM3: 2Q23 | AN3: 3Q23 | AO3: 4Q23 | AP3: 1Q24 | AQ3: 2Q24 | AR3: 3Q24 | AS3: 4Q24 | AT3: 1Q25 | AU3: 2Q25 | AV3: 3Q25 | AW3: 4Q25
A5: x | B5: Income Statement
B7: Marine Transport | G7: =OFFSET(R7,0,MATCH($G$2,$R$3:$AW$3,0)-1)*4 | H7: =SUM(OFFSET(R7,0,MATCH($G$2,$R$3:$AW$3,0)-4),OFFSET(R7,0,MATCH($G$2,$R$3:$AW$3,0)-3),OFFSET(R7,0,MATCH($G$2,$R$3:$AW$3,0)-2),OFFSET(R7,0,MATCH($G$2,$R$3:$AW$3,0)-1)) | J7: =SUM(R7:U7) | K7: =SUM(V7:Y7) | L7: =SUM(Z7:AC7) | M7: =SUM(AD7:AG7) | N7: =SUM(AH7:AK7) | O7: =SUM(AL7:AO7) | R7: 340.403 | S7: 378.163 | T7: 382.04 | U7: 382.537 | V7: 368.121 | W7: 404.286 | X7: 412.665 | Y7: 402.01 | Z7: 403.257 | AA7: 380.987 | AB7: 320.602 | AC7: 299.419 | AD7: 300.951 | AE7: 332.887 | AF7: 338.514 | AG7: 350.566 | AH7: 355.536 | AI7: 405.655 | AJ7: 433.04 | AK7: 422.736 | AL7: 412.495 | AM7: 426.962 | AN7: 429.885 | AO7: 452.595 | AP7: 475.412
B8: Distribution & Services | G8: =OFFSET(R8,0,MATCH($G$2,$R$3:$AW$3,0)-1)*4 | H8: =SUM(OFFSET(R8,0,MATCH($G$2,$R$3:$AW$3,0)-4),OFFSET(R8,0,MATCH($G$2,$R$3:$AW$3,0)-3),OFFSET(R8,0,MATCH($G$2,$R$3:$AW$3,0)-2),OFFSET(R8,0,MATCH($G$2,$R$3:$AW$3,0)-1)) | J8: =SUM(R8:U8) | K8: =SUM(V8:Y8) | L8: =SUM(Z8:AC8) | M8: =SUM(AD8:AG8) | N8: =SUM(AH8:AK8) | O8: =SUM(AL8:AO8) | R8: 401.285 | S8: 424.508 | T8: 322.805 | U8: 338.956 | V8: 376.5 | W8: 366.756 | X8: 254.144 | Y8: 253.917 | Z8: 240.669 | AA8: 160.172 | AB8: 175.965 | AC8: 190.337 | AD8: 195.899 | AE8: 226.737 | AF8: 260.406 | AG8: 240.7 | AH8: 255.246 | AI8: 292.309 | AJ8: 312.803 | AK8: 307.429 | AL8: 337.949 | AM8: 350.286 | AN8: 334.887 | AO8: 346.581 | AP8: 332.61
B9: Total Revenues | G9: =SUM(G7:G8) | H9: =SUM(H7:H8) | J9: =SUM(J7:J8) | K9: =SUM(K7:K8) | L9: =SUM(L7:L8) | M9: =SUM(M7:M8) | N9: =SUM(N7:N8) | O9: =SUM(O7:O8) | R9: =SUM(R7:R8) | S9: =SUM(S7:S8) | T9: =SUM(T7:T8) | U9: =SUM(U7:U8) | V9: =SUM(V7:V8) | W9: =SUM(W7:W8) | X9: =SUM(X7:X8) | Y9: =SUM(Y7:Y8) | ... AP9: =SUM(AP7:AP8)
C10: Y/Y Growth % | G10: =G9/G7 | H10: =H9/H7 | K10: =K9/J9-1 | L10: =L9/K9-1 | M10: =M9/L9-1 | N10: =N9/M9-1 | O10: =O9/N9-1 | V10: =V9/R9-1 | W10: =W9/S9-1 | X10: =X9/T9-1 | Y10: =Y9/U9-1 | Z10: =Z9/V9-1 | AA10: =AA9/W9-1 | AB10: =AB9/X9-1 | AC10: =AC9/Y9-1 | ... AP10: =AP9/AL9-1
C11: Sequential Growth % | S11: =S9/R9-1 | T11: =T9/S9-1 | U11: =U9/T9-1 | V11: =V9/U9-1 | W11: =W9/V9-1 | X11: =X9/W9-1 | Y11: =Y9/X9-1 | Z11: =Z9/Y9-1 | ... AP11: =AP9/AO9-1
B13: Cash COGS & OpEX | G13: =OFFSET(R13,0,MATCH($G$2,$R$3:$AW$3,0)-1)*4 | H13: =SUM(OFFSET(R13,0,MATCH($G$2,$R$3:$AW$3,0)-4),OFFSET(R13,0,MATCH($G$2,$R$3:$AW$3,0)-3),OFFSET(R13,0,MATCH($G$2,$R$3:$AW$3,0)-2),OFFSET(R13,0,MATCH($G$2,$R$3:$AW$3,0)-1)) | J13: =SUM(R13:U13) | K13: =SUM(V13:Y13) | L13: =SUM(Z13:AC13) | M13: =SUM(AD13:AG13) | N13: =SUM(AH13:AK13) | O13: =SUM(AL13:AO13) | R13: -553.317 | S13: -588.628 | T13: -498.421 | U13: -520.58 | V13: -536.655 | W13: -563.495 | X13: -458.514 | Y13: -471.382 | Z13: -453.568 | AA13: -373.539 | AB13: -340.764 | AC13: -342.947 | AD13: -363.04 | AE13: -409.479 | AF13: -446.519 | AG13: -433.923 | AH13: -450.618 | AI13: -523.862 | AJ13: -552.392 | AK13: -534.069 | AL13: -542.08 | AM13: -546.069 | AN13: -530.541 | AO13: -561.732 | AP13: -550.681
B14: Cash Gross Profit | G14: =G9+SUM(G13:G13) | H14: =H9+SUM(H13:H13) | J14: =J9+SUM(J13:J13) | K14: =K9+SUM(K13:K13) | L14: =L9+SUM(L13:L13) | M14: =M9+SUM(M13:M13) | N14: =N9+SUM(N13:N13) | O14: =O9+SUM(O13:O13) | R14: =R9+SUM(R13:R13) | S14: =S9+SUM(S13:S13) | T14: =T9+SUM(T13:T13) | U14: =U9+SUM(U13:U13) | V14: =V9+SUM(V13:V13) | W14: =W9+SUM(W13:W13) | X14: =X9+SUM(X13:X13) | Y14: =Y9+SUM(Y13:Y13) | ... AP14: =AP9+SUM(AP13:AP13)
C15: Gross Margin % | G15: =G14/G9 | H15: =H14/H9 | J15: =J14/J9 | K15: =K14/K9 | L15: =L14/L9 | M15: =M14/M9 | N15: =N14/N9 | O15: =O14/O9 | R15: =R14/R9 | S15: =S14/S9 | T15: =T14/T9 | U15: =U14/U9 | V15: =V14/V9 | W15: =W14/W9 | X15: =X14/X9 | Y15: =Y14/Y9 | ... AP15: =AP14/AP9
B17: SG&A | G17: =OFFSET(R17,0,MATCH($G$2,$R$3:$AW$3,0)-1)*4 | H17: =SUM(OFFSET(R17,0,MATCH($G$2,$R$3:$AW$3,0)-4),OFFSET(R17,0,MATCH($G$2,$R$3:$AW$3,0)-3),OFFSET(R17,0,MATCH($G$2,$R$3:$AW$3,0)-2),OFFSET(R17,0,MATCH($G$2,$R$3:$AW$3,0)-1)) | J17: =SUM(R17:U17) | K17: =SUM(V17:Y17) | L17: =SUM(Z17:AC17) | M17: =SUM(AD17:AG17) | N17: =SUM(AH17:AK17) | O17: =SUM(AL17:AO17) | R17: -76.796 | S17: -92.588 | T17: -70.032 | U17: -64.981 | V17: -72.796 | W17: -69.15 | X17: -64.656 | Y17: -70.786 | Z17: -72.08 | AA17: -65.612 | AB17: -61.72 | AC17: -58.86 | AD17: -69.629 | AE17: -62.74 | AF17: -66.065 | AG17: -68.477 | AH17: -75.765 | AI17: -69.275 | AJ17: -75.381 | AK17: -80.971 | AL17: -88.849 | AM17: -82.896 | AN17: -79.125 | AO17: -84.343 | AP17: -90.206
B18: Taxes other than Income | G18: =OFFSET(R18,0,MATCH($G$2,$R$3:$AW$3,0)-1)*4 | H18: =SUM(OFFSET(R18,0,MATCH($G$2,$R$3:$AW$3,0)-4),OFFSET(R18,0,MATCH($G$2,$R$3:$AW$3,0)-3),OFFSET(R18,0,MATCH($G$2,$R$3:$AW$3,0)-2),OFFSET(R18,0,MATCH($G$2,$R$3:$AW$3,0)-1)) | J18: =SUM(R18:U18) | K18: =SUM(V18:Y18) | L18: =SUM(Z18:AC18) | M18: =SUM(AD18:AG18) | N18: =SUM(AH18:AK18) | O18: =SUM(AL18:AO18) | R18: -8.535 | S18: -10.552 | T18: -10.523 | U18: -9.641 | V18: -9.998 | W18: -10.579 | X18: -10.909 | Y18: -10.447 | Z18: -11.406 | AA18: -13.065 | AB18: -9.077 | AC18: -8.452 | AD18: -8.26 | AE18: -10.364 | AF18: -9.917 | AG18: -7.71 | AH18: -9.59 | AI18: -9.621 | AJ18: -9.121 | AK18: -6.739 | AL18: -9.186 | AM18: -9.758 | AN18: -9.666 | AO18: -6.156 | AP18: -8.044
B19: D&A | G19: =OFFSET(R19,0,MATCH($G$2,$R$3:$AW$3,0)-1)*4 | H19: =SUM(OFFSET(R19,0,MATCH($G$2,$R$3:$AW$3,0)-4),OFFSET(R19,0,MATCH($G$2,$R$3:$AW$3,0)-3),OFFSET(R19,0,MATCH($G$2,$R$3:$AW$3,0)-2),OFFSET(R19,0,MATCH($G$2,$R$3:$AW$3,0)-1)) | J19: =SUM(R19:U19) | K19: =SUM(V19:Y19) | L19: =SUM(Z19:AC19) | M19: =SUM(AD19:AG19) | N19: =SUM(AH19:AK19) | O19: =SUM(AL19:AO19) | R19: -54.218 | S19: -55.492 | T19: -57.93 | U19: -57.332 | V19: -55.223 | W19: -55.093 | X19: -54.455 | Y19: -54.861 | Z19: -55.789 | AA19: -54.502 | AB19: -54.779 | AC19: -54.854 | AD19: -54.89 | AE19: -55.132 | AF19: -53.462 | AG19: -50.234 | AH19: -49.964 | AI19: -50.115 | AJ19: -50.419 | AK19: -50.945 | AL19: -51.109 | AM19: -51.697 | AN19: -53.445 | AO19: -54.905 | AP19: -57.642
B20: Core EBIT | G20: =G14+SUM(G17:G19) | H20: =H14+SUM(H17:H19) | J20: =J14+SUM(J17:J19) | K20: =K14+SUM(K17:K19) | L20: =L14+SUM(L17:L19) | M20: =M14+SUM(M17:M19) | N20: =N14+SUM(N17:N19) | O20: =O14+SUM(O17:O19) | R20: =R14+SUM(R17:R19) | S20: =S14+SUM(S17:S19) | T20: =T14+SUM(T17:T19) | U20: =U14+SUM(U17:U19) | V20: =V14+SUM(V17:V19) | W20: =W14+SUM(W17:W19) | X20: =X14+SUM(X17:X19) | Y20: =Y14+SUM(Y17:Y19) | ... AP20: =AP14+SUM(AP17:AP19)
C21: % Margin | G21: =G20/G9 | H21: =H20/H9 | J21: =J20/J9 | K21: =K20/K9 | L21: =L20/L9 | M21: =M20/M9 | N21: =N20/N9 | O21: =O20/O9 | R21: =R20/R9 | S21: =S20/S9 | T21: =T20/T9 | U21: =U20/U9 | V21: =V20/V9 | W21: =W20/W9 | X21: =X20/X9 | Y21: =Y20/Y9 | ... AP21: =AP20/AP9
B22: (+) D&A | G22: =OFFSET(R22,0,MATCH($G$2,$R$3:$AW$3,0)-1)*4 | H22: =SUM(OFFSET(R22,0,MATCH($G$2,$R$3:$AW$3,0)-4),OFFSET(R22,0,MATCH($G$2,$R$3:$AW$3,0)-3),OFFSET(R22,0,MATCH($G$2,$R$3:$AW$3,0)-2),OFFSET(R22,0,MATCH($G$2,$R$3:$AW$3,0)-1)) | J22: =SUM(R22:U22) | K22: =SUM(V22:Y22) | L22: =SUM(Z22:AC22) | M22: =SUM(AD22:AG22) | N22: =SUM(AH22:AK22) | O22: =SUM(AL22:AO22) | R22: =-R19 | S22: =-S19 | T22: =-T19 | U22: =-U19 | V22: =-V19 | W22: =-W19 | X22: =-X19 | Y22: =-Y19 | ... AP22: =-AP19
B23: Core EBITDA | G23: =G20+G22 | H23: =H20+H22 | J23: =J20+J22 | K23: =K20+K22 | L23: =L20+L22 | M23: =M20+M22 | N23: =N20+N22 | O23: =O20+O22 | R23: =R20+R22 | S23: =S20+S22 | T23: =T20+T22 | U23: =U20+U22 | V23: =V20+V22 | W23: =W20+W22 | X23: =X20+X22 | Y23: =Y20+Y22 | ... AP23: =AP20+AP22
C24: % Margin | G24: =G23/G9 | H24: =H23/H9 | J24: =J23/J9 | K24: =K23/K9 | L24: =L23/L9 | M24: =M23/M9 | N24: =N23/N9 | O24: =O23/O9 | R24: =R23/R9 | S24: =S23/S9 | T24: =T23/T9 | U24: =U23/U9 | V24: =V23/V9 | W24: =W23/W9 | X24: =X23/X9 | Y24: =Y23/Y9 | ... AP24: =AP23/AP9
B26: Impairments & other charges | G26: =OFFSET(R26,0,MATCH($G$2,$R$3:$AW$3,0)-1)*4 | H26: =SUM(OFFSET(R26,0,MATCH($G$2,$R$3:$AW$3,0)-4),OFFSET(R26,0,MATCH($G$2,$R$3:$AW$3,0)-3),OFFSET(R26,0,MATCH($G$2,$R$3:$AW$3,0)-2),OFFSET(R26,0,MATCH($G$2,$R$3:$AW$3,0)-1)) | J26: =SUM(R26:U26) | K26: =SUM(V26:Y26) | L26: =SUM(Z26:AC26) | M26: =SUM(AD26:AG26) | N26: =SUM(AH26:AK26) | O26: =SUM(AL26:AO26) | R26: 0 | S26: 0 | T26: 0 | U26: =-82.705-2.702-2.403 | V26: 0 | W26: 0 | X26: 0 | Y26: -35.525 | Z26: -561.274 | AA26: 0 | AB26: 0 | AC26: 0 | AD26: 0 | AE26: 0 | AF26: -340.713 | AG26: 0 | AH26: 0 | AI26: 0 | AJ26: 0 | AK26: 0 | AL26: 0 | AM26: 0 | AN26: 0 | AO26: 0 | AP26: 0
B27: Gains on disposals | G27: =OFFSET(R27,0,MATCH($G$2,$R$3:$AW$3,0)-1)*4 | H27: =SUM(OFFSET(R27,0,MATCH($G$2,$R$3:$AW$3,0)-4),OFFSET(R27,0,MATCH($G$2,$R$3:$AW$3,0)-3),OFFSET(R27,0,MATCH($G$2,$R$3:$AW$3,0)-2),OFFSET(R27,0,MATCH($G$2,$R$3:$AW$3,0)-1)) | J27: =SUM(R27:U27) | K27: =SUM(V27:Y27) | L27: =SUM(Z27:AC27) | M27: =SUM(AD27:AG27) | N27: =SUM(AH27:AK27) | O27: =SUM(AL27:AO27) | R27: 1.898 | S27: 0.442 | T27: 0.018 | U27: -0.39 | V27: 2.157 | W27: 3.118 | X27: -0.374 | Y27: 3.251 | Z27: 0.492 | AA27: -0.189 | AB27: -0.316 | AC27: 0.131 | AD27: 2.133 | AE27: 2.119 | AF27: 0.83 | AG27: 0.679 | AH27: 4.849 | AI27: 2.745 | AJ27: 0.377 | AK27: 0.308 | AL27: 2.23 | AM27: 0.472 | AN27: 1.528 | AO27: 0.779 | AP27: 0.074
B28: Other Income/Expenses Net | G28: =OFFSET(R28,0,MATCH($G$2,$R$3:$AW$3,0)-1)*4 | H28: =SUM(OFFSET(R28,0,MATCH($G$2,$R$3:$AW$3,0)-4),OFFSET(R28,0,MATCH($G$2,$R$3:$AW$3,0)-3),OFFSET(R28,0,MATCH($G$2,$R$3:$AW$3,0)-2),OFFSET(R28,0,MATCH($G$2,$R$3:$AW$3,0)-1)) | J28: =SUM(R28:U28) | K28: =SUM(V28:Y28) | L28: =SUM(Z28:AC28) | M28: =SUM(AD28:AG28) | N28: =SUM(AH28:AK28) | O28: =SUM(AL28:AO28) | R28: 1.591 | S28: 1.541 | T28: 1.454 | U28: 1.14 | V28: -0.568 | W28: 2.381 | X28: 0.864 | Y28: 1.11 | Z28: 2.723 | AA28: 2.29 | AB28: 1.172 | AC28: 1.962 | AD28: 3.791 | AE28: 2.523 | AF28: 1.832 | AG28: 1.855 | AH28: 4.308 | AI28: 3.749 | AJ28: 3.805 | AK28: 4.824 | AL28: 6.443 | AM28: 1.264 | AN28: 1.589 | AO28: 1.745 | AP28: 3.269
B29: Other EBIT Components | G29: =SUM(G26:G28) | H29: =SUM(H26:H28) | J29: =SUM(J26:J28) | K29: =SUM(K26:K28) | L29: =SUM(L26:L28) | M29: =SUM(M26:M28) | N29: =SUM(N26:N28) | O29: =SUM(O26:O28) | R29: =SUM(R26:R28) | S29: =SUM(S26:S28) | T29: =SUM(T26:T28) | U29: =SUM(U26:U28) | V29: =SUM(V26:V28) | W29: =SUM(W26:W28) | X29: =SUM(X26:X28) | Y29: =SUM(Y26:Y28) | ... AP29: =SUM(AP26:AP28)
B30: As Reported Core EBIT | G30: =G20 | H30: =H20 | J30: =J20 | K30: =K20 | L30: =L20 | M30: =M20 | N30: =N20 | O30: =O20 | R30: =R20 | S30: =S20 | T30: =T20 | U30: =U20 | V30: =V20 | W30: =W20 | X30: =X20 | Y30: =Y20 | ... AP30: =AP20
B31: Total EBIT | G31: =SUM(G29:G30) | H31: =SUM(H29:H30) | J31: =SUM(J29:J30) | K31: =SUM(K29:K30) | L31: =SUM(L29:L30) | M31: =SUM(M29:M30) | N31: =SUM(N29:N30) | O31: =SUM(O29:O30) | R31: =SUM(R29:R30) | S31: =SUM(S29:S30) | T31: =SUM(T29:T30) | U31: =SUM(U29:U30) | V31: =SUM(V29:V30) | W31: =SUM(W29:W30) | X31: =SUM(X29:X30) | Y31: =SUM(Y29:Y30) | ... AP31: =SUM(AP29:AP30) | AQ31: 484.8
C32: % Margin | G32: =G31/G9 | H32: =H31/H9 | J32: =J31/J9 | K32: =K31/K9 | L32: =L31/L9 | M32: =M31/M9 | N32: =N31/N9 | O32: =O31/O9 | R32: =R31/R9 | S32: =S31/S9 | T32: =T31/T9 | U32: =U31/U9 | V32: =V31/V9 | W32: =W31/W9 | X32: =X31/X9 | Y32: =Y31/Y9 | ... AP32: =AP31/AP9
B34: Interest expense, net | G34: =OFFSET(R34,0,MATCH($G$2,$R$3:$AW$3,0)-1)*4 | H34: =SUM(OFFSET(R34,0,MATCH($G$2,$R$3:$AW$3,0)-4),OFFSET(R34,0,MATCH($G$2,$R$3:$AW$3,0)-3),OFFSET(R34,0,MATCH($G$2,$R$3:$AW$3,0)-2),OFFSET(R34,0,MATCH($G$2,$R$3:$AW$3,0)-1)) | J34: =SUM(R34:U34) | K34: =SUM(V34:Y34) | L34: =SUM(Z34:AC34) | M34: =SUM(AD34:AG34) | N34: =SUM(AH34:AK34) | O34: =SUM(AL34:AO34) | R34: -9.78 | S34: -12.54 | T34: -12.345 | U34: -12.191 | V34: -13.201 | W34: -15.515 | X34: -14.31 | Y34: -12.968 | Z34: -12.799 | AA34: -12.708 | AB34: -11.809 | AC34: -11.423 | AD34: -10.966 | AE34: -10.706 | AF34: -10.5 | AG34: -10.297 | AH34: -10.203 | AI34: -10.649 | AJ34: -11.755 | AK34: -11.99 | AL34: -13.221 | AM34: -12.286 | AN34: -13.386 | AO34: -13.115 | AP34: -13.151
B36: PBT | G36: =G31+G34 | H36: =H31+H34 | J36: =J31+J34 | K36: =K31+K34 | L36: =L31+L34 | M36: =M31+M34 | N36: =N31+N34 | O36: =O31+O34 | R36: =R31+R34 | S36: =S31+S34 | T36: =T31+T34 | U36: =U31+U34 | V36: =V31+V34 | W36: =W31+W34 | X36: =X31+X34 | Y36: =Y31+Y34 | ... AP36: =AP31+AP34
B37: (-) Taxes | G37: =OFFSET(R37,0,MATCH($G$2,$R$3:$AW$3,0)-1)*4 | H37: =SUM(OFFSET(R37,0,MATCH($G$2,$R$3:$AW$3,0)-4),OFFSET(R37,0,MATCH($G$2,$R$3:$AW$3,0)-3),OFFSET(R37,0,MATCH($G$2,$R$3:$AW$3,0)-2),OFFSET(R37,0,MATCH($G$2,$R$3:$AW$3,0)-1)) | J37: =SUM(R37:U37) | K37: =SUM(V37:Y37) | L37: =SUM(Z37:AC37) | M37: =SUM(AD37:AG37) | N37: =SUM(AH37:AK37) | O37: =SUM(AL37:AO37) | R37: -9.865 | S37: -16.061 | T37: -15.116 | U37: 5.961 | V37: -13.88 | W37: -15.269 | X37: -16.305 | Y37: -1.347 | Z37: 172.809 | AA37: 1.429 | AB37: 8.419 | AC37: 7.102 | AD37: 0.891 | AE37: -5.493 | AF37: 60.442 | AG37: -12.01 | AH37: -6.213 | AI37: -11.03 | AJ37: -11.713 | AK37: -14.458 | AL37: -14.051 | AM37: -18.96 | AN37: -18.722 | AO37: -19.487 | AP37: -21.726
B38: Net Income | G38: =SUM(G36:G37) | H38: =SUM(H36:H37) | J38: =SUM(J36:J37) | K38: =SUM(K36:K37) | L38: =SUM(L36:L37) | M38: =SUM(M36:M37) | N38: =SUM(N36:N37) | O38: =SUM(O36:O37) | R38: =SUM(R36:R37) | S38: =SUM(S36:S37) | T38: =SUM(T36:T37) | U38: =SUM(U36:U37) | V38: =SUM(V36:V37) | W38: =SUM(W36:W37) | X38: =SUM(X36:X37) | Y38: =SUM(Y36:Y37) | ... AP38: =SUM(AP36:AP37)
B39: (-) NCI | G39: =OFFSET(R39,0,MATCH($G$2,$R$3:$AW$3,0)-1)*4 | H39: =SUM(OFFSET(R39,0,MATCH($G$2,$R$3:$AW$3,0)-4),OFFSET(R39,0,MATCH($G$2,$R$3:$AW$3,0)-3),OFFSET(R39,0,MATCH($G$2,$R$3:$AW$3,0)-2),OFFSET(R39,0,MATCH($G$2,$R$3:$AW$3,0)-1)) | J39: =SUM(R39:U39) | K39: =SUM(V39:Y39) | L39: =SUM(Z39:AC39) | M39: =SUM(AD39:AG39) | N39: =SUM(AH39:AK39) | O39: =SUM(AL39:AO39) | R39: -0.195 | S39: -0.191 | T39: -0.134 | U39: -0.106 | V39: -0.161 | W39: -0.153 | X39: -0.163 | Y39: -0.195 | Z39: -0.278 | AA39: -0.261 | AB39: -0.204 | AC39: -0.211 | AD39: -0.255 | AE39: -0.162 | AF39: 0.422 | AG39: -0.188 | AH39: -0.152 | AI39: -0.1499 | AJ39: -0.153 | AK39: -0.016 | AL39: 0.077 | AM39: 0.049 | AN39: -0.4 | AO39: -0.056 | AP39: 0.153
B40: Net Income to Shareholders | G40: =SUM(G38:G39) | H40: =SUM(H38:H39) | J40: =SUM(J38:J39) | K40: =SUM(K38:K39) | L40: =SUM(L38:L39) | M40: =SUM(M38:M39) | N40: =SUM(N38:N39) | O40: =SUM(O38:O39) | R40: =SUM(R38:R39) | S40: =SUM(S38:S39) | T40: =SUM(T38:T39) | U40: =SUM(U38:U39) | V40: =SUM(V38:V39) | W40: =SUM(W38:W39) | X40: =SUM(X38:X39) | Y40: =SUM(Y38:Y39) | ... AP40: =SUM(AP38:AP39)
B42: Diluted Shares Outstanding | G42: =OFFSET(R42,0,MATCH($G$2,$R$3:$AW$3,0)-1) | H42: =AVERAGE(OFFSET(R42,0,MATCH($G$2,$R$3:$AW$3,0)-4),OFFSET(R42,0,MATCH($G$2,$R$3:$AW$3,0)-3),OFFSET(R42,0,MATCH($G$2,$R$3:$AW$3,0)-2),OFFSET(R42,0,MATCH($G$2,$R$3:$AW$3,0)-1)) | J42: 59.689 | K42: 59.75 | L42: 59.912 | M42: 60.053 | N42: 60.329 | O42: 59.857 | R42: 59.493 | S42: 59.72 | T42: 59.784 | U42: 59.645 | V42: 59.823 | W42: 59.907 | X42: 59.906 | Y42: 59.998 | Z42: 59.883 | AA42: 59.937 | AB42: 59.931 | AC42: 59.975 | AD42: 60.016 | AE42: 60.274 | AF42: 60.062 | AG42: 60.311 | AH42: 60.463 | AI42: 60.467 | AJ42: 60.182 | AK42: 60.211 | AL42: 60.272 | AM42: 60.085 | AN42: 59.764 | AO42: 59.335 | AP42: 58.819
B43: Fully Diluted EPS | G43: =OFFSET(R43,0,MATCH($G$2,$R$3:$AW$3,0)-1)*4 | H43: =SUM(OFFSET(R43,0,MATCH($G$2,$R$3:$AW$3,0)-4),OFFSET(R43,0,MATCH($G$2,$R$3:$AW$3,0)-3),OFFSET(R43,0,MATCH($G$2,$R$3:$AW$3,0)-2),OFFSET(R43,0,MATCH($G$2,$R$3:$AW$3,0)-1)) | J43: =J40/J42 | K43: =K40/K42 | L43: =L40/L42 | M43: =M40/M42 | N43: =N40/N42 | O43: =O40/O42 | R43: =R40/R42 | S43: =S40/S42 | T43: =T40/T42 | U43: =U40/U42 | V43: =V40/V42 | W43: =W40/W42 | X43: =X40/X42 | Y43: =Y40/Y42 | ... AP43: =AP40/AP42
A46: x | B46: Balance Sheet
B48: Cash and cash equivalents | G48: =OFFSET(R48,0,MATCH($G$2,$R$3:$AW$3,0)-1) | H48: =G48 | J48: =U48 | K48: =Y48 | L48: =AC48 | M48: =AG48 | N48: =AK48 | O48: =AO48 | R48: 7.01 | S48: 4.198 | T48: 3.617 | U48: 7.8 | V48: 7.289 | W48: 22.521 | X48: 9.425 | Y48: 24.737 | Z48: 322.571 | AA48: 108.471 | AB48: 119.586 | AC48: 80.338 | AD48: 52.333 | AE48: 53.052 | AF48: 54.377 | AG48: 34.813 | AH48: 32.398 | AI48: 25.104 | AJ48: 36.991 | AK48: 80.577 | AL48: 26.699 | AM48: 36.603 | AN48: 42.116 | AO48: 32.577 | AP48: 75.216
B49: Trade Receivables | G49: =OFFSET(R49,0,MATCH($G$2,$R$3:$AW$3,0)-1) | H49: =G49 | J49: =U49 | K49: =Y49 | L49: =AC49 | M49: =AG49 | N49: =AK49 | O49: =AO49 | R49: 485.865 | S49: 448.281 | T49: 400.87 | U49: 417.644 | V49: 439.975 | W49: 450.958 | X49: 382.465 | Y49: 379.174 | Z49: 389.616 | AA49: 348.453 | AB49: 304.021 | AC49: 315.283 | AD49: 347.275 | AE49: 352.372 | AF49: 389.579 | AG49: 417.958 | AH49: 420.823 | AI49: 445.425 | AJ49: 482.744 | AK49: 483.406 | AL49: 526.489 | AM49: 519.741 | AN49: 514.631 | AO49: 526.691 | AP49: 529.141
B50: Other Receivables | G50: =OFFSET(R50,0,MATCH($G$2,$R$3:$AW$3,0)-1) | H50: =G50 | J50: =U50 | K50: =Y50 | L50: =AC50 | M50: =AG50 | N50: =AK50 | O50: =AO50 | R50: 110.64 | S50: 116.673 | T50: 111.221 | U50: 104.239 | V50: 122.18 | W50: 99.568 | X50: 99.736 | Y50: 104.175 | Z50: 253.688 | AA50: 228.409 | AB50: 257.656 | AC50: 284.899 | AD50: 171.749 | AE50: 165.478 | AF50: 150.811 | AG50: 149.964 | AH50: 125.757 | AI50: 127.181 | AJ50: 133.278 | AK50: 114.556 | AL50: 109.539 | AM50: 40.011 | AN50: 53.936 | AO50: 52.025 | AP50: 55.949
B51: Inventory | G51: =OFFSET(R51,0,MATCH($G$2,$R$3:$AW$3,0)-1) | H51: =G51 | J51: =U51 | K51: =Y51 | L51: =AC51 | M51: =AG51 | N51: =AK51 | O51: =AO51 | R51: 372.182 | S51: 384.007 | T51: 453.173 | U51: 507.441 | V51: 491.566 | W51: 428.26 | X51: 410.261 | Y51: 351.401 | Z51: 341.498 | AA51: 335.958 | AB51: 321.433 | AC51: 309.675 | AD51: 326.475 | AE51: 325.545 | AF51: 308.82 | AG51: 331.35 | AH51: 360.457 | AI51: 370.385 | AJ51: 392.47 | AK51: 461.848 | AL51: 475.218 | AM51: 504.514 | AN51: 505.506 | AO51: 454.389 | AP51: 446.803
B52: Prepaid Expenses | G52: =OFFSET(R52,0,MATCH($G$2,$R$3:$AW$3,0)-1) | H52: =G52 | J52: =U52 | K52: =Y52 | L52: =AC52 | M52: =AG52 | N52: =AK52 | O52: =AO52 | R52: 80.957 | S52: 82.173 | T52: 85.639 | U52: 59.365 | V52: 57.242 | W52: 52.953 | X52: 56.646 | Y52: 58.092 | Z52: 60.64 | AA52: 57.023 | AB52: 58.023 | AC52: 57.776 | AD52: 60.685 | AE52: 66.696 | AF52: 75.004 | AG52: 69.78 | AH52: 75.896 | AI52: 84.16 | AJ52: 80.899 | AK52: 71.372 | AL52: 62.421 | AM52: 67.787 | AN52: 79.382 | AO52: 69.479 | AP52: 68.369
B53: Current Assets | G53: =SUM(G48:G52) | H53: =SUM(H48:H52) | J53: =SUM(J48:J52) | K53: =SUM(K48:K52) | L53: =SUM(L48:L52) | M53: =SUM(M48:M52) | N53: =SUM(N48:N52) | O53: =SUM(O48:O52) | R53: =SUM(R48:R52) | S53: =SUM(S48:S52) | T53: =SUM(T48:T52) | U53: =SUM(U48:U52) | V53: =SUM(V48:V52) | W53: =SUM(W48:W52) | X53: =SUM(X48:X52) | Y53: =SUM(Y48:Y52) | ... AP53: =SUM(AP48:AP52)
B55: PP&E | G55: =OFFSET(R55,0,MATCH($G$2,$R$3:$AW$3,0)-1) | H55: =G55 | J55: =U55 | K55: =Y55 | L55: =AC55 | M55: =AG55 | N55: =AK55 | O55: =AO55 | R55: 3443.868 | S55: 3549.066 | T55: 3561.5 | U55: 3539.802 | V55: 3792.44 | W55: 3796.418 | X55: 3793.732 | Y55: 3777.11 | Z55: 3776.784 | AA55: 3976.025 | AB55: 3958.144 | AC55: 3917.07 | AD55: 3881.273 | AE55: 3862.806 | AF55: 3705.247 | AG55: 3678.515 | AH55: 3660.314 | AI55: 3652.652 | AJ55: 3640.69 | AK55: 3633.462 | AL55: 3665.51 | AM55: 3697.939 | AN55: 3782.124 | AO55: 3861.105 | AP55: 3883.321
B56: Operating Leases ROU | G56: =OFFSET(R56,0,MATCH($G$2,$R$3:$AW$3,0)-1) | H56: =G56 | J56: =U56 | K56: =Y56 | L56: =AC56 | M56: =AG56 | N56: =AK56 | O56: =AO56 | R56: 0 | S56: 0 | T56: 0 | U56: 0 | V56: 159.704 | W56: 158.917 | X56: 156.798 | Y56: 159.641 | Z56: 157.33 | AA56: 183.048 | AB56: 178.714 | AC56: 174.317 | AD56: 172.198 | AE56: 164.911 | AF56: 159.627 | AG56: 167.73 | AH56: 164.986 | AI56: 159.968 | AJ56: 153.723 | AK56: 154.507 | AL56: 155.306 | AM56: 152.504 | AN56: 155.098 | AO56: 152.216 | AP56: 149.412
B57: Goodwill | G57: =OFFSET(R57,0,MATCH($G$2,$R$3:$AW$3,0)-1) | H57: =G57 | J57: =U57 | K57: =Y57 | L57: =AC57 | M57: =AG57 | N57: =AK57 | O57: =AO57 | R57: 0 | S57: 0 | T57: 0 | U57: 2.495 | V57: 0 | W57: 0 | X57: 0 | Y57: 2.025 | Z57: 0 | AA57: 0 | AB57: 0 | AC57: 2.689 | AD57: 0 | AE57: 0 | AF57: 0 | AG57: 2.134 | AH57: 2.41 | AI57: 0 | AJ57: 0 | AK57: 2.171 | AL57: 0 | AM57: 0 | AN57: 0 | AO57: 2.576 | AP57: 438.748
B58: Other Intangibles | G58: =OFFSET(R58,0,MATCH($G$2,$R$3:$AW$3,0)-1) | H58: =G58 | J58: =U58 | K58: =Y58 | L58: =AC58 | M58: =AG58 | N58: =AK58 | O58: =AO58 | R58: 935.755 | S58: 961.745 | T58: 960.006 | U58: 953.826 | V58: 953.826 | W58: 953.826 | X58: 953.826 | Y58: 953.826 | Z58: 704.098 | AA58: 657.832 | AB58: 657.8 | AC58: 657.8 | AD58: 657.8 | AE58: 657.8 | AF58: 438.748 | AG58: 438.748 | AH58: 438.748 | AI58: 438.748 | AJ58: 438.748 | AK58: 438.748 | AL58: 438.748 | AM58: 438.748 | AN58: 438.748 | AO58: 438.748 | AP58: 40.797
B59: Other assets | G59: =OFFSET(R59,0,MATCH($G$2,$R$3:$AW$3,0)-1) | H59: =G59 | J59: =U59 | K59: =Y59 | L59: =AC59 | M59: =AG59 | N59: =AK59 | O59: =AO59 | R59: 278.223 | S59: 283.133 | T59: 278.307 | U59: 278.982 | V59: 276.47 | W59: 269.465 | X59: 264.996 | Y59: 268.916 | Z59: 131.349 | AA59: 121.792 | AB59: 125.743 | AC59: 124.327 | AD59: 118.298 | AE59: 119.155 | AF59: 107.669 | AG59: 108.071 | AH59: 103.413 | AI59: 101.533 | AJ59: 96.755 | AK59: 114.277 | AL59: 114.818 | AM59: 116.732 | AN59: 111.339 | AO59: 132.391 | AP59: 88.081
B60: Total Assets | G60: =G53+SUM(G55:G59) | H60: =H53+SUM(H55:H59) | J60: =J53+SUM(J55:J59) | K60: =K53+SUM(K55:K59) | L60: =L53+SUM(L55:L59) | M60: =M53+SUM(M55:M59) | N60: =N53+SUM(N55:N59) | O60: =O53+SUM(O55:O59) | R60: =R53+SUM(R55:R59) | S60: =S53+SUM(S55:S59) | T60: =T53+SUM(T55:T59) | U60: =U53+SUM(U55:U59) | V60: =V53+SUM(V55:V59) | W60: =W53+SUM(W55:W59) | X60: =X53+SUM(X55:X59) | Y60: =Y53+SUM(Y55:Y59) | ... AP60: =AP53+SUM(AP55:AP59)
B62: Current portion of debt | G62: =OFFSET(R62,0,MATCH($G$2,$R$3:$AW$3,0)-1) | H62: =G62 | J62: =U62 | K62: =Y62 | L62: =AC62 | M62: =AG62 | N62: =AK62 | O62: =AO62 | R62: 0.027 | S62: 0.017 | T62: 0.508 | U62: 0.019 | V62: 0.017 | W62: 0.011 | X62: 0.015 | Y62: 0.016 | Z62: 0 | AA62: 0.007 | AB62: 0.155 | AC62: 0.04 | AD62: 0.434 | AE62: 1.417 | AF62: 1.983 | AG62: 1.934 | AH62: 3.097 | AI62: 4.206 | AJ62: 3.599 | AK62: 3.292 | AL62: 3.983 | AM62: 7.447 | AN62: 9.608 | AO62: 8.068 | AP62: 8.643
B63: Income Taxes Payable | G63: =OFFSET(R63,0,MATCH($G$2,$R$3:$AW$3,0)-1) | H63: =G63 | J63: =U63 | K63: =Y63 | L63: =AC63 | M63: =AG63 | N63: =AK63 | O63: =AO63 | R63: 1.936 | S63: 2.875 | T63: 3.765 | U63: 2.794 | V63: 1.441 | W63: 0.312 | X63: 1.196 | Y63: 0.665 | Z63: 0.698 | AA63: 0.694 | AB63: 0.459 | AC63: 0.474 | AD63: 0.489 | AE63: 0.497 | AF63: 0.499 | AG63: 0 | AH63: 0.093 | AI63: 0 | AJ63: 0 | AK63: 0.323 | AL63: 1.106 | AM63: 0 | AN63: 2.247 | AO63: 1.486 | AP63: 11.252
B64: Accounts Payable | G64: =OFFSET(R64,0,MATCH($G$2,$R$3:$AW$3,0)-1) | H64: =G64 | J64: =U64 | K64: =Y64 | L64: =AC64 | M64: =AG64 | N64: =AK64 | O64: =AO64 | R64: 251.916 | S64: 263.47 | T64: 250.681 | U64: 278.057 | V64: 275.57 | W64: 212.147 | X64: 212.279 | Y64: 206.778 | Z64: 227.02 | AA64: 177.29 | AB64: 156.95 | AC64: 162.507 | AD64: 175.89 | AE64: 188.724 | AF64: 181.313 | AG64: 199.088 | AH64: 218.907 | AI64: 234.64 | AJ64: 241.623 | AK64: 278.081 | AL64: 278.467 | AM64: 279.519 | AN64: 258.126 | AO64: 269.378 | AP64: 249.644
B65: Accrued Liabilities | G65: =OFFSET(R65,0,MATCH($G$2,$R$3:$AW$3,0)-1) | H65: =G65 | J65: =U65 | K65: =Y65 | L65: =AC65 | M65: =AG65 | N65: =AK65 | O65: =AO65 | R65: 196.063 | S65: 228.791 | T65: 237.129 | U65: 246.789 | V65: 204.724 | W65: 225.232 | X65: 225.402 | Y65: 236.35 | Z65: 205.667 | AA65: 230.296 | AB65: 228.764 | AC65: 224.855 | AD65: 198.487 | AE65: 231.603 | AF65: 228.375 | AG65: 236.078 | AH65: 188.302 | AI65: 198.191 | AJ65: 209.724 | AK65: 204.752 | AL65: 173.992 | AM65: 205.254 | AN65: 199.124 | AO65: 228.946 | AP65: 194.819
B66: Current Op Lease Liabilities | G66: =OFFSET(R66,0,MATCH($G$2,$R$3:$AW$3,0)-1) | H66: =G66 | J66: =U66 | K66: =Y66 | L66: =AC66 | M66: =AG66 | N66: =AK66 | O66: =AO66 | R66: 0 | S66: 0 | T66: 0 | U66: 0 | V66: 28.586 | W66: 29.422 | X66: 29.001 | Y66: 27.324 | Z66: 25.92 | AA66: 33.761 | AB66: 32.545 | AC66: 32.75 | AD66: 32.722 | AE66: 31.963 | AF66: 32.813 | AG66: 33.902 | AH66: 34.454 | AI66: 34.667 | AJ66: 33.495 | AK66: 36.444 | AL66: 32.885 | AM66: 33.134 | AN66: 32.17 | AO66: 33.34 | AP66: 32.601
B67: Deferred Revenues | G67: =OFFSET(R67,0,MATCH($G$2,$R$3:$AW$3,0)-1) | H67: =G67 | J67: =U67 | K67: =Y67 | L67: =AC67 | M67: =AG67 | N67: =AK67 | O67: =AO67 | R67: 81.216 | S67: 61.165 | T67: 75.843 | U67: 80.123 | V67: 72.386 | W67: 58.909 | X67: 49.098 | Y67: 42.982 | Z67: 37.027 | AA67: 36.648 | AB67: 31.192 | AC67: 45.406 | AD67: 45.421 | AE67: 44.018 | AF67: 67.214 | AG67: 72.77 | AH67: 68.982 | AI67: 69.668 | AJ67: 82.12 | AK67: 119.305 | AL67: 124.355 | AM67: 130.943 | AN67: 134.577 | AO67: 134.577 | AP67: 153.435
B68: Current Liablities | G68: =SUM(G62:G67) | H68: =SUM(H62:H67) | J68: =SUM(J62:J67) | K68: =SUM(K62:K67) | L68: =SUM(L62:L67) | M68: =SUM(M62:M67) | N68: =SUM(N62:N67) | O68: =SUM(O62:O67) | R68: =SUM(R62:R67) | S68: =SUM(S62:S67) | T68: =SUM(T62:T67) | U68: =SUM(U62:U67) | V68: =SUM(V62:V67) | W68: =SUM(W62:W67) | X68: =SUM(X62:X67) | Y68: =SUM(Y62:Y67) | ... AP68: =SUM(AP62:AP67)
B70: Total Debt | G70: =OFFSET(R70,0,MATCH($G$2,$R$3:$AW$3,0)-1) | H70: =G70 | J70: =U70 | K70: =Y70 | L70: =AC70 | M70: =AG70 | N70: =AK70 | O70: =AO70 | R70: 1423.267 | S70: 1442.513 | T70: 1399.423 | U70: 1410.169 | V70: 1667.457 | W70: 1594.695 | X70: 1434.417 | Y70: 1369.751 | Z70: 1702.476 | AA70: 1642.832 | AB70: 1578.189 | AC70: 1468.546 | AD70: 1348.904 | AE70: 1274.262 | AF70: 1206.193 | AG70: 1161.433 | AH70: 1151.638 | AI70: 1131.849 | AJ70: 1114.86 | AK70: 1076.326 | AL70: 1075.658 | AM70: 990.954 | AN70: 1058.248 | AO70: 1008.527 | AP70: 1051.822
B71: Deferred Income Taxes | G71: =OFFSET(R71,0,MATCH($G$2,$R$3:$AW$3,0)-1) | H71: =G71 | J71: =U71 | K71: =Y71 | L71: =AC71 | M71: =AG71 | N71: =AK71 | O71: =AO71 | R71: 517.421 | S71: 531.284 | T71: 544.882 | U71: 542.785 | V71: 555.414 | W71: 570.954 | X71: 585.507 | Y71: 588.204 | Z71: 582.15 | AA71: 568.816 | AB71: 591.346 | AC71: 606.844 | AD71: 606.561 | AE71: 612.682 | AF71: 552.913 | AG71: 574.152 | AH71: 580.014 | AI71: 590.876 | AJ71: 604.596 | AK71: 625.884 | AL71: 638.438 | AM71: 656.528 | AN71: 672.711 | AO71: 696.557 | AP71: 705.834
B72: Operating Lease Liabilities | G72: =OFFSET(R72,0,MATCH($G$2,$R$3:$AW$3,0)-1) | H72: =G72 | J72: =U72 | K72: =Y72 | L72: =AC72 | M72: =AG72 | N72: =AK72 | O72: =AO72 | R72: 0 | S72: 0 | T72: 0 | U72: 0 | V72: 139.192 | W72: 136.97 | X72: 135.017 | Y72: 139.457 | Z72: 138.884 | AA72: 171.629 | AB72: 167.884 | AC72: 163.496 | AD72: 161.133 | AE72: 153.457 | AF72: 152.615 | AG72: 159.672 | AH72: 156.271 | AI72: 150.355 | AJ72: 144.201 | AK72: 142.14 | AL72: 146.445 | AM72: 142.47 | AN72: 142.237 | AO72: 138.811 | AP72: 136.98
B73: Other LT Liabilities | G73: =OFFSET(R73,0,MATCH($G$2,$R$3:$AW$3,0)-1) | H73: =G73 | J73: =U73 | K73: =Y73 | L73: =AC73 | M73: =AG73 | N73: =AK73 | O73: =AO73 | R73: 100.786 | S73: 111.47 | T73: 108.953 | U73: 94.457 | V73: 90.497 | W73: 82.066 | X73: 81.455 | Y73: 95.978 | Z73: 93.208 | AA73: 103.054 | AB73: 115.269 | AC73: 131.703 | AD73: 129.301 | AE73: 123.863 | AF73: 119.74 | AG73: 71.252 | AH73: 69.169 | AI73: 60.96 | AJ73: 46.717 | AK73: 23.209 | AL73: 14.279 | AM73: 15.521 | AN73: 15.75 | AO73: 15.83 | AP73: 14.066
B74: Total Liabilities | G74: =SUM(G70:G73)+G68 | H74: =SUM(H70:H73)+H68 | J74: =SUM(J70:J73)+J68 | K74: =SUM(K70:K73)+K68 | L74: =SUM(L70:L73)+L68 | M74: =SUM(M70:M73)+M68 | N74: =SUM(N70:N73)+N68 | O74: =SUM(O70:O73)+O68 | R74: =SUM(R70:R73)+R68 | S74: =SUM(S70:S73)+S68 | T74: =SUM(T70:T73)+T68 | U74: =SUM(U70:U73)+U68 | V74: =SUM(V70:V73)+V68 | W74: =SUM(W70:W73)+W68 | X74: =SUM(X70:X73)+X68 | Y74: =SUM(Y70:Y73)+Y68 | ... AP74: =SUM(AP70:AP73)+AP68
B76: Net Debt | G76: =G70+G67-G48 | H76: =H70+H67-H48 | J76: =J70+J67-J48 | K76: =K70+K67-K48 | L76: =L70+L67-L48 | M76: =M70+M67-M48 | N76: =N70+N67-N48 | O76: =O70+O67-O48 | R76: =R70+R62-R48 | S76: =S70+S62-S48 | T76: =T70+T62-T48 | U76: =U70+U62-U48 | V76: =V70+V62-V48 | W76: =W70+W62-W48 | X76: =X70+X62-X48 | Y76: =Y70+Y62-Y48 | ... AP76: =AP70+AP62-AP48
B77: NWC | G77: =G49+G50+G51+G52-G63-G64-G65-G67 | H77: =H49+H50+H51+H52-H63-H64-H65-H67 | J77: =J49+J50+J51+J52-J63-J64-J65-J67 | K77: =K49+K50+K51+K52-K63-K64-K65-K67 | L77: =L49+L50+L51+L52-L63-L64-L65-L67 | M77: =M49+M50+M51+M52-M63-M64-M65-M67 | N77: =N49+N50+N51+N52-N63-N64-N65-N67 | O77: =O49+O50+O51+O52-O63-O64-O65-O67 | R77: =R49+R50+R51+R52-R63-R64-R65-R67 | S77: =S49+S50+S51+S52-S63-S64-S65-S67 | T77: =T49+T50+T51+T52-T63-T64-T65-T67 | U77: =U49+U50+U51+U52-U63-U64-U65-U67 | V77: =V49+V50+V51+V52-V63-V64-V65-V67 | W77: =W49+W50+W51+W52-W63-W64-W65-W67 | X77: =X49+X50+X51+X52-X63-X64-X65-X67 | Y77: =Y49+Y50+Y51+Y52-Y63-Y64-Y65-Y67 | ... AP77: =AP49+AP50+AP51+AP52-AP63-AP64-AP65-AP67
B79: Common Equity | G79: =OFFSET(R79,0,MATCH($G$2,$R$3:$AW$3,0)-1) | H79: =G79 | J79: =U79 | K79: =Y79 | L79: =AC79 | M79: =AG79 | N79: =AK79 | O79: =AO79 | R79: 3138.495 | S79: 3184.35 | T79: 3229.911 | U79: 3213.187 | V79: 3262.336 | W79: 3319.154 | X79: 3371.521 | Y79: 3368.623 | Z79: 3121.482 | AA79: 3048.853 | AB79: 3075.263 | AC79: 3084.306 | AD79: 3085.267 | AE79: 3101.69 | AF79: 2843.746 | AG79: 2886.324 | AH79: 2911.855 | AI79: 2927.387 | AJ79: 2973.057 | AK79: 3042.877 | AL79: 3082.926 | AM79: 3110.644 | AN79: 3156.892 | AO79: 3185.431 | AP79: 3215.648
B80: NCI | G80: =OFFSET(R80,0,MATCH($G$2,$R$3:$AW$3,0)-1) | H80: =G80 | J80: =U80 | K80: =Y80 | L80: =AC80 | M80: =AG80 | N80: =AK80 | O80: =AO80 | R80: 3.373 | S80: 3.373 | T80: 3.237 | U80: 3.237 | V80: 3.072 | W80: 3.018 | X80: 2.977 | Y80: 2.969 | Z80: 3.045 | AA80: 3.104 | AB80: 3.104 | AC80: 3.247 | AD80: 3.477 | AE80: 3.639 | AF80: 2.478 | AG80: 2.458 | AH80: 2.41 | AI80: 2.357 | AJ80: 2.306 | AK80: 2.291 | AL80: 2.214 | AM80: 2.165 | AN80: 1.19 | AO80: 1.246 | AP80: 1.093
B81: Total Equity | G81: =SUM(G79:G80) | H81: =SUM(H79:H80) | J81: =SUM(J79:J80) | K81: =SUM(K79:K80) | L81: =SUM(L79:L80) | M81: =SUM(M79:M80) | N81: =SUM(N79:N80) | O81: =SUM(O79:O80) | R81: =SUM(R79:R80) | S81: =SUM(S79:S80) | T81: =SUM(T79:T80) | U81: =SUM(U79:U80) | V81: =SUM(V79:V80) | W81: =SUM(W79:W80) | X81: =SUM(X79:X80) | Y81: =SUM(Y79:Y80) | ... AP81: =SUM(AP79:AP80)
B83: Total L+E | G83: =SUM(G81,G74) | H83: =SUM(H81,H74) | J83: =SUM(J81,J74) | K83: =SUM(K81,K74) | L83: =SUM(L81,L74) | M83: =SUM(M81,M74) | N83: =SUM(N81,N74) | O83: =SUM(O81,O74) | R83: =SUM(R81,R74) | S83: =SUM(S81,S74) | T83: =SUM(T81,T74) | U83: =SUM(U81,U74) | V83: =SUM(V81,V74) | W83: =SUM(W81,W74) | X83: =SUM(X81,X74) | Y83: =SUM(Y81,Y74) | ... AP83: =SUM(AP81,AP74)
B84: B/S Check | G84: =IF(ROUND(G83-G60,0)=0,"OK",G83-G60) | H84: =IF(ROUND(H83-H60,0)=0,"OK",H83-H60) | J84: =IF(ROUND(J83-J60,1)=0,"OK",J83-J60) | K84: =IF(ROUND(K83-K60,1)=0,"OK",K83-K60) | L84: =IF(ROUND(L83-L60,1)=0,"OK",L83-L60) | M84: =IF(ROUND(M83-M60,1)=0,"OK",M83-M60) | N84: =IF(ROUND(N83-N60,1)=0,"OK",N83-N60) | O84: =IF(ROUND(O83-O60,1)=0,"OK",O83-O60) | R84: =IF(ROUND(R83-R60,1)=0,"OK",R83-R60) | S84: =IF(ROUND(S83-S60,1)=0,"OK",S83-S60) | T84: =IF(ROUND(T83-T60,1)=0,"OK",T83-T60) | U84: =IF(ROUND(U83-U60,1)=0,"OK",U83-U60) | V84: =IF(ROUND(V83-V60,1)=0,"OK",V83-V60) | W84: =IF(ROUND(W83-W60,1)=0,"OK",W83-W60) | X84: =IF(ROUND(X83-X60,1)=0,"OK",X83-X60) | Y84: =IF(ROUND(Y83-Y60,1)=0,"OK",Y83-Y60) | ... AP84: =IF(ROUND(AP83-AP60,1)=0,"OK",AP83-AP60)
A86: x | B86: Segment
B89: Segments
B91: Marine Transport | G91: =OFFSET(R91,0,MATCH($G$2,$R$3:$AW$3,0)-1)*4 | H91: =SUM(OFFSET(R91,0,MATCH($G$2,$R$3:$AW$3,0)-4),OFFSET(R91,0,MATCH($G$2,$R$3:$AW$3,0)-3),OFFSET(R91,0,MATCH($G$2,$R$3:$AW$3,0)-2),OFFSET(R91,0,MATCH($G$2,$R$3:$AW$3,0)-1)) | J91: =SUM(R91:U91) | K91: =SUM(V91:Y91) | L91: =SUM(Z91:AC91) | M91: =SUM(AD91:AG91) | N91: =SUM(AH91:AK91) | O91: =SUM(AL91:AO91) | R91: =R7 | S91: =S7 | T91: =T7 | U91: =U7 | V91: =V7 | W91: =W7 | X91: =X7 | Y91: =Y7 | ... AP91: =AP7
B92: D&S | G92: =OFFSET(R92,0,MATCH($G$2,$R$3:$AW$3,0)-1)*4 | H92: =SUM(OFFSET(R92,0,MATCH($G$2,$R$3:$AW$3,0)-4),OFFSET(R92,0,MATCH($G$2,$R$3:$AW$3,0)-3),OFFSET(R92,0,MATCH($G$2,$R$3:$AW$3,0)-2),OFFSET(R92,0,MATCH($G$2,$R$3:$AW$3,0)-1)) | J92: =SUM(R92:U92) | K92: =SUM(V92:Y92) | L92: =SUM(Z92:AC92) | M92: =SUM(AD92:AG92) | N92: =SUM(AH92:AK92) | O92: =SUM(AL92:AO92) | R92: =R8 | S92: =S8 | T92: =T8 | U92: =U8 | V92: =V8 | W92: =W8 | X92: =X8 | Y92: =Y8 | ... AP92: =AP8
B93: Total Revenues | G93: =SUM(G91:G92) | H93: =SUM(H91:H92) | J93: =SUM(J91:J92) | K93: =SUM(K91:K92) | L93: =SUM(L91:L92) | M93: =SUM(M91:M92) | N93: =SUM(N91:N92) | O93: =SUM(O91:O92) | R93: =SUM(R91:R92) | S93: =SUM(S91:S92) | T93: =SUM(T91:T92) | U93: =SUM(U91:U92) | V93: =SUM(V91:V92) | W93: =SUM(W91:W92) | X93: =SUM(X91:X92) | Y93: =SUM(Y91:Y92) | ... AP93: =SUM(AP91:AP92) | AQ93: 94.9
B94: Check | G94: =IF(ROUND(G93-G9,1)=0,"OK",G93-G9) | H94: =IF(ROUND(H93-H9,1)=0,"OK",H93-H9) | J94: =IF(ROUND(J93-J9,1)=0,"OK",J93-J9) | K94: =IF(ROUND(K93-K9,1)=0,"OK",K93-K9) | L94: =IF(ROUND(L93-L9,1)=0,"OK",L93-L9) | M94: =IF(ROUND(M93-M9,1)=0,"OK",M93-M9) | N94: =IF(ROUND(N93-N9,1)=0,"OK",N93-N9) | O94: =IF(ROUND(O93-O9,1)=0,"OK",O93-O9) | R94: =IF(ROUND(R93-R9,1)=0,"OK",R93-R9) | S94: =IF(ROUND(S93-S9,1)=0,"OK",S93-S9) | T94: =IF(ROUND(T93-T9,1)=0,"OK",T93-T9) | U94: =IF(ROUND(U93-U9,1)=0,"OK",U93-U9) | V94: =IF(ROUND(V93-V9,1)=0,"OK",V93-V9) | W94: =IF(ROUND(W93-W9,1)=0,"OK",W93-W9) | X94: =IF(ROUND(X93-X9,1)=0,"OK",X93-X9) | Y94: =IF(ROUND(Y93-Y9,1)=0,"OK",Y93-Y9) | ... AP94: =IF(ROUND(AP93-AP9,1)=0,"OK",AP93-AP9)
B96: Marine EBIT | G96: =OFFSET(R96,0,MATCH($G$2,$R$3:$AW$3,0)-1)*4 | H96: =SUM(OFFSET(R96,0,MATCH($G$2,$R$3:$AW$3,0)-4),OFFSET(R96,0,MATCH($G$2,$R$3:$AW$3,0)-3),OFFSET(R96,0,MATCH($G$2,$R$3:$AW$3,0)-2),OFFSET(R96,0,MATCH($G$2,$R$3:$AW$3,0)-1)) | J96: =SUM(R96:U96) | K96: =SUM(V96:Y96) | L96: =SUM(Z96:AC96) | M96: =SUM(AD96:AG96) | N96: =SUM(AH96:AK96) | O96: =SUM(AL96:AO96) | R96: 16.18 | S96: 38.228 | T96: 48.517 | U96: 44.491 | V96: 35.424 | W96: 53.243 | X96: 72.697 | Y96: 54.478 | Z96: 50.716 | AA96: 51.375 | AB96: 32.409 | AC96: 29.156 | AD96: 1.94 | AE96: 18.478 | AF96: 16.915 | AG96: 25.682 | AH96: 16.935 | AI96: 30.817 | AJ96: 41.713 | AK96: 46.719 | AL96: 43.036 | AM96: 64.251 | AN96: 63.464 | AO96: 68.189 | AP96: 82.983
B97: Marine D&A | G97: =OFFSET(R97,0,MATCH($G$2,$R$3:$AW$3,0)-1)*4 | H97: =SUM(OFFSET(R97,0,MATCH($G$2,$R$3:$AW$3,0)-4),OFFSET(R97,0,MATCH($G$2,$R$3:$AW$3,0)-3),OFFSET(R97,0,MATCH($G$2,$R$3:$AW$3,0)-2),OFFSET(R97,0,MATCH($G$2,$R$3:$AW$3,0)-1)) | J97: =SUM(R97:U97) | K97: =SUM(V97:Y97) | L97: =SUM(Z97:AC97) | M97: =SUM(AD97:AG97) | N97: =SUM(AH97:AK97) | O97: =SUM(AL97:AO97) | R97: 43.34 | S97: 44.782 | T97: 47.144 | U97: 47.041 | V97: 45.324 | W97: 45.092 | X97: 44.445 | Y97: 44.881 | Z97: 45.299 | AA97: 46.684 | AB97: 47.312 | AC97: 47.503 | AD97: 47.579 | AE97: 47.501 | AF97: 46.48 | AG97: 44.419 | AH97: 44.086 | AI97: 44.211 | AJ97: 44.37 | AK97: 44.884 | AL97: 45.142 | AM97: 45.526 | AN97: 46.656 | AO97: 46.901 | AP97: 47.849
B98: Marine Reported EBITDA | G98: =SUM(G96:G97) | H98: =SUM(H96:H97) | J98: =SUM(J96:J97) | K98: =SUM(K96:K97) | L98: =SUM(L96:L97) | M98: =SUM(M96:M97) | N98: =SUM(N96:N97) | O98: =SUM(O96:O97) | R98: =SUM(R96:R97) | S98: =SUM(S96:S97) | T98: =SUM(T96:T97) | U98: =SUM(U96:U97) | V98: =SUM(V96:V97) | W98: =SUM(W96:W97) | X98: =SUM(X96:X97) | Y98: =SUM(Y96:Y97) | ... AP98: =SUM(AP96:AP97)
B99: Y/Y % | K99: =K98/J98-1 | L99: =L98/K98-1 | M99: =M98/L98-1 | N99: =N98/M98-1 | O99: =O98/N98-1 | V99: =V98/R98-1 | W99: =W98/S98-1 | X99: =X98/T98-1 | Y99: =Y98/U98-1 | Z99: =Z98/V98-1 | AA99: =AA98/W98-1 | AB99: =AB98/X98-1 | AC99: =AC98/Y98-1 | ... AP99: =AP98/AL98-1
B101: D&S EBIT | G101: =OFFSET(R101,0,MATCH($G$2,$R$3:$AW$3,0)-1)*4 | H101: =SUM(OFFSET(R101,0,MATCH($G$2,$R$3:$AW$3,0)-4),OFFSET(R101,0,MATCH($G$2,$R$3:$AW$3,0)-3),OFFSET(R101,0,MATCH($G$2,$R$3:$AW$3,0)-2),OFFSET(R101,0,MATCH($G$2,$R$3:$AW$3,0)-1)) | J101: =SUM(R101:U101) | K101: =SUM(V101:Y101) | L101: =SUM(Z101:AC101) | M101: =SUM(AD101:AG101) | N101: =SUM(AH101:AK101) | O101: =SUM(AL101:AO101) | R101: 36.965 | S101: 40.19 | T101: 23.914 | U101: 28.236 | V101: 37.609 | W101: 23.128 | X101: 9.132 | Y101: -2.668 | Z101: 3.718 | AA101: -14.147 | AB101: 1.1055 | AC101: -2.866 | AD101: 2.911 | AE101: 6.156 | AF101: 11.039 | AG101: 7.501 | AH101: 10.971 | AI101: 16.737 | AJ101: 22.268 | AK101: 17.061 | AL101: 22.792 | AM101: 29.842 | AN101: 33.194 | AO101: 28.653 | AP101: 22.014
B102: D&S D&A | G102: =OFFSET(R102,0,MATCH($G$2,$R$3:$AW$3,0)-1)*4 | H102: =SUM(OFFSET(R102,0,MATCH($G$2,$R$3:$AW$3,0)-4),OFFSET(R102,0,MATCH($G$2,$R$3:$AW$3,0)-3),OFFSET(R102,0,MATCH($G$2,$R$3:$AW$3,0)-2),OFFSET(R102,0,MATCH($G$2,$R$3:$AW$3,0)-1)) | J102: =SUM(R102:U102) | K102: =SUM(V102:Y102) | L102: =SUM(Z102:AC102) | M102: =SUM(AD102:AG102) | N102: =SUM(AH102:AK102) | O102: =SUM(AL102:AO102) | R102: 10.032 | S102: 9.877 | T102: 9.964 | U102: 9.476 | V102: 9.018 | W102: 9.064 | X102: 9.085 | Y102: 8.831 | Z102: 9.336 | AA102: 6.633 | AB102: 6.283 | AC102: 6.003 | AD102: 5.881 | AE102: 5.84 | AF102: 5.018 | AG102: 3.834 | AH102: 4.106 | AI102: 4.133 | AJ102: 4.274 | AK102: 4.263 | AL102: 4.245 | AM102: 4.394 | AN102: 5.017 | AO102: 6.186 | AP102: 7.844
B103: D&S Reported EBITDA | G103: =SUM(G101:G102) | H103: =SUM(H101:H102) | J103: =SUM(J101:J102) | K103: =SUM(K101:K102) | L103: =SUM(L101:L102) | M103: =SUM(M101:M102) | N103: =SUM(N101:N102) | O103: =SUM(O101:O102) | R103: =SUM(R101:R102) | S103: =SUM(S101:S102) | T103: =SUM(T101:T102) | U103: =SUM(U101:U102) | V103: =SUM(V101:V102) | W103: =SUM(W101:W102) | X103: =SUM(X101:X102) | Y103: =SUM(Y101:Y102) | ... AP103: =SUM(AP101:AP102)
B104: Y/Y % | K104: =K103/J103-1 | L104: =L103/K103-1 | M104: =M103/L103-1 | N104: =N103/M103-1 | O104: =O103/N103-1 | V104: =V103/R103-1 | W104: =W103/S103-1 | X104: =X103/T103-1 | Y104: =Y103/U103-1 | Z104: =Z103/V103-1 | AA104: =AA103/W103-1 | AB104: =AB103/X103-1 | AC104: =AC103/Y103-1 | ... AP104: =AP103/AL103-1
B106: Marine EBITDA | G106: =OFFSET(R106,0,MATCH($G$2,$R$3:$AW$3,0)-1)*4 | H106: =SUM(OFFSET(R106,0,MATCH($G$2,$R$3:$AW$3,0)-4),OFFSET(R106,0,MATCH($G$2,$R$3:$AW$3,0)-3),OFFSET(R106,0,MATCH($G$2,$R$3:$AW$3,0)-2),OFFSET(R106,0,MATCH($G$2,$R$3:$AW$3,0)-1)) | J106: =SUM(R106:U106) | K106: =SUM(V106:Y106) | L106: =SUM(Z106:AC106) | M106: =SUM(AD106:AG106) | N106: =SUM(AH106:AK106) | O106: =SUM(AL106:AO106) | R106: =R98 | S106: =S98 | T106: =T98 | U106: =U98 | V106: =V98 | W106: =W98 | X106: =X98 | Y106: =Y98 | ... AP106: =AP98
B107: D&S EBITDA | G107: =OFFSET(R107,0,MATCH($G$2,$R$3:$AW$3,0)-1)*4 | H107: =SUM(OFFSET(R107,0,MATCH($G$2,$R$3:$AW$3,0)-4),OFFSET(R107,0,MATCH($G$2,$R$3:$AW$3,0)-3),OFFSET(R107,0,MATCH($G$2,$R$3:$AW$3,0)-2),OFFSET(R107,0,MATCH($G$2,$R$3:$AW$3,0)-1)) | J107: =SUM(R107:U107) | K107: =SUM(V107:Y107) | L107: =SUM(Z107:AC107) | M107: =SUM(AD107:AG107) | N107: =SUM(AH107:AK107) | O107: =SUM(AL107:AO107) | R107: =R103 | S107: =S103 | T107: =T103 | U107: =U103 | V107: =V103 | W107: =W103 | X107: =X103 | Y107: =Y103 | ... AP107: =AP103
B108: Implied Overhead | G108: =OFFSET(R108,0,MATCH($G$2,$R$3:$AW$3,0)-1)*4 | H108: =SUM(OFFSET(R108,0,MATCH($G$2,$R$3:$AW$3,0)-4),OFFSET(R108,0,MATCH($G$2,$R$3:$AW$3,0)-3),OFFSET(R108,0,MATCH($G$2,$R$3:$AW$3,0)-2),OFFSET(R108,0,MATCH($G$2,$R$3:$AW$3,0)-1)) | J108: =SUM(R108:U108) | K108: =SUM(V108:Y108) | L108: =SUM(Z108:AC108) | M108: =SUM(AD108:AG108) | N108: =SUM(AH108:AK108) | O108: =SUM(AL108:AO108) | R108: =R109-R107-R106 | S108: =S109-S107-S106 | T108: =T109-T107-T106 | U108: =U109-U107-U106 | V108: =V109-V107-V106 | W108: =W109-W107-W106 | X108: =X109-X107-X106 | Y108: =Y109-Y107-Y106 | ... AP108: =AP109-AP107-AP106
B109: Total EBITDA | G109: =SUM(G106:G108) | H109: =SUM(H106:H108) | J109: =SUM(J106:J108) | K109: =SUM(K106:K108) | L109: =SUM(L106:L108) | M109: =SUM(M106:M108) | N109: =SUM(N106:N108) | O109: =SUM(O106:O108) | R109: =R23 | S109: =S23 | T109: =T23 | U109: =U23 | V109: =V23 | W109: =W23 | X109: =X23 | Y109: =Y23 | ... AP109: =AP23
B110: Check | K110: =K109/J109-1 | L110: =L109/K109-1 | M110: =M109/L109-1 | N110: =N109/M109-1 | O110: =O109/N109-1 | V110: =V109/R109-1 | W110: =W109/S109-1 | X110: =X109/T109-1 | Y110: =Y109/U109-1 | Z110: =Z109/V109-1 | AA110: =AA109/W109-1 | AB110: =AB109/X109-1 | AC110: =AC109/Y109-1 | ... AP110: =AP109/AL109-1
B112: Ton Miles (mm) | G112: =OFFSET(R112,0,MATCH($G$2,$R$3:$AW$3,0)-1)*4 | H112: =SUM(OFFSET(R112,0,MATCH($G$2,$R$3:$AW$3,0)-4),OFFSET(R112,0,MATCH($G$2,$R$3:$AW$3,0)-3),OFFSET(R112,0,MATCH($G$2,$R$3:$AW$3,0)-2),OFFSET(R112,0,MATCH($G$2,$R$3:$AW$3,0)-1)) | J112: =SUM(R112:U112) | K112: =SUM(V112:Y112) | L112: =SUM(Z112:AC112) | M112: =SUM(AD112:AG112) | N112: =SUM(AH112:AK112) | O112: =SUM(AL112:AO112) | R112: 3182 | S112: 3921 | T112: 3721 | U112: 3677 | V112: 3146 | W112: 3707 | X112: 3958 | Y112: 3800 | Z112: 3619 | AA112: 3688 | AB112: 2794 | AC112: 2905 | AD112: 2981 | AE112: 3478 | AF112: 3393 | AG112: 3844 | AH112: 3168 | AI112: 3536 | AJ112: 3706 | AK112: 3365 | AL112: 3440 | AM112: 3500 | AN112: 3291 | AO112: 3340 | AP112: 3304
B113: Revenue/ Ton Mile (cents/tm) | G113: =G114/G112*100 | H113: =H114/H112*100 | J113: =J114/J112*100 | K113: =K114/K112*100 | L113: =L114/L112*100 | M113: =M114/M112*100 | N113: =N114/N112*100 | O113: =O114/O112*100 | R113: 8 | S113: 7.3 | T113: 7.7 | U113: 7.9 | V113: 9 | W113: 8.4 | X113: 8 | Y113: 8.2 | Z113: 8.8 | AA113: 8.2 | AB113: 8.9 | AC113: 7.8 | AD113: 7.5 | AE113: 7.3 | AF113: 7.5 | AG113: 7.1 | AH113: 8.8 | AI113: 9 | AJ113: 9.3 | AK113: 10 | AL113: 9.8 | AM113: 10.1 | AN113: 10.7 | AO113: 11.2 | AP113: 11.7
B114: Inland Revenues | G114: =OFFSET(R114,0,MATCH($G$2,$R$3:$AW$3,0)-1)*4 | H114: =SUM(OFFSET(R114,0,MATCH($G$2,$R$3:$AW$3,0)-4),OFFSET(R114,0,MATCH($G$2,$R$3:$AW$3,0)-3),OFFSET(R114,0,MATCH($G$2,$R$3:$AW$3,0)-2),OFFSET(R114,0,MATCH($G$2,$R$3:$AW$3,0)-1)) | J114: =SUM(R114:U114) | K114: =SUM(V114:Y114) | L114: =SUM(Z114:AC114) | M114: =SUM(AD114:AG114) | N114: =SUM(AH114:AK114) | O114: =SUM(AL114:AO114) | R114: =R112*R113/100 | S114: =S112*S113/100 | T114: =T112*T113/100 | U114: =U112*U113/100 | V114: =V112*V113/100 | W114: =W112*W113/100 | X114: =X112*X113/100 | Y114: =Y112*Y113/100 | ... AP114: =AP112*AP113/100
B115: Coastal Revenues | G115: =G91-G114 | H115: =H91-H114 | J115: =J91-J114 | K115: =K91-K114 | L115: =L91-L114 | M115: =M91-M114 | N115: =N91-N114 | O115: =O91-O114 | R115: =R91-R114 | S115: =S91-S114 | T115: =T91-T114 | U115: =U91-U114 | V115: =V91-V114 | W115: =W91-W114 | X115: =X91-X114 | Y115: =Y91-Y114 | ... AP115: =AP91-AP114
A118: x | B118: CFS
B120: As Reported EBITDA | G120: =OFFSET(R120,0,MATCH($G$2,$R$3:$AW$3,0)-1)*4 | H120: =SUM(OFFSET(R120,0,MATCH($G$2,$R$3:$AW$3,0)-4),OFFSET(R120,0,MATCH($G$2,$R$3:$AW$3,0)-3),OFFSET(R120,0,MATCH($G$2,$R$3:$AW$3,0)-2),OFFSET(R120,0,MATCH($G$2,$R$3:$AW$3,0)-1)) | J120: =SUM(R120:U120) | K120: =SUM(V120:Y120) | L120: =SUM(Z120:AC120) | M120: =M23 | N120: =N23 | O120: =O23 | R120: =R23 | S120: =S23 | T120: =T23 | U120: =U23 | V120: =V23 | W120: =W23 | X120: =X23 | Y120: =Y23 | ... AP120: =AP23
B121: (+) Other Income | G121: =OFFSET(R121,0,MATCH($G$2,$R$3:$AW$3,0)-1)*4 | H121: =SUM(OFFSET(R121,0,MATCH($G$2,$R$3:$AW$3,0)-4),OFFSET(R121,0,MATCH($G$2,$R$3:$AW$3,0)-3),OFFSET(R121,0,MATCH($G$2,$R$3:$AW$3,0)-2),OFFSET(R121,0,MATCH($G$2,$R$3:$AW$3,0)-1)) | J121: =SUM(R121:U121) | K121: =SUM(V121:Y121) | L121: =SUM(Z121:AC121) | M121: =M28 | N121: =N28 | O121: =O28 | R121: =R28 | S121: =S28 | T121: =T28 | U121: =U28 | V121: =V28 | W121: =W28 | X121: =X28 | Y121: =Y28 | ... AP121: =AP28
B122: (-) Cash Interest | G122: =OFFSET(R122,0,MATCH($G$2,$R$3:$AW$3,0)-1)*4 | H122: =SUM(OFFSET(R122,0,MATCH($G$2,$R$3:$AW$3,0)-4),OFFSET(R122,0,MATCH($G$2,$R$3:$AW$3,0)-3),OFFSET(R122,0,MATCH($G$2,$R$3:$AW$3,0)-2),OFFSET(R122,0,MATCH($G$2,$R$3:$AW$3,0)-1)) | J122: =- 40.772 | K122: =-55.766 | L122: =-48.721 | M122: -40.878 | N122: -42.816 | O122: -49.317 | AH122: -18.022 | AI122: =-20.161-AH122 | AJ122: =-39.754-AI122-AH122 | AK122: =N122-SUM(AH122:AJ122) | AL122: -20.293 | AM122: =-24.553-AL122 | AN122: =-45.276-AM122-AL122 | AO122: =O122-SUM(AL122:AN122) | AP122: -21.511
B123: (-) Cash Tax | G123: =OFFSET(R123,0,MATCH($G$2,$R$3:$AW$3,0)-1)*4 | H123: =SUM(OFFSET(R123,0,MATCH($G$2,$R$3:$AW$3,0)-4),OFFSET(R123,0,MATCH($G$2,$R$3:$AW$3,0)-3),OFFSET(R123,0,MATCH($G$2,$R$3:$AW$3,0)-2),OFFSET(R123,0,MATCH($G$2,$R$3:$AW$3,0)-1)) | J123: =SUM(R123:U123) | K123: =SUM(V123:Y123) | L123: =SUM(Z123:AC123) | M123: 116.648 | N123: -2.553 | O123: 65.787 | AH123: =0.024 | AI123: =-1.19-AH123 | AJ123: =2.097-AI123-AH123 | AK123: =N123-SUM(AH123:AJ123) | AL123: -0.694 | AM123: =67.921-AL123 | AN123: =67.118-AM123-AL123 | AO123: =O123-SUM(AL123:AN123) | AP123: -1.062
B124: SBC | G124: =OFFSET(R124,0,MATCH($G$2,$R$3:$AW$3,0)-1)*4 | H124: =SUM(OFFSET(R124,0,MATCH($G$2,$R$3:$AW$3,0)-4),OFFSET(R124,0,MATCH($G$2,$R$3:$AW$3,0)-3),OFFSET(R124,0,MATCH($G$2,$R$3:$AW$3,0)-2),OFFSET(R124,0,MATCH($G$2,$R$3:$AW$3,0)-1)) | J124: =SUM(R124:U124) | K124: =SUM(V124:Y124) | L124: =SUM(Z124:AC124) | M124: 15.713 | N124: 13.865 | O124: 14.941 | AH124: 5.965 | AI124: =8.555-AH124 | AJ124: =11.448-AI124-AH124 | AK124: =N124-SUM(AH124:AJ124) | AL124: 5.808 | AM124: =8.912-AL124 | AN124: =12.31-AM124-AL124 | AO124: =O124-SUM(AL124:AN124) | AP124: 6.408
B125: Amortization of maint. Costs | G125: =OFFSET(R125,0,MATCH($G$2,$R$3:$AW$3,0)-1)*4 | H125: =SUM(OFFSET(R125,0,MATCH($G$2,$R$3:$AW$3,0)-4),OFFSET(R125,0,MATCH($G$2,$R$3:$AW$3,0)-3),OFFSET(R125,0,MATCH($G$2,$R$3:$AW$3,0)-2),OFFSET(R125,0,MATCH($G$2,$R$3:$AW$3,0)-1)) | J125: =SUM(R125:U125) | K125: =SUM(V125:Y125) | L125: =SUM(Z125:AC125) | M125: 33.213 | N125: 29.031 | O125: 28.966 | AH125: 7.113 | AI125: =14.405-AH125 | AJ125: =21.677-AI125-AH125 | AK125: =N125-SUM(AH125:AJ125) | AL125: 6.992 | AM125: =14.043-AL125 | AN125: =21.05-AM125-AL125 | AO125: =O125-SUM(AL125:AN125) | AP125: 8.345
B126: Working Capital Ex-Tax | G126: =OFFSET(R126,0,MATCH($G$2,$R$3:$AW$3,0)-1)*4 | H126: =SUM(OFFSET(R126,0,MATCH($G$2,$R$3:$AW$3,0)-4),OFFSET(R126,0,MATCH($G$2,$R$3:$AW$3,0)-3),OFFSET(R126,0,MATCH($G$2,$R$3:$AW$3,0)-2),OFFSET(R126,0,MATCH($G$2,$R$3:$AW$3,0)-1)) | J126: =SUM(R126:U126) | K126: =SUM(V126:Y126) | L126: =SUM(Z126:AC126) | M126: =29.126-19.248-38.335+0.48+15.951+27.974-M123 | N126: =-31.55-127.095-27.801+1.975+75.996+5.1-N123 | O126: =-50.135+7.695-37.688+71.604-18.271+31.703-O123 | AH126: =-50.782-AH123 | AI126: =-82.51-AH126-AI123 | AJ126: =-126.252-AI126-AH126-AJ123 | AK126: =N126-SUM(AH126:AJ126) | AL126: =-98.321-AL123 | AM126: =-22.878-AL126-AM123 | AN126: =-64.767-AM126-AL126-AN123 | AO126: =O126-SUM(AL126:AN126) | AP126: =-30.04-AP123
B127: Other | G127: =OFFSET(R127,0,MATCH($G$2,$R$3:$AW$3,0)-1)*4 | H127: =SUM(OFFSET(R127,0,MATCH($G$2,$R$3:$AW$3,0)-4),OFFSET(R127,0,MATCH($G$2,$R$3:$AW$3,0)-3),OFFSET(R127,0,MATCH($G$2,$R$3:$AW$3,0)-2),OFFSET(R127,0,MATCH($G$2,$R$3:$AW$3,0)-1)) | J127: =SUM(R127:U127) | K127: =SUM(V127:Y127) | L127: =SUM(Z127:AC127) | M127: -0.64 | N127: -0.283 | O127: =-3.338 | AH127: -3.48 | AI127: =-6.412-AH127 | AJ127: =-7.608-AI127-AH127 | AK127: =N127-SUM(AH127:AJ127) | AL127: -2.302 | AM127: =-3.111-AL127 | AN127: =-8.001-AM127-AL127 | AO127: =O127-SUM(AL127:AN127) | AP127: 1.607
B128: Plug | G128: =OFFSET(R128,0,MATCH($G$2,$R$3:$AW$3,0)-1)*4 | H128: =SUM(OFFSET(R128,0,MATCH($G$2,$R$3:$AW$3,0)-4),OFFSET(R128,0,MATCH($G$2,$R$3:$AW$3,0)-3),OFFSET(R128,0,MATCH($G$2,$R$3:$AW$3,0)-2),OFFSET(R128,0,MATCH($G$2,$R$3:$AW$3,0)-1)) | J128: =J129-SUM(J120:J127) | K128: =K129-SUM(K120:K127) | L128: =L129-SUM(L120:L127) | M128: =M129-SUM(M120:M127) | N128: =N129-SUM(N120:N127) | O128: =O129-SUM(O120:O127) | R128: =R129-SUM(R120:R127) | S128: =S129-SUM(S120:S127) | T128: =T129-SUM(T120:T127) | U128: =U129-SUM(U120:U127) | V128: =V129-SUM(V120:V127) | W128: =W129-SUM(W120:W127) | X128: =X129-SUM(X120:X127) | Y128: =Y129-SUM(Y120:Y127) | ... AP128: =AP129-SUM(AP120:AP127)
...

Sheet BBPTACShadowWks0002
K2: ='Marine DCF'!K2 | L2: ='Marine DCF'!L2 | M2: ='Marine DCF'!M2 | N2: ='Marine DCF'!N2 | O2: ='Marine DCF'!O2 | P2: ='Marine DCF'!P2 | Q2: ='Marine DCF'!Q2 | R2: ='Marine DCF'!R2
E3: ='Marine DCF'!E3 | F3: ='Marine DCF'!F3 | G3: ='Marine DCF'!G3 | H3: ='Marine DCF'!H3 | I3: ='Marine DCF'!I3 | J3: ='Marine DCF'!J3 | K3: ='Marine DCF'!K3 | L3: ='Marine DCF'!L3 | ... Q3: ='Marine DCF'!Q3
E4: ='Marine DCF'!E4 | F4: ='Marine DCF'!F4 | G4: ='Marine DCF'!G4 | H4: ='Marine DCF'!H4 | I4: ='Marine DCF'!I4 | J4: ='Marine DCF'!J4 | K4: ='Marine DCF'!K4 | L4: ='Marine DCF'!L4 | ... R4: ='Marine DCF'!R4
F5: ='Marine DCF'!F5 | G5: ='Marine DCF'!G5 | H5: ='Marine DCF'!H5 | I5: ='Marine DCF'!I5 | J5: ='Marine DCF'!J5 | K5: ='Marine DCF'!K5 | L5: ='Marine DCF'!L5 | M5: ='Marine DCF'!M5 | ... Q5: ='Marine DCF'!Q5
E6: ='Marine DCF'!E6 | F6: ='Marine DCF'!F6 | G6: ='Marine DCF'!G6 | H6: ='Marine DCF'!H6 | I6: ='Marine DCF'!I6 | J6: ='Marine DCF'!J6 | K6: ='Marine DCF'!K6 | L6: ='Marine DCF'!L6 | ... R6: ='Marine DCF'!R6
F7: ='Marine DCF'!F7 | G7: ='Marine DCF'!G7 | H7: ='Marine DCF'!H7 | I7: ='Marine DCF'!I7 | J7: ='Marine DCF'!J7 | K7: ='Marine DCF'!K7 | L7: ='Marine DCF'!L7 | M7: ='Marine DCF'!M7 | ... Q7: ='Marine DCF'!Q7
E8: ='Marine DCF'!$E$8 | F8: ='Marine DCF'!F8 | G8: ='Marine DCF'!G8 | H8: ='Marine DCF'!H8 | I8: ='Marine DCF'!I8 | J8: ='Marine DCF'!J8 | K8: ='Marine DCF'!K8 | L8: ='Marine DCF'!L8 | M8: ='Marine DCF'!M8 | ... R8: ='Marine DCF'!R8
F9: ='Marine DCF'!F9 | G9: ='Marine DCF'!G9 | H9: ='Marine DCF'!H9 | I9: ='Marine DCF'!I9 | J9: ='Marine DCF'!J9 | K9: ='Marine DCF'!K9 | L9: ='Marine DCF'!L9 | M9: ='Marine DCF'!M9 | ... R9: ='Marine DCF'!R9
E10: ='Marine DCF'!E10 | F10: ='Marine DCF'!F10 | G10: ='Marine DCF'!G10 | H10: ='Marine DCF'!H10 | I10: ='Marine DCF'!I10 | J10: ='Marine DCF'!J10 | K10: ='Marine DCF'!K10 | L10: ='Marine DCF'!L10 | ... R10: ='Marine DCF'!R10
F11: ='Marine DCF'!F11 | G11: ='Marine DCF'!G11 | H11: ='Marine DCF'!H11 | I11: ='Marine DCF'!I11 | J11: ='Marine DCF'!J11 | K11: ='Marine DCF'!K11 | L11: ='Marine DCF'!L11 | M11: ='Marine DCF'!M11 | ... R11: ='Marine DCF'!R11
E12: ='Marine DCF'!E12 | F12: ='Marine DCF'!F12 | G12: ='Marine DCF'!G12 | H12: ='Marine DCF'!H12 | I12: ='Marine DCF'!I12 | J12: ='Marine DCF'!J12 | K12: ='Marine DCF'!K12 | L12: ='Marine DCF'!L12 | ... R12: ='Marine DCF'!R12
E14: ='Marine DCF'!E14 | F14: ='Marine DCF'!F14 | G14: ='Marine DCF'!G14 | H14: ='Marine DCF'!H14 | I14: ='Marine DCF'!I14 | J14: ='Marine DCF'!J14 | K14: ='Marine DCF'!K14 | L14: ='Marine DCF'!L14 | ... R14: ='Marine DCF'!R14
E15: ='Marine DCF'!E15 | F15: ='Marine DCF'!F15 | G15: ='Marine DCF'!G15 | H15: ='Marine DCF'!H15 | I15: ='Marine DCF'!I15 | J15: ='Marine DCF'!J15 | K15: ='Marine DCF'!K15 | L15: ='Marine DCF'!L15 | ... R15: ='Marine DCF'!R15
E16: ='Marine DCF'!E16 | F16: ='Marine DCF'!F16 | G16: ='Marine DCF'!G16 | H16: ='Marine DCF'!H16 | I16: ='Marine DCF'!I16 | J16: ='Marine DCF'!J16 | K16: ='Marine DCF'!K16 | L16: ='Marine DCF'!L16 | ... R16: ='Marine DCF'!R16
F17: ='Marine DCF'!F17 | G17: ='Marine DCF'!G17 | H17: ='Marine DCF'!H17 | I17: ='Marine DCF'!I17 | J17: ='Marine DCF'!J17 | K17: ='Marine DCF'!K17 | L17: ='Marine DCF'!L17 | M17: ='Marine DCF'!M17 | ... Q17: ='Marine DCF'!Q17
E18: ='Marine DCF'!E18 | F18: ='Marine DCF'!F18 | G18: ='Marine DCF'!G18 | H18: ='Marine DCF'!H18 | I18: ='Marine DCF'!I18 | J18: ='Marine DCF'!J18 | K18: ='Marine DCF'!K18 | L18: ='Marine DCF'!L18 | ... R18: ='Marine DCF'!R18
E19: ='Marine DCF'!E19 | F19: ='Marine DCF'!F19 | G19: ='Marine DCF'!G19 | H19: ='Marine DCF'!H19 | I19: ='Marine DCF'!I19 | J19: ='Marine DCF'!J19 | K19: ='Marine DCF'!K19 | L19: ='Marine DCF'!L19 | ... R19: ='Marine DCF'!R19 | S19: ='Marine DCF'!$S$19
E20: ='Marine DCF'!E20 | F20: ='Marine DCF'!F20 | G20: ='Marine DCF'!G20 | H20: ='Marine DCF'!H20 | I20: ='Marine DCF'!I20 | J20: ='Marine DCF'!J20 | K20: ='Marine DCF'!K20 | L20: ='Marine DCF'!L20 | ... R20: ='Marine DCF'!R20
E21: ='Marine DCF'!E21 | F21: ='Marine DCF'!F21 | G21: ='Marine DCF'!G21 | H21: ='Marine DCF'!H21 | I21: ='Marine DCF'!I21 | J21: ='Marine DCF'!J21 | K21: ='Marine DCF'!K21 | L21: ='Marine DCF'!L21 | ... R21: ='Marine DCF'!R21
E22: ='Marine DCF'!E22 | F22: ='Marine DCF'!F22 | G22: ='Marine DCF'!G22 | H22: ='Marine DCF'!H22 | I22: ='Marine DCF'!I22 | J22: ='Marine DCF'!J22 | K22: ='Marine DCF'!K22 | L22: ='Marine DCF'!L22 | ... R22: ='Marine DCF'!R22
K24: ='Marine DCF'!K24 | L24: ='Marine DCF'!L24 | M24: ='Marine DCF'!M24 | N24: ='Marine DCF'!N24 | O24: ='Marine DCF'!O24 | P24: ='Marine DCF'!P24 | Q24: ='Marine DCF'!Q24 | R24: ='Marine DCF'!R24 | S24: ='Marine DCF'!S24
K26: ='Marine DCF'!K25 | L26: ='Marine DCF'!L25 | M26: ='Marine DCF'!M25 | N26: ='Marine DCF'!N25 | O26: ='Marine DCF'!O25 | P26: ='Marine DCF'!P25 | Q26: ='Marine DCF'!Q25 | R26: ='Marine DCF'!R25 | S26: ='Marine DCF'!S26
E28: ='Marine DCF'!E27
E29: ='Marine DCF'!#REF!
E30: ='Marine DCF'!E28

Sheet Marine DCF
A2: x | B2: Marine Transport DCF | K2: 1 | L2: =K2+1 | M2: =L2+1 | N2: =M2+1 | O2: =N2+1 | P2: =O2+1 | Q2: =P2+1 | R2: =Q2+1
E3: 2018 | F3: =E3+1 | G3: =F3+1 | H3: =G3+1 | I3: =H3+1 | J3: =I3+1 | K3: =J3+1 | L3: =K3+1 | M3: =L3+1 | ... Q3: =P3+1 | R3: LT Normalized
B4: Ton Miles | E4: ='Model Shell'!J112 | F4: ='Model Shell'!K112 | G4: ='Model Shell'!L112 | H4: ='Model Shell'!M112 | I4: ='Model Shell'!N112 | J4: ='Model Shell'!O112 | K4: =J4*(1+K5) | L4: =K4*(1+L5) | M4: =L4*(1+M5) | N4: =M4*(1+N5) | O4: =N4*(1+O5) | P4: =O4*(1+P5) | Q4: =P4*(1+Q5) | R4: =Q4
C5: % Growth | F5: =F4/E4-1 | G5: =G4/F4-1 | H5: =H4/G4-1 | I5: =I4/H4-1 | J5: =J4/I4-1 | K5: 0.02 | L5: 0.02 | M5: 0.02 | N5: 0.02 | O5: 0.02 | P5: 0.02 | Q5: 0.02
B6: Pricing | E6: ='Model Shell'!J113 | F6: ='Model Shell'!K113 | G6: ='Model Shell'!L113 | H6: ='Model Shell'!M113 | I6: ='Model Shell'!N113 | J6: ='Model Shell'!O113 | K6: =J6*(1+K7) | L6: =K6*(1+L7) | M6: =L6*(1+M7) | N6: =M6*(1+N7) | O6: =N6*(1+O7) | P6: =O6*(1+P7) | Q6: =P6*(1+Q7) | R6: =Q6
C7: % Growth | F7: =F6/E6-1 | G7: =G6/F6-1 | H7: =H6/G6-1 | I7: =I6/H6-1 | J7: =J6/I6-1 | K7: 0.07 | L7: 0.07 | M7: 0.05 | N7: 0.04 | O7: 0.03 | P7: 0 | Q7: 0
B8: Inland Revenue | E8: =E6*E4/100 | F8: =F6*F4/100 | G8: =G6*G4/100 | H8: =H6*H4/100 | I8: =I6*I4/100 | J8: =J6*J4/100 | K8: =K6*K4/100 | L8: =L6*L4/100 | ... R8: =R6*R4/100
F9: =F8/E8-1 | G9: =G8/F8-1 | H9: =H8/G8-1 | I9: =I8/H8-1 | J9: =J8/I8-1 | K9: =K8/J8-1 | L9: =L8/K8-1 | M9: =M8/L8-1 | ... R9: =R8/Q8-1
B10: (+) Coastal Revenue | E10: ='Model Shell'!J115 | F10: ='Model Shell'!K115 | G10: ='Model Shell'!L115 | H10: ='Model Shell'!M115 | I10: ='Model Shell'!N115 | J10: ='Model Shell'!O115 | K10: =J10*(1+K11) | L10: =K10*(1+L11) | M10: =L10*(1+M11) | N10: =M10*(1+N11) | O10: =N10*(1+O11) | P10: =O10*(1+P11) | Q10: =P10*(1+Q11) | R10: =350
C11: % Growth | F11: =F10/E10-1 | G11: =G10/F10-1 | H11: =H10/G10-1 | I11: =I10/H10-1 | J11: =J10/I10-1 | K11: 0.04 | L11: 0 | M11: 0 | N11: 0 | O11: 0 | P11: 0 | Q11: 0 | R11: =R10/Q10-1
B12: Total Revenue | E12: =E10+E8 | F12: =F10+F8 | G12: =G10+G8 | H12: =H10+H8 | I12: =I10+I8 | J12: =J10+J8 | K12: =K10+K8 | L12: =L10+L8 | ... R12: =R10+R8
B14: EBIT | E14: =E12*E15 | F14: =F12*F15 | G14: =G12*G15 | H14: =H12*H15 | I14: =I12*I15 | J14: =J12*J15 | K14: =K12*K15 | L14: =L12*L15 | ... R14: =R12*R15
C15: EBIT Margin % | E15: ='Model Shell'!J96/'Model Shell'!J91 | F15: ='Model Shell'!K96/'Model Shell'!K91 | G15: ='Model Shell'!L96/'Model Shell'!L91 | H15: ='Model Shell'!M96/'Model Shell'!M91 | I15: ='Model Shell'!N96/'Model Shell'!N91 | J15: ='Model Shell'!O96/'Model Shell'!O91 | K15: 0.17 | L15: 0.18 | M15: 0.19 | N15: 0.2 | O15: 0.2 | P15: 0.2 | Q15: 0.2 | R15: 0.13
B16: (+) D&A | E16: ='Model Shell'!J97 | F16: ='Model Shell'!K97 | G16: ='Model Shell'!L97 | H16: ='Model Shell'!M97 | I16: ='Model Shell'!N97 | J16: ='Model Shell'!O97 | K16: =J16+K17 | L16: =K16+L17 | M16: =L16+M17 | N16: =M16+N17 | O16: =N16+O17 | P16: =O16+P17 | Q16: =P16+Q17 | R16: =Q16
C17: Step-up $mm | F17: =F16-E16 | G17: =G16-F16 | H17: =H16-G16 | I17: =I16-H16 | J17: =J16-I16 | K17: 10 | L17: 10 | M17: 10 | N17: 10 | O17: 10 | P17: 10 | Q17: 10
B18: EBITDA | E18: =E16+E14 | F18: =F16+F14 | G18: =G16+G14 | H18: =H16+H14 | I18: =I16+I14 | J18: =J16+J14 | K18: =K16+K14 | L18: =L16+L14 | ... R18: =R16+R14 | S18: Tax on EBITDA
B19: (-) Tax | E19: 0 | F19: 0 | G19: 0 | H19: 0 | I19: 0 | J19: 0 | K19: 0 | L19: 0 | M19: 0 | N19: =N18*(-$S$19) | O19: =O18*(-$S$19) | P19: =P18*(-$S$19) | Q19: =Q18*(-$S$19) | R19: =R18*(-$S$19) | S19: 0.1
B20: (-) mCAPEX | E20: -150 | F20: -150 | G20: -150 | H20: -150 | I20: -150 | J20: -240 | K20: -240 | L20: -240 | M20: -200 | N20: -200 | O20: -200 | P20: -200 | Q20: -200 | R20: -150
B21: FCFF | E21: =SUM(E18:E20) | F21: =SUM(F18:F20) | G21: =SUM(G18:G20) | H21: =SUM(H18:H20) | I21: =SUM(I18:I20) | J21: =SUM(J18:J20) | K21: =SUM(K18:K20) | L21: =SUM(L18:L20) | ... R21: =SUM(R18:R20)
C22: Conversion % | E22: =E21/E18 | F22: =F21/F18 | G22: =G21/G18 | H22: =H21/H18 | I22: =I21/I18 | J22: =J21/J18 | K22: =K21/K18 | L22: =L21/L18 | ... R22: =R21/R18
S23: Disc Rate
B24: PV Factor | K24: =1/(1+$S$24)^K2 | L24: =1/(1+$S$24)^L2 | M24: =1/(1+$S$24)^M2 | N24: =1/(1+$S$24)^N2 | O24: =1/(1+$S$24)^O2 | P24: =1/(1+$S$24)^P2 | Q24: =1/(1+$S$24)^Q2 | R24: =1/(1+$S$24)^R2 | S24: 0.08
B25: PV | K25: =K21*K24 | L25: =L21*L24 | M25: =M21*M24 | N25: =N21*N24 | O25: =O21*O24 | P25: =P21*P24 | Q25: =Q21*Q24 | R25: =(R21/(S24-S26))*Q24 | S25: Terminal G
S26: 0.02
A27: x | B27: TEV | E27: =SUM(K25:R25)
C28: Impl FCF Yield | E28: =K21/E27
