Workbook
Name circ: LBO!$M$12
Name IQ_CH: 110000
Name IQ_CQ: 5000
Name IQ_CY: 10000
Name IQ_DAILY: 500000
Name IQ_FH: 100000
Name IQ_FQ: 500
Name IQ_FY: 1000
Name IQ_LTM: 2000
Name IQ_MONTH: 15000
Name IQ_NTM: 6000
Name IQ_WEEK: 50000
Name IQ_YTD: 3000

Sheet Data
C2: Summary P&L
C3: (€m, FYE 31-Dec) | D3: 2017A | E3: 2018A | F3: 2019A | G3: 2020E
D4: GAAP | E4: GAAP | F4: IFRS | G4: IFRS
C5: Output
C6: AMS Europe | D6: 31.5 | E6: 32.4 | F6: 37.3 | G6: 53.946401
C7: ECS Europe | D7: 31 | E7: 32.9 | F7: 38.9 | G7: 42.650783
C8: Americas & Asia | D8: 18.6 | E8: 22.8 | F8: 28.3 | G8: 32.533501
C9: Others | D9: 62.8 | E9: 57.9 | F9: 42.6 | G9: 36.202339
C10: Total Output | D10: 143.9 | E10: 146 | F10: 147.1 | G10: 165.33302
C12: Gross profit
C13: AMS Europe | D13: 9.5 | E13: 9.2 | F13: 11.2 | G13: 15.564811
C14: ECS Europe | D14: 11.1 | E14: 10.3 | F14: 14.4 | G14: 15.21323
C15: Americas & Asia | D15: 4 | E15: 3.8 | F15: 5.4 | G15: 6.9185281
C16: Others | D16: 16 | E16: 15.6 | F16: 15 | G16: 14.528397
C17: Total Gross Profit | D17: 40.6 | E17: 38.9 | F17: 46 | G17: 52.224966
C19: Overheads and Other
C20: Personnel expenses | D20: -23.774162 | E20: -24.428558 | F20: -25.728552 | G20: -26.453284
C21: Other operating expenses | D21: -11.355504 | E21: -9.1910144 | F21: -9.1900621 | G21: -9.3418151
C22: Other operating income | D22: 1.9575444 | E22: 1.9168258 | F22: 1.9825992 | G22: 2.1493293
C23: Total Overheads and Other | D23: -33.172121 | E23: -31.702747 | F23: -32.936015 | G23: -33.64577
C25: EBITDA | D25: 7.4278788 | E25: 7.1972532 | F25: 13.063985 | G25: 18.579196
D26: =+D17+D23 | E26: =+E17+E23 | F26: =+F17+F23 | G26: =+G17+G23
C27: Other items:
C28: D&A | D28: -3.2109359 | E28: -2.9779364 | F28: -5.5279112 | G28: -4.3133125
C29: Capex | D29: -2 | E29: -2.7 | F29: -2.8 | G29: -3.140329
C30: IFRS-16 leasing costs | D30: n.a. | E30: n.a. | F30: -1.4 | G30: -1.5701645
C31: Financial lease costs (IAS 17) | D31: n.a. | E31: -1 | F31: -1.4 | G31: -1.4
C32: Factoring (fees and interest) | D32: n.a. | E32: -1.4432411 | F32: -1.7267365 | G32: -1.9366145
C34: % Growth
C35: Total Output | D35: n.a. | E35: =+E10/D10-1 | F35: =+F10/E10-1 | G35: =+G10/F10-1
C36: Total Gross Profit | E36: =E17/D17-1 | F36: =F17/E17-1 | G36: =G17/F17-1
C37: Total Overheads and Other | E37: =E23/D23-1 | F37: =F23/E23-1 | G37: =G23/F23-1
C38: EBITDA | E38: =E25/D25-1 | F38: =F25/E25-1 | G38: =G25/F25-1
C40: % of Total Output
C41: Total Gross Profit | D41: =+D17/D10 | E41: =+E17/E10 | F41: =+F17/F10 | G41: =+G17/G10
C42: Total Overheads and Other | D42: =D23/D10 | E42: =E23/E10 | F42: =F23/F10 | G42: =G23/G10
C43: EBITDA | D43: =D25/D10 | E43: =E25/E10 | F43: =F25/F10 | G43: =G25/G10
C45: Summary Balance sheet
C46: (€m) | E46: =E3 | F46: =F3 | G46: =G3
C47: Assets
C48: Tangible assets(1) | E48: 3.0813375 | F48: 7.1965907 | G48: 7.4236071
C49: Intangible assets | E49: 44.430985 | F49: 46.330678 | G49: 46.330678
C50: Financial assets | E50: 5.5237092 | F50: 7.4368547 | G50: 8.3340342
C51: Inventories | E51: 4.8956701 | F51: 1.2501711 | G51: 0.95922502
C52: Trade receivables | E52: 14.432411 | F52: 17.267365 | G52: 19.366145
C53: Factor receivables(2) | E53: 1.4432411 | F53: 1.7267365 | G53: 1.9366145
C54: Cash | E54: 17.410773 | F54: 21.633166 | G54: 25.892916
C55: Deferred tax assets | E55: 2.4459022 | F55: 0.61386157 | G55: 0.68847402
C56: Other assets | E56: 1.9192558 | F56: 1.752548 | G56: 1.9655633
C57: Total | E57: 95.583285 | F57: 105.20797 | G57: 112.89726
C59: Liabilities
C60: Provisions(3) | E60: 5.8420197 | F60: 2.1252234 | G60: 4.8344713
C61: Bank debt | E61: 25.364503 | F61: 25.882796 | G61: 28.133635
C62: Shareholder loans | E62: 8.7 | F62: 13.279203 | G62: 15.139317
C63: Other financial liabilities | E63: 17.22571 | F63: 17.292548 | G63: 17.504447
C64: Financial lease liabilties (IAS 17) | E64: 1.2305627 | F64: 1.8583791 | G64: 1.8583791
C65: IFRS 16 leasing liabilities | E65: 0 | F65: 3.7733252 | G65: 3.7733252
C66: Trade payables | E66: 23.503779 | F66: 26.824981 | G66: 29.951474
C67: Deferred tax liabilities | E67: 0.56064377 | F67: 0.52455577 | G67: 0.58831346
C68: Accruals short term (tax and other provisions) | E68: 0.79652329 | F68: 1.0315279 | G68: 1.1569061
C69: Income tax liabilities | E69: 0.32406812 | F69: 1.1894241 | G69: 1.3339939
C70: Total | E70: 83.54781 | F70: 93.781962 | G70: 104.27426
C72: Net assets | E72: 12.035475 | F72: 11.42601 | G72: 8.6229954
C74: Due diligence findings:
C75: (1) Tangible asset base underinvested. DD estimated a capex underinvestment of c.€1.75m.
C76: (2) Non-recourse factoring of 50% of annual receivables. Terms include 80% cash upfront with 10% all-in interest cost (incl. discount and fees)
C77: (3) FY20E includes a management transaction bonus of €4.5m.

Sheet LBO
A1: in EURm unless otherwise stated | D1: Historical | E1: Historical | F1: Historical | G1: Estimated | H1: 1 | I1: =+H1+1 | J1: =+I1+1 | K1: =+J1+1 | L1: =+K1+1 | N1: CAGR
D2: 2017 | E2: =+D2+1 | F2: =+E2+1 | G2: =+F2+1 | H2: =+G2+1 | I2: =+H2+1 | J2: =+I2+1 | K2: =+J2+1 | L2: =+K2+1 | N2: 20-'25
A4: x | B4: Cover
C5: Txn assumptions | F5: Sources and Uses | K5: Other assumptions | O5: Financing assumptions | R5: xEBITDA | S5: Cash inter' | T5: PIK | U5: Maturity
C6: Purchase multiple | D6: 12 | F6: Revolver | I6: =+R6*$G$92 | K6: Min cash | M6: 20 | O6: Revolver | R6: 0 | S6: 0.04 | U6: 2027
C7: Pricing EBITDA (FY20E) | D7: =+G92 | F7: 1L debt | I7: =+R7*$G$92 | K7: Fees % of EV | M7: 0.05 | O7: 1L TLB | R7: 4 | S7: 0.06 | U7: 2027
C8: Purchase EV | D8: =+D7*D6 | F8: PIK notes | I8: =+R8*$G$92 | K8: Exit multiple | M8: 12 | O8: PIK notes | R8: 2 | T8: 0.08 | U8: 2027
F9: Sponsor equity | I9: =+I12-I10-I11-I8-I7-I6
C10: (-) debt | D10: =+Data!G61+Data!G62 | F10: Rolled lease liabilities | I10: =+D12
C11: (-) debt like items | D11: =+Data!G60+Data!G63 | F11: Cash on BS | I11: =+D13 | K11: Switches
C12: (-) leases | D12: =+Data!G65 | F12: Total sources | I12: =+I19 | K12: Circ switch | M12: 1
C13: (+) cash and equivalents | D13: =+Data!G54+Data!G50
C14: Purchase EqV | D14: =+D8-D10-D11+D12+D13 | F14: Purchase EqV | I14: =+D14
F15: Debt & debt-like items | I15: =+D10+D11
F16: Lease liabilities | I16: =+D12
F17: Fees | I17: =+M7*D8
F18: Min cash | I18: =+M6
F19: Total uses | I19: =SUM(I14:I18)
A20: x | B20: Operating assumptions
C21: AMS Europe | D21: =+Data!D6 | E21: =+Data!E6 | F21: =+Data!F6 | G21: =+Data!G6 | H21: =+G21*(1+$N21) | I21: =+H21*(1+$N21) | J21: =+I21*(1+$N21) | K21: =+J21*(1+$N21) | L21: =+K21*(1+$N21) | N21: 0.07
C22: ECS Europe | D22: =+Data!D7 | E22: =+Data!E7 | F22: =+Data!F7 | G22: =+Data!G7 | H22: =+G22*(1+$N22) | I22: =+H22*(1+$N22) | J22: =+I22*(1+$N22) | K22: =+J22*(1+$N22) | L22: =+K22*(1+$N22) | N22: 0.05
C23: Americas & Asia | D23: =+Data!D8 | E23: =+Data!E8 | F23: =+Data!F8 | G23: =+Data!G8 | H23: =+G23*(1+$N23) | I23: =+H23*(1+$N23) | J23: =+I23*(1+$N23) | K23: =+J23*(1+$N23) | L23: =+K23*(1+$N23) | N23: =+(L32/G32)^(0.2)-1
C24: Others | D24: =+Data!D9 | E24: =+Data!E9 | F24: =+Data!F9 | G24: =+Data!G9 | H24: =+G24*(1+$N24) | I24: =+H24*(1+$N24) | J24: =+I24*(1+$N24) | K24: =+J24*(1+$N24) | L24: =+K24*(1+$N24) | N24: =+(L38/G38)^(0.2)-1
C25: Total revenue | D25: =SUM(D21:D24) | E25: =SUM(E21:E24) | F25: =SUM(F21:F24) | G25: =SUM(G21:G24) | H25: =SUM(H21:H24) | I25: =SUM(I21:I24) | J25: =SUM(J21:J24) | K25: =SUM(K21:K24) | L25: =SUM(L21:L24)
C27: Memo: Europe
C28: Revenue | D28: =+D22+D21 | E28: =+E22+E21 | F28: =+F22+F21 | G28: =+G22+G21 | H28: =+H22+H21 | I28: =+I22+I21 | J28: =+J22+J21 | K28: =+K22+K21 | L28: =+L22+L21
C29: % YoY | E29: =+E28/D28-1 | F29: =+F28/E28-1 | G29: =+G28/F28-1 | H29: =+H28/G28-1 | I29: =+I28/H28-1 | J29: =+J28/I28-1 | K29: =+K28/J28-1 | L29: =+L28/K28-1
C31: Memo: Americas & Asia
C32: Revenue | D32: =+D23 | E32: =+E23 | F32: =+F23 | G32: =+G23 | H32: =+(1+H33)*G32 | I32: =+(1+I33)*H32 | J32: =+(1+J33)*I32 | K32: =+(1+K33)*J32 | L32: =+(1+L33)*K32
C33: % YoY | E33: =+E32/D32-1 | F33: =+F32/E32-1 | G33: =+G32/F32-1 | H33: =+H34+H35 | I33: =+I34+I35 | J33: =+J34+J35 | K33: =+K34+K35 | L33: =+L34+L35
C34: Baseline growth | H34: =+$N$21 | I34: =+$N$21 | J34: =+$N$21 | K34: =+$N$21 | L34: =+$N$21
C35: Excess growth | H35: 0.15 | I35: 0.125 | J35: 0.1 | K35: 0.075 | L35: 0.05
C37: Memo: Others
C38: Revenue | D38: =+D24 | E38: =+E24 | F38: =+F24 | G38: =+G24 | H38: =+(1+H39)*G38 | I38: =+(1+I39)*H38 | J38: =+(1+J39)*I38 | K38: =+(1+K39)*J38 | L38: =+(1+L39)*K38
C39: % YoY | E39: =+E38/D38-1 | F39: =+F38/E38-1 | G39: =+G38/F38-1 | H39: 0 | I39: 0 | J39: 0 | K39: 0 | L39: 0
C41: AMS Europe | D41: =+Data!D13 | E41: =+Data!E13 | F41: =+Data!F13 | G41: =+Data!G13
C42: ECS Europe | D42: =+Data!D14 | E42: =+Data!E14 | F42: =+Data!F14 | G42: =+Data!G14
C43: Americas & Asia | D43: =+Data!D15 | E43: =+Data!E15 | F43: =+Data!F15 | G43: =+Data!G15
C44: Others | D44: =+Data!D16 | E44: =+Data!E16 | F44: =+Data!F16 | G44: =+Data!G16
C45: Total gross profit | D45: =SUM(D41:D44) | E45: =SUM(E41:E44) | F45: =SUM(F41:F44) | G45: =SUM(G41:G44) | H45: =+H46*H25 | I45: =+I46*I25 | J45: =+J46*J25 | K45: =+K46*K25 | L45: =+L46*L25
C46: % of revenue | D46: =+D45/D25 | E46: =+E45/E25 | F46: =+F45/F25 | G46: =+G45/G25 | H46: =+AVERAGE($D$46:$G$46) | I46: =+AVERAGE($D$46:$G$46) | J46: =+AVERAGE($D$46:$G$46) | K46: =+AVERAGE($D$46:$G$46) | L46: =+AVERAGE($D$46:$G$46)
C48: Personnel expenses | D48: =+Data!D20 | E48: =+Data!E20 | F48: =+Data!F20 | G48: =+Data!G20 | H48: =+H55 | I48: =+I55 | J48: =+J55 | K48: =+K55 | L48: =+L55
C49: Other operating expenses | D49: =+Data!D21 | E49: =+Data!E21 | F49: =+Data!F21 | G49: =+Data!G21 | H49: =+H59 | I49: =+I59 | J49: =+J59 | K49: =+K59 | L49: =+L59
C50: Other operating income | D50: =+Data!D22 | E50: =+Data!E22 | F50: =+Data!F22 | G50: =+Data!G22 | H50: =+$G$50 | I50: =+$G$50 | J50: =+$G$50 | K50: =+$G$50 | L50: =+$G$50
C51: IFRS16 adjustments | D51: 0 | E51: =+Data!E31*-1
C52: Total overheads and other costs | D52: =SUM(D48:D51) | E52: =SUM(E48:E51) | F52: =SUM(F48:F51) | G52: =SUM(G48:G51) | H52: =SUM(H48:H51) | I52: =SUM(I48:I51) | J52: =SUM(J48:J51) | K52: =SUM(K48:K51) | L52: =SUM(L48:L51)
C54: Memo: Personnel and other operating expense
C55: Personnel expenses | D55: =+D48 | E55: =+E48 | F55: =+F48 | G55: =+G48 | H55: =+(1+H57)*G55 | I55: =+(1+I57)*H55 | J55: =+(1+J57)*I55 | K55: =+(1+K57)*J55 | L55: =+(1+L57)*K55
C56: % of revenue | D56: =+D55/D25*-1 | E56: =+E55/E25*-1 | F56: =+F55/F25*-1 | G56: =+G55/G25*-1 | H56: =+H55/H25*-1 | I56: =+I55/I25*-1 | J56: =+J55/J25*-1 | K56: =+K55/K25*-1 | L56: =+L55/L25*-1
C57: % YoY | E57: =+E55/D55-1 | F57: =+F55/E55-1 | G57: =+G55/F55-1 | H57: 0.03 | I57: 0.03 | J57: 0.03 | K57: 0.03 | L57: 0.03
C59: Other operating expenses | D59: =+D49 | E59: =+E49 | F59: =+F49 | G59: =+G49 | H59: =+(1+H61)*G59 | I59: =+(1+I61)*H59 | J59: =+(1+J61)*I59 | K59: =+(1+K61)*J59 | L59: =+(1+L61)*K59
C60: % of revenue | D60: =+D59/D25*-1 | E60: =+E59/E25*-1 | F60: =+F59/F25*-1 | G60: =+G59/G25*-1 | H60: =+H59/H25*-1 | I60: =+I59/I25*-1 | J60: =+J59/J25*-1 | K60: =+K59/K25*-1 | L60: =+L59/L25*-1
C61: % YoY | E61: =+E59/D59-1 | F61: =+F59/E59-1 | G61: =+G59/F59-1 | H61: 0.03 | I61: 0.03 | J61: 0.03 | K61: 0.03 | L61: 0.03
C63: Cost item driven by inflation
C65: EBITDA (post IFRS16) | D65: =+D52+D45 | E65: =+E52+E45 | F65: =+F52+F45 | G65: =+G52+G45 | H65: =+H52+H45 | I65: =+I52+I45 | J65: =+J52+J45 | K65: =+K52+K45 | L65: =+L52+L45
C67: D&A | D67: =+Data!D28 | E67: =+Data!E28 | F67: =+Data!F28 | G67: =+Data!G28 | H67: =+H73 | I67: =+I73 | J67: =+J73 | K67: =+K73 | L67: =+L73
C68: IFRS-16 leasing costs | D68: =+D51*-1 | E68: =+E51*-1 | F68: =+Data!F30 | G68: =+Data!G30 | H68: =+G68 | I68: =+H68 | J68: =+I68 | K68: =+J68 | L68: =+K68
C69: Factoring (fees and interest) | D69: 0 | E69: =+Data!E32 | F69: =+Data!F32 | G69: =+Data!G32 | H69: =+IF(circ=1, H151, 0) | I69: =+IF(circ=1, I151, 0) | J69: =+IF(circ=1, J151, 0) | K69: =+IF(circ=1, K151, 0) | L69: =+IF(circ=1, L151, 0)
C70: Total other costs | D70: =SUM(D67:D69) | E70: =SUM(E67:E69) | F70: =SUM(F67:F69) | G70: =SUM(G67:G69) | H70: =SUM(H67:H69) | I70: =SUM(I67:I69) | J70: =SUM(J67:J69) | K70: =SUM(K67:K69) | L70: =SUM(L67:L69)
C72: Memo: D&A
C73: D&A | D73: =+D67 | E73: =+E67 | F73: =+F67 | G73: =+G67 | H73: =+H74*H78 | I73: =+I74*I78 | J73: =+J74*J78 | K73: =+K74*K78 | L73: =+L74*L78
C74: D&A % of capex | D74: =+D73/D78 | E74: =+E73/E78 | F74: =+F73/F78 | G74: =+G73/G78 | H74: 1.3 | I74: 1.2 | J74: 1.1 | K74: 1 | L74: 1
C76: EBT | D76: =+D70+D65 | E76: =+E70+E65 | F76: =+F70+F65 | G76: =+G70+G65 | H76: =+H70+H65 | I76: =+I70+I65 | J76: =+J70+J65 | K76: =+K70+K65 | L76: =+L70+L65
C78: Capex | D78: =+Data!D29 | E78: =+Data!E29 | F78: =+Data!F29 | G78: =+Data!G29 | H78: =+H79+H80 | I78: =+I79+I80 | J78: =+J79+J80 | K78: =+K79+K80 | L78: =+L79+L80
C79: Additional capex due to underinvestment | H79: =1.75*-1
C80: Run rate capex | D80: =+D78 | E80: =+E78 | F80: =+F78 | G80: =+G78 | H80: =+H81*H25*-1 | I80: =+I81*I25*-1 | J80: =+J81*J25*-1 | K80: =+K81*K25*-1 | L80: =+L81*L25*-1
C81: % of revenue (run rate capex) | D81: =+D80/D25*-1 | E81: =+E80/E25*-1 | F81: =+F80/F25*-1 | G81: =+G80/G25*-1 | H81: =+AVERAGE($D$81:$G$81) | I81: =+AVERAGE($D$81:$G$81) | J81: =+AVERAGE($D$81:$G$81) | K81: =+AVERAGE($D$81:$G$81) | L81: =+AVERAGE($D$81:$G$81)
C83: ETR | H83: 0.16 | I83: 0.16 | J83: 0.16 | K83: 0.16 | L83: 0.16
A85: x | B85: Partial P&L
C86: Revenue | D86: =+D25 | E86: =+E25 | F86: =+F25 | G86: =+G25 | H86: =+H25 | I86: =+I25 | J86: =+J25 | K86: =+K25 | L86: =+L25 | N86: =+(L86/G86)^(0.2)-1
C87: % YoY | E87: =+E86/D86-1 | F87: =+F86/E86-1 | G87: =+G86/F86-1 | H87: =+H86/G86-1 | I87: =+I86/H86-1 | J87: =+J86/I86-1 | K87: =+K86/J86-1 | L87: =+L86/K86-1
C89: Gross profit | D89: =+D45 | E89: =+E45 | F89: =+F45 | G89: =+G45 | H89: =+H45 | I89: =+I45 | J89: =+J45 | K89: =+K45 | L89: =+L45 | N89: =+(L89/G89)^(0.2)-1
C90: % margin | D90: =+D89/D86 | E90: =+E89/E86 | F90: =+F89/F86 | G90: =+G89/G86 | H90: =+H89/H86 | I90: =+I89/I86 | J90: =+J89/J86 | K90: =+K89/K86 | L90: =+L89/L86
C92: EBITDA | D92: =+D65 | E92: =+E65 | F92: =+F65 | G92: =+G65 | H92: =+H65 | I92: =+I65 | J92: =+J65 | K92: =+K65 | L92: =+L65 | N92: =+(L92/G92)^(0.2)-1
C93: % margin | D93: =+D92/D86 | E93: =+E92/E86 | F93: =+F92/F86 | G93: =+G92/G86 | H93: =+H92/H86 | I93: =+I92/I86 | J93: =+J92/J86 | K93: =+K92/K86 | L93: =+L92/L86
C95: EBT | D95: =+D76 | E95: =+E76 | F95: =+F76 | G95: =+G76 | H95: =+H76 | I95: =+I76 | J95: =+J76 | K95: =+K76 | L95: =+L76 | N95: =+(L95/G95)^(0.2)-1
C96: % margin | D96: =+D95/D86 | E96: =+E95/E86 | F96: =+F95/F86 | G96: =+G95/G86 | H96: =+H95/H86 | I96: =+I95/I86 | J96: =+J95/J86 | K96: =+K95/K86 | L96: =+L95/L86
A98: x | B98: Partial Balance Sheet
C99: Cash and equivalents | G99: =+I18 | H99: =+H156 | I99: =+I156 | J99: =+J156 | K99: =+K156 | L99: =+L156
C101: Inventories | E101: =+Data!E51 | F101: =+Data!F51 | G101: =+Data!G51 | H101: =+H102/365*(H86-H89) | I101: =+I102/365*(I86-I89) | J101: =+J102/365*(J86-J89) | K101: =+K102/365*(K86-K89) | L101: =+L102/365*(L86-L89)
C102: Inventory days | E102: =+E101/(E86-E89)*365 | F102: =+F101/(F86-F89)*365 | G102: =+G101/(G86-G89)*365 | H102: =+G102 | I102: =+H102 | J102: =+I102 | K102: =+J102 | L102: =+K102
C103: Trade receivables | E103: =+Data!E52 | F103: =+Data!F52 | G103: =+Data!G52 | H103: =+H104/365*H86 | I103: =+I104/365*I86 | J103: =+J104/365*J86 | K103: =+K104/365*K86 | L103: =+L104/365*L86
C104: DSO | E104: =+E103/E86*365 | F104: =+F103/F86*365 | G104: =+G103/G86*365 | H104: =+G104 | I104: =+H104 | J104: =+I104 | K104: =+J104 | L104: =+K104
C106: Trade payables | E106: =+Data!E66 | F106: =+Data!F66 | G106: =+Data!G66 | H106: =+H107/365*(H86-H89) | I106: =+I107/365*(I86-I89) | J106: =+J107/365*(J86-J89) | K106: =+K107/365*(K86-K89) | L106: =+L107/365*(L86-L89)
C107: DPO | E107: =+E106/(E86-E89)*365 | F107: =+F106/(F86-F89)*365 | G107: =+G106/(G86-G89)*365 | H107: =+G107 | I107: =+H107 | J107: =+I107 | K107: =+J107 | L107: =+K107
C108: Accruals short term (tax and other provisions) | E108: =+Data!E68 | F108: =+Data!F68 | G108: =+Data!G68 | H108: =+H109/365*(H86-H89) | I108: =+I109/365*(I86-I89) | J108: =+J109/365*(J86-J89) | K108: =+K109/365*(K86-K89) | L108: =+L109/365*(L86-L89)
C109: Accrued days | E109: =+E108/(E86-E89)*365 | F109: =+F108/(F86-F89)*365 | G109: =+G108/(G86-G89)*365 | H109: =+G109 | I109: =+H109 | J109: =+I109 | K109: =+J109 | L109: =+K109
C111: NWC | E111: =+E103+E101-E106-E108 | F111: =+F103+F101-F106-F108 | G111: =+G103+G101-G106-G108 | H111: =+H103+H101-H106-H108 | I111: =+I103+I101-I106-I108 | J111: =+J103+J101-J106-J108 | K111: =+K103+K101-K106-K108 | L111: =+L103+L101-L106-L108
C112: Chg in NWC | F112: =+E111-F111 | G112: =+F111-G111 | H112: =+G111-H111 | I112: =+H111-I111 | J112: =+I111-J111 | K112: =+J111-K111 | L112: =+K111-L111
C114: Revolver | G114: =+G136 | H114: =+H136 | I114: =+I136 | J114: =+J136 | K114: =+K136 | L114: =+L136
C115: 1L TLB | G115: =+G142 | H115: =+H142 | I115: =+I142 | J115: =+J142 | K115: =+K142 | L115: =+L142
C116: PIK note | G116: =+G148 | H116: =+H148 | I116: =+I148 | J116: =+J148 | K116: =+K148 | L116: =+L148
C117: Total debt | G117: =SUM(G114:G116) | H117: =SUM(H114:H116) | I117: =SUM(I114:I116) | J117: =SUM(J114:J116) | K117: =SUM(K114:K116) | L117: =SUM(L114:L116)
A119: x | B119: FCF
C120: EBITDA | H120: =+H92 | I120: =+I92 | J120: =+J92 | K120: =+K92 | L120: =+L92
C121: Chg in NWC | H121: =+H112 | I121: =+I112 | J121: =+J112 | K121: =+K112 | L121: =+L112
C122: Cash interest | H122: =+H151 | I122: =+I151 | J122: =+J151 | K122: =+K151 | L122: =+L151
C123: Cash taxes | H123: =+H95*H83*-1 | I123: =+I95*I83*-1 | J123: =+J95*J83*-1 | K123: =+K95*K83*-1 | L123: =+L95*L83*-1
C124: Capex | H124: =+H78 | I124: =+I78 | J124: =+J78 | K124: =+K78 | L124: =+L78
C125: FCF | H125: =+SUM(H120:H124) | I125: =+SUM(I120:I124) | J125: =+SUM(J120:J124) | K125: =+SUM(K120:K124) | L125: =+SUM(L120:L124)
...
