Workbook

Sheet Forecast
B2: 2020E | C2: 2021 | D2: 2022 | E2: 2023 | F2: 2024 | G2: 2025
A4: Revenue
A5: AMS Europe | B5: =Data!F6 | C5: =Forecast!B5*(1+Forecast!B11) | D5: =Forecast!C5*(1+Forecast!B11) | E5: =Forecast!D5*(1+Forecast!B11) | F5: =Forecast!E5*(1+Forecast!B11) | G5: =Forecast!F5*(1+Forecast!B11)
A6: ECS Europe | B6: =Data!F7 | C6: =Forecast!B6*(1+Forecast!B12) | D6: =Forecast!C6*(1+Forecast!B12) | E6: =Forecast!D6*(1+Forecast!B12) | F6: =Forecast!E6*(1+Forecast!B12) | G6: =Forecast!F6*(1+Forecast!B12)
A7: Americas & Asia | B7: =Data!F8 | C7: =Forecast!B7*(1+Forecast!B13) | D7: =Forecast!C7*(1+Forecast!B13) | E7: =Forecast!D7*(1+Forecast!B13) | F7: =Forecast!E7*(1+Forecast!B13) | G7: =Forecast!F7*(1+Forecast!B13)
A9: Total Revenue | B9: =SUM(B5:B7) | C9: =SUM(C5:C7) | D9: =SUM(D5:D7) | E9: =SUM(E5:E7) | F9: =SUM(F5:F7) | G9: =SUM(G5:G7)
A10: Growth assumptions
B11: 0.07
B12: 0.05
B13: 0.1
A14: EBITDA Margin | B14: 0.11 | C14: =B14 | D14: =B14 | E14: =B14 | F14: =B14 | G14: =B14
A15: EBITDA | B15: =Forecast!B9*Forecast!B14 | C15: =Forecast!C9*Forecast!C14 | D15: =Forecast!D9*Forecast!D14 | E15: =Forecast!E9*Forecast!E14 | F15: =Forecast!F9*Forecast!F14 | G15: =Forecast!G9*Forecast!G14

Sheet Valuation
A2: Entry EV/EBITDA | B2: 8
A3: Entry EV | B3: =Forecast!B15*Valuation!B2
A4: Net Debt | B4: 20
A5: Equity Value | B5: =B3-B4

Sheet SourcesUses
A2: Uses
A3: Equity Purchase | B3: =Valuation!B5
A6: Sources
A7: Debt | B7: 0.5
A8: Equity | B8: =B3-B7

Sheet Returns
A2: Exit EV/EBITDA | B2: 8.5
A3: Exit EV | B3: =Forecast!G15*B2
A4: Exit Equity | B4: =B3-Valuation!B4
A5: MOIC | B5: =B4/Valuation!B5
A6: IRR | B6: =POWER(B5,1/5)-1

Sheet Sensitivity
A1: IRR Sensitivity (Entry vs Exit Multiple)
