Workbook
Name _2001_MODEL: #REF!
Name _4WORD_M_001_07: #N/A
Name _4WORD_O_005_L_: #N/A
Name _CHANGE: #REF!
Name _PB1: #REF!
Name _PB2: #REF!
Name _TOP12: #REF!
Name _TOP14: #REF!
Name _TOP15: #REF!
Name _TOP16: #REF!
Name _TOP17: #REF!
Name _TOP18: #REF!
Name AAAForecast: #REF!
Name ACE: #REF!
Name ACEE: #REF!
Name Acquirer: #REF!
Name ALL: #REF!
Name ALLE: #REF!
Name allearnings: #REF!
Name allquarter: #REF!
Name Annuities: #REF!
Name Argentina: #REF!
Name AssetAnal9: #REF!
Name AssetGathering: #REF!
Name AssetMngmt: #REF!
Name AssetsManaged: #REF!
Name asumpmatrix: #REF!
Name AUM: #REF!
Name Auto: #REF!
Name AutoHome: #REF!
Name AxesFormat: #REF!
Name BalanceSheet: #REF!
Name BODY: #REF!
Name Business_Line: #REF!
Name BV: #REF!
Name CapStruc10: #REF!
Name cash: #REF!
Name Cashflow: #REF!
Name CB: #REF!
Name CBE: #REF!
Name Charts1: #REF!
Name Charts2: #REF!
Name Chile1: #REF!
Name Chile2: #REF!
Name CINF: #REF!
Name CINFE: #REF!
Name Closed_End: #REF!
Name ClosedBlock: #REF!
Name CLval: #REF!
Name CNF: #REF!
Name Comm_Lines: #N/A
Name Commercial_lines: RANGE33
Name Consolidated: #REF!
Name ConsolidatedBal: #REF!
Name ConsolidatedInc: #REF!
Name ConsolidatedSales: #REF!
Name ConsolIncome: #REF!
Name ConvDate: #REF!
Name Current_GS: #REF!
Name Current_JW: #REF!

Sheet Segments
S1: 14Y | X1: 15Y | Y1: CQ1 | Z1: CQ2 | AA1: CQ3 | AB1: CQ4 | AC1: 16Y | AD1: CQ1 | AE1: CQ2 | AF1: CQ3 | AG1: CQ4 | AH1: 17Y | AI1: CQ1 | AJ1: CQ2 | AK1: CQ3 | AL1: CQ4 | AM1: 18Y | AN1: CQ1 | AO1: CQ2 | AP1: CQ3 | AQ1: CQ4 | AR1: 19Y | AS1: CQ1 | AT1: CQ2 | AU1: CQ3 | AV1: CQ4 | AW1: 20Y
B3: Moody's (MCO)
B4: Segments
B5: ($ in Millions, except per share data)
E6: 2012A | J6: 2013A | O6: 2014A | T6: 2015A | Y6: 2016A | AD6: 2017A | AI6: 2018A | AN6: 2019A | AS6: 2020A | AX6: 2021A | BC6: 2022A | BH6: 2023A | BM6: 2024A | BR6: 2025E | BW6: 2026E | CB6: 2027E
E7: 1Q12A | F7: 2Q12A | G7: 3Q12A | H7: 4Q12A | I7: 2012A | J7: 1Q13A | K7: 2Q13A | L7: 3Q13A | M7: 4Q13A | N7: 2013A | O7: 1Q14A | P7: 2Q14A | Q7: 3Q14A | R7: 4Q14A | S7: 2014A | T7: 1Q15A | U7: 2Q15A | V7: 3Q15A | W7: 4Q15A | X7: 2015A | Y7: 1Q16A | Z7: 2Q16A | AA7: 3Q16A | AB7: 4Q16A | AC7: 2016A | AD7: 1Q17A | AE7: 2Q17A | AF7: 3Q17A | AG7: 4Q17A | AH7: 2017A | AI7: 1Q18A | AJ7: 2Q18A | AK7: 3Q18A | AL7: 4Q18A | AM7: 2018A | AN7: 1Q19A | AO7: 2Q19A | AP7: 3Q19A | AQ7: 4Q19A | AR7: 2019A | AS7: 1Q20A | AT7: 2Q20A | AU7: 3Q20A | AV7: 4Q20A | AW7: 2020A | AX7: 1Q21A | AY7: 2Q21A | AZ7: 3Q21A | BA7: 4Q21A | BB7: 2021A | BC7: 1Q22A | BD7: 2Q22A | BE7: 3Q22A | BF7: 4Q22A | BG7: 2022A | BH7: 1Q23A | BI7: 2Q23A | BJ7: 3Q23A | BK7: 4Q23A | BL7: 2023A | BM7: 1Q24A | BN7: 2Q24A | BO7: 3Q24A | BP7: 4Q24A | BQ7: 2024A | BR7: 1Q25A | BS7: 2Q25A | BT7: 3Q25E | BU7: 4Q25E | BV7: 2025E | BW7: 1Q26E | BX7: 2Q26E | BY7: 3Q26E | BZ7: 4Q26E | CA7: 2026E | CB7: 1Q27E | CC7: 2Q27E | CD7: 3Q27E | CE7: 4Q27E | CF7: 2027E
B8: MOODY'S INVESTOR SERVICE (MIS, RATINGS)
B9: MIS-rated Issuance (in $bln) | AI9: 1400 | AJ9: 1300 | AK9: 1100 | AL9: 856 | AM9: =SUM(AI9:AL9) -> 4656 | AN9: =AS9/(1+AS10) -> 1229.661 | AO9: 1168 | AP9: 1189 | AQ9: 1013 | AR9: =SUM(AN9:AQ9) -> 4599.661 | AS9: 1451 | AT9: 1843 | AU9: 1270 | AV9: 983 | AW9: =SUM(AS9:AV9) -> 5547 | AX9: 1803 | AY9: 1595 | AZ9: 1436 | BA9: 1211 | BB9: =SUM(AX9:BA9) -> 6045 | BC9: 1409 | BD9: 1111 | BE9: 859 | BF9: 791 | BG9: =SUM(BC9:BF9) -> 4170 | BH9: 1264 | BI9: 1173 | BJ9: 994 | BK9: 942 | BL9: =SUM(BH9:BK9) -> 4373 | BM9: 1767 | BN9: 1708 | BO9: 1537 | BP9: 1253 | BQ9: =SUM(BM9:BP9) -> 6265 | BR9: 1924 | BS9: 1511 | BT9: 1764
B10: % y/y | AN10: =AN9/AI9-1 -> -0.1216707 | AO10: =AO9/AJ9-1 -> -0.10153846 | AP10: =AP9/AK9-1 -> 0.080909091 | AQ10: =AQ9/AL9-1 -> 0.18341121 | AR10: =AR9/AM9-1 -> -0.012100297 | AS10: 0.18 | AT10: =AT9/AO9-1 -> 0.57791096 | AU10: =AU9/AP9-1 -> 0.068124474 | AV10: =AV9/AQ9-1 -> -0.029615005 | AW10: =AW9/AR9-1 -> 0.20595843 | AX10: =AX9/AS9-1 -> 0.24259132 | AY10: =AY9/AT9-1 -> -0.13456321 | AZ10: =AZ9/AU9-1 -> 0.13070866 | BA10: =BA9/AV9-1 -> 0.23194303 | ... BT10: =BT9/BO9-1 -> 0.14769031
B11: % qtr/qtr | AJ11: =AJ9/AI9-1 -> -0.071428571 | AK11: =AK9/AJ9-1 -> -0.15384615 | AL11: =AL9/AK9-1 -> -0.22181818 | AN11: =AN9/AL9-1 -> 0.43651988 | AO11: =AO9/AN9-1 -> -0.050144728 | AP11: =AP9/AO9-1 -> 0.017979452 | AQ11: =AQ9/AP9-1 -> -0.14802355 | AS11: =AS9/AQ9-1 -> 0.43237907 | AT11: =AT9/AS9-1 -> 0.27015851 | AU11: =AU9/AT9-1 -> -0.31090613 | AV11: =AV9/AU9-1 -> -0.22598425 | AX11: =AX9/AV9-1 -> 0.83418108 | AY11: =AY9/AX9-1 -> -0.11536328 | AZ11: =AZ9/AY9-1 -> -0.09968652 | BA11: =BA9/AZ9-1 -> -0.15668524 | BC11: =BC9/BA9-1 -> 0.16350124 | BD11: =BD9/BC9-1 -> -0.21149752 | BE11: =BE9/BD9-1 -> -0.22682268 | BF11: =BF9/BE9-1 -> -0.079161816 | BH11: =BH9/BF9-1 -> 0.59797724 | BI11: =BI9/BH9-1 -> -0.071993671 | BJ11: =BJ9/BI9-1 -> -0.15260017 | BK11: =BK9/BJ9-1 -> -0.052313883 | BM11: =BM9/BK9-1 -> 0.87579618 | BN11: =BN9/BM9-1 -> -0.033389926 | BO11: =BO9/BN9-1 -> -0.1001171 | BP11: =BP9/BO9-1 -> -0.18477554 | BR11: =BR9/BP9-1 -> 0.53551476 | BS11: =BS9/BR9-1 -> -0.21465696 | BT11: =BT9/BS9-1 -> 0.16743878
B12: Take Rate (total revenues / total issuance; in bps) | AI12: =AI60/AI9*10 -> 5.355 | AJ12: =AJ60/AJ9*10 -> 6.0223077 | AK12: =AK60/AK9*10 -> 6.1490909 | AL12: =AL60/AL9*10 -> 7.3294393 | AM12: =AM60/AM9*10 -> 6.0919244 | AN12: =AN60/AN9*10 -> 5.7121433 | AO12: =AO60/AO9*10 -> 6.6044521 | AP12: =AP60/AP9*10 -> 6.567704 | ... BT12: =BT60/BT9*10 -> 6.4876984
B13: Implied Realized Price % Y/Y | AN13: =AN12/AI12-1 -> 0.066693436 | AO13: =AO12/AJ12-1 -> 0.096664666 | AP13: =AP12/AK12-1 -> 0.068077225 | AQ13: =AQ12/AL12-1 -> 0.016873095 | AR13: =AR12/AM12-1 -> 0.07409545 | AS13: =AS12/AN12-1 -> 0.0026157291 | AT13: =AT12/AO12-1 -> -0.20062472 | AU13: =AU12/AP12-1 -> 0.033451207 | ... BT13: =BT12/BO12-1 -> -0.031884227
B14: Mix Impact (% y/y change in Transaction revs - % y/y change in issuance) | AN14: =AN28-AN10 -> 0.0069838771 | AO14: =AO28-AO10 -> 0.06463586 | AP14: =AP28-AP10 -> 0.1446991 | AQ14: =AQ28-AQ10 -> 0.1323001 | AR14: =AR28-AR10 -> 0.085049707 | AS14: =AS28-AS10 -> 0.086162479 | AT14: =AT28-AT10 -> -0.1876262 | AU14: =AU28-AU10 -> 0.076881794 | ... BT14: =BT28-BT10 -> -0.012690306
B16: Corporates (2024: 73% transaction) | C16: =BQ16/BQ$31 -> 0.51410493 | E16: 200.5 | F16: 191.5 | G16: 220.7 | H16: 244.9 | I16: =SUM(E16:H16) -> 857.6 | J16: 258.3 | K16: 262.9 | L16: 232.9 | M16: 242.6 | N16: =SUM(J16:M16) -> 996.7 | O16: 264.4 | P16: 320.9 | Q16: 260.7 | R16: 263.3 | S16: =SUM(O16:R16) -> 1109.3 | T16: 298.7 | U16: 319.6 | V16: 248.3 | W16: 246.1 | X16: =SUM(T16:W16) -> 1112.7 | Y16: 240.3 | Z16: 304.8 | AA16: 299.6 | AB16: 277.6 | AC16: =SUM(Y16:AB16) -> 1122.3 | AD16: 352.8 | AE16: 355.8 | AF16: 350.2 | AG16: 333.9 | AH16: =SUM(AD16:AG16) -> 1392.7 | AI16: 389.6 | AJ16: 391 | AK16: =78+39+55+135 -> 307 | AL16: =145+57+19+70 -> 291 | AM16: =SUM(AI16:AL16) -> 1378.6 | AN16: 355.4 | AO16: 387.4 | AP16: 392 | AQ16: 362 | AR16: =SUM(AN16:AQ16) -> 1496.8 | AS16: 453 | AT16: 572 | AU16: 461 | AV16: 371 | AW16: =SUM(AS16:AV16) -> 1857 | AX16: 605 | AY16: 550 | AZ16: 488 | BA16: 444 | BB16: =SUM(AX16:BA16) -> 2087 | BC16: 417 | BD16: 322 | BE16: 277 | BF16: 253 | BG16: =SUM(BC16:BF16) -> 1269 | BH16: 356 | BI16: 365 | BJ16: 346 | BK16: 337 | BL16: =SUM(BH16:BK16) -> 1404 | BM16: 529 | BN16: 525 | BO16: 515 | BP16: 381 | BQ16: =SUM(BM16:BP16) -> 1950 | BR16: 564 | BS16: 512 | BT16: 576
B17: % y/y | J17: =J16/E16-1 -> 0.2882793 | K17: =K16/F16-1 -> 0.37284595 | L17: =L16/G16-1 -> 0.055278659 | M17: =M16/H16-1 -> -0.0093915884 | N17: =N16/I16-1 -> 0.16219683 | O17: =O16/J16-1 -> 0.02361595 | P17: =P16/K16-1 -> 0.2206162 | Q17: =Q16/L16-1 -> 0.11936453 | ... AC17: =AC16/X16-1 -> 0.0086276624 | AD17: =IFERROR( AD16/Y16-1, "NA") -> 0.46816479 | AE17: =IFERROR( AE16/Z16-1, "NA") -> 0.16732283 | AF17: =IFERROR( AF16/AA16-1, "NA") -> 0.16889186 | AG17: =IFERROR( AG16/AB16-1, "NA") -> 0.2028098 | AH17: =AH16/AC16-1 -> 0.2409338 | AI17: =IFERROR( AI16/AD16-1, "NA") -> 0.10430839 | AJ17: =IFERROR( AJ16/AE16-1, "NA") -> 0.098931984 | AK17: =IFERROR( AK16/AF16-1, "NA") -> -0.12335808 | AL17: =IFERROR( AL16/AG16-1, "NA") -> -0.12848158 | AM17: =AM16/AH16-1 -> -0.010124219 | AN17: =IFERROR( AN16/AI16-1, "NA") -> -0.087782341 | AO17: =IFERROR( AO16/AJ16-1, "NA") -> -0.0092071611 | AP17: =IFERROR( AP16/AK16-1, "NA") -> 0.27687296 | AQ17: =IFERROR( AQ16/AL16-1, "NA") -> 0.24398625 | AR17: =AR16/AM16-1 -> 0.085739156 | AS17: =IFERROR( AS16/AN16-1, "NA") -> 0.27462015 | AT17: =IFERROR( AT16/AO16-1, "NA") -> 0.47651007 | AU17: =IFERROR( AU16/AP16-1, "NA") -> 0.17602041 | AV17: =IFERROR( AV16/AQ16-1, "NA") -> 0.024861878 | AW17: =AW16/AR16-1 -> 0.24064671 | AX17: =IFERROR( AX16/AS16-1, "NA") -> 0.33554084 | AY17: =IFERROR( AY16/AT16-1, "NA") -> -0.038461538 | AZ17: =IFERROR( AZ16/AU16-1, "NA") -> 0.05856833 | BA17: =IFERROR( BA16/AV16-1, "NA") -> 0.1967655 | BB17: =BB16/AW16-1 -> 0.12385568 | BC17: =IFERROR( BC16/AX16-1, "NA") -> -0.3107438 | BD17: =IFERROR( BD16/AY16-1, "NA") -> -0.41454545 | BE17: =IFERROR( BE16/AZ16-1, "NA") -> -0.43237705 | BF17: =IFERROR( BF16/BA16-1, "NA") -> -0.43018018 | BG17: =BG16/BB16-1 -> -0.39195017 | BH17: =IFERROR( BH16/BC16-1, "NA") -> -0.14628297 | BI17: =IFERROR( BI16/BD16-1, "NA") -> 0.13354037 | BJ17: =IFERROR( BJ16/BE16-1, "NA") -> 0.24909747 | BK17: =IFERROR( BK16/BF16-1, "NA") -> 0.33201581 | BL17: =BL16/BG16-1 -> 0.10638298 | BM17: =IFERROR( BM16/BH16-1, "NA") -> 0.48595506 | BN17: =IFERROR( BN16/BI16-1, "NA") -> 0.43835616 | BO17: =IFERROR( BO16/BJ16-1, "NA") -> 0.48843931 | BP17: =IFERROR( BP16/BK16-1, "NA") -> 0.1305638 | BQ17: =BQ16/BL16-1 -> 0.38888889 | BR17: =IFERROR( BR16/BM16-1, "NA") -> 0.066162571 | BS17: =IFERROR( BS16/BN16-1, "NA") -> -0.024761905 | BT17: =IFERROR( BT16/BO16-1, "NA") -> 0.1184466
B18: Financial services (2024: 57% transaction) | C18: =BQ18/BQ$31 -> 0.19166886 | E18: 78.7 | F18: 77.9 | G18: 82.6 | H18: 86.2 | I18: =SUM(E18:H18) -> 325.4 | J18: 86.5 | K18: 84.5 | L18: 78.9 | M18: 88.9 | N18: =SUM(J18:M18) -> 338.8 | O18: 85.4 | P18: 92.2 | Q18: 91.8 | R18: 85.3 | S18: =SUM(O18:R18) -> 354.7 | T18: 93.8 | U18: 90.4 | V18: 89.5 | W18: 91.9 | X18: =SUM(T18:W18) -> 365.6 | Y18: 94.9 | Z18: 89.7 | AA18: 95.8 | AB18: 88.5 | AC18: =SUM(Y18:AB18) -> 368.9 | AD18: 112.3 | AE18: 102.4 | AF18: 102.1 | AG18: 119 | AH18: =SUM(AD18:AG18) -> 435.8 | AI18: 114.3 | AJ18: 120.6 | AK18: =73+38+6+3 -> 120 | AL18: =63+15+6+3 -> 87 | AM18: =SUM(AI18:AL18) -> 441.9 | AN18: 115.8 | AO18: 125.2 | AP18: 120.5 | AQ18: 115 | AR18: =SUM(AN18:AQ18) -> 476.5 | AS18: 125 | AT18: 142 | AU18: 134 | AV18: 129 | AW18: =SUM(AS18:AV18) -> 530 | AX18: 162 | AY18: 150 | AZ18: 153 | BA18: 137 | BB18: =SUM(AX18:BA18) -> 602 | BC18: 131 | BD18: 128 | BE18: 109 | BF18: 123 | BG18: =SUM(BC18:BF18) -> 491 | BH18: 142 | BI18: 145 | BJ18: 126 | BK18: 132 | BL18: =SUM(BH18:BK18) -> 545 | BM18: 195 | BN18: 195 | BO18: 170 | BP18: 167 | BQ18: =SUM(BM18:BP18) -> 727 | BR18: 191 | BS18: 191 | BT18: 208
B19: % y/y | J19: =J18/E18-1 -> 0.099110546 | K19: =K18/F18-1 -> 0.084724005 | L19: =L18/G18-1 -> -0.044794189 | M19: =M18/H18-1 -> 0.031322506 | N19: =N18/I18-1 -> 0.041180086 | O19: =O18/J18-1 -> -0.012716763 | P19: =P18/K18-1 -> 0.09112426 | Q19: =Q18/L18-1 -> 0.1634981 | ... AC19: =AC18/X18-1 -> 0.0090262582 | AD19: =IFERROR( AD18/Y18-1, "NA") -> 0.1833509 | AE19: =IFERROR( AE18/Z18-1, "NA") -> 0.14158305 | AF19: =IFERROR( AF18/AA18-1, "NA") -> 0.065762004 | AG19: =IFERROR( AG18/AB18-1, "NA") -> 0.34463277 | AH19: =AH18/AC18-1 -> 0.18134996 | AI19: =IFERROR( AI18/AD18-1, "NA") -> 0.017809439 | AJ19: =IFERROR( AJ18/AE18-1, "NA") -> 0.17773437 | AK19: =IFERROR( AK18/AF18-1, "NA") -> 0.17531832 | AL19: =IFERROR( AL18/AG18-1, "NA") -> -0.26890756 | AM19: =AM18/AH18-1 -> 0.013997246 | AN19: =IFERROR( AN18/AI18-1, "NA") -> 0.01312336 | AO19: =IFERROR( AO18/AJ18-1, "NA") -> 0.03814262 | AP19: =IFERROR( AP18/AK18-1, "NA") -> 0.0041666667 | AQ19: =IFERROR( AQ18/AL18-1, "NA") -> 0.32183908 | AR19: =AR18/AM18-1 -> 0.078298258 | AS19: =IFERROR( AS18/AN18-1, "NA") -> 0.079447323 | AT19: =IFERROR( AT18/AO18-1, "NA") -> 0.1341853 | AU19: =IFERROR( AU18/AP18-1, "NA") -> 0.1120332 | AV19: =IFERROR( AV18/AQ18-1, "NA") -> 0.12173913 | AW19: =AW18/AR18-1 -> 0.11227702 | AX19: =IFERROR( AX18/AS18-1, "NA") -> 0.296 | AY19: =IFERROR( AY18/AT18-1, "NA") -> 0.056338028 | AZ19: =IFERROR( AZ18/AU18-1, "NA") -> 0.14179104 | BA19: =IFERROR( BA18/AV18-1, "NA") -> 0.062015504 | BB19: =BB18/AW18-1 -> 0.13584906 | BC19: =IFERROR( BC18/AX18-1, "NA") -> -0.19135802 | BD19: =IFERROR( BD18/AY18-1, "NA") -> -0.14666667 | BE19: =IFERROR( BE18/AZ18-1, "NA") -> -0.2875817 | BF19: =IFERROR( BF18/BA18-1, "NA") -> -0.10218978 | BG19: =BG18/BB18-1 -> -0.18438538 | BH19: =IFERROR( BH18/BC18-1, "NA") -> 0.083969466 | BI19: =IFERROR( BI18/BD18-1, "NA") -> 0.1328125 | BJ19: =IFERROR( BJ18/BE18-1, "NA") -> 0.1559633 | BK19: =IFERROR( BK18/BF18-1, "NA") -> 0.073170732 | BL19: =BL18/BG18-1 -> 0.10997963 | BM19: =IFERROR( BM18/BH18-1, "NA") -> 0.37323944 | BN19: =IFERROR( BN18/BI18-1, "NA") -> 0.34482759 | BO19: =IFERROR( BO18/BJ18-1, "NA") -> 0.34920635 | BP19: =IFERROR( BP18/BK18-1, "NA") -> 0.26515152 | BQ19: =BQ18/BL18-1 -> 0.33394495 | BR19: =IFERROR( BR18/BM18-1, "NA") -> -0.020512821 | BS19: =IFERROR( BS18/BN18-1, "NA") -> -0.020512821 | BT19: =IFERROR( BT18/BO18-1, "NA") -> 0.22352941
B20: Structured (2024: 56% transaction) | C20: =BQ20/BQ$31 -> 0.13656736 | E20: 94.2 | F20: 90.8 | G20: 93 | H20: 102.9 | I20: =SUM(E20:H20) -> 380.9 | J20: 93 | K20: 97.2 | L20: 83.5 | M20: 108.7 | N20: =SUM(J20:M20) -> 382.4 | O20: 95.3 | P20: 110.6 | Q20: 102.1 | R20: 118.5 | S20: =SUM(O20:R20) -> 426.5 | T20: 101.3 | U20: 121.2 | V20: 112.5 | W20: 114.1 | X20: =SUM(T20:W20) -> 449.1 | Y20: 90.6 | Z20: 111.5 | AA20: 104.2 | AB20: 130.5 | AC20: =SUM(Y20:AB20) -> 436.8 | AD20: 100.2 | AE20: 119.2 | AF20: 128.3 | AG20: 147.8 | AH20: =SUM(AD20:AG20) -> 495.5 | AI20: 117.8 | AJ20: 128.2 | AK20: =1+51+15+24+25 -> 116 | AL20: =48+24+23+26 -> 121 | AM20: =SUM(AI20:AL20) -> 483 | AN20: 100.7 | AO20: 112.1 | AP20: 105.4 | AQ20: 109 | AR20: =SUM(AN20:AQ20) -> 427.2 | AS20: 96 | AT20: 81 | AU20: 88 | AV20: 97 | AW20: =SUM(AS20:AV20) -> 362 | AX20: 116 | AY20: 140 | AZ20: 143 | BA20: 161 | BB20: =SUM(AX20:BA20) -> 560 | BC20: 144 | BD20: 123 | BE20: 101 | BF20: 94 | BG20: =SUM(BC20:BF20) -> 462 | BH20: 99 | BI20: 102 | BJ20: 102 | BK20: 102 | BL20: =SUM(BH20:BK20) -> 405 | BM20: 114 | BN20: 131 | BO20: 135 | BP20: 138 | BQ20: =SUM(BM20:BP20) -> 518 | BR20: 138 | BS20: 135 | BT20: 146
B21: % y/y | J21: =J20/E20-1 -> -0.012738854 | K21: =K20/F20-1 -> 0.070484581 | L21: =L20/G20-1 -> -0.10215054 | M21: =M20/H20-1 -> 0.056365403 | N21: =N20/I20-1 -> 0.0039380415 | O21: =O20/J20-1 -> 0.024731183 | P21: =P20/K20-1 -> 0.13786008 | Q21: =Q20/L20-1 -> 0.22275449 | ... AC21: =AC20/X20-1 -> -0.02738811 | AD21: =IFERROR( AD20/Y20-1, "NA") -> 0.10596026 | AE21: =IFERROR( AE20/Z20-1, "NA") -> 0.069058296 | AF21: =IFERROR( AF20/AA20-1, "NA") -> 0.23128599 | AG21: =IFERROR( AG20/AB20-1, "NA") -> 0.13256705 | AH21: =AH20/AC20-1 -> 0.13438645 | AI21: =IFERROR( AI20/AD20-1, "NA") -> 0.1756487 | AJ21: =IFERROR( AJ20/AE20-1, "NA") -> 0.075503356 | AK21: =IFERROR( AK20/AF20-1, "NA") -> -0.095869057 | AL21: =IFERROR( AL20/AG20-1, "NA") -> -0.18132612 | AM21: =AM20/AH20-1 -> -0.025227043 | AN21: =IFERROR( AN20/AI20-1, "NA") -> -0.14516129 | AO21: =IFERROR( AO20/AJ20-1, "NA") -> -0.12558502 | AP21: =IFERROR( AP20/AK20-1, "NA") -> -0.09137931 | AQ21: =IFERROR( AQ20/AL20-1, "NA") -> -0.099173554 | AR21: =AR20/AM20-1 -> -0.11552795 | AS21: =IFERROR( AS20/AN20-1, "NA") -> -0.046673287 | AT21: =IFERROR( AT20/AO20-1, "NA") -> -0.27743087 | AU21: =IFERROR( AU20/AP20-1, "NA") -> -0.16508539 | AV21: =IFERROR( AV20/AQ20-1, "NA") -> -0.11009174 | AW21: =AW20/AR20-1 -> -0.15262172 | AX21: =IFERROR( AX20/AS20-1, "NA") -> 0.20833333 | AY21: =IFERROR( AY20/AT20-1, "NA") -> 0.72839506 | AZ21: =IFERROR( AZ20/AU20-1, "NA") -> 0.625 | BA21: =IFERROR( BA20/AV20-1, "NA") -> 0.65979381 | BB21: =BB20/AW20-1 -> 0.54696133 | BC21: =IFERROR( BC20/AX20-1, "NA") -> 0.24137931 | BD21: =IFERROR( BD20/AY20-1, "NA") -> -0.12142857 | BE21: =IFERROR( BE20/AZ20-1, "NA") -> -0.29370629 | BF21: =IFERROR( BF20/BA20-1, "NA") -> -0.41614907 | BG21: =BG20/BB20-1 -> -0.175 | BH21: =IFERROR( BH20/BC20-1, "NA") -> -0.3125 | BI21: =IFERROR( BI20/BD20-1, "NA") -> -0.17073171 | BJ21: =IFERROR( BJ20/BE20-1, "NA") -> 0.0099009901 | BK21: =IFERROR( BK20/BF20-1, "NA") -> 0.085106383 | BL21: =BL20/BG20-1 -> -0.12337662 | BM21: =IFERROR( BM20/BH20-1, "NA") -> 0.15151515 | BN21: =IFERROR( BN20/BI20-1, "NA") -> 0.28431373 | BO21: =IFERROR( BO20/BJ20-1, "NA") -> 0.32352941 | BP21: =IFERROR( BP20/BK20-1, "NA") -> 0.35294118 | BQ21: =BQ20/BL20-1 -> 0.27901235 | BR21: =IFERROR( BR20/BM20-1, "NA") -> 0.21052632 | BS21: =IFERROR( BS20/BN20-1, "NA") -> 0.030534351 | BT21: =IFERROR( BT20/BO20-1, "NA") -> 0.081481481
B22: Governments/public/other (2024: 68% transaction) | C22: =BQ22/BQ$31 -> 0.15765885 | E22: 79.2 | F22: 81.1 | G22: 77 | H22: 85.3 | I22: =SUM(E22:H22) -> 322.6 | J22: 83.45 | K22: 92.7 | L22: =82.7+0.1 -> 82.8 | M22: =82.48+3.32 -> 85.8 | N22: =SUM(J22:M22) -> 344.75 | O22: =80.7+3.3 -> 84 | P22: =98+3.3 -> 101.3 | Q22: =88.5+3.5 -> 92 | R22: =90.1+7.9 -> 98 | S22: =SUM(O22:R22) -> 375.3 | T22: =100.7+7.8 -> 108.5 | U22: =99.9+8.1 -> 108 | V22: =90.6+7.2 -> 97.8 | W22: 85.3 | X22: =SUM(T22:W22) -> 399.6 | Y22: =91.5+7.8 -> 99.3 | Z22: =112.3+7.3 -> 119.6 | AA22: =105.2+7.5 -> 112.7 | AB22: =103.2+8 -> 111.2 | AC22: =SUM(Y22:AB22) -> 442.8 | AD22: =98.1+4.8 -> 102.9 | AE22: =104.7+4.6 -> 109.3 | AF22: =109.2+4.4 -> 113.6 | AG22: =119.3+4.7 -> 124 | AH22: =SUM(AD22:AG22) -> 449.8 | AI22: =93.2+5 -> 98.2 | AJ22: =108.1+4.4 -> 112.5 | AK22: =99+4.8 -> 103.8 | AL22: =90.8+4.8 -> 95.6 | AM22: =SUM(AI22:AL22) -> 410.1 | AN22: 92.7 | AO22: =108.6+5.1 -> 113.7 | AP22: =119.8+8.9 -> 128.7 | AQ22: =125+9 -> 134 | AR22: =SUM(AN22:AQ22) -> 469.1 | AS22: =109+11 -> 120 | AT22: =133+10 -> 143 | AU22: =133+9 -> 142 | AV22: =121+17 -> 138 | AW22: =SUM(AS22:AV22) -> 543 | AX22: =143+10 -> 153 | AY22: =130+10 -> 140 | AZ22: =130+11 -> 141 | BA22: =118+11 -> 129 | BB22: =SUM(AX22:BA22) -> 563 | BC22: =123+12 -> 135 | BD22: =122+11 -> 133 | BE22: =92+11 -> 103 | BF22: =94+12 -> 106 | BG22: =SUM(BC22:BF22) -> 477 | BH22: =129+7 -> 136 | BI22: =127 +8 -> 135 | BJ22: =115+7 -> 122 | BK22: =105+8 -> 113 | BL22: =SUM(BH22:BK22) -> 506 | BM22: =141+8 -> 149 | BN22: =154+10 -> 164 | BO22: =154+8 -> 162 | BP22: =115+8 -> 123 | BQ22: =SUM(BM22:BP22) -> 598 | BR22: =163+9 -> 172 | BS22: =162+10 -> 172 | BT22: =161+7 -> 168
B23: % y/y | J23: =J22/E22-1 -> 0.053661616 | K23: =K22/F22-1 -> 0.14303329 | L23: =L22/G22-1 -> 0.075324675 | M23: =M22/H22-1 -> 0.0058616647 | N23: =N22/I22-1 -> 0.06866088 | O23: =O22/J22-1 -> 0.0065907729 | P23: =P22/K22-1 -> 0.092772384 | Q23: =Q22/L22-1 -> 0.11111111 | ... AC23: =AC22/X22-1 -> 0.10810811 | AD23: =IFERROR( AD22/Y22-1, "NA") -> 0.036253776 | AE23: =IFERROR( AE22/Z22-1, "NA") -> -0.086120401 | AF23: =IFERROR( AF22/AA22-1, "NA") -> 0.007985803 | AG23: =IFERROR( AG22/AB22-1, "NA") -> 0.11510791 | AH23: =AH22/AC22-1 -> 0.015808491 | AI23: =IFERROR( AI22/AD22-1, "NA") -> -0.045675413 | AJ23: =IFERROR( AJ22/AE22-1, "NA") -> 0.029277219 | AK23: =IFERROR( AK22/AF22-1, "NA") -> -0.086267606 | AL23: =IFERROR( AL22/AG22-1, "NA") -> -0.22903226 | AM23: =AM22/AH22-1 -> -0.08826145 | AN23: =IFERROR( AN22/AI22-1, "NA") -> -0.056008147 | AO23: =IFERROR( AO22/AJ22-1, "NA") -> 0.010666667 | AP23: =IFERROR( AP22/AK22-1, "NA") -> 0.23988439 | AQ23: =IFERROR( AQ22/AL22-1, "NA") -> 0.40167364 | AR23: =AR22/AM22-1 -> 0.14386735 | AS23: =IFERROR( AS22/AN22-1, "NA") -> 0.29449838 | AT23: =IFERROR( AT22/AO22-1, "NA") -> 0.25769569 | AU23: =IFERROR( AU22/AP22-1, "NA") -> 0.1033411 | AV23: =IFERROR( AV22/AQ22-1, "NA") -> 0.029850746 | AW23: =AW22/AR22-1 -> 0.15753571 | AX23: =IFERROR( AX22/AS22-1, "NA") -> 0.275 | AY23: =IFERROR( AY22/AT22-1, "NA") -> -0.020979021 | AZ23: =IFERROR( AZ22/AU22-1, "NA") -> -0.0070422535 | BA23: =IFERROR( BA22/AV22-1, "NA") -> -0.065217391 | BB23: =BB22/AW22-1 -> 0.036832413 | BC23: =IFERROR( BC22/AX22-1, "NA") -> -0.11764706 | BD23: =IFERROR( BD22/AY22-1, "NA") -> -0.05 | BE23: =IFERROR( BE22/AZ22-1, "NA") -> -0.26950355 | BF23: =IFERROR( BF22/BA22-1, "NA") -> -0.17829457 | BG23: =BG22/BB22-1 -> -0.15275311 | BH23: =IFERROR( BH22/BC22-1, "NA") -> 0.0074074074 | BI23: =IFERROR( BI22/BD22-1, "NA") -> 0.015037594 | BJ23: =IFERROR( BJ22/BE22-1, "NA") -> 0.18446602 | BK23: =IFERROR( BK22/BF22-1, "NA") -> 0.066037736 | BL23: =BL22/BG22-1 -> 0.060796646 | BM23: =IFERROR( BM22/BH22-1, "NA") -> 0.095588235 | BN23: =IFERROR( BN22/BI22-1, "NA") -> 0.21481481 | BO23: =IFERROR( BO22/BJ22-1, "NA") -> 0.32786885 | BP23: =IFERROR( BP22/BK22-1, "NA") -> 0.088495575 | BQ23: =BQ22/BL22-1 -> 0.18181818 | BR23: =IFERROR( BR22/BM22-1, "NA") -> 0.15436242 | BS23: =IFERROR( BS22/BN22-1, "NA") -> 0.048780488 | BT23: =IFERROR( BT22/BO22-1, "NA") -> 0.037037037
B24: Leveraged Loans | I24: 120 | N24: 155 | S24: 212 | X24: 242 | AC24: 204 | AH24: 254 | AI24: 110 | AJ24: 121 | AK24: 78 | AL24: 70 | AM24: =SUM(AI24:AL24) -> 379 | AN24: 73 | AO24: 83 | AP24: 90 | AQ24: 96 | AR24: =SUM(AN24:AQ24) -> 342 | AS24: 89 | AT24: 43 | AU24: 72 | AV24: 82 | AW24: =SUM(AS24:AV24) -> 286 | AX24: 180 | AY24: 157 | AZ24: 145 | BA24: 124 | BB24: =SUM(AX24:BA24) -> 606 | BC24: 113 | BD24: 72 | BE24: 47 | BF24: 43 | BG24: =SUM(BC24:BF24) -> 275 | BH24: 59 | BI24: 68 | BJ24: 82 | BK24: 83 | BL24: =SUM(BH24:BK24) -> 292 | BM24: 155 | BN24: 147 | BO24: 120 | BP24: 105 | BQ24: =SUM(BM24:BP24) -> 527 | BR24: 160 | BS24: 98 | BT24: 155
B25: % y/y | I25: N/A | N25: =N24/I24-1 -> 0.29166667 | S25: =S24/N24-1 -> 0.36774194 | X25: =X24/S24-1 -> 0.14150943 | AC25: =AC24/X24-1 -> -0.15702479 | AH25: =AH24/AC24-1 -> 0.24509804 | AI25: N/A | AJ25: N/A | AK25: N/A | AL25: N/A | AM25: =AM24/AH24-1 -> 0.49212598 | AN25: =AN24/AI24-1 -> -0.33636364 | AO25: =AO24/AJ24-1 -> -0.31404959 | AP25: =AP24/AK24-1 -> 0.15384615 | AQ25: =AQ24/AL24-1 -> 0.37142857 | AR25: =AR24/AM24-1 -> -0.09762533 | AS25: =AS24/AN24-1 -> 0.21917808 | AT25: =AT24/AO24-1 -> -0.48192771 | ... BT25: =BT24/BO24-1 -> 0.29166667
B26: % of Ratings Revenue | I26: =I24/I31 -> 0.06360986 | N26: =N24/N31 -> 0.07514605 | S26: =S24/S31 -> 0.093565187 | X26: =X24/X31 -> 0.10367578 | AC26: =AC24/AC31 -> 0.086046904 | AH26: =AH24/AH31 -> 0.09157113 | AI26: =AI24/AI31 -> 0.152799 | AJ26: =AJ24/AJ31 -> 0.16084009 | AK26: =AK24/AK31 -> 0.12096774 | AL26: =AL24/AL31 -> 0.11756802 | AM26: =AM24/AM31 -> 0.13972865 | AN26: =AN24/AN31 -> 0.10893896 | AO26: =AO24/AO31 -> 0.1124052 | ... BT26: =BT24/BT31 -> 0.14149695
B27: Transaction | C27: =BQ27/BQ$31 -> 0.66359083 | E27: =0.62*E31 -> 280.612 | F27: =0.6*F31 -> 264.78 | G27: =0.62*G31 -> 293.446 | H27: =0.65*H31 -> 337.545 | I27: =SUM(E27:H27) -> 1176.383 | J27: =0.64*J31 -> 333.6 | K27: 343.6 | L27: 280.2 | M27: 319.6 | N27: =SUM(J27:M27) -> 1277 | O27: 315.6 | P27: 402.8 | Q27: 326.2 | R27: 338.4 | S27: =SUM(O27:R27) -> 1383 | T27: 380.9 | U27: 412.2 | V27: 316.3 | W27: 322.6 | X27: =SUM(T27:W27) -> 1432 | Y27: 294.5 | Z27: 389.2 | AA27: 382.7 | AB27: 374.5 | AC27: =SUM(Y27:AB27) -> 1440.9 | AD27: 431 | AE27: 449.1 | AF27: 450.5 | AG27: 477.2 | AH27: =SUM(AD27:AG27) -> 1807.8 | AI27: 463 | AJ27: 495.9 | AK27: 390.5 | AL27: 336.7 | AM27: =SUM(AI27:AL27) -> 1686.1 | AN27: 409.9 | AO27: 477.6 | AP27: 478.6 | AQ27: 443 | AR27: =SUM(AN27:AQ27) -> 1809.1 | AS27: 519 | AT27: 664 | AU27: 548 | AV27: 451 | AW27: =SUM(AS27:AV27) -> 2182 | AX27: 745 | AY27: 686 | AZ27: 631 | BA27: 578 | BB27: =SUM(AX27:BA27) -> 2640 | BC27: 529 | BD27: 409 | BE27: 296 | BF27: 277 | BG27: =SUM(BC27:BF27) -> 1511 | BH27: 431 | BI27: 443 | BJ27: 388 | BK27: 375 | BL27: =SUM(BH27:BK27) -> 1637 | BM27: 677 | BN27: 692 | BO27: 663 | BP27: 485 | BQ27: =SUM(BM27:BP27) -> 2517 | BR27: 732 | BS27: 663 | BT27: =BO27*(1+BT28) -> 752.505 | BU27: =BP27*(1+BU28) -> 550.475 | BV27: =SUM(BR27:BU27) -> 2697.98 | BW27: =BR27*(1+BW28) -> 805.2 | BX27: =BS27*(1+BX28) -> 729.3 | BY27: =BT27*(1+BY28) -> 812.7054 | BZ27: =BU27*(1+BZ28) -> 594.513 | CA27: =SUM(BW27:BZ27) -> 2941.7184 | CB27: =BW27*(1+CB28) -> 865.59 | CC27: =BX27*(1+CC28) -> 783.9975 | CD27: =BY27*(1+CD28) -> 873.65831 | CE27: =BZ27*(1+CE28) -> 639.10148 | CF27: =SUM(CB27:CE27) -> 3162.3473
B28: % y/y | I28: =IFERROR( I27/#REF!-1, "NA") -> NA | J28: =IFERROR( J27/E27-1, "NA") -> 0.18883013 | K28: =IFERROR( K27/F27-1, "NA") -> 0.29768109 | L28: =IFERROR( L27/G27-1, "NA") -> -0.045139481 | M28: =IFERROR( M27/H27-1, "NA") -> -0.053163282 | N28: =IFERROR( N27/I27-1, "NA") -> 0.085530818 | O28: =IFERROR( O27/J27-1, "NA") -> -0.053956835 | P28: =IFERROR( P27/K27-1, "NA") -> 0.17229336 | Q28: =IFERROR( Q27/L27-1, "NA") -> 0.16416845 | ... BS28: =IFERROR( BS27/BN27-1, "NA") -> -0.041907514 | BT28: 0.135 | BU28: 0.135 | BV28: =IFERROR( BV27/BQ27-1, "NA") -> 0.071903059 | BW28: 0.1 | BX28: 0.1 | BY28: 0.08 | BZ28: 0.08 | CA28: =IFERROR( CA27/BV27-1, "NA") -> 0.09034107 | CB28: 0.075 | CC28: 0.075 | CD28: 0.075 | CE28: 0.075 | CF28: =IFERROR( CF27/CA27-1, "NA") -> 0.075
B29: Non-transaction (MCO deems "recurring") | C29: =BQ29/BQ$31 -> 0.33640917 | E29: =0.38*E31 -> 171.988 | F29: =0.4*F31 -> 176.52 | G29: =0.38*G31 -> 179.854 | H29: =0.35*H31 -> 181.755 | I29: =SUM(E29:H29) -> 710.117 | J29: =0.36*J31 -> 187.65 | K29: 193.7 | L29: 197.9 | M29: 206.4 | N29: =SUM(J29:M29) -> 785.65 | O29: 213.5 | P29: 222.2 | Q29: 220.4 | R29: 226.7 | S29: =SUM(O29:R29) -> 882.8 | T29: 221.4 | U29: 227 | V29: 231.8 | W29: 222 | X29: =SUM(T29:W29) -> 902.2 | Y29: 230.6 | Z29: 236.4 | AA29: 229.6 | AB29: 233.3 | AC29: =SUM(Y29:AB29) -> 929.9 | AD29: 237.2 | AE29: 237.6 | AF29: 243.7 | AG29: 247.5 | AH29: =SUM(AD29:AG29) -> 966 | AI29: 256.9 | AJ29: 256.4 | AK29: 254.3 | AL29: 258.7 | AM29: =SUM(AI29:AL29) -> 1026.3 | AN29: 260.2 | AO29: 260.8 | AP29: 268 | AQ29: 277 | AR29: =SUM(AN29:AQ29) -> 1066 | AS29: 275 | AT29: 274 | AU29: 277 | AV29: 284 | AW29: =SUM(AS29:AV29) -> 1110 | AX29: 291 | AY29: 294 | AZ29: 294 | BA29: 293 | BB29: =SUM(AX29:BA29) -> 1172 | BC29: 298 | BD29: 297 | BE29: 294 | BF29: 299 | BG29: =SUM(BC29:BF29) -> 1188 | BH29: 302 | BI29: 304 | BJ29: 308 | BK29: 309 | BL29: =SUM(BH29:BK29) -> 1223 | BM29: 310 | BN29: 323 | BO29: 319 | BP29: 324 | BQ29: =SUM(BM29:BP29) -> 1276 | BR29: 333 | BS29: 347 | BT29: =BO29*(1+BT30) -> 342.925 | BU29: =BP29*(1+BU30) -> 348.3 | BV29: =SUM(BR29:BU29) -> 1371.225 | BW29: =BR29*(1+BW30) -> 354.645 | BX29: =BS29*(1+BX30) -> 369.555 | BY29: =BT29*(1+BY30) -> 361.78587 | BZ29: =BU29*(1+BZ30) -> 367.4565 | CA29: =SUM(BW29:BZ29) -> 1453.4424 | CB29: =BW29*(1+CB30) -> 374.15047 | CC29: =BX29*(1+CC30) -> 389.88052 | CD29: =BY29*(1+CD30) -> 381.6841 | CE29: =BZ29*(1+CE30) -> 387.66661 | CF29: =SUM(CB29:CE29) -> 1533.3817
B30: % y/y | I30: =IFERROR( I29/#REF!-1, "NA") -> NA | J30: =IFERROR( J29/E29-1, "NA") -> 0.091064493 | K30: =IFERROR( K29/F29-1, "NA") -> 0.097326082 | L30: =IFERROR( L29/G29-1, "NA") -> 0.10033694 | M30: =IFERROR( M29/H29-1, "NA") -> 0.13559462 | N30: =IFERROR( N29/I29-1, "NA") -> 0.10636698 | O30: =IFERROR( O29/J29-1, "NA") -> 0.13775646 | P30: =IFERROR( P29/K29-1, "NA") -> 0.14713474 | Q30: =IFERROR( Q29/L29-1, "NA") -> 0.11369378 | ... BS30: =IFERROR( BS29/BN29-1, "NA") -> 0.074303406 | BT30: 0.075 | BU30: 0.075 | BV30: =IFERROR( BV29/BQ29-1, "NA") -> 0.074627743 | BW30: 0.065 | BX30: 0.065 | BY30: 0.055 | BZ30: 0.055 | CA30: =IFERROR( CA29/BV29-1, "NA") -> 0.059959069 | CB30: 0.055 | CC30: 0.055 | CD30: 0.055 | CE30: 0.055 | CF30: =IFERROR( CF29/CA29-1, "NA") -> 0.055
B31: RATINGS REVENUE | E31: =E16+E18+E20+E22 -> 452.6 | F31: =F16+F18+F20+F22 -> 441.3 | G31: =G16+G18+G20+G22 -> 473.3 | H31: =H16+H18+H20+H22 -> 519.3 | I31: =I16+I18+I20+I22 -> 1886.5 | J31: =J16+J18+J20+J22 -> 521.25 | K31: =K29+K27 -> 537.3 | L31: =L29+L27 -> 478.1 | M31: =M29+M27 -> 526 | N31: =N16+N18+N20+N22 -> 2062.65 | O31: =O29+O27 -> 529.1 | P31: =P29+P27 -> 625 | Q31: =Q29+Q27 -> 546.6 | R31: =R29+R27 -> 565.1 | S31: =S29+S27 -> 2265.8 | T31: =T29+T27 -> 602.3 | U31: =U29+U27 -> 639.2 | V31: =V29+V27 -> 548.1 | ... AN31: =AN29+AN27 -> 670.1 | AO31: =AO16+AO18+AO20+AO22 -> 738.4 | AP31: =AP16+AP18+AP20+AP22 -> 746.6 | AQ31: =AQ16+AQ18+AQ20+AQ22 -> 720 | AR31: =AR29+AR27 -> 2875.1 | AS31: =AS16+AS18+AS20+AS22 -> 794 | AT31: =AT16+AT18+AT20+AT22 -> 938 | AU31: =AU16+AU18+AU20+AU22 -> 825 | AV31: =AV16+AV18+AV20+AV22 -> 735 | AW31: =AW29+AW27 -> 3292 | AX31: =AX29+AX27 -> 1036 | AY31: =AY29+AY27 -> 980 | AZ31: =AZ29+AZ27 -> 925 | BA31: =BA29+BA27 -> 871 | BB31: =BB29+BB27 -> 3812 | BC31: =BC29+BC27 -> 827 | BD31: =BD29+BD27 -> 706 | ... CF31: =CF29+CF27 -> 4695.729
B32: Reported growth % y/y | J32: =IFERROR( J31/E31-1, "NA") -> 0.15167919 | K32: =IFERROR( K31/F31-1, "NA") -> 0.21753909 | L32: =IFERROR( L31/G31-1, "NA") -> 0.010141559 | M32: =IFERROR( M31/H31-1, "NA") -> 0.012901983 | N32: =IFERROR( N31/I31-1, "NA") -> 0.093373973 | O32: =IFERROR( O31/J31-1, "NA") -> 0.015059952 | P32: =IFERROR( P31/K31-1, "NA") -> 0.16322353 | Q32: =IFERROR( Q31/L31-1, "NA") -> 0.14327547 | ... CF32: =IFERROR( CF31/CA31-1, "NA") -> 0.06838617
B33: M&A impact % y/y | O33: 0 | P33: 0.02 | Q33: 0.02 | R33: 0.02 | S33: =SUMPRODUCT(O33:R33,J$31:M$31)/N$31 -> 0.014945822 | T33: 0.02 | U33: 0 | V33: 0 | W33: 0 | X33: =SUMPRODUCT(T33:W33,O$31:R$31)/S$31 -> 0.0046703151 | Y33: 0 | Z33: 0 | AA33: 0 | AB33: 0 | AC33: =SUMPRODUCT(Y33:AB33,T$31:W$31)/X$31 -> 0 | AD33: 0 | AE33: 0 | AF33: 0 | AG33: 0 | AH33: =SUMPRODUCT(AD33:AG33,Y$31:AB$31)/AC$31 -> 0 | AI33: 0 | AJ33: 0 | AK33: 0 | AL33: 0 | AM33: =SUMPRODUCT(AI33:AL33,AD$31:AG$31)/AH$31 -> 0 | AN33: 0 | AO33: 0 | AP33: 0 | AQ33: 0 | AR33: =SUMPRODUCT(AN33:AQ33,AI$31:AL$31)/AM$31 -> 0 | AS33: 0 | AT33: 0 | AU33: 0 | AV33: 0 | AW33: =SUMPRODUCT(AS33:AV33,AN$31:AQ$31)/AR$31 -> 0 | AX33: 0 | AY33: 0 | AZ33: 0 | BA33: 0 | BB33: =SUMPRODUCT(AX33:BA33,AS$31:AV$31)/AW$31 -> 0 | BC33: 0 | BD33: 0 | BE33: 0 | BF33: 0 | BG33: =SUMPRODUCT(BC33:BF33,AX$31:BA$31)/BB$31 -> 0 | BH33: 0 | BI33: =BI216/BD31 -> 0 | BJ33: =BJ216/BE31 -> 0 | BK33: =BK216/BF31 -> 0 | BL33: =SUMPRODUCT(BH33:BK33,BC$31:BF$31)/BG$31 -> 0 | BM33: 0 | BN33: =BN216/BI31 -> 0 | BO33: =BO216/BJ31 -> 0.0043103448 | BP33: =BP216/BK31 -> 0.0043859649 | BQ33: =SUMPRODUCT(BM33:BP33,BH$31:BK$31)/BL$31 -> 0.0020979021 | BR33: =BR216/BM31 -> 0.0040526849 | BS33: =BS216/BN31 -> 0.002955665 | BT33: =BT216/BO31 -> 0 | BU33: =BU216/BP31 -> 0.0024721879 | BV33: =SUMPRODUCT(BR33:BU33,BM$31:BP$31)/BQ$31 -> 0.002372792 | BW33: =BW216/BR31 -> 0.0018779343 | BX33: =BX216/BS31 -> 0.001980198 | BY33: =BY216/BT31 -> 0.00091288353 | BZ33: =BZ216/BU31 -> 0 | CA33: =SUMPRODUCT(BW33:BZ33,BR$31:BU$31)/BV$31 -> 0.0012287412 | CB33: 0 | CC33: =CC216/BX31 -> 0 | CD33: =CD216/BY31 -> 0 | CE33: =CE216/BZ31 -> 0 | CF33: =SUMPRODUCT(CB33:CE33,BW$31:BZ$31)/CA$31 -> 0
B34: Organic growth % y/y | O34: =O32-O33 -> 0.015059952 | P34: =P32-P33 -> 0.14322353 | Q34: =Q32-Q33 -> 0.12327547 | R34: =R32-R33 -> 0.054334601 | S34: =SUMPRODUCT(O34:R34,J$31:M$31)/N$31 -> 0.083543985 | T34: =T32-T33 -> 0.11834814 | U34: =U32-U33 -> 0.02272 | V34: =V32-V33 -> 0.0027442371 | W34: =W32-W33 -> -0.036276765 | X34: =SUMPRODUCT(T34:W34,O$31:R$31)/S$31 -> 0.025517698 | Y34: =Y32-Y33 -> -0.12817533 | Z34: =Z32-Z33 -> -0.021276596 | AA34: =AA32-AA33 -> 0.11713191 | AB34: =AB32-AB33 -> 0.11604848 | AC34: =SUMPRODUCT(Y34:AB34,T$31:W$31)/X$31 -> 0.01567989 | AD34: =AD32-AD33 -> 0.27251952 | AE34: =AE32-AE33 -> 0.09766624 | AF34: =AF32-AF33 -> 0.13375796 | AG34: =AG32-AG33 -> 0.192333 | AH34: =SUMPRODUCT(AD34:AG34,Y$31:AB$31)/AC$31 -> 0.16998482 | AI34: =AI32-AI33 -> 0.077372044 | AJ34: =AJ32-AJ33 -> 0.095529343 | AK34: =AK32-AK33 -> -0.071161049 | AL34: =AL32-AL33 -> -0.17841866 | AM34: =SUMPRODUCT(AI34:AL34,AD$31:AG$31)/AH$31 -> -0.022135698 | AN34: =AN32-AN33 -> -0.069176274 | AO34: =AO32-AO33 -> -0.018476672 | AP34: =AP32-AP33 -> 0.15787841 | AQ34: =AQ32-AQ33 -> 0.20927108 | AR34: =SUMPRODUCT(AN34:AQ34,AI$31:AL$31)/AM$31 -> 0.059983778 | AS34: =AS32-AS33 -> 0.18489778 | AT34: =AT32-AT33 -> 0.27031419 | AU34: =AU32-AU33 -> 0.10500938 | AV34: =AV32-AV33 -> 0.020833333 | AW34: =SUMPRODUCT(AS34:AV34,AN$31:AQ$31)/AR$31 -> 0.14500365 | AX34: =AX32-AX33 -> 0.30478589 | AY34: =AY32-AY33 -> 0.044776119 | AZ34: =AZ32-AZ33 -> 0.12121212 | BA34: =BA32-BA33 -> 0.18503401 | BB34: =SUMPRODUCT(AX34:BA34,AS$31:AV$31)/AW$31 -> 0.15795869 | BC34: =BC32-BC33 -> -0.20173745 | BD34: =BD32-BD33 -> -0.27959184 | BE34: =BE32-BE33 -> -0.36216216 | BF34: =BF32-BF33 -> -0.33869116 | BG34: =SUMPRODUCT(BC34:BF34,AX$31:BA$31)/BB$31 -> -0.29197272 | BH34: =BH32-BH33 -> -0.11366385 | BI34: =BI32-BI33 -> 0.058073654 | BJ34: =BJ32-BJ33 -> 0.17966102 | BK34: =BK32-BK33 -> 0.1875 | BL34: =SUMPRODUCT(BH34:BK34,BC$31:BF$31)/BG$31 -> 0.059651723 | BM34: =BM32-BM33 -> 0.34652115 | BN34: =BN32-BN33 -> 0.35876841 | BO34: =BO32-BO33 -> 0.4066092 | BP34: =BP32-BP33 -> 0.17836257 | BQ34: =SUMPRODUCT(BM34:BP34,BH$31:BK$31)/BL$31 -> 0.32412587 | BR34: =BR32-BR33 -> 0.074974671 | BS34: =BS32-BS33 -> -0.0078817734 | BT34: =BT32-BT33 -> 0.11550916 | BU34: =BU32-BU33 -> 0.10849815 | BV34: =SUMPRODUCT(BR34:BU34,BM$31:BP$31)/BQ$31 -> 0.070446876 | BW34: =BW32-BW33 -> 0.087178404 | BX34: =BX32-BX33 -> 0.08599505 | BY34: =BY32-BY33 -> 0.071260852 | BZ34: =BZ32-BZ33 -> 0.070311813 | CA34: =SUMPRODUCT(BW34:BZ34,BR$31:BU$31)/BV$31 -> 0.078874319 | CB34: =CB32-CB33 -> 0.068884614 | CC34: =CC32-CC33 -> 0.068273817 | CD34: =CD32-CD33 -> 0.068839275 | CE34: =CE32-CE33 -> 0.06736033 | CF34: =SUMPRODUCT(CB34:CE34,BW$31:BZ$31)/CA$31 -> 0.06838617
B35: FX impact % y/y | O35: 0 | P35: 0.01 | Q35: 0 | R35: -0.03 | S35: =SUMPRODUCT(O35:R35,J$31:M$31)/N$31 -> -0.0050454512 | T35: -0.05 | U35: -0.05 | V35: -0.05 | W35: -0.04 | X35: =SUMPRODUCT(T35:W35,O$31:R$31)/S$31 -> -0.047505958 | Y35: -0.014 | Z35: 0 | AA35: 0 | AB35: 0 | AC35: =SUMPRODUCT(Y35:AB35,T$31:W$31)/X$31 -> -0.0036124582 | AD35: 0 | AE35: 0 | AF35: 0.01 | AG35: 0.03 | AH35: =SUMPRODUCT(AD35:AG35,Y$31:AB$31)/AC$31 -> 0.010273747 | AI35: 0.032 | AJ35: 0.01 | AK35: 0 | AL35: -0.01 | AM35: =SUMPRODUCT(AI35:AL35,AD$31:AG$31)/AH$31 -> 0.0075717067 | AN35: -0.02 | AO35: -0.018 | AP35: -0.01 | AQ35: -0.01 | AR35: =SUMPRODUCT(AN35:AQ35,AI$31:AL$31)/AM$31 -> -0.014872954 | AS35: -0.01 | AT35: -0.01 | AU35: 0 | AV35: 0.02 | AW35: =SUMPRODUCT(AS35:AV35,AN$31:AQ$31)/AR$31 -> 0.00010956141 | AX35: 0.03 | AY35: 0.02 | AZ35: 0.002 | BA35: 0 | BB35: =SUMPRODUCT(AX35:BA35,AS$31:AV$31)/AW$31 -> 0.013435601 | BC35: -0.01 | BD35: =-20/AY31 -> -0.020408163 | BE35: =-(67-41)/AZ31 -> -0.028108108 | BF35: =-(51-32)/BA31 -> -0.021814007 | BG35: =SUMPRODUCT(BC35:BF35,AX$31:BA$31)/BB$31 -> -0.01976915 | BH35: =-10/BC31 -> -0.012091898 | BI35: 0 | BJ35: 0 | BK35: =9/BF31 -> 0.015625 | BL35: =SUMPRODUCT(BH35:BK35,BC$31:BF$31)/BG$31 -> -0.0003705076 | BM35: =1/BH31 -> 0.0013642565 | BN35: =-5/BI31 -> -0.0066934404 | BO35: =3/BJ31 -> 0.0043103448 | BP35: =-4/BK31 -> -0.0058479532 | BQ35: =SUMPRODUCT(BM35:BP35,BH$31:BK$31)/BL$31 -> -0.0017482517 | BR35: =-6/BM31 -> -0.0060790274 | BS35: =12/BN31 -> 0.01182266 | BT35: =BT246 -> 0.010183299 | BU35: =BU246 -> 0.015241758 | BV35: =SUMPRODUCT(BR35:BU35,BM$31:BP$31)/BQ$31 -> 0.0074691753 | BW35: =BW245*$BB$247 -> 0.021364132 | BX35: =BX245*$BB$247 -> 0.003008046 | BY35: =BY245*$BB$247 -> -0.0022191205 | BZ35: =BZ245*$BB$247 -> -0.0036363533 | CA35: =SUMPRODUCT(BW35:BZ35,BR$31:BU$31)/BV$31 -> 0.004937518 | CB35: =CB245*$BB$247 -> -0.00099011186 | CC35: =CC245*$BB$247 -> -0.00099011186 | CD35: =CD245*$BB$247 -> -0.00099011186 | CE35: =CE245*$BB$247 -> -0.00099011186 | CF35: =SUMPRODUCT(CB35:CE35,BW$31:BZ$31)/CA$31 -> -0.00099011186
B36: MIS organic constant currency growth % y/y | O36: =IFERROR(O32-O33-O35,"NA") -> 0.015059952 | P36: =IFERROR(P32-P33-P35,"NA") -> 0.13322353 | Q36: =IFERROR(Q32-Q33-Q35,"NA") -> 0.12327547 | R36: =IFERROR(R32-R33-R35,"NA") -> 0.084334601 | S36: =SUMPRODUCT(O36:R36,J$31:M$31)/N$31 -> 0.088589436 | T36: =IFERROR(T32-T33-T35,"NA") -> 0.16834814 | U36: =IFERROR(U32-U33-U35,"NA") -> 0.07272 | V36: =IFERROR(V32-V33-V35,"NA") -> 0.052744237 | W36: =IFERROR(W32-W33-W35,"NA") -> 0.0037232348 | X36: =SUMPRODUCT(T36:W36,O$31:R$31)/S$31 -> 0.073023656 | Y36: =IFERROR(Y32-Y33-Y35,"NA") -> -0.11417533 | Z36: =IFERROR(Z32-Z33-Z35,"NA") -> -0.021276596 | AA36: =IFERROR(AA32-AA33-AA35,"NA") -> 0.11713191 | AB36: =IFERROR(AB32-AB33-AB35,"NA") -> 0.11604848 | AC36: =SUMPRODUCT(Y36:AB36,T$31:W$31)/X$31 -> 0.019292349 | AD36: =IFERROR(AD32-AD33-AD35,"NA") -> 0.27251952 | AE36: =IFERROR(AE32-AE33-AE35,"NA") -> 0.09766624 | AF36: =IFERROR(AF32-AF33-AF35,"NA") -> 0.12375796 | AG36: =IFERROR(AG32-AG33-AG35,"NA") -> 0.162333 | AH36: =SUMPRODUCT(AD36:AG36,Y$31:AB$31)/AC$31 -> 0.15971107 | AI36: =IFERROR(AI32-AI33-AI35,"NA") -> 0.045372044 | AJ36: =IFERROR(AJ32-AJ33-AJ35,"NA") -> 0.085529343 | AK36: =IFERROR(AK32-AK33-AK35,"NA") -> -0.071161049 | AL36: =IFERROR(AL32-AL33-AL35,"NA") -> -0.16841866 | AM36: =SUMPRODUCT(AI36:AL36,AD$31:AG$31)/AH$31 -> -0.029707405 | AN36: =IFERROR(AN32-AN33-AN35,"NA") -> -0.049176274 | AO36: =IFERROR(AO32-AO33-AO35,"NA") -> -0.00047667154 | AP36: =IFERROR(AP32-AP33-AP35,"NA") -> 0.16787841 | AQ36: =IFERROR(AQ32-AQ33-AQ35,"NA") -> 0.21927108 | AR36: =SUMPRODUCT(AN36:AQ36,AI$31:AL$31)/AM$31 -> 0.074856732 | AS36: =IFERROR(AS32-AS33-AS35,"NA") -> 0.19489778 | AT36: =IFERROR(AT32-AT33-AT35,"NA") -> 0.28031419 | AU36: =IFERROR(AU32-AU33-AU35,"NA") -> 0.10500938 | AV36: =IFERROR(AV32-AV33-AV35,"NA") -> 0.00083333333 | AW36: =SUMPRODUCT(AS36:AV36,AN$31:AQ$31)/AR$31 -> 0.14489409 | AX36: =IFERROR(AX32-AX33-AX35,"NA") -> 0.27478589 | AY36: =IFERROR(AY32-AY33-AY35,"NA") -> 0.024776119 | AZ36: =IFERROR(AZ32-AZ33-AZ35,"NA") -> 0.11921212 | BA36: =IFERROR(BA32-BA33-BA35,"NA") -> 0.18503401 | BB36: =SUMPRODUCT(AX36:BA36,AS$31:AV$31)/AW$31 -> 0.14452309 | BC36: =IFERROR(BC32-BC33-BC35,"NA") -> -0.19173745 | BD36: =IFERROR(BD32-BD33-BD35,"NA") -> -0.25918367 | BE36: =IFERROR(BE32-BE33-BE35,"NA") -> -0.33405405 | BF36: =IFERROR(BF32-BF33-BF35,"NA") -> -0.31687715 | BG36: =SUMPRODUCT(BC36:BF36,AX$31:BA$31)/BB$31 -> -0.27220357 | BH36: =IFERROR(BH32-BH33-BH35,"NA") -> -0.10157195 | BI36: =IFERROR(BI32-BI33-BI35,"NA") -> 0.058073654 | BJ36: =IFERROR(BJ32-BJ33-BJ35,"NA") -> 0.17966102 | BK36: =IFERROR(BK32-BK33-BK35,"NA") -> 0.171875 | BL36: =SUMPRODUCT(BH36:BK36,BC$31:BF$31)/BG$31 -> 0.06002223 | BM36: =IFERROR(BM32-BM33-BM35,"NA") -> 0.34515689 | BN36: =IFERROR(BN32-BN33-BN35,"NA") -> 0.36546185 | BO36: =IFERROR(BO32-BO33-BO35,"NA") -> 0.40229885 | BP36: =IFERROR(BP32-BP33-BP35,"NA") -> 0.18421053 | BQ36: =SUMPRODUCT(BM36:BP36,BH$31:BK$31)/BL$31 -> 0.32587413 | BR36: =IFERROR(BR32-BR33-BR35,"NA") -> 0.081053698 | BS36: =IFERROR(BS32-BS33-BS35,"NA") -> -0.019704433 | BT36: =IFERROR(BT32-BT33-BT35,"NA") -> 0.10532587 | BU36: =IFERROR(BU32-BU33-BU35,"NA") -> 0.093256388 | BV36: =SUMPRODUCT(BR36:BU36,BM$31:BP$31)/BQ$31 -> 0.062977701 | BW36: =IFERROR(BW32-BW33-BW35,"NA") -> 0.065814271 | BX36: =IFERROR(BX32-BX33-BX35,"NA") -> 0.082987004 | BY36: =IFERROR(BY32-BY33-BY35,"NA") -> 0.073479972 | BZ36: =IFERROR(BZ32-BZ33-BZ35,"NA") -> 0.073948167 | CA36: =SUMPRODUCT(BW36:BZ36,BR$31:BU$31)/BV$31 -> 0.073936801 | CB36: =IFERROR(CB32-CB33-CB35,"NA") -> 0.069874726 | CC36: =IFERROR(CC32-CC33-CC35,"NA") -> 0.069263929 | CD36: =IFERROR(CD32-CD33-CD35,"NA") -> 0.069829387 | CE36: =IFERROR(CE32-CE33-CE35,"NA") -> 0.068350441 | CF36: =SUMPRODUCT(CB36:CE36,BW$31:BZ$31)/CA$31 -> 0.069376282
B37: Reported growth % sequential | O37: =O31/M31-1 -> 0.0058935361 | P37: =P31/O31-1 -> 0.18125118 | Q37: =Q31/P31-1 -> -0.12544 | R37: =R31/Q31-1 -> 0.033845591 | T37: =T31/R31-1 -> 0.065829057 | U37: =U31/T31-1 -> 0.06126515 | V37: =V31/U31-1 -> -0.1425219 | W37: =W31/V31-1 -> -0.006385696 | Y37: =Y31/W31-1 -> -0.035806096 | Z37: =Z31/Y31-1 -> 0.19139212 | AA37: =AA31/Z31-1 -> -0.021259591 | AB37: =AB31/AA31-1 -> -0.0073493386 | AD37: =AD31/AB31-1 -> 0.099374794 | AE37: =AE31/AD31-1 -> 0.027686321 | AF37: =AF31/AE31-1 -> 0.0109218 | AG37: =AG31/AF31-1 -> 0.043935465 | AI37: =AI31/AG31-1 -> -0.0066234304 | AJ37: =AJ31/AI31-1 -> 0.045006251 | AK37: =AK31/AJ31-1 -> -0.14289512 | AL37: =AL31/AK31-1 -> -0.076612903 | AN37: =AN31/AL31-1 -> 0.12546187 | AO37: =AO31/AN31-1 -> 0.10192509 | AP37: =AP31/AO31-1 -> 0.011105092 | AQ37: =AQ31/AP31-1 -> -0.035628181 | AS37: =AS31/AQ31-1 -> 0.10277778 | AT37: =AT31/AS31-1 -> 0.1813602 | AU37: =AU31/AT31-1 -> -0.12046908 | AV37: =AV31/AU31-1 -> -0.10909091 | AX37: =AX31/AV31-1 -> 0.40952381 | AY37: =AY31/AX31-1 -> -0.054054054 | AZ37: =AZ31/AY31-1 -> -0.056122449 | BA37: =BA31/AZ31-1 -> -0.058378378 | BC37: =BC31/BA31-1 -> -0.050516648 | BD37: =BD31/BC31-1 -> -0.14631197 | BE37: =BE31/BD31-1 -> -0.16430595 | BF37: =BF31/BE31-1 -> -0.023728814 | BH37: =BH31/BF31-1 -> 0.27256944 | BI37: =BI31/BH31-1 -> 0.019099591 | BJ37: =BJ31/BI31-1 -> -0.068273092 | BK37: =BK31/BJ31-1 -> -0.017241379 | BM37: =BM31/BK31-1 -> 0.44298246 | BN37: =BN31/BM31-1 -> 0.028368794 | BO37: =BO31/BN31-1 -> -0.032512315 | BP37: =BP31/BO31-1 -> -0.17617108 | BR37: =BR31/BP31-1 -> 0.31644005 | BS37: =BS31/BR31-1 -> -0.051643192 | BT37: =BT31/BS31-1 -> 0.084584158 | BU37: =BU31/BT31-1 -> -0.17952311 | BW37: =BW31/BU31-1 -> 0.29047314 | BX37: =BX31/BW31-1 -> -0.052584613 | BY37: =BY31/BX31-1 -> 0.068831898 | BZ37: =BZ31/BY31-1 -> -0.18094794 | CB37: =CB31/BZ31-1 -> 0.28875237 | CC37: =CC31/CB31-1 -> -0.053125998 | CD37: =CD31/CC31-1 -> 0.069397652 | CE37: =CE31/CD31-1 -> -0.18208126
AS38: =AS31/$AW$31 -> 0.24119077 | AT38: =AT31/$AW$31 -> 0.28493317 | AU38: =AU31/$AW$31 -> 0.25060753
B39: Operating and SG&A expenses | L39: 235.6 | M39: 269.7 | N39: 1034 | O39: 248.6 | P39: 271.7 | Q39: 263.4 | R39: 292.6 | S39: =SUM(O39:R39) -> 1076.3 | T39: 281.6 | U39: 287 | V39: 268.1 | W39: 283.9 | X39: =SUM(T39:W39) -> 1120.6 | Y39: 278.6 | Z39: 281.3 | AA39: 272.8 | AB39: 285.5 | AC39: =SUM(Y39:AB39) -> 1118.2 | AD39: 286.2 | AE39: 289.7 | AF39: 317.3 | AG39: 346.1 | AH39: =SUM(AD39:AG39) -> 1239.3 | AI39: 310.4 | AJ39: 303.6 | AK39: =303.5-AK43 -> 287.7 | AL39: 277.3 | AM39: =SUM(AI39:AL39) -> 1179 | AN39: 316.8 | AO39: 307 | AP39: =339.9-AP43-AP46 -> 312.6 | AQ39: =348-AQ43-AQ46 -> 328 | AR39: =SUM(AN39:AQ39) -> 1264.4 | AS39: =343-AS43-AS46 -> 328 | AT39: =369-AT43-AT46 -> 350 | AU39: =339-AU43-AU46 -> 309 | AV39: =425-AV43-AV46 -> 400 | AW39: =SUM(AS39:AV39) -> 1387 | AX39: =366-AX43-AX46 -> 348 | AY39: =362-AY43-AY46 -> 344 | AZ39: =404-AZ43-AZ46 -> 387 | BA39: 423 | BB39: =SUM(AX39:BA39) -> 1502 | BC39: 360 | BD39: 334 | BE39: 344 | BF39: 347 | BG39: =SUM(BC39:BF39) -> 1385 | BH39: 336 | BI39: 350 | BJ39: 348 | BK39: 352 | BL39: =SUM(BH39:BK39) -> 1386 | BM39: 366 | BN39: 392 | BO39: 416 | BP39: 418 | BQ39: =SUM(BM39:BP39) -> 1592 | BR39: 379 | BS39: 380 | BT39: =BT31-BT52 -> 392.84886 | BU39: =BU31-BU52 -> 405.96522 | BV39: =SUM(BR39:BU39) -> 1557.8141 | BW39: =BW31-BW52 -> 395.35468 | BX39: =BX31-BX52 -> 396.94777 | BY39: =BY31-BY52 -> 430.01092 | BZ39: =BZ31-BZ52 -> 441.72415 | CA39: =SUM(BW39:BZ39) -> 1664.0375 | CB39: =CB31-CB52 -> 407.09178 | CC39: =CC31-CC52 -> 409.37543 | CD39: =CD31-CD52 -> 447.05913 | CE39: =CE31-CE52 -> 461.21115 | CF39: =SUM(CB39:CE39) -> 1724.7375
B40: % y/y | L40: =IFERROR(L39/G39-1,"NA") -> NA | M40: =IFERROR(M39/H39-1,"NA") -> NA | N40: =IFERROR(N39/I39-1,"NA") -> NA | O40: =IFERROR(O39/J39-1,"NA") -> NA | P40: =IFERROR(P39/K39-1,"NA") -> NA | Q40: =IFERROR(Q39/L39-1,"NA") -> 0.1179966 | R40: =IFERROR(R39/M39-1,"NA") -> 0.084909158 | S40: =IFERROR(S39/N39-1,"NA") -> 0.040909091 | ... AH40: =IFERROR(AH39/AC39-1,"NA") -> 0.10829905 | AI40: =AI39/AD39-1 -> 0.084556254 | AJ40: =AJ39/AE39-1 -> 0.04798067 | AK40: =AK39/AF39-1 -> -0.09328711 | AL40: =AL39/AG39-1 -> -0.19878648 | AM40: =IFERROR(AM39/AH39-1,"NA") -> -0.0486565 | AN40: =AN39/AI39-1 -> 0.020618557 | AO40: =AO39/AJ39-1 -> 0.011198946 | AP40: =AP39/AK39-1 -> 0.086548488 | AQ40: =AQ39/AL39-1 -> 0.18283448 | AR40: =IFERROR(AR39/AM39-1,"NA") -> 0.072434266 | AS40: =AS39/AN39-1 -> 0.035353535 | AT40: =AT39/AO39-1 -> 0.14006515 | AU40: =AU39/AP39-1 -> -0.011516315 | AV40: =AV39/AQ39-1 -> 0.2195122 | AW40: =IFERROR(AW39/AR39-1,"NA") -> 0.096962986 | AX40: =AX39/AS39-1 -> 0.06097561 | AY40: =AY39/AT39-1 -> -0.017142857 | AZ40: =AZ39/AU39-1 -> 0.25242718 | BA40: =BA39/AV39-1 -> 0.0575 | BB40: =IFERROR(BB39/AW39-1,"NA") -> 0.082912761 | BC40: =BC39/AX39-1 -> 0.034482759 | BD40: =BD39/AY39-1 -> -0.029069767 | BE40: =BE39/AZ39-1 -> -0.11111111 | BF40: =BF39/BA39-1 -> -0.17966903 | BG40: =IFERROR(BG39/BB39-1,"NA") -> -0.077896138 | BH40: =BH39/BC39-1 -> -0.066666667 | BI40: =BI39/BD39-1 -> 0.047904192 | BJ40: =BJ39/BE39-1 -> 0.011627907 | BK40: =BK39/BF39-1 -> 0.014409222 | BL40: =IFERROR(BL39/BG39-1,"NA") -> 0.00072202166 | BM40: =BM39/BH39-1 -> 0.089285714 | BN40: =BN39/BI39-1 -> 0.12 | BO40: =BO39/BJ39-1 -> 0.1954023 | BP40: =BP39/BK39-1 -> 0.1875 | BQ40: =IFERROR(BQ39/BL39-1,"NA") -> 0.14862915 | BR40: =BR39/BM39-1 -> 0.035519126 | BS40: =BS39/BN39-1 -> -0.030612245 | BT40: =BT39/BO39-1 -> -0.055651773 | BU40: =BU39/BP39-1 -> -0.028791329 | BV40: =IFERROR(BV39/BQ39-1,"NA") -> -0.021473563 | BW40: =BW39/BR39-1 -> 0.043152182 | BX40: =BX39/BS39-1 -> 0.044599392 | BY40: =BY39/BT39-1 -> 0.094596314 | BZ40: =BZ39/BU39-1 -> 0.088083708 | CA40: =IFERROR(CA39/BV39-1,"NA") -> 0.068187484 | CB40: =CB39/BW39-1 -> 0.029687516 | CC40: =CC39/BX39-1 -> 0.031308058 | CD40: =CD39/BY39-1 -> 0.039646007 | CE40: =CE39/BZ39-1 -> 0.044115775 | CF40: =IFERROR(CF39/CA39-1,"NA") -> 0.036477532
B41: % revenue | L41: =L39/L$31 -> 0.49278394 | M41: =M39/M$31 -> 0.51273764 | N41: =N39/N$31 -> 0.50129688 | O41: =O39/O$31 -> 0.46985447 | P41: =P39/P$31 -> 0.43472 | Q41: =Q39/Q$31 -> 0.48188804 | R41: =R39/R$31 -> 0.51778446 | S41: =S39/S$31 -> 0.47501986 | ... AZ41: =AZ39/AZ$31 -> 0.41837838 | BA41: =BA39/BA31 -> 0.48564868 | BB41: =BB39/BB$31 -> 0.39401889 | BC41: =BC39/BC$31 -> 0.43530834 | BD41: =BD39/BD$31 -> 0.47308782 | BE41: =BE39/BE31 -> 0.58305085 | BF41: =BF39/BF31 -> 0.60243056 | BG41: =BG39/BG$31 -> 0.51315302 | BH41: =BH39/BH$31 -> 0.45839018 | BI41: =BI39/BI$31 -> 0.46854083 | BJ41: =BJ39/BJ$31 -> 0.5 | BK41: =BK39/BK$31 -> 0.51461988 | BL41: =BL39/BL$31 -> 0.48461538 | BM41: =BM39/BM$31 -> 0.37082067 | BN41: =BN39/BN$31 -> 0.3862069 | BO41: =BO39/BO$31 -> 0.42362525 | BP41: =BP39/BP31 -> 0.51668727 | BQ41: =BQ39/BQ$31 -> 0.41972054 | BR41: =BR39/BR31 -> 0.35586854 | BS41: =BS39/BS31 -> 0.37623762 | BT41: =BT39/BT31 -> 0.35862525 | BU41: =BU39/BU31 -> 0.45168727 | BV41: =BV39/BV$31 -> 0.38283008 | BW41: =BW39/BW31 -> 0.34086854 | BX41: =BX39/BX31 -> 0.36123762 | BY41: =BY39/BY31 -> 0.36612525 | BZ41: =BZ39/BZ31 -> 0.45918727 | CA41: =CA39/CA$31 -> 0.37860674 | CB41: =CB39/CB31 -> 0.32836854 | CC41: =CC39/CC31 -> 0.34873762 | CD41: =CD39/CD31 -> 0.35612525 | CE41: =CE39/CE31 -> 0.44918727 | CF41: =CF39/CF$31 -> 0.3672992
B42: bps y/y | Q42: =(Q41-L41)*10000 -> -108.95901 | R42: =(R41-M41)*10000 -> 50.468203 | S42: =(S41-N41)*10000 -> -262.77015 | T42: =(T41-O41)*10000 -> -23.133774 | U42: =(U41-P41)*10000 -> 142.78748 | V42: =(V41-Q41)*10000 -> 72.562816 | W42: =(W41-R41)*10000 -> 35.155738 | X42: =(X41-S41)*10000 -> 50.589673 | ... CF42: =(CF41-CA41)*10000 -> -113.07546
B43: D&A | L43: 12.1 | M43: 11.7 | N43: 46.7 | O43: 11.4 | P43: 11.4 | Q43: 11.6 | R43: 15 | S43: =SUM(O43:R43) -> 49.4 | T43: 16 | U43: 15.8 | V43: 11.4 | W43: 17.3 | X43: =SUM(T43:W43) -> 60.5 | Y43: 17.5 | Z43: 18.2 | AA43: 19.1 | AB43: 19 | AC43: =SUM(Y43:AB43) -> 73.8 | AD43: 18.9 | AE43: 18.9 | AF43: 18.6 | AG43: 18.3 | AH43: =SUM(AD43:AG43) -> 74.7 | AI43: 16.8 | AJ43: 16.7 | AK43: 15.8 | AL43: 15.6 | AM43: =SUM(AI43:AL43) -> 64.9 | AN43: 17 | AO43: 18 | AP43: 18 | AQ43: 18 | AR43: =SUM(AN43:AQ43) -> 71 | AS43: 16 | AT43: 19 | AU43: 17 | AV43: 18 | AW43: =SUM(AS43:AV43) -> 70 | AX43: 18 | AY43: 18 | AZ43: 17 | BA43: 19 | BB43: =SUM(AX43:BA43) -> 72 | BC43: 18 | BD43: 21 | BE43: 21 | BF43: 21 | BG43: =SUM(BC43:BF43) -> 81 | BH43: 18 | BI43: 19 | BJ43: 19 | BK43: 19 | BL43: =SUM(BH43:BK43) -> 75 | BM43: 18 | BN43: 20 | BO43: 20 | BP43: 20 | BQ43: =SUM(BM43:BP43) -> 78 | BR43: 19 | BS43: 23 | BT43: =BO43+2 -> 22 | BU43: =BP43+2 -> 22 | BV43: =SUM(BR43:BU43) -> 86 | BW43: =BR43+1 -> 20 | BX43: =BS43+1 -> 24 | BY43: =BT43 -> 22 | BZ43: =BU43 -> 22 | CA43: =SUM(BW43:BZ43) -> 88 | CB43: =BZ43 -> 22 | CC43: =CB43 -> 22 | CD43: =CC43 -> 22 | CE43: =CD43 -> 22 | CF43: =SUM(CB43:CE43) -> 88
B44: % y/y | L44: =IFERROR(L43/G43-1,"NA") -> NA | M44: =IFERROR(M43/H43-1,"NA") -> NA | N44: =IFERROR(N43/I43-1,"NA") -> NA | O44: =IFERROR(O43/J43-1,"NA") -> NA | P44: =IFERROR(P43/K43-1,"NA") -> NA | Q44: =IFERROR(Q43/L43-1,"NA") -> -0.041322314 | R44: =IFERROR(R43/M43-1,"NA") -> 0.28205128 | S44: =IFERROR(S43/N43-1,"NA") -> 0.057815846 | ... AH44: =IFERROR(AH43/AC43-1,"NA") -> 0.012195122 | AI44: =AI43/AD43-1 -> -0.11111111 | AJ44: =AJ43/AE43-1 -> -0.11640212 | AK44: =AK43/AF43-1 -> -0.15053763 | AL44: =AL43/AG43-1 -> -0.14754098 | AM44: =IFERROR(AM43/AH43-1,"NA") -> -0.13119143 | AN44: =AN43/AI43-1 -> 0.011904762 | AO44: =AO43/AJ43-1 -> 0.077844311 | AP44: =AP43/AK43-1 -> 0.13924051 | AQ44: =AQ43/AL43-1 -> 0.15384615 | AR44: =IFERROR(AR43/AM43-1,"NA") -> 0.093990755 | AS44: =AS43/AN43-1 -> -0.058823529 | AT44: =AT43/AO43-1 -> 0.055555556 | AU44: =AU43/AP43-1 -> -0.055555556 | AV44: =AV43/AQ43-1 -> 0 | AW44: =IFERROR(AW43/AR43-1,"NA") -> -0.014084507 | AX44: =AX43/AS43-1 -> 0.125 | AY44: =AY43/AT43-1 -> -0.052631579 | AZ44: =AZ43/AU43-1 -> 0 | BA44: =BA43/AV43-1 -> 0.055555556 | BB44: =IFERROR(BB43/AW43-1,"NA") -> 0.028571429 | BC44: =BC43/AX43-1 -> 0 | BD44: =BD43/AY43-1 -> 0.16666667 | BE44: =BE43/AZ43-1 -> 0.23529412 | BF44: =BF43/BA43-1 -> 0.10526316 | BG44: =IFERROR(BG43/BB43-1,"NA") -> 0.125 | BH44: =BH43/BC43-1 -> 0 | BI44: =BI43/BD43-1 -> -0.095238095 | BJ44: =BJ43/BE43-1 -> -0.095238095 | BK44: =BK43/BF43-1 -> -0.095238095 | BL44: =IFERROR(BL43/BG43-1,"NA") -> -0.074074074 | BM44: =BM43/BH43-1 -> 0 | BN44: =BN43/BI43-1 -> 0.052631579 | BO44: =BO43/BJ43-1 -> 0.052631579 | BP44: =BP43/BK43-1 -> 0.052631579 | BQ44: =IFERROR(BQ43/BL43-1,"NA") -> 0.04 | BR44: =BR43/BM43-1 -> 0.055555556 | BS44: =BS43/BN43-1 -> 0.15 | BT44: =BT43/BO43-1 -> 0.1 | BU44: =BU43/BP43-1 -> 0.1 | BV44: =IFERROR(BV43/BQ43-1,"NA") -> 0.1025641 | BW44: =BW43/BR43-1 -> 0.052631579 | BX44: =BX43/BS43-1 -> 0.043478261 | BY44: =BY43/BT43-1 -> 0 | BZ44: =BZ43/BU43-1 -> 0 | CA44: =IFERROR(CA43/BV43-1,"NA") -> 0.023255814 | CB44: =CB43/BW43-1 -> 0.1 | CC44: =CC43/BX43-1 -> -0.083333333 | CD44: =CD43/BY43-1 -> 0 | CE44: =CE43/BZ43-1 -> 0 | CF44: =IFERROR(CF43/CA43-1,"NA") -> 0
B45: % revenue | L45: =L43/L$31 -> 0.025308513 | M45: =M43/M$31 -> 0.022243346 | N45: =N43/N$31 -> 0.022640778 | O45: =O43/O$31 -> 0.021546022 | P45: =P43/P$31 -> 0.01824 | Q45: =Q43/Q$31 -> 0.0212221 | R45: =R43/R$31 -> 0.026543975 | S45: =S43/S$31 -> 0.021802454 | ... CF45: =CF43/CF$31 -> 0.018740434
B46: M&A/Restructuring/Other | L46: 0 | M46: 0 | N46: 0 | O46: 0 | P46: 0 | Q46: 0 | R46: 0 | S46: =SUM(O46:R46) -> 0 | T46: 0 | U46: 0 | V46: 0 | W46: 0 | X46: =SUM(T46:W46) -> 0 | Y46: 0 | Z46: 0 | AA46: 7.6 | AB46: 863.8 | AC46: =SUM(Y46:AB46) -> 871.4 | AD46: 0 | AE46: 0 | AF46: 0 | AG46: 0 | AH46: =SUM(AD46:AG46) -> 0 | AI46: 0 | AJ46: 0 | AK46: 0 | AL46: 32.2 | AM46: =SUM(AI46:AL46) -> 32.2 | AN46: 2.7 | AO46: 26.5 | AP46: =9.4-0.1 -> 9.3 | AQ46: 2 | AR46: =SUM(AN46:AQ46) -> 40.5 | AS46: -1 | AT46: 0 | AU46: 13 | AV46: 7 | AW46: =SUM(AS46:AV46) -> 19 | AX46: 0 | AY46: 0 | AZ46: 0 | BA46: -1 | BB46: =SUM(AX46:BA46) -> -1 | BC46: 0 | BD46: 15 | BE46: 0 | BF46: 50 | BG46: =SUM(BC46:BF46) -> 65 | BH46: 6 | BI46: 2 | BJ46: 5 | BK46: 15 | BL46: =SUM(BH46:BK46) -> 28 | BM46: 2 | BN46: 1 | BO46: 2 | BP46: 11 | BQ46: =SUM(BM46:BP46) -> 16 | BR46: 7 | BS46: 9 | BT46: 4 | BU46: 4 | BV46: =SUM(BR46:BU46) -> 24 | BW46: 9 | BX46: 9 | BY46: 9 | BZ46: 9 | CA46: =SUM(BW46:BZ46) -> 36 | CB46: 0 | CC46: 0 | CD46: 0 | CE46: 0 | CF46: =SUM(CB46:CE46) -> 0
B47: % revenue | L47: =L46/L$31 -> 0 | M47: =M46/M$31 -> 0 | N47: =N46/N$31 -> 0 | O47: =O46/O$31 -> 0 | P47: =P46/P$31 -> 0 | Q47: =Q46/Q$31 -> 0 | R47: =R46/R$31 -> 0 | S47: =S46/S$31 -> 0 | ... CF47: =CF46/CF$31 -> 0
B48: Total operating expenses - MOODY'S INVESTOR SERVICE | L48: =L39+L43+L46 -> 247.7 | M48: =M39+M43+M46 -> 281.4 | N48: =N39+N43+N46 -> 1080.7 | O48: =O39+O43+O46 -> 260 | P48: =P39+P43+P46 -> 283.1 | Q48: =Q39+Q43+Q46 -> 275 | R48: =R39+R43+R46 -> 307.6 | S48: =SUM(O48:R48) -> 1125.7 | T48: =T39+T43+T46 -> 297.6 | U48: =U39+U43+U46 -> 302.8 | V48: =V39+V43+V46 -> 279.5 | W48: =W39+W43+W46 -> 301.2 | X48: =SUM(T48:W48) -> 1181.1 | Y48: =Y39+Y43+Y46 -> 296.1 | Z48: =Z39+Z43+Z46 -> 299.5 | AA48: =AA39+AA43+AA46 -> 299.5 | AB48: =AB39+AB43+AB46 -> 1168.3 | AC48: =SUM(Y48:AB48) -> 2063.4 | AD48: =AD39+AD43+AD46 -> 305.1 | AE48: =AE39+AE43+AE46 -> 308.6 | AF48: =AF39+AF43+AF46 -> 335.9 | AG48: =AG39+AG43+AG46 -> 364.4 | AH48: =SUM(AD48:AG48) -> 1314 | AI48: =AI39+AI43+AI46 -> 327.2 | AJ48: =AJ39+AJ43+AJ46 -> 320.3 | AK48: =AK39+AK43+AK46 -> 303.5 | AL48: =AL39+AL43+AL46 -> 325.1 | AM48: =SUM(AI48:AL48) -> 1276.1 | AN48: =AN39+AN43+AN46 -> 336.5 | AO48: =AO39+AO43+AO46 -> 351.5 | AP48: =AP39+AP43+AP46 -> 339.9 | AQ48: =AQ39+AQ43+AQ46 -> 348 | AR48: =SUM(AN48:AQ48) -> 1375.9 | AS48: =AS39+AS43+AS46 -> 343 | AT48: =AT39+AT43+AT46 -> 369 | AU48: =AU39+AU43+AU46 -> 339 | AV48: =AV39+AV43+AV46 -> 425 | AW48: =SUM(AS48:AV48) -> 1476 | AX48: =AX39+AX43+AX46 -> 366 | AY48: =AY39+AY43+AY46 -> 362 | AZ48: =AZ39+AZ43+AZ46 -> 404 | BA48: =BA39+BA43+BA46 -> 441 | BB48: =SUM(AX48:BA48) -> 1573 | BC48: =BC39+BC43+BC46 -> 378 | BD48: =BD39+BD43+BD46 -> 370 | BE48: =BE39+BE43+BE46 -> 365 | BF48: =BF39+BF43+BF46 -> 418 | BG48: =SUM(BC48:BF48) -> 1531 | BH48: =BH39+BH43+BH46 -> 360 | BI48: =BI39+BI43+BI46 -> 371 | BJ48: =BJ39+BJ43+BJ46 -> 372 | BK48: =BK39+BK43+BK46 -> 386 | BL48: =SUM(BH48:BK48) -> 1489 | BM48: =BM39+BM43+BM46 -> 386 | BN48: =BN39+BN43+BN46 -> 413 | BO48: =BO39+BO43+BO46 -> 438 | BP48: =BP39+BP43+BP46 -> 449 | BQ48: =SUM(BM48:BP48) -> 1686 | BR48: =BR39+BR43+BR46 -> 405 | BS48: =BS39+BS43+BS46 -> 412 | BT48: =BT39+BT43+BT46 -> 418.84886 | BU48: =BU39+BU43+BU46 -> 431.96522 | BV48: =SUM(BR48:BU48) -> 1667.8141 | BW48: =BW39+BW43+BW46 -> 424.35468 | BX48: =BX39+BX43+BX46 -> 429.94777 | BY48: =BY39+BY43+BY46 -> 461.01092 | BZ48: =BZ39+BZ43+BZ46 -> 472.72415 | CA48: =SUM(BW48:BZ48) -> 1788.0375 | CB48: =CB39+CB43+CB46 -> 429.09178 | CC48: =CC39+CC43+CC46 -> 431.37543 | CD48: =CD39+CD43+CD46 -> 469.05913 | CE48: =CE39+CE43+CE46 -> 483.21115 | CF48: =SUM(CB48:CE48) -> 1812.7375
B49: % y/y | L49: =IFERROR( L48/G48-1, "NA") -> NA | M49: =IFERROR( M48/H48-1, "NA") -> NA | N49: =IFERROR( N48/I48-1, "NA") -> NA | O49: =IFERROR( O48/J48-1, "NA") -> NA | P49: =IFERROR( P48/K48-1, "NA") -> NA | Q49: =IFERROR( Q48/L48-1, "NA") -> 0.11021397 | R49: =IFERROR( R48/M48-1, "NA") -> 0.093105899 | S49: =IFERROR( S48/N48-1, "NA") -> 0.041639678 | ... CF49: =IFERROR( CF48/CA48-1, "NA") -> 0.013814017
B50: % segment revenue | L50: =L48/L31 -> 0.51809245 | M50: =M48/M31 -> 0.53498099 | N50: =N48/N31 -> 0.52393765 | O50: =O48/O31 -> 0.49140049 | P50: =P48/P31 -> 0.45296 | Q50: =Q48/Q31 -> 0.50311014 | R50: =R48/R31 -> 0.54432844 | S50: =S48/S31 -> 0.49682231 | ... CF50: =CF48/CF31 -> 0.38603963
B52: Adj. operating income - MOODY'S INVESTOR SERVICE | L52: =L31-L39 -> 242.5 | M52: =M31-M39 -> 256.3 | N52: =N31-N39 -> 1028.65 | O52: =O31-O39 -> 280.5 | P52: =P31-P39 -> 353.3 | Q52: =Q31-Q39 -> 283.2 | R52: =R31-R39 -> 272.5 | S52: =SUM(O52:R52) -> 1189.5 | T52: =T31-T39 -> 320.7 | U52: =U31-U39 -> 352.2 | V52: =V31-V39 -> 280 | W52: =W31-W39 -> 260.7 | X52: =SUM(T52:W52) -> 1213.6 | Y52: =Y31-Y39 -> 246.5 | Z52: =Z31-Z39 -> 344.3 | AA52: =AA31-AA39 -> 339.5 | AB52: =AB31-AB39 -> 322.3 | AC52: =SUM(Y52:AB52) -> 1252.6 | AD52: =AD31-AD39 -> 382 | AE52: =AE31-AE39 -> 397 | AF52: =AF31-AF39 -> 376.9 | AG52: =AG31-AG39 -> 378.6 | AH52: =SUM(AD52:AG52) -> 1534.5 | AI52: =AI31-AI39 -> 409.5 | AJ52: =AJ31-AJ39 -> 448.7 | AK52: =AK31-AK39 -> 357.1 | AL52: =AL31-AL39 -> 318.1 | AM52: =SUM(AI52:AL52) -> 1533.4 | AN52: =AN31-AN39 -> 353.3 | AO52: =AO31-AO39 -> 431.4 | AP52: =AP31-AP39 -> 434 | AQ52: =AQ31-AQ39 -> 392 | AR52: =SUM(AN52:AQ52) -> 1610.7 | AS52: =AS31-AS39 -> 466 | AT52: =AT31-AT39 -> 588 | AU52: =AU31-AU39 -> 516 | AV52: =AV31-AV39 -> 335 | AW52: =SUM(AS52:AV52) -> 1905 | AX52: =AX31-AX39 -> 688 | AY52: =AY31-AY39 -> 636 | AZ52: =AZ31-AZ39 -> 538 | BA52: =BA31-BA39 -> 448 | BB52: =SUM(AX52:BA52) -> 2310 | BC52: =BC31-BC39 -> 467 | BD52: =BD31-BD39 -> 372 | BE52: =BE31-BE39 -> 246 | BF52: =BF31-BF39 -> 229 | BG52: =SUM(BC52:BF52) -> 1314 | BH52: =BH31-BH39 -> 397 | BI52: =BI31-BI39 -> 397 | BJ52: =BJ31-BJ39 -> 348 | BK52: =BK31-BK39 -> 332 | BL52: =SUM(BH52:BK52) -> 1474 | BM52: =BM31-BM39 -> 621 | BN52: =BN31-BN39 -> 623 | BO52: =BO31-BO39 -> 566 | BP52: =BP31-BP39 -> 391 | BQ52: =SUM(BM52:BP52) -> 2201 | BR52: =BR31-BR39 -> 686 | BS52: =BS31-BS39 -> 630 | BT52: =BT54*BT31 -> 702.58114 | BU52: =BU54*BU31 -> 492.80978 | BV52: =SUM(BR52:BU52) -> 2511.3909 | BW52: =BW54*BW31 -> 764.49032 | BX52: =BX54*BX31 -> 701.90723 | BY52: =BY54*BY31 -> 744.48036 | BZ52: =BZ54*BZ31 -> 520.24535 | CA52: =SUM(BW52:BZ52) -> 2731.1233 | CB52: =CB54*CB31 -> 832.6487 | CC52: =CC54*CC31 -> 764.50259 | CD52: =CD54*CD31 -> 808.28327 | CE52: =CE54*CE31 -> 565.55693 | CF52: =SUM(CB52:CE52) -> 2970.9915
B53: % growth y/y | L53: =IFERROR( L52/G52-1, "NA") -> NA | M53: =IFERROR( M52/H52-1, "NA") -> NA | N53: =IFERROR( N52/I52-1, "NA") -> NA | O53: =IFERROR( O52/J52-1, "NA") -> NA | P53: =IFERROR( P52/K52-1, "NA") -> NA | Q53: =IFERROR( Q52/L52-1, "NA") -> 0.16783505 | R53: =IFERROR( R52/M52-1, "NA") -> 0.063207179 | S53: =IFERROR( S52/N52-1, "NA") -> 0.15637 | ... CF53: =IFERROR( CF52/CA52-1, "NA") -> 0.087827683
B54: % margin | L54: =L52/(L31) -> 0.50721606 | M54: =M52/(M31) -> 0.48726236 | N54: =N52/(N31) -> 0.49870312 | O54: =O52/(O31) -> 0.53014553 | P54: =P52/(P31) -> 0.56528 | Q54: =Q52/(Q31) -> 0.51811196 | R54: =R52/(R31) -> 0.48221554 | S54: =S52/(S31) -> 0.52498014 | ... BS54: =BS52/(BS31) -> 0.62376238 | BT54: =BO54+(BT55/10000) -> 0.64137475 | BU54: =BP54+(BU55/10000) -> 0.54831273 | BV54: =BV52/(BV31) -> 0.61716992 | BW54: =BR54+(BW55/10000) -> 0.65913146 | BX54: =BS54+(BX55/10000) -> 0.63876238 | BY54: =BT54+(BY55/10000) -> 0.63387475 | BZ54: =BU54+(BZ55/10000) -> 0.54081273 | CA54: =CA52/(CA31) -> 0.62139326 | CB54: =BW54+(CB55/10000) -> 0.67163146 | CC54: =BX54+(CC55/10000) -> 0.65126238 | CD54: =BY54+(CD55/10000) -> 0.64387475 | CE54: =BZ54+(CE55/10000) -> 0.55081273 | CF54: =CF52/(CF31) -> 0.6327008
B55: margin y/y (bps) | L55: =(L54-G54)*10000 -> 5072.1606 | M55: =(M54-H54)*10000 -> 4872.6236 | N55: =(N54-I54)*10000 -> 4987.0312 | O55: =(O54-J54)*10000 -> 5301.4553 | P55: =(P54-K54)*10000 -> 5652.8 | Q55: =(Q54-L54)*10000 -> 108.95901 | R55: =(R54-M54)*10000 -> -50.468203 | S55: =(S54-N54)*10000 -> 262.77015 | ... BS55: =(BS54-BN54)*10000 -> 99.692728 | BT55: 650 | BU55: 650 | BV55: =(BV54-BQ54)*10000 -> 368.90455 | BW55: 150 | BX55: 150 | BY55: -75 | BZ55: -75 | CA55: =(CA54-BV54)*10000 -> 42.233389 | CB55: 125 | CC55: 125 | CD55: 100 | CE55: 100 | CF55: =(CF54-CA54)*10000 -> 113.07546
B56: margin sequential (bps) | L56: =(L54-J54)*10000 -> 5072.1606 | M56: =(M54-K54)*10000 -> 4872.6236 | N56: =(N54-L54)*10000 -> -85.12939 | O56: =(O54-M54)*10000 -> 428.83173 | P56: =(P54-O54)*10000 -> 351.3447 | Q56: =(Q54-P54)*10000 -> -471.68035 | R56: =(R54-Q54)*10000 -> -358.96428 | T56: =(T54-R54)*10000 -> 502.4337 | U56: =(U54-T54)*10000 -> 185.42344 | V56: =(V54-U54)*10000 -> -401.45568 | W56: =(W54-V54)*10000 -> -321.5572 | Y56: =(Y54-W54)*10000 -> -92.655698 | Z56: =(Z54-Y54)*10000 -> 809.17269 | AA56: =(AA54-Z54)*10000 -> 41.151023 | AB56: =(AB54-AA54)*10000 -> -241.93649 | AD56: =(AD54-AB54)*10000 -> 414.12008 | AE56: =(AE54-AD54)*10000 -> 64.421512 | AF56: =(AF54-AE54)*10000 -> -352.00165 | AG56: =(AG54-AF54)*10000 -> -205.04039 | AI56: =(AI54-AG54)*10000 -> 464.05932 | AJ56: =(AJ54-AI54)*10000 -> 276.08587 | AK56: =(AK54-AJ54)*10000 -> -426.22455 | AL56: =(AL54-AK54)*10000 -> -195.52456 | AN56: =(AN54-AL54)*10000 -> -70.279395 | AO56: =(AO54-AN54)*10000 -> 570.01445 | AP56: =(AP54-AO54)*10000 -> -29.342844 | AQ56: =(AQ54-AP54)*10000 -> -368.57458 | AS56: =(AS54-AQ54)*10000 -> 424.57319 | AT56: =(AT54-AS54)*10000 -> 399.63908 | AU56: =(AU54-AT54)*10000 -> -14.111262 | AV56: =(AV54-AU54)*10000 -> -1696.7223 | AX56: =(AX54-AV54)*10000 -> 2083.1035 | AY56: =(AY54-AX54)*10000 -> -151.13072 | AZ56: =(AZ54-AY54)*10000 -> -673.5797 | BA56: =(BA54-AZ54)*10000 -> -672.70301 | BC56: =(BC54-BA54)*10000 -> 503.40336 | BD56: =(BD54-BC54)*10000 -> -377.79475 | BE56: =(BE54-BD54)*10000 -> -1099.6303 | BF56: =(BF54-BE54)*10000 -> -193.79708 | BH56: =(BH54-BF54)*10000 -> 1440.4038 | BI56: =(BI54-BH54)*10000 -> -101.50653 | BJ56: =(BJ54-BI54)*10000 -> -314.5917 | BK56: =(BK54-BJ54)*10000 -> -146.19883 | BM56: =(BM54-BK54)*10000 -> 1437.9921 | BN56: =(BN54-BM54)*10000 -> -153.86228 | BO56: =(BO54-BN54)*10000 -> -374.18358 | BP56: =(BP54-BO54)*10000 -> -930.62014 | BR56: =(BR54-BP54)*10000 -> 1608.1872 | BS56: =(BS54-BR54)*10000 -> -203.69079 | BT56: =(BT54-BS54)*10000 -> 176.12369 | BU56: =(BU54-BT54)*10000 -> -930.62014 | BW56: =(BW54-BU54)*10000 -> 1108.1872 | BX56: =(BX54-BW54)*10000 -> -203.69079 | BY56: =(BY54-BX54)*10000 -> -48.876308 | BZ56: =(BZ54-BY54)*10000 -> -930.62014 | CB56: =(CB54-BZ54)*10000 -> 1308.1872 | CC56: =(CC54-CB54)*10000 -> -203.69079 | CD56: =(CD54-CC54)*10000 -> -73.876308 | CE56: =(CE54-CD54)*10000 -> -930.62014
B58: Memo: including intercompany
B59: Intercompany revenue | L59: 19.6 | M59: 21.1 | N59: 78.6 | O59: 21.5 | P59: 21.9 | Q59: 22.2 | R59: 21.9 | S59: =SUM(O59:R59) -> 87.5 | T59: 22.3 | U59: 23.7 | V59: 23.5 | W59: 24 | X59: =SUM(T59:W59) -> 93.5 | Y59: 24 | Z59: 24.6 | AA59: 23.5 | AB59: 26.3 | AC59: =SUM(Y59:AB59) -> 98.4 | AD59: 26 | AE59: 27 | AF59: 29 | AG59: 29.7 | AH59: =SUM(AD59:AG59) -> 111.7 | AI59: 29.8 | AJ59: 30.6 | AK59: 31.6 | AL59: 32 | AM59: =SUM(AI59:AL59) -> 124 | AN59: 32.3 | AO59: 33 | AP59: 34.3 | AQ59: 35 | AR59: =SUM(AN59:AQ59) -> 134.6 | AS59: 37 | AT59: 35 | AU59: 37 | AV59: 38 | AW59: =SUM(AS59:AV59) -> 147 | AX59: 40 | AY59: 42 | AZ59: 42 | BA59: 41 | BB59: =SUM(AX59:BA59) -> 165 | BC59: 43 | BD59: 43 | BE59: 43 | BF59: 45 | BG59: =SUM(BC59:BF59) -> 174 | BH59: 45 | BI59: 46 | BJ59: 47 | BK59: 48 | BL59: =SUM(BH59:BK59) -> 186 | BM59: 47 | BN59: 49 | BO59: 48 | BP59: 49 | BQ59: =SUM(BM59:BP59) -> 193 | BR59: 49 | BS59: 50 | BT59: =BO59+1 -> 49 | BU59: =BP59+1 -> 50 | BV59: =SUM(BR59:BU59) -> 198 | BW59: =BR59+1 -> 50 | BX59: =BS59+1 -> 51 | BY59: =BT59+1 -> 50 | BZ59: =BU59+1 -> 51 | CA59: =SUM(BW59:BZ59) -> 202 | CB59: =BW59+1 -> 51 | CC59: =BX59+1 -> 52 | CD59: =BY59+1 -> 51 | CE59: =BZ59+1 -> 52 | CF59: =SUM(CB59:CE59) -> 206
B60: Revenue (incl. intercompany) - MOODY'S INVESTOR SERVICE | L60: =L59+L31 -> 497.7 | M60: =M59+M31 -> 547.1 | N60: =N59+N31 -> 2141.25 | O60: =O59+O31 -> 550.6 | P60: =P59+P31 -> 646.9 | Q60: =Q59+Q31 -> 568.8 | R60: =R59+R31 -> 587 | S60: =SUM(O60:R60) -> 2353.3 | T60: =T59+T31 -> 624.6 | U60: =U59+U31 -> 662.9 | V60: =V59+V31 -> 571.6 | W60: =W59+W31 -> 568.6 | X60: =SUM(T60:W60) -> 2427.7 | Y60: =Y59+Y31 -> 549.1 | Z60: =Z59+Z31 -> 650.2 | AA60: =AA59+AA31 -> 635.8 | AB60: =AB59+AB31 -> 634.1 | AC60: =SUM(Y60:AB60) -> 2469.2 | AD60: =AD59+AD31 -> 694.2 | AE60: =AE59+AE31 -> 713.7 | AF60: =AF59+AF31 -> 723.2 | AG60: =AG59+AG31 -> 754.4 | AH60: =SUM(AD60:AG60) -> 2885.5 | AI60: =AI59+AI31 -> 749.7 | AJ60: =AJ59+AJ31 -> 782.9 | AK60: =AK59+AK31 -> 676.4 | AL60: =AL59+AL31 -> 627.4 | AM60: =SUM(AI60:AL60) -> 2836.4 | AN60: =AN59+AN31 -> 702.4 | AO60: =AO59+AO31 -> 771.4 | AP60: =AP59+AP31 -> 780.9 | AQ60: =AQ59+AQ31 -> 755 | AR60: =SUM(AN60:AQ60) -> 3009.7 | AS60: =AS59+AS31 -> 831 | AT60: =AT59+AT31 -> 973 | AU60: =AU59+AU31 -> 862 | AV60: =AV59+AV31 -> 773 | AW60: =SUM(AS60:AV60) -> 3439 | AX60: =AX59+AX31 -> 1076 | AY60: =AY59+AY31 -> 1022 | AZ60: =AZ59+AZ31 -> 967 | BA60: =BA59+BA31 -> 912 | BB60: =SUM(AX60:BA60) -> 3977 | BC60: =BC59+BC31 -> 870 | BD60: =BD59+BD31 -> 749 | BE60: =BE59+BE31 -> 633 | BF60: =BF59+BF31 -> 621 | BG60: =SUM(BC60:BF60) -> 2873 | BH60: =BH59+BH31 -> 778 | BI60: =BI59+BI31 -> 793 | BJ60: =BJ59+BJ31 -> 743 | BK60: =BK59+BK31 -> 732 | BL60: =SUM(BH60:BK60) -> 3046 | BM60: =BM59+BM31 -> 1034 | BN60: =BN59+BN31 -> 1064 | BO60: =BO59+BO31 -> 1030 | BP60: =BP59+BP31 -> 858 | BQ60: =SUM(BM60:BP60) -> 3986 | BR60: =BR59+BR31 -> 1114 | BS60: =BS59+BS31 -> 1060 | BT60: =BT59+BT31 -> 1144.43 | BU60: =BU59+BU31 -> 948.775 | BV60: =SUM(BR60:BU60) -> 4267.205 | BW60: =BW59+BW31 -> 1209.845 | BX60: =BX59+BX31 -> 1149.855 | BY60: =BY59+BY31 -> 1224.4913 | BZ60: =BZ59+BZ31 -> 1012.9695 | CA60: =SUM(BW60:BZ60) -> 4597.1608 | CB60: =CB59+CB31 -> 1290.7405 | CC60: =CC59+CC31 -> 1225.878 | CD60: =CD59+CD31 -> 1306.3424 | CE60: =CE59+CE31 -> 1078.7681 | CF60: =SUM(CB60:CE60) -> 4901.729
B61: % y/y | L61: =IFERROR( L60/G60-1, "NA") -> NA | M61: =IFERROR( M60/H60-1, "NA") -> NA | N61: =IFERROR( N60/I60-1, "NA") -> NA | O61: =IFERROR( O60/J60-1, "NA") -> NA | P61: =IFERROR( P60/K60-1, "NA") -> NA | Q61: =IFERROR( Q60/L60-1, "NA") -> 0.14285714 | R61: =IFERROR( R60/M60-1, "NA") -> 0.072929995 | S61: =IFERROR( S60/N60-1, "NA") -> 0.09903094 | ... CF61: =IFERROR( CF60/CA60-1, "NA") -> 0.066251372
B62: Expenses(incl. intercompany) - MOODY'S INVESTOR SERVICE | L62: =L60-L63 -> 235.6 | M62: =M60-M63 -> 269.7 | N62: =N60-N63 -> 1034 | O62: =O60-O63 -> 248.6 | P62: =P60-P63 -> 271.7 | Q62: =Q60-Q63 -> 263.4 | R62: =R60-R63 -> 292.6 | S62: =S60-S63 -> 1076.3 | ... CF62: =CF60-CF63 -> 1724.7375
B63: Adj. operating income (incl. intercompany) - MOODY'S INVESTOR SERVICE | L63: =L52+L59 -> 262.1 | M63: =M52+M59 -> 277.4 | N63: =N52+N59 -> 1107.25 | O63: =O52+O59 -> 302 | P63: =P52+P59 -> 375.2 | Q63: =Q52+Q59 -> 305.4 | R63: =R52+R59 -> 294.4 | S63: =S52+S59 -> 1277 | ... CF63: =CF52+CF59 -> 3176.9915
B64: Adj. operating income margins (incl. intercompany) - MOODY'S INVESTOR SERVICE | L64: =(L52+L59)/L60 -> 0.52662246 | M64: =(M52+M59)/M60 -> 0.5070371 | N64: =N63/N60 -> 0.5171045 | O64: =O63/O60 -> 0.54849255 | P64: =(P52+P59)/P60 -> 0.57999691 | Q64: =(Q52+Q59)/Q60 -> 0.53691983 | R64: =(R52+R59)/R60 -> 0.50153322 | S64: =S63/S60 -> 0.54264225 | T64: =T63/T60 -> 0.54915146 | U64: =(U52+U59)/U60 -> 0.56705385 | V64: =(V52+V59)/V60 -> 0.53096571 | W64: =(W52+W59)/W60 -> 0.50070348 | X64: =X63/X60 -> 0.53841084 | Y64: =Y63/Y60 -> 0.49262429 | Z64: =(Z52+Z59)/Z60 -> 0.56736389 | AA64: =(AA52+AA59)/AA60 -> 0.57093426 | AB64: =(AB52+AB59)/AB60 -> 0.54975556 | AC64: =AC63/AC60 -> 0.54714077 | AD64: =AD63/AD60 -> 0.58772688 | AE64: =(AE52+AE59)/AE60 -> 0.59408715 | AF64: =(AF52+AF59)/AF60 -> 0.56125553 | AG64: =(AG52+AG59)/AG60 -> 0.54122481 | AH64: =AH63/AH60 -> 0.57050771 | AI64: =AI63/AI60 -> 0.58596772 | AJ64: =(AJ52+AJ59)/AJ60 -> 0.61221101 | AK64: =(AK52+AK59)/AK60 -> 0.57465996 | AL64: =(AL52+AL59)/AL60 -> 0.55801721 | AM64: =AM63/AM60 -> 0.58433225 | AN64: =AN63/AN60 -> 0.54897494 | AO64: =AO63/AO60 -> 0.6020223 | AP64: =AP63/AP60 -> 0.59969266 | AQ64: =AQ63/AQ60 -> 0.56556291 | AR64: =AR63/AR60 -> 0.57989168 | AS64: =AS63/AS60 -> 0.60529483 | AT64: =AT63/AT60 -> 0.64028777 | ... CF64: =CF63/CF60 -> 0.64813691
B65: margin y/y (bps) | L65: =(L64-G64)*10000 -> 5266.2246 | M65: =(M64-H64)*10000 -> 5070.371 | N65: =(N64-I64)*10000 -> 5171.045 | O65: =(O64-J64)*10000 -> 5484.9255 | P65: =(P64-K64)*10000 -> 5799.9691 | Q65: =(Q64-L64)*10000 -> 102.97368 | R65: =(R64-M64)*10000 -> -55.03885 | S65: =(S64-N64)*10000 -> 255.37752 | ... CF65: =(CF64-CA64)*10000 -> 101.07615
B66: Incremental/decremental margins | Q66: =(Q63-L63)/(Q60-L60) -> 0.60900141 | R66: =(R63-M63)/(R60-M60) -> 0.42606516 | S66: =(S63-N63)/(S60-N60) -> 0.80051875 | T66: =(T63-O63)/(T60-O60) -> 0.55405405 | U66: =(U63-P63)/(U60-P60) -> 0.04375 | V66: =(V63-Q63)/(V60-Q60) -> -0.67857143 | W66: =(W63-R63)/(W60-R60) -> 0.52717391 | X66: =(X63-S63)/(X60-S60) -> 0.40456989 | ... CF66: =(CF63-CA63)/(CF60-CA60) -> 0.80070152
B68: MOODY'S ANALYTICS
B69: Subsegments (through 2021)
B70: Research, Data & Analytics (RD&A) | E70: 119.5 | F70: 121.4 | G70: 123.8 | H70: 126.3 | I70: =SUM(E70:H70) -> 491 | J70: 126.4 | K70: 127.5 | L70: 133.7 | M70: 135.2 | N70: =SUM(J70:M70) -> 522.8 | O70: 137.6 | P70: 141.4 | Q70: 143.3 | R70: 149.5 | S70: =SUM(O70:R70) -> 571.8 | T70: 149.6 | U70: 157.5 | V70: 157.9 | W70: 161.4 | X70: =SUM(T70:W70) -> 626.4 | Y70: 164.9 | Z70: 168.3 | AA70: 167.7 | AB70: 166.7 | AC70: =SUM(Y70:AB70) -> 667.6 | AD70: 175.4 | AE70: 180.9 | AF70: 218.4 | AG70: 258 | AH70: =SUM(AD70:AG70) -> 832.7 | AI70: 267.1 | AJ70: 275.9 | AK70: 280.3 | AL70: 297.1 | AM70: =SUM(AI70:AL70) -> 1120.4 | AN70: 307.7 | AO70: 315.3 | AP70: 317.5 | AQ70: 333 | AR70: =SUM(AN70:AQ70) -> 1273.5 | AS70: 358 | AT70: 366 | AU70: 386 | AV70: 404 | AW70: =SUM(AS70:AV70) -> 1514 | AX70: 419 | AY70: 435 | AZ70: 445 | BA70: 454 | BB70: =SUM(AX70:BA70) -> 1753
B71: % y/y | J71: =IFERROR( J70/E70-1, "NA") -> 0.057740586 | K71: =IFERROR( K70/F70-1, "NA") -> 0.050247117 | L71: =IFERROR( L70/G70-1, "NA") -> 0.07996769 | M71: =IFERROR( M70/H70-1, "NA") -> 0.070467142 | N71: =N70/I70-1 -> 0.064765784 | O71: =IFERROR( O70/J70-1, "NA") -> 0.088607595 | P71: =IFERROR( P70/K70-1, "NA") -> 0.10901961 | Q71: =IFERROR( Q70/L70-1, "NA") -> 0.071802543 | R71: =IFERROR( R70/M70-1, "NA") -> 0.10576923 | S71: =S70/N70-1 -> 0.09372609 | T71: =IFERROR( T70/O70-1, "NA") -> 0.087209302 | U71: =IFERROR( U70/P70-1, "NA") -> 0.11386139 | V71: =IFERROR( V70/Q70-1, "NA") -> 0.10188416 | W71: =IFERROR( W70/R70-1, "NA") -> 0.079598662 | X71: =X70/S70-1 -> 0.095487933 | Y71: =IFERROR( Y70/T70-1, "NA") -> 0.10227273 | Z71: =IFERROR( Z70/U70-1, "NA") -> 0.068571429 | AA71: =IFERROR( AA70/V70-1, "NA") -> 0.062064598 | AB71: =IFERROR( AB70/W70-1, "NA") -> 0.03283767 | AC71: =AC70/X70-1 -> 0.065772669 | AD71: =IFERROR( AD70/Y70-1, "NA") -> 0.063674955 | AE71: =IFERROR( AE70/Z70-1, "NA") -> 0.07486631 | AF71: =IFERROR( AF70/AA70-1, "NA") -> 0.30232558 | AG71: =IFERROR( AG70/AB70-1, "NA") -> 0.54769046 | AH71: =AH70/AC70-1 -> 0.24730377 | AI71: =IFERROR( AI70/AD70-1, "NA") -> 0.52280502 | AJ71: =IFERROR( AJ70/AE70-1, "NA") -> 0.52515202 | AK71: =IFERROR( AK70/AF70-1, "NA") -> 0.28342491 | AL71: =IFERROR( AL70/AG70-1, "NA") -> 0.15155039 | AM71: =AM70/AH70-1 -> 0.34550258 | AN71: =IFERROR( AN70/AI70-1, "NA") -> 0.152003 | AO71: =IFERROR( AO70/AJ70-1, "NA") -> 0.14280536 | AP71: =IFERROR( AP70/AK70-1, "NA") -> 0.13271495 | AQ71: =IFERROR( AQ70/AL70-1, "NA") -> 0.12083474 | AR71: =IFERROR( AR70/AM70-1, "NA") -> 0.13664763 | AS71: =IFERROR( AS70/AN70-1, "NA") -> 0.16347091 | AT71: =IFERROR( AT70/AO70-1, "NA") -> 0.16079924 | AU71: =IFERROR( AU70/AP70-1, "NA") -> 0.21574803 | ... BB71: =IFERROR( BB70/AW70-1, "NA") -> 0.15785997
B72: Enterprise Risk Solutions | E72: 48.1 | F72: 51.5 | G72: 64 | H72: 79 | I72: =SUM(E72:H72) -> 242.6 | J72: 53 | K72: 60.2 | L72: 64.4 | M72: 84.9 | N72: =SUM(J72:M72) -> 262.5 | O72: 59.8 | P72: 67.2 | Q72: 81.1 | R72: 120.4 | S72: =SUM(O72:R72) -> 328.5 | T72: 77.1 | U72: 83.2 | V72: 92.2 | W72: 121.5 | X72: =SUM(T72:W72) -> 374 | Y72: 89.5 | Z72: 97.5 | AA72: 101.5 | AB72: 130.3 | AC72: =SUM(Y72:AB72) -> 418.8 | AD72: 95.9 | AE72: 97.3 | AF72: 112.6 | AG72: 142.8 | AH72: =SUM(AD72:AG72) -> 448.6 | AI72: 102.2 | AJ72: 109.5 | AK72: 115.3 | AL72: 124.1 | AM72: =SUM(AI72:AL72) -> 451.1 | AN72: 121.9 | AO72: 117.7 | AP72: 133.3 | AQ72: 149 | AR72: =SUM(AN72:AQ72) -> 521.9 | AS72: 138 | AT72: 131 | AU72: 145 | AV72: 151 | AW72: =SUM(AS72:AV72) -> 565 | AX72: 145 | AY72: 138 | AZ72: 156 | BA72: 214 | BB72: =SUM(AX72:BA72) -> 653
B73: % y/y | J73: =IFERROR( J72/E72-1, "NA") -> 0.1018711 | K73: =IFERROR( K72/F72-1, "NA") -> 0.16893204 | L73: =IFERROR( L72/G72-1, "NA") -> 0.00625 | M73: =IFERROR( M72/H72-1, "NA") -> 0.074683544 | N73: =N72/I72-1 -> 0.08202803 | O73: =IFERROR( O72/J72-1, "NA") -> 0.12830189 | P73: =IFERROR( P72/K72-1, "NA") -> 0.11627907 | Q73: =IFERROR( Q72/L72-1, "NA") -> 0.25931677 | R73: =IFERROR( R72/M72-1, "NA") -> 0.41813899 | S73: =S72/N72-1 -> 0.25142857 | T73: =IFERROR( T72/O72-1, "NA") -> 0.28929766 | U73: =IFERROR( U72/P72-1, "NA") -> 0.23809524 | V73: =IFERROR( V72/Q72-1, "NA") -> 0.13686806 | W73: =IFERROR( W72/R72-1, "NA") -> 0.0091362126 | X73: =X72/S72-1 -> 0.13850837 | Y73: =IFERROR( Y72/T72-1, "NA") -> 0.16083009 | Z73: =IFERROR( Z72/U72-1, "NA") -> 0.171875 | AA73: =IFERROR( AA72/V72-1, "NA") -> 0.10086768 | AB73: =IFERROR( AB72/W72-1, "NA") -> 0.072427984 | AC73: =AC72/X72-1 -> 0.1197861 | AD73: =IFERROR( AD72/Y72-1, "NA") -> 0.07150838 | AE73: =IFERROR( AE72/Z72-1, "NA") -> -0.0020512821 | AF73: =IFERROR( AF72/AA72-1, "NA") -> 0.10935961 | AG73: =IFERROR( AG72/AB72-1, "NA") -> 0.095932464 | AH73: =AH72/AC72-1 -> 0.071155683 | AI73: =IFERROR( AI72/AD72-1, "NA") -> 0.065693431 | AJ73: =IFERROR( AJ72/AE72-1, "NA") -> 0.12538541 | AK73: =IFERROR( AK72/AF72-1, "NA") -> 0.023978686 | AL73: =IFERROR( AL72/AG72-1, "NA") -> -0.13095238 | AM73: =AM72/AH72-1 -> 0.0055728934 | AN73: =IFERROR( AN72/AI72-1, "NA") -> 0.1927593 | AO73: =IFERROR( AO72/AJ72-1, "NA") -> 0.074885845 | AP73: =IFERROR( AP72/AK72-1, "NA") -> 0.15611448 | AQ73: =IFERROR( AQ72/AL72-1, "NA") -> 0.20064464 | AR73: =IFERROR( AR72/AM72-1, "NA") -> 0.15694968 | AS73: =IFERROR( AS72/AN72-1, "NA") -> 0.13207547 | AT73: =IFERROR( AT72/AO72-1, "NA") -> 0.11299915 | AU73: =IFERROR( AU72/AP72-1, "NA") -> 0.087771943 | ... BB73: =IFERROR( BB72/AW72-1, "NA") -> 0.15575221
B74: Professional Services | E74: 26.5 | F74: 26.7 | G74: 27.2 | H74: 29.5 | I74: =SUM(E74:H74) -> 109.9 | J74: 28 | K74: 28.3 | L74: 29.3 | M74: 33.1 | N74: =SUM(J74:M74) -> 118.7 | O74: 40.7 | P74: 39.9 | Q74: 45.1 | R74: 42.5 | S74: =SUM(O74:R74) -> 168.2 | T74: 36.6 | U74: 38.2 | V74: 36.7 | W74: 38.4 | X74: =SUM(T74:W74) -> 149.9 | Y74: 36.6 | Z74: 37.5 | AA74: 35.6 | AB74: 37.3 | AC74: =SUM(Y74:AB74) -> 147 | AD74: 35.7 | AE74: 35.6 | AF74: 37.7 | AG74: 40 | AH74: =SUM(AD74:AG74) -> 149 | AI74: 37.5 | AJ74: 37.4 | AK74: 40.4 | AL74: 43.5 | AM74: =SUM(AI74:AL74) -> 158.8 | AN74: 42.4 | AO74: 42.2 | AP74: =43.1 -> 43.1 | AQ74: 31 | AR74: =SUM(AN74:AQ74) -> 158.7
B75: % y/y | J75: =IFERROR( J74/E74-1, "NA") -> 0.056603774 | K75: =IFERROR( K74/F74-1, "NA") -> 0.059925094 | L75: =IFERROR( L74/G74-1, "NA") -> 0.077205882 | M75: =IFERROR( M74/H74-1, "NA") -> 0.1220339 | N75: =N74/I74-1 -> 0.080072793 | O75: =IFERROR( O74/J74-1, "NA") -> 0.45357143 | P75: =IFERROR( P74/K74-1, "NA") -> 0.40989399 | Q75: =IFERROR( Q74/L74-1, "NA") -> 0.53924915 | R75: =IFERROR( R74/M74-1, "NA") -> 0.28398792 | S75: =S74/N74-1 -> 0.41701769 | T75: =IFERROR( T74/O74-1, "NA") -> -0.1007371 | U75: =IFERROR( U74/P74-1, "NA") -> -0.042606516 | V75: =IFERROR( V74/Q74-1, "NA") -> -0.18625277 | W75: =IFERROR( W74/R74-1, "NA") -> -0.096470588 | X75: =X74/S74-1 -> -0.10879905 | Y75: =IFERROR( Y74/T74-1, "NA") -> 0 | Z75: =IFERROR( Z74/U74-1, "NA") -> -0.018324607 | AA75: =IFERROR( AA74/V74-1, "NA") -> -0.029972752 | AB75: =IFERROR( AB74/W74-1, "NA") -> -0.028645833 | AC75: =AC74/X74-1 -> -0.019346231 | AD75: =IFERROR( AD74/Y74-1, "NA") -> -0.024590164 | AE75: =IFERROR( AE74/Z74-1, "NA") -> -0.050666667 | AF75: =IFERROR( AF74/AA74-1, "NA") -> 0.058988764 | AG75: =IFERROR( AG74/AB74-1, "NA") -> 0.072386059 | AH75: =AH74/AC74-1 -> 0.013605442 | AI75: =IFERROR( AI74/AD74-1, "NA") -> 0.050420168 | AJ75: =IFERROR( AJ74/AE74-1, "NA") -> 0.050561798 | AK75: =IFERROR( AK74/AF74-1, "NA") -> 0.071618037 | AL75: =IFERROR( AL74/AG74-1, "NA") -> 0.0875 | AM75: =AM74/AH74-1 -> 0.065771812 | AN75: =IFERROR( AN74/AI74-1, "NA") -> 0.13066667 | AO75: =IFERROR( AO74/AJ74-1, "NA") -> 0.12834225 | AP75: =IFERROR( AP74/AK74-1, "NA") -> 0.066831683 | AQ75: =IFERROR( AQ74/AL74-1, "NA") -> -0.28735632 | AR75: =IFERROR( AR74/AM74-1, "NA") -> -0.00062972292
B76: Subsegments (since 2022)
B77: Data & Information (Data sets on economies, companies incl. Orbis, real estate, securities, etc.) | AS77: 141 | AT77: 143 | AU77: 151 | AV77: 159 | AW77: =SUM(AS77:AV77) -> 594 | AX77: 168 | AY77: 176 | AZ77: 174 | BA77: 180 | BB77: =SUM(AX77:BA77) -> 698 | BC77: 178 | BD77: 178 | BE77: 176 | BF77: 180 | BG77: =SUM(BC77:BF77) -> 712 | BH77: 188 | BI77: 196 | BJ77: 200 | BK77: 205 | BL77: =SUM(BH77:BK77) -> 789 | BM77: 212 | BN77: 210 | BO77: 213 | BP77: 218 | BQ77: =SUM(BM77:BP77) -> 853 | BR77: 218 | BS77: 226 | BT77: 233 | BU77: =BP77*(1+BU78) -> 237.31007 | BV77: =SUM(BR77:BU77) -> 914.31007 | BW77: =BR77*(1+BW78) -> 238.54387 | BX77: =BS77*(1+BX78) -> 241.62037 | BY77: =BT77*(1+BY78) -> 247.43738 | BZ77: =BU77*(1+BZ78) -> 252.74079 | CA77: =SUM(BW77:BZ77) -> 980.34241 | CB77: =BW77*(1+CB78) -> 256.32691 | CC77: =BX77*(1+CC78) -> 259.63276 | CD77: =BY77*(1+CD78) -> 265.88343 | CE77: =BZ77*(1+CE78) -> 271.58219 | CF77: =SUM(CB77:CE77) -> 1053.4253
B78: Reported growth % y/y | AX78: =AX77/AS77-1 -> 0.19148936 | AY78: =AY77/AT77-1 -> 0.23076923 | AZ78: =AZ77/AU77-1 -> 0.15231788 | BA78: =BA77/AV77-1 -> 0.13207547 | BB78: =BB77/AW77-1 -> 0.17508418 | BC78: =BC77/AX77-1 -> 0.05952381 | BD78: =BD77/AY77-1 -> 0.011363636 | BE78: =BE77/AZ77-1 -> 0.011494253 | ... BT78: =BT77/BO77-1 -> 0.093896714 | BU78: =BU79+BU80 -> 0.088578296 | BV78: =BV77/BQ77-1 -> 0.071875813 | BW78: =BW79+BW80 -> 0.094237919 | BX78: =BX79+BX80 -> 0.069116666 | BY78: =BY79+BY80 -> 0.061963019 | BZ78: =BZ79+BZ80 -> 0.065023462 | CA78: =CA77/BV77-1 -> 0.072220947 | CB78: =CB79+CB80 -> 0.074548327 | CC78: =CC79+CC80 -> 0.074548327 | CD78: =CD79+CD80 -> 0.074548327 | CE78: =CE79+CE80 -> 0.074548327 | CF78: =CF77/CA77-1 -> 0.074548327
B79: M&A impact % y/y | BB79: =BG89/BG95 -> 0.4496208 | BC79: =2/AX77 -> 0.011904762 | BD79: 0 | BE79: 0 | BF79: 0 | BG79: =SUMPRODUCT(BC79:BF79,AX$77:BA$77)/BB$77 -> 0.0028653295 | BH79: 0 | BI79: 0 | BJ79: 0 | BK79: 0 | BL79: =SUMPRODUCT(BH79:BK79,BC$77:BF$77)/BG$77 -> 0 | BM79: 0 | BN79: 0 | BO79: =BO219/BJ77 -> 0 | BP79: =BP219/BK77 -> 0 | BQ79: =SUMPRODUCT(BM79:BP79,BH$77:BK$77)/BL$77 -> 0 | BR79: 0 | BS79: 0 | BT79: 0 | BU79: =BU219/BP77 -> 0 | BV79: =SUMPRODUCT(BR79:BU79,BM$77:BP$77)/BQ$77 -> 0 | BW79: =BW219/BR77 -> 0 | BX79: =BX219/BS77 -> 0 | BY79: =BY219/BT77 -> 0 | BZ79: =BZ219/BU77 -> 0 | CA79: =SUMPRODUCT(BW79:BZ79,BR$77:BU$77)/BV$77 -> 0 | CB79: =CB219/BW77 -> 0 | CC79: =CC219/BX77 -> 0 | CD79: =CD219/BY77 -> 0 | CE79: =CE219/BZ77 -> 0 | CF79: =SUMPRODUCT(CB79:CE79,BW$77:BZ$77)/CA$77 -> 0
B80: Organic growth % y/y | BC80: =BC78-BC79 -> 0.047619048 | BD80: =BD78-BD79 -> 0.011363636 | BE80: =BE78-BE79 -> 0.011494253 | BF80: =BF78-BF79 -> 0 | BG80: =SUMPRODUCT(BC80:BF80,AX$77:BA$77)/BB$77 -> 0.017191977 | BH80: =BH78-BH79 -> 0.056179775 | BI80: =BI78-BI79 -> 0.1011236 | BJ80: =BJ78-BJ79 -> 0.13636364 | BK80: =BK78-BK79 -> 0.13888889 | BL80: =SUMPRODUCT(BH80:BK80,BC$77:BF$77)/BG$77 -> 0.10814607 | BM80: =BM78-BM79 -> 0.12765957 | BN80: =BN78-BN79 -> 0.071428571 | BO80: =BO78-BO79 -> 0.065 | BP80: =BP78-BP79 -> 0.063414634 | BQ80: =SUMPRODUCT(BM80:BP80,BH$77:BK$77)/BL$77 -> 0.081115336 | BR80: =BR78-BR79 -> 0.028301887 | BS80: =BS78-BS79 -> 0.076190476 | BT80: =BT78-BT79 -> 0.093896714 | BU80: =BU81+BU82 -> 0.088578296 | BV80: =SUMPRODUCT(BR80:BU80,BM$77:BP$77)/BQ$77 -> 0.071875813 | BW80: =BW81+BW82 -> 0.094237919 | BX80: =BX81+BX82 -> 0.069116666 | BY80: =BY81+BY82 -> 0.061963019 | BZ80: =BZ81+BZ82 -> 0.065023462 | CA80: =SUMPRODUCT(BW80:BZ80,BR$77:BU$77)/BV$77 -> 0.072220947 | CB80: =CB81+CB82 -> 0.074548327 | CC80: =CC81+CC82 -> 0.074548327 | CD80: =CD81+CD82 -> 0.074548327 | CE80: =CE81+CE82 -> 0.074548327 | CF80: =SUMPRODUCT(CB80:CE80,BW$77:BZ$77)/CA$77 -> 0.074548327
B81: FX impact % y/y | BC81: =-7/AX77 -> -0.041666667 | BD81: =-12/AY77 -> -0.068181818 | BE81: =-19/AZ77 -> -0.1091954 | BF81: =-14/BA77 -> -0.077777778 | BG81: =SUMPRODUCT(BC81:BF81,AX$77:BA$77)/BB$77 -> -0.074498567 | BH81: =-8/BC77 -> -0.04494382 | BI81: 0.003 | BJ81: =9/BE77 -> 0.051136364 | BK81: =5/BF77 -> 0.027777778 | BL81: =SUMPRODUCT(BH81:BK81,BC$77:BF$77)/BG$77 -> 0.0091769663 | BM81: 0 | BN81: =-1/BI77 -> -0.0051020408 | BO81: =2/BJ77 -> 0.01 | BP81: 0 | BQ81: =SUMPRODUCT(BM81:BP81,BH$77:BK$77)/BL$77 -> 0.0012674271 | BR81: =-4/BM77 -> -0.018867925 | BS81: =6/BN77 -> 0.028571429 | BT81: =6/BO77 -> 0.028169014 | BU81: =BU$248 -> 0.028578296 | BV81: =SUMPRODUCT(BR81:BU81,BM$77:BP$77)/BQ$77 -> 0.016682378 | BW81: =BW$248 -> 0.029237919 | BX81: =BX$248 -> 0.0041166664 | BY81: =BY$248 -> -0.0030369812 | BZ81: =BZ$248 -> -0.0049765375 | CA81: =SUMPRODUCT(BW81:BZ81,BR$77:BU$77)/BV$77 -> 0.0059231919 | CB81: =CB$248 -> -0.00045167309 | CC81: =CC$248 -> -0.00045167309 | CD81: =CD$248 -> -0.00045167309 | CE81: =CE$248 -> -0.00045167309 | CF81: =SUMPRODUCT(CB81:CE81,BW$77:BZ$77)/CA$77 -> -0.00045167309
B82: Data & Information organic constant currency growth % y/y | BC82: =BC78-BC79-BC81 -> 0.089285714 | BD82: =BD78-BD79-BD81 -> 0.079545455 | BE82: =BE78-BE79-BE81 -> 0.12068966 | BF82: =BF78-BF79-BF81 -> 0.077777778 | BG82: =SUMPRODUCT(BC82:BF82,AX$77:BA$77)/BB$77 -> 0.091690544 | BH82: =BH78-BH79-BH81 -> 0.1011236 | BI82: =BI78-BI79-BI81 -> 0.098123596 | BJ82: =BJ78-BJ79-BJ81 -> 0.085227273 | BK82: =BK78-BK79-BK81 -> 0.11111111 | BL82: =SUMPRODUCT(BH82:BK82,BC$77:BF$77)/BG$77 -> 0.098969101 | BM82: =BM78-BM79-BM81 -> 0.12765957 | BN82: =BN78-BN79-BN81 -> 0.076530612 | BO82: =BO78-BO79-BO81 -> 0.055 | BP82: =BP78-BP79-BP81 -> 0.063414634 | BQ82: =SUMPRODUCT(BM82:BP82,BH$77:BK$77)/BL$77 -> 0.079847909 | BR82: =BR78-BR79-BR81 -> 0.047169811 | BS82: =BS78-BS79-BS81 -> 0.047619048 | BT82: =BT78-BT79-BT81 -> 0.0657277 | BU82: 0.06 | BV82: =SUMPRODUCT(BR82:BU82,BM$77:BP$77)/BQ$77 -> 0.055193435 | BW82: 0.065 | BX82: 0.065 | BY82: 0.065 | BZ82: 0.07 | CA82: =SUMPRODUCT(BW82:BZ82,BR$77:BU$77)/BV$77 -> 0.066297755 | CB82: 0.075 | CC82: 0.075 | CD82: 0.075 | CE82: 0.075 | CF82: =SUMPRODUCT(CB82:CE82,BW$77:BZ$77)/CA$77 -> 0.075
B83: Research & Insights (Credit & economics models, scores, expert insights & commentary) | AS83: 174 | AT83: 174 | AU83: 181 | AV83: 188 | AW83: =SUM(AS83:AV83) -> 717 | AX83: 188 | AY83: 193 | AZ83: 195 | BA83: 196 | BB83: =SUM(AX83:BA83) -> 772 | BC83: 203 | BD83: 203 | BE83: 201 | BF83: 205 | BG83: =SUM(BC83:BF83) -> 812 | BH83: 215 | BI83: 217 | BJ83: 222 | BK83: 230 | BL83: =SUM(BH83:BK83) -> 884 | BM83: 222 | BN83: 226 | BO83: 235 | BP83: 243 | BQ83: =SUM(BM83:BP83) -> 926 | BR83: 236 | BS83: 249 | BT83: 252 | BU83: =BP83*(1+BU84) -> 264.52453 | BV83: =SUM(BR83:BU83) -> 1001.5245 | BW83: =BR83*(1+BW84) -> 259.42015 | BX83: =BS83*(1+BX84) -> 267.45505 | BY83: =BT83*(1+BY84) -> 270.13468 | BZ83: =BU83*(1+BZ84) -> 283.04745 | CA83: =SUM(BW83:BZ83) -> 1080.0573 | CB83: =BW83*(1+CB84) -> 277.46239 | CC83: =BX83*(1+CC84) -> 286.0561 | CD83: =BY83*(1+CD84) -> 288.9221 | CE83: =BZ83*(1+CE84) -> 302.73293 | CF83: =SUM(CB83:CE83) -> 1155.1735
B84: % y/y | AX84: =AX83/AS83-1 -> 0.08045977 | AY84: =AY83/AT83-1 -> 0.1091954 | AZ84: =AZ83/AU83-1 -> 0.077348066 | BA84: =BA83/AV83-1 -> 0.042553191 | BB84: =BB83/AW83-1 -> 0.076708508 | BC84: =BC83/AX83-1 -> 0.079787234 | BD84: =BD83/AY83-1 -> 0.051813472 | BE84: =BE83/AZ83-1 -> 0.030769231 | ... BT84: =BT83/BO83-1 -> 0.072340426 | BU84: =BU85+BU86 -> 0.088578296 | BV84: =BV83/BQ83-1 -> 0.081559963 | BW84: =BW85+BW86 -> 0.099237919 | BX84: =BX85+BX86 -> 0.074116666 | BY84: =BY85+BY86 -> 0.071963019 | BZ84: =BZ85+BZ86 -> 0.070023462 | CA84: =CA83/BV83-1 -> 0.07841326 | CB84: =CB85+CB86 -> 0.069548327 | CC84: =CC85+CC86 -> 0.069548327 | CD84: =CD85+CD86 -> 0.069548327 | CE84: =CE85+CE86 -> 0.069548327 | CF84: =CF83/CA83-1 -> 0.069548327
B85: M&A impact % y/y | BC85: 0 | BD85: 0 | BE85: 0 | BF85: 0 | BG85: =SUMPRODUCT(BC85:BF85,AX$83:BA$83)/BB$83 -> 0 | BH85: 0 | BI85: 0 | BJ85: 0 | BK85: 0 | BL85: =SUMPRODUCT(BH85:BK85,BC$83:BF$83)/BG$83 -> 0 | BM85: 0 | BN85: 0 | BO85: 0 | BP85: =BP220/BK83 -> 0 | BQ85: =SUMPRODUCT(BM85:BP85,BH$83:BK$83)/BL$83 -> 0 | BR85: 0 | BS85: 0 | BT85: 0 | BU85: =BU220/BP83 -> 0 | BV85: =SUMPRODUCT(BR85:BU85,BM$83:BP$83)/BQ$83 -> 0 | BW85: =BW220/BR83 -> 0 | BX85: =BX220/BS83 -> 0 | BY85: =BY220/BT83 -> 0 | BZ85: =BZ220/BU83 -> 0 | CA85: =SUMPRODUCT(BW85:BZ85,BR$83:BU$83)/BV$83 -> 0 | CB85: =CB220/BW83 -> 0 | CC85: =CC220/BX83 -> 0 | CD85: =CD220/BY83 -> 0 | CE85: =CE220/BZ83 -> 0 | CF85: =SUMPRODUCT(CB85:CE85,BW$83:BZ$83)/CA$83 -> 0
B86: Organic growth % y/y | BC86: =BC84-BC85 -> 0.079787234 | BD86: =BD84-BD85 -> 0.051813472 | BE86: =BE84-BE85 -> 0.030769231 | BF86: =BF84-BF85 -> 0.045918367 | BG86: =SUMPRODUCT(BC86:BF86,AX$83:BA$83)/BB$83 -> 0.051813472 | BH86: =BH84-BH85 -> 0.0591133 | BI86: =BI84-BI85 -> 0.068965517 | BJ86: =BJ84-BJ85 -> 0.10447761 | BK86: =BK84-BK85 -> 0.12195122 | BL86: =SUMPRODUCT(BH86:BK86,BC$83:BF$83)/BG$83 -> 0.088669951 | BM86: =BM84-BM85 -> 0.03255814 | BN86: =BN84-BN85 -> 0.041474654 | BO86: =BO84-BO85 -> 0.058558559 | BP86: =BP84-BP85 -> 0.056521739 | BQ86: =SUMPRODUCT(BM86:BP86,BH$83:BK$83)/BL$83 -> 0.047511312 | BR86: =BR84-BR85 -> 0.063063063 | BS86: =BS84-BS85 -> 0.10176991 | BT86: =BT84-BT85 -> 0.072340426 | BU86: =BU87+BU88 -> 0.088578296 | BV86: =SUMPRODUCT(BR86:BU86,BM$83:BP$83)/BQ$83 -> 0.081559963 | BW86: =BW87+BW88 -> 0.099237919 | BX86: =BX87+BX88 -> 0.074116666 | BY86: =BY87+BY88 -> 0.071963019 | BZ86: =BZ87+BZ88 -> 0.070023462 | CA86: =SUMPRODUCT(BW86:BZ86,BR$83:BU$83)/BV$83 -> 0.07841326 | CB86: =CB87+CB88 -> 0.069548327 | CC86: =CC87+CC88 -> 0.069548327 | CD86: =CD87+CD88 -> 0.069548327 | CE86: =CE87+CE88 -> 0.069548327 | CF86: =SUMPRODUCT(CB86:CE86,BW$83:BZ$83)/CA$83 -> 0.069548327
B87: FX impact % y/y | BC87: =-1/AX83 -> -0.0053191489 | BD87: =-4/AY83 -> -0.020725389 | BE87: =-10/AZ83 -> -0.051282051 | BF87: =-6/BA83 -> -0.030612245 | BG87: =SUMPRODUCT(BC87:BF87,AX$83:BA$83)/BB$83 -> -0.027202073 | BH87: =-3/BC83 -> -0.014778325 | BI87: 0.003 | BJ87: =3/BE83 -> 0.014925373 | BK87: =2/BF83 -> 0.0097560976 | BL87: =SUMPRODUCT(BH87:BK87,BC$83:BF$83)/BG$83 -> 0.0032130542 | BM87: 0 | BN87: 0 | BO87: =2/BJ83 -> 0.009009009 | BP87: 0 | BQ87: =SUMPRODUCT(BM87:BP87,BH$83:BK$83)/BL$83 -> 0.0022624434 | BR87: =-1/BM83 -> -0.0045045045 | BS87: =4/BN83 -> 0.017699115 | BT87: =3/BO83 -> 0.012765957 | BU87: =BU$248 -> 0.028578296 | BV87: =SUMPRODUCT(BR87:BU87,BM$83:BP$83)/BQ$83 -> 0.01397897 | BW87: =BW$248 -> 0.029237919 | BX87: =BX$248 -> 0.0041166664 | BY87: =BY$248 -> -0.0030369812 | BZ87: =BZ$248 -> -0.0049765375 | CA87: =SUMPRODUCT(BW87:BZ87,BR$83:BU$83)/BV$83 -> 0.0058345685 | CB87: =CB$248 -> -0.00045167309 | CC87: =CC$248 -> -0.00045167309 | CD87: =CD$248 -> -0.00045167309 | CE87: =CE$248 -> -0.00045167309 | CF87: =SUMPRODUCT(CB87:CE87,BW$83:BZ$83)/CA$83 -> -0.00045167309
B88: Research & Insights organic constant currency growth % y/y | BC88: =BC84-BC85-BC87 -> 0.085106383 | BD88: =BD84-BD85-BD87 -> 0.07253886 | BE88: =BE84-BE85-BE87 -> 0.082051282 | BF88: =BF84-BF85-BF87 -> 0.076530612 | BG88: =SUMPRODUCT(BC88:BF88,AX$83:BA$83)/BB$83 -> 0.079015544 | BH88: =BH84-BH85-BH87 -> 0.073891626 | BI88: =BI84-BI85-BI87 -> 0.065965517 | BJ88: =BJ84-BJ85-BJ87 -> 0.089552239 | BK88: =BK84-BK85-BK87 -> 0.11219512 | BL88: =SUMPRODUCT(BH88:BK88,BC$83:BF$83)/BG$83 -> 0.085456897 | BM88: =BM84-BM85-BM87 -> 0.03255814 | BN88: =BN84-BN85-BN87 -> 0.041474654 | BO88: =BO84-BO85-BO87 -> 0.04954955 | BP88: =BP84-BP85-BP87 -> 0.056521739 | BQ88: =SUMPRODUCT(BM88:BP88,BH$83:BK$83)/BL$83 -> 0.045248869 | BR88: =BR84-BR85-BR87 -> 0.067567568 | BS88: =BS84-BS85-BS87 -> 0.084070796 | BT88: =BT84-BT85-BT87 -> 0.059574468 | BU88: 0.06 | BV88: =SUMPRODUCT(BR88:BU88,BM$83:BP$83)/BQ$83 -> 0.067580994 | BW88: 0.07 | BX88: 0.07 | BY88: 0.075 | BZ88: 0.075 | CA88: =SUMPRODUCT(BW88:BZ88,BR$83:BU$83)/BV$83 -> 0.072578691 | CB88: 0.07 | CC88: 0.07 | CD88: 0.07 | CE88: 0.07 | CF88: =SUMPRODUCT(CB88:CE88,BW$83:BZ$83)/CA$83 -> 0.07
B89: Decision Solutions (Software & workflow tools for Banking, Insurance, KYC, RMS, etc.) | AS89: 181 | AT89: 180 | AU89: 199 | AV89: 208 | AW89: =SUM(AS89:AV89) -> 768 | AX89: 208 | AY89: 204 | AZ89: 232 | BA89: 292 | BB89: =SUM(AX89:BA89) -> 936 | BC89: 314 | BD89: 294 | BE89: 308 | BF89: 329 | BG89: =SUM(BC89:BF89) -> 1245 | BH89: =668-BI89 -> 334 | BI89: 334 | BJ89: 354 | BK89: 361 | BL89: =SUM(BH89:BK89) -> 1383 | BM89: 365 | BN89: 366 | BO89: 383 | BP89: 402 | BQ89: =SUM(BM89:BP89) -> 1516 | BR89: 405 | BS89: 413 | BT89: 424 | BU89: =BP89*(1+BU90) -> 447.62847 | BV89: =SUM(BR89:BU89) -> 1689.6285 | BW89: =BR89*(1+BW90) -> 449.29136 | BX89: =BS89*(1+BX90) -> 447.87018 | BY89: =BT89*(1+BY90) -> 465.35232 | BZ89: =BU89*(1+BZ90) -> 494.63997 | CA89: =SUM(BW89:BZ89) -> 1857.1538 | CB89: =BW89*(1+CB90) -> 494.01756 | CC89: =BX89*(1+CC90) -> 492.45491 | CD89: =BY89*(1+CD90) -> 511.67736 | CE89: =BZ89*(1+CE90) -> 543.88055 | CF89: =SUM(CB89:CE89) -> 2042.0304
B90: % y/y | AX90: =AX89/AS89-1 -> 0.14917127 | AY90: =AY89/AT89-1 -> 0.13333333 | AZ90: =AZ89/AU89-1 -> 0.16582915 | BA90: =BA89/AV89-1 -> 0.40384615 | BB90: =BB89/AW89-1 -> 0.21875 | BC90: =BC89/AX89-1 -> 0.50961538 | BD90: =BD89/AY89-1 -> 0.44117647 | BE90: =BE89/AZ89-1 -> 0.32758621 | ... BT90: =BT89/BO89-1 -> 0.10704961 | BU90: =BU91+BU92 -> 0.11350367 | BV90: =BV89/BQ89-1 -> 0.11453066 | BW90: =BW91+BW92 -> 0.10936138 | BX90: =BX91+BX92 -> 0.084431436 | BY90: =BY91+BY92 -> 0.097529057 | BZ90: =BZ91+BZ92 -> 0.10502346 | CA90: =CA89/BV89-1 -> 0.099149224 | CB90: =CB91+CB92 -> 0.099548327 | CC90: =CC91+CC92 -> 0.099548327 | CD90: =CD91+CD92 -> 0.099548327 | CE90: =CE91+CE92 -> 0.099548327 | CF90: =CF89/CA89-1 -> 0.099548327
B91: M&A impact % y/y | BC91: =77/AX89 -> 0.37019231 | BD91: =83/AY89 -> 0.40686275 | BE91: =70/AZ89 -> 0.30172414 | BF91: =4/BA89 -> 0.01369863 | BG91: =SUMPRODUCT(BC91:BF91,AX$83:BA$83)/BB$83 -> 0.27155674 | BH91: 0 | BI91: 0 | BJ91: 0 | BK91: 0 | BL91: =SUMPRODUCT(BH91:BK91,BC$83:BF$83)/BG$83 -> 0 | BM91: 0 | BN91: 0 | BO91: 0 | BP91: =BP221/BK89 -> 0.0055401662 | BQ91: =SUMPRODUCT(BM91:BP91,BH$83:BK$83)/BL$83 -> 0.001441446 | BR91: =BR221/BM89 -> 0.030136986 | BS91: =BS221/BN89 -> 0.038251366 | BT91: =BT221/BO89 -> 0.033942559 | BU91: =BU221/BP89 -> 0.014925373 | BV91: =SUMPRODUCT(BR91:BU91,BM$83:BP$83)/BQ$83 -> 0.029091346 | BW91: =BW221/BR89 -> -0.0098765432 | BX91: =BX221/BS89 -> -0.00968523 | BY91: =BY221/BT89 -> -0.0094339623 | BZ91: =BZ221/BU89 -> 0 | CA91: =SUMPRODUCT(BW91:BZ91,BR$83:BU$83)/BV$83 -> -0.0071090071 | CB91: =CB221/BW89 -> 0 | CC91: =CC221/BX89 -> 0 | CD91: =CD221/BY89 -> 0 | CE91: =CE221/BZ89 -> 0 | CF91: =SUMPRODUCT(CB91:CE91,BW$83:BZ$83)/CA$83 -> 0
B92: Organic growth % y/y | BC92: =BC90-BC91 -> 0.13942308 | BD92: =BD90-BD91 -> 0.034313725 | BE92: =BE90-BE91 -> 0.025862069 | BF92: =BF90-BF91 -> 0.1130137 | BG92: =SUMPRODUCT(BC92:BF92,AX$83:BA$83)/BB$83 -> 0.077756316 | BH92: =BH90-BH91 -> 0.063694268 | BI92: =BI90-BI91 -> 0.13605442 | BJ92: =BJ90-BJ91 -> 0.14935065 | BK92: =BK90-BK91 -> 0.097264438 | BL92: =SUMPRODUCT(BH92:BK92,BC$83:BF$83)/BG$83 -> 0.11146265 | BM92: =BM90-BM91 -> 0.092814371 | BN92: =BN90-BN91 -> 0.095808383 | BO92: =BO90-BO91 -> 0.081920904 | BP92: =BP90-BP91 -> 0.10803324 | BQ92: =SUMPRODUCT(BM92:BP92,BH$83:BK$83)/BL$83 -> 0.094773298 | BR92: =BR90-BR91 -> 0.079452055 | BS92: =BS90-BS91 -> 0.090163934 | BT92: =BT90-BT91 -> 0.07310705 | BU92: =BU93+BU94 -> 0.098578296 | BV92: =SUMPRODUCT(BR92:BU92,BM$83:BP$83)/BQ$83 -> 0.085475257 | BW92: =BW93+BW94 -> 0.11923792 | BX92: =BX93+BX94 -> 0.094116666 | BY92: =BY93+BY94 -> 0.10696302 | BZ92: =BZ93+BZ94 -> 0.10502346 | CA92: =SUMPRODUCT(BW92:BZ92,BR$83:BU$83)/BV$83 -> 0.10614933 | CB92: =CB93+CB94 -> 0.099548327 | CC92: =CC93+CC94 -> 0.099548327 | CD92: =CD93+CD94 -> 0.099548327 | CE92: =CE93+CE94 -> 0.099548327 | CF92: =SUMPRODUCT(CB92:CE92,BW$83:BZ$83)/CA$83 -> 0.099548327
B93: FX impact % y/y | BC93: =-5/AX89 -> -0.024038462 | BD93: =-11/AY89 -> -0.053921569 | BE93: =-12/AZ89 -> -0.051724138 | BF93: =-12/BA89 -> -0.04109589 | BG93: =SUMPRODUCT(BC93:BF93,AX$83:BA$83)/BB$83 -> -0.042833025 | BH93: =-7/BC89 -> -0.022292994 | BI93: 0.003 | BJ93: =5/BE89 -> 0.016233766 | BK93: =5/BF89 -> 0.015197568 | BL93: =SUMPRODUCT(BH93:BK93,BC$83:BF$83)/BG$83 -> 0.003032033 | BM93: =2/BH89 -> 0.005988024 | BN93: =-1/BI89 -> -0.002994012 | BO93: =1/BJ89 -> 0.0028248588 | BP93: 0 | BQ93: =SUMPRODUCT(BM93:BP93,BH$83:BK$83)/BL$83 -> 0.0014308181 | BR93: =-3/BM89 -> -0.0082191781 | BS93: =5/BN89 -> 0.013661202 | BT93: =5/BO89 -> 0.01305483 | BU93: =BU$248 -> 0.028578296 | BV93: =SUMPRODUCT(BR93:BU93,BM$83:BP$83)/BQ$83 -> 0.012176226 | BW93: =BW$248 -> 0.029237919 | BX93: =BX$248 -> 0.0041166664 | BY93: =BY$248 -> -0.0030369812 | BZ93: =BZ$248 -> -0.0049765375 | CA93: =SUMPRODUCT(BW93:BZ93,BR$83:BU$83)/BV$83 -> 0.0058345685 | CB93: =CB$248 -> -0.00045167309 | CC93: =CC$248 -> -0.00045167309 | CD93: =CD$248 -> -0.00045167309 | CE93: =CE$248 -> -0.00045167309 | CF93: =SUMPRODUCT(CB93:CE93,BW$83:BZ$83)/CA$83 -> -0.00045167309
B94: Decision Solutions organic constant currency growth % y/y | BC94: =BC90-BC91-BC93 -> 0.16346154 | BD94: =BD90-BD91-BD93 -> 0.088235294 | BE94: =BE90-BE91-BE93 -> 0.077586207 | BF94: =BF90-BF91-BF93 -> 0.15410959 | BG94: =SUMPRODUCT(BC94:BF94,AX$83:BA$83)/BB$83 -> 0.12058934 | BH94: =BH90-BH91-BH93 -> 0.085987261 | BI94: =BI90-BI91-BI93 -> 0.13305442 | BJ94: =BJ90-BJ91-BJ93 -> 0.13311688 | BK94: =BK90-BK91-BK93 -> 0.082066869 | BL94: =SUMPRODUCT(BH94:BK94,BC$83:BF$83)/BG$83 -> 0.10843062 | BM94: =BM90-BM91-BM93 -> 0.086826347 | BN94: =BN90-BN91-BN93 -> 0.098802395 | BO94: =BO90-BO91-BO93 -> 0.079096045 | BP94: =BP90-BP91-BP93 -> 0.10803324 | BQ94: =SUMPRODUCT(BM94:BP94,BH$83:BK$83)/BL$83 -> 0.09334248 | BR94: =BR90-BR91-BR93 -> 0.087671233 | BS94: =BS90-BS91-BS93 -> 0.076502732 | BT94: =BT90-BT91-BT93 -> 0.060052219 | BU94: 0.07 | BV94: =SUMPRODUCT(BR94:BU94,BM$83:BP$83)/BQ$83 -> 0.073299031 | BW94: 0.09 | BX94: 0.09 | BY94: 0.11 | BZ94: 0.11 | CA94: =SUMPRODUCT(BW94:BZ94,BR$83:BU$83)/BV$83 -> 0.10031477 | CB94: 0.1 | CC94: 0.1 | CD94: 0.1 | CE94: 0.1 | CF94: =SUMPRODUCT(CB94:CE94,BW$83:BZ$83)/CA$83 -> 0.1
B95: MOODY'S ANALYTICS REVENUE | E95: =E72+E70+E74 -> 194.1 | F95: =F72+F70+F74 -> 199.6 | G95: =G72+G70+G74 -> 215 | H95: =H72+H70+H74 -> 234.8 | I95: =I72+I70+I74 -> 843.5 | J95: =J72+J70+J74 -> 207.4 | K95: =K72+K70+K74 -> 216 | L95: =L72+L70+L74 -> 227.4 | ... BA95: =BA72+BA70+BA74 -> 668 | BB95: =SUM(AX95:BA95) -> 2406 | BC95: =BC77+BC83+BC89 -> 695 | BD95: =BD77+BD83+BD89 -> 675 | BE95: =BE77+BE83+BE89 -> 685 | BF95: =BF77+BF83+BF89 -> 714 | BG95: =SUM(BC95:BF95) -> 2769 | BH95: =BH77+BH83+BH89 -> 737 | BI95: =BI77+BI83+BI89 -> 747 | BJ95: =BJ77+BJ83+BJ89 -> 776 | BK95: =BK77+BK83+BK89 -> 796 | BL95: =SUM(BH95:BK95) -> 3056 | BM95: =BM77+BM83+BM89 -> 799 | BN95: =BN77+BN83+BN89 -> 802 | BO95: =BO77+BO83+BO89 -> 831 | BP95: =BP77+BP83+BP89 -> 863 | BQ95: =SUM(BM95:BP95) -> 3295 | BR95: =BR77+BR83+BR89 -> 859 | BS95: =BS77+BS83+BS89 -> 888 | BT95: =BT77+BT83+BT89 -> 909 | BU95: =BU77+BU83+BU89 -> 949.46307 | BV95: =SUM(BR95:BU95) -> 3605.4631 | BW95: =BW77+BW83+BW89 -> 947.25537 | BX95: =BX77+BX83+BX89 -> 956.9456 | BY95: =BY77+BY83+BY89 -> 982.92438 | BZ95: =BZ77+BZ83+BZ89 -> 1030.4282 | CA95: =SUM(BW95:BZ95) -> 3917.5536 | CB95: =CB77+CB83+CB89 -> 1027.8069 | CC95: =CC77+CC83+CC89 -> 1038.1438 | CD95: =CD77+CD83+CD89 -> 1066.4829 | CE95: =CE77+CE83+CE89 -> 1118.1957 | CF95: =SUM(CB95:CE95) -> 4250.6292
B96: Reported growth % y/y | J96: =IFERROR( J95/E95-1, "NA") -> 0.068521381 | K96: =IFERROR( K95/F95-1, "NA") -> 0.082164329 | L96: =IFERROR( L95/G95-1, "NA") -> 0.057674419 | M96: =IFERROR( M95/H95-1, "NA") -> 0.078364566 | N96: =IFERROR( N95/I95-1, "NA") -> 0.071724956 | O96: =IFERROR( O95/J95-1, "NA") -> 0.14802314 | P96: =IFERROR( P95/K95-1, "NA") -> 0.15046296 | Q96: =IFERROR( Q95/L95-1, "NA") -> 0.18513632 | ... CF96: =IFERROR( CF95/CA95-1, "NA") -> 0.085021332
B97: M&A impact % y/y | O97: 0.05 | P97: 0.05 | Q97: 0.07 | R97: 0.055 | S97: =SUMPRODUCT(O97:R97,J$95:M$95)/N$95 -> 0.056431416 | T97: 0.044 | U97: 0.05 | V97: =(0.03*Q70)/Q95 -> 0.015951763 | W97: 0 | X97: =SUMPRODUCT(T97:W97,O$95:R$95)/S$95 -> 0.025456621 | Y97: 0.0225 | Z97: 0.03 | AA97: 0.03 | AB97: 0.03 | AC97: =SUMPRODUCT(Y97:AB97,T$95:W$95)/X$95 -> 0.028283274 | AD97: 0.03 | AE97: 0 | AF97: =30.2/AA95 -> 0.099081365 | AG97: =62/AB95 -> 0.18546216 | AH97: =SUMPRODUCT(AD97:AG97,Y$95:AB$95)/AC$95 -> 0.081830712 | AI97: =73.5/AD95 -> 0.23941368 | AJ97: =80/AE95 -> 0.25493945 | AK97: =(436-399.1)/AF95 -> 0.10008137 | AL97: =(464.7-453.4)/AG95 -> 0.025635209 | AM97: =SUMPRODUCT(AI97:AL97,AD$95:AG$95)/AH$95 -> 0.14101937 | AN97: =(2.5+8.9)/AI95 -> 0.028023599 | AO97: =(1.1+8.8)/AJ95 -> 0.023415326 | AP97: =(1.1+9+2.5)/AK95 -> 0.028899083 | AQ97: =(1+5+2-16)/AL95 -> -0.017215408 | AR97: =SUMPRODUCT(AN97:AQ97,AI$95:AL$95)/AM$95 -> 0.014968503 | AS97: =(-17/AN95) -> -0.036016949 | AT97: =(6+2+14-28)/AO95 -> -0.012626263 | AU97: =(2+3+16-28)/AP95-0.005 -> -0.019172909 | AV97: =(15+2-11)/AQ95 -> 0.011695906 | AW97: =SUMPRODUCT(AS97:AV97,AN$95:AQ$95)/AR$95 -> -0.013545622 | AX97: =19/AS95 -> 0.038306452 | AY97: =13/AT95 -> 0.026156942 | AZ97: =28/AU95 -> 0.052730697 | BA97: =78/AV95 -> 0.14054054 | BB97: =SUMPRODUCT(AX97:BA97,AS$95:AV$95)/AW$95 -> 0.066378066 | BC97: =79/AX95 -> 0.14007092 | BD97: =83/AY95 -> 0.14485166 | BE97: =70/AZ95 -> 0.11647255 | BF97: =4/BA95 -> 0.005988024 | BG97: =SUMPRODUCT(BC97:BF97,AX$95:BA$95)/BB$95 -> 0.098088113 | BH97: =SUM((BH79*BC$77),(BH85*BC$83),(BH91*BC$89))/BC$95 -> 0 | BI97: =SUM((BI79*BD$77),(BI85*BD$83),(BI91*BD$89))/BD$95 -> 0 | BJ97: =SUM((BJ79*BE$77),(BJ85*BE$83),(BJ91*BE$89))/BE$95 -> 0 | BK97: =SUM((BK79*BF$77),(BK85*BF$83),(BK91*BF$89))/BF$95 -> 0 | BL97: =SUMPRODUCT(BH97:BK97,BC$95:BF$95)/BG$95 -> 0 | BM97: =SUM((BM79*BH$77),(BM85*BH$83),(BM91*BH$89))/BH$95 -> 0 | BN97: =SUM((BN79*BI$77),(BN85*BI$83),(BN91*BI$89))/BI$95 -> 0 | BO97: =SUM((BO79*BJ$77),(BO85*BJ$83),(BO91*BJ$89))/BJ$95 -> 0 | BP97: =SUM((BP79*BK$77),(BP85*BK$83),(BP91*BK$89))/BK$95 -> 0.0025125628 | BQ97: =SUMPRODUCT(BM97:BP97,BH$95:BK$95)/BL$95 -> 0.00065445026 | BR97: =SUM((BR79*BM$77),(BR85*BM$83),(BR91*BM$89))/BM$95 -> 0.013767209 | BS97: =SUM((BS79*BN$77),(BS85*BN$83),(BS91*BN$89))/BN$95 -> 0.017456359 | BT97: =SUM((BT79*BO$77),(BT85*BO$83),(BT91*BO$89))/BO$95 -> 0.015643803 | BU97: =SUM((BU79*BP$77),(BU85*BP$83),(BU91*BP$89))/BP$95 -> 0.0069524913 | BV97: =SUMPRODUCT(BR97:BU97,BM$95:BP$95)/BQ$95 -> 0.013353566 | BW97: =SUM((BW79*BR$77),(BW85*BR$83),(BW91*BR$89))/BR$95 -> -0.0046565774 | BX97: =SUM((BX79*BS$77),(BX85*BS$83),(BX91*BS$89))/BS$95 -> -0.0045045045 | BY97: =SUM((BY79*BT$77),(BY85*BT$83),(BY91*BT$89))/BT$95 -> -0.00440044 | BZ97: =SUM((BZ79*BU$77),(BZ85*BU$83),(BZ91*BU$89))/BU$95 -> 0 | CA97: =SUMPRODUCT(BW97:BZ97,BR$95:BU$95)/BV$95 -> -0.0033282826 | CB97: =SUM((CB79*BW$77),(CB85*BW$83),(CB91*BW$89))/BW$95 -> 0 | CC97: =SUM((CC79*BX$77),(CC85*BX$83),(CC91*BX$89))/BX$95 -> 0 | CD97: =SUM((CD79*BY$77),(CD85*BY$83),(CD91*BY$89))/BY$95 -> 0 | CE97: =SUM((CE79*BZ$77),(CE85*BZ$83),(CE91*BZ$89))/BZ$95 -> 0 | CF97: =SUMPRODUCT(CB97:CE97,BW$95:BZ$95)/CA$95 -> 0
B98: Organic growth % y/y | O98: =O96-O97 -> 0.098023144 | P98: =P96-P97 -> 0.10046296 | Q98: =Q96-Q97 -> 0.11513632 | R98: =R96-R97 -> 0.17880727 | S98: =SUMPRODUCT(O98:R98,J$95:M$95)/N$95 -> 0.12553761 | T98: =T96-T97 -> 0.061837883 | U98: =U96-U97 -> 0.072334004 | V98: =V96-V97 -> 0.048241187 | W98: =W96-W97 -> 0.028489117 | X98: =SUMPRODUCT(T98:W98,O$95:R$95)/S$95 -> 0.051099298 | Y98: =Y96-Y97 -> 0.08270319 | Z98: =Z96-Z97 -> 0.057486554 | AA98: =AA96-AA97 -> 0.032761506 | AB98: =AB96-AB97 -> 0.010460629 | AC98: =SUMPRODUCT(Y98:AB98,T$95:W$95)/X$95 -> 0.04395875 | AD98: =AD96-AD97 -> 0.024982818 | AE98: =AE96-AE97 -> 0.034619189 | AF98: =AF96-AF97 -> 0.1105643 | AG98: =AG96-AG97 -> 0.13311397 | AH98: =SUMPRODUCT(AD98:AG98,Y$95:AB$95)/AC$95 -> 0.077809308 | AI98: =AI96-AI97 -> 0.085667752 | AJ98: =AJ96-AJ97 -> 0.092415551 | AK98: =AK96-AK97 -> 0.082451858 | AL98: =AL96-AL97 -> 0.028584392 | AM98: =SUMPRODUCT(AI98:AL98,AD$95:AG$95)/AH$95 -> 0.068726841 | AN98: =AN96-AN97 -> 0.13225172 | AO98: =AO96-AO97 -> 0.10052034 | AP98: =AP96-AP97 -> 0.10389908 | AQ98: =AQ96-AQ97 -> 0.12115343 | AR98: =SUMPRODUCT(AN98:AQ98,AI$95:AL$95)/AM$95 -> 0.11437323 | AS98: =AS96-AS97 -> 0.086864407 | AT98: =AT96-AT97 -> 0.058501684 | AU98: =AU96-AU97 -> 0.09428933 | AV98: =AV96-AV97 -> 0.070175439 | AW98: =SUMPRODUCT(AS98:AV98,AN$95:AQ$95)/AR$95 -> 0.077462515 | AX98: =AX96-AX97 -> 0.098790323 | AY98: =AY96-AY97 -> 0.12676056 | AZ98: =AZ96-AZ97 -> 0.079096045 | BA98: =BA96-BA97 -> 0.063063063 | BB98: =SUMPRODUCT(AX98:BA98,AS$95:AV$95)/AW$95 -> 0.090909091 | BC98: =BC96-BC97 -> 0.092198582 | BD98: =BD96-BD97 -> 0.033158813 | BE98: =BE96-BE97 -> 0.023294509 | BF98: =BF96-BF97 -> 0.062874251 | BG98: =SUMPRODUCT(BC98:BF98,AX$95:BA$95)/BB$95 -> 0.052784705 | BH98: =BH96-BH97 -> 0.060431655 | BI98: =BI96-BI97 -> 0.10666667 | BJ98: =BJ96-BJ97 -> 0.13284672 | BK98: =BK96-BK97 -> 0.11484594 | BL98: =SUMPRODUCT(BH98:BK98,BC$95:BF$95)/BG$95 -> 0.10364753 | BM98: =BM96-BM97 -> 0.08412483 | BN98: =BN96-BN97 -> 0.073627845 | BO98: =BO96-BO97 -> 0.070876289 | BP98: =BP96-BP97 -> 0.081658291 | BQ98: =SUMPRODUCT(BM98:BP98,BH$95:BK$95)/BL$95 -> 0.077552356 | BR98: =BR96-BR97 -> 0.061326658 | BS98: =BS96-BS97 -> 0.089775561 | BT98: =BT96-BT97 -> 0.078219013 | BU98: =BU96-BU97 -> 0.093236465 | BV98: =SUMPRODUCT(BR98:BU98,BM$95:BP$95)/BQ$95 -> 0.080868913 | BW98: =BW96-BW97 -> 0.10739857 | BX98: =BX96-BX97 -> 0.082145946 | BY98: =BY96-BY97 -> 0.085725395 | BZ98: =BZ96-BZ97 -> 0.085274657 | CA98: =SUMPRODUCT(BW98:BZ98,BR$95:BU$95)/BV$95 -> 0.08988873 | CB98: =CB96-CB97 -> 0.085036716 | CC98: =CC96-CC97 -> 0.084851399 | CD98: =CD96-CD97 -> 0.085010103 | CE98: =CE96-CE97 -> 0.085175716 | CF98: =SUMPRODUCT(CB98:CE98,BW$95:BZ$95)/CA$95 -> 0.085021332
B99: FX impact % y/y | O99: 0 | P99: 0.03 | Q99: 0.02 | R99: -0.03 | S99: =SUMPRODUCT(O99:R99,J$95:M$95)/N$95 -> 0.0037964602 | T99: -0.05 | U99: -0.06 | V99: -0.05 | W99: -0.03 | X99: =SUMPRODUCT(T99:W99,O$95:R$95)/S$95 -> -0.046478241 | Y99: -0.02 | Z99: -0.01 | AA99: -0.03 | AB99: -0.04 | AC99: =SUMPRODUCT(Y99:AB99,T$95:W$95)/X$95 -> -0.025655047 | AD99: -0.01 | AE99: 0 | AF99: 0.01 | AG99: 0.03 | AH99: =SUMPRODUCT(AD99:AG99,Y$95:AB$95)/AC$95 -> 0.0082430679 | AI99: 0.04 | AJ99: 0.02 | AK99: -0.01 | AL99: -0.02 | AM99: =SUMPRODUCT(AI99:AL99,AD$95:AG$95)/AH$95 -> 0.0042319793 | AN99: -0.03 | AO99: -0.03 | AP99: -0.02 | AQ99: 0 | AR99: =SUMPRODUCT(AN99:AQ99,AI$95:AL$95)/AM$95 -> -0.019423221 | AS99: -0.01 | AT99: -0.02 | AU99: =8/AP95 -> 0.016197611 | AV99: 0.02 | AW99: =SUMPRODUCT(AS99:AV99,AN$95:AQ$95)/AR$95 -> 0.002065401 | AX99: 0.04 | AY99: 0.05 | AZ99: 0.01 | BA99: -0.01 | BB99: =SUMPRODUCT(AX99:BA99,AS$95:AV$95)/AW$95 -> 0.021380471 | BC99: =-13/AX95 -> -0.023049645 | BD99: =-27/AY95 -> -0.047120419 | BE99: =-41/AZ95 -> -0.068219634 | BF99: =-32/BA95 -> -0.047904192 | BG99: =SUMPRODUCT(BC99:BF99,AX$95:BA$95)/BB$95 -> -0.046965919 | BH99: =SUM((BH81*BC$77),(BH87*BC$83),(BH93*BC$89))/BC$95 -> -0.025899281 | BI99: =SUM((BI81*BD$77),(BI87*BD$83),(BI93*BD$89))/BD$95 -> 0.003 | BJ99: =SUM((BJ81*BE$77),(BJ87*BE$83),(BJ93*BE$89))/BE$95 -> 0.024817518 | BK99: =SUM((BK81*BF$77),(BK87*BF$83),(BK93*BF$89))/BF$95 -> 0.016806723 | BL99: =SUMPRODUCT(BH99:BK99,BC$95:BF$95)/BG$95 -> 0.0047038642 | BM99: =SUM((BM81*BH$77),(BM87*BH$83),(BM93*BH$89))/BH$95 -> 0.0027137042 | BN99: =SUM((BN81*BI$77),(BN87*BI$83),(BN93*BI$89))/BI$95 -> -0.0026773762 | BO99: =SUM((BO81*BJ$77),(BO87*BJ$83),(BO93*BJ$89))/BJ$95 -> 0.006443299 | BP99: =SUM((BP81*BK$77),(BP87*BK$83),(BP93*BK$89))/BK$95 -> 0 | BQ99: =SUMPRODUCT(BM99:BP99,BH$95:BK$95)/BL$95 -> 0.0016361257 | BR99: =SUM((BR81*BM$77),(BR87*BM$83),(BR93*BM$89))/BM$95 -> -0.010012516 | BS99: =SUM((BS81*BN$77),(BS87*BN$83),(BS93*BN$89))/BN$95 -> 0.018703242 | BT99: =SUM((BT81*BO$77),(BT87*BO$83),(BT93*BO$89))/BO$95 -> 0.016847172 | BU99: =SUM((BU81*BP$77),(BU87*BP$83),(BU93*BP$89))/BP$95 -> 0.028578296 | BV99: =SUMPRODUCT(BR99:BU99,BM$95:BP$95)/BQ$95 -> 0.013858291 | BW99: =SUM((BW81*BR$77),(BW87*BR$83),(BW93*BR$89))/BR$95 -> 0.029237919 | BX99: =SUM((BX81*BS$77),(BX87*BS$83),(BX93*BS$89))/BS$95 -> 0.0041166664 | BY99: =SUM((BY81*BT$77),(BY87*BT$83),(BY93*BT$89))/BT$95 -> -0.0030369812 | BZ99: =SUM((BZ81*BU$77),(BZ87*BU$83),(BZ93*BU$89))/BU$95 -> -0.0049765375 | CA99: =SUMPRODUCT(BW99:BZ99,BR$95:BU$95)/BV$95 -> 0.0059036295 | CB99: =SUM((CB81*BW$77),(CB87*BW$83),(CB93*BW$89))/BW$95 -> -0.00045167309 | CC99: =SUM((CC81*BX$77),(CC87*BX$83),(CC93*BX$89))/BX$95 -> -0.00045167309 | CD99: =SUM((CD81*BY$77),(CD87*BY$83),(CD93*BY$89))/BY$95 -> -0.00045167309 | CE99: =SUM((CE81*BZ$77),(CE87*BZ$83),(CE93*BZ$89))/BZ$95 -> -0.00045167309 | CF99: =SUMPRODUCT(CB99:CE99,BW$95:BZ$95)/CA$95 -> -0.00045167309
B100: MA organic constant currency growth % y/y | O100: =IFERROR(O96-O97-O99,"NA") -> 0.098023144 | P100: =IFERROR(P96-P97-P99,"NA") -> 0.070462963 | Q100: =IFERROR(Q96-Q97-Q99,"NA") -> 0.095136324 | R100: =IFERROR(R96-R97-R99,"NA") -> 0.20880727 | S100: =SUMPRODUCT(O100:R100,J$95:M$95)/N$95 -> 0.12174115 | T100: =IFERROR(T96-T97-T99,"NA") -> 0.11183788 | U100: =IFERROR(U96-U97-U99,"NA") -> 0.132334 | V100: =IFERROR(V96-V97-V99,"NA") -> 0.098241187 | W100: =IFERROR(W96-W97-W99,"NA") -> 0.058489117 | X100: =SUMPRODUCT(T100:W100,O$95:R$95)/S$95 -> 0.097577539 | Y100: =IFERROR(Y96-Y97-Y99,"NA") -> 0.10270319 | Z100: =IFERROR(Z96-Z97-Z99,"NA") -> 0.067486554 | AA100: =IFERROR(AA96-AA97-AA99,"NA") -> 0.062761506 | AB100: =IFERROR(AB96-AB97-AB99,"NA") -> 0.050460629 | AC100: =SUMPRODUCT(Y100:AB100,T$95:W$95)/X$95 -> 0.069613796 | AD100: =AD96-AD97-AD99 -> 0.034982818 | AE100: =AE96-AE97-AE99 -> 0.034619189 | AF100: =AF96-AF97-AF99 -> 0.1005643 | AG100: =AG96-AG97-AG99 -> 0.10311397 | AH100: =SUMPRODUCT(AD100:AG100,Y$95:AB$95)/AC$95 -> 0.06956624 | AI100: =AI96-AI97-AI99 -> 0.045667752 | AJ100: =AJ96-AJ97-AJ99 -> 0.072415551 | AK100: =AK96-AK97-AK99 -> 0.092451858 | AL100: =AL96-AL97-AL99 -> 0.048584392 | AM100: =SUMPRODUCT(AI100:AL100,AD$95:AG$95)/AH$95 -> 0.064494861 | AN100: =AN96-AN97-AN99 -> 0.16225172 | AO100: =AO96-AO97-AO99 -> 0.13052034 | AP100: =AP96-AP97-AP99 -> 0.12389908 | AQ100: =AQ96-AQ97-AQ99 -> 0.12115343 | AR100: =SUMPRODUCT(AN100:AQ100,AI$95:AL$95)/AM$95 -> 0.13379645 | AS100: =AS96-AS97-AS99 -> 0.096864407 | AT100: =AT96-AT97-AT99 -> 0.078501684 | AU100: =AU96-AU97-AU99 -> 0.078091719 | AV100: =AV96-AV97-AV99 -> 0.050175439 | AW100: =SUMPRODUCT(AS100:AV100,AN$95:AQ$95)/AR$95 -> 0.075397114 | AX100: =AX96-AX97-AX99 -> 0.058790323 | AY100: =AY96-AY97-AY99 -> 0.076760563 | AZ100: =AZ96-AZ97-AZ99 -> 0.069096045 | BA100: =BA96-BA97-BA99 -> 0.073063063 | BB100: =SUMPRODUCT(AX100:BA100,AS$95:AV$95)/AW$95 -> 0.06952862 | BC100: =BC96-BC97-BC99 -> 0.11524823 | BD100: =BD96-BD97-BD99 -> 0.080279232 | BE100: =BE96-BE97-BE99 -> 0.091514143 | BF100: =BF96-BF97-BF99 -> 0.11077844 | BG100: =SUMPRODUCT(BC100:BF100,AX$95:BA$95)/BB$95 -> 0.099750623 | BH100: =BH96-BH97-BH99 -> 0.086330935 | BI100: =BI96-BI97-BI99 -> 0.10366667 | BJ100: =BJ96-BJ97-BJ99 -> 0.1080292 | BK100: =BK96-BK97-BK99 -> 0.098039216 | BL100: =SUMPRODUCT(BH100:BK100,BC$95:BF$95)/BG$95 -> 0.098943662 | BM100: =BM96-BM97-BM99 -> 0.081411126 | BN100: =BN96-BN97-BN99 -> 0.076305221 | BO100: =BO96-BO97-BO99 -> 0.06443299 | BP100: =BP96-BP97-BP99 -> 0.081658291 | BQ100: =SUMPRODUCT(BM100:BP100,BH$95:BK$95)/BL$95 -> 0.07591623 | BR100: =BR96-BR97-BR99 -> 0.071339174 | BS100: =BS96-BS97-BS99 -> 0.071072319 | BT100: =BT96-BT97-BT99 -> 0.061371841 | BU100: =BU96-BU97-BU99 -> 0.064658169 | BV100: =SUMPRODUCT(BR100:BU100,BM$95:BP$95)/BQ$95 -> 0.067010622 | BW100: =BW96-BW97-BW99 -> 0.078160652 | BX100: =BX96-BX97-BX99 -> 0.078029279 | BY100: =BY96-BY97-BY99 -> 0.088762376 | BZ100: =BZ96-BZ97-BZ99 -> 0.090251195 | CA100: =SUMPRODUCT(BW100:BZ100,BR$95:BU$95)/BV$95 -> 0.0839851 | CB100: =CB96-CB97-CB99 -> 0.085488389 | CC100: =CC96-CC97-CC99 -> 0.085303072 | CD100: =CD96-CD97-CD99 -> 0.085461776 | CE100: =CE96-CE97-CE99 -> 0.08562739 | CF100: =SUMPRODUCT(CB100:CE100,BW$95:BZ$95)/CA$95 -> 0.085473005
B101: Reported growth % sequential | O101: =O95/M95-1 -> -0.059636651 | P101: =P95/O95-1 -> 0.043679126 | Q101: =Q95/P95-1 -> 0.084507042 | R101: =R95/Q95-1 -> 0.15918367 | T101: =T95/R95-1 -> -0.15717029 | U101: =U95/T95-1 -> 0.059248006 | V101: =V95/U95-1 -> 0.028325565 | W101: =W95/V95-1 -> 0.12029289 | Y101: =Y95/W95-1 -> -0.094304388 | Z101: =Z95/Y95-1 -> 0.042268041 | AA101: =AA95/Z95-1 -> 0.0049455984 | AB101: =AB95/AA95-1 -> 0.096784777 | AD101: =AD95/AB95-1 -> -0.081663177 | AE101: =AE95/AD95-1 -> 0.022149837 | AF101: =AF95/AE95-1 -> 0.1749522 | AG101: =AG95/AF95-1 -> 0.19555194 | AI101: =AI95/AG95-1 -> -0.077132486 | AJ101: =AJ95/AI95-1 -> 0.039331367 | AK101: =AK95/AJ95-1 -> 0.031220435 | AL101: =AL95/AK95-1 -> 0.065825688 | AN101: =AN95/AL95-1 -> 0.01570906 | AO101: =AO95/AN95-1 -> 0.006779661 | AP101: =AP95/AO95-1 -> 0.039351852 | AQ101: =AQ95/AP95-1 -> 0.038671796 | AS101: =AS95/AQ95-1 -> -0.033138402 | AT101: =AT95/AS95-1 -> 0.002016129 | AU101: =AU95/AT95-1 -> 0.068410463 | AV101: =AV95/AU95-1 -> 0.04519774 | AX101: =AX95/AV95-1 -> 0.016216216 | AY101: =AY95/AW95-1 -> -0.72438672 | AZ101: =AZ95/AY95-1 -> 0.04886562 | BA101: =BA95/AZ95-1 -> 0.11148087 | BC101: =BC95/BA95-1 -> 0.040419162 | BD101: =BD95/BC95-1 -> -0.028776978 | BE101: =BE95/BD95-1 -> 0.014814815 | BF101: =BF95/BE95-1 -> 0.042335766 | BH101: =BH95/BF95-1 -> 0.032212885 | BI101: =BI95/BH95-1 -> 0.013568521 | BJ101: =BJ95/BI95-1 -> 0.038821954 | BK101: =BK95/BJ95-1 -> 0.025773196 | BM101: =BM95/BK95-1 -> 0.0037688442 | BN101: =BN95/BM95-1 -> 0.0037546934 | BO101: =BO95/BN95-1 -> 0.036159601 | BP101: =BP95/BO95-1 -> 0.038507822 | BR101: =BR95/BP95-1 -> -0.0046349942 | BS101: =BS95/BR95-1 -> 0.033760186 | BT101: =BT95/BS95-1 -> 0.023648649 | BU101: =BU95/BT95-1 -> 0.044513827 | BW101: =BW95/BU95-1 -> -0.0023252049 | BX101: =BX95/BW95-1 -> 0.010229794 | BY101: =BY95/BX95-1 -> 0.027147608 | BZ101: =BZ95/BY95-1 -> 0.048329071 | CB101: =CB95/BZ95-1 -> -0.0025439401 | CC101: =CC95/CB95-1 -> 0.010057253 | CD101: =CD95/CC95-1 -> 0.027297871 | CE101: =CE95/CD95-1 -> 0.048489086
B103: Annualized Recurring Revenue (ARR; in $mm)
B104: Banking | BI104: 390 | BJ104: 397 | BK104: 418 | BL104: =BK104 -> 418 | BM104: 424 | BN104: 428 | BO104: 439 | BP104: 457 | BQ104: =BP104 -> 457 | BR104: 453 | BS104: 456
B105: Insurance | BI105: 497 | BJ105: 511 | BK105: 533 | BL105: =BK105 -> 533 | BM105: 552 | BN105: 569 | BO105: 579 | BP105: 601 | BQ105: =BP105 -> 601 | BR105: 609 | BS105: 616
B106: KYC | BI106: 292 | BJ106: 308 | BK106: 326 | BL106: =BK106 -> 326 | BM106: 344 | BN106: 352 | BO106: 360 | BP106: 390 | BQ106: =BP106 -> 390 | BR106: 393 | BS106: 395
...

Sheet IS
N1: 14Y | S1: 15Y | T1: CQ1 | U1: CQ2 | V1: CQ3 | W1: CQ4 | X1: 16Y | Y1: CQ1 | Z1: CQ2 | AA1: CQ3 | AB1: CQ4 | AC1: 17Y | AD1: CQ1 | AE1: CQ2 | AF1: CQ3 | AG1: CQ4 | AH1: 18Y | AI1: CQ1 | AJ1: CQ2 | AK1: CQ3 | AL1: CQ4 | AM1: 19Y | AN1: CQ1 | AO1: CQ2 | AP1: CQ3 | AQ1: CQ4 | AR1: 20Y
B3: Moody's (MCO)
B4: Quarterly & Annual Earnings Model
B5: ($ in Millions, except per share data)
E6: 2013A | J6: 2014A | O6: 2015A | T6: 2016A | Y6: 2017A | AD6: 2018A | AI6: 2019A | AN6: 2020A | AS6: 2021A | AX6: 2022A | BC6: 2023A | BH6: 2024A | BM6: 2025E | BR6: 2026E | BW6: 2027E
E7: 1Q13A | F7: 2Q13A | G7: 3Q13A | H7: 4Q13A | I7: 2013A | J7: 1Q14A | K7: 2Q14A | L7: 3Q14A | M7: 4Q14A | N7: 2014A | O7: 1Q15A | P7: 2Q15A | Q7: 3Q15A | R7: 4Q15A | S7: 2015A | T7: 1Q16A | U7: 2Q16A | V7: 3Q16A | W7: 4Q16A | X7: 2016A | Y7: 1Q17A | Z7: 2Q17A | AA7: 3Q17A | AB7: 4Q17A | AC7: 2017A | AD7: 1Q18A | AE7: 2Q18A | AF7: 3Q18A | AG7: 4Q18A | AH7: 2018A | AI7: 1Q19A | AJ7: 2Q19A | AK7: 3Q19A | AL7: 4Q19A | AM7: 2019A | AN7: 1Q20A | AO7: 2Q20A | AP7: 3Q20A | AQ7: 4Q20A | AR7: 2020A | AS7: 1Q21A | AT7: 2Q21A | AU7: 3Q21A | AV7: 4Q21A | AW7: 2021A | AX7: 1Q22A | AY7: 2Q22A | AZ7: 3Q22A | BA7: 4Q22A | BB7: 2022A | BC7: 1Q23A | BD7: 2Q23A | BE7: 3Q23A | BF7: 4Q23A | BG7: 2023A | BH7: 1Q24A | BI7: 2Q24A | BJ7: 3Q24A | BK7: 4Q24A | BL7: 2024A | BM7: 1Q25A | BN7: 2Q25A | BO7: 3Q25E | BP7: 4Q25E | BQ7: 2025E | BR7: 1Q26E | BS7: 2Q26E | BT7: 3Q26E | BU7: 4Q26E | BV7: 2026E | BW7: 1Q27E | BX7: 2Q27E | BY7: 3Q27E | BZ7: 4Q27E | CA7: 2027E
B9: MOODY'S INVESTOR SERVICE (RATINGS) | E9: =Segments!J31 -> 521.25 | F9: =Segments!K31 -> 537.3 | G9: =Segments!L31 -> 478.1 | H9: =Segments!M31 -> 526 | I9: =Segments!N31 -> 2062.65 | J9: =Segments!O31 -> 529.1 | K9: =Segments!P31 -> 625 | L9: =Segments!Q31 -> 546.6 | ... CA9: =Segments!CF31 -> 4695.729
B10: =Segments!B32 -> Reported growth % y/y | E10: =Segments!J32 -> 0.15167919 | F10: =Segments!K32 -> 0.21753909 | G10: =Segments!L32 -> 0.010141559 | H10: =Segments!M32 -> 0.012901983 | I10: =Segments!N32 -> 0.093373973 | J10: =Segments!O32 -> 0.015059952 | K10: =Segments!P32 -> 0.16322353 | L10: =Segments!Q32 -> 0.14327547 | ... CA10: =Segments!CF32 -> 0.06838617
B11: =Segments!B37 -> Reported growth % sequential | O11: =Segments!T37 -> 0.065829057 | P11: =Segments!U37 -> 0.06126515 | Q11: =Segments!V37 -> -0.1425219 | R11: =Segments!W37 -> -0.006385696 | T11: =Segments!Y37 -> -0.035806096 | U11: =Segments!Z37 -> 0.19139212 | V11: =Segments!AA37 -> -0.021259591 | W11: =Segments!AB37 -> -0.0073493386 | Y11: =Segments!AD37 -> 0.099374794 | Z11: =Segments!AE37 -> 0.027686321 | AA11: =Segments!AF37 -> 0.0109218 | AB11: =Segments!AG37 -> 0.043935465 | AD11: =Segments!AI37 -> -0.0066234304 | AE11: =Segments!AJ37 -> 0.045006251 | AF11: =Segments!AK37 -> -0.14289512 | AG11: =Segments!AL37 -> -0.076612903 | AI11: =Segments!AN37 -> 0.12546187 | AJ11: =Segments!AO37 -> 0.10192509 | AK11: =Segments!AP37 -> 0.011105092 | AL11: =Segments!AQ37 -> -0.035628181 | AN11: =Segments!AS37 -> 0.10277778 | AO11: =Segments!AT37 -> 0.1813602 | AP11: =Segments!AU37 -> -0.12046908 | AQ11: =Segments!AV37 -> -0.10909091 | AS11: =Segments!AX37 -> 0.40952381 | AT11: =Segments!AY37 -> -0.054054054 | AU11: =Segments!AZ37 -> -0.056122449 | AV11: =Segments!BA37 -> -0.058378378 | AX11: =Segments!BC37 -> -0.050516648 | AY11: =Segments!BD37 -> -0.14631197 | AZ11: =Segments!BE37 -> -0.16430595 | BA11: =Segments!BF37 -> -0.023728814 | BC11: =Segments!BH37 -> 0.27256944 | BD11: =Segments!BI37 -> 0.019099591 | BE11: =Segments!BJ37 -> -0.068273092 | BF11: =Segments!BK37 -> -0.017241379 | BH11: =Segments!BM37 -> 0.44298246 | BI11: =Segments!BN37 -> 0.028368794 | BJ11: =Segments!BO37 -> -0.032512315 | BK11: =Segments!BP37 -> -0.17617108 | BM11: =Segments!BR37 -> 0.31644005 | BN11: =Segments!BS37 -> -0.051643192 | BO11: =Segments!BT37 -> 0.084584158 | BP11: =Segments!BU37 -> -0.17952311 | BR11: =Segments!BW37 -> 0.29047314 | BS11: =Segments!BX37 -> -0.052584613 | BT11: =Segments!BY37 -> 0.068831898 | BU11: =Segments!BZ37 -> -0.18094794 | BW11: =Segments!CB37 -> 0.28875237 | BX11: =Segments!CC37 -> -0.053125998 | BY11: =Segments!CD37 -> 0.069397652 | BZ11: =Segments!CE37 -> -0.18208126
B12: =Segments!B33 -> M&A impact % y/y | J12: =Segments!O33 -> 0 | K12: =Segments!P33 -> 0.02 | L12: =Segments!Q33 -> 0.02 | M12: =Segments!R33 -> 0.02 | O12: =Segments!T33 -> 0.02 | P12: =Segments!U33 -> 0 | Q12: =Segments!V33 -> 0 | R12: =Segments!W33 -> 0 | S12: =Segments!X33 -> 0.0046703151 | T12: =Segments!Y33 -> 0 | U12: =Segments!Z33 -> 0 | V12: =Segments!AA33 -> 0 | ... CA12: =Segments!CF33 -> 0
B13: =Segments!B34 -> Organic growth % y/y | J13: =Segments!O34 -> 0.015059952 | K13: =Segments!P34 -> 0.14322353 | L13: =Segments!Q34 -> 0.12327547 | M13: =Segments!R34 -> 0.054334601 | O13: =Segments!T34 -> 0.11834814 | P13: =Segments!U34 -> 0.02272 | Q13: =Segments!V34 -> 0.0027442371 | R13: =Segments!W34 -> -0.036276765 | S13: =Segments!X34 -> 0.025517698 | T13: =Segments!Y34 -> -0.12817533 | U13: =Segments!Z34 -> -0.021276596 | V13: =Segments!AA34 -> 0.11713191 | ... CA13: =Segments!CF34 -> 0.06838617
B14: =Segments!B35 -> FX impact % y/y | J14: =Segments!O35 -> 0 | K14: =Segments!P35 -> 0.01 | L14: =Segments!Q35 -> 0 | M14: =Segments!R35 -> -0.03 | O14: =Segments!T35 -> -0.05 | P14: =Segments!U35 -> -0.05 | Q14: =Segments!V35 -> -0.05 | R14: =Segments!W35 -> -0.04 | S14: =Segments!X35 -> -0.047505958 | T14: =Segments!Y35 -> -0.014 | U14: =Segments!Z35 -> 0 | V14: =Segments!AA35 -> 0 | ... CA14: =Segments!CF35 -> -0.00099011186
B15: =Segments!B36 -> MIS organic constant currency growth % y/y | J15: =Segments!O36 -> 0.015059952 | K15: =Segments!P36 -> 0.13322353 | L15: =Segments!Q36 -> 0.12327547 | M15: =Segments!R36 -> 0.084334601 | O15: =Segments!T36 -> 0.16834814 | P15: =Segments!U36 -> 0.07272 | Q15: =Segments!V36 -> 0.052744237 | R15: =Segments!W36 -> 0.0037232348 | S15: =Segments!X36 -> 0.073023656 | T15: =Segments!Y36 -> -0.11417533 | U15: =Segments!Z36 -> -0.021276596 | V15: =Segments!AA36 -> 0.11713191 | ... CA15: =Segments!CF36 -> 0.069376282
B17: MOODY'S ANALYTICS | E17: =Segments!J95 -> 207.4 | F17: =Segments!K95 -> 216 | G17: =Segments!L95 -> 227.4 | H17: =Segments!M95 -> 253.2 | I17: =Segments!N95 -> 904 | J17: =Segments!O95 -> 238.1 | K17: =Segments!P95 -> 248.5 | L17: =Segments!Q95 -> 269.5 | ... CA17: =Segments!CF95 -> 4250.6292
B18: =Segments!B96 -> Reported growth % y/y | E18: =Segments!J96 -> 0.068521381 | F18: =Segments!K96 -> 0.082164329 | G18: =Segments!L96 -> 0.057674419 | H18: =Segments!M96 -> 0.078364566 | I18: =Segments!N96 -> 0.071724956 | J18: =Segments!O96 -> 0.14802314 | K18: =Segments!P96 -> 0.15046296 | L18: =Segments!Q96 -> 0.18513632 | ... CA18: =Segments!CF96 -> 0.085021332
B19: =Segments!B41 -> % revenue | J19: =Segments!O101 -> -0.059636651 | K19: =Segments!P101 -> 0.043679126 | L19: =Segments!Q101 -> 0.084507042 | M19: =Segments!R101 -> 0.15918367 | O19: =Segments!T101 -> -0.15717029 | P19: =Segments!U101 -> 0.059248006 | Q19: =Segments!V101 -> 0.028325565 | R19: =Segments!W101 -> 0.12029289 | T19: =Segments!Y101 -> -0.094304388 | U19: =Segments!Z101 -> 0.042268041 | V19: =Segments!AA101 -> 0.0049455984 | W19: =Segments!AB101 -> 0.096784777 | Y19: =Segments!AD101 -> -0.081663177 | Z19: =Segments!AE101 -> 0.022149837 | AA19: =Segments!AF101 -> 0.1749522 | AB19: =Segments!AG101 -> 0.19555194 | AD19: =Segments!AI101 -> -0.077132486 | AE19: =Segments!AJ101 -> 0.039331367 | AF19: =Segments!AK101 -> 0.031220435 | AG19: =Segments!AL101 -> 0.065825688 | AI19: =Segments!AN101 -> 0.01570906 | AJ19: =Segments!AO101 -> 0.006779661 | AK19: =Segments!AP101 -> 0.039351852 | AL19: =Segments!AQ101 -> 0.038671796 | AN19: =Segments!AS101 -> -0.033138402 | AO19: =Segments!AT101 -> 0.002016129 | AP19: =Segments!AU101 -> 0.068410463 | AQ19: =Segments!AV101 -> 0.04519774 | AS19: =Segments!AX101 -> 0.016216216 | AT19: =Segments!AY101 -> -0.72438672 | AU19: =Segments!AZ101 -> 0.04886562 | AV19: =Segments!BA101 -> 0.11148087 | AX19: =Segments!BC101 -> 0.040419162 | AY19: =Segments!BD101 -> -0.028776978 | AZ19: =Segments!BE101 -> 0.014814815 | BA19: =Segments!BF101 -> 0.042335766 | BC19: =Segments!BH101 -> 0.032212885 | BD19: =Segments!BI101 -> 0.013568521 | BE19: =Segments!BJ101 -> 0.038821954 | BF19: =Segments!BK101 -> 0.025773196 | BH19: =Segments!BM101 -> 0.0037688442 | BI19: =Segments!BN101 -> 0.0037546934 | BJ19: =Segments!BO101 -> 0.036159601 | BK19: =Segments!BP101 -> 0.038507822 | BM19: =Segments!BR101 -> -0.0046349942 | BN19: =Segments!BS101 -> 0.033760186 | BO19: =Segments!BT101 -> 0.023648649 | BP19: =Segments!BU101 -> 0.044513827 | BR19: =Segments!BW101 -> -0.0023252049 | BS19: =Segments!BX101 -> 0.010229794 | BT19: =Segments!BY101 -> 0.027147608 | BU19: =Segments!BZ101 -> 0.048329071 | BW19: =Segments!CB101 -> -0.0025439401 | BX19: =Segments!CC101 -> 0.010057253 | BY19: =Segments!CD101 -> 0.027297871 | BZ19: =Segments!CE101 -> 0.048489086
B20: =Segments!B97 -> M&A impact % y/y | J20: =Segments!O97 -> 0.05 | K20: =Segments!P97 -> 0.05 | L20: =Segments!Q97 -> 0.07 | M20: =Segments!R97 -> 0.055 | O20: =Segments!T97 -> 0.044 | P20: =Segments!U97 -> 0.05 | Q20: =Segments!V97 -> 0.015951763 | R20: =Segments!W97 -> 0 | S20: =Segments!X97 -> 0.025456621 | T20: =Segments!Y97 -> 0.0225 | U20: =Segments!Z97 -> 0.03 | V20: =Segments!AA97 -> 0.03 | ... CA20: =Segments!CF97 -> 0
B21: =Segments!B98 -> Organic growth % y/y | J21: =Segments!O98 -> 0.098023144 | K21: =Segments!P98 -> 0.10046296 | L21: =Segments!Q98 -> 0.11513632 | M21: =Segments!R98 -> 0.17880727 | O21: =Segments!T98 -> 0.061837883 | P21: =Segments!U98 -> 0.072334004 | Q21: =Segments!V98 -> 0.048241187 | R21: =Segments!W98 -> 0.028489117 | S21: =Segments!X98 -> 0.051099298 | T21: =Segments!Y98 -> 0.08270319 | U21: =Segments!Z98 -> 0.057486554 | V21: =Segments!AA98 -> 0.032761506 | ... CA21: =Segments!CF98 -> 0.085021332
B22: =Segments!B99 -> FX impact % y/y | J22: =Segments!O99 -> 0 | K22: =Segments!P99 -> 0.03 | L22: =Segments!Q99 -> 0.02 | M22: =Segments!R99 -> -0.03 | O22: =Segments!T99 -> -0.05 | P22: =Segments!U99 -> -0.06 | Q22: =Segments!V99 -> -0.05 | R22: =Segments!W99 -> -0.03 | S22: =Segments!X99 -> -0.046478241 | T22: =Segments!Y99 -> -0.02 | U22: =Segments!Z99 -> -0.01 | V22: =Segments!AA99 -> -0.03 | ... CA22: =Segments!CF99 -> -0.00045167309
B23: =Segments!B100 -> MA organic constant currency growth % y/y | J23: =Segments!O100 -> 0.098023144 | K23: =Segments!P100 -> 0.070462963 | L23: =Segments!Q100 -> 0.095136324 | M23: =Segments!R100 -> 0.20880727 | O23: =Segments!T100 -> 0.11183788 | P23: =Segments!U100 -> 0.132334 | Q23: =Segments!V100 -> 0.098241187 | R23: =Segments!W100 -> 0.058489117 | S23: =Segments!X100 -> 0.097577539 | T23: =Segments!Y100 -> 0.10270319 | U23: =Segments!Z100 -> 0.067486554 | V23: =Segments!AA100 -> 0.062761506 | ... CA23: =Segments!CF100 -> 0.085473005
B25: TOTAL revenue | E25: =E17+E9 -> 728.65 | F25: =F17+F9 -> 753.3 | G25: =G17+G9 -> 705.5 | H25: =H17+H9 -> 779.2 | I25: =I17+I9 -> 2966.65 | J25: =J17+J9 -> 767.2 | K25: =K17+K9 -> 873.5 | L25: =L17+L9 -> 816.1 | ... CA25: =CA17+CA9 -> 8946.3582
B26: Reported growth % y/y | I26: =Segments!N151 -> 0.089 | J26: =Segments!O151 -> 0.052906059 | K26: =Segments!P151 -> 0.15956458 | L26: =Segments!Q151 -> 0.15676825 | M26: =Segments!R151 -> 0.12615503 | N26: =Segments!S151 -> 0.12392766 | O26: =Segments!T151 -> 0.1282586 | P26: =Segments!U151 -> 0.051058958 | ... CA26: =Segments!CF151 -> 0.076225864
B27: Reported growth % sequential | J27: =Segments!O152 -> -0.015400411 | K27: =Segments!P152 -> 0.13855579 | L27: =Segments!Q152 -> -0.06571265 | M27: =Segments!R152 -> 0.075235878 | O27: =Segments!T152 -> -0.013561254 | P27: =Segments!U152 -> 0.060651571 | Q27: =Segments!V152 -> -0.090621937 | R27: =Segments!W152 -> 0.037130195 | T27: =Segments!Y152 -> -0.057512415 | U27: =Segments!Z152 -> 0.13821836 | V27: =Segments!AA152 -> -0.012703197 | W27: =Segments!AB152 -> 0.027259841 | Y27: =Segments!AD152 -> 0.035134274 | Z27: =Segments!AE152 -> 0.025943396 | AA27: =Segments!AF152 -> 0.062368816 | AB27: =Segments!AG152 -> 0.096528366 | AD27: =Segments!AI152 -> -0.033290433 | AE27: =Segments!AJ152 -> 0.042957309 | AF27: =Segments!AK152 -> -0.080248489 | AG27: =Segments!AL152 -> -0.01915248 | AI27: =Segments!AN152 -> 0.077351193 | AJ27: =Segments!AO152 -> 0.062603975 | AK27: =Segments!AP152 -> 0.022165458 | AL27: =Segments!AQ152 -> -0.0060459492 | AN27: =Segments!AS152 -> 0.04622871 | AO27: =Segments!AT152 -> 0.1124031 | AP27: =Segments!AU152 -> -0.055052265 | AQ27: =Segments!AV152 -> -0.048672566 | AS27: =Segments!AX152 -> 0.24031008 | AT27: =Segments!AY152 -> -0.71085459 | AU27: =Segments!AZ152 -> -0.04625 | AV27: =Segments!BA152 -> 0.0085190039 | AX27: =Segments!BC152 -> -0.011046134 | AY27: =Segments!BD152 -> -0.092641261 | AZ27: =Segments!BE152 -> -0.076755974 | BA27: =Segments!BF152 -> 0.011764706 | BC27: =Segments!BH152 -> 0.13953488 | BD27: =Segments!BI152 -> 0.016326531 | BE27: =Segments!BJ152 -> -0.014725569 | BF27: =Segments!BK152 -> 0.0054347826 | BH27: =Segments!BM152 -> 0.20675676 | BI27: =Segments!BN152 -> 0.017357223 | BJ27: =Segments!BO152 -> -0.0022014309 | BK27: =Segments!BP152 -> -0.077771649 | BM27: =Segments!BR152 -> 0.1507177 | BN27: =Segments!BS152 -> -0.013513514 | BO27: =Segments!BT152 -> 0.056074816 | BP27: =Segments!BU152 -> -0.077923365 | BR27: =Segments!BW152 -> 0.14005896 | BS27: =Segments!BX152 -> -0.024346146 | BT27: =Segments!BY152 -> 0.049428461 | BU27: =Segments!BZ152 -> -0.076488715 | BW27: =Segments!CB152 -> 0.13809975 | BX27: =Segments!CC152 -> -0.024487046 | BY27: =Segments!CD152 -> 0.049639426 | BZ27: =Segments!CE152 -> -0.076173492
B28: M&A impact % y/y | I28: =Segments!N153 -> 0.001 | J28: =Segments!O153 -> 0.014231799 | K28: =Segments!P153 -> 0.028602151 | L28: =Segments!Q153 -> 0.03611623 | M28: =Segments!R153 -> 0.031373203 | N28: =Segments!S153 -> 0.027587346 | O28: =Segments!T153 -> 0.027448384 | P28: =Segments!U153 -> 0.014224385 | ... CA28: =Segments!CF153 -> 0
B29: Organic growth % y/y | I29: =Segments!N154 -> 0.088 | J29: =Segments!O154 -> 0.038674261 | K29: =Segments!P154 -> 0.13096243 | L29: =Segments!Q154 -> 0.12065202 | M29: =Segments!R154 -> 0.094781828 | N29: =Segments!S154 -> 0.096340317 | O29: =Segments!T154 -> 0.10081022 | P29: =Segments!U154 -> 0.036834574 | ... CA29: =Segments!CF154 -> 0.076225864
B30: FX impact % y/y | I30: =Segments!N155 -> -0.001 | J30: =Segments!O155 -> 0 | K30: =Segments!P155 -> 0.015734767 | L30: =Segments!Q155 -> 0 | M30: =Segments!R155 -> -0.03 | N30: =Segments!S155 -> 0.001 | O30: =Segments!T155 -> -0.05 | P30: =Segments!U155 -> -0.052844877 | ... CA30: =Segments!CF155 -> -0.00073636048
B31: Organic constant currency growth % y/y | I31: =Segments!N156 -> 0.089 | J31: =Segments!O156 -> 0.038674261 | K31: =Segments!P156 -> 0.11522766 | L31: =Segments!Q156 -> 0.12065202 | M31: =Segments!R156 -> 0.12478183 | N31: =Segments!S156 -> 0.095340317 | O31: =Segments!T156 -> 0.15081022 | P31: =Segments!U156 -> 0.08967945 | ... CA31: =Segments!CF156 -> 0.076962225
B33: Operating and SG&A expenses | G33: =Segments!L39+Segments!L122 -> 413.2 | H33: =Segments!M39+Segments!M122 -> 468.3 | I33: =Segments!N39+Segments!N122 -> 1735.5 | J33: =Segments!O39+Segments!O122 -> 435.9 | K33: =Segments!P39+Segments!P122 -> 464.7 | L33: =Segments!Q39+Segments!Q122 -> 468.9 | M33: =Segments!R39+Segments!R122 -> 530.9 | N33: =SUM(J33:M33) -> 1900.4 | O33: =Segments!T39+Segments!T122 -> 491.6 | P33: =Segments!U39+Segments!U122 -> 497.7 | Q33: =Segments!V39+Segments!V122 -> 483.7 | R33: =Segments!W39+Segments!W122 -> 531.5 | S33: =SUM(O33:R33) -> 2004.5 | T33: =Segments!Y39+Segments!Y122 -> 508.9 | U33: =Segments!Z39+Segments!Z122 -> 514.9 | V33: =Segments!AA39+Segments!AA122 -> 508 | W33: =Segments!AB39+Segments!AB122 -> 548.5 | X33: =SUM(T33:W33) -> 2080.3 | Y33: =Segments!AD39+Segments!AD122 -> 525.7 | Z33: =Segments!AE39+Segments!AE122 -> 531.7 | AA33: =Segments!AF39+Segments!AF122 -> 594.4 | AB33: =Segments!AG39+Segments!AG122 -> 678.4 | AC33: =SUM(Y33:AB33) -> 2330.2 | AD33: =Segments!AI39+Segments!AI122 -> 620.8 | AE33: =Segments!AJ39+Segments!AJ122 -> 623.7 | AF33: =Segments!AK39+Segments!AK122 -> 600.8 | AG33: =Segments!AL39+Segments!AL122 -> 616.6 | AH33: =SUM(AD33:AG33) -> 2461.9 | AI33: =Segments!AN39+Segments!AN122 -> 657.9 | AJ33: =Segments!AO39+Segments!AO122 -> 649.8 | AK33: =Segments!AP39+Segments!AP122 -> 663 | AL33: =Segments!AQ39+Segments!AQ122 -> 711 | AM33: =SUM(AI33:AL33) -> 2681.7 | AN33: =Segments!AS39+Segments!AS122 -> 680 | AO33: =Segments!AT39+Segments!AT122 -> 706 | AP33: =Segments!AU39+Segments!AU122 -> 674 | AQ33: =Segments!AV39+Segments!AV122 -> 799 | AR33: =SUM(AN33:AQ33) -> 2859 | AS33: =Segments!AX39+Segments!AX122 -> 728 | AT33: =Segments!AY39+Segments!AY122 -> 736 | AU33: =Segments!AZ39+Segments!AZ122 -> 833 | AV33: =Segments!BA39+Segments!BA122 -> 992 | AW33: =SUM(AS33:AV33) -> 3289 | AX33: =Segments!BC39+Segments!BC122 -> 833 | AY33: =Segments!BD39+Segments!BD122 -> 805 | AZ33: =Segments!BE39+Segments!BE122 -> 823 | BA33: =Segments!BF39+Segments!BF122 -> 861 | BB33: =SUM(AX33:BA33) -> 3322 | BC33: =Segments!BH39+Segments!BH122 -> 862 | BD33: =Segments!BI39+Segments!BI122 -> 891 | BE33: =Segments!BJ39+Segments!BJ122 -> 865 | BF33: =Segments!BK39+Segments!BK122 -> 900 | BG33: =SUM(BC33:BF33) -> 3518 | BH33: =Segments!BM39+Segments!BM122 -> 930 | BI33: =Segments!BN39+Segments!BN122 -> 968 | BJ33: =Segments!BO39+Segments!BO122 -> 997 | BK33: =Segments!BP39+Segments!BP122 -> 991 | BL33: =SUM(BH33:BK33) -> 3886 | BM33: =Segments!BR39+Segments!BR122 -> 982 | BN33: =Segments!BS39+Segments!BS122 -> 985 | BO33: =Segments!BT39+Segments!BT122 -> 1003.3857 | BP33: =Segments!BU39+Segments!BU122 -> 1010.2633 | BQ33: =SUM(BM33:BP33) -> 3980.6489 | BR33: =Segments!BW39+Segments!BW122 -> 1043.7311 | BS33: =Segments!BX39+Segments!BX122 -> 1032.1743 | BT33: =Segments!BY39+Segments!BY122 -> 1070.5411 | BU33: =Segments!BZ39+Segments!BZ122 -> 1076.9449 | BV33: =SUM(BR33:BU33) -> 4223.3915 | BW33: =Segments!CB39+Segments!CB122 -> 1097.7564 | BX33: =Segments!CC39+Segments!CC122 -> 1085.525 | BY33: =Segments!CD39+Segments!CD122 -> 1128.7098 | BZ33: =Segments!CE39+Segments!CE122 -> 1136.5599 | CA33: =SUM(BW33:BZ33) -> 4448.5512
B34: % y/y | G34: =IFERROR(G33/B33-1,"NA") -> NA | H34: =IFERROR(H33/C33-1,"NA") -> NA | I34: =IFERROR(I33/D33-1,"NA") -> NA | J34: =IFERROR(J33/E33-1,"NA") -> NA | K34: =IFERROR(K33/F33-1,"NA") -> NA | L34: =IFERROR(L33/G33-1,"NA") -> 0.13480155 | M34: =IFERROR(M33/H33-1,"NA") -> 0.13367499 | N34: =IFERROR(N33/I33-1,"NA") -> 0.095015846 | ... CA34: =IFERROR(CA33/BV33-1,"NA") -> 0.053312534
B35: % revenue | G35: =G33/G$25 -> 0.58568391 | H35: =H33/H$25 -> 0.60100103 | I35: =I33/I$25 -> 0.58500329 | J35: =J33/J$25 -> 0.56816997 | K35: =K33/K$25 -> 0.53199771 | L35: =L33/L$25 -> 0.57456194 | M35: =M33/M$25 -> 0.60501425 | N35: =N33/N$25 -> 0.56995471 | ... CA35: =CA33/CA$25 -> 0.49724716
B36: Stock based comp | X36: 98.7 | Y36: 32.5 | Z36: 28.7 | AA36: 31.8 | AB36: 29.9 | AC36: 122.9 | AD36: 35.1 | AE36: 34.4 | AF36: 30.5 | AG36: 30.3 | AH36: 130.3 | AI36: 35.7 | AJ36: 34 | AK36: 31 | AL36: 30.3 | AM36: =SUM(AI36:AL36) -> 131 | AN36: ='BS & CFS'!AA45 -> 37 | AO36: ='BS & CFS'!AB45 -> 35 | AP36: ='BS & CFS'!AC45 -> 38 | AQ36: ='BS & CFS'!AD45 -> 44 | AR36: =SUM(AN36:AQ36) -> 154 | AS36: ='BS & CFS'!AF45 -> 45 | AT36: ='BS & CFS'!AG45 -> 41 | AU36: ='BS & CFS'!AH45 -> 41 | AV36: ='BS & CFS'!AI45 -> 48 | AW36: =SUM(AS36:AV36) -> 175 | AX36: ='BS & CFS'!AK45 -> 46 | AY36: ='BS & CFS'!AL45 -> 38 | AZ36: ='BS & CFS'!AM45 -> 46 | BA36: ='BS & CFS'!AN45 -> 39 | BB36: =SUM(AX36:BA36) -> 169 | BC36: ='BS & CFS'!AP45 -> 47 | BD36: ='BS & CFS'!AQ45 -> 50 | BE36: ='BS & CFS'!AR45 -> 46 | BF36: ='BS & CFS'!AS45 -> 50 | BG36: =SUM(BC36:BF36) -> 193 | BH36: ='BS & CFS'!AU45 -> 53 | BI36: ='BS & CFS'!AV45 -> 56 | BJ36: ='BS & CFS'!AW45 -> 7 | BK36: ='BS & CFS'!AX45 -> 104 | BL36: =SUM(BH36:BK36) -> 220 | BM36: ='BS & CFS'!AZ45 -> 56 | BN36: ='BS & CFS'!BA45 -> 61 | BO36: ='BS & CFS'!BB45 -> 8 | BP36: ='BS & CFS'!BC45 -> 50 | BQ36: =SUM(BM36:BP36) -> 175 | BR36: ='BS & CFS'!BE45 -> 57 | BS36: ='BS & CFS'!BF45 -> 62 | BT36: ='BS & CFS'!BG45 -> 9 | BU36: ='BS & CFS'!BH45 -> 51 | BV36: =SUM(BR36:BU36) -> 179 | BW36: ='BS & CFS'!BJ45 -> 58 | BX36: ='BS & CFS'!BK45 -> 63 | BY36: ='BS & CFS'!BL45 -> 10 | BZ36: ='BS & CFS'!BM45 -> 52 | CA36: =SUM(BW36:BZ36) -> 183
B37: D&A | G37: =Segments!L43+Segments!L126 -> 23.4 | H37: =Segments!M43+Segments!M126 -> 23.3 | I37: =Segments!N43+Segments!N126 -> 93.4 | J37: =Segments!O43+Segments!O126 -> 23.1 | K37: =Segments!P43+Segments!P126 -> 22.3 | L37: =Segments!Q43+Segments!Q126 -> 23.2 | M37: =Segments!R43+Segments!R126 -> 27 | N37: =SUM(J37:M37) -> 95.6 | O37: =Segments!T43+Segments!T126 -> 28.6 | P37: =Segments!U43+Segments!U126 -> 27.9 | Q37: =Segments!V43+Segments!V126 -> 22.8 | R37: =Segments!W43+Segments!W126 -> 28.7 | S37: =SUM(O37:R37) -> 108 | T37: =Segments!Y43+Segments!Y126 -> 29.9 | U37: =Segments!Z43+Segments!Z126 -> 31.2 | V37: =Segments!AA43+Segments!AA126 -> 32.7 | W37: =Segments!AB43+Segments!AB126 -> 32.9 | X37: =SUM(T37:W37) -> 126.7 | Y37: =Segments!AD43+Segments!AD126 -> 32.5 | Z37: =Segments!AE43+Segments!AE126 -> 32.9 | AA37: =Segments!AF43+Segments!AF126 -> 43 | AB37: =Segments!AG43+Segments!AG126 -> 49.9 | AC37: =SUM(Y37:AB37) -> 158.3 | AD37: =Segments!AI43+Segments!AI126 -> 49.1 | AE37: =Segments!AJ43+Segments!AJ126 -> 48.4 | AF37: =Segments!AK43+Segments!AK126 -> 46.1 | AG37: =Segments!AL43+Segments!AL126 -> 48.3 | AH37: =SUM(AD37:AG37) -> 191.9 | AI37: =Segments!AN43+Segments!AN126 -> 50.3 | AJ37: =Segments!AO43+Segments!AO126 -> 51 | AK37: =Segments!AP43+Segments!AP126 -> 48.6 | AL37: =Segments!AQ43+Segments!AQ126 -> 50 | AM37: =SUM(AI37:AL37) -> 199.9 | AN37: =Segments!AS43+Segments!AS126 -> 49 | AO37: =Segments!AT43+Segments!AT126 -> 58 | AP37: =Segments!AU43+Segments!AU126 -> 56 | AQ37: =Segments!AV43+Segments!AV126 -> 57 | AR37: =SUM(AN37:AQ37) -> 220 | AS37: =Segments!AX43+Segments!AX126 -> 59 | AT37: =Segments!AY43+Segments!AY126 -> 60 | AU37: =Segments!AZ43+Segments!AZ126 -> 61 | AV37: =Segments!BA43+Segments!BA126 -> 77 | AW37: =SUM(AS37:AV37) -> 257 | AX37: =Segments!BC43+Segments!BC126 -> 78 | AY37: =Segments!BD43+Segments!BD126 -> 81 | AZ37: =Segments!BE43+Segments!BE126 -> 83 | BA37: =Segments!BF43+Segments!BF126 -> 89 | BB37: =SUM(AX37:BA37) -> 331 | BC37: =Segments!BH43+Segments!BH126 -> 88 | BD37: =Segments!BI43+Segments!BI126 -> 93 | BE37: =Segments!BJ43+Segments!BJ126 -> 95 | BF37: =Segments!BK43+Segments!BK126 -> 97 | BG37: =SUM(BC37:BF37) -> 373 | BH37: =Segments!BM43+Segments!BM126 -> 100 | BI37: =Segments!BN43+Segments!BN126 -> 110 | BJ37: =Segments!BO43+Segments!BO126 -> 108 | BK37: =Segments!BP43+Segments!BP126 -> 113 | BL37: =SUM(BH37:BK37) -> 431 | BM37: =Segments!BR43+Segments!BR126 -> 113 | BN37: =Segments!BS43+Segments!BS126 -> 120 | BO37: =Segments!BT43+Segments!BT126 -> 118.25993 | BP37: =Segments!BU43+Segments!BU126 -> 124.31757 | BQ37: =SUM(BM37:BP37) -> 475.5775 | BR37: =Segments!BW43+Segments!BW126 -> 123.65775 | BS37: =Segments!BX43+Segments!BX126 -> 128.53122 | BT37: =Segments!BY43+Segments!BY126 -> 126.08826 | BU37: =Segments!BZ43+Segments!BZ126 -> 133.04267 | BV37: =SUM(BR37:BU37) -> 511.3199 | BW37: =Segments!CB43+Segments!CB126 -> 134.47246 | BX37: =Segments!CC43+Segments!CC126 -> 135.40084 | BY37: =Segments!CD43+Segments!CD126 -> 134.93682 | BZ37: =Segments!CE43+Segments!CE126 -> 142.50081 | CA37: =SUM(BW37:BZ37) -> 547.31093
B38: % y/y | G38: =IFERROR(G37/B37-1,"NA") -> NA | H38: =IFERROR(H37/C37-1,"NA") -> NA | I38: =IFERROR(I37/D37-1,"NA") -> NA | J38: =IFERROR(J37/E37-1,"NA") -> NA | K38: =IFERROR(K37/F37-1,"NA") -> NA | L38: =IFERROR(L37/G37-1,"NA") -> -0.0085470085 | M38: =IFERROR(M37/H37-1,"NA") -> 0.15879828 | N38: =IFERROR(N37/I37-1,"NA") -> 0.023554604 | ... CA38: =IFERROR(CA37/BV37-1,"NA") -> 0.070388474
B39: % revenue | G39: =G37/G$25 -> 0.033167966 | H39: =H37/H$25 -> 0.029902464 | I39: =I37/I$25 -> 0.031483323 | J39: =J37/J$25 -> 0.030109489 | K39: =K37/K$25 -> 0.025529479 | L39: =L37/L$25 -> 0.028427889 | M39: =M37/M$25 -> 0.030769231 | N39: =N37/N$25 -> 0.028671685 | ... CA39: =CA37/CA$25 -> 0.061176952
B40: M&A/Restructuring/Other | G40: =Segments!L46+Segments!L129 -> 0 | H40: =Segments!M46+Segments!M129 -> 0 | I40: =Segments!N46+Segments!N129 -> 0 | J40: =Segments!O46+Segments!O129 -> 0 | K40: =Segments!P46+Segments!P129 -> 0 | L40: =Segments!Q46+Segments!Q129 -> 0 | M40: =Segments!R46+Segments!R129 -> 0 | N40: =SUM(J40:M40) -> 0 | O40: =Segments!T46+Segments!T129 -> 0 | P40: =Segments!U46+Segments!U129 -> 0 | Q40: =Segments!V46+Segments!V129 -> 0 | R40: =Segments!W46+Segments!W129 -> 0 | S40: =SUM(O40:R40) -> 0 | T40: =Segments!Y46+Segments!Y129 -> 0 | U40: =Segments!Z46+Segments!Z129 -> 0 | V40: =Segments!AA46+Segments!AA129 -> 8.4 | W40: =Segments!AB46+Segments!AB129 -> 863.8 | X40: =SUM(T40:W40) -> 872.2 | Y40: =Segments!AD46+Segments!AD129 -> 0 | Z40: =Segments!AE46+Segments!AE129 -> 6.6 | AA40: =Segments!AF46+Segments!AF129 -> 10.1 | AB40: =Segments!AG46+Segments!AG129 -> 5.8 | AC40: =SUM(Y40:AB40) -> 22.5 | AD40: =Segments!AI46+Segments!AI129 -> 0.8 | AE40: =Segments!AJ46+Segments!AJ129 -> 2 | AF40: =Segments!AK46+Segments!AK129 -> 1.3 | AG40: =Segments!AL46+Segments!AL129 -> 52.9 | AH40: =SUM(AD40:AG40) -> 57 | AI40: =Segments!AN46+Segments!AN129 -> 6.9 | AJ40: =Segments!AO46+Segments!AO129+8.7 -> 64.5 | AK40: =Segments!AP46+Segments!AP129 -> 16.5 | AL40: =Segments!AQ46+Segments!AQ129 -> 5 | AM40: =SUM(AI40:AL40) -> 92.9 | AN40: =Segments!AS46+Segments!AS129 -> 8 | AO40: =Segments!AT46+Segments!AT129 -> -2 | AP40: =Segments!AU46+Segments!AU129 -> 23 | AQ40: =Segments!AV46+Segments!AV129 -> 30 | AR40: =SUM(AN40:AQ40) -> 59 | AS40: =Segments!AX46+Segments!AX129 -> 2 | AT40: =Segments!AY46+Segments!AY129 -> 0 | AU40: =Segments!AZ46+Segments!AZ129 -> 0 | AV40: =Segments!BA46+Segments!BA129 -> -2 | AW40: =SUM(AS40:AV40) -> 0 | AX40: =Segments!BC46+Segments!BC129 -> 0 | AY40: =Segments!BD46+Segments!BD129 -> 31 | AZ40: =Segments!BE46+Segments!BE129 -> 1 | BA40: =Segments!BF46+Segments!BF129 -> 82 | BB40: =SUM(AX40:BA40) -> 114 | BC40: =Segments!BH46+Segments!BH129 -> 14 | BD40: =Segments!BI46+Segments!BI129 -> 10 | BE40: =Segments!BJ46+Segments!BJ129 -> 27 | BF40: =Segments!BK46+Segments!BK129 -> 36 | BG40: =SUM(BC40:BF40) -> 87 | BH40: =Segments!BM46+Segments!BM129 -> 5 | BI40: =Segments!BN46+Segments!BN129 -> 17 | BJ40: =Segments!BO46+Segments!BO129 -> 21 | BK40: =Segments!BP46+Segments!BP129 -> 59 | BL40: =SUM(BH40:BK40) -> 102 | BM40: =Segments!BR46+Segments!BR129 -> 35 | BN40: =Segments!BS46+Segments!BS129 -> 28 | BO40: =Segments!BT46+Segments!BT129 -> 14 | BP40: =Segments!BU46+Segments!BU129 -> 14 | BQ40: =SUM(BM40:BP40) -> 91 | BR40: =Segments!BW46+Segments!BW129 -> 21 | BS40: =Segments!BX46+Segments!BX129 -> 21 | BT40: =Segments!BY46+Segments!BY129 -> 21 | BU40: =Segments!BZ46+Segments!BZ129 -> 21 | BV40: =SUM(BR40:BU40) -> 84 | BW40: =Segments!CB46+Segments!CB129 -> 0 | BX40: =Segments!CC46+Segments!CC129 -> 0 | BY40: =Segments!CD46+Segments!CD129 -> 0 | BZ40: =Segments!CE46+Segments!CE129 -> 0 | CA40: =SUM(BW40:BZ40) -> 0
B41: % revenue | G41: =G40/G$25 -> 0 | H41: =H40/H$25 -> 0 | I41: =I40/I$25 -> 0 | J41: =J40/J$25 -> 0 | K41: =K40/K$25 -> 0 | L41: =L40/L$25 -> 0 | M41: =M40/M$25 -> 0 | N41: =N40/N$25 -> 0 | ... CA41: =CA40/CA$25 -> 0
B42: Intercompany eliminations | G42: =Segments!L142+Segments!L59 -> 22.6 | H42: =Segments!M142+Segments!M59 -> 24.3 | I42: =Segments!N142+Segments!N59 -> 91 | J42: =Segments!O142+Segments!O59 -> 24.8 | K42: =Segments!P142+Segments!P59 -> 25.2 | L42: =Segments!Q142+Segments!Q59 -> 25.7 | M42: =Segments!R142+Segments!R59 -> 25.1 | N42: =SUM(J42:M42) -> 100.8 | O42: =Segments!T142+Segments!T59 -> 25.6 | P42: =Segments!U142+Segments!U59 -> 26.8 | Q42: =Segments!V142+Segments!V59 -> 26.8 | R42: =Segments!W142+Segments!W59 -> 27.4 | S42: =SUM(O42:R42) -> 106.6 | T42: =Segments!Y142+Segments!Y59 -> 26.8 | U42: =Segments!Z142+Segments!Z59 -> 27.4 | V42: =Segments!AA142+Segments!AA59 -> 27.7 | W42: =Segments!AB142+Segments!AB59 -> 30 | X42: =SUM(T42:W42) -> 111.9 | Y42: =Segments!AD142+Segments!AD59 -> 29.7 | Z42: =Segments!AE142+Segments!AE59 -> 30.8 | AA42: =Segments!AF142+Segments!AF59 -> 33.1 | AB42: =Segments!AG142+Segments!AG59 -> 34.1 | AC42: =SUM(Y42:AB42) -> 127.7 | AD42: =Segments!AI142+Segments!AI59 -> 34.8 | AE42: =Segments!AJ142+Segments!AJ59 -> 33 | AF42: =Segments!AK142+Segments!AK59 -> 34.2 | AG42: =Segments!AL142+Segments!AL59 -> 34.3 | AH42: =SUM(AD42:AG42) -> 136.3 | AI42: =Segments!AN142+Segments!AN59 -> 34.7 | AJ42: =Segments!AO142+Segments!AO59 -> 35.2 | AK42: =Segments!AP142+Segments!AP59 -> 36.4 | AL42: =Segments!AQ142+Segments!AQ59 -> 37 | AM42: =SUM(AI42:AL42) -> 143.3 | AN42: =Segments!AS142+Segments!AS59 -> 39 | AO42: =Segments!AT142+Segments!AT59 -> 37 | AP42: =Segments!AU142+Segments!AU59 -> 39 | AQ42: =Segments!AV142+Segments!AV59 -> 40 | AR42: =SUM(AN42:AQ42) -> 155 | AS42: =Segments!AX142+Segments!AX59 -> 42 | AT42: =Segments!AY142+Segments!AY59 -> 44 | AU42: =Segments!AZ142+Segments!AZ59 -> 44 | AV42: =Segments!BA142+Segments!BA59 -> 42 | AW42: =SUM(AS42:AV42) -> 172 | AX42: =Segments!BC142+Segments!BC59 -> 45 | AY42: =Segments!BD142+Segments!BD59 -> 44 | AZ42: =Segments!BE142+Segments!BE59 -> 45 | BA42: =Segments!BF142+Segments!BF59 -> 48 | BB42: =SUM(AX42:BA42) -> 182 | BC42: =Segments!BH142+Segments!BH59 -> 48 | BD42: =Segments!BI142+Segments!BI59 -> 50 | BE42: =Segments!BJ142+Segments!BJ59 -> 50 | BF42: =Segments!BK142+Segments!BK59 -> 51 | BG42: =SUM(BC42:BF42) -> 199 | BH42: =Segments!BM142+Segments!BM59 -> 50 | BI42: =Segments!BN142+Segments!BN59 -> 53 | BJ42: =Segments!BO142+Segments!BO59 -> 51 | BK42: =Segments!BP142+Segments!BP59 -> 52 | BL42: =SUM(BH42:BK42) -> 206 | BM42: =Segments!BR142+Segments!BR59 -> 52 | BN42: =Segments!BS142+Segments!BS59 -> 53 | BO42: =Segments!BT142+Segments!BT59 -> 52 | BP42: =Segments!BU142+Segments!BU59 -> 53 | BQ42: =SUM(BM42:BP42) -> 210 | BR42: =Segments!BW142+Segments!BW59 -> 53 | BS42: =Segments!BX142+Segments!BX59 -> 54 | BT42: =Segments!BY142+Segments!BY59 -> 53 | BU42: =Segments!BZ142+Segments!BZ59 -> 54 | BV42: =SUM(BR42:BU42) -> 214 | BW42: =Segments!CB142+Segments!CB59 -> 54 | BX42: =Segments!CC142+Segments!CC59 -> 55 | BY42: =Segments!CD142+Segments!CD59 -> 54 | BZ42: =Segments!CE142+Segments!CE59 -> 55 | CA42: =SUM(BW42:BZ42) -> 218
B43: Total operating expenses | G43: =G40+G37+G33-G42 -> 414 | H43: =H40+H37+H33-H42 -> 467.3 | I43: =I40+I37+I33-I42 -> 1737.9 | J43: =J40+J37+J33-J42 -> 434.2 | K43: =K40+K37+K33-K42 -> 461.8 | L43: =L40+L37+L33-L42 -> 466.4 | M43: =M40+M37+M33-M42 -> 532.8 | N43: =SUM(J43:M43) -> 1895.2 | O43: =O40+O37+O33-O42 -> 494.6 | P43: =P40+P37+P33-P42 -> 498.8 | Q43: =Q40+Q37+Q33-Q42 -> 479.7 | R43: =R40+R37+R33-R42 -> 532.8 | S43: =SUM(O43:R43) -> 2005.9 | T43: =T40+T37+T33-T42 -> 512 | U43: =U40+U37+U33-U42 -> 518.7 | V43: =V40+V37+V33-V42 -> 521.4 | W43: =W40+W37+W33-W42 -> 1415.2 | X43: =SUM(T43:W43) -> 2967.3 | Y43: =Y40+Y37+Y33-Y42 -> 528.5 | Z43: =Z40+Z37+Z33-Z42 -> 540.4 | AA43: =AA40+AA37+AA33-AA42 -> 614.4 | AB43: =AB40+AB37+AB33-AB42 -> 700 | AC43: =SUM(Y43:AB43) -> 2383.3 | AD43: =AD40+AD37+AD33-AD42 -> 635.9 | AE43: =AE40+AE37+AE33-AE42 -> 641.1 | AF43: =AF40+AF37+AF33-AF42 -> 614 | AG43: =AG40+AG37+AG33-AG42 -> 683.5 | AH43: =SUM(AD43:AG43) -> 2574.5 | AI43: =AI40+AI37+AI33-AI42 -> 680.4 | AJ43: =AJ40+AJ37+AJ33-AJ42 -> 730.1 | AK43: =AK40+AK37+AK33-AK42 -> 691.7 | AL43: =AL40+AL37+AL33-AL42 -> 729 | AM43: =SUM(AI43:AL43) -> 2831.2 | AN43: =AN40+AN37+AN33-AN42 -> 698 | AO43: =AO40+AO37+AO33-AO42 -> 725 | AP43: =AP40+AP37+AP33-AP42 -> 714 | AQ43: =AQ40+AQ37+AQ33-AQ42 -> 846 | AR43: =SUM(AN43:AQ43) -> 2983 | AS43: =AS40+AS37+AS33-AS42 -> 747 | AT43: =AT40+AT37+AT33-AT42 -> 752 | AU43: =AU40+AU37+AU33-AU42 -> 850 | AV43: =AV40+AV37+AV33-AV42 -> 1025 | AW43: =SUM(AS43:AV43) -> 3374 | AX43: =AX40+AX37+AX33-AX42 -> 866 | AY43: =AY40+AY37+AY33-AY42 -> 873 | AZ43: =AZ40+AZ37+AZ33-AZ42 -> 862 | BA43: =BA40+BA37+BA33-BA42 -> 984 | BB43: =SUM(AX43:BA43) -> 3585 | BC43: =BC40+BC37+BC33-BC42 -> 916 | BD43: =BD40+BD37+BD33-BD42 -> 944 | BE43: =BE40+BE37+BE33-BE42 -> 937 | BF43: =BF40+BF37+BF33-BF42 -> 982 | BG43: =SUM(BC43:BF43) -> 3779 | BH43: =BH40+BH37+BH33-BH42 -> 985 | BI43: =BI40+BI37+BI33-BI42 -> 1042 | BJ43: =BJ40+BJ37+BJ33-BJ42 -> 1075 | BK43: =BK40+BK37+BK33-BK42 -> 1111 | BL43: =SUM(BH43:BK43) -> 4213 | BM43: =BM40+BM37+BM33-BM42 -> 1078 | BN43: =BN40+BN37+BN33-BN42 -> 1080 | BO43: =BO40+BO37+BO33-BO42 -> 1083.6456 | BP43: =BP40+BP37+BP33-BP42 -> 1095.5808 | BQ43: =SUM(BM43:BP43) -> 4337.2264 | BR43: =BR40+BR37+BR33-BR42 -> 1135.3889 | BS43: =BS40+BS37+BS33-BS42 -> 1127.7055 | BT43: =BT40+BT37+BT33-BT42 -> 1164.6294 | BU43: =BU40+BU37+BU33-BU42 -> 1176.9876 | BV43: =SUM(BR43:BU43) -> 4604.7114 | BW43: =BW40+BW37+BW33-BW42 -> 1178.2289 | BX43: =BX40+BX37+BX33-BX42 -> 1165.9259 | BY43: =BY40+BY37+BY33-BY42 -> 1209.6466 | BZ43: =BZ40+BZ37+BZ33-BZ42 -> 1224.0607 | CA43: =SUM(BW43:BZ43) -> 4777.8621
B44: % y/y | G44: =IFERROR(G43/B43-1, "NA") -> NA | H44: =IFERROR(H43/C43-1, "NA") -> NA | I44: =IFERROR(I43/D43-1, "NA") -> NA | J44: =IFERROR(J43/E43-1, "NA") -> NA | K44: =IFERROR(K43/F43-1, "NA") -> NA | L44: =IFERROR(L43/G43-1, "NA") -> 0.12657005 | M44: =IFERROR(M43/H43-1, "NA") -> 0.14016692 | N44: =IFERROR(N43/I43-1, "NA") -> 0.090511537 | ... CA44: =IFERROR(CA43/BV43-1, "NA") -> 0.03760295
B45: % revenue | G45: =G43/G25 -> 0.58681786 | H45: =H43/H25 -> 0.59971766 | I45: =I43/I25 -> 0.58581228 | J45: =J43/J25 -> 0.56595412 | K45: =K43/K25 -> 0.52867773 | L45: =L43/L25 -> 0.57149859 | M45: =M43/M25 -> 0.60717949 | N45: =N43/N25 -> 0.56839517 | ... CA45: =CA43/CA25 -> 0.53405665
BG46: `
B47: Total operating income (GAAP) | G47: =G25-G43 -> 291.5 | H47: =H25-H43 -> 311.9 | I47: =I25-I43 -> 1228.75 | J47: =J25-J43 -> 333 | K47: =K25-K43 -> 411.7 | L47: =L25-L43 -> 349.7 | M47: =M25-M43 -> 344.7 | N47: =N25-N43 -> 1439.1 | ... CA47: =CA25-CA43 -> 4168.4961
B48: % y/y | G48: =IFERROR(G47/B47-1, "NA") -> NA | H48: =IFERROR(H47/C47-1, "NA") -> NA | I48: =IFERROR(I47/D47-1, "NA") -> NA | J48: =IFERROR(J47/E47-1, "NA") -> NA | K48: =IFERROR(K47/F47-1, "NA") -> NA | L48: =IFERROR(L47/G47-1, "NA") -> 0.19965695 | M48: =IFERROR(M47/H47-1, "NA") -> 0.10516191 | N48: =IFERROR(N47/I47-1, "NA") -> 0.17119023 | ... CA48: =IFERROR(CA47/BV47-1, "NA") -> 0.12418898
B49: % margin | G49: =IFERROR(G47/G25,"NA") -> 0.41318214 | H49: =IFERROR(H47/H25,"NA") -> 0.40028234 | I49: =IFERROR(I47/I25,"NA") -> 0.41418772 | J49: =IFERROR(J47/J25,"NA") -> 0.43404588 | K49: =IFERROR(K47/K25,"NA") -> 0.47132227 | L49: =IFERROR(L47/L25,"NA") -> 0.42850141 | M49: =IFERROR(M47/M25,"NA") -> 0.39282051 | N49: =IFERROR(N47/N25,"NA") -> 0.43160483 | ... CA49: =IFERROR(CA47/CA25,"NA") -> 0.46594335
B50: margin y/y (bps) | I50: =IFERROR((I49-D49)*10000,"NA") -> 4141.8772 | J50: =IFERROR((J49-E49)*10000,"NA") -> 4340.4588 | K50: =IFERROR((K49-F49)*10000,"NA") -> 4713.2227 | L50: =IFERROR((L49-G49)*10000,"NA") -> 153.19269 | M50: =IFERROR((M49-H49)*10000,"NA") -> -74.61828 | N50: =IFERROR((N49-I49)*10000,"NA") -> 174.17114 | O50: =IFERROR((O49-J49)*10000,"NA") -> -54.414449 | P50: =IFERROR((P49-K49)*10000,"NA") -> -146.18204 | ... CA50: =IFERROR((CA49-BV49)*10000,"NA") -> 198.79304
B51: margin sequential (bps) | I51: =IFERROR((I49-H49)*10000,"NA") -> 139.05379 | J51: =IFERROR((J49-H49)*10000,"NA") -> 337.6354 | K51: =IFERROR((K49-J49)*10000,"NA") -> 372.76386 | L51: =IFERROR((L49-K49)*10000,"NA") -> -428.20858 | M51: =IFERROR((M49-L49)*10000,"NA") -> -356.80896 | O51: =IFERROR((O49-M49)*10000,"NA") -> 357.83923 | P51: =IFERROR((P49-O49)*10000,"NA") -> 280.99627 | Q51: =IFERROR((Q49-P49)*10000,"NA") -> -312.6389 | R51: =IFERROR((R49-Q49)*10000,"NA") -> -407.53719 | T51: =IFERROR((T49-R49)*10000,"NA") -> -120.6055 | U51: =IFERROR((U49-T49)*10000,"NA") -> 689.71685 | V51: =IFERROR((V49-U49)*10000,"NA") -> -101.28828 | W51: =IFERROR((W49-V49)*10000,"NA") -> -9336.4475 | Y51: =IFERROR((Y49-W49)*10000,"NA") -> 9602.3587 | Z51: =IFERROR((Z49-Y49)*10000,"NA") -> 18.101798 | AA51: =IFERROR((AA49-Z49)*10000,"NA") -> -379.11273 | AB51: =IFERROR((AB49-AA49)*10000,"NA") -> -225.59393 | AD51: =IFERROR((AD49-AB49)*10000,"NA") -> 362.09015 | AE51: =IFERROR((AE49-AD49)*10000,"NA") -> 188.20996 | AF51: =IFERROR((AF49-AE49)*10000,"NA") -> -225.27116 | AG51: =IFERROR((AG49-AF49)*10000,"NA") -> -766.5279 | AI51: =IFERROR((AI49-AG49)*10000,"NA") -> 490.05814 | AJ51: =IFERROR((AJ49-AI49)*10000,"NA") -> -58.538689 | AK51: =IFERROR((AK49-AJ49)*10000,"NA") -> 440.00807 | AL51: =IFERROR((AL49-AK49)*10000,"NA") -> -336.43133 | AN51: =IFERROR((AN49-AL49)*10000,"NA") -> 501.55605 | AO51: =IFERROR((AO49-AN49)*10000,"NA") -> 358.5879 | AP51: =IFERROR((AP49-AO49)*10000,"NA") -> -213.22192 | AQ51: =IFERROR((AQ49-AP49)*10000,"NA") -> -1292.6528 | AS51: =IFERROR((AS49-AQ49)*10000,"NA") -> 1889.3895 | AT51: =IFERROR((AT49-AS49)*10000,"NA") -> -173.49082 | AU51: =IFERROR((AU49-AT49)*10000,"NA") -> -727.87713 | AV51: =IFERROR((AV49-AU49)*10000,"NA") -> -1090.051 | AX51: =IFERROR((AX49-AV49)*10000,"NA") -> 970.28721 | AY51: =IFERROR((AY49-AX49)*10000,"NA") -> -631.62442 | AZ51: =IFERROR((AZ49-AY49)*10000,"NA") -> -439.27816 | BA51: =IFERROR((BA49-AZ49)*10000,"NA") -> -867.12266 | BC51: =IFERROR((BC49-BA49)*10000,"NA") -> 1396.6145 | BD51: =IFERROR((BD49-BC49)*10000,"NA") -> -87.315247 | BE51: =IFERROR((BE49-BD49)*10000,"NA") -> -46.881366 | BF51: =IFERROR((BF49-BE49)*10000,"NA") -> -269.646 | BH51: =IFERROR((BH49-BF49)*10000,"NA") -> 1120.0176 | BI51: =IFERROR((BI49-BH49)*10000,"NA") -> -219.60999 | BJ51: =IFERROR((BJ49-BI49)*10000,"NA") -> -194.67121 | BK51: =IFERROR((BK49-BJ49)*10000,"NA") -> -715.33806 | BM51: =IFERROR((BM49-BK49)*10000,"NA") -> 1041.8262 | BN51: =IFERROR((BN49-BM49)*10000,"NA") -> -87.289608 | BO51: =IFERROR((BO49-BN49)*10000,"NA") -> 283.94713 | BP51: =IFERROR((BP49-BO49)*10000,"NA") -> -521.451 | BR51: =IFERROR((BR49-BP49)*10000,"NA") -> 539.30924 | BS51: =IFERROR((BS49-BR49)*10000,"NA") -> -97.086158 | BT51: =IFERROR((BT49-BS49)*10000,"NA") -> 87.219611 | BU51: =IFERROR((BU49-BT49)*10000,"NA") -> -509.13146 | BW51: =IFERROR((BW49-BU49)*10000,"NA") -> 711.34295 | BX51: =IFERROR((BX49-BW49)*10000,"NA") -> -74.810725 | BY51: =IFERROR((BY49-BX49)*10000,"NA") -> 60.965457 | BZ51: =IFERROR((BZ49-BY49)*10000,"NA") -> -496.77786
B53: Other income, net | T53: 0 | U53: 0 | V53: 1 | W53: 0 | Y53: -7.7 | Z53: 10.4 | AA53: 0.5 | AB53: 0.5 | AC53: =SUM(Y53:AB53) -> 3.7 | AD53: 1 | AE53: 14.9 | AF53: 2.4 | AG53: 0.5 | AH53: =SUM(AD53:AG53) -> 18.8 | AI53: 0 | AJ53: 0 | AK53: 0 | AL53: 0 | AM53: =SUM(AI53:AL53) -> 0 | AN53: 0 | AO53: 0 | AP53: 0 | AQ53: 1 | AR53: =SUM(AN53:AQ53) -> 1 | AS53: 0 | AT53: 0 | AU53: 0 | AV53: 0 | AW53: =SUM(AS53:AV53) -> 0 | AX53: 0 | AY53: 0 | AZ53: 0 | BA53: 70 | BB53: =SUM(AX53:BA53) -> 70 | BC53: 0 | BD53: 13 | BE53: 18 | BF53: 18 | BG53: =SUM(BC53:BF53) -> 49 | BH53: 13 | BI53: 7 | BJ53: 25 | BK53: 16 | BL53: =SUM(BH53:BK53) -> 61 | BM53: 19 | BN53: 15 | BO53: 15 | BP53: 8 | BQ53: =SUM(BM53:BP53) -> 57 | BR53: =BM53+1 -> 20 | BS53: =BN53+1 -> 16 | BT53: =BO53+1 -> 16 | BU53: =BP53+1 -> 9 | BV53: =SUM(BR53:BU53) -> 61 | BW53: =BR53+1 -> 21 | BX53: =BS53+1 -> 17 | BY53: =BT53+1 -> 17 | BZ53: =BU53+1 -> 10 | CA53: =SUM(BW53:BZ53) -> 65
B54: Interest expense, net | T54: 40.4 | U54: 42.1 | V54: 39 | W54: 38 | Y54: -47.4 | Z54: -49.7 | AA54: -53.1 | AB54: -58.3 | AC54: =SUM(Y54:AB54) -> -208.5 | AD54: -50.7 | AE54: -53.4 | AF54: -56.4 | AG54: -55.5 | AH54: =SUM(AD54:AG54) -> -216 | AI54: -50.2 | AJ54: -50.6 | AK54: -45.9 | AL54: -59 | AM54: =SUM(AI54:AL54) -> -205.7 | AN54: -40 | AO54: -60 | AP54: -53 | AQ54: -52 | AR54: =SUM(AN54:AQ54) -> -205 | AS54: -7 | AT54: -49 | AU54: -53 | AV54: -62 | AW54: =SUM(AS54:AV54) -> -171 | AX54: -53 | AY54: -55 | AZ54: -58 | BA54: -65 | BB54: =SUM(AX54:BA54) -> -231 | BC54: -48 | BD54: -71 | BE54: -66 | BF54: -66 | BG54: =SUM(BC54:BF54) -> -251 | BH54: -62 | BI54: -63 | BJ54: -60 | BK54: -52 | BL54: =SUM(BH54:BK54) -> -237 | BM54: -61 | BN54: -61 | BO54: ='BS & CFS'!BB138 -> -58.066523 | BP54: ='BS & CFS'!BC138 -> -58.133123 | BQ54: =SUM(BM54:BP54) -> -238.19965 | BR54: ='BS & CFS'!BE138 -> -58.133123 | BS54: ='BS & CFS'!BF138 -> -58.133123 | BT54: ='BS & CFS'!BG138 -> -58.133123 | BU54: ='BS & CFS'!BH138 -> -58.133123 | BV54: =SUM(BR54:BU54) -> -232.53249 | BW54: ='BS & CFS'!BJ138 -> -58.133123 | BX54: ='BS & CFS'!BK138 -> -58.133123 | BY54: ='BS & CFS'!BL138 -> -58.133123 | BZ54: ='BS & CFS'!BM138 -> -58.133123 | CA54: =SUM(BW54:BZ54) -> -232.53249
B55: Other | Y55: 59.7 | Z55: 41.2 | AA55: 69.9 | AB55: 0 | AC55: =SUM(Y55:AB55) -> 170.8 | AD55: 0 | AE55: 0 | AF55: 0 | AG55: 0 | AH55: =SUM(AD55:AG55) -> 0 | AI55: 0 | AJ55: 0.4 | AK55: 9.9 | AL55: 7 | AM55: =SUM(AI55:AL55) -> 17.3 | AN55: 12 | AO55: 16 | AP55: 10 | AQ55: 8 | AR55: =SUM(AN55:AQ55) -> 46 | AS55: 16 | AT55: 6 | AU55: -4 | AV55: 64 | AW55: =SUM(AS55:AV55) -> 82 | AX55: 6 | AY55: -10 | AZ55: 26 | BA55: 16 | BB55: =SUM(AX55:BA55) -> 38 | BC55: 0 | BD55: 0 | BE55: 0 | BF55: 0 | BG55: =SUM(BC55:BF55) -> 0 | BH55: 0 | BI55: 0 | BJ55: 0 | BK55: 0 | BL55: =SUM(BH55:BK55) -> 0 | BM55: 0 | BN55: 0 | BO55: 0 | BP55: -14 | BQ55: =SUM(BM55:BP55) -> -14 | BR55: 0 | BS55: 0 | BT55: 0 | BU55: 0 | BV55: =SUM(BR55:BU55) -> 0 | BW55: 0 | BX55: 0 | BY55: 0 | BZ55: 0 | CA55: =SUM(BW55:BZ55) -> 0
B56: Income before taxes | Y56: =Y47+SUM(Y53:Y55) -> 451.3 | Z56: =Z47+SUM(Z53:Z55) -> 462 | AA56: =AA47+SUM(AA53:AA55) -> 465.8 | AB56: =AB47+SUM(AB53:AB55) -> 407.7 | AC56: =SUM(Y56:AB56) -> 1786.8 | AD56: =AD47+SUM(AD53:AD55) -> 441.1 | AE56: =AE47+SUM(AE53:AE55) -> 495.5 | AF56: =AF47+SUM(AF53:AF55) -> 412.8 | AG56: =AG47+SUM(AG53:AG55) -> 321.6 | AH56: =SUM(AD56:AG56) -> 1671 | AI56: =AI47+SUM(AI53:AI55) -> 411.5 | AJ56: =AJ47+SUM(AJ53:AJ55) -> 433.3 | AK56: =AK47+SUM(AK53:AK55) -> 512.8 | AL56: =AL47+SUM(AL53:AL55) -> 452 | AM56: =SUM(AI56:AL56) -> 1809.6 | AN56: =AN47+SUM(AN53:AN55) -> 564 | AO56: =AO47+SUM(AO53:AO55) -> 666 | AP56: =AP47+SUM(AP53:AP55) -> 599 | AQ56: =AQ47+SUM(AQ53:AQ55) -> 401 | AR56: =SUM(AN56:AQ56) -> 2230 | AS56: =AS47+SUM(AS53:AS55) -> 862 | AT56: =AT47+SUM(AT53:AT55) -> 758 | AU56: =AU47+SUM(AU53:AU55) -> 619 | AV56: =AV47+SUM(AV53:AV55) -> 516 | AW56: =SUM(AS56:AV56) -> 2755 | AX56: =AX47+SUM(AX53:AX55) -> 609 | AY56: =AY47+SUM(AY53:AY55) -> 443 | AZ56: =AZ47+SUM(AZ53:AZ55) -> 381 | BA56: =BA47+SUM(BA53:BA55) -> 327 | BB56: =SUM(AX56:BA56) -> 1760 | BC56: =BC47+SUM(BC53:BC55) -> 506 | BD56: =BD47+SUM(BD53:BD55) -> 492 | BE56: =BE47+SUM(BE53:BE55) -> 487 | BF56: =BF47+SUM(BF53:BF55) -> 450 | BG56: =SUM(BC56:BF56) -> 1935 | BH56: =BH47+SUM(BH53:BH55) -> 752 | BI56: =BI47+SUM(BI53:BI55) -> 719 | BJ56: =BJ47+SUM(BJ53:BJ55) -> 703 | BK56: =BK47+SUM(BK53:BK55) -> 525 | BL56: =SUM(BH56:BK56) -> 2699 | BM56: =BM47+SUM(BM53:BM55) -> 804 | BN56: =BN47+SUM(BN53:BN55) -> 772 | BO56: =BO47+SUM(BO53:BO55) -> 877.71789 | BP56: =BP47+SUM(BP53:BP55) -> 688.52411 | BQ56: =SUM(BM56:BP56) -> 3142.242 | BR56: =BR47+SUM(BR53:BR55) -> 933.57837 | BS56: =BS47+SUM(BS53:BS55) -> 885.96196 | BT56: =BT47+SUM(BT53:BT55) -> 950.65317 | BU56: =BU47+SUM(BU53:BU55) -> 766.27699 | BV56: =SUM(BR56:BU56) -> 3536.4705 | BW56: =BW47+SUM(BW53:BW55) -> 1052.1853 | BX56: =BX47+SUM(BX53:BX55) -> 1004.9628 | BY56: =BY47+SUM(BY53:BY55) -> 1071.0455 | BZ56: =BZ47+SUM(BZ53:BZ55) -> 872.76995 | CA56: =SUM(BW56:BZ56) -> 4000.9636
B58: Provision for income tax | T58: 161.4 | U58: 196 | V58: 187.4 | W58: 184.5 | X58: =SUM(T58:W58) -> 729.3 | Y58: 105.4 | Z58: 148.4 | AA58: 146.1 | AB58: 379.2 | AC58: =SUM(Y58:AB58) -> 779.1 | AD58: 64.3 | AE58: 117.6 | AF58: 100.8 | AG58: 68.9 | AH58: =SUM(AD58:AG58) -> 351.6 | AI58: 37.9 | AJ58: 121.3 | AK58: 130.4 | AL58: 91 | AM58: =SUM(AI58:AL58) -> 380.6 | AN58: 77 | AO58: 157 | AP58: 132 | AQ58: 86 | AR58: =SUM(AN58:AQ58) -> 452 | AS58: 126 | AT58: 181 | AU58: 145 | AV58: 89 | AW58: =SUM(AS58:AV58) -> 541 | AX58: 111 | AY58: 116 | AZ58: 78 | BA58: 81 | BB58: =SUM(AX58:BA58) -> 386 | BC58: 5 | BD58: 115 | BE58: 97 | BF58: 110 | BG58: =SUM(BC58:BF58) -> 327 | BH58: 175 | BI58: 166 | BJ58: 169 | BK58: 130 | BL58: =SUM(BH58:BK58) -> 640 | BM58: 179 | BN58: 193 | BO58: =BO59*BO56 -> 157.98922 | BP58: =BP59*BP56 -> 123.93434 | BQ58: =SUM(BM58:BP58) -> 653.92356 | BR58: =BR59*BR56 -> 214.72303 | BS58: =BS59*BS56 -> 208.20106 | BT58: =BT59*BT56 -> 228.15676 | BU58: =BU59*BU56 -> 187.73786 | BV58: =SUM(BR58:BU58) -> 838.81871 | BW58: =BW59*BW56 -> 247.26355 | BX58: =BX59*BX56 -> 236.16626 | BY58: =BY59*BY56 -> 257.05093 | BZ58: =BZ59*BZ56 -> 213.82864 | CA58: =SUM(BW58:BZ58) -> 954.30937
B59: GAAP tax rate | Y59: =Y58/Y56 -> 0.23354753 | Z59: =Z58/Z56 -> 0.32121212 | AA59: =AA58/AA56 -> 0.31365393 | AB59: =AB58/AB56 -> 0.93009566 | AC59: =AC58/AC56 -> 0.43603089 | AD59: =AD58/AD56 -> 0.14577193 | AE59: =AE58/AE56 -> 0.23733602 | AF59: =AF58/AF56 -> 0.24418605 | ... BN59: =BN58/BN56 -> 0.25 | BO59: 0.18 | BP59: 0.18 | BQ59: =BQ58/BQ56 -> 0.20810732 | BR59: 0.23 | BS59: 0.235 | BT59: 0.24 | BU59: 0.245 | BV59: =BV58/BV56 -> 0.23719093 | BW59: 0.235 | BX59: 0.235 | BY59: 0.24 | BZ59: 0.245 | CA59: =CA58/CA56 -> 0.23851988
B60: Non-controlling interests | T60: 29 | U60: 29.5 | V60: 31 | W60: 32.5 | Y60: 0.3 | Z60: 1.4 | AA60: 2.4 | AB60: 3 | AC60: =SUM(Y60:AB60) -> 7.1 | AD60: 3.9 | AE60: 1.7 | AF60: 1.8 | AG60: 2.4 | AH60: =SUM(AD60:AG60) -> 9.8 | AI60: 0.7 | AJ60: 1.7 | AK60: 3 | AL60: 2 | AM60: =SUM(AI60:AL60) -> 7.4 | AN60: -0.4 | AO60: 0 | AP60: 0 | AQ60: 1 | AR60: =SUM(AN60:AQ60) -> 0.6 | AS60: 0 | AT60: 0 | AU60: 0 | AV60: 0 | AW60: =SUM(AS60:AV60) -> 0 | AX60: 0 | AY60: 0 | AZ60: 0 | BA60: 0 | BB60: =SUM(AX60:BA60) -> 0 | BC60: 0 | BD60: 0 | BE60: 1 | BF60: 0 | BG60: =SUM(BC60:BF60) -> 1 | BH60: 0 | BI60: 1 | BJ60: 0 | BK60: 0 | BL60: =SUM(BH60:BK60) -> 1 | BM60: 0 | BN60: 1 | BO60: =BN60 -> 1 | BP60: =BO60 -> 1 | BQ60: =SUM(BM60:BP60) -> 3 | BR60: =BP60 -> 1 | BS60: =BR60 -> 1 | BT60: =BS60 -> 1 | BU60: =BT60 -> 1 | BV60: =SUM(BR60:BU60) -> 4 | BW60: =BU60 -> 1 | BX60: =BW60 -> 1 | BY60: =BX60 -> 1 | BZ60: =BY60 -> 1 | CA60: =SUM(BW60:BZ60) -> 4
B62: GAAP Net income attributable to MCO | Y62: =Y56-Y58-Y60 -> 345.6 | Z62: =Z56-Z58-Z60 -> 312.2 | AA62: =AA56-AA58-AA60 -> 317.3 | AB62: =AB56-AB58-AB60 -> 25.5 | AC62: =SUM(Y62:AB62) -> 1000.6 | AD62: =AD56-AD58-AD60 -> 372.9 | AE62: =AE56-AE58-AE60 -> 376.2 | AF62: =AF56-AF58-AF60 -> 310.2 | AG62: =AG56-AG58-AG60 -> 250.3 | AH62: =SUM(AD62:AG62) -> 1309.6 | AI62: =AI56-AI58-AI60 -> 372.9 | AJ62: =AJ56-AJ58-AJ60 -> 310.3 | AK62: =AK56-AK58-AK60 -> 379.4 | AL62: =AL56-AL58-AL60 -> 359 | AM62: =SUM(AI62:AL62) -> 1421.6 | AN62: =AN56-AN58-AN60 -> 487.4 | AO62: =AO56-AO58-AO60 -> 509 | AP62: =AP56-AP58-AP60 -> 467 | AQ62: =AQ56-AQ58-AQ60 -> 314 | AR62: =SUM(AN62:AQ62) -> 1777.4 | AS62: =AS56-AS58-AS60 -> 736 | AT62: =AT56-AT58-AT60 -> 577 | AU62: =AU56-AU58-AU60 -> 474 | AV62: =AV56-AV58-AV60 -> 427 | AW62: =SUM(AS62:AV62) -> 2214 | AX62: =AX56-AX58-AX60 -> 498 | AY62: =AY56-AY58-AY60 -> 327 | AZ62: =AZ56-AZ58-AZ60 -> 303 | BA62: =BA56-BA58-BA60 -> 246 | BB62: =SUM(AX62:BA62) -> 1374 | BC62: =BC56-BC58-BC60 -> 501 | BD62: =BD56-BD58-BD60 -> 377 | BE62: =BE56-BE58-BE60 -> 389 | BF62: =BF56-BF58-BF60 -> 340 | BG62: =SUM(BC62:BF62) -> 1607 | BH62: =BH56-BH58-BH60 -> 577 | BI62: =BI56-BI58-BI60 -> 552 | BJ62: =BJ56-BJ58-BJ60 -> 534 | BK62: =BK56-BK58-BK60 -> 395 | BL62: =SUM(BH62:BK62) -> 2058 | BM62: =BM56-BM58-BM60 -> 625 | BN62: =BN56-BN58-BN60 -> 578 | BO62: =BO56-BO58-BO60 -> 718.72867 | BP62: =BP56-BP58-BP60 -> 563.58977 | BQ62: =SUM(BM62:BP62) -> 2485.3184 | BR62: =BR56-BR58-BR60 -> 717.85535 | BS62: =BS56-BS58-BS60 -> 676.7609 | BT62: =BT56-BT58-BT60 -> 721.49641 | BU62: =BU56-BU58-BU60 -> 577.53913 | BV62: =SUM(BR62:BU62) -> 2693.6518 | BW62: =BW56-BW58-BW60 -> 803.92176 | BX62: =BX56-BX58-BX60 -> 767.79655 | BY62: =BY56-BY58-BY60 -> 812.9946 | BZ62: =BZ56-BZ58-BZ60 -> 657.94131 | CA62: =SUM(BW62:BZ62) -> 3042.6542
B63: GAAP Net income per share - diluted | Y63: =Y62/Y65 -> 1.7786927 | Z63: =Z62/Z65 -> 1.6109391 | AA63: =AA62/AA65 -> 1.6347244 | AB63: =AB62/AB65 -> 0.13117284 | AC63: =SUM(Y63:AB63) -> 5.1555291 | AD63: =AD62/AD65 -> 1.9172237 | AE63: =AE62/AE65 -> 1.9351852 | AF63: =AF62/AF65 -> 1.5948586 | AG63: =AG62/AG65 -> 1.2902062 | AH63: =SUM(AD63:AG63) -> 6.7374736 | AI63: =AI62/AI65 -> 1.9341286 | AJ63: =AJ62/AJ65 -> 1.6220596 | AK63: =AK62/AK65 -> 1.985348 | AL63: =AL62/AL65 -> 1.8835257 | AM63: =SUM(AI63:AL63) -> 7.4250619 | AN63: =AN62/AN65 -> 2.5706751 | AO63: =AO62/AO65 -> 2.6931217 | AP63: =AP62/AP65 -> 2.4669836 | AQ63: =AQ62/AQ65 -> 1.6596195 | AR63: =SUM(AN63:AQ63) -> 9.3903999 | AS63: =AS62/AS65 -> 3.902439 | AT63: =AT62/AT65 -> 3.0707823 | AU63: =AU62/AU65 -> 2.5306994 | AV63: =AV62/AV65 -> 2.2785486 | AW63: =SUM(AS63:AV63) -> 11.782469 | AX63: =AX62/AX65 -> 2.6759807 | AY63: =AY62/AY65 -> 1.7685235 | AZ63: =AZ62/AZ65 -> 1.6476346 | BA63: =BA62/BA65 -> 1.3376835 | BB63: =SUM(AX63:BA63) -> 7.4298223 | BC63: =BC62/BC65 -> 2.7213471 | BD63: =BD62/BD65 -> 2.0478001 | BE63: =BE62/BE65 -> 2.1141304 | BF63: =BF62/BF65 -> 1.8518519 | BG63: =BG62/BG65 -> 8.7336957 | BH63: =BH62/BH65 -> 3.1461287 | BI63: =BI62/BI65 -> 3.0163934 | BJ63: =BJ62/BJ65 -> 2.9260274 | BK63: =BK62/BK65 -> 2.173913 | BL63: =SUM(BH63:BK63) -> 11.262463 | BM63: =BM62/BM65 -> 3.4587714 | BN63: =BN62/BN65 -> 3.2075472 | BO63: =BO62/BO65 -> 4.0029444 | BP63: =BP62/BP65 -> 3.1503062 | BQ63: =SUM(BM63:BP63) -> 13.819569 | BR63: =BR62/BR65 -> 4.0261096 | BS63: =BS62/BS65 -> 3.8084463 | BT63: =BT62/BT65 -> 4.0739492 | BU63: =BU62/BU65 -> 3.2721763 | BV63: =SUM(BR63:BU63) -> 15.180681 | BW63: =BW62/BW65 -> 4.5716335 | BX63: =BX62/BX65 -> 4.3811501 | BY63: =BY62/BY65 -> 4.6549934 | BZ63: =BZ62/BZ65 -> 3.7801856 | CA63: =SUM(BW63:BZ63) -> 17.387963
B64: % y/y | Y64: =IFERROR(Y63/T63-1,"NA") -> NA | Z64: =IFERROR(Z63/U63-1,"NA") -> NA | AA64: =IFERROR(AA63/V63-1,"NA") -> NA | AB64: =IFERROR(AB63/W63-1,"NA") -> NA | AC64: =IFERROR(AC63/X63-1,"NA") -> NA | AD64: =IFERROR(AD63/Y63-1,"NA") -> 0.077883551 | AE64: =IFERROR(AE63/Z63-1,"NA") -> 0.20127767 | AF64: =IFERROR(AF63/AA63-1,"NA") -> -0.024386837 | ... CA64: =IFERROR(CA63/BV63-1,"NA") -> 0.14540067
B65: Weighted average shares outstanding (diluted) | Y65: 194.3 | Z65: 193.8 | AA65: 194.1 | AB65: 194.4 | AC65: 194.2 | AD65: 194.5 | AE65: 194.4 | AF65: 194.5 | AG65: 194 | AH65: 194.4 | AI65: 192.8 | AJ65: 191.3 | AK65: 191.1 | AL65: 190.6 | AM65: =AVERAGE(AI65:AL65) -> 191.45 | AN65: 189.6 | AO65: 189 | AP65: 189.3 | AQ65: 189.2 | AR65: =AVERAGE(AN65:AQ65) -> 189.275 | AS65: 188.6 | AT65: 187.9 | AU65: 187.3 | AV65: 187.4 | AW65: 187.9 | AX65: 186.1 | AY65: 184.9 | AZ65: 183.9 | BA65: 183.9 | BB65: =AVERAGE(AX65:BA65) -> 184.7 | BC65: 184.1 | BD65: 184.1 | BE65: 184 | BF65: 183.6 | BG65: 184 | BH65: 183.4 | BI65: 183 | BJ65: 182.5 | BK65: 181.7 | BL65: =AVERAGE(BH65:BK65) -> 182.65 | BM65: 180.7 | BN65: 180.2 | BO65: =BN65-0.65 -> 179.55 | BP65: =BO65-0.65 -> 178.9 | BQ65: =AVERAGE(BM65:BP65) -> 179.8375 | BR65: =BP65-0.6 -> 178.3 | BS65: =BR65-0.6 -> 177.7 | BT65: =BS65-0.6 -> 177.1 | BU65: =BT65-0.6 -> 176.5 | BV65: =AVERAGE(BR65:BU65) -> 177.4 | BW65: =BU65-0.65 -> 175.85 | BX65: =BW65-0.6 -> 175.25 | BY65: =BX65-0.6 -> 174.65 | BZ65: =BY65-0.6 -> 174.05 | CA65: =AVERAGE(BW65:BZ65) -> 174.95
B67: EBITDA (adj. operating income)
B68: =B47 -> Total operating income (GAAP) | G68: =G47 -> 291.5 | H68: =H47 -> 311.9 | I68: =I47 -> 1228.75 | J68: =J47 -> 333 | K68: =K47 -> 411.7 | L68: =L47 -> 349.7 | M68: =M47 -> 344.7 | N68: =SUM(J68:M68) -> 1439.1 | O68: =O47 -> 371 | P68: =P47 -> 419.3 | Q68: =Q47 -> 355.2 | R68: =R47 -> 333.1 | S68: =SUM(O68:R68) -> 1478.6 | T68: =T47 -> 304.1 | U68: =U47 -> 410.2 | V68: =V47 -> 395.7 | W68: =W47 -> -473.1 | X68: =SUM(T68:W68) -> 636.9 | Y68: =Y47 -> 446.7 | Z68: =Z47 -> 460.1 | AA68: =AA47 -> 448.5 | AB68: =AB47 -> 465.5 | AC68: =SUM(Y68:AB68) -> 1820.8 | AD68: =AD47 -> 490.8 | AE68: =AE47 -> 534 | AF68: =AF47 -> 466.8 | AG68: =AG47 -> 376.6 | AH68: =SUM(AD68:AG68) -> 1868.2 | AI68: =AI47 -> 461.7 | AJ68: =AJ47 -> 483.5 | AK68: =AK47 -> 548.8 | AL68: =AL47 -> 504 | AM68: =SUM(AI68:AL68) -> 1998 | AN68: =AN47 -> 592 | AO68: =AO47 -> 710 | AP68: =AP47 -> 642 | AQ68: =AQ47 -> 444 | AR68: =SUM(AN68:AQ68) -> 2388 | AS68: =AS47 -> 853 | AT68: =AT47 -> 801 | AU68: =AU47 -> 676 | AV68: =AV47 -> 514 | AW68: =SUM(AS68:AV68) -> 2844 | AX68: =AX47 -> 656 | AY68: =AY47 -> 508 | AZ68: =AZ47 -> 413 | BA68: =BA47 -> 306 | BB68: =SUM(AX68:BA68) -> 1883 | BC68: =BC47 -> 554 | BD68: =BD47 -> 550 | BE68: =BE47 -> 535 | BF68: =BF47 -> 498 | BG68: =SUM(BC68:BF68) -> 2137 | BH68: =BH47 -> 801 | BI68: =BI47 -> 775 | BJ68: =BJ47 -> 738 | BK68: =BK47 -> 561 | BL68: =SUM(BH68:BK68) -> 2875 | BM68: =BM47 -> 846 | BN68: =BN47 -> 818 | BO68: =BO47 -> 920.78441 | BP68: =BP47 -> 752.65723 | BQ68: =SUM(BM68:BP68) -> 3337.4416 | BR68: =BR47 -> 971.71149 | BS68: =BS47 -> 928.09509 | BT68: =BT47 -> 992.78629 | BU68: =BU47 -> 815.41011 | BV68: =SUM(BR68:BU68) -> 3708.003 | BW68: =BW47 -> 1089.3184 | BX68: =BX47 -> 1046.0959 | BY68: =BY47 -> 1112.1787 | BZ68: =BZ47 -> 920.90307 | CA68: =SUM(BW68:BZ68) -> 4168.4961
B69: =B37 -> D&A | G69: =G37 -> 23.4 | H69: =H37 -> 23.3 | I69: =I37 -> 93.4 | J69: =J37 -> 23.1 | K69: =K37 -> 22.3 | L69: =L37 -> 23.2 | M69: =M37 -> 27 | N69: =SUM(J69:M69) -> 95.6 | O69: =O37 -> 28.6 | P69: =P37 -> 27.9 | Q69: =Q37 -> 22.8 | R69: =R37 -> 28.7 | S69: =SUM(O69:R69) -> 108 | T69: =T37 -> 29.9 | U69: =U37 -> 31.2 | V69: =V37 -> 32.7 | W69: =W37 -> 32.9 | X69: =SUM(T69:W69) -> 126.7 | Y69: =Y37 -> 32.5 | Z69: =Z37 -> 32.9 | AA69: =AA37 -> 43 | AB69: =AB37 -> 49.9 | AC69: =SUM(Y69:AB69) -> 158.3 | AD69: =AD37 -> 49.1 | AE69: =AE37 -> 48.4 | AF69: =AF37 -> 46.1 | AG69: =AG37 -> 48.3 | AH69: =SUM(AD69:AG69) -> 191.9 | AI69: =AI37 -> 50.3 | AJ69: =AJ37 -> 51 | AK69: =AK37 -> 48.6 | AL69: =AL37 -> 50 | AM69: =SUM(AI69:AL69) -> 199.9 | AN69: =AN37 -> 49 | AO69: =AO37 -> 58 | AP69: =AP37 -> 56 | AQ69: =AQ37 -> 57 | AR69: =SUM(AN69:AQ69) -> 220 | AS69: =AS37 -> 59 | AT69: =AT37 -> 60 | AU69: =AU37 -> 61 | AV69: =AV37 -> 77 | AW69: =SUM(AS69:AV69) -> 257 | AX69: =AX37 -> 78 | AY69: =AY37 -> 81 | AZ69: =AZ37 -> 83 | BA69: =BA37 -> 89 | BB69: =SUM(AX69:BA69) -> 331 | BC69: =BC37 -> 88 | BD69: =BD37 -> 93 | BE69: =BE37 -> 95 | BF69: =BF37 -> 97 | BG69: =SUM(BC69:BF69) -> 373 | BH69: =BH37 -> 100 | BI69: =BI37 -> 110 | BJ69: =BJ37 -> 108 | BK69: =BK37 -> 113 | BL69: =SUM(BH69:BK69) -> 431 | BM69: =BM37 -> 113 | BN69: =BN37 -> 120 | BO69: =BO37 -> 118.25993 | BP69: =BP37 -> 124.31757 | BQ69: =SUM(BM69:BP69) -> 475.5775 | BR69: =BR37 -> 123.65775 | BS69: =BS37 -> 128.53122 | BT69: =BT37 -> 126.08826 | BU69: =BU37 -> 133.04267 | BV69: =SUM(BR69:BU69) -> 511.3199 | BW69: =BW37 -> 134.47246 | BX69: =BX37 -> 135.40084 | BY69: =BY37 -> 134.93682 | BZ69: =BZ37 -> 142.50081 | CA69: =SUM(BW69:BZ69) -> 547.31093
B70: =B40 -> M&A/Restructuring/Other | G70: =G40 -> 0 | H70: =H40 -> 0 | I70: =I40 -> 0 | J70: =J40 -> 0 | K70: =K40 -> 0 | L70: =L40 -> 0 | M70: =M40 -> 0 | N70: =SUM(J70:M70) -> 0 | O70: =O40 -> 0 | P70: =P40 -> 0 | Q70: =Q40 -> 0 | R70: =R40 -> 0 | S70: =SUM(O70:R70) -> 0 | T70: =T40 -> 0 | U70: =U40 -> 0 | V70: =V40 -> 8.4 | W70: =W40 -> 863.8 | X70: =SUM(T70:W70) -> 872.2 | Y70: =Y40 -> 0 | Z70: =Z40 -> 6.6 | AA70: =AA40 -> 10.1 | AB70: =AB40 -> 5.8 | AC70: =SUM(Y70:AB70) -> 22.5 | AD70: =AD40 -> 0.8 | AE70: =AE40 -> 2 | AF70: =AF40 -> 1.3 | AG70: =AG40 -> 52.9 | AH70: =SUM(AD70:AG70) -> 57 | AI70: =AI40 -> 6.9 | AJ70: =AJ40 -> 64.5 | AK70: =AK40 -> 16.5 | AL70: =AL40 -> 5 | AM70: =SUM(AI70:AL70) -> 92.9 | AN70: =AN40 -> 8 | AO70: =AO40 -> -2 | AP70: =AP40 -> 23 | AQ70: =AQ40 -> 30 | AR70: =SUM(AN70:AQ70) -> 59 | AS70: =AS40 -> 2 | AT70: =AT40 -> 0 | AU70: =AU40 -> 0 | AV70: =AV40 -> -2 | AW70: =SUM(AS70:AV70) -> 0 | AX70: =AX40 -> 0 | AY70: =AY40 -> 31 | AZ70: =AZ40 -> 1 | BA70: =BA40 -> 82 | BB70: =SUM(AX70:BA70) -> 114 | BC70: =BC40 -> 14 | BD70: =BD40 -> 10 | BE70: =BE40 -> 27 | BF70: =BF40 -> 36 | BG70: =SUM(BC70:BF70) -> 87 | BH70: =BH40 -> 5 | BI70: =BI40 -> 17 | BJ70: =BJ40 -> 21 | BK70: =BK40 -> 59 | BL70: =SUM(BH70:BK70) -> 102 | BM70: =BM40 -> 35 | BN70: =BN40 -> 28 | BO70: =BO40 -> 14 | BP70: =BP40 -> 14 | BQ70: =SUM(BM70:BP70) -> 91 | BR70: =BR40 -> 21 | BS70: =BS40 -> 21 | BT70: =BT40 -> 21 | BU70: =BU40 -> 21 | BV70: =SUM(BR70:BU70) -> 84 | BW70: =BW40 -> 0 | BX70: =BX40 -> 0 | BY70: =BY40 -> 0 | BZ70: =BZ40 -> 0 | CA70: =SUM(BW70:BZ70) -> 0
B71: Other | G71: 0.3 | H71: 0.3 | I71: 6 | J71: 0.3 | K71: 0 | L71: 0 | M71: 0 | N71: =SUM(J71:M71) -> 0.3 | O71: 0.3 | P71: 0 | Q71: 0 | R71: 0 | S71: =SUM(O71:R71) -> 0.3 | T71: 0 | U71: 0 | V71: 0 | W71: 5.2 | X71: =SUM(T71:W71) -> 5.2 | Y71: 0 | Z71: 0 | AA71: 0 | AB71: 0 | AC71: =SUM(Y71:AB71) -> 0 | AD71: 0 | AE71: 0 | AF71: 0 | AG71: 0 | AH71: =SUM(AD71:AG71) -> 0 | AI71: 0 | AJ71: 0 | AK71: 0 | AL71: 0 | AM71: =SUM(AI71:AL71) -> 0 | AN71: 0 | AO71: 0 | AP71: 0 | AQ71: 0 | AR71: =SUM(AN71:AQ71) -> 0 | AS71: 0 | AT71: 0 | AU71: 0 | AV71: 0 | AW71: =SUM(AS71:AV71) -> 0 | AX71: 0 | AY71: 0 | AZ71: 0 | BA71: 0 | BB71: =SUM(AX71:BA71) -> 0 | BC71: 0 | BD71: 0 | BE71: 0 | BF71: 0 | BG71: =SUM(BC71:BF71) -> 0 | BH71: 0 | BI71: 0 | BJ71: 0 | BK71: 0 | BL71: =SUM(BH71:BK71) -> 0 | BM71: 0 | BN71: 0 | BO71: 0 | BP71: 0 | BQ71: =SUM(BM71:BP71) -> 0 | BR71: 0 | BS71: 0 | BT71: 0 | BU71: 0 | BV71: =SUM(BR71:BU71) -> 0 | BW71: 0 | BX71: 0 | BY71: 0 | BZ71: 0 | CA71: =SUM(BW71:BZ71) -> 0
B72: EBITDA (adj. operating income) | G72: =SUM(G68:G71) -> 315.2 | H72: =SUM(H68:H71) -> 335.5 | I72: =SUM(I68:I71) -> 1328.15 | J72: =SUM(J68:J71) -> 356.4 | K72: =SUM(K68:K71) -> 434 | L72: =SUM(L68:L71) -> 372.9 | M72: =SUM(M68:M71) -> 371.7 | N72: =SUM(J72:M72) -> 1535 | O72: =SUM(O68:O71) -> 399.9 | P72: =SUM(P68:P71) -> 447.2 | Q72: =SUM(Q68:Q71) -> 378 | R72: =SUM(R68:R71) -> 361.8 | S72: =SUM(O72:R72) -> 1586.9 | T72: =SUM(T68:T71) -> 334 | U72: =SUM(U68:U71) -> 441.4 | V72: =SUM(V68:V71) -> 436.8 | W72: =SUM(W68:W71) -> 428.8 | X72: =SUM(T72:W72) -> 1641 | Y72: =SUM(Y68:Y71) -> 479.2 | Z72: =SUM(Z68:Z71) -> 499.6 | AA72: =SUM(AA68:AA71) -> 501.6 | AB72: =SUM(AB68:AB71) -> 521.2 | AC72: =SUM(Y72:AB72) -> 2001.6 | AD72: =SUM(AD68:AD71) -> 540.7 | AE72: =SUM(AE68:AE71) -> 584.4 | AF72: =SUM(AF68:AF71) -> 514.2 | AG72: =SUM(AG68:AG71) -> 477.8 | AH72: =SUM(AD72:AG72) -> 2117.1 | AI72: =SUM(AI68:AI71) -> 518.9 | AJ72: =SUM(AJ68:AJ71) -> 599 | AK72: =SUM(AK68:AK71) -> 613.9 | AL72: =SUM(AL68:AL71) -> 559 | AM72: =SUM(AI72:AL72) -> 2290.8 | AN72: =SUM(AN68:AN71) -> 649 | AO72: =SUM(AO68:AO71) -> 766 | AP72: =SUM(AP68:AP71) -> 721 | AQ72: =SUM(AQ68:AQ71) -> 531 | AR72: =SUM(AN72:AQ72) -> 2667 | AS72: =SUM(AS68:AS71) -> 914 | AT72: =SUM(AT68:AT71) -> 861 | AU72: =SUM(AU68:AU71) -> 737 | AV72: =SUM(AV68:AV71) -> 589 | AW72: =SUM(AS72:AV72) -> 3101 | AX72: =SUM(AX68:AX71) -> 734 | AY72: =SUM(AY68:AY71) -> 620 | AZ72: =SUM(AZ68:AZ71) -> 497 | BA72: =SUM(BA68:BA71) -> 477 | BB72: =SUM(AX72:BA72) -> 2328 | BC72: =SUM(BC68:BC71) -> 656 | BD72: =SUM(BD68:BD71) -> 653 | BE72: =SUM(BE68:BE71) -> 657 | BF72: =SUM(BF68:BF71) -> 631 | BG72: =SUM(BC72:BF72) -> 2597 | BH72: =SUM(BH68:BH71) -> 906 | BI72: =SUM(BI68:BI71) -> 902 | BJ72: =SUM(BJ68:BJ71) -> 867 | BK72: =SUM(BK68:BK71) -> 733 | BL72: =SUM(BH72:BK72) -> 3408 | BM72: =SUM(BM68:BM71) -> 994 | BN72: =SUM(BN68:BN71) -> 966 | BO72: =SUM(BO68:BO71) -> 1053.0443 | BP72: =SUM(BP68:BP71) -> 890.97481 | BQ72: =SUM(BM72:BP72) -> 3904.0191 | BR72: =SUM(BR68:BR71) -> 1116.3692 | BS72: =SUM(BS68:BS71) -> 1077.6263 | BT72: =SUM(BT68:BT71) -> 1139.8746 | BU72: =SUM(BU68:BU71) -> 969.45278 | BV72: =SUM(BR72:BU72) -> 4303.3229 | BW72: =SUM(BW68:BW71) -> 1223.7909 | BX72: =SUM(BX68:BX71) -> 1181.4968 | BY72: =SUM(BY68:BY71) -> 1247.1155 | BZ72: =SUM(BZ68:BZ71) -> 1063.4039 | CA72: =SUM(BW72:BZ72) -> 4715.807
B73: y/y growth % | I73: =IFERROR(I72/D72-1,"NA") -> NA | J73: =IFERROR(J72/E72-1,"NA") -> NA | K73: =IFERROR(K72/F72-1,"NA") -> NA | L73: =IFERROR(L72/G72-1,"NA") -> 0.18305838 | M73: =IFERROR(M72/H72-1,"NA") -> 0.10789866 | N73: =IFERROR(N72/I72-1,"NA") -> 0.15574295 | O73: =IFERROR(O72/J72-1,"NA") -> 0.12205387 | P73: =IFERROR(P72/K72-1,"NA") -> 0.030414747 | ... AG73: =IFERROR(AG72/AB72-1,"NA") -> -0.083269378 | AH73: =AH72/AC72-1 -> 0.057703837 | AI73: =IFERROR(AI72/AD72-1,"NA") -> -0.040318106 | AJ73: =IFERROR(AJ72/AE72-1,"NA") -> 0.024982888 | AK73: =IFERROR(AK72/AF72-1,"NA") -> 0.19389343 | AL73: =IFERROR(AL72/AG72-1,"NA") -> 0.16994558 | AM73: =AM72/AH72-1 -> 0.082046195 | AN73: =IFERROR(AN72/AI72-1,"NA") -> 0.25072268 | AO73: =IFERROR(AO72/AJ72-1,"NA") -> 0.278798 | AP73: =IFERROR(AP72/AK72-1,"NA") -> 0.17445838 | AQ73: =IFERROR(AQ72/AL72-1,"NA") -> -0.050089445 | AR73: =AR72/AM72-1 -> 0.16422211 | AS73: =IFERROR(AS72/AN72-1,"NA") -> 0.40832049 | AT73: =IFERROR(AT72/AO72-1,"NA") -> 0.12402089 | AU73: =IFERROR(AU72/AP72-1,"NA") -> 0.022191401 | AV73: =IFERROR(AV72/AQ72-1,"NA") -> 0.10922787 | AW73: =AW72/AR72-1 -> 0.16272966 | AX73: =IFERROR(AX72/AS72-1,"NA") -> -0.19693654 | AY73: =IFERROR(AY72/AT72-1,"NA") -> -0.27990708 | AZ73: =IFERROR(AZ72/AU72-1,"NA") -> -0.3256445 | BA73: =IFERROR(BA72/AV72-1,"NA") -> -0.1901528 | BB73: =BB72/AW72-1 -> -0.24927443 | BC73: =IFERROR(BC72/AX72-1,"NA") -> -0.10626703 | BD73: =IFERROR(BD72/AY72-1,"NA") -> 0.053225806 | BE73: =IFERROR(BE72/AZ72-1,"NA") -> 0.32193159 | BF73: =IFERROR(BF72/BA72-1,"NA") -> 0.32285115 | BG73: =BG72/BB72-1 -> 0.11554983 | BH73: =IFERROR(BH72/BC72-1,"NA") -> 0.38109756 | BI73: =IFERROR(BI72/BD72-1,"NA") -> 0.381317 | BJ73: =IFERROR(BJ72/BE72-1,"NA") -> 0.3196347 | BK73: =IFERROR(BK72/BF72-1,"NA") -> 0.16164818 | BL73: =BL72/BG72-1 -> 0.3122834 | BM73: =IFERROR(BM72/BH72-1,"NA") -> 0.097130243 | BN73: =IFERROR(BN72/BI72-1,"NA") -> 0.070953437 | BO73: =IFERROR(BO72/BJ72-1,"NA") -> 0.21458402 | BP73: =IFERROR(BP72/BK72-1,"NA") -> 0.21551815 | BQ73: =BQ72/BL72-1 -> 0.14554552 | BR73: =IFERROR(BR72/BM72-1,"NA") -> 0.12310789 | BS73: =IFERROR(BS72/BN72-1,"NA") -> 0.11555518 | BT73: =IFERROR(BT72/BO72-1,"NA") -> 0.082456371 | BU73: =IFERROR(BU72/BP72-1,"NA") -> 0.088081022 | BV73: =BV72/BQ72-1 -> 0.10228017 | BW73: =IFERROR(BW72/BR72-1,"NA") -> 0.096224117 | BX73: =IFERROR(BX72/BS72-1,"NA") -> 0.096388211 | BY73: =IFERROR(BY72/BT72-1,"NA") -> 0.09408133 | BZ73: =IFERROR(BZ72/BU72-1,"NA") -> 0.096911477 | CA73: =CA72/BV72-1 -> 0.095852471
B74: % margin | G74: =G72/G25 -> 0.44677534 | H74: =H72/H25 -> 0.43056982 | I74: =I72/I25 -> 0.44769353 | J74: =J72/J25 -> 0.4645464 | K74: =K72/K25 -> 0.49685175 | L74: =L72/L25 -> 0.4569293 | M74: =M72/M25 -> 0.42358974 | N74: =N72/N25 -> 0.46036649 | ... CA74: =CA72/CA25 -> 0.5271203
B75: y/y margin change bps | I75: =IFERROR((I74-D74)*10000,"NA") -> 4476.9353 | J75: =IFERROR((J74-E74)*10000,"NA") -> 4645.464 | K75: =IFERROR((K74-F74)*10000,"NA") -> 4968.5175 | L75: =IFERROR((L74-G74)*10000,"NA") -> 101.53961 | M75: =IFERROR((M74-H74)*10000,"NA") -> -69.800716 | N75: =IFERROR((N74-I74)*10000,"NA") -> 126.72967 | O75: =IFERROR((O74-J74)*10000,"NA") -> -25.547204 | P75: =IFERROR((P74-K74)*10000,"NA") -> -97.588366 | ... CA75: =IFERROR((CA74-BV74)*10000,"NA") -> 94.406712
B76: Incremental/(decremental) margins | I76: =(I72-D72)/(I25-D25) -> 0.44769353 | N76: =(N72-I72)/(N25-I25) -> 0.5626275 | S76: =(S72-N72)/(S25-N25) -> 0.34553928 | X76: =(X72-S72)/(X25-S25) -> 0.45196324 | AC76: =(AC72-X72)/(AC25-X25) -> 0.60110018 | AH76: =(AH72-AC72)/(AH25-AC25) -> 0.48407376 | AI76: =(AI72-AD72)/(AI25-AD25) -> -1.4155844 | AJ76: =(AJ72-AE72)/(AJ25-AE25) -> 0.37922078 | AK76: =(AK72-AF72)/(AK25-AF25) -> 0.62429555 | AL76: =(AL72-AG72)/(AL25-AG25) -> 0.46963563 | AM76: =(AM72-AH72)/(AM25-AH25) -> 0.44941785 | AN76: =(AN72-AI72)/(AN25-AI25) -> 0.87964841 | AO76: =(AO72-AJ72)/(AO25-AJ25) -> 0.75429088 | ... CA76: =(CA72-BV72)/(CA25-BV25) -> 0.65097159
B77: Adj. operating income (pre-stock comp) | Y77: =Y72+Y36 -> 511.7 | Z77: =Z72+Z36 -> 528.3 | AA77: =AA72+AA36 -> 533.4 | AB77: =AB72+AB36 -> 551.1 | AC77: =AC72+AC36 -> 2124.5 | AD77: =AD72+AD36 -> 575.8 | AE77: =AE72+AE36 -> 618.8 | AF77: =AF72+AF36 -> 544.7 | ... CA77: =CA72+CA36 -> 4898.807
B79: Adj. net income
B80: GAAP Net income attributable to MCO | Y80: =Y62 -> 345.6 | Z80: =Z62 -> 312.2 | AA80: =AA62 -> 317.3 | AB80: =AB62 -> 25.5 | AC80: =SUM(Y80:AB80) -> 1000.6 | AD80: =AD62 -> 372.9 | AE80: =AE62 -> 376.2 | AF80: =AF62 -> 310.2 | AG80: =AG62 -> 250.3 | AH80: =SUM(AD80:AG80) -> 1309.6 | AI80: =AI62 -> 372.9 | AJ80: =AJ62 -> 310.3 | AK80: =AK62 -> 379.4 | AL80: =AL62 -> 359 | AM80: =SUM(AI80:AL80) -> 1421.6 | AN80: =AN62 -> 487.4 | AO80: =AO62 -> 509 | AP80: =AP62 -> 467 | AQ80: =AQ62 -> 314 | AR80: =SUM(AN80:AQ80) -> 1777.4 | AS80: =AS62 -> 736 | AT80: =AT62 -> 577 | AU80: =AU62 -> 474 | AV80: =AV62 -> 427 | AW80: =SUM(AS80:AV80) -> 2214 | AX80: =AX62 -> 498 | AY80: =AY62 -> 327 | AZ80: =AZ62 -> 303 | BA80: =BA62 -> 246 | BB80: =SUM(AX80:BA80) -> 1374 | BC80: =BC62 -> 501 | BD80: =BD62 -> 377 | BE80: =BE62 -> 389 | BF80: =BF62 -> 340 | BG80: =SUM(BC80:BF80) -> 1607 | BH80: =BH62 -> 577 | BI80: =BI62 -> 552 | BJ80: =BJ62 -> 534 | BK80: =BK62 -> 395 | BL80: =SUM(BH80:BK80) -> 2058 | BM80: =BM62 -> 625 | BN80: =BN62 -> 578 | BO80: =BO62 -> 718.72867 | BP80: =BP62 -> 563.58977 | BQ80: =SUM(BM80:BP80) -> 2485.3184 | BR80: =BR62 -> 717.85535 | BS80: =BS62 -> 676.7609 | BT80: =BT62 -> 721.49641 | BU80: =BU62 -> 577.53913 | BV80: =SUM(BR80:BU80) -> 2693.6518 | BW80: =BW62 -> 803.92176 | BX80: =BX62 -> 767.79655 | BY80: =BY62 -> 812.9946 | BZ80: =BZ62 -> 657.94131 | CA80: =SUM(BW80:BZ80) -> 3042.6542
B81: Acquisition related expenses, net | Y81: 0 | Z81: 6.6 | AA81: 8.5 | AB81: 3.8 | AC81: =SUM(Y81:AB81) -> 18.9 | AD81: 0.6 | AE81: 1.6 | AF81: =0.9 -> 0.9 | AG81: 3.1 | AH81: =SUM(AD81:AG81) -> 6.2 | AI81: 1.1 | AJ81: 1.4 | AK81: 0 | AL81: 0 | AM81: =SUM(AI81:AL81) -> 2.5 | AN81: 0 | AO81: 0 | AP81: 0 | AQ81: 0 | AR81: =SUM(AN81:AQ81) -> 0 | AS81: 0 | AT81: 0 | AU81: 0 | AV81: 0 | AW81: =SUM(AS81:AV81) -> 0 | AX81: 0 | AY81: 0 | AZ81: 0 | BA81: 0 | BB81: =SUM(AX81:BA81) -> 0 | BC81: 0 | BD81: 0 | BE81: 0 | BF81: 0 | BG81: =SUM(BC81:BF81) -> 0 | BH81: 0 | BI81: 0 | BJ81: 0 | BK81: 0 | BL81: =SUM(BH81:BK81) -> 0 | BM81: 0 | BN81: 0 | BO81: 0 | BP81: 0 | BQ81: =SUM(BM81:BP81) -> 0 | BR81: 0 | BS81: 0 | BT81: 0 | BU81: 0 | BV81: =SUM(BR81:BU81) -> 0 | BW81: 0 | BX81: 0 | BY81: 0 | BZ81: 0 | CA81: =SUM(BW81:BZ81) -> 0
B82: Acquisition related intangible amortization, net | Y82: 6.2 | Z82: 6.2 | AA82: 13.8 | AB82: 17.5 | AC82: =SUM(Y82:AB82) -> 43.7 | AD82: 19.8 | AE82: 19.5 | AF82: 19.1 | AG82: 20.3 | AH82: =SUM(AD82:AG82) -> 78.7 | AI82: 20.3 | AJ82: 20.1 | AK82: 18.9 | AL82: 20 | AM82: =SUM(AI82:AL82) -> 79.3 | AN82: =22+9 -> 31 | AO82: 24 | AP82: 24 | AQ82: 26 | AR82: =SUM(AN82:AQ82) -> 105 | AS82: =27+2 -> 29 | AT82: 28 | AU82: 29 | AV82: 38 | AW82: =SUM(AS82:AV82) -> 124 | AX82: 39 | AY82: 39 | AZ82: =48-11 -> 37 | BA82: 38 | BB82: =SUM(AX82:BA82) -> 153 | BC82: 39 | BD82: 38 | BE82: 37 | BF82: 36 | BG82: =SUM(BC82:BF82) -> 150 | BH82: 37 | BI82: 36 | BJ82: 39 | BK82: 38 | BL82: =SUM(BH82:BK82) -> 150 | BM82: 40 | BN82: =55-13 -> 42 | BO82: =BJ82 -> 39 | BP82: =BK82 -> 38 | BQ82: =SUM(BM82:BP82) -> 159 | BR82: =BM82 -> 40 | BS82: =BN82 -> 42 | BT82: =BO82 -> 39 | BU82: =BP82 -> 38 | BV82: =SUM(BR82:BU82) -> 159 | BW82: =BR82 -> 40 | BX82: =BS82 -> 42 | BY82: =BT82 -> 39 | BZ82: =BU82 -> 38 | CA82: =SUM(BW82:BZ82) -> 159
B83: Restructuring, net | Y83: 0 | Z83: 0 | AA83: 0 | AB83: 0 | AC83: =SUM(Y83:AB83) -> 0 | AD83: 0 | AE83: 0 | AF83: 0 | AG83: 36.8 | AH83: =SUM(AD83:AG83) -> 36.8 | AI83: 4.1 | AJ83: 40.7 | AK83: -0.7 | AL83: 1 | AM83: =SUM(AI83:AL83) -> 45.1 | AN83: 0 | AO83: -1 | AP83: 18 | AQ83: 22 | AR83: =SUM(AN83:AQ83) -> 39 | AS83: 0 | AT83: 0 | AU83: 0 | AV83: -2 | AW83: =SUM(AS83:AV83) -> -2 | AX83: 0 | AY83: 24 | AZ83: 0 | BA83: 64 | BB83: =SUM(AX83:BA83) -> 88 | BC83: 10 | BD83: 8 | BE83: 21 | BF83: 26 | BG83: =SUM(BC83:BF83) -> 65 | BH83: 4 | BI83: 1 | BJ83: 5 | BK83: 34 | BL83: =SUM(BH83:BK83) -> 44 | BM83: 25 | BN83: =27-7 -> 20 | BO83: =BO40*(1-BO59) -> 11.48 | BP83: =BP40*(1-BP59) -> 11.48 | BQ83: =SUM(BM83:BP83) -> 67.96 | BR83: =BR40*(1-BR59) -> 16.17 | BS83: =BS40*(1-BS59) -> 16.065 | BT83: =BT40*(1-BT59) -> 15.96 | BU83: =BU40*(1-BU59) -> 15.855 | BV83: =SUM(BR83:BU83) -> 64.05 | BW83: =BW40*(1-BW59) -> 0 | BX83: =BX40*(1-BX59) -> 0 | BY83: =BY40*(1-BY59) -> 0 | BZ83: =BZ40*(1-BZ59) -> 0 | CA83: =SUM(BW83:BZ83) -> 0
B84: Other | Y84: -59.7 | Z84: -25.3 | AA84: -44.4 | AB84: =247.3-1.7 -> 245.6 | AC84: =SUM(Y84:AB84) -> 116.2 | AD84: 0 | AE84: 0 | AF84: =-64.7+63.9 -> -0.8 | AG84: 5.7 | AH84: =SUM(AD84:AG84) -> 4.9 | AI84: 0 | AJ84: =8.7+15 -> 23.7 | AK84: =2+11.7 -> 13.7 | AL84: =3-2 -> 1 | AM84: =SUM(AI84:AL84) -> 38.4 | AN84: 0 | AO84: 0 | AP84: 0 | AQ84: 0 | AR84: =SUM(AN84:AQ84) -> 0 | AS84: 0 | AT84: 0 | AU84: 0 | AV84: -27 | AW84: =SUM(AS84:AV84) -> -27 | AX84: 0 | AY84: 20 | AZ84: 0 | BA84: -53 | BB84: =SUM(AX84:BA84) -> -33 | BC84: 0 | BD84: 0 | BE84: 0 | BF84: 0 | BG84: =SUM(BC84:BF84) -> 0 | BH84: 0 | BI84: 11 | BJ84: =12-5 -> 7 | BK84: 9 | BL84: =SUM(BH84:BK84) -> 27 | BM84: 2 | BN84: =1-1 -> 0 | BO84: =BO55 -> 0 | BP84: =BP55 -> -14 | BQ84: =SUM(BM84:BP84) -> -12 | BR84: 0 | BS84: 0 | BT84: 0 | BU84: 0 | BV84: =SUM(BR84:BU84) -> 0 | BW84: 0 | BX84: 0 | BY84: 0 | BZ84: 0 | CA84: =SUM(BW84:BZ84) -> 0
B85: Adj. net income | Y85: =SUM(Y80:Y84) -> 292.1 | Z85: =SUM(Z80:Z84) -> 299.7 | AA85: =SUM(AA80:AA84) -> 295.2 | AB85: =SUM(AB80:AB84) -> 292.4 | AC85: =SUM(Y85:AB85) -> 1179.4 | AD85: =SUM(AD80:AD84) -> 393.3 | AE85: =SUM(AE80:AE84) -> 397.3 | AF85: =SUM(AF80:AF84) -> 329.4 | AG85: =SUM(AG80:AG84) -> 316.2 | AH85: =SUM(AD85:AG85) -> 1436.2 | AI85: =SUM(AI80:AI84) -> 398.4 | AJ85: =SUM(AJ80:AJ84) -> 396.2 | AK85: =SUM(AK80:AK84) -> 411.3 | AL85: =SUM(AL80:AL84) -> 381 | AM85: =SUM(AI85:AL85) -> 1586.9 | AN85: =SUM(AN80:AN84) -> 518.4 | AO85: =SUM(AO80:AO84) -> 532 | AP85: =SUM(AP80:AP84) -> 509 | AQ85: =SUM(AQ80:AQ84) -> 362 | AR85: =SUM(AN85:AQ85) -> 1921.4 | AS85: =SUM(AS80:AS84) -> 765 | AT85: =SUM(AT80:AT84) -> 605 | AU85: =SUM(AU80:AU84) -> 503 | AV85: =SUM(AV80:AV84) -> 436 | AW85: =SUM(AS85:AV85) -> 2309 | AX85: =SUM(AX80:AX84) -> 537 | AY85: =SUM(AY80:AY84) -> 410 | AZ85: =SUM(AZ80:AZ84) -> 340 | BA85: =SUM(BA80:BA84) -> 295 | BB85: =SUM(AX85:BA85) -> 1582 | BC85: =SUM(BC80:BC84) -> 550 | BD85: =SUM(BD80:BD84) -> 423 | BE85: =SUM(BE80:BE84) -> 447 | BF85: =SUM(BF80:BF84) -> 402 | BG85: =SUM(BC85:BF85) -> 1822 | BH85: =SUM(BH80:BH84) -> 618 | BI85: =SUM(BI80:BI84) -> 600 | BJ85: =SUM(BJ80:BJ84) -> 585 | BK85: =SUM(BK80:BK84) -> 476 | BL85: =SUM(BH85:BK85) -> 2279 | BM85: =SUM(BM80:BM84) -> 692 | BN85: =SUM(BN80:BN84) -> 640 | BO85: =SUM(BO80:BO84) -> 769.20867 | BP85: =SUM(BP80:BP84) -> 599.06977 | BQ85: =SUM(BM85:BP85) -> 2700.2784 | BR85: =SUM(BR80:BR84) -> 774.02535 | BS85: =SUM(BS80:BS84) -> 734.8259 | BT85: =SUM(BT80:BT84) -> 776.45641 | BU85: =SUM(BU80:BU84) -> 631.39413 | BV85: =SUM(BR85:BU85) -> 2916.7018 | BW85: =SUM(BW80:BW84) -> 843.92176 | BX85: =SUM(BX80:BX84) -> 809.79655 | BY85: =SUM(BY80:BY84) -> 851.9946 | BZ85: =SUM(BZ80:BZ84) -> 695.94131 | CA85: =SUM(BW85:BZ85) -> 3201.6542
B86: y/y growth % | Y86: =IFERROR(Y85/T85-1,"NA") -> NA | Z86: =IFERROR(Z85/U85-1,"NA") -> NA | AA86: =IFERROR(AA85/V85-1,"NA") -> NA | AB86: =IFERROR(AB85/W85-1,"NA") -> NA | AC86: =IFERROR(AC85/X85-1,"NA") -> NA | AD86: =IFERROR(AD85/Y85-1,"NA") -> 0.34645669 | AE86: =IFERROR(AE85/Z85-1,"NA") -> 0.32565899 | AF86: =IFERROR(AF85/AA85-1,"NA") -> 0.11585366 | ... CA86: =IFERROR(CA85/BV85-1,"NA") -> 0.097696803
B88: Adj. EPS (Published) | Y88: =Y85/Y65 -> 1.5033453 | Z88: =Z85/Z65 -> 1.5464396 | AA88: =AA85/AA65 -> 1.5208655 | AB88: =AB85/AB65 -> 1.5041152 | AC88: =AC85/AC65 -> 6.0731205 | AD88: =AD85/AD65 -> 2.022108 | AE88: =AE85/AE65 -> 2.0437243 | AF88: =AF85/AF65 -> 1.6935733 | ... AV88: =AV85/AV65 -> 2.3265742 | AW88: =AW85/AW65-0.01 -> 12.278451 | AX88: =AX85/AX65 -> 2.8855454 | AY88: =AY85/AY65 -> 2.2174148 | AZ88: =AZ85/AZ65 -> 1.8488309 | BA88: =BA85/BA65 -> 1.6041327 | BB88: =BB85/BB65 -> 8.5652409 | BC88: =BC85/BC65 -> 2.9875068 | BD88: =BD85/BD65 -> 2.2976643 | BE88: =BE85/BE65 -> 2.4293478 | ... BM88: =BM85/BM65 -> 3.8295517 | BN88: =BN85/BN65+0.01 -> 3.5616093 | BO88: =BO85/BO65 -> 4.2840917 | BP88: =BP85/BP65 -> 3.3486292 | BQ88: =BQ85/BQ65 -> 15.015102 | BR88: =BR85/BR65 -> 4.3411405 | BS88: =BS85/BS65 -> 4.1352049 | BT88: =BT85/BT65 -> 4.3842824 | BU88: =BU85/BU65 -> 3.5773038 | BV88: =BV85/BV65 -> 16.441385 | ... CA88: =CA85/CA65 -> 18.300396
B89: y/y growth % | N89: =IFERROR(N88/I88-1,"NA") -> NA | S89: =IFERROR(S88/N88-1,"NA") -> NA | X89: =IFERROR(X88/S88-1,"NA") -> NA | Y89: =IFERROR(Y88/T88-1,"NA") -> NA | Z89: =IFERROR(Z88/U88-1,"NA") -> NA | AA89: =IFERROR(AA88/V88-1,"NA") -> NA | AB89: =IFERROR(AB88/W88-1,"NA") -> NA | AC89: =IFERROR(AC88/X88-1,"NA") -> NA | AD89: =IFERROR(AD88/Y88-1,"NA") -> 0.34507216 | AE89: =IFERROR(AE88/Z88-1,"NA") -> 0.32156745 | ... CA89: =IFERROR(CA88/BV88-1,"NA") -> 0.11306895
B90: Adj. EPS (pre stock comp) | Y90: =((Y36*(1-Y59))+Y85)/Y65 -> 1.6315476 | Z90: =((Z36*(1-Z59))+Z85)/Z65 -> 1.6469619 | AA90: =((AA36*(1-AA59))+AA85)/AA65 -> 1.6333117 | AB90: =((AB36*(1-AB59))+AB85)/AB65 -> 1.514867 | AC90: =((AC36*(1-AC59))+AC85)/AC65 -> 6.4300299 | AD90: =((AD36*(1-AD59))+AD85)/AD65 -> 2.1762643 | AE90: =((AE36*(1-AE59))+AE85)/AE65 -> 2.1786813 | AF90: =((AF36*(1-AF59))+AF85)/AF65 -> 1.8120942 | ... CA90: =((CA36*(1-CA59))+CA85)/CA65 -> 19.096914
B92: Free cash flow
B93: Cash from operations | Y93: -512.4 | Z93: -40.6 | AA93: 349.8 | AB93: 754.6 | AC93: 754.6 | AD93: 391.5 | AE93: 777.3 | AF93: 1084.6 | AG93: 1461.1 | AH93: 1461.1 | AI93: 367.1 | AJ93: ='BS & CFS'!W57 -> 747.8 | AK93: ='BS & CFS'!X57 -> 83.7 | AL93: ='BS & CFS'!Y57 -> 476.7 | AM93: ='BS & CFS'!Z57 -> 1675.3 | AN93: ='BS & CFS'!AA57 -> 345.4 | AO93: ='BS & CFS'!AB57 -> 632 | AP93: ='BS & CFS'!AC57 -> 511 | AQ93: ='BS & CFS'!AD57 -> 658 | ... CA93: ='BS & CFS'!BN57 -> 3811.2964
B94: y/y growth % | Y94: =IFERROR(Y93/T93-1,"NA") -> NA | Z94: =IFERROR(Z93/U93-1,"NA") -> NA | AA94: =IFERROR(AA93/V93-1,"NA") -> NA | AB94: =IFERROR(AB93/W93-1,"NA") -> NA | AC94: =IFERROR(AC93/X93-1,"NA") -> NA | AD94: NA | AE94: NA | AF94: NA | AG94: NA | AH94: =IFERROR(AH93/AC93-1,"NA") -> 0.93625762 | AI94: =IFERROR(AI93/AD93-1,"NA") -> -0.062324393 | AJ94: =IFERROR(AJ93/AE93-1,"NA") -> -0.037951885 | AK94: =IFERROR(AK93/AF93-1,"NA") -> -0.92282869 | AL94: =IFERROR(AL93/AG93-1,"NA") -> -0.67373896 | AM94: =IFERROR(AM93/AH93-1,"NA") -> 0.14660188 | AN94: =IFERROR(AN93/AI93-1,"NA") -> -0.059111959 | AO94: =IFERROR(AO93/AJ93-1,"NA") -> -0.15485424 | ... CA94: =IFERROR(CA93/BV93-1,"NA") -> 0.10997993
B95: Capex | Y95: -18.7 | Z95: -42.8 | AA95: -69.4 | AB95: -90.6 | AC95: -90.6 | AD95: -15 | AE95: -37.9 | AF95: -62.9 | AG95: -90.4 | AH95: -90.4 | AI95: -20 | AJ95: ='BS & CFS'!W60 -> -38.7 | AK95: ='BS & CFS'!X60 -> -10 | AL95: ='BS & CFS'!Y60 -> 0 | AM95: ='BS & CFS'!Z60 -> -68.7 | AN95: ='BS & CFS'!AA60 -> -21 | AO95: ='BS & CFS'!AB60 -> -41 | AP95: ='BS & CFS'!AC60 -> -21 | AQ95: ='BS & CFS'!AD60 -> -20 | ... CA95: ='BS & CFS'!BN60 -> -359
B96: % revenue | Y96: =IFERROR(Y95/Y25,"NA") -> -0.019175554 | Z96: =IFERROR(Z95/Z25,"NA") -> -0.042778611 | AA96: =IFERROR(AA95/AA25,"NA") -> -0.065293066 | AB96: =IFERROR(AB95/AB25,"NA") -> -0.077734878 | AC96: =IFERROR(AC95/AC25,"NA") -> -0.021550391 | AD96: =IFERROR(AD95/AD25,"NA") -> -0.013313216 | AE96: =IFERROR(AE95/AE25,"NA") -> -0.032252574 | AF96: =IFERROR(AF95/AF25,"NA") -> -0.058197631 | ... CA96: =IFERROR(CA95/CA25,"NA") -> -0.04012806
B97: Free cash flow (CFO - capex) | Y97: =Y93+Y95 -> -531.1 | Z97: =Z93+Z95 -> -83.4 | AA97: =AA93+AA95 -> 280.4 | AB97: =AB93+AB95 -> 664 | AC97: =AC93+AC95 -> 664 | AD97: =AD93+AD95 -> 376.5 | AE97: =AE93+AE95 -> 739.4 | AF97: =AF93+AF95 -> 1021.7 | ... CA97: =CA93+CA95 -> 3452.2964
B98: % growth (y/y) | Y98: =IFERROR(Y97/T97-1,"NA") -> NA | Z98: =IFERROR(Z97/U97-1,"NA") -> NA | AA98: =IFERROR(AA97/V97-1,"NA") -> NA | AB98: =IFERROR(AB97/W97-1,"NA") -> NA | AC98: =IFERROR(AC97/X97-1,"NA") -> NA | AD98: =IFERROR(AD97/Y97-1,"NA") -> -1.708906 | AE98: =IFERROR(AE97/Z97-1,"NA") -> -9.8657074 | AF98: =IFERROR(AF97/AA97-1,"NA") -> 2.6437233 | ... CA98: =IFERROR(CA97/BV97-1,"NA") -> 0.11918126
B99: FCF per share | Y99: =Y97/Y65 -> -2.733402 | Z99: =Z97/Z65 -> -0.43034056 | AA99: =AA97/AA65 -> 1.4446162 | AB99: =AB97/AB65 -> 3.4156379 | AC99: =AC97/AC65 -> 3.4191555 | AD99: =AD97/AD65 -> 1.9357326 | AE99: =AE97/AE65 -> 3.8034979 | AF99: =AF97/AF65 -> 5.2529563 | ... CA99: =CA97/CA65 -> 19.733046
B100: % EBITDA | Y100: =IFERROR(Y97/Y72,"NA") -> -1.1083055 | Z100: =IFERROR(Z97/Z72,"NA") -> -0.16693355 | AA100: =IFERROR(AA97/AA72,"NA") -> 0.55901116 | AB100: =IFERROR(AB97/AB72,"NA") -> 1.2739831 | AC100: =IFERROR(AC97/AC72,"NA") -> 0.33173461 | AD100: =IFERROR(AD97/AD72,"NA") -> 0.69631959 | AE100: =IFERROR(AE97/AE72,"NA") -> 1.2652293 | AF100: =IFERROR(AF97/AF72,"NA") -> 1.9869701 | ... CA100: =IFERROR(CA97/CA72,"NA") -> 0.73206906
B102: Management guidance (annual) | AG102: 2019 | AI102: 2019 | AJ102: 2019 | AK102: 2019 | AL102: 2020 (post-iDay) | AN102: 2020 | AO102: 2020 | AP102: 2020 | AQ102: 2021 | AS102: 2021 | AT102: 2021 | AU102: 2021 | AV102: 2022 | AX102: 2022 | AY102: 2022 | AZ102: 2022
B103: Revenue | AG103: MSD | AI103: MSD | AJ103: MSD | AK103: HSD | AL103: MSD | AN103: Down MSD | AO103: LSD | AP103: HSD | AQ103: MSD | AS103: HSD | AT103: LDD | AU103: Low-Teens | AV103: HSD | AX103: ~Flat | AY103: down HSD | AZ103: down LDD
B104: Operating margin | AG104: ~43% | AI104: ~43% | AJ104: ~42% | AK104: ~42% | AL104: ~44% | AN104: ~41-43% | AO104: ~43-44% | AP104: ~45% | AQ104: ~45% | AS104: ~46% | AT104: ~47% | AU104: 46-47% | AV104: 44-45% | AX104: 41-42% | AY104: 37-38% | AZ104: 34-35%
B105: Adj. operating margin | AG105: ~48% | AI105: ~48% | AJ105: ~48% | AK105: ~48% | AL105: 48-49% | AN105: 46-48% | AO105: 48-49% | AP105: ~50% | AQ105: 49-50% | AS105: ~50% | AT105: ~51% | AU105: ~51% | AV105: 49-50% | AX105: ~47% | AY105: ~44% | AZ105: ~42%
B106: MCO total expenses | AG106: MSD | AI106: HSD | AJ106: HSD | AK106: HSD | AL106: LSD | AN106: Down MSD | AO106: ~flat | AP106: up LSD | AQ106: up MSD | AS106: up MSD | AT106: up MSD | AU106: ~10% y/y | AV106: up LDD | AX106: up HSD | AY106: up HSD | AZ106: up MSD
B107: Interest expense, net | AG107: $200-225m | AI107: $200-225m | AJ107: $195m | AK107: $195m | AL107: $180-200m | AN107: $180-200m | AO107: $180-200m | AP107: $180-200m | AQ107: $190-210m | AS107: $160-180m | AT107: $160-180m | AU107: $160-180m | AV107: $200-220m | AX107: $200-220m | AY107: $220-240mm | AZ107: $220-240mm
B108: Effective tax rate | AG108: 21-22% | AI108: 21-22% | AJ108: 21-22% | AK108: 21.5-22.5% | AL108: 20-22% | AN108: 19.5-21.5% | AO108: 19.5-21.5% | AP108: 19.5-21.5% | AQ108: 20.0-22.0% | AS108: 20.0-22.0% | AT108: 20.0-22.0% | AU108: 19.5-20.5% | AV108: 20.5-22.5% | AX108: 20.5-22.5% | AY108: 20.5-22.5% | AZ108: 20.5-22.5%
B109: Diluted EPS | AG109: $7.30-7.55 | AI109: $7.30-7.55 | AJ109: $7.15-7.35 | AK109: $7.20-7.35 | AL109: $8.60-8.80 | AN109: $7.25-7.85 | AO109: $8.15-8.55 | AP109: $9.30-9.50 | AQ109: $9.70-10.10 | AS109: $10.40-10.70 | AT109: $10.95-11.25 | AU109: $11.65-11.85 | AV109: $11.50-12.00 | AX109: $9.85-10.35 | AY109: $8.10-8.60 | AZ109: $6.90-7.20
B110: Adjusted diluted EPS | AG110: $7.85-8.10 | AI110: $7.85-8.10 | AJ110: $7.95-8.15 | AK110: $8.05-8.20 | AL110: $9.10-9.30 | AN110: $7.80-8.40 | AO110: $8.80-9.20 | AP110: $9.95-10.15 | AQ110: $10.30-10.70 | AS110: $11.00-11.30 | AT110: $11.55-11.85 | AU110: $12.15-12.35 | AV110: $12.40-12.90 | AX110: $10.75-11.25 | AY110: $9.20-9.70 | AZ110: $8.20-8.50
B111: Free cash flow | AG111: $1,600-1,700m | AI111: $1,600-1,700m | AJ111: $1,600-1,700m | AK111: $1,600-1,700m | AL111: $1,700-1,800m | AN111: $1,200-1,400m | AO111: $1,500-1,700m | AP111: $1,500-1,700m | AQ111: $1,900-2,100m | AS111: $2,100-2,200m | AT111: $2,200-2,300m | AU111: $2,200-2,300m | AV111: $2300-2500m | AX111: $1.8-$2.0bln | AY111: $1.4-1.6bln | AZ111: ~$1.2bln
B112: Repurchases | AU112: ~$750m | AV112: >$1,500m | AX112: >$1,500m | AY112: ~$1,000mm | AZ112: ~$1,000mm
B114: Moody's Investor Service (MIS)
...

Sheet BS & CFS
G1: CQ1 | H1: CQ2 | I1: CQ3 | J1: CQ4 | K1: 16Y | L1: CQ1 | M1: CQ2 | N1: CQ3 | O1: CQ4 | P1: 17Y | Q1: CQ1 | R1: CQ2 | S1: CQ3 | T1: CQ4 | U1: 18Y | V1: CQ1 | W1: CQ2 | X1: CQ3 | Y1: CQ4 | Z1: 19Y | AA1: CQ1 | AB1: CQ2 | AC1: CQ3 | AD1: CQ4 | AE1: 20Y
B3: Moody's (MCO)
B4: Balance sheet & cash flow statement
B5: ($ in Millions, except per share data)
G6: 2016A | L6: 2017A | Q6: 2018A | V6: 2019A | AA6: 2020A | AF6: 2021A | AK6: 2022A | AP6: 2023A | AU6: 2024A | AZ6: 2025E | BE6: 2026E | BJ6: 2027E
F7: 2015A | G7: 1Q16A | H7: 2Q16A | I7: 3Q16A | J7: 4Q16A | K7: 2016A | L7: 1Q17A | M7: 2Q17A | N7: 3Q17A | O7: 4Q17A | P7: 2017A | Q7: 1Q18A | R7: 2Q18A | S7: 3Q18A | T7: 4Q18A | U7: 2018A | V7: 1Q19A | W7: 2Q19A | X7: 3Q19A | Y7: 4Q19A | Z7: 2019A | AA7: 1Q20A | AB7: 2Q20A | AC7: 3Q20A | AD7: 4Q20A | AE7: 2020A | AF7: 1Q21A | AG7: 2Q21A | AH7: 3Q21A | AI7: 4Q21A | AJ7: 2021A | AK7: 1Q22A | AL7: 2Q22A | AM7: 3Q22A | AN7: 4Q22A | AO7: 2022A | AP7: 1Q23A | AQ7: 2Q23A | AR7: 3Q23A | AS7: 4Q23A | AT7: 2023A | AU7: 1Q24A | AV7: 2Q24A | AW7: 3Q24A | AX7: 4Q24A | AY7: 2024A | AZ7: 1Q25A | BA7: 2Q25A | BB7: 3Q25E | BC7: 4Q25E | BD7: 2025E | BE7: 1Q26E | BF7: 2Q26E | BG7: 3Q26E | BH7: 4Q26E | BI7: 2026E | BJ7: 1Q27E | BK7: 2Q27E | BL7: 3Q27E | BM7: 4Q27E | BN7: 2027E
B8: BALANCE SHEET
B9: Assets
B10: Cash, cash equivalents, and restricted cash | J10: 2051.5 | K10: =J10 -> 2051.5 | O10: =1071.5 -> 1071.5 | P10: =O10 -> 1071.5 | Q10: =1277.3 -> 1277.3 | R10: 1314.5 | S10: =1034.8 -> 1034.8 | T10: 1685 | U10: =T10 -> 1685 | V10: 1196.6 | W10: 1195.9 | X10: 1178 | Y10: 1832 | Z10: =Y10 -> 1832 | AA10: 2141 | AB10: 2099 | AC10: 2492 | AD10: 2597 | AE10: =AD10 -> 2597 | AF10: 2769 | AG10: 2809 | AH10: 2239 | AI10: 1811 | AJ10: =AI10 -> 1811 | AK10: 1750 | AL10: 1617 | AM10: 1656 | AN10: 1769 | AO10: =AN10 -> 1769 | AP10: 2119 | AQ10: 2278 | AR10: 2006 | AS10: 2130 | AT10: =AS10 -> 2130 | AU10: 2476 | AV10: 2635 | AW10: 2642 | AX10: 2408 | AY10: =AX10 -> 2408 | AZ10: 2139 | BA10: 2174 | BB10: =BB91 -> 2116.9886 | BC10: =BC91 -> 2318.1482 | BD10: =BC10 -> 2318.1482 | BE10: =BE91 -> 2881.1873 | BF10: =BF91 -> 2955.3385 | BG10: =BG91 -> 3097.3721 | BH10: =BH91 -> 3430.8107 | BI10: =BH10 -> 3430.8107 | BJ10: =BJ91 -> 4094.9165 | BK10: =BK91 -> 4250.921 | BL10: =BL91 -> 4482.3424 | BM10: =BM91 -> 4911.1071 | BN10: =BM10 -> 4911.1071
B11: Short-term investments | J11: 173.4 | K11: =J11 -> 173.4 | O11: 111.8 | P11: =O11 -> 111.8 | Q11: 100.5 | R11: 101.2 | S11: 110.7 | T11: 132.5 | U11: =T11 -> 132.5 | V11: 114 | W11: 119.5 | X11: 95.8 | Y11: 98 | Z11: =Y11 -> 98 | AA11: 90 | AB11: 100 | AC11: 96 | AD11: 99 | AE11: =AD11 -> 99 | AF11: 96 | AG11: 88 | AH11: 104 | AI11: 91 | AJ11: =AI11 -> 91 | AK11: 103 | AL11: 86 | AM11: 89 | AN11: 90 | AO11: =AN11 -> 90 | AP11: 78 | AQ11: 57 | AR11: 73 | AS11: 63 | AT11: =AS11 -> 63 | AU11: 58 | AV11: 63 | AW11: 573 | AX11: 566 | AY11: =AX11 -> 566 | AZ11: 62 | BA11: 116 | BB11: =BA11 -> 116 | BC11: =BB11 -> 116 | BD11: =BC11 -> 116 | BE11: =BC11 -> 116 | BF11: =BE11 -> 116 | BG11: =BF11 -> 116 | BH11: =BG11 -> 116 | BI11: =BH11 -> 116 | BJ11: =BH11 -> 116 | BK11: =BJ11 -> 116 | BL11: =BK11 -> 116 | BM11: =BL11 -> 116 | BN11: =BM11 -> 116
B12: Accounts receivables | J12: 887.4 | K12: =J12 -> 887.4 | O12: 1147.2 | P12: =O12 -> 1147.2 | Q12: 1207.4 | R12: 1137.1 | S12: 1131.8 | T12: 1287.1 | U12: =T12 -> 1287.1 | V12: 1301.2 | W12: =W124 -> 1263.474 | X12: =X124 -> 1332.263 | Y12: =Y124 -> 1486.3562 | Z12: =Y12 -> 1486.3562 | AA12: 1526.7945 | AB12: 1401 | AC12: 1360 | AD12: 1430 | AE12: =AD12 -> 1430 | AF12: 1497 | AG12: 1458 | AH12: 1589 | AI12: 1720 | AJ12: =AI12 -> 1720 | AK12: 1824 | AL12: 1602 | AM12: 1518 | AN12: 1652 | AO12: =AN12 -> 1652 | AP12: 1712 | AQ12: 1542 | AR12: 1513 | AS12: 1659 | AT12: =AS12 -> 1659 | AU12: 1835 | AV12: 1694 | AW12: 1708 | AX12: 1801 | AY12: =AX12 -> 1801 | AZ12: 1850 | BA12: 1776 | BB12: =BB124 -> 1774 | BC12: =BC124 -> 2071.854 | BD12: =BC12 -> 2071.854 | BE12: =BE124 -> 2026.0581 | BF12: =BF124 -> 1923.6575 | BG12: =BG124 -> 1909.3984 | BH12: =BH124 -> 2233.4554 | BI12: =BH12 -> 2233.4554 | BJ12: =BJ124 -> 2180.334 | BK12: =BK124 -> 2069.837 | BL12: =BL124 -> 2054.9074 | BM12: =BM124 -> 2404.4802 | BN12: =BM12 -> 2404.4802
B13: Other current assets | J13: 140.8 | K13: =J13 -> 140.8 | O13: 250.1 | P13: =O13 -> 250.1 | Q13: 233.6 | R13: 286.9 | S13: 238.9 | T13: 282.3 | U13: =T13 -> 282.3 | V13: 286.6 | W13: 575.72603 | X13: 436.23699 | Y13: 262.64384 | Z13: =Y13 -> 262.64384 | AA13: 236 | AB13: =363 -> 363 | AC13: 333 | AD13: 383 | AE13: =AD13 -> 383 | AF13: 333 | AG13: 379 | AH13: 323 | AI13: 389 | AJ13: =AI13 -> 389 | AK13: 385 | AL13: 515 | AM13: 463 | AN13: 583 | AO13: =AN13 -> 583 | AP13: 517 | AQ13: 513 | AR13: 445 | AS13: 489 | AT13: =AS13 -> 489 | AU13: 437 | AV13: 489 | AW13: 470 | AX13: 515 | AY13: =AX13 -> 515 | AZ13: 514 | BA13: 573 | BB13: 566 | BC13: =BB13 -> 566 | BD13: =BC13 -> 566 | BE13: =BC13 -> 566 | BF13: =BE13 -> 566 | BG13: =BF13 -> 566 | BH13: =BG13 -> 566 | BI13: =BH13 -> 566 | BJ13: =BH13 -> 566 | BK13: =BJ13 -> 566 | BL13: =BK13 -> 566 | BM13: =BL13 -> 566 | BN13: =BM13 -> 566
B14: Total current assets | J14: =SUM(J10:J13) -> 3253.1 | K14: =SUM(K10:K13) -> 3253.1 | O14: =SUM(O10:O13) -> 2580.6 | P14: =SUM(P10:P13) -> 2580.6 | Q14: =SUM(Q10:Q13) -> 2818.8 | R14: =SUM(R10:R13) -> 2839.7 | S14: =SUM(S10:S13) -> 2516.2 | T14: =SUM(T10:T13) -> 3386.9 | U14: =SUM(U10:U13) -> 3386.9 | V14: =SUM(V10:V13) -> 2898.4 | ... BN14: =SUM(BN10:BN13) -> 7997.5873
B15: Property and equipment, net | J15: 325.9 | K15: =J15 -> 325.9 | O15: 325.1 | P15: =O15 -> 325.1 | Q15: 321.6 | R15: 312.2 | S15: 311.1 | T15: 320.4 | U15: =T15 -> 320.4 | V15: 318.7 | W15: =W114 -> 331.9 | X15: =X114 -> 317.6 | Y15: =Y114 -> 292.6 | Z15: =Y15 -> 292.6 | AA15: =AA114 -> 289.1 | AB15: 298 | AC15: 282 | AD15: 278 | AE15: =AD15 -> 278 | AF15: 269 | AG15: 282 | AH15: 301 | AI15: 347 | AJ15: =AI15 -> 347 | AK15: 381 | AL15: 433 | AM15: 472 | AN15: 502 | AO15: =AN15 -> 502 | AP15: 525 | AQ15: 541 | AR15: 573 | AS15: 603 | AT15: =AS15 -> 603 | AU15: 613 | AV15: 652 | AW15: 662 | AX15: 656 | AY15: =AX15 -> 656 | AZ15: 671 | BA15: 689 | BB15: =BB114 -> 712 | BC15: =BC114 -> 743.84121 | BD15: =BC15 -> 743.84121 | BE15: =BE114 -> 769.51234 | BF15: =BF114 -> 782.74673 | BG15: =BG114 -> 807.2026 | BH15: =BH114 -> 837.18126 | BI15: =BH15 -> 837.18126 | BJ15: =BJ114 -> 859.94503 | BK15: =BK114 -> 872.24461 | BL15: =BL114 -> 894.77621 | BM15: =BM114 -> 922.5258 | BN15: =BM15 -> 922.5258
B16: Operating leases | J16: 0 | K16: 0 | O16: 0 | P16: 0 | Q16: 0 | R16: 0 | S16: 0 | T16: 0 | U16: =T16 -> 0 | V16: 508.1 | W16: 476.8 | X16: 464.6 | Y16: 456 | Z16: =Y16 -> 456 | AA16: 437 | AB16: 429 | AC16: 410 | AD16: 393 | AE16: =AD16 -> 393 | AF16: 375 | AG16: 357 | AH16: 451 | AI16: 438 | AJ16: =AI16 -> 438 | AK16: 427 | AL16: 413 | AM16: 387 | AN16: 346 | AO16: =AN16 -> 346 | AP16: 332 | AQ16: 330 | AR16: 298 | AS16: 277 | AT16: =AS16 -> 277 | AU16: 260 | AV16: 242 | AW16: 242 | AX16: 216 | AY16: =AX16 -> 216 | AZ16: 217 | BA16: 226 | BB16: =BA16 -> 226 | BC16: =BB16 -> 226 | BD16: =BC16 -> 226 | BE16: =BC16 -> 226 | BF16: =BE16 -> 226 | BG16: =BF16 -> 226 | BH16: =BG16 -> 226 | BI16: =BH16 -> 226 | BJ16: =BH16 -> 226 | BK16: =BJ16 -> 226 | BL16: =BK16 -> 226 | BM16: =BL16 -> 226 | BN16: =BM16 -> 226
